Workbook

Sheet Synthèse
C4: Synthèse Numérique
C6: N° | D6: Domaines | E6: Total OUI | F6: Total NON | G6: Total PAS | H6: Total | I6: Score
C7: 1 | D7: COSO | E7: =COUNTIF(Ref_COSO!F3:F322,"OUI") -> 129 | F7: =COUNTIF(Ref_COSO!F3:F322,"NON") -> 146 | G7: =COUNTIF(Ref_COSO!F3:F322,"PAS") -> 45 | H7: =SUM(E7:G7) -> 320 | I7: =E7/H7 -> 0.403125
C8: 2 | D8: Fonction_Informatique | E8: =COUNTIF(Ref_fontion_informatique!$F$2:$F$197,"OUI") -> 64 | F8: =COUNTIF(Ref_fontion_informatique!$F$2:$F$197,"NON") -> 93 | G8: =COUNTIF(Ref_fontion_informatique!$F$2:$F$197,"PAS") -> 39 | H8: =SUM(E8:G8) -> 196 | I8: =E8/H8 -> 0.32653061
C9: 3 | D9: Projets Informatiques | E9: =COUNTIF(Ref_control_projet_informatique!$E$2:$E$586,"OUI") -> 325 | F9: =COUNTIF(Ref_control_projet_informatique!$E$2:$E$586,"NON") -> 181 | G9: =COUNTIF(Ref_control_projet_informatique!$E$2:$E$586,"PAS") -> 79 | H9: =SUM(E9:G9) -> 585 | I9: =E9/H9 -> 0.55555556
C10: 4 | D10: Support Utilisateur | E10: =COUNTIF(Ref_Support_utili_gestion_parc!$F$2:$F$156,"OUI") -> 80 | F10: =COUNTIF(Ref_Support_utili_gestion_parc!$F$2:$F$156,"NON") -> 51 | G10: =COUNTIF(Ref_Support_utili_gestion_parc!$F$2:$F$156,"PAS") -> 24 | H10: =SUM(E10:G10) -> 155 | I10: =E10/H10 -> 0.51612903
C11: 5 | D11: Sécurité Informatique | E11: =COUNTIF('Ref_sécurité-informatique'!$E$2:$E$126,"OUI") -> 56 | F11: =COUNTIF('Ref_sécurité-informatique'!$E$2:$E$126,"NON") -> 49 | G11: =COUNTIF('Ref_sécurité-informatique'!$E$2:$E$126,"PAS") -> 20 | H11: =SUM(E11:G11) -> 125 | I11: =E11/H11 -> 0.448
C12: 6 | D12: Application_service | E12: =COUNTIF(Ref_Appli_Serv!$F$3:$F$257,"OUI") -> 130 | F12: =COUNTIF(Ref_Appli_Serv!$F$3:$F$257,"NON") -> 90 | G12: =COUNTIF(Ref_Appli_Serv!$F$3:$F$257,"PAS") -> 35 | H12: =SUM(E12:G12) -> 255 | I12: =E12/H12 -> 0.50980392
C13: Total | E13: =SUM(E7:E12) -> 784 | F13: =SUM(F7:F12) -> 610 | G13: =SUM(G7:G12) -> 242 | H13: =SUM(E13:G13) -> 1636 | I13: =E13/H13 -> 0.4792176
I14: SYNTHESE GRAPHIQUE

Sheet Ref_Appli_Serv
A2: Domaines | B2: Points de Contrôle | C2: Objectifs de Contrôle | D2: Critère d’Évaluation | E2: Question d’Évaluation | F2: Réponses | G2: Documents Requis | H2: Risques | I2: Criticités | J2: Conséquences | K2: Recommandations
A3: Audit des Applications en Service | B3: Organisation | C3: S’assurer de l’existence d'un comité informatique | D3: Un comité informatique est officiellement constitué et documenté. | E3: Un comité informatique est-il formellement mis en place ? | F3: OUI | G3: Charte du comité, Organigramme du comité | H3: Absence de gouvernance informatique | I3: Élevée | J3: Perte de pilotage stratégique du SI | K3: Mettre en place une structure de gouvernance dédiée au SI ; Définir des politiques claires.
D4: - La liste des membres du comité est disponible et mise à jour. | E4: La liste des membres du comité est-elle tenue à jour ? | F4: NON | G4: Liste des membres, PV de nomination | H4: Manque de clarté sur les responsabilités | I4: Moyenne | J4: Multiplication des erreurs et conflits | K4: Documenter et diffuser les rôles et responsabilités ; Utiliser un organigramme fonctionnel.
D5: - Le comité se réunit régulièrement (ex. : mensuellement ou trimestriellement). | E5: Le comité informatique tient-il des réunions régulières ? | F5: NON | G5: Calendrier des réunions, PV des réunions | H5: Manque de suivi des décisions stratégiques | I5: Élevée | J5: Objectifs non atteints ou dérive des projets | K5: Mettre en place un comité de suivi ; Utiliser des outils de reporting régulier.
D6: - Des comptes rendus de réunion sont archivés et accessibles. | E6: Les comptes rendus des réunions sont-ils archivés et consultables ? | F6: OUI | G6: Registre des comptes rendus, Plateforme de stockage documentaire | H6: Manque de traçabilité des décisions | I6: Moyenne | J6: Impossibilité de justifier ou de corriger les décisions | K6: Tenir des procès-verbaux ; Archiver systématiquement les décisions.
D7: - Le comité prend des décisions stratégiques et suit des actions correctives. | E7: Le comité suit-il l’exécution des décisions et actions correctives ? | F7: OUI | G7: Plan d’actions, Rapports de suivi | H7: Actions non suivies ou inefficaces | I7: Élevée | J7: Non atteinte des résultats escomptés | K7: Affecter des responsables et des indicateurs aux actions ; Réaliser des revues périodiques.
C8: S’assurer que les rôle et responsabilités des utilisateurs sont bien définis | D8: Chaque utilisateur a un rôle clairement défini dans l’organisation. | E8: Les rôles des utilisateurs sont-ils documentés ? | F8: OUI | G8: Manuel des responsabilités, Organigramme | H8: Confusion des responsabilités | I8: Moyenne | J8: Blocages ou doublons dans l’exécution | K8: Clarifier les tâches dans un RACI ; Sensibiliser les équipes.
D9: - Un document officiel détaille les responsabilités de chaque rôle. | E9: Un document formel précise-t-il les responsabilités de chaque poste ? | F9: OUI | G9: Fiches de poste, Manuel interne | H9: Attribution floue des responsabilités | I9: Moyenne | J9: Absence de redevabilité en cas d’échec | K9: Formaliser les responsabilités dans les fiches de poste ; Réviser périodiquement.
D10: - Les utilisateurs ont accès uniquement aux fonctionnalités nécessaires à leur travail. | E10: Les accès des utilisateurs sont-ils restreints à leurs besoins ? | F10: OUI | G10: Liste des droits d’accès, Rapports de permissions | H10: Accès excessifs aux ressources | I10: Élevée | J10: Risque accru de fuite ou d’abus | K10: Mettre en œuvre un principe du moindre privilège ; Réaliser des revues d’accès régulières.
D11: - Les droits et accès sont revus périodiquement pour éviter les abus. | E11: Un audit des accès est-il effectué régulièrement ? | F11: NON | G11: Rapports d’audit d’accès, Politique de gestion des accès | H11: Risque d’abus ou de fraude | I11: Élevée | J11: Perte financière ou atteinte à l’image | K11: Implémenter des contrôles d'accès renforcés ; Mettre en place un système d’alerte.
D12: - Une procédure existe pour modifier ou supprimer des droits en cas de changement de poste. | E12: Un processus formel gère-t-il les modifications d’accès ? | F12: PAS | G12: Procédure de gestion des droits, Journal des modifications d’accès | H12: Maintien d’accès injustifiés | I12: Élevée | J12: Utilisation non contrôlée de ressources sensibles | K12: Supprimer les comptes inactifs ; Intégrer des audits périodiques des droits.
C13: S’assurer qu’une analyse des risques a été réalisée | D13: Une analyse des risques a été formellement menée et documentée. | E13: Une analyse des risques SI a-t-elle été réalisée ? | F13: OUI | G13: Rapport d’analyse des risques, Cartographie des risques | H13: Manque de visibilité sur les menaces | I13: Élevée | J13: Réaction tardive aux incidents | K13: Mettre en place un système de détection des intrusions ; Mettre à jour la cartographie des risques.
D14: - Les risques identifiés sont classés en fonction de leur criticité. | E14: Les risques SI sont-ils classés selon leur criticité ? | F14: OUI | G14: Matrice des risques, Liste des risques classifiés | H14: Gestion inefficace des priorités | I14: Moyenne | J14: Ressources mal allouées ; perte d'efficacité | K14: Définir une matrice d’analyse des risques ; Prioriser selon les impacts.
D15: - Des mesures de mitigation des risques ont été définies. | E15: Des mesures de mitigation des risques ont-elles été établies ? | F15: NON | G15: Plan de mitigation, Rapports de suivi des risques | H15: Absence de stratégie de réduction des risques | I15: Élevée | J15: Vulnérabilité constante du SI | K15: Développer un plan de traitement des risques ; Allouer un budget spécifique.
D16: - L’analyse des risques est revue périodiquement. | E16: L’analyse des risques est-elle régulièrement mise à jour ? | F16: OUI | G16: Planning des revues, Historique des mises à jour | H16: Risques non pris en compte | I16: Élevée | J16: Événements inattendus impactant l’activité | K16: Effectuer une analyse de risques régulière ; Intégrer les parties prenantes.
D17: - La direction a validé et approuvé les résultats de l’analyse | E17: La direction valide-t-elle l’analyse des risques ? | F17: PAS | G17: PV d’approbation, Rapports aux décideurs | H17: Absence de soutien stratégique | I17: Moyenne | J17: Initiatives SI non alignées aux objectifs | K17: Obtenir un engagement formel de la direction ; Intégrer le SI au plan stratégique.
C18: S’assurer que le prolongement de l'analyse de risque et de son expansion ont été réalisés | D18: L’analyse des risques est mise à jour après chaque évolution majeure de l’application. | E18: L’analyse des risques est-elle mise à jour après un changement majeur ? | F18: OUI | G18: Rapports de mise à jour, Liste des nouvelles menaces | H18: Failles de sécurité non identifiées | I18: Élevée | J18: Exploitation possible par des attaquants | K18: Réaliser des audits de sécurité réguliers ; Mettre à jour les outils de sécurité.
D19: - Les nouveaux risques identifiés sont ajoutés et évalués. | E19: Les nouveaux risques sont-ils évalués lors des mises à jour ? | F19: PAS | G19: Matrice des risques, Registre des incidents | H19: Menaces émergentes non anticipées | I19: Élevée | J19: Obsolescence des défenses ; vulnérabilité accrue | K19: Assurer une veille technologique et sécuritaire ; Adapter les politiques de sécurité.
D20: - Les mesures de contrôle sont adaptées en fonction des nouvelles menaces. | E20: Les contrôles de sécurité évoluent-ils selon les nouvelles menaces ? | F20: PAS | G20: Rapport de mise à jour des contrôles, Registre des actions correctives | H20: Mesures inadaptées aux menaces actuelles | I20: Élevée | J20: Inefficacité de la défense du SI | K20: Revoir les mesures selon les scénarios de risques ; Tester la robustesse des mesures.
D21: - Les responsables sont informés des mises à jour de l’analyse de risque. | E21: Les responsables sont-ils informés des mises à jour des risques ? | F21: PAS | G21: Notes de service, Comptes rendus de réunion | H21: Manque de sensibilisation des parties prenantes | I21: Moyenne | J21: Comportements à risque ; négligence | K21: Former régulièrement le personnel ; Diffuser des guides de bonnes pratiques.
D22: - Un suivi est effectué pour s’assurer que les nouvelles mesures sont appliquées. | E22: Les mesures correctives sont-elles suivies et validées ? | F22: PAS | G22: Rapports de conformité, Journal des actions mises en œuvre | H22: Absence de suivi des correctifs | I22: Élevée | J22: Systèmes exposés à des vulnérabilités connues | K22: Automatiser les mises à jour ; Mettre en place un plan de patch management.
C23: S’assurer que l’analyse et évaluation du niveau de sensibilité a été réalisée | D23: Un document définit les niveaux de sensibilité des données de l’application. | E23: Un document de classification des données existe-t-il ? | F23: NON | G23: Politique de classification des données, Registre des données sensibles | H23: Manque de gestion des données sensibles | I23: Élevée | J23: Risque de non-conformité RGPD / fuite de données | K23: Classifier les données ; Appliquer des politiques de protection spécifiques.
D24: - La classification des données est basée sur leur impact potentiel en cas de perte. | E24: Les niveaux de classification tiennent-ils compte des impacts potentiels ? | F24: NON | G24: Étude d’impact, Registre de classification | H24: Mauvaise catégorisation des données | I24: Moyenne | J24: Mauvaise gestion des niveaux de sécurité | K24: Mettre en place un système de classification clair ; Revoir les étiquetages existants.
D25: - Les données sensibles ont des mesures de protection spécifiques. | E25: Des mesures spécifiques protègent-elles les données sensibles ? | F25: NON | G25: Politique de sécurité des données, Rapport d’audit de sécurité | H25: Protection insuffisante des données critiques | I25: Élevée | J25: Risques de perte ou vol de données | K25: Chiffrer les données sensibles ; Sauvegarder régulièrement.
D26: - Une procédure existe pour modifier la classification en cas d’évolution. | E26: Une procédure de mise à jour de la classification est-elle en place ? | F26: NON | G26: Procédure de modification des classifications, Journal des modifications | H26: Classification obsolète | I26: Moyenne | J26: Données critiques mal protégées ou surprotégées | K26: Mettre à jour la classification des données ; Auditer régulièrement les accès.
D27: - L’accès aux données sensibles est restreint et contrôlé. | E27: L’accès aux données sensibles est-il limité et surveillé ? | F27: NON | G27: Liste des accès aux données sensibles, Logs d’accès | H27: Accès non autorisés aux données sensibles | I27: Élevée | J27: Violations de la confidentialité | K27: Restreindre les droits d’accès ; Mettre en œuvre un contrôle d’accès logique.
C28: Vérifier l’existence d’un manuel d'administration de l'application | D28: Un manuel d’administration est disponible et à jour. | E28: Un manuel d’administration est-il disponible ? | F28: OUI | G28: Manuel d’administration, Documentation technique | H28: Manque de référence pour les administrateurs | I28: Élevée | J28: Risques de mauvaise configuration | K28: Créer un référentiel de bonnes pratiques ; Documenter les procédures d’administration.
D29: - Il décrit les configurations techniques et les paramètres de l’application. | E29: Le manuel contient-il les configurations techniques et les paramètres de l’application ? | F29: OUI | G29: Manuel d’administration, Liste des configurations | H29: Mauvaise gestion des configurations | I29: Élevée | J29: Instabilités et vulnérabilités système | K29: Utiliser un outil de gestion de configuration ; Centraliser les changements.
D30: - Les procédures de maintenance et de dépannage y sont documentées. | E30: Les procédures de maintenance et de dépannage sont-elles documentées ? | F30: PAS | G30: Manuel d’administration, Guide de dépannage | H30: Temps d’arrêt prolongé en cas d’incident | I30: Élevée | J30: Baisse de productivité ; perte financière | K30: Élaborer un plan de continuité d’activité ; Effectuer des tests de restauration.
D31: - Seuls les administrateurs autorisés ont accès au manuel. | E31: L’accès au manuel d’administration est-il restreint aux administrateurs ? | F31: OUI | G31: Liste des administrateurs autorisés, Registre des accès | H31: Risque d’accès non autorisé à des informations sensibles | I31: Élevée | J31: Risque juridique et réputationnel | K31: Implanter un système d’authentification ; Journaliser tous les accès.
D32: - Le manuel est régulièrement mis à jour en cas de changement dans l’application. | E32: Le manuel d’administration est-il mis à jour après chaque modification majeure ? | F32: OUI | G32: Historique des mises à jour, Procédure de validation des mises à jour | H32: Utilisation de configurations obsolètes | I32: Moyenne | J32: Exposition à des failles connues | K32: Maintenir une documentation à jour ; Mettre à jour les configurations régulièrement.
C33: Vérifier l’existence de procédures formalisées | D33: Toutes les procédures liées à l’application sont documentées. | E33: Toutes les procédures de l’application sont-elles documentées ? | F33: OUI | G33: Référentiel des procédures, Guide utilisateur | H33: Manque de standardisation des processus | I33: Moyenne | J33: Hétérogénéité, erreurs et lenteurs | K33: Documenter les processus ; Mettre en place une démarche qualité.
D34: - Les documents sont accessibles aux utilisateurs concernés. | E34: Les documents sont-ils accessibles uniquement aux utilisateurs concernés ? | F34: OUI | G34: Liste des accès aux documents, Plateforme documentaire | H34: Accès non autorisé aux documents sensibles | I34: Élevée | J34: Risque de divulgation d’informations confidentielles | K34: Sécuriser les partages de documents ; Limiter les droits d'accès.
D35: - Les procédures couvrent les opérations courantes et exceptionnelles. | E35: Les procédures documentées couvrent-elles toutes les opérations ? | F35: OUI | G35: Manuel des procédures, Rapports d’incidents | H35: Mauvaise gestion des situations exceptionnelles | I35: Moyenne | J35: Pertes de données ou interruption des services | K35: Établir un protocole d'urgence ; Former les équipes à ces scénarios.
D36: - Elles sont validées par les responsables avant leur mise en application. | E36: Les responsables valident-ils les procédures avant leur application ? | F36: OUI | G36: PV de validation, Workflow d’approbation | H36: Procédures non conformes aux exigences | I36: Moyenne | J36: Non-conformité réglementaire | K36: Réviser les procédures en fonction des normes ; Soumettre à validation juridique.
D37: - Un processus de mise à jour des procédures est défini | E37: Un processus de mise à jour des procédures est-il formalisé ? | F37: OUI | G37: Plan de mise à jour des procédures, Historique des révisions | H37: Utilisation de procédures obsolètes | I37: Moyenne | J37: Inefficacité ou erreurs d’application | K37: Mettre à jour périodiquement ; Informer les utilisateurs des changements.
C38: S’assurer de l’existence et de la mise à disposition du compte rendu mensuel au propriétaire | D38: Un compte rendu est produit chaque mois. | E38: Un compte rendu sur l’application est-il produit mensuellement ? | F38: NON | G38: Rapports mensuels, Registre des comptes rendus | H38: Manque de suivi des performances et anomalies | I38: Élevée | J38: Répétition des incidents sans traitement | K38: Instaurer un outil de supervision ; Mettre en place un tableau de bord SI.
D39: - Il contient des informations sur l’utilisation et la performance de l’application. | E39: Le compte rendu contient-il des indicateurs de performance ? | F39: NON | G39: Modèle de compte rendu, Tableau de bord des performances | H39: Absence d’indicateurs de suivi | I39: Moyenne | J39: Difficulté d’évaluation et de pilotage | K39: Définir des KPI clairs ; Intégrer ces indicateurs dans les rapports.
D40: - Le propriétaire de l’application reçoit et valide ce compte rendu. | E40: Le propriétaire de l’application valide-t-il le compte rendu mensuel ? | F40: NON | G40: PV de validation, Liste des destinataires du rapport | H40: Décisions non prises sur la base d’informations validées | I40: Moyenne | J40: Risques d’erreurs stratégiques | K40: Mettre en place des outils d’aide à la décision ; Valider les données sources.
D41: - Des actions correctives sont proposées en cas d’anomalie. | E41: Des actions correctives sont-elles proposées dans les comptes rendus ? | F41: NON | G41: Plan d’actions correctives, Historique des corrections | H41: Non-prise en charge des anomalies identifiées | I41: Élevée | J41: Résurgence d’erreurs et instabilité | K41: Assigner des responsables au suivi ; Créer une base d’incidents.
D42: - Les comptes rendus sont archivés pour référence future. | E42: Les comptes rendus sont-ils archivés et accessibles ? | F42: NON | G42: Registre des comptes rendus, Plateforme de stockage | H42: Perte d’historique et de traçabilité | I42: Moyenne | J42: Difficulté d’analyse et d’audit | K42: Activer la journalisation systématique ; Conserver les logs sur une durée définie.
C43: S’assurer de l’existence d'un guide d'utilisateur, manuel de procédure | D43: Un guide d’utilisateur est disponible et facile à comprendre. | E43: Un guide utilisateur est-il disponible ? | F43: NON | G43: Guide utilisateur, Manuel de prise en main | H43: Difficulté d’utilisation de l’application | I43: Moyenne | J43: Faible adoption ou erreurs fréquentes | K43: Simplifier l’interface ; Réaliser des tests utilisateurs.
D44: Il couvre les fonctionnalités principales de l’application. | E44: Le guide utilisateur couvre-t-il toutes les fonctionnalités principales ? | F44: PAS | G44: Guide utilisateur, Liste des fonctionnalités | H44: Manque de compréhension des fonctionnalités | I44: Moyenne | J44: Sous-utilisation des outils | K44: Proposer des formations et des guides ; Fournir des démonstrations interactives.
D45: Il est mis à jour à chaque changement majeur. | E45: Le guide utilisateur est-il mis à jour après chaque évolution majeure ? | F45: PAS | G45: Historique des mises à jour, Procédure de validation des mises à jour | H45: Utilisation d’informations obsolètes | I45: Moyenne | J45: Mauvaises décisions ; erreurs | K45: Mettre à jour les bases de données ; Mettre en place un système d’alerte.
D46: Les nouveaux utilisateurs reçoivent une formation basée sur ce guide. | E46: Une formation basée sur le guide utilisateur est-elle dispensée aux nouveaux utilisateurs ? | F46: PAS | G46: Plan de formation, Liste des participants aux formations | H46: Manque de compétences des nouveaux utilisateurs | I46: Moyenne | J46: Erreurs fréquentes ; baisse d’efficacité | K46: Intégrer une formation d’accueil ; Créer un mentorat interne.
D47: Le guide est accessible aux utilisateurs autorisés. | E47: L’accès au guide utilisateur est-il restreint aux utilisateurs concernés ? | F47: PAS | G47: Liste des accès aux documents, Plateforme documentaire | H47: Accès non contrôlé au guide utilisateur | I47: Faible | J47: Risque de fuite d’informations sur l’utilisation | K47: Protéger les guides sensibles par mot de passe ; Restreindre la diffusion.
B48: Application | C48: S'assurer que l'accès aux ressources de l'application (données et transactions) est restreint par un système de gestion d'accès | D48: Existence d'un système formalisé de gestion des accès | E48: Existe-t-il un système formalisé de gestion des accès ? | F48: OUI | G48: Politique de sécurité des accès (document officiel) | H48: Non-conformité avec les standards de sécurité (ISO 27001, RGPD) | I48: Elevée | J48: Exposition à des sanctions juridiques et financières | K48: Réaliser un audit de conformité régulier ; mettre à jour les politiques internes selon les normes
D49: Le système est activé et effectivement appliqué sur l'application | E49: Le système est-il activé et effectivement appliqué sur l'application? | F49: OUI | G49: Preuve de configuration | H49: Accès non contrôlés exposant à des violations de données | I49: Elevée | J49: Fuite de données sensibles et perte de confiance | K49: Mettre en place un système de contrôle d'accès basé sur les rôles ; utiliser l’authentification forte
D50: Les accès aux fonctions sensibles (données critiques, transactions) sont spécifiquement restreints | E50: Les accès aux fonctions sensibles (données critiques, transactions) sont-elles spécifiquement restreints? | F50: NON | G50: Matrice des droits (tableau des accès par rôle/métier) | H50: Fraude ou fuite de données critiques | I50: Elevée | J50: Perte de données stratégiques ou financières | K50: Renforcer les mécanismes de journalisation et d’alerte ; former le personnel à la cybersécurité
D51: Les droits d'accès sont attribués en fonction des rôles et responsabilités des utilisateurs | E51: Les droits d'accès sont-ils attribués en fonction des rôles et responsabilités des utilisateurs ? | F51: NON | G51: Fiches de poste ou descriptions des responsabilités | H51: Privilèges excessifs (violation du principe de moindre privilège) | I51: Moyenne | J51: Risque d'abus d'accès ou modification non autorisée | K51: Implémenter le principe de moindre privilège ; effectuer des revues périodiques des accès
D52: Les révocations d'accès sont immédiates en cas de changement de poste ou de départ | E52: Les révocations d'accès sont-elles immédiates en cas de changement de poste ou de départ? | F52: NON | G52: Procédure de départ et journal des désactivations | H52: Accès résiduels exploités par d'anciens collaborateurs | I52: Elevée | J52: Compromission du système via des comptes inactifs | K52: Mettre en place une procédure de désactivation automatique des comptes après départ
C53: S’assurer qu’une procédure de gestion des profils utilisateurs existe | D53: Existence d’une procédure écrite de gestion des profils utilisateurs | E53: Existe t-il une procédure écrite de gestion des profils utilisateurs? | F53: OUI | G53: Manuel des procédures utilisateurs | H53: Incohérence dans la gestion des profils | I53: Moyenne | J53: Conflits d'accès, erreurs ou abus | K53: Uniformiser la gestion des profils via un référentiel centralisé
D54: La procédure définit clairement les rôles et permissions associés | E54: La procédure définit-elle clairement les rôles et permissions associés? | F54: OUI | G54: Arbre des rôles | H54: Attribution arbitraire des droits | I54: Moyenne | J54: Risque d’accès inapproprié à des informations sensibles | K54: Mettre en place des règles de validation multi-niveaux pour toute modification de droits
D55: Les demandes de création/modification de profils suivent un processus formalisé | E55: Les demandes de création/modification de profils suivent-elles un processus formalisé? | F55: OUI | G55: Formulaires de demande | H55: Création de profils non autorisés | I55: Moyenne | J55: Accès fantôme aux systèmes critiques | K55: Restreindre les droits de création de profils aux administrateurs certifiés
D56: Les profils inactifs ou obsolètes sont régulièrement supprimés ou désactivés | E56: Les profils inactifs ou obsolètes sont-ils régulièrement supprimés ou désactivés? | F56: NON | G56: Rapport des comptes désactivés (historique 6 mois) | H56: Portes dérobées pour attaques (comptes zombies) | I56: Elevée | J56: Intrusion discrète et durable dans le système | K56: Auditer régulièrement les comptes utilisateurs ; supprimer les comptes inactifs
D57: Un suivi des modifications apportées aux profils est maintenu et auditable. | E57: Un suivi des modifications apportées aux profils est-il maintenu et auditable? | F57: NON | G57: Logs des changements (exports Active Directory/outil IAM) | H57: Impossible de tracer les changements frauduleux | I57: Moyenne | J57: Difficulté d’enquête et de responsabilité | K57: Mettre en place un système de journalisation inviolable et horodaté
C58: Vérifier que l’identification des utilisateurs est réalisée | D58: Chaque utilisateur possède un identifiant unique et personnel | E58: Chaque utilisateur possède t-il un identifiant unique et personnel? | F58: OUI | G58: Liste des comptes actifs de l'application | H58: Impossible d'imputer les actions aux utilisateurs | I58: Elevée | J58: Non-respect des responsabilités, difficulté de sanction | K58: Appliquer des identifiants uniques non partagés ; désactiver les comptes partagés
D59: L’authentification requiert au moins un facteur robuste (mot de passe complexe, MFA, etc.) | E59: L’authentification requiert-il au moins un facteur robuste (mot de passe complexe, ,,.)? | F59: OUI | G59: Preuve de configuration | H59: Compromission facile des comptes | I59: Elevée | J59: Multiplication des attaques internes | K59: Renforcer les politiques de mot de passe et l’authentification à plusieurs facteurs
D60: Les comptes génériques ou partagés sont interdits ou strictement contrôlés | E60: Les comptes génériques ou partagés sont-ils interdits ou strictement contrôlés? | F60: OUI | G60: Audit des comptes (recherche de comptes génériques) | H60: Point d'entrée pour attaques internes | I60: Moyenne | J60: Accès non autorisé aux données sensibles | K60: Isoler les environnements critiques ; auditer les connexions internes
D61: Le système bloque les tentatives d’accès après plusieurs échecs d’authentification | E61: Le système bloque t-il les tentatives d’accès après plusieurs échecs d’authentification? | F61: NON | G61: Paramètres de sécurité (seuil de verrouillage) | H61: Attaques par force brute possibles | I61: Elevée | J61: Compromission des identifiants | K61: Imposer des limites de tentatives de connexion ; utiliser un captcha ou MFA
D62: Les identifiants inactifs sont automatiquement désactivés après une période définie | E62: Les identifiants inactifs sont-ils automatiquement désactivés après une période définie? | F62: NON | G62: Politique d'inactivité et liste des comptes désactivés | H62: Réutilisation par des tiers malveillants | I62: Elevée | J62: Détournement d'identifiants valides | K62: Interdire la réutilisation de mots de passe ; imposer des expirations régulières
C63: Vérifier qu’un mot de passe est associé à l'identifiant | D63: Tous les identifiants actifs disposent d'un mot de passe enregistré | E63: Tous les identifiants actifs disposent-ils d'un mot de passe enregistré? | F63: OUI | G63: Test de connexion (vérification sur échantillon) | H63: Accès sans authentification | I63: Elevée | J63: Accès libre aux ressources critiques | K63: Exiger l’authentification obligatoire sur tous les services
D64: Les mots de passe répondent aux exigences de complexité définies | E64: Les mots de passe répondent-ils aux exigences de complexité définiesv | F64: OUI | G64: Règles de sécurité | H64: Cassage facile des mots de passe | I64: Moyenne | J64: Intrusion rapide et indétectable | K64: Utiliser des politiques de complexité ; interdire les mots de passe trop simples
D65: Le stockage des mots de passe est chiffré et sécurisé | E65: Le stockage des mots de passe est-il chiffré et sécurisé? | F65: NON | G65: Preuve de hachage | H65: Fuite des credentials en clair | I65: Elevée | J65: Usurpation d’identité et compromission des systèmes | K65: Forcer l’utilisation de connexions chiffrées (HTTPS, SSH, etc.)
D66: La réinitialisation du mot de passe nécessite une validation sécurisée | E66: La réinitialisation du mot de passe nécessite t-il une validation sécurisée? | F66: NON | G66: Processus de reset | H66: Détournement de compte | I66: Elevée | J66: Utilisation malveillante du compte utilisateur | K66: Mettre en place la détection d’activités anormales
D67: Les mots de passe sont renouvelés périodiquement selon la politique établie | E67: Les mots de passe sont-ils renouvelés périodiquement selon la politique établie? | F67: NON | G67: Historique des changements (logs de rotations) | H67: Mots de passe périmés toujours actifs | I67: Faible | J67: Exploitation d’anciens accès | K67: Forcer l’expiration périodique et suppression automatique des accès inactifs
C68: S’assurer que les tentatives de connexions infructueuses à l'application sont suivies | D68: Toutes les tentatives de connexion infructueuses sont enregistrées dans un fichier de logs dédié | E68: Toutes les tentatives de connexion infructueuses sont-elles enregistrées dans un fichier de logs dédié? | F68: NON | G68: Fichiers de logs | H68: Impossible de détecter les attaques | I68: Moyenne | J68: Attaques prolongées sans réponse | K68: Mettre en place des outils de détection d'intrusion (IDS/IPS)
D69: Les logs contiennent systématiquement l'identifiant utilisé, l'horodatage et l'adresse IP source | E69: Les logs contiennent-ils systématiquement l'identifiant utilisé ? | F69: NON | G69: fichier de logs | H69: Investigation impossible après incident | I69: Moyenne | J69: Difficulté à remonter l’origine et étendue de l’attaque | K69: Assurer une journalisation complète, horodatée et centralisée
D70: Un mécanisme de blocage temporaire est déclenché après X tentatives infructueuses consécutives | E70: Un mécanisme de blocage temporaire est-il déclenché après X tentatives infructueuses consécutives? | F70: NON | G70: Paramètres de verrouillage | H70: Attaques par dictionnaire facilitées | I70: Elevée | J70: Compromission des comptes utilisateurs | K70: Bloquer les IP après tentatives répétées ; activer MFA
D71: Les logs des tentatives infructueuses sont conservés pendant une durée minimale de Y jours | E71: Les logs des tentatives infructueuses sont-ils conservés pendant une durée minimale de Y jours? | F71: NON | G71: Politique de rétention | H71: Non-conformité réglementaire | I71: Faible | J71: Sanctions financières et image dégradée | K71: Mettre à jour les politiques de sécurité régulièrement ; former les responsables
D72: Une alerte automatique est générée en cas de nombre anormal de tentatives infructueuses | E72: Une alerte automatique est-elle générée en cas de nombre anormal de tentatives infructueuses? | F72: NON | G72: Rapports d'alertes | H72: Détection tardive des intrusions | I72: Moyenne | J72: Dommages plus importants sur le SI | K72: Utiliser des outils SIEM pour l’analyse des logs en temps réel
C73: Vérifier que le niveau d’information et de moyen de contrôle adapté | D73: S'assurer que les informations critiques sont accessibles aux parties prenantes concernées. | E73: Les informations critiques sont-elles accessibles aux parties prenantes concernées ? | F73: OUI | G73: Politique de gestion des accès | H73: Accès non autorisé aux informations critiques | I73: Elevée | J73: Fuite ou modification de données sensibles | K73: Limiter les accès par niveaux de sensibilité ; surveiller en continu les accès
D74: Vérifier que les moyens de contrôle mis en place couvrent efficacement les risques identifiés. | E74: Les moyens de contrôle mis en place couvrent-ils efficacement les risques identifiés ? | F74: OUI | G74: Cartographie des risques | H74: Risques non couverts pouvant impacter l’organisation | I74: Moyenne | J74: Failles non anticipées exploitables | K74: Mettre en place une cartographie des risques et la réviser périodiquement
D75: Confirmer que les outils et ressources utilisés pour le contrôle sont adaptés aux besoins de l'organisation. | E75: Les outils et ressources utilisés pour le contrôle sont-ils adaptés aux besoins de l'organisation ? | F75: OUI | G75: Inventaire des outils de contrôle | H75: Utilisation d’outils inadaptés entraînant des contrôles inefficaces | I75: Elevée | J75: Échec de la détection des incidents ou anomalies | K75: Évaluer et adapter les outils aux besoins de l'organisation
D76: Garantir que les processus de contrôle sont documentés et mis à jour régulièrement. | E76: Les processus de contrôle sont-ils documentés et mis à jour régulièrement ? | F76: NON | G76: Procédures de contrôle interne | H76: Procédures de contrôle obsolètes ou inexistantes | I76: Elevée | J76: Failles ignorées ou mal traitées | K76: Mettre à jour les procédures de contrôle ; documenter les bonnes pratiques
D77: Évaluer l'efficacité des contrôles en analysant les résultats et en identifiant d'éventuelles lacunes. | E77: L’efficacité des contrôles est-elle évaluée à travers l’analyse des résultats et l’identification des lacunes ? | F77: NON | G77: Rapports d’audit interne | H77: Détection tardive des failles de contrôle | I77: Faible | J77: Décisions prises sur des informations erronées | K77: Mettre en place des contrôles d'intégrité ; utiliser des protocoles de transfert sécurisés
C78: Vérifier que les contrôles utilisateurs des états de sortie sont effectifs | D78: Confirmer que les utilisateurs effectuent des vérifications sur les états de sortie avant leur utilisation. | E78: Les utilisateurs effectuent-ils des vérifications sur les états de sortie avant leur utilisation ? | F78: NON | G78: Journal des vérifications utilisateur | H78: Utilisation de données erronées en raison d’un manque de vérification | I78: Moyenne | J78: Dysfonctionnements applicatifs ou résultats incohérents | K78: Vérifier la cohérence des échanges inter-modules ; documenter les API
D79: Vérifier la traçabilité des contrôles réalisés par les utilisateurs. | E79: Existe-t-il une traçabilité des contrôles réalisés par les utilisateurs ? | F79: NON | G79: Logs d’audit des systèmes | H79: Absence de traçabilité rendant difficile l’identification des erreurs | I79: Moyenne | J79: Difficulté à détecter ou corriger les erreurs | K79: Activer et conserver les logs des échanges entre systèmes
D80: S'assurer que des actions correctives sont mises en place en cas d'erreur détectée. | E80: Des actions correctives sont-elles mises en place en cas d'erreur détectée ? | F80: NON | G80: Registre des anomalies et corrections | H80: Non-correction des erreurs pouvant entraîner des impacts financiers ou opérationnels | I80: Elevée | J80: Décisions opérationnelles erronées | K80: Implémenter des contrôles de qualité sur les données entrantes
D81: Évaluer la formation des utilisateurs sur les contrôles à effectuer. | E81: Les utilisateurs sont-ils formés aux contrôles à effectuer ? | F81: NON | G81: Registre des formations | H81: Manque de compétences des utilisateurs sur les contrôles à effectuer | I81: Faible | J81: Conséquences financières ou organisationnelles | K81: Documenter et suivre les anomalies jusqu’à résolution complète
D82: Vérifier que les outils utilisés pour la vérification des états de sortie sont adaptés et performants. | E82: Les outils utilisés pour la vérification des états de sortie sont-ils adaptés et performants ? | F82: PAS | G82: Rapports de performance des outils | H82: Faible fiabilité des outils de vérification entraînant des erreurs non détectées | I82: Moyenne | J82: Dépendance excessive aux développeurs ; erreurs de manipulation | K82: Mettre en place une politique de documentation technique obligatoire
C83: S’assurer que les procédures de validation des résultats existent | D83: Vérifier l'existence de procédures documentées de validation des résultats. | E83: Existe-t-il des procédures documentées de validation des résultats ? | F83: OUI | G83: Manuel des procédures | H83: Absence de validation des résultats pouvant fausser les décisions | I83: Elevée | J83: Régressions et instabilité du système | K83: Utiliser une procédure de gestion de changement avec tests et validation
D84: S'assurer que ces procédures sont appliquées de manière systématique. | E84: Ces procédures sont-elles appliquées de manière systématique ? | F84: NON | G84: Journal des validations effectuées | H84: Procédures de validation non appliquées, compromettant la qualité des données | I84: Moyenne | J84: Retards et conflits dans les projets | K84: Clarifier les rôles dans une matrice RACI
D85: Confirmer que les validations sont effectuées par des personnes autorisées. | E85: Les validations sont-elles effectuées par des personnes autorisées ? | F85: NON | G85: Liste des personnes habilitées | H85: Validations effectuées par des personnes non autorisées, augmentant le risque d’erreurs | I85: Elevée | J85: Arrêts prolongés ; insatisfaction des utilisateurs | K85: Mettre en place une procédure de gestion des incidents avec indicateurs de suivi
D86: Vérifier que les résultats validés sont archivés de manière sécurisée. | E86: Les résultats validés sont-ils archivés de manière sécurisée ? | F86: NON | G86: Politique d’archivage | H86: Perte ou falsification des résultats validés | I86: Elevée | J86: Multiplication des risques non détectés | K86: Planifier des audits réguliers et suivre les plans d’action correctifs
D87: Évaluer l'efficacité des procédures à travers des tests ou des simulations. | E87: L’efficacité des procédures est-elle évaluée à travers des tests ou des simulations ? | F87: OUI | G87: Rapports de tests | H87: Procédures inefficaces ne permettant pas d’identifier les anomalies | I87: Faible | J87: Décisions non prises ou prises de manière inefficace | K87: Définir clairement les rôles dans une charte d’organisation
C88: S’assurer que l'intégrité et l'exhaustivité des données transmises entre les différents modules est garantie | D88: Vérifier l'existence de mécanismes de contrôle garantissant l'intégrité des données transmises. | E88: Des mécanismes de contrôle garantissent-ils l'intégrité des données transmises ? | F88: OUI | G88: Documentation des mécanismes de validation des données | H88: Altération ou perte de données lors des transmissions | I88: Moyenne | J88: Pertes financières ; atteinte à l’image | K88: Séparer les fonctions sensibles ; tracer toutes les opérations critiques
D89: S'assurer que les données transmises entre modules ne subissent pas de perte ou d'altération. | E89: Les données transmises entre modules subissent-elles une perte ou une altération ? | F89: NON | G89: Rapports de comparaison avant/après transmission | H89: Transmission incomplète ou corrompue des données entre modules | I89: Moyenne | J89: Arrêt de services ; mauvaise qualité de données | K89: Effectuer des tests approfondis avant mise en production
D90: Vérifier que des mécanismes de journalisation et de traçabilité des échanges existent. | E90: Des mécanismes de journalisation et de traçabilité des échanges existent-ils ? | F90: NON | G90: Logs de transaction | H90: Absence de journalisation empêchant la traçabilité des échanges | I90: Elevée | J90: Violation de données ; amendes réglementaires | K90: Utiliser des contrôles d’accès stricts et une gestion des identités
D91: Évaluer la gestion des erreurs en cas d'incohérence des données. | E91: La gestion des erreurs en cas d'incohérence des données est-elle efficace ? | F91: OUI | G91: Registre des erreurs et incidents | H91: Données erronées non détectées à temps | I91: Faible | J91: Altération malveillante de données | K91: Mettre en œuvre des revues périodiques des droits
D92: Confirmer que des tests réguliers sont réalisés pour garantir l’exactitude des transmissions. | E92: Des tests réguliers sont-ils réalisés pour garantir l’exactitude des transmissions ? | F92: NON | G92: Planning des tests | H92: Défauts non corrigés entraînant des décisions basées sur des informations incorrectes | I92: Moyenne | J92: Dysfonctionnement du système | K92: Formaliser un processus de validation avant tout déploiement
B93: Fonction informatique | C93: S’assurer que les tâches relatives au développement et à l'exploitation de l'application sont bien suivies et documentées | D93: Vérifier l'existence d'une documentation détaillée pour le développement et l’exploitation. | E93: Existe-t-il une documentation détaillée pour le développement et l’exploitation ? | F93: OUI | G93: Documentation technique de l’application | H93: Manque de documentation entraînant des difficultés de maintenance et d’exploitation | I93: Moyenne | J93: Ralentissements ou crashs | K93: Automatiser les tests unitaires et de non-régression
D94: S'assurer que les modifications et mises à jour sont bien suivies et validées. | E94: Les modifications et mises à jour sont-elles bien suivies et validées ? | F94: OUI | G94: Registre des modifications | H94: Changements non maîtrisés pouvant générer des dysfonctionnements | I94: Elevée | J94: Fonctionnalités existantes non fonctionnelles | K94: Effectuer des tests de régression après chaque modification
D95: Confirmer que les rôles et responsabilités des intervenants sont définis et respectés. | E95: Les rôles et responsabilités des intervenants sont-ils définis et respectés ? | F95: OUI | G95: Organigramme des responsabilités | H95: Absence de définition des responsabilités entraînant une mauvaise répartition des tâches | I95: Faible | J95: Sous-utilisation des outils ; gaspillage de ressources | K95: Former les utilisateurs ; accompagner le changement
D96: Vérifier la mise en place d’un processus de gestion des incidents et des anomalies. | E96: Un processus de gestion des incidents et des anomalies est-il mis en place ? | F96: NON | G96: Procédure de gestion des incidents | H96: Non-traitement des incidents pouvant perturber l’activité | I96: Moyenne | J96: Dégradation progressive du service | K96: Mettre en place une procédure de suivi et résolution des bugs
D97: S'assurer que des audits internes ou revues régulières sont réalisés pour garantir le suivi et la documentation. | E97: Des audits internes ou revues régulières sont-ils réalisés pour garantir le suivi et la documentation ? | F97: NON | G97: Plan d’audit interne | H97: Manque d’audits internes favorisant la persistance des failles et des erreurs | I97: Elevée | J97: Erreurs d’exploitation ou mauvaise maintenance | K97: Former régulièrement les administrateurs et utilisateurs
C98: Vérifier que la maintenance de la séparation des tâches est effective | D98: Les responsabilités des différents utilisateurs sont distinctes et clairement attribuées. | E98: Les responsabilités des utilisateurs sont-elles clairement définies ? | F98: OUI | G98: Organigramme des responsabilités, Fiches de poste | H98: Confusion des rôles et responsabilités | I98: Élevée | J98: Indisponibilité ou mauvais fonctionnement des services | K98: Créer des procédures d’installation documentées et validées
D99: - Il existe un mécanisme de contrôle empêchant les conflits d’intérêt dans les tâches critiques. | E99: Un contrôle empêche-t-il les conflits d’intérêts ? | F99: OUI | G99: Matrice de séparation des tâches, Rapport d’audit interne | H99: Risque de fraude interne | I99: Élevée | J99: Sanctions RGPD ; perte de confiance des partenaires | K99: Chiffrer les données sensibles et surveiller les accès
D100: - Les accès aux environnements de développement, test et production sont bien séparés. | E100: Les accès aux environnements sont-ils strictement séparés ? | F100: OUI | G100: Politique de gestion des accès, Liste des utilisateurs autorisés | H100: Risque d’erreurs en production | I100: Élevée | J100: Mauvaises décisions techniques ou fonctionnelles | K100: Mettre à jour la documentation à chaque évolution
D101: - Toute modification des droits est soumise à une validation formelle. | E101: Une validation formelle est-elle requise pour modifier les droits ? | F101: OUI | G101: Procédure de gestion des accès, Journal des modifications | H101: Risque d’accès non autorisé | I101: Élevée | J101: Temps de rétablissement plus long | K101: Mettre en place une cellule de crise et des playbooks
...

Sheet Ref_fontion_informatique
A1: Domaines | B1: points de contrôles | C1: objectifs de contrôle | D1: critères d'évaluation | E1: questions d'évaluation | F1: Réponses | G1: Documents requis | H1: Risques | I1: Criticités | J1: conséquences | K1: Recommandations
A2: Audit de la Fonction Informatique | B2: Rôle et positionnement de l'informatique dans l'organisation | C2: Vérifier qu’ont été créés des Comités « informatique » regroupant les différentes directions de l’Organisation en charge de recenser les besoins et les opportunités, gérer les priorités et suivre les projets | D2: Fréquence des réunions adaptée. | E2: La fréquence des réunions du comité SI est-elle adaptée aux besoins de pilotage ? | F2: OUI | G2: Calendrier des réunions, Comptes rendus de réunions | H2: Mauvais suivi des décisions SI | I2: Moyenne | J2: Décalage entre la stratégie et l’opérationnel | K2: Planifier un rythme régulier avec ajustements selon l’actualité SI
D3: Représentation et participation de toutes les directions clés. | E3: Toutes les directions clés sont-elles représentées et actives dans les réunions ? | F3: NON | G3: Liste des participants, Procès-verbaux | H3: Décisions prises sans vision globale | I3: Élevée | J3: Incohérence stratégique | K3: Assurer la présence obligatoire de chaque direction clé
D4: Formalisation et communication des décisions. | E4: Les décisions du comité sont-elles formalisées et communiquées aux parties prenantes ? | F4: OUI | G4: Procès-verbaux, Notes de service | H4: Manque de suivi des décisions | I4: Moyenne | J4: Non-exécution des décisions | K4: Diffuser systématiquement un relevé de décisions après chaque réunion
D5: Suivi de l'avancement des actions décidé. | E5: Un suivi formel est-il réalisé sur l’état d’avancement des actions décidées en réunion ? | F5: PAS | G5: Tableaux de bord de suivi, Rapports d’avancement | H5: Actions non mises en œuvre | I5: Élevée | J5: Retards ou blocages non détectés | K5: Mettre en place un tableau de suivi partagé avec mise à jour périodique
D6: Objectifs des comités clairs et atteints. | E6: Les objectifs du comité SI sont-ils clairement définis et évalués ? | F6: NON | G6: Charte du comité, Rapports d'activité | H6: Perte de sens du comité | I6: Moyenne | J6: Faible efficacité des réunions | K6: Formaliser les objectifs du comité et les évaluer régulièrement
C7: Vérifier l’existence d’une charte informatique ou de tout autre document définissant le rôle et le périmètre de responsabilité de la DSI | D7: Existence, accessibilité et communication de la charte. | E7: La charte de gouvernance du SI existe-t-elle et est-elle accessible aux acteurs concernés ? | F7: OUI | G7: Charte de gouvernance SI, Portail intranet | H7: Non-respect des règles établies | I7: Moyenne | J7: Incohérences de pilotage | K7: Veiller à sa diffusion auprès de tous les acteurs concernés
D8: Définition claire des rôles et responsabilités de la DSI. | E8: Les rôles et responsabilités de la DSI sont-ils définis clairement dans la charte ? | F8: OUI | G8: Organigramme DSI, Charte SI | H8: Chevauchement ou vide de responsabilités | I8: Moyenne | J8: Dysfonctionnements opérationnels | K8: Clarifier et documenter toutes les responsabilités dans la charte
D9: Couverture des domaines clés (sécurité, ressources, etc.). | E9: La charte couvre-t-elle tous les domaines clés de la gouvernance SI ? | F9: NON | G9: Charte SI, Cartographie des processus | H9: Gouvernance SI incomplète | I9: Élevée | J9: Risques non maîtrisés | K9: Compléter la charte avec tous les aspects essentiels du SI
D10: Mise à jour régulière et approbation de la charte. | E10: La charte est-elle mise à jour régulièrement et validée par les instances ? | F10: NON | G10: Historique des versions, PV de validation | H10: Obsolescence de la charte | I10: Moyenne | J10: Application de règles dépassées | K10: Mettre en place un processus de révision annuelle
D11: Cohérence pratiques/charte et contrôle de l'application. | E11: Les pratiques actuelles sont-elles conformes à la charte et font-elles l’objet de contrôles ? | F11: NON | G11: Rapports d’audit, Grilles de conformité | H11: Décalage entre règles et pratiques | I11: Élevée | J11: Failles dans la gouvernance | K11: Réaliser des audits réguliers de conformité
C12: Évaluer le degré d’implication et de maîtrise des organes de gestion dans les systèmes d’information de l’Organisation | D12: Participation active aux instances de décision SI. | E12: Les acteurs clés participent-ils activement aux comités décisionnels SI ? | F12: PAS | G12: Feuilles de présence, Comptes rendus | H12: Manque d’adhésion aux décisions | I12: Moyenne | J12: Mauvaise appropriation | K12: Sensibiliser et responsabiliser les membres sur leur rôle
D13: Compréhension des enjeux stratégiques des SI. | E13: Les membres des instances comprennent-ils les enjeux SI pour l’organisation ? | F13: NON | G13: Compte rendu de formation, Fiches d’objectifs | H13: Décisions mal orientées | I13: Élevée | J13: Investissements SI mal alignés | K13: Organiser des sessions de sensibilisation et d'acculturation
D14: Validation éclairée des orientations et investissements SI. | E14: Les décisions SI sont-elles prises en toute connaissance des impacts ? | F14: NON | G14: Business case, Études d’impact | H14: Mauvais arbitrage budgétaire | I14: Élevée | J14: Perte financière ou inefficacité | K14: Exiger une étude d’impact pour toute décision SI
D15: Réception et utilisation des indicateurs de performance SI. | E15: Les indicateurs de performance SI sont-ils transmis et utilisés ? | F15: PAS | G15: Tableau de bord SI, Rapports mensuels | H15: Pilotage à l’aveugle | I15: Moyenne | J15: Mauvais suivi de performance | K15: Mettre en place des indicateurs clairs et automatisés
D16: Actions de formation/sensibilisation aux enjeux SI. | E16: Des actions sont-elles menées pour former ou sensibiliser les parties prenantes ? | F16: NON | G16: Programmes de formation, Attestations de participation | H16: Incompréhension des enjeux | I16: Moyenne | J16: Mauvaise adoption des projets | K16: Planifier des formations annuelles obligatoires
C17: Vérifier en pratique que le leadership des grands projets est assuré par les organes de gestion | D17: Responsables des grands projets clairement désignés et légitimes. | E17: Les grands projets ont-ils des responsables désignés, reconnus et compétents ? | F17: OUI | G17: Organigramme projets, Fiches de poste | H17: Flou de responsabilité | I17: Moyenne | J17: Retards et dérives projet | K17: S’assurer de la désignation officielle et claire de responsables
D18: Définition collaborative des objectifs et livrables. | E18: Les objectifs et livrables sont-ils définis en concertation avec les parties prenantes ? | F18: NON | G18: Cahiers des charges, PV de réunion | H18: Non-adhésion des utilisateurs | I18: Moyenne | J18: Projets non conformes aux attentes | K18: Impliquer les utilisateurs dès la phase de cadrage
D19: Implication dans l'arbitrage et la prise de décision. | E19: Les utilisateurs sont-ils impliqués dans les arbitrages et décisions clés ? | F19: PAS | G19: PV de comités, Grille d’arbitrage | H19: Décisions mal acceptées | I19: Moyenne | J19: Rejet ou résistance | K19: Créer des groupes de co-décision par projet
D20: Communication régulière sur l'avancement des projets. | E20: Une communication fréquente est-elle faite sur l’avancement des projets SI ? | F20: NON | G20: Newsletters projets, Réunions de suivi | H20: Manque de visibilité | I20: Faible | J20: Mauvaise coordination | K20: Mettre en place des bulletins périodiques d’information
D21: Validation des étapes clés basée sur des critères objectifs. | E21: Les étapes des projets sont-elles validées sur la base de critères définis ? | F21: NON | G21: Plan qualité projet, Matrice de validation | H21: Validation arbitraire | I21: Moyenne | J21: Livrables non conformes | K21: Définir des critères de validation clairs dès le début
C22: Vérifier que les métiers assurent leur rôle de MOA | D22: Responsables MOA identifiés et rôle compris. | E22: Les responsables MOA sont-ils bien identifiés et leur rôle compris ? | F22: OUI | G22: Organigramme projet, Fiches de mission | H22: Ambiguïté dans les responsabilités | I22: Moyenne | J22: Problèmes d’interface MOA-MOE | K22: Clarifier les rôles dans les documents de projet
D23: Expression claire et détaillée des besoins fonctionnels. | E23: Les besoins fonctionnels sont-ils exprimés clairement par la MOA ? | F23: NON | G23: Cahier des charges, Comptes rendus d’ateliers | H23: Mauvaise interprétation des attentes | I23: Élevée | J23: Livrables non adaptés | K23: Organiser des ateliers de recueil des besoins
D24: Participation active à toutes les phases du projet. | E24: La MOA participe-t-elle à toutes les phases du projet ? | F24: PAS | G24: Planning de participation, Feuilles de présence | H24: Manque de suivi et de cohérence | I24: Moyenne | J24: Projet mal piloté | K24: Impliquer formellement la MOA dans chaque étape
D25: Validation des livrables par rapport aux besoins exprimés. | E25: Les livrables sont-ils validés en regard des besoins exprimés ? | F25: NON | G25: Grille de validation, PV de recette | H25: Non-conformité fonctionnelle | I25: Élevée | J25: Reprises coûteuses ou insatisfaction | K25: Organiser des phases de validation systématiques
D26: Implication dans la gestion du changement et la formation. | E26: Les utilisateurs sont-ils impliqués dans la conduite du changement et formés ? | F26: NON | G26: Plan de conduite du changement, Liste des participants | H26: Rejet du projet | I26: Élevée | J26: Non-appropriation des outils SI | K26: Prévoir un accompagnement structuré au changement
B27: Planification stratégique | C27: Vérifier la couverture du périmètre fonctionnel | D27: Adéquation entre le périmètre défini et les besoins métiers | E27: Le périmètre défini du projet répond-il aux besoins métiers identifiés ? | F27: NON | G27: Cahier des charges, Compte rendu des ateliers métiers | H27: Dérive fonctionnelle du projet | I27: Élevée | J27: Projet non aligné avec les attentes des utilisateurs | K27: Revoir les besoins métiers avec les parties prenantes
D28: Exhaustivité des fonctions couvertes dans la documentation | E28: Toutes les fonctions sont-elles bien documentées ? | F28: PAS | G28: Documentation fonctionnelle, Spécifications détaillées | H28: Risque de lacunes dans le développement ou la maintenance | I28: Moyenne | J28: Incohérence ou oubli lors de la mise en œuvre | K28: Compléter la documentation en impliquant les utilisateurs clés
D29: Cohérence entre le périmètre fonctionnel et les objectifs stratégiques | E29: Le périmètre fonctionnel est-il en cohérence avec les objectifs stratégiques ? | F29: NON | G29: Plan stratégique SI, Cartographie des processus | H29: Risque de perte de valeur métier | I29: Élevée | J29: Déconnexion entre l’informatique et la stratégie de l’organisation | K29: Aligner les projets SI sur la stratégie globale
D30: Identification des écarts entre périmètre prévu et réalisé | E30: Les écarts entre le périmètre prévu et celui réalisé sont-ils identifiés et documentés ? | F30: NON | G30: Revue de projet, Rapports d’audit | H30: Mauvais contrôle de projet | I30: Moyenne | J30: Écart de qualité ou de performance | K30: Mettre en place une procédure de suivi des écarts
D31: Validation de la couverture fonctionnelle par les parties prenantes | E31: Les parties prenantes valident-elles la couverture fonctionnelle du projet ? | F31: NON | G31: PV de validation, Emails de validation | H31: Mauvaise adoption de l’outil | I31: Moyenne | J31: Résistance au changement | K31: Impliquer les utilisateurs finaux dans la validation
C32: Vérifier l’existence d’une analyse à jour des procédures de pilotage et de mise à jour du plan informatique | D32: Disponibilité d'une documentation récente sur les procédures de pilotage | E32: Existe-t-il une documentation récente des procédures de pilotage ? | F32: NON | G32: Procédures de pilotage, Registre de version | H32: Pilotage inefficace ou inadapté | I32: Élevée | J32: Perte de contrôle sur les projets SI | K32: Mettre à jour régulièrement les procédures et les archiver
D33: Mise en évidence des rôles et responsabilités dans le processus de pilotage | E33: Les rôles et responsabilités sont-ils clairement définis dans le processus de pilotage ? | F33: NON | G33: Organigramme de gouvernance, Fiche de responsabilités | H33: Ambiguïtés dans la gestion | I33: Moyenne | J33: Conflits de rôle et blocages décisionnels | K33: Documenter clairement les rôles et les diffuser
D34: Preuve de révisions régulières du plan informatique | E34: Le plan informatique est-il révisé régulièrement ? | F34: PAS | G34: Historique des révisions, PV de comité | H34: Stratégie inadaptée | I34: Moyenne | J34: Décalage entre besoins métiers et SI | K34: Programmer des révisions périodiques avec suivi
D35: Adéquation des procédures avec les standards du secteur | E35: Les procédures de pilotage sont-elles alignées avec les standards du secteur ? | F35: NON | G35: Référentiel de bonnes pratiques, Audit de conformité | H35: Non-conformité aux bonnes pratiques | I35: Élevée | J35: Inefficacité ou risques accrus | K35: Comparer régulièrement les procédures aux standards reconnus
D36: Existence d'un mécanisme de suivi des actions correctives | E36: Un mécanisme est-il en place pour suivre les actions correctives issues du pilotage ? | F36: PAS | G36: Registre d’actions correctives, Suivi d’audit | H36: Répétition des erreurs ou dérives | I36: Élevée | J36: Accumulation de non-conformités | K36: Mettre en place un tableau de bord de suivi des corrections
C37: Vérifier l’existence des documents à jour d’urbanisme de l’Organisation | D37: Disponibilité des schémas directeurs d'urbanisme récents | E37: Les schémas directeurs d’urbanisme sont-ils disponibles et à jour ? | F37: NON | G37: Schéma directeur, PV de validation | H37: Désalignement stratégique | I37: Élevée | J37: Incohérence SI/stratégie | K37: Mettre à jour le schéma directeur régulièrement
D38: Cohérence entre l'urbanisme documenté et l'architecture réelle | E38: L’architecture réelle correspond-elle au schéma directeur documenté ? | F38: NON | G38: Cartographie technique, Rapport d’audit | H38: Incohérence structurelle | I38: Moyenne | J38: Difficile à maintenir ou faire évoluer | K38: Réaliser des audits d’alignement
D39: Mise à jour des documents suite aux évolutions organisationnelles | E39: Les documents sont-ils mis à jour à chaque évolution organisationnelle ? | F39: PAS | G39: Historique des versions, Organigrammes | H39: Obsolescence documentaire | I39: Moyenne | J39: Mauvaise adaptation du SI | K39: Définir un processus de mise à jour déclenché par les changements
D40: Accessibilité des documents pour les parties prenantes concernées | E40: Les parties prenantes ont-elles accès aux documents d’urbanisme ? | F40: NON | G40: Registre d’accès, Intranet documentaire | H40: Non-appropriation des référentiels | I40: Faible | J40: Erreurs ou décisions mal fondées | K40: Déployer une plateforme documentaire partagée
D41: Intégration des normes et réglementations en vigueur | E41: Les normes en vigueur sont-elles intégrées dans les documents ? | F41: NON | G41: Veille réglementaire, Référentiels métiers | H41: Non-conformité légale | I41: Élevée | J41: Risques juridiques et pénaux | K41: Mettre en place une veille active et intégrer ses résultats
C42: Vérifier l’existence d’une analyse à jour des procédures de pilotage et de mise à jour du plan d’occupation des sols (POS) | D42: Documentation récente des procédures de pilotage du POS | E42: Existe-t-il une version récente des procédures de pilotage du POS ? | F42: NON | G42: Manuel POS, Registre des mises à jour | H42: Inadéquation avec les réalités opérationnelles | I42: Moyenne | J42: Perte d’efficacité opérationnelle | K42: Réviser régulièrement les procédures
D43: Preuve de révisions régulières du POS | E43: Y a-t-il une trace des révisions régulières du POS ? | F43: NON | G43: Historique POS, PV de validation | H43: Obsolescence fonctionnelle | I43: Moyenne | J43: Non-respect des objectifs de pilotage | K43: Imposer un calendrier de révision du POS
D44: Adéquation des procédures avec la réglementation locale | E44: Les procédures du POS respectent-elles la réglementation locale ? | F44: PAS | G44: Texte de loi, Rapport de conformité | H44: Non-conformité réglementaire | I44: Élevée | J44: Sanctions ou blocage de projet | K44: Associer un juriste à la révision des procédures
D45: Mécanisme de suivi des modifications documenté | E45: Existe-t-il un mécanisme formalisé de suivi des modifications du POS ? | F45: NON | G45: Registre des modifications, Procédure de gestion des versions | H45: Perte de traçabilité | I45: Moyenne | J45: Incohérence dans les mises à jour | K45: Mettre en place une procédure de versionnage
D46: Validation par les autorités compétentes | E46: Les documents du POS sont-ils validés par les autorités concernées ? | F46: NON | G46: PV de validation, Signature des autorités | H46: Perte de légitimité | I46: Élevée | J46: Blocage de mise en œuvre | K46: Prévoir systématiquement une étape de validation officielle
C47: Vérifier la cohérence et l’homogénéité des technologies | D47: Inventaire technologique centralisé à jour | E47: Un inventaire technologique centralisé et à jour existe-t-il ? | F47: NON | G47: Base de données d’inventaire, Outil de gestion d’actifs | H47: Méconnaissance des ressources | I47: Élevée | J47: Risques de redondances ou obsolescence | K47: Utiliser un outil de gestion centralisé automatisé
D48: Analyse des compatibilités entre systèmes | E48: Les compatibilités entre systèmes sont-elles analysées ? | F48: PAS | G48: Rapport d’interopérabilité, Matrice de compatibilité | H48: Incompatibilités fonctionnelles | I48: Moyenne | J48: Échecs d’intégration | K48: Réaliser systématiquement une analyse de compatibilité
D49: Standards technologiques formalisés | E49: Les standards technologiques sont-ils documentés et diffusés ? | F49: NON | G49: Référentiel technique, Charte SI | H49: Disparité technologique | I49: Moyenne | J49: Maintenance complexe | K49: Établir et diffuser un référentiel unique
D50: Plan de gestion du cycle de vie des technologies | E50: Un plan de gestion du cycle de vie des technologies existe-t-il ? | F50: NON | G50: Plan d’évolution technologique, Planning de renouvellement | H50: Technologies obsolètes | I50: Élevée | J50: Augmentation des coûts et vulnérabilités | K50: Mettre en place une stratégie de renouvellement continue
D51: Procédures de contrôle des déviations | E51: Des procédures sont-elles en place pour contrôler les écarts aux normes ? | F51: OUI | G51: Fiches d’écart, Plan de contrôle | H51: Dérives non maîtrisées | I51: Moyenne | J51: Perte de qualité et de sécurité | K51: Instaurer un contrôle qualité régulier
C52: Vérifier l’existence et l’unicité des référentiels (clients, fournisseurs, articles…) et des saisies | D52: Référentiels uniques identifiés par domaine | E52: Chaque domaine dispose-t-il d’un référentiel unique identifié ? | F52: OUI | G52: Référentiels métiers, Cartographies fonctionnelles | H52: Multiplicité de sources de vérité | I52: Moyenne | J52: Risques d’erreurs ou de conflits | K52: Centraliser les référentiels et en limiter les doublons
D53: Procédures de gestion des doublons | E53: Des procédures existent-elles pour détecter et gérer les doublons ? | F53: OUI | G53: Rapport d’analyse, Procédure de nettoyage | H53: Incohérences dans les données | I53: Moyenne | J53: Mauvaise qualité des décisions | K53: Mettre en place un processus d’unification des données
D54: Contrôles d'intégrité des données | E54: Des contrôles d’intégrité des données sont-ils régulièrement effectués ? | F54: OUI | G54: Journal de contrôle, Rapport d’audit | H54: Données corrompues ou inexactes | I54: Élevée | J54: Décisions erronées | K54: Programmer des vérifications automatisées régulières
D55: Droits d'accès différenciés documentés | E55: Les droits d’accès sont-ils différenciés et documentés ? | F55: OUI | G55: Matrice des accès, Politique de sécurité | H55: Risque d’accès non autorisé | I55: Élevée | J55: Fuite ou corruption de données sensibles | K55: Réaliser un audit des droits d’accès et documenter les règles
D56: Historique des modifications tracé | E56: L’historique des modifications est-il bien tracé ? | F56: OUI | G56: Journal d’activité, Outil de versioning | H56: Perte de traçabilité | I56: Moyenne | J56: Difficulté à identifier les causes d’erreurs | K56: Intégrer des mécanismes d’audit trail systématiques
B57: Mesure et suivi de la performance informatique | C57: Vérifier que des objectifs de court, moyen et long termes existent et sont assignés à la DSI (approche BSC ) et que ces objectifs sont déclinés au sein de l’entité | D57: Balanced Scorecard disponible avec les 4 perspectives | E57: Le Balanced Scorecard couvre-t-il les perspectives finances, clients, processus internes et apprentissage ? | F57: OUI | G57: Balanced Scorecard, Rapport stratégique | H57: Suivi incomplet de la performance | I57: Élevée | J57: Vision stratégique déséquilibrée | K57: Élaborer un BSC intégral avec toutes les perspectives
D58: Arbre de déploiement des objectifs par service | E58: Existe-t-il un arbre de déploiement des objectifs par service ? | F58: OUI | G58: Arbre stratégique, Feuille de route par service | H58: Objectifs mal alignés | I58: Moyenne | J58: Difficulté de pilotage local | K58: Déployer les objectifs top-down avec traçabilité
D59: Indicateurs SMART définis | E59: Les indicateurs sont-ils spécifiques, mesurables, atteignables, réalistes et temporels ? | F59: OUI | G59: Fiches d’indicateurs, Tableaux de bord | H59: Pilotage inefficace | I59: Moyenne | J59: Indicateurs non exploitables | K59: Revoir les indicateurs selon la méthode SMART
D60: Calendrier des revues formelles | E60: Un calendrier des revues formelles est-il établi et respecté ? | F60: OUI | G60: Planning de gouvernance, PV de réunion | H60: Manque de suivi régulier | I60: Moyenne | J60: Retard dans les ajustements | K60: Mettre à jour et suivre un calendrier des revues
D61: Mécanismes d'ajustement documentés | E61: Les mécanismes d’ajustement sont-ils formalisés ? | F61: OUI | G61: Procédure d’ajustement, Fiches de décisions | H61: Réactivité limitée | I61: Moyenne | J61: Maintien d’indicateurs inadaptés | K61: Documenter les processus de révision des objectifs
C62: Vérifier l’existence d’un comité informatique regroupant les différentes directions de l’organisation | D62: Composition représentative documentée | E62: La composition des comités est-elle représentative et documentée ? | F62: OUI | G62: PV de nomination, Liste des membres | H62: Déséquilibre décisionnel | I62: Moyenne | J62: Mauvaise représentativité | K62: Formaliser et équilibrer la composition des instances
D63: Périmètre de décision clairement défini | E63: Le périmètre de décision des instances est-il clairement défini ? | F63: NON | G63: Règlement de fonctionnement, Fiches de rôle | H63: Conflits d'autorité | I63: Moyenne | J63: Blocage dans la prise de décision | K63: Définir et documenter les périmètres de responsabilité
D64: Fréquence des réunions conforme aux besoins | E64: La fréquence des réunions est-elle adaptée aux besoins du pilotage ? | F64: OUI | G64: Calendrier des réunions, PV | H64: Retard dans le suivi | I64: Faible | J64: Manque de réactivité | K64: Réajuster la fréquence en fonction des enjeux
D65: Comptes-rendus diffusés et archivés | E65: Les comptes-rendus de réunion sont-ils diffusés et archivés ? | F65: OUI | G65: PV, Dossier de réunion | H65: Perte d’historique des décisions | I65: Moyenne | J65: Risque de redondance ou oubli | K65: Mettre en place un espace d’archivage partagé
D66: Suivi des actions décidées | E66: Les actions décidées en réunion sont-elles suivies ? | F66: OUI | G66: Plan d’actions, Tableau de suivi | H66: Actions non réalisées | I66: Moyenne | J66: Perte d’efficacité du pilotage | K66: Mettre en œuvre un tableau de suivi avec responsable et délai
C67: Évaluer la pertinence des indicateurs de qualité et de performance ainsi que les moyens et outils de mesure | D67: Cartographie des indicateurs liée aux processus | E67: Existe-t-il une cartographie liant indicateurs et processus ? | F67: NON | G67: Cartographie, Tableaux de bord | H67: Mauvais positionnement des indicateurs | I67: Moyenne | J67: Suivi décorrélé des réalités | K67: Lier chaque indicateur à un processus métier précis
D68: Métadonnées disponibles (calcul, fréquence, cible) | E68: Les métadonnées des indicateurs sont-elles documentées ? | F68: PAS | G68: Fiches de définition, Glossaire | H68: Mauvaise interprétation des indicateurs | I68: Moyenne | J68: Pilotage erroné | K68: Standardiser la fiche de chaque indicateur
D69: Outils de collecte et d'analyse identifiés | E69: Les outils de collecte et d’analyse sont-ils identifiés et documentés ? | F69: NON | G69: Liste des outils, Manuel d’utilisation | H69: Collecte incohérente | I69: Moyenne | J69: Résultats non comparables | K69: Uniformiser les outils et leur utilisation
D70: Processus d'amélioration continue | E70: Un processus d'amélioration continue est-il en place ? | F70: NON | G70: Plan d’amélioration, Retours d’expérience | H70: Stagnation de la performance | I70: Élevée | J70: Perte de compétitivité | K70: Instaurer une démarche PDCA ou équivalente
D71: Benchmark sectoriel réalisé | E71: Un benchmark avec le secteur est-il régulièrement réalisé ? | F71: NON | G71: Rapport de benchmark, Analyse comparative | H71: Manque de positionnement | I71: Moyenne | J71: Objectifs mal calibrés | K71: Comparer les résultats aux standards du secteur
C72: Vérifier que la DSI tient un tableau de bord (idéalement de type BSC) permettant un suivi consolidé de la performance (opérationnelle et financière) et de la qualité des prestations informatiques | D72: Couverture des axes financiers, clients et processus | E72: Les indicateurs couvrent-ils bien les axes financiers, clients et processus ? | F72: PAS | G72: Tableau de bord, Référentiel d’indicateurs | H72: Pilotage partiel | I72: Moyenne | J72: Incohérence stratégique | K72: Vérifier la complétude du tableau de bord
D73: Doncées sources identifiées et fiables | E73: Les sources de données sont-elles identifiées et fiables ? | F73: NON | G73: Référentiel des données, Procédures de contrôle | H73: Mauvaise qualité de l'information | I73: Élevée | J73: Décisions basées sur des données erronées | K73: Répertorier les sources et en vérifier la fiabilité
D74: Fréquence de mise à jour adaptée | E74: La fréquence de mise à jour des indicateurs est-elle adaptée ? | F74: NON | G74: Planning de mise à jour, Historique de suivi | H74: Décalage temporel | I74: Moyenne | J74: Décision sur des données obsolètes | K74: Adapter la fréquence à la criticité des indicateurs
D75: Tableaux de bord différenciés par public | E75: Les tableaux de bord sont-ils adaptés aux différents profils d’utilisateurs ? | F75: NON | G75: Tableau de bord, Matrice des besoins | H75: Surcharge ou manque d’information | I75: Moyenne | J75: Incompréhension ou mauvaise utilisation | K75: Concevoir des dashboards adaptés à chaque rôle
D76: Processus d'alerte sur les écarts | E76: Un processus d’alerte est-il mis en œuvre pour les écarts significatifs ? | F76: NON | G76: Seuils d’alerte, Procédure de notification | H76: Non-réactivité face aux anomalies | I76: Moyenne | J76: Aggravation des écarts | K76: Définir des seuils et automatiser les alertes
C77: Vérifier qu’il est systématiquement effectué un bilan après chaque projet et notamment un bilan économique (bilan rapproché des prévisions de l’étude préalable) | D77: Modèle standard de bilan post-projet | E77: Existe-t-il un modèle standard pour les bilans post-projets ? | F77: OUI | G77: Fiche post-mortem, Modèle de bilan | H77: Apprentissage non capitalisé | I77: Moyenne | J77: Répétition des erreurs | K77: Formaliser un modèle standardisé à utiliser systématiquement
D78: Analyse des écarts (coûts, délais, qualité) | E78: Les écarts coûts/délais/qualité sont-ils systématiquement analysés ? | F78: PAS | G78: Rapport d’analyse, Feuille de suivi | H78: Non-maîtrise des dérives | I78: Moyenne | J78: Dérives récurrentes non maîtrisées | K78: Inscrire l’analyse d’écarts comme obligation de clôture
D79: Plan d'actions correctives formalisé | E79: Les actions correctives sont-elles formalisées après les bilans ? | F79: PAS | G79: Plan d’action, Responsable désigné | H79: Répétition des erreurs | I79: Élevée | J79: Perte de crédibilité | K79: Mettre en œuvre un plan d’action avec échéances et responsables
D80: Capitalisation des bonnes pratiques | E80: Les bonnes pratiques sont-elles capitalisées ? | F80: OUI | G80: Base de connaissances, Retours d’expérience | H80: Perte de savoir-faire | I80: Moyenne | J80: Réinvention permanente | K80: Mettre à disposition un référentiel de bonnes pratiques
D81: Communication aux sponsors | E81: Les sponsors reçoivent-ils une communication régulière sur les projets ? | F81: OUI | G81: Compte-rendu, Rapport périodique | H81: Désengagement du sponsor | I81: Moyenne | J81: Perte de soutien | K81: Prévoir une communication formelle dans le plan projet
B82: Organisation et structure de la DSI | C82: Vérifier l’existence d’un organigramme à jour de la DSI | D82: Version datée et validée | E82: La documentation est-elle datée et validée formellement ? | F82: NON | G82: Signature, Historique des versions | H82: Utilisation de documents obsolètes | I82: Élevée | J82: Erreurs dans l’application | K82: Intégrer une procédure de versionnage avec validation
D83: Fonctions et postes clairement identifiés | E83: Les fonctions et postes sont-ils clairement mentionnés dans les documents ? | F83: OUI | G83: Organigramme, Fiche de poste | H83: Ambiguïté des responsabilités | I83: Moyenne | J83: Manque de responsabilité ou doublon | K83: Clarifier les affectations dans chaque processus
D84: Circuit de validation des modifications | E84: Un circuit de validation des modifications est-il défini ? | F84: OUI | G84: Procédure de validation, Matrice des responsabilités | H84: Changements non contrôlés | I84: Moyenne | J84: Risques d’erreurs non approuvées | K84: Documenter et respecter un
D85: Diffusion contrôlée aux parties prenantes | E85: La diffusion des documents clés est-elle restreinte aux parties prenantes concernées ? | F85: NON | G85: Liste de diffusion, Registre d’accès | H85: Divulgation d’informations sensibles | I85: Élevée | J85: Risques juridiques, pertes de confidentialité | K85: Utiliser des listes de diffusion contrôlées et journaliser les accès
D86: Alignement avec la structure réelle | E86: L’organigramme officiel reflète-t-il la réalité opérationnelle ? | F86: PAS | G86: Organigramme, Rapports d’audit interne | H86: Mauvaise répartition des responsabilités | I86: Moyenne | J86: Inefficacité dans les processus décisionnels | K86: Réviser périodiquement l’organigramme selon les évolutions de l’activité
C87: Vérifier l’existence d’une définition de fonction et d’un partage clair des rôles et des responsabilités pour chaque poste figurant sur l’organigramme | D87: Fiches de poste disponibles pour chaque position | E87: Chaque poste dispose-t-il d’une fiche de poste à jour ? | F87: NON | G87: Fiches de poste, Dossier RH | H87: Flou dans les missions, conflits internes | I87: Moyenne | J87: Baisse de performance, désorganisation des équipes | K87: Mettre en place un modèle standard et en assurer la mise à jour régulière
D88: Matrice RACI pour les processus clés | E88: Une matrice RACI est-elle formalisée pour les processus clés ? | F88: NON | G88: Matrice RACI, Cartographie des processus | H88: Confusion dans les responsabilités | I88: Élevée | J88: Retards, redondances ou omissions dans les actions | K88: Élaborer une matrice RACI claire et la communiquer à toutes les parties prenantes
D89: Mécanismes de résolution des conflits | E89: Existe-t-il une procédure formelle de gestion des conflits ? | F89: NON | G89: Procédure de médiation, Charte de conduite | H89: Dégradation du climat social | I89: Moyenne | J89: Démotivation, turnover | K89: Mettre en place une cellule de médiation et une procédure transparente
D90: Processus d'évaluation des compétences | E90: Un processus formel d’évaluation des compétences est-il en place ? | F90: PAS | G90: Grille d’évaluation, Compte rendu d’entretien | H90: Inadéquation compétences/postes | I90: Élevée | J90: Baisse de qualité des prestations, erreurs métier | K90: Réaliser une évaluation annuelle liée au plan de formation
D91: Mise à jour annuelle formalisée | E91: Les documents de gouvernance sont-ils mis à jour chaque année ? | F91: NON | G91: Planning de révision, PV de revue annuelle | H91: Obsolescence des informations utilisées | I91: Moyenne | J91: Décisions prises sur des bases erronées | K91: Planifier une revue documentaire annuelle avec responsables désignés
C92: Vérifier que l’ensemble des composantes d’une fonction informatique est convenablement pris en compte, notamment la veille technologique, la sécurité informatique, la fonction qualité & méthodes, la gestion des ressources humaines, le contrôle de gestion, le support utilisateurs (de proximité et à distance), l’administration des serveurs | D92: Cartographie complète des fonctions IT | E92: Une cartographie des fonctions IT est-elle disponible et à jour ? | F92: NON | G92: Cartographie IT, Schéma fonctionnel | H92: Incohérences entre l’organisation IT et les besoins métiers | I92: Moyenne | J92: Redondances, lacunes, difficulté d’alignement | K92: Mettre à jour la cartographie en fonction des évolutions techniques et organisationnelles
D93: Responsables nommés pour chaque domaine | E93: Chaque domaine IT ou métier a-t-il un responsable identifié ? | F93: NON | G93: Notes de service, Organigramme fonctionnel | H93: Absence de pilotage | I93: Élevée | J93: Perte de contrôle, retards dans les livrables | K93: Affecter formellement un responsable à chaque périmètre
D94: Budget alloué à chaque composante | E94: Chaque composante fonctionnelle dispose-t-elle d’un budget dédié ? | F94: NON | G94: Plan budgétaire, Fiches de ventilation | H94: Blocages dans les projets | I94: Élevée | J94: Activités non réalisées, dépendance à des financements exceptionnels | K94: Allouer un budget prévisionnel annuel par activité clé
D95: Plan de développement des compétences | E95: Un plan structuré de développement des compétences est-il défini ? | F95: OUI | G95: Plan de formation, Entretien professionnel | H95: Non-anticipation des besoins futurs | I95: Élevée | J95: Pénurie de compétences, désalignement avec la stratégie | K95: Définir un plan triennal évolutif aligné avec les objectifs de l’organisation
D96: Indicateurs de performance spécifiques | E96: Des indicateurs de performance adaptés sont-ils suivis pour chaque processus ? | F96: PAS | G96: Tableaux de bord, Fiches de KPI | H96: Absence de mesure de l’efficacité | I96: Moyenne | J96: Pilotage à vue, décisions subjectives | K96: Mettre en place des indicateurs SMART revus périodiquement
C97: Évaluer l’adéquation des effectifs aux besoins et aux enjeux | D97: Analyse des volumes d'activité par métier | E97: Le volume d’activité est-il mesuré par métier ou fonction ? | F97: PAS | G97: Tableaux de suivi, Données opérationnelles | H97: Surcharge ou sous-utilisation de certaines équipes | I97: Moyenne | J97: Déséquilibre dans la répartition des charges | K97: Suivre mensuellement les volumes et ajuster les ressources
D98: Comparaison avec les référentiels sectoriels | E98: Les pratiques internes sont-elles comparées aux standards du secteur ? | F98: OUI | G98: Études de marché, Benchmarks | H98: Manque de compétitivité | I98: Moyenne | J98: Retard stratégique, perte d’attractivité | K98: Intégrer une veille concurrentielle dans la revue annuelle
D99: Plan de charge prévisionnel | E99: Un plan de charge est-il établi pour chaque équipe ou projet ? | F99: OUI | G99: Planification annuelle, Outils de gestion | H99: Retards, surcharge, conflits de ressources | I99: Élevée | J99: Dérive des délais, burn-out | K99: Utiliser des outils de gestion de la charge et suivre en temps réel
D100: Gestion des pics d'activité | E100: Existe-t-il des dispositifs de gestion des pics d’activité ? | F100: NON | G100: Plan de continuité, Renforts temporaires | H100: Dégradation du service rendu | I100: Moyenne | J100: Baisse de qualité, insatisfaction des usagers | K100: Prévoir des renforts ponctuels ou externes selon les périodes critiques
...

Sheet Ref_control_projet_informatique
A1: Points de controle | B1: Objectifs de controle | C1: Criteres d'évaluations | D1: Questions d'évaluation | E1: Réponses | F1: Document requis | G1: Risque | H1: Criticités | I1: Conséquence | J1: Recommandations
A2: Objectifs et enjeux du projet | B2: S’assurer qu’une étude de la valeur et des études d'opportunité et d'impacts ont été réalisées | C2: Une étude formelle documente le retour sur investissement attendu | D2: Existe-t-il une analyse coûts/bénéfices chiffrée ? | E2: NON | F2: Rapport d'analyse coûts/bénéfices | G2: Décision non éclairée | H2: Elevée | I2: Investissements inefficaces, gaspillage de budget | J2: Réaliser une étude économique détaillée avant validation.
C3: Les impacts opérationnels ont été évalués (processus, organisation) | D3: Les conséquences sur l'organisation ont-elles été étudiées ? | E3: OUI | F3: Rapport d'impact organisationnel | G3: Résistance au changement, perturbation opérationnelle | H3: Moyenne | I3: Baisse de productivité, échec d'adoption | J3: Prévoir un plan de changement management.
C4: Les risques techniques et fonctionnels ont été identifiés | D4: Une analyse des risques spécifiques a-t-elle été conduite ? | E4: OUI | F4: Matrice des risques | G4: Risques non identifiés | H4: Moyenne | I4: Problèmes imprévus, dépassement de coûts | J4: Mettre à jour l'analyse des risques régulièrement.
C5: L'étude compare plusieurs scénarios possibles | D5: Plusieurs options ont-elles été comparées objectivement ? | E5: OUI | F5: Comparatif des solutions | G5: Choix sous-optimal | H5: Elevée | I5: Coûts élevés, performance insuffisante | J5: Évaluer au moins 3 scénarios avec critères clairs.
C6: L'étude a été validée par la direction et les parties prenantes | D6: Les décideurs ont-ils formellement approuvé l'étude ? | E6: NON | F6: PV de validation | G6: Absence d'engagement | H6: Moyenne | I6: Retards, conflits stratégiques | J6: Obtenir une signature formelle des parties prenantes.
B7: S’assurer qu’un bilan critique des processus existants a été effectué | C7: Un audit complet des processus actuels a été réalisé | D7: Existe-t-il un rapport d'audit des processus existants ? | E7: NON | F7: Rapport d'audit | G7: Inefficacités non détectées | H7: Elevée | I7: Perpétuation des dysfonctionnements | J7: Auditer les processus avant toute refonte.
C8: Les dysfonctionnements et goulots d'étranglement sont documentés | D8: Les points critiques ont-ils été clairement identifiés ? | E8: NON | F8: Cartographie des risques | G8: Goulots d'étranglement | H8: Moyenne | I8: Retards, échec partiel | J8: Prioriser les actions sur les points critiques.
C9: Les indicateurs de performance actuels sont mesurés et analysés | D9: Des métriques de performance existantes sont-elles disponibles ? | E9: NON | F9: Tableau de bord KPIs | G9: Évaluation subjective | H9: Moyenne | I9: Impossible de mesurer le succès | J9: Définir des indicateurs clés avant démarrage.
C10: Les coûts associés aux processus actuels sont chiffrés | D10: Le coût total de possession des processus est-il connu ? | E10: PAS | F10: Modèle financier TCO | G10: Dépenses imprévues | H10: Elevée | I10: Dérive budgétaire | J10: Inclure maintenance, formation et support dans le calcul.
C11: Le bilan inclut des retours d'expérience des utilisateurs | D11: Le feedback des opérationnels a-t-il été recueilli ? | E11: NON | F11: Compte-rendu de consultation | G11: Besoins terrain ignorés | H11: Moyenne | I11: Solution inadaptée | J11: Organiser des ateliers avec les utilisateurs finaux.
B12: S’assurer que le choix de recourir à un nouveau système est obtenu après optimisation des processus concernés et vérification que cette optimisation ne suffit pas à apporter par elle-même les gains de performance attendus | C12: Des pistes d'amélioration des processus existants ont été explorées | D12: Des solutions sans nouveau système ont-elles été envisagées ? | E12: NON | F12: Analyse d'optimisation | G12: Investissement inutile | H12: Moyenne | I12: Coûts superflus | J12: Explorer les améliorations process avant tout achat.
C13: Un prototype d'optimisation a été testé avec des résultats mesurés | D13: Des tests d'optimisation ont-ils démontré leurs limites ? | E13: OUI | F13: Rapport de tests | G13: Illusion de gains faciles | H13: Moyenne | I13: Améliorations insuffisantes | J13: Tester rigoureusement avant décision finale.
C14: La décision finale est justifiée par des éléments tangibles | D14: Le choix du nouveau système s'appuie-t-il sur des preuves ? | E14: NON | F14: Benchmark techniques | G14: Solution inadéquate | H14: Elevée | I14: Échec fonctionnel | J14: Exiger des preuves (POC, références clients).
C15: Le comité de direction a validé la nécessité du changement | D15: La direction a-t-elle acté l'insuffisance des optimisations ? | E15: OUI | F15: PV de décision | G15: Dénis des problèmes | H15: Elevée | I15: Retard dans la modernisation | J15: Formaliser les constats d'inefficacité.
C16: Le plan de transition préserve les améliorations déjà réalisées | D16: Les optimisations existantes seront-elles conservées ? | E16: OUI | F16: Plan de migration | G16: Perte des bonnes pratiques | H16: Moyenne | I16: Régression opérationnelle | J16: Documenter les éléments à conserver.
B17: S’assure que les objectifs et périmètres du projet sont définis, partagés et stabilisés | C17: Un document de cadrage formalise les objectifs et le périmètre | D17: Existe-t-il un document de référence approuvé ? | E17: NON | F17: Charte de projet | G17: Flou sur les objectifs | H17: Moyenne | I17: Dérives de scope | J17: Valider un document cadre signé.
C18: Les livrables attendus sont spécifiés et quantifiés | D18: Les résultats concrets attendus sont-ils clairement définis ? | E18: OUI | F18: Cahier des charges | G18: Attentes irréalistes | H18: Elevée | I18: Insatisfaction | J18: Spécifier des objectifs SMART.
C19: Les limites du projet sont explicitement mentionnées | D19: Ce qui est hors scope est-il précisément identifié ? | E19: OUI | F19: Périmètre documenté | G19: "Scope creep" | H19: Elevée | I19: Délais et coûts non maîtrisés | J19: Lister explicitement les exclusions.
C20: Tous les départements concernés ont validé le périmètre | D20: Les différentes directions ont-elles signé le cadrage ? | E20: OUI | F20: Accord inter-directions | G20: Conflits internes | H20: Moyenne | I20: Blocages politiques | J20: Obtenir l'alignement transversal.
C21: Un mécanisme de gestion des changements de périmètre existe | D21: Comment les évolutions de scope seront-elles gérées ? | E21: NON | F21: Procédure de changement | G21: Dérives non contrôlées | H21: Elevée | I21: Explosion budgétaire | J21: Instaurer un comité de changement.
B22: S’assurer que les principales orientations du système cible ont été explicitées | C22: L'architecture générale du futur système est décrite | D22: Existe-t-il un schéma d'architecture validé ? | E22: NON | F22: Diagramme d'architecture | G22: Incompatibilités techniques | H22: Elevée | I22: Retards d'intégration | J22: Faire valider l'architecture par un expert.
C23: Les choix technologiques majeurs sont documentés et justifiés | D23: Les technologies clés ont-elles été sélectionnées avec raison ? | E23: NON | F23: Argumentaire technologique | G23: Obsolescence rapide | H23: Elevée | I23: Coûts de migration futurs | J23: Choisir des technologies évolutives.
C24: Les principes de conception (SaaS, cloud, etc.) sont arrêtés | D24: Le modèle de déploiement est-il clairement défini ? | E24: NON | F24: Plan de déploiement | G24: Mise en production chaotique | H24: Elevée | I24: Interruptions de service | J24: Prévoir un pilote avant généralisation.
C25: Les interfaces avec les systèmes existants sont planifiées | D25: Comment l'intégration avec le SI actuel sera-t-elle gérée ? | E25: PAS | F25: Plan d'intégration | G25: Silos techniques | H25: Moyenne | I25: Données fragmentées | J25: Tester les APIs et connecteurs en amont.
C26: La roadmap des évolutions futures est esquissée | D26: Les besoins d'évolution à moyen terme sont-ils anticipés ? | E26: NON | F26: Feuille de route | G26: Solution rigide | H26: Elevée | I26: Coûts de refonte | J26: Privilégier des solutions modulaires.
B27: S’assurer que les principaux acteurs sont identifiés | C27: Un organigramme des parties prenantes a été établi | D27: Tous les acteurs clés sont-ils identifiés avec leurs rôles ? | E27: NON | F27: Matrice RACI | G27: Responsabilités floues | H27: Moyenne | I27: Retards dans les validations | J27: Affecter un responsable par livrable.
C28: Les sponsors et décideurs sont clairement désignés | D28: Qui sont les responsables de la validation des étapes clés ? | E28: OUI | F28: Désignation formelle | G28: Blocages décisionnels | H28: Moyenne | I28: Retards critiques | J28: Nommer un sponsor exécutif.
C29: Les équipes opérationnelles (MOA, MOE) sont constituées | D29: Les ressources internes/externes sont-elles affectées ? | E29: NON | F29: Plan de ressourcement | G29: Sous-effectif | H29: Elevée | I29: Délais non tenus | J29: Sécuriser les ressources avant lancement.
C30: Un comité de pilotage incluant toutes les parties est formé | D30: Existe-t-il une instance de gouvernance multidisciplinaire ? | E30: OUI | F30: Comité de pilotage | G30: Décisions cloisonnées | H30: Moyenne | I30: Incohérences | J30: Réunir les parties prenantes mensuellement.
C31: Les dépendances entre acteurs sont cartographiées | D31: Les interactions critiques entre parties prenantes sont-elles connues ? | E31: OUI | F31: Cartographie des parties prenantes | G31: Communication inefficace | H31: Moyenne | I31: Malentendus, conflits | J31: Clarifier les canaux de communication.
B32: S’assurer que les coûts sont évalués | C32: Une estimation détaillée des investissements initiaux existe | D32: Les coûts d'acquisition/implémentation sont-ils chiffrés ? | E32: OUI | F32: Budget détaillé | G32: Sous-estimation | H32: Moyenne | I32: Dépassement financier | J32: Inclure une marge pour imprévus (10-15%).
C33: Les coûts récurrents (maintenance, licences) sont budgétés | D33: Le TCO (coût total de possession) est-il calculé ? | E33: PAS | F33: Modèle TCO sur 5 ans | G33: Coûts cachés | H33: Elevée | I33: Budget insuffisant | J33: Intégrer maintenance, licences, et formation.
C34: Les économies attendues sont quantifiées et datées | D34: Le ROI est-il projeté avec un échéancier réaliste ? | E34: OUI | F34: Business case | G34: Retour sur investissement illusoire | H34: Elevée | I34: Échec économique | J34: Baser les projections sur des données historiques.
C35: Un plan de financement pluriannuel a été établi | D35: Comment le projet sera-t-il financé année après année ? | E35: NON | F35: Plan de financement | G35: Pénurie de trésorerie | H35: Moyenne | I35: Arrêt du projet | J35: Sécuriser les fonds avant chaque phase.
C36: Des scénarios alternatifs avec leurs impacts financiers sont prévus | D36: Que se passe-t-il en cas de dépassement budgétaire ? | E36: PAS | F36: Plan de contingence | G36: Dette technique | H36: Moyenne | I36: Abandon partiel | J36: Prévoir des leviers de réduction des coûts.
B37: S’assurer que les liens et impacts avec des projets connexes et les infrastructures (Datacenter, réseaux, etc.) sont pris en compte | C37: Une cartographie des dépendances avec d'autres projets existe | D37: Les interactions avec les initiatives parallèles sont-elles analysées ? | E37: OUI | F37: Cartographie des projets | G37: Doublons ou contradictions | H37: Elevée | I37: Gaspi de ressources | J37: Harmoniser les feuilles de route.
C38: Les impacts sur les infrastructures techniques sont évalués | D38: Les besoins en datacenter, réseau, etc. sont-ils anticipés ? | E38: NON | F38: Audit infrastructure | G38: Goulots techniques | H38: Elevée | I38: Performances médiocres | J38: Mettre à niveau l'infrastructure si besoin.
C39: Un plan de coordination avec les autres projets est défini | D39: Comment les synergies seront-elles exploitées ? | E39: OUI | F39: Analyse des synergies | G39: Opportunités manquées | H39: Moyenne | I39: Coûts non mutualisés | J39: Identifier les partages de ressources.
C40: Les risques de conflits de ressources sont identifiés | D40: Les compétitions pour les ressources partagées sont-elles gérées ? | E40: OUI | F40: Plan de priorisation | G40: Goulots ressources | H40: Elevée | I40: Retards en chaîne | J40: Établir des règles d'arbitrage claires.
C41: Les calendriers des projets liés sont synchronisés | D41: Les échéances critiques sont-elles alignées ? | E41: OUI | F41: Calendrier intégré | G41: Chevauchements | H41: Moyenne | I41: Surcharge des équipes | J41: Synchroniser les plannings via un outil commun.
A42: Étude d'opportunité et expression des besoins | B42: S’assurer que l'expression détaillée des besoins est formalisée dans un cahier des charges fait par la MOA | C42: Le cahier des charges est rédigé par la MOA et validé par les métiers | D42: La MOA a-t-elle produit le document avec l'accord des utilisateurs finaux ? | E42: OUI | F42: PV de validation utilisateurs | G42: Non-adoption | H42: Elevée | I42: Rejet de la solution | J42: Formaliser les validations par signature
C43: Tous les besoins fonctionnels sont décrits avec un niveau de détail suffisant | D43: Les exigences sont-elles suffisamment granulaires (ex : cas d'usage) ? | E43: OUI | F43: Spécifications détaillées | G43: Incompréhension | H43: Elevée | I43: Solution inadaptée | J43: Utiliser des templates standardisés
C44: Les contraintes techniques et réglementaires sont explicitement mentionnées | D44: Les limites techniques et obligations légales sont-elles listées ? | E44: NON | F44: Registre des contraintes | G44: Non-conformité | H44: Moyenne | I44: Sanctions légales | J44: Auditer avec les experts métiers
C45: Le document intègre des critères d'acceptation mesurables | D45: Existe-t-il des KPIs clairs pour valider la solution ? | E45: NON | F45: Tableau de bord KPIs | G45: Évaluation subjective | H45: Elevée | I45: Succès non mesurable | J45: Définir 3-5 indicateurs clés
C46: Le cahier des charges a une version contrôlée et un historique des modifications | D46: Le document est-il sous gestion de version avec traçabilité ? | E46: PAS | F46: Système de versioning | G46: Incohérences | H46: Elevée | I46: Erreurs de mise en œuvre | J46: Utiliser un outil de gestion documentaire
B47: S’assurer que le cahier des charges préconise une solution fonctionnellement et techniquement pertinente au regard des besoins exprimés | C47: La solution proposée couvre ≥90% des besoins fonctionnels critiques | D47: Les fonctionnalités essentielles sont-elles toutes adressées ? | E47: PAS | F47: Matrice de couverture | G47: Lacunes fonctionnelles | H47: Elevée | I47: Insatisfaction utilisateurs | J47: Prioriser via la méthode MoSCoW
C48: L'architecture technique est compatible avec l'existant (SI, infra) | D48: La solution s'intègre-t-elle sans rupture avec le parc actuel ? | E48: NON | F48: Plan d'intégration | G48: Incompatibilités | H48: Elevée | I48: Retards coûteux | J48: Réaliser des tests d'interopérabilité
C49: Le choix technologique est justifié par une analyse comparative | D49: Plusieurs options ont-elles été évaluées objectivement ? | E49: NON | F49: Comparatif technique | G49: Choix biaisé | H49: Moyenne | I49: Coûts superflus | J49: Établir une grille de critères
C50: La solution respecte les standards et bonnes pratiques du secteur | D50: Le choix est-il aligné sur les référentiels professionnels ? | E50: OUI | F50: Référentiel sectoriel | G50: Obsolescence | H50: Elevée | I50: Désalignement stratégique | J50: Faire certifier par un expert
C51: Les propositions incluent un plan de montée en charge progressif | D51: La solution permet-elle une implémentation par phases ? | E51: OUI | F51: Plan de déploiement | G51: Big-bang risqué | H51: Moyenne | I51: Perturbation majeure | J51: Privilégier une approche agile
B52: S’assurer que les exigences utilisateurs, les populations ciblées, les options et principes de gestion retenus sont précisés et priorisés | C52: Les personas utilisateurs sont documentés avec leurs besoins spécifiques | D52: Les différents profils d'utilisateurs sont-ils identifiés ? | E52: OUI | F52: Personas utilisateurs | G52: Expérience médiocre | H52: Moyenne | I52: Faible adoption | J52: Cartographier tous les rôles
C53: Un classement MoSCoW (Must/Should/Could/Won't) a été réalisé | D53: Les exigences sont-elles priorisées méthodiquement ? | E53: OUI | F53: Backlog priorisé | G53: Désorganisation | H53: Elevée | I53: Délais non tenus | J53: Appliquer la méthode RICE
C54: Les scénarios de gestion des cas particuliers sont décrits | D54: Les processus exceptionnels sont-ils anticipés ? | E54: OUI | F54: Scénarios d'exception | G54: Bugs critiques | H54: Moyenne | I54: Blocages opérationnels | J54: Prévoir 20% de marge
C55: Les règles de gestion métier sont formalisées sous forme de décisionnels | D55: Les politiques métiers sont-elles modélisées (ex : arbres de décision) ? | E55: OUI | F55: Modèles métiers | G55: Incohérences | H55: Elevée | I55: Non-respect des règles | J55: Formaliser en BPMN
C56: Un backlog priorisé est maintenu et accessible à toutes les parties | D56: Existe-t-il un référentiel dynamique des exigences ? | E56: OUI | F56: Outil de suivi | G56: Requirements drift | H56: Moyenne | I56: Écart avec les besoins | J56: Mettre en place Jira/DOORS
B57: S’assurer que le projet est cohérent avec le plan directeur informatique | C57: Le projet apparaît explicitement dans la roadmap du plan directeur | D57: Le PDI mentionne-t-il ce projet avec son échéancier ? | E57: OUI | F57: Plan directeur SI | G57: Désalignement | H57: Moyenne | I57: Doublons d'efforts | J57: Mettre à jour le PDI trimestriellement
C58: Les technologies préconisées respectent les standards de la DSI | D58: La solution est-elle conforme à la cible d'architecture ? | E58: OUI | F58: Architecture cible | G58: Silos techniques | H58: Elevée | I58: Coûts d'intégration | J58: Faire valider par l'architecte
C59: Le budget projet est aligné avec les enveloppes prévues au PDI | D59: Le financement correspond-il aux prévisions stratégiques ? | E59: OUI | F59: Business case | G59: Sous-financement | H59: Elevée | I59: Arrêt du projet | J59: Aligner sur le budget pluriannuel
C60: Les livrables contribuent aux objectifs stratégiques du PDI | D60: Comment le projet sert-il les axes du plan directeur ? | E60: NON | F60: Feuille de route | G60: Effet tunnel | H60: Moyenne | I60: Valeur non délivrée | J60: Lier aux OKRs de l'entreprise
C61: Un responsable PDI a validé l'alignement du projet | D61: Un architecte ou RSSI a-t-il certifié la conformité ? | E61: NON | F61: Attestation de conformité | G61: Vulnérabilités | H61: Elevée | I61: Incident de sécurité | J61: Obtenir les accords formels
B62: S’assurer que le projet est cohérent avec le SI actuel ou futur | C62: Une cartographie des interfaces avec l'existant a été réalisée | D62: Tous les points de connexion avec le SI sont-ils identifiés ? | E62: NON | F62: Cartographie des interfaces | G62: Points aveugles | H62: Moyenne | I62: Données corrompues | J62: Documenter les APIs
C63: Les impacts sur les systèmes legacy sont documentés et budgétés | D63: Les adaptations nécessaires des systèmes existants sont-elles prévues ? | E63: OUI | F63: Plan de migration | G63: Régressions | H63: Elevée | I63: Perte de fonctionnalités | J63: Budgeter 15-20% pour l'adaptatif
C64: La solution préserve les investissements antérieurs (ex : réutilisation de briques) | D64: Le projet capitalise-t-il sur l'existant quand c'est pertinent ? | E64: OUI | F64: Audit des actifs | G64: Redondances | H64: Elevée | I64: Gaspillage | J64: Appliquer le principe "réutiliser d'abord"
C65: Le modèle de données est compatible avec le référentiel d'entreprise | D65: L'architecture data respecte-t-elle les standards du SI ? | E65: OUI | F65: Modèle de données | G65: Silos informationnels | H65: Moyenne | I65: Reporting impossible | J65: Imposer le RGPD dès la conception
C66: Un plan de convergence vers l'architecture cible est défini | D66: Comment la solution évoluera-t-elle avec le SI futur ? | E66: NON | F66: Schéma d'évolution | G66: Obsolescence | H66: Elevée | I66: Coûts de refonte | J66: Privilégier les APIs ouvertes
B67: S’assurer que la direction est bien impliquée dans le projet | C67: Un sponsor exécutif est nommé avec des responsabilités définies | D67: Un membre du COMEX porte-t-il formellement le projet ? | E67: NON | F67: Désignation officielle | G67: Manque de sponsorship | H67: Elevée | I67: Décisions bloquées | J67: Nommer un sponsor exécutif
C68: La direction valide les jalons clés et les budgets | D68: Les décisions importantes requièrent-elles une signature DG ? | E68: NON | F68: Matrice de gouvernance | G68: Paralysie | H68: Elevée | I68: Retards critiques | J68: Définir les seuils de validation
C69: Des points d'avancement réguliers sont présentés au comité de direction | D69: La direction reçoit-elle des rapports périodiques (ex : mensuels) ? | E69: NON | F69: Reporting standardisé | G69: Décisions aveugles | H69: Elevée | I69: Dérives non détectées | J69: Automatiser les tableaux de bord
C70: Les alertes et demandes d'arbitrage remontent systématiquement à la DG | D70: Existe-t-il un canal dédié pour les escalades directionnelles ? | E70: PAS | F70: Procédure d'escalade | G70: Blocages prolongés | H70: Moyenne | I70: Pénuries de ressources | J70: Afficher le RACI clairement
C71: La direction participe aux revues des objectifs stratégiques | D71: La DG valide-t-elle les ajustements d'orientation majeurs ? | E71: NON | F71: PV de comité de pilotage | G71: Dérive stratégique | H71: Moyenne | I71: Échec du projet | J71: Limiter à 2 revues stratégiques/an
B72: S’assurer que les acteurs de l'équipe projet et leurs responsabilités sont bien identifiés | C72: Un organigramme des rôles projet (RACI) est formalisé et diffusé | D72: Qui fait quoi est-il clair pour tous les participants ? | E72: NON | F72: Matrice RACI | G72: Doublons | H72: Elevée | I72: Tensions internes | J72: Afficher les rôles physiquement
C73: Les représentants métiers et techniques sont mandatés à temps plein si besoin | D73: Les ressources clés sont-elles dédiées au projet ? | E73: OUI | F73: Plan de ressourcement | G73: Multitasking | H73: Moyenne | I73: Retards chroniques | J73: Garantir 50% de temps minimum
C74: Les modalités de prise de décision sont documentées (qui décide quoi) | D74: Le processus décisionnel est-il transparent ? | E74: NON | F74: Charte de gouvernance | G74: Opacité | H74: Elevée | I74: Défiance | J74: Publier les comptes-rendus
C75: Un plan de communication interne définit les canaux et fréquences | D75: Comment l'information circule-t-elle dans l'équipe ? | E75: OUI | F75: Plan de communication | G75: Silos informationnels | H75: Moyenne | I75: Erreurs de coordination | J75: Utiliser Slack/Teams dédié
C76: Les suppléances sont prévues pour chaque rôle critique | D76: Que se passe-t-il en cas d'absence d'un acteur clé ? | E76: OUI | F76: Plan de continuité | G76: Blocages | H76: Moyenne | I76: Arrêt des activités | J76: Désigner des suppléants
B77: S’assurer que les compétences du personnel sont en adéquation avec les tâches | C77: Une matrice compétences/rôles a été établie | D77: Les profils correspondent-ils aux besoins des postes ? | E77: NON | F77: Référentiel de compétences | G77: Incompétences | H77: Elevée | I77: Livrables médiocres | J77: Faire auditer par les RH
C78: Le plan de formation couvre les écarts identifiés | D78: Des formations spécifiques sont-elles prévues ? | E78: OUI | F78: Plan de formation | G78: Mauvaise utilisation | H78: Moyenne | I78: ROI diminué | J78: Budgeter 5% du projet en formation
C79: Les consultants externes complètent judicieusement les compétences internes | D79: Le recours à l'externe est-il ciblé sur les bons sujets ? | E79: OUI | F79: Stratégie de sourcing | G79: Dépendance | H79: Moyenne | I79: Coûts explosifs | J79: Limiter aux expertises rares
C80: Les évaluations individuelles incluent les objectifs projet | D80: La participation au projet compte-t-elle dans les évaluations ? | E80: OUI | F80: Politique RH | G80: Démotivation | H80: Moyenne | I80: Turnover | J80: Lier aux objectifs annuels
C81: Un plan de transfert de compétences est prévu pour les savoir-faire critiques | D81: Comment les connaissances seront-elles capitalisées ? | E81: NON | F81: Base de connaissances | G81: Perte de savoir | H81: Elevée | I81: Réinvention | J81: Documenter dans un wiki interne
A82: Planification | B82: S’assurer qu’il existe un planning directeur commun à tout le projet | C82: Un planning global couvrant toutes les phases du projet est disponible | D82: Existe-t-il une vue d'ensemble du calendrier projet ? | E82: NON | F82: Diagramme de Gantt | G82: Manque de visibilité | H82: Elevée | I82: Délais non respectés | J82: Produire un planning consolidé avec jalons clés
C83: Le planning intègre les dépendances entre lots et sous-projets | D83: Les interactions entre activités sont-elles clairement visualisées ? | E83: NON | F83: Graphe PERT | G83: Séquencement erroné | H83: Moyenne | I83: Retards en cascade | J83: Modéliser les dépendances critiques
C84: Les jalons clés sont validés par toutes les parties prenantes | D84: Les dates importantes sont-elles approuvées par la MOA et MOE ? | E84: NON | F84: PV de validation planning | G84: Désalignement | H84: Moyenne | I84: Conflits opérationnels | J84: Organiser des revues trimestrielles
C85: Le planning est accessible à l'ensemble de l'équipe projet | D85: Tous les acteurs peuvent-ils consulter le planning en temps réel ? | E85: PAS | F85: Outil collaboratif (MS Project, Jira) | G85: Information obsolète | H85: Elevée | I85: Décisions inadaptées | J85: Centraliser sur une plateforme unique
C86: Le planning mentionne explicitement les livrables principaux | D86: Les outputs critiques sont-ils associés à des dates précises ? | E86: NON | F86: Matrice livrables-dates | G86: Priorisation floue | H86: Elevée | I86: Retard des livrables clés | J86: Lier chaque livrable à un KPI temporel
B87: S’assurer qu’il existe un plan de projet initial | C87: Le document couvre les 6 dimensions clés (coût, délais, qualité, etc.) | D87: Le plan aborde-t-il scope, temps, coût, qualité, risques, ressources ? | E87: NON | F87: Plan de management de projet | G87: Vision fragmentée | H87: Moyenne | I87: Dérives multiples | J87: Adopter une méthodologie type PMBOK
C88: Les méthodologies de gestion projet sont spécifiées (agile, cycle en V, etc.) | D88: L'approche méthodologique est-elle clairement définie ? | E88: OUI | F88: Charte méthodologique | G88: Improvisation | H88: Elevée | I88: Inefficacité | J88: Choisir entre Agile/Waterfall/Hybride
C89: Le plan inclut une estimation réaliste des ressources nécessaires | D89: Les besoins en RH et matériel sont-ils quantifiés et justifiés ? | E89: NON | F89: Plan de ressourcement | G89: Sous/sur-dimensionnement | H89: Elevée | I89: Coûts explosifs | J89: Utiliser des outils de forecast
C90: Les processus de gouvernance et reporting sont décrits | D90: Comment le projet sera-t-il piloté et contrôlé ? | E90: OUI | F90: Procédure de pilotage | G90: Décisions réactives | H90: Elevée | I90: Dérives non maîtrisées | J90: Instaurer des points hebdomadaires
C91: Le document a été validé en comité de lancement | D91: Le plan initial a-t-il reçu une validation formelle ? | E91: OUI | F91: PV de lancement | G91: Absence d'engagement | H91: Elevée | I91: Changements constants | J91: Obtenir signature DG
B92: S’assurer que ce plan de projet a été révisé | C92: Un processus formel de revue et mise à jour du plan est défini | D92: Existe-t-il une périodicité établie pour les révisions ? | E92: OUI | F92: Calendrier des revues | G92: Plans obsolètes | H92: Moyenne | I92: Inadéquation aux besoins | J92: Réviser mensuellement
C93: Les mises à jour intègrent les enseignements des revues de projet | D93: Les retours d'expérience sont-ils capitalisés ? | E93: PAS | F93: Base de connaissances | G93: Répétition d'erreurs | H93: Elevée | I93: Perte d'efficience | J93: Documenter les lessons learned
C94: Les écarts par rapport au plan initial sont documentés et justifiés | D94: Les dérives font-elles l'objet d'un suivi spécifique ? | E94: OUI | F94: Registre des écarts | G94: Correction tardive | H94: Moyenne | I94: Amplification des problèmes | J94: Mettre en place un seuil d'alerte à 5%
C95: La version du plan est contrôlée avec historique des modifications | D95: Peut-on tracer l'évolution du plan dans le temps ? | E95: NON | F95: Historique des versions | G95: Perte de traçabilité | H95: Moyenne | I95: Conflits de version | J95: Utiliser un système de versioning
C96: Les parties prenantes sont informées des mises à jour significatives | D96: Les modifications importantes sont-elles communiquées ? | E96: PAS | F96: Procédure de communication | G96: Mauvaise coordination | H96: Elevée | I96: Travail inutile | J96: Automatiser les notifications
B97: S’assurer qu’il existe des plans détaillés | C97: Des plans spécifiques existent pour chaque lot ou phase importante | D97: Chaque sous-ensemble a-t-il son propre planning détaillé ? | E97: OUI | F97: Plans annexes | G97: Micro-management | H97: Moyenne | I97: Surcharge administrative | J97: Limiter à 3 niveaux de détail
C98: Les plans techniques décrivent les séquences d'implémentation | D98: Les étapes de déploiement sont-elles planifiées heure par heure ? | E98: NON | F98: Planning de déploiement | G98: Impréparation | H98: Moyenne | I98: Interruptions de service | J98: Prévoir des créneaux horaires
C99: Les plans de tests couvrent tous les scénarios critiques | D99: Les cas de test sont-ils associés à un calendrier précis ? | E99: OUI | F99: Plan de test | G99: Couverture incomplète | H99: Moyenne | I99: Bugs en production | J99: Aligner tests sur cycles de développement
C100: Les plans de communication précisent les messages par cible | D100: Existe-t-il un calendrier éditorial pour les communications ? | E100: OUI | F100: Roadmap communication | G100: Message incohérent | H100: Moyenne | I100: Démotivation des équipes | J100: Planifier 6 mois à l'avance
...

Sheet Ref_Support_utili_gestion_parc
A1: Points de controle | B1: Objectifs de controle | C1: Criteres d'évaluations | D1: Questions d'évaluation | E1: Document requis | F1: Réponses | G1: Risque | H1: Criticités | I1: Conséquence | J1: Recommandations
A2: Fonction support : audit fiabilité et sécurité | B2: S’assurer qu’une structure de centre d’assistance (help-desk) (HD) est mise en place | C2: Vérifier l'existence d'une charte du HD | D2: Où trouver la charte officielle du HD ? | E2: Charte du help desk validée | F2: NON | G2: Non-respect des procédures | H2: Elevée | I2: Incohérence dans le service | J2: Publier la charte sur l'intranet et la partager lors des formations
C3: S'assurer de la définition des rôles (techniciens, superviseurs) | D3: Qui compose l'équipe du help desk ? | E3: Organigramme de l'équipe HD | F3: OUI | G3: Manque de visibilité sur les interlocuteurs | H3: Moyenne | I3: Retards de traitement | J3: Mettre à jour trimestriellement l'organigramme avec contacts
C4: Contrôler l'organisation des plannings | D4: Comment sont organisées les permanences ? | E4: Planning des permanences | F4: OUI | G4: Désorganisation des plannings | H4: Moyenne | I4: Absence de couverture | J4: Automatiser la gestion des plannings avec alertes de chevauchement
C5: Vérifier les locaux et équipements dédiés | D5: Existe-t-il un espace physique dédié ? | E5: Inventaire des locaux | F5: OUI | G5: Conditions de travail inadaptées | H5: Elevée | I5: Baisse de productivité | J5: Prévoir un espace ergonomique conforme aux normes
C6: S'assurer du budget alloué | D6: Quel budget annuel est consacré au HD ? | E6: Budget annuel approuvé | F6: NON | G6: Dépenses non contrôlées | H6: Moyenne | I6: Dérives financières | J6: Établir un suivi budgétaire mensuel
B7: S’assurer qu’une procédure de gestion des demandes d’assistance est diffusée et connue des utilisateurs | C7: Vérifier le document de procédure validé | D7: Où consulter la procédure complète ? | E7: Manuel des procédures HD | F7: NON | G7: Application disparate des règles | H7: Elevée | I7: Service hétérogène | J7: Centraliser la documentation dans un référentiel unique
C8: S'assurer des canaux de diffusion (intranet, affichage) | D8: Comment les utilisateurs accèdent-ils à l'info ? | E8: Guide d'accès aux ressources | F8: NON | G8: Mauvaise information des usagers | H8: Moyenne | I8: Surcharge du support | J8: Créer un portail self-service avec FAQ intelligente
C9: Contrôler les sessions d'information utilisateurs | D9: Quand ont eu lieu les dernières formations ? | E9: Registre des formations | F9: NON | G9: Compétences obsolètes | H9: Moyenne | I9: Erreurs de diagnostic | J9: Planifier des formations semestrielles obligatoires
C10: Vérifier l'existence de supports synthétiques | D10: Existe-t-il une fiche mémo utilisateur ? | E10: Kit d'autoformation utilisateur | F10: PAS | G10: Appels évitables | H10: Elevée | I10: Saturation du help desk | J10: Distribuer des fiches visuelles par processus métier
C11: S'assurer des tests de connaissance | D11: Comment évalue-t-on la compréhension des usagers ? | E11: Questionnaire de satisfaction | F11: NON | G11: Besoins mal identifiés | H11: Moyenne | I11: Solutions inadaptées | J11: Implémenter un système de feedback après résolution
B12: S’assurer qu’une procédure d'escalade mise en place | C12: Vérifier les niveaux d'escalade définis | D12: Combien de niveaux d'escalade existent ? | E12: Procédure d'escalade | F12: NON | G12: Blocage des tickets complexes | H12: Moyenne | I12: Délais excessifs | J12: Limiter à 3 niveaux maximum avec délais définis
C13: S'assurer des seuils de déclenchement | D13: Quels critères déclenchent une escalade ? | E13: Grille de critères d'escalade | F13: NON | G13: Escalades inappropriées | H13: Moyenne | I13: Mauvaise allocation des ressources | J13: Définir des seuils objectifs (temps, criticité)
C14: Contrôler les fiches contacts urgents | D14: Où trouver les contacts des experts ? | E14: Annuaire des référents techniques | F14: NON | G14: Perte de temps en recherche | H14: Elevée | I14: Résolution retardée | J14: Maintenir une liste certifiée mise à jour mensuellement
C15: Vérifier les délais de réponse par niveau | D15: Quel délai maximum pour un problème critique ? | E15: SLA formalisé | F15: OUI | G15: Dégradation de service | H15: Elevée | I15: Impact opérationnel majeur | J15: Fixer un délai de 2h max pour les P1 avec alerte automatique
C16: S'assurer des comptes-rendus d'incident | D16: Comment sont documentés les incidents majeurs ? | E16: Fiche post-mortem d'incident | F16: OUI | G16: Répétition des erreurs | H16: Moyenne | I16: Indisponibilités récurrentes | J16: Rédiger systématiquement un retour d'expérience
B17: S’assurer de la couverture géographique du HD | C17: Vérifier les zones desservies | D17: Quels sites/pays sont couverts ? | E17: Périmètre de couverture géographique | F17: OUI | G17: Demandes hors zone | H17: Moyenne | I17: Frustration des usagers | J17: Cartographier clairement les zones couvertes/non couvertes
C18: S'assurer des horaires de disponibilité | D18: Quelles sont les plages horaires d'ouverture ? | E18: Tableau des horaires de service | F18: PAS | G18: Attentes déçues | H18: Elevée | I18: Insatisfaction client | J18: Afficher les horaires sur tous les canaux de contact
C19: Contrôler les compétences linguistiques | D19: Quelles langues sont disponibles ? | E19: Politique linguistique du support | F19: OUI | G19: Barrière de communication | H19: Elevée | I19: Incompréhension | J19: Recruter des agents multilingues pour les langues principales
C20: Vérifier les fuseaux horaires couverts | D20: Comment gère-t-on les différences horaires ? | E20: Procédure de gestion des fuseaux | F20: NON | G20: Erreurs de planning | H20: Moyenne | I20: Service non disponible | J20: Utiliser un outil de planification avec fuseaux horaires
C21: S'assurer des relais locaux | D21: Existe-t-il des correspondants locaux ? | E21: Liste des correspondants locaux | F21: PAS | G21: Délais de réponse allongés | H21: Elevée | I21: Résolution inefficace | J21: Désigner un référent par zone géographique
B22: S’assurer de la couverture fonctionnelle du HD | C22: Vérifier la liste des applications supportées | D22: Quels logiciels sont pris en charge ? | E22: Catalogue des applications supportées | F22: NON | G22: Demandes hors périmètre | H22: Elevée | I22: Perte de temps | J22: Mettre à jour le catalogue à chaque nouvelle version
C23: S'assurer des périmètres d'intervention | D23: Quelles demandes sont hors périmètre ? | E23: Liste des exclusions de service | F23: NON | G23: Attentes irréalistes | H23: Elevée | I23: Conflits avec les usagers | J23: Communiquer clairement sur les limites du support
C24: Contrôler les limites d'assistance documentées | D24: Où sont listées les limites d'intervention ? | E24: Charte des responsabilités | F24: NON | G24: Empiètement sur d'autres services | H24: Elevée | I24: Tensions internes | J24: Délimiter visuellement les zones de responsabilité
C25: Vérifier les compétences techniques de l'équipe | D25: L'équipe a-t-elle les certifications nécessaires ? | E25: Registre des certifications | F25: OUI | G25: Incompétence technique | H25: Moyenne | I25: Résolutions inadéquates | J25: Financer les certifications obligatoires annuellement
C26: S'assurer des partenariats avec les éditeurs | D26: Comment contacter les support éditeurs ? | E26: Liste des contacts éditeurs | F26: OUI | G26: Délais prolongés | H26: Elevée | I26: Prolongation des incidents | J26: Négocier des canaux prioritaires avec les éditeurs clés
B27: S’assurer qu’un outil est implémenté pour la prise d'appel et le suivi des tickets ; | C27: Vérifier l'existence d'un logiciel dédié | D27: Quel outil est utilisé pour la gestion des tickets ? | E27: Documentation de l'outil ITSM | F27: OUI | G27: Mauvaise utilisation de l'outil | H27: Moyenne | I27: Données inexploitables | J27: Former les agents à l'outil et auditer son usage
C28: S'assurer de l'intégration avec les autres systèmes | D28: Est-il connecté à l'annuaire et au monitoring ? | E28: Architecture d'intégration | F28: OUI | G28: Silos d'information | H28: Moyenne | I28: Diagnostic incomplet | J28: Automatiser les flux entre systèmes via API
C29: Contrôler les fonctionnalités de base (création, suivi, clôture) | D29: Peut-on suivre l'historique complet d'un ticket ? | E29: Politique de rétention des données | F29: OUI | G29: Manque de transparence | H29: Elevée | I29: Difficulté d'audit | J29: Configurer l'outil pour conserver l'historique 12 mois
C30: Vérifier les droits d'accès différenciés | D30: Comment gère-t-on les droits des agents ? | E30: Matrice des habilitations | F30: NON | G30: Accès non autorisés | H30: Moyenne | I30: Fuites d'information | J30: Appliquer le principe du moindre privilège
C31: S'assurer des sauvegardes régulières | D31: Quelle est la fréquence des sauvegardes ? | E31: Politique de sauvegarde | F31: NON | G31: Perte de données | H31: Moyenne | I31: Interruption de service | J31: Sauvegarder quotidiennement avec test mensuel de restauration
B32: S’assurer que des critères à renseigner pour la qualification des tickets existent | C32: Vérifier la grille de qualification obligatoire | D32: Quels critères doivent être renseignés ? | E32: Template de ticket obligatoire | F32: NON | G32: Tickets incomplets | H32: Moyenne | I32: Retards de traitement | J32: Rendre obligatoires les champs critiques (urgence, impact)
C33: S'assurer de la typologie des tickets | D33: Comment classe-t-on les demandes (incident, requête | E33: Arbre de décision de classification | F33: NON | G33: Mauvaise priorisation | H33: Elevée | I33: Ressources mal allouées | J33: Utiliser des algorithmes de classification automatique
C34: Contrôler les champs obligatoires | D34: Quels champs ne peuvent pas être laissés vides ? | E34: Règles de validation des tickets | F34: PAS | G34: Données manquantes | H34: Elevée | I34: Impossible à traiter | J34: Configurer des validations obligatoires dans l'outil
C35: Vérifier les règles d'affectation automatique | D35: Comment sont attribués les tickets aux techniciens ? | E35: Procédure d'assignation | F35: NON | G35: Charge déséquilibrée | H35: Moyenne | I35: Surcharge des experts | J35: Automatiser l'assignation par compétences/disponibilité
C36: S'assurer des indicateurs de qualité | D36: Comment mesure-t-on la qualité de qualification ? | E36: Grille d'évaluation des tickets | F36: NON | G36: Erreurs répétées | H36: Moyenne | I36: Réouvertures fréquentes | J36: Auditer aléatoirement 10% des tickets qualifiés
B37: S’assure qu’il existe une liste de questions à dérouler lors d'un appel afin préciser au mieux la demande de l'utilisateur | C37: Vérifier l'existence d'un arbre de questions | D37: Où trouver le script des questions standard ? | E37: Bibliothèque de scripts | F37: NON | G37: Approche non standardisée | H37: Elevée | I37: Informations manquantes | J37: Intégrer les scripts dans l'outil de ticketing
C38: S'assurer de l'adaptation aux différents types de demandes | D38: Existe-t-il des variantes selon la nature du problème ? | E38: Arbres décisionnels par type d'incident | F38: NON | G38: Diagnostic imprécis | H38: Elevée | I38: Résolution inadaptée | J38: Développer des workflows spécifiques par catégorie
C39: Contrôler la mise à jour régulière | D39: Quand a-t-il été mis à jour pour la dernière fois ? | E39: Historique des versions des scripts | F39: OUI | G39: Questions obsolètes | H39: Moyenne | I39: Efficacité réduite | J39: Réviser les scripts tous les 6 mois
C40: Vérifier l'ergonomie du questionnaire | D40: Le questionnaire est-il facile à utiliser ? | E40: Rapport d'ergonomie | F40: OUI | G40: Résistance des agents | H40: Elevée | I40: Non-utilisation | J40: Concevoir des interfaces intuitives avec UX designer
C41: S'assurer de l'utilisation effective | D41: Comment vérifie-t-on son application ? | E41: Procédure d'audit des appels | F41: OUI | G41: Écarts par rapport au script | H41: Moyenne | I41: Qualité inconstante | J41: Enregistrer et analyser aléatoirement des appels
A42: Fonction support : audit d'efficacité et de performance | B42: S’assurer qu’il existe une aide à la saisie pour la saisie des tickets | C42: Un guide de saisie complet et actualisé est disponible pour les utilisateurs | D42: Existe-t-il un document ou un module d'aide détaillant la procédure de création des tickets ? | E42: Manuel de procédure de ticketing | F42: PAS | G42: Tickets mal formulés | H42: Elevée | I42: Retards de traitement | J42: Développer un guide interactif avec vidéos explicatives
C43: L'aide à la saisie est facilement accessible depuis l'interface de ticket | D43: Les utilisateurs peuvent-ils accéder à l'aide directement dans l'outil de ticketing ? | E43: Capture d'écran de l'interface | F43: OUI | G43: Mauvaise utilisation | H43: Elevée | I43: Saisie incomplète | J43: Intégrer un chatbot d'assistance contextuelle
C44: Des exemples concrets et des modèles sont fournis pour faciliter la saisie | D44: L'aide comprend-elle des cas pratiques et des templates prédéfinis ? | E44: Bibliothèque de templates | F44: NON | G44: Incohérence des données | H44: Moyenne | I44: Difficultés d'analyse | J44: Standardiser 5 templates types couvrant 80% des cas
C45: Un mécanisme d'auto-complétion ou d'assistance intelligente est implémenté | D45: L'outil propose-t-il des suggestions automatiques pendant la saisie ? | E45: Logs des fonctionnalités IA | F45: PAS | G45: Erreurs de saisie | H45: Elevée | I45: Mauvais routage | J45: Implémenter une IA de suggestion basée sur l'historique
C46: Une formation initiale sur l'utilisation de l'aide est dispensée aux nouveaux utilisateurs | D46: Les collaborateurs reçoivent-ils une formation spécifique sur l'utilisation des outils d'aide ? | E46: Programme de formation | F46: PAS | G46: Sous-utilisation | H46: Elevée | I46: ROI faible | J46: Organiser des ateliers mensuels "découverte"
B47: S’assurer qu’il existe des revues qualité pour la saisie des tickets | C47: S'assurer qu'il existe des revues qualité pour la saisie des tickets | D47: 1. Une procédure formalisée de revue qualité est documentée et accessible | E47: Procédure QC signée | F47: PAS | G47: Non-conformité | H47: Elevée | I47: Amendes | J47: Nommer un responsable qualité dédié
C48: Les revues qualité sont planifiées régulièrement avec une fréquence définie | D48: Des sessions de revue sont-elles organisées au moins mensuellement ? | E48: PV des réunions QC | F48: NON | G48: Problèmes récurrents | H48: Elevée | I48: Insatisfaction | J48: Automatiser les rappels de réunion
C49: Un comité pluridisciplinaire participe activement aux revues qualité | D49: Plusieurs services concernés sont-ils représentés dans les revues ? | E49: Liste des participants | F49: NON | G49: Silotage | H49: Moyenne | I49: Solutions partielles | J49: Imposer 3 services minimum par revue
C50: Un système de suivi des actions correctives est mis en place | D50: Les anomalies identifiées font-elles l'objet d'un plan d'action avec responsable et échéance ? | E50: Fiche d'action corrective | F50: OUI | G50: Corrections inefficaces | H50: Elevée | I50: Répétition erreurs | J50: Utiliser la méthode 5W2H pour les actions
C51: Des indicateurs de performance mesurent l'impact des revues qualité | D51: Peut-on constater une amélioration quantitative de la qualité des tickets après mise en œuvre des revues ? | E51: Dashboard qualité | F51: OUI | G51: Décisions non data-driven | H51: Moyenne | I51: Gaspillage | J51: Suivre 3 KPIs clés (complétude, temps, réouverture)
B52: Vérifier l’existence d’une base de connaissance | C52: Vérifier l'existence d'une base de connaissance | D52: 1. La base de connaissance est centralisée et accessible à l'ensemble des acteurs concernés | E52: Inventaire des ressources | F52: OUI | G52: Duplication | H52: Moyenne | I52: Confusion | J52: Migrer vers une plateforme unique type SharePoint
C53: Le contenu est organisé par thématiques et mots-clés pertinents | D53: La recherche d'informations dans la base est-elle intuitive et efficace ? | E53: Rapport d'UX | F53: OUI | G53: Abandon des recherches | H53: Elevée | I53: Appels évitables | J53: Ajouter un moteur de recherche sémantique
C54: Un processus de validation et de mise à jour des articles est formalisé | D54: Chaque article de la base fait-il l'objet d'une validation avant publication ? | E54: Workflow de publication | F54: OUI | G54: Information erronée | H54: Moyenne | I54: Décisions fautives | J54: Mettre en place une validation à 2 niveaux
C55: La base intègre des fonctionnalités de feedback utilisateur | D55: Les utilisateurs peuvent-ils noter et commenter les articles ? | E55: Système de feedback | F55: OUI | G55: Contenu obsolète | H55: Elevée | I55: Perte de confiance | J55: Implémenter un "like/dislike" avec commentaires
C56: Des statistiques d'utilisation et d'efficacité sont régulièrement analysées | D56: La fréquentation et l'utilité perçue de la base sont-elles mesurées ? | E56: Analytics d'usage | F56: OUI | G56: Investissement non justifié | H56: Moyenne | I56: Désengagement | J56: Calculer un indice de satisfaction (CSAT)
B57: S’assurer que les appels sont enregistrés+B62 | C57: S'assurer que les appels sont enregistrés | D57: 1. L'ensemble des canaux de communication avec les utilisateurs fait l'objet d'enregistrements | E57: Audit de conformité | F57: OUI | G57: Sanctions | H57: Moyenne | I57: Amendes | J57: Désigner un DPO interne
C58: La politique d'enregistrement est conforme aux réglementations en vigueur | D58: Les modalités d'enregistrement respectent-elles les exigences du RGPD ? | E58: Matrice des habilitations | F58: OUI | G58: Fuites de données | H58: Elevée | I58: Atteinte réputation | J58: Mettre en place un PAM (Privileged Access Management)
C59: Les enregistrements sont stockés de manière sécurisée avec contrôle d'accès | D59: Seules les personnes autorisées peuvent-elles accéder aux enregistrements ? | E59: Politique de rétention | F59: OUI | G59: Stockage illégal | H59: Elevée | I59: Problèmes légaux | J59: Appliquer la durée maximale de 13 mois
C60: La durée de conservation des enregistrements est définie et appliquée | D60: Existe-t-il une règle claire concernant la période de conservation des données ? | E60: Catalogue des cas d'apprentissage | F60: NON | G60: Opportunités perdues | H60: Moyenne | I60: Stagnation | J60: Créer une librairie anonymisée pour le coaching
C61: Un échantillonnage des enregistrements est utilisé pour l'amélioration continue | D61: Les enregistrements servent-ils régulièrement à des fins de formation et d'optimisation ? | E61: Politique de réutilisation | F61: NON | G61: Non valorisation | H61: Elevée | I61: Retour sur investissement faible | J61: Formaliser un processus d'extraction de bonnes pratiques
B62: S’assurer que les appels sont enregistrés | C62: Image master standardisée disponible | D62: Existe-t-il des images système de référence ? | F62: NON | H62: Moyenne
C63: Configuration minimum définie | D63: Les spécifications minimales sont-elles documentées ? | F63: OUI | H63: Elevée
C64: Processus de déploiement automatisé | D64: L'installation peut-elle se faire sans intervention manuelle ? | F64: OUI | H64: Elevée
C65: Tests de conformité post-installation | D65: Vérifie-t-on la conformité des machines déployées ? | F65: OUI | H65: Moyenne
C66: Mise à jour régulière du master | D66: L'image de référence est-elle actualisée trimestriellement ? | F66: OUI | H66: Elevée
B67: S’assurer que des études de satisfaction sont réalisées auprès des utilisateurs | C67: S'assurer que des études de satisfaction sont réalisées | D67: 1. Un questionnaire standardisé est utilisé pour mesurer la satisfaction utilisateur | E67: Modèle de questionnaire validé | F67: NON | G67: Feedback non standardisé | H67: Elevée | I67: Données non comparables | J67: Adopter un outil professionnel type NPS/CSAT
C68: La fréquence des enquêtes permet un suivi significatif de l'évolution | D68: Des enquêtes sont-elles menées après chaque interaction significative avec les utilisateurs ? | E68: Calendrier des enquêtes | F68: NON | G68: Perception incomplète | H68: Elevée | I68: Opportunités manquées | J68: Automatiser les sondages post-intervention
C69: Les résultats sont analysés et présentés sous forme de tableaux de bord | D69: Les données de satisfaction font-elles l'objet d'un reporting mensuel ? | E69: Exemple de dashboard satisfaction | F69: NON | G69: Décisions sans données | H69: Elevée | I69: Stagnation qualité | J69: Produire un rapport analytique mensuel
C70: Des actions correctives sont engagées lorsque les scores sont insuffisants | D70: Les retours négatifs déclenchent-ils systématiquement un plan d'amélioration ? | E70: Procédure gestion réclamations | F70: NON | G70: Problèmes récurrents | H70: Moyenne | I70: Dégradation service | J70: Instaurer un processus de traitement en 48h
C71: La communication des résultats et des améliorations est faite auprès des utilisateurs | D71: Les clients sont-ils informés des mesures prises suite à leurs feedbacks ? | E71: Modèle de communication post-feedback | F71: PAS | G71: Manque de transparence | H71: Moyenne | I71: Perte de confiance | J71: Envoyer un retour personnalisé sous 5 jours
B72: S’assurer qu’il existe une évaluation de l’équipe HD, notamment pour les prestataires afin d’en évaluer le niveau de connaissance | C72: S'assurer qu'il existe une évaluation de l'équipe HD | D72: 1. Un référentiel de compétences techniques et relationnelles est défini pour le HD | E72: Référentiel métier complet | F72: NON | G72: Compétences hétérogènes | H72: Elevée | I72: Service inégal | J72: Cartographier 10 compétences clés
C73: Le processus d'évaluation inclut des mesures objectives et des feedbacks qualitatifs | D73: Les évaluations combinent-elles des KPI quantitatifs et des appréciations managériales ? | E73: Grille d'évaluation mixte | F73: NON | G73: Jugement subjectif | H73: Moyenne | I73: Démotivation | J73: Pondérer 70% KPI/30% qualitatif
C74: Les prestataires externes sont soumis aux mêmes exigences d'évaluation que le personnel interne | D74: Les sous-traitants font-ils l'objet d'évaluations régulières selon les mêmes critères ? | E74: Rapport d'évaluation fournisseurs | F74: NON | G74: Double standard | H74: Elevée | I74: Risque qualité | J74: Appliquer le même référentiel
C75: Les résultats des évaluations influent sur les plans de formation individuels | D75: Chaque collaborateur dispose-t-il d'un programme de développement personnalisé ? | E75: Plan de développement individuel | F75: NON | G75: Stagnation compétences | H75: Moyenne | I75: Turnover | J75: Co-construire des PDP annuels
C76: La performance globale de l'équipe HD est suivie dans le temps | D76: Des indicateurs synthétiques permettent-ils de mesurer les progrès collectifs ? | E76: Tableau de bord des compétences | F76: OUI | G76: Vision parcellaire | H76: Moyenne | I76: Décisions erronées | J76: Calculer un indice de maturité trimestriel
B77: S’assurer que l’obtention des certifications (ITIL, ISO, COBIT, SIGMA) est encouragée au sein de la DSI, et du HD en particulier | C77: Encourager l'obtention de certifications | D77: 1. La direction affiche clairement son soutien à la démarche de certification | E77: PV de comité de direction | F77: OUI | G77: Manque d'engagement | H77: Elevée | I77: Échec certification | J77: Inclure la certification dans la stratégie
C78: Des moyens financiers et organisationnels sont alloués à la préparation aux certifications | D78: Un budget spécifique est-il réservé chaque année aux frais d'examen et de formation ? | E78: Budget formation certifié | F78: OUI | G78: Financement aléatoire | H78: Moyenne | I78: Abandons en cours | J78: Allouer 5% de la masse salariale
C79: Les certifications obtenues sont valorisées dans les parcours professionnels | D79: L'obtention de certifications ouvre-t-elle droit à des reconnaissances concrètes ? | E79: Politique de récompense | F79: PAS | G79: Effort non valorisé | H79: Moyenne | I79: Démotivation | J79: Prévoir bonus ou promotions
C80: Un suivi centralisé des certifications permet de piloter la démarche | D80: Existe-t-il un registre des certifications obtenues par les collaborateurs ? | E80: Registre des certifications | F80: OUI | G80: Visibilité insuffisante | H80: Moyenne | I80: Doublons formations | J80: Tenir un registre centralisé
C81: Les référentiels normatifs sont intégrés dans les processus métiers | D81: Les bonnes pratiques des normes sont-elles effectivement appliquées au quotidien ? | E81: Audit de conformité aux normes | F81: NON | G81: Écart théorie/pratique | H81: Elevée | I81: Non-conformité | J81: Organiser des audits surprises
A82: Gestion du parc matériel et logiciel : audit fiabilité et sécurité | B82: Vérifier la procédure de déploiement des mises à jour, d’un nouveau logiciel | C82: Procédure documentée pour le déploiement | D82: Existe-t-il un document officiel décrivant les étapes ? | E82: Procédure de déploiement | F82: PAS | G82: Incohérence des processus | H82: Elevée | I82: Erreurs de déploiement | J82: Formaliser un document unique de référence
C83: Plan de rollback prévu | D83: Des mécanismes de retour arrière sont-ils prévus ? | E83: Plan de rollback | F83: OUI | G83: Impossibilité de restauration | H83: Moyenne | I83: Indisponibilité prolongée | J83: Pré-tester les procédures de rollback
C84: Tests en environnement isolé | D84: Les mises à jour sont-elles testées avant déploiement ? | E84: Rapport de tests | F84: PAS | G84: Bugs en production | H84: Moyenne | I84: Perturbation des utilisateurs | J84: Implémenter un environnement de test dédié
C85: Calendrier de déploiement établi | D85: Les utilisateurs sont-ils informés des fenêtres de maintenance ? | E85: Calendrier des maintenances | F85: OUI | G85: Perturbations imprévues | H85: Elevée | I85: Perte de productivité | J85: Automatiser les notifications 48h à l'avance
C86: Mesure d'impact post-déploiement | D86: Des indicateurs de performance sont-ils analysés ? | E86: Dashboard de suivi | F86: NON | G86: Dégradation non détectée | H86: Elevée | I86: Baisse de qualité de service | J86: Définir 5 KPI clés mensuels
B87: Vérifier les outils mis en place pour gérer les versions des logiciels | C87: Outil centralisé de gestion des versions | D87: Existe-t-il un système unique pour suivre les versions ? | E87: Outil de gestion des versions | F87: OUI | G87: Confusion entre versions | H87: Moyenne | I87: Erreurs de déploiement | J87: Centraliser dans un CMDB
C88: Politique de versioning définie | D88: Les règles de numérotation sont-elles formalisées ? | E88: Charte de versioning | F88: OUI | G88: Incohérence des numéros | H88: Elevée | I88: Gestion chaotique | J88: Adopter le semver (major.minor.patch)
C89: Historique des modifications documenté | D89: Peut-on tracer toutes les évolutions logicielles ? | E89: Journal des changements | F89: NON | G89: Historique incomplet | H89: Elevée | I89: Difficulté d'audit | J89: Imposer un commentaire obligatoire par commit
C90: Identification des versions critiques | D90: Les versions stables sont-elles clairement marquées ? | E90: Politique de tagging | F90: OUI | G90: Utilisation de versions instables | H90: Elevée | I90: Incidents évitables | J90: Différencier clairement dev/stable/prod
C91: Comparaison possible entre versions | D91: Peut-on facilement comparer différentes versions ? | E91: Outil de comparaison | F91: PAS | G91: Récupération difficile d'anciennes versions | H91: Elevée | I91: Perte de fonctionnalités | J91: Implémenter un système de diff visuel
B92: Vérifier les outils mis en place pour gérer le matériel informatique | C92: Inventaire matériel à jour | D92: Tous les équipements sont-ils répertoriés ? | E92: Inventaire matériel | F92: OUI | G92: Machines non gérées | H92: Moyenne | I92: Failles de sécurité | J92: Scanner automatiquement le réseau mensuellement
C93: Suivi du cycle de vie du matériel | D93: Existe-t-il un suivi de la durée d'utilisation ? | E93: Registre de cycle de vie | F93: PAS | G93: Utilisation obsolète | H93: Elevée | I93: Coûts inutiles | J93: Définir une durée maximale d'utilisation (ex: 5 ans)
C94: Monitoring en temps réel du matériel | D94: La santé des équipements est-elle surveillée ? | E94: Dashboard de monitoring | F94: OUI | G94: Pannes imprévues | H94: Moyenne | I94: Indisponibilité | J94: Mettre en place des alertes automatiques
C95: Historique des interventions techniques | D95: Les réparations sont-elles documentées ? | E95: Fiche d'intervention | F95: PAS | G95: Historique de maintenance perdu | H95: Moyenne | I95: Garanties non honorées | J95: Compléter systématiquement un ticket de suivi
C96: Analyse des performances matérielles | D96: Des rapports périodiques sont-ils produits ? | E96: Rapport d'activité trimestriel | F96: OUI | G96: Vision à court terme | H96: Elevée | I96: Décisions non éclairées | J96: Générer automatiquement des rapports
B97: S’assurer que l'installation des PC / portables est faite à partir d'un master (configuration minimum et standardisée) | C97: Image master standardisée disponible | D97: Existe-t-il des images système de référence ? | E97: Catalogue des images | F97: OUI | G97: Configuration hétérogène | H97: Moyenne | I97: Problèmes de compatibilité | J97: Maintenir une image par type de machine
C98: Configuration minimum définie | D98: Les spécifications minimales sont-elles documentées ? | E98: Fiche technique standard | F98: PAS | G98: Performances insuffisantes | H98: Moyenne | I98: Expérience utilisateur dégradée | J98: Publier les specs sur l'intranet
C99: Processus de déploiement automatisé | D99: L'installation peut-elle se faire sans intervention manuelle ? | E99: Script d'installation automatisé | F99: OUI | G99: Temps de déploiement longs | H99: Moyenne | I99: Coûts élevés | J99: Développer des packages autonomes
C100: Tests de conformité post-installation | D100: Vérifie-t-on la conformité des machines déployées ? | E100: Checklist de conformité | F100: OUI | G100: Écarts par rapport au standard | H100: Moyenne | I100: Vulnérabilités | J100: Automatiser les vérifications post-install
...

Sheet Ref_sécurité-informatique
A1: Points de contrôle | B1: Objectifs de contrôle | C1: Critères d'évaluation | D1: Questions d'évaluation | E1: Réponses | F1: Document requis | G1: Risque | H1: Criticités | I1: Conséquence | J1: Recommandations
A2: Gestion des communications et des opérations | B2: Vérifier que la documentation des procédures et les responsabilités opérationnelles existe | C2: Toutes les procédures opérationnelles critiques sont documentées | D2: Toutes les procédures critiques sont-elles formalisées par écrit ? | E2: NON | F2: Inventaire des procédures critiques | G2: Non-conformité | H2: Elevée | I2: Erreurs opérationnelles | J2: Établir une matrice des procédures obligatoires
C3: Les responsabilités opérationnelles sont clairement attribuées et documentées | D3: Les rôles et responsabilités sont-ils explicitement définis ? | E3: OUI | F3: Matrice RACI | G3: Confusion des responsabilités | H3: Moyenne | I3: Retards dans l'exécution | J3: Mettre à jour la matrice semestriellement
C4: La documentation est accessible à l'ensemble du personnel concerné | D4: Le personnel a-t-il facilement accès à la documentation ? | E4: OUI | F4: Guide d'accès à la documentation | G4: Non-application des procédures | H4: Moyenne | I4: Incohérences | J4: Déployer un portail documentaire unique
C5: La documentation est à jour et révisée régulièrement | D5: La documentation est-elle actualisée au moins annuellement ? | E5: OUI | F5: Historique des révisions | G5: Procédures obsolètes | H5: Elevée | I5: Non-conformité | J5: Planifier des revues annuelles systématiques
C6: Un processus de validation de la documentation est formalisé | D6: Existe-t-il une procédure de validation des documents ? | E6: NON | F6: Workflow de validation | G6: Documents non validés | H6: Moyenne | I6: Information erronée | J6: Imposer une validation à deux niveaux
B7: Vérifier que le contrôle des modifications opérationnelles est réalisé | C7: Toute modification opérationnelle fait l'objet d'une demande formalisée | D7: Existe-t-il un formulaire de demande de modification ? | E7: NON | F7: Modèle de demande de modification | G7: Changements non contrôlés | H7: Elevée | I7: Instabilité | J7: Standardiser les demandes via un formulaire électronique
C8: Les modifications sont analysées pour évaluer leur impact | D8: L'impact des modifications est-il systématiquement évalué ? | E8: NON | F8: Grille d'analyse d'impact | G8: Changements mal évalués | H8: Moyenne | I8: Incidents post-déploiement | J8: Implémenter une analyse d'impact formelle
C9: Un processus d'approbation des modifications est en place | D9: Les modifications requièrent-elles une approbation formelle ? | E9: NON | F9: Procédure d'approbation | G9: Changements non autorisés | H9: Moyenne | I9: Risques non maîtrisés | J9: Exiger une signature électronique
C10: Les modifications sont testées avant mise en production | D10: Des tests sont-ils réalisés avant déploiement ? | E10: PAS | F10: Plan de tests | G10: Bugs en production | H10: Elevée | I10: Perturbation du service | J10: Créer un environnement de test dédié
C11: Un journal des modifications est tenu à jour | D11: Toutes les modifications sont-elles enregistrées et tracées ? | E11: NON | F11: Journal des changements | G11: Historique incomplet | H11: Moyenne | I11: Difficulté d'audit | J11: Utiliser un système de ticketing
B12: Vérifier que des procédures de gestion des incidents existent | C12: Une procédure formelle de déclaration des incidents existe | D12: Comment les incidents doivent-ils être déclarés ? | E12: NON | F12: Procédure de déclaration d'incident | G12: Signalement tardif | H12: Moyenne | I12: Aggravation | J12: Simplifier le processus de déclaration
C13: Les différents niveaux de gravité des incidents sont définis | D13: Existe-t-il une classification des incidents par criticité ? | E13: OUI | F13: Grille de criticité | G13: Priorisation erronée | H13: Moyenne | I13: Ressources mal allouées | J13: Adopter une échelle à 4 niveaux
C14: Les délais de traitement sont formalisés pour chaque type d'incident | D14: Des délais de résolution sont-ils définis ? | E14: NON | F14: Tableau des SLA incidents | G14: Délais excessifs | H14: Elevée | I14: Insatisfaction | J14: Définir des objectifs réalistes
C15: Un processus d'analyse post-incident est prévu | D15: Les incidents font-ils l'objet d'une analyse a posteriori ? | E15: OUI | F15: Procédure post-mortem | G15: Répétition des incidents | H15: Elevée | I15: Non-amélioration | J15: Organiser des retours d'expérience
C16: Les actions correctives sont documentées et suivies | D16: Les solutions apportées sont-elles enregistrées ? | E16: OUI | F16: Base de connaissances | G16: Perte d'expérience | H16: Moyenne | I16: Temps perdu | J16: Alimenter systématiquement la KB
B17: Vérifier que la séparation des fonctions et des infrastructures existe | C17: Les droits d'accès sont attribués selon le principe de moindre privilège | D17: Les accès sont-ils limités au strict nécessaire ? | E17: OUI | F17: Politique de moindre privilège | G17: Accès excessifs | H17: Moyenne | I17: Fuites de données | J17: Réviser les habilitations trimestriellement
C18: Les environnements de production et de développement sont physiquement ou logiquement séparés | D18: La séparation production/développement est-elle effective ? | E18: PAS | F18: Audit d'environnements | G18: Contamination production | H18: Elevée | I18: Indisponibilité | J18: Isoler physiquement les environnements
C19: Aucun individu ne cumule des fonctions incompatibles | D19: Les conflits d'intérêts potentiels sont-ils identifiés ? | E19: OUI | F19: Matrice des conflits | G19: Abus de position | H19: Elevée | I19: Fraude | J19: Former les managers à la détection
C20: Les accès aux systèmes critiques font l'objet d'un contrôle renforcé | D20: Existe-t-il un double contrôle pour les accès sensibles ? | E20: NON | F20: Procédure à quatre yeux | G20: Actions non contrôlées | H20: Moyenne | I20: Erreurs critiques | J20: Imposer une validation systématique
C21: La matrice des droits d'accès est documentée et actualisée | D21: La liste des habilitations est-elle à jour ? | E21: PAS | F21: Rapport d'habilitations | G21: Accès obsolètes | H21: Elevée | I21: Sécurité compromise | J21: Automatiser les désactivations
B22: Vérifier qu’une étude de sécurité en cas de gestion externe des infrastructures a été réalisée | C22: Une analyse des risques spécifiques a été conduite pour l'externalisation | D22: Les risques liés à l'externalisation ont-ils été identifiés ? | E22: NON | F22: Analyse de risques spécifique | G22: Menaces sous-estimées | H22: Elevée | I22: Incidents graves | J22: Réaliser une analyse poussée préalable
C23: Les exigences de sécurité sont contractualisées avec le prestataire | D23: Le contrat inclut-il des clauses de sécurité précises ? | E23: NON | F23: Modèle de contrat type | G23: Responsabilités floues | H23: Elevée | I23: Litiges | J23: Faire valider par le juridique
C24: Les contrôles d'accès du prestataire sont conformes à la politique interne | D24: Les accès du prestataire respectent-ils nos standards ? | E24: PAS | F24: Politique d'accès externes | G24: Failles introduites | H24: Elevée | I24: Compromission | J24: Appliquer les mêmes règles qu'en interne
C25: Un audit de sécurité du prestataire a été réalisé avant la contractualisation | D25: Le prestataire a-t-il été audité sur ses pratiques de sécurité ? | E25: NON | F25: Rapport d'audit fournisseur | G25: Pratiques défaillantes | H25: Moyenne | I25: Vulnérabilités | J25: Exiger des certifications reconnues
C26: Un plan de continuité d'activité spécifique a été élaboré | D26: Existe-t-il un PCA pour le scénario d'externalisation ? | E26: NON | F26: Plan de Continuité d'Activité | G26: Indisponibilité prolongée | H26: Elevée | I26: Pertes financières | J26: Tester le PCA annuellement
A27: Conformité | B27: Vérifier que les politique et procédures de sécurité internalisent les exigences légales et réglementaires | C27: Les politiques de sécurité mentionnent explicitement les textes réglementaires applicables. | D27: Les politiques font-elles référence aux lois et règlements en vigueur ? | E27: OUI | F27: Référentiel législatif annexé | G27: Non-conformité juridique | H27: Moyenne | I27: Sanctions pénales | J27: Mettre à jour les références légales semestriellement
C28: Les procédures opérationnelles intègrent les obligations légales (ex : RGPD, directives sectorielles). | D28: Les procédures reflètent-elles les exigences légales ? | E28: NON | F28: Matrice de correspondance procédures-lois | G28: Procédures non conformes | H28: Moyenne | I28: Nullité des actes | J28: Réaliser un audit de conformité procédurale
C29: Un processus de veille réglementaire est formalisé pour mettre à jour les documents. | D29: Existe-t-il un mécanisme de mise à jour face aux évolutions légales ? | E29: OUI | F29: Procédure de veille réglementaire | G29: Délais d'adaptation trop longs | H29: Elevée | I29: Amendes | J29: Nommer un veilleur réglementaire dédié
C30: Les employés sont formés sur les aspects réglementaires liés à leur fonction. | D30: Le personnel connaît-il ses obligations légales ? | E30: OUI | F30: Registre des formations | G30: Méconnaissance des règles | H30: Moyenne | I30: Erreurs involontaires | J30: Organiser des formations annuelles obligatoires
C31: Un contrôle annuel vérifie l’alignement des politiques avec le cadre légal. | D31: Un audit de conformité est-il réalisé chaque année ? | E31: OUI | F31: Programme d'audit annuel | G31: Dérives non détectées | H31: Moyenne | I31: Cumul de non-conformités | J31: Externaliser l'audit pour impartialité
B32: Vérifier que la convergence vers le cadre règlementaire national est recherchée | C32: Une analyse comparative entre les pratiques internes et les exigences nationales est disponible. | D32: Une cartographie des écarts avec la réglementation nationale existe-t-elle ? | E32: PAS | F32: Matrice des écarts | G32: Cécité réglementaire | H32: Moyenne | I32: Risques cachés | J32: Maintenir un tableau de bord dynamique
C33: Un plan d’action priorise les corrections pour atteindre la conformité. | D33: Des mesures correctives sont-elles planifiées pour réduire les écarts ? | E33: OUI | F33: Plan d'action correctif | G33: Correction aléatoire | H33: Elevée | I33: Persistance des écarts | J33: Prioriser les écarts par criticité
C34: Les mises à jour réglementaires nationales sont intégrées dans un délai maximal de 6 mois. | D34: Les nouvelles obligations légales sont-elles implémentées rapidement ? | E34: NON | F34: Journal des mises en conformité | G34: Retards d'implémentation | H34: Elevée | I34: Sanctions | J34: Fixer un délai max de 3 mois
C35: La direction valide annuellement les objectifs de conformité réglementaire. | D35: La conformité nationale est-elle une priorité stratégique ? | E35: PAS | F35: Procès-verbal du COMEX | G35: Manque d'engagement | H35: Moyenne | I35: Culture non conforme | J35: Inscrire la conformité dans la stratégie
C36: Les indicateurs de conformité sont suivis et rapportés trimestriellement. | D36: La progression vers la conformité est-elle mesurée et communiquée ? | E36: OUI | F36: Tableau de bord de conformité | G36: Efforts invisibles | H36: Moyenne | I36: Démotivation | J36: Publier un bulletin trimestriel
B37: S’assurer qu’un document retraçant le gap entre l’état actuel des politiques et procédures de sécurité interne et le cadre réglementaire existe et est tenu à jour | C37: Un registre des écarts de conformité est maintenu et accessible. | D37: Le document identifiant les gaps est-il facilement consultable ? | E37: OUI | F37: Politique d'accès aux documents | G37: Information cachée | H37: Elevée | I37: Mauvaises décisions | J37: Héberger sur l'intranet
C38: Chaque écart documenté est associé à un responsable de correction. | D38: Des responsables sont-ils assignés pour chaque non-conformité ? | E38: NON | F38: Matrice des responsables | G38: Dilution des responsabilités | H38: Elevée | I38: Aucune correction | J38: Utiliser la méthode RACI
C39: Le registre est mis à jour lors de changements réglementaires ou internes. | D39: Le document est-il actualisé au moins semestriellement ? | E39: OUI | F39: Historique des versions | G39: Données obsolètes | H39: Moyenne | I39: Décisions erronées | J39: Programmer des mises à jour
C40: Les écarts sont classés par niveau de criticité (ex : légal, financier, opérationnel). | D40: Une analyse de risque est-elle appliquée aux écarts identifiés ? | E40: OUI | F40: Grille d'analyse des risques | G40: Priorisation impossible | H40: Elevée | I40: Gaspillage de ressources | J40: Adopter la méthode EBIOS
C41: Le registre inclut des preuves de résolution pour les écarts corrigés. | D41: Les corrections sont-elles justifiées par des preuves documentées ? | E41: OUI | F41: Dossier de preuves | G41: Actions non vérifiables | H41: Moyenne | I41: Audit défavorable | J41: Constituer un dossier par écart
B42: S’assurer que tous les audits réglementaires sont réalisés | C42: Un calendrier des audits obligatoires est établi et respecté. | D42: Tous les audits requis sont-ils planifiés et exécutés à temps ? | E42: OUI | F42: Calendrier des audits | G42: Manquement aux obligations | H42: Elevée | I42: Sanctions | J42: Automatiser les rappels
C43: Les rapports d’audit identifient clairement les non-conformités. | D43: Les écarts sont-ils formalisés dans les comptes rendus d’audit ? | E43: OUI | F43: Modèle de compte-rendu | G43: Problèmes minimisés | H43: Elevée | I43: Non-traitement | J43: Standardiser les rapports
C44: Les recommandations des audits font l’objet d’un suivi formalisé. | D44: Un plan d’action est-il élaboré pour chaque audit ? | E44: NON | F44: Template de plan d'action | G44: Correction inefficace | H44: Moyenne | I44: Répétition des écarts | J44: Imposer des échéances contraignantes
C45: Les auditeurs internes ou externes sont accrédités selon les standards sectoriels. | D45: Les auditeurs disposent-ils des compétences requises ? | E45: NON | F45: Référentiel de compétences | G45: Audit superficiel | H45: Elevée | I45: Dangers non détectés | J45: Exiger des certifications spécifiques
C46: La direction examine systématiquement les conclusions des audits. | D46: Les résultats des audits sont-ils présentés au comité de direction ? | E46: PAS | F46: PV de présentation | G46: Manque de visibilité | H46: Elevée | I46: Priorité faible | J46: Inscrire à l'ordre du jour annuel
B47: S’assurer qu’un responsable conformité est désigné | C47: Le rôle et les missions du responsable conformité sont formalisés par écrit. | D47: Une fiche de poste détaillée existe-t-elle pour ce responsable ? | E47: PAS | F47: Description de poste | G47: Rôle mal défini | H47: Elevée | I47: Pouvoirs insuffisants | J47: Faire valider par la DRH
C48: Le responsable conformité a une autorité suffisante pour agir sur les processus. | D48: Le responsable a-t-il le pouvoir de faire appliquer les corrections ? | E48: NON | F48: Procès-verbal de délégation | G48: Impuissance | H48: Elevée | I48: Blocage des corrections | J48: Donner un pouvoir de sanction
C49: Un délégataire est prévu en cas d’absence du responsable titulaire. | D49: Existe-t-il un suppléant désigné ? | E49: OUI | F49: Arrêté de suppléance | G49: Vacance du poste | H49: Moyenne | I49: Paralysie | J49: Former un binôme
C50: Le responsable rend compte directement à la direction générale ou au conseil d’administration. | D50: Le responsable a-t-il un accès direct aux décideurs ? | E50: NON | F50: Organigramme fonctionnel | G50: Filtrage de l'information | H50: Elevée | I50: Alertes non remontées | J50: Prévoir des points directs
C51: Les compétences du responsable sont régulièrement évaluées et mises à jour. | D51: Le responsable suit-il des formations sur les évolutions réglementaires ? | E51: NON | F51: Plan de formation individuel | G51: Connaissances obsolètes | H51: Moyenne | I51: Conseils erronés | J51: Abonnement à des revues spécialisées
A52: Gestion des identifiants et des mots de passe | B52: Vérifier qu'il y a un seul utilisateur par identifiant | C52: Chaque identifiant système est attribué à un unique utilisateur nominatif | D52: Les identifiants sont-ils strictement individuels et nominatifs ? | E52: NON | F52: Politique de gestion des identifiants | G52: Usurpation d'identité | H52: Moyenne | I52: Fraude | J52: Imposer la création nominative avec vérification RH
C53: Le partage d'identifiants entre collaborateurs est formellement interdit | D53: Existe-t-il une clause explicite interdisant le partage d'identifiants ? | E53: NON | F53: Charte utilisateur signée | G53: Accès non autorisés | H53: Elevée | I53: Fuites de données | J53: Inclure la clause dans le contrat de travail
C54: La liste des identifiants actifs est vérifiée trimestriellement | D54: Une revue périodique des comptes utilisateurs est-elle effectuée ? | E54: PAS | F54: Rapport de revue des comptes | G54: Comptes obsolètes | H54: Moyenne | I54: Accès résiduels | J54: Automatiser les revues trimestrielles
C55: Les comptes génériques font l'objet d'une gestion exceptionnelle et documentée | D55: Les comptes non nominatifs sont-ils justifiés et contrôlés ? | E55: NON | F55: Registre des comptes génériques | G55: Traçabilité impossible | H55: Elevée | I55: Abus | J55: Limiter aux cas techniques avec double approbation
C56: Le système technique empêche la création de comptes dupliqués | D56: L'outil informatique bloque-t-il la création de doublons ? | E56: NON | F56: Configuration technique | G56: Doublons d'identité | H56: Moyenne | I56: Confusion | J56: Activer le contrôle d'unicité dans l'AD
B57: Vérifier que les identifiants inutilisés pendant un certain délai sont révoqués | C57: Une politique de durée maximale d'inactivité est définie (ex: 90 jours) | D57: Le délai maximal d'inactivité avant révocation est-il formalisé ? | E57: OUI | F57: Politique de révocation | G57: Comptes dormants | H57: Moyenne | I57: Vulnérabilités | J57: Fixer à 90 jours max pour les comptes standards
C58: Le système identifie automatiquement les comptes inactifs | D58: Existe-t-il un processus automatisé de détection d'inactivité ? | E58: NON | F58: Procédure technique | G58: Détection manuelle | H58: Elevée | I58: Oublis | J58: Implémenter des scripts de détection
C59: Les comptes inactifs sont désactivés selon le délai prévu | D59: La révocation est-elle systématique après la période définie ? | E59: OUI | F59: Journal des révocations | G59: Non-application | H59: Elevée | I59: Accumulation de risques | J59: Automatiser le processus
C60: Une procédure exceptionnelle permet de réactiver les comptes nécessaires | D60: Existe-t-il un processus sécurisé pour réactiver des comptes ? | E60: OUI | F60: Procédure de réactivation | G60: Réactivations frauduleuses | H60: Moyenne | I60: Accès illégitimes | J60: Exiger une validation hiérarchique
C61: Un rapport mensuel liste les comptes désactivés pour inactivité | D61: La révocation des comptes inactifs est-elle tracée ? | E61: OUI | F61: Log des actions d'administration | G61: Actions non tracées | H61: Elevée | I61: Non-reconstitution | J61: Centraliser les logs dans un SIEM
B62: Vérifier que des règles de gestion de la casse des mots de passe existent | C62: La politique exige une alternance de minuscules et majuscules | D62: Les mots de passe doivent-ils contenir des majuscules et minuscules ? | E62: PAS | F62: Politique de complexité | G62: Faible robustesse | H62: Moyenne | I62: Bruteforce | J62: Imposer 12 caractères minimum avec 4 types
C63: Le système impose la complexité lors de la création/modification | D63: L'outil technique valide-t-il automatiquement la complexité ? | E63: OUI | F63: Configuration système | G63: Contournements possibles | H63: Elevée | I63: Mots de passe faibles | J63: Activer le contrôle technique
C64: Les règles sont documentées et accessibles aux utilisateurs | D64: Les exigences sont-elles communiquées à tous les collaborateurs ? | E64: NON | F64: Support de formation | G64: Méconnaissance des règles | H64: Elevée | I64: Non-respect | J64: Diffuser des mémo visuels
C65: La politique distingue les exigences selon la criticité des accès | D65: Les comptes sensibles ont-ils des règles renforcées ? | E65: PAS | F65: Politique des comptes privilégiés | G65: Cible privilégiée | H65: Moyenne | I65: Compromission | J65: Imposer 16 caractères + changement 30 jours
C66: Un mécanisme empêche la réutilisation des anciens mots de passe | D66: Le système interdit-il la réutilisation des N derniers mots de passe ? | E66: NON | F66: Paramétrage technique | G66: Recyclage de mots de passe | H66: Elevée | I66: Sécurité illusoire | J66: Bloquer les 24 derniers mots de passe
B67: Vérifier que ces règles sont respectées | C67: Un contrôle technique empêche la création de mots de passe non conformes | D67: Le système bloque-t-il les mots de passe non conformes ? | E67: NON | F67: Journal des rejets | G67: Contournement des règles | H67: Elevée | I67: Vulnérabilités | J67: Mettre en place un contrôle en temps réel
C68: Des audits aléatoires vérifient la conformité des mots de passe existants | D68: Des vérifications ponctuelles des mots de passe sont-elles faites ? | E68: PAS | F68: Rapport de vérification | G68: Mots de passe faibles persistants | H68: Elevée | I68: Risque résiduel | J68: Tester mensuellement via scripts
C69: Les exceptions font l'objet d'une autorisation exceptionnelle documentée | D69: Les dérogations sont-elles approuvées et justifiées ? | E69: NON | F69: Registre des dérogations | G69: Exceptions non contrôlées | H69: Elevée | I69: Failles | J69: Limiter à 7 jours max avec approbation CISO
C70: Les violations des règles déclenchent des alertes sécurité | D70: Les tentatives de contournement sont-elles détectées ? | E70: NON | F70: Configuration des logs | G70: Contournements non vus | H70: Moyenne | I70: Culture du non-respect | J70: Monitorer les tentatives de modification
C71: Le taux de conformité des mots de passe est mesuré mensuellement | D71: Existe-t-il un indicateur de conformité des mots de passe ? | E71: OUI | F71: Dashboard sécurité | G71: Visibilité insuffisante | H71: Moyenne | I71: Mauvaise priorisation | J71: Calculer un % de conformité mensuel
B72: Vérifier qu’il existe une procédure de gestion des mots de passe | C72: Une procédure écrite décrit le cycle de vie complet des mots de passe | D72: Existe-t-il un document formalisant la gestion des mots de passe ? | E72: NON | F72: Politique de sécurité | G72: Approche disparate | H72: Elevée | I72: Incohérences | J72: Rédiger une politique approuvée par la DG
C73: Le processus couvre la création, modification et révocation des accès | D73: Toutes les étapes de gestion sont-elles prévues ? | E73: OUI | F73: Workflow complet | G73: Processus incomplet | H73: Moyenne | I73: Points aveugles | J73: Modéliser le cycle de vie complet
C74: La procédure inclut un mécanisme sécurisé de réinitialisation | D74: Comment un utilisateur peut-il réinitialiser son mot de passe ? | E74: OUI | F74: Procédure de reset | G74: Délais excessifs | H74: Elevée | I74: Pertes de productivité | J74: Mettre en place un portail self-service
C75: Les rôles et responsabilités dans la gestion des accès sont définis | D75: Qui est responsable de l'administration des mots de passe ? | E75: NON | F75: Désignation officielle | G75: Dilution des responsabilités | H75: Moyenne | I75: Non-application | J75: Nommer un référent sécurité dédié
C76: La procédure est révisée annuellement ou après incident majeur | D76: Quand la procédure a-t-elle été mise à jour pour la dernière fois ? | E76: PAS | F76: Historique des versions | G76: Politique obsolète | H76: Moyenne | I76: Non-conformité | J76: Réviser annuellement ou après incident
A77: Contrôle des accès | B77: Vérifier que la définition et la documentation de la politique de contrôle d'accès existent | C77: La politique de contrôle d'accès est formalisée par écrit | D77: Existe-t-il un document officiel définissant la politique de contrôle d'accès ? | E77: NON | F77: Politique de contrôle d'accès signée | G77: Accès non contrôlés | H77: Elevée | I77: Fuites de données | J77: Formaliser et faire valider par la direction
C78: La politique couvre tous les systèmes critiques de l'organisation | D78: Tous les systèmes importants sont-ils inclus dans la politique ? | E78: NON | F78: Inventaire des systèmes critiques | G78: Zones non sécurisées | H78: Moyenne | I78: Vulnérabilités ciblées | J78: Mettre à jour l'inventaire trimestriellement
C79: Les rôles et niveaux d'accès sont clairement définis | D79: La politique précise-t-elle les différents profils d'accès ? | E79: OUI | F79: Matrice des profils d'accès | G79: Accès inadaptés | H79: Moyenne | I79: Sur/sous-privilèges | J79: Définir 5 niveaux d'accès standardisés
C80: La politique est approuvée par la direction | D80: La direction a-t-elle validé formellement le document ? | E80: NON | F80: Procès-verbal de validation | G80: Manque d'engagement | H80: Moyenne | I80: Non-application | J80: Obtenir signature formelle de la DG
C81: La politique est révisée annuellement | D81: La politique est-elle mise à jour régulièrement ? | E81: OUI | F81: Historique des versions | G81: Règles obsolètes | H81: Elevée | I81: Non-conformité | J81: Prévoir une révision annuelle systématique
B82: S’assurer que la gestion des accès utilisateurs est effective | C82: Un processus formalisé existe pour la création/modification/suppression des accès | D82: Existe-t-il une procédure documentée pour la gestion des comptes ? | E82: OUI | F82: Procédure de gestion des comptes | G82: Création anarchique | H82: Elevée | I82: Problèmes de traçabilité | J82: Standardiser le workflow complet
C83: Les demandes d'accès nécessitent une approbation préalable | D83: Tous les nouveaux accès sont-ils approuvés avant activation ? | E83: OUI | F83: Formulaire de demande d'accès | G83: Accès non autorisés | H83: Moyenne | I83: Fraude | J83: Imposer une approbation hiérarchique + validation SI
C84: Les droits d'accès sont révisés semestriellement | D84: Une revue périodique des habilitations est-elle effectuée ? | E84: PAS | F84: Rapport de revue des habilitations | G84: Droit d'accès résiduels | H84: Moyenne | I84: Failles persistantes | J84: Automatiser les revues trimestrielles
C85: Les comptes obsolètes sont désactivés dans un délai maximum de 24h après départ | D85: Les comptes des collaborateurs partis sont-ils rapidement désactivés ? | E85: OUI | F85: Procédure de départ | G85: Accès actifs post-départ | H85: Elevée | I85: Usurpation | J85: Désactiver le jour même du départ
C86: Un registre des modifications d'accès est maintenu | D86: Toutes les modifications d'accès sont-elles tracées ? | E86: NON | F86: Journal des modifications | G86: Actions non traçables | H86: Elevée | I86: Non-reconstitution | J86: Centraliser dans un SIEM avec alertes
B87: S’assurer que l'utilisation de mots de passe et de systèmes de déconnexion automatique est effective | C87: Une politique de complexité des mots de passe est implémentée | D87: Les mots de passe doivent-ils respecter des règles de complexité ? | E87: PAS | F87: Politique de mots de passe | G87: Authentification faible | H87: Moyenne | I87: Bruteforce | J87: Imposer 12 caractères minimum avec 4 types
C88: Le système impose le changement périodique des mots de passe | D88: Les utilisateurs doivent-ils changer leur mot de passe régulièrement ? | E88: NON | F88: Paramétrage technique | G88: Mots de passe persistants | H88: Elevée | I88: Risque accru | J88: Forcer le changement tous les 90 jours
C89: Les sessions inactives se ferment automatiquement après 15 minutes | D89: Existe-t-il un mécanisme de déconnexion automatique ? | E89: NON | F89: Configuration système | G89: Sessions orphelines | H89: Elevée | I89: Accès non surveillés | J89: Déconnexion après 15 min d'inactivité
C90: L'historique des mots de passe empêche leur réutilisation | D90: Peut-on réutiliser les N derniers mots de passe ? | E90: PAS | F90: Paramètres de sécurité | G90: Recyclage de mots de passe | H90: Elevée | I90: Sécurité illusoire | J90: Bloquer les 24 derniers mots de passe
C91: Les tentatives infructueuses de connexion bloquent temporairement le compte | D91: Le système limite-t-il les tentatives de connexion ? | E91: NON | F91: Configuration des logs | G91: Attaques par bruteforce | H91: Elevée | I91: Compromission | J91: Bloquer après 5 tentatives + alerte
B92: Vérifier que le contrôle des accès aux réseaux est effectif | C92: Critère d'évaluation | D92: Question d'évaluation | E92: NON | F92: Schéma d'architecture réseau | G92: Contamination croisée | H92: Moyenne | I92: Propagation de menaces | J92: Implémenter le modèle Zero Trust
C93: Les accès réseau sont segmentés par zones de sécurité | D93: Le réseau est-il divisé en zones avec différents niveaux d'accès ? | E93: OUI | F93: Schéma d'architecture réseau | G93: Contamination croisée | H93: Elevée | I93: Propagation de menaces | J93: Implémenter une segmentation VLAN stricte
C94: Les connexions distantes utilisent des canaux sécurisés (VPN) | D94: Les accès externes passent-ils par des tunnels sécurisés ? | E94: NON | F94: Politique d'accès distant | G94: Interceptions | H94: Moyenne | I94: Fuites de données | J94: Imposer VPN avec chiffrement AES-256
C95: Les équipements réseau critiques sont protégés par des contrôles d'accès stricts | D95: Les routeurs/switchs ont-ils des protections renforcées ? | E95: OUI | F95: Benchmark CIS pour équipements | G95: Equipements vulnérables | H95: Moyenne | I95: Portes dérobées | J95: Désactiver les services inutiles (Telnet)
C96: Les flux réseau sont monitorés et analysés en continu | D96: Existe-t-il une solution de surveillance du trafic réseau ? | E96: OUI | F96: Rapport de configuration IDS/IPS | G96: Anomalies non détectées | H96: Elevée | I96: Intrusions persistantes | J96: Déployer un SIEM avec analyse comportementale
B97: Vérifier que le contrôle d'accès aux systèmes d'exploitation est effectif | C97: Les comptes administrateurs sont strictement limités | D97: Le nombre de comptes privilégiés est-il minimisé ? | E97: OUI | F97: Inventaire des comptes admin | G97: Surface d'attaque étendue | H97: Moyenne | I97: Risque élevé | J97: Appliquer le principe du besoin de savoir
C98: L'accès root/administrateur nécessite une double authentification | D98: Les comptes privilégiés ont-ils une protection renforcée ? | E98: PAS | F98: Politique des comptes sensibles | G98: Compromission critique | H98: Moyenne | I98: Paralysie du SI | J98: Imposer MFA + journalisation complète
C99: Les journaux d'accès aux systèmes sont activés et conservés 6 mois | D99: Les connexions aux systèmes sont-elles journalisées ? | E99: OUI | F99: Politique de journalisation | G99: Activités non tracées | H99: Moyenne | I99: Investigations impossibles | J99: Conserver les logs 13 mois minimum
C100: Les correctifs de sécurité sont appliqués dans un délai maximum d'1 mois | D100: Les systèmes sont-ils patchés régulièrement ? | E100: NON | F100: Calendrier de patching | G100: Failles connues non corrigées | H100: Moyenne | I100: Exploitations | J100: Automatiser les mises à jour critiques (<72h)
...

Sheet Ref_COSO
A2: Domaines | B2: Points de Contrôle | C2: Objectifs de Contrôle | D2: Critère d’Évaluation | E2: Question d’Évaluation | F2: Réponses | G2: Documents Requis | H2: Risques | I2: Criticités | J2: Conséquences | K2: Recommandations
A3: Environnement de Contrôle | B3: Engagement envers l’intégrité et les valeurs éthiques | C3: S’assurer que l'organisation dispose d'une charte éthique formelle qui couvre l'ensemble des pratiques professionnelles et des interactions au sein de l'organisation, y compris les activités liées aux systèmes d'information. | D3: Existence d’un document officiel décrivant la charte éthique. | E3: Existe-t-il un document officiel décrivant la charte éthique de l'organisation ? | F3: OUI | G3: Charte éthique, Manuel des procédures internes | H3: Absence de cadre éthique formel pouvant entraîner des comportements non conformes | I3: Élevée | J3: Sanctions réglementaires et amendes
D4: Inclusion explicite des pratiques liées aux systèmes d’information dans la charte. | E4: La charte éthique inclut-elle explicitement des pratiques et des directives spécifiques concernant l'utilisation et la gestion des systèmes d'information ? | F4: OUI | G4: Charte éthique, Politique de sécurité des SI | H4: Manque de directives claires sur l’usage des SI, augmentant les risques de non-conformité et de failles | I4: Élevée | J4: Dérives organisationnelles incontrôlées
D5: Validation et approbation de la charte par la direction et les instances compétentes. | E5: La charte éthique a-t-elle été validée et approuvée par la direction et les instances compétentes de l'organisation ? | F5: OUI | G5: Procès-verbal d'approbation, Document de validation interne | H5: Absence d’engagement de la direction, réduisant l’efficacité et l’application de la charte | I5: Élevée | J5: Non-respect des règles par méconnaissance
D6: Disponibilité et accessibilité de la charte pour tous les employés et partenaires. | E6: La charte éthique est-elle facilement disponible et accessible à tous les employés et partenaires de l'organisation ? | F6: OUI | G6: Site intranet de l'organisation, Support de communication interne | H6: Manque de sensibilisation pouvant entraîner des violations involontaires | I6: Moyenne | J6: Pertes financières et atteinte à la réputation
D7: Mise à jour régulière de la charte en fonction des évolutions réglementaires et technologiques. | E7: La charte éthique est-elle mise à jour régulièrement pour tenir compte des évolutions réglementaires et technologiques ? | F7: NON | G7: Versionnage des mises à jour, Références aux nouvelles réglementations | H7: Risque de non-conformité aux nouvelles réglementations | I7: Élevée | J7: Décisions incohérentes et inefficaces
C8: Vérifier que des mécanismes existent pour garantir que tous les acteurs (employés, partenaires, prestataires) respectent cette charte éthique dans leurs activités professionnelles, y compris dans leur utilisation des systèmes d'information | D8: Existence de procédures de contrôle et de suivi du respect de la charte. | E8: Des procédures de contrôle et de suivi sont-elles en place pour s'assurer du respect de la charte éthique par les employés et partenaires ? | F8: OUI | G8: Rapports d’audit interne, Registre des incidents éthiques | H8: Absence de contrôle favorisant la non-application des règles éthiques | I8: Élevée | J8: Perte de confiance des parties prenantes
D9: Signature d’un engagement de conformité à la charte par les employés, partenaires et prestataires. | E9: Les employés, partenaires et prestataires sont-ils tenus de signer un engagement de conformité à la charte éthique ? | F9: NON | G9: Registre des engagements signés, Contrats de prestation | H9: Absence d’obligation formelle pouvant limiter la responsabilisation | I9: Moyenne | J9: Violations involontaires des réglementations
D10: Mise en place de sanctions claires et appliquées en cas de non-respect. | E10: Des sanctions claires et définies sont-elles en place en cas de non-respect de la charte éthique ? | F10: PAS | G10: Politique disciplinaire, Procès-verbaux de sanctions | H10: Absence de mesures dissuasives entraînant une application inefficace des règles | I10: Élevée | J10: Baisse de l'adhésion et de l'implication
D11: Réalisation d’audits périodiques pour évaluer le respect des règles éthiques. | E11: Des audits périodiques sont-ils réalisés pour évaluer le respect des règles éthiques au sein de l'organisation ? | F11: NON | G11: Plan d’audit, Rapports d’audit éthique | H11: Non-détection des violations éthiques entraînant des risques légaux et réputationnels | I11: Élevée | J11: Erreurs répétées et non-conformités
D12: Présence d’un responsable ou d’un comité chargé du suivi de la conformité à la charte. | E12: Un responsable ou un comité spécifique est-il chargé du suivi de la conformité à la charte éthique au sein de l'organisation ? | F12: OUI | G12: Organigramme de gouvernance, Procès-verbal de nomination | H12: Manque de gouvernance claire sur l’application des principes éthiques | I12: Moyenne | J12: Impossibilité de démontrer la conformité
C13: S’assurer que des actions de sensibilisation, telles que des formations régulières, sont mises en place pour garantir que tous les employés et intervenants comprennent et appliquent les principes éthiques dans leurs interactions avec les systèmes d'information | D13: Existence d’un programme de formation régulier sur l’éthique et l’utilisation des systèmes d’information. | E13: Un programme de formation régulier sur l'éthique et l'utilisation des systèmes d'information est-il en place pour les employés ? | F13: NON | G13: Programme de formation | H13: Manque de sensibilisation augmentant les risques d’erreurs humaines | I13: Moyenne | J13: Pratiques dépassées et non adaptatives
D14: Obligation pour les employés et intervenants de suivre ces formations. | E14: Les employés et intervenants sont-ils tenus de suivre les formations sur l'éthique et l'utilisation des systèmes d'information ? | F14: NON | G14: Liste des participants | H14: Non-formation des employés entraînant des comportements non conformes | I14: Moyenne | J14: Inadéquation avec l'environnement actuel
D15: Évaluation des connaissances acquises après chaque session de formation. | E15: Les connaissances acquises par les participants aux formations sur l'éthique et l'utilisation des systèmes d'information sont-elles évaluées ? | F15: NON | G15: Résultats d’évaluation | H15: Formation inefficace ne garantissant pas une réelle assimilation | I15: Moyenne | J15: Malentendus et conflits internes
D16: Enregistrement et suivi des employés ayant suivi la formation. | E16: Un enregistrement et un suivi des employés ayant suivi les formations sur l'éthique et l'utilisation des systèmes d'information sont-ils mis en place ? | F16: NON | G16: Registre des formations | H16: Absence de traçabilité empêchant de vérifier la couverture des formations | I16: Moyenne | J16: Impossibilité d'audit et de preuve
D17: Mise à jour des supports de formation en fonction des évolutions des bonnes pratiques et des réglementations. | E17: Les supports de formation sur l'éthique et l'utilisation des systèmes d'information sont-ils mis à jour en fonction des évolutions des bonnes pratiques et des réglementations ? | F17: NON | G17: Versions mises à jour des supports | H17: Obsolescence des formations menant à une non-conformité | I17: Moyenne | J17: Incompatibilités techniques et dysfonctionnements
C18: S’assurer que l'organisation dispose d'un mécanisme de suivi et de gestion des violations éthiques, permettant de détecter, traiter et sanctionner tout comportement contraire à la charte éthique, y compris dans le cadre des activités liées aux systèmes d'information. | D18: Existence d’un processus formel de signalement et de traitement des violations éthiques. | E18: Un processus formel de signalement et de traitement des violations éthiques est-il en place au sein de l'organisation ? | F18: OUI | G18: Procédure de signalement | H18: Absence de canal de signalement décourageant les déclarations d’incidents | I18: Élevée | J18: Comportements à risque non maîtrisés
D19: Définition de sanctions proportionnées en fonction de la gravité des violations. | E19: Les sanctions applicables en cas de violation éthique sont-elles définies de manière proportionnée à la gravité des violations ? | F19: PAS | G19: Politique disciplinaire | H19: Incohérence dans l’application des sanctions, compromettant l’équité | I19: Moyenne | J19: Formations inefficaces et ressources gaspillées
D20: Mise en place d’un système de suivi des incidents éthiques. | E20: Un système de suivi des incidents éthiques (signalements, enquêtes, sanctions) est-il en place ? | F20: NON | G20: Registre des incidents éthiques | H20: Absence de traçabilité limitant les actions correctives | I20: Moyenne | J20: Zones d'ombre dans les processus
D21: Communication transparente des mesures correctives prises en cas de violation. | E21: Les mesures correctives prises en cas de violation éthique sont-elles communiquées de manière transparente au sein de l'organisation (dans le respect de la confidentialité) ? | F21: PAS | G21: Rapports internes de conformité | H21: Manque de transparence réduisant l’effet dissuasif des sanctions | I21: Moyenne | J21: Incapacité à appliquer en situation réelle
D22: Audit périodique pour évaluer l’efficacité du mécanisme de gestion des violations éthiques. | E22: Des audits périodiques sont-ils réalisés pour évaluer l'efficacité du mécanisme de gestion des violations éthiques ? | F22: NON | G22: Rapports d’audit interne | H22: Inefficacité du processus de gestion des violations, augmentant les risques de récidive | I22: Élevée | J22: Dégradation de la qualité de service
C23: S’assurer que l’organisation dispose d’un canal de signalement confidentiel et accessible, permettant aux employés, partenaires et prestataires de signaler toute violation éthique, notamment en lien avec l’utilisation des systèmes d’information, sans crainte de représailles. | D23: Mise en place d’un canal de signalement anonyme et sécurisé (ex : hotline, plateforme en ligne). | E23: Un canal de signalement anonyme et sécurisé (ex : hotline, plateforme en ligne) est-il mis à disposition des employés et partenaires pour signaler des violations éthiques ? | F23: NON | G23: Documentation du canal | H23: Absence de moyen sécurisé pouvant décourager le signalement | I23: Élevée | J23: Incidents non remontés et aggravés
D24: Garantie de la confidentialité des signalements pour protéger les lanceurs d’alerte. | E24: Des mesures sont-elles en place pour garantir la confidentialité des signalements et protéger les lanceurs d'alerte contre les représailles ? | F24: NON | G24: Politique de protection des lanceurs d’alerte | H24: Peur des représailles réduisant le taux de signalement | I24: Élevée | J24: Atteinte à la confidentialité des données
D25: Communication claire sur l’existence et l’accessibilité de ce canal à tous les employés et partenaires. | E25: L'existence et l'accessibilité du canal de signalement anonyme et sécurisé sont-elles clairement communiquées à tous les employés et partenaires ? | F25: NON | G25: Communication interne sur le canal | H25: Méconnaissance du canal entraînant une sous-utilisation | I25: Moyenne | J25: Manquements aux engagements contractuels
D26: Existence d’une procédure d’enquête et de traitement des signalements reçus. | E26: Une procédure d'enquête et de traitement des signalements reçus via le canal anonyme est-elle en place ? | F26: PAS | G26: Procédure d’enquête | H26: Signalements non traités réduisant la confiance des employés | I26: Élevée | J26: Traitements inappropriés des demandes
D27: Suivi des signalements et évaluation de l’efficacité du canal mis en place. | E27: Les signalements reçus via le canal anonyme sont-ils suivis et l'efficacité de ce canal est-elle évaluée périodiquement ? | F27: PAS | G27: Rapports d’évaluation du canal | H27: Manque d’amélioration continue pouvant réduire son efficacité | I27: Moyenne | J27: Détection trop tardive des fraudes
B28: Structures, autorités et responsabilités | C28: S’assurer que la structure organisationnelle est clairement définie, incluant les rattachements hiérarchiques, les rôles, les responsabilités et les pouvoirs de chaque collaborateur. | D28: Existence d’un organigramme détaillé décrivant les rôles et responsabilités. | E28: Un organigramme détaillé décrivant les rôles et responsabilités de chaque fonction au sein de l'organisation existe-t-il ? | F28: OUI | G28: Organigramme officiel | H28: Manque de clarté organisationnelle créant des conflits de responsabilité | I28: Moyenne | J28: Prise de décision biaisée
D29: Définition formelle des attributions et pouvoirs de chaque poste. | E29: Les attributions et les pouvoirs de chaque poste au sein de l'organisation sont-ils formellement définis ? | F29: NON | G29: Fiches de poste | H29: Risque de confusion dans la prise de décisions et la délégation | I29: Moyenne | J29: Réponse inefficace aux crises
D30: Mise en place de fiches de poste précisant les responsabilités de chaque collaborateur. | E30: Des fiches de poste précisant les responsabilités de chaque collaborateur sont-elles en place et régulièrement mises à jour ? | F30: OUI | G30: Fiches de poste mises à jour | H30: Incohérences dans la répartition des tâches | I30: Moyenne | J30: Accès non autorisés aux informations
D31: Présence d’un cadre de référence pour clarifier les relations hiérarchiques et fonctionnelles. | E31: Un cadre de référence est-il en place pour clarifier les relations hiérarchiques et fonctionnelles entre les différentes entités et les collaborateurs ? | F31: NON | G31: Document de référence organisationnel | H31: Ambiguïtés dans la gestion des interactions et responsabilités | I31: Moyenne | J31: Impossibilité de reconstituer les événements
D32: Accessibilité de la structure organisationnelle à tous les employés via un support officiel (intranet, manuel interne, etc.). | E32: La structure organisationnelle est-elle accessible à tous les employés via un support officiel (intranet, manuel interne, etc.) ? | F32: NON | G32: Support de communication interne | H32: Méconnaissance des circuits hiérarchiques ralentissant la prise de décision | I32: Moyenne | J32: Évaluations subjectives et partiales
C33: Vérifier que les responsabilités et laes pouvoirs sont attribués de manière appropriée, en fonction des compétences et des objectifs stratégiques de l’organisation. | D33: Processus formalisé d’attribution des responsabilités basé sur les compétences et qualifications. | E33: Un processus formalisé d’attribution des responsabilités basé sur les compétences et qualifications est-il en place ? | F33: OUI | G33: Procédure de gestion des compétences | H33: Attribution inadaptée des responsabilités pouvant compromettre l’efficacité | I33: Moyenne | J33: Prise de décision sur des bases erronées
D34: Cohérence entre les attributions de pouvoir et les objectifs stratégiques de l’organisation. | E34: Existe-t-il une cohérence entre les attributions de pouvoir et les objectifs stratégiques de l’organisation ? | F34: PAS | G34: Politique interne d’alignement stratégique | H34: Décalage entre les décisions prises et les objectifs globaux | I34: Moyenne | J34: Suivi irrégulier des performances
D35: Présence de mécanismes de contrôle pour éviter la concentration excessive de pouvoirs. | E35: Des mécanismes de contrôle sont-ils en place pour éviter la concentration excessive de pouvoirs au sein de l'organisation ? | F35: PAS | G35: Procédure de délégation et contrôle interne | H35: Risque d’abus de pouvoir et de fraude | I35: Élevée | J35: Décisions prises sans visibilité complète
D36: Existence d’un processus d’évaluation des compétences avant l’attribution de nouvelles responsabilités. | E36: Un processus d’évaluation des compétences est-il en place avant l’attribution de nouvelles responsabilités ? | F36: OUI | G36: Rapports d’évaluation des compétences | H36: Affectation inadaptée compromettant la performance | I36: Moyenne | J36: Processus incontrôlés et variables
D37: Vérification régulière de l’adéquation entre les responsabilités attribuées et les résultats attendus. | E37: L'adéquation entre les responsabilités attribuées et les résultats attendus est-elle vérifiée régulièrement ? | F37: NON | G37: Rapports de performance | H37: Risque de non-atteinte des objectifs stratégiques | I37: Moyenne | J37: Perte d'informations critiques
C38: Vérifier que le management reçoit l’approbation du Conseil pour les modifications de la structure organisationnelle, afin d’assurer une supervision adéquate des changements importants. | D38: Existence d’un processus formel de validation des changements structurels par le Conseil. | E38: Un processus formel de validation des changements structurels par le Conseil d'administration existe-t-il ? | F38: NON | G38: Procès-verbaux du Conseil d'Administration, Politique de gestion des changements | H38: Changements structurels non approuvés. | I38: Élevée | J38: Décisions sans consensus ni légitimité
D39: Documentation des décisions et des motivations derrière chaque modification de la structure. | E39: Les décisions et les motivations derrière chaque modification de la structure organisationnelle sont-elles documentées ? | F39: NON | G39: Documents de conception de la structure, Procès-verbaux des décisions | H39: Manque de traçabilité des décisions. | I39: Moyenne | J39: Choix stratégiques non éclairés
D40: Participation active du Conseil dans l’analyse des impacts des changements organisationnels. | E40: Le Conseil d'administration participe-t-il activement à l’analyse des impacts des changements organisationnels ? | F40: NON | G40: Procès-verbaux du Conseil d'Administration, Rapports d'analyse d'impact | H40: Impacts négatifs des changements non anticipés. | I40: Moyenne | J40: Communication inefficace entre services
D41: Intégration des recommandations du Conseil avant la mise en œuvre des modifications. | E41: Les recommandations du Conseil d'administration sont-elles intégrées avant la mise en œuvre des modifications structurelles ? | F41: NON | G41: Procès-verbaux du Conseil d'Administration, Plans de mise en œuvre des changements | H41: Non-prise en compte de l'expertise du Conseil. | I41: Moyenne | J41: Actions correctives non suivies
D42: Vérification de la conformité des modifications avec les objectifs et les valeurs de l’organisation. | E42: La conformité des modifications structurelles avec les objectifs et les valeurs de l’organisation est-elle vérifiée ? | F42: PAS | G42: Documents de conception de la structure, Référentiel des objectifs et valeurs | H42: Structure organisationnelle non alignée avec la stratégie. | I42: Moyenne | J42: Décisions arbitraires et contestables
C43: S’assurer que des mécanismes sont en place pour communiquer la structure organisationnelle à tous les collaborateurs, afin qu'ils comprennent clairement leurs rôles et leurs responsabilités. | D43: Disponibilité d’un document officiel décrivant la structure organisationnelle. | E43: Un document officiel décrivant la structure organisationnelle est-il disponible et à jour ? | F43: NON | G43: Organigramme officiel, Manuel d'organisation | H43: Manque de clarté sur les rôles et responsabilités. | I43: Moyenne | J43: Évaluations non reproductibles
D44: Organisation de sessions d’information ou de formation sur la structure et les responsabilités. | E44: Des sessions d’information ou de formation sur la structure organisationnelle et les responsabilités sont-elles organisées pour les employés ? | F44: NON | G44: Plans de formation, Supports de formation, Compte-rendus de sessions | H44: Mauvaise compréhension de la structure. | I44: Faible | J44: Critères d'évaluation inconstants
D45: Accès facile aux documents via l’intranet ou tout autre moyen de diffusion interne. | E45: Les documents relatifs à la structure organisationnelle sont-ils facilement accessibles aux employés via l’intranet ou d'autres moyens de diffusion interne ? | F45: NON | G45: Intranet, Manuel d'organisation, Plateformes de communication interne | H45: Difficulté à trouver les informations. | I45: Faible | J45: Données historiques inexactes
D46: Mise en place d’un point de contact pour répondre aux questions des employés sur l’organisation. | E46: Un point de contact est-il en place pour répondre aux questions des employés concernant la structure organisationnelle et les responsabilités ? | F46: NON | G46: Liste des contacts, Portail RH | H46: Questions des employés sans réponse. | I46: Faible | J46: Problèmes récurrents non résolus
D47: Vérification de la compréhension de la structure organisationnelle par les employés via des enquêtes ou des entretiens. | E47: La compréhension de la structure organisationnelle par les employés est-elle vérifiée via des enquêtes ou des entretiens ? | F47: NON | G47: Résultats d'enquêtes, Compte-rendus d'entretiens | H47: Lacunes dans la compréhension non identifiées. | I47: Faible | J47: Information incomplète pour décideurs
C48: Vérifier que les structures, les rattachements et les responsabilités sont clairement documentés et accessibles pour consultation, garantissant une traçabilité des décisions organisation | D48: Existence d’un document officiel mis à jour sur les rattachements et responsabilités. | E48: Un document officiel et à jour sur les rattachements hiérarchiques et les responsabilités de chaque poste existe-t-il ? | F48: OUI | G48: Fiches de poste, Organigramme détaillé | H48: Ambiguïté sur les responsabilités. | I48: Moyenne | J48: Réponse inadéquate aux incidents
D49: Archivage des modifications structurelles avec justification et validation. | E49: Les modifications structurelles sont-elles archivées avec la justification et la validation correspondantes ? | F49: OUI | G49: Archives des documents organisationnels, Historique des modifications | H49: Perte de traçabilité des évolutions. | I49: Faible | J49: Problèmes non clôturés durablement
D50: Accessibilité des documents organisationnels aux managers et employés concernés. | E50: Les documents organisationnels sont-ils facilement accessibles aux managers et aux employés concernés ? | F50: NON | G50: Intranet, Systèmes de gestion documentaire | H50: Difficulté d'accès à l'information pour la prise de décision. | I50: Faible | J50: Délais critiques non respectés
D51: Présence d’un processus de contrôle pour garantir la cohérence des documents avec la réalité opérationnelle. | E51: Un processus de contrôle est-il en place pour garantir la cohérence des documents organisationnels avec la réalité opérationnelle ? | F51: OUI | G51: Procédures de revue documentaire, Audits internes | H51: Documents obsolètes ou incorrects. | I51: Moyenne | J51: Erreurs répétées par manque de retour
D52: Intégration des documents organisationnels dans un référentiel structuré et centralisé. | E52: Les documents organisationnels sont-ils intégrés dans un référentiel structuré et centralisé ? | F52: PAS | G52: Système de gestion documentaire, Intranet | H52: Difficulté à trouver les informations fiables. | I52: Faible | J52: Améliorations non mesurables
B53: Compétences des individus | C53: S’assurer que l’organisation dispose de processus clairs et formalisés pour attirer des talents qualifiés dans les domaines nécessaires à son fonctionnement, y compris pour les systèmes d’information. | D53: Existence d’une politique de recrutement détaillant les besoins en compétences clés. | E53: Une politique de recrutement détaillant les besoins en compétences clés est-elle en place ? | F53: NON | G53: Politique de recrutement | H53: Difficulté à attirer les bons profils. | I53: Moyenne | J53: Structure inadaptée aux besoins
D54: Présence d’un processus structuré de sélection des candidats basé sur des critères objectifs. | E54: Un processus structuré de sélection des candidats basé sur des critères objectifs est-il en place ? | F54: NON | G54: Procédure de recrutement, Grilles d'évaluation | H54: Risque de biais dans le recrutement. | I54: Moyenne | J54: Confusion dans les chaînes hiérarchiques
D55: Utilisation de canaux de recrutement adaptés (plateformes spécialisées, réseaux professionnels, partenariats avec des universités). | E55: L'organisation utilise-t-elle des canaux de recrutement adaptés (plateformes spécialisées, réseaux professionnels, partenariats avec des universités) ? | F55: NON | G55: Stratégie de sourcing, Liste des canaux utilisés | H55: Difficulté à atteindre les profils recherchés. | I55: Faible | J55: Processus non actualisés
D56: Intégration d’une grille d’évaluation pour s’assurer de l’adéquation entre les profils recrutés et les besoins organisationnels. | E56: Une grille d'évaluation est-elle utilisée pour s'assurer de l'adéquation entre les profils recrutés et les besoins organisationnels ? | F56: NON | G56: Grilles d'évaluation, Descriptions de poste | H56: Risque de recruter des personnes inadaptées aux postes. | I56: Moyenne | J56: Modifications non maîtrisées
D57: Suivi et évaluation des performances des nouvelles recrues pour valider leur adaptation et efficacité. | E57: Un suivi et une évaluation des performances des nouvelles recrues sont-ils réalisés pour valider leur adaptation et leur efficacité ? | F57: NON | G57: Politique d'intégration, Entretiens de suivi, Périodes d'essai | H57: Difficulté à identifier les problèmes d'intégration rapidement. | I57: Faible | J57: Perte de connaissance organisationnelle
