Workbook

Sheet Explications
B2: Dans le cadre de notre mission d'audit de l'application APPLICATION chez Lizbiz, nous avons développé cet outil complet organisé en 8 feuilles : une feuille Explication (présentant l'outil), une feuille Global (recensant l'ensemble des audits), une feuille COSO (alignée sur ce référentiel), ainsi que 5 feuilles thématiques couvrant l'Application en service, la Fonction informatique, le Contrôle des projets informatiques, le Support utilisateur et gestion du parc, et la Sécurité informatique. Conçu lors des phases de planification et d'exécution, cet outil sur mesure permet une analyse rigoureuse de tous les aspects techniques et fonctionnels de l'application web audité.

Sheet Synthèse
B2: Synthèse Numérique
B3: N° | C3: Domaines | D3: Total OUI | E3: Total NON | F3: Total PAS | G3: Total | H3: Score
B4: 1 | C4: Application en service | D4: =COUNTIF(Global!F2:F506,"OUI") -> 288 | E4: =COUNTIF(Global!F2:F506, "NON") -> 145 | F4: =COUNTIF(Global!F2:F506, "PAS") -> 72 | G4: =SUM(D4:F4) -> 505 | H4: =D4/G4 -> 0.57029703
B5: 2 | C5: Fonction informatique | D5: =COUNTIF(Global!F507:F726, "OUI") -> 119 | E5: =COUNTIF(Global!F507:F726, "NON") -> 64 | F5: =COUNTIF(Global!F507:F726, "PAS") -> 36 | G5: =SUM(D5:F5) -> 219 | H5: =D5/G5 -> 0.543379
B6: 3 | C6: Application en service | D6: =COUNTIF(Global!F1102:F1331, "OUI") -> 111 | E6: =COUNTIF(Global!F727:F1101, "NON") -> 104 | F6: =COUNTIF(Global!F727:F1101, "PAS") -> 54 | G6: =SUM(D6:F6) -> 269 | H6: =D6/G6 -> 0.41263941
B7: 4 | C7: Support Utilisateur et de la Gestion du Parc | D7: =COUNTIF(Global!F728:F1102, "OUI") -> 217 | E7: =COUNTIF(Global!F728:F1102, "NON") -> 104 | F7: =COUNTIF(Global!F728:F1102, "PAS") -> 54 | G7: =SUM(D7:F7) -> 375 | H7: =D7/G7 -> 0.57866667
B8: 5 | C8: Sécurité Informatique | D8: =COUNTIF(Global!F1132:F1676, "OUI") -> 337 | E8: =COUNTIF(Global!F1132:F1676, "NON") -> 131 | F8: =COUNTIF(Global!F1132:F1676, "PAS") -> 77 | G8: =SUM(D8:F8) -> 545 | H8: =D8/G8 -> 0.61834862
B9: Total | D9: =SUM(D4:D8) -> 1072 | E9: =SUM(E4:E8) -> 548 | F9: =SUM(F4:F8) -> 293 | G9: =SUM(G4:G8) -> 1913 | H9: =D9/G9 -> 0.56037637

Sheet Global
A1: Domaines | B1: Points de contrôles | C1: Objectifs de contrôle | D1: Critères d'évaluation | E1: Questions d'évaluation | F1: Réponses | G1: Documents requis | H1: Risques | I1: Criticités | J1: Conséquences | K1: Recommandations
A2: Application en service | B2: Organisation | C2: S’assurer de l’existence d'un comité informatique | D2: Vérifier l’existence d’un organigramme officiel du comité signé par la direction. | E2: L'organigramme du comité est-il signé par la direction ? | F2: OUI | G2: Organigramme de l’entité | H2: Absence de gouvernance clairement définie | I2: Moyenne | J2: Non-conformité aux réglementations en vigueur entraînant des sanctions légales. | K2: Élaborer un cadre de gouvernance aligné sur COBIT ou ISO 27001 en formalisant les rôles et responsabilités.
D3: Confirmer la présence d’au moins 3 procès-verbaux de réunion datés des 6 derniers mois. | E3: Trois procès-verbaux de réunion existent-ils pour les 6 derniers mois ? | F3: OUI | G3: Organigramme fonctionnel de la DSI | H3: Documentation insuffisante des décisions stratégiques | I3: Elevée | J3: Détérioration de la confiance des parties prenantes due à l'absence de traçabilité des décisions. | K3: Documenter et diffuser les politiques de sécurité et les procédures internes pour garantir leur accessibilité.
D4: Analyser la composition du comité (CV/certifications des membres). | E4: Les CV et certifications des membres du comité sont-ils disponibles ? | F4: NON | G4: Procès-verbaux des réunions du comité | H4: Incompétence des membres du comité de pilotage | I4: Elevée | J4: Augmentation des erreurs opérationnelles par manque de directives claires. | K4: Mettre en place une formation continue sur les enjeux de sécurité et la conformité réglementaire pour les employés.
D5: Identifier un mandat écrit précisant les missions et la fréquence des réunions. | E5: Un mandat écrit définit-il les missions et la fréquence des réunions ? | F5: PAS | G5: Fiches de postes de la DSI | H5: Définition floue des responsabilités du comité | I5: Faible | J5: Vulnérabilité accrue aux cyberattaques en raison de politiques obsolètes. | K5: Implémenter des contrôles d'accès stricts basés sur le principe du moindre privilège et revoir périodiquement les habilitations.
D6: Contrôler la diffusion des décisions du comité via des emails ou documents internes. | E6: Les décisions du comité sont-elles diffusées par email ou documents internes ? | F6: OUI | G6: Politique des Applications approuvée par la direction | H6: Non-diffusion des orientations stratégiques aux équipes | I6: Elevée | J6: Inefficacité des contrôles internes causant des pertes financières. | K6: Concevoir et tester régulièrement un plan de continuité d'activité (PCA) et un plan de reprise d'activité (PRA).
C7: S’assurer de l’existence d'une politique relative aux applications | D7: Vérifier la présence d’un document intitulé "Politique des Applications" approuvé par la direction. | E7: La "Politique des Applications" est-elle approuvée par la direction ? | F7: OUI | G7: Accusés de réception des employés pour la politique | H7: Politique de sécurité non formalisée | I7: Moyenne | J7: Exposition à des litiges juridiques faute de documentation appropriée. | K7: Instaurer une matrice des risques mise à jour annuellement et intégrée aux processus décisionnels.
D8: Confirmer la date de la dernière mise à jour (moins de 12 mois). | E8: La dernière mise à jour date-t-elle de moins de 12 mois ? | F8: NON | G8: Plan de formation annuel lié à la politique | H8: Non-conformité réglementaire | I8: Elevée | J8: Dysfonctionnements dans la gestion des accès menant à des fuites de données sensibles. | K8: Automatiser les contrôles de validation des données critiques pour réduire les erreurs manuelles.
D9: Analyser les mentions de conformité RGPD/ISO dans le document. | E9: Le document mentionne-t-il la conformité RGPD/ISO ? | F9: PAS | G9: Matrice des autorisations/droits d’accès | H9: Manque de sensibilisation des employés aux politiques | I9: Moyenne | J9: Interruptions prolongées des activités en cas de sinistre non anticipé. | K9: Déployer des outils de surveillance en temps réel pour détecter les anomalies et les activités suspectes.
D10: Vérifier la diffusion de la politique aux employés (accusés de réception signés). | E10: Les employés ont-ils signé des accusés de réception pour la politique ? | F10: OUI | G10: Liste des 100 derniers incidents du domaine d’audit | H10: Absence de formation continue sur les enjeux de sécurité | I10: Moyenne | J10: Dégradation de la performance des systèmes due à une maintenance inadéquate. | K10: Réaliser des audits réguliers des configurations des systèmes et des droits d'accès privilégiés.
D11: Identifier un plan de formation annuel lié à cette politique. | E11: Un plan de formation annuel lié à cette politique existe-t-il ? | F11: NON | G11: Rapport d’analyse des risques récent (moins de 12 mois) | H11: Définition imprécise des rôles utilisateurs | I11: Elevée | J11: Non-respect des engagements contractuels envers les clients ou partenaires. | K11: Mettre en œuvre des mécanismes de chiffrement des données en transit et au repos conformes aux normes ISO 27001.
C12: S’assurer que les rôle et responsabilités des utilisateurs sont bien définis | D12: Contrôler l’existence de fiches de poste pour chaque profil utilisateur. | E12: Des fiches de poste sont-elles disponibles pour chaque profil utilisateur ? | F12: OUI | G12: Document de classification des données (public, interne, confidentiel) | H12: Violation des engagements contractuels | I12: Moyenne | J12: Augmentation des coûts opérationnels liés à des processus inefficients. | K12: Séparer les environnements de développement, de test et de production pour limiter les risques de corruption.
D13: Vérifier la signature des utilisateurs sur des chartes d’utilisation. | E13: Les utilisateurs ont-ils signé des chartes d'utilisation ? | F13: NON | G13: Manuel d’administration des applications | H13: Droits d'accès obsolètes ou inadaptées | I13: Moyenne | J13: Perte de données critiques par absence de sauvegardes fiables. | K13: Établir des procédures de gestion des incidents incluant une analyse post-mortem et des plans d'action correctifs.
D14: Confirmer la mise à jour des habilitations dans un tableau de gestion des accès. | E14: Le tableau de gestion des accès est-il à jour ? | F14: OUI | G14: Logs d’accès aux données sensibles sur 30 jours | H14: Détournement de privilèges | I14: Moyenne | J14: Retards dans les prises de décision faute d’informations actualisées. | K14: Valider l'exhaustivité et l'intégrité des sauvegardes via des tests de restauration périodiques.
D15: Analyser des logs d’accès pour corréler avec les rôles déclarés. | E15: Les logs d'accès correspondent-ils aux rôles déclarés ? | F15: OUI | G15: Procédures écrites pour les processus critiques | H15: Absence de revue périodique des habilitations | I15: Moyenne | J15: Compromission de l’intégrité des données financières ou métiers. | K15: Créer un comité de pilotage IT pour superviser l'alignement stratégique des projets avec les objectifs métiers.
D16: Identifier des procédures de révision trimestrielle des droits. | E16: Une procédure de révision trimestrielle des droits est-elle en place ? | F16: NON | G16: Comptes rendus mensuels de l’application | H16: Fraude interne via l'exploitation de droits excessifs | I16: Moyenne | J16: Risque accru de fraude interne en l’absence de séparation des tâches. | K16: Utiliser des outils de gestion des identités et des accès (IAM) pour centraliser et auditer les permissions.
C17: S’assurer qu’une analyse des risques a été réalisée | D17: Vérifier un rapport d’analyse des risques daté de moins de 12 mois. | E17: Un rapport d'analyse des risques de moins de 12 mois existe-t-il ? | F17: OUI | G17: Guide utilisateur et manuel de procédures | H17: Évaluation des risques non actualisée | I17: Elevée | J17: Détérioration de la qualité des services IT impactant la satisfaction client. | K17: Réaliser des tests de pénétration et des audits de code pour identifier les vulnérabilités applicatives.
D18: Confirmer l’utilisation d’une méthodologie reconnue (ex : EBIOS, OCTAVE). | E18: La méthodologie utilisée est-elle reconnue (EBIOS, OCTAVE) ? | F18: OUI | G18: Matrice des tâches et fonctions incompatibles | H18: Utilisation de méthodologies obsolètes | I18: Faible | J18: Exposition à des amendes réglementaires pour non-conformité RGPD. | K18: Documenter les flux de données et les interfaces entre systèmes pour garantir la traçabilité des échanges.
D19: Analyser la liste des risques identifiés (au moins 10 risques critiques). | E19: Au moins 10 risques critiques sont-ils identifiés ? | F19: NON | G19: Contrat de maintenance ou d’assistance | H19: Sous-estimation des menaces critiques | I19: Faible | J19: Interruptions fréquentes des services en production par manque de redondance. | K19: Adopter une politique de gestion des correctifs avec des délais stricts pour les mises à jour critiques.
D20: Identifier un plan d’action avec des responsables et des échéances. | E20: Un plan d'action avec responsables et échéances est-il établi ? | F20: PAS | G20: Plan de continuité des activités (PCA) | H20: Absence de planification corrective | I20: Moyenne | J20: Difficultés à assurer la continuité des activités lors de crises majeures. | K20: Instaurer des contrôles d'intégrité des données lors des migrations ou des transferts inter-systèmes.
D21: Contrôler des preuves de mise en œuvre des actions (rapports de suivi). | E21: Des preuves de mise en œuvre des actions sont-elles disponibles ? | F21: OUI | G21: Plan de reprise d’activité (PRA) | H21: Contrôles inefficaces face aux risques identifiés | I21: Moyenne | J21: Dépendance excessive vis-à-vis de prestataires externes non supervisés. | K21: Mettre en place une journalisation centralisée et une analyse proactive des logs pour détecter les menaces.
C22: S’assurer que le prolongement de l'analyse de risque et de son expansion ont été réalisés | D22: Vérifier des mises à jour de l’analyse des risques (au moins 2 révisions annuelles). | E22: L'analyse des risques a-t-elle été mise à jour deux fois dans l'année ? | F22: OUI | G22: Rapports de traitements des incidents | H22: Ignorance des nouvelles vulnérabilités | I22: Elevée | J22: Altération de la réputation de l’organisation suite à des incidents récurrents. | K22: Élaborer une charte de sécurité informatique incluant des clauses contractuelles avec les fournisseurs externes.
D23: Confirmer l’intégration des nouveaux risques (ex : cybermenaces, RGPD). | E23: Les nouveaux risques (cybermenaces, RGPD) sont-ils intégrés ? | F23: NON | G23: Inventaire des licences | H23: Défaut de reporting aux instances décisionnelles | I23: Moyenne | J23: Inefficacité des plans de reprise après sinistre prolongeant les temps d’arrêt. | K23: Concevoir des tableaux de bord de performance alignés sur les KPI métiers pour mesurer l'efficacité des SI.
D24: Analyser des indicateurs de suivi des risques (tableaux de bord). | E24: Des indicateurs de suivi des risques existent-ils ? | F24: PAS | G24: Bilan de qualité logiciel | H24: Culture du risque insuffisante dans l'organisation | I24: Moyenne | J24: Augmentation des vulnérabilités logicielles par absence de mises à jour. | K24: Sensibiliser les utilisateurs aux risques de phishing et d'ingénierie sociale via des simulations régulières.
D25: Identifier des procédures de reporting aux instances dirigeantes. | E25: Des procédures de reporting aux instances dirigeantes sont-elles définies ? | F25: OUI | G25: Bilan de satisfaction des utilisateurs | H25: Classification inappropriée des données sensibles | I25: Faible | J25: Désorganisation des équipes IT faute de procédures standardisées. | K25: Auditer régulièrement les configurations des pare-feux et des équipements réseau pour prévenir les attaques.
D26: Contrôler des preuves de sensibilisation des équipes aux risques majeurs. | E26: Les équipes sont-elles sensibilisées aux risques majeurs ? | F26: OUI | G26: Schéma d’interaction des applications métiers | H26: Exposition de données critiques | I26: Moyenne | J26: Non-atteinte des objectifs stratégiques en raison d’un mauvais alignement IT-métier. | K26: Intégrer des contrôles de conformité RGPD dans les processus de traitement des données personnelles.
C27: S’assurer que l’analyse et évaluation du niveau de sensibilité a été réalisée | D27: Vérifier un document classifiant les données par niveau de sensibilité (public, interne, confidentiel). | E27: Un document classe-t-il les données (public, interne, confidentiel) ? | F27: NON | G27: Diagramme de flux de données des applications | H27: Surveillance inadéquate des accès privilégiés | I27: Moyenne | J27: Perte de compétitivité due à des technologies obsolètes ou sous-utilisées. | K27: Définir une stratégie de gestion des actifs numériques incluant leur classification et leur cycle de vie.
D28: Confirmer la mise à jour de la classification (moins de 6 mois). | E28: La classification a-t-elle été mise à jour dans les 6 mois ? | F28: OUI | G28: Procédures de gestion des changements | H28: Protection insuffisante des actifs informationnels | I28: Elevée | J28: Erreurs humaines accrues par manque de formation ou de documentation. | K28: Mettre en œuvre des contrôles d'accès physique aux salles serveurs et aux centres de données.
D29: Analyser des logs d’accès aux données sensibles sur 30 jours. | E29: Les logs d'accès aux données sensibles sur 30 jours sont-ils analysables ? | F29: OUI | G29: Logs de connexion avec adresses IP et horodatages | H29: Manque de formation sur la manipulation des données | I29: Moyenne | J29: Détection tardive des anomalies opérationnelles réduisant la réactivité. | K29: Réaliser des audits de sécurité des APIs pour prévenir les exploitations malveillantes.
D30: Identifier des procédures de protection spécifiques pour les données critiques. | E30: Des procédures spécifiques protègent-elles les données critiques ? | F30: NON | G30: Politique de sécurité des mots de passe | H30: Documentation technique obsolète | I30: Moyenne | J30: Fuite d’informations confidentielles par des contrôles d’accès laxistes. | K30: Standardiser les procédures de gestion des changements avec validation technique et métier préalable.
D31: Contrôler des preuves de formation des utilisateurs sur la classification. | E31: Les utilisateurs sont-ils formés sur la classification des données ? | F31: PAS | G31: Procédures de gestion des identifiants et mots de passe | H31: Procédures de secours non testées | I31: Moyenne | J31: Dégradation de la productivité des utilisateurs face à des outils inadaptés. | K31: Instaurer des revues indépendantes des architectures techniques pour garantir leur résilience.
C32: Vérifier l’existence d’un manuel d'administration de l'application | D32: Vérifier l’existence d’un manuel d’administration mis à jour (moins de 12 mois). | E32: Le manuel d'administration est-il à jour (moins de 12 mois) ? | F32: OUI | G32: Document de stratégie de migration des données | H32: Dépendance excessive au savoir-faire individuel | I32: Moyenne | J32: Difficultés à auditer les systèmes en raison d’une journalisation insuffisante. | K32: Adopter des contrats de service (SLA) clairs avec des pénalités en cas de non-respect des engagements.
D33: Confirmer la couverture des procédures clés (ex : sauvegarde, restauration). | E33: Les procédures clés (sauvegarde, restauration) sont-elles couvertes ? | F33: OUI | G33: Procédures de sauvegarde et restauration | H33: Absence de capitalisation des connaissances | I33: Moyenne | J33: Augmentation des coûts de conformité pour rattraper les lacunes identifiées. | K33: Utiliser des solutions de détection d'intrusion (IDS/IPS) pour surveiller les activités réseau anormales.
D34: Analyser des exemples de procédures détaillées (étapes, screenshots). | E34: Des procédures détaillées avec étapes et captures existent-elles ? | F34: NON | G34: Rapports de tests de restauration après sinistre | H34: Défaut de traçabilité des opérations sensibles | I34: Moyenne | J34: Risque de corruption des données lors de migrations non contrôlées. | K34: Documenter les dépendances critiques entre systèmes pour anticiper les impacts des pannes.
D35: Identifier des preuves d’utilisation du manuel (logs de consultation). | E35: Des logs de consultation du manuel sont-ils disponibles ? | F35: OUI | G35: Clauses de contrat SLA avec les fournisseurs | H35: Contrôles métier inefficaces | I35: Faible | J35: Incapacité à répondre aux audits externes faute de preuves tangibles. | K35: Mettre en place une politique de gestion des mots de passe exigeant une complexité et une rotation régulière.
D36: Contrôler des formations dédiées à l’équipe d’administration. | E36: L'équipe d'administration reçoit-elle des formations dédiées ? | F36: OUI | G36: Feuille de route technologique approuvée | H36: Non-respect des bonnes pratiques sectorielles | I36: Faible | J36: Fragilisation de la gouvernance IT par une supervision inefficace. | K36: Auditer les configurations des bases de données pour limiter les risques d'exposition non autorisée.
C37: Vérifier l’existence de procédures formalisées | D37: Vérifier des procédures écrites pour au moins 5 processus critiques (ex : gestion des incidents). | E37: Cinq procédures écrites pour processus critiques existent-elles ? | F37: NON | G37: Rapports d’évaluation de l’alignement stratégique | H37: Défaut de supervision des processus clés | I37: Moyenne | J37: Exposition à des attaques ciblées en l’absence de surveillance proactive. | K37: Formaliser une procédure de réponse aux incidents cyber incluant une communication structurée.
D38: Confirmer la signature des procédures par les responsables concernés. | E38: Les responsables ont-ils signé ces procédures ? | F38: PAS | G38: Spécifications fonctionnelles signées | H38: Erreurs de conception des workflows | I38: Elevée | J38: Déséquilibre entre investissements IT et retours sur investissement attendus. | K38: Implémenter des contrôles d'accès hiérarchiques pour les environnements virtualisés et cloud.
D39: Analyser des preuves d’application (logs, rapports d’exécution). | E39: Des preuves d'application (logs, rapports) sont-elles vérifiables ? | F39: OUI | G39: Fiches de poste détaillant les tâches des utilisateurs | H39: Interface utilisateur peu intuitive | I39: Moyenne | J39: Perte de données historiques critiques par archivage défaillant. | K39: Réaliser des évaluations de maturité des processus IT selon le référentiel COBIT.
D40: Identifier des indicateurs de performance liés aux procédures. | E40: Des indicateurs de performance liés aux procédures existent-ils ? | F40: OUI | G40: Rapports de performance des systèmes parallèles | H40: Absence de validation automatique des saisies | I40: Moyenne | J40: Complexification des processus métier due à des interfaces peu ergonomiques. | K40: Instaurer des mécanismes de contrôle qualité automatisés dans les pipelines DevOps.
D41: Contrôler des mises à jour récentes (moins de 6 mois). | E41: Les procédures ont-elles été mises à jour dans les 6 mois ? | F41: NON | G41: Retours d’expérience des utilisateurs sur l’adéquation | H41: Défaut de maintenance évolutive | I41: Moyenne | J41: Délais prolongés dans les projets IT par mauvaise gestion des priorités. | K41: Mettre à jour régulièrement les politiques de sécurité pour refléter l'évolution des menaces.
C42: S’assurer de l’existence et de la mise à disposition du compte rendu mensuel au propriétaire | D42: Vérifier des comptes rendus mensuels datés des 6 derniers mois. | E42: Des comptes rendus mensuels existent-ils pour les 6 derniers mois ? | F42: OUI | G42: Rapport ROI (Return on Investment) avec calculs détaillés | H42: Incohérences dans les données de référence | I42: Elevée | J42: Non-respect des SLA entraînant des pénalités contractuelles. | K42: Créer un référentiel unique des configurations matérielles et logicielles pour éviter les divergences.
D43: Confirmer la signature des comptes rendus par le propriétaire de l’application. | E43: Le propriétaire de l'application a-t-il signé ces comptes rendus ? | F43: OUI | G43: Contrats signés avec les fournisseurs | H43: Faiblesses dans les mécanismes de réconciliation | I43: Moyenne | J43: Détérioration de la relation avec les fournisseurs par manque de suivi. | K43: Effectuer des audits de conformité des licences logicielles pour prévenir les risques juridiques.
D44: Analyser des indicateurs clés inclus (ex : disponibilité, incidents). | E44: Des indicateurs clés (disponibilité, incidents) sont-ils inclus ? | F44: NON | G44: Calendrier de mise en œuvre du projet | H44: Manque d'intégrité des données | I44: Moyenne | J44: Augmentation des conflits internes liés à des rôles mal définis. | K44: Déployer des solutions de protection contre les attaques DDoS pour les services exposés en ligne.
D45: Identifier des actions correctives planifiées dans les comptes rendus. | E45: Des actions correctives sont-elles planifiées dans les comptes rendus ? | F45: PAS | G45: Bilan post-projet avec conclusions | H45: Exposition des flux inter-applicatifs | I45: Moyenne | J45: Incapacité à capitaliser sur les innovations technologiques par rigidité organisationnelle. | K45: Établir des procédures de destruction sécurisée des données en fin de cycle de vie.
D46: Contrôler des preuves de suivi des actions (rapports de clôture). | E46: Des preuves de suivi des actions (rapports de clôture) existent-elles ? | F46: OUI | G46: Rapports d’économie réalisées | H46: Défaut de chiffrement des transmissions | I46: Moyenne | J46: Risque de non-conformité aux standards sectoriels nuisant à la crédibilité. | K46: Réaliser des tests de résistance des infrastructures face aux catastrophes naturelles.
C47: S’assurer de l’existence d'un guide d'utilisateur, manuel de procédure | D47: Vérifier l’existence d’un guide d’utilisateur et d’un manuel de procédures. | E47: Un guide utilisateur et un manuel de procédures sont-ils disponibles ? | F47: OUI | G47: Document de réingénierie des processus | H47: Contournement des contrôles d'accès | I47: Moyenne | J47: Désalignement entre les besoins métier et les capacités techniques disponibles. | K47: Intégrer des contrôles de sécurité dans les phases de conception des applications (Security by Design).
D48: Confirmer la mise à jour des documents (moins de 12 mois). | E48: Ces documents ont-ils été mis à jour dans les 12 mois ? | F48: NON | G48: Rapport d’architecture technique de l’application | H48: Journalisation insuffisante des activités | I48: Moyenne | J48: Fragmentation des systèmes réduisant l’efficacité globale de l’infrastructure. | K48: Mettre en place une veille technologique pour anticiper les risques liés aux nouvelles technologies.
D49: Analyser des exemples de procédures détaillées (étapes, screenshots). | E49: Des procédures détaillées avec captures d'écran existent-elles ? | F49: OUI | G49: Tableaux de bord avec indicateurs de performance (KPI) | H49: Détection tardive des incidents de sécurité | I49: Moyenne | J49: Exposition à des erreurs de traitement par absence de validation automatisée. | K49: Auditer régulièrement les fournisseurs tiers pour s'assurer de leur conformité aux exigences de sécurité.
D50: Identifier des preuves de diffusion aux utilisateurs (accusés de réception). | E50: Des accusés de réception prouvent-ils la diffusion aux utilisateurs ? | F50: OUI | G50: Rapports de maturité technologique (ex : Gartner) | H50: Absence de revue des journaux d'audit | I50: Moyenne | J50: Détérioration de la qualité des données utilisées pour la prise de décision. | K50: Documenter les procédures de gestion des identités temporaires et des comptes de service.
D51: Contrôler des formations dédiées à l’utilisation des documents. | E51: Des formations sur l'utilisation des documents sont-elles organisées ? | F51: NON | G51: Procédures de gestion des accès privilégiés | H51: Failles dans les interfaces d'intégration | I51: Moyenne | J51: Inadéquation des compétences des équipes face aux évolutions technologiques. | K51: Instaurer des revues post-incident pour améliorer continuellement les processus de sécurité.
B52: Application | C52: S'assurer que l'accès aux ressources de l'application (données et transactions) est restreint par un système de gestion d'accès | D52: Vérifier l’existence d’un système RBAC (Role-Based Access Control) actif. | E52: Un système RBAC est-il actif ? | F52: PAS | G52: Logs d’actions administratives sur 90 jours | H52: Corruption des données lors des échanges | I52: Elevée | J52: Augmentation des temps d’indisponibilité des systèmes critiques. | K52: Adopter des outils de monitoring des performances applicatives pour détecter les goulets d'étranglement.
D53: Confirmer la présence de logs d’accès aux données sensibles sur 30 jours. | E53: Des logs d'accès aux données sensibles sur 30 jours existent-ils ? | F53: OUI | G53: Procédures de révocation des accès en cas de départ | H53: Absence de mécanismes de rejeu | I53: Moyenne | J53: Perte d’opportunités commerciales par lenteur des processus informatiques. | K53: Mettre en œuvre une politique de gestion des clés de chiffrement incluant leur rotation et stockage sécurisé.
D54: Analyser la liste des utilisateurs avec droits administrateurs (moins de 5% du total). | E54: Moins de 5% des utilisateurs ont-ils des droits administrateur ? | F54: OUI | G54: Document de schéma-directeur du SI | H54: Perte de données critiques | I54: Moyenne | J54: Dépassements budgétaires récurrents dans les projets IT non maîtrisés. | K54: Réaliser des audits de code statique et dynamique (SAST/DAST) pour les applications critiques.
D55: Tester le rejet d’accès hors profil via un compte test. | E55: Un compte test confirme-t-il le rejet d'accès hors profil ? | F55: NON | G55: Procédures de contrôle qualité des données saisies | H55: Archivage non conforme | I55: Moyenne | J55: Risque de perte de savoir-faire interne par dépendance à des solutions externes. | K55: Formaliser une stratégie de sortie pour les technologies obsolètes incluant leur remplacement progressif.
D56: Identifier une procédure de révocation des accès en cas de départ. | E56: Une procédure de révocation des accès en cas de départ existe-t-elle ? | F56: OUI | G56: Manuels d’exploitation mis à jour | H56: Restauration impossible après incident | I56: Moyenne | J56: Difficultés à maintenir la cohérence des données entre systèmes hétérogènes. | K56: Instaurer des contrôles d'accès basés sur les rôles (RBAC) pour les environnements cloud.
C57: S’assurer qu’une procédure de gestion des profils utilisateurs existe | D57: Contrôler un workflow de création/suppression de profils (outil Jira ou équivalent). | E57: Un workflow de gestion des profils (Jira ou équivalent) est-il utilisé ? | F57: OUI | G57: Procédures de gestion des correctifs urgents | H57: Pertes d'informations historiques | I57: Moyenne | J57: Détérioration de l’expérience utilisateur impactant l’adoption des outils. | K57: Documenter les procédures de gestion des vulnérabilités logicielles et des correctifs d'urgence.
D58: Vérifier des traces de validation hiérarchique pour 5 profils aléatoires. | E58: La validation hiérarchique pour 5 profils aléatoires est-elle tracée ? | F58: NON | G58: Rapports de revue de code pour les projets récents | H58: Défaut de purge sécurisée | I58: Moyenne | J58: Non-respect des exigences réglementaires en matière de transparence. | K58: Mettre en place des mécanismes de détection des fuites de données (DLP) pour les informations sensibles.
D59: Analyser l’existence d’un référentiel des profils types (PDF ou Excel). | E59: Un référentiel des profils types (PDF/Excel) est-il disponible ? | F59: PAS | G59: Procédures de déploiement en environnement de production | H59: Défaut de gestion des anomalies | I59: Moyenne | J59: Augmentation des coûts de maintenance corrective faute de prévention. | K59: Auditer les configurations des conteneurs et des orchestrateurs pour limiter les risques d'exploitation.
D60: Confirmer la réalisation d’un audit semestriel des droits. | E60: Un audit semestriel des droits est-il réalisé ? | F60: OUI | G60: Contrats incluant des clauses « Escrow Agreement » | H60: Absence de processus de correction | I60: Moyenne | J60: Incapacité à détecter les anomalies en temps réel par monitoring insuffisant. | K60: Implémenter une politique de gestion des risques spécifique aux projets d'intelligence artificielle.
D61: Identifier des sanctions en cas de non-respect (ex : mentions dans des PV). | E61: Des sanctions pour non-respect sont-elles prévues (mention dans PV) ? | F61: OUI | G61: Rapports de tests de montée en charge | H61: Défaut de traçabilité des corrections | I61: Moyenne | J61: Dégradation de la résilience des systèmes face aux perturbations externes. | K61: Réaliser des tests d'intégration pour valider la cohérence des données entre systèmes hétérogènes.
C62: Vérifier que l’identification des utilisateurs est réalisée | D62: Tester l’impossibilité de se connecter sans identifiant unique. | E62: La connexion sans identifiant unique est-elle impossible ? | F62: NON | G62: Procédures de gestion des données archivées | H62: Réintégration non contrôlée des données | I62: Elevée | J62: Exposition à des conflits d’intérêts dans la gestion des fournisseurs IT. | K62: Instaurer des contrôles d'accès biométriques pour les zones sensibles des datacenters.
D63: Vérifier l’absence de comptes génériques ("admin", "invité"). | E63: Les comptes génériques ("admin", "invité") sont-ils absents ? | F63: OUI | G63: Rapports de suivi des paiements des redevances | H63: Validation insuffisante des correctifs | I63: Moyenne | J63: Perte de contrôle sur les actifs informationnels par mauvaise gouvernance. | K63: Documenter les procédures de gestion des incidents liés aux fournisseurs de services cloud.
D64: Analyser l’existence d’un annuaire LDAP/Active Directory synchronisé. | E64: Un annuaire LDAP/Active Directory est-il synchronisé ? | F64: OUI | G64: Procédures de gestion des partenariats avec les éditeurs | H64: Défaut de supervision des mises à jour | I64: Moyenne | J64: Risque de non-reconnaissance des dépenses IT par manque de traçabilité. | K64: Mettre en œuvre des solutions de segmentation réseau pour isoler les flux critiques.
D65: Confirmer la présence d’une procédure de réinitialisation sécurisée des identifiants. | E65: Une procédure sécurisée de réinitialisation des identifiants existe-t-elle ? | F65: NON | G65: Documentation technique des interfaces d’intégration | H65: Exposition aux vulnérabilités non patchées | I65: Moyenne | J65: Désorganisation des workflows métier par intégration défaillante des systèmes. | K65: Auditer régulièrement les configurations des équipements IoT pour prévenir les compromissions.
D66: Contrôler des logs de connexion avec adresses IP et horodatages. | E66: Les logs de connexion incluent-ils adresses IP et horodatages ? | F66: PAS | G66: Procédures de suppression sécurisée des données obsolètes | H66: Journalisation incomplète des modifications | I66: Moyenne | J66: Augmentation des erreurs de saisie manuelle par absence de contrôles automatisés. | K66: Formaliser une politique de gestion des journaux d'activité conforme aux exigences réglementaires.
C67: Vérifier qu’un mot de passe est associé à l'identifiant | D67: Vérifier que chaque identifiant est associé à un mot de passe unique. | E67: Chaque identifiant a-t-il un mot de passe unique ? | F67: OUI | G67: Rapports de performance de l’équipe de maintenance | H67: Défaut de détection des changements non autorisés | I67: Moyenne | J67: Fragilisation de la position concurrentielle par retard technologique. | K67: Implémenter des contrôles de validation des entrées utilisateur pour prévenir les injections SQL.
D68: Confirmer l’application d’une politique de complexité des mots de passe (ex : 12 caractères, majuscules, chiffres). | E68: La politique impose-t-elle 12 caractères avec majuscules et chiffres ? | F68: OUI | G68: Procédures de recrutement et formation des équipes IT | H68: Absence de revue des configurations | I68: Moyenne | J68: Incapacité à répondre aux attentes des utilisateurs finaux par rigidité des processus. | K68: Réaliser des audits de conformité aux normes sectorielles (PCI DSS, HIPAA, etc.).
D69: Analyser des logs de connexion pour détecter des mots de passe faibles. | E69: Les logs de connexion révèlent-ils des mots de passe faibles ? | F69: NON | G69: Retours d’expérience du club utilisateurs | H69: Contrôles automatisés inefficaces | I69: Moyenne | J69: Détérioration de la coordination entre équipes IT et métier par communication inefficace. | K69: Instaurer des mécanismes de surveillance des activités des robots logiciels (RPA).
D70: Tester la réinitialisation forcée après 90 jours. | E70: La réinitialisation forcée a-t-elle lieu après 90 jours ? | F70: OUI | G70: Procédures de gestion des mises à jour logicielles | H70: Défaut d'alerte sur les anomalies | I70: Moyenne | J70: Exposition à des sanctions pour non-respect des clauses contractuelles avec les éditeurs. | K70: Documenter les procédures de gestion des certificats SSL/TLS pour éviter leur expiration.
D71: Identifier des alertes en cas de tentative de réutilisation d’un ancien mot de passe. | E71: Des alertes signalent-elles la réutilisation d'anciens mots de passe ? | F71: OUI | G71: Rapports d’évaluation de la conformité RGPD/ISO | H71: Absence de suivi des indicateurs clés | I71: Moyenne | J71: Perte de données opérationnelles par corruption ou suppression accidentelle. | K71: Mettre en place des contrôles d'accès contextuels pour les applications métiers sensibles.
C72: S’assurer que les tentatives de connexions infructueuses à l'application sont suivies | D72: Vérifier des logs de tentatives infructueuses sur 30 jours. | E72: Les tentatives infructueuses sur 30 jours sont-elles tracées ? | F72: NON | G72: Procédures de gestion des accès aux bibliothèques logicielles | H72: Reporting incomplet ou erroné | I72: Moyenne | J72: Augmentation des vulnérabilités réseau par configuration inadéquate. | K72: Auditer les configurations des systèmes de virtualisation pour garantir leur isolation.
D73: Confirmer la présence d’un système de verrouillage après 5 échecs. | E73: Le système se verrouille-t-il après 5 échecs ? | F73: PAS | G73: Logs de consultation de la documentation par les utilisateurs | H73: Décisions basées sur des informations obsolètes | I73: Moyenne | J73: Incapacité à anticiper les besoins futurs par planification stratégique absente. | K73: Implémenter des contrôles de sécurité physique pour les supports de sauvegarde hors site.
D74: Analyser des alertes automatiques envoyées à l’administrateur. | E74: Des alertes automatiques sont-elles envoyées à l'administrateur ? | F74: OUI | G74: Procédures de validation hiérarchique des profils utilisateurs | H74: Distribution non sécurisée des états | I74: Elevée | J74: Dégradation de la qualité des services supportés par des outils obsolètes. | K74: Réaliser des tests de résistance aux attaques zero-day via des simulations réalistes.
D75: Tester la réinitialisation manuelle par l’administrateur. | E75: La réinitialisation manuelle par l'admin est-elle fonctionnelle ? | F75: OUI | G75: Rapports d’audit semestriel des droits d’accès | H75: Accès non contrôlé aux informations sensibles | I75: Faible | J75: Risque de non-atteinte des objectifs de transformation numérique. | K75: Instaurer une politique de gestion des données archivées incluant leur classification et chiffrement.
D76: Identifier des procédures de suivi des tentatives suspectes. | E76: Une procédure de suivi des tentatives suspectes existe-t-elle ? | F76: NON | G76: Procédures de gestion des alertes de sécurité automatiques | H76: Validation manquante des outputs | I76: Moyenne | J76: Exposition à des litiges liés à la propriété intellectuelle des développements logiciels. | K76: Documenter les procédures de réponse aux fuites de données personnelles conformes au RGPD.
C77: S’assurer que l'accès aux données et aux transactions de l’application est géré | D77: Vérifier des logs d’accès aux transactions sensibles sur 30 jours. | E77: Les logs d'accès aux transactions sensibles sur 30 jours existent-ils ? | F77: OUI | G77: Documents de référence des règles de gestion des données | H77: Erreurs de traitement non détectées | I77: Moyenne | J77: Perte de flexibilité opérationnelle par architecture technique rigide. | K77: Mettre en œuvre des contrôles d'intégrité des métadonnées associées aux données critiques.
D78: Confirmer la présence d’un système de chiffrement des données en transit. | E78: Les données en transit sont-elles chiffrées ? | F78: OUI | G78: Procédures de contrôle qualité des corrections de données | H78: Incohérences dans les codifications | I78: Moyenne | J78: Détérioration de la collaboration interne par outils collaboratifs inadaptés. | K78: Auditer les configurations des systèmes de gestion des identités (IAM) pour limiter les erreurs.
D79: Analyser des procédures de validation des accès par un supérieur hiérarchique. | E79: Un supérieur hiérarchique valide-t-il les accès sensibles ? | F79: NON | G79: Rapports de tests d’interopérabilité avec les systèmes existants | H79: Défaut d'application des règles métier | I79: Moyenne | J79: Augmentation des délais de livraison des projets IT par mauvaise gestion des ressources. | K79: Implémenter des mécanismes de détection des comportements anormaux des utilisateurs.
D80: Tester le rejet d’accès hors profil via un compte test. | E80: Un compte test confirme-t-il le rejet d'accès hors profil ? | F80: PAS | G80: Procédures de gestion des environnements (dev/test/prod) | H80: Défaut de cohérence inter-modules | I80: Moyenne | J80: Incapacité à garantir l’authenticité des transactions électroniques. | K80: Réaliser des revues architecturales pour s'assurer de la résilience des infrastructures hybrides.
D81: Identifier des alertes en cas d’accès hors heures ouvrables. | E81: Des alertes existent-elles pour les accès hors heures ouvrables ? | F81: OUI | G81: Rapports de tests de modularité de l’application | H81: Interfaces non sécurisées | I81: Moyenne | J81: Fragilisation de la chaîne d’approvisionnement IT par dépendance à un seul fournisseur. | K81: Instaurer des contrôles d'accès temporaires avec expiration automatique pour les prestataires.
C82: Vérifier l’existence de pistes d’audit sur le système d’administration de l’application | D82: Vérifier des logs d’audit des actions administratives sur 90 jours. | E82: Les logs d'actions administratives sur 90 jours sont-ils disponibles ? | F82: OUI | G82: Procédures de gestion des versions logicielles | H82: Défaut de validation des développements | I82: Moyenne | J82: Détérioration de l’image de marque suite à des incidents de sécurité médiatisés. | K82: Documenter les procédures de gestion des risques liés à l'utilisation de l'Internet des objets (IoT).
D83: Confirmer la présence d’un système de journalisation centralisé. | E83: Un système de journalisation centralisé est-il en place ? | F83: NON | G83: Rapports de suivi des demandes de maintenance utilisateur | H83: Code non conforme aux standards | I83: Moyenne | J83: Non-respect des engagements environnementaux liés à la gestion des infrastructures IT. | K83: Mettre en place des solutions de chiffrement homomorphique pour les données sensibles en traitement.
D84: Analyser des alertes automatiques pour les actions critiques (ex : suppression de données). | E84: Des alertes automatiques pour actions critiques existent-elles ? | F84: OUI | G84: Procédures de gestion des clés SSH/API | H84: Absence de revue par les pairs | I84: Moyenne | J84: Augmentation des coûts de licence par utilisation non optimisée des logiciels. | K84: Auditer les configurations des passerelles API pour prévenir les exploitations malveillantes.
D85: Tester la traçabilité des actions via un compte administrateur. | E85: La traçabilité des actions via un compte admin est-elle vérifiable ? | F85: OUI | G85: Rapports de performance des travaux batch | H85: Déploiement non contrôlé en production | I85: Moyenne | J85: Incapacité à maintenir la cohérence des données lors de fusions ou acquisitions. | K85: Implémenter des contrôles de sécurité dans les pipelines CI/CD pour les déploiements automatisés.
D86: Identifier des procédures de revue trimestrielle des logs. | E86: Une revue trimestrielle des logs est-elle prévue ? | F86: NON | G86: Procédures de gestion des données rejetées | H86: Accès non autorisé aux environnements critiques | I86: Moyenne | J86: Dégradation de l’agilité organisationnelle par lenteur des processus IT. | K86: Réaliser des tests de charge pour valider la scalabilité des applications critiques.
C87: Vérifier que tous les documents servant de base à la saisie sont pris en compte | D87: Vérifier des exemples de documents sources (ex : factures, bons de commande). | E87: Des exemples de documents sources (factures, bons de commande) existent-ils ? | F87: PAS | G87: Rapports de tests de compatibilité ascendante/descendante | H87: Défaut de séparation des environnements | I87: Faible | J87: Exposition à des erreurs de configuration entraînant des pannes critiques. | K87: Instaurer une politique de gestion des secrets applicatifs (mots de passe, clés API).
D88: Confirmer la présence d’un workflow de validation des documents. | E88: Un workflow de validation des documents est-il établi ? | F88: OUI | G88: Procédures de gestion des formations utilisateurs | H88: Gestion hasardeuse des accès privilégiés | I88: Moyenne | J88: Perte de compétitivité sur le marché par innovation technologique insuffisante. | K88: Documenter les procédures de gestion des incidents liés aux systèmes de paiement électronique.
D89: Analyser des logs de saisie pour corréler avec les documents sources. | E89: Les logs de saisie correspondent-ils aux documents sources ? | F89: OUI | G89: Rapports de suivi des indicateurs de satisfaction utilisateur | H89: Compromission des clés d'accès | I89: Moyenne | J89: Détérioration de la satisfaction client due à des services IT peu fiables. | K89: Mettre en œuvre des contrôles d'accès physiques et logiques pour les salles de contrôle.
D90: Tester la reprise des données après une erreur de saisie. | E90: La reprise des données après erreur de saisie est-elle possible ? | F90: NON | G90: Procédures de gestion des risques résiduels | H90: Défaut de rotation des identifiants | I90: Elevée | J90: Augmentation des risques liés à l’externalisation non supervisée. | K90: Auditer les configurations des systèmes SCADA/OT pour limiter les risques cyberindustriels.
D91: Identifier des procédures de contrôle qualité des données saisies. | E91: Des procédures de contrôle qualité des données saisies existent-elles ? | F91: OUI | G91: Rapports de revue trimestrielle des logs d’activité | H91: Compétences insuffisantes des équipes | I91: Moyenne | J91: Incapacité à aligner les investissements IT sur les priorités métier. | K91: Implémenter des mécanismes de protection contre les attaques par ingénierie sociale.
C92: S’assurer que les facilités de saisie, l’ergonomie de la saisie, les messages écrans et les contrôles sont mis en œuvre | D92: Vérifier des captures d’écran des interfaces de saisie. | E92: Des captures d'écran des interfaces de saisie sont-elles disponibles ? | F92: OUI | G92: Procédures de gestion des accès hors heures ouvrables | H92: Défaut de plan de continuité d'activité | I92: Elevée | J92: Fragilisation de la conformité aux normes internationales par pratiques obsolètes. | K92: Réaliser des revues de conformité des contrats avec les fournisseurs de services managés.
D93: Confirmer la présence de messages d’erreur clairs et explicites. | E93: Les messages d'erreur sont-ils clairs et explicites ? | F93: NON | G93: Rapports de tests de stabilité des technologies utilisées | H93: Procédures de secours non opérationnelles | I93: Elevée | J93: Détérioration de la capacité à auditer les processus internes efficacement. | K93: Instaurer des contrôles de sécurité pour les environnements DevOps et les outils low-code.
D94: Analyser des tests utilisateurs pour évaluer l’ergonomie. | E94: Des tests utilisateurs évaluent-ils l'ergonomie ? | F94: PAS | G94: Procédures de gestion des budgets d’extension d’infrastructure | H94: Temps de restauration excessif | I94: Moyenne | J94: Exposition à des interruptions d’activité par absence de redondance des systèmes. | K94: Documenter les procédures de gestion des risques liés à l'adoption de la blockchain.
D95: Tester la validation automatique des champs obligatoires. | E95: La validation automatique des champs obligatoires fonctionne-t-elle ? | F95: OUI | G95: Rapports de tests de réversibilité en cas d’échec de déploiement | H95: Perte de disponibilité du système | I95: Elevée | J95: Perte de données stratégiques par absence de politiques de sauvegarde robustes. | K95: Mettre en place des mécanismes de validation des données en temps réel pour les transactions.
D96: Identifier des procédures de mise à jour des interfaces. | E96: Des procédures de mise à jour des interfaces existent-elles ? | F96: OUI | G96: Procédures de gestion des alertes de tentative d’accès non autorisé | H96: Défaut de tests de reprise | I96: Moyenne | J96: Augmentation des conflits entre équipes par manque de clarté des responsabilités. | K96: Auditer les configurations des systèmes de gestion de contenu (CMS) pour prévenir les vulnérabilités.
C97: S’assurer que les contrôles de validation des « brouillards » de saisie pour validation par réconciliation existent | D97: Vérifier des exemples de brouillards de saisie validés. | E97: Des brouillards de saisie validés sont-ils disponibles ? | F97: NON | G97: Rapports de suivi des indicateurs de productivité des processus | H97: Inadéquation des sauvegardes | I97: Moyenne | J97: Incapacité à répondre aux audits réglementaires faute de documentation adéquate. | K97: Implémenter des contrôles d'accès basés sur l'attestation pour les appareils connectés.
D98: Confirmer la présence d’un workflow de réconciliation. | E98: Un workflow de réconciliation est-il en place ? | F98: OUI | G98: Procédures de gestion des mises à jour des spécifications fonctionnelles | H98: Exposition aux sinistres majeurs | I98: Elevée | J98: Dégradation de la qualité des décisions managériales par données incomplètes. | K98: Réaliser des tests de résilience des infrastructures face aux pannes matérielles.
D99: Analyser des logs de validation pour corréler avec les brouillards. | E99: Les logs de validation correspondent-ils aux brouillards ? | F99: OUI | G99: Rapports de tests de performance des développements spécifiques | H99: Non-respect des SLA | I99: Elevée | J99: Risque de non-conformité aux exigences sectorielles spécifiques. | K99: Instaurer une politique de gestion des correctifs critiques avec des délais contraignants.
D100: Tester la détection d’erreurs de saisie via des contrôles automatiques. | E100: Les contrôles automatiques détectent-ils les erreurs de saisie ? | F100: NON | G100: Procédures de gestion des partenariats avec les clubs utilisateurs | H100: Dégradation de la qualité de service | I100: Elevée | J100: Détérioration de la collaboration avec les partenaires externes par systèmes incompatibles. | K100: Documenter les procédures de gestion des risques liés aux technologies émergentes (IA, 5G).
...

Sheet COSO
A1: Domaines | B1: Points de Contrôle | C1: Objectifs de Contrôle | D1: Critère d’Évaluation
A2: Environnement de Contrôle | B2: Engagement envers l’intégrité et les valeurs éthiques | C2: S’assurer que l’organisation dispose d’une charte éthique formelle. | D2: La charte éthique est documentée et accessible à tous les employés.
D3: La charte éthique couvre les pratiques professionnelles et les interactions au sein de l’organisation.
D4: La charte éthique est régulièrement mise à jour pour refléter les nouvelles normes et réglementations.
D5: La charte éthique est communiquée à tous les nouveaux employés lors de leur intégration.
D6: La charte éthique est soutenue par la direction et le Conseil.
C7: Vérifier que des mécanismes existent pour garantir le respect de la charte éthique. | D7: Des mécanismes de surveillance sont en place pour détecter les violations de la charte éthique.
D8: Des procédures disciplinaires sont définies pour les violations de la charte éthique.
D9: Des rapports réguliers sont produits sur les violations de la charte éthique.
D10: Des formations sur la charte éthique sont dispensées régulièrement.
D11: Un système de signalement anonyme est disponible pour les violations éthiques.
C12: Mettre en place des actions de sensibilisation (formations régulières). | D12: Des formations sur l’éthique sont planifiées et dispensées annuellement.
D13: Les formations incluent des études de cas et des exemples pratiques.
D14: Les employés sont tenus de participer aux formations sur l’éthique.
D15: Les formations sont adaptées aux différents niveaux hiérarchiques de l’organisation.
D16: Des évaluations post-formation sont réalisées pour mesurer l’efficacité des sessions.
C17: Gérer les violations éthiques de manière proactive. | D17: Un comité d’éthique est en place pour traiter les violations.
D18: Des procédures claires sont définies pour signaler et traiter les violations.
D19: Les violations sont documentées et suivies jusqu’à leur résolution.
D20: Des sanctions sont appliquées en cas de violation de la charte éthique.
D21: Des rapports annuels sur les violations éthiques sont présentés au Conseil.
C22: Assurer que la charte éthique est régulièrement mise à jour pour refléter les nouvelles normes. | D22: La charte éthique est révisée au moins une fois par an.
D23: Les mises à jour de la charte éthique sont communiquées à tous les employés.
D24: Les nouvelles normes et réglementations sont intégrées dans la charte éthique.
D25: La direction et le Conseil approuvent les mises à jour de la charte éthique.
D26: Des retours d’expérience des employés sont pris en compte lors des mises à jour de la charte éthique.
B27: Le Conseil fait preuve d’indépendance vis-à-vis du management | C27: S’assurer que le Conseil est composé de membres indépendants du management. | D27: Le Conseil est composé d’au moins 50 % de membres indépendants.
D28: Les membres indépendants du Conseil ne détiennent pas de fonctions opérationnelles dans l’organisation.
D29: Les membres indépendants du Conseil sont nommés par un comité de nomination indépendant.
D30: Les membres indépendants du Conseil participent activement aux réunions et aux décisions.
D31: Les membres indépendants du Conseil sont évalués régulièrement pour leur performance et leur indépendance.
C32: Vérifier que le Conseil dispose des ressources et des informations nécessaires. | D32: Le Conseil a accès à des rapports détaillés sur le contrôle interne.
D33: Le Conseil dispose d’un budget dédié pour ses activités de surveillance.
D34: Le Conseil reçoit des informations en temps utile pour prendre des décisions éclairées.
D35: Le Conseil a accès à des experts externes pour l’aider dans ses évaluations.
D36: Le Conseil dispose d’un système de gestion de l’information pour organiser et suivre les données.
C37: Impliquer le Conseil dans l’évaluation des audits internes. | D37: Le Conseil reçoit des rapports réguliers sur les résultats des audits internes.
D38: Le Conseil participe à la définition des objectifs des audits internes.
D39: Le Conseil examine les recommandations des audits internes et suit leur mise en œuvre.
D40: Le Conseil évalue l’efficacité des audits internes.
D41: Le Conseil reçoit des rapports sur les actions correctives mises en place suite aux audits internes.
C42: Vérifier que le Conseil joue un rôle actif dans la définition des objectifs de contrôle. | D42: Le Conseil participe à la définition des objectifs stratégiques de contrôle interne.
D43: Le Conseil valide les critères de performance du contrôle interne.
D44: Le Conseil examine les résultats des évaluations de contrôle interne.
D45: Le Conseil propose des améliorations pour le système de contrôle interne.
D46: Le Conseil suit la mise en œuvre des recommandations issues des évaluations de contrôle interne.
C47: Assurer que le Conseil évalue régulièrement la performance des responsables du contrôle interne. | D47: Le Conseil reçoit des rapports sur la performance des responsables du contrôle interne.
D48: Le Conseil évalue l’indépendance et l’objectivité des responsables du contrôle interne.
D49: Le Conseil examine les actions correctives proposées par les responsables du contrôle interne.
D50: Le Conseil suit la mise en œuvre des recommandations des responsables du contrôle interne.
D51: Le Conseil évalue l’efficacité des actions mises en place par les responsables du contrôle interne.
B52: Structures, autorités et responsabilités | C52: S’assurer que la structure organisationnelle est clairement définie. | D52: La structure organisationnelle est documentée et accessible à tous les employés.
D53: Les rôles et responsabilités sont clairement définis pour chaque poste.
D54: Les rattachements hiérarchiques sont clairement indiqués dans la structure organisationnelle.
D55: La structure organisationnelle est régulièrement mise à jour pour refléter les changements internes.
D56: La structure organisationnelle est approuvée par le Conseil.
C57: Vérifier que les responsabilités et les pouvoirs sont attribués de manière appropriée. | D57: Les responsabilités sont attribuées en fonction des compétences et des objectifs stratégiques.
D58: Les pouvoirs décisionnels sont clairement définis pour chaque poste.
D59: Les responsabilités et les pouvoirs sont documentés et accessibles pour consultation.
D60: Les employés comprennent leurs responsabilités et leurs pouvoirs.
D61: Les responsabilités et les pouvoirs sont régulièrement revus pour s’assurer de leur pertinence.
C62: Mettre à jour régulièrement la structure organisationnelle. | D62: La structure organisationnelle est révisée au moins une fois par an.
D63: Les changements dans la structure organisationnelle sont communiqués à tous les employés.
D64: Les mises à jour de la structure organisationnelle sont approuvées par le Conseil.
D65: Les employés sont informés des changements dans leurs rôles et responsabilités.
D66: Les mises à jour de la structure organisationnelle sont documentées et archivées.
C67: Vérifier que le management reçoit l’approbation du Conseil pour les modifications de la structure. | D67: Le Conseil est informé des modifications proposées à la structure organisationnelle.
D68: Le Conseil approuve les modifications de la structure organisationnelle avant leur mise en œuvre.
D69: Les modifications de la structure organisationnelle sont documentées et archivées.
D70: Le Conseil reçoit des rapports sur l’impact des modifications de la structure organisationnelle.
D71: Le Conseil évalue l’efficacité des modifications de la structure organisationnelle.
C72: S’assurer que des mécanismes de communication claire de la structure organisationnelle sont en place. | D72: Des outils de communication (intranet, réunions, etc.) sont utilisés pour partager la structure organisationnelle.
D73: Les employés ont accès à des documents détaillés sur la structure organisationnelle.
D74: Des sessions de formation sont organisées pour expliquer la structure organisationnelle.
D75: Les nouveaux employés reçoivent une explication détaillée de la structure organisationnelle lors de leur intégration.
D76: Des mécanismes de feedback sont en place pour recueillir les commentaires des employés sur la structure organisationnelle.
B77: Compétences des individus | C77: S’assurer que l’organisation dispose de processus clairs pour attirer des talents qualifiés. | D77: Des processus de recrutement formalisés sont en place pour attirer des talents qualifiés.
D78: Les offres d’emploi sont claires et détaillées, reflétant les compétences requises.
D79: Des partenariats avec des institutions éducatives ou des réseaux professionnels sont établis pour attirer des talents.
D80: Les processus de recrutement sont régulièrement évalués et améliorés.
D81: Les nouveaux employés sont évalués pour s’assurer qu’ils répondent aux attentes de l’organisation.
C82: Mettre en place des programmes de formation continue. | D82: Des programmes de formation continue sont disponibles pour tous les employés.
D83: Les formations sont adaptées aux besoins spécifiques des employés et de l’organisation.
D84: Les employés sont encouragés à participer aux formations continues.
D85: Les formations sont évaluées pour mesurer leur efficacité.
D86: Des plans de développement individuel sont établis pour chaque employé.
C87: Mettre en place des mécanismes de fidélisation des talents. | D87: Des parcours de carrière clairs sont proposés aux employés.
D88: Des avantages compétitifs (salaires, avantages sociaux, etc.) sont offerts pour fidéliser les talents.
D89: Des opportunités de développement personnel sont proposées aux employés.
D90: Des programmes de reconnaissance des performances sont en place.
D91: Des enquêtes de satisfaction sont réalisées pour recueillir les feedbacks des employés.
C92: Évaluer régulièrement la performance des collaborateurs. | D92: Des évaluations de performance sont réalisées au moins une fois par an.
D93: Les évaluations de performance incluent des retours constructifs.
D94: Les évaluations de performance sont alignées sur les objectifs stratégiques de l’organisation.
D95: Les employés ont accès à des plans d’amélioration après les évaluations de performance.
D96: Les évaluations de performance sont documentées et archivées.
C97: Assurer que les processus de gestion des talents sont alignés avec les objectifs stratégiques. | D97: Les processus de gestion des talents sont alignés sur les objectifs stratégiques de l’organisation.
D98: Les plans de développement des talents sont régulièrement revus pour s’assurer de leur alignement avec les objectifs stratégiques.
D99: Les responsables des ressources humaines participent à la définition des objectifs stratégiques.
D100: Les indicateurs de performance des talents sont alignés sur les objectifs stratégiques.
...

Sheet 4.1 Applications en service
A1: Points de contrôles | B1: Objectifs de contrôle | C1: Critères d'évaluation | D1: Questions d'évaluation | E1: Réponses | F1: Documents requis | G1: Risques | H1: Criticités | I1: Conséquences | J1: Recommandations
A2: Organisation | B2: S’assurer de l’existence d'un comité informatique | C2: Vérifier l’existence d’un organigramme officiel du comité signé par la direction. | D2: L'organigramme du comité est-il signé par la direction ? | E2: OUI | F2: Organigramme de l’entité | G2: Absence de gouvernance clairement définie | H2: Moyenne | I2: Non-conformité aux réglementations en vigueur entraînant des sanctions légales. | J2: Élaborer un cadre de gouvernance aligné sur COBIT ou ISO 27001 en formalisant les rôles et responsabilités.
C3: Confirmer la présence d’au moins 3 procès-verbaux de réunion datés des 6 derniers mois. | D3: Trois procès-verbaux de réunion existent-ils pour les 6 derniers mois ? | E3: OUI | F3: Organigramme fonctionnel de la DSI | G3: Documentation insuffisante des décisions stratégiques | H3: Elevée | I3: Détérioration de la confiance des parties prenantes due à l'absence de traçabilité des décisions. | J3: Documenter et diffuser les politiques de sécurité et les procédures internes pour garantir leur accessibilité.
C4: Analyser la composition du comité (CV/certifications des membres). | D4: Les CV et certifications des membres du comité sont-ils disponibles ? | E4: NON | F4: Procès-verbaux des réunions du comité | G4: Incompétence des membres du comité de pilotage | H4: Elevée | I4: Augmentation des erreurs opérationnelles par manque de directives claires. | J4: Mettre en place une formation continue sur les enjeux de sécurité et la conformité réglementaire pour les employés.
C5: Identifier un mandat écrit précisant les missions et la fréquence des réunions. | D5: Un mandat écrit définit-il les missions et la fréquence des réunions ? | E5: PAS | F5: Fiches de postes de la DSI | G5: Définition floue des responsabilités du comité | H5: Faible | I5: Vulnérabilité accrue aux cyberattaques en raison de politiques obsolètes. | J5: Implémenter des contrôles d'accès stricts basés sur le principe du moindre privilège et revoir périodiquement les habilitations.
C6: Contrôler la diffusion des décisions du comité via des emails ou documents internes. | D6: Les décisions du comité sont-elles diffusées par email ou documents internes ? | E6: OUI | F6: Politique des Applications approuvée par la direction | G6: Non-diffusion des orientations stratégiques aux équipes | H6: Elevée | I6: Inefficacité des contrôles internes causant des pertes financières. | J6: Concevoir et tester régulièrement un plan de continuité d'activité (PCA) et un plan de reprise d'activité (PRA).
B7: S’assurer de l’existence d'une politique relative aux applications | C7: Vérifier la présence d’un document intitulé "Politique des Applications" approuvé par la direction. | D7: La "Politique des Applications" est-elle approuvée par la direction ? | E7: OUI | F7: Accusés de réception des employés pour la politique | G7: Politique de sécurité non formalisée | H7: Moyenne | I7: Exposition à des litiges juridiques faute de documentation appropriée. | J7: Instaurer une matrice des risques mise à jour annuellement et intégrée aux processus décisionnels.
C8: Confirmer la date de la dernière mise à jour (moins de 12 mois). | D8: La dernière mise à jour date-t-elle de moins de 12 mois ? | E8: NON | F8: Plan de formation annuel lié à la politique | G8: Non-conformité réglementaire | H8: Elevée | I8: Dysfonctionnements dans la gestion des accès menant à des fuites de données sensibles. | J8: Automatiser les contrôles de validation des données critiques pour réduire les erreurs manuelles.
C9: Analyser les mentions de conformité RGPD/ISO dans le document. | D9: Le document mentionne-t-il la conformité RGPD/ISO ? | E9: PAS | F9: Matrice des autorisations/droits d’accès | G9: Manque de sensibilisation des employés aux politiques | H9: Moyenne | I9: Interruptions prolongées des activités en cas de sinistre non anticipé. | J9: Déployer des outils de surveillance en temps réel pour détecter les anomalies et les activités suspectes.
C10: Vérifier la diffusion de la politique aux employés (accusés de réception signés). | D10: Les employés ont-ils signé des accusés de réception pour la politique ? | E10: OUI | F10: Liste des 100 derniers incidents du domaine d’audit | G10: Absence de formation continue sur les enjeux de sécurité | H10: Moyenne | I10: Dégradation de la performance des systèmes due à une maintenance inadéquate. | J10: Réaliser des audits réguliers des configurations des systèmes et des droits d'accès privilégiés.
C11: Identifier un plan de formation annuel lié à cette politique. | D11: Un plan de formation annuel lié à cette politique existe-t-il ? | E11: NON | F11: Rapport d’analyse des risques récent (moins de 12 mois) | G11: Définition imprécise des rôles utilisateurs | H11: Elevée | I11: Non-respect des engagements contractuels envers les clients ou partenaires. | J11: Mettre en œuvre des mécanismes de chiffrement des données en transit et au repos conformes aux normes ISO 27001.
B12: S’assurer que les rôle et responsabilités des utilisateurs sont bien définis | C12: Contrôler l’existence de fiches de poste pour chaque profil utilisateur. | D12: Des fiches de poste sont-elles disponibles pour chaque profil utilisateur ? | E12: OUI | F12: Document de classification des données (public, interne, confidentiel) | G12: Violation des engagements contractuels | H12: Moyenne | I12: Augmentation des coûts opérationnels liés à des processus inefficients. | J12: Séparer les environnements de développement, de test et de production pour limiter les risques de corruption.
C13: Vérifier la signature des utilisateurs sur des chartes d’utilisation. | D13: Les utilisateurs ont-ils signé des chartes d'utilisation ? | E13: NON | F13: Manuel d’administration des applications | G13: Droits d'accès obsolètes ou inadaptées | H13: Moyenne | I13: Perte de données critiques par absence de sauvegardes fiables. | J13: Établir des procédures de gestion des incidents incluant une analyse post-mortem et des plans d'action correctifs.
C14: Confirmer la mise à jour des habilitations dans un tableau de gestion des accès. | D14: Le tableau de gestion des accès est-il à jour ? | E14: OUI | F14: Logs d’accès aux données sensibles sur 30 jours | G14: Détournement de privilèges | H14: Moyenne | I14: Retards dans les prises de décision faute d’informations actualisées. | J14: Valider l'exhaustivité et l'intégrité des sauvegardes via des tests de restauration périodiques.
C15: Analyser des logs d’accès pour corréler avec les rôles déclarés. | D15: Les logs d'accès correspondent-ils aux rôles déclarés ? | E15: OUI | F15: Procédures écrites pour les processus critiques | G15: Absence de revue périodique des habilitations | H15: Moyenne | I15: Compromission de l’intégrité des données financières ou métiers. | J15: Créer un comité de pilotage IT pour superviser l'alignement stratégique des projets avec les objectifs métiers.
C16: Identifier des procédures de révision trimestrielle des droits. | D16: Une procédure de révision trimestrielle des droits est-elle en place ? | E16: NON | F16: Comptes rendus mensuels de l’application | G16: Fraude interne via l'exploitation de droits excessifs | H16: Moyenne | I16: Risque accru de fraude interne en l’absence de séparation des tâches. | J16: Utiliser des outils de gestion des identités et des accès (IAM) pour centraliser et auditer les permissions.
B17: S’assurer qu’une analyse des risques a été réalisée | C17: Vérifier un rapport d’analyse des risques daté de moins de 12 mois. | D17: Un rapport d'analyse des risques de moins de 12 mois existe-t-il ? | E17: OUI | F17: Guide utilisateur et manuel de procédures | G17: Évaluation des risques non actualisée | H17: Elevée | I17: Détérioration de la qualité des services IT impactant la satisfaction client. | J17: Réaliser des tests de pénétration et des audits de code pour identifier les vulnérabilités applicatives.
C18: Confirmer l’utilisation d’une méthodologie reconnue (ex : EBIOS, OCTAVE). | D18: La méthodologie utilisée est-elle reconnue (EBIOS, OCTAVE) ? | E18: OUI | F18: Matrice des tâches et fonctions incompatibles | G18: Utilisation de méthodologies obsolètes | H18: Faible | I18: Exposition à des amendes réglementaires pour non-conformité RGPD. | J18: Documenter les flux de données et les interfaces entre systèmes pour garantir la traçabilité des échanges.
C19: Analyser la liste des risques identifiés (au moins 10 risques critiques). | D19: Au moins 10 risques critiques sont-ils identifiés ? | E19: NON | F19: Contrat de maintenance ou d’assistance | G19: Sous-estimation des menaces critiques | H19: Faible | I19: Interruptions fréquentes des services en production par manque de redondance. | J19: Adopter une politique de gestion des correctifs avec des délais stricts pour les mises à jour critiques.
C20: Identifier un plan d’action avec des responsables et des échéances. | D20: Un plan d'action avec responsables et échéances est-il établi ? | E20: PAS | F20: Plan de continuité des activités (PCA) | G20: Absence de planification corrective | H20: Moyenne | I20: Difficultés à assurer la continuité des activités lors de crises majeures. | J20: Instaurer des contrôles d'intégrité des données lors des migrations ou des transferts inter-systèmes.
C21: Contrôler des preuves de mise en œuvre des actions (rapports de suivi). | D21: Des preuves de mise en œuvre des actions sont-elles disponibles ? | E21: OUI | F21: Plan de reprise d’activité (PRA) | G21: Contrôles inefficaces face aux risques identifiés | H21: Moyenne | I21: Dépendance excessive vis-à-vis de prestataires externes non supervisés. | J21: Mettre en place une journalisation centralisée et une analyse proactive des logs pour détecter les menaces.
B22: S’assurer que le prolongement de l'analyse de risque et de son expansion ont été réalisés | C22: Vérifier des mises à jour de l’analyse des risques (au moins 2 révisions annuelles). | D22: L'analyse des risques a-t-elle été mise à jour deux fois dans l'année ? | E22: OUI | F22: Rapports de traitements des incidents | G22: Ignorance des nouvelles vulnérabilités | H22: Elevée | I22: Altération de la réputation de l’organisation suite à des incidents récurrents. | J22: Élaborer une charte de sécurité informatique incluant des clauses contractuelles avec les fournisseurs externes.
C23: Confirmer l’intégration des nouveaux risques (ex : cybermenaces, RGPD). | D23: Les nouveaux risques (cybermenaces, RGPD) sont-ils intégrés ? | E23: NON | F23: Inventaire des licences | G23: Défaut de reporting aux instances décisionnelles | H23: Moyenne | I23: Inefficacité des plans de reprise après sinistre prolongeant les temps d’arrêt. | J23: Concevoir des tableaux de bord de performance alignés sur les KPI métiers pour mesurer l'efficacité des SI.
C24: Analyser des indicateurs de suivi des risques (tableaux de bord). | D24: Des indicateurs de suivi des risques existent-ils ? | E24: PAS | F24: Bilan de qualité logiciel | G24: Culture du risque insuffisante dans l'organisation | H24: Moyenne | I24: Augmentation des vulnérabilités logicielles par absence de mises à jour. | J24: Sensibiliser les utilisateurs aux risques de phishing et d'ingénierie sociale via des simulations régulières.
C25: Identifier des procédures de reporting aux instances dirigeantes. | D25: Des procédures de reporting aux instances dirigeantes sont-elles définies ? | E25: OUI | F25: Bilan de satisfaction des utilisateurs | G25: Classification inappropriée des données sensibles | H25: Faible | I25: Désorganisation des équipes IT faute de procédures standardisées. | J25: Auditer régulièrement les configurations des pare-feux et des équipements réseau pour prévenir les attaques.
C26: Contrôler des preuves de sensibilisation des équipes aux risques majeurs. | D26: Les équipes sont-elles sensibilisées aux risques majeurs ? | E26: OUI | F26: Schéma d’interaction des applications métiers | G26: Exposition de données critiques | H26: Moyenne | I26: Non-atteinte des objectifs stratégiques en raison d’un mauvais alignement IT-métier. | J26: Intégrer des contrôles de conformité RGPD dans les processus de traitement des données personnelles.
B27: S’assurer que l’analyse et évaluation du niveau de sensibilité a été réalisée | C27: Vérifier un document classifiant les données par niveau de sensibilité (public, interne, confidentiel). | D27: Un document classe-t-il les données (public, interne, confidentiel) ? | E27: NON | F27: Diagramme de flux de données des applications | G27: Surveillance inadéquate des accès privilégiés | H27: Moyenne | I27: Perte de compétitivité due à des technologies obsolètes ou sous-utilisées. | J27: Définir une stratégie de gestion des actifs numériques incluant leur classification et leur cycle de vie.
C28: Confirmer la mise à jour de la classification (moins de 6 mois). | D28: La classification a-t-elle été mise à jour dans les 6 mois ? | E28: OUI | F28: Procédures de gestion des changements | G28: Protection insuffisante des actifs informationnels | H28: Elevée | I28: Erreurs humaines accrues par manque de formation ou de documentation. | J28: Mettre en œuvre des contrôles d'accès physique aux salles serveurs et aux centres de données.
C29: Analyser des logs d’accès aux données sensibles sur 30 jours. | D29: Les logs d'accès aux données sensibles sur 30 jours sont-ils analysables ? | E29: OUI | F29: Logs de connexion avec adresses IP et horodatages | G29: Manque de formation sur la manipulation des données | H29: Moyenne | I29: Détection tardive des anomalies opérationnelles réduisant la réactivité. | J29: Réaliser des audits de sécurité des APIs pour prévenir les exploitations malveillantes.
C30: Identifier des procédures de protection spécifiques pour les données critiques. | D30: Des procédures spécifiques protègent-elles les données critiques ? | E30: NON | F30: Politique de sécurité des mots de passe | G30: Documentation technique obsolète | H30: Moyenne | I30: Fuite d’informations confidentielles par des contrôles d’accès laxistes. | J30: Standardiser les procédures de gestion des changements avec validation technique et métier préalable.
C31: Contrôler des preuves de formation des utilisateurs sur la classification. | D31: Les utilisateurs sont-ils formés sur la classification des données ? | E31: PAS | F31: Procédures de gestion des identifiants et mots de passe | G31: Procédures de secours non testées | H31: Moyenne | I31: Dégradation de la productivité des utilisateurs face à des outils inadaptés. | J31: Instaurer des revues indépendantes des architectures techniques pour garantir leur résilience.
B32: Vérifier l’existence d’un manuel d'administration de l'application | C32: Vérifier l’existence d’un manuel d’administration mis à jour (moins de 12 mois). | D32: Le manuel d'administration est-il à jour (moins de 12 mois) ? | E32: OUI | F32: Document de stratégie de migration des données | G32: Dépendance excessive au savoir-faire individuel | H32: Moyenne | I32: Difficultés à auditer les systèmes en raison d’une journalisation insuffisante. | J32: Adopter des contrats de service (SLA) clairs avec des pénalités en cas de non-respect des engagements.
C33: Confirmer la couverture des procédures clés (ex : sauvegarde, restauration). | D33: Les procédures clés (sauvegarde, restauration) sont-elles couvertes ? | E33: OUI | F33: Procédures de sauvegarde et restauration | G33: Absence de capitalisation des connaissances | H33: Moyenne | I33: Augmentation des coûts de conformité pour rattraper les lacunes identifiées. | J33: Utiliser des solutions de détection d'intrusion (IDS/IPS) pour surveiller les activités réseau anormales.
C34: Analyser des exemples de procédures détaillées (étapes, screenshots). | D34: Des procédures détaillées avec étapes et captures existent-elles ? | E34: NON | F34: Rapports de tests de restauration après sinistre | G34: Défaut de traçabilité des opérations sensibles | H34: Moyenne | I34: Risque de corruption des données lors de migrations non contrôlées. | J34: Documenter les dépendances critiques entre systèmes pour anticiper les impacts des pannes.
C35: Identifier des preuves d’utilisation du manuel (logs de consultation). | D35: Des logs de consultation du manuel sont-ils disponibles ? | E35: OUI | F35: Clauses de contrat SLA avec les fournisseurs | G35: Contrôles métier inefficaces | H35: Faible | I35: Incapacité à répondre aux audits externes faute de preuves tangibles. | J35: Mettre en place une politique de gestion des mots de passe exigeant une complexité et une rotation régulière.
C36: Contrôler des formations dédiées à l’équipe d’administration. | D36: L'équipe d'administration reçoit-elle des formations dédiées ? | E36: OUI | F36: Feuille de route technologique approuvée | G36: Non-respect des bonnes pratiques sectorielles | H36: Faible | I36: Fragilisation de la gouvernance IT par une supervision inefficace. | J36: Auditer les configurations des bases de données pour limiter les risques d'exposition non autorisée.
B37: Vérifier l’existence de procédures formalisées | C37: Vérifier des procédures écrites pour au moins 5 processus critiques (ex : gestion des incidents). | D37: Cinq procédures écrites pour processus critiques existent-elles ? | E37: NON | F37: Rapports d’évaluation de l’alignement stratégique | G37: Défaut de supervision des processus clés | H37: Moyenne | I37: Exposition à des attaques ciblées en l’absence de surveillance proactive. | J37: Formaliser une procédure de réponse aux incidents cyber incluant une communication structurée.
C38: Confirmer la signature des procédures par les responsables concernés. | D38: Les responsables ont-ils signé ces procédures ? | E38: PAS | F38: Spécifications fonctionnelles signées | G38: Erreurs de conception des workflows | H38: Elevée | I38: Déséquilibre entre investissements IT et retours sur investissement attendus. | J38: Implémenter des contrôles d'accès hiérarchiques pour les environnements virtualisés et cloud.
C39: Analyser des preuves d’application (logs, rapports d’exécution). | D39: Des preuves d'application (logs, rapports) sont-elles vérifiables ? | E39: OUI | F39: Fiches de poste détaillant les tâches des utilisateurs | G39: Interface utilisateur peu intuitive | H39: Moyenne | I39: Perte de données historiques critiques par archivage défaillant. | J39: Réaliser des évaluations de maturité des processus IT selon le référentiel COBIT.
C40: Identifier des indicateurs de performance liés aux procédures. | D40: Des indicateurs de performance liés aux procédures existent-ils ? | E40: OUI | F40: Rapports de performance des systèmes parallèles | G40: Absence de validation automatique des saisies | H40: Moyenne | I40: Complexification des processus métier due à des interfaces peu ergonomiques. | J40: Instaurer des mécanismes de contrôle qualité automatisés dans les pipelines DevOps.
C41: Contrôler des mises à jour récentes (moins de 6 mois). | D41: Les procédures ont-elles été mises à jour dans les 6 mois ? | E41: NON | F41: Retours d’expérience des utilisateurs sur l’adéquation | G41: Défaut de maintenance évolutive | H41: Moyenne | I41: Délais prolongés dans les projets IT par mauvaise gestion des priorités. | J41: Mettre à jour régulièrement les politiques de sécurité pour refléter l'évolution des menaces.
B42: S’assurer de l’existence et de la mise à disposition du compte rendu mensuel au propriétaire | C42: Vérifier des comptes rendus mensuels datés des 6 derniers mois. | D42: Des comptes rendus mensuels existent-ils pour les 6 derniers mois ? | E42: OUI | F42: Rapport ROI (Return on Investment) avec calculs détaillés | G42: Incohérences dans les données de référence | H42: Elevée | I42: Non-respect des SLA entraînant des pénalités contractuelles. | J42: Créer un référentiel unique des configurations matérielles et logicielles pour éviter les divergences.
C43: Confirmer la signature des comptes rendus par le propriétaire de l’application. | D43: Le propriétaire de l'application a-t-il signé ces comptes rendus ? | E43: OUI | F43: Contrats signés avec les fournisseurs | G43: Faiblesses dans les mécanismes de réconciliation | H43: Moyenne | I43: Détérioration de la relation avec les fournisseurs par manque de suivi. | J43: Effectuer des audits de conformité des licences logicielles pour prévenir les risques juridiques.
C44: Analyser des indicateurs clés inclus (ex : disponibilité, incidents). | D44: Des indicateurs clés (disponibilité, incidents) sont-ils inclus ? | E44: NON | F44: Calendrier de mise en œuvre du projet | G44: Manque d'intégrité des données | H44: Moyenne | I44: Augmentation des conflits internes liés à des rôles mal définis. | J44: Déployer des solutions de protection contre les attaques DDoS pour les services exposés en ligne.
C45: Identifier des actions correctives planifiées dans les comptes rendus. | D45: Des actions correctives sont-elles planifiées dans les comptes rendus ? | E45: PAS | F45: Bilan post-projet avec conclusions | G45: Exposition des flux inter-applicatifs | H45: Moyenne | I45: Incapacité à capitaliser sur les innovations technologiques par rigidité organisationnelle. | J45: Établir des procédures de destruction sécurisée des données en fin de cycle de vie.
C46: Contrôler des preuves de suivi des actions (rapports de clôture). | D46: Des preuves de suivi des actions (rapports de clôture) existent-elles ? | E46: OUI | F46: Rapports d’économie réalisées | G46: Défaut de chiffrement des transmissions | H46: Moyenne | I46: Risque de non-conformité aux standards sectoriels nuisant à la crédibilité. | J46: Réaliser des tests de résistance des infrastructures face aux catastrophes naturelles.
B47: S’assurer de l’existence d'un guide d'utilisateur, manuel de procédure | C47: Vérifier l’existence d’un guide d’utilisateur et d’un manuel de procédures. | D47: Un guide utilisateur et un manuel de procédures sont-ils disponibles ? | E47: OUI | F47: Document de réingénierie des processus | G47: Contournement des contrôles d'accès | H47: Moyenne | I47: Désalignement entre les besoins métier et les capacités techniques disponibles. | J47: Intégrer des contrôles de sécurité dans les phases de conception des applications (Security by Design).
C48: Confirmer la mise à jour des documents (moins de 12 mois). | D48: Ces documents ont-ils été mis à jour dans les 12 mois ? | E48: NON | F48: Rapport d’architecture technique de l’application | G48: Journalisation insuffisante des activités | H48: Moyenne | I48: Fragmentation des systèmes réduisant l’efficacité globale de l’infrastructure. | J48: Mettre en place une veille technologique pour anticiper les risques liés aux nouvelles technologies.
C49: Analyser des exemples de procédures détaillées (étapes, screenshots). | D49: Des procédures détaillées avec captures d'écran existent-elles ? | E49: OUI | F49: Tableaux de bord avec indicateurs de performance (KPI) | G49: Détection tardive des incidents de sécurité | H49: Moyenne | I49: Exposition à des erreurs de traitement par absence de validation automatisée. | J49: Auditer régulièrement les fournisseurs tiers pour s'assurer de leur conformité aux exigences de sécurité.
C50: Identifier des preuves de diffusion aux utilisateurs (accusés de réception). | D50: Des accusés de réception prouvent-ils la diffusion aux utilisateurs ? | E50: OUI | F50: Rapports de maturité technologique (ex : Gartner) | G50: Absence de revue des journaux d'audit | H50: Moyenne | I50: Détérioration de la qualité des données utilisées pour la prise de décision. | J50: Documenter les procédures de gestion des identités temporaires et des comptes de service.
C51: Contrôler des formations dédiées à l’utilisation des documents. | D51: Des formations sur l'utilisation des documents sont-elles organisées ? | E51: NON | F51: Procédures de gestion des accès privilégiés | G51: Failles dans les interfaces d'intégration | H51: Moyenne | I51: Inadéquation des compétences des équipes face aux évolutions technologiques. | J51: Instaurer des revues post-incident pour améliorer continuellement les processus de sécurité.
A52: Application | B52: S'assurer que l'accès aux ressources de l'application (données et transactions) est restreint par un système de gestion d'accès | C52: Vérifier l’existence d’un système RBAC (Role-Based Access Control) actif. | D52: Un système RBAC est-il actif ? | E52: PAS | F52: Logs d’actions administratives sur 90 jours | G52: Corruption des données lors des échanges | H52: Elevée | I52: Augmentation des temps d’indisponibilité des systèmes critiques. | J52: Adopter des outils de monitoring des performances applicatives pour détecter les goulets d'étranglement.
C53: Confirmer la présence de logs d’accès aux données sensibles sur 30 jours. | D53: Des logs d'accès aux données sensibles sur 30 jours existent-ils ? | E53: OUI | F53: Procédures de révocation des accès en cas de départ | G53: Absence de mécanismes de rejeu | H53: Moyenne | I53: Perte d’opportunités commerciales par lenteur des processus informatiques. | J53: Mettre en œuvre une politique de gestion des clés de chiffrement incluant leur rotation et stockage sécurisé.
C54: Analyser la liste des utilisateurs avec droits administrateurs (moins de 5% du total). | D54: Moins de 5% des utilisateurs ont-ils des droits administrateur ? | E54: OUI | F54: Document de schéma-directeur du SI | G54: Perte de données critiques | H54: Moyenne | I54: Dépassements budgétaires récurrents dans les projets IT non maîtrisés. | J54: Réaliser des audits de code statique et dynamique (SAST/DAST) pour les applications critiques.
C55: Tester le rejet d’accès hors profil via un compte test. | D55: Un compte test confirme-t-il le rejet d'accès hors profil ? | E55: NON | F55: Procédures de contrôle qualité des données saisies | G55: Archivage non conforme | H55: Moyenne | I55: Risque de perte de savoir-faire interne par dépendance à des solutions externes. | J55: Formaliser une stratégie de sortie pour les technologies obsolètes incluant leur remplacement progressif.
C56: Identifier une procédure de révocation des accès en cas de départ. | D56: Une procédure de révocation des accès en cas de départ existe-t-elle ? | E56: OUI | F56: Manuels d’exploitation mis à jour | G56: Restauration impossible après incident | H56: Moyenne | I56: Difficultés à maintenir la cohérence des données entre systèmes hétérogènes. | J56: Instaurer des contrôles d'accès basés sur les rôles (RBAC) pour les environnements cloud.
B57: S’assurer qu’une procédure de gestion des profils utilisateurs existe | C57: Contrôler un workflow de création/suppression de profils (outil Jira ou équivalent). | D57: Un workflow de gestion des profils (Jira ou équivalent) est-il utilisé ? | E57: OUI | F57: Procédures de gestion des correctifs urgents | G57: Pertes d'informations historiques | H57: Moyenne | I57: Détérioration de l’expérience utilisateur impactant l’adoption des outils. | J57: Documenter les procédures de gestion des vulnérabilités logicielles et des correctifs d'urgence.
C58: Vérifier des traces de validation hiérarchique pour 5 profils aléatoires. | D58: La validation hiérarchique pour 5 profils aléatoires est-elle tracée ? | E58: NON | F58: Rapports de revue de code pour les projets récents | G58: Défaut de purge sécurisée | H58: Moyenne | I58: Non-respect des exigences réglementaires en matière de transparence. | J58: Mettre en place des mécanismes de détection des fuites de données (DLP) pour les informations sensibles.
C59: Analyser l’existence d’un référentiel des profils types (PDF ou Excel). | D59: Un référentiel des profils types (PDF/Excel) est-il disponible ? | E59: PAS | F59: Procédures de déploiement en environnement de production | G59: Défaut de gestion des anomalies | H59: Moyenne | I59: Augmentation des coûts de maintenance corrective faute de prévention. | J59: Auditer les configurations des conteneurs et des orchestrateurs pour limiter les risques d'exploitation.
C60: Confirmer la réalisation d’un audit semestriel des droits. | D60: Un audit semestriel des droits est-il réalisé ? | E60: OUI | F60: Contrats incluant des clauses « Escrow Agreement » | G60: Absence de processus de correction | H60: Moyenne | I60: Incapacité à détecter les anomalies en temps réel par monitoring insuffisant. | J60: Implémenter une politique de gestion des risques spécifique aux projets d'intelligence artificielle.
C61: Identifier des sanctions en cas de non-respect (ex : mentions dans des PV). | D61: Des sanctions pour non-respect sont-elles prévues (mention dans PV) ? | E61: OUI | F61: Rapports de tests de montée en charge | G61: Défaut de traçabilité des corrections | H61: Moyenne | I61: Dégradation de la résilience des systèmes face aux perturbations externes. | J61: Réaliser des tests d'intégration pour valider la cohérence des données entre systèmes hétérogènes.
B62: Vérifier que l’identification des utilisateurs est réalisée | C62: Tester l’impossibilité de se connecter sans identifiant unique. | D62: La connexion sans identifiant unique est-elle impossible ? | E62: NON | F62: Procédures de gestion des données archivées | G62: Réintégration non contrôlée des données | H62: Elevée | I62: Exposition à des conflits d’intérêts dans la gestion des fournisseurs IT. | J62: Instaurer des contrôles d'accès biométriques pour les zones sensibles des datacenters.
C63: Vérifier l’absence de comptes génériques ("admin", "invité"). | D63: Les comptes génériques ("admin", "invité") sont-ils absents ? | E63: OUI | F63: Rapports de suivi des paiements des redevances | G63: Validation insuffisante des correctifs | H63: Moyenne | I63: Perte de contrôle sur les actifs informationnels par mauvaise gouvernance. | J63: Documenter les procédures de gestion des incidents liés aux fournisseurs de services cloud.
C64: Analyser l’existence d’un annuaire LDAP/Active Directory synchronisé. | D64: Un annuaire LDAP/Active Directory est-il synchronisé ? | E64: OUI | F64: Procédures de gestion des partenariats avec les éditeurs | G64: Défaut de supervision des mises à jour | H64: Moyenne | I64: Risque de non-reconnaissance des dépenses IT par manque de traçabilité. | J64: Mettre en œuvre des solutions de segmentation réseau pour isoler les flux critiques.
C65: Confirmer la présence d’une procédure de réinitialisation sécurisée des identifiants. | D65: Une procédure sécurisée de réinitialisation des identifiants existe-t-elle ? | E65: NON | F65: Documentation technique des interfaces d’intégration | G65: Exposition aux vulnérabilités non patchées | H65: Moyenne | I65: Désorganisation des workflows métier par intégration défaillante des systèmes. | J65: Auditer régulièrement les configurations des équipements IoT pour prévenir les compromissions.
C66: Contrôler des logs de connexion avec adresses IP et horodatages. | D66: Les logs de connexion incluent-ils adresses IP et horodatages ? | E66: PAS | F66: Procédures de suppression sécurisée des données obsolètes | G66: Journalisation incomplète des modifications | H66: Moyenne | I66: Augmentation des erreurs de saisie manuelle par absence de contrôles automatisés. | J66: Formaliser une politique de gestion des journaux d'activité conforme aux exigences réglementaires.
B67: Vérifier qu’un mot de passe est associé à l'identifiant | C67: Vérifier que chaque identifiant est associé à un mot de passe unique. | D67: Chaque identifiant a-t-il un mot de passe unique ? | E67: OUI | F67: Rapports de performance de l’équipe de maintenance | G67: Défaut de détection des changements non autorisés | H67: Moyenne | I67: Fragilisation de la position concurrentielle par retard technologique. | J67: Implémenter des contrôles de validation des entrées utilisateur pour prévenir les injections SQL.
C68: Confirmer l’application d’une politique de complexité des mots de passe (ex : 12 caractères, majuscules, chiffres). | D68: La politique impose-t-elle 12 caractères avec majuscules et chiffres ? | E68: OUI | F68: Procédures de recrutement et formation des équipes IT | G68: Absence de revue des configurations | H68: Moyenne | I68: Incapacité à répondre aux attentes des utilisateurs finaux par rigidité des processus. | J68: Réaliser des audits de conformité aux normes sectorielles (PCI DSS, HIPAA, etc.).
C69: Analyser des logs de connexion pour détecter des mots de passe faibles. | D69: Les logs de connexion révèlent-ils des mots de passe faibles ? | E69: NON | F69: Retours d’expérience du club utilisateurs | G69: Contrôles automatisés inefficaces | H69: Moyenne | I69: Détérioration de la coordination entre équipes IT et métier par communication inefficace. | J69: Instaurer des mécanismes de surveillance des activités des robots logiciels (RPA).
C70: Tester la réinitialisation forcée après 90 jours. | D70: La réinitialisation forcée a-t-elle lieu après 90 jours ? | E70: OUI | F70: Procédures de gestion des mises à jour logicielles | G70: Défaut d'alerte sur les anomalies | H70: Moyenne | I70: Exposition à des sanctions pour non-respect des clauses contractuelles avec les éditeurs. | J70: Documenter les procédures de gestion des certificats SSL/TLS pour éviter leur expiration.
C71: Identifier des alertes en cas de tentative de réutilisation d’un ancien mot de passe. | D71: Des alertes signalent-elles la réutilisation d'anciens mots de passe ? | E71: OUI | F71: Rapports d’évaluation de la conformité RGPD/ISO | G71: Absence de suivi des indicateurs clés | H71: Moyenne | I71: Perte de données opérationnelles par corruption ou suppression accidentelle. | J71: Mettre en place des contrôles d'accès contextuels pour les applications métiers sensibles.
B72: S’assurer que les tentatives de connexions infructueuses à l'application sont suivies | C72: Vérifier des logs de tentatives infructueuses sur 30 jours. | D72: Les tentatives infructueuses sur 30 jours sont-elles tracées ? | E72: NON | F72: Procédures de gestion des accès aux bibliothèques logicielles | G72: Reporting incomplet ou erroné | H72: Moyenne | I72: Augmentation des vulnérabilités réseau par configuration inadéquate. | J72: Auditer les configurations des systèmes de virtualisation pour garantir leur isolation.
C73: Confirmer la présence d’un système de verrouillage après 5 échecs. | D73: Le système se verrouille-t-il après 5 échecs ? | E73: PAS | F73: Logs de consultation de la documentation par les utilisateurs | G73: Décisions basées sur des informations obsolètes | H73: Moyenne | I73: Incapacité à anticiper les besoins futurs par planification stratégique absente. | J73: Implémenter des contrôles de sécurité physique pour les supports de sauvegarde hors site.
C74: Analyser des alertes automatiques envoyées à l’administrateur. | D74: Des alertes automatiques sont-elles envoyées à l'administrateur ? | E74: OUI | F74: Procédures de validation hiérarchique des profils utilisateurs | G74: Distribution non sécurisée des états | H74: Elevée | I74: Dégradation de la qualité des services supportés par des outils obsolètes. | J74: Réaliser des tests de résistance aux attaques zero-day via des simulations réalistes.
C75: Tester la réinitialisation manuelle par l’administrateur. | D75: La réinitialisation manuelle par l'admin est-elle fonctionnelle ? | E75: OUI | F75: Rapports d’audit semestriel des droits d’accès | G75: Accès non contrôlé aux informations sensibles | H75: Faible | I75: Risque de non-atteinte des objectifs de transformation numérique. | J75: Instaurer une politique de gestion des données archivées incluant leur classification et chiffrement.
C76: Identifier des procédures de suivi des tentatives suspectes. | D76: Une procédure de suivi des tentatives suspectes existe-t-elle ? | E76: NON | F76: Procédures de gestion des alertes de sécurité automatiques | G76: Validation manquante des outputs | H76: Moyenne | I76: Exposition à des litiges liés à la propriété intellectuelle des développements logiciels. | J76: Documenter les procédures de réponse aux fuites de données personnelles conformes au RGPD.
B77: S’assurer que l'accès aux données et aux transactions de l’application est géré | C77: Vérifier des logs d’accès aux transactions sensibles sur 30 jours. | D77: Les logs d'accès aux transactions sensibles sur 30 jours existent-ils ? | E77: OUI | F77: Documents de référence des règles de gestion des données | G77: Erreurs de traitement non détectées | H77: Moyenne | I77: Perte de flexibilité opérationnelle par architecture technique rigide. | J77: Mettre en œuvre des contrôles d'intégrité des métadonnées associées aux données critiques.
C78: Confirmer la présence d’un système de chiffrement des données en transit. | D78: Les données en transit sont-elles chiffrées ? | E78: OUI | F78: Procédures de contrôle qualité des corrections de données | G78: Incohérences dans les codifications | H78: Moyenne | I78: Détérioration de la collaboration interne par outils collaboratifs inadaptés. | J78: Auditer les configurations des systèmes de gestion des identités (IAM) pour limiter les erreurs.
C79: Analyser des procédures de validation des accès par un supérieur hiérarchique. | D79: Un supérieur hiérarchique valide-t-il les accès sensibles ? | E79: NON | F79: Rapports de tests d’interopérabilité avec les systèmes existants | G79: Défaut d'application des règles métier | H79: Moyenne | I79: Augmentation des délais de livraison des projets IT par mauvaise gestion des ressources. | J79: Implémenter des mécanismes de détection des comportements anormaux des utilisateurs.
C80: Tester le rejet d’accès hors profil via un compte test. | D80: Un compte test confirme-t-il le rejet d'accès hors profil ? | E80: PAS | F80: Procédures de gestion des environnements (dev/test/prod) | G80: Défaut de cohérence inter-modules | H80: Moyenne | I80: Incapacité à garantir l’authenticité des transactions électroniques. | J80: Réaliser des revues architecturales pour s'assurer de la résilience des infrastructures hybrides.
C81: Identifier des alertes en cas d’accès hors heures ouvrables. | D81: Des alertes existent-elles pour les accès hors heures ouvrables ? | E81: OUI | F81: Rapports de tests de modularité de l’application | G81: Interfaces non sécurisées | H81: Moyenne | I81: Fragilisation de la chaîne d’approvisionnement IT par dépendance à un seul fournisseur. | J81: Instaurer des contrôles d'accès temporaires avec expiration automatique pour les prestataires.
B82: Vérifier l’existence de pistes d’audit sur le système d’administration de l’application | C82: Vérifier des logs d’audit des actions administratives sur 90 jours. | D82: Les logs d'actions administratives sur 90 jours sont-ils disponibles ? | E82: OUI | F82: Procédures de gestion des versions logicielles | G82: Défaut de validation des développements | H82: Moyenne | I82: Détérioration de l’image de marque suite à des incidents de sécurité médiatisés. | J82: Documenter les procédures de gestion des risques liés à l'utilisation de l'Internet des objets (IoT).
C83: Confirmer la présence d’un système de journalisation centralisé. | D83: Un système de journalisation centralisé est-il en place ? | E83: NON | F83: Rapports de suivi des demandes de maintenance utilisateur | G83: Code non conforme aux standards | H83: Moyenne | I83: Non-respect des engagements environnementaux liés à la gestion des infrastructures IT. | J83: Mettre en place des solutions de chiffrement homomorphique pour les données sensibles en traitement.
C84: Analyser des alertes automatiques pour les actions critiques (ex : suppression de données). | D84: Des alertes automatiques pour actions critiques existent-elles ? | E84: OUI | F84: Procédures de gestion des clés SSH/API | G84: Absence de revue par les pairs | H84: Moyenne | I84: Augmentation des coûts de licence par utilisation non optimisée des logiciels. | J84: Auditer les configurations des passerelles API pour prévenir les exploitations malveillantes.
C85: Tester la traçabilité des actions via un compte administrateur. | D85: La traçabilité des actions via un compte admin est-elle vérifiable ? | E85: OUI | F85: Rapports de performance des travaux batch | G85: Déploiement non contrôlé en production | H85: Moyenne | I85: Incapacité à maintenir la cohérence des données lors de fusions ou acquisitions. | J85: Implémenter des contrôles de sécurité dans les pipelines CI/CD pour les déploiements automatisés.
C86: Identifier des procédures de revue trimestrielle des logs. | D86: Une revue trimestrielle des logs est-elle prévue ? | E86: NON | F86: Procédures de gestion des données rejetées | G86: Accès non autorisé aux environnements critiques | H86: Moyenne | I86: Dégradation de l’agilité organisationnelle par lenteur des processus IT. | J86: Réaliser des tests de charge pour valider la scalabilité des applications critiques.
B87: Vérifier que tous les documents servant de base à la saisie sont pris en compte | C87: Vérifier des exemples de documents sources (ex : factures, bons de commande). | D87: Des exemples de documents sources (factures, bons de commande) existent-ils ? | E87: PAS | F87: Rapports de tests de compatibilité ascendante/descendante | G87: Défaut de séparation des environnements | H87: Faible | I87: Exposition à des erreurs de configuration entraînant des pannes critiques. | J87: Instaurer une politique de gestion des secrets applicatifs (mots de passe, clés API).
C88: Confirmer la présence d’un workflow de validation des documents. | D88: Un workflow de validation des documents est-il établi ? | E88: OUI | F88: Procédures de gestion des formations utilisateurs | G88: Gestion hasardeuse des accès privilégiés | H88: Moyenne | I88: Perte de compétitivité sur le marché par innovation technologique insuffisante. | J88: Documenter les procédures de gestion des incidents liés aux systèmes de paiement électronique.
C89: Analyser des logs de saisie pour corréler avec les documents sources. | D89: Les logs de saisie correspondent-ils aux documents sources ? | E89: OUI | F89: Rapports de suivi des indicateurs de satisfaction utilisateur | G89: Compromission des clés d'accès | H89: Moyenne | I89: Détérioration de la satisfaction client due à des services IT peu fiables. | J89: Mettre en œuvre des contrôles d'accès physiques et logiques pour les salles de contrôle.
C90: Tester la reprise des données après une erreur de saisie. | D90: La reprise des données après erreur de saisie est-elle possible ? | E90: NON | F90: Procédures de gestion des risques résiduels | G90: Défaut de rotation des identifiants | H90: Elevée | I90: Augmentation des risques liés à l’externalisation non supervisée. | J90: Auditer les configurations des systèmes SCADA/OT pour limiter les risques cyberindustriels.
C91: Identifier des procédures de contrôle qualité des données saisies. | D91: Des procédures de contrôle qualité des données saisies existent-elles ? | E91: OUI | F91: Rapports de revue trimestrielle des logs d’activité | G91: Compétences insuffisantes des équipes | H91: Moyenne | I91: Incapacité à aligner les investissements IT sur les priorités métier. | J91: Implémenter des mécanismes de protection contre les attaques par ingénierie sociale.
B92: S’assurer que les facilités de saisie, l’ergonomie de la saisie, les messages écrans et les contrôles sont mis en œuvre | C92: Vérifier des captures d’écran des interfaces de saisie. | D92: Des captures d'écran des interfaces de saisie sont-elles disponibles ? | E92: OUI | F92: Procédures de gestion des accès hors heures ouvrables | G92: Défaut de plan de continuité d'activité | H92: Elevée | I92: Fragilisation de la conformité aux normes internationales par pratiques obsolètes. | J92: Réaliser des revues de conformité des contrats avec les fournisseurs de services managés.
C93: Confirmer la présence de messages d’erreur clairs et explicites. | D93: Les messages d'erreur sont-ils clairs et explicites ? | E93: NON | F93: Rapports de tests de stabilité des technologies utilisées | G93: Procédures de secours non opérationnelles | H93: Elevée | I93: Détérioration de la capacité à auditer les processus internes efficacement. | J93: Instaurer des contrôles de sécurité pour les environnements DevOps et les outils low-code.
C94: Analyser des tests utilisateurs pour évaluer l’ergonomie. | D94: Des tests utilisateurs évaluent-ils l'ergonomie ? | E94: PAS | F94: Procédures de gestion des budgets d’extension d’infrastructure | G94: Temps de restauration excessif | H94: Moyenne | I94: Exposition à des interruptions d’activité par absence de redondance des systèmes. | J94: Documenter les procédures de gestion des risques liés à l'adoption de la blockchain.
C95: Tester la validation automatique des champs obligatoires. | D95: La validation automatique des champs obligatoires fonctionne-t-elle ? | E95: OUI | F95: Rapports de tests de réversibilité en cas d’échec de déploiement | G95: Perte de disponibilité du système | H95: Elevée | I95: Perte de données stratégiques par absence de politiques de sauvegarde robustes. | J95: Mettre en place des mécanismes de validation des données en temps réel pour les transactions.
C96: Identifier des procédures de mise à jour des interfaces. | D96: Des procédures de mise à jour des interfaces existent-elles ? | E96: OUI | F96: Procédures de gestion des alertes de tentative d’accès non autorisé | G96: Défaut de tests de reprise | H96: Moyenne | I96: Augmentation des conflits entre équipes par manque de clarté des responsabilités. | J96: Auditer les configurations des systèmes de gestion de contenu (CMS) pour prévenir les vulnérabilités.
B97: S’assurer que les contrôles de validation des « brouillards » de saisie pour validation par réconciliation existent | C97: Vérifier des exemples de brouillards de saisie validés. | D97: Des brouillards de saisie validés sont-ils disponibles ? | E97: NON | F97: Rapports de suivi des indicateurs de productivité des processus | G97: Inadéquation des sauvegardes | H97: Moyenne | I97: Incapacité à répondre aux audits réglementaires faute de documentation adéquate. | J97: Implémenter des contrôles d'accès basés sur l'attestation pour les appareils connectés.
C98: Confirmer la présence d’un workflow de réconciliation. | D98: Un workflow de réconciliation est-il en place ? | E98: OUI | F98: Procédures de gestion des mises à jour des spécifications fonctionnelles | G98: Exposition aux sinistres majeurs | H98: Elevée | I98: Dégradation de la qualité des décisions managériales par données incomplètes. | J98: Réaliser des tests de résilience des infrastructures face aux pannes matérielles.
C99: Analyser des logs de validation pour corréler avec les brouillards. | D99: Les logs de validation correspondent-ils aux brouillards ? | E99: OUI | F99: Rapports de tests de performance des développements spécifiques | G99: Non-respect des SLA | H99: Elevée | I99: Risque de non-conformité aux exigences sectorielles spécifiques. | J99: Instaurer une politique de gestion des correctifs critiques avec des délais contraignants.
C100: Tester la détection d’erreurs de saisie via des contrôles automatiques. | D100: Les contrôles automatiques détectent-ils les erreurs de saisie ? | E100: NON | F100: Procédures de gestion des partenariats avec les clubs utilisateurs | G100: Dégradation de la qualité de service | H100: Elevée | I100: Détérioration de la collaboration avec les partenaires externes par systèmes incompatibles. | J100: Documenter les procédures de gestion des risques liés aux technologies émergentes (IA, 5G).
...

Sheet 4.2 Fonction informatique
A1: Points de Contrôle | B1: Objectifs de Contrôle | C1: Critère d’Évaluation | D1: Question d’Évaluation | E1: Réponses | F1: Documents requis | G1: Risques | H1: Criticités | I1: Conséquences | J1: Recommandations
A2: Rôle et positionnement de l'informatique dans l'organisation | B2: Vérifier qu’ont été créés des Comités « informatique » (stratégique, pilotage,...) regroupant les différentes directions | C2: Existence de procès-verbaux des réunions des comités | D2: Les procès-verbaux des réunions des comités sont-ils systématiquement rédigés et archivés ? | E2: OUI | F2: Procès-verbaux archivés | G2: Absence de coordination inter-directions | H2: Moyenne | I2: Priorités incohérentes, retards de projets | J2: Formaliser les comités et planifier des réunions trimestrielles avec rappels automatisés.
C3: Liste des membres représentant toutes les directions | D3: La composition des comités inclut-elle des représentants de toutes les directions concernées ? | E3: OUI | F3: Liste des membres signée | G3: Exclusion de certaines directions | H3: Moyenne | I3: Décisions non alignées avec les besoins métiers | J3: Imposer une représentation équilibrée (ex : 1 membre par direction).
C4: Périmètre de responsabilité des comités documenté | D4: Le périmètre de responsabilité de chaque comité est-il clairement défini et documenté ? | E4: NON | F4: Charte des comités | G4: Chevauchement des rôles | H4: Elevée | I4: Conflits de responsabilités | J4: Rédiger une charte claire et la diffuser via l’intranet.
C5: Fréquence régulière des réunions (trimestrielle/semestrielle) | D5: Les comités se réunissent-ils avec la régularité prévue (trimestrielle, semestrielle) ? | E5: OUI | F5: Calendrier des réunions | G5: Désengagement des parties prenantes | H5: Elevée | I5: Décisions stratégiques retardées | J5: Automatiser les invitations et suivre les présences via un outil collaboratif.
C6: Preuves de décisions impactant les priorités projets | D6: Y a-t-il des décisions documentées qui influencent les priorités des projets ? | E6: OUI | F6: PV de décisions validées | G6: Priorités non alignées avec la stratégie | H6: Faible | I6: Ressources gaspillées sur des projets non prioritaires | J6: Intégrer un suivi des décisions dans un outil de gestion de projet (ex : Jira).
B7: Vérifier l’existence d’une charte informatique ou document définissant le rôle de la DSI | C7: Charte approuvée par la direction générale | D7: La charte informatique a-t-elle été officiellement approuvée par la direction générale ? | E7: NON | F7: Cartographie à jour | G7: Gaps fonctionnels non identifiés | H7: Elevée | I7: Inadéquation SI-besoins métiers | J7: Mettre à jour la cartographie annuellement via des ateliers métiers/DSI.
C8: Version actualisée datée de moins de 3 ans | D8: La version actuelle de la charte informatique date-t-elle de moins de 3 ans ? | E8: PAS | F8: Rapport d’analyse des gaps | G8: Solutions temporaires non pérennes | H8: Moyenne | I8: Accumulation de dette technique | J8: Planifier des revues trimestrielles des gaps avec les parties prenantes.
C9: Diffusion officielle à l'ensemble des services | D9: La charte informatique a-t-elle été officiellement diffusée à l'ensemble des services ? | E9: OUI | F9: Plan stratégique signé | G9: Projets non alignés sur la vision long terme | H9: Elevée | I9: Investissements inefficaces | J9: Intégrer le plan dans un tableau de bord stratégique (ex : Power BI).
C10: Référence explicite aux rôles MOA/MOE | D10: La charte ou les documents afférents précisent-ils les rôles MOA (Maîtrise d’Ouvrage) et MOE (Maîtrise d’Œuvre) ? | E10: OUI | F10: Grille de priorisation validée | G10: Priorités contradictoires | H10: Moyenne | I10: Dilution des efforts | J10: Créer un comité de priorisation interdisciplinaire.
C11: Processus de mise à jour formalisé | D11: Existe-t-il un processus formel pour la mise à jour régulière de la charte informatique ? | E11: NON | F11: PV de revue des besoins | G11: Besoins obsolètes ou non validés | H11: Moyenne | I11: Retards dans les livraisons | J11: Automatiser la collecte des besoins via une plateforme (ex : Confluence).
B12: Évaluer le degré d’implication des organes de gestion dans les SI | C12: Participation aux revues stratégiques SI | D12: Les organes de gestion participent-ils systématiquement aux revues stratégiques des systèmes d'information ? | E12: OUI | F12: Document d’objectifs signé | G12: Objectifs flous ou contradictoires | H12: Elevée | I12: Désalignement stratégique | J12: Formaliser les objectifs via un atelier avec la direction générale.
C13: Allocation budgétaire alignée sur les besoins métiers | D13: Les budgets alloués aux projets SI sont-ils alignés avec les besoins métiers identifiés ? | E13: OUI | F13: Tableau de bord BSC | G13: Indicateurs non alignés | H13: Moyenne | I13: Décisions basées sur des données erronées | J13: Former les équipes à l’utilisation du BSC et des KPI.
C14: Désignation de correspondants SI par direction | D14: Chaque direction a-t-elle désigné officiellement un correspondant pour les systèmes d'information ? | E14: NON | F14: Rapport d’alignement stratégique | G14: Ressources mal allouées | H14: Moyenne | I14: Échec des projets clés | J14: Organiser des revues trimestrielles d’alignement avec les métiers.
C15: Implication dans les comités de pilotage | D15: Les organes de gestion participent-ils activement aux comités de pilotage des projets SI ? | E15: PAS | F15: PV de communication | G15: Manque d’adhésion des métiers | H15: Moyenne | I15: Résistance au changement | J15: Diffuser les objectifs via des newsletters et des réunions dédiées.
C16: Revue formelle des indicateurs SI par la direction | D16: La direction procède-t-elle à une revue formelle et périodique des indicateurs de performance des SI ? | E16: OUI | F16: Historique des mises à jour | G16: Objectifs obsolètes | H16: Moyenne | I16: Perte de pertinence stratégique | J16: Intégrer un processus de révision semestrielle automatisé.
B17: Vérifier que le leadership des grands projets est assuré par les organes de gestion | C17: Désignation écrite des responsables métiers | D17: Les responsables métiers sont-ils désignés par écrit pour chaque projet ? | E17: OUI | F17: Inventaire à jour | G17: Utilisation de logiciels non licenciés | H17: Moyenne | I17: Amendes légales et atteinte à la réputation | J17: Automatiser le suivi des licences avec un outil comme Snow License Manager.
C18: Participation aux jalons clés (lancement, recette) | D18: Les responsables métiers participent-ils aux étapes clés des projets (lancement, recette) ? | E18: NON | F18: Procédure d’achat validée | G18: Achats non contrôlés | H18: Elevée | I18: Dépenses superflues | J18: Imposer une validation par la DSI avant tout achat de logiciel.
C19: Validation des budgets et délais | D19: Les budgets et délais des projets sont-ils systématiquement validés par les métiers concernés ? | E19: OUI | F19: Rapports d’audit | G19: Vulnérabilités techniques | H19: Faible | I19: Risques de sécurité | J19: Déployer un outil de détection d’intrusions (ex : CrowdStrike).
C20: Suivi des risques par les métiers | D20: Les métiers suivent-ils activement les risques identifiés dans les projets SI ? | E20: OUI | F20: Rapports d’audit antipiratage | G20: Non-conformité légale | H20: Faible | I20: Sanctions réglementaires | J20: Planifier des audits semestriels avec un tiers indépendant.
C21: Bilans économiques partagés avec la direction | D21: Les bilans économiques des projets sont-ils partagés avec la direction après chaque clôture de projet ? | E21: NON | F21: Politique de sanctions documentée | G21: Répétition des violations | H21: Moyenne | I21: Culture de non-conformité | J21: Sensibiliser les employés via des formations annuelles sur la propriété intellectuelle.
B22: Vérifier que les métiers assurent leur rôle de MOA | C22: Rédaction des cahiers des charges par les métiers | D22: Les cahiers des charges sont-ils rédigés par les métiers en fonction de leurs besoins spécifiques ? | E22: PAS | F22: Organigramme actuel | G22: Structure confuse | H22: Moyenne | I22: Délais de prise de décision | J22: Mettre à jour l’organigramme trimestriellement et le publier sur l’intranet.
C23: Validation des spécifications fonctionnelles | D23: Les spécifications fonctionnelles sont-elles validées par les métiers avant la mise en œuvre ? | E23: OUI | F23: PV de validation | G23: Décisions non alignées | H23: Elevée | I23: Conflits hiérarchiques | J23: Impliquer la direction dans les mises à jour via des réunions dédiées.
C24: Tests utilisateurs réalisés par les métiers | D24: Les utilisateurs finaux réalisent-ils systématiquement les tests avant la mise en production ? | E24: OUI | F24: Liste des postes clés | G24: Absence de relève | H24: Moyenne | I24: Risque de rupture opérationnelle | J24: Élaborer un plan de succession pour chaque poste clé.
C25: Procès-verbal de recette signé par les métiers | D25: Y a-t-il un procès-verbal de recette signé par les métiers pour chaque projet avant la mise en production ? | E25: NON | F25: Procédure de validation | G25: Blocages bureaucratiques | H25: Moyenne | I25: Retards dans les projets | J25: Simplifier les circuits via une matrice RACI.
C26: Retours post-déploiement formalisés | D26: Les retours d'expérience post-déploiement sont-ils formalisés et analysés ? | E26: OUI | F26: Plateforme de partage | G26: Manque de transparence | H26: Faible | I26: Déperdition d’informations | J26: Centraliser les documents sur un intranet sécurisé avec accès contrôlé.
A27: Planification stratégique | B27: Vérifier la couverture du périmètre fonctionnel | C27: Cartographie des processus métiers couverts | D27: Une cartographie des processus métiers couverts par les systèmes d'information existe-t-elle et est-elle à jour ? | E27: OUI | F27: Cartographie des processus métiers | G27: Processus non couverts par les SI | H27: Moyenne | I27: Inefficacités opérationnelles | J27: Mettre à jour la cartographie trimestriellement avec les métiers
C28: Analyse des gaps fonctionnels documentée | D28: Les écarts fonctionnels identifiés sont-ils documentés et pris en compte dans les plans d'amélioration ? | E28: NON | F28: Rapport d'analyse des gaps | G28: Besoins non satisfaits | H28: Moyenne | I28: Dette technique accumulée | J28: Prioriser les gaps dans le backlog avec les métiers
C29: Plan de couverture pluriannuel | D29: Un plan pluriannuel de couverture des besoins fonctionnels est-il défini et suivi ? | E29: PAS | F29: Plan pluriannuel signé | G29: Projets non alignés | H29: Elevée | I29: Ressources mal allouées | J29: Aligner le plan sur la stratégie via des revues semestrielles
C30: Priorisation alignée sur la stratégie globale | D30: Les projets SI sont-ils priorisés en fonction de la stratégie globale de l'organisation ? | E30: OUI | F30: Grille de priorisation | G30: Décisions arbitraires | H30: Moyenne | I30: Investissements inefficaces | J30: Impliquer la direction dans l'établissement des priorités
C31: Mécanismes de revue des besoins | D31: Existe-t-il un mécanisme formel de revue et d'ajustement des besoins métiers ? | E31: OUI | F31: Procès-verbal de revue des besoins | G31: Besoins obsolètes | H31: Moyenne | I31: Solutions inadaptées | J31: Automatiser la collecte via plateforme collaborative
B32: Vérifier l’existence d’une analyse à jour des procédures de pilotage du plan informatique | C32: Document de procédures daté de moins d'un an | D32: Le document de procédures a-t-il été mis à jour au cours des 12 derniers mois ? | E32: NON | F32: Procédures actualisées | G32: Non-conformité | H32: Moyenne | I32: Risques réglementaires | J32: Planifier des mises à jour semestrielles
C33: Calendrier des revues stratégiques | D33: Un calendrier des revues stratégiques est-il défini et respecté ? | E33: OUI | F33: Calendrier des revues | G33: Retards stratégiques | H33: Moyenne | I33: Opportunités manquées | J33: Synchroniser avec le cycle budgétaire
C34: Outils de suivi des évolutions (ex : Gantt) | D34: Des outils tels qu’un diagramme de Gantt sont-ils utilisés pour suivre l'évolution des projets ? | E34: OUI | F34: Diagrammes de Gantt | G34: Délais non respectés | H34: Moyenne | I34: Dépassements de coûts | J34: Intégrer des alertes sur les écarts
C35: Circuit de validation des modifications | D35: Les modifications apportées aux projets suivent-elles un circuit de validation formalisé ? | E35: NON | F35: Workflow de validation | G35: Modifications non contrôlées | H35: Moyenne | I35: Instabilité des SI | J35: Digitaliser le circuit avec outils de workflow
C36: Historique des ajustements | D36: Un historique des ajustements et des modifications est-il maintenu à jour ? | E36: PAS | F36: Historique des changements | G36: Perte de traçabilité | H36: Faible | I36: Difficultés d'audit | J36: Centraliser dans un système de gestion des configurations
B37: Vérifier l’existence des documents d’urbanisme à jour | C37: Schéma directeur validé dans les 2 ans | D37: Le schéma directeur a-t-il été validé ou mis à jour au cours des deux dernières années ? | E37: OUI | F37: Schéma directeur | G37: Architecture désorganisée | H37: Faible | I37: Coûts d'intégration élevés | J37: Valider avec un comité architecture
C38: Cartographie applicative actualisée | D38: La cartographie des applications utilisées est-elle actualisée et documentée ? | E38: OUI | F38: Cartographie applicative | G38: Redondances | H38: Moyenne | I38: Coûts de maintenance | J38: Automatiser la détection des doublons
C39: Standards techniques opposables | D39: Les standards techniques applicables sont-ils clairement définis et opposables ? | E39: NON | F39: Standards techniques | G39: Incompatibilités | H39: Elevée | I39: Problèmes d'interopérabilité | J39: Former les équipes aux standards
C40: Plan de migration versionné | D40: Les plans de migration des systèmes sont-ils documentés avec des versions clairement identifiées ? | E40: OUI | F40: Plan de migration | G40: Échecs de migration | H40: Moyenne | I40: Pertes de données | J40: Prévoir des rollbacks automatisés
C41: Indicateurs de conformité urbaine | D41: Des indicateurs de conformité sont-ils en place pour vérifier le respect de l'urbanisme des SI ? | E41: OUI | F41: Tableau de bord de conformité | G41: Écarts non détectés | H41: Moyenne | I41: Sanctions possibles | J41: Automatiser les contrôles via outils dédiés
B42: Vérifier l’existence d’une analyse à jour des procédures depilotage et de mise à jour du plan d’occupation des sols (POS) ; | C42: Analyse formalisée et à jour des procédures de pilotage du POS | D42: Une analyse récente et formalisée des procédures de pilotage du plan d'occupation des sols est-elle disponible ? | E42: NON | F42: Analyse POS formalisée | G42: Décisions non documentées | H42: Moyenne | I42: Contentieux juridiques | J42: Archiver les décisions dans un SAE
C43: Intégration des objectifs de la DSI dans l'approche BSC | D43: Les objectifs de la DSI sont-ils alignés avec l'approche Balanced Scorecard (BSC) pour le court, moyen et long terme ? | E43: PAS | F43: Tableau de bord BSC | G43: Objectifs divergents | H43: Elevée | I43: Perte d'alignement | J43: Organiser des ateliers d'alignement trimestriels
C44: Cohérence avec les besoins stratégiques de l'organisation | D44: Les objectifs de la DSI sont-ils cohérents avec les besoins stratégiques de l'organisation ? | E44: OUI | F44: Rapport d'alignement stratégique | G44: Incohérences | H44: Moyenne | I44: Échecs stratégiques | J44: Mapper les objectifs DSI vs organisation
C45: Mécanisme de mise à jour périodique des objectifs et procédures | D45: Les objectifs et procédures sont-ils régulièrement mis à jour pour refléter les évolutions stratégiques et opérationnelles ? | E45: OUI | F45: Procédures de mise à jour | G45: Documentation obsolète | H45: Moyenne | I45: Erreurs opérationnelles | J45: Automatiser les alertes de révision
C46: Suivi et évaluation de la performance via des indicateurs mesurables et pertinents | D46: Des indicateurs mesurables et pertinents sont-ils utilisés pour suivre et évaluer la performance ? | E46: NON | F46: Indicateurs de performance | G46: Décisions non éclairées | H46: Moyenne | I46: Performance dégradée | J46: Benchmarquer avec le secteur
B47: Vérifier la cohérence et l’homogénéité des technologies | C47: Politique de standardisation formalisée | D47: Une politique de standardisation formalisée des processus et outils existe-t-elle ? | E47: OUI | F47: Politique de standardisation | G47: Hétérogénéité technique | H47: Moyenne | I47: Coûts de formation | J47: Appliquer le principe "1 outil par besoin"
C48: Inventaire des technologies en production | D48: Un inventaire complet et à jour des technologies en production est-il maintenu ? | E48: OUI | F48: Inventaire technologique | G48: Technologies non supportées | H48: Moyenne | I48: Vulnérabilités de sécurité | J48: Scanner automatiquement le parc
C49: Processus d'homologation des nouveaux outils | D49: Un processus formalisé pour homologuer les nouveaux outils est-il en place ? | E49: NON | F49: Procédure d'homologation | G49: Outils non conformes | H49: Moyenne | I49: Risques réglementaires | J49: Ajouter des checklists de conformité
C50: Taux de rationalisation mesuré | D50: Le taux de rationalisation des outils et technologies est-il mesuré périodiquement ? | E50: PAS | F50: Rapport de rationalisation | G50: Coûts superflus | H50: Moyenne | I50: Budgets explosés | J50: Fixer des objectifs de rationalisation annuels
C51: Plan de suppression des technologies obsolètes | D51: Un plan pour supprimer progressivement les technologies obsolètes existe-t-il ? | E51: OUI | F51: Plan de suppression | G51: Obsolescence technique | H51: Moyenne | I51: Problèmes de compatibilité | J51: Planifier des migrations progressives
B52: Vérifier l’existence et l’unicité des référentiels | C52: Inventaire centralisé des référentiels | D52: Les référentiels critiques (données, outils, procédures) sont-ils centralisés et mis à jour ? | E52: OUI | F52: Référentiel central | G52: Données fragmentées | H52: Moyenne | I52: Incohérences | J52: Mettre en place un MDM (Master Data Management)
C53: Processus de gestion des données maîtres | D53: Un processus formalisé de gestion des données maîtres est-il défini et appliqué ? | E53: NON | F53: Procédure MDM | G53: Qualité des données dégradée | H53: Elevée | I53: Erreurs décisionnelles | J53: Nommer des data stewards
C54: Outils de dédoublonnage en place | D54: Des outils automatisés pour le dédoublonnage des données existent-ils ? | E54: OUI | F54: Outils de déduplication | G54: Données dupliquées | H54: Moyenne | I54: Reporting erroné | J54: Implémenter des règles automatiques
C55: Taux de complétude mesuré | D55: Le taux de complétude des données critiques est-il mesuré régulièrement ? | E55: OUI | F55: Métriques de complétude | G55: Données manquantes | H55: Moyenne | I55: Analyses partielles | J55: Mettre en place des contrôles à la saisie
C56: Responsables désignés par référentiel | D56: Chaque référentiel clé a-t-il un responsable désigné ? | E56: NON | F56: Désignation des responsables | G56: Redevabilité floue | H56: Moyenne | I56: Problèmes non résolus | J56: Publier l'organigramme des responsabilités
A57: Budgets et coûts informatiques | B57: Objectifs assignés à la DSI (court/moyen/long terme, approche BSC) | C57: Définition claire des objectifs à court, moyen et long terme | D57: Les objectifs sont-ils clairement définis selon des horizons temporels (court, moyen et long terme) ? | E57: PAS | F57: Document d'objectifs daté | G57: Objectifs flous | H57: Moyenne | I57: Désalignement stratégique | J57: Formaliser les objectifs via ateliers annuels
C58: Utilisation de l'approche Balanced Scorecard (BSC) | D58: L'approche BSC (Balanced Scorecard) est-elle utilisée pour structurer les objectifs ? | E58: OUI | F58: Tableau de bord BSC | G58: Indicateurs non pertinents | H58: Moyenne | I58: Décisions erronées | J58: Former les équipes à la méthodologie BSC
C59: Alignement avec les objectifs stratégiques de l'organisation | D59: Les objectifs IT sont-ils alignés avec les objectifs stratégiques globaux de l'organisation ? | E59: OUI | F59: Rapport d'alignement stratégique | G59: Objectifs divergents | H59: Moyenne | I59: Échecs projets | J59: Organiser des revues trimestrielles
C60: Communication et validation des objectifs avec les parties prenantes | D60: Les objectifs sont-ils validés et communiqués aux parties prenantes concernées ? | E60: NON | F60: PV de validation des objectifs | G60: Manque d'adhésion | H60: Moyenne | I60: Résistance au changement | J60: Communiquer via différents canaux
C61: Mise à jour périodique des objectifs pour s'adapter aux changements | D61: Les objectifs sont-ils mis à jour périodiquement pour s'adapter aux changements internes et externes ? | E61: OUI | F61: Historique des mises à jour | G61: Objectifs obsolètes | H61: Moyenne | I61: Pertinence diminuée | J61: Automatiser les alertes de révision
B62: Existence d'un comité informatique transversal | C62: Existence d'un comité formalisé avec des responsabilités définies | D62: Un comité officiel avec des responsabilités formalisées est-il en place pour piloter la gouvernance IT ? | E62: OUI | F62: Charte du comité IT | G62: Gouvernance inefficace | H62: Moyenne | I62: Décisions incohérentes | J62: Publier la charte sur l'intranet
C63: Représentation équilibrée des différentes parties prenantes (DSI, métiers, direction) | D63: Les parties prenantes (DSI, métiers, direction) sont-elles représentées de manière équilibrée dans le comité ? | E63: OUI | F63: Liste des membres | G63: Déséquilibre représentation | H63: Elevée | I63: Biais décisionnels | J63: Imposer des quotas par direction
C64: Fréquence et régularité des réunions | D64: Les réunions du comité ont-elles lieu à une fréquence régulière et respectée ? | E64: OUI | F64: Calendrier des réunions | G64: Fréquence irrégulière | H64: Moyenne | I64: Retards stratégiques | J64: Synchroniser avec agenda direction
C65: Documentation des décisions et suivi des actions | D65: Les décisions prises sont-elles documentées avec un suivi des actions assignées ? | E65: OUI | F65: Base de décisions | G65: Actions non suivies | H65: Moyenne | I65: Problèmes récurrents | J65: Assigner des responsables clairs
C66: Implication du comité dans les décisions stratégiques liées à l'IT | D66: Le comité est-il impliqué dans les décisions stratégiques liées à l'IT ? | E66: NON | F66: PV de participation | G66: Décisions non partagées | H66: Moyenne | I66: Manque de transparence | J66: Diffuser les comptes-rendus
B67: Pertinence des indicateurs de qualité/performance et outils de mesure | C67: Existence d'indicateurs de performance (KPI) bien définis | D67: Des indicateurs de performance (KPI) clairs et spécifiques sont-ils définis pour les objectifs IT ? | E67: OUI | F67: Référentiel KPI | G67: Mesures inadaptées | H67: Moyenne | I67: Performance illusoire | J67: Aligner sur objectifs SMART
C68: Pertinence et alignement des indicateurs avec les objectifs stratégiques | D68: Les KPI sont-ils alignés avec les objectifs stratégiques de l'organisation ? | E68: OUI | F68: Matrice d'alignement | G68: Indicateurs non stratégiques | H68: Moyenne | I68: Efforts dispersés | J68: Valider avec la direction
C69: Disponibilité et fiabilité des outils de mesure utilisés | D69: Les outils de mesure de performance sont-ils disponibles et fiables ? | E69: OUI | F69: Documentation outils | G69: Données non fiables | H69: Moyenne | I69: Erreurs d'analyse | J69: Auditer les sources régulièrement
C70: Fréquence et régularité de la mesure des indicateurs | D70: La performance est-elle mesurée à intervalles réguliers (mensuel, trimestriel, annuel) ? | E70: PAS | F70: Calendrier de reporting | G70: Évaluations irrégulières | H70: Moyenne | I70: Réactivité faible | J70: Automatiser les rapports
C71: Utilisation des résultats pour l'amélioration continue | D71: Les résultats des indicateurs sont-ils utilisés pour identifier les points d'amélioration ? | E71: OUI | F71: Registre d'améliorations | G71: Correction inefficace | H71: Moyenne | I71: Problèmes persistants | J71: Implémenter un PDCA
B72: Tableau de bord consolidé (BSC) pour le suivi opérationnel et financier | C72: Existence d'un tableau de bord consolidé couvrant les dimensions clés | D72: Un tableau de bord consolidé regroupant les dimensions clés (finances, performance, sécurité) existe-t-il ? | E72: NON | F72: Dashboard consolidé | G72: Vision fragmentée | H72: Moyenne | I72: Décisions partielles | J72: Centraliser les données
C73: Mise à jour régulière des données affichées | D73: Les données du tableau de bord sont-elles mises à jour régulièrement ? | E73: OUI | F73: Historique des mises à jour | G73: Données obsolètes | H73: Moyenne | I73: Analyses erronées | J73: Connecter aux sources temps réel
C74: Visualisation claire et compréhensible des données | D74: Les données du tableau de bord sont-elles présentées de manière claire et accessible ? | E74: PAS | F74: Guide de visualisation | G74: Difficulté d'interprétation | H74: Moyenne | I74: Mauvaise utilisation | J74: Standardiser les formats
C75: Accessibilité pour les parties prenantes clés | D75: Le tableau de bord est-il accessible aux parties prenantes concernées ? | E75: OUI | F75: Politique d'accès | G75: Restrictions excessives | H75: Moyenne | I75: Blocages opérationnels | J75: Appliquer RBAC
C76: Utilisation des données pour la prise de décision | D76: Les données du tableau de bord sont-elles réellement utilisées pour orienter les décisions stratégiques ? | E76: OUI | F76: PV de décisions | G76: Données ignorées | H76: Moyenne | I76: Opportunités manquées | J76: Lier aux processus décisionnels
B77: Bilan post-projet systématique (économique et technique) | C77: Existence d'un processus formalisé pour les bilans post-projet | D77: Un processus formalisé de bilan post-projet existe-t-il pour analyser les résultats ? | E77: OUI | F77: Modèle de bilan projet | G77: Évaluations subjectives | H77: Moyenne | I77: Répétition erreurs | J77: Standardiser le processus
C78: Évaluation à la fois économique et technique des projets | D78: Les bilans de projet incluent-ils à la fois une analyse économique et technique ? | E78: OUI | F78: Rapport d'analyse | G78: Vision partielle | H78: Moyenne | I78: Améliorations partielles | J78: Croiser données techniques/financières
C79: Participation des parties prenantes au processus d'évaluation | D79: Les parties prenantes sont-elles impliquées dans l'évaluation des projets après leur achèvement ? | E79: Réponses | F79: Liste participants | G79: Points de vue manquants | H79: Moyenne | I79: Biais d'évaluation | J79: Inclure toutes les parties prenantes
C80: Documentation et archivage des leçons apprises | D80: Les leçons apprises sont-elles documentées et archivées pour une utilisation future ? | E80: OUI | F80: Base de connaissances | G80: Perte d'expérience | H80: Moyenne | I80: Réinvention constante | J80: Mettre en place un wiki
C81: Mise en œuvre d'actions correctives sur la base des résultats | D81: Des actions correctives sont-elles mises en place sur la base des résultats des bilans post-projet ? | E81: OUI | F81: Plan d'actions | G81: Corrections inefficaces | H81: Moyenne | I81: Problèmes récurrents | J81: Assigner délais et responsables
A82: Mesure et suivi de la performance informatique | B82: Vérifier que des objectifs de court, moyen et long termes existent et sont assignés à la DSI | C82: Objectifs stratégiques documentés et datés | D82: Les objectifs stratégiques sont-ils documentés avec une date de mise à jour récente ? | E82: NON | F82: Document d'objectifs daté et signé | G82: Objectifs obsolètes | H82: Moyenne | I82: Désalignement stratégique | J82: Mettre à jour annuellement et valider par la direction
C83: Déclinaison en indicateurs opérationnels | D83: Les objectifs stratégiques sont-ils traduits en indicateurs opérationnels mesurables ? | E83: PAS | F83: Tableau de déclinaison des indicateurs | G83: Mesures imprécises | H83: Moyenne | I83: Évaluation biaisée | J83: Appliquer la méthode SMART pour les indicateurs
C84: Lien clair avec la vision de l'organisation | D84: Les objectifs sont-ils clairement alignés avec la vision globale de l'organisation ? | E84: OUI | F84: Charte d'alignement stratégique | G84: Priorités contradictoires | H84: Moyenne | I84: Ressources mal allouées | J84: Organiser des ateliers d'alignement semestriels
C85: Calendrier des évaluations formalisé | D85: Un calendrier formel pour l'évaluation des objectifs est-il défini et respecté ? | E85: OUI | F85: Calendrier officiel d'évaluation | G85: Contrôles irréguliers | H85: Moyenne | I85: Détection tardive des écarts | J85: Intégrer au calendrier de gestion
C86: Affectation des responsables par objectif | D86: Chaque objectif a-t-il un responsable désigné pour son suivi et sa réalisation ? | E86: NON | F86: Matrice des responsables | G86: Dilution des responsabilités | H86: Moyenne | I86: Objectifs non atteints | J86: Publier la matrice et inclure dans les évaluations
B87: Vérifier l’existence d’un comité informatique regroupant les différentes directions | C87: Composition interdisciplinaire du comité | D87: Le comité de gouvernance inclut-il des membres aux compétences variées (DSI, métiers) ? | E87: PAS | F87: Composition du comité validée | G87: Biais décisionnels | H87: Moyenne | I87: Solutions inadaptées | J87: Imposer une représentation équilibrée
C88: Fréquence des réunions respectée | D88: Les réunions du comité se tiennent-elles selon la fréquence planifiée ? | E88: OUI | F88: PV des réunions et feuilles de présence | G88: Désengagement | H88: Faible | I88: Perte de légitimité | J88: Lier la participation aux objectifs individuels
C89: Ordres du jour et comptes-rendus disponibles | D89: Les ordres du jour et les comptes-rendus sont-ils systématiquement documentés ? | E89: NON | F89: Base documentaire des décisions | G89: Manque de transparence | H89: Moyenne | I89: Confiance érodée | J89: Centraliser dans un système de gestion
C90: Décisions impactant les priorités visibles | D90: Les décisions importantes sont-elles visibles et intégrées aux priorités stratégiques ? | E90: OUI | F90: Tableau de suivi des priorités | G90: Incohérences stratégiques | H90: Moyenne | I90: Efforts dispersés | J90: Aligner avec le BSC organisationnel
C91: Représentation équilibrée métiers/DSI | D91: La représentation entre les métiers et la DSI est-elle équilibrée dans le comité ? | E91: NON | F91: Rapport de parité métiers/DSI | G91: Déséquilibre d'influence | H91: Elevée | I91: Besoins mal pris en compte | J91: Instaurer des quotas
B92: Évaluer la pertinence des indicateurs de qualité et de performance | C92: Couverture des 4 perspectives BSC (si applicable) | D92: Les 4 perspectives du Balanced Scorecard (financière, clients, processus, apprentissage) sont-elles bien couvertes ? | E92: OUI | F92: Référentiel BSC complet | G92: Vision partielle | H92: Moyenne | I92: Déséquilibres de performance | J92: Couvrir les 4 perspectives
C93: Fréquence de mise à jour des indicateurs | D93: Les indicateurs de performance sont-ils mis à jour à des intervalles réguliers ? | E93: OUI | F93: Calendrier de mise à jour des KPI | G93: Données obsolètes | H93: Elevée | I93: Décisions inadaptées | J93: Automatiser les mises à jour
C94: Seuils d'alerte définis pour chaque KPI | D94: Des seuils d'alerte spécifiques sont-ils définis pour chaque indicateur clé ? | E94: NON | F94: Documentation des seuils d'alerte | G94: Réactivité insuffisante | H94: Elevée | I94: Crises non anticipées | J94: Implémenter des notifications automatiques
C95: Outils de visualisation accessibles | D95: Des outils de visualisation (dashboards) sont-ils accessibles à toutes les parties prenantes concernées ? | E95: OUI | F95: Guide d'utilisation des dashboards | G95: Mauvaise interprétation | H95: Moyenne | I95: Erreurs d'analyse | J95: Former les utilisateurs
C96: Processus d'ajustement des indicateurs | D96: Un processus d'ajustement des indicateurs est-il en place pour s'adapter aux changements ? | E96: OUI | F96: Procédure d'ajustement des KPI | G96: Rigidité organisationnelle | H96: Elevée | I96: Résistance au changement | J96: Prévoir des revues trimestrielles
B97: Vérifier que la DSI tient un tableau de bord de type BSC | C97: Existence des 4 dimensions (financière, clients, processus, apprentissage) | D97: Les indicateurs couvrent-ils toutes les dimensions critiques (finances, clients, processus, apprentissage) ? | E97: NON | F97: Rapport de couverture des dimensions | G97: Déséquilibres stratégiques | H97: Moyenne | I97: Performance globale médiocre | J97: Rééquilibrer les investissements
C98: Alignement avec les objectifs stratégiques | D98: Les indicateurs de performance sont-ils alignés avec les objectifs stratégiques de l'organisation ? | E98: PAS | F98: Matrice d'alignement stratégique | G98: Efforts non coordonnés | H98: Moyenne | I98: Efficacité réduite | J98: Valider avec la direction générale
C99: Mise à jour mensuelle/trimestrielle | D99: Les indicateurs sont-ils actualisés mensuellement ou trimestriellement ? | E99: OUI | F99: Historique des mises à jour | G99: Décisions sur données périmées | H99: Elevée | I99: Opportunités manquées | J99: Auditer mensuellement
C100: Diffusion aux parties prenantes | D100: Les résultats des indicateurs sont-ils partagés avec les parties prenantes concernées ? | E100: OUI | F100: PV de diffusion des résultats | G100: Communication défaillante | H100: Elevée | I100: Manque d'appropriation | J100: Multiplier les canaux de diffusion
...

Sheet 4.3 Contrôle des Projets Inform
A1: Points de Contrôle | B1: Objectifs de Contrôle | C1: Critère d’Évaluation | D1: Question d’Évaluation | E1: Réponses | F1: Documents requis | G1: Risques | H1: Criticités | I1: Conséquences | J1: Recommandations
A2: Objectifs et enjeux du projet | B2: S'assurer qu'une étude de la valeur et des études d'opportunité et d'impacts ont été réalisées | C2: Étude de valeur documentée | D2: Une étude de valeur formalisée a-t-elle été produite ? | E2: OUI | F2: Rapport d'étude de valeur | G2: Choix non optimisé | H2: Elevée | I2: Investissements inefficaces | J2: Formaliser une grille multicritères pour évaluer les options
C3: Analyse d’impact complète | D3: Une analyse d’impact (technique, métier, sécurité…) a-t-elle été réalisée ? | E3: OUI | F3: Analyse d'impact complète | G3: Effets secondaires non anticipés | H3: Elevée | I3: Problèmes opérationnels | J3: Impliquer tous les métiers dans l'analyse
C4: Bilan critique des processus existants | D4: Un bilan critique des processus existants a-t-il été réalisé avant le projet ? | E4: NON | F4: Bilan des processus existants | G4: Améliorations manquées | H4: Moyenne | I4: Gains non maximisés | J4: Auditer les processus avant projet
C5: Optimisation préalable des processus | D5: Les processus ont-ils été optimisés en amont du projet ? | E5: PAS | F5: Plan d'optimisation préalable | G5: Solutions sous-optimales | H5: Moyenne | I5: Coûts supplémentaires | J5: Faire valider par un comité transverse
C6: Gains de performance quantifiés | D6: Les gains de performance attendus ont-ils été chiffrés ? | E6: OUI | F6: Étude de gains chiffrée | G6: ROI non atteint | H6: Elevée | I6: Échec économique | J6: Benchmarker avec des projets similaires
B7: S'assurer que les objectifs et périmètres du projet sont définis, partagés et stabilisés | C7: Périmètre signé par la direction | D7: Le périmètre du projet a-t-il été validé et signé par la direction ? | E7: OUI | F7: Périmètre signé | G7: Dérives de scope | H7: Elevée | I7: Retards et dépassements | J7: Mettre en place un comité de changement
C8: Objectifs SMART formalisés | D8: Les objectifs sont-ils définis selon la méthode SMART ? | E8: NON | F8: Fiche d'objectifs SMART | G8: Résultats flous | H8: Moyenne | I8: Évaluation difficile | J8: Former les équipes à la méthode SMART
C9: Document partagé avec les parties prenantes | D9: Le document de cadrage est-il partagé avec toutes les parties prenantes ? | E9: OUI | F9: Document de cadrage partagé | G9: Incompréhensions | H9: Moyenne | I9: Attentes divergentes | J9: Organiser des ateliers de partage
C10: Versionning des modifications | D10: Les modifications du périmètre sont-elles tracées et versionnées ? | E10: OUI | F10: Historique des versions | G10: Traçabilité perdue | H10: Moyenne | I10: Conflits sur les évolutions | J10: Utiliser un outil de gestion de versions
C11: Alignement avec la stratégie SI | D11: Le projet est-il aligné avec la stratégie SI de l’organisation ? | E11: NON | F11: Rapport d'alignement SI | G11: Incohérences techniques | H11: Elevée | I11: Problèmes d'intégration | J11: Valider avec l'architecte SI
B12: S'assurer que les coûts sont évalués | C12: Budget prévisionnel détaillé | D12: Un budget prévisionnel détaillé a-t-il été établi ? | E12: PAS | F12: Budget prévisionnel | G12: Dépassements financiers | H12: Elevée | I12: Manque de ressources | J12: Prévoir une réserve de gestion (10-15%)
C13: Coûts de développement estimés | D13: Les coûts de développement sont-ils clairement estimés ? | E13: OUI | F13: Estimation des coûts dev | G13: Sous-évaluation | H13: Elevée | I13: Retards de livraison | J13: Appliquer la méthode des points de fonction
C14: Coûts de maintenance prévus | D14: Les coûts de maintenance sont-ils anticipés et budgétisés ? | E14: OUI | F14: Plan de maintenance | G14: Coûts cachés | H14: Moyenne | I14: Budgets dépassés | J14: Intégrer le TCO (Total Cost of Ownership)
C15: ROI calculé | D15: Un retour sur investissement (ROI) a-t-il été calculé ? | E15: NON | F15: Étude ROI | G15: Rentabilité non prouvée | H15: Elevée | I15: Échec économique | J15: Valider les hypothèses avec la direction financière
C16: Financement sécurisé | D16: Le financement du projet est-il entièrement sécurisé ? | E16: OUI | F16: Contrats de financement | G16: Interruptions de paiement | H16: Elevée | I16: Arrêt du projet | J16: Sécuriser les engagements par écrit
B17: S'assurer que les liens et impacts avec des projets connexes sont pris en compte | C17: Cartographie des interdépendances | D17: Une cartographie des dépendances inter-systèmes est-elle disponible ? | E17: OUI | F17: Cartographie des dépendances | G17: Problèmes d'interfaçage | H17: Elevée | I17: Dysfonctionnements | J17: Prototyper les interfaces critiques
C18: Analyse d’impact réseau/datacenter | D18: L’impact du projet sur le réseau et les datacenters a-t-il été évalué ? | E18: NON | F18: Analyse impact infrastructure | G18: Goulots techniques | H18: Elevée | I18: Performances médiocres | J18: Tester en environnement réel
C19: Plan de synchronisation | D19: Un plan de synchronisation avec les autres projets est-il prévu ? | E19: PAS | F19: Plan de synchronisation | G19: Chevauchements néfastes | H19: Faible | I19: Conflits de ressources | J19: Utiliser un outil de portfolio management
C20: Gestion des ressources partagées | D20: Les ressources partagées (humaines, matérielles) sont-elles identifiées et planifiées ? | E20: OUI | F20: Inventaire des ressources | G20: Surcharge des équipes | H20: Moyenne | I20: Burn-out | J20: Limiter le multitâche (<3 projets simultanés)
C21: Revue des chevauchements | D21: Les chevauchements avec d’autres projets ont-ils été analysés ? | E21: OUI | F21: Analyse des chevauchements | G21: Doublons d'efforts | H21: Moyenne | I21: Gaspillage | J21: Centraliser la vue des projets
B22: S'assurer que les principaux acteurs sont identifiés | C22: Matrice RACI complète | D22: Une matrice RACI complète a-t-elle été formalisée ? | E22: NON | F22: Matrice RACI complète | G22: Responsabilités floues | H22: Elevée | I22: Retards de décision | J22: Valider la matrice avec chaque partie
C23: Fiches de rôle validées | D23: Les fiches de rôle ont-elles été validées par les parties concernées ? | E23: OUI | F23: Fiches de rôle signées | G23: Attentes divergentes | H23: Moyenne | I23: Conflits internes | J23: Organiser des ateliers de clarification
C24: Niveaux de délégation définis | D24: Les niveaux de délégation de décision sont-ils clairement définis ? | E24: OUI | F24: Charte de délégation | G24: Blocages hiérarchiques | H24: Moyenne | I24: Décisions retardées | J24: Définir des seuils de délégation clairs
C25: Plan de communication établi | D25: Un plan de communication a-t-il été établi et diffusé ? | E25: NON | F25: Plan de communication | G25: Informations parcellaires | H25: Moyenne | I25: Rumeurs | J25: Diffuser un bulletin hebdomadaire
C26: Organigramme projet à jour | D26: L’organigramme du projet est-il à jour et reflète-t-il l’organisation réelle ? | E26: PAS | F26: Organigramme actualisé | G26: Structure confuse | H26: Moyenne | I26: Mauvaise coordination | J26: Publier sur l'intranet projet
A27: Étude d'opportunité et expression des besoins | B27: S'assurer que l'expression détaillée des besoins est formalisée dans un cahier des charges | C27: Besoins fonctionnels détaillés | D27: Les besoins fonctionnels ont-ils été formalisés avec précision ? | E27: OUI | F27: Cahier des charges complet | G27: Besoins incomplets | H27: Elevée | I27: Livraison inadaptée | J27: Faire valider par les utilisateurs finaux
C28: Contraintes techniques listées | D28: Les contraintes techniques ont-elles été identifiées et documentées ? | E28: OUI | F28: Liste des contraintes techniques | G28: Problèmes tardifs | H28: Elevée | I28: Refactoring coûteux | J28: Auditer l'existant avant conception
C29: Populations ciblées identifiées | D29: Les populations cibles (internes ou externes) ont-elles été identifiées ? | E29: NON | F29: Profils utilisateurs | G29: Solutions non ergonomiques | H29: Moyenne | I29: Rejet utilisateur | J29: Réaliser des tests utilisateurs précoces
C30: Priorisations validées | D30: Les priorités ont-elles été définies et validées avec les parties prenantes ? | E30: OUI | F30: Grille de priorisation | G30: Mauvaises allocations | H30: Moyenne | I30: Frustrations | J30: Utiliser la méthode MoSCoW
C31: Cohérence avec le plan directeur informatique | D31: Le projet est-il cohérent avec le plan directeur informatique ? | E31: OUI | F31: Alignement PDI | G31: Incohérences stratégiques | H31: Elevée | I31: Obsolescence rapide | J31: Valider avec le comité architecture
B32: S'assurer que la direction est bien impliquée dans le projet | C32: PV de réunions de cadrage | D32: Des procès-verbaux ont-ils été rédigés pour toutes les réunions de cadrage ? | E32: NON | F32: PV de réunions DG | G32: Décisions non formalisées | H32: Elevée | I32: Désalignement | J32: Envoyer les PV sous 48h
C33: Décideurs identifiés dans l’organigramme | D33: Les décideurs sont-ils clairement identifiés dans l’organigramme projet ? | E33: PAS | F33: Organigramme décisionnel | G33: Blocages hiérarchiques | H33: Moyenne | I33: Retards | J33: Clarifier les circuits de validation
C34: Budget validé par la DG | D34: Le budget a-t-il été validé par la direction générale ? | E34: OUI | F34: Budget validé | G34: Incertitudes financières | H34: Elevée | I34: Arrêt brutal | J34: Sécuriser les fonds avant démarrage
C35: Feuille de route approuvée | D35: Une feuille de route du projet a-t-elle été approuvée ? | E35: OUI | F35: Feuille de route signée | G35: Dérives temporelles | H35: Elevée | I35: Retards majeurs | J35: Suivre les jalons mensuellement
C36: Reporting régulier à la direction | D36: Un reporting régulier est-il effectué auprès de la direction ? | E36: NON | F36: Reporting régulier | G36: Problèmes cachés | H36: Moyenne | I36: Surprises négatives | J36: Imposer des indicateurs clés
B37: S'assurer que les compétences du personnel sont en adéquation avec les tâches | C37: Matrice compétences/ressources | D37: Une matrice des compétences et des ressources est-elle disponible ? | E37: OUI | F37: Matrice compétences | G37: Inadéquation des ressources | H37: Elevée | I37: Échec technique | J37: Auditer les compétences dès le démarrage
C38: Plan de formation établi | D38: Un plan de formation a-t-il été défini pour accompagner le projet ? | E38: OUI | F38: Plan de formation | G38: Manque de savoir-faire | H38: Moyenne | I38: Sous-performance | J38: Budgetter 5% du projet en formation
C39: Recrutements complétés | D39: Les recrutements nécessaires ont-ils été effectués ? | E39: NON | F39: Contrats de recrutement | G39: Postes vacants | H39: Elevée | I39: Retards critiques | J39: Anticiper les délais de recrutement
C40: Sous-traitance encadrée | D40: La sous-traitance éventuelle est-elle contractualisée et encadrée ? | E40: PAS | F40: Contrats sous-traitance | G40: Dépendance externe | H40: Moyenne | I40: Perte de contrôle | J40: Limiter à 30% de l'effort total
C41: Tutorat interne organisé | D41: Un tutorat interne est-il mis en place pour capitaliser les savoir-faire ? | E41: OUI | F41: Programme de tutorat | G41: Perte de connaissances | H41: Moyenne | I41: Erreurs récurrentes | J41: Formaliser les binômes expérimentés/nouveaux
B42: S'assurer que l'étude d'opportunité est validée | C42: Document signé par la MOA | D42: Le document de cadrage a-t-il été signé par la Maîtrise d’Ouvrage (MOA) ? | E42: OUI | F42: Cadrage signé MOA | G42: Attentes divergentes | H42: Elevée | I42: Conflits MOA/MOE | J42: Organiser une revue formelle
C43: Avis DSI formalisé | D43: L’avis de la DSI sur le projet a-t-il été formalisé ? | E43: NON | F43: Avis DSI formalisé | G43: Problèmes techniques tardifs | H43: Elevée | I43: Refonte coûteuse | J43: Impliquer la DSI dès l'avant-projet
C44: Réserves documentées | D44: Les réserves identifiées sont-elles formalisées dans un document officiel ? | E44: OUI | F44: Registre des réserves | G44: Risques ignorés | H44: Moyenne | I44: Surprises négatives | J44: Mettre à jour mensuellement
C45: Scénarios alternatifs analysés | D45: Des scénarios alternatifs ont-ils été envisagés et analysés ? | E45: OUI | F45: Étude d'alternatives | G45: Solution sous-optimale | H45: Elevée | I45: Coûts supplémentaires | J45: Évaluer 3 scénarios minimum
C46: Faisabilité technique validée | D46: La faisabilité technique du projet a-t-elle été validée ? | E46: NON | F46: Rapport de faisabilité | G46: Échec technique | H46: Elevée | I46: Abandon du projet | J46: Faire valider par un expert externe
B47: S'assurer que les bénéfices attendus et la rentabilité économique du projet sont définis | C47: Gains productivité chiffrés | D47: Les gains en productivité ont-ils été chiffrés de manière précise ? | E47: PAS | F47: Étude de gains | G47: Bénéfices non matérialisés | H47: Elevée | I47: Échec économique | J47: Lier aux objectifs stratégiques
C48: Indicateurs de performance définis | D48: Des indicateurs de performance sont-ils définis et suivis ? | E48: OUI | F48: Tableau de bord KPI | G48: Suivi inefficace | H48: Moyenne | I48: Dérives non détectées | J48: Automatiser le reporting
C49: Avantages concurrentiels listés | D49: Les avantages concurrentiels liés au projet ont-ils été identifiés et listés ? | E49: OUI | F49: Analyse concurrentielle | G49: Avantage manqué | H49: Faible | I49: Opportunités perdues | J49: Benchmarker les solutions
C50: Impacts métiers modélisés | D50: Les impacts métiers sont-ils modélisés (ex : via des schémas, matrices d’impact…) ? | E50: NON | F50: Modélisation impacts | G50: Perturbations opérationnelles | H50: Elevée | I50: Rejet utilisateur | J50: Simuler avant déploiement
C51: Calendrier de réalisation des bénéfices | D51: Un calendrier de réalisation des bénéfices a-t-il été établi ? | E51: OUI | F51: Calendrier bénéfices | G51: Retour retardé | H51: Moyenne | I51: Frustration DG | J51: Planifier des livraisons intermédiaires
A52: Planification | B52: S'assurer qu'il existe un planning directeur commun à tout le projet | C52: Planning directeur validé | D52: Le planning directeur a-t-il été validé par les instances de pilotage ? | E52: OUI | F52: Planning directeur | G52: Dérives temporelles | H52: Elevée | I52: Retards coûteux | J52: Utiliser un outil de Gantt
C53: Diagramme de Gantt détaillé | D53: Un diagramme de Gantt détaillé existe-t-il pour le suivi du projet ? | E53: NON | F53: Diagramme de Gantt | G53: Visibilité limitée | H53: Moyenne | I53: Mauvaise anticipation | J53: Mettre à jour hebdomadairement
C54: Jalons contractuels | D54: Les jalons contractuels sont-ils définis et suivis ? | E54: PAS | F54: Contrat de jalons | G54: Pénalités non appliquées | H54: Moyenne | I54: Laxisme | J54: Lier les paiements aux jalons
C55: Plan de charge ressources | D55: Un plan de charge des ressources est-il établi ? | E55: OUI | F55: Plan de charge | G55: Surcharge des ressources | H55: Elevée | I55: Burn-out | J55: Limiter à 80% d'occupation
C56: Budget phasé | D56: Le budget est-il phasé dans le temps ? | E56: OUI | F56: Budget phasé | G56: Dépenses incontrôlées | H56: Elevée | I56: Dépassements | J56: Valider chaque tranche
B57: S'assurer qu'il existe une évaluation des risques liés à la nature du projet | C57: Matrice risques/probabilités | D57: Une matrice croisant risques et probabilités est-elle en place ? | E57: NON | F57: Matrice risques | G57: Problèmes non anticipés | H57: Elevée | I57: Crises | J57: Mettre à jour mensuellement
C58: Plan d'atténuation | D58: Un plan d'atténuation des risques est-il défini ? | E58: OUI | F58: Plan d'atténuation | G58: Réactions tardives | H58: Elevée | I58: Impacts aggravés | J58: Désigner des responsables risques
C59: Fiches risque par lot | D59: Des fiches de risques existent-elles pour chaque lot du projet ? | E59: OUI | F59: Fiches risques | G59: Vulnérabilités ignorées | H59: Moyenne | I59: Incidents répétés | J59: Classer par criticité
C60: Responsables risques désignés | D60: Les responsables pour chaque risque sont-ils désignés ? | E60: NON | F60: Désignation responsables | G60: Actions non suivies | H60: Moyenne | I60: Risques persistants | J60: Intégrer aux objectifs individuels
C61: Revue trimestrielle des risques | D61: Une revue des risques est-elle planifiée au moins tous les trimestres ? | E61: PAS | F61: Calendrier revues risques | G61: Détection tardive | H61: Moyenne | I61: Crises évitables | J61: Organiser des revues trimestrielles
B62: S'assurer que les lots sont bien identifiés et suivis dans le planning | C62: Découpage en lots validé | D62: Le découpage en lots du projet a-t-il été validé ? | E62: OUI | F62: Découpage en lots | G62: Déséquilibres de charge | H62: Moyenne | I62: Retards localisés | J62: Équilibrer les lots
C63: Chefs de lot nommés | D63: Les chefs de lot ont-ils été désignés ? | E63: OUI | F63: Désignation chefs de lot | G63: Coordination défaillante | H63: Moyenne | I63: Silos | J63: Organiser des points hebdomadaires
C64: Avancement mensuel mesuré | D64: L’avancement du projet est-il mesuré au moins chaque mois ? | E64: NON | F64: Rapport d'avancement | G64: Problèmes cachés | H64: Moyenne | I64: Dérives | J64: Imposer des indicateurs clés
C65: Points de synchronisation définis | D65: Des points de synchronisation sont-ils planifiés entre les lots ou sous-projets ? | E65: OUI | F65: Plan de synchronisation | G65: Incohérences | H65: Moyenne | I65: Rejets | J65: Harmoniser les livrables
C66: Procédures d'alerte opérationnelles | D66: Des procédures d’alerte sont-elles définies et fonctionnelles ? | E66: OUI | F66: Procédures d'alerte | G66: Réactions tardives | H66: Elevée | I66: Crises | J66: Tester les circuits
B67: S'assurer qu'une méthode d'estimation des charges est appliquée | C67: Référentiel métrique existant | D67: Un référentiel de métriques est-il utilisé pour mesurer l’avancement ? | E67: NON | F67: Référentiel métrique | G67: Estimations fantaisistes | H67: Moyenne | I67: Dérives | J67: Utiliser l'historique projet
C68: Historique des projets analysé | D68: Les données issues de projets antérieurs ont-elles été analysées ? | E68: PAS | F68: Analyse historique | G68: Répétition d'erreurs | H68: Moyenne | I68: Gaspillage | J68: Capitaliser les retours d'expérience
C69: Outils de calcul utilisés | D69: Des outils de calcul fiables sont-ils utilisés pour les prévisions/estimations ? | E69: OUI | F69: Outils de calcul | G69: Données erronées | H69: Moyenne | I69: Mauvaises décisions | J69: Valider les algorithmes
C70: Marge d'erreur documentée | D70: Les marges d’erreur sont-elles identifiées et documentées ? | E70: OUI | F70: Documentation marges | G70: Incertitudes sous-évaluées | H70: Moyenne | I70: Surprises | J70: Appliquer la loi de Hofstadter
C71: Révisions planifiées | D71: Des révisions du planning ou budget sont-elles programmées à l’avance ? | E71: NON | F71: Calendrier de révisions | G71: Dérives non corrigées | H71: Moyenne | I71: Échec | J71: Prévoir des points mensuels
B72: S'assurer que la mise en adéquation des moyens techniques est cohérente | C72: Inventaire matériel disponible | D72: Un inventaire des ressources matérielles disponibles est-il établi ? | E72: OUI | F72: Inventaire matériel | G72: Pénuries techniques | H72: Elevée | I72: Blocages | J72: Pré-commander le matériel critique
C73: Logiciels licenciés | D73: Les logiciels nécessaires sont-ils acquis sous licences valides ? | E73: OUI | F73: Licences logicielles | G73: Non-conformité | H73: Elevée | I73: Pénalités | J73: Centraliser la gestion
C74: Capacité infrastructure vérifiée | D74: La capacité de l’infrastructure est-elle suffisante pour le projet ? | E74: NON | F74: Audit infrastructure | G74: Capacité insuffisante | H74: Elevée | I74: Surcharges | J74: Tester en charge réelle
C75: Contrats fournisseurs signés | D75: Les contrats avec les fournisseurs sont-ils signés et accessibles ? | E75: PAS | F75: Contrats fournisseurs | G75: Délais non tenus | H75: Elevée | I75: Retards | J75: Négocier des pénalités
C76: Plan de montée en charge | D76: Un plan de montée en charge des ressources a-t-il été défini ? | E76: OUI | F76: Plan montée en charge | G76: Goulots techniques | H76: Elevée | I76: Performances médiocres | J76: Simuler à 120% de charge
A77: Instances de pilotage | B77: S'assurer que la structure de pilotage est formalisée et connue de tous les acteurs | C77: Organigramme du pilotage diffusé | D77: L’organigramme du pilotage est-il diffusé à toutes les parties concernées ? | E77: OUI | F77: Organigramme pilotage | G77: Gouvernance floue | H77: Elevée | I77: Décisions chaotiques | J77: Publier et diffuser largement
C78: Niveaux de délégation documentés | D78: Les niveaux de délégation sont-ils formalisés par écrit ? | E78: NON | F78: Charte de délégation | G78: Blocages hiérarchiques | H78: Moyenne | I78: Retards | J78: Formaliser les seuils
C79: Objectifs des délégations atteints | D79: Les objectifs fixés pour les délégations sont-ils atteints ? | E79: OUI | F79: Rapport objectifs délégation | G79: Contrôle perdu | H79: Moyenne | I79: Dérives | J79: Mettre en place des garde-fous
C80: Comité de pilotage actif | D80: Un comité de pilotage est-il actif et régulièrement consulté ? | E80: OUI | F80: PV comité pilotage | G80: Décisions non tracées | H80: Elevée | I80: Conflits | J80: Archiver systématiquement
C81: Comité projet opérationnel | D81: Un comité projet est-il constitué et opérationnel ? | E81: NON | F81: PV comité projet | G81: Actions non suivies | H81: Moyenne | I81: Retards | J81: Assigner des responsables
B82: S'assurer que les participants aux différents comités sont représentatifs | C82: Utilisateurs intégrés aux comités | D82: Les utilisateurs finaux sont-ils représentés dans les comités ? | E82: PAS | F82: Liste participants comités | G82: Représentation incomplète | H82: Moyenne | I82: Biais décisionnels | J82: Imposer une présence métier
C83: Participants ayant pouvoir décisionnel | D83: Les participants aux comités disposent-ils du pouvoir de décision ? | E83: OUI | F83: PV avec décideurs | G83: Impasse sur les objections | H83: Moyenne | I83: Résistances | J83: Recueillir les votes formels
C84: Nombre de participants conforme | D84: Le nombre de participants est-il conforme aux recommandations ? | E84: OUI | F84: Rapport assiduité | G84: Désengagement | H84: Moyenne | I84: Perte de légitimité | J84: Publier les statistiques
C85: Gestionnaires production impliqués | D85: Les gestionnaires de production sont-ils impliqués dès la phase projet ? | E85: NON | F85: Liste gestionnaires production | G85: Problèmes post-livraison | H85: Elevée | I85: Incidents | J85: Impliquer dès la conception
C86: Fréquence des réunions adaptée | D86: La fréquence des réunions est-elle adaptée aux besoins du projet ? | E86: OUI | F86: Calendrier réunions | G86: Rythme inadapté | H86: Moyenne | I86: Retards | J86: Ajuster selon la phase projet
B87: S'assurer qu'il existe des indicateurs de suivi du projet | C87: Tableaux de bord mis à jour | D87: Les tableaux de bord projet sont-ils à jour et pertinents ? | E87: OUI | F87: Tableaux de bord | G87: Visibilité insuffisante | H87: Moyenne | I87: Décisions tardives | J87: Automatiser les remontées
C88: Indicateurs adaptés à l'étape | D88: Les indicateurs suivis sont-ils adaptés à l’étape du projet ? | E88: NON | F88: Rapport indicateurs | G88: Suivi inadapté | H88: Faible | I88: Dérives | J88: Aligner sur les objectifs
C89: Pertinence des métriques | D89: Les métriques utilisées sont-elles pertinentes et validées ? | E89: PAS | F89: Étude pertinence métriques | G89: Mesures trompeuses | H89: Moyenne | I89: Mauvaises décisions | J89: Valider avec un expert
C90: Formalisme de reporting défini | D90: Un formalisme de reporting est-il défini et respecté ? | E90: OUI | F90: Modèle reporting | G90: Informations parcellaires | H90: Moyenne | I90: Analyse incomplète | J90: Standardiser les templates
C91: Fréquence de reporting respectée | D91: La fréquence du reporting est-elle respectée ? | E91: OUI | F91: Calendrier reporting | G91: Retards d'information | H91: Faible | I91: Réactivité faible | J91: Imposer des échéances
B92: S'assurer que la traçabilité des évolutions de périmètre, coût et délai est assurée | C92: Évolutions de périmètre tracées | D92: Les changements de périmètre sont-ils tracés et justifiés ? | E92: NON | F92: Registre changements | G92: Périmètre flou | H92: Elevée | I92: Dérives | J92: Exiger une approbation écrite
C93: Modifications de coûts historisées | D93: Les modifications de coûts sont-elles historisées ? | E93: OUI | F93: Historique coûts | G93: Dépassements cachés | H93: Elevée | I93: Dettes | J93: Comparer prévu/réel
C94: Ajustements de délais documentés | D94: Les ajustements de délais sont-ils documentés ? | E94: OUI | F94: Journal délais | G94: Retards cumulatifs | H94: Elevée | I94: Échec | J94: Publier un diagramme de retard
C95: Décisions archivées | D95: Les décisions prises sont-elles formellement archivées ? | E95: NON | F95: Archives décisions | G95: Conflits mémoriels | H95: Moyenne | I95: Répétition d'erreurs | J95: Centraliser les PV
C96: Accès centralisé aux historiques | D96: L’accès aux historiques (décisions, coûts, délais…) est-il centralisé ? | E96: PAS | F96: Base documentaire | G96: Information perdue | H96: Moyenne | I96: Gaspillage de temps | J96: Mettre en place un ECM
B97: S'assurer qu'il existe une réunion périodique de revue du projet | C97: Calendrier des revues établi | D97: Un calendrier de revue (revue de phase, jalon…) est-il établi ? | E97: OUI | F97: Calendrier revues | G97: Points manqués | H97: Moyenne | I97: Problèmes non traités | J97: Synchroniser avec les jalons
C98: PV des réunions disponibles | D98: Les procès-verbaux des réunions sont-ils disponibles et accessibles ? | E98: OUI | F98: PV de revues | G98: Actions non tracées | H98: Moyenne | I98: Retards | J98: Assigner des responsables
C99: Actions correctives suivies | D99: Les actions correctives sont-elles suivies et clôturées ? | E99: NON | F99: Suivi actions correctives | G99: Problèmes récurrents | H99: Moyenne | I99: Échec | J99: Imposer des dates butoir
C100: Participants assidus | D100: Le taux d’assiduité des participants aux réunions est-il satisfaisant ? | E100: OUI | F100: Rapport assiduité | G100: Désengagement | H100: Moyenne | I100: Perte d'efficacité | J100: Communiquer les taux
...

Sheet 4.4 Support Utilisateur et de l
A1: Points de Contrôle | B1: Objectifs de Contrôle | C1: Critère d’Évaluation | D1: Question d’Évaluation | E1: Réponses | F1: Documents requis | G1: Risques | H1: Criticités | I1: Conséquences | J1: Recommandations
A2: Fonction support : audit fiabilité et sécurité | B2: S’assurer qu’une structure de centre d’assistance (help-desk) (HD) est mise en place | C2: Existence d'une équipe dédiée HD. | D2: Existe-t-il une équipe dédiée au help-desk ? | E2: OUI | F2: Organigramme de l'équipe, Fiches de poste, Contrats des membres | G2: Absence de responsabilités claires, turnover élevé, manque de compétences | H2: Elevée | I2: Impact modéré sur la qualité ou les délais de service. | J2: Existence d'une équipe dédiée HD
C3: Documentation des rôles et responsabilités de l'équipe. | D3: Les rôles et responsabilités de l'équipe help-desk sont-ils documentés ? | E3: OUI | F3: Charte d'équipe, Fiches de mission, Procès-verbal de validation | G3: Rôles mal définis, chevauchements, conflits d'attribution | H3: Moyenne | I3: Peut entraîner une interruption majeure du service ou une perte importante de données. | J3: Documentation des rôles et responsabilités de l'équipe
C4: Local physique ou virtuel défini pour le HD. | D4: Un local physique ou virtuel est-il défini pour le help-desk ? | E4: OUI | F4: Plan des locaux, Contrat d'hébergement cloud, Accès VPN | G4: Manque d'accessibilité, problèmes de sécurité, isolement de l'équipe | H4: Moyenne | I4: Impact mineur, généralement sans conséquence grave. | J4: Local physique ou virtuel défini pour le HD
C5: Budget alloué au fonctionnement du HD. | D5: Existe-t-il des preuves de la mise en œuvre du help-desk (PV, charte, etc.) ? | E5: NON | F5: Budget annuel approuvé, Factures, Rapport de dépenses | G5: Sous-financement, dépenses imprévues, manque de ressources | H5: Elevée | I5: Impact modéré sur la qualité ou les délais de service. | J5: Budget alloué au fonctionnement du HD
C6: Preuve de la mise en œuvre (procès-verbal, charte, etc.) | D6: La procédure de gestion des demandes est-elle documentée et accessible ? | E6: NON | F6: Procès-verbal de création, Charte HD, Rapport de lancement | G6: Non-conformité, manque de traçabilité, contestations | H6: Moyenne | I6: Impact mineur, généralement sans conséquence grave. | J6: Preuve de la mise en œuvre (procès-verbal, charte, etc.)
B7: S’assurer qu’une procédure de gestion des demandes d’assistance est diffusée et connue des utilisateurs | C7: Procédure documentée et accessible (intranet, wiki). | D7: Les utilisateurs sont-ils formés sur la procédure de gestion des demandes ? | E7: PAS | F7: Lien vers l'intranet, Manuel utilisateur, Capture d'écran de la page wiki | G7: Procédure obsolète, accès difficile, incomplétude | H7: Elevée | I7: Impact modéré sur la qualité ou les délais de service. | J7: Procédure documentée et accessible (intranet, wiki)
C8: Formation des utilisateurs sur la procédure | D8: Existe-t-il un support (FAQ, guide) pour les utilisateurs ? | E8: NON | F8: Planning de formation, Supports de formation, Liste des participants | G8: Manque de compréhension, erreurs fréquentes, résistance au changement | H8: Elevée | I8: Peut entraîner une interruption majeure du service ou une perte importante de données. | J8: Formation des utilisateurs sur la procédure
C9: Existence d'un support (FAQ, guide). | D9: Les utilisateurs ont-ils donné leur feedback sur la clarté de la procédure ? | E9: OUI | F9: FAQ mise en ligne, Guide utilisateur, Capture d'écran du support | G9: Information inexacte, support peu consulté, mise à jour rare | H9: Moyenne | I9: Impact modéré sur la qualité ou les délais de service. | J9: Existence d'un support (FAQ, guide)
C10: Feedback des utilisateurs sur la clarté de la procédure. | D10: Existe-t-il des preuves de diffusion de la procédure (emails, affichage) ? | E10: PAS | F10: Enquête de satisfaction, Retours écrits, Statistiques de compréhension | G10: Désengagement, retours non pris en compte, frustration | H10: Faible | I10: Impact mineur, généralement sans conséquence grave. | J10: Feedback des utilisateurs sur la clarté de la procédure
C11: Preuve de diffusion (emails, affichage). | D11: La procédure d'escalade est-elle formalisée avec des niveaux et des acteurs définis ? | E11: OUI | F11: Copie d'email, Photo de l'affichage, Log de diffusion | G11: Communication inefficace, canaux inadaptés, non-réception | H11: Moyenne | I11: Impact mineur, généralement sans conséquence grave. | J11: Preuve de diffusion (emails, affichage)
B12: S’assurer qu’une procédure d'escalade mise en place | C12: Procédure d'escalade formalisée (niveaux, acteurs). | D12: Des délais sont-ils définis pour chaque niveau d'escalade ? | E12: OUI | F12: Document de procédure, Organigramme d'escalade, Liste des acteurs | G12: Retards de traitement, confusion des acteurs, blocages | H12: Elevée | I12: Impact mineur, généralement sans conséquence grave. | J12: Procédure d'escalade formalisée (niveaux, acteurs)
C13: Délais définis pour chaque niveau d'escalade. | D13: Existe-t-il un historique de l'utilisation de la procédure d'escalade ? | E13: OUI | F13: Tableau des délais, SLA interne, Exemples de tickets avec délais | G13: Délais non respectés, priorités mal gérées, insatisfaction | H13: Elevée | I13: Impact modéré sur la qualité ou les délais de service. | J13: Délais définis pour chaque niveau d'escalade
C14: Historique d'utilisation de la procédure. | D14: Les équipes sont-elles formées sur la procédure d'escalade ? | E14: OUI | F14: Logs d'escalade, Rapport d'incidents, Tickets résolus | G14: Manque d'amélioration, répétition des erreurs, absence d'analyse | H14: Moyenne | I14: Impact modéré sur la qualité ou les délais de service. | J14: Historique d'utilisation de la procédure
C15: Formation des équipes sur l'escalade. | D15: La procédure d'escalade est-elle intégrée dans l'outil de ticketing ? | E15: OUI | F15: Plan de formation, Attestations de formation, Évaluation des compétences | G15: Mauvaise application, incompétence, manque de réactivité | H15: Elevée | I15: Peut entraîner une interruption majeure du service ou une perte importante de données. | J15: Formation des équipes sur l'escalade
C16: Intégration de la procédure dans l'outil de ticketing. | D16: Les zones géographiques couvertes par le help-desk sont-elles documentées ? | E16: OUI | F16: Capture d'écran de l'outil, Manuel technique, Procès-verbal de déploiement | G16: Dysfonctionnements, silos informationnels, double saisie | H16: Elevée | I16: Impact modéré sur la qualité ou les délais de service. | J16: Intégration de la procédure dans l'outil de ticketing
B17: S’assurer de la couverture géographique du HD | C17: Zones géographiques couvertes documentées. | D17: Existe-t-il des preuves de prise en charge des demandes hors siège ? | E17: OUI | F17: Carte des zones, Liste des sites, Accord de couverture | G17: Zones non couvertes, délais allongés, inégalité de service | H17: Moyenne | I17: Peut entraîner une interruption majeure du service ou une perte importante de données. | J17: Zones géographiques couvertes documentées
C18: Preuve de prise en charge des demandes hors siège. | D18: Le help-desk s'adapte-t-il aux fuseaux horaires des utilisateurs ? | E18: OUI | F18: Tickets hors siège, Rapport de support, Témoignages utilisateurs | G18: Demandes ignorées, retards, manque de ressources locales | H18: Elevée | I18: Impact modéré sur la qualité ou les délais de service. | J18: Preuve de prise en charge des demandes hors siège
C19: Adaptabilité aux fuseaux horaires. | D19: Quelles langues sont supportées pour les utilisateurs internationaux ? | E19: OUI | F19: Tableau des plages horaires, Contrats des équipes offshore, Politique de garde | G19: Disponibilité insuffisante, temps de réponse inégaux | H19: Moyenne | I19: Impact modéré sur la qualité ou les délais de service. | J19: Adaptabilité aux fuseaux horaires
C20: Langues supportées pour les utilisateurs internationaux. | D20: Des mesures sont-elles prévues pour les utilisateurs distants (VPN, accès sécurisé) ? | E20: OUI | F20: Liste des langues, Supports multilingues, Contrats des traducteurs | G20: Barrière linguistique, incompréhension, frustration utilisateur | H20: Faible | I20: Impact modéré sur la qualité ou les délais de service. | J20: Langues supportées pour les utilisateurs internationaux
C21: Mesures pour les utilisateurs distants (VPN, accès sécurisé). | D21: Existe-t-il une liste des applications/logiciels supportés par le help-desk ? | E21: OUI | F21: Politique de sécurité, Guide d'accès distant, Logs de connexion | G21: Problèmes de connexion, sécurité compromise, accès limité | H21: Elevée | I21: Peut entraîner une interruption majeure du service ou une perte importante de données. | J21: Mesures pour les utilisateurs distants (VPN, accès sécurisé)
B22: S’assurer de la couverture fonctionnelle du HD | C22: Liste des applications/logiciels supportés. | D22: Le périmètre fonctionnel du help-desk est-il validé par la DSI ? | E22: OUI | F22: Catalogue des services, Liste approuvée par la DSI, Document d'exclusions | G22: Demandes hors périmètre, confusion, refus non justifiés | H22: Moyenne | I22: Impact mineur, généralement sans conséquence grave. | J22: Liste des applications/logiciels supportés
C23: Périmètre fonctionnel validé par la DSI. | D23: Les exclusions de prise en charge sont-elles clairement documentées ? | E23: OUI | F23: PV de validation, Cahier des charges, Courriel de confirmation | G23: Conflits métiers/DSI, couverture insuffisante | H23: Elevée | I23: Impact mineur, généralement sans conséquence grave. | J23: Périmètre fonctionnel validé par la DSI
C24: Exclusions clairement documentées. | D24: Existe-t-il un processus pour étendre la couverture fonctionnelle du help-desk ? | E24: OUI | F24: Liste des exclusions, FAQ métier, Exemples de tickets rejetés | G24: Attentes non gérées, litiges, mécontentement | H24: Moyenne | I24: Impact modéré sur la qualité ou les délais de service. | J24: Exclusions clairement documentées
C25: Processus pour étendre la couverture. | D25: Le help-desk est-il aligné avec les besoins métiers (enquête utilisateurs) ? | E25: NON | F25: Procédure de demande, Modèle de formulaire, Historique des extensions | G25: Rigidité, lenteur, inadaptation aux besoins émergents | H25: Moyenne | I25: Impact modéré sur la qualité ou les délais de service. | J25: Processus pour étendre la couverture
C26: Alignement avec les besoins métiers (enquête utilisateurs). | D26: Quel outil est utilisé pour la prise d'appel et le suivi des tickets ? | E26: NON | F26: Résultats d'enquête, Rapport d'analyse, Plan d'action | G26: Décalage, sous-utilisation, inefficacité | H26: Elevée | I26: Impact modéré sur la qualité ou les délais de service. | J26: Alignement avec les besoins métiers (enquête utilisateurs)
B27: S’assurer qu’un outil est implémenté pour la prise d'appel et le suivi des tickets | C27: Outil identifié et déployé (ex : ServiceNow, Jira). | D27: Les fonctionnalités de base de l'outil (création, suivi, clôture) sont-elles opérationnelles ? | E27: PAS | F27: Contrat de licence, Procès-verbal de déploiement, Manuel utilisateur | G27: Outil inadapté, coûts excessifs, résistance des utilisateurs | H27: Elevée | I27: Impact mineur, généralement sans conséquence grave. | J27: Outil identifié et déployé (ex : ServiceNow, Jira)
C28: Fonctionnalités de base opérationnelles (création, suivi, clôture). | D28: L'outil est-il intégré avec d'autres outils (messagerie, monitoring) ? | E28: NON | F28: Tests de validation, Captures d'écran, Rapport de fonctionnement | G28: Bugs, lacunes fonctionnelles, inefficacité | H28: Elevée | I28: Impact modéré sur la qualité ou les délais de service. | J28: Fonctionnalités de base opérationnelles (création, suivi, clôture)
C29: Intégration avec d'autres outils (messagerie, monitoring). | D29: Des sauvegardes régulières des données de l'outil sont-elles effectuées ? | E29: OUI | F29: Documentation technique, Procès-verbal d'intégration, Logs de synchronisation | G29: Silos, travail manuel accru, erreurs | H29: Elevée | I29: Impact modéré sur la qualité ou les délais de service. | J29: Intégration avec d'autres outils (messagerie, monitoring)
C30: Sauvegardes régulières des données. | D30: Existe-t-il un journal des modifications de l'outil pour assurer la traçabilité ? | E30: PAS | F30: Politique de sauvegarde, Logs de sauvegarde, Test de restauration | G30: Perte de données, corruption, indisponibilité | H30: Elevée | I30: Impact mineur, généralement sans conséquence grave. | J30: Sauvegardes régulières des données
C31: Journal des modifications de l'outil (traçabilité). | D31: Existe-t-il une liste des champs obligatoires à renseigner dans l'outil de ticketing ? | E31: OUI | F31: Journal des changements, Tickets de modification, Approbations des mises à jour | G31: Perte de traçabilité, conflits de version, audit impossible | H31: Moyenne | I31: Impact modéré sur la qualité ou les délais de service. | J31: Journal des modifications de l'outil (traçabilité)
B32: S’assurer que des critères à renseigner pour la qualification des tickets existent | C32: Liste des champs obligatoires dans l'outil. | D32: L'outil dispose-t-il d'une liste claire et accessible des champs obligatoires à renseigner pour chaque ticket ? | E32: OUI | F32: Modèle de ticket, Règles de saisie, Exemple de ticket valide | G32: Tickets incomplets, informations manquantes, retards | H32: Moyenne | I32: Impact mineur, généralement sans conséquence grave. | J32: Liste des champs obligatoires dans l'outil
C33: Cohérence des critères avec les besoins métiers. | D33: Les critères de saisie des tickets sont-ils alignés sur les besoins métiers identifiés ? | E33: OUI | F33: Matrice de correspondance, Retours métiers, Procès-verbal d'alignement | G33: Champs inutiles, manque de pertinence, frustration | H33: Moyenne | I33: Impact mineur, généralement sans conséquence grave. | J33: Cohérence des critères avec les besoins métiers
C34: Exemple de tickets correctement renseignés. | D34: Des exemples de tickets correctement renseignés sont-ils disponibles pour guider les utilisateurs ? | E34: OUI | F34: Tickets exemplaires, Base de connaissances, Guide de bonnes pratiques | G34: Mauvaises pratiques, formation inefficace | H34: Faible | I34: Peut entraîner une interruption majeure du service ou une perte importante de données. | J34: Exemple de tickets correctement renseignés
C35: Contrôle qualité aléatoire sur les tickets. | D35: Un processus de contrôle qualité aléatoire est-il mis en place pour vérifier la qualité des tickets ? | E35: NON | F35: Procédure de contrôle, Rapport d'audit, Liste des corrections | G35: Erreurs non détectées, qualité variable | H35: Moyenne | I35: Impact modéré sur la qualité ou les délais de service. | J35: Contrôle qualité aléatoire sur les tickets
C36: Procédure de rejet des tickets incomplets. | D36: Existe-t-il une procédure documentée pour rejeter les tickets incomplets ou non conformes ? | E36: NON | F36: Modèle de notification, Historique des rejets, FAQ sur les rejets | G36: Retards, rejets non justifiés, conflits | H36: Moyenne | I36: Impact modéré sur la qualité ou les délais de service. | J36: Procédure de rejet des tickets incomplets
B37: S’assure qu’il existe une liste de questions à dérouler lors d'un appel afin préciser au mieux la demande de l'utilisateur | C37: Checklist intégrée à l'outil ou accessible aux agents. | D37: Une checklist est-elle intégrée directement dans l'outil ou facilement accessible pour les agents ? | E37: PAS | F37: Capture d'écran de la checklist, Procédure d'utilisation, Feedback des agents | G37: Checklist obsolète, non-utilisation, rigidité | H37: Moyenne | I37: Peut entraîner une interruption majeure du service ou une perte importante de données. | J37: Checklist intégrée à l'outil ou accessible aux agents
C38: Questions adaptées aux types de demandes courantes. | D38: Les questions posées dans les tickets sont-elles adaptées aux types de demandes les plus courantes ? | E38: NON | F38: Liste des questions, Statistiques d'utilisation, Retours utilisateurs | G38: Questions inutiles, lenteur, frustration | H38: Faible | I38: Peut entraîner une interruption majeure du service ou une perte importante de données. | J38: Questions adaptées aux types de demandes courantes
C39: Mise à jour régulière de la checklist. | D39: La checklist est-elle mise à jour régulièrement pour refléter les évolutions des besoins ? | E39: OUI | F39: Historique des versions, Planning de mise à jour, Procès-verbal de validation | G39: Désuétude, inadaptation aux nouveaux besoins | H39: Moyenne | I39: Impact modéré sur la qualité ou les délais de service. | J39: Mise à jour régulière de la checklist
C40: Taux de résolution amélioré grâce à la checklist. | D40: Le taux de résolution des tickets a-t-il été amélioré depuis l'implémentation de la checklist ? | E40: PAS | F40: Rapport de performance, Comparaison avant/après, Témoignages | G40: Aucun impact mesurable, temps perdu | H40: Faible | I40: Impact modéré sur la qualité ou les délais de service. | J40: Taux de résolution amélioré grâce à la checklist
C41: Feedback des utilisateurs sur la pertinence des questions. | D41: Les utilisateurs ont-ils la possibilité de donner leur feedback sur la pertinence des questions de la checklist ? | E41: OUI | F41: Enquête de satisfaction, Commentaires utilisateurs, Suggestions d'amélioration | G41: Désengagement, retours ignorés | H41: Faible | I41: Impact modéré sur la qualité ou les délais de service. | J41: Feedback des utilisateurs sur la pertinence des questions
B42: S’assurer que les problèmes sont gérés | C42: Processus de gestion des problèmes documenté. | D42: Le processus de gestion des problèmes est-il documenté et accessible à toutes les parties prenantes ? | E42: OUI | F42: Procédure ITIL, RACI des problèmes, Exemples de résolution | G42: Problèmes récurrents, résolution inefficace | H42: Elevée | I42: Impact modéré sur la qualité ou les délais de service. | J42: Processus de gestion des problèmes documenté
C43: Différenciation problème/incident dans l'outil. | D43: L'outil permet-il de différencier clairement un problème d'un incident ? | E43: OUI | F43: Capture d'écran des catégories, Guide de classification, Exemples concrets | G43: Confusion, mauvaise priorisation | H43: Moyenne | I43: Impact modéré sur la qualité ou les délais de service. | J43: Différenciation problème/incident dans l'outil
C44: Exemples de problèmes résolus (ROOT CAUSE). | D44: Des exemples de problèmes résolus avec leur cause racine sont-ils disponibles pour référence ? | E44: OUI | F44: Rapports d'analyse, RCA formalisés, Retours d'expérience | G44: Manque de capitalisation, répétition des erreurs | H44: Moyenne | I44: Peut entraîner une interruption majeure du service ou une perte importante de données. | J44: Exemples de problèmes résolus (ROOT CAUSE)
C45: Mesures préventives issues des problèmes. | D45: Des mesures préventives sont-elles mises en place suite à l'analyse des problèmes résolus ? | E45: NON | F45: Plan d'action préventif, Documentation des correctifs, Suivi des implémentations | G45: Problèmes évitables non anticipés | H45: Elevée | I45: Peut entraîner une interruption majeure du service ou une perte importante de données. | J45: Mesures préventives issues des problèmes
C46: Revue périodique des problèmes récurrents. | D46: Une revue périodique des problèmes récurrents est-elle organisée pour identifier des tendances ? | E46: NON | F46: Comptes-rendus de revue, Liste des problèmes récurrents, Actions correctives | G46: Pas d'amélioration continue, gaspillage | H46: Moyenne | I46: Peut entraîner une interruption majeure du service ou une perte importante de données. | J46: Revue périodique des problèmes récurrents
B47: S’assurer qu’un processus de gestion des problèmes existe | C47: Procédure alignée sur ITIL ou autre référentiel. | D47: La procédure de gestion des problèmes est-elle alignée sur un référentiel tel qu'ITIL ? | E47: PAS | F47: Documentation ITIL, Audit de conformité, Certifications | G47: Complexité, non-adhésion, lourdeur | H47: Moyenne | I47: Impact mineur, généralement sans conséquence grave. | J47: Procédure alignée sur ITIL ou autre référentiel
C48: Rôles définis (responsable problèmes). | D48: Un responsable des problèmes est-il désigné et ses rôles clairement définis ? | E48: NON | F48: Fiche de poste, Désignation officielle, Procès-verbal de nomination | G48: Dilution des responsabilités, inaction | H48: Elevée | I48: Impact modéré sur la qualité ou les délais de service. | J48: Rôles définis (responsable problèmes)
C49: Outil dédié ou module spécifique. | D49: Existe-t-il un outil dédié ou un module spécifique pour la gestion des problèmes ? | E49: OUI | F49: Documentation de l'outil, Contrat de maintenance, Procès-verbal de configuration | G49: Manque de fonctionnalités, inadaptation | H49: Moyenne | I49: Impact modéré sur la qualité ou les délais de service. | J49: Outil dédié ou module spécifique
C50: KPIs suivis (ex : temps moyen de résolution). | D50: Des indicateurs clés (KPIs) tels que le temps moyen de résolution sont-ils suivis et analysés ? | E50: PAS | F50: Tableau de bord KPI, Rapports mensuels, Objectifs définis | G50: Pas de mesure de performance, opacité | H50: Elevée | I50: Impact modéré sur la qualité ou les délais de service. | J50: KPIs suivis (ex : temps moyen de résolution)
C51: Revue annuelle du processus par la DSI. | D51: Le processus de gestion des problèmes est-il revu annuellement par la DSI pour évaluer son efficacité ? | E51: OUI | F51: PV de revue, Plan d'amélioration, Recommandations | G51: Obsolescence, non-alignement stratégique | H51: Moyenne | I51: Peut entraîner une interruption majeure du service ou une perte importante de données. | J51: Revue annuelle du processus par la DSI
B52: S’assurer que les incidents de production de nuit et jour ferrier sont aussi saisis dans l'outil | C52: Preuve de tickets créés pour des incidents hors horaires. | D52: Des preuves de création de tickets pour des incidents hors horaires sont-elles disponibles ? | E52: OUI | F52: Logs des tickets hors horaires, Rapport de garde, Liste des intervenants | G52: Retards, incidents non traités | H52: Elevée | I52: Impact modéré sur la qualité ou les délais de service. | J52: Preuve de tickets créés pour des incidents hors horaires
C53: Procédure spécifique pour les urgences. | D53: Existe-t-il une procédure spécifique pour traiter les incidents urgents ? | E53: OUI | F53: Procédure d'urgence, Liste des contacts, Historique des déclenchements | G53: Mauvaise gestion de crise, panique | H53: Elevée | I53: Peut entraîner une interruption majeure du service ou une perte importante de données. | J53: Procédure spécifique pour les urgences
C54: Disponibilité d'une équipe de garde. | D54: Une équipe de garde est-elle disponible pour intervenir en cas d'incident hors horaires ? | E54: OUI | F54: Planning de garde, Contrats des agents, Procédure d'astreinte | G54: Indisponibilité, temps de réponse excessif | H54: Elevée | I54: Peut entraîner une interruption majeure du service ou une perte importante de données. | J54: Disponibilité d'une équipe de garde
C55: Intégration avec les outils de monitoring. | D55: L'outil de ticketing est-il intégré avec des outils de monitoring pour détecter automatiquement les incidents ? | E55: NON | F55: Documentation technique, Alerts logs, Procès-verbal de tests | G55: Détection tardive, silos | H55: Elevée | I55: Impact modéré sur la qualité ou les délais de service. | J55: Intégration avec les outils de monitoring
C56: Rapport d'incidents critiques incluant les périodes non ouvrables. | D56: Les rapports d'incidents critiques incluent-ils les périodes non ouvrables pour une analyse complète ? | E56: NON | F56: Rapports d'incidents, Analyse post-mortem, Actions correctives | G56: Manque de transparence, non-amélioration | H56: Moyenne | I56: Impact mineur, généralement sans conséquence grave. | J56: Rapport d'incidents critiques incluant les périodes non ouvrables
B57: S’assurer que des comités mis en place pour suivre les incidents et leur résolution existent et définissent, Qui participe, et comment sont suivies les actions | C57: Composition des comités documentée. | D57: La composition des comités de gestion des incidents est-elle documentée et connue de tous ? | E57: PAS | F57: Liste des membres, PV de nomination, Règlement interne | G57: Absence de parties prenantes, déséquilibre | H57: Moyenne | I57: Impact modéré sur la qualité ou les délais de service. | J57: Composition des comités documentée
C58: Périodicité des réunions respectée. | D58: Les réunions des comités sont-elles organisées à la fréquence définie dans les procédures ? | E58: NON | F58: Calendrier des réunions, PV des réunions, Suivi des présences | G58: Retards décisionnels, lenteur | H58: Moyenne | I58: Impact modéré sur la qualité ou les délais de service. | J58: Périodicité des réunions respectée
C59: Comptes-rendus des réunions disponibles. | D59: Les comptes-rendus des réunions des comités sont-ils archivés et accessibles aux parties prenantes ? | E59: OUI | F59: Archives des CR, Décisions actées, Plans d'action | G59: Opacité, non-restitution | H59: Faible | I59: Impact modéré sur la qualité ou les délais de service. | J59: Comptes-rendus des réunions disponibles
C60: Actions correctives suivies. | D60: Les actions correctives décidées lors des réunions sont-elles suivies jusqu'à leur résolution ? | E60: PAS | F60: Suivi des actions, Responsables désignés, Preuves de clôture | G60: Aucune implémentation, inefficacité | H60: Elevée | I60: Peut entraîner une interruption majeure du service ou une perte importante de données. | J60: Actions correctives suivies
C61: Participation effective des parties prenantes (DSI, métiers). | D61: Les parties prenantes (DSI, métiers) participent-elles activement aux réunions des comités ? | E61: OUI | F61: Liste de présence, Engagements signés, Feedback des participants | G61: Désengagement, décisions unilatérales | H61: Moyenne | I61: Impact modéré sur la qualité ou les délais de service. | J61: Participation effective des parties prenantes (DSI, métiers)
B62: S’assurer que si le HD est externalisé, il existe un contrat de service | C62: Contrat signé avec les SLA définis. | D62: Un contrat incluant les SLA (Service Level Agreements) est-il signé avec le prestataire ? | E62: OUI | F62: Contrat de service, Annexe SLA, PV de signature | G62: Pénalités non appliquées, flou contractuel | H62: Elevée | I62: Impact modéré sur la qualité ou les délais de service. | J62: Contrat signé avec les SLA définis
C63: Pénalités en cas de non-respect des SLA. | D63: Des pénalités sont-elles prévues en cas de non-respect des SLA par le prestataire ? | E63: OUI | F63: Clause de pénalités, Historique des pénalités, Rapports de non-conformité | G63: Conflits, perte financière | H63: Moyenne | I63: Impact modéré sur la qualité ou les délais de service. | J63: Pénalités en cas de non-respect des SLA
C64: Procédure de révision du contrat. | D64: Existe-t-il une procédure pour réviser régulièrement les termes du contrat avec le prestataire ? | E64: OUI | F64: Procédure de mise à jour, Historique des révisions, Avenants signés | G64: Contrat obsolète, rigidité | H64: Moyenne | I64: Peut entraîner une interruption majeure du service ou une perte importante de données. | J64: Procédure de révision du contrat
C65: Points de contact identifiés chez le prestataire. | D65: Les points de contact chez le prestataire sont-ils clairement identifiés et accessibles ? | E65: NON | F65: Liste des contacts, Organigramme prestataire, Procédure d'escalade | G65: Délais de réponse longs, interlocuteurs multiples | H65: Moyenne | I65: Impact mineur, généralement sans conséquence grave. | J65: Points de contact identifiés chez le prestataire
C66: Audit annuel du prestataire. | D66: Un audit annuel du prestataire est-il réalisé pour évaluer sa conformité aux engagements ? | E66: NON | F66: Rapport d'audit, Plan d'action, Preuves de correction | G66: Non-conformité, risques non détectés | H66: Elevée | I66: Impact modéré sur la qualité ou les délais de service. | J66: Audit annuel du prestataire
B67: S’assurer que les indicateurs pour suivre le contrat de service existent | C67: Tableau de bord des SLA (ex : temps de réponse, taux de résolution). | D67: Un tableau de bord des SLA (temps de réponse, taux de résolution) est-il disponible et mis à jour régulièrement ? | E67: PAS | F67: Dashboard SLA, Exports de données, Alertes configurées | G67: Indicateurs non fiables, manque de visibilité | H67: Elevée | I67: Impact modéré sur la qualité ou les délais de service. | J67: Tableau de bord des SLA (ex : temps de réponse, taux de résolution)
C68: Alertes en cas de dérive des indicateurs. | D68: Des alertes sont-elles configurées pour signaler toute dérive des indicateurs de performance ? | E68: NON | F68: Configuration des alertes, Historique des alertes, Actions déclenchées | G68: Réaction tardive, problèmes non anticipés | H68: Elevée | I68: Impact mineur, généralement sans conséquence grave. | J68: Alertes en cas de dérive des indicateurs
C69: Revue trimestrielle des indicateurs avec le prestataire. | D69: Une revue trimestrielle des indicateurs de performance est-elle organisée avec le prestataire ? | E69: OUI | F69: PV de revue, Graphiques d'évolution, Engagements mutuels | G69: Pas d'ajustement, inefficacité | H69: Moyenne | I69: Impact modéré sur la qualité ou les délais de service. | J69: Revue trimestrielle des indicateurs avec le prestataire
C70: Historique des indicateurs sur 12 mois. | D70: L'historique des indicateurs de performance est-il conservé sur une période minimale de 12 mois ? | E70: PAS | F70: Archives des rapports, Analyse comparative, Tendances | G70: Pas d'analyse tendancielle, décisions aveugles | H70: Moyenne | I70: Impact modéré sur la qualité ou les délais de service. | J70: Historique des indicateurs sur 12 mois
C71: Intégration des indicateurs dans le reporting DSI. | D71: Les indicateurs de performance sont-ils intégrés dans les reportings destinés à la DSI ? | E71: OUI | F71: Modèle de reporting, Exemples de slides, Procédure d'intégration | G71: Silo, manque de cohérence globale | H71: Moyenne | I71: Impact modéré sur la qualité ou les délais de service. | J71: Intégration des indicateurs dans le reporting DSI
B72: S’assurer qu’il y a un planning systématique concernant les mises en production | C72: Calendrier partagé des mises en production. | D72: Un calendrier partagé des mises en production est-il disponible et accessible à toutes les équipes concernées ? | E72: OUI | F72: Calendrier publié, Historique des déploiements, Procédure de communication | G72: Conflits de planning, retards | H72: Elevée | I72: Impact mineur, généralement sans conséquence grave. | J72: Calendrier partagé des mises en production
C73: Processus de validation des déploiements. | D73: Existe-t-il un processus de validation des déploiements avant leur mise en production ? | E73: OUI | F73: Procédure de validation, Checklists, PV de validation | G73: Erreurs en production, recettes insuffisantes | H73: Elevée | I73: Impact mineur, généralement sans conséquence grave. | J73: Processus de validation des déploiements
