Workbook

Sheet Synthèse
A3: N° | B3: Domaines | C3: Total OUI | D3: Total NON | E3: Total PAS | F3: Total | G3: Score | H3: Score | J3: Equipe de Mission
A4: 1 | B4: Audit des Applications en Service (4.1) | C4: =COUNTIF('4.1'!G2:G1019, "OUI") -> 217 | D4: =COUNTIF('4.1'!G2:G1019, "NON") -> 219 | E4: =COUNTIF('4.1'!G2:G1019, "PAS") -> 73 | F4: =SUM(C4:E4) -> 509 | G4: =C4/F4 -> 0.42632613 | H4: =C4/F4 -> 0.42632613
A5: 2 | B5: Audit de la Fonction Informatique (4.2) | C5: =COUNTIF('4.2'!F2:F443,"oui") -> 84 | D5: =COUNTIF('4.2'!F2:F443,"non") -> 75 | E5: =COUNTIF('4.2'!F2:F443,"pas") -> 62 | F5: =SUM(C5:E5) -> 221 | G5: =C5/F5 -> 0.3800905 | H5: =C5/F5 -> 0.3800905 | M5: Nom | N5: Prénom | O5: Grade
A6: 3 | B6: Audit et Contrôle des Projets Informatiques (4.3) | C6: =COUNTIF('4.3'!F2:F1239,"Oui") -> 307 | D6: =COUNTIF('4.3'!F2:F1239,"Non") -> 312 | E6: =COUNTIF('4.3'!F2:F1239,"Pas") -> 0 | F6: =SUM(C6:E6) -> 619 | G6: =C6/F6 -> 0.49596123 | H6: =C6/F6 -> 0.49596123 | K6: Chef : | M6: DJEUMENI | N6: WINNIE
A7: 4 | B7: Audit du Support Utilisateur et de la Gestion du Parc (4.4) | C7: =COUNTIF([1]Q_Resp_Facturation!B2:B109,"OUI") -> 69 | D7: =COUNTIF('4.3'!F2:F1239,"Non") -> 312 | E7: =COUNTIF('4.3'!F2:F1239,"Pas") -> 0 | F7: =SUM(C7:E7) -> 381 | G7: =C7/F7 -> 0.18110236 | H7: =C7/F7 -> 0.18110236
A8: 5 | B8: Conduire une Mission d’Audit du Support aux utilisateurs et de la gestion du Parc (4.5) | C8: =COUNTIF('4.5'!F2:F601,"Oui") -> 100 | D8: =COUNTIF('4.5'!F2:F601,"Non") -> 100 | E8: =COUNTIF('4.5'!F2:F601,"Pas") -> 100 | F8: =SUM(C8:E8) -> 300 | G8: =C8/F8 -> 0.33333333 | H8: =C8/F8 -> 0.33333333 | K8: Membres:
A9: 6 | B9: COSO | C9: =COUNTIF(Ref_COSO!F2:F1311,"OUI") -> 283 | D9: =COUNTIF(Ref_COSO!F2:F1311,"NON") -> 146 | E9: =COUNTIF(Ref_COSO!F2:F1311,"PAS") -> 15 | F9: =SUM(C9:E9) -> 444 | G9: =C9/F9 -> 0.63738739 | H9: =C9/F9 -> 0.63738739 | L9: 1
A10: Total | C10: =SUM(C4:C9) -> 1060 | D10: =SUM(D4:D9) -> 1164 | E10: 1 | F10: =SUM(C10:E10) -> 2225 | G10: =C10/F10 -> 0.47640449 | H10: =C10/F10 -> 0.47640449 | L10: 4
K11: Chauffeur:

Sheet 4.1
A1: Domaines | B1: Points de contrôle | C1: objectifs de contrôle | D1: criteres d'evaluation | E1: Documents Requis | F1: Questions d'evaluation | G1: Réponses | H1: Risques | I1: Criticités | J1: Consequences | K1: Recommandations
A2: Audit des applications en service | B2: Organisation | C2: S’assurer de l’existence d'un comité informatique | D2: Existence d'un comité informatique | E2: Décision de création du comité informatique signée par le DG | F2: Existe-t-il un comité informatique ? | G2: OUI | H2: Inexistence d'un comité informatique | I2: Elevée | J2: Décisions informatiques déconnectées des besoins métiers. | K2: mpliquer les métiers dans les instances de décision concernant les SI.
E3: Procès-verbal de réunion attestant de la création du comité informatique. | K3: Formaliser les besoins métiers et les traduire en exigences fonctionnelles et techniques.
D4: Le Comité est présidé par le Directeur Général | E4: PV de session du comité | F4: Le Comité est-il présidé par le Directeur Général ? | G4: NON | H4: Le Comité n'est pas présidé par le Directeur Général | I4: Moyenne | J4: Manque d'autorité et de légitimité des décisions du comité. | K4: Clarifier les rôles et responsabilités du comité de pilotage SI.
E5: Décision de nomination du Président du comité informatique signée par le Directeur Général. | K5: Documenter les décisions prises et les diffuser aux parties prenantes.
D6: Les directions utilisatrices sont représentées au sein de ce Comité | E6: Décision d'affectation des directions au comité | F6: Les directions utilisatrices sont-elles représentées au sein de ce Comité ? | G6: PAS | H6: Les directions utilisatrices ne sont pas représentées au sein de ce Comité. | I6: Elevée | J6: Systèmes inadaptés aux besoins réels des utilisateurs. | K6: Mener des études d'utilisabilité et des tests utilisateurs avant et après la mise en production.
E7: PV de session du comité | K7: Mettre en place un processus de recueil et de gestion des feedbacks utilisateurs.
D8: Les directions utilisatrices sont influentes au sein de ce Comité | E8: Procès-verbal des réunions mentionnant les contributions des directions utilisatrices | F8: Les directions utilisatrices sont-elles influentes au sein de ce Comité ? | G8: NON | H8: Les directions utilisatrices ne sont pas influentes au sein de ce Comité | I8: Faible | J8: Faible adoption par les utilisateurs et non atteinte des objectifs métiers. | K8: Accompagner les utilisateurs dans la prise en main des nouveaux systèmes.
E9: Document de gouvernance IT attestant du poids décisionnel des directions métiers | K9: Définir des indicateurs de performance (KPI) pour mesurer l'adoption et l'atteinte des objectifs.
D10: L'ordre du jour des réunions est documenté? | E10: Ordres du jour archivés des réunions du comité | F10: L'ordre du jour des réunions est-il documenté? | G10: NON | H10: Systèmes inadaptés aux besoins métiers. | I10: Elevée | J10: Pertes de temps et sujets importants non traités. | K10: Prioriser les sujets et les tâches en fonction de leur importance et de leur urgence.
E11: Procès-verbaux des réunions avec suivi des points traités | K11: Mettre en place des outils de gestion de projet et de suivi des tâches.
C12: S’assurer de l’existence d'une politique relative aux applications | D12: Il existe une politique relative aux applications au sein de l'institution | E12: Document officiel de la politique applicative | F12: Existe-t-il une politique relative aux applications au sein de l'institution? | G12: OUI | H12: Réunions inefficaces. | I12: Moyenne | J12: Coûts élevés et duplication des fonctions. | K12: Rationaliser les applications et les systèmes existants.
E13: Procès-verbal de validation par la direction générale | K13: Automatiser les tâches répétitives et chronophages.
D14: La politique est connue des utilisateurs d'applications | E14: Registre des formations suivies par les utilisateurs | F14: La politique est-elle connue des utilisateurs d'applications? | G14: OUI | H14: Gestion anarchique des applications. | I14: Elevée | J14: Problèmes de sécurité et erreurs d'utilisation. | K14: Sensibiliser les utilisateurs aux bonnes pratiques de sécurité.
E15: Attestations de connaissance de la politique signées par les utilisateurs | K15: Mettre en place des contrôles d'accès et des mécanismes d'authentification robustes.
D16: La politique est largement diffusée | E16: Plan de communication institutionnel | F16: La politique est-elle largement diffusée? | G16: OUI | H16: Non-respect de la politique. | I16: Faible | J16: Application incomplète de la politique et problèmes de conformité. | K16: Formaliser et diffuser la politique de sécurité SI.
E17: Preuves matérielles de diffusion (emails, publications intranet) | K17: Effectuer des audits réguliers pour vérifier la conformité aux normes et réglementations.
D18: La politique est mise en œuvre | E18: Rapport d'audit de conformité | F18: La politique est-elle mise en œuvre? | G18: NON | H18: Méconnaissance de la politique par une partie du personnel. | I18: Elevée | J18: Aucun impact concret sur les pratiques et les problèmes persistent. | K18: Mettre en place un plan d'action correctif pour résoudre les problèmes identifiés.
E19: Journal des contrôles effectués | K19: Suivre l'efficacité des actions correctives et ajuster si nécessaire.
D20: La politique couvre l'ensemble du cycle de vie de l’application | E20: Document décrivant le cycle de vie complet des applications | F20: La politique couvre-t-elle l'ensemble du cycle de vie de l'application? | G20: PAS | H20: La politique reste théorique. | I20: Moyenne | J20: Problèmes de sécurité et erreurs lors de certaines phases du cycle de vie de l'application. | K20: Intégrer la sécurité dès la phase de conception des applications (approche Security by Design).
E21: Procédures opérationnelles pour chaque phase du cycle | K21: Réaliser des tests de sécurité tout au long du cycle de développement.
D22: La politique favorise la responsabilisation des utilisateurs dans l'usage de leur système d’information (application) | E22: Charte d'utilisation signée par les utilisateurs | F22: La politique favorise-t-elle la responsabilisation des utilisateurs dans l'usage de leur système d'information (application)? | G22: NON | H22: La politique est incomplète et ne couvre pas toutes les étapes. | I22: Elevée | J22: Mauvaise qualité des données et pertes d'informations. | K22: Mettre en place des processus de validation et de nettoyage des données.
E23: Registre des sanctions appliquées | K23: Sauvegarder régulièrement les données et mettre en place un plan de reprise d'activité.
D24: La politique préconise l'attribution formelle de responsabilités aux utilisateurs du système (application) | E24: Fiches de poste avec responsabilités applicatives définies | F24: La politique préconise-t-elle l'attribution formelle de responsabilités aux utilisateurs du système (application)? | G24: NON | H24: Manque d'implication des utilisateurs. | I24: Faible | J24: Manque de clarté sur qui fait quoi et erreurs fréquentes. | K24: Définir clairement les rôles et responsabilités de chaque acteur.
E25: Matrice RACI officielle | K25: Documenter les processus et les procédures.
C26: S’assurer que les rôle et responsabilités des utilisateurs sont bien définis | D26: Le rôle et les responsabilités des utilisateurs vis-à-vis de l’application sont clairement identifiés | E26: Manuel des procédures utilisateurs | F26: Le rôle et les responsabilités des utilisateurs vis-à-vis de l'application sont-ils clairement identifiés? | G26: OUI | H26: Responsabilités mal définies. | I26: Elevée | J26: Difficultés à identifier les responsables en cas de problème. | K26: Mettre en place une matrice RACI (Responsible, Accountable, Consulted, Informed).
E27: Tableau des droits d'accès par profil métier | K27: Définir un processus d'escalade des problèmes.
D28: Le rôle et les responsabilités des utilisateurs vis-à-vis de l’application couvrent l’analyse des risques | E28: Rapport d'analyse des risques impliquant les utilisateurs métiers | F28: Le rôle et les responsabilités des utilisateurs vis-à-vis de l'application couvrent-ils l'analyse des risques? | G28: OUI | H28: Manque de clarté sur les rôles et responsabilités. | I28: Moyenne | J28: Mesures de sécurité non adaptées. | K28: Effectuer une analyse de risques pour identifier les menaces et les vulnérabilités.
E29: Procès-verbal de validation des risques par les responsables métiers | K29: Mettre en place des mesures de sécurité appropriées pour atténuer les risques.
D30: Le rôle et les responsabilités des utilisateurs vis-à-vis de l’application couvrent la définition des besoins de sécurité | E30: Cahier des charges sécurité co-construit avec les métiers | F30: Le rôle et les responsabilités des utilisateurs vis-à-vis de l'application couvrent-ils la définition des besoins de sécurité? | G30: OUI | H30: Absence de prise en compte des besoins de sécurité par les utilisateurs. | I30: Elevée | J30: Systèmes obsolètes. | K30: Systèmes à jour et maintenus.
E31: PV de réunion de définition des exigences de sécurité | K31: Plan de secours et de reprise après sinistre.
D32: Le rôle et les responsabilités des utilisateurs vis-à-vis de l’application couvrent la gestion des changements et des évolutions | E32: Procédure formalisée de gestion des changements | F32: Le rôle et les responsabilités des utilisateurs vis-à-vis de l'application couvrent-ils la gestion des changements et des évolutions? | G32: NON | H32: Gestion des changements et des évolutions inadaptée aux besoins. | I32: Faible | J32: Difficultés à maintenir l'application et insatisfaction des utilisateurs. | K32: Définir des objectifs de sécurité clairs et mesurables.
E33: Registre des demandes d'évolution initiées par les métiers | K33: Suivre et évaluer régulièrement la performance de la sécurité.
D34: Le rôle et les responsabilités des utilisateurs vis-à-vis de l’application couvrent l’administration de l’application | E34: Procédures d'administration déléguée aux utilisateurs | F34: Le rôle et les responsabilités des utilisateurs vis-à-vis de l'application couvrent-ils l'administration de l'application? | G34: PAS | H34: Administration de l'application déconnectée des besoins des utilisateurs. | I34: Elevée | J34: Difficulté à maintenir l'application et insatisfaction des utilisateurs. | K34: Séparer les tâches critiques pour éviter les conflits d'intérêts et les fraudes.
E35: Journal des opérations administratives réalisées par les métiers | K35: Former le personnel sur les politiques et procédures de sécurité.
C36: S’assurer qu’une analyse des risques a été réalisée | D36: Une analyse des risques spécifique à l’application a été réalisée | E36: Rapport complet d'analyse des risques applicative | F36: Une analyse des risques spécifique à l'application a-t-elle été réalisée? | G36: NON | H36: Mauvaise identification des risques pour l'application. | I36: Moyenne | J36: Mauvaise identification des risques pour l'application. | K36: Définir un niveau de sécurité cible et allouer les ressources nécessaires.
E37: Grille d'évaluation des risques spécifique à l'application | K37: Mettre en œuvre des contrôles de sécurité pour surveiller et protéger les systèmes.
D38: L'analyse des risques a débouché sur la définition des besoins de sécurité | E38: Document de synthèse des besoins de sécurité | F38: L'analyse des risques a-t-elle débouché sur la définition des besoins de sécurité? | G38: NON | H38: Définition des besoins de sécurité incomplète ou inadaptée. | I38: Elevée | J38: Définition des besoins de sécurité incomplète ou inadéquate. | K38: Documenter la méthodologie utilisée pour l'analyse et la gestion des risques.
E39: PV de validation des exigences par la direction | K39: Former le personnel sur la méthodologie et les outils utilisés.
D40: La méthode d'analyse des risques est définie et documentée (ex: EBIOS Risk Manager, MEHARI)? | E40: Manuel méthodologique d'analyse des risques (EBIOS/MEHARI) | F40: La méthode d'analyse des risques est-elle définie et documentée (ex: EBIOS Risk Manager, MEHARI)? | G40: OUI | H40: Méthode d'analyse des risques non standardisée et non documentée. | I40: Faible | J40: Méthode d'analyse des risques non standardisée et non documentée. | K40: Prendre en compte la confidentialité, l'intégrité et la disponibilité des données lors de la conception et de la mise en œuvre des systèmes.
E41: Procédure d'évaluation des risques documentée | K41: Mettre en place des mesures pour protéger les données contre les accès non autorisés, les modifications et les pertes.
D42: Les risques identifiés sont classifiés et priorisés? | E42: Matrice de criticité des risques classés | F42: Les risques identifiés sont-ils classifiés et priorisés? | G42: OUI | H42: Risques mal identifiés et non priorisés. | I42: Elevée | J42: Risques mal identifiés et non priorisés. | K42: Effectuer une analyse de risques approfondie et prioriser les risques en fonction de leur impact potentiel.
E43: Plan de traitement des risques priorisés | K43: Mettre en place un processus de gestion des risques.
D44: Les mesures de sécurité mises en place sont proportionnées aux risques identifiés? | E44: Rapport de mise en œuvre des mesures de sécurité | F44: Les mesures de sécurité mises en place sont-elles proportionnées aux risques identifiés? | G44: OUI | H44: Mesures de sécurité inadaptées aux risques identifiés. | I44: Moyenne | J44: Mesures de sécurité inadaptées aux risques identifiés. | K44: Adopter des mesures de sécurité appropriées et proportionnées aux risques identifiés.
E45: Évaluation du niveau de couverture des risques | K45: Effectuer des tests de pénétration et des audits de sécurité réguliers.
C46: S’assurer que le prolongement de l'analyse de risque et de son expansion ont été réalisés | D46: Il y a eu un prolongement de l'analyse des risques et de l'expression des besoins de sécurité? | E46: Compte-rendu d'extension de l'analyse des risques | F46: Y a-t-il eu un prolongement de l'analyse des risques et de l'expression des besoins de sécurité? | G46: NON | H46: Expression des besoins de sécurité non prise en compte. | I46: Elevée | J46: Expression des besoins de sécurité non prise en compte. | K46: Recueillir et prendre en compte les besoins de sécurité des utilisateurs et des parties prenantes.
E47: Document d'évolution des besoins de sécurité | K47: Organiser des sessions de sensibilisation à la sécurité pour les utilisateurs.
D48: Un contrat de service (SLA) entre l'informatique et la direction utilisatrice a été mis en œuvre? | E48: Contrat de Service (SLA) signé avec la direction métier | F48: Un contrat de service (SLA) entre l'informatique et la direction utilisatrice a-t-il été mis en œuvre? | G48: PAS | H48: Contrat de service (SLA) inexistant ou non appliqué. | I48: Faible | J48: Contrat de service (SLA) inexistant ou non appliqué. | K48: Mettre en place un contrat de service (SLA) clair et précis qui définit les responsabilités en matière de sécurité.
E49: Annexe sécurité du SLA définissant les engagements | K49: S'assurer que le SLA est respecté et appliqué.
D50: L'analyse des risques est mise à jour régulièrement en fonction des évolutions de l'application et des menaces? | E50: Plan de révision périodique des risques | F50: L'analyse des risques est-elle mise à jour régulièrement en fonction des évolutions de l'application et des menaces? | G50: NON | H50: Analyse des risques non mise à jour régulièrement. | I50: Elevée | J50: Analyse des risques non mise à jour régulièrement. | K50: Mettre à jour régulièrement l'analyse des risques pour refléter l'évolution des menaces et des vulnérabilités.
E51: PV des mises à jour de l'analyse des risques | K51: Documenter les modifications apportées à l'analyse des risques.
D52: Les besoins de sécurité sont revus et validés par les parties prenantes? | E52: PV de revue des besoins de sécurité | F52: Les besoins de sécurité sont-ils revus et validés par les parties prenantes? | G52: NON | H52: Besoins de sécurité non revus ni validés. | I52: Moyenne | J52: Besoins de sécurité non revus ni validés. | K52: Revoir et valider régulièrement les besoins de sécurité pour s'assurer qu'ils restent pertinents.
E53: Fiche de validation des modifications par les métiers | K53: Documenter les besoins de sécurité et les décisions prises.
D54: Les résultats de l'analyse des risques sont utilisés pour définir les priorités en matière de sécurité? | E54: Plan d'action sécurité priorisé | F54: Les résultats de l'analyse des risques sont-ils utilisés pour définir les priorités en matière de sécurité? | G54: OUI | H54: Mauvaise définition des priorités en matière de sécurité. | I54: Elevée | J54: Mauvaise définition des priorités en matière de sécurité. | K54: Définir clairement les priorités en matière de sécurité en fonction des risques identifiés et des objectifs de l'organisation.
E55: Tableau de bord des risques résiduels | K55: Allouer les ressources nécessaires pour mettre en œuvre les mesures de sécurité prioritaires.
C56: S’assurer que l’analyse et évaluation du niveau de sensibilité a été réalisée | D56: Il y a une séparation des tâches au sein de la direction utilisatrice indépendamment de l'application? | E56: Organigramme fonctionnel avec séparation des tâches | F56: Il y a une séparation des tâches au sein de la direction utilisatrice indépendamment de l'application? | G56: OUI | H56: Absence de séparation des tâches au sein de la direction utilisatrice. | I56: Faible | J56: Absence de séparation des tâches au sein de la direction utilisatrice. | K56: Mettre en place une séparation des tâches pour les fonctions critiques au sein de la direction utilisatrice afin de minimiser les risques de conflits d'intérêts et de fraudes.
E57: Description des contrôles d'incompatibilité | K57: Définir des rôles et des responsabilités clairs pour chaque membre du personnel.
D58: Il y a une « maturité » de l'organisation vis-à-vis de ses systèmes d'information? | E58: Rapport d'évaluation de la maturité organisationnelle | F58: Il y a une «maturité» de l'organisation vis-à-vis de ses systèmes d'information? | G58: OUI | H58: Niveau de sécurité insuffisant. | I58: Elevée | J58: Niveau de sécurité insuffisant. | K58: Définir un niveau de sécurité cible et allouer les ressources nécessaires pour atteindre ce niveau.
E59: Plan d'amélioration continue des processus | K59: Mettre en œuvre des contrôles de sécurité pour surveiller et protéger les systèmes et les données.
D60: Une méthode d'évaluation de la sensibilité des données est définie et documentée? | E60: Politique de classification des données | F60: Une méthode d'évaluation de la sensibilité des données est définie et documentée? | G60: NON | H60: Méthode non définie et non documentée. | I60: Moyenne | J60: Méthode non définie et non documentée. | K60: Définir et documenter une méthodologie claire pour l'analyse et la gestion des risques de sécurité.
E61: Grille d'évaluation de la sensibilité des informations | K61: Former le personnel sur la méthodologie et les outils utilisés.
D62: L'évaluation prend en compte la confidentialité, l'intégrité et la disponibilité des données? | E62: Rapport d'évaluation CID (Confidentialité, Intégrité, Disponibilité) | F62: L'évaluation prend en compte la confidentialité, l'intégrité et la disponibilité des données? | G62: PAS | H62: Confidentialité, l'intégrité et la disponibilité non prises en compte. | I62: Elevée | J62: Confidentialité, l'intégrité et la disponibilité non prises en compte. | K62: Prendre en compte la confidentialité, l'intégrité et la disponibilité des données lors de la conception et de la mise en œuvre des systèmes.
E63: Cartographie des flux de données sensibles | K63: Mettre en place des mesures pour protéger les données contre les accès non autorisés, les modifications et les pertes.
D64: Les résultats de l'évaluation sont utilisés pour définir les mesures de sécurité appropriées? | E64: Plan de sécurité adapté aux niveaux de sensibilité | F64: Les résultats de l'évaluation sont utilisés pour définir les mesures de sécurité appropriées? | G64: NON | H64: Mesures de sécurité inappropriées. | I64: Faible | J64: Vulnérabilité aux menaces. | K64: Identifier et corriger les vulnérabilités.
E65: Matrice des mesures de protection par type de données | K65: Mettre en place des mesures de sécurité pour atténuer les menaces.
C66: Vérifier l’existence d’un manuel d'administration de l'application | D66: Un ou des manuels pour l’application existe | E66: Fiche de versionnage du manuel | F66: Un ou des manuels pour l'application existe? | G66: NON | H66: Manuels inexistants. | I66: Elevée | J66: Difficulté d'utilisation et erreurs potentielles. | K66: Simplifier l'interface utilisateur et fournir une documentation claire.
E67: Procès-verbal de validation | K67: Former les utilisateurs sur l'utilisation correcte de l'application.
D68: Le manuel est à jour | E68: Registre de formation des utilisateurs | F68: Le manuel est à jour? | G68: OUI | H68: Manuels non mis à jour. | I68: Moyenne | J68: Information obsolète et utilisation incorrecte de l'application. | K68: Mettre à jour régulièrement les informations et les données de l'application.
E69: Test de connaissance utilisateurs | K69: Fournir des instructions claires sur l'utilisation prévue de l'application.
D70: Le manuel est maitrisé | E70: Manuel utilisateur complet | F70: Le manuel est maîtrisé? | G70: OUI | H70: Manuels non maîtrisés. | I70: Elevée | J70: Difficulté à appliquer les bonnes pratiques et procédures. | K70: Fournir une formation et un soutien adéquats aux utilisateurs.
E71: Procédure opérationnelle standardisée | K71: Mettre en place des mécanismes pour encourager l'adoption des meilleures pratiques.
D72: Le manuel comprend un mode d'emploi | E72: Guide administrateur applicatif | F72: Le manuel comprend un mode d'emploi? | G72: OUI | H72: Absence de mode d'emploi. | I72: Faible | J72: Difficulté d'utilisation et erreurs potentielles. | K72: Concevoir une interface utilisateur intuitive et conviviale.
E73: Schéma d'architecture technique | K73: Mettre en œuvre des contrôles pour prévenir les erreurs potentielles.
D74: Le manuel comprend une présentation du module d’administration de l’application | E74: Matrice des droits d'accès | F74: Le manuel comprend une présentation du module d'administration de l'application? | G74: NON | H74: Absence de présentation du module d'administration. | I74: Elevée | J74: Administration difficile. | K74: Simplifier les tâches d'administration et automatiser les processus.
E75: Politique de sécurité applicative | K75: Fournir aux administrateurs les outils et la formation nécessaires.
D76: Le manuel comprend des droits d’accès | E76: Formulaire de demande de modification | F76: Le manuel comprend des droits d'accès? | G76: PAS | H76: Absence d'information sur les droits d'accès. | I76: Moyenne | J76: Accès non autorisés et gestion des droits inefficace. | K76: Mettre en place un contrôle d'accès strict et une gestion des droits efficace.
E77: Procès-verbal de validation propriétaire | K77: Surveiller régulièrement les accès et les activités des utilisateurs.
C78: Vérifier l’existence de procédures formalisées | D78: Des procédures formalisées imposant l’accord du « propriétaire » de l’application pour tout changement sur les programmes de l’application existent | E78: Procédure de changement de planning | F78: Des procédures formalisées imposant l'accord du «propriétaire» de l'application pour tout changement sur les programmes de l'application existent? | G78: NON | H78: Absence d'accord du « propriétaire » de l'application pour tout changement sur les programmes. | I78: Elevée | J78: Changement non autorisées. | K78: Mettre en place des contrôles pour empêcher les modifications non autorisées.
E79: Journal des modifications approuvées | K79: Enregistrer et auditer tous les changements.
D80: Des procédures formalisées imposant l’accord du « propriétaire » de l’application pour tout changement sur la planification des traitements informatiques existent | E80: Charte d'évolution technologique | F80: Des procédures formalisées imposant l'accord du «propriétaire» de l'application pour tout changement sur la planification des traitements informatiques existent? | G80: NON | H80: Absence d'accord du « propriétaire » de l'application pour la planification des traitements informatiques. | I80: Faible | J80: Risques liées à une gestion mauvaise. | K80: Adopter des pratiques de gestion des risques saines.
E81: PV du comité technique | K81: Examiner et mettre à jour régulièrement les politiques et les procédures.
D82: Des procédures formalisées imposant l’accord du « propriétaire » de l’application pour tout changement sur l’environnement technologique de l’application existent | E82: Procédures administratives formalisées | F82: Des procédures formalisées imposant l'accord du «propriétaire» de l'application pour tout changement sur l'environnement technologique de l'application existent? | G82: OUI | H82: Absence d'accord du « propriétaire » de l'application pour tout changement sur l'environnement technologique. | I82: Elevée | J82: Résolution lente des incidents. | K82: Mettre en place un processus efficace de gestion des incidents.
E83: Registre des opérations effectuées | K83: Allouer des ressources suffisantes pour la résolution des incidents.
D84: L'administration est bien assurée par les utilisateurs | E84: Processus de gestion des incidents | F84: L'administration est bien assurée par les utilisateurs? | G84: OUI | H84: Mauvaise gestion de l'application. | I84: Moyenne | J84: Identifier les performance des applications pas a jour | K84: Mettre en place une surveillance des performances et des alertes.
E85: Fiches types d'intervention | K85: Maintenir les applications à jour.
D86: Vérifier l'existence de procédures formalisées de gestion des incidents | E86: Rapport mensuel de performance | F86: Des procédures formalisées de gestion des incidents sont-elles en place ? | G86: OUI | H86: Problèmes de gestion des incidents. | I86: Elevée | J86: Résolution lente des incidents. | K86: Définir des accords de niveau de service (SLA) et des procédures d'escalade.
E87: Tableau de bord SLA | K87: Automatiser la résolution des incidents.
C88: S’assurer de l’existence et de la mise à disposition du compte rendu mensuel au propriétaire | D88: Le propriétaire dispose d'un compte rendu mensuel de la performance de l'application | E88: Engagement contractuel formalisé | F88: Le propriétaire dispose-t-il d'un compte rendu mensuel de la performance de l'application ? | G88: NON | H88: Manque de visibilité sur la performance de l'application. | I88: Faible | J88: Dégradation des performances non détectées. | K88: Mettre en place une surveillance proactive des performances.
E89: Preuve de livraison dans les délais | K89: Analyser les causes profondes des dégradations de performance.
D90: Le compte rendu respecte le contrat du service | E90: Indicateurs clés de performance | F90: Le compte rendu respecte-t-il le contrat de service ? | G90: PAS | H90: Non-respect des obligations contractuelles. | I90: Elevée | J90: Contentieux avec le fournisseur. | K90: Négocier des contrats clairs avec des clauses de pénalité.
E91: Commentaires du propriétaire | K91: Mettre en place une communication régulière avec le fournisseur.
D92: Le compte rendu est transmis au propriétaire dans les délais convenus? | E92: Procédure de validation | F92: Le compte rendu est-il transmis au propriétaire dans les délais convenus ? | G92: NON | H92: Comptes rendus incompréhensibles ou incomplets. | I92: Moyenne | J92: Compte rendu inexistant. | K92: Fournir des comptes rendus réguliers sur les performances et les incidents.
E93: Attestation de réception | K93: Documenter tous les échanges et les accords.
D94: Le compte rendu contient des indicateurs de performance pertinents pour le propriétaire? | E94: Manuel des procédures | F94: Le compte rendu contient-il des indicateurs de performance pertinents pour le propriétaire ? | G94: NON | H94: Mauvaise communication avec le propriétaire. | I94: Elevée | J94: Contrats de niveau service inadéquats. | K94: Négocier des contrats de niveau de service adaptés aux besoins de l'entreprise.
E95: Plan de diffusion interne | K95: Revoir régulièrement les contrats et les ajuster si nécessaire.
D96: Un processus est en place pour s'assurer que le propriétaire comprend et valide le compte rendu | E96: Registre de diffusion | F96: Un processus est-il en place pour s'assurer que le propriétaire comprend et valide le compte rendu ? | G96: OUI | H96: Absence de guide utilisateur. | I96: Faible | J96: Mauvaise connaissance et manque de conformité. | K96: Former le personnel sur les politiques, les procédures et les exigences de conformité.
E97: Accusés de réception | K97: Mettre à disposition des ressources et une documentation accessibles.
C98: S’assurer de l’existence d'un guide d'utilisateur, manuel de procédures | D98: Il existe un guide utilisateurs / manuel de procédures | E98: Version officielle du manuel utilisateur | F98: Existe-t-il un guide utilisateurs / manuel de procédures ? | G98: OUI | H98: Mauvaise diffusion des guides. | I98: Elevée | J98: Information inaccessible. | K98: Mettre en place des contrôles d'accès pour restreindre l'accès aux informations sensibles.
E99: Plan de diffusion et registre de distribution | K99: Chiffrer les données sensibles.
D100: Le manuel est diffusé | E100: Historique des versions et dates de mise à jour | F100: Le manuel est-il diffusé ? | G100: OUI | H100: Guides non mis à jour. | I100: Moyenne | J100: Mauvaise utilisation de l'outil. | K100: Fournir une formation adéquate sur l'utilisation correcte des outils.
...

Sheet 4.2
A1: Domaines | B1: Points de Contrôle | C1: Objectifs de Contrôle | D1: Critère d’Évaluation | E1: Question d’Évaluation | F1: Réponses | G1: Documents Requis | H1: Risques | I1: Criticités | J1: Conséquences | K1: Recommendations
A2: Audit de la Fonction Informatique | B2: Rôle et positionnement de l'informatique dans l'organisation | C2: Vérifier qu’ont été créés des Comités « informatique » (stratégique, pilotage,..) regroupant les différentes directions de l’Organisation en charge de recenser les besoins et les opportunités, gérer les priorités et suivre les projets ; | D2: Existence officielle des comités | E2: Existe-t-il officiellement des comités informatiques ? | F2: oui | G2: Comptes rendus de réunions. | H2: Absence de gouvernance claire due à des comités non formalisés. | I2: Elevée | J2: Désalignement stratégique compromettant les objectifs IT. | K2: Voici deux recommandations pour chaque critère d'évaluation:
F3: . | G3: Invitations aux réunions ou Ordres du jour. | H3: . | J3: . | K3: Établir un mécanisme de nomination formalisé garantissant une représentation équilibrée des directions au sein des comités informatiques.
D4: Représentation adéquate des différentes directions | E4: Les différentes directions sont-elles représentées dans ces comités ? | F4: non | G4: Listes des participants. | H4: Manque de diversité des perspectives dans les décisions informatiques. | I4: Moyenne | J4: Solutions inadaptées aux besoins réels de l’entreprise. | K4: Mettre en place des réunions trimestrielles de coordination inter-directions pour assurer l'expression des besoins de toutes les entités.
F5: . | G5: Organigramme de l'entreprise. | H5: . | J5: . | K5: Implémenter un processus structuré de collecte des besoins avec des entretiens réguliers auprès des utilisateurs clés.
D6: Capacité à identifier les besoins et opportunités informatiques | E6: Les comités sont-ils capables d'identifier les besoins et opportunités informatiques ? | F6: pas | G6: Comptes rendus de réunions. | H6: Incapacité à anticiper les évolutions technologiques ou métiers. | I6: Elevée | J6: Retard technologique affectant la compétitivité. | K6: Créer une veille technologique participative où chaque département contribue à l'identification d'opportunités d'amélioration.
F7: . | G7: Liste des demandes ou projets en attente/proposés. | H7: . | J7: . | K7: Déployer une matrice de priorisation multicritères (valeur business, coût, risque, alignement stratégique) pour objectiver les décisions.
D8: Gestion efficace des priorités | E8: Les comités gèrent-ils efficacement les priorités ? | F8: oui | G8: Comptes rendus de réunions. | H8: Mauvaise allocation des ressources par priorisation inadéquate. | I8: Faible | J8: Surcoûts ou inefficacités opérationnelles. | K8: Instaurer des revues trimestrielles de portefeuille projets permettant de réaligner les priorités selon l'évolution du contexte.
F9: . | G9: Liste des projets en cours. | H9: . | J9: . | K9: Mettre en place un tableau de bord de suivi de projet standardisé avec indicateurs clés consultable par toutes les parties prenantes.
D10: Suivi régulier des projets | E10: Les comités assurent-ils un suivi régulier des projets ? | F10: pas | G10: Ordres du jour ou Comptes rendus sur plusieurs périodes. | H10: Retards ou échecs de projets par manque de suivi. | I10: Elevée | J10: Échecs de projets entraînant des pertes financières. | K10: Instaurer des réunions d'avancement hebdomadaires avec compte-rendu formalisé et suivi des actions.
F11: . | G11: Emails de suivi ou points d'avancement. | H11: . | J11: . | K11: Officialiser les comités par une charte définissant leur composition, rôle, fréquence et modes de fonctionnement.
C12: Vérifier l’existence d’une charte informatique ou de tout autre document définissant le rôle et le périmètre de responsabilité de la DSI ; | D12: Existence officielle des comités | E12: Existe-t-il officiellement des comités informatiques ? | F12: non | G12: Charte ou mandat officiel du comité informatique. | H12: Redondance dans la prise de décision sans comités officiels. | I12: Moyenne | J12: Retards décisionnels et inefficacité organisationnelle. | K12: Documenter systématiquement les décisions des comités dans un référentiel accessible et diffusé à tous les acteurs concernés.
F13: . | G13: Procès-verbaux ou rapports des réunions du comité informatique. | H13: . | J13: . | K13: Établir un quota minimum de représentation pour chaque direction dans les instances de gouvernance informatique.
D14: Représentation adéquate des différentes directions | E14: Les différentes directions sont-elles représentées dans ces comités ? | F14: oui | G14: Liste des membres du comité informatique avec leurs rôles et départements. | H14: Décisions biaisées par une représentation déséquilibrée. | I14: Elevée | J14: Mauvais choix stratégiques impactant la performance IT. | K14: Organiser des sessions de travail dédiées pour les directions sous-représentées afin de garantir la prise en compte de leurs besoins.
F15: . | G15: Organigramme ou tableau de représentation des directions au sein du comité. | H15: . | J15: . | K15: Mettre en œuvre un processus continu d'analyse des besoins utilisateurs incluant observations terrain et ateliers de co-création.
D16: Capacité à identifier les besoins et opportunités informatiques | E16: Les comités sont-ils capables d'identifier les besoins et opportunités informatiques ? | F16: pas | G16: Documents de synthèse ou rapports sur l’identification des besoins informatiques. | H16: Solutions inadaptées faute d’identification des besoins. | I16: Faible | J16: Mise en œuvre de systèmes inefficaces ou coûteux. | K16: Développer un canal de remontée d'idées innovantes avec un système de valorisation des propositions retenues.
F17: . | G17: Plan stratégique informatique basé sur les recommandations du comité. | H17: . | J17: . | K17: Adopter une méthodologie de scoring objective pour hiérarchiser les projets selon des critères stratégiques préétablis.
D18: Gestion efficace des priorités | E18: Les comités gèrent-ils efficacement les priorités ? | F18: pas | G18: Tableau de bord des priorités informatiques validé par le comité. | H18: Surcoûts ou délais dus à une mauvaise gestion des priorités. | I18: Elevée | J18: Dérapages budgétaires et retards de livraison. | K18: Établir un comité d'arbitrage mensuel pour réévaluer les priorités face aux changements de contexte business.
F19: . | G19: Plan d’action ou calendrier des projets priorisés par le comité. | H19: . | J19: . | K19: Implémenter un outil de gestion de projet collaboratif permettant un suivi en temps réel des avancées et blocages.
D20: Suivi régulier des projets | E20: Les comités assurent-ils un suivi régulier des projets ? | F20: oui | G20: Rapports périodiques de suivi des projets (exemple : état d’avancement, KPI). | H20: Déviation des objectifs sans suivi régulier des projets. | I20: Moyenne | J20: Échec dans l’atteinte des objectifs stratégiques. | K20: Instituer des revues de jalons formelles avec validation explicite des livrables par les parties prenantes.
F21: . | G21: Minutes ou comptes rendus des réunions de suivi des projets. | H21: . | J21: . | K21: Intégrer systématiquement le DSI aux comités de direction et aux sessions de planification stratégique de l'entreprise.
C22: Évaluer le degré d’implication et de maîtrise des organes de gestion dans les systèmes d’information de l’Organisation ; 4.2.4.1.4. Vérifier en pratique que le leadership des grands projets est assuré par les organes de gestion ; | D22: Niveau d'implication dans la prise de décision stratégique | E22: Les organes de gestion sont-ils impliqués dans la prise de décision stratégique ? | F22: non | G22: Procès-verbaux des réunions stratégiques auxquelles les organes de gestion ont participé | H22: Influence limitée sur les orientations stratégiques de l’IT. | I22: Elevée | J22: Incapacité à orienter les investissements IT efficacement. | K22: Formaliser le rôle consultatif de la DSI dans les décisions business ayant des implications technologiques significatives.
F23: . | G23: Plan stratégique validé par les organes de gestion | H23: . | J23: . | K23: Établir un programme de formation continue pour la direction informatique sur les processus métiers et les enjeux sectoriels.
D24: Compréhension approfondie des systèmes d'information | E24: Les organes de gestion ont-ils une compréhension approfondie des systèmes d'information ? | F24: non | G24: Documents de formation ou de sensibilisation aux systèmes d’information destinés aux organes de gestion | H24: Choix technologiques inadaptés par méconnaissance des systèmes. | I24: Faible | J24: Adoption de solutions obsolètes ou non performantes. | K24: Organiser des immersions périodiques des responsables informatiques dans les départements opérationnels.
F25: . | G25: Rapports ou présentations sur le fonctionnement des systèmes d’information, destinés aux organes de gestion | H25: . | J25: . | K25: Créer un comité d'innovation technologique présidé par le DSI pour évaluer et proposer des orientations stratégiques.
D26: Capacité à influencer les orientations technologiques | E26: Les organes de gestion peuvent-ils influencer les orientations technologiques ? | F26: pas | G26: Documents de planification des orientations technologiques avec contributions des organes de gestion | H26: Retard dans l’adoption de technologies pertinentes. | I26: Elevée | J26: Perte de compétitivité face aux concurrents. | K26: Établir un processus formel de validation des choix technologiques impliquant consultations et démonstrations de faisabilité.
F27: . | G27: Recommandations ou avis des organes de gestion sur les choix technologiques | H27: . | J27: . | K27: Développer un curriculum de formation adapté au profil de chaque décideur couvrant les fondamentaux des SI.
D28: Accès à une formation ou support adéquat | E28: Les organes de gestion ont-ils accès à une formation ou support adéquat ? | F28: oui | G28: Programme de formation des organes de gestion sur les systèmes d’information | H28: Incompétence dans la gestion IT faute de formation. | I28: Moyenne | J28: Erreurs opérationnelles dues à des compétences insuffisantes. | K28: Mettre en place un système de mentorat ou coaching technologique pour les dirigeants moins familiers avec le numérique.
F29: . | G29: Documentation de support ou guide d’utilisation des systèmes d’information, destinés aux organes de gestion | H29: . | J29: . | K29: Rendre obligatoire la présence des décideurs aux réunions stratégiques liées aux SI avec préparation préalable structurée.
D30: Participation active aux réunions liées aux systèmes d'information | E30: Les organes de gestion participent-ils activement aux réunions liées aux systèmes d'information ? | F30: pas | G30: Liste de présence aux réunions concernant les systèmes d’information | H30: Décisions mal informées par manque de participation. | I30: Elevée | J30: Mauvais choix technologiques ou stratégiques. | K30: Créer des synthèses décisionnelles adaptées aux profils des dirigeants pour faciliter leur participation informée.
F31: . | G31: Comptes rendus des réunions montrant la participation des organes de gestion | H31: . | J31: . | K31: Établir une matrice RACI claire définissant le rôle de la direction dans chaque phase critique des projets.
C32: Vérifier en pratique que le leadership des grands projets est assuré par les organes de gestion ; | D32: Présence active et leadership dans la direction des projets | E32: Les organes de gestion sont-ils présents et actifs dans la direction des projets ? | F32: non | G32: Comptes rendus des réunions de direction de projets montrant la participation des organes de gestion | H32: Échecs de projets par absence de leadership affirmé. | I32: Faible | J32: Abandon ou échec de projets critiques. | K32: Instituer des points de décision formels nécessitant l'implication directe de la direction avec préparation adéquate.
F33: . | G33: Documents de suivi des actions ou décisions prises par les organes de gestion dans le cadre des projets | H33: . | J33: . | K33: Mettre en place un processus budgétaire itératif avec révisions trimestrielles basées sur l'avancement réel des projets.
D34: Allocation efficace des ressources nécessaires | E34: Les ressources nécessaires sont-elles allouées efficacement ? | F34: oui | G34: Budget alloué aux projets informatiques validé par les organes de gestion | H34: Sous-utilisation des ressources par une allocation inefficace. | I34: Elevée | J34: Gaspillage de ressources humaines et matérielles. | K34: Développer des scénarios d'allocation de ressources alternatifs pour s'adapter rapidement aux changements de priorités.
F35: . | G35: État des ressources (humaines, financières, matérielles) allouées aux projets | H35: . | J35: . | K35: Implémenter un système de rapports d'avancement standardisés avec indicateurs de performance alignés sur les objectifs stratégiques.
D36: Suivi régulier et ajustements stratégiques des progrès | E36: Un suivi régulier des progrès est-il effectué avec des ajustements stratégiques ? | F36: oui | G36: Rapports d’avancement réguliers des projets informatiques | H36: Dérapages stratégiques sans ajustements réguliers. | I36: Moyenne | J36: Déviation des priorités stratégiques de l’entreprise. | K36: Établir des revues d'étape obligatoires avec la direction pour valider les ajustements de cap nécessaires.
F37: . | G37: Documents justifiant les ajustements stratégiques apportés aux projets | H37: . | J37: . | K37: Définir un plan de communication structuré incluant fréquence, format et canaux adaptés à chaque niveau de l'organisation.
D38: Communication efficace avec les équipes de projet | E38: La communication avec les équipes de projet est-elle efficace ? | F38: non | G38: Plan de communication entre les organes de gestion et les équipes de projet | H38: Mauvaise coordination due à une communication insuffisante. | I38: Elevée | J38: Retards ou conflits inter-équipes. | K38: Mettre en place des sessions de feedback régulières entre la direction et les équipes projet pour maintenir l'alignement.
F39: . | G39: Enquêtes de satisfaction ou retours d’expérience sur la communication | H39: . | J39: . | K39: Établir un processus décisionnel clair avec niveaux d'escalade et délais maximums de réponse pour éviter les blocages.
D40: Capacité à prendre des décisions stratégiques pour les projets | E40: Les organes de gestion sont-ils capables de prendre des décisions stratégiques pour les projets ? | F40: pas | G40: Documents de décision stratégique validés par les organes de gestion | H40: Blocages ou erreurs par manque de décisions stratégiques. | I40: Faible | J40: Blocages opérationnels ou stratégiques. | K40: Développer un cadre d'évaluation des impacts business pour éclairer les décisions avec une vision globale des enjeux.
F41: . | G41: Analyses d'impact ou études de faisabilité ayant mené à ces décisions | H41: . | J41: . | K41: Former les MOA aux techniques d'analyse des processus métiers et cartographie des flux d'information.
C42: Vérifier que les métiers assurent leur rôle de MOA. | D42: Compréhension approfondie des besoins métiers | E42: Les organes de gestion ont-ils une compréhension approfondie des besoins métiers ? | F42: pas | G42: Documents de synthèse des besoins métiers validés par les organes de gestion | H42: Solutions inadaptées par méconnaissance des besoins métiers. | I42: Elevée | J42: Mise en place de solutions non fonctionnelles. | K42: Organiser des ateliers réguliers entre MOA et utilisateurs finaux pour capturer les besoins implicites.
F43: . | G43: Spécifications fonctionnelles détaillées rédigées ou validées par les organes de gestion | H43: . | J43: . | K43: Établir des modèles standardisés de spécifications fonctionnelles avec exemples concrets et cas d'utilisation.
D44: Capacité à spécifier clairement les exigences fonctionnelles | E44: Les organes de gestion peuvent-ils spécifier clairement les exigences fonctionnelles ? | F44: oui | G44: Spécifications fonctionnelles détaillées rédigées ou approuvées par les organes de gestion. | H44: Exigences floues entraînant des livrables non conformes. | I44: Moyenne | J44: Livraison de systèmes non conformes aux attentes. | K44: Former les MOA aux techniques de rédaction de user stories et critères d'acceptation selon les méthodologies agiles.
F45: . | G45: Matrice de traçabilité des exigences fonctionnelles, montrant comment les exigences métiers sont traduites en spécifications techniques. | H45: . | J45: . | K45: Instaurer des rituels de collaboration structurés (ateliers de conception, démonstrations intermédiaires, revues de sprint).
D46: Collaboration efficace avec les équipes techniques | E46: Une collaboration efficace avec les équipes techniques est-elle assurée ? | F46: non | G46: Plan de communication et de collaboration entre les organes de gestion et les équipes techniques | H46: Conflits ou retards dus à une mauvaise collaboration technique. | I46: Elevée | J46: Retards de projets et tensions organisationnelles. | K46: Établir un glossaire commun MOA/MOE pour assurer une compréhension partagée des concepts techniques et métiers.
F47: . | G47: Retours d'expérience ou enquêtes de satisfaction mesurant l'efficacité de cette collaboration | H47: . | J47: . | K47: Systématiser les tests utilisateurs avec scénarios réels avant validation finale des solutions.
D48: Validation des solutions pour s'assurer de leur adéquation | E48: Les solutions sont-elles validées pour s'assurer de leur adéquation ? | F48: oui | G48: Documents de validation des solutions informatiques par les organes de gestion | H48: Mise en production de solutions inadéquates. | I48: Faible | J48: Pertes financières et insatisfaction des utilisateurs. | K48: Mettre en place des phases de recette formalisées avec critères d'acceptation mesurables et objectifs.
F49: . | G49: Critères de validation des solutions | H49: . | J49: . | K49: Développer un parcours de formation certifiant pour les MOA couvrant analyse fonctionnelle, gestion de projet et techniques de test.
D50: Accès à une formation ou support pour leur rôle de MOA | E50: Les MOA ont-ils accès à une formation ou support pour leur rôle ? | F50: pas | G50: Plan de formation pour les MOA | H50: Incapacité à assumer le rôle de MOA faute de support. | I50: Elevée | J50: Échec des projets par manque de pilotage MOA. | K50: Créer une communauté de pratique des MOA pour le partage d'expériences et l'entraide entre pairs.
F51: . | G51: Documentation ou support mis à disposition des MOA | H51: . | J51: . | K51: Établir un processus de validation des exigences métiers impliquant les utilisateurs finaux et la direction.
F52: non | I52: Moyenne | K52: Instituer des revues régulières des solutions déployées pour évaluer leur adéquation continue aux besoins évolutifs.
F53: . | K53: Mettre en place une matrice de couverture fonctionnelle évaluée régulièrement par les utilisateurs clés.
B54: Planification stratégique | C54: Vérifier la couverture du périmètre fonctionnel ; | D54: Alignement avec les besoins métiers | E54: Les solutions sont-elles alignées avec les besoins métiers ? | F54: non | G54: Matrice de traçabilité des exigences métiers vers les fonctionnalités de la solution. | H54: Solutions déconnectées des besoins opérationnels. | I54: Elevée | J54: Insatisfaction des utilisateurs et inefficacité opérationnelle. | K54: Établir un processus d'amélioration continue avec collecte structurée des besoins non couverts.
F55: . | G55: Résultats des tests d'acceptation utilisateur (UAT) validant l'alignement avec les besoins métiers. | H55: . | J55: . | K55: Développer une cartographie des interfaces et flux de données entre systèmes, régulièrement mise à jour.
D56: Exhaustivité des fonctionnalités couvertes | E56: Les fonctionnalités couvertes sont-elles exhaustives ? | F56: oui | G56: Tableau comparatif des fonctionnalités requises et des fonctionnalités implémentées. | H56: Manque de fonctionnalités critiques dans les systèmes. | I56: Faible | J56: Systèmes incomplets ou inutilisables. | K56: Établir des standards d'interopérabilité et API governance pour faciliter les intégrations futures.
F57: . | G57: Documentation des analyses de couverture fonctionnelle. | H57: . | J57: . | K57: Mettre en place une veille réglementaire proactive avec évaluation périodique des impacts sur les systèmes.
D58: Intégration avec d'autres systèmes existants | E58: Les solutions sont-elles intégrées avec d'autres systèmes existants ? | F58: pas | G58: Tableau comparatif des fonctionnalités requises et des fonctionnalités implémentées. | H58: Problèmes d’interopérabilité avec les systèmes existants. | I58: Elevée | J58: Pannes ou inefficacités dues à des systèmes non intégrés. | K58: Établir un comité de conformité impliquant DSI, juridique et métiers pour anticiper les évolutions réglementaires.
F59: . | G59: Documentation des analyses de couverture fonctionnelle. | H59: . | J59: . | K59: Adopter des architectures modulaires permettant d'isoler les composants susceptibles d'évoluer fréquemment.
D60: Capacité à répondre aux exigences réglementaires | E60: Les solutions répondent-elles aux exigences réglementaires ? | F60: oui | G60: Rapport d'audit de conformité réglementaire. | H60: Non-conformité réglementaire des solutions déployées. | I60: Moyenne | J60: Amendes ou sanctions réglementaires. | K60: Établir des principes d'architecture évolutive privilégiant le découplage et les microservices quand pertinent.
F61: . | G61: Documentation des contrôles mis en place pour répondre aux exigences réglementaires. | H61: . | J61: . | K61: Instituer une révision semestrielle des analyses et procédures avec validation formelle des mises à jour.
D62: Flexibilité pour s'adapter aux changements organisationnels | E62: Les solutions sont-elles flexibles pour s'adapter aux changements organisationnels ? | F62: oui | G62: Documentation sur la modularité et la configurabilité de la solution. | H62: Inflexibilité face aux évolutions organisationnelles. | I62: Elevée | J62: Incapacité à répondre aux évolutions organisationnelles. | K62: Mettre en place un système d'alerte automatique pour les documents n'ayant pas été revus depuis plus de 12 mois.
F63: . | G63: Exemples de modifications ou d'adaptations réalisées lors de changements organisationnels. | H63: . | J63: . | K63: Cartographier les contributions des systèmes d'information aux objectifs stratégiques de l'entreprise.
C64: Vérifier l’existence d’une analyse à jour des procédures de pilotage et de mise à jour du plan informatique ; | D64: Actualité des analyses et des procédures | E64: Les analyses et procédures sont-elles à jour ? | F64: non | G64: Historique des révisions des documents d'analyse et de procédure. | H64: Obsolescence des processus par analyses non actualisées. | I64: Faible | J64: Processus inefficaces ou obsolètes. | K64: Établir un processus de validation croisée des initiatives informatiques avec la stratégie globale documentée.
F65: . | G65: Dates de dernière revue et approbation des documents. | H65: . | J65: . | K65: Systématiser les workshops multi-acteurs lors des phases d'analyse et de conception des solutions.
D66: Cohérence avec la stratégie informatique globale | E66: Les solutions sont-elles cohérentes avec la stratégie informatique globale ? | F66: non | G66: Schéma directeur informatique montrant l'alignement de la solution avec la stratégie. | H66: Déviation des objectifs IT par manque de cohérence stratégique. | I66: Elevée | J66: Non-atteinte des objectifs IT stratégiques. | K66: Mettre en place un modèle de gouvernance participative avec représentation formelle des parties prenantes clés.
F67: . | G67: Justification de la solution par rapport aux objectifs stratégiques de l'entreprise. | H67: . | J67: . | K67: Établir un calendrier de révision systématique des documents avec responsables désignés.
D68: Implication des parties prenantes dans le processus | E68: Les parties prenantes sont-elles impliquées dans le processus ? | F68: oui | G68: Liste des parties prenantes impliquées dans le projet. | H68: Décisions mal informées sans implication des parties prenantes. | I68: Moyenne | J68: Décisions stratégiques mal fondées. | K68: Implémenter un workflow de validation des mises à jour incluant approbations multi-niveaux.
F69: . | G69: Comptes rendus des réunions avec les parties prenantes. | H69: . | J69: . | K69: Créer un tableau de bord de suivi des actions correctives avec statuts et échéances claires.
D70: Efficacité des mécanismes de mise à jour | E70: Les mécanismes de mise à jour sont-ils efficaces ? | F70: pas | G70: Procédure de gestion des mises à jour. | H70: Stagnation des processus par des mises à jour inefficaces. | I70: Elevée | J70: Absence d’amélioration des processus IT. | K70: Mettre en place des revues périodiques dédiées au suivi des recommandations antérieures.
F71: . | G71: Historique des mises à jour avec les résultats et les incidents éventuels. | H71: . | J71: . | K71: Établir un référentiel documentaire centralisé avec modèles standardisés et métadonnées.
D72: Suivi des recommandations et des actions correctives | E72: Les recommandations et actions correctives sont-elles suivies ? | F72: oui | G72: Plan d'action pour le suivi des recommandations. | H72: Non-application des recommandations correctives. | I72: Faible | J72: Répétition des erreurs opérationnelles. | K72: Formaliser le processus de création et validation des documents avec étapes et responsables clairement définis.
F73: . | G73: Rapports de suivi des actions correctives. | H73: . | J73: . | K73: Mettre en place un processus de revue périodique avec alertes automatiques pour les documents obsolètes.
C74: Vérifier l’existence des documents à jour d’urbanisme de l’Organisation ; | D74: Existence formelle des documents | E74: Existe-t-il des documents formels pour ces processus ? | F74: non | G74: Manuel des procédures. | H74: Absence de documentation entraînant des incohérences. | I74: Elevée | J74: Erreurs opérationnelles dues à des incohérences. | K74: Établir un calendrier rolling de mise à jour des informations critiques avec responsables désignés.
F75: . | G75: Diagrammes de processus (BPMN, etc.). | H75: . | J75: . | K75: Déployer une plateforme documentaire collaborative avec droits d'accès différenciés selon les profils utilisateurs.
D76: Actualité des informations contenues | E76: Les informations contenues dans les documents sont-elles à jour ? | F76: pas | G76: Historique des révisions des documents. | H76: Utilisation d’informations obsolètes dans les décisions. | I76: Moyenne | J76: Décisions stratégiques erronées. | K76: Mettre en œuvre un système d'indexation et recherche performant facilitant l'accès contextuel aux documents.
F77: . | G77: Dates de la dernière mise à jour des documents. | H77: . | J77: . | K77: Établir une matrice de conformité entre la documentation SI et les politiques organisationnelles.
D78: Accessibilité pour toutes les parties concernées | E78: Les documents sont-ils accessibles pour toutes les parties concernées ? | F78: oui | G78: Politique d'accès aux documents. | H78: Manque de transparence par documents inaccessibles. | I78: Elevée | J78: Manque de confiance des parties prenantes. | K78: Instaurer un processus de validation croisée impliquant les responsables des politiques internes.
F79: . | G79: Liste des droits d'accès aux documents. | H79: . | J79: . | K79: Créer des liens explicites entre la documentation et les processus décisionnels qu'elle doit éclairer.
D80: Alignement avec les politiques organisationnelles | E80: Les solutions sont-elles alignées avec les politiques organisationnelles ? | F80: oui | G80: Tableau de conformité des solutions avec les politiques. | H80: Non-respect des politiques par manque d’alignement. | I80: Faible | J80: Non-conformité aux politiques internes. | K80: Formaliser l'utilisation obligatoire de certains documents clés dans les processus de gouvernance.
F81: . | G81: Justification de l'alignement des solutions avec les politiques. | H81: . | J81: . | K81: Établir un calendrier de révision obligatoire avec rôles et responsabilités clairement définis.
D82: Intégration dans les processus décisionnels | E82: Les solutions sont-elles intégrées dans les processus décisionnels ? | F82: non | G82: Diagramme montrant l'intégration des solutions dans les processus décisionnels. | H82: Décisions non documentées compromettant la traçabilité. | I82: Elevée | J82: Perte de traçabilité des décisions critiques. | K82: Mettre en place des indicateurs de fraîcheur des analyses visibles par tous les utilisateurs.
F83: . | G83: Exemples de décisions prises basées sur l'utilisation de ces solutions. | H83: . | J83: . | K83: Développer une matrice de conformité documentant l'alignement des pratiques avec les exigences réglementaires.
C84: Vérifier l’existence d’une analyse à jour des procédures de pilotage et de mise à jour du plan d’occupation des sols (POS) ; | D84: Actualité des analyses et des procédures | E84: Les analyses et procédures sont-elles à jour ? | F84: non | G84: Historique des révisions des documents d'analyse. | H84: Décisions basées sur des analyses dépassées. | I84: Moyenne | J84: Mauvais choix opérationnels ou stratégiques. | K84: Établir un processus de revue réglementaire annuel impliquant experts juridiques et informatiques.
F85: . | G85: Dates de dernière revue et approbation des procédures. | H85: . | J85: . | K85: Former des référents locaux responsables de la collecte et validation des informations spécifiques.
D86: Conformité aux réglementations locales | E86: Les procédures sont-elles conformes aux réglementations locales ? | F86: oui | G86: Rapport d'audit de conformité aux réglementations locales. | H86: Risques juridiques par non-conformité réglementaire. | I86: Elevée | J86: Poursuites judiciaires ou amendes. | K86: Organiser des ateliers collaboratifs réguliers impliquant les équipes locales dans les mises à jour.
F87: . | G87: Tableau de conformité des procédures avec les réglementations locales. | H87: . | J87: . | K87: Automatiser les alertes de révision basées sur des événements déclencheurs (changements organisationnels, évolutions réglementaires).
D88: Implication des acteurs locaux dans le processus | E88: Les acteurs locaux sont-ils impliqués dans le processus ? | F88: pas | G88: Liste des acteurs locaux impliqués. | H88: Manque d’adhésion locale aux processus IT. | I88: Faible | J88: Résistance au changement et inefficacité locale. | K88: Établir un workflow de validation des mises à jour avec étapes et responsables clairement identifiés.
F89: . | G89: Comptes rendus des réunions avec les acteurs locaux. | H89: . | J89: . | K89: Implémenter un système de tracking des recommandations avec indicateurs de mise en œuvre.
D90: Efficacité des mécanismes de mise à jour | E90: Les mécanismes de mise à jour sont-ils efficaces ? | F90: pas | G90: Procédure de gestion des mises à jour. | H90: Retards dans l’adaptation des procédures aux changements. | I90: Elevée | J90: Processus inadaptés aux nouvelles exigences. | K90: Établir des revues formelles d'efficacité post-implémentation des actions correctives.
F91: . | G91: Historique des mises à jour et incidents rencontrés. | H91: . | J91: . | K91: Établir un référentiel technologique officiel avec roadmaps d'évolution pour chaque composant.
D92: Suivi des recommandations et des actions correctives | E92: Les recommandations et actions correctives sont-elles suivies ? | F92: oui | G92: Plan de suivi des recommandations (ou simple liste Excel). | H92: Persistance des problèmes par absence de suivi correctif. | I92: Moyenne | J92: Problèmes récurrents affectant la performance. | K92: Mettre en place un comité d'architecture chargé de valider les choix technologiques et exceptions.
F93: . | G93: Emails ou preuves de clôture des actions. | H93: . | J93: . | K93: Cartographier les flux de données inter-applications et identifier les opportunités d'intégration.
C94: Vérifier la cohérence et l’homogénéité des technologies ; | D94: Standardisation des technologies utilisées | E94: Les technologies utilisées sont-elles standardisées ? | F94: non | G94: Liste des logiciels et matériels principaux utilisés. | H94: Hétérogénéité technologique compliquant la maintenance. | I94: Elevée | J94: Coûts de maintenance élevés et pannes fréquentes. | K94: Déployer une plateforme d'intégration (ESB ou API Management) pour standardiser les échanges.
F95: . | G95: Inventaire du parc informatique. | H95: . | J95: . | K95: Établir une matrice d'alignement entre les choix technologiques et les orientations stratégiques.
D96: Intégration des systèmes pour éviter les silos | E96: Les systèmes sont-ils intégrés pour éviter les silos ? | F96: oui | G96: Schéma simplifié des applications et de leurs liens. | H96: Inefficacité due à des systèmes non intégrés. | I96: Faible | J96: Perte d’efficacité opérationnelle. | K96: Développer des principes d'architecture d'entreprise guidant les décisions techniques vers la cible.
F97: . | G97: Description des flux de données entre systèmes principaux. | H97: . | J97: . | K97: Mettre en place des tests utilisateurs systématiques avant déploiement de nouvelles interfaces.
D98: Cohérence avec la stratégie technologique globale | E98: Les solutions sont-elles cohérentes avec la stratégie technologique globale ? | F98: non | G98: Document de stratégie informatique (même synthétique). | H98: Incohérence avec les objectifs technologiques à long terme. | I98: Elevée | J98: Déviation des priorités technologiques. | K98: Établir des standards d'ergonomie et d'expérience utilisateur adaptés aux différents profils.
F99: . | G99: Compte-rendu de comité validant les choix technologiques. | H99: . | J99: .
D100: Facilité d'utilisation pour les utilisateurs | E100: Les solutions sont-elles faciles à utiliser pour les utilisateurs ? | F100: pas | G100: Retours utilisateurs collectés (emails, tickets support, notes). | H100: Adoption limitée par une interface utilisateur complexe. | I100: Moyenne | J100: Faible adoption des systèmes par les utilisateurs. | K100: Voici deux recommandations pour chaque critère d'évaluation:
...

Sheet 4.3
A1: Domaine | B1: Points de Contrôle | C1: Objectifs de Contrôle | D1: Critère d’Évaluation | E1: Question d’Évaluation | F1: Réponses | G1: Documents Requis | H1: Risques | I1: Criticités | J1: Conséquences | K1: Recommendations
A2: Audit et Contrôle des Projets Informatiques | B2: Objectifs et enjeux du projet | C2: S’assurer qu’une étude de la valeur et des études d'opportunité et d'impacts ont été réalisées ; | D2: Existence d'un document formel d'étude de la valeur avec analyse coûts/bénéfices quantifiée | E2: Un document formel d'étude de la valeur avec une analyse coûts/bénéfices quantifiée a-t-il été établi ? | F2: Non | G2: Registre des risques du projet | H2: Absence d'une étude complète d'analyse de la valeur ajoutée compromettant la justification économique du projet. | I2: Elevée | J2: Absence de justification économique du projet, pouvant entraîner un rejet par la direction. | K2: Élaborez un modèle standardisé pour l’étude de la valeur, incluant une analyse coûts/bénéfices claire et quantifiée.
G3: Plan de gestion des risques | H3: . | J3: . | K3: .
D4: Présence d'une analyse des impacts organisationnels, techniques et humains documentée | E4: Existe-t-il une analyse documentée des impacts organisationnels, techniques et humains du projet ? | F4: Oui | G4: Diagramme des processus (ex. BPMN ou flowchart) | H4: Sous-estimation des perturbations organisationnelles et résistances au changement faute d'analyse d'impact approfondie. | I4: Moyenne | J4: Manque de préparation aux changements, risquant des résistances organisationnelles ou des échecs techniques. | K4: Impliquez des experts financiers pour valider les hypothèses et les projections de l’étude de la valeur.
G5: Rapport de validation de la cartographie par les parties prenantes | H5: . | J5: . | K5: .
D6: Validation de l'étude d'opportunité par les parties prenantes concernées (signatures, PV de réunion) | E6: L'étude d'opportunité a-t-elle été formellement validée par les parties prenantes concernées (signatures, PV de réunion) ? | F6: Non | G6: Rapport d’analyse des inefficacités | H6: Contestation ultérieure des choix initiaux par absence de validation formelle des parties prenantes. | I6: Elevée | J6: Décision non validée, pouvant conduire à un manque de soutien des parties prenantes. | K6: Réalisez une analyse des impacts à l’aide d’un cadre structuré (ex. : matrice SWOT) couvrant les dimensions organisationnelles, techniques et humaines.
G7: Compte-rendu des ateliers avec les utilisateurs | H7: . | J7: . | K7: .
D8: Cohérence entre les bénéfices attendus et les objectifs stratégiques de l'entreprise | E8: Les bénéfices attendus du projet sont-ils clairement alignés avec les objectifs stratégiques de l'entreprise ? | F8: Non | G8: Tableau de bord des KPI actuels | H8: Désalignement entre les investissements informatiques et les priorités stratégiques de l'entreprise. | I8: Faible | J8: Déviation des objectifs stratégiques, réduisant l’impact positif du projet. | K8: Organisez des ateliers avec les parties prenantes pour identifier et documenter les impacts potentiels.
G9: Méthodologie de collecte et de calcul des KPI | H9: . | J9: . | K9: .
D10: Évaluation des risques potentiels liés au projet et mesures d'atténuation identifiées | E10: Les risques potentiels liés au projet ont-ils été évalués et des mesures d'atténuation ont-elles été identifiées ? | F10: Oui | G10: Procès-verbal des réunions de consultation | H10: Exposition à des menaces non anticipées pouvant compromettre le succès du projet. | I10: Elevée | J10: Exposition à des échecs imprévus due à l’absence de gestion proactive des risques. | K10: Mettez en place un processus formel de validation impliquant toutes les parties prenantes, avec signatures et PV de réunion.
G11: Questionnaire ou grille de collecte des retours | H11: . | J11: . | K11: .
C12: S’assurer qu’un bilan critique des processus existants a été Effectué ; | D12: Existence d'une cartographie complète des processus actuels | E12: Une cartographie complète des processus actuels a-t-elle été réalisée ? | F12: Non | G12: Rapport d’analyse comparative (benchmarking) | H12: Développement de solutions inadaptées par méconnaissance des flux de travail actuels. | I12: Moyenne | J12: Vision incomplète des opérations, entraînant des solutions inadaptées. | K12: Utilisez un outil de gestion de projet pour consigner les validations et assurer leur traçabilité.
G13: Liste des écarts identifiés avec priorisation | H13: . | J13: . | K13: .
F14: Oui | G14: Plan d’optimisation des processus | H14: Persistance de problèmes opérationnels non identifiés dans le nouveau système. | I14: Elevée | J14: Maintien de processus inefficaces, nuisant à la performance globale. | K14: Alignez les bénéfices attendus sur les objectifs stratégiques via une matrice de correspondance validée par la direction.
D15: Documentation des inefficacités, goulots d'étranglement et points de douleur identifiés | E15: Les inefficacités, goulots d'étranglement et points de douleur ont-ils été documentés ? | G15: Rapport d’évaluation des résultats des optimisations | H15: . | J15: . | K15: .
F16: Oui | G16: Comparatif des KPI avant/après optimisation | H16: Impossibilité d'évaluer objectivement les améliorations apportées par le projet. | I16: Faible | J16: Incapacité à évaluer les progrès ou à identifier les priorités d’amélioration. | K16: Organisez des revues régulières avec les parties prenantes pour vérifier la cohérence des bénéfices avec les priorités stratégiques.
D17: Mesure des performances actuelles avec indicateurs quantifiables (KPI) | E17: Des indicateurs quantifiables (KPI) mesurant les performances actuelles sont-ils en place ? | G17: Rapport d’audit des gains réalisés | H17: . | J17: . | K17: .
F18: Non | G18: Étude d’impact comparatif | H18: Conception de solutions déconnectées des besoins réels des utilisateurs. | I18: Elevée | J18: Solutions déconnectées des besoins réels, risquant un rejet par les utilisateurs. | K18: Établissez un registre des risques avec une méthode standard (ex. : AMDEC) pour identifier et évaluer les risques.
D19: Consultation formelle des utilisateurs et parties prenantes sur les problèmes rencontrés | E19: Une consultation formelle des utilisateurs et parties prenantes sur les problèmes rencontrés a-t-elle été menée ? | G19: Matrice de décision | H19: . | J19: . | K19: .
F20: Oui | G20: Analyse financière du ROI | H20: Perpétuation des pratiques sous-optimales par méconnaissance des standards du secteur. | I20: Moyenne | J20: Maintien de pratiques obsolètes, réduisant la compétitivité de l’entreprise. | K20: Définissez des plans d’atténuation clairs pour chaque risque, avec des responsables désignés et des échéances.
D21: Identification des écarts entre l'état actuel et les meilleures pratiques du secteur | E21: Les écarts entre l'état actuel et les meilleures pratiques du secteur ont-ils été identifiés ? | G21: Hypothèses et méthodologie du calcul du ROI | H21: . | J21: . | K21: .
C22: S’assurer que le choix de recourir à un nouveau système est obtenu après optimisation des processus concernés et vérification que cette optimisation ne suffit pas à apporter par elle-même les gains de performance attendus ; | D22: Preuve d'actions d'optimisation des processus existants avant décision de changement de système | E22: Des actions d'optimisation des processus existants ont-elles été entreprises avant la décision de changer de système ? | F22: Non | G22: Procès-verbal de la réunion de validation par la direction | H22: Surinvestissement dans de nouvelles solutions alors que l'optimisation des processus existants aurait pu suffire. | I22: Elevée | J22: Décision hâtive de changement de système, gaspillant des ressources sur des solutions non nécessaires. | K22: Utilisez un outil de cartographie des processus (ex. : BPMN) pour documenter les processus actuels de manière complète.
G23: Note de synthèse pour la direction | H23: . | J23: . | K23: .
D24: Mesure des gains de performance obtenus après optimisation des processus existants | E24: Les gains de performance obtenus après optimisation des processus existants ont-ils été mesurés ? | F24: Oui | G24: Document de cadrage du projet (Project Charter) | H24: Incapacité à quantifier les bénéfices réels des améliorations de processus déjà réalisées. | I24: Faible | J24: Incapacité à prouver l’efficacité des optimisations, affaiblissant la justification du projet. | K24: Impliquez les équipes opérationnelles pour valider l’exactitude de la cartographie des processus.
G25: Fiche de validation signée par les parties prenantes | H25: . | J25: . | K25: .
D26: Analyse comparative documentée entre l'amélioration des processus existants et l'adoption d'un nouveau système | E26: Une analyse comparative entre l'amélioration des processus existants et l'adoption d'un nouveau système a-t-elle été documentée ? | F26: Non | G26: Liste des indicateurs SMART | H26: Décision d'investissement biaisée par absence de comparaison méthodique entre options stratégiques. | I26: Elevée | J26: Choix non éclairé entre optimisation et nouveau système, risquant des investissements inadéquats. | K26: Documentez les inefficacités dans un rapport structuré, en utilisant des diagrammes pour illustrer les goulots d’étranglement.
G27: Plan de suivi des indicateurs | H27: . | J27: . | K27: .
D28: Évaluation du retour sur investissement (ROI) des différentes options envisagées | E28: Le retour sur investissement (ROI) des différentes options envisagées a-t-il été évalué ? | F28: Non | G28: Compte-rendu des ateliers de communication | H28: Sélection de solutions non optimales économiquement par manque d'analyse comparative rigoureuse. | I28: Moyenne | J28: Sous-estimation des coûts ou surestimation des bénéfices, faussant la décision d’investissement. | K28: Priorisez les points de douleur identifiés en fonction de leur impact sur les performances opérationnelles.
G29: Retours formalisés des parties prenantes (ex. formulaires d’adhésion) | H29: . | J29: . | K29: .
D30: Validation formelle par la direction que l'optimisation seule est insuffisante pour atteindre les objectifs visés | E30: La direction a-t-elle formellement validé que l'optimisation seule est insuffisante pour atteindre les objectifs visés ? | F30: Oui | G30: Procédure de gestion des changements | H30: Investissement dans un nouveau système sans preuve de la nécessité absolue de remplacement. | I30: Elevée | J30: Manque de soutien stratégique, compromettant la priorité accordée au projet. | K30: Définissez des KPI clairs et mesurables, alignés sur les objectifs opérationnels, pour évaluer les performances actuelles.
G31: Registre des demandes de changement | H31: . | J31: . | K31: .
C32: S’assure que les objectifs et périmètres du projet sont définis, partagés et stabilisés ; | D32: Existence d'un document de cadrage validé définissant clairement les objectifs et le périmètre | E32: Existe-t-il un document de cadrage validé définissant clairement les objectifs et le périmètre du projet ? | F32: Oui | G32: Matrice d’alignement stratégique | H32: Dérive progressive du projet par absence de référentiel clair définissant les objectifs et limites. | I32: Faible | J32: Objectifs flous ou mal définis, entraînant des dérives de périmètre. | K32: Mettez en place un tableau de bord pour suivre les KPI en temps réel et faciliter l’analyse.
G33: Plan stratégique de l’organisation | H33: . | J33: . | K33: .
D34: Définition d'indicateurs de succès mesurables (SMART) pour chaque objectif | E34: Des indicateurs de succès mesurables (SMART) ont-ils été définis pour chaque objectif du projet ? | F34: Non | G34: Cahier des exigences (SRS - Software Requirements Specification) | H34: Impossibilité d'évaluer objectivement le succès du projet faute d'indicateurs mesurables. | I34: Elevée | J34: Incapacité à mesurer le succès, rendant l’évaluation du projet subjective. | K34: Organisez des sessions de consultation formelles avec les utilisateurs, en utilisant des questionnaires structurés pour recueillir leurs retours.
G35: Matrice de traçabilité des exigences | H35: . | J35: . | K35: .
D36: Preuve de communication et d'adhésion des parties prenantes aux objectifs et périmètres (réunions, ateliers) | E36: Existe-t-il des preuves de communication et d'adhésion des parties prenantes aux objectifs et périmètres du projet ? | F36: Non | G36: Schéma d’architecture technique | H36: Désengagement progressif des parties prenantes par manque d'implication initiale dans la définition des objectifs. | I36: Moyenne | J36: Résistance au changement due à un manque d’adhésion, freinant l’implémentation. | K36: Documentez les résultats des consultations dans un rapport consolidé, partagé avec les parties prenantes.
G37: Document de description de l’architecture | H37: . | J37: . | K37: .
D38: Procédure formelle de gestion des modifications de périmètre (change management) | E38: Une procédure formelle de gestion des modifications de périmètre (change management) a-t-elle été mise en place ? | F38: Oui | G38: Inventaire des interfaces | H38: Expansion incontrôlée du périmètre ("scope creep") compromettant les délais et budgets. | I38: Elevée | J38: Modifications non contrôlées, provoquant des retards ou des surcoûts. | K38: Comparez l’état actuel aux meilleures pratiques du secteur à l’aide de benchmarks externes ou de normes reconnues.
G39: Diagramme des flux de données | H39: . | J39: . | K39: .
D40: Alignement documenté entre les objectifs du projet et les objectifs stratégiques de l'organisation | E40: L'alignement entre les objectifs du projet et les objectifs stratégiques de l'organisation est-il documenté ? | F40: Oui | G40: Plan de migration | H40: Développement de solutions informatiques sans valeur métier directe pour l'organisation. | I40: Faible | J40: Déconnexion avec la stratégie globale, réduisant la valeur du projet. | K40: Impliquez des consultants externes pour identifier les écarts critiques et proposer des améliorations.
G41: Analyse des risques de migration | H41: . | J41: . | K41: .
C42: S’assurer que les principales orientations du système cible ont été explicitées ; | D42: Documentation des exigences fonctionnelles et non-fonctionnelles principales du système cible | E42: Les exigences fonctionnelles et non-fonctionnelles principales du système cible sont-elles documentées ? | F42: Non | G42: Procès-verbal des réunions de validation technique | H42: Création de fonctionnalités inadaptées aux besoins réels par manque de documentation précise des exigences. | I42: Elevée | J42: Solutions inadéquates ou incomplètes, ne répondant pas aux besoins réels. | K42: Mettez en œuvre des actions d’optimisation mesurables avant toute décision de changement, en documentant chaque initiative.
G43: Rapport technique des experts | H43: . | J43: . | K43: .
D44: Définition de l'architecture technique globale envisagée | E44: L'architecture technique globale envisagée a-t-elle été définie ? | F44: Oui | G44: Matrice RACI | H44: Incompatibilité avec l'infrastructure existante par absence de vision architecturale globale. | I44: Moyenne | J44: Conception technique inadaptée, entraînant des problèmes de performance ou d’évolutivité. | K44: Utilisez des pilotes ou des tests pour valider l’efficacité des optimisations avant leur déploiement à grande échelle.
G45: Document de validation de la matrice RACI | H45: . | J45: . | K45: .
D46: Identification des interfaces critiques avec les autres systèmes | E46: Les interfaces critiques avec les autres systèmes ont-elles été identifiées ? | F46: Oui | G46: Lettre de nomination du sponsor | H46: Ruptures fonctionnelles avec les systèmes connexes par manque d'identification des interfaces critiques. | I46: Elevée | J46: Dysfonctionnements dus à des interfaces mal gérées, affectant l’intégration. | K46: Mesurez les gains de performance post-optimisation à l’aide de KPI comparables à l’état initial.
G47: Charte des responsabilités du sponsor | H47: . | J47: . | K47: .
D48: Élaboration d'une stratégie de migration/transition depuis les systèmes existants | E48: Une stratégie de migration/transition depuis les systèmes existants a-t-elle été élaborée ? | F48: Non | G48: Acte de nomination du chef de projet | H48: Perturbations opérationnelles majeures lors du déploiement faute de stratégie de transition clairement définie. | I48: Faible | J48: Transition chaotique, risquant des interruptions de service ou des pertes de données. | K48: Documentez les résultats dans un rapport clair, en mettant en évidence les améliorations quantifiées.
G49: Fiche de poste ou termes de référence | H49: . | J49: . | K49: .
D50: Validation des orientations techniques par les experts métiers et IT concernés | E50: Les orientations techniques ont-elles été validées par les experts métiers et IT concernés ? | F50: Oui | G50: Liste des utilisateurs clés avec leur rôle | H50: Rejet des solutions techniques par inadéquation avec les contraintes opérationnelles réelles. | I50: Elevée | J50: Solutions non viables, rejetées par les experts, entraînant des retards. | K50: Réalisez une analyse comparative structurée (ex. : matrice décisionnelle) pour évaluer les options d’optimisation versus nouveau système.
G51: Plan d’implication des utilisateurs | H51: . | J51: . | K51: .
C52: S’assurer que les principaux acteurs sont identifiés ; | D52: Existence d'une matrice RACI (Responsable, Approbateur, Consulté, Informé) complète | E52: Une matrice RACI (Responsable, Approbateur, Consulté, Informé) complète a-t-elle été établie ? | F52: Non | G52: Contrat ou accord avec les prestataires | H52: Confusion dans l'exécution des tâches et prises de décision par absence de clarification des responsabilités. | I52: Moyenne | J52: Confusion des rôles, provoquant des retards ou des conflits internes. | K52: Impliquez les parties prenantes clés dans la validation de l’analyse comparative pour garantir son objectivité.
G53: Annexe des responsabilités des partenaires | H53: . | J53: . | K53: .
D54: Désignation formelle d'un sponsor de projet avec autorité suffisante | E54: Un sponsor de projet disposant d'une autorité suffisante a-t-il été formellement désigné ? | F54: Non | G54: Cahier des charges signé | H54: Manque de soutien exécutif lors des arbitrages critiques par défaut de sponsor officiel engagé. | I54: Elevée | J54: Manque de leadership, affaiblissant la prise de décision et la coordination. | K54: Calculez le ROI de chaque option à l’aide d’un modèle financier standardisé, incluant les coûts directs et indirects.
G55: Procès-verbal de validation du cahier des charges | H55: . | J55: . | K55: .
D56: Nomination documentée d'un chef de projet et définition de ses responsabilités | E56: Un chef de projet a-t-il été nommé officiellement et ses responsabilités ont-elles été clairement définies ? | F56: Oui | G56: Document des spécifications fonctionnelles | H56: Pilotage inefficace par absence de chef de projet formellement mandaté et légitimé. | I56: Faible | J56: Pilotage inefficace, entraînant des erreurs ou des retards dans l’exécution. | K56: Faites valider les hypothèses du ROI par un comité financier pour garantir leur fiabilité.
G57: Matrice de conformité des spécifications | H57: . | J57: . | K57: .
D58: Identification des utilisateurs clés et de leur niveau d'implication dans le projet | E58: Les utilisateurs clés et leur niveau d'implication dans le projet ont-ils été clairement identifiés ? | F58: Non | G58: Étude de la valeur avec analyse coûts/bénéfices | H58: Développement de fonctionnalités peu pertinentes par manque d'implication des utilisateurs experts. | I58: Elevée | J58: Manque d’implication des utilisateurs, réduisant l’adoption de la solution. | K58: Obtenez une validation écrite de la direction, justifiant pourquoi l’optimisation seule est insuffisante, avec des arguments chiffrés.
G59: Modèle de calcul des coûts et bénéfices | H59: . | J59: . | K59: .
D60: Définition claire des rôles des prestataires externes et partenaires impliqués dans le projet | E60: Les rôles des prestataires externes et partenaires impliqués dans le projet sont-ils clairement définis ? | F60: Non | G60: Rapport d’analyse des impacts organisationnels, techniques et humains | H60: Coordination défaillante avec les prestataires externes par manque de clarté dans la définition des responsabilités. | I60: Moyenne | J60: Mauvaise coordination avec les prestataires, causant des écarts de livraison. | K60: Organisez une réunion formelle avec la direction pour présenter les conclusions et recueillir leur approbation.
G61: Plan de gestion des impacts | H61: . | J61: . | K61: .
B62: Étude d'opportunité et expression des besoins | C62: S’assurer que l'expression détaillée des besoins est formalisée dans un cahier des charges fait par la MOA ; | D62: Existence d'un cahier des charges validé et signé par la MOA | E62: Existe-t-il un cahier des charges validé et signé par la MOA ? | F62: Oui | G62: Procès-verbal de validation de l’étude d’opportunité | H62: Livraison d'un système non conforme aux attentes par absence de référentiel contractuel validé. | I62: Elevée | J62: Solutions non alignées avec les besoins, risquant un rejet par les utilisateurs. | K62: Rédigez un document de cadrage clair, avec des objectifs et un périmètre validés par toutes les parties prenantes.
G63: Fiche de signatures des parties prenantes | H63: . | J63: . | K63: .
D64: Détail et précision des spécifications fonctionnelles dans le document | E64: Les spécifications fonctionnelles sont-elles détaillées et précises dans le document ? | F64: Non | G64: Analyse de cohérence des bénéfices attendus | H64: Développement de fonctionnalités imprécises ou incomplètes par manque de détail dans les spécifications. | I64: Faible | J64: Solutions vagues ou incomplètes, entraînant des développements coûteux pour corriger. | K64: Utilisez un modèle standard pour le document de cadrage afin d’assurer sa complétude et sa clarté.
G65: Matrice de correspondance bénéfices-objectifs stratégiques | H65: . | J65: . | K65: .
D66: Clarté et exhaustivité des besoins exprimés (sans ambiguïté) | E66: Les besoins exprimés sont-ils clairs et exhaustifs, sans ambiguïté ? | F66: Oui | G66: Registre des risques du projet | H66: Interprétations divergentes des besoins entre équipes techniques et métiers par ambiguïté des exigences. | I66: Elevée | J66: Besoins mal compris, conduisant à une solution inadaptée. | K66: Définissez des indicateurs SMART pour chaque objectif, en les alignant sur les priorités stratégiques.
G67: Plan de gestion des risques | H67: . | J67: . | K67: .
D68: Processus documenté de collecte des besoins auprès des utilisateurs finaux | E68: Le processus de collecte des besoins auprès des utilisateurs finaux est-il documenté ? | F68: Oui | G68: Diagramme des processus (ex. BPMN ou flowchart) | H68: Omission de besoins critiques par déficience du processus de recueil des exigences. | I68: Moyenne | J68: Besoins mal recueillis, ignorant des attentes critiques des utilisateurs. | K68: Validez les indicateurs avec les parties prenantes pour garantir leur pertinence et leur mesurabilité.
G69: Rapport de validation de la cartographie par les parties prenantes | H69: . | J69: . | K69: .
D70: Traçabilité entre les besoins exprimés et les objectifs stratégiques du projet | E70: Existe-t-il une traçabilité entre les besoins exprimés et les objectifs stratégiques du projet ? | F70: Non | G70: Rapport d’analyse des inefficacités | H70: Développement de fonctionnalités sans valeur ajoutée réelle pour l'entreprise. | I70: Elevée | J70: Solutions déconnectées des objectifs stratégiques, réduisant leur pertinence. | K70: Organisez des ateliers et des réunions pour communiquer les objectifs et le périmètre, en consignant l’adhésion des parties prenantes.
G71: Compte-rendu des ateliers avec les utilisateurs | H71: . | J71: . | K71: .
C72: S’assurer que le cahier des charges préconise une solution fonctionnellement et techniquement pertinente au regard des besoins Exprimés | D72: Adéquation démontrée entre les fonctionnalités préconisées et les besoins exprimés | E72: L'adéquation entre les fonctionnalités préconisées et les besoins exprimés a-t-elle été démontrée ? | F72: Non | G72: Tableau de bord des KPI actuels | H72: Inadéquation entre les solutions développées et les problématiques métiers à résoudre. | I72: Faible | J72: Fonctionnalités superflues ou absentes, compromettant la satisfaction des utilisateurs. | K72: Utilisez des outils collaboratifs pour documenter les échanges et assurer la transparence des communications.
G73: Méthodologie de collecte et de calcul des KPI | H73: . | J73: . | K73: .
D74: Justification technique des solutions proposées (faisabilité, évolutivité) | E74: Les solutions proposées sont-elles justifiées techniquement en termes de faisabilité et d'évolutivité ? | F74: Oui | G74: Procès-verbal des réunions de consultation | H74: Adoption de technologies inadaptées au contexte de l'entreprise par manque de justification technique rigoureuse. | I74: Elevée | J74: Solutions irréalisables ou non évolutives, entraînant des échecs techniques. | K74: Établissez une procédure formelle de gestion des modifications, avec un comité dédié pour évaluer les demandes.
G75: Questionnaire ou grille de collecte des retours | H75: . | J75: . | K75: .
D76: Prise en compte des contraintes spécifiques de l'entreprise (techniques, organisationnelles) | E76: Les contraintes spécifiques de l'entreprise (techniques, organisationnelles) ont-elles été prises en compte ? | F76: Non | G76: Rapport d’analyse comparative (benchmarking) | H76: Mise en production de solutions incompatibles avec l'environnement existant. | I76: Moyenne | J76: Ignorance des contraintes, provoquant des incompatibilités ou des échecs. | K76: Utilisez un outil de gestion des changements pour suivre les demandes et leurs impacts sur le projet.
G77: Liste des écarts identifiés avec priorisation | H77: . | J77: . | K77: .
D78: Évaluation des alternatives possibles et justification du choix retenu | E78: Les alternatives possibles ont-elles été évaluées et le choix retenu est-il justifié ? | F78: Non | G78: Plan d’optimisation des processus | H78: Sélection d'options sous-optimales par défaut d'exploration des alternatives possibles. | I78: Elevée | J78: Choix non optimal, gaspillant des ressources sur une solution moins efficace. | K78: Documentez l’alignement des objectifs du projet avec les objectifs stratégiques dans une matrice de correspondance.
G79: Rapport d’évaluation des résultats des optimisations | H79: . | J79: . | K79: .
D80: Validation par des experts techniques et métiers de la pertinence des solutions préconisées | E80: La pertinence des solutions préconisées a-t-elle été validée par des experts techniques et métiers ? | F80: Non | G80: Comparatif des KPI avant/après optimisation | H80: Rejet des solutions par les équipes techniques ou métiers faute de validation préalable. | I80: Faible | J80: Solutions inadéquates, rejetées par les experts, causant des retards. | K80: Organisez des revues régulières avec la direction pour vérifier cet alignement tout au long du projet.
G81: Rapport d’audit des gains réalisés | H81: . | J81: . | K81: .
C82: S’assurer que les exigences utilisateurs, les populations ciblées, les options et principes de gestion retenus sont précisés et priorisés ; | D82: Segmentation claire des différentes populations d'utilisateurs concernées | E82: Les différentes populations d'utilisateurs concernées sont-elles clairement segmentées ? | F82: Oui | G82: Étude d’impact comparatif | H82: Développement de fonctionnalités inadaptées à certains profils d'utilisateurs. | I82: Elevée | J82: Solutions inadaptées à certains utilisateurs, réduisant l’efficacité globale. | K82: Rédigez un document détaillant les exigences fonctionnelles et non-fonctionnelles, validé par les utilisateurs et la MOA.
G83: Matrice de décision | H83: . | J83: . | K83: .
D84: Classification des exigences par niveau de priorité (must have, should have, could have, won't have) | E84: Les exigences ont-elles été classifiées par niveau de priorité (must have, should have, could have, won't have) ? | F84: Non | G84: Analyse financière du ROI | H84: Allocation inefficiente des ressources par absence de hiérarchisation claire des exigences. | I84: Moyenne | J84: Mauvaise priorisation, négligeant des besoins critiques. | K84: Utilisez des ateliers de recueil des besoins pour garantir l’exhaustivité des exigences documentées.
G85: Hypothèses et méthodologie du calcul du ROI | H85: . | J85: . | K85: .
D86: Documentation des principes de gestion validés par les responsables métiers | E86: Les principes de gestion ont-ils été documentés et validés par les responsables métiers ? | F86: Non | G86: Procès-verbal de la réunion de validation par la direction | H86: Création de processus applicatifs en contradiction avec les règles métiers établies. | I86: Elevée | J86: Gestion inefficace, entraînant des retards ou des conflits opérationnels. | K86: Définissez l’architecture technique dans un document clair, incluant des diagrammes pour illustrer les composants.
G87: Note de synthèse pour la direction | H87: . | J87: . | K87: .
D88: Matrice de traçabilité entre exigences et populations d'utilisateurs | E88: Existe-t-il une matrice de traçabilité entre les exigences et les populations d'utilisateurs ? | F88: Oui | G88: Document de cadrage du projet (Project Charter) | H88: Dispersion des efforts de développement sur des fonctionnalités à faible valeur pour les utilisateurs réels. | I88: Faible | J88: Solutions inadaptées à certains utilisateurs, réduisant leur adoption. | K88: Impliquez des architectes IT pour valider la faisabilité et l’évolutivité de l’architecture proposée.
G89: Fiche de validation signée par les parties prenantes | H89: . | J89: . | K89: .
D90: Processus formalisé d'arbitrage en cas de conflit entre exigences | E90: Un processus formalisé d'arbitrage en cas de conflit entre exigences a-t-il été mis en place ? | F90: Oui | G90: Liste des indicateurs SMART | H90: Blocages décisionnels sur des exigences contradictoires faute de processus d'arbitrage défini. | I90: Elevée | J90: Conflits non résolus, bloquant l’avancement du projet. | K90: Cartographiez les interfaces critiques dans un document dédié, en précisant les flux de données et les protocoles.
G91: Plan de suivi des indicateurs | H91: . | J91: . | K91: .
C92: S’assurer que le projet est cohérent avec le plan directeur Informatique | D92: Référence explicite au plan directeur informatique dans les documents du projet | E92: Les documents clés du projet font-ils explicitement référence au plan directeur informatique en vigueur ? | F92: Non | G92: Compte-rendu des ateliers de communication | H92: Développement de solutions en contradiction avec la stratégie SI de l'entreprise. | I92: Moyenne | J92: Projet déconnecté du SI, risquant des incompatibilités techniques. | K92: Validez la cartographie des interfaces avec les équipes IT responsables des systèmes connectés.
G93: Retours formalisés des parties prenantes (ex. formulaires d’adhésion) | H93: . | J93: . | K93: .
D94: Alignement du projet avec les orientations technologiques définies dans le plan directeur | E94: Les choix technologiques du projet s'alignent-ils sur les orientations définies dans le plan directeur informatique ? | F94: Non | G94: Procédure de gestion des changements | H94: Non-conformité aux choix technologiques stratégiques définis par la DSI. | I94: Elevée | J94: Solutions non alignées avec la stratégie IT, compromettant l’évolutivité. | K94: Élaborez une stratégie de migration détaillée, incluant des scénarios de transition et des plans de secours.
G95: Registre des demandes de changement | H95: . | J95: . | K95: .
D96: Conformité avec la roadmap d'évolution des systèmes d'information | E96: Le positionnement du projet est-il cohérent avec la roadmap d'évolution des systèmes d'information validée ? | F96: Oui | G96: Matrice d’alignement stratégique | H96: Création de dette technique par non-respect de la trajectoire d'évolution du SI. | I96: Faible | J96: Incohérence avec la roadmap, provoquant des conflits de priorités. | K96: Testez la stratégie de migration dans un environnement pilote pour identifier les problèmes potentiels.
G97: Plan stratégique de l’organisation | H97: . | J97: . | K97: .
D98: Respect des standards et référentiels définis dans le plan directeur | E98: Le projet assure-t-il le respect des standards et référentiels définis dans le plan directeur ? | F98: Oui | G98: Cahier des exigences (SRS - Software Requirements Specification) | H98: Violation des standards techniques compromettant la maintenance future des solutions. | I98: Elevée | J98: Non-conformité aux standards, entraînant des problèmes d’intégration. | K98: Organisez des revues techniques avec des experts métiers et IT pour valider les orientations techniques.
G99: Matrice de traçabilité des exigences | H99: . | J99: . | K99: .
D100: Validation formelle par le responsable du plan directeur informatique | E100: Existe-t-il une preuve de validation formelle du projet par le responsable du plan directeur informatique ? | F100: Oui | G100: Schéma d’architecture technique | H100: Développement de solutions non validées par les instances de gouvernance du SI. | I100: Moyenne | J100: Solutions non validées, risquant des incompatibilités avec le SI cible. | K100: Documentez les retours des experts dans un rapport consolidé pour garantir leur prise en compte.
...

Sheet 4.4
A1: Domaine | B1: Points de Contrôle | C1: Objectifs de Contrôle | D1: Critère d’Évaluation | E1: Question d’Évaluation | F1: Réponses | G1: Documents Requis | H1: Risques | I1: Criticités | J1: Conséquences | K1: Recommendations
A2: Audit du Support Utilisateur et de la Gestion du Parc | B2: Fonction support : audit fiabilité et sécurité | C2: S’assurer qu’une structure de centre d’assistance (help-desk) (HD) est mise en place | D2: Existence d'un organigramme et d'une définition claire des rôles et responsabilités de l'équipe HD | E2: Un organigramme définissant clairement les rôles et responsabilités de l'équipe helpdesk est-il formalisé et disponible ? | F2: Non | G2: Charte du Help Desk définissant sa mission, ses objectifs et ses engagements | H2: Absence de rôles clairement définis entraînant des chevauchements ou des zones de flou dans les responsabilités. | I2: Elevée | J2: Manque de clarté dans les responsabilités peut entraîner des erreurs de prise en charge ou des oublis dans le traitement des incidents. | K2: Clarifier et formaliser les rôles et responsabilités dans un organigramme accessible à toute l’équipe HD.
G3: Document de politique de service incluant la définition du périmètre d'intervention du HD | H3: . | J3: . | K3: Mettre en place des sessions de formation régulières pour assurer la compréhension et l’appropriation des rôles par les membres de l’équipe.
D4: Présence d'un responsable désigné pour le help-desk | E4: Existe-t-il un responsable formellement désigné pour le helpdesk ? | F4: Oui | G4: Liste des correspondants locaux avec leurs coordonnées et responsabilités | H4: Risque d'inefficacité ou de manque de coordination sans responsable clairement identifié. | I4: Moyenne | J4: Absence de pilotage et de supervision directe peut réduire la réactivité et la qualité du service rendu. | K4: Désigner officiellement un responsable du help-desk avec des missions clairement définies.
G5: Procédures spécifiques aux relais locaux et périmètre d'intervention | H5: . | J5: . | K5: Assurer la communication régulière sur le rôle et les responsabilités du responsable auprès de l’ensemble des équipes et utilisateurs.
D6: Disponibilité de canaux de communication multiples (téléphone, email, portail web, etc.) | E6: Les utilisateurs disposent-ils de plusieurs canaux de communication (téléphone, email, portail web) pour contacter le helpdesk ? | F6: Non | G6: Matrice des compétences linguistiques des agents du HD | H6: Difficulté à joindre le support en cas de panne d’un canal unique. | I6: Elevée | J6: Difficultés d’accès au support pouvant entraîner des retards de traitement et une insatisfaction des utilisateurs. | K6: Multiplier les canaux de communication (téléphone, email, portail web) pour faciliter l’accès au support.
G7: Documentation multilingue disponible (guides, formulaires, FAQ) | H7: . | J7: . | K7: Mettre en place un système de suivi des demandes via tous les canaux pour garantir leur traitement efficace.
D8: Mise en place d'horaires de service définis et communiqués | E8: Les horaires de service du helpdesk sont-ils clairement définis et communiqués aux utilisateurs ? | F8: Non | G8: Contrats avec prestataires locaux pour interventions sur site | H8: Non-respect des plages horaires en l’absence d’une communication claire. | I8: Faible | J8: Attentes non maîtrisées des utilisateurs en dehors des plages de service, pouvant générer des tensions et des escalades. | K8: Définir et communiquer clairement les horaires de service pour gérer les attentes des utilisateurs.
G9: Journal des interventions physiques avec temps de résolution par site | H9: . | J9: . | K9: Adapter les horaires de service aux besoins réels des utilisateurs, en tenant compte des pics d’activité.
D10: Existence d'un document formalisant la mission et les objectifs du HD | E10: Existe-t-il un document officiel qui formalise la mission et les objectifs du helpdesk ? | F10: Oui | G10: Inventaire/Catalogue des services ou applications gérés par l'entreprise. | H10: Dérive des activités du HD sans mission formalisée. | I10: Elevée | J10: Incompréhension de la mission du HD, menant à une sollicitation inappropriée du service ou à des attentes irréalistes. | K10: Rédiger un document formalisant la mission et les objectifs du help-desk, validé par la direction.
G11: Liste/Cartographie des applications/systèmes spécifiquement couverts par le HD (précisant le périmètre exact du support). | H11: . | J11: . | K11: Diffuser largement ce document auprès des équipes pour assurer l’alignement des actions sur les objectifs.
C12: S’assurer qu’une procédure de gestion des demandes d’assistance est diffusée et connue des utilisateurs | D12: Existence d'une documentation formalisée décrivant la procédure de demande d'assistance | E12: Une documentation formalisée décrivant la procédure de demande d'assistance est-elle disponible ? | F12: Non | G12: Matrice de compétences de l'équipe HD (liant techniciens, compétences techniques/fonctionnelles et applications/systèmes). | H12: Erreur ou perte de temps due à une mauvaise compréhension du processus de demande. | I12: Moyenne | J12: Risque de demandes mal formulées ou non traitées en raison d’un manque de clarté sur la procédure à suivre. | K12: Documenter précisément la procédure de demande d’assistance et la rendre accessible.
G13: Plan de formation ou actions de montée en compétence basés sur les écarts de la matrice. | H13: . | J13: . | K13: Former les utilisateurs à la procédure pour garantir une bonne utilisation et réduire les erreurs de saisie.
D14: Taux d'utilisateurs ayant reçu une communication sur la procédure (emails, sessions d'information) | E14: Au moins 80% des utilisateurs ont-ils reçu une communication officielle sur la procédure de demande d'assistance ? | F14: Oui | G14: Annuaire/Liste officielle des experts ou points de contact (internes/externes) par domaine/application. | H14: Méconnaissance des procédures par une partie des utilisateurs. | I14: Elevée | J14: Faible adoption des bonnes pratiques par les utilisateurs, augmentant le taux d'erreurs dans la saisine de demandes. | K14: Communiquer régulièrement aux utilisateurs la procédure via emails et sessions d’information.
G15: Procédure d'escalade définissant quand et comment solliciter ces experts. | H15: . | J15: . | K15: Mettre à disposition des supports pédagogiques accessibles en permanence (intranet, FAQ).
D16: Disponibilité des instructions sur l'intranet ou autre plateforme accessible aux utilisateurs | E16: Les instructions pour contacter le helpdesk sont-elles disponibles sur l'intranet ou une autre plateforme accessible à tous les utilisateurs ? | F16: Oui | G16: Rapports périodiques (ex: mensuels) générés par l'outil de ticketing montrant le taux de résolution L1 par domaine/catégorie. | H16: Perte d’autonomie des utilisateurs en l’absence d’accès facile aux procédures. | I16: Faible | J16: Accès difficile à la procédure pouvant générer des demandes mal orientées ou redondantes. | K16: Publier un guide utilisateur simplifié pour les nouvelles recrues afin de faciliter leur prise en main.
G17: Journal de mise à jour du contenu des plateformes d'information | H17: . | J17: . | K17: Organiser des sessions d’accueil ou de formation spécifiques pour les nouveaux utilisateurs.
D18: Présence d'un guide utilisateur simplifié pour les nouvelles recrues | E18: Un guide utilisateur simplifié est-il fourni aux nouvelles recrues concernant l'utilisation du helpdesk ? | F18: Non | G18: Guide d'accueil spécifique au Help Desk pour nouveaux collaborateurs | H18: Prise en main difficile pour les nouveaux arrivants. | I18: Elevée | J18: Allongement du délai d’autonomie des nouvelles recrues et surcharge du HD sur des demandes basiques. | K18: Mettre en place un système de rappel périodique des procédures auprès des utilisateurs.
G19: Support de formation simplifié pour les nouveaux utilisateurs | H19: . | J19: . | K19: Utiliser des campagnes de communication variées (email, notifications) pour maintenir la sensibilisation.
D20: Existence d'un mécanisme de rappel périodique des procédures auprès des utilisateurs | E20: Existe-t-il un mécanisme de rappel périodique des procédures helpdesk auprès des utilisateurs ? | F20: Oui | G20: Planning annuel des communications de rappel | H20: Oubli des bonnes pratiques en l’absence de rappels réguliers. | I20: Moyenne | J20: Oubli progressif des procédures, engendrant une baisse de la qualité des demandes et du temps de traitement. | K20: Formaliser une matrice d’escalade par type d’incident, validée par la direction.
G21: Exemples de newsletters ou emails de rappel envoyés aux utilisateurs | H21: . | J21: . | K21: Former les équipes à l’application rigoureuse de cette matrice pour garantir une gestion efficace des incidents.
C22: S’assurer qu’une procédure d'escalade mise en place | D22: Existence d'une matrice d'escalade documentée par type d'incident | E22: Une matrice d'escalade documentée par type d'incident est-elle formalisée ? | F22: Non | G22: Document de matrice d'escalade par catégorie d'incident | H22: Retard ou mauvaise gestion des escalades sans matrice claire. | I22: Elevée | J22: Mauvaise orientation ou escalade tardive des incidents critiques, allongeant le temps de résolution. | K22: Définir clairement les niveaux de support (N1, N2, N3) avec leurs responsabilités respectives.
G23: Procédure détaillée d'escalade avec arbre de décision | H23: . | J23: . | K23: Assurer la montée en compétence des équipes à chaque niveau pour optimiser la résolution des incidents.
D24: Présence de niveaux de support clairement définis (N1, N2, N3) | E24: Les niveaux de support (N1, N2, N3) sont-ils clairement définis dans la documentation ? | F24: Oui | G24: Organigramme fonctionnel du service avec distinction des niveaux | H24: Confusion dans la répartition des tickets sans définition des niveaux. | I24: Faible | J24: Sur-sollicitation du niveau 1 ou confusion sur les responsabilités des différents niveaux. | K24: Établir des délais maximums d’escalade selon la criticité, avec un suivi régulier.
G25: Document de description des compétences et responsabilités par niveau | H25: . | J25: . | K25: Mettre en place des alertes automatiques pour respecter ces délais et éviter les blocages.
D26: Définition de délais maximums avant escalade selon la criticité des incidents | E26: Des délais maximums avant escalade sont-ils définis selon la criticité des incidents ? | F26: Non | G26: Tableau des SLA (Service Level Agreement) par niveau de criticité | H26: Allongement des délais de résolution sans règles d’escalade claires. | I26: Elevée | J26: Retards dans la prise en charge des incidents critiques, augmentant leur impact sur l’activité. | K26: Identifier formellement les responsables par niveau d’escalade et domaine d’expertise.
G27: Procédure de gestion temporelle des incidents et escalades | H27: . | J27: . | K27: Communiquer clairement ces responsabilités à toutes les parties prenantes.
D28: Identification des responsables par niveau d'escalade et par domaine d'expertise | E28: Les responsables sont-ils identifiés pour chaque niveau d'escalade et par domaine d'expertise ? | F28: Non | G28: Annuaire des contacts et responsables par niveau et domaine | H28: Manque de réactivité si les responsabilités d’escalade ne sont pas identifiées. | I28: Moyenne | J28: Escalades inefficaces ou mal dirigées, conduisant à un allongement du délai de résolution. | K28: Assurer la traçabilité complète des escalades dans l’outil de gestion des tickets.
G29: Document de répartition des rôles et responsabilités avec coordonnées | H29: . | J29: . | K29: Réaliser des audits réguliers pour vérifier la conformité de la traçabilité.
D30: Traçabilité des escalades dans l'outil de gestion des tickets | E30: Les escalades sont-elles systématiquement tracées dans l'outil de gestion des tickets ? | F30: Oui | G30: Rapports d'extraction de l'outil de ticketing montrant le suivi des escalades | H30: Risque de perte de traçabilité ou d’analyse sans enregistrement des escalades. | I30: Elevée | J30: Absence de traçabilité rendant difficile l’analyse des causes et la responsabilité des délais. | K30: Cartographier exhaustivement les sites et locaux couverts par le service HD.
G31: Manuel d'utilisation de l'outil de gestion des tickets section escalade | H31: . | J31: . | K31: Mettre à jour régulièrement cette cartographie pour refléter les évolutions.
C32: S’assurer de la couverture géographique du HD | D32: Taux de sites/locaux couverts par le service HD | E32: Au moins 90% des sites/locaux de l'entreprise sont-ils couverts par le service helpdesk ? | F32: Oui | G32: Rapport de couverture géographique du service Help Desk | H32: Utilisateurs non couverts en l'absence d’un suivi global de la couverture. | I32: Faible | J32: Non-couverture de certains sites entraînant des délais de réponse inégaux et un service perçu comme inéquitable. | K32: Documenter les horaires de support associés à chaque site.
G33: Contrat de service précisant les sites couverts et les modalités | H33: . | J33: . | K33: Communiquer ces horaires aux utilisateurs pour gérer leurs attentes.
D34: Existence d'une cartographie des sites et des horaires de support associés | E34: Une cartographie des sites avec les horaires de support associés est-elle formalisée ? | F34: Non | G34: Document cartographique des sites avec horaires de support spécifiques | H34: Impossibilité d’assurer une qualité homogène de support sans cartographie claire. | I34: Elevée | J34: Méconnaissance des horaires de support par site pouvant générer des sollicitations hors périmètre ou hors horaires. | K34: Mettre en place des relais locaux sur sites distants pour améliorer la réactivité.
G35: Planning des équipes HD par zone géographique et fuseau horaire | H35: . | J35: . | K35: Former ces relais aux procédures et outils du HD pour garantir la qualité du support.
D36: Mise en place de relais locaux sur les sites distants si nécessaire | E36: Des relais locaux sont-ils mis en place sur les sites distants lorsque nécessaire ? | F36: Non | G36: Liste des correspondants locaux avec leurs coordonnées et responsabilités | H36: Abandon des utilisateurs distants faute de relais locaux. | I36: Moyenne | J36: Perte d’efficacité sur les sites distants faute d’appui local en cas d’incident physique ou urgent. | K36: Assurer la disponibilité d’un support dans les langues requises selon les implantations.
G37: Procédures spécifiques aux relais locaux et périmètre d'intervention | H37: . | J37: . | K37: Former les équipes aux spécificités culturelles et linguistiques des utilisateurs.
D38: Disponibilité d'un support dans les différentes langues requises selon les implantations | E38: Un support est-il disponible dans toutes les langues requises selon les implantations géographiques ? | F38: Oui | G38: Matrice des compétences linguistiques des agents du HD | H38: Incompréhensions ou erreurs si le support n’est pas multilingue. | I38: Elevée | J38: Difficulté de communication avec les utilisateurs non francophones, impactant la qualité de la prise en charge. | K38: Garantir la capacité d’intervention physique sur tous les sites dans les délais contractuels.
G39: Documentation multilingue disponible (guides, formulaires, FAQ) | H39: . | J39: . | K39: Mettre en place un suivi des interventions pour respecter les engagements.
D40: Capacité à intervenir physiquement sur tous les sites dans des délais contractuels | E40: Le helpdesk peut-il intervenir physiquement sur tous les sites dans les délais contractuels établis ? | F40: Oui | G40: Contrats avec prestataires locaux pour interventions sur site | H40: Non-respect des engagements contractuels de temps d’intervention. | I40: Faible | J40: Non-respect des engagements contractuels et insatisfaction en cas d’intervention physique non garantie. | K40: Couvrir un pourcentage élevé d’applications et systèmes par le support HD.
G41: Journal des interventions physiques avec temps de résolution par site | H41: . | J41: . | K41: Actualiser régulièrement la liste des applications supportées pour suivre l’évolution du SI.
C42: S’assurer de la couverture fonctionnelle du HD | D42: Pourcentage d'applications et systèmes couverts par le support HD | E42: Au moins 90% des applications et systèmes critiques sont-ils couverts par le support helpdesk ? | F42: Non | G42: Inventaire/Catalogue des services ou applications gérés par l'entreprise. | H42: Non-assistance d’utilisateurs ou d’applications critiques hors périmètre. | I42: Elevée | J42: Incapacité à répondre sur certaines applications, générant une frustration utilisateur et un transfert excessif vers d’autres équipes. | K42: Établir une matrice de compétences de l’équipe HD par rapport aux applications supportées.
G43: Liste/Cartographie des applications/systèmes spécifiquement couverts par le HD (précisant le périmètre exact du support). | H43: . | J43: . | K43: Identifier les besoins en formation pour combler les écarts de compétences.
D44: Existence d'une matrice de compétences de l'équipe HD par rapport aux applications supportées | E44: Existe-t-il une matrice de compétences de l'équipe helpdesk par rapport aux applications supportées ? | F44: Oui | G44: Matrice de compétences de l'équipe HD (liant techniciens, compétences techniques/fonctionnelles et applications/systèmes). | H44: Inadéquation des compétences de l’équipe face aux besoins spécifiques. | I44: Moyenne | J44: Sur-dépendance à quelques individus et difficulté de planification en cas d’absence ou de départ. | K44: Mettre à disposition des experts ou points de contact pour chaque domaine fonctionnel.
G45: Plan de formation ou actions de montée en compétence basés sur les écarts de la matrice. | H45: . | J45: . | K45: Faciliter l’accès rapide à ces experts pour les techniciens du HD.
D46: Disponibilité d'experts ou points de contact pour chaque domaine fonctionnel | E46: Des experts ou points de contact sont-ils désignés pour chaque domaine fonctionnel ? | F46: Oui | G46: Annuaire/Liste officielle des experts ou points de contact (internes/externes) par domaine/application. | H46: Risque de blocage sans expert désigné sur certaines applications. | I46: Elevée | J46: Retards de traitement sur les incidents spécifiques faute de référents ou de connaissances documentées. | K46: Suivre et améliorer le taux de résolution des incidents au premier niveau par domaine fonctionnel.
G47: Procédure d'escalade définissant quand et comment solliciter ces experts. | H47: . | J47: . | K47: Analyser les causes des non-résolutions pour améliorer les processus et formations.
D48: Taux de résolution des incidents au premier niveau par domaine fonctionnel | E48: Le taux de résolution des incidents au premier niveau est-il mesuré par domaine fonctionnel ? | F48: Non | G48: Rapports périodiques (ex: mensuels) générés par l'outil de ticketing montrant le taux de résolution L1 par domaine/catégorie. | H48: Faible performance du support de premier niveau dans certains domaines. | I48: Faible | J48: Faible efficacité du niveau 1, augmentant la charge sur les niveaux supérieurs et les délais globaux. | K48: Cartographier les applications et systèmes avec leur niveau de couverture (24/7, heures ouvrées).
G49: Définition formelle de l'indicateur (KPI) "Taux de résolution L1" (incluant la formule de calcul et les sources de données). | H49: . | J49: . | K49: Adapter les ressources du HD en fonction des niveaux de couverture requis.
D50: Cartographie des applications et systèmes avec leur niveau de couverture (24/7, heures ouvrées, etc.) | E50: Une cartographie des applications et systèmes avec leur niveau de couverture (24/7, heures ouvrées) est-elle formalisée ? | F50: Oui | G50: Cartographie/Liste des applications/systèmes indiquant les plages horaires et niveaux de support (SLA/OLA) convenus. | H50: Incohérence dans la disponibilité du support selon les outils ou les horaires. | I50: Elevée | J50: Mauvaise anticipation des ressources à allouer selon les plages horaires et l’importance des systèmes. | K50: Utiliser un logiciel de gestion des tickets accessible à tous les membres du HD.
G51: Catalogue de services (s'il formalise ces niveaux) ou les OLA/SLA correspondants. | H51: . | J51: . | K51: Assurer la formation des utilisateurs à cet outil pour garantir une utilisation optimale.
C52: S’assurer qu’un outil est implémenté pour la prise d'appel et le suivi des tickets | D52: Existence d'un logiciel de gestion des tickets accessible à tous les membres du HD | E52: Un logiciel de gestion des tickets accessible à tous les membres du helpdesk est-il déployé ? | F52: Non | G52: Documentation ou présentation de l'outil de gestion des tickets (ITSM) utilisé. | H52: Tickets non enregistrés ou mal suivis sans outil commun accessible. | I52: Moyenne | J52: Traitement manuel ou parallèle des tickets, entraînant des erreurs, des doublons ou une perte d’historique. | K52: Garantir que l’outil génère des numéros de référence uniques pour chaque demande.
G53: Liste des comptes utilisateurs actifs pour les membres de l'équipe HD dans l'outil. | H53: . | J53: . | K53: Mettre en place un suivi rigoureux des tickets via ces références.
D54: Capacité de l'outil à générer des numéros de référence uniques pour chaque demande | E54: L'outil de gestion génère-t-il automatiquement des numéros de référence uniques pour chaque demande ? | F54: Non | G54: Exemples de tickets montrant la génération de numéros de référence uniques et séquentiels. | H54: Difficulté à référencer les demandes sans identifiants uniques. | I54: Elevée | J54: Confusion pour les utilisateurs et les techniciens sur les tickets ouverts, rendant le suivi difficile. | K54: Exploiter les fonctionnalités de suivi de l’état d’avancement et des délais de résolution.
G55: Documentation technique ou guide utilisateur de l'outil confirmant cette fonctionnalité. | H55: . | J55: . | K55: Mettre en place des alertes pour les tickets en retard ou bloqués.
D56: Fonctionnalités de suivi de l'état d'avancement des tickets et des délais de résolution | E56: L'outil dispose-t-il de fonctionnalités permettant de suivre l'état d'avancement des tickets et les délais de résolution ? | F56: Oui | G56: Captures d'écran de l'outil illustrant le suivi des statuts et des échéances (SLA). | H56: Perte de visibilité sur l’état des demandes en cours. | I56: Faible | J56: Suivi difficile des engagements, des délais contractuels, et absence de vision sur la performance. | K56: Produire régulièrement des rapports et statistiques sur l’activité du HD.
G57: Documentation de l'outil décrivant les fonctionnalités de workflow et de gestion des SLA. | H57: . | J57: . | K57: Utiliser ces rapports pour piloter la performance et identifier les axes d’amélioration.
D58: Capacité à produire des rapports et statistiques sur l'activité du HD | E58: L'outil permet-il de produire des rapports et statistiques sur l'activité du helpdesk ? | F58: Non | G58: Exemples de rapports standards ou personnalisés générés par l'outil (volumétrie, performance, délais...). | H58: Manque de pilotage sans indicateurs fiables. | I58: Elevée | J58: Difficulté d’analyse des volumes et d’optimisation du service par manque de données consolidées. | K58: Intégrer l’outil avec d’autres systèmes (gestion des assets, base de connaissances).
G59: Liste des rapports périodiques effectivement produits et diffusés (ex: reporting mensuel d'activité). | H59: . | J59: . | K59: Assurer la synchronisation des données entre les différents outils pour éviter les silos.
D60: Niveau d'intégration de l'outil avec d'autres systèmes (gestion des assets, base de connaissances, etc.) | E60: L'outil de gestion des tickets est-il intégré avec d'autres systèmes (gestion des assets, base de connaissances) ? | F60: Non | G60: Schéma d'architecture applicative montrant les flux et intégrations de l'outil HD. | H60: Risque de doublon ou d’erreurs sans intégration des systèmes. | I60: Moyenne | J60: Impossibilité de croiser les informations avec d'autres systèmes (matériel, incidents récurrents, etc.). | K60: Standardiser la typologie des incidents et demandes pour faciliter le traitement.
G61: Documentation technique des intégrations (API, connecteurs) ou preuves de leur fonctionnement (logs, données synchronisées). | H61: . | J61: . | K61: Former les techniciens à l’utilisation de cette typologie pour garantir la cohérence.
C62: S’assurer que des critères à renseigner pour la qualification des tickets existent | D62: Présence d'une typologie standardisée des incidents et demandes | E62: Une typologie standardisée des incidents et demandes est-elle définie dans l'outil ? | F62: Oui | G62: Arborescence/Liste de la typologie (catégories, sous-catégories, items) configurée dans l'outil. | H62: Classement erroné ou imprécis des tickets. | I62: Elevée | J62: Mauvaise classification des tickets, empêchant les analyses ou l’orientation automatique vers les bons interlocuteurs. | K62: Imposer des champs obligatoires pour la priorisation des tickets.
G63: Guide ou procédure de qualification/catégorisation des tickets pour les techniciens. | H63: . | J63: . | K63: Contrôler régulièrement la qualité des données saisies pour assurer la fiabilité.
D64: Existence de champs obligatoires pour la priorisation des tickets | E64: Des champs obligatoires pour la priorisation des tickets sont-ils configurés dans l'outil ? | F64: Non | G64: Captures d'écran de la configuration de l'outil montrant les champs obligatoires (ex: impact, urgence) pour la priorisation. | H64: Traitement inadapté en l’absence d’informations de priorité. | I64: Faible | J64: Perte de temps et de qualité dans le tri des tickets, allongeant les délais de traitement. | K64: Inclure des critères d’impact business dans la qualification des tickets.
G65: Matrice de priorisation officielle (définissant la priorité en fonction de l'impact et de l'urgence). | H65: . | J65: . | K65: Sensibiliser les équipes au poids des impacts pour prioriser efficacement.
D66: Inclusion de critères d'impact business dans la qualification | E66: Des critères d'impact business sont-ils inclus dans la qualification des tickets ? | F66: Oui | G66: Définition des niveaux d'impact business utilisés dans la matrice de priorisation. | H66: Erreur d’évaluation de l’urgence sans considération de l’impact métier. | I66: Elevée | J66: Non-prise en compte de l’impact métier dans les priorités, engendrant un traitement déséquilibré des incidents. | K66: Catégoriser techniquement les tickets pour orienter rapidement vers les bonnes équipes.
G67: Procédure ou guide de qualification expliquant comment évaluer l'impact business d'un ticket. | H67: . | J67: . | K67: Mettre à jour régulièrement la catégorisation en fonction des évolutions technologiques.
D68: Présence d'une catégorisation technique permettant une orientation efficace des tickets | E68: Une catégorisation technique permettant une orientation efficace des tickets est-elle en place ? | F68: Oui | G68: Arborescence de catégorisation technique (distincte de la typologie fonctionnelle si nécessaire) utilisée dans l'outil. | H68: Désorientation des tickets vers des équipes non pertinentes. | I68: Moyenne | J68: Mauvaise orientation technique, retardant la prise en charge ou entraînant des escalades inutiles. | K68: Identifier et marquer les incidents récurrents ou liés pour faciliter leur gestion.
G69: Matrice de routage/affectation des tickets basée sur la catégorie technique (vers les groupes de support L2/L3). | H69: . | J69: . | K69: Analyser ces incidents pour mettre en place des actions préventives.
D70: Capacité à identifier et marquer les incidents récurrents ou liés | E70: L'outil permet-il d'identifier et de marquer les incidents récurrents ou liés ? | F70: Non | G70: Procédure pour l'identification et la liaison des incidents (ex: lien vers un incident parent ou un problème). | H70: Sous-estimation des incidents récurrents sans identification spécifique. | I70: Elevée | J70: Incidents récurrents non identifiés, empêchant les actions préventives et l'amélioration continue. | K70: Fournir des scripts d’accueil et de qualification standardisés aux techniciens.
G71: Exemples de tickets liés dans l'outil ou rapports spécifiques sur les incidents récurrents. | H71: . | J71: . | K71: Former régulièrement les techniciens à l’utilisation de ces scripts pour homogénéiser les réponses.
C72: S’assure qu’il existe une liste de questions à dérouler lors d'un appel afin préciser au mieux la demande de l'utilisateur | D72: Disponibilité de scripts d'accueil et de qualification standardisés pour les techniciens | E72: Des scripts d'accueil et de qualification standardisés sont-ils mis à disposition des techniciens ? | F72: Non | G72: Modèles de scripts d'accueil (téléphonique, email, chat...). | H72: Accueil incohérent des utilisateurs en l’absence de scripts unifiés. | I72: Faible | J72: Accueil et qualification hétérogènes selon le technicien, provoquant une inégalité de traitement. | K72: Mettre en place des questionnaires spécifiques par type d’incident ou demande.
G73: Check-lists ou scripts de qualification pour les types de demandes les plus fréquents. | H73: . | J73: . | K73: Actualiser les questionnaires en fonction des retours d’expérience pour améliorer la pertinence.
D74: Existence de questionnaires spécifiques par type d'incident ou de demande | E74: Des questionnaires spécifiques par type d'incident ou de demande sont-ils disponibles ? | F74: Oui | G74: Exemples de questionnaires de diagnostic intégrés ou référencés pour des incidents spécifiques. | H74: Qualification incomplète ou inadaptée sans guides dédiés. | I74: Elevée | J74: Qualification incomplète ou incorrecte sur des incidents spécifiques, entraînant des erreurs de diagnostic. | K74: Utiliser un arbre de décision pour guider l’analyse de premier niveau.
G75: Base de connaissances ou référentiel documentaire contenant ces questionnaires structurés. | H75: . | J75: . | K75: Former les équipes à l’utilisation de cet outil pour améliorer la qualité des diagnostics.
D76: Présence d'un arbre de décision pour guider l'analyse de premier niveau | E76: Un arbre de décision pour guider l'analyse de premier niveau est-il formalisé ? | F76: Non | G76: Exemples d'arbres de décision formalisés pour des scénarios de dépannage courants. | H76: Erreurs d’analyse de premier niveau sans aide à la décision. | I76: Moyenne | J76: Perte de temps dans l’analyse des incidents en l’absence de guidance claire et structurée. | K76: Intégrer les questions dans l’outil de gestion des tickets pour assurer leur utilisation systématique.
G77: Preuve de l'intégration ou de la mise à disposition de ces arbres dans l'outil ou la base de connaissances. | H77: . | J77: . | K77: Contrôler l’usage de ces questions et corriger les écarts.
D78: Mise à jour régulière des questions en fonction des retours d'expérience | E78: Les questions de qualification sont-elles mises à jour régulièrement en fonction des retours d'expérience ? | F78: Non | G78: Procédure de revue et de mise à jour des scripts, questionnaires et arbres de décision. | H78: Déconnexion des procédures de la réalité terrain sans mise à jour régulière. | I78: Elevée | J78: Mauvaise prise en compte des apprentissages du terrain, reproduisant les mêmes erreurs ou lacunes. | K78: Distinguer clairement la gestion des incidents de celle des problèmes.
G79: Registre des modifications ou compte-rendu de réunions prouvant la réalisation de ces mises à jour. | H79: . | J79: . | K79: Former les équipes aux processus spécifiques de gestion des problèmes.
D80: Intégration des questions dans l'outil de gestion des tickets pour assurer leur utilisation | E80: Les questions standardisées sont-elles intégrées dans l'outil de gestion des tickets ? | F80: Non | G80: Captures d'écran de l'outil montrant l'intégration active de questionnaires ou de champs guidés. | H80: Non-utilisation des guides si non intégrés à l’outil de ticketing. | I80: Faible | J80: Questions oubliées ou mal posées, conduisant à un diagnostic incorrect dès le départ. | K80: Mettre en place des indicateurs de suivi des problèmes identifiés.
G81: Guide utilisateur ou procédure interne démontrant l'utilisation obligatoire ou assistée de ces questions. | H81: . | J81: . | K81: Analyser régulièrement ces indicateurs pour piloter les actions correctives.
C82: S’assurer que les problèmes sont gérés | D82: Distinction claire entre la gestion des incidents et la gestion des problèmes | E82: Une distinction claire entre la gestion des incidents et la gestion des problèmes est-elle établie dans les procédures ? | F82: Oui | G82: Procédure de gestion des incidents. | H82: Confusion dans le traitement entre incidents ponctuels et problèmes systémiques. | I82: Elevée | J82: Confusion entre résolution rapide et traitement de fond, empêchant la pérennité des solutions apportées. | K82: Suivre le taux de problèmes résolus par rapport aux problèmes identifiés.
G83: Procédure de gestion des problèmes (soulignant les différences d'objectifs et d'activités). | H83: . | J83: . | K83: Mettre en place des plans d’action pour améliorer ce taux.
D84: Existence d'indicateurs de suivi des problèmes identifiés | E84: Des indicateurs de suivi des problèmes identifiés sont-ils définis et mesurés ? | F84: Non | G84: Définition des indicateurs clés (KPIs) spécifiques à la gestion des problèmes (ex: nombre de problèmes ouverts, backlog...). | H84: Suivi inefficace sans indicateurs de gestion des problèmes. | I84: Moyenne | J84: Non-suivi des problèmes identifiés, laissant perdurer les incidents récurrents. | K84: Mesurer le délai moyen de résolution des problèmes par niveau de priorité.
G85: Tableaux de bord ou rapports périodiques de suivi de ces indicateurs de gestion des problèmes. | H85: . | J85: . | K85: Fixer des objectifs de performance et suivre leur atteinte.
D86: Taux de problèmes résolus vs. problèmes identifiés | E86: Le taux de problèmes résolus par rapport aux problèmes identifiés est-il mesuré régulièrement ? | F86: Non | G86: Rapports périodiques montrant le ratio/taux de problèmes résolus (avec cause racine identifiée et solution pérenne) par rapport aux problèmes créés. | H86: Problèmes non résolus faute de suivi ou d’escalade. | I86: Elevée | J86: Accumulation de problèmes non résolus, provoquant un engorgement du support. | K86: Formaliser un processus d’analyse des causes racines.
G87: Définition de l'indicateur "Taux de résolution des problèmes". | H87: . | J87: . | K87: Former les équipes à cette méthode pour assurer des analyses efficaces.
D88: Délai moyen de résolution des problèmes par niveau de priorité | E88: Le délai moyen de résolution des problèmes est-il mesuré par niveau de priorité ? | F88: Oui | G88: Rapports périodiques montrant le délai moyen de résolution (MTTR) des problèmes, ventilé par priorité. | H88: Temps de traitement excessif pour les problèmes critiques. | I88: Faible | J88: Problèmes critiques non traités en priorité, affectant significativement la productivité. | K88: Documenter formellement le processus de gestion des problèmes.
G89: Définition des niveaux de priorité des problèmes et des objectifs de délai associés. | H89: . | J89: . | K89: Diffuser et faire appliquer ce processus au sein des équipes.
D90: Existence d'un processus d'analyse des causes racines | E90: Un processus formalisé d'analyse des causes racines est-il en place ? | F90: Oui | G90: Procédure formalisée d'analyse des causes racines (RCA), incluant les méthodes possibles (5 Pourquoi, Ishikawa...). | H90: Répétition des incidents sans analyse approfondie. | I90: Elevée | J90: Traitements symptomatiques répétés au lieu d’éradication des causes profondes. | K90: Désigner un responsable clairement identifié pour la gestion des problèmes.
G91: Exemples de rapports d'analyse de cause racine (RCA reports) documentés pour des problèmes résolus. | H91: . | J91: . | K91: Assurer le suivi et le reporting régulier des activités liées aux problèmes.
C92: S’assurer qu’un processus de gestion des problèmes existe | D92: Documentation formelle du processus de gestion des problèmes | E92: Le processus de gestion des problèmes est-il formellement documenté ? | F92: Non | G92: Procédure/Politique de gestion des problèmes décrivant le cycle de vie complet d'un problème. | H92: Absence de traçabilité et d’amélioration continue sans documentation. | I92: Moyenne | J92: Résolutions ponctuelles sans partage ou formalisation, empêchant la réutilisation collective. | K92: Définir des critères précis pour qualifier un incident en problème.
G93: Manuel Qualité ou documentation du Système de Management (ITIL, ISO 20000...) décrivant le processus. | H93: . | J93: . | K93: Former les équipes à ces critères pour garantir une bonne qualification.
D94: Désignation d'un responsable de la gestion des problèmes | E94: Un responsable de la gestion des problèmes est-il formellement désigné ? | F94: Non | G94: Organigramme ou description de rôle montrant explicitement la fonction de "Problem Manager" ou le responsable désigné. | H94: Pas de pilote pour coordonner la résolution des problèmes. | I94: Elevée | J94: Flou dans les responsabilités empêchant la bonne coordination et la priorisation des actions. | K94: Mettre en place des comités de revue périodique des problèmes en cours.
G95: Fiche de poste du "Problem Manager". | H95: . | J95: . | K95: Assurer la participation des parties prenantes clés à ces comités.
D96: Existence de critères de qualification pour transformer un incident en problème | E96: Des critères formels de qualification permettant de transformer un incident en problème sont-ils définis ? | F96: Oui | G96: Procédure de gestion des problèmes décrivant les critères précis de création d'un enregistrement "Problème". | H96: Incident grave non transformé en problème faute de critères définis. | I96: Faible | J96: Mauvaise gestion du cycle de vie des incidents transformés en problèmes, causant des lenteurs et un suivi incomplet. | K96: Intégrer le processus de gestion des problèmes dans le système de management de la qualité.
G97: Exemples de tickets d'incident ayant conduit à la création d'un problème, justifiant l'application des critères. | H97: . | J97: . | K97: Documenter et auditer régulièrement cette intégration pour assurer son efficacité.
D98: Mise en place de comités de revue périodique des problèmes en cours | E98: Des comités de revue périodique des problèmes en cours sont-ils organisés régulièrement ? | F98: Oui | G98: Planning ou invitations récurrentes aux réunions de revue des problèmes. | H98: Manque de priorisation et de suivi sans comité de revue. | I98: Elevée | J98: Problèmes persistants non revus régulièrement, limitant l’amélioration continue. | K98: Amélioration de la qualité des données saisies, facilitant le traitement et l’analyse des tickets.
G99: Comptes-rendus des dernières réunions de revue des problèmes (participants, points abordés, décisions, actions). | H99: . | J99: . | K99: .
D100: Intégration du processus de gestion des problèmes dans le système de management de la qualité | E100: Le processus de gestion des problèmes est-il intégré dans le système de management de la qualité ? | F100: Oui | G100: Manuel Qualité ou documentation du SMSI/SMQ mentionnant le processus de gestion des problèmes. | H100: Gestion des problèmes déconnectée des autres processus qualité. | I100: Moyenne | J100: Manque d’alignement qualité/suivi, entraînant une gestion isolée du traitement des problèmes. | K100: Réduction des erreurs de classification et accélération du processus de saisie des incidents.
...

Sheet 4.5
A1: Domaine | B1: Points de Contrôle | C1: Objectifs de Contrôle | D1: Critère d’Évaluation | E1: Question d’Évaluation | F1: Réponses | G1: Documents Requis | H1: Risques | I1: Criticités | J1: Conséquences | K1: Recommendations
A2: AUDIT SECURITE INFORMATIQUE | B2: Facteurs clés de succès | C2: Vérifier qu’une politique de sécurité est définie et correspond à l'activité de l'Organisation | D2: Existence d'un document formalisé intitulé "Politique de Sécurité de l'Information" (ou équivalent). | E2: La politique de sécurité de l'information existe-t-elle sous une forme documentée ? | F2: oui | G2: Politique de Sécurité de l’Information version actuelle | H2: Absence de cadre directeur pour la sécurité | I2: Elevée | J2: Décisions de sécurité incohérentes et inefficaces. | K2: Établir un cadre décisionnel basé sur une analyse des risques standardisée (ISO 27001, NIST).
E3: . | F3: . | G3: Historique de validation ou création de la politique | J3: Difficulté à obtenir des ressources et du soutien pour les initiatives de sécurité. | K3: Développer un business case clair pour démontrer le ROI des initiatives de sécurité.
D4: Approbation formelle de la politique par la Direction Générale (ou instance équivalente). | E4: La politique a-t-elle été approuvée formellement par la Direction Générale ou une instance équivalente ? | F4: non | G4: Procès-verbal de réunion de validation par la Direction | H4: Mesures de sécurité inadéquates ou disproportionnées | I4: Moyenne | J4: Vulnérabilités persistantes et risques accrus d'incidents de sécurité. | K4: Mettre en place un programme de gestion des vulnérabilités avec scans réguliers et priorisation des correctifs.
E5: . | F5: . | G5: Document signé d’approbation officielle de la politique | J5: Gaspillage de ressources sur des mesures inefficaces ou inutiles. | K5: Évaluer les mesures existantes pour réallouer les ressources vers des solutions efficaces.
D6: Alignement explicite des objectifs de la politique avec les activités métier et les risques spécifiques de l'Organisation. | E6: Les objectifs de la politique sont-ils explicitement alignés avec les activités métier et les risques spécifiques de l'organisation ? | F6: pas | G6: Cartographie des risques métier | H6: Politique de sécurité obsolète et inadaptée | I6: Elevée | J6: Non-conformité aux exigences réglementaires et aux meilleures pratiques. | K6: Réaliser un audit de conformité et aligner les pratiques sur les réglementations (RGPD, PCI-DSS, etc.).
E7: . | F7: . | G7: Note de cadrage ou étude de cohérence entre politique et stratégie métier | J7: Protection inadéquate contre les menaces actuelles. | K7: Déployer des solutions de protection adaptées (pare-feu, EDR, SIEM) aux menaces actuelles.
D8: Couverture des domaines clés de la sécurité (accès, données, continuité, etc.) dans la politique. | E8: La politique couvre-t-elle les domaines clés de la sécurité (accès, données, continuité, etc.) ? | F8: oui | G8: Sommaire de la politique listant les domaines couverts | H8: Manque de sensibilisation et de connaissance des règles de sécurité | I8: Faible | J8: Comportements à risque et erreurs des employés. | K8: Lancer des programmes de formation continue pour réduire les comportements à risque.
E9: . | F9: . | G9: Annexes détaillant les mesures de sécurité par domaine | J9: Augmentation des incidents de sécurité. | K9: Implémenter un système de détection et de réponse aux incidents (SOC ou MDR).
D10: Date de dernière révision de la politique documentée et inférieure à une période définie (ex: 1 an). | E10: La date de dernière révision de la politique est-elle documentée et inférieure à une période définie (ex : 1 an) ? | F10: pas | G10: Registre des révisions de la politique | H10: Non-application de la politique de sécurité par les employés | I10: Elevée | J10: Non-respect des règles et procédures de sécurité. | K10: Renforcer l’application des politiques via des audits internes et des sanctions claires.
E11: . | F11: . | G11: Capture d’écran ou copie du document avec la date de dernière mise à jour | J11: Exposition accrue aux risques. | K11: Effectuer une analyse de risques régulière pour identifier et prioriser les expositions.
C12: Vérifier qu’une démarche de mise en œuvre de la gestion de la sécurité est adoptée et compatible avec la culture de l'Organisation | D12: Existence d'un plan de mise en œuvre documenté de la politique de sécurité. | E12: Un plan de mise en œuvre documenté de la politique de sécurité existe-t-il ? | F12: non | G12: Plan d’action ou feuille de route de mise en œuvre | H12: Absence d'une approche structurée de la sécurité | I12: Moyenne | J12: Difficulté à gérer et à coordonner les activités de sécurité. | K12: Centraliser la gestion des activités de sécurité avec un outil de GRC (Gouvernance, Risque, Conformité).
E13: . | F13: . | G13: Tableau de suivi des jalons de mise en œuvre | J13: Inefficacité des mesures de sécurité. | K13: Évaluer l’efficacité des mesures via des tests de pénétration et des simulations.
D14: Adéquation démontrée entre les actions de sécurité planifiées et la culture (ex: niveau de formalisme, communication). | E14: Les actions de sécurité planifiées sont-elles adaptées à la culture de l’organisation (niveau de formalisme, communication) ? | F14: oui | G14: Rapport d’adéquation culture/sécurité | H14: Manque d'adhésion et de coopération des parties prenantes | I14: Elevée | J14: Résistance au changement et faible adoption des mesures de sécurité. | K14: Mener des campagnes de communication pour favoriser l’adoption des mesures de sécurité.
E15: . | F15: . | G15: Preuves de communications internes adaptées (affiches, slides, etc.) | J15: Difficulté à mettre en œuvre la politique de sécurité. | K15: Simplifier les processus de mise en œuvre des politiques avec des guides clairs.
D16: Présence d'indicateurs de suivi de l'adoption de la démarche de sécurité. | E16: Des indicateurs de suivi de l’adoption de la démarche de sécurité sont-ils en place ? | F16: non | G16: Tableaux de bord avec indicateurs clés | H16: Mesures de sécurité trop restrictives ou inadaptées | I16: Faible | J16: Frustration des utilisateurs et perturbation des opérations. | K16: Optimiser l’ergonomie des outils de sécurité pour réduire la frustration des utilisateurs.
E17: . | F17: . | G17: Rapports de suivi périodique des KPIs de sécurité | J17: Impact négatif sur la productivité. | K17: Mesurer l’impact des mesures de sécurité sur la productivité pour ajuster les priorités.
D18: Identification et prise en compte documentées des résistances potentielles au changement. | E18: Les résistances potentielles au changement ont-elles été identifiées et documentées ? | F18: pas | G18: Rapport d’analyse des risques sociaux/organisationnels | H18: Difficulté à évaluer l'efficacité des mesures de sécurité | I18: Elevée | J18: Difficulté à justifier les investissements en sécurité. | K18: Utiliser des métriques (KPI) pour justifier les besoins d’investissement en sécurité.
E19: . | F19: . | G19: Plan de gestion du changement ou fiche d’impact | J19: Manque d'indicateurs de performance pertinents. | K19: Définir des indicateurs de performance (ex. : taux de résolution des vulnérabilités) pour évaluer les progrès.
D20: Validation de la démarche par les instances représentatives du personnel (si applicable). | E20: La démarche a-t-elle été validée par les instances représentatives du personnel, si applicable ? | F20: non | G20: Procès-verbal de validation par les instances représentatives | H20: Lacunes de sécurité dans les processus métier | I20: Moyenne | J20: Perturbation des activités et pertes financières. | K20: Mettre en place un plan de continuité et de reprise d’activité (BCP/DRP).
E21: . | F21: . | G21: Courriers ou courriels d’accord officiel des représentants du personnel | J21: Atteinte à la réputation de l'entreprise. | K21: Renforcer la protection des données via le chiffrement et des sauvegardes régulières.
C22: Vérifier que la direction assure un soutien total et un engagement visible pour la sécurité | D22: Existence de communications régulières de la Direction sur l'importance de la sécurité. | E22: La Direction communique-t-elle régulièrement sur l’importance de la sécurité ? | F22: oui | G22: Courriels de la Direction traitant de sécurité | H22: Manque de visibilité et de soutien de la direction | I22: Elevée | J22: Manque d'engagement envers la sécurité. | K22: Intégrer des modules de sensibilisation à la sécurité dans les processus RH.
E23: . | F23: . | G23: Captures d’écrans ou archives de messages intranet/diffusions internes | J23: Difficulté à obtenir le soutien nécessaire pour les initiatives de sécurité. | K23: Effectuer des audits réguliers pour identifier les failles exploitables.
D24: Allocation de ressources (budgétaires, humaines) suffisantes et démontrables pour les initiatives de sécurité. | E24: Les ressources (budgétaires, humaines) allouées aux initiatives de sécurité sont-elles suffisantes et démontrables ? | F24: pas | G24: Budget annuel de la DSI ou sécurité | H24: Insuffisance des ressources allouées à la sécurité | I24: Faible | J24: Budget insuffisant pour mettre en œuvre des mesures de sécurité efficaces. | K24: Prioriser les investissements en fonction d’une matrice de risques actualisée.
E25: . | F25: . | G25: Fiche de poste ou organigramme RH montrant l’allocation humaine | J25: Recours à des solutions de sécurité inadéquates. | K25: Mettre à jour les sources d’information pour des décisions basées sur des données fiables.
D26: Participation active et documentée de membres de la Direction aux comités de sécurité ou revues stratégiques. | E26: La participation active et documentée de membres de la Direction aux comités de sécurité ou revues stratégiques est-elle assurée ? | F26: oui | G26: Comptes-rendus de comités de sécurité | H26: Manque d'implication de la direction dans les décisions de sécurité | I26: Elevée | J26: Décisions stratégiques erronées et manque de priorisation des risques. | K26: Adopter une méthodologie d’analyse des risques reconnue (EBIOS, OCTAVE).
E27: . | F27: . | G27: Liste de présence des membres de la Direction aux réunions | J27: Exposition accrue aux menaces. | K27: Réévaluer les mesures de sécurité pour garantir leur pertinence face aux menaces.
D28: Intégration des objectifs de sécurité dans les objectifs stratégiques globaux de l'Organisation. | E28: Les objectifs de sécurité sont-ils intégrés dans les objectifs stratégiques globaux de l’organisation ? | F28: non | G28: Plan stratégique de l’Organisation intégrant la sécurité | H28: Mauvaise gestion des incidents de sécurité | I28: Moyenne | J28: Impact négatif sur la continuité des activités. | K28: Utiliser des outils d’évaluation adaptés pour des résultats fiables.
E29: . | F29: . | G29: Matrice de contribution entre objectifs sécurité et stratégie globale | J29: Perte de données et atteinte à la réputation. | K29: Développer un plan d’action basé sur une priorisation claire des risques.
D30: Endossement formel et visible de la politique de sécurité par la Direction Générale. | E30: La politique de sécurité bénéficie-t-elle d’un endossement formel et visible par la Direction Générale ? | F30: pas | G30: Note de service ou déclaration officielle signée par la Direction | H30: Manque de sensibilisation et de compétences en sécurité chez les employés | I30: Elevée | J30: Erreurs humaines et négligence en matière de sécurité. | K30: Accélérer la mise en œuvre des correctifs via des processus automatisés.
E31: . | F31: . | G31: Visuel interne (poster, intranet) affichant l’engagement formel | J31: Vulnérabilité accrue aux attaques. | K31: Réviser régulièrement les politiques pour réduire les incidents.
C32: Vérifier que les exigences de sécurité et les risques sont compris et évalués | D32: Existence d'une méthodologie formalisée d'analyse des risques de sécurité. | E32: Une méthodologie formalisée d’analyse des risques de sécurité existe-t-elle ? | F32: non | G32: Document décrivant la méthode d’analyse des risques (EBIOS, ISO, etc.) | H32: Décisions de sécurité prises sans connaissance suffisante des risques | I32: Faible | J32: Mauvaise allocation des ressources et investissements inefficaces. | K32: Actualiser les bases de connaissances pour des décisions alignées sur les menaces actuelles.
E33: . | F33: . | G33: Manuel de sécurité ou procédures associées à l’analyse des risques | J33: Décisions de sécurité basées sur des informations incomplètes. | K33: Intégrer des technologies modernes pour contrer les nouvelles menaces.
D34: Réalisation documentée d'une analyse des risques couvrant les actifs informationnels clés. | E34: Une analyse des risques couvrant les actifs informationnels clés a-t-elle été réalisée et documentée ? | F34: oui | G34: Rapport d’analyse de risques complet | H34: Analyse des risques incomplète ou biaisée | I34: Elevée | J34: Analyse de risques erronée et sous-estimation des menaces. | K34: Effectuer des analyses de risques dynamiques pour réduire les vulnérabilités.
E35: . | F35: . | G35: Inventaire des actifs critiques analysés | J35: Mise en place de mesures de sécurité inadéquates. | K35: Renforcer la surveillance pour détecter rapidement les incidents potentiels.
D36: Identification et documentation des exigences de sécurité légales, réglementaires et contractuelles. | E36: Les exigences légales, réglementaires et contractuelles sont-elles identifiées et documentées ? | F36: pas | G36: Revue réglementaire ou juridique | H36: Méthodologie d'analyse des risques inadéquate | I36: Moyenne | J36: Méthodologie inappropriée et résultats peu fiables. | K36: Mettre en place un comité de gestion des risques pour une vision globale.
E37: . | F37: . | G37: Registre des exigences légales avec cartographie des obligations | J37: Difficulté à prioriser les risques et à allouer les ressources efficacement. | K37: Intégrer la sécurité dans l’onboarding des nouveaux employés.
D38: Validation des résultats de l'analyse des risques par les propriétaires métier. | E38: Les résultats de l’analyse des risques ont-ils été validés par les propriétaires métier ? | F38: oui | G38: Document de validation signé par les responsables métier | H38: Difficulté à suivre et à mettre en œuvre les mesures correctives | I38: Elevée | J38: Retard dans la mise en œuvre des mesures correctives. | K38: Diversifier les formats de sensibilisation (jeux, vidéos) pour plus d’impact.
E39: . | F39: . | G39: Compte-rendu de réunion de validation des risques | J39: Augmentation du risque d'incidents de sécurité. | K39: Justifier les programmes de sensibilisation avec des études d’impact.
D40: Mise à jour périodique de l'analyse des risques documentée. | E40: La mise à jour périodique de l’analyse des risques est-elle documentée ? | F40: non | G40: Registre de mise à jour des analyses de risques | H40: L'analyse des risques devient obsolète et ne reflète plus la réalité des menaces et des vulnérabilités | I40: Faible | J40: Décisions de sécurité basées sur des informations obsolètes. | K40: Clarifier les règles de sécurité via des communications régulières.
E41: . | F41: . | G41: Agenda ou planification des prochaines analyses | J41: Inefficacité des mesures de sécurité face aux nouvelles menaces. | K41: Améliorer la détection des incidents via des outils d’analyse comportementale.
C42: Vérifier que l’ensemble des responsables et des employés sont sensibilisés et informés | D42: Existence d'un programme de sensibilisation à la sécurité formalisé et planifié. | E42: Un programme de sensibilisation à la sécurité formalisé et planifié existe-t-il ? | F42: pas | G42: Programme annuel ou pluriannuel de sensibilisation | H42: Manque de sensibilisation des employés aux risques de sécurité | I42: Elevée | J42: Exposition accrue aux risques et vulnérabilités. | K42: Créer des canaux de support dédiés pour les questions de sécurité.
E43: . | F43: . | G43: Calendrier des sessions prévues | J43: Augmentation de la probabilité d'incidents de sécurité. | K43: Reconnaître les efforts des employés pour renforcer leur motivation.
D44: Preuves de sessions de sensibilisation régulières pour tous les employés (listes d'émargement, supports). | E44: Des preuves de sessions de sensibilisation régulières pour tous les employés (listes d’émargement, supports) sont-elles disponibles ? | F44: oui | G44: Listes d’émargement signées | H44: Les nouveaux arrivants ne sont pas conscients des risques et des bonnes pratiques de sécurité | I44: Moyenne | J44: Risques accrus pour l'organisation. | K44: Centraliser les ressources de sécurité dans un portail accessible.
E45: . | F45: . | G45: Supports de présentation utilisés lors des sessions | J45: Difficulté à intégrer les nouveaux employés dans la culture de sécurité de l'entreprise. | K45: Documenter les politiques et les rendre facilement consultables.
D46: post-sensibilisation (quiz, etc.). | E46: Des évaluations post-sensibilisation (quiz, etc.) sont-elles réalisées ? | F46: non | G46: Résultats des quiz post-formation | H46: Difficulté à évaluer l'efficacité des campagnes de sensibilisation | I46: Elevée | J46: Inefficacité des mesures de sensibilisation et persistance des comportements à risque. | K46: Maintenir un registre des communications pour prouver la conformité.
E47: . | F47: . | G47: Rapport d’analyse des scores ou des retours | J47: Difficulté à justifier les investissements dans les programmes de sensibilisation. | K47: Auditer régulièrement les fournisseurs pour garantir leur conformité.
D48: Existence de canaux de communication dédiés aux informations de sécurité (intranet, newsletter...). | E48: Des canaux de communication dédiés aux informations de sécurité (intranet, newsletter, etc.) existent-ils ? | F48: pas | G48: Copies de newsletters sécurité | H48: Incertitude quant au niveau de compréhension des enjeux de sécurité par les employés | I48: Faible | J48: Comportements à risque et non-respect des règles de sécurité. | K48: Mettre en place des plans de réponse aux incidents impliquant les fournisseurs.
E49: . | F49: . | G49: Captures de pages intranet dédiées | J49: Augmentation des incidents de sécurité. | K49: Renforcer les contrats avec des clauses de sécurité strictes.
D50: Contenu des actions de sensibilisation adapté aux différents profils de personnel. | E50: Le contenu des actions de sensibilisation est-il adapté aux différents profils de personnel ? | F50: non | G50: Planning des actions de sensibilisation par type de personnel | H50: Manque de ressources disponibles pour aider les employés à comprendre et à appliquer les règles de sécurité | I50: Elevée | J50: Manque de soutien et de conseils pour les employés en matière de sécurité. | K50: Définir des mécanismes de responsabilisation (contrats, formations).
E51: . | F51: . | G51: Guides adaptés aux différents profils (RH, IT, utilisateurs, etc.) | J51: Frustration et démotivation des employés. | K51: Mettre en place des rappels réguliers pour minimiser les erreurs.
C52: Vérifier que les lignes directrices de la politique de sécurité et des normes de sécurité de l'information sont distribuées à tous les employés et à tous les fournisseurs | D52: Existence d'une procédure documentée pour la diffusion des documents de sécurité. | E52: Une procédure documentée pour la diffusion des documents de sécurité existe-t-elle ? | F52: oui | G52: Procédure de diffusion des documents sécurité | H52: Difficulté d'accès à la politique de sécurité | I52: Moyenne | J52: Difficulté à trouver et à comprendre les informations de sécurité. | K52: Surveiller les indicateurs de risque pour anticiper les incidents.
E53: . | F53: . | G53: Liste de distribution officielle | J53: Non-respect des règles de sécurité par manque d'information. | K53: Adopter une approche proactive pour gérer les risques (scans, audits).
D54: Preuves de distribution de la politique et des normes à tous les employés (ex: accusé de réception, intranet). | E54: Des preuves de distribution de la politique et des normes à tous les employés (accusé de réception, intranet) sont-elles disponibles ? | F54: pas | G54: Accusés de réception des employés | H54: Manque de preuve de la diffusion de la politique de sécurité | I54: Elevée | J54: Difficulté à prouver la communication des politiques de sécurité. | K54: Investir dans des technologies émergentes pour rester à jour.
E55: . | F55: . | G55: Preuve d’hébergement intranet avec accès | J55: Risque accru de non-conformité. | K55: Offrir des perspectives de carrière pour motiver les équipes sécurité.
D56: Inclusion des exigences de sécurité dans les contrats avec les fournisseurs. | E56: Les exigences de sécurité sont-elles incluses dans les contrats avec les fournisseurs ? | F56: oui | G56: Clauses contractuelles types intégrant la sécurité | H56: Failles de sécurité introduites par les fournisseurs | I56: Faible | J56: Vulnérabilités de sécurité dans les systèmes et services des fournisseurs. | K56: Évaluer les nouvelles menaces via une veille technologique active.
E57: . | F57: . | G57: Copie d’un contrat fournisseur incluant ces clauses | J57: Incidents de sécurité affectant l'organisation. | K57: Mesurer l’efficacité des formations pour optimiser les ressources.
D58: Mise à disposition des documents de sécurité dans un format accessible et compréhensible. | E58: Les documents de sécurité sont-ils mis à disposition dans un format accessible et compréhensible ? | F58: pas | G58: Documents en version PDF ou HTML accessibles | H58: Incertitude quant à la prise de connaissance effective de la politique de sécurité | I58: Elevée | J58: Non-application des mesures de sécurité et augmentation des risques. | K58: Utiliser des tableaux de bord pour visualiser les performances de sécurité.
E59: . | F59: . | G59: Traductions éventuelles ou documents en FALC | J59: Difficulté à responsabiliser les employés en cas de non-respect des politiques. | K59: Détecter les failles via des audits proactifs et des tests réguliers.
D60: Mécanisme de suivi de la prise de connaissance des documents par les employés et fournisseurs. | E60: Un mécanisme de suivi de la prise de connaissance des documents par les employés et fournisseurs est-il en place ? | F60: non | G60: Registre des prises de connaissance | H60: Mauvaise compréhension des documents de sécurité par certaines populations | I60: Moyenne | J60: Erreurs et négligences en matière de sécurité. | K60: Mettre en place un cycle d’amélioration continue pour corriger les erreurs.
E61: . | F61: . | G61: Captures de l’outil RH ou intranet de validation | J61: Augmentation des risques d'incidents. | K61: Présenter des rapports clairs à la direction pour obtenir leur soutien.
C62: Vérifier que les acteurs de la sécurité sont formés de manière appropriée | D62: Identification claire des rôles et responsabilités spécifiques en matière de sécurité (RSSI, correspondants, etc.). | E62: Les rôles et responsabilités spécifiques en matière de sécurité (RSSI, correspondants, etc.) sont-ils clairement identifiés ? | F62: oui | G62: Fiches de fonction mentionnant la sécurité | H62: Compétences insuffisantes des personnes en charge de la sécurité | I62: Elevée | J62: Difficulté à gérer efficacement les risques de sécurité. Augmentation de la probabilité d'incidents. | K62: Impliquer la direction dans les comités de sécurité pour un engagement fort.
E63: . | F63: . | G63: Organigramme ou annuaire des rôles sécurité | J63: Incapacité à s'adapter aux nouvelles technologies et menaces. Vulnérabilités accrues. | K63: Clarifier les rôles et responsabilités via une matrice RACI.
D64: Existence d'un plan de formation spécifique pour les acteurs de la sécurité. | E64: Un plan de formation spécifique pour les acteurs de la sécurité existe-t-il ? | F64: non | G64: Plan de formation des acteurs clés | H64: Compétences techniques obsolètes | I64: Faible | J64: Démotivation et manque d'engagement des équipes sécurité. Difficulté à attirer et retenir les talents. | K64: Renforcer le leadership avec des coordinateurs sécurité dédiés.
E65: . | F65: . | G65: Référentiel des compétences visées | J65: Exposition accrue aux nouvelles menaces. Difficulté à mettre en place des mesures de protection adéquates. | K65: Documenter les écarts de conformité pour des audits externes.
D66: Preuves de réalisation des formations prévues pour les acteurs de la sécurité (certificats, attestations). | E66: Des preuves de réalisation des formations prévues pour les acteurs de la sécurité (certificats, attestations) sont-elles disponibles ? | F66: pas | G66: Attestations de présence ou certificats de formation | H66: Manque de reconnaissance des compétences et expertise en sécurité insuffisante | I66: Elevée | J66: Posture de sécurité faible et persistance des vulnérabilités. Gaspillage des ressources investies dans la formation. | K66: Aligner les objectifs de sécurité avec les priorités métier via des ateliers.
E67: . | F67: . | G67: Rapports de formation mensuels ou annuels | J67: Difficulté à mesurer l'efficacité des mesures de sécurité. Incapacité à identifier les points faibles et à améliorer la sécurité. | K67: Former les employés pour une meilleure application des règles.
D68: Adéquation du contenu des formations avec les responsabilités attribuées à chaque acteur. | E68: Le contenu des formations est-il adapté aux responsabilités attribuées à chaque acteur ? | F68: oui | G68: Grille d’évaluation des compétences | H68: Méconnaissance des nouvelles menaces et vulnérabilités | I68: Moyenne | J68: Faiblesses de sécurité non détectées et non corrigées. Risque accru d'incidents de sécurité. | K68: Analyser les incidents passés pour améliorer les pratiques.
E69: . | F69: . | G69: Résultats des évaluations ou tests pratiques | J69: Non-amélioration des pratiques de sécurité et répétition des erreurs. Augmentation des coûts liés aux incidents. | K69: Encourager la participation via des programmes d’incitation.
D70: Évaluation régulière des compétences des acteurs de la sécurité. | E70: Une évaluation régulière des compétences des acteurs de la sécurité est-elle effectuée ? | F70: pas | G70: Liste des KPIs validés | H70: Formations inadaptées ou inefficaces, n'améliorant pas la posture de sécurité | I70: Elevée | J70: Manque de visibilité sur la performance de la sécurité. Difficulté à obtenir le soutien de la direction. | K70: Auditer l’accessibilité pour garantir la conformité aux normes.
E71: . | F71: . | G71: Document de définition des indicateurs | J71: Manque d'engagement de la direction envers la sécurité. Non-priorisation des initiatives de sécurité. | K71: Maintenir une veille active pour des informations à jour.
C72: Vérifier qu’un système de mesure complet est mis en place afin d'évaluer l'efficacité de la gestion de la sécurité de l'information et pour collecter les suggestions d'amélioration | D72: Définition d'indicateurs clés de performance (KPIs) pour la sécurité de l'information. | E72: Des indicateurs clés de performance (KPIs) pour la sécurité de l’information sont-ils définis ? | F72: non | G72: Rapports trimestriels de suivi des indicateurs | H72: Absence de suivi des indicateurs clés de performance (KPI) liés à la sécurité | I72: Faible | J72: Confusion sur les rôles et responsabilités. Difficulté à appliquer la politique de sécurité. | K72: Réviser les politiques pour les aligner sur les meilleures pratiques.
E73: . | F73: . | G73: Tableaux de bord issus d’un outil de BI ou Excel | J73: Manque de leadership et de coordination des efforts de sécurité. Inefficacité des mesures de sécurité. | K73: Renforcer le leadership avec des coordinateurs sécurité dédiés.
D74: Collecte et analyse documentées et régulières des KPIs de sécurité. | E74: La collecte et l’analyse documentées et régulières des KPIs de sécurité sont-elles en place ? | F74: oui | G74: Tableau de bord sécurité présenté en comité | H74: Absence de réalisation régulière des audits internes ou externes | I74: Elevée | J74: Non-respect des règles de sécurité et augmentation des risques. Difficulté à prouver la conformité. | K74: Documenter les écarts de conformité pour des audits externes.
E75: . | F75: . | G75: Procès-verbal de présentation à la Direction | J75: Difficulté à aligner les objectifs de sécurité avec les objectifs métier. Manque d'efficacité des mesures de sécurité. | K75: Aligner les objectifs de sécurité avec les priorités métier via des ateliers.
D76: Existence d'un tableau de bord de sécurité présenté périodiquement à la Direction. | E76: Un tableau de bord de sécurité est-il présenté périodiquement à la Direction ? | F76: non | G76: Procédure de traitement des suggestions internes | H76: Manque de mécanisme de retour d’expérience après des incidents de sécurité | I76: Moyenne | J76: Incompréhension et mauvaise application des règles de sécurité. Augmentation des risques d'incidents. | K76: Former les employés pour une meilleure application des règles.
E77: . | F77: . | G77: Registre ou outil de suivi des suggestions reçues | J77: Non-prise en compte des retours d'expérience et persistance des erreurs. Difficulté à améliorer la sécurité. | K77: Analyser les incidents passés pour améliorer les pratiques.
D78: Processus formalisé pour la collecte et le traitement des suggestions d'amélioration en matière de sécurité. | E78: Un processus formalisé pour la collecte et le traitement des suggestions d’amélioration en matière de sécurité existe-t-il ? | F78: pas | G78: Rapport d’ajustement de stratégie | H78: Absence de rapport régulier sur la sécurité présenté à la direction | I78: Elevée | J78: Manque d'engagement et de participation des employés. Inefficacité des mesures de sécurité. | K78: Encourager la participation via des programmes d’incitation.
E79: . | F79: . | G79: Plan d’actions mis à jour suite aux mesures | J79: Exclusion et discrimination des personnes en situation de handicap. Non-conformité aux exigences d'accessibilité. | K79: Auditer l’accessibilité pour garantir la conformité aux normes.
D80: Utilisation démontrée des mesures pour ajuster la stratégie et les actions de sécurité. | E80: L’utilisation des mesures issues des suggestions pour ajuster la stratégie et les actions de sécurité est-elle démontrée ? | F80: non | G80: Plan de communication formel | H80: Absence de formalisation et validation de la politique de sécurité par la direction | I80: Faible | J80: Informations obsolètes et inadaptées aux menaces actuelles. Augmentation des risques. | K80: Maintenir une veille active pour des informations à jour.
E81: . | F81: . | G81: Note interne de validation de la stratégie de communication | J81: Politique de sécurité inadaptée et non conforme aux meilleures pratiques. Risque accru de vulnérabilités. | K81: Réviser les politiques pour les aligner sur les meilleures pratiques.
C82: S’assurer que la communication se fait à tous les utilisateurs sous une forme pertinente, accessible et compréhensible au lecteur | D82: Existence d’un plan de communication formalisé couvrant tous les utilisateurs. | E82: Un plan de communication formalisé couvrant tous les utilisateurs existe-t-il ? | F82: oui | G82: Captures des supports utilisés | H82: Responsabilités en matière de sécurité non clairement définies dans la politique | I82: Elevée | J82: Manque de coordination et de cohérence dans la revue de la politique. Décisions de sécurité non optimales. | K82: Mettre en place un comité de revue pour assurer la cohérence des politiques.
D83: . | E83: . | F83: . | G83: Comptes-rendus de réunions ou photos d’affichage | J83: Politique de sécurité inadaptée aux changements de l'environnement. Augmentation des risques. | K83: Adapter les politiques aux évolutions via des mises à jour régulières.
D84: Utilisation de supports variés adaptés aux profils des utilisateurs (email, intranet, réunions, affichages). | E84: Des supports variés adaptés aux profils des utilisateurs sont-ils utilisés (email, intranet, réunions, affichages) ? | F84: pas | G84: Exemples de communications (newsletter, guides simplifiés) | H84: Manque d’implication de la direction générale dans la gouvernance de la sécurité | I84: Moyenne | J84: Difficulté à suivre l'évolution de la politique et à justifier les modifications. Manque de transparence. | K84: Documenter les modifications des politiques avec un système de suivi.
D85: . | E85: . | F85: . | G85: Documents traduits ou en FALC (Facile À Lire et à Comprendre) | J85: Difficulté à restaurer des versions antérieures en cas de problème. Risque de perte d'informations importantes. | K85: Utiliser un outil de gestion des versions pour restaurer les politiques si besoin.
D86: Langage clair, sans jargon technique, et adapté aux différents niveaux de compétence. | E86: Le langage utilisé dans les communications est-il clair, sans jargon technique, et adapté aux différents niveaux de compétence ? | F86: oui | G86: Résultats d’enquêtes de satisfaction | H86: Non-diffusion ou non-affichage de la politique de sécurité aux parties prenantes | I86: Elevée | J86: Difficulté à identifier et à protéger tous les actifs. Risque accru de compromission des données. | K86: Inventorier tous les actifs avec un outil de gestion des configurations.
D87: . | E87: . | F87: . | G87: Synthèse des retours utilisateurs | J87: Lacunes de sécurité pour les nouveaux dispositifs et technologies. Augmentation de la surface d'attaque. | K87: Évaluer la sécurité des nouveaux dispositifs avant leur déploiement.
D88: Mesure régulière de la compréhension via enquêtes ou retours utilisateurs. | E88: Une mesure régulière de la compréhension via enquêtes ou retours utilisateurs est-elle réalisée ? | F88: non | G88: Documentation mentionnant les adaptations (langue, accessibilité) | H88: Politique de sécurité non intégrée dans la stratégie globale de l’organisation | I88: Faible | J88: Vulnérabilités non détectées dans certains systèmes. Risque accru d'incidents de sécurité. | K88: Effectuer des scans réguliers pour détecter les vulnérabilités système.
D89: . | E89: . | F89: . | G89: Audit d’accessibilité ou conformité RGAA | J89: Exposition accrue aux risques dans les domaines exclus | K89: Élargir l’analyse des risques pour inclure tous les domaines.
D90: Accessibilité des communications (ex : prise en compte des handicaps, traduction si nécessaire). | E90: Les communications sont-elles accessibles (prise en compte des handicaps, traduction si nécessaire) ? | F90: pas | G90: Planning annuel ou semestriel des revues | H90: Absence de supports de sensibilisation et de formation adaptés aux différents utilisateurs | I90: Elevée | J90: Exploitation des vulnérabilités des systèmes non traditionnels. | K90: Auditer les systèmes non traditionnels pour identifier les failles.
F91: . | G91: Agenda partagé ou feuille de route | J91: Non-conformité et sanctions potentielles. | K91: Réaliser un audit de conformité pour éviter les sanctions.
C92: S’assurer qu’une revue régulière de la politique est réalisée afin de vérifier son adéquation avec | D92: Existence d’un calendrier formel de revue périodique de la politique de sécurité. | E92: Existe-t-il un calendrier documenté et suivi pour la revue périodique de la politique de sécurité ? | F92: oui | G92: Invitations aux parties prenantes | H92: Utilisation de canaux de communication inappropriés pour la diffusion des retours d’expérience | I92: Moyenne | J92: Fuites d’informations sensibles | K92: Chiffrer les données sensibles pour prévenir les fuites.
D93: . | E93: . | F93: . | G93: Comptes-rendus de réunion de revue | J93: Mauvaise compréhension des leçons apprises | K93: Capitaliser sur les retours d’expérience via des ateliers post-incident.
D94: Implication des parties prenantes clés (direction, IT, utilisateurs) dans la revue. | E94: Les parties prenantes clés (direction, IT, utilisateurs) sont-elles activement impliquées dans le processus de revue de la politique de sécurité ? | F94: non | G94: Analyse d’écarts (gap analysis) | H94: Absence de mécanismes de retour d’information pour mesurer l’assimilation des supports de sécurité | I94: Elevée | J94: Non-respect des consignes de sécurité | K94: Communiquer clairement les consignes de sécurité à tous les niveaux.
D95: . | E95: . | F95: . | G95: Rapport comparatif entre exigences et politique | J95: Faiblesse dans l’application des mesures | K95: Renforcer l’application des mesures par des contrôles réguliers.
D96: Analyse des écarts entre la politique actuelle et les exigences réglementaires ou opérationnelles. | E96: Une analyse des écarts entre la politique de sécurité actuelle et les exigences réglementaires ou opérationnelles est-elle réalisée et documentée ? | F96: pas | G96: Document de synthèse de la revue | H96: Supports de sécurité non accessibles aux personnes en situation de handicap | I96: Faible | J96: Exclusion des utilisateurs concernés | K96: Inclure les utilisateurs concernés dans la conception des mesures.
D97: . | E97: . | F97: . | G97: Plan d’actions suite à la revue | J97: Non-conformité aux obligations d’accessibilité | K97: Mettre en place des formations sur l’accessibilité pour assurer la conformité.
D98: Documentation des résultats et plan d’actions correctives. | E98: Les résultats des revues sont-ils documentés avec un plan d’actions correctives clairement défini ? | F98: non | G98: Email de notification des mises à jour | H98: Supports de sécurité non mis à jour régulièrement | I98: Elevée | J98: Exposition à des menaces émergentes | K98: Surveiller les menaces émergentes via une veille proactive.
D99: . | E99: . | F99: . | G99: Document d’accompagnement des modifications | J99: Obsolescence des consignes de sécurité | K99: Mettre à jour les consignes pour refléter les nouveaux risques.
D100: Communication des mises à jour aux utilisateurs concernés. | E100: Les mises à jour de la politique de sécurité sont-elles communiquées de manière claire et systématique aux utilisateurs concernés ? | F100: oui | G100: Email ou note interne annonçant les mises à jour | H100: Absence de calendrier annuel de révision de la politique de sécurité | I100: Moyenne | J100: Politiques inadaptées aux nouveaux risques | K100: Réviser les politiques pour intégrer les évolutions du contexte.
...

Sheet Ref_COSO
A1: Domaines | B1: Points de Contrôle | C1: Objectifs de Contrôle | D1: Critères d’Évaluation | E1: Questions d'évaluation | F1: Reponses | G1: Documents Requis | H1: Risques | I1: Criticité | J1: Conséquences | K1: Recommandations
A2: Environnement de Contrôle | B2: Engagement envers l’intégrité et les valeurs éthiques | C2: S’assurer que l'organisation dispose d'une charte éthique formelle qui couvre l'ensemble des pratiques professionnelles et des interactions au sein de l'organisation, y compris les activités liées aux systèmes d'information | D2: La charte existe et couvre tous les aspects des interactions professionnelles et des systèmes d'information | E2: Existe-t-il une charte couvrant tous les aspects des interactions professionnelles et des systèmes d'information? | F2: OUI | G2: Charte éthique et de bonne conduite | H2: Non-respect des principes éthiques par manque de sensibilisation. | I2: Elevée | J2: Manque d’implication des employés dans l’éthique de l’entreprise. | K2: Renforcer la sensibilisation et l’engagement des employés à l’éthique de l’entreprise
G3: Politique d’utilisation des systèmes d’information | H3: Usage inapproprié des outils informatiques. | I3: Elevée | J3: Augmentation des risques de fraude et de cybersécurité. | K3: Mettre en place des contrôles renforcés pour limiter les fraudes et améliorer la cybersécurité
D4: La charte éthique est officiellement validée et mise à disposition de tous les employés | E4: La charte éthique est-elle officiellement validée et mise à disposition de tous les employés? | F4: OUI | G4: Charte éthique et de bonne conduite | H4: Absence de traçabilité des validations, | I4: Elevée | J4: Remise en cause de la légitimité de la charte éthique. | K4: Communiquer régulièrement sur la charte éthique et impliquer les employés dans son élaboration
G5: Procès-verbal de validation de la charte éthique | H5: Non-prise en compte des mises à jour réglementaires, . | I5: Faible | J5: Non-conformité aux réglementations et aux normes internes. | K5: Effectuer des audits de conformité réguliers et assurer une veille réglementaire
D6: La charte éthique est mise à jour régulièrement en fonction des évolutions réglementaires et organisationnelle | E6: La charte éthique est-elle mise à jour régulièrement en fonction des évolutions réglementaires et organisationnelle? | F6: NON | G6: Plan de mise à jour des documents internes | H6: Confusion entre les différentes versions, | I6: Moyenne | J6: Confusion dans l’application des règles éthiques. | K6: Clarifier les règles éthiques à travers des guides pratiques et des formations adaptées
G7: Historique des versions de la charte éthique | H7: Non-preuve d’adhésion aux règles éthiques en cas de litige. | I7: Elevée | J7: Impossibilité de prouver l’adhésion aux principes éthiques. | K7: Instaurer un système de documentation pour prouver l’adhésion aux principes éthiques
D8: Les employés signent un engagement attestant qu'ils ont lu et compris la charte éthique | E8: Les employés signent-ils un engagement attestant qu'ils ont lu et compris la charte éthique? | F8: OUI | G8: Registre des engagements signés par les employés | H8: Falsification des signatures ou absence d’engagement formel. | I8: Elevée | J8: Risque juridique en cas de litige sur l’engagement éthique. | K8: S’assurer de la traçabilité des engagements éthiques pour limiter les risques juridiques
G9: Formulaire d’adhésion aux règles éthiques | H9: Manque de clarté sur les missions du comité,. | I9: Elevée | J9: Inefficacité du comité d’éthique et perte de crédibilité. | K9: Définir des rôles clairs et assurer l’indépendance du comité d’éthique
D10: Un comité d'éthique est chargé de l'application des termes de son application et de son amélioration continue | E10: Existe-t-il un comité d'éthique chargé de l'application des termes de son application et de son amélioration continue? | F10: NON | G10: Charte de gouvernance du comité d’éthique | H10: Omission d’incidents éthiques | I10: Elevée | J10: Vision faussée de l’état de l’éthique dans l’entreprise. | K10: Réaliser des enquêtes internes pour évaluer la perception de l’éthique dans l’entreprise
G11: Rapport annuel du comité d’éthique | H11: Couverture insuffisante des risques éthiques | I11: Elevée | J11: Risques de fraudes non détectés à temps. | K11: Déployer des outils de détection précoce des fraudes et renforcer les contrôles internes
C12: Vérifier que des mécanismes existent pour garantir que tous les acteurs (employés, partenaires, prestataires) respectent cette charte éthique dans leurs activités professionnelles, y compris dans leur utilisation des systèmes d'information | D12: Des contrôles réguliers sont effectués pour vérifier le respect des règles éthiques | E12: Des contrôles réguliers sont-ils effectués pour vérifier le respect des règles éthiques? | F12: OUI | G12: Plan d’audit éthique | H12: Manipulation des résultats | I12: Elevée | J12: Absence d’amélioration des pratiques éthiques. | K12: Évaluer et ajuster périodiquement les pratiques éthiques de l’entreprise
G13: Rapports d’audit interne sur l’éthique | H13: Sanctions inappropriées, | I13: Elevée | J13: Climat de travail détérioré et tensions internes. | K13: Mettre en place un dispositif de médiation et encourager le dialogue interne
D14: Un processus de sanction est défini et appliqué en cas de non-respect des règles | E14: Un processus de sanction est-il défini et appliqué en cas de non-respect des règles? | F14: OUI | G14: Règlement disciplinaire | H14: Violation de la confidentialité des données des employés sanctionnés. | I14: Elevée | J14: Problèmes de confidentialité et de conformité juridique. | K14: Garantir la protection des données et la conformité aux réglementations en vigueur
G15: Registre des sanctions disciplinaires | H15: Conflits d’intérêts si les référents ne sont pas indépendants. | I15: Elevée | J15: Méconnaissance ou mauvaise interprétation des règles éthiques. | K15: Proposer des formations interactives pour éviter toute mauvaise interprétation des règles éthiques
D16: Les collaborateurs ont un référent éthique à qui poser leurs questions en cas de doute | E16: Les collaborateurs ont-ils un référent éthique à qui poser leurs questions en cas de doute ? | F16: OUI | G16: Charte éthique | H16: Indicateurs mal définis | I16: Elevée | J16: Absence de relais efficaces pour traiter les problématiques éthiques. | K16: Créer un réseau de référents éthiques pour mieux traiter les problématiques internes
G17: Liste des référents éthiques | H17: Rapports incomplets | I17: Faible | J17: Incapacité à mesurer l’évolution des pratiques éthiques. | K17: Développer des indicateurs de suivi pour mesurer l’évolution des pratiques éthiques
D18: Des indicateurs de performance mesurent l'application de la charte dans les activités courantes | E18: Des indicateurs de performance mesurent-ils l'application de la charte dans les activités courantes? | F18: OUI | G18: Tableau de bord des indicateurs éthiques | H18: Sensibilisation insuffisante aux valeurs éthiques dès l’arrivée. | I18: Moyenne | J18: Manque de crédibilité des audits internes. | K18: Améliorer la transparence et l’indépendance des audits internes
G19: Rapports d’audit interne sur l’éthique | H19: Contenu inadapté ou dépassé, | I19: Moyenne | J19: Faible culture éthique chez les nouveaux employés. | K19: Intégrer une formation éthique obligatoire pour les nouveaux employés
D20: Les nouvelles recrues reçoivent une formation spécifique sur la charte éthique | E20: Les nouvelles recrues reçoivent-ils une formation spécifique sur la charte éthique ? | F20: OUI | G20: Programme d’intégration des nouvelles recrues | H20: Inégalités dans l’accès à la formation, | I20: Moyenne | J20: Formation inefficace, ne répondant pas aux attentes. | K20: Adapter les formations aux enjeux réels rencontrés par les employés
G21: Matériel de formation sur l’éthique | H21: Non-respect des échéances, | I21: Elevée | J21: Employés insuffisamment formés aux questions éthiques. | K21: Augmenter la fréquence et la qualité des formations éthiques
C22: S’assurer que des actions de sensibilisation, telles que des formations régulières, sont mises en place pour garantir que tous les employés et intervenants comprennent et appliquent les principes éthiques dans leurs interactions avec les systèmes d'information | D22: Un programme de formation éthique est défini avec une fréquence obligatoire | E22: Un programme de formation éthique est-il défini avec une fréquence obligatoire? | F22: NON | G22: Plan de formation éthique | H22: Absence de suivi des employés formés et non formés. | I22: Elevée | J22: Désengagement des employés face aux formations. | K22: Rendre les formations plus engageantes et adaptées aux attentes des employés
G23: Calendrier des sessions de formation | H23: Falsification ou non-reconnaissance officielle des certifications. | I23: Elevée | J23: Absence de suivi sur l’évolution des compétences éthiques. | K23: Mettre en place un suivi régulier de l’évolution des compétences éthiques
D24: Tous les employés suivent une session de formation annuelle sur l'éthique | E24: Tous les employés suivent-ils une session de formation annuelle sur l'éthique? | F24: NON | G24: Registre des participants aux formations | H24: Scénarios non représentatifs des défis éthiques réels. | I24: Elevée | J24: Détournement ou falsification des certificats de formation. | K24: Renforcer la sécurité et l’authenticité des certificats de formation
G25: Certificats de formation des employés | H25: Exemples obsolètes, | I25: Elevée | J25: Détournement ou falsification des certificats de formation. | K25: Sensibiliser les employés à la gestion des dilemmes éthiques à travers des cas pratiques
D26: Des mises en situation et études de cas pour illustrer les principes éthiques | E26: Y a-t'il des mises en situation et études de cas pour illustrer les principes éthiques ? | F26: OUI | G26: Supports pédagogiques des mises en situation | H26: Réponses biaisées | I26: Elevée | J26: Manque de préparation aux dilemmes éthiques réels. | K26: Organiser des mises en situation pour améliorer la compréhension des enjeux éthiques
G27: Études de cas utilisées en formation | H27: Mauvaise interprétation des performances des employés formés. | I27: Elevée | J27: Mauvaise compréhension des enjeux éthiques dans les situations concrètes. | K27: Établir des indicateurs objectifs pour évaluer l’impact réel des formations
D28: Les sessions incluent des tests d'évaluation pour mesurer la compréhension des employés | E28: Les sessions incluent-elles des tests d'évaluation pour mesurer la compréhension des employés? | F28: OUI | G28: Questionnaires d’évaluation post-formation | H28: Discrimination si l’accès à la formation est inégalement réparti. | I28: Elevée | J28: Évaluation biaisée de l’impact de la formation. | K28: Clarifier les critères d’évaluation et assurer la transparence des résultats
G29: Rapports d’analyse des résultats des tests | H29: Non-conformité en cas d’absence de contrôle strict des formations suivies. | I29: Elevée | J29: Mauvaise interprétation des résultats d’évaluation. | K29: Garantir une égalité de formation pour éviter les injustices perçues
D30: Un suivi des formations est réalisé pour identifier les personnes non formées | E30: Un suivi des formations est-il réalisé pour identifier les personnes non formées? | F30: OUI | G30: Liste des employés formés et non formés | H30: Faible utilisation en raison de la peur des représailles. | I30: Elevée | J30: Injustice perçue entre employés formés et non formés. | K30: Instaurer un contrôle strict du respect des obligations de formation éthique
G31: Rapport de suivi des formations obligatoires | H31: . Incompréhension des procédures, | I31: Elevée | J31: Manque de conformité aux exigences de formation obligatoire. | K31: Encourager activement le signalement des infractions en garantissant l’anonymat
C32: S’assurer que l'organisation dispose d'un mécanisme de suivi et de gestion des violations éthiques, permettant de détecter, traiter et sanctionner tout comportement contraire à la charte éthique, y compris dans le cadre des activités liées aux systèmes d'information | D32: Un processus clair est défini pour signalé pour traiter les violations éthiques | E32: Un processus clair est-il défini pour signaler et pour traiter les violations éthiques ? | F32: OUI | G32: Procédure de signalement des violations éthiques | H32: Gouvernance mal définie, | I32: Elevée | J32: Faible taux de signalement des infractions éthiques. | K32: Former les employés aux protocoles de signalement pour éviter les abus
G33: Guide des bonnes pratiques en matière de signalement | H33: Informations incomplètes ou occultées, | I33: Elevée | J33: Non-respect des protocoles de signalement, entraînant des abus. | K33: Structurer et renforcer le rôle du comité d’éthique pour améliorer sa prise de décision
D34: Un comité d'éthique analyse toutes infractions signalées | E34: Existe-t-il un comité d'éthique analysant toutes infractions signalées ? | F34: OUI | G34: Charte du comité d’éthique | H34: Application inégale des sanctions, nuisant à la cohérence disciplinaire. | I34: Elevée | J34: Dysfonctionnement du comité d’éthique et décisions inefficaces. | K34: Mettre en place un processus clair et coordonné pour le traitement des cas éthiques
G35: Rapports des réunions du comité d’éthique | H35: Sous-déclaration des incidents, | I35: Elevée | J35: Manque de coordination dans le traitement des cas éthiques. | K35: Appliquer des sanctions proportionnées pour dissuader les comportements non éthiques
D36: Des sanctions cohérentes et proportionées sont appliquées aux contrevenants | E36: Des sanctions cohérentes et proportionées sont-elles appliquées aux contrevenants? | F36: OUI | G36: Registre des sanctions disciplinaires | H36: Mesures inefficaces ou non appliquées, | I36: Elevée | J36: Sentiment d’impunité favorisant les comportements non éthiques. | K36: Clarifier les processus de gestion des infractions et assurer un suivi efficace
G37: Politique de gestion des infractions éthiques | H37: Manque d’engagement des employés si les actions correctives sont mal suivies. | I37: Elevée | J37: Flou dans la gestion des infractions, réduisant l’efficacité des sanctions. | K37: Suivre les infractions de manière stricte pour éviter les récidives
D38: Un rapport annuel sur les violations et actions correctives est disponible | E38: Un rapport annuel sur les violations et actions correctives estil disponible ? | F38: PAS | G38: Rapport annuel sur les infractions éthiques | H38: Absence de communication efficace sur les infractions et mesures préventives. | I38: Moyenne | J38: Récidive des infractions et manque d’amélioration des pratiques. | K38: Réviser régulièrement le plan d’action pour s’assurer de son efficacité
G39: Plan d’action correctif des violations éthiques | H39: Faible participation des employés, | I39: Moyenne | J39: Plan d’action inefficace, laissant persister les problèmes. | K39: Renforcer la sensibilisation à travers des campagnes interactives
D40: Des mesures de prévention sont mises en place pour éviter la récurrence des infractions | E40: Des mesures de prévention sont-elles mises en place pour éviter la récurrence des infractions? | F40: OUI | G40: Programme de sensibilisation à la prévention des infractions | H40: Obsolescence du programme si les actions de sensibilisation ne sont pas renouvelées. | I40: Moyenne | J40: Sensibilisation insuffisante, augmentant les infractions. | K40: Mettre en place un cadre strict pour la détection et la prévention des fraudes
G41: Rapports d’analyse des tendances des infractions | H41: Manque d’anticipation des tendances des infractions | I41: Moyenne | J41: Augmentation du risque de fraudes et d’infractions | K41: Protéger et encourager les lanceurs d’alerte pour garantir un meilleur signalement
C42: Vérifier que des procédures existent pour signaler anonymement et en toute sécurité les violations des principes éthiques. | D42: Un canal de signalement anonyme est disponible | E42: Un canal de signalement anonyme est-il disponible ? | F42: OUI | G42: Procédure de gestion des signalements anonymes | H42: Anonymat des lanceurs d’alerte mal protégé | I42: Moyenne | J42: Réduction du nombre de signalements par crainte de représailles | K42: Favoriser la communication transparente sur les signalements et leurs traitements
G43: Documentation du canal de signalement | H43: Canaux de signalement inaccessibles ou non sécurisés | I43: Moyenne | J43: Perte de confiance des employés et parties prenantes | K43: Créer un environnement de travail qui encourage la prévention des fraudes
D44: Le signalements sont analysés rapidement , avec des délais définis pour chaque étape | E44: Le signalements sont-ils analysés rapidement , avec des délais définis pour chaque étape? | F44: NON | G44: Rapport de suivi des délais de traitement des signalements | H44: Retards excessifs dans le traitement des signalements | I44: Faible | J44: Sanctions réglementaires pour non-respect des délais de traitement | K44: Améliorer la traçabilité des signalements et garantir un suivi efficace
G45: Plan d’amélioration continue du processus de signalement | H45: Processus de signalement rigide et peu évolutif | I45: Faible | J45: Inefficacité du système de signalement face aux nouvelles menaces | K45: Sanctionner les délais non respectés pour le traitement des signalements
D46: Le système garantit la confidentialité et l'absence des représailles pour les lanceurs d'alertes | E46: Le système garantit-il la confidentialité et l'absence des représailles pour les lanceurs d'alertes? | F46: OUI | G46: Charte de protection des lanceurs d’alerte | H46: Protection des lanceurs d’alerte insuffisante | I46: Faible | J46: Dissuasion des lanceurs d’alerte et faible détection des fraudes | K46: Intégrer une plateforme numérique pour faciliter le suivi des infractions éthiques
G47: Rapport d’analyse des signalements et mesures prises | H47: Mesures insuffisantes suite aux signalements analysés | I47: Faible | J47: Récidive des infractions faute de mesures correctives adaptées | K47: Former régulièrement les équipes en charge du traitement des signalements
D48: Les employés sont informés de l'existence du canal de signalement | E48: Les employés sont-ils informés de l'existence du canal de signalement? | F48: OUI | G48: Documentation des canaux de communication interne | H48: Canaux de communication interne inefficaces | I48: Elevée | J48: Manque de circulation de l’information sur les signalements | K48: Rendre les procédures d’alerte plus accessibles et compréhensibles
G49: Supports de sensibilisation sur le signalement | H49: Faible sensibilisation au signalement des infractions | I49: Elevée | J49: Faible implication des employés dans la prévention des fraudes | K49: Encourager la remontée d’informations par des incitations positives
D50: Chaque signalement est traité de manière impartiale | E50: Chaque signalement est-il traité de manière impartiale? | F50: OUI | G50: Registre des signalements et décisions associées | H50: Traçabilité défaillante des signalements et décisions | I50: Elevée | J50: Perte de données et difficulté à suivre les signalements | K50: Mettre en place des contrôles croisés pour éviter les conflits d’intérêts
G51: Procédure de traitement des signalements | H51: Procédure de traitement des signalements mal définie | I51: Elevée | J51: Traitement arbitraire des signalements sans cadre défini | K51: Établir une procédure claire et documentée pour le traitement des signalements.
B52: Le Conseil fait preuve d’indépendance vis-à-vis du management | C52: S’assurer que le Conseil est composé de membres indépendants du management, avec une structure de gouvernance claire garantissant cette indépendance | D52: La majorité des membres du conseil ne détient aucun poste opérationnel au sein de l'organisation | E52: La majorité des membres du conseil ne détient-elle aucun poste opérationnel au sein de l'organisation? | F52: NON | G52: Liste des membres du conseil et de leurs fonctions | H52: Manque de transparence sur la composition du conseil | I52: Elevée | J52: Suspicion de favoritisme ou de conflits d’intérêts | K52: Mettre en place un comité indépendant pour examiner les conflits d’intérêts et garantir l’équité.
G53: Statuts de l’organisation | H53: Statuts non conformes aux réglementations en vigueur | I53: Elevée | J53: Risques juridiques liés à la non-conformité des statuts | K53: Effectuer des contrôles réguliers pour assurer la conformité des statuts aux réglementations en vigueur.
D54: La sélection des membres du Conseil se fait par un comité indépendant | E54: La sélection des membres du Conseil se fait-elle par un comité indépendant? | F54: NON | G54: Procédure de nomination des membres du conseil | H54: Processus de nomination des membres du conseil biaisé | I54: Elevée | J54: Désignation de membres incompétents ou influencés | K54: Définir des critères de sélection objectifs et transparents pour les membres du conseil.
G55: Rapport d’activité du comité de sélection | H55: Sélection des membres du conseil non documentée | I55: Elevée | J55: Manque de légitimité du processus de sélection du conseil | K55: Rendre public le processus de sélection des membres du conseil et assurer son impartialité.
D56: Les membres du Conseil signent une déclaration annuelle d'indépendance | E56: Les membres du Conseil signent-ils une déclaration annuelle d'indépendance? | F56: NON | G56: Déclarations annuelles d’indépendance signées | H56: Conflits d’intérêts non détectés | I56: Elevée | J56: Décisions biaisées par des intérêts personnels | K56: Élaborer un cadre éthique rigoureux pour éviter toute influence indue dans la prise de décision.
