Workbook

Sheet Synthèse
B3: Synthèse Numérique
B5: N° | C5: Domaines | D5: Total OUI | E5: Total NON | F5: Total PAS | G5: Total | H5: Score
B6: 1 | C6: Application en service | D6: =COUNTIF('4.1'!F2:F151, "oui") -> 100 | E6: =COUNTIF('4.1'!F2:F151, "non") -> 18 | F6: =COUNTIF('4.1'!F2:F151, "pas") -> 32 | G6: =SUM(D6:F6) -> 150 | H6: =D6/G6 -> 0.66666667
B7: 2 | C7: Fonction informatique | D7: =COUNTIF('4.2'!F2:F206, "oui") -> 124 | E7: =COUNTIF('4.2'!F2:F206, "non") -> 81 | F7: =COUNTIF('4.2'!F2:F206, "pas") -> 0 | G7: =SUM(D7:F7) -> 205 | H7: =D7/G7 -> 0.60487805
B8: 3 | C8: Contrôle des projets informatique | D8: =COUNTIF('4.3'!F2:F2951, "oui") -> 2515 | E8: =COUNTIF('4.3'!F2:F2951, "non") -> 154 | F8: =COUNTIF('4.3'!F2:F2951, "pas") -> 281 | G8: =SUM(D8:F8) -> 2950 | H8: =D8/G8 -> 0.85254237
B9: 4 | C9: Support utilisateur et de la gestion du parc | D9: =COUNTIF('4.4'!F2:F461, "OUI") -> 234 | E9: =COUNTIF('4.4'!F2:F461, "NON") -> 225 | F9: =COUNTIF('4.4'!F2:F461, "PAS") -> 0 | G9: =SUM(D9:F9) -> 459 | H9: =D9/G9 -> 0.50980392
B10: 5 | C10: Audit de la sécurité informatique | D10: =COUNTIF('4.5'!F2:F701, "oui") -> 375 | E10: =COUNTIF('4.5'!F2:F701, "non") -> 18 | F10: =COUNTIF('4.5'!F2:F701, "pas") -> 32 | G10: =SUM(D10:F10) -> 425 | H10: =D10/G10 -> 0.88235294
B11: Total | D11: =SUM(D6:D10) -> 3348 | E11: =SUM(E6:E10) -> 496 | F11: =SUM(F6:F10) -> 345 | G11: =SUM(D11:F11) -> 4189 | H11: =D11/G11 -> 0.79923609
B13: Sythèse Graphique

Sheet Global
A2: Domaine | B2: Points de Contrôle | C2: Objectifs de Contrôle | D2: Critère d’Évaluation | E2: Question d’Évaluation | F2: Réponses | G2: Documents Requis | H2: Risques | I2: Criticités | J2: Conséquences | K2: Recommandations
A3: Application en service | B3: Organisation | C3: S’assurer de l’existence d'un comité informatique | D3: Existence d'un comité informatique | E3: Existe-t-il un comité informatique ? | F3: oui | G3: Charte du comité informatique, liste des membres, procès-verbaux des réunions | H3: Absence de gouvernance claire | I3: Élevé | J3: Décisions incohérentes et manque de coordination | K3: Mettre en place un comité de gouvernance structuré
D4: Le Comité est présidé par le Directeur Général | E4: Le comité est-il présidé par le Directeur Général ? | F4: oui | G4: Document de nomination du Directeur Général, procès-verbaux des réunions | H4: Manque de leadership dans la prise de décisions stratégiques | I4: Élevé | J4: Retards et décisions inefficaces | K4: Nommer un leader compétent avec des pouvoirs clairs
D5: Les directions utilisatrices sont représentées au sein de ce Comité | E5: Les directions utilisatrices sont-elles représentées au sein du comité ? | F5: oui | G5: Liste des membres du comité, organigramme | H5: Mauvaise représentation des parties prenantes | I5: Élevé | J5: Conflits d'intérêts et mauvaise acceptation des décisions | K5: Garantir l’inclusion des parties prenantes critiques
D6: Les directions utilisatrices sont influentes au sein de ce Comité | E6: Les directions utilisatrices sont-elles influentes au sein du comité ? | F6: non | G6: Comptes rendus des réunions, décisions prises incluant les contributions des directions utilisatrices | H6: Négligence des apports des directions utilisatrices | I6: Élevé | J6: Solutions non adaptées aux besoins réels | K6: Renforcer la collaboration avec les utilisateurs finaux
D7: Présence de membres qualifiés et diversifiés | E7: Les membres du comité sont-ils qualifiés et diversifiés ? | F7: oui | G7: Profils des membres, CV, évaluation des compétences | H7: Compétences inadéquates des membres du comité | I7: Élevé | J7: Erreurs stratégiques et décisions inefficaces | K7: Former ou remplacer les membres avec des experts qualifiés
C8: S’assurer de l’existence d'une politique relative aux applications | D8: Il existe une politique relative aux applications au sein de l'institution | E8: Une politique relative aux applications existe-t-elle au sein de l'institution ? | F8: oui | G8: Politique des applications, document de gouvernance | H8: Non-existence ou non-application de la politique. | I8: Élevé | J8: Désorganisation et manque de cadre | K8: Élaborer et appliquer une politique claire et documentée
D9: La politique est connue des utilisateurs d'applications | E9: Les utilisateurs d'applications connaissent-ils cette politique ? | F9: oui | G9: Rapport de sensibilisation ou de communication | H9: Méconnaissance des obligations des utilisateurs | I9: Élevé | J9: Non-respect des procédures et inefficacité | K9: Sensibiliser et former les utilisateurs sur leurs responsabilités
D10: La politique est largement diffusée | E10: La politique est-elle largement diffusée ? | F10: non | G10: Support de communication (emails, brochures, affiches) | H10: Faible diffusion des informations | I10: Moyen | J10: Manque de transparence et communication inefficace | K10: Utiliser des outils modernes de gestion des informations
D11: La politique est mise en œuvre | E11: La politique est-elle mise en œuvre ? | F11: pas | G11: Rapports d'audit de conformité | H11: Non-conformité aux normes | I11: Élevé | J11: Risques juridiques et pénalités | K11: Auditer et corriger les écarts avec les normes
D12: La politique couvre l'ensemble du cycle de vie de l’application | E12: La politique couvre-t-elle l'ensemble du cycle de vie de l'application ? | F12: pas | G12: Documentation de la politique, schéma de cycle de vie | H12: Gestion incohérente des étapes du cycle de vie des applications | I12: Élevé | J12: Dysfonctionnements fréquents | K12: Automatiser le suivi du cycle de vie des applications
C13: S’assurer que les rôle et responsabilités des utilisateurs sont bien définis | D13: Le rôle et les responsabilités des utilisateurs vis-à-vis de l’application sont clairement identifiés | E13: Les rôles et responsabilités des utilisateurs vis-à-vis de l'application sont-ils clairement identifiés ? | F13: oui | G13: Matrice des rôles et responsabilités, charte utilisateur | H13: Absence de définition claire des rôles | I13: Élevé | J13: Confusion et responsabilités non assumées | K13: Formaliser et communiquer les rôles clairement
D14: Le rôle et les responsabilités des utilisateurs vis-à-vis de l’application couvrent l’analyse des risques | E14: Les rôles et responsabilités des utilisateurs vis-à-vis de l'application couvrent-ils l'analyse des risques ? | F14: non | G14: Documentation d'analyse des risques, rapports spécifiques | H14: Non-réalisation des analyses des risques | I14: Élevé | J14: Survenue imprévisible de risques importants | K14: Planifier et réaliser des analyses régulières des risques
D15: Le rôle et les responsabilités des utilisateurs vis-à-vis de l’application couvrent la définition des besoins de sécurité | E15: Les rôles et responsabilités des utilisateurs vis-à-vis de l'application couvrent-ils la définition des besoins de sécurité ? | F15: non | G15: Expression des besoins de sécurité | H15: Non-définition des besoins de sécurité | I15: Élevé | J15: Failles exploitables par des acteurs malveillants | K15: Identifier et intégrer les exigences sécuritaires dès la conception
D16: Le rôle et les responsabilités des utilisateurs vis-à-vis de l’application couvrent la gestion des changements et des évolutions | E16: Les rôles et responsabilités des utilisateurs vis-à-vis de l'application couvrent-ils la gestion des changements et des évolutions ? | F16: non | G16: Processus de gestion des changements | H16: Changements mal gérés | I16: Élevé | J16: Instabilité du système | K16: Mettre en place un processus de gestion des changements standardisé
D17: Le rôle et les responsabilités des utilisateurs vis-à-vis de l’application couvrent l’administration de l’application | E17: Les rôles et responsabilités des utilisateurs vis-à-vis de l'application couvrent-ils l'administration de l'application ? | F17: non | G17: Procédure d'administration de l'application | H17: Administration non sécurisée | I17: Élevé | J17: Accès non autorisé et perte de données | K17: Renforcer les contrôles d’administration et les audits
C18: S’assurer qu’une analyse des risques a été réalisée | D18: Une analyse des risques spécifique à l'application a été réalisée | E18: Une analyse des risques spécifique à l'application a-t-elle été réalisée ? | F18: oui | G18: Rapport d'analyse des risques spécifiques | H18: Documentation insuffisante des risques critiques | I18: Moyen | J18: Problèmes non identifiés et résolus | K18: Compléter la documentation des risques prioritaires
D19: L'analyse des risques a débouché sur la définition des besoins de sécurité | E19: L'analyse des risques a-t-elle débouché sur la définition des besoins de sécurité ? | F19: oui | G19: Plan de sécurité, documentation des besoins de sécurité | H19: Non-prise en compte des besoins de sécurité | I19: Élevé | J19: Vulnérabilité accrue face aux cyberattaques | K19: Prioriser les mécanismes de sécurité dans les opérations
D20: Les résultats de l'analyse des risques sont documentés et approuvés | E20: Les résultats de l'analyse des risques sont-ils documentés et approuvés ? | F20: oui | G20: Rapports d'approbation, validation formelle des résultats | H20: Absence de validation formelle | I20: Élevé | J20: Détection tardive des erreurs | K20: Mettre en place des étapes de validation rigoureuses
D21: L'analyse des risques est mise à jour régulièrement | E21: L'analyse des risques est-elle mise à jour régulièrement ? | F21: oui | G21: Historique des mises à jour, calendrier des analyses | H21: Analyses de risques obsolètes | I21: Élevé | J21: Décisions basées sur des informations incorrectes | K21: Mettre à jour les analyses périodiquement
D22: Les risques identifiés sont pris en compte dans le plan d'action de sécurité | E22: Les risques identifiés sont-ils pris en compte dans le plan d'action de sécurité ? | F22: oui | G22: Plan d'action de sécurité, rapports d'intégration des risques | H22: Actions non mises en œuvre | I22: Élevé | J22: Maintien des risques identifiés | K22: Suivre et exécuter les plans d'action
C23: S’assurer que le prolongement de l'analyse de risque et de son expansion ont été réalisés | D23: Il y a eu un prolongement de l'analyse des risques et de l'expression des besoins de sécurité | E23: Le prolongement de l'analyse des risques et de l'expression des besoins de sécurité a-t-il eu lieu ? | F23: pas | G23: Contrat de service SLA, documentation de mise en œuvre | H23: Non-respect des SLA | I23: Élevé | J23: Insatisfaction et perte de clients | K23: Surveiller et respecter strictement les SLA établis
D24: Un contrat de service (SLA) entre l'informatique et la direction utilisatrice a été mis en œuvre | E24: Un contrat de service (SLA) entre l'informatique et la direction utilisatrice a-t-il été mis en œuvre ? | F24: pas | G24: Politique de contrôle d'accès, matrice des rôles | H24: Accès inappropriés | I24: Élevé | J24: Fuites ou abus de données sensibles | K24: Réévaluer et contrôler régulièrement les droits d'accès
D25: L'analyse des risques étendue couvre tous les aspects de l'application | E25: L'analyse des risques étendue couvre-t-elle tous les aspects de l'application ? | F25: oui | G25: Journal des droits d'accès, rapports d'audit | H25: Absence de journalisation | I25: Élevé | J25: Impossibilité de retracer les activités suspectes | K25: Implémenter un système de journalisation des événements
D26: Les résultats de l'analyse des risques étendue sont communiqués aux parties prenantes | E26: Les résultats de l'analyse des risques étendue sont-ils communiqués aux parties prenantes ? | F26: oui | G26: Journaux d'accès, rapports de surveillance | H26: Activités suspectes non détectées | I26: Élevé | J26: Survenue de failles de sécurité | K26: Utiliser des outils de surveillance et détection proactive
D27: L'analyse des risques étendue est utilisée pour la planification stratégique | E27: L'analyse des risques étendue est-elle utilisée pour la planification stratégique ? | F27: oui | G27: Procédure de révocation des accès | H27: Retard dans la révocation des accès | I27: Élevé | J27: Accès non autorisé prolongé | K27: Automatiser la gestion des accès pour une révocation rapide
B28: Application | C28: S'assurer que l'accès aux ressources de l'application (données et transactions) est restreint par un système de gestion d'accès | D28: Contrôle d'accès basé sur les rôles est mis en place | E28: Un contrôle d'accès basé sur les rôles est-il mis en place ? | F28: oui | G28: Spécifications techniques de l'authentification, rapports de mise en œuvre | H28: Faiblesse dans l’authentification | I28: Élevé | J28: Compromission des comptes et données sensibles | K28: Renforcer les mécanismes d'authentification
D29: Les droits d'accès sont attribués de manière appropriée | E29: Les droits d'accès sont-ils attribués de manière appropriée ? | F29: oui | G29: Politique de mots de passe, guides utilisateurs | H29: Mauvaises pratiques de mots de passe | I29: Élevé | J29: Vulnérabilité aux attaques par force brute | K29: Éduquer les utilisateurs sur les bonnes pratiques de gestion des mots de passe
D30: Les accès sont journalisés et surveillés | E30: Les accès sont-ils journalisés et surveillés ? | F30: oui | G30: Journaux des tentatives de connexion | H30: Tentatives suspectes non identifiées | I30: Élevé | J30: Intrusions non détectées | K30: Mettre en place des solutions de détection des anomalies
D31: Un processus est en place pour révoquer les accès | E31: Un processus est-il en place pour révoquer les accès ? | F31: pas | G31: Rapports d'incidents, base de données des suivis d'incidents | H31: Absence de suivi des incidents | I31: Élevé | J31: Problèmes récurrents non résolus | K31: Créer un processus clair de gestion des incidents
D32: Les accès sont audités régulièrement | E32: Les accès sont-ils audités régulièrement ? | F32: non | G32: Charte du comité informatique, liste des membres, procès-verbaux des réunions | H32: Absence de gouvernance claire | I32: Élevé | J32: Décisions incohérentes et manque de coordination | K32: Établir des structures de gouvernance précises et documentées
C33: S’assurer qu’une procédure de gestion des profils utilisateurs existe | D33: Procédure documentée pour la création, modification et suppression des profils | E33: Une procédure documentée pour la création, modification et suppression des profils existe-t-elle ? | F33: oui | G33: Document de nomination du Directeur Général, procès-verbaux des réunions | H33: Manque de leadership dans la prise de décisions stratégiques | I33: Élevé | J33: Retards et décisions inefficaces | K33: Nommer un responsable qualifié pour les décisions stratégiques
D34: Les droits d'accès sont attribués en fonction des rôles | E34: Les droits d'accès sont-ils attribués en fonction des rôles ? | F34: oui | G34: Liste des membres du comité, organigramme | H34: Mauvaise représentation des parties prenantes | I34: Moyen | J34: Conflits et résistance aux décisions prises | K34: Assurer une représentation équitable des parties prenantes
D35: Les profils sont révisés régulièrement | E35: Les profils sont-ils révisés régulièrement ? | F35: oui | G35: Comptes rendus des réunions, décisions prises incluant les contributions des directions utilisatrices | H35: Négligence des apports des directions utilisatrices | I35: Moyen | J35: Solutions inadaptées aux besoins réels | K35: Renforcer les échanges avec les directions utilisatrices
D36: La procédure est communiquée aux parties prenantes | E36: La procédure est-elle communiquée aux parties prenantes ? | F36: pas | G36: Profils des membres, CV, évaluation des compétences | H36: Compétences inadéquates des membres du comité | I36: Élevé | J36: Décisions inefficaces et erreurs majeures | K36: Organiser des formations ou ajuster la composition du comité
D37: Des outils d'automatisation sont utilisés pour la gestion des profils | E37: Des outils d'automatisation sont-ils utilisés pour la gestion des profils ? | F37: pas | G37: Politique des applications, document de gouvernance | H37: Non-existence ou non-application de la politique | I37: Élevé | J37: Désorganisation opérationnelle | K37: Créer et appliquer une politique claire et standardisée
C38: Vérifier que l’identification des utilisateurs est réalisée | D38: Mécanismes d'identification uniques sont utilisés | E38: Des mécanismes d'identification uniques sont-ils utilisés ? | F38: oui | G38: Rapport de sensibilisation ou de communication | H38: Méconnaissance des obligations des utilisateurs | I38: Moyen | J38: Utilisation incorrecte des applications | K38: Former les utilisateurs sur leurs responsabilités
D39: Authentification forte est mise en place | E39: Une authentification forte est-elle mise en place ? | F39: oui | G39: Support de communication (emails, brochures, affiches) | H39: Faible diffusion des informations | I39: Moyen | J39: Collaboration et coordination limitées | K39: Utiliser des outils modernes pour améliorer la communication
D40: Procédure de gestion des identifiants est claire | E40: La procédure de gestion des identifiants est-elle claire ? | F40: oui | G40: Rapports d'audit de conformité | H40: Non-conformité aux normes | I40: Élevé | J40: Risques juridiques et pertes financières | K40: Réaliser des audits réguliers pour garantir la conformité
D41: Les identifiants sont protégés | E41: Les identifiants sont-ils protégés ? | F41: oui | G41: Documentation de la politique, schéma de cycle de vie | H41: Gestion incohérente des étapes du cycle de vie des applications | I41: Élevé | J41: Dysfonctionnements et retards fréquents | K41: Automatiser le suivi des étapes clés du cycle de vie.
D42: Les identifiants sont audités régulièrement | E42: Les identifiants sont-ils audités régulièrement ? | F42: non | G42: Matrice des rôles et responsabilités, charte utilisateur | H42: Absence de définition claire des rôles | I42: Moyen | J42: Confusion et duplication des responsabilités | K42: Clarifier et documenter les rôles et responsabilités
C43: Vérifier qu’un mot de passe est associé à l'identifiant | D43: Politique de mots de passe est en place | E43: Une politique de mots de passe est-elle en place ? | F43: oui | G43: Documentation d'analyse des risques, rapports spécifiques | H43: Non-réalisation des analyses des risques | I43: Élevé | J43: Risques non identifiés pouvant entraîner des interruptions majeures | K43: Mettre en place une stratégie d'analyse des risques régulière
D44: Les mots de passe sont stockés de manière sécurisée | E44: Les mots de passe sont-ils stockés de manière sécurisée ? | F44: oui | G44: Expression des besoins de sécurité | H44: Non-définition des besoins de sécurité | I44: Élevé | J44: Failles exploitables entraînant des violations de données | K44: Identifier et documenter les besoins de sécurité dès la conception
D45: Procédure de gestion des mots de passe est claire | E45: La procédure de gestion des mots de passe est-elle claire ? | F45: pas | G45: Processus de gestion des changements | H45: Changements mal gérés | I45: Élevé | J45: Instabilité opérationnelle et pannes récurrentes | K45: Adopter un processus de gestion des changements standardisé
D46: Les utilisateurs sont formés sur les bonnes pratiques de mots de passe | E46: Les utilisateurs sont-ils formés sur les bonnes pratiques de mots de passe ? | F46: oui | G46: Procédure d'administration de l'application | H46: Administration non sécurisée | I46: Élevé | J46: Accès non autorisé et compromission des données sensibles | K46: Renforcer les contrôles d'accès et sécuriser les outils d'administration
D47: Les mots de passe sont audités régulièrement | E47: Les mots de passe sont-ils audités régulièrement ? | F47: non | G47: Rapport d'analyse des risques spécifiques | H47: Documentation insuffisante des risques critiques | I47: Élevé | J47: Incapacité à prévoir et à atténuer les problèmes majeurs | K47: Compléter et maintenir à jour une documentation détaillée des risques critiques
C48: S’assurer que les tentatives de connexions infructueuses à l'application sont suivies | D48: Les tentatives de connexion sont journalisées | E48: Les tentatives de connexion sont-elles journalisées ? | F48: non | G48: Plan de sécurité, documentation des besoins de sécurité | H48: Non-prise en compte des besoins de sécurité | I48: Moyen | J48: Exploitation accrue par des acteurs malveillants | K48: Intégrer les besoins en sécurité dans toutes les étapes du projet
D49: Des alertes sont générées en cas d'activité suspecte | E49: Des alertes sont-elles générées en cas d'activité suspecte ? | F49: pas | G49: Rapports d'approbation, validation formelle des résultats | H49: Absence de validation formelle | I49: Moyen | J49: Erreurs non détectées et performance insuffisante | K49: Mettre en place des processus formalisés de validation et tests rigoureux
D50: Les journaux de connexion sont analysés régulièrement | E50: Les journaux de connexion sont-ils analysés régulièrement ? | F50: pas | G50: Historique des mises à jour, calendrier des analyses | H50: Analyses de risques obsolètes | I50: Moyen | J50: Décisions basées sur des informations périmées | K50: Réaliser des mises à jour périodiques des analyses de risques
D51: Les comptes sont bloqués en cas de tentatives répétées | E51: Les comptes sont-ils bloqués en cas de tentatives répétées ? | F51: oui | G51: Plan d'action de sécurité, rapports d'intégration des risques | H51: Actions non mises en œuvre. | I51: Élevé | J51: Risques identifiés persistant sans résolution | K51: Mettre en place un suivi rigoureux des plans d'actions recommandés
D52: Les incidents de sécurité sont documentés et suivis | E52: Les incidents de sécurité sont-ils documentés et suivis ? | F52: oui | G52: Contrat de service SLA, documentation de mise en œuvre | H52: Non-respect des SLA | I52: Élevé | J52: Insatisfaction des clients, perte de confiance et potentiels litiges | K52: Surveiller les SLA et établir des mécanismes de correction en cas de déviation
B53: Fonction informatique | C53: S’assurer que les tâches relatives au développement et à l'exploitation de l'application sont bien suivies et documentées | D53: Existence d'un plan de projet détaillé avec les tâches, les responsabilités et les échéances | E53: Existe-il un plan de projet detaillé avec les tâches, les responsabilités et les échéances? | F53: oui | G53: Plan de projet, diagramme de Gantt, feuille de route des tâches | H53: Mauvaise gestion des délais et des tâches | I53: Élevé | J53: Retards importants et baisse de productivité | K53: Mettre en place un planification stricte et un suivi des échéances
D54: Utilisation d'outils de suivi de projet pour gérer les tâches et les progrès | E54: Des outils de suivi de projet sont-ils utilisés pour gérer les tâches et les progrès ? | F54: oui | G54: Liste des outils de suivi (exemple : Jira, Trello), rapports de suivi | H54: Absence de suivi centralisé des progrès | I54: Élevé | J54: Difficulté à évaluer l'état d'avancement des projets | K54: Utiliser des outils de gestion centralisés tels que des tableaux de bord
D55: Documentation des activités de développement et d'exploitation (journal des modifications, rapports d'incidents... | E55: Les activités de développement et d'exploitation sont-elles documentées (journal des modifications, rapports d'incidents, etc.) ? | F55: oui | G55: Journal des modifications, rapport d’incidents, documentation des processus | H55: Manque de traçabilité | I55: Moyen | J55: Perte d'informations et incapacité à reproduire les étapes | K55: Implémenter des systèmes qui assurent une traçabilité complète
D56: Communication régulière entre les équipes de développement et d'exploitation | E56: Une communication régulière existe-t-elle entre les équipes de développement et d'exploitation ? | F56: pas | G56: Comptes rendus de réunions, rapports de communication inter-équipes | H56: Communication insuffisante entre équipes | I56: Élevé | J56: Risques de malentendus et travail en silo | K56: Favoriser des outils de collaboration et organiser des réunions régulières
D57: Validation des livrables et des jalons par les parties prenantes concernées | E57: Les livrables et jalons sont-ils validés par les parties prenantes concernées ? | F57: oui | G57: Rapport de validation des livrables, procès-verbaux de réunions | H57: Livrables non validés | I57: Moyen | J57: Qualité réduite et non-conformité aux attentes | K57: Mettre en œuvre un processus rigoureux de validation des livrables
C58: S’assurer que l'accès aux bibliothèques de production est réglementé | D58: Existence d'une procédure formelle pour gérer l'accès aux bibliothèques de production | E58: Existe-t-il une procédure formelle pour gérer l'accès aux bibliothèques de production ? | F58: non | G58: Documentation des procédures d’accès, matrice des rôles | H58: Mauvaise définition des accès | I58: Élevé | J58: Risques d’accès non autorisé ou accès excessif | K58: Réévaluer et clarifier les permissions d’accès
D59: Attribution des droits d'accès basée sur les rôles et les responsabilités | E59: Les droits d'accès sont-ils attribués en fonction des rôles et responsabilités ? | F59: oui | G59: Matrice des droits d’accès, charte des rôles | H59: Droits d'accès inappropriés | I59: Élevé | J59: Exploitation des systèmes et violations de sécurité | K59: Limiter les accès aux rôles nécessaires et effectuer des audits réguliers
D60: Journalisation des accès aux bibliothèques de production | E60: Les accès aux bibliothèques de production sont-ils journalisés ? | F60: pas | G60: Journaux d’accès, rapports d’audit des accès | H60: Absence de journalisation | I60: Moyen | J60: Impossible de retracer les incidents | K60: Activer et surveiller la journalisation dans les systèmes
D61: Révision régulière des droits d'accès | E61: Les droits d'accès sont-ils révisés régulièrement ? | F61: pas | G61: Historique des révisions, rapport de conformité | H61: Révisions non effectuées régulièrement | I61: Élevé | J61: Découverte tardive d’erreurs et risques accrus | K61: Mettre en place une politique de révision périodique
D62: Mise en place de contrôles pour prévenir les modifications non autorisées | E62: Des contrôles sont-ils mis en place pour prévenir les modifications non autorisées ? | F62: oui | G62: Documentation des contrôles, journal des modifications | H62: Changements non documentés | I62: Moyen | J62: Difficulté à comprendre l’historique des modifications | K62: Maintenir un registre de tous les changements effectués
C63: Vérifier que la maintenance de la séparation des tâches est effective | D63: Définition claire des rôles et des responsabilités pour les tâches sensibles | E63: Les rôles et responsabilités pour les tâches sensibles sont-ils clairement définis ? | F63: oui | G63: Description des rôles, charte des responsabilités | H63: Définitions floues des rôles | I63: Moyen | J63: Confusion et responsabilités non assumées | K63: Documenter et diffuser clairement les rôles attribués
D64: Implémentation de contrôles pour prévenir les conflits d'intérêts | E64: Des contrôles sont-ils implémentés pour prévenir les conflits d'intérêts ? | F64: oui | G64: Politique de contrôle des conflits, rapport de conformité | H64: Conflits d’intérêts mal gérés | I64: Élevé | J64: Décisions biaisées et manque de transparence | K64: Appliquer des politiques claires pour éviter les conflits d’intérêts
D65: Journalisation des activités des utilisateurs ayant des privilèges élevés | E65: Les activités des utilisateurs ayant des privilèges élevés sont-elles journalisées ? | F65: pas | G65: Journaux d’audit, rapports d’accès privilégié | H65: Absence de surveillance des utilisateurs privilégiés | I65: Élevé | J65: Exploitation non autorisée des privilèges | K65: Introduire une surveillance régulière des comptes privilégiés
D66: Révision régulière des rôles et des responsabilités | E66: Les rôles et responsabilités sont-ils révisés régulièrement ? | F66: non | G66: Rapports d’évaluation des rôles, documentation des mises à jour des responsabilités | H66: Rôles ou responsabilités obsolètes | I66: Moyen | J66: Inefficacité et duplication des efforts | K66: Réévaluer et adapter régulièrement les rôles et responsabilités
D67: Formation des utilisateurs sur l'importance de la séparation des tâches | E67: Les utilisateurs sont-ils formés sur l'importance de la séparation des tâches ? | F67: non | G67: Programme de formation, rapport de participation des utilisateurs | H67: Absence de formation des utilisateurs | I67: Moyen | J67: Mauvaise utilisation des systèmes | K67: Organiser des sessions de formation adaptées aux besoins
C68: S’assurer que l'équipe actuelle en charge de la maintenance est autonome et compétente | D68: Membres de l'équipe possédant les compétences techniques et fonctionnelles nécessaires | E68: Les membres de l'équipe possèdent-ils les compétences techniques et fonctionnelles nécessaires ? | F68: oui | G68: CV des membres, résultats d’évaluations des compétences | H68: Compétences insuffisantes | I68: Élevé | J68: Failles dans la gestion et erreurs fréquentes | K68: Identifier les besoins et fournir des formations ciblées
D69: Existence d'un plan de formation continue pour l'équipe de maintenance | E69: Un plan de formation continue pour l'équipe de maintenance existe-t-il ? | F69: pas | G69: Plan de formation continue, calendrier des sessions | H69: Manque de formation continue | I69: Moyen | J69: Obsolescence des compétences | K69: Instaurer un programme de développement continu des compétences
D70: Documentation des connaissances et des procédures de maintenance | E70: Les connaissances et procédures de maintenance sont-elles documentées ? | F70: oui | G70: Guides de maintenance, base de connaissances | H70: Documentation de maintenance insuffisante | I70: Élevé | J70: Retards et inefficacités dans la gestion de la maintenance | K70: Tenir une documentation complète et à jour pour chaque système
D71: Capacité de l'équipe à résoudre les problèmes et à répondre aux incidents | E71: L'équipe est-elle capable de résoudre les problèmes et de répondre aux incidents ? | F71: oui | G71: Rapport d’évaluation des performances, historique des incidents résolus | H71: Performances non évaluées | I71: Élevé | J71: Absence d’amélioration et maintien des inefficacités | K71: Mettre en place des processus d’évaluation régulière des performances
D72: Evaluation régulière des performances de l'équipe de maintenance | E72: Les performances de l'équipe de maintenance sont-elles évaluées régulièrement ? | F72: oui | G72: Rapports d’évaluation des performances | H72: Plan de maintenance inexistant ou mal appliqué | I72: Moyen | J72: Augmentation des pannes et dégradations | K72: Élaborer et mettre en œuvre un plan de maintenance détaillé
C73: S’assurer de l’existence de procédure formalisée et standard de maintenance de l’application | D73: Existence d'un plan de maintenance documenté | E73: Un plan de maintenance documenté existe-t-il ? | F73: pas | G73: Plan de maintenance, rapport de stratégie | H73: Activités mal planifiées ou non réalisées | I73: Élevé | J73: Délais non respectés et inefficience dans l’exécution | K73: Formaliser un plan détaillé et surveiller la réalisation des tâches
D74: Définition des activités de maintenance préventive et corrective | E74: Les activités de maintenance préventive et corrective sont-elles définies ? | F74: oui | G74: Liste des activités préventives/correctives, calendrier de maintenance | H74: Absence d'outils adaptés | I74: Élevé | J74: Inefficacité dans les opérations | K74: Investir dans des outils adaptés aux besoins et les intégrer efficacement
D75: Utilisation d'outils de gestion des incidents et des problèmes | E75: Des outils de gestion des incidents et des problèmes sont-ils utilisés ? | F75: oui | G75: Liste des outils de gestion (exemple : ServiceNow), rapports d’incidents | H75: Tests insuffisants ou inexistants | I75: Élevé | J75: Failles non détectées et dysfonctionnements fréquents | K75: Effectuer des tests rigoureux et réguliers pour garantir la qualité
D76: Mise en place de procédures de test et de validation des modifications | E76: Des procédures de test et de validation des modifications sont-elles mises en place ? | F76: oui | G76: Plan de tests, procédure de validation | H76: Changements non communiqués | I76: Moyen | J76: Confusion et interruption des processus | K76: Documenter et communiquer tous les changements aux parties concernées
D77: Communication des changements et des mises à jour aux utilisateurs | E77: Les changements et mises à jour sont-ils communiqués aux utilisateurs ? | F77: oui | G77: Rapports de communication des changements | H77: Schéma directeur obsolète ou mal aligné aux objectifs stratégiques | I77: Élevé | J77: Dysfonctionnement et inadéquation stratégique | K77: Mettre à jour et aligner le schéma directeur sur les objectifs
B78: Adéquation de l'application aux besoins | C78: Vérifier qu’un Schéma-directeur du système d’information existe et est à jour | D78: Existence d'un Schéma-directeur du système d'information (SDSI) documenté | E78: Un Schéma-directeur du système d'information (SDSI) documenté existe-t-il ? | F78: pas | G78: Schéma directeur documenté, plan stratégique IT | H78: Absence d'évaluation approfondie | I78: Élevé | J78: Risques non identifiés ou mal gérés | K78: Réaliser une évaluation complète et fréquente des risques
D79: Le SDSI couvre tous les aspects du système d'information | E79: Le SDSI couvre-t-il tous les aspects du système d'information ? | F79: pas | G79: Rapport d’évaluation du SDSI | H79: Stratégies mal alignées | I79: Élevé | J79: Décisions inefficaces et déviation des objectifs | K79: Alignement stratégique avec les objectifs organisationnels
D80: Le SDSI est aligné sur la stratégie de l'entreprise | E80: Le SDSI est-il aligné sur la stratégie de l'entreprise ? | F80: pas | G80: Documentation de l’alignement stratégique | H80: Mises à jour non suivies | I80: Moyen | J80: Instabilité du système et failles potentielles | K80: Mettre en place un suivi systématique des mises à jour
D81: Le SDSI est mis à jour régulièrement | E81: Le SDSI est-il mis à jour régulièrement ? | F81: pas | G81: Historique des mises à jour | H81: Information mal diffusée | I81: Moyen | J81: Manque de coordination et erreurs fréquentes | K81: Utiliser des outils collaboratifs pour partager les informations
D82: Le SDSI est communiqué aux parties prenantes concernées | E82: Le SDSI est-il communiqué aux parties prenantes concernées ? | F82: pas | G82: Liste de diffusion, rapports de communication | H82: Non-évaluation de l'alignement stratégique | I82: Moyen | J82: Ressources mal utilisées et inefficacité globale | K82: Intégrer des revues régulières de l’alignement stratégique
C83: S’assurer qu’une évaluation de l’alignement stratégique de l’application avec les orientation de l’entreprise a été réalisée | D83: Existence d'un document d'évaluation de l'alignement stratégique | E83: Un document d'évaluation de l'alignement stratégique existe-t-il ? | F83: non | G83: Document d’évaluation de l’alignement stratégique | H83: Évaluations superficielles | I83: Moyen | J83: Résultats insuffisants et décisions biaisées | K83: Réaliser des analyses détaillées et approfondies
D84: L'évaluation couvre les aspects fonctionnels, techniques et financiers | E84: L'évaluation couvre-t-elle les aspects fonctionnels, techniques et financiers ? | F84: oui | G84: Rapports d’évaluation détaillés | H84: Experts non qualifiés | I84: Élevé | J84: Erreurs majeures et inefficacité dans les processus | K84: Engager ou former des experts compétents
D85: L'évaluation est réalisée par des experts qualifiés | E85: L'évaluation est-elle réalisée par des experts qualifiés ? | F85: oui | G85: Profil des évaluateurs, rapport d’expertise | H85: Absence de mise à jour | I85: Moyen | J85: Décisions basées sur des données périmées | K85: Actualiser régulièrement les données et analyses
D86: L'évaluation est mise à jour régulièrement | E86: L'évaluation est-elle mise à jour régulièrement ? | F86: pas | G86: Rapports de mise à jour de l’évaluation | H86: Résultats mal communiqués | I86: Moyen | J86: Confusion et résistance aux conclusions | K86: Standardiser le processus de communication des résultats
D87: Les résultats de l'évaluation sont communiqués aux parties prenantes concernées | E87: Les résultats de l'évaluation sont-ils communiqués aux parties prenantes concernées ? | F87: oui | G87: Documentation de communication des résultats | H87: Spécifications incomplètes ou imprécises | I87: Élevé | J87: Mauvaise conception et risques d’incompatibilité | K87: Clarifier et documenter minutieusement les spécifications
C88: S’assurer que la définition des spécifications ou les critères de choix de la solution a été clairement établie | D88: Existence d'un document de spécifications ou de critères de choix | E88: Un document de spécifications ou de critères de choix existe-t-il ? | F88: oui | G88: Document de spécifications, cahier des charges | H88: Critères non validés | I88: Élevé | J88: Solutions non adaptées et insatisfaction des utilisateurs | K88: Valider les critères avec des experts et parties prenantes
D89: Les spécifications ou les critères de choix sont clairs, précis et mesurables | E89: Les spécifications ou critères de choix sont-ils clairs, précis et mesurables ? | F89: oui | G89: Documentation des critères de choix validés | H89: Validation insuffisante | I89: Moyen | J89: Défauts et dysfonctionnements non détectés | K89: Mettre en place des tests rigoureux avant déploiement
D90: Les spécifications ou les critères de choix sont validés par les parties prenantes concernées | E90: Les spécifications ou critères de choix sont-ils validés par les parties prenantes concernées ? | F90: oui | G90: Rapports de validation, signatures des parties prenantes | H90: Critères de comparaison partiels | I90: Moyen | J90: Décisions biaisées et manque d’équité | K90: Compléter et harmoniser les critères de comparaison
D91: Les spécifications ou les critères de choix sont utilisés pour évaluer les solutions potentielles | E91: Les spécifications ou critères de choix sont-ils utilisés pour évaluer les solutions potentielles ? | F91: oui | G91: Matrice d’évaluation des solutions, documentation de comparaison | H91: Processus de sélection non documenté | I91: Moyen | J91: Difficulté à justifier les choix effectués | K91: Documenter toutes les étapes du processus de sélection
D92: Le processus de sélection de la solution est documenté | E92: Le processus de sélection de la solution est-il documenté ? | F92: non | G92: Documentation du processus de sélection | H92: Rôles mal définis ou mal répartis | I92: Moyen | J92: Confusion et inefficacité dans l’exécution des tâches | K92: Revoir et clarifier la répartition des rôles
C93: Vérifier que les tâches des utilisateurs dans l’application sont clairement définies | D93: Existence d'une documentation des rôles et des responsabilités des utilisateurs | E93: Une documentation des rôles et des responsabilités des utilisateurs existe-t-elle ? | F93: oui | G93: Charte des rôles, description des responsabilités | H93: Tâches mal documentées | I93: Moyen | J93: Pertes de temps et erreurs dans les opérations | K93: Tenir un registre précis et détaillé des tâches effectuées
D94: Les tâches des utilisateurs sont définies de manière précise et détaillée | E94: Les tâches des utilisateurs sont-elles définies de manière précise et détaillée ? | F94: oui | G94: Guide des tâches des utilisateurs, procédures définies | H94: Processus non alignés avec les objectifs | I94: Élevé | J94: Inefficacité globale et gaspillage de ressources | K94: Revoir et ajuster les processus pour qu’ils soutiennent les objectifs
D95: Les tâches des utilisateurs sont alignées sur les processus métier | E95: Les tâches des utilisateurs sont-elles alignées sur les processus métier ? | F95: oui | G95: Documentation de l’alignement des tâches et processus | H95: Utilisateurs non formés | I95: Moyen | J95: Erreurs fréquentes et mauvaise utilisation des systèmes | K95: Instaurer des programmes de formation adaptés
D96: Les utilisateurs sont formés sur leurs tâches et responsabilités | E96: Les utilisateurs sont-ils formés sur leurs tâches et responsabilités ? | F96: non | G96: Rapports de formation, supports de formation | H96: Performances non évaluées | I96: Moyen | J96: Maintien des inefficacités et absence d’améliorations | K96: Mettre en place des indicateurs et audits de performances
D97: Les performances des utilisateurs sont évaluées régulièrement | E97: Les performances des utilisateurs sont-elles évaluées régulièrement ? | F97: non | G97: Rapports d’évaluation des performances | H97: Absence de systèmes parallèles | I97: Élevé | J97: Interruption totale en cas de panne | K97: Déployer des systèmes de secours ou parallèles
C98: Vérifier que des systèmes parallèles sont maintenus en activité | D98: Existence de systèmes parallèles pour les fonctions critiques | E98: Des systèmes parallèles pour les fonctions critiques existent-ils ? | F98: oui | G98: Documentation des systèmes parallèles, plan de secours | H98: Systèmes parallèles non testés régulièrement | I98: Moyen | J98: Dysfonctionnements non détectés | K98: Effectuer des tests périodiques des systèmes de secours
D99: Les systèmes parallèles sont maintenus à jour et testés régulièrement | E99: Les systèmes parallèles sont-ils maintenus à jour et testés régulièrement ? | F99: oui | G99: Historique des tests et mises à jour des systèmes | H99: Manque de formation aux systèmes parallèles | I99: Moyen | J99: Difficulté à basculer vers les systèmes de secours | K99: Former les équipes à l’utilisation des systèmes parallèles
D100: Les utilisateurs sont formés à l'utilisation des systèmes parallèles | E100: Les utilisateurs sont-ils formés à l'utilisation des systèmes parallèles ? | F100: non | G100: Rapports de formation, guides utilisateurs | H100: Procédures de basculement non documentées | I100: Élevé | J100: Retards en cas de transition entre systèmes | K100: Documenter et diffuser les procédures de basculement
D101: Les procédures de basculement vers les systèmes parallèles sont documentées | E101: Les procédures de basculement vers les systèmes parallèles sont-elles documentées ? | F101: oui | G101: Documentation de basculement | H101: Performances des systèmes non surveillées | I101: Élevé | J101: Dégradations non détectées et inefficacité | K101: Mettre en place des outils de surveillance continue
...

Sheet 4.1
A1: Domaine | B1: Points de Contrôle | C1: Objectifs de Contrôle | D1: Critère d’Évaluation | E1: Question d’Évaluation | F1: Réponses | G1: Documents Requis | H1: Risques | I1: Criticités | J1: Conséquences | K1: Recommandations
A2: Application en service | B2: Organisation | C2: S’assurer de l’existence d'un comité informatique | D2: Existence d'un comité informatique | E2: Existe-t-il un comité informatique ? | F2: oui | G2: Charte du comité informatique, liste des membres, procès-verbaux des réunions | H2: Absence de gouvernance claire | I2: Élevé | J2: Décisions incohérentes et manque de coordination | K2: Mettre en place un comité de gouvernance structuré
D3: Le Comité est présidé par le Directeur Général | E3: Le comité est-il présidé par le Directeur Général ? | F3: oui | G3: Document de nomination du Directeur Général, procès-verbaux des réunions | H3: Manque de leadership dans la prise de décisions stratégiques | I3: Élevé | J3: Retards et décisions inefficaces | K3: Nommer un leader compétent avec des pouvoirs clairs
D4: Les directions utilisatrices sont représentées au sein de ce Comité | E4: Les directions utilisatrices sont-elles représentées au sein du comité ? | F4: oui | G4: Liste des membres du comité, organigramme | H4: Mauvaise représentation des parties prenantes | I4: Élevé | J4: Conflits d'intérêts et mauvaise acceptation des décisions | K4: Garantir l’inclusion des parties prenantes critiques
D5: Les directions utilisatrices sont influentes au sein de ce Comité | E5: Les directions utilisatrices sont-elles influentes au sein du comité ? | F5: non | G5: Comptes rendus des réunions, décisions prises incluant les contributions des directions utilisatrices | H5: Négligence des apports des directions utilisatrices | I5: Élevé | J5: Solutions non adaptées aux besoins réels | K5: Renforcer la collaboration avec les utilisateurs finaux
D6: Présence de membres qualifiés et diversifiés | E6: Les membres du comité sont-ils qualifiés et diversifiés ? | F6: oui | G6: Profils des membres, CV, évaluation des compétences | H6: Compétences inadéquates des membres du comité | I6: Élevé | J6: Erreurs stratégiques et décisions inefficaces | K6: Former ou remplacer les membres avec des experts qualifiés
C7: S’assurer de l’existence d'une politique relative aux applications | D7: Il existe une politique relative aux applications au sein de l'institution | E7: Une politique relative aux applications existe-t-elle au sein de l'institution ? | F7: oui | G7: Politique des applications, document de gouvernance | H7: Non-existence ou non-application de la politique. | I7: Élevé | J7: Désorganisation et manque de cadre | K7: Élaborer et appliquer une politique claire et documentée
D8: La politique est connue des utilisateurs d'applications | E8: Les utilisateurs d'applications connaissent-ils cette politique ? | F8: oui | G8: Rapport de sensibilisation ou de communication | H8: Méconnaissance des obligations des utilisateurs | I8: Élevé | J8: Non-respect des procédures et inefficacité | K8: Sensibiliser et former les utilisateurs sur leurs responsabilités
D9: La politique est largement diffusée | E9: La politique est-elle largement diffusée ? | F9: non | G9: Support de communication (emails, brochures, affiches) | H9: Faible diffusion des informations | I9: Moyen | J9: Manque de transparence et communication inefficace | K9: Utiliser des outils modernes de gestion des informations
D10: La politique est mise en œuvre | E10: La politique est-elle mise en œuvre ? | F10: pas | G10: Rapports d'audit de conformité | H10: Non-conformité aux normes | I10: Élevé | J10: Risques juridiques et pénalités | K10: Auditer et corriger les écarts avec les normes
D11: La politique couvre l'ensemble du cycle de vie de l’application | E11: La politique couvre-t-elle l'ensemble du cycle de vie de l'application ? | F11: pas | G11: Documentation de la politique, schéma de cycle de vie | H11: Gestion incohérente des étapes du cycle de vie des applications | I11: Élevé | J11: Dysfonctionnements fréquents | K11: Automatiser le suivi du cycle de vie des applications
C12: S’assurer que les rôle et responsabilités des utilisateurs sont bien définis | D12: Le rôle et les responsabilités des utilisateurs vis-à-vis de l’application sont clairement identifiés | E12: Les rôles et responsabilités des utilisateurs vis-à-vis de l'application sont-ils clairement identifiés ? | F12: oui | G12: Matrice des rôles et responsabilités, charte utilisateur | H12: Absence de définition claire des rôles | I12: Élevé | J12: Confusion et responsabilités non assumées | K12: Formaliser et communiquer les rôles clairement
D13: Le rôle et les responsabilités des utilisateurs vis-à-vis de l’application couvrent l’analyse des risques | E13: Les rôles et responsabilités des utilisateurs vis-à-vis de l'application couvrent-ils l'analyse des risques ? | F13: non | G13: Documentation d'analyse des risques, rapports spécifiques | H13: Non-réalisation des analyses des risques | I13: Élevé | J13: Survenue imprévisible de risques importants | K13: Planifier et réaliser des analyses régulières des risques
D14: Le rôle et les responsabilités des utilisateurs vis-à-vis de l’application couvrent la définition des besoins de sécurité | E14: Les rôles et responsabilités des utilisateurs vis-à-vis de l'application couvrent-ils la définition des besoins de sécurité ? | F14: non | G14: Expression des besoins de sécurité | H14: Non-définition des besoins de sécurité | I14: Élevé | J14: Failles exploitables par des acteurs malveillants | K14: Identifier et intégrer les exigences sécuritaires dès la conception
D15: Le rôle et les responsabilités des utilisateurs vis-à-vis de l’application couvrent la gestion des changements et des évolutions | E15: Les rôles et responsabilités des utilisateurs vis-à-vis de l'application couvrent-ils la gestion des changements et des évolutions ? | F15: non | G15: Processus de gestion des changements | H15: Changements mal gérés | I15: Élevé | J15: Instabilité du système | K15: Mettre en place un processus de gestion des changements standardisé
D16: Le rôle et les responsabilités des utilisateurs vis-à-vis de l’application couvrent l’administration de l’application | E16: Les rôles et responsabilités des utilisateurs vis-à-vis de l'application couvrent-ils l'administration de l'application ? | F16: non | G16: Procédure d'administration de l'application | H16: Administration non sécurisée | I16: Élevé | J16: Accès non autorisé et perte de données | K16: Renforcer les contrôles d’administration et les audits
C17: S’assurer qu’une analyse des risques a été réalisée | D17: Une analyse des risques spécifique à l'application a été réalisée | E17: Une analyse des risques spécifique à l'application a-t-elle été réalisée ? | F17: oui | G17: Rapport d'analyse des risques spécifiques | H17: Documentation insuffisante des risques critiques | I17: Moyen | J17: Problèmes non identifiés et résolus | K17: Compléter la documentation des risques prioritaires
D18: L'analyse des risques a débouché sur la définition des besoins de sécurité | E18: L'analyse des risques a-t-elle débouché sur la définition des besoins de sécurité ? | F18: oui | G18: Plan de sécurité, documentation des besoins de sécurité | H18: Non-prise en compte des besoins de sécurité | I18: Élevé | J18: Vulnérabilité accrue face aux cyberattaques | K18: Prioriser les mécanismes de sécurité dans les opérations
D19: Les résultats de l'analyse des risques sont documentés et approuvés | E19: Les résultats de l'analyse des risques sont-ils documentés et approuvés ? | F19: oui | G19: Rapports d'approbation, validation formelle des résultats | H19: Absence de validation formelle | I19: Élevé | J19: Détection tardive des erreurs | K19: Mettre en place des étapes de validation rigoureuses
D20: L'analyse des risques est mise à jour régulièrement | E20: L'analyse des risques est-elle mise à jour régulièrement ? | F20: oui | G20: Historique des mises à jour, calendrier des analyses | H20: Analyses de risques obsolètes | I20: Élevé | J20: Décisions basées sur des informations incorrectes | K20: Mettre à jour les analyses périodiquement
D21: Les risques identifiés sont pris en compte dans le plan d'action de sécurité | E21: Les risques identifiés sont-ils pris en compte dans le plan d'action de sécurité ? | F21: oui | G21: Plan d'action de sécurité, rapports d'intégration des risques | H21: Actions non mises en œuvre | I21: Élevé | J21: Maintien des risques identifiés | K21: Suivre et exécuter les plans d'action
C22: S’assurer que le prolongement de l'analyse de risque et de son expansion ont été réalisés | D22: Il y a eu un prolongement de l'analyse des risques et de l'expression des besoins de sécurité | E22: Le prolongement de l'analyse des risques et de l'expression des besoins de sécurité a-t-il eu lieu ? | F22: pas | G22: Contrat de service SLA, documentation de mise en œuvre | H22: Non-respect des SLA | I22: Élevé | J22: Insatisfaction et perte de clients | K22: Surveiller et respecter strictement les SLA établis
D23: Un contrat de service (SLA) entre l'informatique et la direction utilisatrice a été mis en œuvre | E23: Un contrat de service (SLA) entre l'informatique et la direction utilisatrice a-t-il été mis en œuvre ? | F23: pas | G23: Politique de contrôle d'accès, matrice des rôles | H23: Accès inappropriés | I23: Élevé | J23: Fuites ou abus de données sensibles | K23: Réévaluer et contrôler régulièrement les droits d'accès
D24: L'analyse des risques étendue couvre tous les aspects de l'application | E24: L'analyse des risques étendue couvre-t-elle tous les aspects de l'application ? | F24: oui | G24: Journal des droits d'accès, rapports d'audit | H24: Absence de journalisation | I24: Élevé | J24: Impossibilité de retracer les activités suspectes | K24: Implémenter un système de journalisation des événements
D25: Les résultats de l'analyse des risques étendue sont communiqués aux parties prenantes | E25: Les résultats de l'analyse des risques étendue sont-ils communiqués aux parties prenantes ? | F25: oui | G25: Journaux d'accès, rapports de surveillance | H25: Activités suspectes non détectées | I25: Élevé | J25: Survenue de failles de sécurité | K25: Utiliser des outils de surveillance et détection proactive
D26: L'analyse des risques étendue est utilisée pour la planification stratégique | E26: L'analyse des risques étendue est-elle utilisée pour la planification stratégique ? | F26: oui | G26: Procédure de révocation des accès | H26: Retard dans la révocation des accès | I26: Élevé | J26: Accès non autorisé prolongé | K26: Automatiser la gestion des accès pour une révocation rapide
B27: Application | C27: S'assurer que l'accès aux ressources de l'application (données et transactions) est restreint par un système de gestion d'accès | D27: Contrôle d'accès basé sur les rôles est mis en place | E27: Un contrôle d'accès basé sur les rôles est-il mis en place ? | F27: oui | G27: Spécifications techniques de l'authentification, rapports de mise en œuvre | H27: Faiblesse dans l’authentification | I27: Élevé | J27: Compromission des comptes et données sensibles | K27: Renforcer les mécanismes d'authentification
D28: Les droits d'accès sont attribués de manière appropriée | E28: Les droits d'accès sont-ils attribués de manière appropriée ? | F28: oui | G28: Politique de mots de passe, guides utilisateurs | H28: Mauvaises pratiques de mots de passe | I28: Élevé | J28: Vulnérabilité aux attaques par force brute | K28: Éduquer les utilisateurs sur les bonnes pratiques de gestion des mots de passe
D29: Les accès sont journalisés et surveillés | E29: Les accès sont-ils journalisés et surveillés ? | F29: oui | G29: Journaux des tentatives de connexion | H29: Tentatives suspectes non identifiées | I29: Élevé | J29: Intrusions non détectées | K29: Mettre en place des solutions de détection des anomalies
D30: Un processus est en place pour révoquer les accès | E30: Un processus est-il en place pour révoquer les accès ? | F30: pas | G30: Rapports d'incidents, base de données des suivis d'incidents | H30: Absence de suivi des incidents | I30: Élevé | J30: Problèmes récurrents non résolus | K30: Créer un processus clair de gestion des incidents
D31: Les accès sont audités régulièrement | E31: Les accès sont-ils audités régulièrement ? | F31: non | G31: Charte du comité informatique, liste des membres, procès-verbaux des réunions | H31: Absence de gouvernance claire | I31: Élevé | J31: Décisions incohérentes et manque de coordination | K31: Établir des structures de gouvernance précises et documentées
C32: S’assurer qu’une procédure de gestion des profils utilisateurs existe | D32: Procédure documentée pour la création, modification et suppression des profils | E32: Une procédure documentée pour la création, modification et suppression des profils existe-t-elle ? | F32: oui | G32: Document de nomination du Directeur Général, procès-verbaux des réunions | H32: Manque de leadership dans la prise de décisions stratégiques | I32: Élevé | J32: Retards et décisions inefficaces | K32: Nommer un responsable qualifié pour les décisions stratégiques
D33: Les droits d'accès sont attribués en fonction des rôles | E33: Les droits d'accès sont-ils attribués en fonction des rôles ? | F33: oui | G33: Liste des membres du comité, organigramme | H33: Mauvaise représentation des parties prenantes | I33: Moyen | J33: Conflits et résistance aux décisions prises | K33: Assurer une représentation équitable des parties prenantes
D34: Les profils sont révisés régulièrement | E34: Les profils sont-ils révisés régulièrement ? | F34: oui | G34: Comptes rendus des réunions, décisions prises incluant les contributions des directions utilisatrices | H34: Négligence des apports des directions utilisatrices | I34: Moyen | J34: Solutions inadaptées aux besoins réels | K34: Renforcer les échanges avec les directions utilisatrices
D35: La procédure est communiquée aux parties prenantes | E35: La procédure est-elle communiquée aux parties prenantes ? | F35: pas | G35: Profils des membres, CV, évaluation des compétences | H35: Compétences inadéquates des membres du comité | I35: Élevé | J35: Décisions inefficaces et erreurs majeures | K35: Organiser des formations ou ajuster la composition du comité
D36: Des outils d'automatisation sont utilisés pour la gestion des profils | E36: Des outils d'automatisation sont-ils utilisés pour la gestion des profils ? | F36: pas | G36: Politique des applications, document de gouvernance | H36: Non-existence ou non-application de la politique | I36: Élevé | J36: Désorganisation opérationnelle | K36: Créer et appliquer une politique claire et standardisée
C37: Vérifier que l’identification des utilisateurs est réalisée | D37: Mécanismes d'identification uniques sont utilisés | E37: Des mécanismes d'identification uniques sont-ils utilisés ? | F37: oui | G37: Rapport de sensibilisation ou de communication | H37: Méconnaissance des obligations des utilisateurs | I37: Moyen | J37: Utilisation incorrecte des applications | K37: Former les utilisateurs sur leurs responsabilités
D38: Authentification forte est mise en place | E38: Une authentification forte est-elle mise en place ? | F38: oui | G38: Support de communication (emails, brochures, affiches) | H38: Faible diffusion des informations | I38: Moyen | J38: Collaboration et coordination limitées | K38: Utiliser des outils modernes pour améliorer la communication
D39: Procédure de gestion des identifiants est claire | E39: La procédure de gestion des identifiants est-elle claire ? | F39: oui | G39: Rapports d'audit de conformité | H39: Non-conformité aux normes | I39: Élevé | J39: Risques juridiques et pertes financières | K39: Réaliser des audits réguliers pour garantir la conformité
D40: Les identifiants sont protégés | E40: Les identifiants sont-ils protégés ? | F40: oui | G40: Documentation de la politique, schéma de cycle de vie | H40: Gestion incohérente des étapes du cycle de vie des applications | I40: Élevé | J40: Dysfonctionnements et retards fréquents | K40: Automatiser le suivi des étapes clés du cycle de vie.
D41: Les identifiants sont audités régulièrement | E41: Les identifiants sont-ils audités régulièrement ? | F41: non | G41: Matrice des rôles et responsabilités, charte utilisateur | H41: Absence de définition claire des rôles | I41: Moyen | J41: Confusion et duplication des responsabilités | K41: Clarifier et documenter les rôles et responsabilités
C42: Vérifier qu’un mot de passe est associé à l'identifiant | D42: Politique de mots de passe est en place | E42: Une politique de mots de passe est-elle en place ? | F42: oui | G42: Documentation d'analyse des risques, rapports spécifiques | H42: Non-réalisation des analyses des risques | I42: Élevé | J42: Risques non identifiés pouvant entraîner des interruptions majeures | K42: Mettre en place une stratégie d'analyse des risques régulière
D43: Les mots de passe sont stockés de manière sécurisée | E43: Les mots de passe sont-ils stockés de manière sécurisée ? | F43: oui | G43: Expression des besoins de sécurité | H43: Non-définition des besoins de sécurité | I43: Élevé | J43: Failles exploitables entraînant des violations de données | K43: Identifier et documenter les besoins de sécurité dès la conception
D44: Procédure de gestion des mots de passe est claire | E44: La procédure de gestion des mots de passe est-elle claire ? | F44: pas | G44: Processus de gestion des changements | H44: Changements mal gérés | I44: Élevé | J44: Instabilité opérationnelle et pannes récurrentes | K44: Adopter un processus de gestion des changements standardisé
D45: Les utilisateurs sont formés sur les bonnes pratiques de mots de passe | E45: Les utilisateurs sont-ils formés sur les bonnes pratiques de mots de passe ? | F45: oui | G45: Procédure d'administration de l'application | H45: Administration non sécurisée | I45: Élevé | J45: Accès non autorisé et compromission des données sensibles | K45: Renforcer les contrôles d'accès et sécuriser les outils d'administration
D46: Les mots de passe sont audités régulièrement | E46: Les mots de passe sont-ils audités régulièrement ? | F46: non | G46: Rapport d'analyse des risques spécifiques | H46: Documentation insuffisante des risques critiques | I46: Élevé | J46: Incapacité à prévoir et à atténuer les problèmes majeurs | K46: Compléter et maintenir à jour une documentation détaillée des risques critiques
C47: S’assurer que les tentatives de connexions infructueuses à l'application sont suivies | D47: Les tentatives de connexion sont journalisées | E47: Les tentatives de connexion sont-elles journalisées ? | F47: non | G47: Plan de sécurité, documentation des besoins de sécurité | H47: Non-prise en compte des besoins de sécurité | I47: Moyen | J47: Exploitation accrue par des acteurs malveillants | K47: Intégrer les besoins en sécurité dans toutes les étapes du projet
D48: Des alertes sont générées en cas d'activité suspecte | E48: Des alertes sont-elles générées en cas d'activité suspecte ? | F48: pas | G48: Rapports d'approbation, validation formelle des résultats | H48: Absence de validation formelle | I48: Moyen | J48: Erreurs non détectées et performance insuffisante | K48: Mettre en place des processus formalisés de validation et tests rigoureux
D49: Les journaux de connexion sont analysés régulièrement | E49: Les journaux de connexion sont-ils analysés régulièrement ? | F49: pas | G49: Historique des mises à jour, calendrier des analyses | H49: Analyses de risques obsolètes | I49: Moyen | J49: Décisions basées sur des informations périmées | K49: Réaliser des mises à jour périodiques des analyses de risques
D50: Les comptes sont bloqués en cas de tentatives répétées | E50: Les comptes sont-ils bloqués en cas de tentatives répétées ? | F50: oui | G50: Plan d'action de sécurité, rapports d'intégration des risques | H50: Actions non mises en œuvre. | I50: Élevé | J50: Risques identifiés persistant sans résolution | K50: Mettre en place un suivi rigoureux des plans d'actions recommandés
D51: Les incidents de sécurité sont documentés et suivis | E51: Les incidents de sécurité sont-ils documentés et suivis ? | F51: oui | G51: Contrat de service SLA, documentation de mise en œuvre | H51: Non-respect des SLA | I51: Élevé | J51: Insatisfaction des clients, perte de confiance et potentiels litiges | K51: Surveiller les SLA et établir des mécanismes de correction en cas de déviation
B52: Fonction informatique | C52: S’assurer que les tâches relatives au développement et à l'exploitation de l'application sont bien suivies et documentées | D52: Existence d'un plan de projet détaillé avec les tâches, les responsabilités et les échéances | E52: Existe-il un plan de projet detaillé avec les tâches, les responsabilités et les échéances? | F52: oui | G52: Plan de projet, diagramme de Gantt, feuille de route des tâches | H52: Mauvaise gestion des délais et des tâches | I52: Élevé | J52: Retards importants et baisse de productivité | K52: Mettre en place un planification stricte et un suivi des échéances
D53: Utilisation d'outils de suivi de projet pour gérer les tâches et les progrès | E53: Des outils de suivi de projet sont-ils utilisés pour gérer les tâches et les progrès ? | F53: oui | G53: Liste des outils de suivi (exemple : Jira, Trello), rapports de suivi | H53: Absence de suivi centralisé des progrès | I53: Élevé | J53: Difficulté à évaluer l'état d'avancement des projets | K53: Utiliser des outils de gestion centralisés tels que des tableaux de bord
D54: Documentation des activités de développement et d'exploitation (journal des modifications, rapports d'incidents... | E54: Les activités de développement et d'exploitation sont-elles documentées (journal des modifications, rapports d'incidents, etc.) ? | F54: oui | G54: Journal des modifications, rapport d’incidents, documentation des processus | H54: Manque de traçabilité | I54: Moyen | J54: Perte d'informations et incapacité à reproduire les étapes | K54: Implémenter des systèmes qui assurent une traçabilité complète
D55: Communication régulière entre les équipes de développement et d'exploitation | E55: Une communication régulière existe-t-elle entre les équipes de développement et d'exploitation ? | F55: pas | G55: Comptes rendus de réunions, rapports de communication inter-équipes | H55: Communication insuffisante entre équipes | I55: Élevé | J55: Risques de malentendus et travail en silo | K55: Favoriser des outils de collaboration et organiser des réunions régulières
D56: Validation des livrables et des jalons par les parties prenantes concernées | E56: Les livrables et jalons sont-ils validés par les parties prenantes concernées ? | F56: oui | G56: Rapport de validation des livrables, procès-verbaux de réunions | H56: Livrables non validés | I56: Moyen | J56: Qualité réduite et non-conformité aux attentes | K56: Mettre en œuvre un processus rigoureux de validation des livrables
C57: S’assurer que l'accès aux bibliothèques de production est réglementé | D57: Existence d'une procédure formelle pour gérer l'accès aux bibliothèques de production | E57: Existe-t-il une procédure formelle pour gérer l'accès aux bibliothèques de production ? | F57: non | G57: Documentation des procédures d’accès, matrice des rôles | H57: Mauvaise définition des accès | I57: Élevé | J57: Risques d’accès non autorisé ou accès excessif | K57: Réévaluer et clarifier les permissions d’accès
D58: Attribution des droits d'accès basée sur les rôles et les responsabilités | E58: Les droits d'accès sont-ils attribués en fonction des rôles et responsabilités ? | F58: oui | G58: Matrice des droits d’accès, charte des rôles | H58: Droits d'accès inappropriés | I58: Élevé | J58: Exploitation des systèmes et violations de sécurité | K58: Limiter les accès aux rôles nécessaires et effectuer des audits réguliers
D59: Journalisation des accès aux bibliothèques de production | E59: Les accès aux bibliothèques de production sont-ils journalisés ? | F59: pas | G59: Journaux d’accès, rapports d’audit des accès | H59: Absence de journalisation | I59: Moyen | J59: Impossible de retracer les incidents | K59: Activer et surveiller la journalisation dans les systèmes
D60: Révision régulière des droits d'accès | E60: Les droits d'accès sont-ils révisés régulièrement ? | F60: pas | G60: Historique des révisions, rapport de conformité | H60: Révisions non effectuées régulièrement | I60: Élevé | J60: Découverte tardive d’erreurs et risques accrus | K60: Mettre en place une politique de révision périodique
D61: Mise en place de contrôles pour prévenir les modifications non autorisées | E61: Des contrôles sont-ils mis en place pour prévenir les modifications non autorisées ? | F61: oui | G61: Documentation des contrôles, journal des modifications | H61: Changements non documentés | I61: Moyen | J61: Difficulté à comprendre l’historique des modifications | K61: Maintenir un registre de tous les changements effectués
C62: Vérifier que la maintenance de la séparation des tâches est effective | D62: Définition claire des rôles et des responsabilités pour les tâches sensibles | E62: Les rôles et responsabilités pour les tâches sensibles sont-ils clairement définis ? | F62: oui | G62: Description des rôles, charte des responsabilités | H62: Définitions floues des rôles | I62: Moyen | J62: Confusion et responsabilités non assumées | K62: Documenter et diffuser clairement les rôles attribués
D63: Implémentation de contrôles pour prévenir les conflits d'intérêts | E63: Des contrôles sont-ils implémentés pour prévenir les conflits d'intérêts ? | F63: oui | G63: Politique de contrôle des conflits, rapport de conformité | H63: Conflits d’intérêts mal gérés | I63: Élevé | J63: Décisions biaisées et manque de transparence | K63: Appliquer des politiques claires pour éviter les conflits d’intérêts
D64: Journalisation des activités des utilisateurs ayant des privilèges élevés | E64: Les activités des utilisateurs ayant des privilèges élevés sont-elles journalisées ? | F64: pas | G64: Journaux d’audit, rapports d’accès privilégié | H64: Absence de surveillance des utilisateurs privilégiés | I64: Élevé | J64: Exploitation non autorisée des privilèges | K64: Introduire une surveillance régulière des comptes privilégiés
D65: Révision régulière des rôles et des responsabilités | E65: Les rôles et responsabilités sont-ils révisés régulièrement ? | F65: non | G65: Rapports d’évaluation des rôles, documentation des mises à jour des responsabilités | H65: Rôles ou responsabilités obsolètes | I65: Moyen | J65: Inefficacité et duplication des efforts | K65: Réévaluer et adapter régulièrement les rôles et responsabilités
D66: Formation des utilisateurs sur l'importance de la séparation des tâches | E66: Les utilisateurs sont-ils formés sur l'importance de la séparation des tâches ? | F66: non | G66: Programme de formation, rapport de participation des utilisateurs | H66: Absence de formation des utilisateurs | I66: Moyen | J66: Mauvaise utilisation des systèmes | K66: Organiser des sessions de formation adaptées aux besoins
C67: S’assurer que l'équipe actuelle en charge de la maintenance est autonome et compétente | D67: Membres de l'équipe possédant les compétences techniques et fonctionnelles nécessaires | E67: Les membres de l'équipe possèdent-ils les compétences techniques et fonctionnelles nécessaires ? | F67: oui | G67: CV des membres, résultats d’évaluations des compétences | H67: Compétences insuffisantes | I67: Élevé | J67: Failles dans la gestion et erreurs fréquentes | K67: Identifier les besoins et fournir des formations ciblées
D68: Existence d'un plan de formation continue pour l'équipe de maintenance | E68: Un plan de formation continue pour l'équipe de maintenance existe-t-il ? | F68: pas | G68: Plan de formation continue, calendrier des sessions | H68: Manque de formation continue | I68: Moyen | J68: Obsolescence des compétences | K68: Instaurer un programme de développement continu des compétences
D69: Documentation des connaissances et des procédures de maintenance | E69: Les connaissances et procédures de maintenance sont-elles documentées ? | F69: oui | G69: Guides de maintenance, base de connaissances | H69: Documentation de maintenance insuffisante | I69: Élevé | J69: Retards et inefficacités dans la gestion de la maintenance | K69: Tenir une documentation complète et à jour pour chaque système
D70: Capacité de l'équipe à résoudre les problèmes et à répondre aux incidents | E70: L'équipe est-elle capable de résoudre les problèmes et de répondre aux incidents ? | F70: oui | G70: Rapport d’évaluation des performances, historique des incidents résolus | H70: Performances non évaluées | I70: Élevé | J70: Absence d’amélioration et maintien des inefficacités | K70: Mettre en place des processus d’évaluation régulière des performances
D71: Evaluation régulière des performances de l'équipe de maintenance | E71: Les performances de l'équipe de maintenance sont-elles évaluées régulièrement ? | F71: oui | G71: Rapports d’évaluation des performances | H71: Plan de maintenance inexistant ou mal appliqué | I71: Moyen | J71: Augmentation des pannes et dégradations | K71: Élaborer et mettre en œuvre un plan de maintenance détaillé
C72: S’assurer de l’existence de procédure formalisée et standard de maintenance de l’application | D72: Existence d'un plan de maintenance documenté | E72: Un plan de maintenance documenté existe-t-il ? | F72: pas | G72: Plan de maintenance, rapport de stratégie | H72: Activités mal planifiées ou non réalisées | I72: Élevé | J72: Délais non respectés et inefficience dans l’exécution | K72: Formaliser un plan détaillé et surveiller la réalisation des tâches
D73: Définition des activités de maintenance préventive et corrective | E73: Les activités de maintenance préventive et corrective sont-elles définies ? | F73: oui | G73: Liste des activités préventives/correctives, calendrier de maintenance | H73: Absence d'outils adaptés | I73: Élevé | J73: Inefficacité dans les opérations | K73: Investir dans des outils adaptés aux besoins et les intégrer efficacement
D74: Utilisation d'outils de gestion des incidents et des problèmes | E74: Des outils de gestion des incidents et des problèmes sont-ils utilisés ? | F74: oui | G74: Liste des outils de gestion (exemple : ServiceNow), rapports d’incidents | H74: Tests insuffisants ou inexistants | I74: Élevé | J74: Failles non détectées et dysfonctionnements fréquents | K74: Effectuer des tests rigoureux et réguliers pour garantir la qualité
D75: Mise en place de procédures de test et de validation des modifications | E75: Des procédures de test et de validation des modifications sont-elles mises en place ? | F75: oui | G75: Plan de tests, procédure de validation | H75: Changements non communiqués | I75: Moyen | J75: Confusion et interruption des processus | K75: Documenter et communiquer tous les changements aux parties concernées
D76: Communication des changements et des mises à jour aux utilisateurs | E76: Les changements et mises à jour sont-ils communiqués aux utilisateurs ? | F76: oui | G76: Rapports de communication des changements | H76: Schéma directeur obsolète ou mal aligné aux objectifs stratégiques | I76: Élevé | J76: Dysfonctionnement et inadéquation stratégique | K76: Mettre à jour et aligner le schéma directeur sur les objectifs
B77: Adéquation de l'application aux besoins | C77: Vérifier qu’un Schéma-directeur du système d’information existe et est à jour | D77: Existence d'un Schéma-directeur du système d'information (SDSI) documenté | E77: Un Schéma-directeur du système d'information (SDSI) documenté existe-t-il ? | F77: pas | G77: Schéma directeur documenté, plan stratégique IT | H77: Absence d'évaluation approfondie | I77: Élevé | J77: Risques non identifiés ou mal gérés | K77: Réaliser une évaluation complète et fréquente des risques
D78: Le SDSI couvre tous les aspects du système d'information | E78: Le SDSI couvre-t-il tous les aspects du système d'information ? | F78: pas | G78: Rapport d’évaluation du SDSI | H78: Stratégies mal alignées | I78: Élevé | J78: Décisions inefficaces et déviation des objectifs | K78: Alignement stratégique avec les objectifs organisationnels
D79: Le SDSI est aligné sur la stratégie de l'entreprise | E79: Le SDSI est-il aligné sur la stratégie de l'entreprise ? | F79: pas | G79: Documentation de l’alignement stratégique | H79: Mises à jour non suivies | I79: Moyen | J79: Instabilité du système et failles potentielles | K79: Mettre en place un suivi systématique des mises à jour
D80: Le SDSI est mis à jour régulièrement | E80: Le SDSI est-il mis à jour régulièrement ? | F80: pas | G80: Historique des mises à jour | H80: Information mal diffusée | I80: Moyen | J80: Manque de coordination et erreurs fréquentes | K80: Utiliser des outils collaboratifs pour partager les informations
D81: Le SDSI est communiqué aux parties prenantes concernées | E81: Le SDSI est-il communiqué aux parties prenantes concernées ? | F81: pas | G81: Liste de diffusion, rapports de communication | H81: Non-évaluation de l'alignement stratégique | I81: Moyen | J81: Ressources mal utilisées et inefficacité globale | K81: Intégrer des revues régulières de l’alignement stratégique
C82: S’assurer qu’une évaluation de l’alignement stratégique de l’application avec les orientation de l’entreprise a été réalisée | D82: Existence d'un document d'évaluation de l'alignement stratégique | E82: Un document d'évaluation de l'alignement stratégique existe-t-il ? | F82: non | G82: Document d’évaluation de l’alignement stratégique | H82: Évaluations superficielles | I82: Moyen | J82: Résultats insuffisants et décisions biaisées | K82: Réaliser des analyses détaillées et approfondies
D83: L'évaluation couvre les aspects fonctionnels, techniques et financiers | E83: L'évaluation couvre-t-elle les aspects fonctionnels, techniques et financiers ? | F83: oui | G83: Rapports d’évaluation détaillés | H83: Experts non qualifiés | I83: Élevé | J83: Erreurs majeures et inefficacité dans les processus | K83: Engager ou former des experts compétents
D84: L'évaluation est réalisée par des experts qualifiés | E84: L'évaluation est-elle réalisée par des experts qualifiés ? | F84: oui | G84: Profil des évaluateurs, rapport d’expertise | H84: Absence de mise à jour | I84: Moyen | J84: Décisions basées sur des données périmées | K84: Actualiser régulièrement les données et analyses
D85: L'évaluation est mise à jour régulièrement | E85: L'évaluation est-elle mise à jour régulièrement ? | F85: pas | G85: Rapports de mise à jour de l’évaluation | H85: Résultats mal communiqués | I85: Moyen | J85: Confusion et résistance aux conclusions | K85: Standardiser le processus de communication des résultats
D86: Les résultats de l'évaluation sont communiqués aux parties prenantes concernées | E86: Les résultats de l'évaluation sont-ils communiqués aux parties prenantes concernées ? | F86: oui | G86: Documentation de communication des résultats | H86: Spécifications incomplètes ou imprécises | I86: Élevé | J86: Mauvaise conception et risques d’incompatibilité | K86: Clarifier et documenter minutieusement les spécifications
C87: S’assurer que la définition des spécifications ou les critères de choix de la solution a été clairement établie | D87: Existence d'un document de spécifications ou de critères de choix | E87: Un document de spécifications ou de critères de choix existe-t-il ? | F87: oui | G87: Document de spécifications, cahier des charges | H87: Critères non validés | I87: Élevé | J87: Solutions non adaptées et insatisfaction des utilisateurs | K87: Valider les critères avec des experts et parties prenantes
D88: Les spécifications ou les critères de choix sont clairs, précis et mesurables | E88: Les spécifications ou critères de choix sont-ils clairs, précis et mesurables ? | F88: oui | G88: Documentation des critères de choix validés | H88: Validation insuffisante | I88: Moyen | J88: Défauts et dysfonctionnements non détectés | K88: Mettre en place des tests rigoureux avant déploiement
D89: Les spécifications ou les critères de choix sont validés par les parties prenantes concernées | E89: Les spécifications ou critères de choix sont-ils validés par les parties prenantes concernées ? | F89: oui | G89: Rapports de validation, signatures des parties prenantes | H89: Critères de comparaison partiels | I89: Moyen | J89: Décisions biaisées et manque d’équité | K89: Compléter et harmoniser les critères de comparaison
D90: Les spécifications ou les critères de choix sont utilisés pour évaluer les solutions potentielles | E90: Les spécifications ou critères de choix sont-ils utilisés pour évaluer les solutions potentielles ? | F90: oui | G90: Matrice d’évaluation des solutions, documentation de comparaison | H90: Processus de sélection non documenté | I90: Moyen | J90: Difficulté à justifier les choix effectués | K90: Documenter toutes les étapes du processus de sélection
D91: Le processus de sélection de la solution est documenté | E91: Le processus de sélection de la solution est-il documenté ? | F91: non | G91: Documentation du processus de sélection | H91: Rôles mal définis ou mal répartis | I91: Moyen | J91: Confusion et inefficacité dans l’exécution des tâches | K91: Revoir et clarifier la répartition des rôles
C92: Vérifier que les tâches des utilisateurs dans l’application sont clairement définies | D92: Existence d'une documentation des rôles et des responsabilités des utilisateurs | E92: Une documentation des rôles et des responsabilités des utilisateurs existe-t-elle ? | F92: oui | G92: Charte des rôles, description des responsabilités | H92: Tâches mal documentées | I92: Moyen | J92: Pertes de temps et erreurs dans les opérations | K92: Tenir un registre précis et détaillé des tâches effectuées
D93: Les tâches des utilisateurs sont définies de manière précise et détaillée | E93: Les tâches des utilisateurs sont-elles définies de manière précise et détaillée ? | F93: oui | G93: Guide des tâches des utilisateurs, procédures définies | H93: Processus non alignés avec les objectifs | I93: Élevé | J93: Inefficacité globale et gaspillage de ressources | K93: Revoir et ajuster les processus pour qu’ils soutiennent les objectifs
D94: Les tâches des utilisateurs sont alignées sur les processus métier | E94: Les tâches des utilisateurs sont-elles alignées sur les processus métier ? | F94: oui | G94: Documentation de l’alignement des tâches et processus | H94: Utilisateurs non formés | I94: Moyen | J94: Erreurs fréquentes et mauvaise utilisation des systèmes | K94: Instaurer des programmes de formation adaptés
D95: Les utilisateurs sont formés sur leurs tâches et responsabilités | E95: Les utilisateurs sont-ils formés sur leurs tâches et responsabilités ? | F95: non | G95: Rapports de formation, supports de formation | H95: Performances non évaluées | I95: Moyen | J95: Maintien des inefficacités et absence d’améliorations | K95: Mettre en place des indicateurs et audits de performances
D96: Les performances des utilisateurs sont évaluées régulièrement | E96: Les performances des utilisateurs sont-elles évaluées régulièrement ? | F96: non | G96: Rapports d’évaluation des performances | H96: Absence de systèmes parallèles | I96: Élevé | J96: Interruption totale en cas de panne | K96: Déployer des systèmes de secours ou parallèles
C97: Vérifier que des systèmes parallèles sont maintenus en activité | D97: Existence de systèmes parallèles pour les fonctions critiques | E97: Des systèmes parallèles pour les fonctions critiques existent-ils ? | F97: oui | G97: Documentation des systèmes parallèles, plan de secours | H97: Systèmes parallèles non testés régulièrement | I97: Moyen | J97: Dysfonctionnements non détectés | K97: Effectuer des tests périodiques des systèmes de secours
D98: Les systèmes parallèles sont maintenus à jour et testés régulièrement | E98: Les systèmes parallèles sont-ils maintenus à jour et testés régulièrement ? | F98: oui | G98: Historique des tests et mises à jour des systèmes | H98: Manque de formation aux systèmes parallèles | I98: Moyen | J98: Difficulté à basculer vers les systèmes de secours | K98: Former les équipes à l’utilisation des systèmes parallèles
D99: Les utilisateurs sont formés à l'utilisation des systèmes parallèles | E99: Les utilisateurs sont-ils formés à l'utilisation des systèmes parallèles ? | F99: non | G99: Rapports de formation, guides utilisateurs | H99: Procédures de basculement non documentées | I99: Élevé | J99: Retards en cas de transition entre systèmes | K99: Documenter et diffuser les procédures de basculement
D100: Les procédures de basculement vers les systèmes parallèles sont documentées | E100: Les procédures de basculement vers les systèmes parallèles sont-elles documentées ? | F100: oui | G100: Documentation de basculement | H100: Performances des systèmes non surveillées | I100: Élevé | J100: Dégradations non détectées et inefficacité | K100: Mettre en place des outils de surveillance continue
...

Sheet 4.2
A1: DOMAINES | B1: Points de Contrôle | C1: Objectifs de contrôle | D1: critères d'évaluations | E1: Questions d'évaluations | F1: Réponses | G1: Documents réquis | H1: Risques | I1: Criticités | J1: Conséquences | K1: Recommandatons
A2: Audit de la Fonction Informatique | B2: Rôle et positionnement de l'informatique dans l'organisation | C2: Vérifier qu’ont été créés des Comités « informatique » (stratégique, pilotage,..) regroupant les différentes directions de l’Organisation en charge de recenser les besoins et les opportunités, gérer les priorités et suivre les projets | D2: Existence formelle des comités avec des attributions claires | E2: Existence formelle des comités avec des attributions claires | F2: oui | G2: Charte de gouvernance SI | H2: Risque de manque de définition des rôles et responsabilités | I2: Élevé | J2: Perte de compétences clés | K2: Programmes de mentorat
D3: Fréquence et régularité des réunions des comités | E3: Un comité dédié à la gouvernance SI est-il officiellement défini? | F3: oui | G3: Calendrier des réunions | H3: Risque de manque de visibilité sur les décisions prises | I3: Élevé | J3: Risque juridique élevé | K3: Audits légaux trimestriels
D4: Participation des différentes directions aux réunions | E4: Les attributions et responsabilités des comités sont-elles clairement documentées? | F4: oui | G4: Feuilles de présence | H4: Risque de conflits ou incohérences entre les membres du comité | I4: Élevé | J4: Fuite de données sensibles | K4: Solutions de chiffrement avancées
D5: Documentation et suivi des décisions prises | E5: Les membres des comités sont-ils officiellement désignés? | F5: oui | G5: Procès-verbaux des réunions | H5: Risque de non-adhésion aux objectifs du comité | I5: Moyenne | J5: Démotivation des équipes | K5: Enquêtes de satisfaction annuelles
D6: Impact des décisions sur la stratégie informatique | E6: Fréquence et régularité des réunions des comités | F6: oui | G6: Plan stratégique SI | H6: Risque de mauvaise gestion du temps ou des priorités | I6: Moyenne | J6: Désalignement salarial | K6: Benchmark salarial annuel
C7: Vérifier l’existence d’une charte informatique ou de tout autre document définissant le rôle et le périmètre de responsabilité de la DSI | D7: Présence d’un document officiel définissant les rôles de la DSI | E7: À quelle fréquence les comités se réunissent-ils? | F7: oui | G7: Fiche de fonction de la DSI | H7: Risque de manque de participation des parties prenantes | I7: Élevé | J7: Dépendance organisationnelle | K7: Plans de rotation du personnel
D8: Validation et diffusion de la charte informatique | E8: Les réunions ont-elles lieu conformément au calendrier défini? | F8: oui | G8: Charte informatique validée | H8: Risque de mauvaise documentation des décisions | I8: Moyenne | J8: Délais de transfert de compétences | K8: Procédures de passation formalisées
D9: Alignement de la charte avec les bonnes pratiques et normes | E9: Les réunions sont-elles systématiquement documentées et suivies? | F9: oui | G9: Référentiel de bonnes pratiques | H9: Risque d'impact insuffisant sur la stratégie informatique | I9: Faible | J9: Perte de savoir-faire | K9: Systèmes de gestion des connaissances
D10: Niveau de connaissance et d’adhésion des parties prenantes | E10: Participation des différentes directions aux réunions | F10: oui | G10: Résultats des enquêtes de sensibilisation | H10: Risque d'absence de mise à jour des rôles de la DSI | I10: Moyenne | J10: Discontinuité opérationnelle | K10: Plans de continuité d'activité
D11: Mise à jour régulière du document en fonction des évolutions | E11: Toutes les directions concernées participent-elles aux réunions des comités? | F11: oui | G11: Historique des versions du document | H11: Risque de non-prise en compte des évolutions dans la charte informatique | I11: Élevé | J11: Vulnérabilité stratégique | K11: Analyse SWOT des risques
C12: Évaluer le degré d’implication et de maîtrise des organes de gestion dans les systèmes d’information de l’Organisation | D12: Participation des organes de gestion aux décisions SI | E12: Existe-t-il une liste de présence permettant de suivre la participation des directions? | F12: oui | G12: Comptes rendus de décisions SI | H12: Risque d'absence de validation des bonnes pratiques et normes | I12: Moyenne | J12: Succession non assurée | K12: Programmes accélérés de succession
D13: Existence de formations ou de sensibilisations SI pour les dirigeants | E13: Les représentants des directions sont-ils impliqués dans la prise de décision? | F13: oui | G13: Programme de formation ou de sensibilisation SI | H13: Risque de non-alignement avec les bonnes pratiques et standards | I13: Faible | J13: Contentieux juridiques | K13: Revues contractuelles systématiques
D14: Alignement des décisions SI avec la stratégie globale | E14: Documentation et suivi des décisions prises | F14: oui | G14: Tableau de correspondance SI stratégie globale | H14: Risque de faible implication des parties prenantes dans la charte | I14: Élevé | J14: Non-respect contractuel | K14: Checklists de conformité
D15: Capacité à comprendre et à évaluer les enjeux technologiques | E15: Un compte-rendu est-il systématiquement rédigé après chaque réunion? | F15: oui | G15: Fiches d’analyse d’impact technologique | H15: Risque de non-actualisation des documents de gouvernance | I15: Faible | J15: Concurrence déloyale | K15: Clauses de non-concurrence renforcées
D16: Suivi des indicateurs de performance SI par la direction | E16: Les décisions prises sont-elles suivies et mises en œuvre? | F16: oui | G16: Tableaux de bord SI | H16: Risque d’absence de sensibilisation des dirigeants aux enjeux SI | I16: Moyenne | J16: Divulgation involontaire | K16: Formations RGPD obligatoires
C17: Vérifier en pratique que le leadership des grands projets est assuré par les organes de gestion | D17: Implication des organes de gestion dans la gouvernance des projets | E17: Existe-t-il un outil de suivi des décisions et de leurs impacts? | F17: oui | G17: Procès-verbaux des comités projets | H17: Risque de mauvaise évaluation des enjeux technologiques | I17: Élevé | J17: Atteinte à la réputation | K17: Stratégie de gestion de crise média
D18: Suivi des jalons et prise de décisions stratégiques par la direction | E18: Impact des décisions sur la stratégie informatique | F18: oui | G18: Planning de suivi de projet | H18: Risque d’absence de suivi des performances de la DSI | I18: Moyenne | J18: Brèche de sécurité | K18: Tests de pénétration réguliers
D19: Allocation des ressources et arbitrages budgétaires par la direction | E19: Les décisions prises influencent-elles directement la stratégie informatique? | F19: oui | G19: Budgets validés | H19: Risque d'insuffisance dans l'analyse des résultats des projets SI | I19: Faible | J19: Rupture de service | K19: Infrastructure haute disponibilité
D20: Présence de sponsors métiers au sein des projets | E20: Existe-t-il des indicateurs permettant d’évaluer l’impact des décisions? | F20: oui | G20: Liste des sponsors métiers | H20: Risque d'imprécision dans la gestion des responsabilités entre MOA/MOE | I20: Élevé | J20: Désorganisation soudaine | K20: Plans de reprise après sinistre
D21: Évaluation des résultats et impacts des projets par la direction | E21: Les décisions sont-elles alignées avec les objectifs stratégiques de l’organisation? | F21: oui | G21: Rapports d’évaluation de projets | H21: Risque de mauvaise définition des besoins métiers | I21: Moyenne | J21: Pertes financières | K21: Contrôles financiers mensuels
C22: Vérifier que les métiers assurent leur rôle de MOA | D22: Définition claire des responsabilités MOA/MOE | E22: Présence d’un document officiel définissant les rôles de la DSI | F22: oui | G22: Responsabilités MOA/MOE documentées | H22: Risque de non-participation des utilisateurs à la recette | I22: Faible | J22: Blocage opérationnel | K22: Processus de secours préétablis
D23: Implication des métiers dans l’expression des besoins | E23: Un document officiel définit-il clairement les rôles et responsabilités de la DSI? | F23: oui | G23: Cahier des charges fonctionnel | H23: Risque d’absence de prise en charge du changement par les utilisateurs | I23: Élevé | J23: Délais critiques | K23: Marge de manœuvre dans les plannings
D24: Validation des spécifications et suivi des développements | E24: Ce document est-il régulièrement mis à jour? | F24: oui | G24: Spécifications fonctionnelles validées | H24: Risque d'une gestion inadéquate du périmètre fonctionnel | I24: Moyenne | J24: Inadéquation des compétences | K24: Évaluations annuelles des compétences
D25: Participation active aux tests et recettes | E25: Les parties prenantes ont-elles accès à ce document? | F25: oui | G25: Plans de test et comptes rendus de recette | H25: Risque de mauvaises adéquations entre les besoins métiers et les solutions | I25: Faible | J25: Obsolescence des savoirs | K25: Abonnements plateformes de veille
D26: Prise en charge du changement et de l’accompagnement des utilisateurs | E26: Validation et diffusion de la charte informatique | F26: oui | G26: Plan de conduite du changement | H26: Risque de non-évaluation des lacunes fonctionnelles | I26: Faible | J26: Décalage stratégique | K26: Réunions d'alignement trimestrielles
B27: Planification stratégique | C27: Vérifier la couverture du périmètre fonctionnel | D27: Définition claire du périmètre fonctionnel couvert | E27: La charte informatique a-t-elle été validée par la direction? | F27: oui | G27: Description du périmètre fonctionnel | H27: Risque de non-mise à jour du périmètre | I27: Moyenne | J27: Inégalités d'accès | K27: Politique d'accès équitable
D28: Adéquation entre les besoins métiers et les fonctionnalités déployées | E28: La charte est-elle communiquée à tous les employés? | F28: oui | G28: Matrice de couverture fonctionnelle | H28: Risque de mauvaise validation du périmètre | I28: Faible | J28: Faible ROI formation | K28: Mesures d'impact des formations
D29: Identification et traitement des éventuelles lacunes fonctionnelles | E29: Existe-t-il un processus de mise à jour et de validation de la charte? | F29: oui | G29: Rapports d’audit fonctionnel | H29: Risque de non-adaptation des procédures aux objectifs stratégiques | I29: Faible | J29: Planification inefficace | K29: Logiciels de planification intégrée
D30: Mise à jour régulière du périmètre en fonction des évolutions métiers | E30: Alignement de la charte avec les bonnes pratiques et normes | F30: oui | G30: Historique des modifications du périmètre | H30: Risque d'inefficacité dans l’analyse et la mise à jour des procédures | I30: Élevé | J30: Incohérence pédagogique | K30: Standards pédagogiques unifiés
D31: Validation du périmètre par les parties prenantes | E31: La charte informatique respecte-t-elle les standards et normes en vigueur? | F31: oui | G31: PV de validation du périmètre | H31: Risque de non-adéquation des documents d’urbanisme avec les besoins réels | I31: Moyenne | J31: Retard technologique | K31: Parcours de certification tech
C32: Vérifier l’existence d’une analyse à jour des procédures de pilotage et de mise à jour du plan informatique | D32: Disponibilité d’un document décrivant les procédures de pilotage | E32: Des comparaisons avec les meilleures pratiques du secteur sont-elles effectuées? | F32: oui | G32: Manuel de procédures de pilotage | H32: Risque d’absence de révision des référentiels technologiques | I32: Faible | J32: Déficit de compétences | K32: Cartographie des parcours formation
D33: Actualisation régulière des procédures en fonction des évolutions SI | E33: Un audit de conformité est-il réalisé périodiquement? | F33: oui | G33: Historique des versions des procédures | H33: Risque de manque d’accessibilité des documents d’urbanisme | I33: Faible | J33: Qualité inégale | K33: Partenariats avec universités
D34: Adéquation des procédures avec les objectifs stratégiques | E34: Niveau de connaissance et d’adhésion des parties prenantes | F34: oui | G34: Tableau de correspondance objectifs/procédures | H34: Risque d’absence de prise en compte des normes sectorielles | I34: Moyenne | J34: Sanctions réglementaires | K34: Inspections conformité inopinées
D35: Existence d’un processus formalisé de revue et d’amélioration continue | E35: Les parties prenantes connaissent-elles la charte informatique? | F35: oui | G35: Compte rendu de revues périodiques | H35: Risque de non-existence d’un processus de mise à jour du POS | I35: Faible | J35: Non-conformité légale | K35: Politique sécurité documentée
D36: Implication des parties prenantes dans l’analyse et la mise à jour | E36: Des actions de sensibilisation et de formation sont-elles mises en place? | F36: oui | G36: Compte rendu de réunions d’analyse | H36: Risque de mauvaise adéquation entre le POS et les réglementations | I36: Moyenne | J36: Vulnérabilité aux audits | K36: Surveillance continue conformité
C37: Vérifier l’existence des documents à jour d’urbanisme de l’Organisation | D37: Disponibilité des documents d’urbanisme validés | E37: Y a-t-il un mécanisme permettant de mesurer l’adhésion des parties prenantes? | F37: oui | G37: Cartographie du système d'information | H37: Risque de non-archivage des modifications du POS | I37: Faible | J37: Procédures défaillantes | K37: Police assurance cybersécurité
D38: Mise à jour régulière en fonction des évolutions des systèmes | E38: Mise à jour régulière du document en fonction des évolutions | F38: oui | G38: Historique des mises à jour de l’urbanisme | H38: Risque de manque de standardisation des référentiels | I38: Faible | J38: Risques financiers | K38: Modules formation anti-hameçonnage
D39: Cohérence des documents avec l’architecture SI actuelle | E39: À quelle fréquence le document est-il mis à jour? | F39: oui | G39: Schéma directeur actualisé | H39: Risque de non-interopérabilité des différentes solutions technologiques | I39: Élevé | J39: Cyberattaques probables | K39: Système signalement sécurisé
D40: Diffusion et accessibilité des documents aux parties prenantes concernées | E40: Existe-t-il un processus formalisé de révision et de mise à jour? | F40: oui | G40: Portail documentaire ou intranet SI | H40: Risque de mauvaise gestion des évolutions technologiques | I40: Élevé | J40: Fraude facilitée | K40: Authentification multi-facteurs
D41: Prise en compte des bonnes pratiques et des normes du secteur | E41: Les évolutions réglementaires et technologiques sont-elles prises en compte? | F41: oui | G41: Référentiel de bonnes pratiques | H41: Risque de manque de gouvernance des référentiels | I41: Élevé | J41: Contrôles inefficaces | K41: Certifications sécurité sectorielles
C42: Vérifier l’existence d’une analyse à jour des procédures de pilotage et de mise à jour du plan d’occupation des sols (POS) | D42: Présence d’un processus formalisé de mise à jour du POS | E42: Participation des organes de gestion aux décisions SI | F42: oui | G42: Procédure de gestion du Plan d’Occupation du SI (POS) | H42: Risque d'inefficacité des processus métier | I42: Moyenne | J42: Comportements à risque | K42: Analyse ROI des processus
D43: Existence d’indicateurs de suivi et de pilotage du POS | E43: Les organes de gestion participent-ils activement aux décisions SI? | F43: oui | G43: Tableau de bord POS | H43: Risque d’absence d’indicateurs de performance des processus | I43: Faible | J43: Impact mineur sur l'organisation | K43: Tableaux bord surveillance
D44: Implication des parties prenantes dans l’analyse et la validation des mises à jour | E44: Les comités de gestion sont-ils consultés avant toute décision stratégique SI? | F44: oui | G44: Comptes rendus de comités POS | H44: Risque d'incapacité d'adaptation aux évolutions organisationnelles | I44: Moyenne | J44: Déséquilibres occasionnels | K44: Sauvegardes géo-distribuées
D45: Adéquation du POS avec les réglementations et contraintes métier | E45: Les décisions SI sont-elles validées par les organes de gouvernance? | F45: oui | G45: Table de correspondance POS/réglementation | H45: Risque de faiblesse dans la mise en place d’amélioration continue | I45: Élevé | J45: Risque de paralysie opérationnelle | K45: Programmes qualité vie travail
D46: Archivage et traçabilité des modifications du POS | E46: Existence de formations ou de sensibilisations SI pour les dirigeants | F46: oui | G46: Journal des modifications du POS | H46: Risque de non-évaluation des performances via benchmarks | I46: Moyenne | J46: Tensions internes modérées | K46: Analyse concurrentielle continue
C47: Vérifier la cohérence et l’homogénéité des technologies | D47: Utilisation de standards et de référentiels technologiques unifiés | E47: Des sessions de formation sur les enjeux SI sont-elles organisées pour les dirigeants? | F47: oui | G47: Catalogue de standards technologiques | H47: Risque de manque d'alignement avec la stratégie globale | I47: Élevé | J47: Perte d'avantage concurrentiel | K47: Intégration pratiques DevOps
D48: Compatibilité et interopérabilité entre les différentes solutions SI | E48: Les dirigeants sont-ils informés des évolutions technologiques impactant l’organisation? | F48: non | G48: Études de compatibilité SI | H48: Risque de non-définition des objectifs en termes mesurables | I48: Moyenne | J48: Retards projets occasionnels | K48: Validation légale nouveaux outils
D49: Centralisation et rationalisation des choix technologiques | E49: Existe-t-il un programme de sensibilisation continue pour les décideurs? | F49: non | G49: Rapport de rationalisation SI | H49: Risque de mauvaise évaluation de l’atteinte des objectifs | I49: Élevé | J49: Exposition à des amendes | K49: Plans développement professionnel
D50: Existence d’une gouvernance dédiée à la gestion des technologies | E50: Alignement des décisions SI avec la stratégie globale | F50: non | G50: Charte de gouvernance technologique | H50: Risque de composition déséquilibrée du comité informatique | I50: Moyenne | J50: Désengagement progressif | K50: Outils prévention fuites données
D51: Suivi des évolutions technologiques et impact sur le SI | E51: Les décisions SI sont-elles alignées avec la vision stratégique de l’entreprise? | F51: non | G51: Veille technologique documentée | H51: Risque de mauvaise gestion des actions décidées par le comité | I51: Élevé | J51: Vulnérabilité cyber majeure | K51: Simulations biannuelles crise
C52: Vérifier l’existence et l’unicité des référentiels (clients, fournisseurs, articles…) et des saisies. | D52: Existence d’un référentiel unique et centralisé | E52: Un cadre de référence stratégique est-il utilisé pour guider les décisions SI? | F52: non | G52: Référentiel de données unifié | H52: Risque d’absence d’objectifs cibles clairs pour les performances | I52: Moyenne | J52: Défauts de gouvernance | K52: Accords transition contractualisés
D53: Mécanismes de contrôle pour éviter les doublons et incohérences | E53: Les choix technologiques sont-ils cohérents avec les objectifs de l’entreprise? | F53: non | G53: Procédures de contrôle qualité des données | H53: Risque de mauvaise mise à jour des indicateurs | I53: Élevé | J53: Non-atteinte d'objectifs clés | K53: Évaluation comparative compétences
D54: Mise à jour et gouvernance des référentiels définies | E54: Capacité à comprendre et à évaluer les enjeux technologiques | F54: non | G54: Plan de gouvernance des référentiels | H54: Risque de non-accessibilité des outils de mesure adéquats | I54: Moyenne | J54: Désorganisation temporaire | K54: Automatisation processus répétitifs
D55: Accessibilité et intégrité des données du référentiel | E55: Les décideurs sont-ils formés pour comprendre les enjeux SI? | F55: non | G55: Journal d’accès et de modification du référentiel | H55: Risque de non-évolution du tableau de bord | I55: Élevé | J55: Coûts de remédiation | K55: Migration architectures cloud
D56: Interopérabilité des référentiels avec les autres systèmes SI | E56: Un support technique est-il disponible pour aider à la prise de décision SI? | F56: non | G56: Schéma d’intégration SI | H56: Risque d'inefficacité du processus de retour d’expérience | I56: Moyenne | J56: Dépassements budgétaires | K56: Formations accessibles à tous
B57: Budgets et coûts informatiques | C57: Évaluer l’organisation et les processus existants | D57: Clarté et formalisation des rôles et responsabilités | E57: Les impacts technologiques des décisions sont-ils systématiquement évalués? | F57: non | G57: Organigrammes et fiches de poste | H57: Risque de non-identification des enseignements tirés | I57: Élevé | J57: Dépendance aux prestataires | K57: Système validation acquis
D58: Efficacité et fluidité des processus métier | E58: Suivi des indicateurs de performance SI par la direction | F58: non | G58: Cartographie des processus métier | H58: Risque de non-mise à jour de l’organigramme | I58: Moyenne | J58: Défaut de continuité | K58: Plateformes apprentissage en ligne
D59: Existence d’indicateurs de performance et de suivi des processus | E59: Des indicateurs de performance SI sont-ils définis et suivis par la direction? | F59: non | G59: Tableau de bord des processus | H59: Risque de non-adaptabilité de l’organigramme aux évolutions | I59: Élevé | J59: Litiges potentiels | K59: Collaborations éditeurs tech
D60: Capacité d’adaptation aux évolutions organisationnelles et technologiques | E60: Les tableaux de bord SI sont-ils mis à jour et utilisés pour la prise de décision? | F60: non | G60: Rapport de changement organisationnel | H60: Risque de non-clarification des responsabilités des postes | I60: Moyenne | J60: Déficit de compétences critiques | K60: Audits croisés départements
D61: Mise en place de mécanismes d’amélioration continue | E61: Les performances SI sont-elles évaluées régulièrement et comparées aux objectifs? | F61: non | G61: Plan d’amélioration continue | H61: Risque de non-régularité dans la mise à jour des fiches de poste | I61: Élevé | J61: Démotivation ciblée | K61: Protocoles gestion incidents
C62: Vérifier l’existence des ratios et des éléments de benchmark (interne et/ou externe, ratio coûts/CA, …) | D62: Définition et mise à jour régulière des ratios pertinents | E62: Implication des organes de gestion dans la gouvernance des projets | F62: non | G62: Fiches de définition des ratios | H62: Risque de non-cohérence des rôles avec la structure organisationnelle | I62: Moyenne | J62: Non-conformité partielle | K62: Contrôles accès basés rôles
D63: Comparaison des performances avec des références internes et externes | E63: Les organes de gestion sont-ils impliqués dès le démarrage des projets SI? | F63: non | G63: Rapports de benchmarking | H63: Risque de non-intégration des meilleures pratiques en fonction des fonctions | I63: Élevé | J63: Risque réputationnel modéré | K63: Normes internes renforcées
D64: Exploitation des benchmarks pour l’optimisation des coûts et des ressources | E64: Des réunions de suivi de projet sont-elles organisées avec les instances de gouvernance? | F64: non | G64: Rapports d’analyse comparative | H64: Risque de mauvais suivi des responsabilités de chaque fonction | I64: Moyenne | J64: Productivité fluctuante | K64: Externalisation fonctions non-essentielles
D65: Accessibilité et fiabilité des données utilisées pour les analyses | E65: Les décisions stratégiques des projets SI sont-elles validées par la direction? | F65: non | G65: Données d’analyse validées | H65: Risque d'inefficacité de la séparation des rôles fonctionnels | I65: Élevé | J65: Délais allongés | K65: Outils analyse prédictive
D66: Intégration des résultats des benchmarks dans la prise de décision stratégique | E66: Suivi des jalons et prise de décisions stratégiques par la direction | F66: non | G66: Compte rendu de réunions stratégiques | H66: Risque de non-gestion proactive des effectifs | I66: Moyenne | J66: Qualité altérée ponctuellement | K66: Réplication temps réel systèmes
C67: Vérifier que des objectifs de court, moyen et long termes existent et sont assignés à la DSI (approche BSC ?) et que ces objectifs sont déclinés au sein de l’entité | D67: Alignement des objectifs DSI avec la stratégie globale | E67: Alignement des objectifs DSI avec la stratégie globale ? | F67: non | G67: Plan stratégique DSI | H67: Risque de mauvais équilibre entre sous-traitance et effectifs internes | I67: Élevé | J67: Désalignement stratégique | K67: Stratégie marque employeur
D68: Déclinaison des objectifs en indicateurs mesurables | E68: Déclinaison des objectifs en indicateurs mesurables ? | F68: non | G68: Tableau de déclinaison des objectifs | H68: Risque d'insuffisance de planification des effectifs à long terme | I68: Moyenne | J68: Impact négligeable | K68: Systèmes automatisés veille
D69: Mise en place de revues périodiques des objectifs | E69: Mise en place de revues périodiques des objectifs ? | F69: non | G69: Compte rendus de revues d’objectifs | H69: Risque de non-adéquation des qualifications avec les fonctions | I69: Élevé | J69: Retards administratifs | K69: Chaînes outils DevSecOps
D70: Implication des parties prenantes dans la définition des objectifs | E70: Implication des parties prenantes dans la définition des objectifs ? | F70: non | G70: PV de réunions avec parties prenantes | H70: Risque de formation insuffisante pour des fonctions critiques | I70: Faible | J70: Exposition juridique grave | K70: Comités surveillance technologique
D71: Évaluation de l’atteinte des objectifs et ajustements nécessaires | E71: Évaluation de l’atteinte des objectifs et ajustements nécessaires ? | F71: non | G71: Rapports d’évaluation des objectifs | H71: Risque d’absence de processus structuré de recette | I71: Moyenne | J71: Désynchronisation métiers/SI | K71: Programmes leadership technique
C72: Vérifier l’existence d’un comité informatique regroupant les différentes directions de l’organisation | D72: Composition représentative du comité informatique | E72: Composition représentative du comité informatique ? | F72: non | G72: Charte du comité informatique | H72: Risque de mauvaise gestion de la séparation des tâches entre études et exploitation | I72: Élevé | J72: Pertes données critiques | K72: Solutions détection anomalies
D73: Fréquence et efficacité des réunions du comité | E73: Fréquence et efficacité des réunions du comité ? | F73: non | G73: Calendrier et procès-verbaux du comité | H73: Risque de non-respect des procédures avant mise en production | I73: Moyenne | J73: Défaut de traçabilité | K73: Plan réponse ransomwares
D74: Prise en compte des besoins des directions métiers | E74: Prise en compte des besoins des directions métiers ? | F74: non | G74: Études de besoins métiers | H74: Risque de gestion inadéquate des mises en production | I74: Élevé | J74: Erreurs humaines accrues | K74: Contrats engagements service
D75: Documentation des décisions prises par le comité | E75: Documentation des décisions prises par le comité ? | F75: non | G75: Registre des décisions du comité | H75: Risque de non-formation des équipes sur les procédures | I75: Moyenne | J75: Conséquence minime | K75: Inventaire compétences internes
D76: Suivi des actions décidées et mises en œuvre | E76: Suivi des actions décidées et mises en œuvre ? | F76: non | G76: Tableau de suivi des actions | H76: Risque d’absence de mécanismes de contrôle des mises en production | I76: Faible | J76: Vulnérabilité aux attaques | K76: Tests automatisés exhaustifs
C77: Évaluer la pertinence des indicateurs de qualité et de performance ainsi que les moyens et outils de mesure | D77: Définition claire des indicateurs de performance | E77: Définition claire des indicateurs de performance ? | F77: non | G77: Fiche des indicateurs définis | H77: Risque d’absence de séparation des rôles dans la gestion des bases de données | I77: Élevé | J77: Défaut de supervision | K77: Modernisation systèmes hérités
D78: Mise en place de seuils d’alerte et d’objectifs cibles | E78: Mise en place de seuils d’alerte et d’objectifs cibles ? | F78: non | G78: Documentation des seuils et cibles | H78: Risque de mauvais contrôle des accès aux systèmes | I78: Moyenne | J78: Fraude possible | K78: Conception universelle supports
D79: Disponibilité des outils de mesure adéquats | E79: Disponibilité des outils de mesure adéquats ? | F79: non | G79: Catalogue des outils de pilotage | H79: Risque de manque d'adaptation des contrôles en cas de transition | I79: Élevé | J79: Contrôles insuffisants | K79: Politique promotion interne
D80: Suivi régulier et analyse des écarts | E80: Suivi régulier et analyse des écarts ? | F80: non | G80: Rapports d’analyse des écarts | H80: Risque de dépendance excessive à un individu clé dans la DSI | I80: Moyenne | J80: Non-respect normes | K80: Centres innovation interne
D81: Intégration des indicateurs dans la gouvernance SI | E81: Intégration des indicateurs dans la gouvernance SI ? | F81: non | G81: Tableau de gouvernance SI | H81: Risque d'inefficacité des stratégies de fidélisation du personnel | I81: Élevé | J81: Sanctions réglementaires | K81: Partenariats recherche-développement
B82: Mesure et suivi de la performance informatique | C82: Vérifier que la DSI tient un tableau de bord (idéalement de type BSC) permettant un suivi consolidé de la performance (opérationnelle et financière) et de la qualité des prestations informatiques | D82: Contenu du tableau de bord et couverture des domaines clés | E82: Contenu du tableau de bord et couverture des domaines clés ? | F82: non | G82: Extrait du tableau de bord SI | H82: Risque d'insuffisance des moyens pour réduire le turnover | I82: Élevé | J82: Impact opérationnel limité | K82: Vérifications automatisées conformité
D83: Mise à jour et suivi régulier des indicateurs | E83: Mise à jour et suivi régulier des indicateurs ? | F83: non | G83: Tableau de bord des indicateurs | H83: Risque de mauvaise gestion des carrières des informaticiens | I83: Moyenne | J83: Risques mal couverts | K83: Analyse approfondie des risques
D84: Accessibilité et diffusion du tableau de bord aux parties prenantes | E84: Accessibilité et diffusion du tableau de bord aux parties prenantes ? | F84: non | G84: Journal de mise à jour du tableau de bord | H84: Risque de faible reconnaissance des performances | I84: Faible | J84: Défaut d'actualisation | K84: Mise à jour trimestrielle des processus
D85: Prise de décision basée sur les données du tableau de bord | E85: Prise de décision basée sur les données du tableau de bord ? | F85: non | G85: Rapports d’analyse décisionnelle | H85: Risque d’insuffisance de rémunération et de motivation du personnel | I85: Moyenne | J85: Problèmes récurrents mineurs | K85: Suivi des incidents récurrents
D86: Évolution du tableau de bord en fonction des besoins | E86: Évolution du tableau de bord en fonction des besoins ? | F86: non | G86: Documentation de l’évolution du tableau de bord | H86: Risque de non-évaluation de la dépendance à certaines personnes clés | I86: Faible | J86: Défaut de documentation | K86: Documentation standardisée des procédures
C87: Vérifier qu’il est systématiquement effectué un bilan après chaque projet et notamment un bilan économique (bilan rapproché des prévisions de l’étude préalable) | D87: Existence d’un processus de retour d’expérience | E87: Existence d’un processus de retour d’expérience ? | F87: non | G87: Procédures de retour d’expérience | H87: Risque de mauvaise gestion des connaissances critiques lors du départ des employés | I87: Moyenne | J87: Risque résiduel acceptable | K87: Évaluation des risques résiduels
D88: Comparaison des coûts et bénéfices réalisés vs prévus | E88: Comparaison des coûts et bénéfices réalisés vs prévus ? | F88: non | G88: Étude coûts-bénéfices projet | H88: Risque d'inefficacité de la politique de confidentialité et de non-concurrence | I88: Faible | J88: Dysfonctionnements ponctuels | K88: Procédures de correction rapide
D89: Identification et capitalisation des enseignements tirés | E89: Identification et capitalisation des enseignements tirés ? | F89: non | G89: Rapport d’analyse des écarts | H89: Risque d'absence de protection des données sensibles | I89: Moyenne | J89: Exposition légale critique | K89: Audit juridique complet
D90: Mise en place d’actions correctives et d’améliorations | E90: Mise en place d’actions correctives et d’améliorations ? | F90: non | G90: Plan d’actions correctives | H90: Risque de non-respect des obligations légales en cybersécurité | I90: Faible | J90: Inertie organisationnelle | K90: Revue organisationnelle biannuelle
D91: Partage des bilans avec les parties prenantes concernées | E91: Partage des bilans avec les parties prenantes concernées ? | F91: non | G91: Procès-verbaux de réunions de restitution | H91: Risque de fraude informatique non traitée | I91: Moyenne | J91: Faible réactivité | K91: Plan de réponse d'urgence
C92: Vérifier l’existence d’un organigramme à jour de la DSI | D92: Mise à jour régulière de l’organigramme | E92: Mise à jour régulière de l’organigramme ? | F92: non | G92: Organigramme officiel à jour | H92: Risque de non-conformité avec la législation sur les transactions électroniques | I92: Élevé | J92: Rupture de service grave | K92: Solution de haute disponibilité
D93: Cohérence entre l’organigramme et les fonctions réelles | E93: Cohérence entre l’organigramme et les fonctions réelles ? | F93: non | G93: Fiches de cohérence organigramme-fonctions | H93: Risque de mauvaise communication des rôles et responsabilités | I93: Moyenne | J93: Atteinte à l'image de marque | K93: Stratégie de communication de crise
D94: Documentation et communication de l’organigramme | E94: Documentation et communication de l’organigramme ? | F94: non | G94: Note de service de diffusion de l’organigramme | H94: Risque de non-adaptabilité de l’organigramme face aux évolutions | I94: Faible | J94: Désorganisation mineure | K94: Optimisation des workflows
D95: Adaptabilité de l’organigramme aux évolutions organisationnelles | E95: Adaptabilité de l’organigramme aux évolutions organisationnelles ? | F95: non | G95: Rapport d’analyse organisationnelle | H95: Risque de divergence entre les objectifs stratégiques et les responsabilités | I95: Élevé | J95: Rupture opérationnelle critique | K95: Architecture redondante critique
D96: Alignement des responsabilités avec les objectifs stratégiques | E96: Alignement des responsabilités avec les objectifs stratégiques ? | F96: non | G96: Matrice responsabilités vs objectifs | H96: Risque de flou dans les fiches de poste | I96: Élevé | J96: Perte de données stratégiques | K96: Sauvegarde sécurisée des données
C97: Vérifier l’existence d’une définition de fonction et d’un partage clair des rôles et des responsabilités pour chaque poste figurant sur l’organigramme | D97: Formalisation des fiches de poste pour chaque fonction | E97: Formalisation des fiches de poste pour chaque fonction ? | F97: oui | G97: Fiches de poste validées | H97: Risque de confusion des périmètres d’action | I97: Moyenne | J97: Baisse de productivité notable | K97: Analyse des goulots d'étranglement
D98: Clarification des responsabilités et des périmètres d’action | E98: Clarification des responsabilités et des périmètres d’action ? | F98: non | G98: Tableau de répartition des responsabilités | H98: Risque de difficulté d’accès aux descriptions de poste | I98: Faible | J98: Dysfonctionnement localisé | K98: Automatisation des points faibles
D99: Communication et accessibilité des descriptions de poste | E99: Communication et accessibilité des descriptions de poste ? | F99: oui | G99: Base documentaire des fiches de poste | H99: Risque de non-mise à jour des documents en fonction des évolutions du SI | I99: Moyenne | J99: Retards récurrents projets | K99: Méthodologie agile renforcée
D100: Mise à jour régulière en fonction des évolutions du SI | E100: Mise à jour régulière en fonction des évolutions du SI ? | F100: non | G100: Historique des mises à jour des postes | H100: Risque de désalignement entre rôles et structure organisationnelle | I100: Faible | J100: Problèmes qualité ponctuels | K100: Contrôle qualité renforcé
...

Sheet 4.3
A1: Domaines | B1: Point de contrôle | C1: Objectifs de contrôle | D1: critères d'évaluation | E1: Questions d'évaluation | F1: Réponses | G1: Document requis | H1: Risques | I1: Criticité | J1: conséquence | K1: Recommandation
A2: Audit et Contrôle des Projets Informatiques | B2: Objectifs et enjeux du projet | C2: S’assurer qu’une étude de la valeur et des études d'opportunité et d'impacts ont été réalisées ; | D2: organigramme officiel doit inclure le comité informatique | E2: L'organigramme officiel inclut-il clairement le comité informatique ? | F2: oui | G2: Organigramme officiel incluant le comité informatique | H2: Manque de coordination et de gouvernance | I2: Élevé | J2: Décisions incohérentes, retards dans les projets, conflits entre équipes, perte de confiance des parties prenantes. | K2: Créer une structure de gouvernance claire avec des rôles, responsabilités et processus bien définis
D3: Documentation formelle doit décrire les responsabilités du comité | E3: Les responsabilités du comité informatique sont-elles documentées de manière formelle ? | F3: oui | G3: Document formel décrivant les responsabilités du comité | H3: Confusion et chevauchement des tâches | I3: Élevé | J3: Gaspillage de ressources, frustration des employés, responsabilités floues, omissions critiques. | K3: Élaborer une matrice RACI pour clarifier les responsabilités et éviter les chevauchements
D4: réunions frequentes et compte doivent etre rendus disponibles | E4: Les réunions du comité informatique sont-elles tenues régulièrement avec des comptes rendus disponibles ? | F4: oui | G4: Comptes rendus des réunions du comité | H4: Perte d’informations importantes et de décisions non formalisées | I4: Élevé | J4: Impossibilité de tracer les décisions, risques juridiques, erreurs répétées. | K4: Utiliser un outil de gestion documentaire et consigner systématiquement les décisions importantes
D5: les membres doivent etre désignés pour participer | E5: Les membres désignés participent-ils activement aux réunions et décisions du comité ? | F5: non | G5: Liste de présence et participation des membres désignés | H5: Mauvaise prise de décisions et inactivité du comité | I5: Élevé | J5: Opportunités manquées, dégradation de la performance, démotivation des équipes. | K5: Mettre en place un calendrier de réunions de gouvernance avec un suivi rigoureux des décisions
D6: la direction doit valider l'existence du comité | E6: La direction a-t-elle officiellement validé l’existence du comité informatique ? | F6: oui | G6: Validation officielle de la direction attestant l’existence du comité | H6: Manque de légitimité et de reconnaissance | I6: Élevé | J6: Non-respect des directives, difficulté à faire appliquer les règles, perte d’autorité. | K6: Renforcer la communication interne sur le rôle et l'importance des instances de gouvernance
C7: S’assurer qu’un bilan critique des processus existants a été effectué ; | D7: Existence d’un document formalisé couvrant la politique des applications | E7: Un document formalisé sur la politique des applications existe-t-il ? | F7: oui | G7: Document formalisé couvrant la politique des applications | H7: Gestion incohérente des applications | I7: Élevé | J7: Surcharge des systèmes, coûts supplémentaires, failles de sécurité. | K7: Adopter un référentiel de gestion des applications et centraliser les décisions d’urbanisation du SI
D8: la politique doit etre alignée avec les objectifs de l'organisation | E8: La politique des applications est-elle alignée avec les objectifs stratégiques de l’organisation ? | F8: oui | G8: Rapport d’alignement de la politique avec les objectifs de l’organisation | H8: Non-conformité aux priorités stratégiques | I8: Élevé | J8: Investissements inutiles, désavantage concurrentiel, échec des transformations. | K8: Aligner systématiquement les projets sur les orientations stratégiques définies par la direction
D9: Date de dernière révision et mise à jour disponible | E9: La dernière révision de la politique est-elle documentée avec une mise à jour récente ? | F9: non | G9: Historique des révisions et mise à jour de la politique | H9: Utilisation de directives obsolètes | I9: Moyen | J9: Non-conformité réglementaire, processus inefficaces, risques juridiques. | K9: Mettre à jour régulièrement les directives en fonction de l’évolution des besoins et des technologies
D10: les parties prenantes doivent avoir acces a la poitique | E10: La politique des applications est-elle accessible aux parties prenantes concernées ? | F10: pas | G10: Document accessible détaillant la politique pour les parties prenantes | H10: Mauvaise compréhension ou application des directives | I10: Élevé | J10: Erreurs opérationnelles, non-atteinte des objectifs, sanctions. | K10: Former les équipes aux directives internes et instaurer des contrôles pour vérifier leur application
D11: Processus pour signaler et traiter les non-conformités | E11: Un processus est-il défini pour signaler et résoudre les cas de non-conformité ? | F11: pas | G11: Procédure formelle pour signaler et traiter les non-conformités | H11: Non-traitement des écarts détectés | I11: Élevé | J11: Aggravation des faiblesses, incidents majeurs, perte de crédibilité. | K11: Documenter, suivre et corriger systématiquement tous les écarts détectés lors des audits ou contrôles
C12: S’assurer que le choix de recourir à un nouveau système est obtenu après optimisation des processus concernés et vérification que cette optimisation ne suffit pas à apporter par elle-même les gains de performance attendus ; | D12: un document listant les rôles et responsabilités des utilisateurs doit etre disponible | E12: Existe-t-il un document formel listant les rôles et responsabilités des utilisateurs ? | F12: oui | G12: Document listant les rôles et responsabilités des utilisateurs | H12: Attribution incorrecte des tâches | I12: Élevé | J12: Surcharge ou sous-utilisation des compétences, baisse de productivité, turnover. | K12: Mettre en place un système de validation des affectations avec relecture croisée des responsabilités
D13: Communication formelle des responsabilités aux utilisateurs concernés | E13: Les responsabilités des utilisateurs sont-elles communiquées de manière formelle ? | F13: non | G13: Preuve de communication formelle des responsabilités aux utilisateurs | H13: Incompréhension ou mauvaises pratiques | I13: Élevé | J13: Violations de sécurité, non-respect des procédures. | K13: Former les collaborateurs aux bonnes pratiques opérationnelles et outils métiers
D14: Documentation des autorisations doit etre spécifiques par rôle | E14: Les autorisations spécifiques pour chaque rôle sont-elles documentées ? | F14: non | G14: Document de gestion des autorisations spécifiques par rôle | H14: Accès non autorisé ou contrôle inefficace | I14: Élevé | J14: Fuites de données, cyberattaques facilitées, sanctions légales. | K14: Renforcer le contrôle d’accès avec des outils de gestion des identités et des accès (IAM)
D15: Fréquence des mises à jour des descriptions des rôles | E15: Les descriptions de rôles sont-elles mises à jour régulièrement ? | F15: non | G15: Journal des mises à jour des descriptions de rôles | H15: Confusion ou manque de pertinence des responsabilités | I15: Élevé | J15: Tâches non réalisées, retards dans les processus critiques. | K15: Clarifier les fiches de poste et les responsabilités associées à chaque fonction
D16: Existence de formations liées aux rôles utilisateurs | E16: Des formations sont-elles proposées pour les utilisateurs en fonction de leurs rôles ? | F16: non | G16: Programme de formation lié aux rôles des utilisateurs | H16: Faible adoption des outils ou erreurs d’utilisation | I16: Élevé | J16: ROI faible, données corrompues ou incomplètes. | K16: Former les utilisateurs aux outils internes et mesurer leur taux d’adoption
C17: S’assure que les objectifs et périmètres du projet sont définis, partagés et stabilisés ; | D17: un document d’analyse des risques formalisé doit etre disponible | E17: Un document formalisé d’analyse des risques est-il disponible ? | F17: oui | G17: Document formalisé d’analyse des risques | H17: Ignorance face aux menaces potentielles | I17: Moyen | J17: Incidents non anticipés, crises majeures. | K17: Sensibiliser régulièrement les équipes aux risques de cybersécurité et aux menaces émergentes
D18: les principaux risques liés aux applications doivent etre identifiés | E18: Les principaux risques associés aux applications ont-ils été identifiés ? | F18: oui | G18: Rapport d’identification des principaux risques | H18: Dommages non anticipés | I18: Élevé | J18: Coûts de réparation élevés, interruptions d’activité. | K18: Mettre en place des tests de sécurité préventifs et plans de reprise d’activité
D19: Documentation des mesures doit etre atténuée pour chaque risque | E19: Les mesures d’atténuation associées à chaque risque sont-elles documentées ? | F19: oui | G19: Rapport de documentation des mesures d’atténuation pour chaque risque | H19: Exposition accrue aux menaces | I19: Élevé | J19: Pertes financières, atteinte à la réputation. | K19: Renforcer les contrôles d’accès physique et logique pour limiter l’exposition aux menaces
D20: les parties prenantes doivent valider l'analyse | E20: L’analyse des risques a-t-elle été validée par les parties prenantes ? | F20: oui | G20: Validation des analyses par les parties prenantes | H20: Manque d’adhésion aux résultats | I20: Élevé | J20: Résistance au changement, échec des projets. | K20: Favoriser l’adhésion par la communication des résultats et l’implication dans la définition des objectifs
D21: Calendrier de révision régulière de l’analyse des risques | E21: Un calendrier de révision régulière de l’analyse des risques est-il défini ? | F21: oui | G21: Calendrier de révision des analyses des risques | H21: Décisions basées sur des données périmées | I21: Élevé | J21: Stratégies inefficaces, opportunités perdues. | K21: Mettre en place un système de collecte et de mise à jour automatique des données stratégiques
C22: S’assurer que les principales orientations du système cible ont été explicitées ; | D22: les nouveaux risques doivent etre identifiés suite à l’expansion | E22: Les nouveaux risques liés à l’expansion ont-ils été identifiés ? | F22: pas | G22: Rapport d’identification des nouveaux risques suite à l’expansion | H22: Vulnérabilités inattendues | I22: Élevé | J22: Incidents de sécurité non anticipés, exploitation des failles par des attaquants | K22: Effectuer des analyses de vulnérabilités régulières et audits de sécurité du SI
D23: Documentation supplémentaire liée à l’analyse étendue | E23: Une documentation supplémentaire a-t-elle été réalisée pour l’analyse étendue ? | F23: pas | G23: Documentation complémentaire pour l’analyse étendue | H23: Évaluation incomplète | I23: Élevé | J23: Analyse partielle des risques, couverture insuffisante des menaces | K23: Compléter les évaluations de risques par des audits indépendants et des tests d’intrusion
D24: Validation officielle de l’analyse élargie | E24: L’analyse élargie a-t-elle été validée officiellement par les responsables ? | F24: oui | G24: Validation officielle de l’analyse élargie | H24: Non-fiabilité des résultats | I24: Élevé | J24: Conclusions erronées, fausse impression de sécurité | K24: Mettre en place un processus de validation croisée des résultats d’analyse
D25: . Ajustements aux mesures d’atténuation en conséquence | E25: Les mesures d’atténuation ont-elles été ajustées en fonction des nouveaux risques ? | F25: oui | G25: Preuve des ajustements des mesures d’atténuation | H25: Solutions inefficaces pour de nouveaux risques | I25: Élevé | J25: Protection inadéquate, persistance des vulnérabilités | K25: Adopter une veille technologique pour anticiper les nouveaux risques et adapter les solutions
D26: Communication des mises à jour aux parties prenantes | E26: Les mises à jour de l’analyse des risques ont-elles été communiquées aux parties prenantes ? | F26: oui | G26: Communication des mises à jour des analyses de risques aux parties concernées | H26: Décisions non éclairées par les parties concernées | I26: Élevé | J26: Choix stratégiques inappropriés, conflits organisationnels | K26: Instaurer un cadre de concertation avec les parties prenantes pour la prise de décision
B27: Étude d'opportunité et expression des besoins | C27: S’assurer que l'expression détaillée des besoins est formalisée dans un cahier des charges fait par la MOA ; | D27: Présence d’un système de gestion d’accès centralisé | E27: Un système de gestion d’accès centralisé est-il en place ? | F27: oui | G27: Rapport sur le système de gestion d’accès centralisé | H27: Accès non autorisé | I27: Élevé | J27: Fuites de données, compromission d'informations | K27: Renforcer les politiques d’accès avec des règles de moindre privilège strictement appliquées
D28: Documentation des autorisations d’accès par utilisateur | E28: Les autorisations d’accès par utilisateur sont-elles documentées ? | F28: oui | G28: Documentation des autorisations d’accès par utilisateur | H28: Confusion ou d’abus | I28: Élevé | J28: Utilisation abusive des ressources, détournements | K28: Mettre en place des contrôles pour éviter les abus ou les confusions dans la gestion des accès
D29: Mise à jour régulière des droits d’accès | E29: Les droits d’accès sont-ils mis à jour régulièrement ? | F29: oui | G29: Journal des mises à jour régulières des droits d’accès | H29: Permissions obsolètes ou inappropriées | I29: Élevé | J29: Privilèges excessifs, accès injustifiés aux systèmes sensibles | K29: Mettre à jour régulièrement les permissions et supprimer les accès obsolètes
D30: Validation des accès par la direction | E30: Les accès sont-ils validés par la direction ? | F30: pas | G30: Validation des accès par la direction | H30: Mauvaise gestion des privilèges | I30: Élevé | J30: Accès non autorisés, permissions excessives, abus de droits | K30: Utiliser des outils d’audit pour surveiller l’attribution et l’utilisation des privilèges
D31: Suivi des modifications des accès aux ressources | E31: Les modifications des accès aux ressources sont-elles suivies ? | F31: non | G31: Journal de suivi des modifications des accès aux ressources | H31: Contrôle insuffisant | I31: Élevé | J31: Failles non détectées, violations de sécurité persistantes | K31: Automatiser la gestion du cycle de vie des utilisateurs et leurs accès
C32: S’assurer que le cahier des charges préconise une solution fonctionnellement et techniquement pertinente au regard des besoins exprimés ; | D32: Existence d’un document formalisé des profils utilisateurs | E32: Un document formalisé des profils utilisateurs existe-t-il ? | F32: oui | G32: Document formalisé des profils utilisateurs | H32: Gestion inefficace des utilisateurs | I32: Élevé | J32: Comptes obsolètes actifs, accès non révoqués | K32: Mettre en œuvre des procédures claires de création, modification et suppression des comptes
D33: Processus de création, modification et suppression des profils | E33: Un processus de création, modification et suppression des profils est-il défini ? | F33: oui | G33: Procédure formelle de création, modification et suppression des profils | H33: Désorganisation | I33: Moyen | J33: Confusion dans les accès, responsabilités floues | K33: Attribuer les permissions selon le principe du moindre privilège
D34: Validation des profils par les parties prenantes | E34: Les profils utilisateurs ont-ils été validés par les parties prenantes ? | F34: oui | G34: Validation des profils par les parties prenantes | H34: Permissions incorrectes | I34: Moyen | J34: Accès injustifiés à des données sensibles | K34: Mettre en place un système de suivi et de journalisation pour assurer la traçabilité
D35: Suivi des modifications des profils utilisateurs | E35: Les modifications des profils utilisateurs sont-elles suivies ? | F35: pas | G35: Journal de suivi des modifications des profils utilisateurs | H35: Non-conformité ou perte de traçabilité | I35: Élevé | J35: Sanctions légales, impossibilité d'auditer les actions | K35: Mettre à jour régulièrement les profils utilisateurs et valider leur adéquation aux rôles
D36: Formation des administrateurs sur la gestion des profils | E36: Les administrateurs ont-ils reçu une formation sur la gestion des profils ? | F36: pas | G36: Rapport de formation des administrateurs sur la gestion des profils | H36: Erreurs de gestion des profils | I36: Élevé | J36: Droits inadaptés aux besoins réels | K36: Utiliser l’authentification multifactorielle pour prévenir l’usurpation d’identité
C37: S’assurer que les exigences utilisateurs, les populations ciblées, les options et principes de gestion retenus sont précisés et priorisés ; | D37: Utilisation de techniques d’authentification (ex. identifiant unique) | E37: Des techniques d’authentification, comme un identifiant unique, sont-elles utilisées ? | F37: oui | G37: Rapport décrivant les techniques d’authentification utilisées | H37: Usurpation d’identité | I37: Moyen | J37: Accès frauduleux, actions malveillantes au nom d'un utilisateur légitime | K37: Mettre en œuvre un processus d’approbation pour toute demande d’accès sensible
D38: Documentation des processus d’identification des utilisateurs | E38: Les processus d’identification des utilisateurs sont-ils documentés ? | F38: oui | G38: Documentation des processus d’identification des utilisateurs | H38: Gestion inadéquate des accès | I38: Moyen | J38: Exposition accrue aux menaces internes/externes | K38: Effectuer des contrôles réguliers pour détecter toute erreur ou abus
D39: Validation des identifiants par l’administration | E39: Les identifiants des utilisateurs sont-ils validés par l’administration ? | F39: oui | G39: Validation des identifiants par l’administration | H39: Erreurs ou abus | I39: Élevé | J39: Modifications non autorisées, fuites de données | K39: Utiliser des outils de détection d’anomalies pour repérer les failles de sécurité
D40: Fréquence des audits sur le processus d’identification | E40: Le processus d’identification est-il audité régulièrement ? | F40: oui | G40: Rapport des audits réguliers sur le processus d’identification | H40: Failles non détectées | I40: Élevé | J40: Exploitation par des attaquants, incidents majeurs | K40: Mettre à jour les correctifs de sécurité dès leur publication
D41: Suivi des tentatives d’usurpation d’identité | E41: Le suivi des tentatives d’usurpation d’identité est-il assuré ? | F41: non | G41: Rapport de suivi des tentatives d’usurpation d’identité | H41: Sécurité compromise | I41: Moyen | J41: Perte de confidentialité/intégrité des données | K41: Imposer des règles de complexité et de renouvellement des mots de passe
C42: S’assurer que le projet est cohérent avec le plan directeur informatique ; | D42: Présence obligatoire d’un mot de passe pour chaque utilisateur | E42: Un mot de passe est-il obligatoire pour chaque utilisateur ? | F42: oui | G42: Preuve de la présence obligatoire d’un mot de passe pour chaque utilisateur | H42: Accès non sécurisé | I42: Élevé | J42: Interceptions de données, attaques MITM | K42: Supprimer ou renouveler immédiatement les mots de passe obsolètes
D43: Respect des critères de complexité des mots de passe | E43: Les critères de complexité des mots de passe sont-ils respectés ? | F43: oui | G43: Document décrivant les critères de complexité des mots de passe | H43: Mot de passe vulnérable | I43: Élevé | J43: Piratage de comptes par force brute | K43: Mettre en place des systèmes de détection d’intrusion pour repérer les tentatives
D44: Fréquence de mise à jour des mots de passe | E44: La fréquence de mise à jour des mots de passe est-elle suffisante ? | F44: pas | G44: Rapport de mise à jour des mots de passe | H44: Usurpation via des mots de passe obsolètes | I44: Élevé | J44: Accès avec d'anciens identifiants non révoqués | K44: Sensibiliser les utilisateurs aux bonnes pratiques de cybersécurité
D45: Suivi des tentatives de connexion avec des mots de passe incorrects | E45: Le suivi des tentatives de connexion avec des mots de passe incorrects est-il effectué ? | F45: oui | G45: Journal des tentatives de connexion avec des mots de passe incorrects | H45: Tentatives non détectées | I45: Élevé | J45: Attaques réussies faute d'alertes | K45: Utiliser des outils de diagnostic avancés pour renforcer la détection des menaces
D46: Sensibilisation des utilisateurs aux bonnes pratiques de mot de passe | E46: Les utilisateurs sont-ils sensibilisés aux bonnes pratiques de mot de passe ? | F46: non | G46: Programme de sensibilisation aux bonnes pratiques de mot de passe | H46: Comportements à risque des utilisateurs | I46: Élevé | J46: Partage de comptes, négligence sécuritaire | K46: Instaurer une veille continue sur les nouvelles menaces et failles potentielles
C47: S’assurer que le projet est cohérent avec le SI actuel ou futur ; | D47: Enregistrement des tentatives de connexion infructueuses | E47: Les tentatives de connexion infructueuses sont-elles enregistrées ? | F47: non | G47: Journal des tentatives de connexion infructueuses | H47: Diagnostics incomplets | I47: Moyen | J47: Évaluations erronées des vulnérabilités | K47: Former les équipes à la réponse aux incidents et établir un plan de gestion de crise
D48: Analyse régulière des logs de connexion | E48: Les logs de connexion sont-ils analysés régulièrement ? | F48: pas | G48: Rapport d’analyse régulière des logs de connexion | H48: Menaces non identifiées | I48: Moyen | J48: Exposition à des attaques connues non corrigées | K48: Surveiller en continu le réseau pour détecter toute activité malveillante
D49: Signalement des anomalies détectées aux responsables | E49: Les anomalies détectées sont-elles signalées aux responsables ? | F49: pas | G49: Signalements des anomalies détectées aux responsables | H49: Réponses inappropriées | I49: Moyen | J49: Aggravation des incidents, temps d'indisponibilité accru | K49: Protéger les journaux système et activer l’audit pour garantir la traçabilité
D50: Présence d’un seuil de blocage après plusieurs tentatives échouées | E50: Un seuil de blocage est-il appliqué après plusieurs tentatives échouées ? | F50: oui | G50: Rapport définissant le seuil de blocage après plusieurs tentatives échouées | H50: Attaques persistantes | I50: Élevé | J50: Pénétration prolongée dans le système | K50: Mettre en place une politique de conservation et d’archivage des données
D51: Mise en œuvre de mesures correctives pour les connexions suspectes | E51: Des mesures correctives pour les connexions suspectes sont-elles mises en œuvre ? | F51: oui | G51: Plan d’action pour corriger les connexions suspectes | H51: Sécurité altérée | I51: Élevé | J51: Perte de confiance des parties prenantes | K51: Adopter une méthode de documentation rigoureuse des processus et décisions
B52: Planification | C52: S’assurer qu’il existe un planning directeur commun à tout le projet ; | D52: Disponibilité d’un journal de suivi des tâches | E52: Un journal de suivi des tâches est-il disponible ? | F52: oui | G52: Journal de suivi des tâches disponibles | H52: Perte de traçabilité | I52: Élevé | J52: Impossibilité de retracer les actions et modifications | K52: Utiliser des outils collaboratifs pour améliorer la coordination et le partage d’information
D53: Fréquence des mises à jour du journal de suivi | E53: Le journal de suivi des tâches est-il mis à jour régulièrement ? | F53: oui | G53: Rapport des mises à jour régulières du journal de suivi | H53: Informations périmées | I53: Élevé | J53: Utilisation d'informations non valides | K53: Archivage automatique des historiques pour assurer la continuité et la traçabilité
D54: Documentation des processus liés au développement et à l'exploitation | E54: Les processus liés au développement et à l'exploitation sont-ils documentés ? | F54: oui | G54: Document décrivant les processus liés au développement et à l’exploitation | H54: Confusion et inefficacité | I54: Moyen | J54: Désorganisation, perte de temps | K54: Superviser en temps réel les accès sensibles et les tentatives d’intrusion
D55: Validation des tâches par les responsables | E55: Les tâches sont-elles validées par les responsables ? | F55: pas | G55: Validation des tâches par les responsables | H55: Mauvaise coordination | I55: Élevé | J55: Actions non coordonnées entre services | K55: Mettre en œuvre une gestion centralisée des droits d’accès
D56: Archivage des anciennes tâches pour référence future | E56: Les anciennes tâches sont-elles archivées pour référence future ? | F56: oui | G56: Archives des anciennes tâches pour référence future | H56: Perte d’historique | I56: Moyen | J56: Absence d'archivage des activités passées | K56: Auditer régulièrement les permissions et corriger les anomalies détectées
C57: S’assurer qu’il existe un plan de projet initial ; | D57: Documentation des droits d’accès aux bibliothèques de production | E57: Les droits d’accès aux bibliothèques de production sont-ils documentés ? | F57: non | G57: Documentation des droits d’accès aux bibliothèques de production | H57: Confusion ou d’abus | I57: Élevé | J57: Utilisation abusive des ressources | K57: Bloquer toute tentative de modification non autorisée via des contrôles d’intégrité
D58: Présence d’un système de gestion des accès | E58: Un système de gestion des accès est-il en place pour les bibliothèques de production ? | F58: oui | G58: Rapport sur la présence d’un système de gestion des accès | H58: Accès non autorisé | I58: Élevé | J58: Accès illégitimes à des données sensibles | K58: Définir clairement les tâches dans les outils de gestion de projet ou de tickets
D59: Validation des autorisations par les responsables | E59: Les autorisations d’accès aux bibliothèques de production ont-elles été validées par les responsables ? | F59: pas | G59: Validation des autorisations par les responsables | H59: Mauvaise gestion des droits | I59: Moyen | J59: Droits d'accès mal attribués | K59: Établir une cartographie des rôles et responsabilités métier
D60: Fréquence des audits des accès | E60: Les audits des accès aux bibliothèques de production sont-ils réalisés régulièrement ? | F60: pas | G60: Rapport des audits réguliers des accès | H60: Failles non détectées | I60: Élevé | J60: Vulnérabilités persistantes non corrigées | K60: Séparer les fonctions critiques pour éviter les conflits d’intérêt ou abus
D61: Restrictions sur les modifications non autorisées | E61: Des restrictions sont-elles en place pour éviter les modifications non autorisées ? | F61: oui | G61: Rapport décrivant les restrictions pour éviter les modifications non autorisées | H61: Manque de contrôle sur les modifications non autorisées | I61: Moyen | J61: Modifications frauduleuses non détectées | K61: Mettre en place des mécanismes de suivi pour assurer la correction effective des anomalies
C62: S’assurer que ce plan de projet a été révisé ; | D62: Existence de rôles clairement définis pour chaque tâche | E62: Des rôles clairement définis pour chaque tâche existent-ils ? | F62: oui | G62: Liste des rôles clairement définis pour chaque tâche | H62: Confusion dans l’attribution des tâches | I62: Moyen | J62: Chevauchement ou omission de tâches | K62: Créer une structure de gouvernance claire avec des rôles, responsabilités et processus bien définis
D63: Documentation formelle des responsabilités par rôle | E63: Les responsabilités de chaque rôle sont-elles documentées formellement ? | F63: oui | G63: Document formel décrivant les responsabilités de chaque rôle | H63: Flou dans les obligations des rôles | I63: Élevé | J63: Responsabilités mal définies | K63: Élaborer une matrice RACI pour clarifier les responsabilités et éviter les chevauchements
D64: Fréquence des audits pour vérifier la séparation des tâches | E64: Des audits pour vérifier la séparation des tâches sont-ils effectués régulièrement ? | F64: pas | G64: Rapports d’audits vérifiant la séparation des tâches | H64: Non-respect des séparations de tâches | I64: Élevé | J64: Risques de fraude ou d'erreurs accrues | K64: Utiliser un outil de gestion documentaire et consigner systématiquement les décisions importantes
D65: Mesures correctives en cas de non-respect des séparations | E65: Des mesures correctives sont-elles mises en place en cas de non-respect des séparations ? | F65: non | G65: Plan d’action avec mesures correctives en cas de non-respect des séparations | H65: Maintien des dysfonctionnements en cas de non-correction | I65: Moyen | J65: Persistance des problèmes non résolus | K65: Mettre en place un calendrier de réunions de gouvernance avec un suivi rigoureux des décisions
D66: Validation par la direction des pratiques de séparation | E66: Les pratiques de séparation des tâches ont-elles été validées par la direction ? | F66: non | G66: Validation officielle des pratiques de séparation des tâches par la direction | H66: Pratiques inefficaces validées par la direction | I66: Moyen | J66: Validation d'approches inefficaces | K66: Renforcer la communication interne sur le rôle et l'importance des instances de gouvernance
C67: S’assurer qu’il existe des plans détaillés ; | D67: Formation régulière des membres de l’équipe | E67: Les membres de l’équipe reçoivent-ils une formation régulière ? | F67: oui | G67: Rapports de formation régulière des membres de l’équipe | H67: Manque de compétences au sein de l’équipe | I67: Élevé | J67: Incapacité à réaliser certaines tâches critiques | K67: Adopter un référentiel de gestion des applications et centraliser les décisions d’urbanisation du SI
D68: Documentation des compétences requises pour la maintenance | E68: Les compétences requises pour la maintenance sont-elles documentées ? | F68: pas | G68: Documentation des compétences requises pour la maintenance | H68: Perte de savoir-faire non documenté | I68: Moyen | J68: Disparition de connaissances importantes | K68: Aligner systématiquement les projets sur les orientations stratégiques définies par la direction
D69: Tests périodiques pour vérifier l’autonomie de l’équipe | E69: Des tests périodiques sont-ils effectués pour vérifier l’autonomie de l’équipe ? | F69: oui | G69: Rapports de tests périodiques sur l’autonomie de l’équipe | H69: Autonomie non garantie pour l’équipe | I69: Élevé | J69: Dépendance excessive à certains collaborateurs | K69: Mettre à jour régulièrement les directives en fonction de l’évolution des besoins et des technologies
D70: Fréquence des évaluations de performance | E70: Les évaluations de performance sont-elles réalisées régulièrement ? | F70: oui | G70: Rapports d’évaluations de performance | H70: Baisse de productivité due à l’absence d’évaluations | I70: Élevé | J70: Ralentissement des activités | K70: Former les équipes aux directives internes et instaurer des contrôles pour vérifier leur application
D71: Présence de plans de relève ou de formation en cas de changement dans l’équipe | E71: Des plans de relève ou de formation sont-ils disponibles en cas de changement dans l’équipe ? | F71: oui | G71: Plan de relève ou de formation pour l’équipe en cas de changement | H71: Rupture dans la continuité opérationnelle en cas de changement | I71: Moyen | J71: Interruptions de service lors de transitions | K71: Documenter, suivre et corriger systématiquement tous les écarts détectés lors des audits ou contrôles
C72: S’assurer que ces plans ont été révisés ; | D72: Documentation des procédures de maintenance formalisées | E72: Les procédures de maintenance sont-elles documentées formellement ? | F72: pas | G72: Document formalisé des procédures de maintenance | H72: Non-conformité aux standards dus à l’absence de procédures documentées | I72: Élevé | J72: Non-respect des réglementations en vigueur | K72: Mettre en place un système de validation des affectations avec relecture croisée des responsabilités
D73: Fréquence des mises à jour des procédures | E73: Les procédures de maintenance sont-elles mises à jour régulièrement ? | F73: oui | G73: Historique des mises à jour régulières des procédures de maintenance | H73: Utilisation de directives obsolètes | I73: Élevé | J73: Application de règles inadaptées à la situation actuelle | K73: Former les collaborateurs aux bonnes pratiques opérationnelles et outils métiers
D74: Validation des procédures par les experts techniques | E74: Les procédures de maintenance ont-elles été validées par des experts techniques ? | F74: oui | G74: Validation des procédures de maintenance par des experts techniques | H74: Contenu incorrect des procédures non validées | I74: Élevé | J74: Mise en œuvre de processus erronés ou incomplets | K74: Renforcer le contrôle d’accès avec des outils de gestion des identités et des accès (IAM)
D75: Disponibilité des procédures pour les équipes concernées | E75: Les procédures sont-elles disponibles pour les équipes concernées ? | F75: oui | G75: Preuve de disponibilité des procédures pour les équipes concernées | H75: Mauvaise application des processus par les équipes | I75: Moyen | J75: Non-respect des standards et procédures établies | K75: Clarifier les fiches de poste et les responsabilités associées à chaque fonction
D76: Archivage des anciennes versions des procédures | E76: Les anciennes versions des procédures sont-elles archivées ? | F76: oui | G76: Archives des anciennes versions des procédures | H76: Perte d’historique des versions de procédures | I76: Élevé | J76: Impossibilité de consulter l'évolution des méthodes | K76: Former les utilisateurs aux outils internes et mesurer leur taux d’adoption
B77: Instances de pilotage | C77: S’assurer que la structure de pilotage est formalisée et connue de tous les acteurs ; | D77: Présence d’un document formel du Schéma-directeur | E77: Un document formel du Schéma-directeur est-il disponible ? | F77: pas | G77: Document officiel du Schéma-directeur du système d’information | H77: Absence de vision stratégique en raison d’un Schéma-directeur inexistant | I77: Élevé | J77: Absence de ligne directrice claire | K77: Sensibiliser régulièrement les équipes aux risques de cybersécurité et aux menaces émergentes
D78: Date de la dernière mise à jour documentée | E78: La date de la dernière mise à jour du Schéma-directeur est-elle documentée ? | F78: pas | G78: Historique de la dernière mise à jour du Schéma-directeur | H78: Stratégie non actualisée en raison d’une mise à jour non documentée | I78: Élevé | J78: Stratégie non adaptée à l'environnement actuel | K78: Mettre en place des tests de sécurité préventifs et plans de reprise d’activité
D79: Validation du Schéma-directeur par la direction | E79: Le Schéma-directeur a-t-il été validé par la direction ? | F79: pas | G79: Validation officielle du Schéma-directeur par la direction | H79: Non-adhésion des décideurs à un Schéma-directeur non validé | I79: Moyen | J79: Manque d'engagement de la direction | K79: Renforcer les contrôles d’accès physique et logique pour limiter l’exposition aux menaces
D80: Alignement du Schéma-directeur avec les objectifs stratégiques de l’organisation | E80: Le Schéma-directeur est-il aligné avec les objectifs stratégiques de l’organisation ? | F80: pas | G80: Rapport d’alignement du Schéma-directeur avec les objectifs stratégiques | H80: Désalignement stratégique dû à un Schéma non aligné avec les objectifs | I80: Moyen | J80: Incohérence entre les actions et les objectifs | K80: Favoriser l’adhésion par la communication des résultats et l’implication dans la définition des objectifs
D81: Accessibilité du document pour les parties prenantes | E81: Le document du Schéma-directeur est-il accessible aux parties prenantes ? | F81: pas | G81: Preuve d’accessibilité du document du Schéma-directeur pour les parties prenantes | H81: Sous-utilisation du Schéma-directeur en raison de son inaccessibilité | I81: Moyen | J81: Faible utilisation des outils stratégiques | K81: Mettre en place un système de collecte et de mise à jour automatique des données stratégiques
C82: S’assurer que les différentes instances de pilotage connaissent leurs niveaux de délégation ; | D82: Documentation de l’évaluation réalisée | E82: Une évaluation a-t-elle été documentée ? | F82: non | G82: Rapport documentant l’évaluation réalisée | H82: Décisions basées sur des données insuffisantes dues à une évaluation non documentée | I82: Moyen | J82: Prise de décision sur des bases fragiles | K82: Effectuer des analyses de vulnérabilités régulières et audits de sécurité du SI
D83: Preuves d’analyse des objectifs stratégiques de l’entreprise | E83: Des preuves d’analyse des objectifs stratégiques de l’entreprise sont-elles disponibles ? | F83: oui | G83: Preuves d’analyse des objectifs stratégiques de l’entreprise | H83: Diagnostic incomplet en raison de l’absence de preuves d’analyse stratégique | I83: Élevé | J83: Analyse incomplète des orientations | K83: Compléter les évaluations de risques par des audits indépendants et des tests d’intrusion
D84: Participation des responsables stratégiques à l’évaluation | E84: Les responsables stratégiques ont-ils participé à l’évaluation ? | F84: oui | G84: Rapport de participation des responsables stratégiques à l’évaluation | H84: Manque de pertinence dû à l’absence de participation des responsables stratégiques | I84: Moyen | J84: Pertinence limitée des choix stratégiques | K84: Mettre en place un processus de validation croisée des résultats d’analyse
D85: Validation des résultats de l’évaluation | E85: Les résultats de l’évaluation ont-ils été validés ? | F85: pas | G85: Validation des résultats de l’évaluation par les parties prenantes | H85: Mise en œuvre non approuvée en raison de résultats non validés | I85: Moyen | J85: Validation impossible des décisions prises | K85: Adopter une veille technologique pour anticiper les nouveaux risques et adapter les solutions
D86: Fréquence des révisions pour vérifier l’alignement continu | E86: Des révisions sont-elles réalisées fréquemment pour vérifier l’alignement continu ? | F86: oui | G86: Rapports de révisions fréquentes pour vérifier l’alignement stratégique continu | H86: Perte de pertinence stratégique sans révisions fréquentes | I86: Élevé | J86: Perte d'alignement avec les besoins réels | K86: Instaurer un cadre de concertation avec les parties prenantes pour la prise de décision
C87: S’assurer que les objectifs des délégations sont atteints ; | D87: Documentation des spécifications ou critères de choix formalisés | E87: Les spécifications ou critères de choix sont-ils documentés de manière formelle ? | F87: oui | G87: Documentation des spécifications ou critères de choix | H87: Décisions basées sur des informations non formalisées dues à des spécifications non documentées | I87: Élevé | J87: Décisions basées sur des informations non structurées | K87: Renforcer les politiques d’accès avec des règles de moindre privilège strictement appliquées
D88: Validation des critères par les parties prenantes | E88: Les critères ont-ils été validés par les parties prenantes ? | F88: oui | G88: Validation des spécifications ou critères de choix par les parties prenantes | H88: Critères non conformes aux attentes faute de validation | I88: Moyen | J88: Exigences ne correspondant pas aux attentes | K88: Mettre en place des contrôles pour éviter les abus ou les confusions dans la gestion des accès
D89: Alignement des critères avec les besoins fonctionnels identifiés | E89: Les critères sont-ils alignés avec les besoins fonctionnels identifiés ? | F89: oui | G89: Rapport d’alignement des critères avec les besoins fonctionnels identifiés | H89: Non-adéquation aux besoins fonctionnels due à des spécifications non alignées | I89: Moyen | J89: Solutions inadaptées aux besoins utilisateurs | K89: Mettre à jour régulièrement les permissions et supprimer les accès obsolètes
D90: Fréquence des mises à jour des spécifications | E90: Les spécifications sont-elles mises à jour fréquemment ? | F90: oui | G90: Historique des mises à jour fréquentes des spécifications | H90: Obsolescence des critères liée à la rareté des mises à jour des spécifications | I90: Moyen | J90: Critères de décision dépassés | K90: Utiliser des outils d’audit pour surveiller l’attribution et l’utilisation des privilèges
D91: Archivage des décisions prises pour traçabilité | E91: Les décisions prises sont-elles archivées pour assurer une traçabilité ? | F91: non | G91: Rapport d'archivage des décisions prises pour la traçabilité | H91: Perte de traçabilité due à des décisions non archivées | I91: Moyen | J91: Impossibilité de retracer l'historique des décisions | K91: Automatiser la gestion du cycle de vie des utilisateurs et leurs accès
C92: S’assurer qu’il existe un comité de pilotage ; | D92: Existence d’une liste des tâches par utilisateur ou rôle | E92: Une liste des tâches par utilisateur ou rôle existe-t-elle ? | F92: oui | G92: Liste des tâches par utilisateur ou rôle | H92: Attribution chaotique des responsabilités en raison d’une liste des tâches absente | I92: Moyen | J92: Confusion dans la répartition des rôles et missions | K92: Mettre en œuvre des procédures claires de création, modification et suppression des comptes
D93: Documentation des responsabilités associées à chaque tâche | E93: Les responsabilités associées à chaque tâche sont-elles documentées ? | F93: oui | G93: Document des responsabilités associées à chaque tâche | H93: Flou organisationnel dû à des responsabilités non documentées | I93: Élevé | J93: Ambiguïté persistante sur qui fait quoi | K93: Attribuer les permissions selon le principe du moindre privilège
D94: Communication des tâches aux utilisateurs concernés | E94: Les tâches sont-elles communiquées aux utilisateurs concernés ? | F94: oui | G94: Preuve de communication des tâches aux utilisateurs concernés | H94: Mauvaise exécution par les utilisateurs faute de communication des tâches | I94: Moyen | J94: Non-réalisation des tâches par méconnaissance | K94: Mettre en place un système de suivi et de journalisation pour assurer la traçabilité
D95: Fréquence des mises à jour des descriptions de tâches | E95: Les descriptions de tâches sont-elles mises à jour régulièrement ? | F95: non | G95: Historique des mises à jour des descriptions de tâches | H95: Incohérence dans les fonctions dues à des descriptions de tâches non mises à jour | I95: Moyen | J95: Incohérences dans les rôles et fonctions | K95: Mettre à jour régulièrement les profils utilisateurs et valider leur adéquation aux rôles
D96: Validation par les responsables des tâches définies | E96: Les tâches définies sont-elles validées par les responsables ? | F96: non | G96: Validation des tâches définies par les responsables | H96: Erreurs opérationnelles dues à des tâches non validées par les responsables | I96: Élevé | J96: Erreurs répétées par manque de validation | K96: Utiliser l’authentification multifactorielle pour prévenir l’usurpation d’identité
C97: S’assurer qu’il existe un comité de projet ; | D97: Documentation des systèmes parallèles actifs | E97: Les systèmes parallèles actifs sont-ils documentés ? | F97: oui | G97: Documentation des systèmes parallèles actifs | H97: Mauvaise gestion des redondances en raison de systèmes parallèles non documentés | I97: Moyen | J97: Duplication inutile des processus | K97: Mettre en œuvre un processus d’approbation pour toute demande d’accès sensible
D98: Justification formelle du maintien des systèmes parallèles | E98: Une justification formelle du maintien des systèmes parallèles existe-t-elle ? | F98: oui | G98: Justification formelle du maintien des systèmes parallèles | H98: Inefficacité des ressources sans justification des systèmes parallèles | I98: Moyen | J98: Gaspillage des ressources disponibles | K98: Effectuer des contrôles réguliers pour détecter toute erreur ou abus
D99: Fréquence des vérifications de la performance des systèmes parallèles | E99: La performance des systèmes parallèles est-elle vérifiée régulièrement ? | F99: non | G99: Rapport de vérification des performances des systèmes parallèles | H99: Sous-optimisation des systèmes faute de vérification des performances | I99: Élevé | J99: Performance globale sous-optimale | K99: Utiliser des outils de détection d’anomalies pour repérer les failles de sécurité
D100: Documentation des liens entre les systèmes parallèles et les principaux systèmes | E100: Les liens entre les systèmes parallèles et les principaux systèmes sont-ils documentés ? | F100: oui | G100: Documentation des liens entre les systèmes parallèles et les systèmes principaux | H100: Désalignement technologique dû à des liens non documentés entre systèmes | I100: Élevé | J100: Incompatibilité entre les systèmes | K100: Mettre à jour les correctifs de sécurité dès leur publication
...

Sheet 4.4
A1: Domaine | B1: Points de contrôle | C1: Objectifs de contrôle | D1: Critères d'évaluation | E1: Questions d'évaluation | F1: Réponses | G1: Documents requis | H1: risques | I1: Criticités | J1: Conséquences | K1: Recommandations
A2: Support Utilisateur | B2: Fiabilité et sécurité | C2: S’assurer qu’une structure de centre d’assistance (help-desk) (HD) est mise en place | D2: La structure du help-desk dispose d'une charte écrite formalisant ses missions. | E2: La structure du help-desk dispose-t-elle d'une charte écrite formalisant ses missions ? | F2: OUI | G2: Charte officielle du help-desk | H2: Missions mal définies | I2: Négligeable | J2: Missions mal définies | K2: formaliser des fiches de poste détaillées avec responsabilités claires
G3: Procès-verbal de validation | H3: Absence de cadre formel | I3: Mineure | J3: Dérive des responsabilités et conflits internes | K3: implémenter une matrice RACI validée par la direction
D4: Les utilisateurs accèdent au help-desk via au moins deux canaux distincts. | E4: Les utilisateurs accèdent-ils au help-desk via au moins deux canaux distincts ? | F4: OUI | G4: Liste des canaux supportés | H4: Canal unique défaillant | I4: Majeure | J4: Absence de cadre formel | K4: rédiger un manuel procédural conforme aux normes ISO
F5: NON | G5: Statistiques d'utilisation | H5: Couverture insuffisante | I5: Négligeable | J5: Non-conformité réglementaire et risques juridiques | K5: réaliser un audit juridique trimestriel avec compliance
D6: Un SLA documenté précise les délais de traitement par typologie de demande. | E6: Un SLA documenté précise-t-il les délais de traitement par typologie de demande ? | F6: OUI | G6: Contrat SLA signé | H6: Délais non respectés | I6: Mineure | J6: Canal unique défaillant | K6: déployer une architecture redondante active/active
F7: OUI | G7: Grille des délais opérationnels | H7: Typologies mal classées | I7: Critique | J7: Interruption totale du service en cas de panne | K7: établir un plan de continuité testé semestriellement
D8: Les agents du help-desk suivent une formation annuelle sur les procédures. | E8: Les agents du help-desk suivent-ils une formation annuelle sur les procédures ? | F8: NON | G8: Registre des formations | H8: Procédures mal appliquées | I8: Négligeable | J8: Couverture insuffisante | K8: cartographier l'ensemble des personas utilisateurs
F9: OUI | G9: Attestations de formation | H9: Formations obsolètes | I9: Mineure | J9: Exclusion de certaines catégories d'utilisateurs | K9: créer des parcours utilisateurs différenciés
D10: Un outil de suivi des tickets enregistre systématiquement les demandes. | E10: Un outil de suivi des tickets enregistre-t-il systématiquement les demandes ? | F10: NON | G10: Journal des tickets créés | H10: Demandes perdues | I10: Majeure | J10: Délais non respectés | K10: mettre en place un système de tracking temps réel
F11: OUI | G11: Procédure d'enregistrement | H11: Pannes du système | I11: Négligeable | J11: Perte de confiance des clients et pénalités contractuelles | K11: instaurer des clauses pénales automatiques dans les contrats
C12: S’assurer qu’une procédure de gestion des demandes d’assistance est diffusée et connue des utilisateurs | D12: La procédure de gestion des demandes est publiée sur l'intranet de l'entreprise. | E12: La procédure de gestion des demandes est-elle publiée sur l'intranet de l'entreprise ? | F12: NON | G12: Capture d'écran intranet | H12: Procédure non accessible | I12: Blocante | J12: Typologies mal classées | K12: standardiser la taxonomie via ateliers métiers
F13: OUI | G13: Historique des versions | H13: Version non actualisée | I13: Négligeable | J13: Impossibilité de priorisation efficace des demandes | K13: développer un moteur de priorisation basé sur l'impact métier
D14: Les nouveaux employés reçoivent une formation incluant cette procédure. | E14: Les nouveaux employés reçoivent-ils une formation incluant cette procédure ? | F14: NON | G14: Programme de formation nouveaux | H14: Nouveaux agents non formés | I14: Mineure | J14: Procédures mal appliquées | K14: digitaliser les workflows avec contrôles d'étapes obligatoires
F15: NON | G15: Liste des participants formés | H15: Intégration incomplète | I15: Négligeable | J15: Incohérence dans le traitement des demandes | K15: organiser des audits croisés bimensuels
D16: Des rappels réguliers sont envoyés aux utilisateurs concernant cette procédure. | E16: Des rappels réguliers sont-ils envoyés aux utilisateurs concernant cette procédure ? | F16: OUI | G16: Calendrier des rappels | H16: Oubli des bonnes pratiques | I16: Majeure | J16: Formations obsolètes | K16: lancer un programme de reskilling trimestriel obligatoire
F17: OUI | G17: Preuves d'envoi | H17: Communication irrégulière | I17: Mineure | J17: Incapacité à répondre aux nouveaux besoins | K17: créer un comité veille technologique hebdomadaire
D18: La procédure est disponible en version imprimable sur demande. | E18: La procédure est-elle disponible en version imprimable sur demande ? | F18: NON | G18: Version imprimable disponible | H18: Indisponibilité des versions imprimées | I18: Négligeable | J18: Demandes perdues | K18: implémenter un système de ticketing avec accusé réception
F19: OUI | G19: Registre des demandes | H19: Support non préparé | I19: Critique | J19: Insatisfaction client et contentieux | K19: instaurer des surveys de satisfaction liés aux bonus
D20: Un responsable est désigné pour mettre à jour annuellement cette procédure. | E20: Un responsable est-il désigné pour mettre à jour annuellement cette procédure ? | F20: NON | G20: Fiche de poste responsable | H20: Procédures obsolètes | I20: Mineure | J20: Pannes du système | K20: migrer vers une infrastructure cloud haute disponibilité
F21: OUI | G21: Procès-verbal de nomination | H21: Mises à jour retardées | I21: Négligeable | J21: Arrêt complet des opérations | K21: documenter les procédures de secours dans un wiki sécurisé
C22: S’assurer qu’une procédure d'escalade mise en place | D22: La procédure d'escalade définit clairement les niveaux d'intervention. | E22: La procédure d'escalade définit-elle clairement les niveaux d'intervention ? | F22: OUI | G22: Procédure d'escalade écrite | H22: Flou dans les niveaux d'intervention | I22: Majeure | J22: Procédure non accessible | K22: automatiser les mises à jour via pipeline CI/CD
F23: NON | G23: Seuils quantitatifs documentés | H23: Hiérarchie mal définie | I23: Mineure | J23: Improvisation et erreurs récurrentes | K23: budgétiser 30 jours de formation pour nouveaux hires
D24: Les seuils de déclenchement de l'escalade sont quantifiés et mesurables. | E24: Les seuils de déclenchement de l'escalade sont-ils quantifiés et mesurables ? | F24: NON | G24: Annuaire des contacts | H24: Seuils d'escalade mal calibrés | I24: Négligeable | J24: Version non actualisée | K24: développer des simulateurs opérationnels en VR
F25: OUI | G25: Journal des mises à jour | H25: Détection tardive | I25: Négligeable | J25: Application de règles obsolètes | K25: auditer les interfaces système tous les trimestres
D26: Les contacts pour chaque niveau d'escalade sont à jour et accessibles. | E26: Les contacts pour chaque niveau d'escalade sont-ils à jour et accessibles ? | F26: NON | G26: Délais formalisés écrits | H26: Contacts indisponibles en urgence | I26: Mineure | J26: Nouveaux agents non formés | K26: créer des communautés de pratique par métier
F27: OUI | G27: Base de données historique | H27: Liste non actualisée | I27: Majeure | J27: Erreurs opérationnelles fréquentes | K27: documenter les best practices dans un knowledge base
D28: Les délais de réponse pour chaque niveau d'escalade sont formalisés. | E28: Les délais de réponse pour chaque niveau d'escalade sont-ils formalisés ? | F28: NON | G28: Cartographie des implantations | H28: Délais non standardisés | I28: Négligeable | J28: Intégration incomplète | K28: instaurer des stand-ups quotidiens pour l'alignement
F29: OUI | G29: Plannings des fuseaux horaires | H29: Variations inexpliquées | I29: Blocante | J29: Fonctionnalités inutilisables | K29: maintenir une documentation papier dans des coffres sécurisés
D30: Un historique des escalades est conservé pour analyse ultérieure. | E30: Un historique des escalades est-il conservé pour analyse ultérieure ? | F30: NON | G30: Liste des langues supportées | H30: Impossibilité d'analyser les tendances | I30: Mineure | J30: Oubli des bonnes pratiques | K30: constituer une task force crise permanente
F31: OUI | G31: Plan de continuité d'activité | H31: Données corrompues | I31: Négligeable | J31: Dégradation progressive de la qualité | K31: réviser les procédures via design sprints mensuels
C32: S’assurer de la couverture géographique du HD | D32: Le HD couvre toutes les zones géographiques où l'entreprise opère. | E32: Le HD couvre-t-il toutes les zones géographiques où l'entreprise opère ? | F32: OUI | G32: Statistiques mensuelles | H32: Zones géographiques non couvertes | I32: Majeure | J32: Communication irrégulière | K32: adopter le framework ITIL v4 pour la gouvernance
F33: NON | G33: Rapports de couverture | H33: Déséquilibre régional | I33: Mineure | J33: Incompréhension et frustration des équipes | K33: déployer un système de patch management automatisé
D34: Les horaires de couverture sont adaptés aux fuseaux horaires concernés. | E34: Les horaires de couverture sont-ils adaptés aux fuseaux horaires concernés ? | F34: OUI | G34: Inventaire des applications | H34: Décalage horaire non pris en compte | I34: Négligeable | J34: Indisponibilité des versions imprimées | K34: établir une matrice de criticité des interventions
F35: NON | G35: Référentiel des compétences | H35: Plannings rigides | I35: Critique | J35: Blocage des opérations en cas de panne numérique | K35: développer des playbooks d'escalade standardisés
D36: Les langues des zones couvertes sont prises en compte par le HD. | E36: Les langues des zones couvertes sont-elles prises en compte par le HD ? | F36: NON | G36: Matrice validée | H36: Barrière linguistique | I36: Mineure | J36: Support non préparé | K36: publier un organigramme dynamique avec RACI intégré
F37: OUI | G37: Procès-verbal d'approbation | H37: Traductions erronées | I37: Négligeable | J37: Incapacité à répondre aux demandes complexes | K37: implémenter des workflows électroniques avec approbations
D38: Un système de redondance existe pour les zones critiques. | E38: Un système de redondance existe-t-il pour les zones critiques ? | F38: OUI | G38: Procédure de transfert | H38: Défaillance des zones critiques | I38: Majeure | J38: Procédures obsolètes | K38: calibrer les seuils d'alerte via machine learning
F39: NON | G39: Journal des redirections | H39: Plan de secours absent | I39: Négligeable | J39: Non-conformité aux standards actuels | K39: installer un SIEM avec corrélation d'événements
D40: Les statistiques de couverture géographique sont mesurées mensuellement. | E40: Les statistiques de couverture géographique sont-elles mesurées mensuellement ? | F40: NON | G40: Plan de développement compétences | H40: Erreurs dans les statistiques de couverture | I40: Négligeable | J40: Mises à jour retardées | K40: mettre en place une astreinte tournante 24/7
F41: OUI | G41: Évaluations annuelles | H41: Données incomplètes | I41: Mineure | J41: Vulnérabilités non corrigées | K41: développer un annuaire unifié synchronisé en temps réel
C42: S’assurer de la couverture fonctionnelle du HD | D42: Le HD traite l'ensemble des applications métiers de l'entreprise. | E42: Le HD traite-t-il l'ensemble des applications métiers de l'entreprise ? | F42: NON | G42: Guide d'utilisation outil | H42: Applications métiers non supportées | I42: Majeure | J42: Flou dans les niveaux d'intervention | K42: standardiser les SLA via analyse des lead times
F43: OUI | G43: Configurations système | H43: Expertise manquante | I43: Négligeable | J43: Escalade inappropriée ou tardive | K43: automatiser les rapports d'écarts avec Power BI
D44: Les compétences techniques couvrent tous les domaines fonctionnels. | E44: Les compétences techniques couvrent-elles tous les domaines fonctionnels ? | F44: OUI | G44: Modèles d'accusés réception | H44: Compétences techniques insuffisantes | I44: Mineure | J44: Hiérarchie mal définie | K44: déployer des dashboards temps réel avec alertes
F45: NON | G45: Journal des envois | H45: Savoir-faire obsolète | I45: Critique | J45: Confusion dans la prise de décision | K45: implémenter des contrôles d'intégrité blockchain
D46: Une matrice de compétences par domaine fonctionnel existe. | E46: Une matrice de compétences par domaine fonctionnel existe-t-elle ? | F46: OUI | G46: Interface de suivi | H46: Matrice des compétences obsolète | I46: Négligeable | J46: Seuils d'escalade mal calibrés | K46: étendre la couverture via CDN et POPs locaux
F47: NON | G47: Paramètres d'alertes | H47: Mises à jour manquantes | I47: Mineure | J47: Interventions disproportionnées | K47: créer des packages régionaux adaptés
D48: Les demandes hors périmètre sont redirigées vers les services compétents. | E48: Les demandes hors périmètre sont-elles redirigées vers les services compétents ? | F48: NON | G48: Rapports statistiques | H48: Redirections inappropriées | I48: Majeure | J48: Détection tardive | K48: développer un système de routing géo-intelligent
F49: OUI | G49: Exports de données | H49: Retards de traitement | I49: Négligeable | J49: Aggravation des incidents | K49: recruter des linguistes pour les marchés critiques
D50: Un processus de mise à jour des compétences fonctionnelles est établi. | E50: Un processus de mise à jour des compétences fonctionnelles est-il établi ? | F50: OUI | G50: Liste des champs obligatoires | H50: Compétences non actualisées | I50: Négligeable | J50: Contacts indisponibles en urgence | K50: mettre en place un processus de validation multicouche
F51: NON | G51: Grille de qualification | H51: Évolution non suivie | I51: Mineure | J51: Retard critique dans la résolution | K51: concevoir des architectures en zones isolées
C52: S’assurer qu’un outil est implémenté pour la prise d'appel et le suivi des tickets | D52: L'outil de prise d'appel permet la création d'un ticket unique. | E52: L'outil de prise d'appel permet-il la création d'un ticket unique ? | F52: OUI | G52: Manuel technique de l'outil | H52: Erreurs de création de tickets | I52: Majeure | J52: Liste non actualisée | K52: automatiser la mise à jour des contacts via synchronisation Active Directory
F53: NON | G53: Journal des créations de tickets | H53: Duplications | I53: Négligeable | J53: Coordonnées erronées des intervenants | K53: implémenter un système de validation croisée des coordonnées bimestriel
D54: L'outil génère un accusé de réception automatique pour chaque demande. | E54: L'outil génère-t-il un accusé de réception automatique pour chaque demande ? | F54: OUI | G54: Modèles d'accusés de réception | H54: Absence d'accusé de réception | I54: Blocante | J54: Délais non standardisés | K54: établir des standards temporels via une étude time-motion
F55: NON | G55: Logs d'envois automatiques | H55: Problèmes techniques | I55: Mineure | J55: Inégalité de traitement | K55: développer un algorithme de répartition équitable des demandes
D56: L'outil permet le suivi de l'état d'avancement en temps réel. | E56: L'outil permet-il le suivi de l'état d'avancement en temps réel ? | F56: NON | G56: Interface de suivi en temps réel | H56: Suivi en temps réel impossible | I56: Négligeable | J56: Variations inexpliquées | K56: instrumenter les processus avec des traceurs de performance
F57: OUI | G57: Captures d'écran du système | H57: Latence du système | I57: Majeure | J57: Impossibilité d'optimisation | K57: déployer des outils d'analyse prédictive avec machine learning
D58: L'outil intègre un système de notification des dépassements de délai. | E58: L'outil intègre-t-il un système de notification des dépassements de délai ? | F58: NON | G58: Configuration des notifications | H58: Dépassements de délai non détectés | I58: Mineure | J58: Impossibilité d'analyser les tendances | K58: créer des tableaux de bord décisionnels avec indicateurs clés
F59: OUI | G59: Historique des alertes | H59: Alertes défaillantes | I59: Négligeable | J59: Décisions basées sur des intuitions | K59: implémenter des contrôles d'intégrité des données en temps réel
D60: L'outil produit des statistiques exploitables sur les tickets traités. | E60: L'outil produit-il des statistiques exploitables sur les tickets traités ? | F60: OUI | G60: Rapports statistiques consolidés | H60: Statistiques inexactes | I60: Critique | J60: Données corrompues | K60: développer un data warehouse avec mécanismes de cleansing
F61: NON | G61: Exports des données analytiques | H61: Biais d'analyse | I61: Mineure | J61: Analyses faussées et décisions erronées | K61: étendre l'infrastructure via des partenariats locaux certifiés
C62: S’assurer que des critères à renseigner pour la qualification des tickets existent | D62: Une liste des critères obligatoires pour qualifier un ticket existe. | E62: Une liste des critères obligatoires pour qualifier un ticket existe-t-elle ? | F62: NON | G62: Liste des champs obligatoires validée | H62: Critères de qualification incomplets | I62: Négligeable | J62: Zones géographiques non couvertes | K62: concevoir des parcours utilisateurs inclusifs (accessibilité)
F63: OUI | G63: Grille de classification des tickets | H63: Exigences floues | I63: Majeure | J63: Exclusion de certaines populations | K63: mettre en place un système de péréquation régionale
D64: Ces critères incluent la nature, l'urgence et l'impact de la demande. | E64: Ces critères incluent-ils la nature, l'urgence et l'impact de la demande ? | F64: NON | G64: Journal des rejets de tickets | H64: Nature/urgence/impact non évalués | I64: Négligeable | J64: Déséquilibre régional | K64: adapter les plages horaires avec suivi des timezones clients
F65: OUI | G65: Procès-verbal de révision des critères | H65: Priorisation erronée | I65: Négligeable | J65: Inégalité de service selon les territoires | K65: implémenter un système de priorisation dynamique des requêtes
D66: Le système empêche la création de tickets sans ces critères obligatoires. | E66: Le système empêche-t-il la création de tickets sans ces critères obligatoires ? | F66: NON | G66: Attestations de formation délivrées | H66: Tickets incomplets acceptés | I66: Mineure | J66: Décalage horaire non pris en compte | K66: déployer une solution d'elastic computing pour absorber les pics
F67: OUI | G67: Checklist opérationnelle approuvée | H67: Contrôles absents | I67: Majeure | J67: Délais de réponse inadaptés | K67: recruter des agents multilingues pour les marchés critiques
D68: Les critères sont régulièrement révisés en fonction des besoins. | E68: Les critères sont-ils régulièrement révisés en fonction des besoins ? | F68: OUI | G68: Guide d'entretien standardisé | H68: Critères obsolètes | I68: Négligeable | J68: Plannings rigides | K68: documenter les user stories via des ateliers avec utilisateurs finaux
F69: NON | G69: Base de connaissances techniques | H69: Adaptation insuffisante | I69: Mineure | J69: Impossibilité de faire face aux pics de demande | K69: établir un processus de validation des traductions par locuteurs natifs
D70: Une formation sur le renseignement des critères est dispensée aux agents. | E70: Une formation sur le renseignement des critères est-elle dispensée aux agents ? | F70: OUI | G70: Fiches processus métiers | H70: Mauvaise qualification des tickets | I70: Critique | J70: Barrière linguistique | K70: concevoir des architectures en zones autonomes sécurisées
F71: NON | G71: Registre des versions de checklist | H71: Erreurs humaines | I71: Négligeable | J71: Incompréhension des besoins réels | K71: développer un plan de reprise multisite testé trimestriellement
C72: S’assure qu’il existe une liste de questions à dérouler lors d'un appel afin préciser au mieux la demande de l'utilisateur | D72: Une checklist standardisée guide les agents lors des appels entrants. | E72: Une checklist standardisée guide-t-elle les agents lors des appels entrants ? | F72: NON | G72: Rapports d'analyse root cause | H72: Checklist non suivie | I72: Mineure | J72: Traductions erronées | K72: automatiser les rapports avec contrôles de cohérence algorithmiques
F73: OUI | G73: Base de données des solutions | H73: Procédures contournées | I73: Majeure | J73: Erreurs de traitement graves | K73: créer un comité stratégique alimenté par des data scientists
D74: Cette checklist couvre les informations techniques et fonctionnelles. | E74: Cette checklist couvre-t-elle les informations techniques et fonctionnelles ? | F74: NON | G74: Procédures de résolution temporaire | H74: Informations techniques manquantes | I74: Négligeable | J74: Défaillance des zones critiques | K74: implémenter des contrôles d'exhaustivité des datasets en ETL
F75: OUI | G75: Documentation des correctifs permanents | H75: Oublis fréquents | I75: Négligeable | J75: Impact majeur sur les opérations sensibles | K75: développer des API métiers avec documentation Swagger complète
D76: La checklist est adaptée à chaque type de demande récurrente. | E76: La checklist est-elle adaptée à chaque type de demande récurrente ? | F76: NON | G76: Protocole de communication de crise | H76: Inadaptation aux demandes récurrentes | I76: Mineure | J76: Plan de secours absent | K76: recruter un architecte fonctionnel senior par domaine critique
F77: OUI | G77: Tableaux de bord de résolution | H77: Modèles inappropriés | I77: Majeure | J77: Impossibilité de reprise après incident | K77: négocier des contrats de support premium avec les fournisseurs clés
D78: Les agents reçoivent une formation sur l'utilisation de cette checklist. | E78: Les agents reçoivent-ils une formation sur l'utilisation de cette checklist ? | F78: NON | G78: Fiche de poste des responsables | H78: Mauvaise utilisation de la checklist | I78: Négligeable | J78: Erreurs dans les statistiques de couverture | K78: lancer un programme de certification technique annuelle obligatoire
F79: OUI | G79: Grille des seuils d'intervention | H79: Formation insuffisante | I79: Blocante | J79: Décisions stratégiques inadaptées | K79: instituer des revues d'architecture trimestrielles avec benchmarks
D80: La checklist est mise à jour semestriellement en fonction des retours. | E80: La checklist est-elle mise à jour semestriellement en fonction des retours ? | F80: OUI | G80: Modèles de documentation d'analyse | H80: Checklist obsolète | I80: Mineure | J80: Données incomplètes | K80: migrer vers un référentiel de compétences dynamique (AI-powered)
F81: NON | G81: Workflow de validation signé | H81: Retours ignorés | I81: Négligeable | J81: Analyse partielle et biaisée | K81: digitaliser la GPEC avec outils de predictive analytics
C82: S’assurer que les problèmes sont gérés | D82: Les problèmes récurrents font l'objet d'une analyse root cause. | E82: Les problèmes récurrents font-ils l'objet d'une analyse root cause ? | F82: NON | G82: Procédure de revue qualité validée | H82: Problèmes récurrents non résolus | I82: Majeure | J82: Applications métiers non supportées | K82: automatiser les mises à jour via un système de package management
F83: OUI | G83: Registre des incidents récurrents | H83: Analyse superficielle | I83: Mineure | J83: Incapacité à répondre aux besoins spécifiques | K83: organiser des hackathons bimestriels sur les nouvelles méthodologies
D84: Un registre des problèmes connus et leurs solutions est maintenu. | E84: Un registre des problèmes connus et leurs solutions est-il maintenu ? | F84: NON | G84: Base de solutions intermédiaires | H84: Solutions non documentées | I84: Négligeable | J84: Expertise manquante | K84: implémenter un moteur de routing intelligent basé sur le machine learning
F85: OUI | G85: Documentation des correctifs définitifs | H85: Connaissances perdues | I85: Critique | J85: Dépendance excessive à des ressources externes | K85: développer des SLA différenciés par criticité des demandes
D86: Les solutions temporaires et définitives sont documentées. | E86: Les solutions temporaires et définitives sont-elles documentées ? | F86: OUI | G86: Plan de communication d'urgence | H86: Correctifs temporaires pérennisés | I86: Mineure | J86: Compétences techniques insuffisantes | K86: installer des sondes de monitoring qualité de service en temps réel
F87: NON | G87: Statistiques mensuelles de résolution | H87: Solutions fragiles | I87: Négligeable | J87: Traitement superficiel des problèmes complexes | K87: créer un programme de upskilling continu avec parcours personnalisés
D88: Un processus de communication existe pour les problèmes majeurs. | E88: Un processus de communication existe-t-il pour les problèmes majeurs ? | F88: OUI | G88: Organigramme fonctionnel détaillé | H88: Communication insuffisante en crise | I88: Majeure | J88: Savoir-faire obsolète | K88: équiper les équipes d'environnements sandbox pour formation pratique
F89: NON | G89: Tableau des seuils critiques | H89: Chaîne défaillante | I89: Négligeable | J89: Inadéquation avec les technologies actuelles | K89: mettre en place une veille technologique systématique avec comité dédié
D90: Les statistiques de résolution des problèmes sont analysées mensuellement. | E90: Les statistiques de résolution des problèmes sont-elles analysées mensuellement ? | F90: OUI | G90: Modèles types de rapports | H90: Tendances non détectées | I90: Négligeable | J90: Matrice des compétences obsolète | K90: développer des indicateurs avancés de maturité technologique
F91: NON | G91: Circuit de validation formalisé | H91: Outils inadéquats | I91: Mineure | J91: Gestion inadaptée des ressources humaines | K91: automatiser les redirections via un système expert à base de règles
C92: S’assurer qu’un processus de gestion des problèmes existe | D92: Le processus de gestion des problèmes définit les rôles et responsabilités. | E92: Le processus de gestion des problèmes définit-il les rôles et responsabilités ? | F92: NON | G92: Procédure de revue post-implémentation | H92: Rôles et responsabilités flous | I92: Majeure | J92: Mises à jour manquantes | K92: instrumenter les processus avec des timestamps blockchain
F93: OUI | G93: Journal des incidents majeurs | H93: Chevauchements | I93: Négligeable | J93: Utilisation de méthodes dépassées | K93: déployer des chatbots intelligents pour le support de premier niveau
D94: Les seuils de déclenchement du processus sont clairement établis. | E94: Les seuils de déclenchement du processus sont-ils clairement établis ? | F94: OUI | G94: Guide de saisie unifié | H94: Seuils de déclenchement inadaptés | I94: Mineure | J94: Redirections inappropriées | K94: créer des laboratoires d'innovation par domaine métier
F95: NON | G95: Plan de continuité du service | H95: Réactions tardives | I95: Critique | J95: Perte de temps et frustration | K95: développer des POC trimestriels sur technologies émergentes
D96: Le processus inclut une phase d'analyse et de documentation. | E96: Le processus inclut-il une phase d'analyse et de documentation ? | F96: OUI | G96: Procédure opérationnelle standard | H96: Analyse superficielle des problèmes | I96: Négligeable | J96: Retards de traitement | K96: établir un processus formalisé de feedback utilisateurs continu
F97: NON | G97: Rapports d'audit qualité | H97: Diagnostic erroné | I97: Mineure | J97: Dégradation de la qualité de service | K97: implémenter des outils de collaboration unifiée avec traduction intégrée
D98: Un circuit de validation des solutions est formalisé. | E98: Un circuit de validation des solutions est-il formalisé ? | F98: OUI | G98: Liste des membres des comités | H98: Validation biaisée des solutions | I98: Majeure | J98: Compétences non actualisées | K98: automatiser la détection des gaps compétences via analyse des tickets
F99: NON | G99: Calendrier des réunions planifiées | H99: Décisions arbitraires | I99: Négligeable | J99: Incapacité à utiliser les nouveaux outils | K99: développer un système de mentoring inversé junior/senior
D100: Le processus prévoit une phase de revue post-résolution. | E100: Le processus prévoit-il une phase de revue post-résolution ? | F100: OUI | G100: Modèles de comptes-rendus types | H100: Absence de retour d'expérience | I100: Négligeable | J100: Évolution non suivie | K100: mettre en place des rotations inter-services planifiées
...

Sheet 4.5
A1: Domaines | B1: Point de contrôle | C1: Objectifs de contrôle | D1: Critere d'evaluations | E1: Questions d'evaluation | F1: Reponses | G1: Documents Requis | H1: Risques | I1: Consequences | J1: Criticités | K1: Recommandations
B2: Facteurs clés de succès | C2: Vérifier qu'une politique de sécurité est définie et correspond à l'activité de l'Organisation | D2: La politique est documentée et accessible à tous les concernés | E2: La politique est-elle documentée et accessible à tous les concernés ? | F2: oui | G2: Politique de sécurité officielle | H2: Non-conformité légale et réglementaire | I2: Amendes et sanctions juridiques | J2: Moyenne | K2: Mettre en place un dispositif de veille réglementaire
F3: oui | G3: Registre de distribution interne
D4: Le contenu reflète les risques spécifiques du secteur d'activité | E4: Le contenu reflète-t-il les risques spécifiques du secteur d'activité ? | F4: oui | G4: Analyse sectorielle des risques | H4: Méconnaissance des obligations par le personnel | I4: Perte de licence d'exploitation | J4: Élevée | K4: Déployer un programme de sensibilisation obligatoire
F5: non | G5: Matrice des risques métiers
D6: Les responsabilités sont clairement définies pour chaque acteur | E6: Les responsabilités sont-elles clairement définies pour chaque acteur ? | F6: oui | G6: Organigramme des responsabilités | H6: Inadéquation aux enjeux réels du secteur | I6: Violations involontaires des règles | J6: Élevée | K6: Réaliser une analyse de risques sectorielle annuelle
F7: oui | G7: Fiches de poste sécurité
D8: Un calendrier de révision périodique est établi | E8: Un calendrier de révision périodique est-il établi ? | F8: oui | G8: Calendrier des révisions annuelles | H8: Protection insuffisante des actifs critiques | I8: Exposition accrue aux risques | J8: Élevée | K8: Établir une classification des actifs critiques
F9: non | G9: Journal des mises à jour
D10: La politique soutient explicitement les objectifs métiers | E10: La politique soutient-elle explicitement les objectifs métiers ? | F10: pas | G10: Déclaration d'alignement stratégique | H10: Flou dans les attributions et rôles | I10: Inadéquation aux réglementations actuelles | J10: Élevée | K10: Définir une matrice RACI claire
F11: pas | G11: Objectifs business formalisés
C12: Vérifier qu'une démarche de mise en œuvre de la gestion de la sécurité est adoptée et compatible avec la culture de l'Organisation | D12: Un plan opérationnel avec livrables et échéances existe | E12: Un plan opérationnel avec livrables et échéances existe-t-il ? | F12: oui | G12: Plan d'implémentation détaillé | H12: Flou dans les attributions et rôles | I12: Mesures de sécurité inefficaces | J12: Moyenne | K12: Instaurer un processus de révision semestrielle
F13: non | G13: Feuille de route opérationnelle
D14: Les ressources humaines et financières sont identifiées | E14: Les ressources humaines et financières sont-elles identifiées ? | F14: non | G14: Budget sécurité approuvé | H14: Politique obsolète non actualisée | I14: Perte d'avantage concurrentiel | J14: Moyenne | K14: Créer un comité de veille technologique
F15: non | G15: Plan de staffing sécurité
D16: La méthode intègre les particularités organisationnelles | E16: La méthode intègre-t-elle les particularités organisationnelles ? | F16: non | G16: Guide d'adaptation organisationnelle | H16: Inadaptation aux nouvelles menaces | I16: Gaspillage de ressources financières | J16: Élevée | K16: Aligner la politique sécurité sur la stratégie d'entreprise
F17: oui | G17: Manuel des procédures locales
D18: Des indicateurs quantitatifs de progression sont suivis | E18: Des indicateurs quantitatifs de progression sont-ils suivis ? | F18: oui | G18: Tableau de bord des KPI | H18: Désalignement avec les objectifs business | I18: Allocation budgétaire insuffisante | J18: Élevée | K18: Réaliser une étude d'impact opérationnel
F19: oui | G19: Système de suivi des indicateurs
D20: Un système de remontée des difficultés est en place | E20: Un système de remontée des difficultés est-il en place ? | F20: oui | G20: Base de données des incidents | H20: Frein à la productivité opérationnelle | I20: Priorisation inadéquate de la sécurité | J20: Élevée | K20: Élaborer un plan directeur sécurité
F21: oui | G21: Procès-verbal de conseil d'administration
C22: Vérifier que la direction assure un soutien total et un engagement visible pour la sécurité | D22: Les dirigeants communiquent régulièrement sur le sujet | E22: Les dirigeants communiquent-ils régulièrement sur le sujet ? | F22: pas | G22: Plan de financement pluriannuel | H22: Absence de feuille de route claire | I22: Compromission des données sensibles | J22: Élevée | K22: Mettre en place un PMO sécurité
F23: pas | G23: Ordre du jour type des réunions
D24: Les budgets alloués sont suffisants | E24: Les budgets alloués sont-ils suffisants ? | F24: oui | G24: Grille d'évaluation des managers | H24: Retards dans les déploiements | I24: Interruptions des activités opérationnelles | J24: Élevée | K24: Développer un plan de recrutement spécialisé
F25: oui | G25: Engagement écrit de la direction
D26: La sécurité est à l'ordre du jour des réunions dirigeants | E26: La sécurité est-elle à l'ordre du jour des réunions dirigeants ? | F26: oui | G26: Registre des actions managériales | H26: Manque de ressources humaines qualifiées | I26: Pertes financières importantes | J26: Élevée | K26: Budgétiser selon la méthode basée sur les risques
F27: oui | G27: Rapport d'analyse des risques
D28: Les managers sont évalués sur ces aspects | E28: Les managers sont-ils évalués sur ces aspects ? | F28: oui | G28: Base de données des scénarios | H28: Budget insuffisant pour les besoins | I28: Atteintes à la réputation de l'organisation | J28: Élevée | K28: Organiser des ateliers d'appropriation
F29: oui | G29: Seuils de tolérance documentés
D30: La direction donne l'exemple dans les pratiques | E30: La direction donne-t-elle l'exemple dans les pratiques ? | F30: pas | G30: Plan de communication des risques | H30: Rejet par les équipes opérationnelles | I30: Pénétration réussie des systèmes | J30: Élevée | K30: Adapter le référentiel à la culture organisationnelle
F31: non | G31: Programme de formation obligatoire
C32: Vérifier que les exigences de sécurité et les risques sont compris et évalués | D32: Une analyse de risques documentée est disponible | E32: Une analyse de risques documentée est-elle disponible ? | F32: oui | G32: Catalogue des modules métiers | H32: Incompatibilité avec la culture d'entreprise | I32: Exploitation des failles de sécurité | J32: Élevée | K32: Implémenter un système de décision data-driven
F33: oui | G33: Calendrier des recyclages
