Workbook

Sheet Audit_Appl_En_Service
A1: Domaines | B1: Points de contrôle | C1: objectifs de contrôle | D1: criteres d'evaluation | E1: Documents Requis | F1: Questions d'evaluation | G1: Réponses | H1: Risques | I1: Criticités | J1: Consequences | K1: Recommandations
A2: Audit des applications en service | B2: Organisation | C2: S’assurer de l’existence d'un comité informatique | D2: Existence d'un comité informatique | E2: Décision de création du comité informatique signée par le DG | F2: Existe-t-il un comité informatique ? | G2: OUI | H2: Inexistence d'un comité informatique | I2: Elevée | J2: Décisions informatiques déconnectées des besoins métiers. | K2: mpliquer les métiers dans les instances de décision concernant les SI.
E3: Procès-verbal de réunion attestant de la création du comité informatique. | K3: Formaliser les besoins métiers et les traduire en exigences fonctionnelles et techniques.
D4: Le Comité est présidé par le Directeur Général | E4: PV de session du comité | F4: Le Comité est-il présidé par le Directeur Général ? | G4: NON | H4: Le Comité n'est pas présidé par le Directeur Général | I4: Moyenne | J4: Manque d'autorité et de légitimité des décisions du comité. | K4: Clarifier les rôles et responsabilités du comité de pilotage SI.
E5: Décision de nomination du Président du comité informatique signée par le Directeur Général. | K5: Documenter les décisions prises et les diffuser aux parties prenantes.
D6: Les directions utilisatrices sont représentées au sein de ce Comité | E6: Décision d'affectation des directions au comité | F6: Les directions utilisatrices sont-elles représentées au sein de ce Comité ? | G6: PAS | H6: Les directions utilisatrices ne sont pas représentées au sein de ce Comité. | I6: Elevée | J6: Systèmes inadaptés aux besoins réels des utilisateurs. | K6: Mener des études d'utilisabilité et des tests utilisateurs avant et après la mise en production.
E7: PV de session du comité | K7: Mettre en place un processus de recueil et de gestion des feedbacks utilisateurs.
D8: Les directions utilisatrices sont influentes au sein de ce Comité | E8: Procès-verbal des réunions mentionnant les contributions des directions utilisatrices | F8: Les directions utilisatrices sont-elles influentes au sein de ce Comité ? | G8: NON | H8: Les directions utilisatrices ne sont pas influentes au sein de ce Comité | I8: Faible | J8: Faible adoption par les utilisateurs et non atteinte des objectifs métiers. | K8: Accompagner les utilisateurs dans la prise en main des nouveaux systèmes.
E9: Document de gouvernance IT attestant du poids décisionnel des directions métiers | K9: Définir des indicateurs de performance (KPI) pour mesurer l'adoption et l'atteinte des objectifs.
D10: L'ordre du jour des réunions est documenté? | E10: Ordres du jour archivés des réunions du comité | F10: L'ordre du jour des réunions est-il documenté? | G10: NON | H10: Systèmes inadaptés aux besoins métiers. | I10: Elevée | J10: Pertes de temps et sujets importants non traités. | K10: Prioriser les sujets et les tâches en fonction de leur importance et de leur urgence.
E11: Procès-verbaux des réunions avec suivi des points traités | K11: Mettre en place des outils de gestion de projet et de suivi des tâches.
C12: S’assurer de l’existence d'une politique relative aux applications | D12: Il existe une politique relative aux applications au sein de l'institution | E12: Document officiel de la politique applicative | F12: Existe-t-il une politique relative aux applications au sein de l'institution? | G12: OUI | H12: Réunions inefficaces. | I12: Moyenne | J12: Coûts élevés et duplication des fonctions. | K12: Rationaliser les applications et les systèmes existants.
E13: Procès-verbal de validation par la direction générale | K13: Automatiser les tâches répétitives et chronophages.
D14: La politique est connue des utilisateurs d'applications | E14: Registre des formations suivies par les utilisateurs | F14: La politique est-elle connue des utilisateurs d'applications? | G14: OUI | H14: Gestion anarchique des applications. | I14: Elevée | J14: Problèmes de sécurité et erreurs d'utilisation. | K14: Sensibiliser les utilisateurs aux bonnes pratiques de sécurité.
E15: Attestations de connaissance de la politique signées par les utilisateurs | K15: Mettre en place des contrôles d'accès et des mécanismes d'authentification robustes.
D16: La politique est largement diffusée | E16: Plan de communication institutionnel | F16: La politique est-elle largement diffusée? | G16: OUI | H16: Non-respect de la politique. | I16: Faible | J16: Application incomplète de la politique et problèmes de conformité. | K16: Formaliser et diffuser la politique de sécurité SI.
E17: Preuves matérielles de diffusion (emails, publications intranet) | K17: Effectuer des audits réguliers pour vérifier la conformité aux normes et réglementations.
D18: La politique est mise en œuvre | E18: Rapport d'audit de conformité | F18: La politique est-elle mise en œuvre? | G18: NON | H18: Méconnaissance de la politique par une partie du personnel. | I18: Elevée | J18: Aucun impact concret sur les pratiques et les problèmes persistent. | K18: Mettre en place un plan d'action correctif pour résoudre les problèmes identifiés.
E19: Journal des contrôles effectués | K19: Suivre l'efficacité des actions correctives et ajuster si nécessaire.
D20: La politique couvre l'ensemble du cycle de vie de l’application | E20: Document décrivant le cycle de vie complet des applications | F20: La politique couvre-t-elle l'ensemble du cycle de vie de l'application? | G20: PAS | H20: La politique reste théorique. | I20: Moyenne | J20: Problèmes de sécurité et erreurs lors de certaines phases du cycle de vie de l'application. | K20: Intégrer la sécurité dès la phase de conception des applications (approche Security by Design).
E21: Procédures opérationnelles pour chaque phase du cycle | K21: Réaliser des tests de sécurité tout au long du cycle de développement.
D22: La politique favorise la responsabilisation des utilisateurs dans l'usage de leur système d’information (application) | E22: Charte d'utilisation signée par les utilisateurs | F22: La politique favorise-t-elle la responsabilisation des utilisateurs dans l'usage de leur système d'information (application)? | G22: NON | H22: La politique est incomplète et ne couvre pas toutes les étapes. | I22: Elevée | J22: Mauvaise qualité des données et pertes d'informations. | K22: Mettre en place des processus de validation et de nettoyage des données.
E23: Registre des sanctions appliquées | K23: Sauvegarder régulièrement les données et mettre en place un plan de reprise d'activité.
D24: La politique préconise l'attribution formelle de responsabilités aux utilisateurs du système (application) | E24: Fiches de poste avec responsabilités applicatives définies | F24: La politique préconise-t-elle l'attribution formelle de responsabilités aux utilisateurs du système (application)? | G24: NON | H24: Manque d'implication des utilisateurs. | I24: Faible | J24: Manque de clarté sur qui fait quoi et erreurs fréquentes. | K24: Définir clairement les rôles et responsabilités de chaque acteur.
E25: Matrice RACI officielle | K25: Documenter les processus et les procédures.
C26: S’assurer que les rôle et responsabilités des utilisateurs sont bien définis | D26: Le rôle et les responsabilités des utilisateurs vis-à-vis de l’application sont clairement identifiés | E26: Manuel des procédures utilisateurs | F26: Le rôle et les responsabilités des utilisateurs vis-à-vis de l'application sont-ils clairement identifiés? | G26: OUI | H26: Responsabilités mal définies. | I26: Elevée | J26: Difficultés à identifier les responsables en cas de problème. | K26: Mettre en place une matrice RACI (Responsible, Accountable, Consulted, Informed).
E27: Tableau des droits d'accès par profil métier | K27: Définir un processus d'escalade des problèmes.
D28: Le rôle et les responsabilités des utilisateurs vis-à-vis de l’application couvrent l’analyse des risques | E28: Rapport d'analyse des risques impliquant les utilisateurs métiers | F28: Le rôle et les responsabilités des utilisateurs vis-à-vis de l'application couvrent-ils l'analyse des risques? | G28: OUI | H28: Manque de clarté sur les rôles et responsabilités. | I28: Moyenne | J28: Mesures de sécurité non adaptées. | K28: Effectuer une analyse de risques pour identifier les menaces et les vulnérabilités.
E29: Procès-verbal de validation des risques par les responsables métiers | K29: Mettre en place des mesures de sécurité appropriées pour atténuer les risques.
D30: Le rôle et les responsabilités des utilisateurs vis-à-vis de l’application couvrent la définition des besoins de sécurité | E30: Cahier des charges sécurité co-construit avec les métiers | F30: Le rôle et les responsabilités des utilisateurs vis-à-vis de l'application couvrent-ils la définition des besoins de sécurité? | G30: OUI | H30: Absence de prise en compte des besoins de sécurité par les utilisateurs. | I30: Elevée | J30: Systèmes obsolètes. | K30: Systèmes à jour et maintenus.
E31: PV de réunion de définition des exigences de sécurité | K31: Plan de secours et de reprise après sinistre.
D32: Le rôle et les responsabilités des utilisateurs vis-à-vis de l’application couvrent la gestion des changements et des évolutions | E32: Procédure formalisée de gestion des changements | F32: Le rôle et les responsabilités des utilisateurs vis-à-vis de l'application couvrent-ils la gestion des changements et des évolutions? | G32: NON | H32: Gestion des changements et des évolutions inadaptée aux besoins. | I32: Faible | J32: Difficultés à maintenir l'application et insatisfaction des utilisateurs. | K32: Définir des objectifs de sécurité clairs et mesurables.
E33: Registre des demandes d'évolution initiées par les métiers | K33: Suivre et évaluer régulièrement la performance de la sécurité.
D34: Le rôle et les responsabilités des utilisateurs vis-à-vis de l’application couvrent l’administration de l’application | E34: Procédures d'administration déléguée aux utilisateurs | F34: Le rôle et les responsabilités des utilisateurs vis-à-vis de l'application couvrent-ils l'administration de l'application? | G34: PAS | H34: Administration de l'application déconnectée des besoins des utilisateurs. | I34: Elevée | J34: Difficulté à maintenir l'application et insatisfaction des utilisateurs. | K34: Séparer les tâches critiques pour éviter les conflits d'intérêts et les fraudes.
E35: Journal des opérations administratives réalisées par les métiers | K35: Former le personnel sur les politiques et procédures de sécurité.
C36: S’assurer qu’une analyse des risques a été réalisée | D36: Une analyse des risques spécifique à l’application a été réalisée | E36: Rapport complet d'analyse des risques applicative | F36: Une analyse des risques spécifique à l'application a-t-elle été réalisée? | G36: NON | H36: Mauvaise identification des risques pour l'application. | I36: Moyenne | J36: Mauvaise identification des risques pour l'application. | K36: Définir un niveau de sécurité cible et allouer les ressources nécessaires.
E37: Grille d'évaluation des risques spécifique à l'application | K37: Mettre en œuvre des contrôles de sécurité pour surveiller et protéger les systèmes.
D38: L'analyse des risques a débouché sur la définition des besoins de sécurité | E38: Document de synthèse des besoins de sécurité | F38: L'analyse des risques a-t-elle débouché sur la définition des besoins de sécurité? | G38: NON | H38: Définition des besoins de sécurité incomplète ou inadaptée. | I38: Elevée | J38: Définition des besoins de sécurité incomplète ou inadéquate. | K38: Documenter la méthodologie utilisée pour l'analyse et la gestion des risques.
E39: PV de validation des exigences par la direction | K39: Former le personnel sur la méthodologie et les outils utilisés.
D40: La méthode d'analyse des risques est définie et documentée (ex: EBIOS Risk Manager, MEHARI)? | E40: Manuel méthodologique d'analyse des risques (EBIOS/MEHARI) | F40: La méthode d'analyse des risques est-elle définie et documentée (ex: EBIOS Risk Manager, MEHARI)? | G40: OUI | H40: Méthode d'analyse des risques non standardisée et non documentée. | I40: Faible | J40: Méthode d'analyse des risques non standardisée et non documentée. | K40: Prendre en compte la confidentialité, l'intégrité et la disponibilité des données lors de la conception et de la mise en œuvre des systèmes.
E41: Procédure d'évaluation des risques documentée | K41: Mettre en place des mesures pour protéger les données contre les accès non autorisés, les modifications et les pertes.
D42: Les risques identifiés sont classifiés et priorisés? | E42: Matrice de criticité des risques classés | F42: Les risques identifiés sont-ils classifiés et priorisés? | G42: OUI | H42: Risques mal identifiés et non priorisés. | I42: Elevée | J42: Risques mal identifiés et non priorisés. | K42: Effectuer une analyse de risques approfondie et prioriser les risques en fonction de leur impact potentiel.
E43: Plan de traitement des risques priorisés | K43: Mettre en place un processus de gestion des risques.
D44: Les mesures de sécurité mises en place sont proportionnées aux risques identifiés? | E44: Rapport de mise en œuvre des mesures de sécurité | F44: Les mesures de sécurité mises en place sont-elles proportionnées aux risques identifiés? | G44: OUI | H44: Mesures de sécurité inadaptées aux risques identifiés. | I44: Moyenne | J44: Mesures de sécurité inadaptées aux risques identifiés. | K44: Adopter des mesures de sécurité appropriées et proportionnées aux risques identifiés.
E45: Évaluation du niveau de couverture des risques | K45: Effectuer des tests de pénétration et des audits de sécurité réguliers.
C46: S’assurer que le prolongement de l'analyse de risque et de son expansion ont été réalisés | D46: Il y a eu un prolongement de l'analyse des risques et de l'expression des besoins de sécurité? | E46: Compte-rendu d'extension de l'analyse des risques | F46: Y a-t-il eu un prolongement de l'analyse des risques et de l'expression des besoins de sécurité? | G46: NON | H46: Expression des besoins de sécurité non prise en compte. | I46: Elevée | J46: Expression des besoins de sécurité non prise en compte. | K46: Recueillir et prendre en compte les besoins de sécurité des utilisateurs et des parties prenantes.
E47: Document d'évolution des besoins de sécurité | K47: Organiser des sessions de sensibilisation à la sécurité pour les utilisateurs.
D48: Un contrat de service (SLA) entre l'informatique et la direction utilisatrice a été mis en œuvre? | E48: Contrat de Service (SLA) signé avec la direction métier | F48: Un contrat de service (SLA) entre l'informatique et la direction utilisatrice a-t-il été mis en œuvre? | G48: PAS | H48: Contrat de service (SLA) inexistant ou non appliqué. | I48: Faible | J48: Contrat de service (SLA) inexistant ou non appliqué. | K48: Mettre en place un contrat de service (SLA) clair et précis qui définit les responsabilités en matière de sécurité.
E49: Annexe sécurité du SLA définissant les engagements | K49: S'assurer que le SLA est respecté et appliqué.
D50: L'analyse des risques est mise à jour régulièrement en fonction des évolutions de l'application et des menaces? | E50: Plan de révision périodique des risques | F50: L'analyse des risques est-elle mise à jour régulièrement en fonction des évolutions de l'application et des menaces? | G50: NON | H50: Analyse des risques non mise à jour régulièrement. | I50: Elevée | J50: Analyse des risques non mise à jour régulièrement. | K50: Mettre à jour régulièrement l'analyse des risques pour refléter l'évolution des menaces et des vulnérabilités.
E51: PV des mises à jour de l'analyse des risques | K51: Documenter les modifications apportées à l'analyse des risques.
D52: Les besoins de sécurité sont revus et validés par les parties prenantes? | E52: PV de revue des besoins de sécurité | F52: Les besoins de sécurité sont-ils revus et validés par les parties prenantes? | G52: NON | H52: Besoins de sécurité non revus ni validés. | I52: Moyenne | J52: Besoins de sécurité non revus ni validés. | K52: Revoir et valider régulièrement les besoins de sécurité pour s'assurer qu'ils restent pertinents.
E53: Fiche de validation des modifications par les métiers | K53: Documenter les besoins de sécurité et les décisions prises.
D54: Les résultats de l'analyse des risques sont utilisés pour définir les priorités en matière de sécurité? | E54: Plan d'action sécurité priorisé | F54: Les résultats de l'analyse des risques sont-ils utilisés pour définir les priorités en matière de sécurité? | G54: OUI | H54: Mauvaise définition des priorités en matière de sécurité. | I54: Elevée | J54: Mauvaise définition des priorités en matière de sécurité. | K54: Définir clairement les priorités en matière de sécurité en fonction des risques identifiés et des objectifs de l'organisation.
E55: Tableau de bord des risques résiduels | K55: Allouer les ressources nécessaires pour mettre en œuvre les mesures de sécurité prioritaires.
C56: S’assurer que l’analyse et évaluation du niveau de sensibilité a été réalisée | D56: Il y a une séparation des tâches au sein de la direction utilisatrice indépendamment de l'application? | E56: Organigramme fonctionnel avec séparation des tâches | F56: Il y a une séparation des tâches au sein de la direction utilisatrice indépendamment de l'application? | G56: OUI | H56: Absence de séparation des tâches au sein de la direction utilisatrice. | I56: Faible | J56: Absence de séparation des tâches au sein de la direction utilisatrice. | K56: Mettre en place une séparation des tâches pour les fonctions critiques au sein de la direction utilisatrice afin de minimiser les risques de conflits d'intérêts et de fraudes.
E57: Description des contrôles d'incompatibilité | K57: Définir des rôles et des responsabilités clairs pour chaque membre du personnel.
D58: Il y a une « maturité » de l'organisation vis-à-vis de ses systèmes d'information? | E58: Rapport d'évaluation de la maturité organisationnelle | F58: Il y a une «maturité» de l'organisation vis-à-vis de ses systèmes d'information? | G58: OUI | H58: Niveau de sécurité insuffisant. | I58: Elevée | J58: Niveau de sécurité insuffisant. | K58: Définir un niveau de sécurité cible et allouer les ressources nécessaires pour atteindre ce niveau.
E59: Plan d'amélioration continue des processus | K59: Mettre en œuvre des contrôles de sécurité pour surveiller et protéger les systèmes et les données.
D60: Une méthode d'évaluation de la sensibilité des données est définie et documentée? | E60: Politique de classification des données | F60: Une méthode d'évaluation de la sensibilité des données est définie et documentée? | G60: NON | H60: Méthode non définie et non documentée. | I60: Moyenne | J60: Méthode non définie et non documentée. | K60: Définir et documenter une méthodologie claire pour l'analyse et la gestion des risques de sécurité.
E61: Grille d'évaluation de la sensibilité des informations | K61: Former le personnel sur la méthodologie et les outils utilisés.
D62: L'évaluation prend en compte la confidentialité, l'intégrité et la disponibilité des données? | E62: Rapport d'évaluation CID (Confidentialité, Intégrité, Disponibilité) | F62: L'évaluation prend en compte la confidentialité, l'intégrité et la disponibilité des données? | G62: PAS | H62: Confidentialité, l'intégrité et la disponibilité non prises en compte. | I62: Elevée | J62: Confidentialité, l'intégrité et la disponibilité non prises en compte. | K62: Prendre en compte la confidentialité, l'intégrité et la disponibilité des données lors de la conception et de la mise en œuvre des systèmes.
E63: Cartographie des flux de données sensibles | K63: Mettre en place des mesures pour protéger les données contre les accès non autorisés, les modifications et les pertes.
D64: Les résultats de l'évaluation sont utilisés pour définir les mesures de sécurité appropriées? | E64: Plan de sécurité adapté aux niveaux de sensibilité | F64: Les résultats de l'évaluation sont utilisés pour définir les mesures de sécurité appropriées? | G64: NON | H64: Mesures de sécurité inappropriées. | I64: Faible | J64: Vulnérabilité aux menaces. | K64: Identifier et corriger les vulnérabilités.
E65: Matrice des mesures de protection par type de données | K65: Mettre en place des mesures de sécurité pour atténuer les menaces.
C66: Vérifier l’existence d’un manuel d'administration de l'application | D66: Un ou des manuels pour l’application existe | E66: Fiche de versionnage du manuel | F66: Un ou des manuels pour l'application existe? | G66: NON | H66: Manuels inexistants. | I66: Elevée | J66: Difficulté d'utilisation et erreurs potentielles. | K66: Simplifier l'interface utilisateur et fournir une documentation claire.
E67: Procès-verbal de validation | K67: Former les utilisateurs sur l'utilisation correcte de l'application.
D68: Le manuel est à jour | E68: Registre de formation des utilisateurs | F68: Le manuel est à jour? | G68: OUI | H68: Manuels non mis à jour. | I68: Moyenne | J68: Information obsolète et utilisation incorrecte de l'application. | K68: Mettre à jour régulièrement les informations et les données de l'application.
E69: Test de connaissance utilisateurs | K69: Fournir des instructions claires sur l'utilisation prévue de l'application.
D70: Le manuel est maitrisé | E70: Manuel utilisateur complet | F70: Le manuel est maîtrisé? | G70: OUI | H70: Manuels non maîtrisés. | I70: Elevée | J70: Difficulté à appliquer les bonnes pratiques et procédures. | K70: Fournir une formation et un soutien adéquats aux utilisateurs.
E71: Procédure opérationnelle standardisée | K71: Mettre en place des mécanismes pour encourager l'adoption des meilleures pratiques.
D72: Le manuel comprend un mode d'emploi | E72: Guide administrateur applicatif | F72: Le manuel comprend un mode d'emploi? | G72: OUI | H72: Absence de mode d'emploi. | I72: Faible | J72: Difficulté d'utilisation et erreurs potentielles. | K72: Concevoir une interface utilisateur intuitive et conviviale.
E73: Schéma d'architecture technique | K73: Mettre en œuvre des contrôles pour prévenir les erreurs potentielles.
D74: Le manuel comprend une présentation du module d’administration de l’application | E74: Matrice des droits d'accès | F74: Le manuel comprend une présentation du module d'administration de l'application? | G74: NON | H74: Absence de présentation du module d'administration. | I74: Elevée | J74: Administration difficile. | K74: Simplifier les tâches d'administration et automatiser les processus.
E75: Politique de sécurité applicative | K75: Fournir aux administrateurs les outils et la formation nécessaires.
D76: Le manuel comprend des droits d’accès | E76: Formulaire de demande de modification | F76: Le manuel comprend des droits d'accès? | G76: PAS | H76: Absence d'information sur les droits d'accès. | I76: Moyenne | J76: Accès non autorisés et gestion des droits inefficace. | K76: Mettre en place un contrôle d'accès strict et une gestion des droits efficace.
E77: Procès-verbal de validation propriétaire | K77: Surveiller régulièrement les accès et les activités des utilisateurs.
C78: Vérifier l’existence de procédures formalisées | D78: Des procédures formalisées imposant l’accord du « propriétaire » de l’application pour tout changement sur les programmes de l’application existent | E78: Procédure de changement de planning | F78: Des procédures formalisées imposant l'accord du «propriétaire» de l'application pour tout changement sur les programmes de l'application existent? | G78: NON | H78: Absence d'accord du « propriétaire » de l'application pour tout changement sur les programmes. | I78: Elevée | J78: Changement non autorisées. | K78: Mettre en place des contrôles pour empêcher les modifications non autorisées.
E79: Journal des modifications approuvées | K79: Enregistrer et auditer tous les changements.
D80: Des procédures formalisées imposant l’accord du « propriétaire » de l’application pour tout changement sur la planification des traitements informatiques existent | E80: Charte d'évolution technologique | F80: Des procédures formalisées imposant l'accord du «propriétaire» de l'application pour tout changement sur la planification des traitements informatiques existent? | G80: NON | H80: Absence d'accord du « propriétaire » de l'application pour la planification des traitements informatiques. | I80: Faible | J80: Risques liées à une gestion mauvaise. | K80: Adopter des pratiques de gestion des risques saines.
E81: PV du comité technique | K81: Examiner et mettre à jour régulièrement les politiques et les procédures.
D82: Des procédures formalisées imposant l’accord du « propriétaire » de l’application pour tout changement sur l’environnement technologique de l’application existent | E82: Procédures administratives formalisées | F82: Des procédures formalisées imposant l'accord du «propriétaire» de l'application pour tout changement sur l'environnement technologique de l'application existent? | G82: OUI | H82: Absence d'accord du « propriétaire » de l'application pour tout changement sur l'environnement technologique. | I82: Elevée | J82: Résolution lente des incidents. | K82: Mettre en place un processus efficace de gestion des incidents.
E83: Registre des opérations effectuées | K83: Allouer des ressources suffisantes pour la résolution des incidents.
D84: L'administration est bien assurée par les utilisateurs | E84: Processus de gestion des incidents | F84: L'administration est bien assurée par les utilisateurs? | G84: OUI | H84: Mauvaise gestion de l'application. | I84: Moyenne | J84: Identifier les performance des applications pas a jour | K84: Mettre en place une surveillance des performances et des alertes.
E85: Fiches types d'intervention | K85: Maintenir les applications à jour.
D86: Vérifier l'existence de procédures formalisées de gestion des incidents | E86: Rapport mensuel de performance | F86: Des procédures formalisées de gestion des incidents sont-elles en place ? | G86: OUI | H86: Problèmes de gestion des incidents. | I86: Elevée | J86: Résolution lente des incidents. | K86: Définir des accords de niveau de service (SLA) et des procédures d'escalade.
E87: Tableau de bord SLA | K87: Automatiser la résolution des incidents.
C88: S’assurer de l’existence et de la mise à disposition du compte rendu mensuel au propriétaire | D88: Le propriétaire dispose d'un compte rendu mensuel de la performance de l'application | E88: Engagement contractuel formalisé | F88: Le propriétaire dispose-t-il d'un compte rendu mensuel de la performance de l'application ? | G88: NON | H88: Manque de visibilité sur la performance de l'application. | I88: Faible | J88: Dégradation des performances non détectées. | K88: Mettre en place une surveillance proactive des performances.
E89: Preuve de livraison dans les délais | K89: Analyser les causes profondes des dégradations de performance.
D90: Le compte rendu respecte le contrat du service | E90: Indicateurs clés de performance | F90: Le compte rendu respecte-t-il le contrat de service ? | G90: PAS | H90: Non-respect des obligations contractuelles. | I90: Elevée | J90: Contentieux avec le fournisseur. | K90: Négocier des contrats clairs avec des clauses de pénalité.
E91: Commentaires du propriétaire | K91: Mettre en place une communication régulière avec le fournisseur.
D92: Le compte rendu est transmis au propriétaire dans les délais convenus? | E92: Procédure de validation | F92: Le compte rendu est-il transmis au propriétaire dans les délais convenus ? | G92: NON | H92: Comptes rendus incompréhensibles ou incomplets. | I92: Moyenne | J92: Compte rendu inexistant. | K92: Fournir des comptes rendus réguliers sur les performances et les incidents.
E93: Attestation de réception | K93: Documenter tous les échanges et les accords.
D94: Le compte rendu contient des indicateurs de performance pertinents pour le propriétaire? | E94: Manuel des procédures | F94: Le compte rendu contient-il des indicateurs de performance pertinents pour le propriétaire ? | G94: NON | H94: Mauvaise communication avec le propriétaire. | I94: Elevée | J94: Contrats de niveau service inadéquats. | K94: Négocier des contrats de niveau de service adaptés aux besoins de l'entreprise.
E95: Plan de diffusion interne | K95: Revoir régulièrement les contrats et les ajuster si nécessaire.
D96: Un processus est en place pour s'assurer que le propriétaire comprend et valide le compte rendu | E96: Registre de diffusion | F96: Un processus est-il en place pour s'assurer que le propriétaire comprend et valide le compte rendu ? | G96: OUI | H96: Absence de guide utilisateur. | I96: Faible | J96: Mauvaise connaissance et manque de conformité. | K96: Former le personnel sur les politiques, les procédures et les exigences de conformité.
E97: Accusés de réception | K97: Mettre à disposition des ressources et une documentation accessibles.
C98: S’assurer de l’existence d'un guide d'utilisateur, manuel de procédures | D98: Il existe un guide utilisateurs / manuel de procédures | E98: Version officielle du manuel utilisateur | F98: Existe-t-il un guide utilisateurs / manuel de procédures ? | G98: OUI | H98: Mauvaise diffusion des guides. | I98: Elevée | J98: Information inaccessible. | K98: Mettre en place des contrôles d'accès pour restreindre l'accès aux informations sensibles.
E99: Plan de diffusion et registre de distribution | K99: Chiffrer les données sensibles.
D100: Le manuel est diffusé | E100: Historique des versions et dates de mise à jour | F100: Le manuel est-il diffusé ? | G100: OUI | H100: Guides non mis à jour. | I100: Moyenne | J100: Mauvaise utilisation de l'outil. | K100: Fournir une formation adéquate sur l'utilisation correcte des outils.
...

Sheet Audit fonction informatique
A1: Domaine | B1: Points de contrôle | C1: Objectifs de contrôle | D1: Critères d'évaluation | E1: Questions d'évaluation | F1: Documents requis | G1: Reponses | H1: Risques | I1: Criticités | J1: Conséquences | K1: Recommendations
A2: Fonction informatique | B2: Rôle et positionnement de l'informatique dans l'organisation | C2: Vérifier qu’ont été créés des Comités « informatique » (stratégique, pilotage,..) regroupant les différentes directions de l’Organisation en charge de recenser les besoins et les opportunités, gérer les priorités et suivre les projets ; | D2: Il existe des comités informatiques formels, tels que le comité stratégique et le comité de pilotage. | E2: Les comités informatiques formels (stratégique, pilotage) sont-ils définis dans une charte officielle et fonctionnent-ils conformément à celle-ci ? | F2: Charte de gouvernance | G2: OUI | H2: Absence de représentation équilibrée des parties prenantes. | I2: Elevée | J2: Décisions déséquilibrées ou non alignées avec les besoins réels. | K2: Formaliser la fréquence et les modalités de rotation des membres
F3: informatique Procès-verbal de nomination des membres | G3: NON | I3: Elevée | K3: Prévoir un mécanisme d'évaluation annuelle des comités
D4: L’ordre du jour des réunions inclut le recensement des besoins, la gestion des priorités et le suivi des projets. | E4: Les ordres du jour des réunions incluent-ils systématiquement les points relatifs au recensement des besoins, à la gestion des priorités et au suivi des projets ? | F4: Modèle standard d'ordre du jour Grille de priorisation | G4: NON | H4: Priorisation inefficace des sujets critiques. | I4: Elevée | J4: Retards dans les prises de décision et perte de vue des objectifs stratégiques. | K4: Impliquer les métiers dans la préparation des sujets
F5: des demandes | G5: NON | I5: Élevée | K5: Mettre en place un suivi systématique des décisions
D6: Les comités sont composés de représentants des différentes directions concernées. | E6: Les comités comprennent-ils des représentants de toutes les directions concernées par les décisions informatiques ? | F6: Tableau de composition des comités | G6: NON | H6: Manque d’engagement des membres. | I6: Moyenne | J6: Décisions peu représentatives des besoins opérationnels. | K6: Garantir la présence effective des représentants
F7: Fiches de délégation de pouvoir | G7: NON | I7: Moyenne | K7: Prévoir des suppléants pour assurer la continuité
D8: Les décisions prises lors des réunions sont documentées dans des procès-verbaux ou des comptes rendus | E8: Toutes les décisions prises lors des réunions sont-elles consignées dans des documents officiels accessibles ? | F8: Modèle de procèsverbal | G8: OUI | H8: Documentation incomplète ou inexacte. | I8: Élevée | J8: Perte de traçabilité et difficultés dans l’exécution des décisions. | K8: Automatiser la diffusion des comptes-rendus
F9: Registre des décisions stratégiques | G9: OUI | I9: Moyenne | K9: Mettre en place une validation formelle des PV
D10: Les réunions des comités ont lieu à une fréquence définie et respectée. | E10: La fréquence définie pour les réunions est-elle respectée dans la pratique ? | F10: Calendrier annuel des réunions | G10: OUI | H10: Réunions trop espacées ou annulées. | I10: Moyenne | J10: Délais de traitement allongés et accumulation de problèmes non résolus. | K10: Envoyer des rappels systématiques avant chaque réunion
F11: Tableau de suivi des présences | G11: Non | I11: Moyenne | K11: Adapter la fréquence en fonction des besoins
C12: Vérifier l’existence d’une charte informatique ou de tout autre document définissant le rôle et le périmètre de responsabilité de la DSI ; | D12: Le rôle et les responsabilités de la DSI sont clairement définis dans le document. | E12: Les rôles et responsabilités de la DSI sont-ils clairement définis et formalisés dans un document officiel ? | F12: Charte des missions DSI | G12: NON | H12: Ambiguïté dans les attributions. | I12: Élevée | J12: Conflits de responsabilités et inefficacité opérationnelle. | K12: Actualiser annuellement le document
F13: Organigramme fonctionnel | G13: Non | I13: Élevée | K13: Diffuser largement auprès de tous les services
D14: Le document est accessible à l’ensemble des collaborateurs concernés. | E14: Le document définissant les rôles de la DSI est-il accessible à tous les collaborateurs concernés ? | F14: Politique de diffusion des documents | G14: Oui | H14: Accès restreint ou diffusion limitée. | I14: Moyenne | J14: Manque de transparence et incompréhension des rôles. | K14: Mettre en place un portail documentaire unique
F15: Registre des accès | G15: Non | I15: Moyenne | K15: Sensibiliser les collaborateurs à la consultation
D16: Le périmètre d’intervention de la DSI est précisé, couvrant des domaines tels que l’infrastructure, les applications et la sécurité. | E16: Le périmètre d'intervention de la DSI est-il clairement défini et documenté pour les domaines d'infrastructure, applications et sécurité ? | F16: Cartographie des domaines de responsabilité | G16: Oui | H16: Périmètre trop large ou mal défini. | I16: Moyenne | J16: Chevauchements avec d’autres services ou zones non couvertes. | K16: Clarifier les zones de responsabilité partagée
F17: Matrice RACI | G17: Non | I17: Moyenne | K17: Mettre à jour lors des réorganisations
D18: La charte est mise à jour régulièrement pour refléter les évolutions organisationnelles et technologiques. | E18: La charte de la DSI est-elle régulièrement mise à jour pour refléter les changements organisationnels et technologiques ? | F18: Planning des revues documentaires | G18: Oui | H18: Charte obsolète. | I18: Élevée | J18: Inadéquation avec les besoins actuels et risques de nonconformité. | K18: Automatiser les alertes de révision
F19: Journal des modifications | G19: OUI | I19: Élevée | K19: Impliquer les parties prenantes dans les mises à jour
D20: La charte a été validée formellement par la direction générale et les parties prenantes. | E20: La charte de la DSI a-t-elle été formellement validée par la direction générale et les parties prenantes ? | F20: PV de validation | G20: Oui | H20: Validation non formalisée. | I20: Moyenne | J20: Manque d’engagement des dirigeants et légitimité affaiblie. | K20: Organiser une cérémonie de signature formelle
F21: Liste des signataires | G21: Non | I21: Élevée | K21: Archiver les preuves de validation
C22: Évaluer le degré d’implication et de maîtrise des organes de gestion dans les systèmes d’information de l’Organisation ; | D22: Ils démontrent une bonne connaissance des enjeux et des risques informatiques. | E22: Les membres de la DSI démontrent-ils une bonne compréhension des enjeux et risques informatiques ? | F22: Rapport d’analyse des risques informatiques | G22: Oui | H22: Manque de formation ou d’expertise. | I22: Moyenne | J22: Prise de décision inadaptée face aux risques. | K22: Organiser des sessions de sensibilisation aux risques
F23: Compte-rendu des revues stratégiques | G23: Non | I23: Moyenne | K23: Mettre en place une veille technologique et réglementaire
D24: Leurs recommandations sont prises en compte dans les projets informatiques. | E24: Les recommandations de la DSI sont-elles systématiquement prises en compte dans les projets informatiques ? | F24: Registre des recommandations et suivi | G24: Oui | H24: Recommandations ignorées. | I24: Élevée | J24: Projets mal alignés avec les besoins métiers ou stratégiques. | K24: Instaurer un processus formel de validation des recommandations
F25: Procès-verbal des décisions projets | G25: Non | I25: Moyenne | K25: Associer systématiquement les parties prenantes aux arbitrages
D26: Ils sont impliqués dans la définition des orientations stratégiques de la DSI. | E26: Les membres de la DSI participent-ils activement à la définition des orientations stratégiques ? | F26: Feuille de route stratégique de la DSI | G26: NON | H26: Implication superficielle. | I26: Moyenne | J26: Stratégie informatique déconnectée des enjeux business. | K26: Organiser des ateliers annuels de définition stratégique
F27: Compte-rendu des ateliers de coconstruction | G27: NON | I27: Moyenne | K27: Créer un comité de pilotage dédié aux orientations IT
D28: Ils sont capables de challenger les propositions de la DSI de manière constructive. | E28: Les membres de la DSI sont-ils capables de remettre en question les propositions de manière constructive ? | F28: Grille d’évaluation des propositions techniques | G28: Non | H28: Absence de remise en question. | I28: Élevée | J28: Propositions non optimisées ou risquées. | K28: Former aux méthodes de revue constructive
F29: Rapport d’analyse critique des solutions | G29: Oui | I29: Élevée | K29: Introduire des revues croisées entre métiers et IT
D30: Des rapports réguliers sur l’état des systèmes d’information leur sont présentés. | E30: Les rapports réguliers sur l'état des systèmes d'information sont-ils présentés aux membres concernés ? | F30: Dashboard de supervision des SI Rapports d’incidents et de performance | G30: Non | H30: Rapports incomplets ou irréguliers. | I30: Moyenne | J30: Manque de visibilité sur les performances et les risques. | K30: Automatiser la production des rapports clés Adapter les indicateurs aux besoins des décideurs
F31: Charte projet validée Document des | G31: Oui | I31: Moyenne | K31: Impliquer les métiers dès l’initialisation des projets
C32: Vérifier en pratique que le leadership des grands projets est assuré par les organes de gestion | D32: Les organes de gestion participent à la définition des objectifs et des livrables des projets. | E32: Les organes de gestion participent-ils à la définition des objectifs et livrables des projets ? | F32: objectifs et livrables | G32: Non | H32: Désalignement entre parties prenantes. | I32: Moyenne | J32: Objectifs flous ou contradictoires, livrables inadaptés. | K32: Formaliser des revues de cadrage périodiques
F33: Reporting d’avancement mensuel | G33: NON | I33: Moyenne | K33: Utiliser des outils collaboratifs de suivi
D34: Ils communiquent régulièrement sur l’avancement des projets auprès des parties prenantes. | E34: Les organes de gestion communiquent-ils régulièrement sur l'avancement des projets ? | F34: Compte-rendu des points d’étape | G34: Non | H34: Communication insuffisante. | I34: Moyenne | J34: Incompréhension des attentes et perte de confiance. | K34: Planifier des points dédiés selon le public cible
F35: Feuille de présence aux COPILs | G35: NON | I35: Moyenne | K35: Rendre obligatoire la participation aux COPILs clés
D36: Ils assistent activement aux comités de pilotage des grands projets. | E36: Les organes de gestion assistent-ils activement aux comités de pilotage des grands projets ? | F36: Plan d’action post- | G36: Non | H36: Participation intermittente. | I36: Moyenne | J36: Décisions prises sans vision globale des impacts. | K36: Formaliser un plan de suivi des décisions
F37: COPIL | G37: Oui | I37: Élevée | K37: Appliquer une gestion proactive des risques projet
D38: Les projets respectent les délais et les budgets sous leur supervision. | E38: Les projets sous leur supervision respectent-ils les délais et budgets prévus ? | F38: Rapport de suivi budgétaire Planning projet actualisé | G38: Non | H38: Dérives fréquentes en coûts ou délais. | I38: Élevée | J38: Perte de crédibilité et dépassements budgétaires. | K38: Mettre en place des revues financières trimestrielles
F39: Procès-verbal des arbitrages | G39: NON | I39: Moyenne | K39: Définir des seuils d’alerte pour déclencher les arbitrages
D40: Ils prennent des décisions en cas de dérives ou de risques identifiés pendant les projets. | E40: Les organes de gestion prennent-ils des décisions appropriées en cas de dérives ou de risques identifiés ? | F40: Plan d’atténuation des risques | G40: OUI | H40: Indécision ou retard dans les arbitrages. | I40: Moyenne | J40: Aggravation des problèmes et impacts sur la réussite du projet. | K40: Former aux techniques de gestion de crise
F41: Charte MOA/MOE | G41: NON | I41: Moyenne | K41: Formaliser une matrice
C42: Vérifier que les métiers assurent leur rôle de MOA. | D42: Les rôles et responsabilités de la MOA sont clairement définis et documentés. | E42: Les rôles et responsabilités de la MOA sont-ils clairement définis et formalisés ? | F42: Fiches de poste détaillées | G42: Non | H42: Rôles mal définis. | I42: Moyenne | J42: Confusion dans la gouvernance et inefficacité des projets. | K42: RACI pour les projets Organiser des ateliers de clarification des rôles
F43: Planning projet validé | G43: Oui | I43: Moyenne | K43: Mettre en place des alertes automatiques sur les dérives
D44: La MOA respecte les délais et les engagements pris dans le cadre des projets. | E44: La MOA respecte-t-elle les délais et engagements pris dans les projets ? | F44: Rapport d’avancement mensuel | G44: Non | H44: Retards chroniques. | I44: Moyenne | J44: Désorganisation et mécontentement des parties prenantes. | K44: Introduire des revues hebdomadaires des engagements
F45: Cahier des charges fonctionnel | G45: Oui | I45: Moyenne | K45: Créer un référent métier dédié par projet
D46: Les métiers sont impliqués dans la définition des besoins et des spécifications fonctionnelles. | E46: Les métiers sont-ils impliqués dans la définition des besoins et spécifications fonctionnelles ? | F46: Procès-verbal des ateliers métiers | G46: Non | H46: Implication limitée. | I46: Moyenne | J46: Besoins mal capturés, solutions inadaptées. | K46: Utiliser des outils collaboratifs de collecte de besoins
F47: Grille de priorisation des besoins | G47: NON | I47: Moyenne | K47: Former les métiers aux méthodes d’arbitrage
D48: Les métiers sont capables de prioriser les besoins et d’arbitrer en cas de conflits. | E48: Les métiers sont-ils capables de prioriser les besoins et d'arbitrer en cas de conflits ? | F48: Compte-rendu des comités d’arbitrage | G48: Non | H48: Priorisation inefficace. | I48: Moyenne | J48: Ressources gaspillées sur des besoins non critiques. | K48: Établir des critères objectifs de priorisation
F49: Prototypes validés | G49: Oui | I49: Moyenne | K49: Impliquer les métiers dans les tests utilisateurs
D50: Ils participent activement aux phases de conception et de validation des solutions. | E50: Les métiers participent-ils activement aux phases de conception et validation des solutions ? | F50: Procès-verbal de recette utilisateur | G50: Non | H50: Participation passive. | I50: Moyenne | J50: Solutions non conformes aux attentes métiers. | K50: Planifier des ateliers de coconception
F51: Document de périmètre signé | G51: Oui | I51: Moyenne | K51: Utiliser des outils de modélisation BPMN
B52: Planification stratégique ; | C52: Vérifier la couverture du périmètre fonctionnel ; | D52: Le périmètre fonctionnel est clairement défini et documenté. | E52: Le périmètre fonctionnel est-il clairement défini et documenté dans un document officiel ? | F52: Cartographie des processus impactés | G52: NON | H52: Périmètre flou ou mouvant. | I52: Moyenne | J52: Projets sans limites claires, dérives fonctionnelles. | K52: Valider le périmètre en comité transverse
F53: Matrice des écarts | G53: Non | I53: Moyenne | K53: Auditer les solutions existantes annuellement
D54: Les écarts entre les besoins fonctionnels et les solutions existantes sont identifiés et documentés. | E54: Les écarts entre les besoins fonctionnels et les solutions existantes sont-ils identifiés et documentés ? | F54: (gap analysis) Plan de mitigation des écarts | G54: NON | H54: Écarts non analysés. | I54: Élevée | J54: Solutions incohérentes avec les processus métiers. | K54: Documenter les solutions de contournement
F55: Liste des processus critiques | G55: Non | I55: Moyenne | K55: Identifier les processus critiques avec les dirigeants
D56: Tous les processus métiers critiques sont inclus dans le périmètre fonctionnel. | E56: Tous les processus métiers critiques sont-ils inclus dans le périmètre fonctionnel ? | F56: Analyse d’impact métier | G56: NON | H56: Processus critiques oubliés. | I56: Moyenne | J56: Risques opérationnels et perturbations métiers. | K56: Intégrer les risques métiers dans l’analyse
F57: Cartographie des processus | G57: Non | I57: Moyenne | K57: Automatiser la mise à jour via des outils dédiés
D58: Une cartographie des processus métiers et des applications associées est disponible et à jour | E58: La cartographie des processus métiers et des applications associées est-elle disponible et à jour ? | F58: Inventaire des applications | G58: Oui | H58: Cartographie obsolète. | I58: Moyenne | J58: Décisions basées sur des informations erronées. | K58: Lier la cartographie aux objectifs stratégiques
F59: Registre des applications Rapport de couverture fonctionnelle | G59: OUI | I59: Moyenne | K59: Réaliser des audits de couverture semestriels Aligner les évolutions IT sur le roadmap métier
D60: Les applications et systèmes informatiques couvrent l’ensemble des besoins fonctionnels identifiés. | E60: Les applications et systèmes informatiques couvrent-ils l'ensemble des besoins fonctionnels identifiés ? | F60: Procédures de pilotage | G60: Non | H60: Couverture incomplète. | I60: Moyenne | J60: Inefficacité opérationnelle et recours à des solutions parallèles. | K60: Automatiser le suivi des indicateurs clés
F61: Rapport d’audit des processus | G61: NON | I61: Élevée | K61: Former les équipes aux bonnes pratiques ITIL
C62: Vérifier l’existence d’une analyse à jour des procédures de pilotage et de mise à jour du plan informatique ; | D62: Une analyse des procédures de pilotage du plan informatique est disponible et à jour. | E62: Une analyse des procédures de pilotage du plan informatique est-elle disponible et à jour ? | F62: Plan stratégique IT Document d’alignement métier/IT | G62: NON | H62: Procédures non formalisées. | I62: Moyenne | J62: Pilotage inefficace et manque de cohérence stratégique. | K62: Organiser des ateliers d’alignement annuels Créer un comité stratégique métier-IT
F63: Matrice des responsabilités (RACI) | G63: Non | I63: Élevée | K63: Nommer un responsable dédié à la gouvernance IT
D64: Le plan informatique est aligné sur la stratégie globale de l’organisation. | E64: Le plan informatique est-il aligné sur la stratégie globale de l'organisation ? | F64: Calendrier des mises à jour | G64: Oui | H64: Désalignement stratégique. | I64: Élevée | J64: Investissements informatiques non pertinents. | K64: Intégrer les feedbacks métiers dans les mises à jour
F65: Historique des versions Rapport de conformité aux échéances | G65: Non | I65: Moyenne | K65: Utiliser des outils de gestion de version Planifier des revues trimestrielles
D66: Les rôles et responsabilités pour la mise à jour du plan informatique sont clairement définis. | E66: Les rôles et responsabilités pour la mise à jour du plan informatique sont-ils clairement définis ? | F66: Veille technologique documentée | G66: NON | H66: Responsabilités floues. | I66: Moyenne | J66: Plan non actualisé et perte de pertinence. | K66: Souscrire à des veilles sectorielles
F67: Analyse SWOT des technologies | G67: Oui | I67: Moyenne | K67: Impliquer les experts techniques dans les revues
D68: Les mises à jour du plan informatique sont réalisées à une fréquence définie et respectée | E68: Les mises à jour du plan informatique sont-elles réalisées à une fréquence définie et respectée ? | F68: Schéma directeur IT Cartographie des systèmes | G68: Non | H68: Mises à jour irrégulières. | I68: Moyenne | J68: Plan obsolète et inadapté aux évolutions. | K68: Centraliser les documents sur un portail collaboratif Mettre en place un workflow de validation
F69: Roadmap | G69: NON | I69: Élevée | K69: Organiser des ateliers de prospective technologique
D70: Les procédures de pilotage incluent des mécanismes de suivi des évolutions technologiques et des besoins métiers. | E70: Les procédures de pilotage incluent-elles des mécanismes de suivi des évolutions technologiques et des besoins métiers ? | F70: technologique Scénarios d’évolution | G70: Non | H70: Mécanismes absents ou inefficaces. | I70: Moyenne | J70: Retards dans l’adoption de technologies pertinentes. | K70: Adopter une méthodologie type TOGAF
F71: Plan de mise à jour | G71: NON | I71: Élevée | K71: Automatiser les alertes de révision
C72: Vérifier l’existence des documents à jour d’urbanisme de l’Organisation | D72: Les documents d’urbanisme (cartographie des systèmes, schémas directeurs, etc.) existent et sont accessibles. | E72: Les documents d'urbanisme existent-ils et sont-ils accessibles ? | F72: Journal des modifications | G72: NON | H72: Documents inexistants ou inaccessibles. | I72: Moyenne | J72: Manque de vision globale et décisions incohérentes. | K72: Auditer l’urbanisme tous les 6 mois
F73: Fiche d’impact des évolutions | G73: Non | I73: Moyenne | K73: Lier les demandes de projet à l’urbanisme
D74: Les documents d’urbanisme incluent une vision à court, moyen et long terme. | E74: Les documents d'urbanisme incluent-ils une vision à court, moyen et long terme ? | F74: Compte-rendu des comités d’architecture | G74: NON | H74: Vision à court terme uniquement. | I74: Moyenne | J74: Architecture inadaptée aux besoins futurs. | K74: Créer un référent architecture dédié
F75: Matrice des dépendances | G75: Non | I75: Moyenne | K75: Utiliser des outils de modélisation (ex.
D76: Les documents d’urbanisme sont mis à jour régulièrement pour refléter l’état actuel des systèmes. | E76: Les documents d'urbanisme sont-ils mis à jour régulièrement pour refléter l'état actuel des systèmes ? | F76: Diagrammes d’architecture | G76: Oui | H76: Documents obsolètes. | I76: Moyenne | J76: Décisions basées sur une vision erronée de l’existant. | K76: Documenter les APIs et interfaces
F77: Procédures du POS Rapport de conformité | G77: Oui | I77: Moyenne | K77: Aligner le POS sur les normes sectorielles Former les équipes aux enjeux du POS
D78: Les évolutions technologiques et fonctionnelles sont intégrées dans les documents d’urbanisme. | E78: Les évolutions technologiques et fonctionnelles sont-elles intégrées dans les documents d'urbanisme ? | F78: Document d’alignement | G78: Non | H78: Retard dans les mises à jour. | I78: Moyenne | J78: Incohérences entre la cible et la réalité. | K78: Valider le POS en comité de direction
F79: Revue stratégique du POS | G79: Oui | I79: Moyenne | K79: Cartographier les liens avec les projets IT
D80: Les dépendances entre les applications et les systèmes sont clairement représentées. | E80: Les dépendances entre les applications et les systèmes sont-elles clairement représentées ? | F80: Fiche de rôle POS | G80: Non | H80: Dépendances mal documentées. | I80: Moyenne | J80: Difficultés dans les évolutions ou les migrations. | K80: Désigner un architecte
F81: Procès-verbal de nomination | G81: Oui | I81: Moyenne | K81: Établir des KPI de mise à jour
C82: Vérifier l’existence d’une analyse à jour des procédures de pilotage et de mise à jour du plan d’occupation des sols (POS) ; | D82: Une analyse des procédures de pilotage du POS est disponible et à jour. | E82: Une analyse des procédures de pilotage du POS est-elle disponible et à jour ? | F82: Calendrier des mises à jour | G82: Non | H82: Procédures non formalisées. | I82: Moyenne | J82: Gestion inefficace du système d’information. | K82: Intégrer le POS dans les revues de gouvernance
F83: Rapport d’avancement | G83: Oui | I83: Moyenne | K83: Automatiser les rappels d’échéances
D84: Le POS est aligné sur la stratégie globale de l’organisation et sur le plan informatique | E84: Le POS est-il aligné sur la stratégie globale de l'organisation et sur le plan informatique ? | F84: Registre des demandes métiers | G84: Oui | H84: Désalignement stratégique. | I84: Moyenne | J84: Investissements incohérents avec les objectifs business. | K84: Créer un comité métier-IT Utiliser des outils de suivi
F85: Compte-rendu des revues techniques | G85: Non | I85: Moyenne | K85: des demandes
D86: Les rôles et responsabilités pour la mise à jour du POS sont clairement définis. | E86: Les rôles et responsabilités pour la mise à jour du POS sont-ils clairement définis ? | F86: Inventaire technologique Politique de standardisation | G86: Oui | H86: Responsabilités floues. | I86: Moyenne | J86: POS non actualisé et perte de pertinence. | K86: Mettre en place un comité de validation technologique Élaborer un guide des bonnes pratiques
F87: Catalogue des interfaces | G87: Non | I87: Moyenne | K87: Automatiser la documentation via des outils dédiés
D88: Les mises à jour du POS sont réalisées à une fréquence définie et respectée. | E88: Les mises à jour du POS sont-elles réalisées à une fréquence définie et respectée ? | F88: Documentation technique des APIs | G88: Oui | H88: Mises à jour irrégulières. | I88: Moyenne | J88: POS obsolète et inadapté aux évolutions. | K88: Implémenter des tests d'intégration réguliers
F89: Procès-verbal des comités de sélection | G89: Non | I89: Moyenne | K89: Établir une grille d'évaluation multicritère
D90: Les procédures de pilotage incluent des mécanismes de suivi des évolutions des besoins métiers et techniques. | E90: Les procédures de pilotage incluent-elles des mécanismes de suivi des évolutions des besoins métiers et techniques ? | F90: Analyse coûtbénéfice | G90: Oui | H90: Mécanismes absents ou inefficaces. | I90: Moyenne | J90: Retards dans l’alignement du POS avec les besoins. | K90: Impliquer les métiers dans les décisions technologiques
F91: Plan de migration technologique Rapport d'obsolescence | G91: Oui | I91: Moyenne | K91: Programmer des audits technologiques semestriels Allouer un budget dédié aux migrations
C92: Vérifier la cohérence et l’homogénéité des technologies | D92: Les technologies utilisées dans l’organisation sont documentées et standardisées. | E92: Les technologies utilisées sont-elles documentées et standardisées ? | F92: Analyse de rationalisation | G92: Non | H92: Technologies non documentées. | I92: Moyenne | J92: Complexité accrue et coûts de maintenance élevés. | K92: Mettre en place une gouvernance des licences logicielles
F93: Plan de suppression des redondances | G93: Oui | I93: Élevée | K93: Centraliser les achats technologiques
D94: Les interfaces entre les différentes technologies sont fonctionnelles et documentées. | E94: Les interfaces entre les différentes technologies sont-elles fonctionnelles et documentées ? | F94: Inventaire des référentiels | G94: Non | H94: Interfaces mal définies. | I94: Moyenne | J94: Problèmes d’intégration et d’interopérabilité. | K94: Standardiser les formats de données
F95: Politique d'accès | G95: Oui | I95: Moyenne | K95: Implémenter un outil de MDM
D96: Les choix technologiques sont alignés sur la stratégie informatique et les besoins métiers. | E96: Les choix technologiques sont-ils alignés sur la stratégie informatique et les besoins métiers ? | F96: Matrice des habilitations | G96: Non | H96: Choix technologiques inadaptés. | I96: Moyenne | J96: Solutions inefficaces ou non utilisées. | K96: Automatiser les revues de droits trimestrielles
F97: Rapports d'audit des accès | G97: Oui | I97: Moyenne | K97: Appliquer le principe du moindre privilège
D98: Les technologies obsolètes ou non supportées sont identifiées et remplacées. | E98: Les technologies obsolètes ou non supportées sont-elles identifiées et remplacées ? | F98: Politique de gestion des données | G98: Non | H98: Technologies obsolètes maintenues. | I98: Moyenne | J98: Risques de sécurité et coûts de maintenance élevés. | K98: Mettre en place des contrôles d'intégrité
F99: Rapport de qualité des données | G99: Oui | I99: Moyenne | K99: Désigner des data stewards par domaine
D100: Les doublons technologiques (applications ou outils redondants) sont identifiés et éliminés. | E100: Les doublons technologiques sont-ils identifiés et éliminés ? | F100: Documentation des processus métiers | G100: Non | H100: Redondances non traitées. | I100: Moyenne | J100: Gaspillage de ressources et complexité inutile. | K100: Organiser des ateliers métiers-
...

Sheet Audit_Controle_Projet_Informati
A1: Domaines | B1: Points de contrôle | C1: Objectifs de controle | D1: Critères d'évaluation | E1: Documents requis | F1: Questions d'evaluation | G1: Reponses | H1: Risques | I1: Criticités | J1: Consequences | K1: Recommendations
A2: Contrôle des Projets Informatiques | B2: Objectifs et enjeux du projet | C2: S’assurer qu’une étude de la valeur et des études d'opportunité et d'impacts ont été réalisées | D2: Une analyse coûts/bénéfices documentée justifie le projet. | E2: Rapport d'analyse financière | F2: Quels indicateurs financiers prouvent la rentabilité du projet ? | G2: OUI | H2: Données financières inexactes | I2: Elevée | J2: Prise de décision erronée | K2: Formaliser un processus de validation collectif des décisions afin d’éviter toute remise en cause des choix finaux.
E3: Synthèse des bénéfices attendus | F3: Comment les bénéfices qualitatifs (ex: satisfaction client) sont-ils intégrés ? | G3: NON | H3: Surestimation des gains potentiels | I3: Elevée | J3: Déséquilibre budgétaire | K3: Documenter systématiquement les critères de choix pour justifier objectivement chaque décision finale.
D4: Les scénarios d'opportunité comparent différentes solutions (interne, externe, hybride). | E4: Comparatif des solutions | F4: Quels critères (coût, délai, risque) ont déterminé le choix ? | G4: NON | H4: Biais en faveur d'une solution non optimale | I4: Elevée | J4: Coûts supplémentaires | K4: Réaliser une veille stratégique régulière pour éviter de s’engager dans une direction inadéquate.
E5: Grille de décision multicritères | F5: Pourquoi les solutions rejetées sont-elles moins pertinentes ? | G5: NON | H5: Pondération subjective des critères | I5: Élevée | J5: Choix inapproprié | K5: Impliquer la direction dans les phases d’orientation pour prévenir les choix stratégiques incohérents.
D6: Les impacts fonctionnels, techniques et organisationnels sont évalués. | E6: Matrice des impacts | F6: Comment les impacts sur les équipes sont-ils mitigés ? | G6: NON | H6: Impacts secondaires non identifiés | I6: Moyenne | J6: Effets domino imprévus | K6: Utiliser des outils de simulation budgétaire pour limiter les erreurs de prévision financière.
E7: Plan de transition organisationnelle | F7: Quelles adaptations techniques sont nécessaires ? | G7: NON | H7: Résistance au changement non anticipée | I7: Moyenne | J7: Retards dans l'implémentation | K7: Intégrer des marges d’erreur dans le chiffrage afin de compenser les imprécisions dans l’estimation.
D8: Les risques liés à la nonréalisation du projet sont identifiés. | E8: Liste des risques métiers | F8: Quels risques critiques justifient le projet en urgence ? | G8: OUI | H8: Risques émergents non inclus | I8: Élevée | J8: Réponse inadéquate aux crises | K8: Mettre à jour régulièrement les plannings de charge pour anticiper tout dépassement de capacité.
E9: Analyse coût de l'inaction | F9: Comment quantifier l'impact financier de l'inaction ? | G9: OUI | H9: Sous-estimation des conséquences financières | I9: Moyenne | J9: Insuffisance de provisions | K9: Établir un suivi des ressources allouées par tâche pour maîtriser l’engagement effectif des moyens.
D10: Les attentes des parties prenantes sont recueillies et prises en compte. | E10: Registre des parties prenantes | F10: Comment les attentes contradictoires sont-elles arbitrées ? | G10: OUI | H10: Parties prenantes influentes oubliées | I10: Moyenne | J10: Opposition au projet | K10: Élaborer un business case dès l’amont du projet pour démontrer sa pertinence.
E11: Compte-rendu d'ateliers | F11: Quelles attentes sont exclues du périmètre ? | G11: Non | H11: Décisions mal retranscrites | I11: Moyenne | J11: Actions contradictoires | K11: Suivre des indicateurs de valeur ajoutée pour justifier la légitimité du projet en cours.
C12: S’assurer qu’un bilan critique des processus existants a été effectué | D12: Les forces et faiblesses des processus actuels sont formalisées. | E12: Audit des processus AS-IS | F12: Quelles faiblesses génèrent des surcoûts récurrents ? | G12: NON | H12: Processus obsolètes non identifiés | I12: Élevée | J12: Inefficacités persistantes | K12: Centraliser les données de pilotage dans un outil unique pour éviter des écarts d'information.
E13: Rapport SWOT processus | F13: Comment les forces actuelles sont-elles préservées ? | G13: Non | H13: Menaces externes sousévaluées | I13: Élevée | J13: Préparation insuffisante | K13: Définir des jalons clairs et validés pour garantir la cohérence du suivi du projet.
D14: Les écarts entre processus existants et besoins métiers sont analysés. | E14: Cartographie des écarts | F14: Quels écarts remettent en cause la conformité réglementaire ? | G14: Oui | H14: Écarts critiques non priorisés | I14: Moyenne | J14: Problèmes non résolus | K14: Mener des actions de communication et de sensibilisation pour limiter la résistance au changement.
E15: Priorisation des gaps | F15: Comment les écarts acceptables sont-ils justifiés ? | G15: Non | H15: Subjectivité dans la hiérarchisation | I15: Moyenne | J15: Allocation inefficace des ressources | K15: Intégrer les utilisateurs dès la conception pour réduire les blocages en phase de déploiement.
D16: Les gains potentiels d’une optimisation des processus sont quantifiés. | E16: Benchmark sectoriel | F16: Quels KPIs mesureront l'efficacité postoptimisation ? | G16: Oui | H16: Données comparatives obsolètes | I16: Moyenne | J16: Analyses erronées | K16: Instaurer des points d’écoute réguliers pour maintenir l’implication des parties prenantes.
E17: Modélisation des gains | F17: Comment les gains sont-ils répartis (temps, qualité, coût) ? | G17: Non | H17: Hypothèses de croissance trop optimistes | I17: Moyenne | J17: Planification irréaliste | K17: Communiquer sur les bénéfices attendus pour éviter le désengagement des acteurs.
D18: Les goulots d’étranglement et dysfonctionnements sont documentés. | E18: Logs d'incidents Analyse des flux de valeur | F18: Quels goulots impactent directement le timeto-market ? | G18: Oui | H18: Interprétation erronée des résultats | I18: Élevée | J18: Actions incorrectes | K18: Archiver toutes les étapes décisionnelles pour répondre aux exigences des audits.
E19: Diagrammes BPMN | F19: Quelles solutions immédiates sont testables ? | G19: OUI | H19: Sous-estimation des coûts cachés | I19: Élevée | J19: Dépassement budgétaire | K19: Mettre en place une revue qualité périodique pour éviter la disqualification en audit.
D20: Une cartographie des processus critiques est disponible. | E20: Fiche de risque par processus | F20: Comment la criticité est-elle définie (risque, fréquence) ? | G20: Oui | H20: Critères de comparaison mal définis | I20: Moyenne | J20: Sanctions réglementaires | K20: Clarifier les rôles et responsabilités des décideurs pour fluidifier les prises de décision.
E21: Résultats A/B testing Retours utilisateurs tests | F21: Quels processus sont éligibles à l'automatisation ? | G21: Non | H21: Omission de critères clés | I21: Élevée | J21: Perte de crédibilité | K21: Mettre en place un circuit court de validation pour éviter les interruptions du processus décisionnel.
C22: S’assurer que le choix de recourir à un nouveau système est obtenu après optimisation des processus concernés et vérification que cette optimisation ne suffit pas à apporter par elle-même les gains de performance attendus | D22: Des tests d’optimisation des processus existants ont été menés. | E22: Analyse ROI sur 3 ans Étude de faisabilité technique | F22: sont-ils insuffisants sans nouveau système ? | G22: Oui | H22: Mauvaise évaluation de la gravité des impacts | I22: Moyenne | J22: Performance sousoptimale | K22: Digitaliser les procédures de validation pour accélérer les démarches administratives.
E23: 3 ans Étude de faisabilité technique | F23: Quel seuil de gain justifie le saut technologique ? Comment | G23: Non | H23: Délais de transition irréalistes | I23: Moyenne | J23: Conflits entre parties prenantes | K23: Mettre à jour les référentiels administratifs pour éviter les blocages liés à l’obsolescence des documents.
D24: Les résultats de l’optimisation montrent des limites claires. | E24: Fiche des objectifs validée Grille d'évaluation | F24: l'évolution des besoins est-elle anticipée ? | G24: Oui | H24: Priorisation incorrecte des risques | I24: Élevée | J24: Dépenses imprévues | K24: Définir des critères d’évaluation en amont pour assurer la validité du bilan.
E25: SMART | F25: Comment l'atteinte des objectifs sera-telle audité ? | G25: Non | H25: Négligence des impacts non financiers | I25: Moyenne | J25: Adoption partielle | K25: Impliquer des auditeurs tiers dans l’analyse pour garantir l’objectivité du bilan final.
D26: Une comparaison entre amélioration continue et nouveau système est réalisée. | E26: Document de scope | F26: Quels objectifs sont ajustables en cours de projet ? | G26: NON | H26: Mauvaise analyse des intérêts et pouvoirs | I26: Moyenne | J26: Augmentation des coûts | K26: Mettre en place un retour d’expérience systématique pour éviter la reproduction des erreurs passées.
E27: PV de validation | F27: Comment les demandes hors périmètre serontelles gérées ? | G27: NON | H27: Actions non assignées ou floues | I27: Moyenne | J27: Détérioration de la trésorerie | K27: Créer une base de données des incidents passés pour capitaliser sur les leçons apprises.
D28: Les gains attendus du nouveau système dépassent significativement l’optimisation. | E28: MOA/MOE | F28: Quelles interfaces techniques sont incluses/exclues ? | G28: Non | H28: Manque de granularité dans l'analyse | I28: Élevée | J28: Besoins clés non couverts | K28: Réaliser des prototypes avant déploiement pour éviter la mise en place de solutions inefficaces.
E29: Schéma d'architecture Plan de migration | F29: Comment l'architecture garantit-elle l'interopérabilité ? | G29: Oui | H29: Opportunités surestimées | I29: Élevée | J29: Responsabilités floues | K29: Impliquer les utilisateurs dans le choix des solutions pour garantir leur adéquation aux besoins.
D30: La nécessité d’un changement technologique ou structurel est démontrée. | E30: d'architecture Plan de migration | F30: Quels composants legacy sont conservés ? | G30: Non | H30: Solutions de correction irréalistes | I30: Moyenne | J30: Non-conformité | K30: Mettre à jour en temps réel les tableaux de bord pour fiabiliser le suivi du projet.
E31: Analyse coût-total | F31: Comment la solution retenue évite le vendor lockin ? | G31: Oui | H31: Manque de justification des choix | I31: Moyenne | J31: Pertes financières | K31: Nommer un responsable du reporting projet pour assurer l’exactitude des données de pilotage.
C32: S’assure que les objectifs et périmètres du projet sont définis, partagés et stabilisés | D32: Les objectifs SMART (Spécifiques, Mesurables, Atteignables, Réalistes, Temporels) sont formalisés. | E32: Évaluation fournisseurs | F32: Quels critères techniques ont guidé le choix ? | G32: Non | H32: Biais de sélection des concurrents | I32: Moyenne | J32: Détérioration de la qualité | K32: Standardiser les formats de reporting pour faciliter la compréhension des données.
E33: Référentiel de conformité Audit de sécurité | F33: Quels écarts aux normes sont tolérés temporairement ? Comment la conformité RGPD est-elle assurée ? | G33: NON | H33: Ignorance des variables externes | I33: Moyenne | J33: Objectifs manqués | K33: Former les parties prenantes à la lecture des indicateurs pour éviter les erreurs d’interprétation.
D34: Le périmètre fonctionnel et technique est délimité et validé. | E34: Planning roadmap | F34: Comment les dépendances entre livrables sont-elles gérées ? | G34: Non | H34: Incidents non documentés | I34: Moyenne | J34: Décisions basées sur des informations périmées | K34: Instaurer un cycle d’amélioration continue pour dynamiser l’évolution des pratiques.
E35: Feuille de route stratégique | F35: Quels jalons sont non négociables ? | G35: NON | H35: Gaspillage non détecté | I35: Moyenne | J35: Échec à atteindre les objectifs | K35: Organiser des ateliers d’innovation participative pour stimuler l’amélioration.
D36: Les livrables principaux sont listés et acceptés par les parties prenantes. | E36: Matrice RACI | F36: Qui a un droit de veto sur les décisions techniques ? Comment les | G36: Non | H36: Erreurs de modélisation des processus | I36: Moyenne | J36: Perte d'opportunités | K36: Définir des indicateurs SMART pour faciliter l’évaluation des résultats.
E37: Organigramme projet | F37: conflits d'intérêt sont-ils prévenus ? | G37: Oui | H37: Risques liés aux interdépendances omis | I37: Élevée | J37: Réduction de la marge bénéficiaire | K37: Associer chaque livrable à une métrique pour objectiver les résultats.
D38: Les exclusions (hors périmètre) sont clairement mentionnées. | E38: Budget détaillé | F38: Comment les dépassements budgétaires serontils alertés ? | G38: Non | H38: Biais dans le groupe de test | I38: Élevée | J38: Évaluation biaisée | K38: Rédiger un livret de présentation du projet pour éviter le manque de compréhension.
E39: Plan de financement | F39: Quels coûts sont éligibles à des subventions ? | G39: NON | H39: Feedback non représentatif | I39: Moyenne | J39: Décisions incomplètes | K39: Organiser des sessions de transfert de connaissances pour diffuser le contenu du projet.
D40: Un document de cadrage (charte de projet) est signé par le sponsor. | E40: CDC signé | F40: Comment les besoins non fonctionnels (ex: performance) sontils spécifiés ? | G40: OUI | H40: Hypothèses économiques invalides | I40: Moyenne | J40: Priorisation erronée | K40: Mettre en place une charte de collaboration pour encadrer les relations interpersonnelles.
E41: Procès-verbal de revue | F41: Qui valide les changements sur les exigences ? | G41: NON | H41: Contraintes techniques sous-estimées | I41: Moyenne | J41: Pression excessive sur les équipes | K41: Organiser des réunions de médiation régulières pour prévenir ou résoudre les conflits.
C42: S’assurer que les principales orientations du système cible ont été explicitées | D42: L’architecture cible (fonctionnelle et technique) est décrite. | E42: Audit d'alignement Plan de migration techno | F42: Quels composants nécessitent une refonte pour être compatibles ? Comment les obsolescences sontelles gérées ? | G42: Non | H42: Objectifs non alignés avec la stratégie | I42: Moyenne | J42: Exposition à des menaces majeures | K42: Archiver systématiquement les sources et versions pour éviter la perte d’informations critiques.
E43: Document d'alignement PV COPIL stratégique | F43: Comment le projet contribue-t-il à la transformation digitale ? Quels autres projets partagent les mêmes dépendances ? | G43: Oui | H43: Objectifs trop ambitieux ou vagues | I43: Moyenne | J43: Atteinte à la réputation | K43: Mettre en place un système de gestion documentaire pour structurer la conservation des références.
D44: Les choix technologiques (build vs. buy, cloud, etc.) sont justifiés. | E44: Charte de projet signée | F44: Quel est le dispositif d'escalade en cas de blocage ? | G44: Non | H44: Scope creep non contrôlé | I44: Moyenne | J44: Conflits non résolus | K44: Journaliser toutes les décisions stratégiques pour garantir la traçabilité.
E45: Compte-rendu de réunions décisionnelles | F45: Comment le sponsor mesure-t-il l'avancement ? | G45: Oui | H45: Approbations non formalisées | I45: Moyenne | J45: Retard dans l'exécution | K45: Utiliser un outil collaboratif avec historique pour suivre l’origine de chaque décision.
D46: Les standards et normes à respecter sont identifiés. | E46: Matrice complétée | F46: Qui est accountable pour les risques critiques ? | G46: Non | H46: Responsabilités mal définies | I46: Moyenne | J46: Détails critiques omis | K46: Réaliser des études d’impact préalables pour anticiper les conséquences des choix.
E47: Fiche de rôle par acteur | F47: Comment les zones grises (responsabilités floues) sont-elles éliminées ? | G47: NON | H47: Incompatibilités techniques non détectées | I47: Moyenne | J47: Attentes irréalistes | K47: Tester les décisions via des simulations pour éviter leur mise en œuvre prématurée.
D48: Les contraintes de sécurité et conformité sont intégrées. | E48: Inventaire des compétences | F48: Quels profils sont impossibles à recruter en interne ? | G48: Non | H48: Pertes de données pendant la migration | I48: Moyenne | J48: Problèmes récurrents | K48: Réaliser des audits réguliers du système pour détecter ses limites.
E49: Plan de formation | F49: Comment les connaissances métiers sont-elles capitalisées ? | G49: Oui | H49: Coûts cachés non inclus | I49: Moyenne | J49: Difficulté à obtenir l'adhésion | K49: Comparer le système actuel avec des alternatives pour envisager des solutions plus efficaces.
D50: Une roadmap des évolutions majeures est proposée. | E50: Business case Analyse des scénarios alternatifs | F50: Quel est le seuil minimal de ROI pour justifier le projet ? | G50: Non | H50: Critères de sélection biaisés | I50: Moyenne | J50: Partenariats sousoptimaux | K50: Formaliser les engagements dans des documents signés pour prévenir les litiges.
E51: Tableau de bord | F51: Comment les gains non financiers (ex: image) sont-ils valorisés ? | G51: Oui | H51: Exigences réglementaires obsolètes | I51: Moyenne | J51: Vulnérabilité aux changements | K51: Vérifier la conformité réglementaire à chaque étape pour éviter toute procédure judiciaire.
C52: S’assurer que les principaux acteurs sont identifiés | D52: Un organigramme des parties prenantes (MOA, MOE, utilisateurs, etc.) est établi. | E52: KPI | F52: Qui est responsable de la mesure des KPI ? | G52: NON | H52: Vulnérabilités non identifiées | I52: Moyenne | J52: Répétition des erreurs | K52: Revoir les procédures de gestion des incidents pour une meilleure réactivité.
E53: Définition des cibles | F53: Comment les KPI sont-ils révisés en cas de changement ? | G53: Non | H53: Jalons irréalistes | I53: Moyenne | J53: Coûts inutiles | K53: Élaborer un plan de reprise pour chaque processus critique.
D54: Les rôles et responsabilités (RACI) sont définis. | E54: SWOT formalisée | F54: Quelles opportunités externes (ex: réglementaires) sont exploitées ? Comment les menaces | G54: NON | H54: Changements stratégiques non anticipés | I54: Élevée | J54: Incompréhension des | K54: Utiliser des critères objectifs pour évaluer les options.
E55: Plan d'action associé | F55: concurrentielles sont-elles contrecarrées ? | G55: Non | H55: Responsabilités ambiguës | I55: Moyenne | J55: flux | K55: Impliquer plusieurs parties prenantes dans la prise de décision.
D56: Les sponsors et décideurs clés sont impliqués. | E56: Budget préliminaire signé | F56: Quels scénarios rendraient le projet infaisable ? | G56: NON | H56: Responsabilités ambiguës | I56: Moyenne | J56: Effets en cascade imprévus | K56: Effectuer une analyse complète des solutions disponibles avant de choisir.
E57: Plan de ressources humaines | F57: Comment les dépendances externes (ex: fournisseurs) sontelles sécurisées ? | G57: Non | H57: Chevauchements de rôles | I57: Moyenne | J57: Résultats non représentatifs | K57: Organiser des sessions de validation avec des experts pour évaluer chaque solution.
D58: Les équipes opérationnelles et supports sont listées. | E58: Note de cadrage, | F58: Les objectifs sont-ils mesurables ? Sont-ils alignés avec la stratégie globale ? | G58: Oui | H58: Dépassement budgétaire non anticipé | I58: Moyenne | J58: Améliorations inappropriées | K58: Mener des séances de formation pour démontrer la valeur du système choisi.
E59: Liste des livrables, Cahier des charges | F59: Les livrables sont-ils cohérents avec les objectifs ? Leur contenu est-il précisé ? | G59: OUI | H59: Sources de financement incertaines | I59: Moyenne | J59: Modèles financiers erronés | K59: Impliquer les utilisateurs finaux dès la phase de conception pour augmenter l'adhésion.
D60: Les représentants des métiers concernés sont associés. | E60: Expression de besoins, Spécifications fonctionnelles | F60: Les besoins sont-ils bien documentés ? Ont-ils été validés par les métiers ? | G60: Non | H60: Exigences contradictoires | I60: Moyenne | J60: Sélection sous-optimale | K60: Documenter de manière claire les critères et décisions prises lors de l’audit.
E61: Spécifications techniques, Architecture cible | F61: Les contraintes techniques sont-elles explicites ? Les choix sont-ils justifiés ? | G61: NON | H61: Décisions non actées | I61: Élevée | J61: Résultats insatisfaisants | K61: Impliquer un auditeur externe pour une perspective indépendante.
C62: S’assurer que les coûts sont évalués | D62: Une estimation budgétaire (CAPEX/OPEX) est réalisée. | E62: Analyse des parties prenantes, RACI | F62: Toutes les parties sont-elles représentées ? Leur rôle est-il clair ? | G62: NON | H62: Objectifs divergents entre équipes | I62: Moyenne | J62: Ressources mal allouées | K62: Mettre en place des points de contrôle réguliers pour suivre l’avancement des actions.
E63: Organigramme projet, Fiche de rôles | F63: Les responsabilités sont-elles bien réparties ? Le pilotage est-il structuré ? | G63: Non | H63: Interruptions de service imprévues | I63: Élevée | J63: Qualité compromise | K63: Clarifier les responsabilités et objectifs de chaque acteur impliqué.
D64: Les coûts de développement, déploiement et maintenance sont inclus. | E64: Budget prévisionnel, Plan de charges | F64: Les estimations sont-elles réalistes ? Les sources sont-elles identifiées ? | G64: Oui | H64: Incohérences avec la vision globale | I64: Élevée | J64: Gasillage de ressources | K64: Revoir et ajuster régulièrement la stratégie en fonction des retours terrain.
E65: Registre des risques, Analyse SWOT | F65: Les risques sont-ils classés ? Des plans d’atténuation sont-ils définis ? | G65: Non | H65: Décisions stratégiques non formalisées | I65: Moyenne | J65: Baisse de moral des équipes | K65: Mettre en place des outils de reporting efficaces pour suivre les objectifs stratégiques.
D66: Les coûts cachés (formation, migration, etc.) sont anticipés. | E66: Étude comparative, Analyse de scénario | F66: Les différentes options ont-elles été évaluées objectivement ? | G66: NON | H66: Objectifs du projet mal définis | I66: Moyenne | J66: Alliances manquées | K66: Organiser des médiations pour résoudre les différends rapidement.
E67: Grille de décision, Compte-rendu de comité | F67: Les critères sont-ils pondérés ? Le choix est-il tracé ? | G67: Oui | H67: Décisions mal communiquées | I67: Moyenne | J67: Responsabilité diluée | K67: Définir des règles de gouvernance claires pour éviter les conflits futurs.
D68: Une analyse des risques financiers est annexée. | E68: Étude d’impact métier, Rapport RH ou d'organisation | F68: Les changements d’organisation sont-ils identifiés ? Les impacts humains (formation, charge, résistance) sont-ils anticipés ? | G68: Non | H68: Données incomplètes ou obsolètes | I68: Moyenne | J68: Solutions superficielles | K68: Identifier et résoudre les goulots d'étranglement dans les processus.
E69: Cartographie des processus, BPMN ou diagrammes de flux | F69: Tous les processus impactés sont-ils représentés ? Les interactions inter-services sont-elles bien modélisées ? | G69: NON | H69: Responsabilités en double | I69: Élevée | J69: Désillusion des parties prenantes | K69: Revoir la planification et ajuster les priorités selon les besoins.
D70: Les sources de financement sont identifiées (interne, subventions, etc.). | E70: PV d’ateliers de co-construction, Liste des participants | F70: Les utilisateurs finaux sont-ils représentés ? Leurs retours sont-ils intégrés aux livrables ? | G70: Non | H70: Besoins futurs non anticipés | I70: Moyenne | J70: Frustration des équipes | K70: Réaliser une analyse d’impact pour maintenir la cohérence du système.
E71: Plan de conduite du changement, Plan de formation | F71: Les actions de sensibilisation sont-elles planifiées ? Le budget de formation est-il prévu ? | G71: NON | H71: Formation inadaptée aux besoins | I71: Élevée | J71: Contestations fréquentes | K71: Documenter et valider les interfaces entre les composants du système.
C72: S’assurer que les liens et impacts avec des projets connexes et les infrastructures (Datacenter, réseaux, etc.) sont pris en compte. | D72: Les dépendances avec d’autres projets sont cartographiées. | E72: Tableau de bord prévisionnel, Liste des KPI projet | F72: Les KPI sont-ils en lien avec les objectifs métiers ? Leur suivi est-il prévu dans le temps ? | G72: NON | H72: Justification économique faible | I72: Moyenne | J72: Coûts supplémentaires | K72: Former régulièrement les équipes techniques sur les nouvelles solutions.
E73: Plan de support utilisateur, Programme de formation | F73: La prise en main est-elle facilitée ? Un support post-déploiement est-il disponible ? | G73: Non | H73: Options non viables incluses | I73: Moyenne | J73: Planification obsolète | K73: Mettre en place des mécanismes de revue de code ou de validation technique.
D74: Les impacts sur l’infrastructure existante (serveurs, bande passante, etc.) sont évalués. | E74: Analyse d’impact technique, Cartographie applicative | F74: Le projet respecte-t-il les standards techniques internes ? Les dépendances techniques sont-elles analysées ? | G74: NON | H74: Analyse root cause superficielle | I74: Moyenne | J74: Amélioration impossible | K74: Mettre en place un suivi rigoureux de l’exécution des tâches.
E75: Analyse de risques SSI, Politique de sécurité applicable | F75: Les habilitations sont-elles maîtrisées ? La gestion des données sensibles est-elle cadrée ? | G75: Non | H75: Flux mal cartographiés | I75: Moyenne | J75: Efficacité réduite | K75: Assurer la disponibilité de ressources compétentes pour l’exécution des actions.
D76: Les synergies possibles avec d’autres initiatives sont analysées. | E76: Étude de volumétrie, Spécifications techniques | F76: Les charges (utilisateurs, transactions, stockage) sont-elles modélisées ? Des scénarios de montée en charge sont-ils prévus ? | G76: Oui | H76: Complexité excessive rendant le diagramme illisible | I76: Moyenne | J76: Décisions basées sur des données erronées | K76: Mettre en place des réunions régulières pour garantir l’alignement des actions.
E77: SLA ou cahier de performances, Tests de charge prévisionnels | F77: Les seuils de performance sont-ils clairs ? Sont-ils atteignables selon les benchmarks ? | G77: Oui | H77: Mesures de mitigation inefficaces | I77: Moyenne | J77: Perturbations majeures | K77: Utiliser des outils de gestion de projet pour suivre la cohérence des actions.
D78: Les contraintes liées à l’urbanisation du SI sont documentées. | E78: Schéma d’interfaces, Plan d’urbanisation applicative | F78: Les flux inter-applications sont-ils maîtrisés ? Les formats et protocoles d’échange sont-ils définis ? | G78: Non | H78: Interprétation erronée des données | I78: Moyenne | J78: Produit inadapté au marché | K78: Simplifier les processus administratifs pour accélérer la prise de décision.
E79: Plan de réversibilité, Clauses contractuelles | F79: Un retour en arrière est-il possible ? Les coûts et délais de réversibilité sont-ils estimés ? | G79: Oui | H79: Biais de confirmation dans l'analyse | I79: Moyenne | J79: Ressources mal orientées | K79: Définir des responsabilités claires pour chaque niveau administratif.
D80: Un plan de coordination avec les autres projets est prévu. | E80: Cahier des charges technique, Étude de portabilité | F80: La solution peut-elle fonctionner dans différents environnements ? Les contraintes de cloud/hybridation sont-elles abordées ? | G80: Non | H80: Ignorance des coûts de maintenance | I80: Moyenne | J80: Décisions stratégiques risquées | K80: Identifier les causes des retards et adapter la planification en conséquence.
E81: Spécifications SSI, Plan de conformité RGPD | F81: Les mesures de sécurité sont-elles détaillées ? Des audits sont-ils prévus ? | G81: Oui | H81: Expertise technique insuffisante | I81: Moyenne | J81: Retards dans la livraison | K81: Allouer des ressources supplémentaires pour les tâches prioritaires.
B82: Étude d'opportunité et expression des besoins | C82: S’assurer que l'expression détaillée des besoins est formalisée dans un cahier des charges fait par la MOA | D82: Le cahier des charges est rédigé par la MOA (Maîtrise d’Ouvrage) et non par la MOE. | E82: Cahier des charges, Plan d’audit | F82: Les actions critiques sont-elles tracées ? Les journaux sont-ils accessibles pour vérification ? | G82: Non | H82: Indicateurs de succès mal définis | I82: Moyenne | J82: Efforts dispersés | K82: Assurer une revue complète des résultats avant l’audit pour rectifier les non-conformités.
E83: Rapport UX/UI, Conformité RGAA (ou équivalent) | F83: Le projet respecte-t-il les normes d’accessibilité ? Les utilisateurs ont-ils testé l’ergonomie ? | G83: Oui | H83: Évaluation non périodique des résultats | I83: Moyenne | J83: Démotivation des équipes | K83: Mettre en place un suivi post-audit pour garantir la conformité.
D84: Les besoins fonctionnels et non fonctionnels sont décrits de manière exhaustive. | E84: RACI, Plan de gouvernance | F84: Les responsabilités sont-elles partagées clairement ? Les circuits de décision sont-ils formalisés ? | G84: Oui | H84: Exigences mal documentées | I84: Moyenne | J84: Délais et coûts explosés | K84: Améliorer les processus de tests et de validation avant le déploiement.
E85: Fiche d’organisation projet, Organigramme projet | F85: Les périmètres MOA/MOE sont-ils bien séparés ? Les rôles et responsabilités sont-ils connus ? | G85: Non | H85: Parties prenantes absentes lors de la validation | I85: Moyenne | J85: Contestations juridiques | K85: Mettre en place des mesures de surveillance continue des systèmes.
D86: Les cas d’utilisation (use cases) ou user stories sont documentés. | E86: Calendrier des comités, Procès-verbaux de réunions | F86: Le pilotage est-il régulier et structuré ? Les comptes rendus sont-ils diffusés ? | G86: Oui | H86: Conflits entre maîtrise d'ouvrage et d'œuvre | I86: Moyenne | J86: Chevauchements et lacunes | K86: Développer des programmes de sensibilisation pour encourager l'adoption.
E87: Registre des risques, Plan de mitigation | F87: Les risques sont-ils identifiés, évalués et suivis ? Des responsables de suivi sont-ils désignés ? | G87: Non | H87: Documentation technique insuffisante | I87: Moyenne | J87: Intégration difficile | K87: Fournir un soutien continu et une assistance technique pour faciliter l'application.
D88: Les exigences sont hiérarchisées (must-have, should-have, etc.). | E88: Plan de gestion de changement, Processus de demande de changement | F88: Les demandes d’évolution sont-elles formalisées ? Leur validation est-elle cadrée ? | G88: Oui | H88: Délais de migration sousestimés | I88: Moyenne | J88: Information critique perdue | K88: Clarifier les rôles et responsabilités dans la gouvernance du projet.
E89: Gantt détaillé, Jalons principaux | F89: Les délais sont-ils crédibles ? Les jalons sont-ils validés par les parties prenantes ? | G89: Non | H89: Actualisation des coûts négligée | I89: Moyenne | J89: Dépenses imprévues | K89: Définir un cadre de gouvernance commun et transparent pour tous les acteurs.
D90: Un glossaire garantit la compréhension commune des termes métiers et techniques. | E90: Planning projet, Roadmap | F90: Les jalons couvrent-ils toutes les phases clés ? Leur séquencement est-il cohérent ? | G90: Oui | H90: Dépendance excessive à un fournisseur | I90: Moyenne | J90: Choix sous-optimal | K90: Mettre en place une cartographie des ressources et des actions pour éviter les doublons.
E91: Diagramme de Pert, Matrice d'interdépendance | F91: Les chevauchements sont-ils maîtrisés ? Des marges de sécurité sont-elles intégrées ? | G91: Oui | H91: Non-conformités non détectées | I91: Moyenne | J91: Amendes et pénalités | K91: Favoriser la communication et la collaboration entre les équipes pour coordonner les actions.
C92: S’assurer que le cahier des charges préconise une solution fonctionnellement et techniquement pertinente au regard des besoins exprimés | D92: La solution proposée répond aux besoins critiques identifiés. | E92: Note de cadrage, | F92: Les objectifs sont-ils mesurables ? Sont-ils alignés avec la stratégie globale ? | G92: Non | H92: Recommandations non implémentées | I92: Moyenne | J92: Breaches de sécurité | K92: Revoir l'organisation pour assurer une meilleure coordination entre les départements.
E93: Liste des livrables, Cahier des charges | F93: Les livrables sont-ils cohérents avec les objectifs ? Leur contenu est-il précisé ? | G93: Oui | H93: Ressources mal allouées | I93: Élevée | J93: Pression excessive | K93: Aligner les objectifs organisationnels avec les objectifs stratégiques de l’entreprise.
D94: Une analyse comparative des solutions possibles (ex. : SaaS, développement sur mesure) est jointe. | E94: Expression de besoins, Spécifications fonctionnelles | F94: Les besoins sont-ils bien documentés ? Ont-ils été validés par les métiers ? | G94: Non | H94: Manque de flexibilité dans l'exécution | I94: Moyenne | J94: Plans obsolètes | K94: Organiser des séances d'information pour expliquer les avantages du changement.
E95: Spécifications techniques, Architecture cible | F95: Les contraintes techniques sont-elles explicites ? Les choix sont-ils justifiés ? | G95: Oui | H95: Parties prenantes non consultées | I95: Moyenne | J95: Tâches non accomplies | K95: Impliquer les employés dans le processus de changement pour augmenter l'adhésion.
D96: Les avantages et inconvénients de la solution retenue sont explicités. | E96: Analyse des parties prenantes, RACI | F96: Toutes les parties sont-elles représentées ? Leur rôle est-il clair ? | G96: Non | H96: Compétences manquantes non identifiées | I96: Moyenne | J96: Efforts dupliqués | K96: Mettre en place des sessions de formation pour les utilisateurs.
E97: Organigramme projet, Fiche de rôles | F97: Les responsabilités sont-elles bien réparties ? Le pilotage est-il structuré ? | G97: Oui | H97: Postes budgétaires oubliés | I97: Moyenne | J97: Ressources insuffisantes | K97: Créer des guides d'utilisation clairs et accessibles pour éviter les erreurs.
D98: La solution est alignée sur les standards technologiques de l’entreprise. | E98: Budget prévisionnel, Plan de charges | F98: Les estimations sont-elles réalistes ? Les sources sont-elles identifiées ? | G98: Non | H98: Délais de paiement non respectés | I98: Moyenne | J98: Retards de paiement | K98: Développer des outils permettant de vérifier automatiquement la conformité.
E99: Registre des risques, Analyse SWOT | F99: Les risques sont-ils classés ? Des plans d’atténuation sont-ils définis ? | G99: Oui | H99: Périmètre mal défini | I99: Moyenne | J99: Produit incohérent | K99: Mettre en place des mécanismes de validation manuelle pour les éléments critiques.
D100: Les risques liés à la solution sont identifiés et atténués. | E100: Étude comparative, Analyse de scénario | F100: Les différentes options ont-elles été évaluées objectivement ? | G100: Non | H100: Actions non suivies | I100: Moyenne | J100: Paralysie du projet | K100: Mettre en place un suivi rigoureux pour garantir la continuité des projets.
...

Sheet Audit_Support_Utilisateur_Gesti
A1: Domaines | B1: Points de Contrôle | C1: Objectifs de contrôle | D1: Critères d'évaluation | E1: Questions d'évaluation | F1: Documents requis | G1: Risques | H1: Reponses | I1: Conséquences | J1: Criticités | K1: Recommendations
A2: Support Utilisateur et de la Gestion du Parc | B2: Fonction support : audit fiabilité et sécurité | C2: S’assurer qu’une structure de centre d’assistance (help-desk) (HD) est mise en place | D2: L'organisation a défini une équipe dédiée | E2: L'entreprise a-t-elle constitué une équipe helpdesk ? | F2: Organigramme de l'équipe support | G2: Manque de réactivité, dilution des responsabilités | H2: OUI | I2: Décisions retardées, | J2: Elevée | K2: Clarifier les rôles et responsabilités,
F3: Fiches de poste | H3: NON | I3: confusion dans les actions à mener | J3: Elevée | K3: mettre en place des procédures d’escalade claires
D4: La direction a nommé un responsable du HD | E4: Un responsable du centre d'assistance est-il désigné ? | F4: Décision de nomination | G4: Absence de pilotage, délais non respectés | H4: NON | I4: Projets en retard, perte de crédibilité | J4: Elevée | K4: Nommer un chef de projet dédié et suivre un plan d’actions avec jalons
F5: Description de mission | H5: NON | I5: Perturbation des activités, coûts supplémentaires | J5: Élevée | K5: Mettre en place une maintenance préventive
D6: Les locaux disposent d'équipements adaptés | E6: Le centre d'assistance possède-t-il l'infrastructure nécessaire ? | F6: Inventaire matériel | G6: Pannes fréquentes, inefficacité opérationnelle | H6: NON | I6: Insatisfaction des clients, perte de revenus | J6: Moyenne | K6: moderniser les équipements critiques
F7: Rapport d’audit des locaux | H7: NON | I7: Sanctions réglementaires, risques juridiques | J7: Moyenne | K7: Allouer des ressources adaptées et prioriser les besoins essentiels
D8: Le budget couvre les besoins opérationnels | E8: Les ressources financières sont-elles allouées au HD ? | F8: Budget annuel | G8: Services dégradés par manque de moyens | H8: OUI | I8: Décisions basées sur des données erronées | J8: Élevée | K8: Renforcer les formations et automatiser les contrôles critiques
F9: Rapport de dépenses | H9: OUI | I9: Perte de contrats, atteinte à la réputation | J9: Moyenne | K9: Mettre à jour régulièrement les bases de données et centraliser l’accès
D10: Les procédures internes sont documentées | E10: Existe-t-il un manuel des procédures du help-desk ? | F10: Manuel des procédures | G10: Erreurs humaines, nonconformité | H10: OUI | I10: Baisse de la qualité, risques accrus | J10: Moyenne | K10: Améliorer le suivi client et respecter les SLA définis
F11: Registre des versions | H11: Non | I11: Accidents, responsabilités légales | J11: Moyenne | K11: Former les équipes et évaluer régulièrement leurs compétences
C12: S’assurer qu’une procédure de gestion des demandes d’assistance est diffusée et connue des utilisateurs | D12: La procédure est accessible sur l'intranet | E12: Les utilisateurs trouvent-ils facilement la procédure ? | F12: Capture d’écran | G12: Information obsolète ou inaccessible | H12: NON | J12: Élevée | K12: Sensibiliser et auditer le respect des procédures de
F13: Politique d’accès | H13: Non | I13: Stagnation des performances, désengagement | J13: Élevée | K13: sécurité
D14: Le document mentionne les délais de traitement | E14: La procédure précise-t-elle les délais d'intervention ? | F14: Procédure avec SLA | G14: Insatisfaction clients, pénalités contractuelles | H14: Oui | I14: Accumulation des dysfonctionnements, crise majeure | J14: Moyenne | K14: Impliquer les utilisateurs dans les évolutions et mettre en place un feedback continu
F15: Exemples de tickets | H15: Non | I15: Paralysie des opérations, inefficacité | J15: Moyenne | K15: Instaurer des points de suivi réguliers et une gestion proactive des risques
D16: Les nouveaux employés reçoivent une formation | E16: L'entreprise forme-t-elle les nouveaux à la procédure ? | F16: Programme de formation | G16: Incompétence, augmentation des erreurs | H16: Oui | I16: Coûts imprévus, détérioration de l’image | J16: Moyenne | K16: Désigner des remplaçants et autorisations déléguées en cas d’absence
F17: Listes de présence | H17: Non | I17: Dégradation silencieuse des performances | J17: Moyenne | K17: Respecter les obligations légales et communiquer de manière transparente
D18: Des affiches rappellent les bonnes pratiques | E18: Des supports visuels existent-ils dans les locaux ? | F18: Modèles d’affiches | G18: Non-respect des consignes de sécurité | H18: Oui | I18: Perte de temps, gaspillage de ressources | J18: Élevée | K18: Mettre en place des outils de monitoring et des audits réguliers
F19: Plan de communication | H19: OUI | J19: Élevée | K19: Analyser les causes racines et documenter les solutions
D20: Un mécanisme recueille les suggestions | E20: Les utilisateurs peuvent-ils faire des remarques ? | F20: Formulaire de feedback | G20: Améliorations ignorées, frustration utilisateurs | H20: Oui | I20: Inégalité de service, frustration ciblée | J20: Moyenne | K20: appliquées
F21: Registre des suggestions | H21: Non | I21: Erreurs d’utilisation, adoption difficile | J21: Élevée | K21: Harmoniser les processus et répartir équitablement les ressources
C22: S’assurer qu’une procédure d'escalade mise en place | D22: Les niveaux d'escalade sont clairement définis | E22: La procédure décrit-elle les différents niveaux ? | F22: Schéma d’escalade | G22: Retards critiques, problèmes non résolus | H22: Oui | I22: Retards, insatisfaction générale | J22: Moyenne | K22: Simplifier les guides utilisateurs et former les équipes concernées
F23: Liste des contacts | H23: Non | J23: Moyenne | K23: Augmenter la capacité de
D24: Les responsables par niveau sont identifiés | E24: Chaque niveau a-t-il son interlocuteur attitré ? | F24: Tableau des responsabilités | G24: Blocages par absence de décideur | H24: Oui | I24: Problèmes non traités jusqu’à crise | J24: Élevée | K24: traitement ou prioriser les demandes urgentes
F25: Organigramme | H25: Non | I25: Pertes financières majeures | J25: Moyenne | K25: Implémenter des indicateurs de performance par zone
D26: Les délais maximaux sont spécifiés | E26: La procédure indique-t-elle des échéances précises ? | F26: Contrat SLA | G26: Sanctions financières, perte de confiance | H26: NON | I26: Risques techniques non résolus | J26: Moyenne | K26: Élaborer un plan de continuité d’activité (PCA) et le tester régulièrement
F27: Dashboard de suivi | H27: NON | I27: Accumulation des problèmes non traités | J27: Moyenne | K27: Étendre les contrats de support ou migrer vers des solutions maintenues
D28: Le processus est testé régulièrement | E28: L'entreprise réalise-t-elle des tests d'escalade ? | F28: Plan de tests | G28: Dysfonctionnements non détectés | H28: Non | I28: Pertes de données, interruptions de service | J28: Élevée | K28: Former une équipe spécialisée ou externaliser l’expertise nécessaire
F29: Comptes-rendus | H29: Oui | I29: Insatisfaction, perte de productivité | J29: Élevée | K29: Automatiser les tâches sensibles et renforcer les vérifications
D30: Les résultats des tests sont analysés | E30: Les retours d'expérience sont-ils exploités ? | F30: Rapports d’analyse | G30: Répétition des mêmes incidents | H30: Non | I30: Utilisation inefficace, confusion | J30: Moyenne | K30: Optimiser les processus de support et fixer des objectifs clairs
F31: Plan d’actions | H31: Oui | I31: Données incomplètes, manque de traçabilité | J31: Moyenne | K31: Actualiser la documentation et communiquer les changements aux utilisateurs
C32: S’assurer de la couverture géographique du HD | D32: Les fuseaux horaires sont pris en compte | E32: Le service adapte-t-il ses horaires aux zones ? | F32: Politique de support global | G32: Délais allongés pour certaines zones | H32: Non | I32: Manque de confiance dans le support | J32: Moyenne | K32: Standardiser les outils de saisie et interdire les processus non officiels
F33: Calendrier de couverture | H33: NON | J33: Moyenne | K33: Utiliser un système de ticketing centralisé avec suivi
D34: Les langues locales sont supportées | E34: L'assistance parle-t-elle les langues nécessaires ? | F34: Liste des langues Traductions des procédures | G34: Mauvaise compréhension des utilisateurs | H34: Non | I34: Stratégies inefficaces, pertes financières | J34: Moyenne | K34: automatique
F35: Traductions des procédures | H35: NON | I35: Confusion, erreurs opérationnelles | J35: Moyenne | K35: Vérifier la qualité des données avant toute analyse décisionnelle
D36: Les canaux de communication sont adaptés | E36: Chaque zone a-t-elle ses moyens de contact ? | F36: Liste des canaux | G36: Saturation, demandes perdues | H36: Non | I36: Atteinte à la conformité, | J36: Moyenne | K36: Mettre en place des outils d’intégration et de synchronisation
F37: Statistiques d’utilisation | H37: Oui | I37: Conclusions partiales, décisions risquées | J37: Élevée | K37: Chiffrer les données et restreindre les accès sensibles
D38: La qualité de service est mesurée par région | E38: Des indicateurs spécifiques existent-ils par site ? | F38: Rapports régionaux | G38: Dégradation invisible dans certaines zones | H38: Non | I38: Abandon des utilisateurs, perte de clients | J38: Élevée | K38: Imposer des règles de saisie obligatoire et complétude des complétude des données
D39: Un plan de continuité est prévu pour chaque site | E39: Des solutions de secours sont-elles prévues ? | F39: PCA/PRA | G39: Interruptions prolongées en cas de crise | H39: NON | I39: Retraitements coûteux, inefficacité | J39: Moyenne | K39: Recueillir les retours et ajuster l’offre de services en conséquence
C40: S’assurer de la couverture fonctionnelle du HD | D40: Le périmètre des applications est documenté | E40: La liste des applications supportées est-elle à jour ? | F40: Cartographie applicative | G40: Applications non couvertes par le support | H40: NON | I40: Gaspillage de ressources, retard compétitif | J40: Moyenne | K40: Simplifier les formulaires et fournir des exemples clairs
E41: L'équipe maîtrise-t-elle les technologies concernées ? | F41: Contrats de support | H41: Non | I41: Défaillances majeures non anticipées | J41: Moyenne | K41: Réviser régulièrement les processus et adopter les meilleures pratiques
D42: Les compétences techniques couvrent les besoins | F42: Matrice des compétences | G42: Incapacité à résoudre des incidents complexes | H42: Oui | J42: Moyenne | K42: Créer des checklists obligatoires et des contrôles
E43: Chaque logiciel a-t-il son guide d'assistance ? | F43: Plans de formation | H43: Non | I43: Problèmes récurrents, temps perdu | J43: Moyenne | K43: croisés
D44: Des procédures spécifiques existent par application | F44: Guides techniques | G44: Erreurs de manipulation critiques | H44: Oui | I44: Sous-performance, risques techniques | J44: Moyenne | K44: Former les équipes aux bonnes méthodes de diagnostic et analyse
E45: Les contacts avec les fournisseurs sont-ils formalisés ? | F45: Bases de connaissances | H45: Non | J45: Moyenne | K45: Organiser des formations pratiques et fournir un support dédié
D46: La coordination avec les éditeurs est établie | F46: Contrats éditeurs | G46: Délais de résolution prolongés | H46: NON | I46: Décisions inappropriées, erreurs stratégiques | J46: Moyenne
E47: Les nouveautés sont-elles intégrées régulièrement ? | F47: Procédures d’escalade | H47: Non | I47: Panne majeure, interruption prolongée | J47: Moyenne | K47: Mettre en place un système d’archivage et de purge automatique
D48: Le catalogue de services est régulièrement révisé | F48: Catalogue mis à jour Historique des modifications | G48: Services obsolètes ou mal décrits | H48: Oui | I48: Confusion, manque de standardisation | J48: Moyenne | K48: Installer des systèmes de surveillance proactive avec alertes
E49: Les utilisateurs créent-ils facilement des tickets ? | F49: Historique des modifications | H49: Non | I49: Pertes financières, réputation endommagée | J49: Moyenne | K49: Documenter les solutions types et partager les bonnes pratiques
C50: S’assurer qu’un outil est implémenté pour la prise d'appel et le suivi des tickets | D50: L'outil permet la création de tickets | F50: Manuel utilisateur | G50: Saisie impossible, travail parallèle non tracé | H50: Oui | I50: Gaspillage d’efforts, inefficacité | J50: Moyenne | K50: Définir des procédures d’urgence et former les équipes à la gestion de crise
E51: L'outil conserve-t-il l'historique des interventions ? | F51: Captures d’écran | H51: NON | I51: Méfiance, collaboration réduite | J51: Moyenne | K51: Centraliser les connaissances et encourager la réutilisation des solutions existantes
D52: Le suivi des tickets est complet | F52: Exemple de ticket | G52: Tickets perdus, délais dépassés | H52: Non | J52: Moyenne | K52: Communiquer régulièrement et partager l’information de manière ouverte
E53: Le système génère-t-il des rapports utiles ? | F53: Rapport de clôture | H53: NON | I53: Non-conformité, risques légaux | J53: Élevée
D54: Les statistiques sont exploitables | F54: Dashboard KPI | G54: Décisions basées sur des données erronées | H54: Non | I54: Productivité réduite, frustration | J54: Moyenne | K54: Simplifier les consignes et former régulièrement sur leur importance
E55: Les échanges de données sont-ils automatisés ? | F55: Exports de données | H55: NON | I55: Résistance au changement, stagnation | J55: Moyenne | K55: Évaluer régulièrement les outils et investir dans des solutions modernes
D56: L'intégration avec les autres systèmes fonctionne | F56: Documentation technique | G56: Données incohérentes entre systèmes | H56: Non | I56: Choix stratégiques risqués, échecs probables | J56: Moyenne | K56: Auditer les processus et impliquer les équipes dans leur amélioration
E57: Les accès sont-ils sécurisés et contrôlés ? | F57: Logs d’intégration | H57: Oui | I57: Aggravation de la situation, crise prolongée | J57: Moyenne | K57: Exiger des données validées avant toute prise de décision importante
C58: S’assurer que des critères à renseigner pour la qualification des tickets existent ; | D58: La sécurité des données est garantie | F58: Politique de sécurité | G58: Fuites ou vols de données sensibles | H58: OUI | I58: Interruptions majeures, pertes d’exploitation | J58: Moyenne | K58: Élaborer des procédures d’intervention claires et les tester en simulation
E59: La création de ticket imposet-elle des champs requis ? | F59: Audits de conformité | H59: Non | I59: Escalade incontrôlée, impacts majeurs | J59: Moyenne | K59: Prévoir un support redondant ou des solutions de secours
D60: Les champs obligatoires sont définis | F60: Modèle de formulaire | G60: Données manquantes pour l’analyse | H60: NON | I60: Décisions erronées, pertes financières | J60: Élevée | K60: Mettre en place un système d’astreinte et des délais de réponse garantis
E61: Les informations demandées sont-elles pertinentes ? | F61: Règles de validation | H61: NON | I61: Dégradation progressive, crise soudaine | J61: Moyenne | K61: Sauvegarder régulièrement et valider l’intégrité des données
D62: Les critères couvrent les besoins essentiels | F62: Référentiel métier | G62: Besoins non satisfaits, insatisfaction | H62: Non | I62: Décisions retardées, | J62: Élevée | K62: Automatiser la détection d’anomalies avec des alertes précoces
E63: L'outil vérifie-t-il le remplissage des champs ? | F63: Retours utilisateurs | H63: Oui | I63: confusion dans les actions à mener | J63: Élevée | K63: Clarifier les rôles et responsabilités,
D64: La validation automatique est implémentée | F64: Spécifications techniques | G64: Erreurs non détectées à la saisie | H64: Non | I64: Projets en retard, perte de crédibilité | J64: Moyenne | K64: mettre en place des procédures d’escalade claires
E65: Existe-t-il une aide pour qualifier les tickets ? | F65: Logs d’erreurs | H65: NON | I65: Perturbation des activités, coûts supplémentaires | J65: Moyenne | K65: Nommer un chef de projet dédié et suivre un plan d’actions avec jalons
D66: Un guide aide au remplissage | F66: Guide PDF/En ligne FAQ | G66: Remplissage incorrect, temps perdu | H66: Oui | J66: Moyenne | K66: Mettre en place une maintenance préventive
E67: Les champs sont-ils adaptés aux nouveaux besoins ? | F67: En ligne FAQ | H67: Non | I67: Insatisfaction des clients, perte de revenus | J67: Moyenne | K67: moderniser les équipements critiques
C68: S’assure qu’il existe une liste de questions à dérouler lors d'un appel afin préciser au mieux la demande de l'utilisateur | D68: Les critères évoluent régulièrement | F68: Historique des versions | G68: Processus obsolètes inefficaces | H68: NON | I68: Sanctions réglementaires, risques juridiques | J68: Élevée | K68: Allouer des ressources adaptées et prioriser les besoins essentiels
E69: Les agents disposent-ils d'un questionnaire type ? | F69: Procès-verbal de revue | H69: Non | I69: Décisions basées sur des données erronées | J69: Moyenne | K69: Renforcer les formations et automatiser les contrôles critiques
D70: Une checklist standardisée est disponible | F70: Modèle de checklist | G70: Oublis dans les vérifications critiques | H70: NON | I70: Perte de contrats, atteinte à la réputation | J70: Élevée | K70: Mettre à jour régulièrement les bases de données et centraliser l’accès
E71: Le script évolue-t-il selon la nature du problème ? | F71: Registre d’utilisation | H71: NON | I71: Baisse de la qualité, risques accrus | J71: Moyenne | K71: Améliorer le suivi client et respecter les SLA définis
D72: Les questions s'adaptent au contexte | F72: Bases de questions dynamiques | G72: Diagnostics imprécis, solutions inadaptées | H72: Non | I72: Accidents, responsabilités légales | J72: Moyenne | K72: Former les équipes et évaluer régulièrement leurs compétences
E73: Le personnel maîtrise-t-il le questionnement ? | F73: Exemples de scénarios | H73: NON | J73: Moyenne | K73: Sensibiliser et auditer le respect des procédures de
D74: Les agents sont formés à son utilisation | F74: Attestations de formation | G74: Mauvaise utilisation de l’outil | H74: Non | I74: Stagnation des performances, désengagement | J74: Moyenne | K74: sécurité
E75: L'entreprise améliore-t-elle le questionnaire ? | F75: Évaluations | H75: Oui | I75: Accumulation des dysfonctionnements, crise majeure | J75: Moyenne | K75: Impliquer les utilisateurs dans les évolutions et mettre en place un feedback continu
D76: La liste est mise à jour régulièrement | F76: Journal des modifications | G76: Informations périmées utilisées | H76: Oui | I76: Paralysie des opérations, inefficacité | J76: Moyenne | K76: Instaurer des points de suivi réguliers et une gestion proactive des risques
E77: L'utilisation améliore-t-elle la qualification ? | F77: Alertes de mise à jour | H77: Non | I77: Coûts imprévus, détérioration de l’image | J77: Moyenne | K77: Désigner des remplaçants et autorisations déléguées en cas d’absence
C78: S’assurer que les problèmes sont gérés | D78: L'efficacité est mesurée | F78: Rapports d’audit | G78: Dégradation non détectée à temps | H78: Oui | I78: Dégradation silencieuse des performances | J78: Moyenne | K78: Respecter les obligations légales et communiquer de manière transparente
E79: Existe-t-il une procédure pour gérer les problèmes ? | F79: Indicateurs de performance | H79: Non | I79: Perte de temps, gaspillage de ressources | J79: Moyenne | K79: Mettre en place des outils de monitoring et des audits réguliers
D80: Une méthode de traitement est définie | F80: Procédure de résolution | G80: Incohérence dans les solutions apportées | H80: Oui | J80: Moyenne | K80: Analyser les causes racines et documenter les solutions
E81: L'entreprise classe-t-elle les problèmes par criticité ? | F81: Arbre de décision | H81: Non | I81: Inégalité de service, frustration ciblée | J81: Moyenne | K81: appliquées
D82: Les problèmes sont priorisés | F82: Grille de priorisation | G82: Urgences mal gérées, impacts business | H82: Oui | I82: Erreurs d’utilisation, adoption difficile | J82: Moyenne | K82: Harmoniser les processus et répartir équitablement les ressources
E83: Les résolutions sont-elles capitalisées ? | F83: Exemples de tickets classés | H83: Oui | I83: Retards, insatisfaction générale | J83: Moyenne | K83: Simplifier les guides utilisateurs et former les équipes concernées
D84: Les solutions sont documentées | F84: Base de connaissances | G84: Redondance, temps perdu à réinventer | H84: Non | J84: Moyenne | K84: Augmenter la capacité de
E85: Les problèmes récurrents sont-ils investigués ? | F85: Historique des résolutions | H85: Oui | I85: Problèmes non traités jusqu’à crise | J85: Moyenne | K85: traitement ou prioriser les demandes urgentes
D86: L'analyse des causes racines est réalisée | F86: Rapports RCA | G86: Répétition des mêmes incidents | H86: Non | I86: Pertes financières majeures | J86: Moyenne | K86: Implémenter des indicateurs de performance par zone
E87: La communication est-elle assurée vers les usagers ? | F87: Plans d’action | H87: Oui | I87: Risques techniques non résolus | J87: Moyenne | K87: Élaborer un plan de continuité d’activité (PCA) et le tester régulièrement
C88: S’assurer qu’un processus de gestion des problèmes existe | D88: Les utilisateurs concernés sont informés | F88: Modèles d’emails | G88: Manque de transparence, frustration | H88: Non | I88: Accumulation des problèmes non traités | J88: Moyenne | K88: Étendre les contrats de support ou migrer vers des solutions maintenues
E89: Un document décrit-il la gestion des problèmes ? | F89: Logs de notification | H89: Oui | I89: Pertes de données, interruptions de service | J89: Moyenne | K89: Former une équipe spécialisée ou externaliser l’expertise nécessaire
D90: Le processus est documenté | F90: Documentation complète | G90: Incompréhension, non-respect des règles | H90: Oui | I90: Insatisfaction, perte de productivité | J90: Moyenne | K90: Automatiser les tâches sensibles et renforcer les vérifications
E91: Des personnes sont-elles nommément responsables ? | F91: Flux de travail | H91: Non | I91: Utilisation inefficace, confusion | J91: Moyenne | K91: Optimiser les processus de support et fixer des objectifs clairs
D92: Les responsables sont désignés | F92: Tableau RACI | G92: Dilution des responsabilités | H92: Oui | I92: Données incomplètes, manque de traçabilité | J92: Élevée | K92: Actualiser la documentation et communiquer les changements aux utilisateurs
E93: Existe-t-il un système spécifique pour le suivi ? | F93: Décisions de nomination | H93: Non | I93: Manque de confiance dans le support | J93: Moyenne | K93: Standardiser les outils de saisie et interdire les processus non officiels
D94: Des outils dédiés sont utilisés | F94: Inventaire des outils | G94: Outils inadaptés ou obsolètes | H94: Oui | J94: Moyenne | K94: Utiliser un système de ticketing centralisé avec suivi
E95: La méthode est-elle réévaluée régulièrement ? | F95: Contrats de maintenance | H95: Non | I95: Stratégies inefficaces, pertes financières | J95: Moyenne | K95: automatique
D96: Le processus est révisé périodiquement | F96: PV de revue | G96: Processus inefficace pérennisé | H96: Oui | I96: Confusion, erreurs opérationnelles | J96: Moyenne | K96: Vérifier la qualité des données avant toute analyse décisionnelle
E97: Des métriques suivent-elles la performance ? | F97: Plan d’amélioration | H97: Non | I97: Atteinte à la conformité, | J97: Moyenne | K97: Mettre en place des outils d’intégration et de synchronisation
D98: Des indicateurs mesurent l'efficacité | F98: Dashboard KPI | G98: Décisions sans données fiables | H98: Oui | I98: Conclusions partiales, décisions risquées | J98: Moyenne | K98: Chiffrer les données et restreindre les accès sensibles
E99: Un mode opératoire couvret-il les périodes atypiques ? | F99: Rapports mensuels | H99: Non | J99: Moyenne | K99: Imposer des règles de saisie obligatoire et complétude des
C100: S’assurer que les incidents de production de nuit et jour ferrier sont aussi saisis dans l'outil | D100: Une procédure spécifique existe | F100: Procédure d’urgence | G100: Réaction inappropriée en cas d’incident | H100: Oui | I100: Abandon des utilisateurs, perte de clients | J100: Moyenne | K100: complétude des données
...

Sheet Audit_Securite_Informatique
A1: Domaines | B1: Points de contrôle | C1: Objectifs de contrôle | D1: Critères d'évaluation | E1: Questions d'évaluation | F1: Documents requis | G1: Reponses | H1: Risques | I1: criticités | J1: Conséquences | K1: Recommendations
A2: Sécurité Informatique | B2: Facteurs clés de succès | C2: Vérifier qu’une politique de sécurité est définie et correspond à l'activité de l'Organisation | D2: La politique de sécurité est documentée et accessible | E2: La politique de sécurité estelle formalisée et partagée avec l'ensemble des collaborateurs ? | F2: Charte de sécurité signée | G2: OUI | H2: Non-conformité réglementaire et actions incohérentes | I2: Elevée | J2: Amendes et sanctions légales | K2: Mettre en place un référentiel réglementaire actualisé
D3: La politique est alignée sur les enjeux métiers de l'organisation | E3: La politique prend-elle en compte les spécificités et les risques liés à l'activité de l'organisation ? | F3: Rapport d'alignement stratégique | G3: NON | H3: Mesures de sécurité inadaptées aux besoins réels | I3: Elevée | J3: Protection inefficace des actifs critiques | K3: Réaliser une analyse de risques métier approfondie
D4: Les rôles et responsabilités sont clairement définis | E4: Existe-t-il une attribution explicite des responsabilités en matière de sécurité ? | F4: Matrice RACI sécurité | G4: NON | H4: Confusion dans la gestion des incidents | I4: Elevée | J4: Temps de résolution prolongé | K4: Élaborer des playbooks d'incidents clairs
D5: La politique est régulièrement mise à jour | E5: Une revue périodique de la politique est-elle planifiée et exécutée ? | F5: Planning des revues politiques | G5: NON | H5: Politique obsolète face aux nouvelles menaces | I5: Élevée | J5: Exposition à des attaques modernes | K5: Instaurer des revues trimestrielles de la politique
D6: La politique couvre l'ensemble des systèmes informatiques | E6: Tous les équipements (réseaux, imprimantes, téléphones IP, etc.) sont-ils inclus dans le périmètre de sécurité ? | F6: Inventaire des systèmes couverts | G6: NON | H6: Zones non couvertes vulnérables | I6: Moyenne | J6: Points d'entrée pour les attaquants | K6: Réaliser un audit complet de couverture
C7: Vérifier qu’une démarche de mise en œuvre de la gestion de la sécurité est adoptée et compatible avec la culture de l'Organisation | D7: Une structure dédiée à la sécurité existe (RSSI, comité sécurité) | E7: L'organisation dispose-t-elle d'une équipe ou d'un responsable dédié à la sécurité ? | F7: Organigramme officiel de la sécurité | G7: NON | H7: Absence de pilotage des initiatives sécurité | I7: Moyenne | J7: Efforts dispersés et inefficaces | K7: Nommer un RSSI avec pouvoir décisionnel
D8: La démarche est comprise et acceptée par les employés | E8: Les employés perçoivent-ils positivement les mesures de sécurité mises en place ? | F8: Enquête de satisfaction sécurité | G8: OUI | H8: Résistance au changement des employés | I8: Élevée | J8: Non-application des mesures | K8: Impliquer les utilisateurs dans la conception des mesures
D9: Les procédures sont adaptées aux besoins opérationnels | E9: Les processus de sécurité sont-ils suffisamment flexibles pour ne pas entraver l'activité ? | F9: Analyse d'impact opérationnel | G9: OUI | H9: Perturbation des processus métiers | I9: Moyenne | J9: Perte de productivité | K9: Adopter une approche Risk-Based Security
D10: Une communication claire sur les enjeux de sécurité est assurée | E10: Les messages relatifs à la sécurité sont-ils diffusés de manière compréhensible et régulière ? | F10: Plan de communication sécurité | G10: OUI | H10: Mauvaise compréhension des enjeux | I10: Moyenne | J10: Comportements à risque persistants | K10: Développer des campagnes de sensibilisation ciblées
D11: La culture sécurité est intégrée dans les formations | E11: Des modules de sensibilisation à la sécurité sont-ils dispensés aux nouveaux arrivants ? | F11: Catalogue des formations obligatoires | G11: Non | H11: Manque de sensibilisation aux risques | I11: Moyenne | J11: Augmentation des incidents humains | K11: Instaurer des formations obligatoires annuelles
C12: Vérifier que la direction assure un soutien total et un engagement visible pour la sécurité | D12: La direction valide et promeut la politique de sécurité | E12: La direction générale participe-t-elle activement aux décisions stratégiques en matière de sécurité ? | F12: PV de validation par la direction | G12: NON | H12: Manque d'engagement hiérarchique | I12: Élevée | J12: Priorisation inadéquate des projets | K12: Inclure la sécurité dans les objectifs stratégiques
D13: Les budgets alloués à la sécurité sont suffisants | E13: Les investissements nécessaires pour la sécurité sont-ils approuvés et financés ? | F13: Budget sécurité approuvé | G13: Non | H13: Sous-investissement dans les protections | I13: Élevée | J13: Exposition accrue aux menaces | K13: Élaborer un business case sécurité clair
D14: La direction donne l'exemple en appliquant les règles | E14: Les membres de la direction respectent-ils les consignes de sécurité (ex : authentification forte) ? | F14: Audit des comptes dirigeants | G14: Oui | H14: Perte de crédibilité des règles | I14: Moyenne | J14: Non-respect généralisé des politiques | K14: Appliquer les règles de manière uniforme à tous niveaux
D15: Les incidents sécurité sont remontés à la direction | E15: La direction est-elle informée des incidents majeurs et des actions correctives ? | F15: Procédure de remontée d'incidents | G15: Non | H15: Délais de traitement trop longs | I15: Moyenne | J15: Aggravation des incidents | K15: Automatiser les processus de remontée d'alertes
D16: La sécurité est intégrée dans les objectifs stratégiques | E16: La sécurité figure-t-elle parmi les priorités définies par la gouvernance ? | F16: Plan stratégique organisationnel | G16: Oui | H16: Sécurité perçue comme contrainte | I16: Moyenne | J16: Contournement des processus | K16: Communiquer sur les bénéfices métier de la sécurité
C17: Vérifier que les exigences de sécurité et les risques sont compris et évalués | D17: Un inventaire des actifs critiques est disponible | E17: Existe-t-il une liste à jour des actifs informatiques classés par criticité ? | F17: Base de données des actifs | G17: Non | H17: Impossibilité de protéger les actifs non recensés | I17: Moyenne | J17: Surface d'attaque inconnue | K17: Déployer une solution CMDB automatique
D18: Une méthodologie d'analyse des risques est appliquée | E18: Des évaluations régulières des risques sont-elles menées avec une méthode reconnue ? | F18: Guide méthodologique d'analyse | G18: Oui | H18: Mauvaise évaluation des vulnérabilités | I18: Élevée | J18: Priorisation incorrecte des correctifs | K18: Adopter une méthodologie d'analyse standardisée
D19: Les niveaux de classification des données sont définis | E19: Les données sensibles sontelles catégorisées selon leur niveau de confidentialité ? | F19: Politique de classification des données | G19: OUI | H19: Traitement inapproprié des informations | I19: Élevée | J19: Fuites de données sensibles | K19: Implémenter un système de classification clair
D20: Les propriétaires des actifs sont identifiés et informés | E20: Chaque actif important a-t-il un responsable désigné connaissant ses obligations ? | F20: Registre des propriétaires d'actifs | G20: Oui | H20: Défaut de maintenance des actifs | I20: Moyenne | J20: Augmentation des vulnérabilités | K20: Assigner des propriétaires clairs pour chaque actif
D21: Les menaces et vulnérabilités sont surveillées | E21: Un processus de veille sur les nouvelles menaces est-il en place ? | F21: Bulletin de veille sécurité | G21: Non | H21: Réaction tardive aux nouvelles menaces | I21: Élevée | J21: Exploitation des failles connues | K21: Mettre en place une veille sécurité active
C22: Vérifier que l’ensemble des responsables et des employés sont sensibilisés et informés | D22: Un programme de formation sécurité est déployé | E22: Tous les employés reçoiventils une formation adaptée à leur niveau de risque ? | F22: Plan de formation annuel | G22: Oui | H22: Personnel non préparé aux attaques | I22: Moyenne | J22: Succès des attaques sociales | K22: Organiser des simulations de phishing régulières
D23: Les bonnes pratiques sont communiquées régulièrement | E23: Des campagnes de sensibilisation (ex : phishing) sont-elles organisées périodiquement ? | F23: Supports de sensibilisation | G23: Non | H23: Répétition d'erreurs évitables | I23: Moyenne | J23: Incidents récurrents | K23: Documenter les leçons apprises après chaque incident
D24: Les employés savent signaler un incident | E24: Les documents évitent-ils le jargon informatique excessif ? | F24: Guide de signalement d'incidents | G24: Oui | H24: Incidents non rapportés ou tardifs | I24: Élevée | J24: Propagation des attaques | K24: Simplifier les canaux de signalement
D25: Les responsables métier relaient les consignes sécurité | E25: Des rappels réguliers sur les bonnes pratiques sont-ils effectués ? | F25: PV des réunions d'équipe | G25: Non | H25: Incohérence dans l'application | I25: Moyenne | J25: Failles dans la protection | K25: Standardiser les procédures opérationnelles
D26: Les supports de communication sont adaptés aux cibles | E26: Les employés peuvent-ils poser des questions ou faire des suggestions sur les consignes ? | F26: Charte éditoriale sécurité | G26: NON | H26: Messages non compris ou ignorés | I26: Moyenne | J26: Efficacité réduite des campagnes | K26: Adapter le langage aux différents métiers
B27: Politique de sécurité | C27: S’assurer qu’il existe une politique de sécurité formalisée avec une implication de la direction générale et une définition claire des responsabilités | D27: Le langage est clair et non technique | E27: La politique est-elle réexaminée au moins une fois par an ou après un incident majeur ? | F27: Glossaire des termes sécurité | G27: NON | H27: Mauvaise interprétation des consignes | I27: Moyenne | J27: Actions inappropriées | K27: Fournir des exemples concrets d'application
D28: La fréquence de communication est suffisante | F28: Calendrier des campagnes | G28: Non | H28: Relâchement de la vigilance | I28: Élevée | J28: Augmentation des risques | K28: Maintenir une communication régulière et variée
D29: Un feedback est collecté pour améliorer la communication | E29: Les incidents passés influencent-ils les mises à jour de la politique ? | F29: Formulaire de retour d'expérience | G29: Oui | H29: Communication inefficace | I29: Élevée | J29: Ressources mal utilisées | K29: Mettre en place des indicateurs d'impact
D30: Un calendrier de revue est établi | E30: La politique est-elle ajustée en fonction des nouvelles lois (ex : RGPD) ? | F30: Agenda des revues politiques | G30: Non | H30: Politique non actualisée | I30: Moyenne | J30: Décrochage par rapport aux bonnes pratiques | K30: Planifier des revues annuelles systématiques
D31: Les retours d'expérience sont pris en compte | E31: Les modifications de l'entreprise (fusion, nouveaux métiers) déclenchent-elles une revue ? | F31: Rapport d'analyse d'incidents | G31: Oui | H31: Répétition des mêmes incidents | I31: Moyenne | J31: Coûts élevés de correction | K31: Implémenter un système de gestion des connaissances
C32: S’assurer que la communication se fait à tous les utilisateurs sous une forme pertinente, accessible et compréhensible au lecteur | D32: Les évolutions réglementaires sont intégrées | E32: Les recommandations d'audit conduisent-elles à des améliorations concrètes ? | F32: Matrice de conformité réglementaire | G32: Non | H32: Amendes pour nonconformité | I32: Moyenne | J32: Impact financier et réputationnel | K32: Désigner un responsable conformité dédié
D33: Les changements organisationnels sont considérés | E33: Les imprimantes, téléphones IP, et systèmes industriels sont-ils inclus dans la politique ? | F33: Procédure de gestion du changement | G33: NON | H33: Nouveaux risques non identifiés | I33: Moyenne | J33: Exposition imprévue | K33: Intégrer la sécurité en amont des projets
D34: Les résultats des audits sont utilisés pour les mises à jour | E34: Des analyses de risques couvrent-elles les objets IoT et l'informatique industrielle ? | F34: Plan d'actions correctives | G34: Non | H34: Persistance des vulnérabilités | I34: Moyenne | J34: Exploitation continue | K34: Automatiser le suivi des correctifs
D35: Tous les équipements connectés sont recensés | E35: Les bâtiments intelligents (GTB) et systèmes de contrôle d'accès sont-ils sécurisés ? | F35: Inventaire du parc informatique | G35: NON | H35: Equipements non sécurisés non identifiés | I35: Moyenne | J35: Brèches de sécurité | K35: Réaliser des inventaires réseau réguliers
D36: Les risques spécifiques aux équipements périphériques sont évalués | E36: Existe-t-il un processus pour identifier et corriger les failles sur les équipements négligés ? | F36: Rapport d'analyse des risques IoT | G36: Non | H36: Vulnérabilités des objets connectés | I36: Moyenne | J36: Compromission des systèmes | K36: Isoler les réseaux IoT des systèmes critiques
C37: S’assurer qu’une revue régulière de la politique est réalisée afin de vérifier son adéquation avec | D37: Des procédures spécifiques sont appliquées aux systèmes techniques | E37: Les mesures de protection physique (ex : accès aux locaux) sont-elles cohérentes avec la politique IT ? | F37: Guide de sécurisation des systèmes industriels | G37: Oui | H37: Perturbation des processus critiques | I37: Élevée | J37: Impact opérationnel majeur | K37: Développer des plans de continuité spécifiques
D38: Aucune zone d'ombre n'est tolérée | E38: L'organisation dispose-t-elle d'un responsable sécurité identifiable ? | F38: Rapport de couverture sécurité | G38: Non | H38: Zones non protégées exploitables | I38: Élevée | J38: Points d'entrée pour attaquants | K38: Réaliser des tests de pénétration réguliers
D39: La sécurité physique est alignée avec la sécurité logique | E39: Des réunions stratégiques sur la sécurité ont-elles lieu au moins trimestriellement ? | F39: Politique de sécurité globale | G39: NON | H39: Incohérence entre protections physiques et logiques | I39: Moyenne | J39: Faiblesses dans la défense | K39: Harmoniser les politiques via une approche globale
D40: Un RSSI ou équivalent est nommé | E40: Chaque département a-t-il un référent sécurité pour relayer les actions ? | F40: Décision de nomination du RSSI | G40: OUI | H40: Absence de leadership en sécurité | I40: Moyenne | J40: Manque de vision stratégique | K40: Nommer un CISO avec accès au COMEX
D41: Un comité sécurité se réunit régulièrement | E41: Les missions liées à la sécurité sont-elles formalisées dans les descriptions de fonction ? | F41: PV des réunions du comité | G41: NON | H41: Décisions sécurité non prises | I41: Moyenne | J41: Retard dans les protections | K41: Instaurer un comité sécurité décisionnel
C42: S’assurer que la démarche de sécurité inclut la totalité de l’informatique et non les seuls réseaux, serveurs et applications. Les imprimantes et téléphones sous IP, l’informatique technique et industrielle, l’informatique de gestion technique des bâtiments, celle de gestion des accès et temps de travail, etc. bénéficient sans exception ni zone d’ombre du dispositif de sécurité | D42: Des correspondants | E42: Le comité sécurité peut-il imposer des mesures correctives si nécessaire ? | F42: Liste des correspondants sécurité | G42: Non | H42: Manque de relais opérationnel | I42: Moyenne | J42: Mauvaise application sur le terrain | K42: Désigner des correspondants sécurité par service
D43: sécurité sont désignés dans les unités | E43: Chaque système critique a-til un responsable désigné ? | F43: Fiches de poste mises à jour | G43: Oui | H43: Confusion sur les responsabilités | I43: Moyenne | J43: Tâches non réalisées | K43: Élaborer des fiches de poste précises
D44: Les rôles sont définis dans des fiches de poste | E44: Existe-t-il une matrice RACI (Responsible, Accountable, Consulted, Informed) pour la sécurité ? | F44: Procédure de gouvernance sécurité | G44: Non | H44: Blocage des initiatives | I44: Moyenne | J44: Innovation entravée | K44: Créer un processus de validation agile
D45: La structure a un pouvoir décisionnel | E45: En cas d'absence, un suppléant est-il prévu pour prendre les décisions sécurité ? | F45: Registre des propriétaires | G45: Oui | H45: Actifs critiques non maintenus | I45: Moyenne | J45: Augmentation des risques techniques | K45: Prioriser les ressources sur les actifs essentiels
D46: Les propriétaires des actifs sont identifiés | E46: Les collaborateurs savent-ils quelles règles appliquer selon leur poste ? | F46: Charte des responsabilités | G46: Non | H46: Déni de responsabilité en cas d'incident | I46: Moyenne | J46: Difficultés d'investigation | K46: Documenter formellement les rôles et obligations
D47: Les responsabilités sont documentées | E47: Le règlement intérieur mentionne-t-il les conséquences d'une | F47: Procédure de délégation | G47: NON | H47: Interruption des processus | I47: Moyenne | J47: Perte de productivité | K47: Prévoir des mécanismes de délégation
C48: Établir et maintenir une politique de sécurité formalisée, alignée sur les risques de l’organisation et les exigences légales, afin de guider toutes les activités en matière de protection des actifs | D48: Les délégations de pouvoir sont formalisées | E48: Les droits des tiers sont-ils strictement limités à ce qui est nécessaire ? | F48: Accusé de lecture des politiques | G48: Non | H48: Non-respect involontaire | I48: Moyenne | J48: Exposition aux risques | K48: Simplifier et expliquer les exigences
D49: Les employés connaissent leurs obligations | E49: Comment sont gérés les retraits d'accès lorsque la collaboration prend fin ? | F49: Règlement intérieur | G49: Oui | H49: Absence de dissuasion | I49: Moyenne | J49: Répétition des manquements | K49: Appliquer systématiquement les sanctions prévues
D50: Les sanctions en cas de non-respect sont définies | E50: Existe-t-il un système de journalisation des accès externes ? | F50: Document de délégation d'autorité | G50: Non | H50: Impossibilité de corriger | I50: Moyenne | J50: Persistance des vulnérabilités | K50: Donner les autorisations nécessaires aux propriétaires
D51: Le propriétaire a une autorité sur l'actif | E51: Les prestataires sont-ils évalués sur leur niveau de sécurité avant d'obtenir des droits ? | F51: Tableau de bord de suivi | G51: Oui | H51: Actions non terminées | I51: Moyenne | J51: Protection incomplète | K51: Mettre en place un suivi projet dédié
B52: Organisation de la sécurité | C52: S’assurer qu’il existe une structure dédiée à la gestion de la sécurité de l'information : un comité sécurité, un responsable de la sécurité du système d'information (RSSI) et des correspondants sécurité dans les unités | D52: Un suivi des actions est mis en place sécurité | E52: L'organisation dispose-t-elle d'une base de données à jour de tous ses actifs informatiques ? | F52: Attestation de formation | G52: NON | H52: Mauvaises décisions | I52: Moyenne | J52: Augmentation des risques | K52: Former les décideurs aux enjeux sécurité
D53: Le propriétaire est formé aux enjeux | E53: Les actifs sont-ils catégorisés (ex : critique, important, standard) selon leur valeur métier ? | F53: Roadmap de sécurisation | G53: Non | H53: Réactivité insuffisante | I53: Moyenne | J53: Fenêtre d'exposition prolongée | K53: Automatiser les processus de détection et réponse
D54: Les évolutions sont planifiées | E54: Les données stratégiques et personnelles sont-elles recensées spécifiquement ? | F54: Rapport d'activité sécurité | G54: NON | H54: Manque de transparence | I54: Élevée | J54: Difficulté de gouvernance | K54: Publier des rapports réguliers au COMEX
D55: La redevabilité est assurée | E55: Chaque élément de l'inventaire a-t-il un propriétaire clairement identifié ? | F55: Procédure d'homologation | G55: Non | H55: Introduction de solutions non sécurisées | I55: Moyenne | J55: Nouveaux vecteurs d'attaque | K55: Instaurer un processus strict d'homologation
D56: Une procédure formelle d'homologation existe | E56: L'inventaire est-il révisé au moins annuellement ou après changements majeurs ? | F56: Référentiel d'homologation | G56: NON | H56: Approbation de solutions non conformes | I56: Moyenne | J56: Non-respect des standards | K56: Créer un référentiel technique contraignant
C57: Vérifier qu’il y a une attribution claire des responsabilités | D57: Les critères de sécurité sont définis pour l'approbation | E57: Existe-t-il un document officiel listant les propriétaires d'actifs et leurs obligations ? | F57: Registre des équipements homologués | G57: Non | H57: Utilisation de matériels non approuvés | I57: Moyenne | J57: Incompatibilités et vulnérabilités | K57: Mettre en place un registre des équipements autorisés
D58: Un registre des équipements autorisés est tenu à jour | E58: Le propriétaire est-il impliqué de l'acquisition à la destruction de l'actif ? | F58: Registre des dérogations | G58: Oui | H58: Multiplication des exceptions | I58: Moyenne | J58: Affaiblissement des protections | K58: Limiter les dérogations avec approbation hiérarchique
D59: Les exceptions sont documentées et justifiées | E59: Les propriétaires reçoivent-ils une formation sur la gestion des risques liés à leurs actifs ? | F59: Rapports de vérification | G59: OUI | H59: Dérive vers la nonconformité | I59: Moyenne | J59: Risque réglementaire | K59: Programmer des audits de conformité réguliers
D60: La conformité est vérifiée périodiquement | E60: Les propriétaires rendent-ils compte régulièrement de l'état de sécurité de leurs actifs ? | F60: Modèle de contrat avec tiers | G60: Non | H60: Fuite via des partenaires | I60: Moyenne | J60: Compromission des données | K60: Imposer des clauses contractuelles strictes
D61: Les accès externes sont régis par des contrats | E61: Que se passe-t-il lorsque le propriétaire quitte l'organisation ou change de poste ? | F61: Matrice des droits d'accès | G61: NON | H61: Accès excessifs augmentant les risques | I61: Élevée | J61: Mouvement latéral facilité | K61: Appliquer strictement le principe du moindre privilège
C62: S’assurer qu’un propriétaire est désigné, il est responsable de la mise en œuvre et du suivi des évolutions à apporter | D62: Le principe du moindre privilège est appliqué | E62: Les niveaux de protection reflètent-ils les exigences réglementaires du métier ? | F62: Procédure de gestion des identités | G62: NON | H62: Anciens collaborateurs conservant des accès | I62: Moyenne | J62: Accès non autorisés | K62: Automatiser les processus d'offboarding
D63: Une procédure de révocation d'accès existe | E63: Existe-t-il un guide expliquant comment classer les différents types d'informations ? | F63: Journal des accès externes | G63: Non | H63: Activités malveillantes non détectées | I63: Élevée | J63: Persistance des attaques | K63: Mettre en place un système de monitoring complet
D64: L'activité des tiers est monitorée | E64: Les collaborateurs savent-ils déterminer le niveau de sensibilité d'un document ? | F64: Grille d'évaluation des tiers | G64: Oui | H64: Sous-estimation des risques partenaires | I64: Élevée | J64: Exposition indirecte | K64: Élaborer une grille d'évaluation des fournisseurs
D65: Une évaluation des risques est faite avant octroi d'accès | E65: Des procédures spécifiques existent-elles pour chaque catégorie (ex : chiffrement obligatoire pour les données critiques) ? | F65: Base de données des actifs | G65: Non | H65: Impossibilité de protéger les actifs non recensés | I65: Moyenne | J65: Impact métier important | K65: Prioriser les investissements sur les actifs sensibles
D66: Un inventaire complet est maintenu | E66: Des audits vérifient-ils que le système de classification est correctement appliqué ? | F66: Politique de classification | G66: NON | H66: Protection inadaptée aux actifs critiques | I66: Moyenne | J66: Atteinte à la réputation | K66: Chiffrer les données sensibles et mettre en place des sauvegardes
C67: S’assurer qu’il existe des procédures d'autorisation de nouveaux matériels ou logiciels | D67: Une classification par criticité est établie | E67: Utilise-t-on une grille standardisée pour attribuer les niveaux de classification ? | F67: Inventaire des données sensibles | G67: Oui | H67: Fuite ou perte de données importantes | I67: Moyenne | J67: Vulnérabilités non corrigées | K67: Assigner systématiquement des propriétaires
D68: L'inventaire inclut les informations sensibles | E68: Le responsable métier participet-il à la détermination du niveau de protection ? | F68: Registre des propriétaires | G68: Non | H68: Actifs orphelins non maintenus | I68: Moyenne | J68: Décisions inappropriées | K68: Automatiser les processus de mise à jour
D69: La propriété des actifs est documentée | E69: Les niveaux sont-ils réévalués lors des changements organisationnels ou technologiques ? | F69: Planning des mises à jour | G69: NON | H69: Données obsolètes induisant en erreur | I69: Élevée | J69: Protection incomplète | K69: Adopter une approche cycle de vie complète
D70: La mise à jour est régulière et planifiée | E70: Les cas particuliers font-ils l'objet d'une justification écrite ? | F70: Décision de nomination | G70: Non | H70: Actifs sans responsable | I70: Moyenne | J70: Non-respect des politiques | K70: Standardiser les procédures de classification
D71: La désignation est formelle et documentée | E71: Peut-on retrouver qui a classifié un actif et sur quelle base ? | F71: Procédure de gestion des actifs | G71: NON | H71: Défauts à certaines étapes | I71: Élevée | J71: Incidents de sécurité | K71: Former régulièrement les utilisateurs
D72: Les responsabilités couvrent le cycle de vie complet | E72: responsabilités en matière de sécurité ? | F72: Attestation de formation | G72: NON | H72: Mauvaises décisions | I72: Moyenne | J72: Risque accru de fuite | K72: Appliquer des contrôles stricts selon la classification
C73: Assurer la mise en place et le maintien d’un système de management de la sécurité (SMS) conforme aux exigences réglementaires et aux meilleures pratiques du secteur. | D73: Une formation spécifique est dispensée | E73: Le principe du moindre privilège est-il appliqué dans l'attribution des droits systèmes | F73: Compte-rendu de revue | G73: Non | H73: Absence de suivi | I73: Moyenne | J73: Protection inadaptée | K73: Impliquer les métiers dans le processus
D74: La redevabilité est assurée | E74: Existe-t-il un référentiel des connaissances sécurité requises par métier ? | F74: Procédure de succession | G74: NON | H74: Interruption de la gestion | I74: Moyenne | J74: Affaiblissement des contrôles | K74: Mettre en place des audits réguliers
D75: Un processus de remplacement existe | E75: Les changements de fonction entraînent-ils une réévaluation des accès ? | F75: Référentiel sectoriel | G75: Non | H75: Non-respect des obligations | I75: Moyenne | J75: Mauvaise exécution des tâches | K75: Élaborer un plan de formation continu
D76: La classification est adaptée au secteur | E76: Les fonctions incompatibles sont-elles réparties entre différentes personnes ? | F76: Guide de classification | G76: Oui | H76: Incohérence dans le traitement | I76: Moyenne | J76: Accès injustifiés | K76: Automatiser les revues d'habilitations
D77: d'activité | E77: Les formations sont-elles adaptées aux différents rôles | F77: Test de connaissance | G77: Oui | H77: Erreurs de manipulation | I77: Moyenne | J77: Pertes financières | K77: Séparer clairement les fonctions sensibles
D78: Les critères de classification sont documentés | E78: (direction, managers, employés, IT) ? | F78: Procédure de gestion des données | G78: Non | H78: Exposition inutile | I78: Moyenne | J78: Points faibles exploitables | K78: Adapter les formations aux besoins spécifiques
C79: Vérifier que pour tout actif important, un propriétaire est désigné et informé de ses responsabilités | D79: Le système est compris par les employés | E79: Les collaborateurs reçoivent-ils une formation sécurité au moins annuellement ? | F79: Rapports d'audit | G79: Oui | H79: Non-respect prolongé | I79: Moyenne | J79: Mauvaise prise de décision | K79: Mettre à jour régulièrement les supports
D80: Les règles de traitement par niveau sont définies | E80: Les modules intègrent-ils les nouvelles menaces et les évolutions réglementaires ? | F80: Procédure d'évaluation | G80: Non | H80: Classification arbitraire | I80: Moyenne | J80: Ressources gaspillées | K80: Mesurer l'impact des formations
D81: La conformité est contrôlée | E81: Des tests ou questionnaires évaluent-ils l'acquisition des connaissances ? | F81: PV de réunion d'évaluation | G81: Oui | H81: Besoins métiers non pris en compte | I81: Moyenne | J81: Vulnérabilités humaines | K81: Intégrer la sécurité dans l'onboarding
D82: Une méthodologie d'évaluation est appliquée | E82: Comment sont formés les nouveaux arrivants ou ceux ayant manqué une session ? | F82: Planning des révisions | G82: Non | H82: Données mal classées | I82: Moyenne | J82: Impact systémique | K82: Mettre en place une solution PAM
D83: L'étude implique le propriétaire métier | E83: Les données stratégiques et personnelles sont-elles recensées spécifiquement ? | F83: Registre des exceptions | G83: Oui | H83: Contournement des règles | I83: Moyenne | J83: Extension des attaques | K83: Segmenter finement le réseau
C84: Vérifier qu'il existe un système de classification qui définit un ensemble approprié de niveaux de protection | D84: La classification est révisée périodiquement | E84: Chaque élément de l'inventaire a-t-il un propriétaire clairement identifié ? | F84: Journal des décisions | G84: Oui | H84: Impossibilité de justifier | I84: Moyenne | J84: Perte de contrôle | K84: Implémenter l'authentification forte
D85: Les exceptions sont documentées | E85: L'inventaire est-il révisé au moins annuellement ou après changements majeurs ? | F85: Référentiel des métiers | G85: Non | H85: Inadéquation des compétences | I85: Moyenne | J85: Exploitation facile | K85: Appliquer des benchmarks de durcissement
D86: La traçabilité des décisions est assurée | E86: Existe-t-il un document officiel listant les propriétaires d'actifs et leurs obligations ? | F86: Matrice des droits d'accès | G86: Oui | H86: Accès excessifs ou insuffisants | I86: Moyenne | J86: Accès non sécurisé | K86: Modifier systématiquement les identifiants par défaut
D87: Des profils de poste sécurité existent | E87: Le propriétaire est-il impliqué de l'acquisition à la destruction de l'actif ? | F87: Référentiel des compétences | G87: Non | H87: Personnel non qualifié | I87: Moyenne | J87: Persistance des menaces | K87: Centraliser et analyser les logs
D88: Les droits d'accès sont proportionnés aux fonctions | E88: Les propriétaires reçoivent-ils une formation sur la gestion des risques liés à leurs actifs ? | F88: Procédure de gestion des carrières | G88: Oui | H88: Droits obsolètes | I88: Moyenne | J88: Compromission des systèmes | K88: Appliquer les correctifs en temps voulu
C89: Vérifier que chaque actif a fait l'objet d'une étude visant à déterminer son niveau de classification | D89: Une matrice des compétences est disponible | E89: Les propriétaires rendent-ils compte régulièrement de l'état de sécurité de leurs actifs ? | F89: Procédure de séparation des fonctions | G89: Non | H89: Fraude ou erreurs non détectées | I89: Moyenne | J89: Exposition inutile | K89: Intégrer la sécurité dans le cycle DevOps
D90: Les évolutions de poste déclenchent une revue des droits | E90: Que se passe-t-il lorsque le propriétaire quitte l'organisation ou change de poste ? | F90: Plan de formation global | G90: Oui | H90: Lacunes dans certains services | I90: Moyenne | J90: Prise de contrôle aisée | K90: Désactiver les comptes par défaut
D91: La séparation des tâches est respectée | E91: Les niveaux de protection reflètent-ils les exigences réglementaires du métier ? | F91: Calendrier des formations | G91: Oui | H91: Relâchement de la vigilance | I91: Moyenne | J91: Impact opérationnel | K91: Mettre en place des tests de sécurité automatisés
D92: Le programme couvre tous les métiers | E92: Existe-t-il un guide expliquant comment classer les différents types d'informations ? | F92: Version des supports | G92: Non | H92: Information obsolète | I92: Moyenne | J92: Répétition des erreurs | K92: Documenter systématiquement les incidents
D93: La fréquence est suffisante | E93: Les collaborateurs savent-ils déterminer le niveau de sensibilité d'un document ? | F93: Rapport d'évaluation | G93: Oui | H93: Formations inefficaces | I93: Élevée | J93: Exposition aux attaques | K93: Intégrer des revues de sécurité dans le SDLC
C94: Analyser les vulnérabilités des réseaux pour anticiper et prévenir les intrusions malveillantes | D94: Les contenus sont | E94: Des procédures spécifiques existent-elles pour chaque catégorie (ex : chiffrement obligatoire pour les données critiques) ? | F94: Procédure de rattrapage | G94: Non | H94: Nouveaux employés non formés | I94: Moyenne | J94: Non-respect RGPD | K94: Chiffrer systématiquement les données sensibles
D95: actualisés régulièrement | E95: Des audits vérifient-ils que le système de classification est correctement appliqué ? | F95: Matrice des droits d'accès | G95: Oui | H95: Impossibilité de justifier | I95: Moyenne | J95: Atteinte prolongée | K95: Implémenter des solutions DLP
D96: L'efficacité est mesurée | E96: Utilise-t-on une grille standardisée pour attribuer les niveaux de classification ? | F96: Référentiel des compétences | G96: Non | H96: Inadéquation des compétences | I96: Moyenne | J96: Violation de confidentialité | K96: Appliquer des méthodes d'effacement sécurisé
D97: Les absents reçoivent une formation de rattrapage | E97: Le responsable métier participet-il à la détermination du niveau de protection ? | F97: Procédure de gestion des carrières | G97: Oui | H97: Accès excessifs ou insuffisants | I97: Moyenne | J97: Mouvement latéral facilité | K97: Appliquer strictement le principe du moindre privilège
D98: Une méthodologie d'évaluation est appliquée | E98: Comment sont formés les nouveaux arrivants ou ceux ayant manqué une session ? | F98: Procédure de séparation des fonctions | G98: Non | H98: Personnel non qualifié | I98: Moyenne | J98: Accès non autorisés | K98: Automatiser les processus d'offboarding
B99: Sécurité du personnel | C99: Vérifier que les postes et les ressources sont définis | D99: L'étude implique le propriétaire métier | E99: Les données stratégiques et personnelles sont-elles recensées spécifiquement ? | F99: Plan de formation global | G99: Oui | H99: Droits obsolètes | I99: Moyenne | J99: Persistance des attaques | K99: Mettre en place un système de monitoring complet
D100: La classification est révisée périodiquement | E100: Chaque élément de l'inventaire a-t-il un propriétaire clairement identifié ? | F100: Calendrier des formations | G100: Non | H100: Fraude ou erreurs non détectées | I100: Moyenne | J100: Exposition indirecte | K100: Élaborer une grille d'évaluation des fournisseurs
...

Sheet COSO
A1: Domaines | B1: Points de contrôle | C1: Objectifs de contrôle | D1: Critères d'évaluation | E1: Questions d'évaluations | F1: Réponses | G1: Documents requis | H1: Risques | I1: Criticité | J1: Conséquences | K1: Recommandations
A2: Environnement de contrôle | B2: Engagement envers l’intégrité et les valeurs éthiques | C2: S’assurer que l'organisation dispose d'une charte éthique formelle qui couvre l'ensemble des pratiques professionnelles et des interactions au sein de l'organisation, y compris les activités liées aux systèmes d'information. | D2: La charte éthique est disponible et accessible à tous les employés (ex : intranet, affichage). | E2: La charte éthique est-elle disponible et accessible à tous les employés (ex : intranet, affichage) ? | F2: NON | G2: Charte éthique officielle | H2: absence de validation par les instances dirigeantes | I2: Elevée | J2: Décisions sans valeur légale | K2: Validation systématique par le service juridique
F3: NON | G3: Preuve de diffusion (intranet/affichage) | H3: NON-conformité aux réglementations en vigueur | I3: Elevée | J3: Amendes et pénalités financières | K3: Audit mensuel des obligations réglementaires
D4: La charte couvre explicitement les pratiques professionnelles et les interactions internes. | E4: La charte couvre-t-elle explicitement les pratiques professionnelles et les interactions internes ? | F4: NON | G4: Manuel des procédures internes | H4: diffusion incomplète ou inégale au sein de l'organisation | I4: Elevée | J4: Certains services mal informés | K4: Mise en place d'un circuit d'information officiel
F5: NON | G5: Guide des bonnes pratiques | H5: interprétations divergentes des collaborateurs | I5: Elevée | J5: Chacun applique à sa manière | K5: Élaboration de protocoles standardisés
D6: La charte mentionne spécifiquement les activités liées aux systèmes d’information. | E6: La charte mentionne-t-elle spécifiquement les activités liées aux systèmes d’information ? | F6: NON | G6: Politique SI annexée à la charte | H6: obsolescence des processus décrits | I6: Elevée | J6: Procédures qui ne fonctionnent plus | K6: Revue trimestrielle des procédures opérationnelles
F7: NON | G7: Procès-verbal du COMEX | H7: inadaptation aux réalités opérationnelles | I7: Elevée | J7: Incompatibilité avec le travail réel | K7: Alignement des règles sur les pratiques terrain
D8: La charte a été officiellement approuvée par la direction (ex : signature, date). | E8: La charte a-t-elle été officiellement approuvée par la direction (ex : signature, date) ? | F8: NON | G8: Registre des mises à jour | H8: NON-intégration des mises à jour réglementaires | I8: Elevée | J8: Problèmes avec les autorités | K8: Consultation préalable des autorités compétentes
F9: NON | G9: Historique des versions | H9: absence de traçabilité des modifications | I9: Elevée | J9: Impossible de retracer les changements | K9: Implémentation d'un journal des modifications
D10: La charte est régulièrement mise à jour pour rester pertinente. | E10: La charte est-elle régulièrement mise à jour pour rester pertinente ? | F10: NON | G10: Registre des signatures employés | H10: falsification ou usage frauduleux des signatures | I10: Elevée | J10: Risque de fraude immédiat | K10: Contrôles aléatoires antifraude
F11: NON | G11: Procédure d'engagement | H11: ambiguïté dans les obligations contractuelles | I11: Elevée | J11: Litiges avec les partenaires | K11: Clauses contractuelles détaillées et actualisées
C12: Vérifier que des mécanismes existent pour garantir que tous les acteurs (employés, partenaires, prestataires) respectent cette charte éthique dans leurs activités professionnelles, y compris dans leur utilisation des systèmes d'information. | D12: Tous les employés ont signé un engagement à respecter la charte éthique. | E12: Tous les employés ont-ils signé un engagement à respecter la charte éthique ? | F12: NON | G12: Clause éthique des contrats partenaires | H12: défaut de preuve de réception par les parties prenantes | I12: Elevée | J12: Impossible de prouver la réception | K12: Système d'accusé de réception électronique
F13: NON | G13: Preuve de transmission | H13: NON-respect des fréquences de rappel prévues | I13: Elevée | J13: Oublis des obligations importantes | K13: Checklists automatisées pour les obligations légales
D14: Les partenaires et prestataires ont reçu une copie de la charte éthique. | E14: Les partenaires et prestataires ont-ils reçu une copie de la charte éthique ? | F14: NON | G14: Planning des rappels éthiques | H14: messages incohérents ou contradictoires | I14: Elevée | J14: Messages contradictoires entre services | K14: Messagerie unifiée pour les communications internes
F15: NON | G15: Supports de communication interne | H15: vulnérabilité aux représailles en cas de signalement | I15: Elevée | J15: Peur de parler par crainte de représailles | K15: Dispositif de signalement aNONyme et sécurisé
D16: Des rappels réguliers sur la charte éthique sont envoyés aux employés (ex : mails, affichage). | E16: Des rappels réguliers sur la charte éthique sont-ils envoyés aux employés (ex : mails, affichage) ? | F16: NON | G16: Procédure de signalement | H16: compétences insuffisantes des référents désignés | I16: Elevée | J16: Référents qui donnent de mauvais conseils | K16: Validation hiérarchique des conseils des référents
F17: NON | G17: Liste des référents éthiques | H17: cas pratiques NON représentatifs des risques réels | I17: Elevée | J17: Formations qui ne préparent PAS au réel | K17: Formations basées sur des cas pratiques
D18: Un point de contact est disponible pour signaler les écarts éthiques (ex : email, hotline). | E18: Un point de contact est-il disponible pour signaler les écarts éthiques (ex : email, hotline) ? | F18: NON | G18: Recueil de cas pratiques | H18: perte d'accès aux documents historiques | I18: Elevée | J18: Documents anciens introuvables | K18: Archivage numérique sécurisé des documents
F19: NON | G19: Archives des communications | H19: inadéquation des bonnes pratiques avec la culture d'entreprise | I19: Elevée | J19: Bonnes pratiques rejetées par les équipes | K19: Concertation avec les équipes pour les bonnes pratiques
D20: Des exemples de bonnes pratiques éthiques sont partagés régulièrement avec les équipes. | E20: Des exemples de bonnes pratiques éthiques sont-ils partagés régulièrement avec les équipes ? | F20: NON | G20: Recueil des bonnes pratiques éthiques | H20: décisions NON ratifiées par les instances compétentes | I20: Elevée | J20: Décisions qui tiennent PAS la route | K20: Revue collégiale des décisions stratégiques
F21: NON | G21: Procès-verbal du dernier comité éthique | H21: formations NON adaptées aux publics cibles | I21: Elevée | J21: Formations inutiles pour les métiers | K21: Formations adaptées aux besoins opérationnels
C22: S’assurer que des actions de sensibilisation, telles que des formations régulières, sont mises en place pour garantir que tous les employés et intervenants comprennent et appliquent les principes éthiques dans leurs interactions avec les systèmes d'information. | D22: Des formations sur l’éthique et les systèmes d’information sont proposées régulièrement aux employés. | E22: Des formations sur l’éthique et les systèmes d’information sont-elles proposées régulièrement aux employés ? | F22: NON | G22: Catalogue des formations en éthique | H22: annulation répétée des sessions prévues | I22: Elevée | J22: Sessions annulées en dernière minute | K22: Calendrier annuel fixe des sessions de formation
F23: NON | G23: Planning des sessions 2024 | H23: participation insuffisante aux sensibilisations | I23: Elevée | J23: Personne ne vient aux formations | K23: Obligation de participation avec suivi RH
D24: Un calendrier des sessions de sensibilisation est disponible et communiqué à tous. | E24: Un calendrier des sessions de sensibilisation est-il disponible et communiqué à tous ? | F24: NON | G24: Calendrier officiel des sensibilisations | H24: canal de communication NON sécurisé | I24: Elevée | J24: Données qui fuient par des canaux NON sécurisés | K24: Cryptage des données et canaux sécurisés
F25: NON | G25: Procédure de communication interne | H25: NON-complétion du module par les nouveaux arrivants | I25: Elevée | J25: Nouveaux arrivants PAS formés correctement | K25: Programme de tutorat pour les nouveaux arrivants
D26: Les nouveaux employés suivent une formation obligatoire sur la charte éthique lors de leur intégration. | E26: Les nouveaux employés suivent-ils une formation obligatoire sur la charte éthique lors de leur intégration ? | F26: NON | G26: Module d'introduction obligatoire | H26: suivi irrégulier des intégrations | I26: Elevée | J26: Intégration mal suivie | K26: Checklist d'intégration avec suivi RH
F27: NON | G27: Fiche de suivi des nouveaux employés | H27: directives trop génériques pour guider l'action | I27: Elevée | J27: Consignes trop vagues pour agir | K27: Rédaction de consignes opérationnelles claires
D28: Des supports de sensibilisation (ex : guides, vidéos) sont accessibles à tous les employés. | E28: Des supports de sensibilisation (ex : guides, vidéos) sont-ils accessibles à tous les employés ? | F28: NON | G28: Guide des bonnes pratiques éthiques | H28: indisponibilité technique de la plateforme | I28: Elevée | J28: Outils techniques qui plantent | K28: Maintenance préventive des outils informatiques
F29: NON | G29: Plateforme de ressources numériques | H29: données de participation erronées ou incomplètes | I29: Elevée | J29: Données fausses dans les rapports | K29: Vérification croisée des données avant publication
D30: Un taux de participation aux formations est mesuré et partagé avec la direction. | E30: Un taux de participation aux formations est-il mesuré et partagé avec la direction ? | F30: NON | G30: Tableau de bord des participations | H30: retard dans la remontée d'information à la direction | I30: Elevée | J30: Retards dans les prises de décision | K30: Délégation de pouvoir pour les décisions urgentes
F31: NON | G31: Rapport trimestriel à la direction | H31: procédure de signalement trop complexe | I31: Elevée | J31: Procédures trop compliquées pour signaler | K31: Simplification des procédures de remontée d'alertes
C32: S’assurer que l'organisation dispose d'un mécanisme de suivi et de gestion des violations éthiques, permettant de détecter, traiter et sanctionner tout comportement contraire à la charte éthique, y compris dans le cadre des activités liées aux systèmes d'information. | D32: Un canal de signalement des violations éthiques est accessible à tous (ex : hotline, boîte mail dédiée). | E32: Un canal de signalement des violations éthiques est-il accessible à tous (ex : hotline, boîte mail dédiée) ? | F32: NON | G32: Procédure de signalement écrite | H32: référents éthiques surchargés ou indisponibles | I32: Elevée | J32: Référents injoignables ou débordés | K32: Plages horaires dédiées pour les référents
F33: NON | G33: Liste des référents éthiques | H33: centralisation défaillante des signalements | I33: Elevée | J33: Signalements qui se perdent | K33: Système de ticketing avec suivi obligatoire
D34: Les violations signalées sont documentées et suivies dans un registre ou une base de données. | E34: Les violations signalées sont-elles documentées et suivies dans un registre ou une base de données ? | F34: OUI | G34: Registre central des signalements | H34: faille de confidentialité dans la base d'incidents | I34: Elevée | J34: Fuites d'informations confidentielles | K34: Protocole de gestion des documents confidentiels
F35: OUI | G35: Base de données des incidents | H35: partialité ou manque d'objectivité dans les enquêtes | I35: Elevée | J35: Enquêtes PAS objectives | K35: Recours à des enquêteurs externes indépendants
D36: Des procédures claires définissent les étapes de traitement des violations (détection, enquête, sanction). | E36: Des procédures claires définissent-elles les étapes de traitement des violations (détection, enquête, sanction) ? | F36: OUI | G36: Protocole d'enquête interne | H36: sanctions incohérentes avec les manquements | I36: Elevée | J36: Sanctions disproportionnées ou absentes | K36: Grille de sanctions proportionnelle et transparente
F37: OUI | G37: Grille des sanctions types | H37: absence de suivi des sanctions proNONcées | I37: Elevée | J37: PAS de suivi des punitions | K37: Suivi informatisé des mesures disciplinaires
D38: Des sanctions sont appliquées en cas de violation avérée et documentées. | E38: Des sanctions sont-elles appliquées en cas de violation avérée et documentées ? | F38: OUI | G38: Recueil des sanctions appliquées | H38: archivage NON sécurisé des décisions sensibles | I38: Elevée | J38: Décisions sensibles mal protégées | K38: Classement sécurisé des décisions sensibles
F39: OUI | G39: Archives des décisions | H39: indicateurs NON alignés sur les objectifs éthiques | I39: Elevée | J39: Indicateurs qui ne reflètent PAS la réalité | K39: Audit externe des indicateurs clés
D40: Un rapport régulier sur les violations et leur gestion est partagé avec la direction. | E40: Un rapport régulier sur les violations et leur gestion est-il partagé avec la direction ? | F40: OUI | G40: Rapport annuel d'activité éthique | H40: communication édulcorée vers les instances dirigeantes | I40: Elevée | J40: Direction mal informée des vrais problèmes | K40: Remontée hebdomadaire des alertes terrain
F41: OUI | G41: Synthèse pour le conseil d'administration | H41: faille dans la distribution des documents clés | I41: Elevée | J41: Documents importants mal distribués | K41: Circuit contrôlé de distribution documentaire
C42: Vérifier que tous les employés ont reçu une copie de la charte éthique (par mail ou papier) et confirmer qu’ils l’ont bien reçue. | D42: Une copie de la charte éthique a été envoyée à tous les employés par mail ou remise en main propre. | E42: Une copie de la charte éthique a-t-elle été envoyée à tous les employés par mail ou remise en main propre ? | F42: OUI | G42: Preuve de distribution collective | H42: liste des destinataires NON actualisée | I42: Elevée | J42: Listes de diffusion PAS à jour | K42: Mise à jour mensuelle des listes de contacts
F43: OUI | G43: Liste de diffusion complète | H43: signature NON vérifiée des accords confidentiels | I43: Elevée | J43: Signatures NON vérifiées sur contrats | K43: Vérification systématique des signatures
D44: Un accusé de réception ou une confirmation écrite de chaque employé est disponible. | E44: Un accusé de réception ou une confirmation écrite de chaque employé est-il disponible ? | F44: OUI | G44: Registre des accords de confidentialité | H44: NON-conservation des attestations individuelles | I44: Elevée | J44: Attestations perdues | K44: Double archivage physique/numérique des attestations
F45: OUI | G45: Dossiers individuels signés | H45: charte d'intégration NON adaptée aux métiers | I45: Elevée | J45: Charte inadaptée aux différents métiers | K45: Chartes métiers avec exemples concrets
D46: Les nouveaux employés reçoivent la charte éthique lors de leur intégration. | E46: Les nouveaux employés reçoivent-ils la charte éthique lors de leur intégration ? | F46: OUI | G46: Charte d'intégration des nouveaux employés | H46: preuve de distribution NON vérifiable | I46: Elevée | J46: Impossible de prouver qui a reçu quoi | K46: Registre électronique des accusés de réception
F47: OUI | G47: Registre de distribution signé | H47: base de données des destinataires corrompue | I47: Elevée | J47: Base de données des contacts corrompue | K47: Purge et sécurisation de la base de contacts
D48: Un registre centralisé recense les employés ayant reçu la charte éthique. | E48: Un registre centralisé recense-t-il les employés ayant reçu la charte éthique ? | F48: OUI | G48: Base de données des destinataires | H48: absence de preuve de réception collective | I48: Elevée | J48: PAS de preuve que tout le monde a bien reçu | K48: Confirmation écrite obligatoire pour les envois importants
F49: OUI | G49: Attestation de réception collective | H49: programmation des rappels NON respectée | I49: Elevée | J49: Rappels qui ne sont PAS faits à temps | K49: Alertes automatiques pour les échéances réglementaires
D50: Des rappels périodiques sont envoyés pour s’assurer que la charte reste accessible et connue. | E50: Des rappels périodiques sont-ils envoyés pour s’assurer que la charte reste accessible et connue ? | F50: OUI | G50: Programmation des rappels éthiques | H50: perte des historiques de communication | I50: Elevée | J50: Historique des échanges perdu | K50: Centralisation des échanges officiels
F51: OUI | G51: Archive des communications envoyées | H51: conflits d'intérêts NON déclarés des administrateurs | I51: Elevée | J51: Problèmes d'objectivité chez les décideurs | K51: Formation des décideurs à l'analyse objective
B52: Le Conseil fait preuve d’indépendance vis-à-vis du management | C52: S’assurer que le Conseil est composé de membres indépendants du management, avec une structure de gouvernance claire garantissant cette indépendance. | D52: La majorité des membres du Conseil sont indépendants et n’occupent PAS de fonctions opérationnelles dans l’organisation. | E52: La majorité des membres du Conseil sont-ils indépendants et n’occupent-ils PAS de fonctions opérationnelles dans l’organisation ? | F52: OUI | G52: Liste actualisée des administrateurs | H52: procédure de nomination NON transparente | I52: Elevée | J52: Décisions de nomination contestables | K52: Publication des critères de nomination
F53: OUI | G53: Procès-verbal de nomination récent | H53: déclaration d'indépendance falsifiée | I53: Elevée | J53: Fausses déclarations PASsant inaperçues | K53: Contrôle aléatoire des déclarations
D54: Les membres indépendants sont identifiés et listés dans les documents officiels du Conseil. | E54: Les membres indépendants sont-ils identifiés et listés dans les documents officiels du Conseil ? | F54: OUI | G54: Déclaration d'indépendance signée | H54: registre des intérêts NON mis à jour | I54: Elevée | J54: Conflits d'intérêts NON détectés | K54: Obligation de déclaration d'intérêts
F55: OUI | G55: Registre des liens d'intérêts | H55: critères d'indépendance trop subjectifs | I55: Elevée | J55: Jugements basés sur des opinions personnelles | K55: Grilles d'évaluation standardisées
D56: Une politique écrite définit les critères d’indépendance des membres du Conseil. | E56: Une politique écrite définit-elle les critères d’indépendance des membres du Conseil ? | F56: OUI | G56: Document cadre d'indépendance | H56: grille d'évaluation biaisée ou partiale | I56: Elevée | J56: Évaluations injustes dès le départ | K56: Formation aux biais cognitifs
F57: OUI | G57: Grille d'évaluation validée | H57: omission de déclarations d'intérêts | I57: Elevée | J57: Intérêts cachés influençant les décisions | K57: Médiation professionnelle pour les conflits
D58: Les conflits d’intérêts potentiels des membres du Conseil sont déclarés et documentés. | E58: Les conflits d’intérêts potentiels des membres du Conseil sont-ils déclarés et documentés ? | F58: OUI | G58: Formulaire de déclaration d'intérêts | H58: gestion opaque des conflits déclarés | I58: Elevée | J58: Conflits mal gérés créant des tensions | K58: Audit terrain des processus réels
F59: OUI | G59: Registre des conflits déclarés | H59: gouvernance en décalage avec les pratiques réelles | I59: Elevée | J59: Règles écrites différentes de la réalité | K59: Mise à jour trimestrielle de l'organigramme
D60: La structure de gouvernance est clairement définie et accessible (ex : organigramme, charte de gouvernance). | E60: La structure de gouvernance est-elle clairement définie et accessible (ex : organigramme, charte de gouvernance) ? | F60: OUI | G60: Charte de gouvernance en vigueur | H60: organigramme NON reflétant les circuits de décision | I60: Elevée | J60: Organigramme inutile car inexact | K60: Checklists de vérification systématiques
F61: OUI | G61: Organigramme certifié par la direction | H61: contrôles internes insuffisants ou absents | I61: Elevée | J61: Problèmes NON détectés par manque de vérification | K61: Cellule de crise pour les urgences opérationnelles
C62: Vérifier que le Conseil dispose des ressources et des informations nécessaires pour surveiller efficacement la mise en place et le bon fonctionnement du dispositif de contrôle interne. | D62: Le Conseil reçoit régulièrement des rapports détaillés sur l’état du contrôle interne. | E62: Le Conseil reçoit-il régulièrement des rapports détaillés sur l’état du contrôle interne ? | F62: OUI | G62: Rapport mensuel de contrôle interne | H62: points critiques NON adressés dans les délais | I62: Elevée | J62: Urgences traitées en retard | K62: Évaluation pratique des formations dirigeants
F63: OUI | G63: Synthèse des points critiques | H63: plan de formation du Conseil irréaliste | I63: Elevée | J63: Formations du Conseil inefficaces | K63: Validation des supports par les utilisateurs
D64: Les membres du Conseil ont accès à des formations ou ressources pour comprendre les enjeux du contrôle interne. | E64: Les membres du Conseil ont-ils accès à des formations ou ressources pour comprendre les enjeux du contrôle interne ? | F64: OUI | G64: Plan de formation du Conseil | H64: ressources pédagogiques inadaptées | I64: Elevée | J64: Supports de formation inutilisables | K64: Alertes automatiques sur les déPASsements budgétaires
F65: OUI | G65: Catalogue des ressources pédagogiques | H65: déPASsement systématique du budget alloué | I65: Elevée | J65: Dépenses déPASsant toujours le budget | K65: Double signature pour les engagements financiers
D66: Un budget spécifique est alloué au Conseil pour soutenir ses activités de surveillance. | E66: Un budget spécifique est-il alloué au Conseil pour soutenir ses activités de surveillance ? | F66: OUI | G66: Budget approuvé du Conseil | H66: dépenses NON autorisées ou NON justifiées | I66: Elevée | J66: Argent dépensé sans autorisation | K66: Appel d'offres obligatoire pour les consultants
F67: OUI | G67: Détail des dépenses autorisées | H67: recours abusif à des experts externes | I67: Elevée | J67: Trop dépendant des consultants externes | K67: Vérification des compétences des prestataires
D68: Le Conseil a accès à des experts indépendants (ex : auditeurs, consultants) si nécessaire. | E68: Le Conseil a-t-il accès à des experts indépendants (ex : auditeurs, consultants) si nécessaire ? | F68: OUI | G68: Protocole de recours aux experts | H68: compétences des consultants NON vérifiées | I68: Elevée | J68: Experts PAS compétents utilisés | K68: Traçage des modifications décisionnelles
F69: OUI | G69: Répertoire des consultants habilités | H69: décisions NON enregistrées ou modifiées a posteriori | I69: Elevée | J69: Décisions modifiées après coup | K69: Validation des PV dans les 48 heures
D70: Les décisions et recommandations du Conseil sont documentées et suivies dans un registre officiel. | E70: Les décisions et recommandations du Conseil sont-elles documentées et suivies dans un registre officiel ? | F70: OUI | G70: Registre officiel des décisions | H70: comptes-rendus NON validés par les participants | I70: Elevée | J70: Procès-verbaux NON approuvés | K70: Contrôles inopinés par l'audit interne
F71: OUI | G71: Compte-rendu de réunion signé | H71: évaluation des contrôles superficielle ou biaisée | I71: Elevée | J71: Contrôles mal faits ou bidons | K71: Recoupement des indicateurs avec les données terrain
C72: S’assurer que le Conseil reçoit régulièrement des rapports détaillés sur l’efficacité du dispositif de contrôle interne et qu'il est impliqué dans l’évaluation des résultats des audits internes. | D72: Des rapports sur l’efficacité du contrôle interne sont présentés au Conseil à intervalles réguliers (ex : trimestriellement). | E72: Des rapports sur l’efficacité du contrôle interne sont-ils présentés au Conseil à intervalles réguliers (ex : trimestriellement) ? | F72: OUI | G72: Évaluation trimestrielle du contrôle interne | H72: KPI NON pertinents ou mal mesurés | I72: Elevée | J72: Indicateurs qui ne reflètent PAS la réalité | K72: Audit trimestriel des indicateurs par des experts externes
F73: OUI | G73: Tableau de bord des KPI | H73: écarts répétés NON corrigés | I73: Elevée | J73: Problèmes qui reviennent sans cesse | K73: Analyse root cause systématique des problèmes récurrents
D74: Les rapports incluent des indicateurs clés de performance (KPI) et des analyses des écarts identifiés. | E74: Les rapports incluent-ils des indicateurs clés de performance (KPI) et des analyses des écarts identifiés ? | F74: OUI | G74: Analyse des écarts constatés | H74: plan correctif inapplicable ou inefficace | I74: Elevée | J74: Solutions proposées qui ne marchent PAS | K74: Tests pilotes obligatoires avant déploiement des solutions
F75: OUI | G75: Plan correctif approuvé | H75: conclusions d'audit ignorées ou minimisées | I75: Elevée | J75: Recommandations d'audit ignorées | K75: Tableau de suivi mensuel des recommandations d'audit
D76: Le Conseil participe activement à l’examen des résultats des audits internes lors de ses réunions. | E76: Le Conseil participe-t-il activement à l’examen des résultats des audits internes lors de ses réunions ? | F76: OUI | G76: Relevé de conclusions d'audit | H76: légitimité des participants NON vérifiée | I76: Elevée | J76: Participants aux réunions PAS légitimes | K76: Vérification des habilitations avant chaque réunion
F77: OUI | G77: Liste des participants certifiée | H77: retard dans la mise en œuvre des recommandations | I77: Elevée | J77: Retards dans l'application des décisions | K77: Mise en place d'un système de suivi des décisions
D78: Les décisions et recommandations du Conseil suite à ces rapports sont documentées et suivies. | E78: Les décisions et recommandations du Conseil suite à ces rapports sont-elles documentées et suivies ? | F78: OUI | G78: Suivi des recommandations clés | H78: suivi des actions correctives NON priorisé | I78: Elevée | J78: Priorités mal définies dans les corrections | K78: Matrice de priorisation claire pour les corrections
F79: OUI | G79: Fiche de progression hebdomadaire | H79: procédures de mise en œuvre trop rigides | I79: Elevée | J79: Procédures trop rigides bloquant l'action | K79: Assouplissement contrôlé des procédures critiques
D80: Un processus formel garantit que les actions correctives recommandées par le Conseil sont mises en œuvre. | E80: Un processus formel garantit-il que les actions correctives recommandées par le Conseil sont mises en œuvre ? | F80: OUI | G80: Procédure de mise en œuvre | H80: échéances constamment repoussées | I80: Elevée | J80: Délais jamais respectés | K80: Sanctions pour retard répété dans les délais
F81: OUI | G81: Échéancier des actions correctives | H81: orientations stratégiques floues ou contradictoires | I81: Elevée | J81: Stratégie floue ou contradictoire | K81: Elaboration d'une stratégie écrite et partagée
C82: Vérifier que le Conseil joue un rôle actif dans la définition des objectifs et des critères de performance du contrôle interne, et qu’il veille à leur alignement avec les objectifs stratégiques de l’organisation. | D82: Le Conseil participe à des réunions dédiées pour définir les objectifs du contrôle interne. | E82: Le Conseil participe-t-il à des réunions dédiées pour définir les objectifs du contrôle interne ? | F82: OUI | G82: Procès-verbal de réunion stratégique | H82: objectifs annuels NON chiffrés ou NON mesurables | I82: Elevée | J82: Objectifs PAS clairs ou PAS mesurables | K82: Définition d'objectifs SMART mesurables
F83: OUI | G83: Document d'objectifs annuels validé | H83: cadre de référence NON partagé ou mal compris | I83: Elevée | J83: Personne ne comprend les référentiels | K83: Formation obligatoire aux référentiels
D84: Les objectifs du contrôle interne sont explicitement alignés avec les objectifs stratégiques de l’organisation. | E84: Les objectifs du contrôle interne sont-ils explicitement alignés avec les objectifs stratégiques de l’organisation ? | F84: OUI | G84: Cadre de référence stratégique | H84: matrice d'alignement NON actualisée | I84: Elevée | J84: Outils d'alignement PAS à jour | K84: Mise à jour semestrielle des outils d'alignement
F85: OUI | G85: Matrice d'alignement actualisée | H85: critères de performance subjectifs ou opaques | I85: Elevée | J85: Évaluations basées sur des critères flous | K85: Grilles d'évaluation standardisées et transparentes
D86: Les critères de performance du contrôle interne sont documentés et approuvés par le Conseil. | E86: Les critères de performance du contrôle interne sont-ils documentés et approuvés par le Conseil ? | F86: OUI | G86: Grille d'évaluation de performance | H86: validation formelle contournée ou ignorée | I86: Elevée | J86: Validations obligatoires contournées | K86: Contrôle aléatoire des validations obligatoires
F87: OUI | G87: Protocole de validation formelle | H87: écarts stratégiques NON identifiés ou reportés | I87: Elevée | J87: Problèmes stratégiques NON vus | K87: Revue stratégique trimestrielle par la direction
D88: Le Conseil examine régulièrement l’alignement entre les objectifs du contrôle interne et la stratégie globale. | E88: Le Conseil examine-t-il régulièrement l’alignement entre les objectifs du contrôle interne et la stratégie globale ? | F88: OUI | G88: Rapport d'alignement stratégique | H88: ajustements NON validés par les instances compétentes | I88: Moyenne | J88: Ajustements PAS validés officiellement | K88: Procédure officielle pour les ajustements
F89: OUI | G89: Proposition d'ajustements validée | H89: modifications NON documentées ou NON communiquées | I89: Moyenne | J89: Changements PAS écrits ni communiqués | K89: Journal centralisé des changements
D90: Les ajustements proposés par le Conseil sont mis en œuvre et documentés. | E90: Les ajustements proposés par le Conseil sont-ils mis en œuvre et documentés ? | F90: OUI | G90: Journal des modifications approuvées | H90: déploiement inégal selon les entités | I90: Moyenne | J90: Application différente selon les services | K90: Harmonisation inter-services des pratiques
F91: OUI | G91: Preuve de déploiement effectif | H91: anomalies récurrentes NON traitées | I91: Moyenne | J91: Problèmes récurrents NON réglés | K91: Plan d'action priorisé avec responsables désignés
C92: S’assurer que le Conseil prend des mesures appropriées lorsque des dysfonctionnements ou des lacunes dans le contrôle interne sont identifiés, y compris la mise en place de plans d’action correctifs. | D92: Les dysfonctionnements ou lacunes identifiés sont documentés et présentés au Conseil. | E92: Les dysfonctionnements ou lacunes identifiés sont-ils documentés et présentés au Conseil ? | F92: OUI | G92: Registre des anomalies identifiées | H92: classification des risques erronée ou obsolète | I92: Moyenne | J92: Risques mal classés | K92: Actualisation mensuelle de la cartographie des risques
F93: OUI | G93: Classement par niveau de risque | H93: plans d'action NON datés ou NON suivis | I93: Moyenne | J93: Plans d'action sans date précise | K93: Fiches actions avec échéances contraignantes
D94: Le Conseil valide des plans d’action correctifs pour chaque problème identifié. | E94: Le Conseil valide-t-il des plans d’action correctifs pour chaque problème identifié ? | F94: OUI | G94: Plan d'action correctif daté | H94: calendrier de résolution NON contraignant | I94: Moyenne | J94: Calendrier de résolution PAS respecté | K94: Points hebdomadaires de suivi des résolutions
F95: OUI | G95: Calendrier de résolution contraignant | H95: responsabilités mal définies ou NON assumées | I95: Moyenne | J95: Personne ne sait qui doit faire quoi | K95: Désignation claire des responsables
D96: Les responsables de la mise en œuvre des plans d’action sont clairement désignés. | E96: Les responsables de la mise en œuvre des plans d’action sont-ils clairement désignés ? | F96: OUI | G96: Désignation officielle des responsables | H96: missions mal définies ou hors périmètre | I96: Moyenne | J96: Missions PAS claires ou hors cadre | K96: Cadrage écrit des missions et périmètres
F97: OUI | G97: Fiche de mission contresignée | H97: suivi opérationnel négligé ou falsifié | I97: Moyenne | J97: Suivi bâclé ou truqué | K97: Audit aléatoire des processus de suivi
D98: Un suivi régulier des plans d’action est effectué et partagé avec le Conseil. | E98: Un suivi régulier des plans d’action est-il effectué et partagé avec le Conseil ? | F98: OUI | G98: Tableau de suivi opérationnel | H98: rapports d'état incomplets ou trompeurs | I98: Moyenne | J98: Rapports incomplets ou faux | K98: Modèles de rapports standardisés obligatoires
F99: OUI | G99: Rapport d'état hebdomadaire | H99: corrections partielles ou NON vérifiées | I99: Moyenne | J99: Corrections faites à moitié | K99: Validation externe des corrections implémentées
D100: Les résultats des actions correctives sont évalués et documentés dans les rapports du Conseil. | E100: Les résultats des actions correctives sont-ils évalués et documentés dans les rapports du Conseil ? | F100: OUI | G100: Bilan des corrections implémentées | H100: gains surestimés ou NON pérennes | I100: Moyenne | J100: Bénéfices anNONcés mais PAS réels | K100: Mesure concrète des bénéfices obtenus
...

Sheet GLOBALE
A1: Domaines | B1: Points de contrôle | C1: objectifs de contrôle | D1: criteres d'evaluation | E1: Documents Requis | F1: Questions d'evaluation | G1: Réponses | H1: Risques | I1: Criticités | J1: Consequences | K1: Recommandations
A2: Audit des applications en service | B2: Organisation | C2: S’assurer de l’existence d'un comité informatique | D2: Existence d'un comité informatique | E2: Décision de création du comité informatique signée par le DG | F2: Existe-t-il un comité informatique ? | G2: OUI | H2: Inexistence d'un comité informatique | I2: Elevée | J2: Décisions informatiques déconnectées des besoins métiers. | K2: mpliquer les métiers dans les instances de décision concernant les SI.
E3: Procès-verbal de réunion attestant de la création du comité informatique. | K3: Formaliser les besoins métiers et les traduire en exigences fonctionnelles et techniques.
D4: Le Comité est présidé par le Directeur Général | E4: PV de session du comité | F4: Le Comité est-il présidé par le Directeur Général ? | G4: NON | H4: Le Comité n'est pas présidé par le Directeur Général | I4: Moyenne | J4: Manque d'autorité et de légitimité des décisions du comité. | K4: Clarifier les rôles et responsabilités du comité de pilotage SI.
E5: Décision de nomination du Président du comité informatique signée par le Directeur Général. | K5: Documenter les décisions prises et les diffuser aux parties prenantes.
D6: Les directions utilisatrices sont représentées au sein de ce Comité | E6: Décision d'affectation des directions au comité | F6: Les directions utilisatrices sont-elles représentées au sein de ce Comité ? | G6: PAS | H6: Les directions utilisatrices ne sont pas représentées au sein de ce Comité. | I6: Elevée | J6: Systèmes inadaptés aux besoins réels des utilisateurs. | K6: Mener des études d'utilisabilité et des tests utilisateurs avant et après la mise en production.
E7: PV de session du comité | K7: Mettre en place un processus de recueil et de gestion des feedbacks utilisateurs.
D8: Les directions utilisatrices sont influentes au sein de ce Comité | E8: Procès-verbal des réunions mentionnant les contributions des directions utilisatrices | F8: Les directions utilisatrices sont-elles influentes au sein de ce Comité ? | G8: NON | H8: Les directions utilisatrices ne sont pas influentes au sein de ce Comité | I8: Faible | J8: Faible adoption par les utilisateurs et non atteinte des objectifs métiers. | K8: Accompagner les utilisateurs dans la prise en main des nouveaux systèmes.
E9: Document de gouvernance IT attestant du poids décisionnel des directions métiers | K9: Définir des indicateurs de performance (KPI) pour mesurer l'adoption et l'atteinte des objectifs.
D10: L'ordre du jour des réunions est documenté? | E10: Ordres du jour archivés des réunions du comité | F10: L'ordre du jour des réunions est-il documenté? | G10: NON | H10: Systèmes inadaptés aux besoins métiers. | I10: Elevée | J10: Pertes de temps et sujets importants non traités. | K10: Prioriser les sujets et les tâches en fonction de leur importance et de leur urgence.
E11: Procès-verbaux des réunions avec suivi des points traités | K11: Mettre en place des outils de gestion de projet et de suivi des tâches.
C12: S’assurer de l’existence d'une politique relative aux applications | D12: Il existe une politique relative aux applications au sein de l'institution | E12: Document officiel de la politique applicative | F12: Existe-t-il une politique relative aux applications au sein de l'institution? | G12: OUI | H12: Réunions inefficaces. | I12: Moyenne | J12: Coûts élevés et duplication des fonctions. | K12: Rationaliser les applications et les systèmes existants.
E13: Procès-verbal de validation par la direction générale | K13: Automatiser les tâches répétitives et chronophages.
D14: La politique est connue des utilisateurs d'applications | E14: Registre des formations suivies par les utilisateurs | F14: La politique est-elle connue des utilisateurs d'applications? | G14: OUI | H14: Gestion anarchique des applications. | I14: Elevée | J14: Problèmes de sécurité et erreurs d'utilisation. | K14: Sensibiliser les utilisateurs aux bonnes pratiques de sécurité.
E15: Attestations de connaissance de la politique signées par les utilisateurs | K15: Mettre en place des contrôles d'accès et des mécanismes d'authentification robustes.
D16: La politique est largement diffusée | E16: Plan de communication institutionnel | F16: La politique est-elle largement diffusée? | G16: OUI | H16: Non-respect de la politique. | I16: Faible | J16: Application incomplète de la politique et problèmes de conformité. | K16: Formaliser et diffuser la politique de sécurité SI.
E17: Preuves matérielles de diffusion (emails, publications intranet) | K17: Effectuer des audits réguliers pour vérifier la conformité aux normes et réglementations.
D18: La politique est mise en œuvre | E18: Rapport d'audit de conformité | F18: La politique est-elle mise en œuvre? | G18: NON | H18: Méconnaissance de la politique par une partie du personnel. | I18: Elevée | J18: Aucun impact concret sur les pratiques et les problèmes persistent. | K18: Mettre en place un plan d'action correctif pour résoudre les problèmes identifiés.
E19: Journal des contrôles effectués | K19: Suivre l'efficacité des actions correctives et ajuster si nécessaire.
D20: La politique couvre l'ensemble du cycle de vie de l’application | E20: Document décrivant le cycle de vie complet des applications | F20: La politique couvre-t-elle l'ensemble du cycle de vie de l'application? | G20: PAS | H20: La politique reste théorique. | I20: Moyenne | J20: Problèmes de sécurité et erreurs lors de certaines phases du cycle de vie de l'application. | K20: Intégrer la sécurité dès la phase de conception des applications (approche Security by Design).
E21: Procédures opérationnelles pour chaque phase du cycle | K21: Réaliser des tests de sécurité tout au long du cycle de développement.
D22: La politique favorise la responsabilisation des utilisateurs dans l'usage de leur système d’information (application) | E22: Charte d'utilisation signée par les utilisateurs | F22: La politique favorise-t-elle la responsabilisation des utilisateurs dans l'usage de leur système d'information (application)? | G22: NON | H22: La politique est incomplète et ne couvre pas toutes les étapes. | I22: Elevée | J22: Mauvaise qualité des données et pertes d'informations. | K22: Mettre en place des processus de validation et de nettoyage des données.
E23: Registre des sanctions appliquées | K23: Sauvegarder régulièrement les données et mettre en place un plan de reprise d'activité.
D24: La politique préconise l'attribution formelle de responsabilités aux utilisateurs du système (application) | E24: Fiches de poste avec responsabilités applicatives définies | F24: La politique préconise-t-elle l'attribution formelle de responsabilités aux utilisateurs du système (application)? | G24: NON | H24: Manque d'implication des utilisateurs. | I24: Faible | J24: Manque de clarté sur qui fait quoi et erreurs fréquentes. | K24: Définir clairement les rôles et responsabilités de chaque acteur.
E25: Matrice RACI officielle | K25: Documenter les processus et les procédures.
C26: S’assurer que les rôle et responsabilités des utilisateurs sont bien définis | D26: Le rôle et les responsabilités des utilisateurs vis-à-vis de l’application sont clairement identifiés | E26: Manuel des procédures utilisateurs | F26: Le rôle et les responsabilités des utilisateurs vis-à-vis de l'application sont-ils clairement identifiés? | G26: OUI | H26: Responsabilités mal définies. | I26: Elevée | J26: Difficultés à identifier les responsables en cas de problème. | K26: Mettre en place une matrice RACI (Responsible, Accountable, Consulted, Informed).
E27: Tableau des droits d'accès par profil métier | K27: Définir un processus d'escalade des problèmes.
D28: Le rôle et les responsabilités des utilisateurs vis-à-vis de l’application couvrent l’analyse des risques | E28: Rapport d'analyse des risques impliquant les utilisateurs métiers | F28: Le rôle et les responsabilités des utilisateurs vis-à-vis de l'application couvrent-ils l'analyse des risques? | G28: OUI | H28: Manque de clarté sur les rôles et responsabilités. | I28: Moyenne | J28: Mesures de sécurité non adaptées. | K28: Effectuer une analyse de risques pour identifier les menaces et les vulnérabilités.
E29: Procès-verbal de validation des risques par les responsables métiers | K29: Mettre en place des mesures de sécurité appropriées pour atténuer les risques.
D30: Le rôle et les responsabilités des utilisateurs vis-à-vis de l’application couvrent la définition des besoins de sécurité | E30: Cahier des charges sécurité co-construit avec les métiers | F30: Le rôle et les responsabilités des utilisateurs vis-à-vis de l'application couvrent-ils la définition des besoins de sécurité? | G30: OUI | H30: Absence de prise en compte des besoins de sécurité par les utilisateurs. | I30: Elevée | J30: Systèmes obsolètes. | K30: Systèmes à jour et maintenus.
E31: PV de réunion de définition des exigences de sécurité | K31: Plan de secours et de reprise après sinistre.
D32: Le rôle et les responsabilités des utilisateurs vis-à-vis de l’application couvrent la gestion des changements et des évolutions | E32: Procédure formalisée de gestion des changements | F32: Le rôle et les responsabilités des utilisateurs vis-à-vis de l'application couvrent-ils la gestion des changements et des évolutions? | G32: NON | H32: Gestion des changements et des évolutions inadaptée aux besoins. | I32: Faible | J32: Difficultés à maintenir l'application et insatisfaction des utilisateurs. | K32: Définir des objectifs de sécurité clairs et mesurables.
E33: Registre des demandes d'évolution initiées par les métiers | K33: Suivre et évaluer régulièrement la performance de la sécurité.
D34: Le rôle et les responsabilités des utilisateurs vis-à-vis de l’application couvrent l’administration de l’application | E34: Procédures d'administration déléguée aux utilisateurs | F34: Le rôle et les responsabilités des utilisateurs vis-à-vis de l'application couvrent-ils l'administration de l'application? | G34: PAS | H34: Administration de l'application déconnectée des besoins des utilisateurs. | I34: Elevée | J34: Difficulté à maintenir l'application et insatisfaction des utilisateurs. | K34: Séparer les tâches critiques pour éviter les conflits d'intérêts et les fraudes.
E35: Journal des opérations administratives réalisées par les métiers | K35: Former le personnel sur les politiques et procédures de sécurité.
C36: S’assurer qu’une analyse des risques a été réalisée | D36: Une analyse des risques spécifique à l’application a été réalisée | E36: Rapport complet d'analyse des risques applicative | F36: Une analyse des risques spécifique à l'application a-t-elle été réalisée? | G36: NON | H36: Mauvaise identification des risques pour l'application. | I36: Moyenne | J36: Mauvaise identification des risques pour l'application. | K36: Définir un niveau de sécurité cible et allouer les ressources nécessaires.
E37: Grille d'évaluation des risques spécifique à l'application | K37: Mettre en œuvre des contrôles de sécurité pour surveiller et protéger les systèmes.
D38: L'analyse des risques a débouché sur la définition des besoins de sécurité | E38: Document de synthèse des besoins de sécurité | F38: L'analyse des risques a-t-elle débouché sur la définition des besoins de sécurité? | G38: NON | H38: Définition des besoins de sécurité incomplète ou inadaptée. | I38: Elevée | J38: Définition des besoins de sécurité incomplète ou inadéquate. | K38: Documenter la méthodologie utilisée pour l'analyse et la gestion des risques.
E39: PV de validation des exigences par la direction | K39: Former le personnel sur la méthodologie et les outils utilisés.
D40: La méthode d'analyse des risques est définie et documentée (ex: EBIOS Risk Manager, MEHARI)? | E40: Manuel méthodologique d'analyse des risques (EBIOS/MEHARI) | F40: La méthode d'analyse des risques est-elle définie et documentée (ex: EBIOS Risk Manager, MEHARI)? | G40: OUI | H40: Méthode d'analyse des risques non standardisée et non documentée. | I40: Faible | J40: Méthode d'analyse des risques non standardisée et non documentée. | K40: Prendre en compte la confidentialité, l'intégrité et la disponibilité des données lors de la conception et de la mise en œuvre des systèmes.
E41: Procédure d'évaluation des risques documentée | K41: Mettre en place des mesures pour protéger les données contre les accès non autorisés, les modifications et les pertes.
D42: Les risques identifiés sont classifiés et priorisés? | E42: Matrice de criticité des risques classés | F42: Les risques identifiés sont-ils classifiés et priorisés? | G42: OUI | H42: Risques mal identifiés et non priorisés. | I42: Elevée | J42: Risques mal identifiés et non priorisés. | K42: Effectuer une analyse de risques approfondie et prioriser les risques en fonction de leur impact potentiel.
E43: Plan de traitement des risques priorisés | K43: Mettre en place un processus de gestion des risques.
D44: Les mesures de sécurité mises en place sont proportionnées aux risques identifiés? | E44: Rapport de mise en œuvre des mesures de sécurité | F44: Les mesures de sécurité mises en place sont-elles proportionnées aux risques identifiés? | G44: OUI | H44: Mesures de sécurité inadaptées aux risques identifiés. | I44: Moyenne | J44: Mesures de sécurité inadaptées aux risques identifiés. | K44: Adopter des mesures de sécurité appropriées et proportionnées aux risques identifiés.
E45: Évaluation du niveau de couverture des risques | K45: Effectuer des tests de pénétration et des audits de sécurité réguliers.
