Workbook

Sheet synthèse
B3: Synthèse Numérique
B5: N° | C5: Domaines | D5: Total OUI | E5: Total NON | F5: Total PAS | G5: Total | H5: Score
B6: 1 | C6: COSO | D6: =COUNTIF(COSO!F2:F401,"oui") -> 285 | E6: =COUNTIF(COSO!F2:F401,"non") -> 45 | F6: =COUNTIF(COSO!F2:F401,"pas") -> 70 | G6: =SUM(D6:F6) -> 400 | H6: =D6/G6 -> 0.7125
B7: 2 | C7: Application service | D7: =COUNTIF('4,1-App_serv'!F2:F161,"oui") -> 104 | E7: =COUNTIF('4,1-App_serv'!F2:F161,"non") -> 18 | F7: =COUNTIF('4,1-App_serv'!F2:F161,"pas") -> 34 | G7: =SUM(D7:F7) -> 156 | H7: =D7/G7 -> 0.66666667
B8: 3 | C8: Fonction informatique | D8: =COUNTIF('4,2_fonction_informatiq'!F3:F222,"oui") -> 68 | E8: =COUNTIF('4,2_fonction_informatiq'!F3:F222,"non") -> 84 | F8: =COUNTIF('4,2_fonction_informatiq'!F3:F222,"pas") -> 68 | G8: =SUM(D8:F8) -> 220 | H8: =D8/G8 -> 0.30909091
B9: 4 | C9: contrôle des projets | D9: =COUNTIF('4,3-contrôle-des-projets-inf'!F3:F647,"oui") -> 493 | E9: =COUNTIF('4,3-contrôle-des-projets-inf'!F3:F647,"non") -> 151 | F9: =COUNTIF('4,3-contrôle-des-projets-inf'!F3:F647,"pas") -> 0 | G9: =SUM(D9:F9) -> 644 | H9: =D9/G9 -> 0.76552795
B10: 5 | C10: audit du support | D10: =COUNTIF('4.4 audit du support ... '!F3:F172,"oui") -> 137 | E10: =COUNTIF('4.4 audit du support ... '!F3:F172,"non") -> 33 | F10: =COUNTIF('4.4 audit du support ... '!F3:F172,"pas") -> 0 | G10: =SUM(D10:F10) -> 170 | H10: =D10/G10 -> 0.80588235
B11: 6 | C11: sécurité informatique | D11: =COUNTIF('4.5 sécurité informatique'!F3:F345,"oui") -> 275 | E11: =COUNTIF('4.5 sécurité informatique'!F3:F345,"non") -> 68 | F11: =COUNTIF('4.5 sécurité informatique'!F3:F345,"pas") -> 0 | G11: =SUM(D11:F11) -> 343 | H11: =D11/G11 -> 0.80174927
B12: Total | D12: =SUM(D6:D11) -> 1362 | E12: =SUM(E6:E11) -> 399 | F12: =SUM(F6:F11) -> 172 | G12: =SUM(D12:F12) -> 1933 | H12: =D12/G12 -> 0.70460424

Sheet COSO
A1: Domaine | B1: Point de contrôle | C1: Objectis de contrôle | D1: Critères d'évaluations | E1: Question d’Évaluation | F1: Réponses | G1: Documents Requis | H1: Risques | I1: Criticités | J1: conséquences | K1: recommandation
A2: Environnement de contrôle | B2: Engagement envers l'intégrité et les valeurs éthiques | C2: S’assurer que l'organisation dispose d'une charte éthique formelle qui couvre l'ensemble des pratiques professionnelles et des interactions au sein de l'organisation, y compris les activités liées aux systèmes d'information. | D2: La charte éthique est rédigée dans un langage clair et compréhensible. | E2: La charte éthique est-elle rédigée dans un langage accessible à tous ? | F2: pas | G2: Charte éthique | H2: Mauvaise compréhension des principes | I2: Élevée | J2: Risques non gérés
D3: La charte est officiellement approuvée par la direction. | E3: La charte a-t-elle reçu l'approbation officielle de la direction ? | F3: pas | G3: Document d'approbation | H3: Charte non valide | I3: Élevée | J3: Non-identification des faiblesses
D4: Les valeurs et principes éthiques sont explicitement définis. | E4: Les valeurs éthiques sont-elles clairement énoncées dans la charte ? | F4: pas | G4: Charte éthique | H4: Ambiguïté sur les valeurs | I4: Élevée | J4: Pertes de connaissances
D5: La charte est alignée sur les normes légales et réglementaires. | E5: La charte respecte-t-elle toutes les normes légales en vigueur ? | F5: pas | G5: Normes légales applicables | H5: Non-conformité légale | I5: Élevée | J5: Non-conformité
D6: =COUNTIF(COSO!F2:F401,"oui") -> 285 | E6: La charte est-elle révisée régulièrement pour rester à jour ? | F6: pas | G6: Procès-verbal de validation | H6: Inadéquation aux évolutions | I6: Élevée | J6: Non-adhésion aux pratiques
C7: Vérifer que des mécanismes existent pour garantir que tous les acteurs (employés, partenaires, prestataires) respectent cette charte éthique dans leurs activités professionnelles, y compris dans leur utilisation des systèmes d'information | D7: La charte est disponible sur l’intranet ou un support accessible. | E7: La charte est-elle facilement accessible pour tous les employés ? | F7: pas | G7: Accès intranet | H7: Manque de sensibilisation | I7: Moyen | J7: Pertes de connaissances non gérées
D8: Des campagnes de communication régulières sont organisées. | E8: Des communications sur la charte sont-elles diffusées régulièrement ? | F8: pas | G8: Planning des communications | H8: Faible sensibilisation | I8: Moyen | J8: Non-identification des faiblesses
D9: Les nouveaux collaborateurs reçoivent une copie de la charte. | E9: Les nouveaux employés reçoivent-ils une copie de la charte éthique ? | F9: pas | G9: Procédure d'intégration | H9: Ignorance des valeurs éthiques | I9: Élevée | J9: Crises mal gérées
D10: Des affiches ou supports visuels rappellent les principes de la charte. | E10: Des supports visuels sont-ils utilisés pour rappeler la charte ? | F10: pas | G10: Exemples de supports visuels | H10: Non-respect des principes | I10: Moyen | J10: Non-conformité
D11: Un système de confirmation de lecture est mis en place. | E11: Un système de confirmation de lecture de la charte est-il en place ? | F11: pas | G11: Procédure de confirmation | H11: Non-lecture des documents | I11: Moyen | J11: Non-adhésion aux pratiques
C12: S’assurer que des actions de sensibilisation, telles que des formations régulières, sont mises en place pour garantir que tous les employés et intervenants comprennent et appliquent les principes éthiques dans leurs interactions avec les systèmes d'information | D12: Un calendrier de révision de la charte est défini et respecté. | E12: Existe-t-il un calendrier pour la révision de la charte ? | F12: pas | G12: Calendrier de révision | H12: Révisions manquées | I12: Élevée | J12: Non-réactivité lors de crises
D13: Les mises à jour sont documentées et communiquées. | E13: Les mises à jour de la charte sont-elles documentées ? | F13: non | G13: Registre des mises à jour | H13: Manque de transparence | I13: Moyen | J13: Non-identification des faiblesses
D14: Les retours d’expérience et évolutions légales sont pris en compte. | E14: Les retours et évolutions sont-ils intégrés dans la charte ? | F14: pas | G14: Rapports d'évaluation | H14: Inadaptation aux nouvelles réalités | I14: Élevée | J14: Relations clients mal gérées
D15: La direction valide chaque mise à jour avant diffusion. | E15: La direction valide-t-elle chaque mise à jour de la charte ? | F15: pas | G15: Document d'approbation | H15: Mises à jour non autorisées | I15: Élevée | J15: Non-conformité
D16: Un historique des versions de la charte est conservé. | E16: Un historique des versions précédentes de la charte est-il maintenu ? | F16: pas | G16: Registre des versions | H16: Difficulté à retracer les modifications | I16: Moyen | J16: Non-adhésion aux pratiques
C17: S’assurer que l'organisation dispose d'un mécanisme de suivi et de gestion des violations éthiques, permettant de détecter, traiter et sanctionner tout comportement contraire à la charte éthique, y compris dans le cadre des activités liées aux systèmes d'information | D17: Des sessions de formation obligatoires sont organisées. | E17: Des formations obligatoires sur la charte sont-elles organisées ? | F17: pas | G17: Planning de formation | H17: Non-formation des employés | I17: Élevée | J17: Réclamations non traitées
D18: Les formations sont adaptées aux différents niveaux hiérarchiques. | E18: Les formations sont-elles personnalisées selon les niveaux hiérarchiques ? | F18: pas | G18: Matériel de formation adapté | H18: Inefficacité des formations | I18: Moyen | J18: Non-identification des faiblesses
D19: Les nouveaux employés suivent une formation dès leur arrivée. | E19: Les nouveaux employés reçoivent-ils une formation à leur arrivée ? | F19: pas | G19: Procédure d'intégration | H19: Ignorance des valeurs éthiques | I19: Élevée | J19: Partenariats mal gérés
D20: Des supports pédagogiques (vidéos, quiz, etc.) sont disponibles. | E20: Des supports pédagogiques sont-ils fournis pour la formation ? | F20: pas | G20: Supports pédagogiques | H20: Manque de ressources pédagogiques | I20: Moyen | J20: Non-conformité
D21: L’efficacité des formations est évaluée via des tests. | E21: Des évaluations de l’efficacité des formations sont-elles réalisées ? | F21: pas | G21: Résultats des tests | H21: Manque d'évaluation des compétences | I21: Moyen | J21: Non-respect des bonnes pratiques
C22: S’assurer qu’un mécanisme de signalement des violations éthiques est en place. | D22: Un canal de signalement sécurisé et anonyme est accessible. | E22: Un canal de signalement est-il disponible pour les employés ? | F22: pas | G22: Procédure de signalement | H22: Risque de non-signalement | I22: Élevée | J22: Risques non gérés
D23: Les procédures de signalement sont clairement expliquées. | E23: Les procédures de signalement sont-elles clairement définies ? | F23: pas | G23: Documentation des procédures | H23: Ambiguïté sur le processus | I23: Élevée | J23: Non-identification des faiblesses
D24: Les signalements sont traités dans des délais définis. | E24: Les signalements sont-ils traités dans un délai établi ? | F24: pas | G24: Procédures de traitement | H24: Retards dans le traitement | I24: Élevée | J24: Ressources humaines mal gérées
D25: Des mesures de protection des lanceurs d’alerte sont mises en place. | E25: Des protections sont-elles en place pour les lanceurs d’alerte ? | F25: pas | G25: Politique de protection | H25: Représailles contre les lanceurs d’alerte | I25: Élevée | J25: Non-conformité
D26: Les résultats des investigations sont communiqués de manière transparente. | E26: Les résultats des enquêtes sont-ils partagés de manière transparente ? | F26: pas | G26: Rapports d'investigation | H26: Manque de transparence | I26: Élevée | J26: Non-respect des bonnes pratiques
B27: Le Conseil fait preuve d’indépendance vis-à-vis du management | C27: S’assurer que le Conseil est composé de membres indépendants du management, avec une structure de gouvernance claire garantissant cette indépendance. | D27: La majorité des membres du Conseil sont indépendants. | E27: La majorité des membres du Conseil sont-ils indépendants du management ? | F27: oui | G27: Liste des membres du Conseil | H27: Conflits d'intérêts | I27: Élevée | J27: Risques non gérés
D28: Le Conseil dispose d’un comité dédié au contrôle interne. | E28: Un comité de contrôle interne existe-t-il au sein du Conseil ? | F28: pas | G28: Charte du comité | H28: Manque de supervision | I28: Élevée | J28: Non-identification des faiblesses
D29: Les membres participent activement aux réunions et décisions. | E29: Les membres du Conseil participent-ils activement aux réunions ? | F29: pas | G29: Procès-verbaux des réunions | H29: Manque d'engagement | I29: Moyen | J29: Finances mal gérées
D30: Des évaluations régulières de l’indépendance du Conseil sont réalisées. | E30: Des évaluations de l'indépendance sont-elles effectuées régulièrement ? | F30: pas | G30: Rapports d'évaluation | H30: Perte d'indépendance | I30: Élevée | J30: Non-conformité
D31: Le Conseil a un accès direct aux auditeurs internes et externes. | E31: Le Conseil a-t-il accès direct aux auditeurs ? | F31: non | G31: Politique d'accès | H31: Manque d'information | I31: Élevée | J31: Non-respect des bonnes pratiques
C32: Vérifer que le Conseil dispose des ressources et des informations nécessaires pour surveiller eﬀicacement la mise en place et le bon fonctionnement du dispositif de contrôle interne | D32: Des rapports détaillés sont présentés au moins trimestriellement. | E32: Des rapports sont-ils fournis au Conseil trimestriellement ? | F32: pas | G32: Rapports trimestriels | H32: Incompréhension des problèmes | I32: Élevée | J32: Risques non gérés
D33: Les rapports incluent une analyse des risques majeurs. | E33: Les rapports contiennent-ils une analyse des risques ? | F33: oui | G33: Rapports d'audit | H33: Risques non identifiés | I33: Élevée | J33: Non-identification des faiblesses
D34: Les membres du Conseil peuvent poser des questions et obtenir des clarifications. | E34: Les membres peuvent-ils poser des questions sur les rapports ? | F34: oui | G34: Procès-verbaux des réunions | H34: Manque de clarté | I34: Moyen | J34: Achats mal gérés
D35: Les rapports sont préparés par des équipes indépendantes. | E35: Les rapports sont-ils préparés par des équipes indépendantes ? | F35: non | G35: Documents des rapports | H35: Partialité dans les rapports | I35: Élevée | J35: Non-conformité
D36: Un suivi des actions recommandées est intégré dans les rapports suivants. | E36: Un suivi est-il effectué sur les recommandations passées ? | F36: oui | G36: Rapports de suivi | H36: Recommandations non mises en œuvre | I36: Élevée | J36: Non-respect des bonnes pratiques
C37: S’assurer que le Conseil reçoit régulièrement des rapports détaillés sur l’eﬀicacité du dispositif de contrôle interne et qu'il est impliqué dans l’évaluation des résultats des audits internes | D37: Le Conseil participe à la définition des priorités en matière de risques. | E37: Le Conseil est-il impliqué dans la définition des priorités de risque ? | F37: oui | G37: Procès-verbaux de réunions | H37: Priorités mal définies | I37: Élevée | J37: Risques non gérés
D38: Les résultats des audits internes sont présentés et discutés. | E38: Les résultats des audits internes sont-ils discutés en Conseil ? | F38: oui | G38: Rapports d'audit | H38: Non-considération des problèmes | I38: Élevée | J38: Non-identification des faiblesses
D39: Le Conseil valide le plan d’audit interne annuel. | E39: Le plan d'audit interne est-il validé par le Conseil ? | F39: oui | G39: Plan d'audit | H39: Audits non conformes | I39: Élevée | J39: Non-détection des faiblesses
D40: Des indicateurs de performance des audits internes sont partagés. | E40: Des KPI sur les audits internes sont-ils partagés avec le Conseil ? | F40: oui | G40: Rapports de performance | H40: Mauvaise évaluation des performances | I40: Moyen | J40: Stratégies inadaptées
D41: Le Conseil formule des recommandations pour améliorer les audits. | E41: Le Conseil formule-t-il des recommandations pour les audits ? | F41: oui | G41: Procès-verbaux des réunions | H41: Manque d'amélioration des audits | I41: Élevée | J41: Efficacité des audits compromise
C42: Vérifer que le Conseil joue un rôle actif dans la défnition des objectifs et des critères de performance du contrôle interne, et qu’il veille à leur alignement avec les objectifs stratégiques de l’organisation. | D42: Des critères d’évaluation clairs et objectifs sont définis. | E42: Des critères d'évaluation sont-ils clairement définis ? | F42: Oui | G42: Document d'évaluation | H42: Évaluations subjectives | I42: Élevée | J42: Mauvaise prise de décision
D43: L’évaluation est réalisée au moins une fois par an. | E43: L'évaluation est-elle effectuée annuellement ? | F43: pas | G43: Calendrier d'évaluation | H43: Évaluations manquées | I43: Élevée | J43: Non-amélioration des processus
D44: Les résultats de l’évaluation sont discutés en séance du Conseil. | E44: Les résultats sont-ils discutés en séance ? | F44: Oui | G44: Procès-verbaux des réunions | H44: Non-considération des résultats | I44: Élevée | J44: Décisions basées sur des informations incomplètes
D45: Des objectifs d’amélioration sont fixés en fonction des résultats. | E45: Des objectifs d'amélioration sont-ils établis ? | F45: Oui | G45: Document d'objectifs | H45: Pas d'orientation pour l'amélioration | I45: Élevée | J45: Manque de progrès
D46: La rémunération des responsables est liée à leur performance. | E46: La rémunération est-elle liée aux performances ? | F46: pas | G46: Politique de rémunération | H46: Manque d'incitation à la performance | I46: Élevée | J46: Faible motivation
C47: S’assurer que le Conseil prend des mesures appropriées lorsque des dysfonctionnements ou des lacunes dans le contrôle interne sont identifés, y compris la mise en place de plans d’action correctifs | D47: Les failles identifiées sont documentées et classées par priorité. | E47: Les failles sont-elles documentées et priorisées ? | F47: Oui | G47: Registre des failles | H47: Non-traitement des failles | I47: Élevée | J47: Répétition des erreurs
D48: Le Conseil valide les plans d’action correctifs proposés. | E48: Le Conseil valide-t-il les plans d'action correctifs ? | F48: pas | G48: Procès-verbaux de validation | H48: Plans non approuvés | I48: Élevée | J48: Non-résolution des problèmes
D49: Un suivi régulier de la mise en œuvre des mesures est assuré. | E49: Un suivi est-il effectué sur la mise en œuvre des mesures ? | F49: Oui | G49: Rapport de suivi | H49: Non-application des mesures | I49: Élevée | J49: Faiblesse persistante
D50: Les résultats des actions correctives sont communiqués au Conseil. | E50: Les résultats sont-ils communiqués au Conseil ? | F50: Oui | G50: Rapports d'action corrective | H50: Manque d'information | I50: Élevée | J50: Non-résolution des anomalies
D51: Des leçons apprises sont tirées pour éviter la répétition des failles. | E51: Des leçons sont-elles tirées après les incidents ? | F51: Oui | G51: Document de leçons apprises | H51: Répétition des erreurs | I51: Élevée | J51: Impact sur l'efficacité
B52: Structures, autorités et responsabilités | C52: S’assurer que la structure organisationnelle est clairement défnie, incluant les rattachements hiérarchiques, les rôles, les responsabilités et les pouvoirs de chaque collaborateur. | D52: La structure organisationnelle est documentée et accessible. | E52: La structure est-elle documentée et accessible ? | F52: non | G52: Organigramme | H52: Manque de clarté | I52: Moyen | J52: Confusion sur les rôles
D53: Les rôles et responsabilités sont clairement attribués. | E53: Les responsabilités sont-elles clairement définies ? | F53: Oui | G53: Document de rôles | H53: Ambiguïté dans les responsabilités | I53: Élevée | J53: Non-respect des tâches
D54: La structure est revue régulièrement pour s’adapter aux besoins. | E54: La structure est-elle revue régulièrement ? | F54: pas | G54: Rapport de révision | H54: Inadéquation aux besoins | I54: Élevée | J54: Inefficacité organisationnelle
D55: Toute modification de la structure est approuvée par la direction. | E55: Les modifications sont-elles approuvées par la direction ? | F55: Oui | G55: Procès-verbaux d'approbation | H55: Changements non contrôlés | I55: Élevée | J55: Dysfonctionnements
D56: Les collaborateurs comprennent bien leur rôle dans la structure. | E56: Les employés comprennent-ils clairement leurs rôles ? | F56: Oui | G56: Rapports d'enquête | H56: Confusion sur les rôles | I56: Élevée | J56: Non-productivité
C57: Vérifer que les responsabilités et laes pouvoirs sont attribués de manière appropriée, en fonction des compétences et des objectifs stratégiques de l’organisation | D57: Un processus de recrutement structuré et transparent est en place. | E57: Un processus de recrutement est-il bien défini ? | F57: Oui | G57: Politique de recrutement | H57: Recrutement biaisé | I57: Élevée | J57: Mauvaise adéquation des candidats
D58: Les critères de sélection sont clairement définis et communiqués. | E58: Les critères de sélection sont-ils communiqués aux candidats ? | F58: Oui | G58: Document de critères de sélection | H58: Manque de transparence | I58: Élevée | J58: Candidats inadaptés
D59: Les nouveaux employés reçoivent une formation adéquate. | E59: Les nouveaux employés reçoivent-ils une formation appropriée ? | F59: pas | G59: Programme de formation | H59: Manque de préparation | I59: Élevée | J59: Faible performance initiale
D60: Des programmes de développement des compétences sont proposés. | E60: Des programmes de développement sont-ils offerts ? | F60: pas | G60: Catalogue de formation | H60: Manque d'opportunités de développement | I60: Moyen | J60: Faible évolution professionnelle
D61: Des évaluations régulières des performances sont réalisées. | E61: Des évaluations de performance sont-elles effectuées régulièrement ? | F61: pas | G61: Planning d'évaluation | H61: Non-évaluation des performances | I61: Élevée | J61: Non-identification des problèmes
C62: S’assurer que la structure organisationnelle est régulièrement revue et mise à jour pour tenir compte des changements dans l’environnement interne ou externe de l’organisation. | D62: Les responsabilités des employés sont formalisées et documentées. | E62: Les responsabilités sont-elles documentées ? | F62: Oui | G62: Document de responsabilités | H62: Ambiguïté des tâches | I62: Élevée | J62: Non-respect des rôles
D63: Des mécanismes existent pour évaluer la conformité des employés. | E63: Existe-t-il des mécanismes d'évaluation de la conformité ? | F63: Oui | G63: Procédures de conformité | H63: Non-conformité non détectée | I63: Élevée | J63: Risques accrus
D64: Les employés reçoivent une formation continue sur leurs responsabilités. | E64: Une formation continue est-elle fournie ? | F64: pas | G64: Programme de formation continue | H64: Manque de mise à jour des connaissances | I64: Élevée | J64: Non-respect des responsabilités
D65: Des mesures correctives sont prises en cas de non-respect des responsabilités. | E65: Des mesures sont-elles appliquées en cas de non-respect ? | F65: pas | G65: Registre des mesures correctives | H65: Non-application des mesures | I65: Élevée | J65: Répétition des erreurs
D66: Les responsabilités en matière de sécurité des systèmes d’information sont claires. | E66: Les responsabilités en sécurité sont-elles définies ? | F66: Oui | G66: Politique de sécurité | H66: Ambiguïté sur les rôles | I66: Élevée | J66: Risques de sécurité
C67: Vérifer que le management reçoit l’approbation du Conseil pour les modifcations de la structure organisationnelle, afn d’assurer une supervision adéquate des changements importants. | D67: Le risque de fraude est inclus dans l’évaluation globale des risques. | E67: Le risque de fraude est-il évalué ? | F67: Oui | G67: Rapport d'évaluation des risques | H67: Sous-estimation des risques de fraude | I67: Élevée | J67: Perte financière
D68: Des méthodologies spécifiques sont utilisées pour évaluer la fraude. | E68: Des méthodologies spécifiques sont-elles appliquées ? | F68: pas | G68: Document de méthodologie | H68: Évaluation inexacte | I68: Élevée | J68: Risques non identifiés
D69: Des responsables sont désignés pour gérer le risque de fraude. | E69: Des responsables pour la fraude sont-ils nommés ? | F69: non | G69: Liste des responsables | H69: Absence de responsabilité | I69: Élevée | J69: Manque de contrôle
D70: Des mécanismes de surveillance spécifiques existent pour détecter la fraude. | E70: Des mécanismes de détection de fraude sont-ils en place ? | F70: non | G70: Politique de surveillance | H70: Fraude non détectée | I70: Élevée | J70: Perte de confiance
D71: Le Conseil d’Administration est informé des risques de fraude identifiés. | E71: Le Conseil est-il informé des risques de fraude ? | F71: Oui | G71: Rapports au Conseil | H71: Manque d'information | I71: Élevée | J71: Non-détection des problèmes
C72: S’assurer que des mécanismes sont en place pour communiquer la structure organisationnelle à tous les collaborateurs, afn qu'ils comprennent clairement leurs rôles et leurs responsabilités. | D72: Les changements susceptibles d’affecter le contrôle interne sont identifiés. | E72: Les changements sont-ils identifiés ? | F72: non | G72: Registre des changements | H72: Risques non identifiés | I72: Élevée | J72: Non-adaptation aux évolutions
D73: Ces changements sont évalués de manière formelle. | E73: Les changements sont-ils évalués formellement ? | F73: non | G73: Rapport d'évaluation des changements | H73: Évaluation incomplète | I73: Élevée | J73: Impact sur le contrôle interne
D74: Les responsables du contrôle interne participent à l’évaluation des changements. | E74: Les responsables participent-ils à l’évaluation ? | F74: Oui | G74: Procès-verbaux de réunions | H74: Manque d'implication | I74: Élevée | J74: Non-adaptation des contrôles
D75: Des plans d’adaptation du contrôle interne sont mis en place. | E75: Des plans d'adaptation existent-ils ? | F75: non | G75: Plans d'adaptation | H75: Plans non approuvés | I75: Élevée | J75: Faiblesse des contrôles internes
D76: La direction et le Conseil valident les mesures liées aux changements. | E76: Les mesures sont-elles validées par la direction et le Conseil ? | F76: Oui | G76: Procès-verbaux de validation | H76: Manque de contrôle | I76: Élevée | J76: Non-résolution des problèmes
B77: Compétences des individus | C77: S’assurer que l’organisation dispose de processus clairs et formalisés pour attirer des talents qualifés dans les domaines nécessaires à son fonctionnement, y compris pour les systèmes d’information. | D77: Les risques stratégiques et opérationnels sont clairement identifiés. | E77: Les risques sont-ils clairement identifiés ? | F77: non | G77: Registre des risques | H77: Risques non identifiés | I77: Élevée | J77: Non-détection des menaces
D78: L’évaluation des risques est un processus continu. | E78: L'évaluation est-elle continue ? | F78: non | G78: Politique d'évaluation des risques | H78: Évaluations ponctuelles | I78: Élevée | J78: Risques non actualisés
D79: Les risques sont hiérarchisés en fonction de leur probabilité et impact. | E79: Les risques sont-ils hiérarchisés ? | F79: Oui | G79: Matrice de risque | H79: Priorisation inappropriée | I79: Élevée | J79: Non-prise en compte des priorités
D80: Des plans d’atténuation des risques sont mis en place. | E80: Des plans d'atténuation existent-ils ? | F80: non | G80: Plans d'atténuation | H80: Plans non appliqués | I80: Élevée | J80: Risques non gérés
D81: Les résultats de l’évaluation des risques sont documentés et communiqués. | E81: Les résultats sont-ils documentés et communiqués ? | F81: Oui | G81: Rapports d'évaluation | H81: Manque de transparence | I81: Élevée | J81: Mauvaise gestion des risques
C82: Vérifer que l’organisation met en place des programmes de formation continue pour ses collaborateurs, en particulier dans les domaines stratégiques comme la gestion des systèmesd'information et la cybersécurité | D82: Les activités de contrôle sont alignées sur les risques identifiés. | E82: Les activités de contrôle sont-elles alignées ? | F82: pas | G82: Procédures de contrôle | H82: Activités inadaptées | I82: Élevée | J82: Efficacité compromise
D83: L’efficacité des activités de contrôle est évaluée régulièrement. | E83: L'efficacité est-elle évaluée régulièrement ? | F83: pas | G83: Rapports d'efficacité | H83: Évaluations manquées | I83: Élevée | J83: Faiblesse des contrôles
D84: Les activités de contrôle sont intégrées aux processus de l’organisation. | E84: Les activités sont-elles intégrées ? | F84: Oui | G84: Document d'intégration | H84: Manque de cohérence | I84: Élevée | J84: Non-synergie dans les processus
D85: Les activités de contrôle évoluent en fonction des risques. | E85: Les activités évoluent-elles en fonction des risques ? | F85: non | G85: Rapport d'évolution des contrôles | H85: Activités stagnantes | I85: Élevée | J85: Risques non gérés
D86: Les responsabilités des acteurs du contrôle interne sont clairement définies. | E86: Les responsabilités sont-elles définies ? | F86: Oui | G86: Document de responsabilités | H86: Ambiguïté des rôles | I86: Élevée | J86: Non-respect des responsabilités
C87: S’assurer que des mécanismes de fdélisation des talents sont en place, tels que des parcours de carrière, des avantages compétitifs et des opportunités de développement personnel, pour encourager les collaborateurs à rester au sein de l’organisation | D87: Des mécanismes existent pour collecter des informations fiables. | E87: Des mécanismes sont-ils en place pour la collecte d'informations ? | F87: Oui | G87: Procédures de collecte | H87: Manque de fiabilité | I87: Élevée | J87: Données inexactes
D88: Les informations de contrôle interne sont complètes et exactes. | E88: Les informations sont-elles complètes et exactes ? | F88: non | G88: Rapports de contrôle | H88: Informations incomplètes | I88: Élevée | J88: Mauvaise prise de décision
D89: Les informations sont accessibles en temps opportun. | E89: Les informations sont-elles accessibles à temps ? | F89: non | G89: Politique d'accès | H89: Retards d'accès | I89: Élevée | J89: Non-réactivité
D90: Les systèmes d’information permettent une communication efficace. | E90: Les systèmes permettent-ils une communication efficace ? | F90: Oui | G90: Analyse des systèmes | H90: Manque de communication | I90: Élevée | J90: Difficultés dans la coordination
D91: Les données sensibles sont protégées et accessibles uniquement aux personnes autorisées. | E91: Les données sensibles sont-elles protégées ? | F91: Oui | G91: Politique de sécurité des données | H91: Risques de fuites | I91: Élevée | J91: Non-conformité aux normes de sécurité
C92: Vérifer que des évaluations régulières de la performance des collaborateurs sont menées, avec des retours constructifs et des opportunités de développement, afn d’assurer leur progression professionnelle. | D92: Un processus structuré de surveillance du contrôle interne est en place. | E92: Un processus de surveillance est-il en place ? | F92: Oui | G92: Politique de surveillance | H92: Absence de surveillance | I92: Élevée | J92: Risques non détectés
D93: Des auto-évaluations sont effectuées régulièrement par les responsables. | E93: Des auto-évaluations sont-elles réalisées régulièrement ? | F93: pas | G93: Rapports d'auto-évaluation | H93: Évaluations manquées | I93: Élevée | J93: Non-identification des problèmes
D94: Des audits internes indépendants sont réalisés périodiquement. | E94: Des audits internes sont-ils réalisés ? | F94: Oui | G94: Rapports d'audit | H94: Absence d'audits | I94: Élevée | J94: Non-detection des anomalies
D95: Les résultats des évaluations internes sont documentés et analysés. | E95: Les résultats sont-ils documentés et analysés ? | F95: Oui | G95: Rapports d'évaluation | H95: Manque d'analyse | I95: Élevée | J95: Non-amélioration des processus
D96: Des mesures correctives sont mises en œuvre suite aux évaluations. | E96: Des mesures correctives sont-elles appliquées ? | F96: Oui | G96: Registre des mesures correctives | H96: Non-application des mesures | I96: Élevée | J96: Répétition des erreurs
C97: S’assurer que les processus d’attraction, de formation et de fdélisation des talents sont alignés avec les objectifs stratégiques de l’organisation, en garantissant qu'ils contribuent à la performance globale. | D97: Des canaux de communication existent pour signaler les dysfonctionnements. | E97: Des canaux de communication existent-ils ? | F97: Oui | G97: Politique de communication | H97: Manque de signalement | I97: Élevée | J97: Problèmes non résolus
D98: Les employés sont informés de leur rôle dans le processus de contrôle. | E98: Les employés comprennent-ils leur rôle ? | F98: Oui | G98: Documentation de formation | H98: Manque de clarté | I98: Élevée | J98: Non-respect des procédures
D99: Des sessions de sensibilisation à la communication interne sont organisées. | E99: Des sessions de sensibilisation sont-elles organisées ? | F99: Oui | G99: Planning de sensibilisation | H99: Manque de formation | I99: Élevée | J99: Mauvaise communication
D100: Des rapports périodiques sur l’état du contrôle interne sont produits. | E100: Des rapports sont-ils produits régulièrement ? | F100: Oui | G100: Rapports de contrôle interne | H100: Manque de rapports | I100: Élevée | J100: Non-suivi des contrôles
...

Sheet 4,1-App_serv
A1: Domaine | B1: Points de Contrôle | C1: Objectifs de Contrôle | D1: Critère d’Évaluation | E1: Question d’Évaluation | F1: Réponses | G1: Documents Requis | H1: Risques | I1: Criticités | J1: Conséquences
A2: Application en service | B2: Organisation | C2: S’assurer de l’existence d'un comité informatique | D2: Existence d'un comité informatique | E2: Existe-t-il un comité informatique ? | F2: oui | G2: Charte du comité informatique, liste des membres, procès-verbaux des réunions | H2: Absence de gouvernance claire | I2: Élevé | J2: Décisions incohérentes et manque de coordination
D3: Le Comité est présidé par le Directeur Général | E3: Le comité est-il présidé par le Directeur Général ? | F3: oui | G3: Document de nomination du Directeur Général, procès-verbaux des réunions | H3: Manque de leadership dans la prise de décisions stratégiques | I3: Élevé | J3: Retards et décisions inefficaces
D4: Les directions utilisatrices sont représentées au sein de ce Comité | E4: Les directions utilisatrices sont-elles représentées au sein du comité ? | F4: oui | G4: Liste des membres du comité, organigramme | H4: Mauvaise représentation des parties prenantes | I4: Élevé | J4: Conflits d'intérêts et mauvaise acceptation des décisions
D5: Les directions utilisatrices sont influentes au sein de ce Comité | E5: Les directions utilisatrices sont-elles influentes au sein du comité ? | F5: non | G5: Comptes rendus des réunions, décisions prises incluant les contributions des directions utilisatrices | H5: Négligence des apports des directions utilisatrices | I5: Élevé | J5: Solutions non adaptées aux besoins réels
D6: Présence de membres qualifiés et diversifiés | E6: Les membres du comité sont-ils qualifiés et diversifiés ? | F6: oui | G6: Profils des membres, CV, évaluation des compétences | H6: Compétences inadéquates des membres du comité | I6: Élevé | J6: Erreurs stratégiques et décisions inefficaces
C7: S’assurer de l’existence d'une politique relative aux applications | D7: Il existe une politique relative aux applications au sein de l'institution | E7: Une politique relative aux applications existe-t-elle au sein de l'institution ? | F7: oui | G7: Politique des applications, document de gouvernance | H7: Non-existence ou non-application de la politique. | I7: Élevé | J7: Désorganisation et manque de cadre
D8: La politique est connue des utilisateurs d'applications | E8: Les utilisateurs d'applications connaissent-ils cette politique ? | F8: oui | G8: Rapport de sensibilisation ou de communication | H8: Méconnaissance des obligations des utilisateurs | I8: Élevé | J8: Non-respect des procédures et inefficacité
D9: La politique est largement diffusée | E9: La politique est-elle largement diffusée ? | F9: non | G9: Support de communication (emails, brochures, affiches) | H9: Faible diffusion des informations | I9: Moyen | J9: Manque de transparence et communication inefficace
D10: La politique est mise en œuvre | E10: La politique est-elle mise en œuvre ? | F10: pas | G10: Rapports d'audit de conformité | H10: Non-conformité aux normes | I10: Élevé | J10: Risques juridiques et pénalités
D11: La politique couvre l'ensemble du cycle de vie de l’application | E11: La politique couvre-t-elle l'ensemble du cycle de vie de l'application ? | F11: pas | G11: Documentation de la politique, schéma de cycle de vie | H11: Gestion incohérente des étapes du cycle de vie des applications | I11: Élevé | J11: Dysfonctionnements fréquents
C12: S’assurer que les rôle et responsabilités des utilisateurs sont bien définis | D12: Le rôle et les responsabilités des utilisateurs vis-à-vis de l’application sont clairement identifiés | E12: Les rôles et responsabilités des utilisateurs vis-à-vis de l'application sont-ils clairement identifiés ? | F12: oui | G12: Matrice des rôles et responsabilités, charte utilisateur | H12: Absence de définition claire des rôles | I12: Élevé | J12: Confusion et responsabilités non assumées
D13: Le rôle et les responsabilités des utilisateurs vis-à-vis de l’application couvrent l’analyse des risques | E13: Les rôles et responsabilités des utilisateurs vis-à-vis de l'application couvrent-ils l'analyse des risques ? | F13: non | G13: Documentation d'analyse des risques, rapports spécifiques | H13: Non-réalisation des analyses des risques | I13: Élevé | J13: Survenue imprévisible de risques importants
D14: Le rôle et les responsabilités des utilisateurs vis-à-vis de l’application couvrent la définition des besoins de sécurité | E14: Les rôles et responsabilités des utilisateurs vis-à-vis de l'application couvrent-ils la définition des besoins de sécurité ? | F14: non | G14: Expression des besoins de sécurité | H14: Non-définition des besoins de sécurité | I14: Élevé | J14: Failles exploitables par des acteurs malveillants
D15: Le rôle et les responsabilités des utilisateurs vis-à-vis de l’application couvrent la gestion des changements et des évolutions | E15: Les rôles et responsabilités des utilisateurs vis-à-vis de l'application couvrent-ils la gestion des changements et des évolutions ? | F15: non | G15: Processus de gestion des changements | H15: Changements mal gérés | I15: Élevé | J15: Instabilité du système
D16: Le rôle et les responsabilités des utilisateurs vis-à-vis de l’application couvrent l’administration de l’application | E16: Les rôles et responsabilités des utilisateurs vis-à-vis de l'application couvrent-ils l'administration de l'application ? | F16: non | G16: Procédure d'administration de l'application | H16: Administration non sécurisée | I16: Élevé | J16: Accès non autorisé et perte de données
C17: S’assurer qu’une analyse des risques a été réalisée | D17: Une analyse des risques spécifique à l'application a été réalisée | E17: Une analyse des risques spécifique à l'application a-t-elle été réalisée ? | F17: oui | G17: Rapport d'analyse des risques spécifiques | H17: Documentation insuffisante des risques critiques | I17: Moyen | J17: Problèmes non identifiés et résolus
D18: L'analyse des risques a débouché sur la définition des besoins de sécurité | E18: L'analyse des risques a-t-elle débouché sur la définition des besoins de sécurité ? | F18: oui | G18: Plan de sécurité, documentation des besoins de sécurité | H18: Non-prise en compte des besoins de sécurité | I18: Élevé | J18: Vulnérabilité accrue face aux cyberattaques
D19: Les résultats de l'analyse des risques sont documentés et approuvés | E19: Les résultats de l'analyse des risques sont-ils documentés et approuvés ? | F19: oui | G19: Rapports d'approbation, validation formelle des résultats | H19: Absence de validation formelle | I19: Élevé | J19: Détection tardive des erreurs
D20: L'analyse des risques est mise à jour régulièrement | E20: L'analyse des risques est-elle mise à jour régulièrement ? | F20: oui | G20: Historique des mises à jour, calendrier des analyses | H20: Analyses de risques obsolètes | I20: Élevé | J20: Décisions basées sur des informations incorrectes
D21: Les risques identifiés sont pris en compte dans le plan d'action de sécurité | E21: Les risques identifiés sont-ils pris en compte dans le plan d'action de sécurité ? | F21: oui | G21: Plan d'action de sécurité, rapports d'intégration des risques | H21: Actions non mises en œuvre | I21: Élevé | J21: Maintien des risques identifiés
C22: S’assurer que le prolongement de l'analyse de risque et de son expansion ont été réalisés | D22: Il y a eu un prolongement de l'analyse des risques et de l'expression des besoins de sécurité | E22: Le prolongement de l'analyse des risques et de l'expression des besoins de sécurité a-t-il eu lieu ? | F22: pas | G22: Contrat de service SLA, documentation de mise en œuvre | H22: Non-respect des SLA | I22: Élevé | J22: Insatisfaction et perte de clients
D23: Un contrat de service (SLA) entre l'informatique et la direction utilisatrice a été mis en œuvre | E23: Un contrat de service (SLA) entre l'informatique et la direction utilisatrice a-t-il été mis en œuvre ? | F23: pas | G23: Politique de contrôle d'accès, matrice des rôles | H23: Accès inappropriés | I23: Élevé | J23: Fuites ou abus de données sensibles
D24: L'analyse des risques étendue couvre tous les aspects de l'application | E24: L'analyse des risques étendue couvre-t-elle tous les aspects de l'application ? | F24: oui | G24: Journal des droits d'accès, rapports d'audit | H24: Absence de journalisation | I24: Élevé | J24: Impossibilité de retracer les activités suspectes
D25: Les résultats de l'analyse des risques étendue sont communiqués aux parties prenantes | E25: Les résultats de l'analyse des risques étendue sont-ils communiqués aux parties prenantes ? | F25: oui | G25: Journaux d'accès, rapports de surveillance | H25: Activités suspectes non détectées | I25: Élevé | J25: Survenue de failles de sécurité
D26: L'analyse des risques étendue est utilisée pour la planification stratégique | E26: L'analyse des risques étendue est-elle utilisée pour la planification stratégique ? | F26: oui | G26: Procédure de révocation des accès | H26: Retard dans la révocation des accès | I26: Élevé | J26: Accès non autorisé prolongé
B27: Application | C27: S'assurer que l'accès aux ressources de l'application (données et transactions) est restreint par un système de gestion d'accès | D27: Contrôle d'accès basé sur les rôles est mis en place | E27: Un contrôle d'accès basé sur les rôles est-il mis en place ? | F27: oui | G27: Spécifications techniques de l'authentification, rapports de mise en œuvre | H27: Faiblesse dans l’authentification | I27: Élevé | J27: Compromission des comptes et données sensibles
D28: Les droits d'accès sont attribués de manière appropriée | E28: Les droits d'accès sont-ils attribués de manière appropriée ? | F28: oui | G28: Politique de mots de passe, guides utilisateurs | H28: Mauvaises pratiques de mots de passe | I28: Élevé | J28: Vulnérabilité aux attaques par force brute
D29: Les accès sont journalisés et surveillés | E29: Les accès sont-ils journalisés et surveillés ? | F29: oui | G29: Journaux des tentatives de connexion | H29: Tentatives suspectes non identifiées | I29: Élevé | J29: Intrusions non détectées
D30: Un processus est en place pour révoquer les accès | E30: Un processus est-il en place pour révoquer les accès ? | F30: pas | G30: Rapports d'incidents, base de données des suivis d'incidents | H30: Absence de suivi des incidents | I30: Élevé | J30: Problèmes récurrents non résolus
D31: Les accès sont audités régulièrement | E31: Les accès sont-ils audités régulièrement ? | F31: non | G31: Charte du comité informatique, liste des membres, procès-verbaux des réunions | H31: Absence de gouvernance claire | I31: Élevé | J31: Décisions incohérentes et manque de coordination
C32: S’assurer qu’une procédure de gestion des profils utilisateurs existe | D32: Procédure documentée pour la création, modification et suppression des profils | E32: Une procédure documentée pour la création, modification et suppression des profils existe-t-elle ? | F32: oui | G32: Document de nomination du Directeur Général, procès-verbaux des réunions | H32: Manque de leadership dans la prise de décisions stratégiques | I32: Élevé | J32: Retards et décisions inefficaces
D33: Les droits d'accès sont attribués en fonction des rôles | E33: Les droits d'accès sont-ils attribués en fonction des rôles ? | F33: oui | G33: Liste des membres du comité, organigramme | H33: Mauvaise représentation des parties prenantes | I33: Moyen | J33: Conflits et résistance aux décisions prises
D34: Les profils sont révisés régulièrement | E34: Les profils sont-ils révisés régulièrement ? | F34: oui | G34: Comptes rendus des réunions, décisions prises incluant les contributions des directions utilisatrices | H34: Négligence des apports des directions utilisatrices | I34: Moyen | J34: Solutions inadaptées aux besoins réels
D35: La procédure est communiquée aux parties prenantes | E35: La procédure est-elle communiquée aux parties prenantes ? | F35: pas | G35: Profils des membres, CV, évaluation des compétences | H35: Compétences inadéquates des membres du comité | I35: Élevé | J35: Décisions inefficaces et erreurs majeures
D36: Des outils d'automatisation sont utilisés pour la gestion des profils | E36: Des outils d'automatisation sont-ils utilisés pour la gestion des profils ? | F36: pas | G36: Politique des applications, document de gouvernance | H36: Non-existence ou non-application de la politique | I36: Élevé | J36: Désorganisation opérationnelle
C37: Vérifier que l’identification des utilisateurs est réalisée | D37: Mécanismes d'identification uniques sont utilisés | E37: Des mécanismes d'identification uniques sont-ils utilisés ? | F37: oui | G37: Rapport de sensibilisation ou de communication | H37: Méconnaissance des obligations des utilisateurs | I37: Moyen | J37: Utilisation incorrecte des applications
D38: Authentification forte est mise en place | E38: Une authentification forte est-elle mise en place ? | F38: oui | G38: Support de communication (emails, brochures, affiches) | H38: Faible diffusion des informations | I38: Moyen | J38: Collaboration et coordination limitées
D39: Procédure de gestion des identifiants est claire | E39: La procédure de gestion des identifiants est-elle claire ? | F39: oui | G39: Rapports d'audit de conformité | H39: Non-conformité aux normes | I39: Élevé | J39: Risques juridiques et pertes financières
D40: Les identifiants sont protégés | E40: Les identifiants sont-ils protégés ? | F40: oui | G40: Documentation de la politique, schéma de cycle de vie | H40: Gestion incohérente des étapes du cycle de vie des applications | I40: Élevé | J40: Dysfonctionnements et retards fréquents
D41: Les identifiants sont audités régulièrement | E41: Les identifiants sont-ils audités régulièrement ? | F41: non | G41: Matrice des rôles et responsabilités, charte utilisateur | H41: Absence de définition claire des rôles | I41: Moyen | J41: Confusion et duplication des responsabilités
C42: Vérifier qu’un mot de passe est associé à l'identifiant | D42: Politique de mots de passe est en place | E42: Une politique de mots de passe est-elle en place ? | F42: oui | G42: Documentation d'analyse des risques, rapports spécifiques | H42: Non-réalisation des analyses des risques | I42: Élevé | J42: Risques non identifiés pouvant entraîner des interruptions majeures
D43: Les mots de passe sont stockés de manière sécurisée | E43: Les mots de passe sont-ils stockés de manière sécurisée ? | F43: oui | G43: Expression des besoins de sécurité | H43: Non-définition des besoins de sécurité | I43: Élevé | J43: Failles exploitables entraînant des violations de données
D44: Procédure de gestion des mots de passe est claire | E44: La procédure de gestion des mots de passe est-elle claire ? | F44: pas | G44: Processus de gestion des changements | H44: Changements mal gérés | I44: Élevé | J44: Instabilité opérationnelle et pannes récurrentes
D45: Les utilisateurs sont formés sur les bonnes pratiques de mots de passe | E45: Les utilisateurs sont-ils formés sur les bonnes pratiques de mots de passe ? | F45: oui | G45: Procédure d'administration de l'application | H45: Administration non sécurisée | I45: Élevé | J45: Accès non autorisé et compromission des données sensibles
D46: Les mots de passe sont audités régulièrement | E46: Les mots de passe sont-ils audités régulièrement ? | F46: non | G46: Rapport d'analyse des risques spécifiques | H46: Documentation insuffisante des risques critiques | I46: Élevé | J46: Incapacité à prévoir et à atténuer les problèmes majeurs
C47: S’assurer que les tentatives de connexions infructueuses à l'application sont suivies | D47: Les tentatives de connexion sont journalisées | E47: Les tentatives de connexion sont-elles journalisées ? | F47: non | G47: Plan de sécurité, documentation des besoins de sécurité | H47: Non-prise en compte des besoins de sécurité | I47: Moyen | J47: Exploitation accrue par des acteurs malveillants
D48: Des alertes sont générées en cas d'activité suspecte | E48: Des alertes sont-elles générées en cas d'activité suspecte ? | F48: pas | G48: Rapports d'approbation, validation formelle des résultats | H48: Absence de validation formelle | I48: Moyen | J48: Erreurs non détectées et performance insuffisante
D49: Les journaux de connexion sont analysés régulièrement | E49: Les journaux de connexion sont-ils analysés régulièrement ? | F49: pas | G49: Historique des mises à jour, calendrier des analyses | H49: Analyses de risques obsolètes | I49: Moyen | J49: Décisions basées sur des informations périmées
D50: Les comptes sont bloqués en cas de tentatives répétées | E50: Les comptes sont-ils bloqués en cas de tentatives répétées ? | F50: oui | G50: Plan d'action de sécurité, rapports d'intégration des risques | H50: Actions non mises en œuvre. | I50: Élevé | J50: Risques identifiés persistant sans résolution
D51: Les incidents de sécurité sont documentés et suivis | E51: Les incidents de sécurité sont-ils documentés et suivis ? | F51: oui | G51: Contrat de service SLA, documentation de mise en œuvre | H51: Non-respect des SLA | I51: Élevé | J51: Insatisfaction des clients, perte de confiance et potentiels litiges
B52: Fonction informatique | C52: S’assurer que les tâches relatives au développement et à l'exploitation de l'application sont bien suivies et documentées | D52: Existence d'un plan de projet détaillé avec les tâches, les responsabilités et les échéances | E52: Existe-il un plan de projet detaillé avec les tâches, les responsabilités et les échéances? | F52: oui | G52: Plan de projet, diagramme de Gantt, feuille de route des tâches | H52: Mauvaise gestion des délais et des tâches | I52: Élevé | J52: Retards importants et baisse de productivité
D53: Utilisation d'outils de suivi de projet pour gérer les tâches et les progrès | E53: Des outils de suivi de projet sont-ils utilisés pour gérer les tâches et les progrès ? | F53: oui | G53: Liste des outils de suivi (exemple : Jira, Trello), rapports de suivi | H53: Absence de suivi centralisé des progrès | I53: Élevé | J53: Difficulté à évaluer l'état d'avancement des projets
D54: Documentation des activités de développement et d'exploitation (journal des modifications, rapports d'incidents... | E54: Les activités de développement et d'exploitation sont-elles documentées (journal des modifications, rapports d'incidents, etc.) ? | F54: oui | G54: Journal des modifications, rapport d’incidents, documentation des processus | H54: Manque de traçabilité | I54: Moyen | J54: Perte d'informations et incapacité à reproduire les étapes
D55: Communication régulière entre les équipes de développement et d'exploitation | E55: Une communication régulière existe-t-elle entre les équipes de développement et d'exploitation ? | F55: pas | G55: Comptes rendus de réunions, rapports de communication inter-équipes | H55: Communication insuffisante entre équipes | I55: Élevé | J55: Risques de malentendus et travail en silo
D56: Validation des livrables et des jalons par les parties prenantes concernées | E56: Les livrables et jalons sont-ils validés par les parties prenantes concernées ? | F56: oui | G56: Rapport de validation des livrables, procès-verbaux de réunions | H56: Livrables non validés | I56: Moyen | J56: Qualité réduite et non-conformité aux attentes
C57: S’assurer que l'accès aux bibliothèques de production est réglementé | D57: Existence d'une procédure formelle pour gérer l'accès aux bibliothèques de production | E57: Existe-t-il une procédure formelle pour gérer l'accès aux bibliothèques de production ? | F57: non | G57: Documentation des procédures d’accès, matrice des rôles | H57: Mauvaise définition des accès | I57: Élevé | J57: Risques d’accès non autorisé ou accès excessif
D58: Attribution des droits d'accès basée sur les rôles et les responsabilités | E58: Les droits d'accès sont-ils attribués en fonction des rôles et responsabilités ? | F58: oui | G58: Matrice des droits d’accès, charte des rôles | H58: Droits d'accès inappropriés | I58: Élevé | J58: Exploitation des systèmes et violations de sécurité
D59: Journalisation des accès aux bibliothèques de production | E59: Les accès aux bibliothèques de production sont-ils journalisés ? | F59: pas | G59: Journaux d’accès, rapports d’audit des accès | H59: Absence de journalisation | I59: Moyen | J59: Impossible de retracer les incidents
D60: Révision régulière des droits d'accès | E60: Les droits d'accès sont-ils révisés régulièrement ? | F60: pas | G60: Historique des révisions, rapport de conformité | H60: Révisions non effectuées régulièrement | I60: Élevé | J60: Découverte tardive d’erreurs et risques accrus
D61: Mise en place de contrôles pour prévenir les modifications non autorisées | E61: Des contrôles sont-ils mis en place pour prévenir les modifications non autorisées ? | F61: oui | G61: Documentation des contrôles, journal des modifications | H61: Changements non documentés | I61: Moyen | J61: Difficulté à comprendre l’historique des modifications
C62: Vérifier que la maintenance de la séparation des tâches est effective | D62: Définition claire des rôles et des responsabilités pour les tâches sensibles | E62: Les rôles et responsabilités pour les tâches sensibles sont-ils clairement définis ? | F62: oui | G62: Description des rôles, charte des responsabilités | H62: Définitions floues des rôles | I62: Moyen | J62: Confusion et responsabilités non assumées
D63: Implémentation de contrôles pour prévenir les conflits d'intérêts | E63: Des contrôles sont-ils implémentés pour prévenir les conflits d'intérêts ? | F63: oui | G63: Politique de contrôle des conflits, rapport de conformité | H63: Conflits d’intérêts mal gérés | I63: Élevé | J63: Décisions biaisées et manque de transparence
D64: Journalisation des activités des utilisateurs ayant des privilèges élevés | E64: Les activités des utilisateurs ayant des privilèges élevés sont-elles journalisées ? | F64: pas | G64: Journaux d’audit, rapports d’accès privilégié | H64: Absence de surveillance des utilisateurs privilégiés | I64: Élevé | J64: Exploitation non autorisée des privilèges
D65: Révision régulière des rôles et des responsabilités | E65: Les rôles et responsabilités sont-ils révisés régulièrement ? | F65: non | G65: Rapports d’évaluation des rôles, documentation des mises à jour des responsabilités | H65: Rôles ou responsabilités obsolètes | I65: Moyen | J65: Inefficacité et duplication des efforts
D66: Formation des utilisateurs sur l'importance de la séparation des tâches | E66: Les utilisateurs sont-ils formés sur l'importance de la séparation des tâches ? | F66: non | G66: Programme de formation, rapport de participation des utilisateurs | H66: Absence de formation des utilisateurs | I66: Moyen | J66: Mauvaise utilisation des systèmes
C67: S’assurer que l'équipe actuelle en charge de la maintenance est autonome et compétente | D67: Membres de l'équipe possédant les compétences techniques et fonctionnelles nécessaires | E67: Les membres de l'équipe possèdent-ils les compétences techniques et fonctionnelles nécessaires ? | F67: oui | G67: CV des membres, résultats d’évaluations des compétences | H67: Compétences insuffisantes | I67: Élevé | J67: Failles dans la gestion et erreurs fréquentes
D68: Existence d'un plan de formation continue pour l'équipe de maintenance | E68: Un plan de formation continue pour l'équipe de maintenance existe-t-il ? | F68: pas | G68: Plan de formation continue, calendrier des sessions | H68: Manque de formation continue | I68: Moyen | J68: Obsolescence des compétences
D69: Documentation des connaissances et des procédures de maintenance | E69: Les connaissances et procédures de maintenance sont-elles documentées ? | F69: oui | G69: Guides de maintenance, base de connaissances | H69: Documentation de maintenance insuffisante | I69: Élevé | J69: Retards et inefficacités dans la gestion de la maintenance
D70: Capacité de l'équipe à résoudre les problèmes et à répondre aux incidents | E70: L'équipe est-elle capable de résoudre les problèmes et de répondre aux incidents ? | F70: oui | G70: Rapport d’évaluation des performances, historique des incidents résolus | H70: Performances non évaluées | I70: Élevé | J70: Absence d’amélioration et maintien des inefficacités
D71: Evaluation régulière des performances de l'équipe de maintenance | E71: Les performances de l'équipe de maintenance sont-elles évaluées régulièrement ? | F71: oui | G71: Rapports d’évaluation des performances | H71: Plan de maintenance inexistant ou mal appliqué | I71: Moyen | J71: Augmentation des pannes et dégradations
C72: S’assurer de l’existence de procédure formalisée et standard de maintenance de l’application | D72: Existence d'un plan de maintenance documenté | E72: Un plan de maintenance documenté existe-t-il ? | F72: pas | G72: Plan de maintenance, rapport de stratégie | H72: Activités mal planifiées ou non réalisées | I72: Élevé | J72: Délais non respectés et inefficience dans l’exécution
D73: Définition des activités de maintenance préventive et corrective | E73: Les activités de maintenance préventive et corrective sont-elles définies ? | F73: oui | G73: Liste des activités préventives/correctives, calendrier de maintenance | H73: Absence d'outils adaptés | I73: Élevé | J73: Inefficacité dans les opérations
D74: Utilisation d'outils de gestion des incidents et des problèmes | E74: Des outils de gestion des incidents et des problèmes sont-ils utilisés ? | F74: oui | G74: Liste des outils de gestion (exemple : ServiceNow), rapports d’incidents | H74: Tests insuffisants ou inexistants | I74: Élevé | J74: Failles non détectées et dysfonctionnements fréquents
D75: Mise en place de procédures de test et de validation des modifications | E75: Des procédures de test et de validation des modifications sont-elles mises en place ? | F75: oui | G75: Plan de tests, procédure de validation | H75: Changements non communiqués | I75: Moyen | J75: Confusion et interruption des processus
D76: Communication des changements et des mises à jour aux utilisateurs | E76: Les changements et mises à jour sont-ils communiqués aux utilisateurs ? | F76: oui | G76: Rapports de communication des changements | H76: Schéma directeur obsolète ou mal aligné aux objectifs stratégiques | I76: Élevé | J76: Dysfonctionnement et inadéquation stratégique
C77: Vérifier que les nouvelles versions (développement interne, progiciel) sont suivies | D77: Documentation des versions | E77: Existe-t-il une documentation complète pour chaque nouvelle version développée ? | F77: Oui. | G77: Journal des versions | H77: Manque de clarté sur les modifications apportées. | I77: Elevé | J77: Difficulté à gérer les mises à jour
D78: Suivi des changements | E78: Les changements apportés dans chaque version sont-ils suivis et évalués ? | F78: oui | G78: Rapports de suivi des changements | H78: Non-identification des impacts des changements | I78: Elevé | J78: Problèmes non résolus lors de l'utilisation
D79: Tests de validation | E79: Des tests de validation sont-ils effectués pour chaque nouvelle version avant déploiement ? | F79: Oui. | G79: Rapports de tests | H79: Bugs non détectés dans les nouvelles versions. | I79: Elevé | J79: Mauvaise expérience utilisateu
D80: Formation sur les nouvelles versions | E80: Les utilisateurs reçoivent-ils une formation sur les nouvelles fonctionnalités après chaque mise à jour ? | F80: Oui | G80: Plan de formation | H80: Mauvaise utilisation des nouvelles fonctionnalités | I80: Moyen | J80: Insatisfaction des utilisateurs
D81: Feedback sur les nouvelles versions | E81: Un système de feedback est-il en place pour recueillir les impressions des utilisateurs sur les nouvelles versions ? | F81: Oui. | G81: Rapports de feedback des utilisateurs | H81: Ignorer les préoccupations des utilisateurs | I81: Elevé | J81: Diminution de l'engagement des utilisateurs
C82: Vérifier l’existence de procédure formalisée de transfert des programmes entre les environnements | D82: Document de procédure | E82: Existe-t-il un document formel décrivant la procédure de transfert des programmes ? | F82: pas | G82: Manuel de procédure de transfert | H82: Absence de procédure standardisée | I82: Élevé | J82: Erreurs lors des transferts
D83: Étapes de transfert définies | E83: Les étapes du processus de transfert sont-elles clairement définies et suivies ? | F83: pas | G83: Check-list de transfert | H83: Omission d'étapes critiques | I83: Moyen | J83: Défaillances dans l'environnement cible
D84: Contrôles de qualité | E84: Des contrôles de qualité sont-ils effectués après le transfert des programmes ? | F84: oui | G84: Rapports de contrôle qualité | H84: Problèmes non détectés après transfert | I84: Moyen | J84: Fonctionnalités inopérantes
D85: Formation du personnel | E85: Le personnel impliqué dans le transfert est-il formé sur la procédure ? | F85: oui | G85: Plan de formation | H85: Manque de compétence lors des transferts | I85: Élevé | J85: Erreurs lors des opérations.
D86: Suivi des transferts | E86: Un suivi est-il effectué pour évaluer l'efficacité des transferts de programmes ? | F86: oui | G86: Rapports de suivi des transferts | H86: Non-identification des points d'amélioration | I86: Moyen | J86: Répétition des erreurs dans les transferts futurs
B87: Adéquation de l'application aux besoins | C87: Vérifier qu’un Schéma-directeur du système d’information existe et est à jour | D87: Existence d'un Schéma-directeur du système d'information (SDSI) documenté | E87: Un Schéma-directeur du système d'information (SDSI) documenté existe-t-il ? | F87: pas | G87: Schéma directeur documenté, plan stratégique IT | H87: Absence d'évaluation approfondie | I87: Élevé | J87: Risques non identifiés ou mal gérés
D88: Le SDSI couvre tous les aspects du système d'information | E88: Le SDSI couvre-t-il tous les aspects du système d'information ? | F88: pas | G88: Rapport d’évaluation du SDSI | H88: Stratégies mal alignées | I88: Élevé | J88: Décisions inefficaces et déviation des objectifs
D89: Le SDSI est aligné sur la stratégie de l'entreprise | E89: Le SDSI est-il aligné sur la stratégie de l'entreprise ? | F89: pas | G89: Documentation de l’alignement stratégique | H89: Mises à jour non suivies | I89: Moyen | J89: Instabilité du système et failles potentielles
D90: Le SDSI est mis à jour régulièrement | E90: Le SDSI est-il mis à jour régulièrement ? | F90: pas | G90: Historique des mises à jour | H90: Information mal diffusée | I90: Moyen | J90: Manque de coordination et erreurs fréquentes
D91: Le SDSI est communiqué aux parties prenantes concernées | E91: Le SDSI est-il communiqué aux parties prenantes concernées ? | F91: pas | G91: Liste de diffusion, rapports de communication | H91: Non-évaluation de l'alignement stratégique | I91: Moyen | J91: Ressources mal utilisées et inefficacité globale
C92: S’assurer qu’une évaluation de l’alignement stratégique de l’application avec les orientation de l’entreprise a été réalisée | D92: Existence d'un document d'évaluation de l'alignement stratégique | E92: Un document d'évaluation de l'alignement stratégique existe-t-il ? | F92: non | G92: Document d’évaluation de l’alignement stratégique | H92: Évaluations superficielles | I92: Moyen | J92: Résultats insuffisants et décisions biaisées
D93: L'évaluation couvre les aspects fonctionnels, techniques et financiers | E93: L'évaluation couvre-t-elle les aspects fonctionnels, techniques et financiers ? | F93: oui | G93: Rapports d’évaluation détaillés | H93: Experts non qualifiés | I93: Élevé | J93: Erreurs majeures et inefficacité dans les processus
D94: L'évaluation est réalisée par des experts qualifiés | E94: L'évaluation est-elle réalisée par des experts qualifiés ? | F94: oui | G94: Profil des évaluateurs, rapport d’expertise | H94: Absence de mise à jour | I94: Moyen | J94: Décisions basées sur des données périmées
D95: L'évaluation est mise à jour régulièrement | E95: L'évaluation est-elle mise à jour régulièrement ? | F95: pas | G95: Rapports de mise à jour de l’évaluation | H95: Résultats mal communiqués | I95: Moyen | J95: Confusion et résistance aux conclusions
D96: Les résultats de l'évaluation sont communiqués aux parties prenantes concernées | E96: Les résultats de l'évaluation sont-ils communiqués aux parties prenantes concernées ? | F96: oui | G96: Documentation de communication des résultats | H96: Spécifications incomplètes ou imprécises | I96: Élevé | J96: Mauvaise conception et risques d’incompatibilité
C97: S’assurer que la définition des spécifications ou les critères de choix de la solution a été clairement établie | D97: Existence d'un document de spécifications ou de critères de choix | E97: Un document de spécifications ou de critères de choix existe-t-il ? | F97: oui | G97: Document de spécifications, cahier des charges | H97: Critères non validés | I97: Élevé | J97: Solutions non adaptées et insatisfaction des utilisateurs
D98: Les spécifications ou les critères de choix sont clairs, précis et mesurables | E98: Les spécifications ou critères de choix sont-ils clairs, précis et mesurables ? | F98: oui | G98: Documentation des critères de choix validés | H98: Validation insuffisante | I98: Moyen | J98: Défauts et dysfonctionnements non détectés
D99: Les spécifications ou les critères de choix sont validés par les parties prenantes concernées | E99: Les spécifications ou critères de choix sont-ils validés par les parties prenantes concernées ? | F99: oui | G99: Rapports de validation, signatures des parties prenantes | H99: Critères de comparaison partiels | I99: Moyen | J99: Décisions biaisées et manque d’équité
D100: Les spécifications ou les critères de choix sont utilisés pour évaluer les solutions potentielles | E100: Les spécifications ou critères de choix sont-ils utilisés pour évaluer les solutions potentielles ? | F100: oui | G100: Matrice d’évaluation des solutions, documentation de comparaison | H100: Processus de sélection non documenté | I100: Moyen | J100: Difficulté à justifier les choix effectués
...

Sheet 4,2_fonction_informatiq
A1: Domaines | B1: Points de contrôle | C1: Objectifs de contrôle | D1: critères d'évaluation | E1: Questions d’évaluation | F1: Réponses | G1: Documents Requis | H1: Risques | I1: Criticités | J1: Conséquences
A3: Audit de la Fonction Informatique | B3: Rôle et positionnement de l'informatique dans l'organisation | C3: Vérifier qu’ont été créés des Comités « informatique » (stratégique, pilotage,..) regroupant les différentes directions de l’Organisation en charge de recenser les besoins et les opportunités, gérer les priorités et suivre les projets | D3: Vérifier si des comités formels ont été établis pour la gouvernance des systèmes d'information | E3: Quels comités formels ont été établis pour la gouvernance des systèmes d'information ? | F3: Non | G3: Support justificatif des dépenses par service | H3: Diminution de la visibilité sur la consommation réelle | I3: Moyenne | J3: Risque de mauvaise allocation des ressources.
D4: Évaluer si les comités regroupent des représentants de toutes les directions pertinentes de l'organisation | E4: Quelles directions de l'organisation sont représentées dans chaque comité ? | F4: Non | G4: État des besoins financiers informatiques | H4: Retard dans l’identification d’écarts financiers | I4: Élevée | J4: Impact sur la qualité des décisions financières.
D5: Analyser la régularité des réunions des comités pour assurer un suivi adéquat des projets et des priorités | E5: À quelle fréquence les comités se réunissent-ils pour suivre les projets et les priorités ? | F5: Pas | G5: Détail des lignes budgétaires allouées | H5: Non-respect des circuits d’approbation | I5: Moyenne | J5: Risque de perte de contrôle sur les dépenses.
D6: Vérifier si les décisions prises lors des réunions des comités sont correctement documentées et accessibles | E6: Les décisions prises lors des réunions des comités sont-elles documentées et accessibles aux parties prenantes ? | F6: Non | G6: Analyse des écarts réalisée en comité | H6: Biais de planification et sous-financement | I6: Élevée | J6: Peut ralentir la mise en œuvre des projets.
D7: Évaluer comment les comités suivent l'avancement des projets et gèrent les priorités identifiées | E7: Comment les comités suivent-ils l'avancement des projets et ajustent-ils les priorités en fonction des besoins ? | F7: Oui | G7: Suivi détaillé des dépenses prévues | H7: Failles dans la remontée d'information financière | I7: Moyenne | J7: Conduit à une mauvaise visibilité financière.
C8: Vérifier l’existence d’une charte informatique ou de tout autre document définissant le rôle et le périmètre de responsabilité de la DSI | D8: Vérifier l'existence d'une charte informatique officiell | E8: Existe-t-il une charte informatique formellement adoptée par l'organisation ? | F8: Oui | G8: Historique des arbitrages budgétaires | H8: Absence de contrôle hiérarchique sur les coûts | I8: Élevée | J8: Peut générer des écarts non maîtrisés.
D9: Évaluer la clarté des rôles et responsabilités dans la charte | E9: La charte définit-elle clairement les rôles et responsabilités de la DSI et des autres parties prenantes ? | F9: Non | G9: Synthèse des plans de réajustement | H9: Décalage entre ressources affectées et dépenses | I9: Moyenne | J9: Risque d'engagements financiers non validés.
D10: Analyser la mise à jour de la charte | E10: La charte informatique est-elle régulièrement mise à jour pour refléter les changements au sein de l'organisation ? | F10: Non | G10: Traçabilité des approbations budgétaires | H10: Manque d’alignement budgétaire stratégique | I10: Élevée | J10: Problème de cohérence entre prévision et réalisation.
D11: Vérifier la diffusion de la charte auprès des employés | E11: Comment la charte a-t-elle été communiquée aux employés et aux parties prenantes de l'organisation ? | F11: Oui | G11: Pièces justificatives centralisées | H11: Omissions dans le reporting budgétaire | I11: Moyenne | J11: Retard dans la détection des anomalies budgétaires.
D12: Évaluer l'application des principes définis dans la charte | E12: Les principes et directives de la charte informatique sont-ils effectivement appliqués dans la gestion des systèmes d'information ? | F12: Oui | G12: Procédure de contrôle budgétaire validée | H12: Risque de dépenses hors périmètre budgétaire | I12: Élevée | J12: Peut entraîner un dépassement de budget.
C13: Évaluer le degré d’implication et de maîtrise des organes de gestion dans les systèmes d’information de l’Organisation | D13: Évaluer la participation des organes de gestion dans les décisions liées aux systèmes d'information | E13: À quelle fréquence les organes de gestion sont-ils impliqués dans les décisions concernant les systèmes d'information | F13: Non | G13: Support justificatif des dépenses par service | H13: Diminution de la visibilité sur la consommation réelle | I13: Moyenne | J13: Risque de mauvaise allocation des ressources.
D14: Analyser la formation et la sensibilisation des organes de gestion aux enjeux des systèmes d'information | E14: Les membres des organes de gestion ont-ils reçu une formation sur les systèmes d'information et leur importance ? | F14: pas | G14: État des besoins financiers informatiques | H14: Retard dans l’identification d’écarts financiers | I14: Élevée | J14: Impact sur la qualité des décisions financières.
D15: Vérifier l'existence de mécanismes de suivi des projets par les organes de gestion | E15: Quels outils ou processus les organes de gestion utilisent-ils pour suivre l'avancement des projets liés aux systèmes d'information ? | F15: pas | G15: Détail des lignes budgétaires allouées | H15: Non-respect des circuits d’approbation | I15: Moyenne | J15: Risque de perte de contrôle sur les dépenses.
D16: Évaluer l'intégration des systèmes d'information dans la stratégie globale de l'organisation | E16: Comment les systèmes d'information sont-ils intégrés dans la stratégie globale de l'organisation par les organes de gestion ? | F16: Non | G16: Analyse des écarts réalisée en comité | H16: Biais de planification et sous-financement | I16: Élevée | J16: Peut ralentir la mise en œuvre des projets.
D17: Analyser la réactivité des organes de gestion face aux problèmes rencontrés dans les systèmes d'information | E17: Comment les organes de gestion réagissent-ils aux problèmes ou aux défis identifiés dans les systèmes d'information ? | F17: pas | G17: Suivi détaillé des dépenses prévues | H17: Failles dans la remontée d'information financière | I17: Moyenne | J17: Conduit à une mauvaise visibilité financière.
C18: Vérifier en pratique que le leadership des grands projets est assuré par les organes de gestion | D18: Les organes de gestion sont identifiés pour chaque grand projet | E18: Comment l'organisation s'assure-t-elle que les organes de gestion sont clairement identifiés et désignés pour chaque grand projet ? | F18: pas | G18: Historique des arbitrages budgétaires | H18: Absence de contrôle hiérarchique sur les coûts | I18: Élevée | J18: Peut générer des écarts non maîtrisés.
D19: Les organes de gestion participent activement aux décisions clés | E19: Comment l'organisation s'assure-t-elle que les organes de gestion sont impliqués dans les décisions clés tout au long du projet ? | F19: Oui | G19: Synthèse des plans de réajustement | H19: Décalage entre ressources affectées et dépenses | I19: Moyenne | J19: Risque d'engagements financiers non validés.
D20: Les organes de gestion fournissent des directives stratégiques claires | E20: Comment l'organisation s'assure-t-elle que les organes de gestion fournissent des directives stratégiques claires et cohérentes ? | F20: Oui | G20: Traçabilité des approbations budgétaires | H20: Manque d’alignement budgétaire stratégique | I20: Élevée | J20: Problème de cohérence entre prévision et réalisation.
D21: Les organes de gestion surveillent la progression du projet | E21: Comment l'organisation s'assure-t-elle que les organes de gestion surveillent régulièrement la progression du projet par rapport aux objectifs fixés ? | F21: Oui | G21: Pièces justificatives centralisées | H21: Omissions dans le reporting budgétaire | I21: Moyenne | J21: Retard dans la détection des anomalies budgétaires.
D22: Les organes de gestion prennent des mesures correctives si nécessaire | E22: Comment l'organisation s'assure-t-elle que les organes de gestion prennent des mesures correctives en cas de déviation par rapport au plan initial ? | F22: Oui | G22: Procédure de contrôle budgétaire validée | H22: Risque de dépenses hors périmètre budgétaire | I22: Élevée | J22: Peut entraîner un dépassement de budget.
C23: Vérifier que les métiers assurent leur rôle de MOA | D23: Les rôles et responsabilités de la MOA sont définis | E23: Comment l'organisation s'assure-t-elle que les rôles et responsabilités de la MOA sont clairement définis et communiqués ? | F23: pas | G23: Support justificatif des dépenses par service | H23: Diminution de la visibilité sur la consommation réelle | I23: Moyenne | J23: Risque de mauvaise allocation des ressources.
D24: La MOA participe à la définition des besoins fonctionnels. | E24: Comment l'organisation s'assure-t-elle que la MOA est impliquée dans la définition des besoins fonctionnels du projet ? | F24: pas | G24: État des besoins financiers informatiques | H24: Retard dans l’identification d’écarts financiers | I24: Élevée | J24: Impact sur la qualité des décisions financières.
D25: La MOA valide les livrables du projet | E25: Comment l'organisation s'assure-t-elle que la MOA valide les livrables du projet pour s'assurer qu'ils répondent aux besoins définis ? | F25: Non | G25: Détail des lignes budgétaires allouées | H25: Non-respect des circuits d’approbation | I25: Moyenne | J25: Risque de perte de contrôle sur les dépenses.
D26: La MOA assure la communication avec les utilisateurs finaux | E26: Comment l'organisation s'assure-t-elle que la MOA assure une communication efficace avec les utilisateurs finaux tout au long du projet ? | F26: Oui | G26: Analyse des écarts réalisée en comité | H26: Biais de planification et sous-financement | I26: Élevée | J26: Peut ralentir la mise en œuvre des projets.
D27: La MOA participe aux tests et à la recette du projet | E27: Comment l'organisation s'assure-t-elle que la MOA est impliquée dans les tests et la recette du projet pour valider sa conformité aux besoins ? | F27: Oui | G27: Suivi détaillé des dépenses prévues | H27: Failles dans la remontée d'information financière | I27: Moyenne | J27: Conduit à une mauvaise visibilité financière.
B28: Planification stratégique | C28: Vérifier la couverture du périmètre fonctionnel | D28: Vérifier la couverture du périmètre fonctionnel | E28: Comment l'organisation s'assure-t-elle que le périmètre fonctionnel est clairement défini et documenté ? | F28: Non | G28: Historique des arbitrages budgétaires | H28: Absence de contrôle hiérarchique sur les coûts | I28: Élevée | J28: Peut générer des écarts non maîtrisés.
D29: Tous les processus métier sont identifiés. | E29: Comment l'organisation s'assure-t-elle que tous les processus métier sont identifiés et inclus dans le périmètre fonctionnel ? | F29: pas | G29: Synthèse des plans de réajustement | H29: Décalage entre ressources affectées et dépenses | I29: Moyenne | J29: Risque d'engagements financiers non validés.
D30: Les interfaces entre les processus sont documentées. | E30: Comment l'organisation s'assure-t-elle que les interfaces entre les processus sont documentées et comprises ? | F30: Oui | G30: Traçabilité des approbations budgétaires | H30: Manque d’alignement budgétaire stratégique | I30: Élevée | J30: Problème de cohérence entre prévision et réalisation.
D31: Les besoins des utilisateurs sont pris en compte. | E31: Comment l'organisation s'assure-t-elle que les besoins des utilisateurs sont pris en compte dans la définition du périmètre fonctionnel ? | F31: Non | G31: Pièces justificatives centralisées | H31: Omissions dans le reporting budgétaire | I31: Moyenne | J31: Retard dans la détection des anomalies budgétaires.
D32: Le périmètre fonctionnel est clairement défini. | E32: Comment l'organisation s'assure-t-elle que le périmètre fonctionnel est régulièrement révisé et mis à jour en fonction des changements ? | F32: pas | G32: Procédure de contrôle budgétaire validée | H32: Risque de dépenses hors périmètre budgétaire | I32: Élevée | J32: Peut entraîner un dépassement de budget.
C33: Vérifier l’existence d’une analyse à jour des procédures de pilotage et de mise à jour du plan informatique | D33: Vérifier l'existence d'une analyse formelle des procédures | E33: Existe-t-il une analyse documentée des procédures de pilotage du plan informatique ? | F33: pas | G33: Support justificatif des dépenses par service | H33: Diminution de la visibilité sur la consommation réelle | I33: Moyenne | J33: Risque de mauvaise allocation des ressources.
D34: Évaluer la fréquence de mise à jour de l'analyse | E34: À quelle fréquence l'analyse des procédures de pilotage est-elle mise à jour ? | F34: Non | G34: État des besoins financiers informatiques | H34: Retard dans l’identification d’écarts financiers | I34: Élevée | J34: Impact sur la qualité des décisions financières.
D35: Analyser l'implication des parties prenantes dans l'analyse | E35: Quelles parties prenantes ont été impliquées dans l'analyse des procédures de pilotage et de mise à jour ? | F35: pas | G35: Détail des lignes budgétaires allouées | H35: Non-respect des circuits d’approbation | I35: Moyenne | J35: Risque de perte de contrôle sur les dépenses.
D36: Vérifier la clarté des procédures définies | E36: Les procédures de pilotage et de mise à jour sont-elles clairement définies et accessibles aux parties concernées ? | F36: Oui | G36: Analyse des écarts réalisée en comité | H36: Biais de planification et sous-financement | I36: Élevée | J36: Peut ralentir la mise en œuvre des projets.
D37: Évaluer l'efficacité des procédures mises en place | E37: Comment l'efficacité des procédures de pilotage et de mise à jour est-elle mesurée et évaluée ? | F37: Oui | G37: Suivi détaillé des dépenses prévues | H37: Failles dans la remontée d'information financière | I37: Moyenne | J37: Conduit à une mauvaise visibilité financière.
C38: Vérifier l’existence des documents à jour d’urbanisme de l’Organisation | D38: Vérifier l'existence de documents d'urbanisme formels | E38: Existe-t-il des documents d'urbanisme officiellement adoptés par l'organisation ? | F38: Oui | G38: Historique des arbitrages budgétaires | H38: Absence de contrôle hiérarchique sur les coûts | I38: Élevée | J38: Peut générer des écarts non maîtrisés.
D39: Évaluer la mise à jour des documents | E39: À quelle fréquence les documents d'urbanisme sont-ils mis à jour ? | F39: pas | G39: Synthèse des plans de réajustement | H39: Décalage entre ressources affectées et dépenses | I39: Moyenne | J39: Risque d'engagements financiers non validés.
D40: Analyser la conformité des documents | E40: Les documents d'urbanisme respectent-ils les réglementations et normes en vigueur ? | F40: Non | G40: Traçabilité des approbations budgétaires | H40: Manque d’alignement budgétaire stratégique | I40: Élevée | J40: Problème de cohérence entre prévision et réalisation.
D41: Vérifier la clarté et l'accessibilité des documents | E41: Les documents d'urbanisme sont-ils clairs et facilement accessibles aux parties prenantes ? | F41: Oui | G41: Pièces justificatives centralisées | H41: Omissions dans le reporting budgétaire | I41: Moyenne | J41: Retard dans la détection des anomalies budgétaires.
D42: Évaluer l'implication des parties prenantes dans l'élaboration | E42: Quelles parties prenantes ont été impliquées dans l'élaboration ou la mise à jour des documents d'urbanisme ? | F42: pas | G42: Procédure de contrôle budgétaire validée | H42: Risque de dépenses hors périmètre budgétaire | I42: Élevée | J42: Peut entraîner un dépassement de budget.
C43: Vérifier l’existence d’une analyse à jour des procédures de pilotage et de mise à jour du plan d’occupation des sols (POS) | D43: Vérifier l'existence d'une analyse formelle des procédures | E43: Existe-t-il une analyse documentée des procédures de pilotage du POS ? | F43: pas | G43: Support justificatif des dépenses par service | H43: Diminution de la visibilité sur la consommation réelle | I43: Moyenne | J43: Risque de mauvaise allocation des ressources.
D44: Évaluer la fréquence de mise à jour de l'analyse | E44: À quelle fréquence l'analyse des procédures de pilotage est-elle mise à jour ? | F44: pas | G44: État des besoins financiers informatiques | H44: Retard dans l’identification d’écarts financiers | I44: Élevée | J44: Impact sur la qualité des décisions financières.
D45: Analyser l'implication des parties prenantes dans l'analyse | E45: Quelles parties prenantes ont été impliquées dans l'analyse des procédures de pilotage et de mise à jour du POS ? | F45: Non | G45: Détail des lignes budgétaires allouées | H45: Non-respect des circuits d’approbation | I45: Moyenne | J45: Risque de perte de contrôle sur les dépenses.
D46: Vérifier la clarté des procédures définies | E46: Les procédures de pilotage et de mise à jour du POS sont-elles clairement définies et accessibles ? | F46: Oui | G46: Analyse des écarts réalisée en comité | H46: Biais de planification et sous-financement | I46: Élevée | J46: Peut ralentir la mise en œuvre des projets.
D47: Évaluer l'efficacité des procédures mises en place | E47: Comment l'efficacité des procédures de pilotage et de mise à jour du POS est-elle mesurée et évaluée ? | F47: Oui | G47: Suivi détaillé des dépenses prévues | H47: Failles dans la remontée d'information financière | I47: Moyenne | J47: Conduit à une mauvaise visibilité financière.
C48: Vérifier la cohérence et l’homogénéité des technologies | D48: Évaluer l'inventaire des technologies utilisées | E48: Existe-t-il un inventaire complet des technologies actuellement utilisées dans l'organisation ? | F48: Non | G48: Historique des arbitrages budgétaires | H48: Absence de contrôle hiérarchique sur les coûts | I48: Élevée | J48: Peut générer des écarts non maîtrisés.
D49: Analyser l'interopérabilité des systèmes | E49: Les différentes technologies et systèmes en place peuvent-ils communiquer efficacement entre eux ? | F49: Non | G49: Synthèse des plans de réajustement | H49: Décalage entre ressources affectées et dépenses | I49: Moyenne | J49: Risque d'engagements financiers non validés.
D50: Vérifier la conformité aux standards | E50: Les technologies utilisées respectent-elles les standards et bonnes pratiques de l'industrie ? | F50: Non | G50: Traçabilité des approbations budgétaires | H50: Manque d’alignement budgétaire stratégique | I50: Élevée | J50: Problème de cohérence entre prévision et réalisation.
D51: Évaluer la documentation des technologies | E51: Y a-t-il une documentation à jour et accessible concernant les technologies déployées ? | F51: pas | G51: Pièces justificatives centralisées | H51: Omissions dans le reporting budgétaire | I51: Moyenne | J51: Retard dans la détection des anomalies budgétaires.
D52: Analyser la formation des utilisateurs | E52: Les utilisateurs sont-ils formés à l'utilisation cohérente des technologies en place ? | F52: Non | G52: Procédure de contrôle budgétaire validée | H52: Risque de dépenses hors périmètre budgétaire | I52: Élevée | J52: Peut entraîner un dépassement de budget.
C53: Vérifier l’existence et l’unicité des référentiels (clients, fournisseurs, articles…) et des saisies | D53: Vérifier l'existence de référentiels documentés | E53: Existe-t-il des référentiels documentés pour les clients, fournisseurs et articles ? | F53: Non | G53: Support justificatif des dépenses par service | H53: Diminution de la visibilité sur la consommation réelle | I53: Moyenne | J53: Risque de mauvaise allocation des ressources.
D54: Évaluer l'unicité des enregistrements | E54: Y a-t-il des mécanismes en place pour garantir l'unicité des enregistrements dans les systèmes ? | F54: Non | G54: État des besoins financiers informatiques | H54: Retard dans l’identification d’écarts financiers | I54: Élevée | J54: Impact sur la qualité des décisions financières.
D55: Analyser la gestion des doublons | E55: Comment les doublons sont-ils gérés et éliminés dans les référentiels ? | F55: Non | G55: Détail des lignes budgétaires allouées | H55: Non-respect des circuits d’approbation | I55: Moyenne | J55: Risque de perte de contrôle sur les dépenses.
D56: Vérifier la mise à jour des référentiels | E56: À quelle fréquence les référentiels sont-ils mis à jour pour refléter les changements ? | F56: Non | G56: Analyse des écarts réalisée en comité | H56: Biais de planification et sous-financement | I56: Élevée | J56: Peut ralentir la mise en œuvre des projets.
D57: Évaluer la formation des utilisateurs | E57: Les utilisateurs sont-ils formés à la saisie correcte des données dans les référentiels ? | F57: Oui | G57: Suivi détaillé des dépenses prévues | H57: Failles dans la remontée d'information financière | I57: Moyenne | J57: Conduit à une mauvaise visibilité financière.
B58: Budgets et coûts informatiques | C58: Évaluer l’organisation et les processus existants | D58: Analyser la structure organisationnelle | E58: La structure organisationnelle est-elle clairement définie et documentée ? | F58: Oui | G58: Historique des arbitrages budgétaires | H58: Absence de contrôle hiérarchique sur les coûts | I58: Élevée | J58: Peut générer des écarts non maîtrisés.
D59: Évaluer la clarté des processus | E59: Les processus existants sont-ils clairement définis et accessibles aux employés ? | F59: Non | G59: Synthèse des plans de réajustement | H59: Décalage entre ressources affectées et dépenses | I59: Moyenne | J59: Risque d'engagements financiers non validés.
D60: Vérifier l'efficacité des processus | E60: Comment l'efficacité des processus existants est-elle mesurée et évaluée ? | F60: Non | G60: Traçabilité des approbations budgétaires | H60: Manque d’alignement budgétaire stratégique | I60: Élevée | J60: Problème de cohérence entre prévision et réalisation.
D61: Analyser la documentation des processus | E61: Y a-t-il une documentation à jour des processus existants ? | F61: pas | G61: Pièces justificatives centralisées | H61: Omissions dans le reporting budgétaire | I61: Moyenne | J61: Retard dans la détection des anomalies budgétaires.
D62: Évaluer l'implication des parties prenantes | E62: Les parties prenantes sont-elles impliquées dans l'évaluation et l'amélioration des processus ? | F62: pas | G62: Procédure de contrôle budgétaire validée | H62: Risque de dépenses hors périmètre budgétaire | I62: Élevée | J62: Peut entraîner un dépassement de budget.
C63: Vérifier l’existence des ratios et des éléments de benchmark (interne et/ou externe, ratio coûts/CA, …) | D63: Vérifier l'existence de ratios documentés | E63: Existe-t-il des ratios clairement documentés pour évaluer la performance financière de l'organisation ? | F63: Non | G63: Support justificatif des dépenses par service | H63: Diminution de la visibilité sur la consommation réelle | I63: Moyenne | J63: Risque de mauvaise allocation des ressources.
D64: Analyser la comparaison avec des benchmarks externes | E64: L'organisation utilise-t-elle des benchmarks externes pour comparer ses performances ? | F64: Oui | G64: État des besoins financiers informatiques | H64: Retard dans l’identification d’écarts financiers | I64: Élevée | J64: Impact sur la qualité des décisions financières.
D65: Évaluer la fréquence de mise à jour des ratios | E65: À quelle fréquence les ratios et benchmarks sont-ils mis à jour ? | F65: Non | G65: Détail des lignes budgétaires allouées | H65: Non-respect des circuits d’approbation | I65: Moyenne | J65: Risque de perte de contrôle sur les dépenses.
D66: Analyser l'utilisation des ratios pour la prise de décision | E66: Les ratios sont-ils utilisés pour guider la prise de décision au sein de l'organisation ? | F66: Oui | G66: Analyse des écarts réalisée en comité | H66: Biais de planification et sous-financement | I66: Élevée | J66: Peut ralentir la mise en œuvre des projets.
D67: Vérifier la communication des résultats | E67: Comment les résultats des ratios et benchmarks sont-ils communiqués aux parties prenantes ? | F67: pas | G67: Suivi détaillé des dépenses prévues | H67: Failles dans la remontée d'information financière | I67: Moyenne | J67: Conduit à une mauvaise visibilité financière.
C68: Évaluer la planification budgétaire et le suivi des coûts | D68: Examiner la méthode de planification budgétaire utilisée | E68: Quelle méthode est utilisée pour établir le budget informatique annuel ? | F68: pas | G68: Historique des arbitrages budgétaires | H68: Absence de contrôle hiérarchique sur les coûts | I68: Élevée | J68: Peut générer des écarts non maîtrisés.
D69: Analyser les écarts entre budget prévisionnel et dépenses réelles | E69: Des écarts significatifs entre budget et dépenses réelles sont-ils identifiés et analysés ? | F69: Non | G69: Synthèse des plans de réajustement | H69: Décalage entre ressources affectées et dépenses | I69: Moyenne | J69: Risque d'engagements financiers non validés.
D70: Vérifier l’existence d’un contrôle régulier des dépenses | E70: Des contrôles réguliers sont-ils mis en place pour suivre les dépenses informatiques ? | F70: Oui | G70: Traçabilité des approbations budgétaires | H70: Manque d’alignement budgétaire stratégique | I70: Élevée | J70: Problème de cohérence entre prévision et réalisation.
D71: Vérifier l’existence de rapports de suivi budgétaire | E71: Des rapports périodiques sur l’exécution du budget informatique sont-ils produits et analysés ? | F71: pas | G71: Pièces justificatives centralisées | H71: Omissions dans le reporting budgétaire | I71: Moyenne | J71: Retard dans la détection des anomalies budgétaires.
D72: Évaluer la responsabilisation des acteurs budgétaires | E72: Les responsables de services sont-ils impliqués et responsabilisés dans la gestion de leurs budgets IT ? | F72: Non | G72: Procédure de contrôle budgétaire validée | H72: Risque de dépenses hors périmètre budgétaire | I72: Élevée | J72: Peut entraîner un dépassement de budget.
C73: Assurer la conformité des budgets informatiques avec les prévisions financière | D73: Exactitude des prévisions budgétaires | E73: Les prévisions budgétaires sont-elles basées sur des données précises ? | F73: pas | G73: Support justificatif des dépenses par service | H73: Diminution de la visibilité sur la consommation réelle | I73: Moyenne | J73: Risque de mauvaise allocation des ressources.
D74: Respect des limites budgétaires | E74: Les dépenses réelles respectent-elles les limites établies dans le budget ? | F74: pas | G74: État des besoins financiers informatiques | H74: Retard dans l’identification d’écarts financiers | I74: Élevée | J74: Impact sur la qualité des décisions financières.
D75: Suivi des écarts budgétaires | E75: Les écarts entre le budget et les dépenses réelles sont-ils régulièrement analysés ? | F75: pas | G75: Détail des lignes budgétaires allouées | H75: Non-respect des circuits d’approbation | I75: Moyenne | J75: Risque de perte de contrôle sur les dépenses.
D76: Suivi des écarts budgétaires | E76: Les dépenses sont-elles correctement documentées et justifiées ? | F76: pas | G76: Analyse des écarts réalisée en comité | H76: Biais de planification et sous-financement | I76: Élevée | J76: Peut ralentir la mise en œuvre des projets.
D77: Révisions budgétaires | E77: Des révisions budgétaires sont-elles effectuées en cas de changements significatifs ? | F77: Non | G77: Suivi détaillé des dépenses prévues | H77: Failles dans la remontée d'information financière | I77: Moyenne | J77: Conduit à une mauvaise visibilité financière.
C78: Optimiser les coûts informatiques tout en maintenant la qualité des services | D78: Analyse des coûts des projets | E78: Les coûts des projets informatiques sont-ils régulièrement évalués pour identifier les économies potentielles ? | F78: Non | G78: Historique des arbitrages budgétaires | H78: Absence de contrôle hiérarchique sur les coûts | I78: Élevée | J78: Peut générer des écarts non maîtrisés.
D79: Évaluation de la performance des fournisseurs | E79: Les fournisseurs sont-ils évalués en fonction de leur rapport coût/qualité ? | F79: Non | G79: Synthèse des plans de réajustement | H79: Décalage entre ressources affectées et dépenses | I79: Moyenne | J79: Risque d'engagements financiers non validés.
D80: Utilisation des ressources | E80: Les ressources informatiques (humaines et matérielles) sont-elles utilisées de manière optimale ? | F80: pas | G80: Traçabilité des approbations budgétaires | H80: Manque d’alignement budgétaire stratégique | I80: Élevée | J80: Problème de cohérence entre prévision et réalisation.
D81: Satisfaction des utilisateurs | E81: Les utilisateurs sont-ils satisfaits des services informatiques fournis en rapport avec les coûts ? | F81: Oui | G81: Pièces justificatives centralisées | H81: Omissions dans le reporting budgétaire | I81: Moyenne | J81: Retard dans la détection des anomalies budgétaires.
D82: Suivi des indicateurs de performance | E82: Des indicateurs de performance sont-ils en place pour évaluer l'efficacité des dépenses informatiques ? | F82: Non | G82: Procédure de contrôle budgétaire validée | H82: Risque de dépenses hors périmètre budgétaire | I82: Élevée | J82: Peut entraîner un dépassement de budget.
B83: Mesure et suivi de la performance informatique | C83: Vérifier que des objectifs de court, moyen et long termes existent et sont assignés à la DSI (approche BSC ?) et que ces objectifs sont déclinés au sein de l’entité | D83: Vérifier l'existence d'objectifs formels | E83: Existe-t-il des objectifs formels de court, moyen et long termes assignés à la DSI ? | F83: Oui | G83: Support justificatif des dépenses par service | H83: Diminution de la visibilité sur la consommation réelle | I83: Moyenne | J83: Risque de mauvaise allocation des ressources.
D84: Analyser la déclinaison des objectifs | E84: Comment ces objectifs sont-ils déclinés au sein de l'entité ? | F84: pas | G84: État des besoins financiers informatiques | H84: Retard dans l’identification d’écarts financiers | I84: Élevée | J84: Impact sur la qualité des décisions financières.
D85: Évaluer la clarté des objectifs | E85: Les objectifs sont-ils clairement définis et mesurables ? | F85: Oui | G85: Détail des lignes budgétaires allouées | H85: Non-respect des circuits d’approbation | I85: Moyenne | J85: Risque de perte de contrôle sur les dépenses.
D86: Vérifier l'implication des parties prenantes | E86: Les parties prenantes sont-elles impliquées dans la définition de ces objectifs ? | F86: Non | G86: Analyse des écarts réalisée en comité | H86: Biais de planification et sous-financement | I86: Élevée | J86: Peut ralentir la mise en œuvre des projets.
D87: Analyser le suivi des objectifs | E87: Comment le suivi des objectifs est-il assuré et rapporté ? | F87: pas | G87: Suivi détaillé des dépenses prévues | H87: Failles dans la remontée d'information financière | I87: Moyenne | J87: Conduit à une mauvaise visibilité financière.
C88: Vérifier l’existence d’un comité informatique regroupant les différentes directions de l’organisation | D88: Vérifier l'existence formelle du comité | E88: Existe-t-il un comité informatique formellement établi ? | F88: pas | G88: Historique des arbitrages budgétaires | H88: Absence de contrôle hiérarchique sur les coûts | I88: Élevée | J88: Peut générer des écarts non maîtrisés.
D89: Analyser la composition du comité | E89: Qui sont les membres du comité et quelles directions sont représentées ? | F89: Non | G89: Synthèse des plans de réajustement | H89: Décalage entre ressources affectées et dépenses | I89: Moyenne | J89: Risque d'engagements financiers non validés.
D90: Évaluer la fréquence des réunions | E90: À quelle fréquence le comité se réunit-il pour discuter des enjeux informatiques ? | F90: Non | G90: Traçabilité des approbations budgétaires | H90: Manque d’alignement budgétaire stratégique | I90: Élevée | J90: Problème de cohérence entre prévision et réalisation.
D91: Vérifier les objectifs du comité | E91: Quels sont les objectifs et missions du comité informatique ? | F91: Non | G91: Pièces justificatives centralisées | H91: Omissions dans le reporting budgétaire | I91: Moyenne | J91: Retard dans la détection des anomalies budgétaires.
D92: Analyser les décisions prises par le comité | E92: Comment les décisions prises par le comité sont-elles communiquées et mises en œuvre ? | F92: pas | G92: Procédure de contrôle budgétaire validée | H92: Risque de dépenses hors périmètre budgétaire | I92: Élevée | J92: Peut entraîner un dépassement de budget.
C93: Évaluer la pertinence des indicateurs de qualité et de performance ainsi que les moyens et outils de mesure | D93: Vérifier l'existence d'indicateurs formels | E93: Existe-t-il des indicateurs de qualité et de performance clairement définis et documentés ? | F93: Non | G93: Support justificatif des dépenses par service | H93: Diminution de la visibilité sur la consommation réelle | I93: Moyenne | J93: Risque de mauvaise allocation des ressources.
D94: Analyser la pertinence des indicateurs | E94: Les indicateurs choisis sont-ils pertinents pour évaluer les objectifs stratégiques de l'organisation ? | F94: Non | G94: État des besoins financiers informatiques | H94: Retard dans l’identification d’écarts financiers | I94: Élevée | J94: Impact sur la qualité des décisions financières.
D95: Évaluer les moyens de mesure | E95: Quels outils et méthodes sont utilisés pour mesurer ces indicateurs ? | F95: Oui | G95: Détail des lignes budgétaires allouées | H95: Non-respect des circuits d’approbation | I95: Moyenne | J95: Risque de perte de contrôle sur les dépenses.
D96: Vérifier la fréquence de mesure | E96: À quelle fréquence les indicateurs de performance sont-ils mesurés et rapportés ? | F96: Oui | G96: Analyse des écarts réalisée en comité | H96: Biais de planification et sous-financement | I96: Élevée | J96: Peut ralentir la mise en œuvre des projets.
D97: Analyser l'utilisation des résultats | E97: Comment les résultats des mesures sont-ils utilisés pour améliorer la qualité et la performance ? | F97: Oui | G97: Suivi détaillé des dépenses prévues | H97: Failles dans la remontée d'information financière | I97: Moyenne | J97: Conduit à une mauvaise visibilité financière.
C98: Vérifier que la DSI tient un tableau de bord (idéalement de type BSC) permettant un suivi consolidé de la performance (opérationnelle et financière) et de la qualité des prestations informatiques | D98: Vérifier l'existence d'un tableau de bord formel | E98: Existe-t-il un tableau de bord formel pour le suivi de la performance de la DSI ? | F98: pas | G98: Historique des arbitrages budgétaires | H98: Absence de contrôle hiérarchique sur les coûts | I98: Élevée | J98: Peut générer des écarts non maîtrisés.
D99: Évaluer le type de tableau de bord | E99: Le tableau de bord est-il de type BSC (Balanced Scorecard) ou un autre type ? | F99: Non | G99: Synthèse des plans de réajustement | H99: Décalage entre ressources affectées et dépenses | I99: Moyenne | J99: Risque d'engagements financiers non validés.
D100: Analyser la pertinence des indicateurs | E100: Les indicateurs utilisés dans le tableau de bord sont-ils pertinents pour mesurer la performance et la qualité ? | F100: Oui | G100: Traçabilité des approbations budgétaires | H100: Manque d’alignement budgétaire stratégique | I100: Élevée | J100: Problème de cohérence entre prévision et réalisation.
D101: Vérifier la fréquence des mises à jour | E101: À quelle fréquence le tableau de bord est-il mis à jour et communiqué ? | F101: pas | G101: Pièces justificatives centralisées | H101: Omissions dans le reporting budgétaire | I101: Moyenne | J101: Retard dans la détection des anomalies budgétaires.
...

Sheet 4,3-contrôle-des-projets-inf
A1: Domaines | B1: Points de contrôle | C1: Objectifs de contrôle | D1: critères d'évaluation | E1: Questions d'évaluation | F1: réponses | G1: Document Requis | H1: Risque | I1: Criticité | J1: Conséquence
A3: contrôle des projets informatiques | B3: Objectifs et enjeux du projet | C3: S’assurer qu’une étude de la valeur et des études d'opportunité et d'impacts ont été réalisées | D3: Les documents d'études sont disponibles et validés | E3: Les documents d'études sont-ils validés ? | F3: oui | G3: Rapport d'étude | H3: Non-respect des délais | I3: Élevée | J3: Retard dans le projet
D4: L'analyse de valeur est pertinente par rapport aux besoins | E4: L'analyse est-elle cohérente avec les objectifs ? | F4: oui | G4: Document de bilan | H4: Manque d'optimisation | I4: Élevée | J4: Inefficacité du système
D5: Les impacts sur l'organisation sont identifiés | E5: Les impacts sont-ils listés dans le rapport ? | F5: non | G5: Procès-verbal | H5: Coûts supplémentaires | I5: Élevée | J5: Dépassement budgétaire
D6: Les opportunités sont quantifiées et mesurées | E6: Les bénéfices attendus sont-ils mesurés ? | F6: oui | G6: Document de projet | H6: Malentendu entre parties | I6: Moyenne | J6: Conflits dans l'équipe
D7: Les parties prenantes ont été consultées | E7: Les acteurs ont-ils été impliqués ? | F7: oui | G7: Cahier des charges | H7: Mauvaise compréhension | I7: Moyenne | J7: Direction erronée
C8: S’assurer qu’un bilan critique des processus existants a été effectué | D8: Les documents d'études sont disponibles et validés | E8: Les documents d'études sont-ils validés ? | F8: oui | G8: Cahier des charges | H8: Incomplétude des besoins | I8: Élevée | J8: Non-satisfaction des utilisateurs
D9: L'analyse de valeur est pertinente par rapport aux besoins | E9: L'analyse est-elle cohérente avec les objectifs ? | F9: non | G9: Analyse technique | H9: Échec de l'intégration | I9: Élevée | J9: Augmentation des coûts
D10: Les impacts sur l'organisation sont identifiés | E10: Les impacts sont-ils listés dans le rapport ? | F10: oui | G10: Compte-rendu de réunion | H10: Manque de soutien | I10: Moyenne | J10: Progrès limités
D11: Les opportunités sont quantifiées et mesurées | E11: Les bénéfices attendus sont-ils mesurés ? | F11: non | G11: Profil de compétences | H11: Sous-performance | I11: Élevée | J11: Retards dans l'exécution
D12: Les parties prenantes ont été consultées | E12: Les acteurs ont-ils été impliqués ? | F12: oui | G12: Rapport d'étude | H12: Décision erronée | I12: Élevée | J12: Risques non évalués
C13: S’assurer que le choix de recourir à un nouveau système est obtenu après optimisation des processus concernés et vérification que cette optimisation ne suffit pas à apporter par elle-même les gains de performance attendus | D13: Optimisation validée | E13: L'optimisation des processus a-t-elle été validée ? | F13: Non | G13: Rapport d'optimisation | H13: Coûts supplémentaires | I13: Élevée | J13: Dépassement budgétaire
D14: Solution évaluée | E14: La solution choisie a-t-elle été évaluée ? | F14: Oui | G14: Rapport d'évaluation | H14: Non-conformité | I14: Élevée | J14: Risques non évalués
D15: Gains de performance | E15: Les gains de performance attendus sont-ils atteints ? | F15: Non | G15: Document de performance | H15: Échec de l'implémentation | I15: Élevée | J15: Inefficacité du système
D16: Coûts analysés | E16: Les coûts du nouveau système ont-ils été analysés ? | F16: Oui | G16: Analyse des coûts | H16: Dépassement budgétaire | I16: Élevée | J16: Budget insuffisant
D17: Impact évalué | E17: L'impact du nouveau système a-t-il été évalué ? | F17: Oui | G17: Rapport d'impact | H17: Non-adhérence | I17: Moyenne | J17: Perturbation du système
C18: S’assure que les objectifs et périmètres du projet sont définis, partagés et stabilisés | D18: Objectifs définis | E18: Les objectifs du projet sont-ils bien définis ? | F18: Oui | G18: Document de projet | H18: Malentendu | I18: Élevée | J18: Conflits de priorités
D19: Périmètre stabilisé | E19: Le périmètre du projet est-il stabilisé ? | F19: Non | G19: Document de périmètre | H19: Changements fréquents | I19: Élevée | J19: Délais allongés
D20: Communication claire | E20: La communication sur les objectifs est-elle claire ? | F20: Oui | G20: Compte-rendu de réunion | H20: Mauvaise compréhension | I20: Moyenne | J20: Risques non évalués
D21: Validation des parties | E21: Les parties prenantes ont-elles validé les objectifs ? | F21: Oui | G21: Document de validation | H21: Opposition | I21: Moyenne | J21: Progrès limités
D22: Suivi des objectifs | E22: Un suivi des objectifs est-il mis en place ? | F22: Oui | G22: Rapport de suivi | H22: Non-respect des délais | I22: Élevée | J22: Retard dans le projet
C23: S’assurer que les principales orientations du système cible ont été explicitées | D23: Orientations claires | E23: Les orientations du système cible sont-elles claires ? | F23: Oui | G23: Cahier des charges | H23: Mauvaise compréhension | I23: Élevée | J23: Direction erronée
D24: Alignment stratégique | E24: Le système cible est-il aligné avec la stratégie ? | F24: Oui | G24: Document stratégique | H24: Disparité | I24: Élevée | J24: Confusion dans l'exécution
D25: Feedback intégré | E25: Le retour des utilisateurs a-t-il été intégré ? | F25: Non | G25: Rapport de feedback | H25: Insatisfaction | I25: Élevée | J25: Adoption limitée
D26: Validité technique | E26: La validité technique du système cible est-elle vérifiée ? | F26: Oui | G26: Rapport technique | H26: Échec d'implémentation | I26: Élevée | J26: Risques non évalués
D27: Délais réalistes | E27: Les délais pour le système cible sont-ils réalistes ? | F27: Oui | G27: Plan de projet | H27: Retard potentiel | I27: Moyenne | J27: Délais allongés
C28: S’assurer que les principaux acteurs sont identifiés | D28: Acteurs principaux | E28: Les principaux acteurs ont-ils été identifiés ? | F28: Oui | G28: Liste des acteurs | H28: Mauvaise compréhension | I28: Moyenne | J28: Direction erronée
D29: Responsabilités claires | E29: Les responsabilités des acteurs sont-elles claires ? | F29: Non | G29: Document de responsabilités | H29: Conflits | I29: Élevée | J29: Progrès limités
D30: Engagement des acteurs | E30: Les acteurs sont-ils engagés dans le projet ? | F30: Oui | G30: Compte-rendu de réunion | H30: Manque de motivation | I30: Moyenne | J30: Retards dans l'exécution
D31: Feedback intégré | E31: Le feedback des acteurs a-t-il été intégré ? | F31: Oui | G31: Rapport de feedback | H31: Insatisfaction | I31: Moyenne | J31: Risques non évalués
D32: Formation adéquate | E32: Les acteurs ont-ils reçu une formation adéquate ? | F32: Non | G32: Rapport de formation | H32: Sous-performance | I32: Élevée | J32: Inefficacité du système
C33: S’assurer que les coûts sont évalués | D33: Coûts estimés | E33: Les coûts du projet ont-ils été estimés ? | F33: Oui | G33: Estimation des coûts | H33: Dépassement budgétaire | I33: Élevée | J33: Budget insuffisant
D34: Suivi des coûts | E34: Un suivi des coûts est-il mis en place ? | F34: Oui | G34: Rapport de suivi | H34: Non-respect des délais | I34: Élevée | J34: Retard dans le projet
D35: Comparaison de coûts | E35: Les coûts ont-ils été comparés aux prévisions ? | F35: Non | G35: Rapport de comparaison | H35: Surprises financières | I35: Élevée | J35: Coûts cachés
D36: Validation des coûts | E36: Les coûts ont-ils été validés par la direction ? | F36: Oui | G36: Document de validation | H36: Contestation | I36: Moyenne | J36: Progrès limités
D37: Rapport détaillé | E37: Un rapport détaillé des coûts est-il disponible ? | F37: Oui | G37: Rapport de coûts | H37: Manque de transparence | I37: Élevée | J37: Conflits dans l'équipe
C38: S’assurer que les liens et impacts avec des projets connexes et les infrastructures (Datacenter, réseaux, etc.) sont pris en compte | D38: Liens identifiés | E38: Les liens avec des projets connexes ont-ils été identifiés ? | F38: Oui | G38: Document de liaison | H38: Non-conformité | I38: Élevée | J38: Perturbation du système
D39: Impact évalué | E39: L'impact des projets connexes a-t-il été évalué ? | F39: Non | G39: Rapport d'impact | H39: Risques non évalués | I39: Élevée | J39: Confusion dans l'exécution
D40: Coordination établie | E40: La coordination avec d'autres projets est-elle établie ? | F40: Oui | G40: Document de coordination | H40: Manque de synergie | I40: Moyenne | J40: Progrès limités
D41: Ressources allouées | E41: Les ressources pour les projets connexes sont-elles allouées ? | F41: Oui | G41: Plan de ressources | H41: Conflits d'allocation | I41: Moyenne | J41: Retards dans l'exécution
D42: Risques identifiés | E42: Les risques liés aux projets connexes ont-ils été identifiés ? | F42: Non | G42: Rapport de risques | H42: Surprise financière | I42: Élevée | J42: Coûts cachés
B43: Étude d'opportunité et expression des besoins | C43: S’assurer que l'expression détaillée des besoins est formalisée dans un cahier des charges fait par la MOA | D43: Le cahier des charges est rédigé par la MOA | E43: Le cahier des charges est-il bien produit par la MOA ? | F43: oui | G43: Cahier des charges signé | H43: Spécifications incomplètes ou biaisées | I43: élevée | J43: Mauvais alignement entre solution livrée et attentes
D44: Les besoins sont validés par les utilisateurs | E44: Les utilisateurs ont-ils validé les besoins ? | F44: oui | G44: PV de validation des besoins | H44: Mauvaise compréhension des besoins réels | I44: élevée | J44: L’application livrée peut être rejetée par les utilisateurs
D45: Le périmètre est défini clairement | E45: Le périmètre du projet est-il défini ? | F45: non | G45: Fiche de cadrage du projet | H45: Débordement ou glissement de périmètre | I45: moyenne | J45: Augmentation imprévue des coûts et des délais
D46: Le planning de réalisation est précisé dans le cahier des charges | E46: Le planning est-il inclus dans le cahier des charges ? | F46: oui | G46: Cahier des charges finalisé | H46: Retards liés à un manque de planification | I46: moyenne | J46: Dérives dans la gestion du projet
D47: Les contraintes techniques sont identifiées | E47: Les contraintes techniques ont-elles été identifiées ? | F47: non | G47: Spécifications techniques | H47: Non-prise en compte des limites du SI actuel | I47: élevée | J47: Incompatibilités avec l’environnement technique
C48: S’assurer que le cahier des charges préconise une solution fonctionnellement et techniquement pertinente au regard des besoins exprimés | D48: Conformité aux besoins | E48: Le cahier des charges préconise-t-il une solution fonctionnellement et techniquement pertinente au regard des besoins exprimés ? | F48: Oui | G48: Cahier des charges | H48: Omission d'informations | I48: Élevée | J48: Mauvaise satisfaction utilisateur
D49: Documentation des solutions | E49: Les solutions proposées sont-elles bien documentées ? | F49: Oui | G49: Rapport de solutions | H49: Manque de clarté | I49: Élevée | J49: Difficultés d'audit
D50: Feedback intégré | E50: Le feedback sur la solution a-t-il été pris en compte ? | F50: Oui | G50: Rapport de feedback | H50: Ignorance des retours | I50: Moyenne | J50: Améliorations non appliquées
D51: Validation par les parties prenantes | E51: La solution a-t-elle été validée par les parties prenantes ? | F51: Oui | G51: Rapport de validation | H51: Manque de consensus | I51: Élevée | J51: Risques non identifiés
D52: Suivi des besoins | E52: Un suivi des besoins exprimés est-il effectué ? | F52: Non | G52: Rapport de suivi | H52: Non-respect des délais | I52: Élevée | J52: Risques de non-conformité
C53: S’assurer que les exigences utilisateurs, les populations ciblées, les options et principes de gestion retenus sont précisés et priorisés | D53: Précision des exigences | E53: Les exigences utilisateurs, les populations ciblées, les options et principes de gestion retenus sont-ils précisés et priorisés ? | F53: Oui | G53: Document des exigences | H53: Omission d'informations | I53: Élevée | J53: Mauvaise gestion des attentes
D54: Documentation des priorités | E54: Les priorités des exigences sont-elles bien documentées ? | F54: Oui | G54: Rapport de priorisation | H54: Manque de clarté | I54: Élevée | J54: Difficultés d'audit
D55: Feedback intégré | E55: Le feedback sur les exigences a-t-il été pris en compte ? | F55: Oui | G55: Rapport de feedback | H55: Ignorance des retours | I55: Moyenne | J55: Améliorations non appliquées
D56: Validation par les parties prenantes | E56: Les exigences ont-elles été validées par les parties prenantes ? | F56: Oui | G56: Rapport de validation | H56: Manque de consensus | I56: Élevée | J56: Risques non identifiés
D57: Suivi des modifications | E57: Un suivi des modifications des exigences est-il effectué ? | F57: Non | G57: Rapport de suivi | H57: Non-respect des délais | I57: Élevée | J57: Risques de non-conformité
C58: S’assurer que le projet est cohérent avec le plan directeur informatique | D58: Conformité au plan | E58: Le projet est-il cohérent avec le plan directeur informatique ? | F58: Oui | G58: Plan directeur | H58: Omission d'informations | I58: Élevée | J58: Mauvaise alignement stratégique
D59: Documentation des alignements | E59: Les alignements avec le plan directeur sont-ils bien documentés ? | F59: Oui | G59: Rapport d'alignement | H59: Manque de clarté | I59: Élevée | J59: Difficultés d'audit
D60: Feedback intégré | E60: Le feedback sur la cohérence a-t-il été pris en compte ? | F60: Oui | G60: Rapport de feedback | H60: Ignorance des retours | I60: Moyenne | J60: Améliorations non appliquées
D61: Validation par les parties prenantes | E61: La cohérence a-t-elle été validée par les parties prenantes ? | F61: Oui | G61: Rapport de validation | H61: Manque de consensus | I61: Élevée | J61: Risques non identifiés
D62: Suivi des exigences | E62: Un suivi des exigences du plan directeur est-il effectué ? | F62: Non | G62: Rapport de suivi | H62: Non-respect des délais | I62: Élevée | J62: Risques de non-conformité
C63: S’assurer que le projet est cohérent avec le SI actuel ou futur | D63: Conformité au SI | E63: Le projet est-il cohérent avec le système d'information actuel ou futur ? | F63: Oui | G63: Document de cohérence | H63: Omission d'informations | I63: Élevée | J63: Mauvaise intégration
D64: Documentation des alignements | E64: Les alignements avec le SI sont-ils bien documentés ? | F64: Oui | G64: Rapport d'alignement | H64: Manque de clarté | I64: Élevée | J64: Difficultés d'audit
D65: Feedback intégré | E65: Le feedback sur la cohérence avec le SI a-t-il été pris en compte ? | F65: Oui | G65: Rapport de feedback | H65: Ignorance des retours | I65: Moyenne | J65: Améliorations non appliquées
D66: Validation par les parties prenantes | E66: La cohérence a-t-elle été validée par les parties prenantes ? | F66: Oui | G66: Rapport de validation | H66: Manque de consensus | I66: Élevée | J66: Risques non identifiés
D67: Suivi des exigences | E67: Un suivi des exigences du SI est-il effectué ? | F67: Non | G67: Rapport de suivi | H67: Non-respect des délais | I67: Élevée | J67: Risques de non-conformité
C68: S’assurer que la direction est bien impliquée dans le projet | D68: Direction impliquée | E68: La direction est-elle impliquée dans le projet ? | F68: Oui | G68: Compte-rendu de réunion | H68: Manque de soutien | I68: Moyenne | J68: Progrès limités
D69: Communication claire | E69: La communication de la direction est-elle claire ? | F69: Non | G69: Compte-rendu de réunion | H69: Mauvaise compréhension | I69: Élevée | J69: Risques non évalués
D70: Feedback intégré | E70: Le feedback de la direction a-t-il été intégré ? | F70: Oui | G70: Rapport de feedback | H70: Insatisfaction | I70: Moyenne | J70: Progrès limités
D71: Objectifs partagés | E71: Les objectifs de la direction sont-ils partagés ? | F71: Oui | G71: Document de projet | H71: Malentendu | I71: Moyenne | J71: Conflits dans l'équipe
D72: Suivi des engagements | E72: Le suivi des engagements de la direction est-il en place ? | F72: Non | G72: Rapport de suivi | H72: Non-respect des délais | I72: Élevée | J72: Retards dans le projet
C73: S’assurer que les acteurs de l'équipe projet et leurs responsabilités sont bien identifiés | D73: Acteurs identifiés | E73: Les acteurs de l'équipe projet sont-ils bien identifiés ? | F73: Oui | G73: Liste des acteurs | H73: Mauvaise communication | I73: Moyenne | J73: Direction erronée
D74: Responsabilités claires | E74: Les responsabilités des acteurs sont-elles clairement définies ? | F74: Non | G74: Document de responsabilités | H74: Confusion de rôle | I74: Élevée | J74: Retards dans l'exécution
D75: Engagement des acteurs | E75: Les acteurs sont-ils engagés dans le projet ? | F75: Oui | G75: Compte-rendu de réunion | H75: Manque de motivation | I75: Moyenne | J75: Progrès limités
D76: Feedback intégré | E76: Le feedback des acteurs a-t-il été intégré ? | F76: Oui | G76: Rapport de feedback | H76: Insatisfaction | I76: Moyenne | J76: Risques non évalués
D77: Formation adéquate | E77: Les acteurs ont-ils reçu une formation adéquate ? | F77: Non | G77: Rapport de formation | H77: Sous-performance | I77: Élevée | J77: Inefficacité du projet
C78: S’assurer que les compétences du personnel sont en adéquation avec les tâches | D78: Compétences adéquates | E78: Les compétences du personnel sont-elles appropriées pour les tâches ? | F78: Oui | G78: Profil de compétences | H78: Sous-performance | I78: Élevée | J78: Inefficacité du projet
D79: Formation continue | E79: Une formation continue est-elle prévue ? | F79: Non | G79: Plan de formation | H79: Manque de développement | I79: Élevée | J79: Retards dans l'exécution
D80: Évaluation des compétences | E80: Les compétences sont-elles régulièrement évaluées ? | F80: Oui | G80: Rapport d'évaluation | H80: Inadéquation | I80: Moyenne | J80: Risques non évalués
D81: Adaptation aux tâches | E81: Les compétences sont-elles adaptées aux tâches à réaliser ? | F81: Oui | G81: Profil de compétences | H81: Inadéquation | I81: Élevée | J81: Inefficacité du projet
D82: Plan de succession | E82: Un plan de succession est-il en place ? | F82: Non | G82: Document de succession | H82: Manque de continuité | I82: Élevée | J82: Risques de perte de connaissance
C83: S’assurer qu’une étude d'opportunité est validée | D83: Étude validée | E83: L'étude d'opportunité a-t-elle été validée ? | F83: Non | G83: Rapport d'étude | H83: Décision erronée | I83: Élevée | J83: Risques non évalués
D84: Analyse des bénéfices | E84: Les bénéfices de l'étude ont-ils été analysés ? | F84: Oui | G84: Rapport d'analyse | H84: Non-conformité | I84: Élevée | J84: Perturbation du projet
D85: Feedback des parties prenantes | E85: Le feedback des parties prenantes a-t-il été intégré ? | F85: Non | G85: Document de feedback | H85: Insatisfaction | I85: Élevée | J85: Conflits d'intérêt
D86: Plan d'action défini | E86: Un plan d'action a-t-il été défini à partir de l'étude ? | F86: Oui | G86: Plan d'action | H86: Manque de clarté | I86: Moyenne | J86: Retards dans l'exécution
D87: Suivi des recommandations | E87: Un suivi des recommandations de l'étude est-il prévu ? | F87: Non | G87: Rapport de suivi | H87: Non-respect des délais | I87: Élevée | J87: Risques non évalués
B88: Planification | C88: S’assurer qu’il existe un planning directeur commun à tout le projet | D88: Un document de planning global est formalisé | E88: Le planning directeur est-il disponible et approuvé ? | F88: Oui | G88: Planning directeur validé | H88: Mauvaise coordination | I88: Moyenne | J88: Retards dans les livraisons
D89: Le planning est partagé avec toutes les parties prenantes | E89: Le planning est-il accessible à tous les acteurs concernés ? | F89: Oui | G89: Registre de diffusion du planning | H89: Communication incomplète | I89: Moyenne | J89: Incompréhensions sur les délais
D90: Le planning est mis à jour régulièrement | E90: Le planning a-t-il été mis à jour récemment ? | F90: Non | G90: Historique de versions du planning | H90: Utilisation de versions obsolètes | I90: Élevée | J90: Mauvais suivi des échéances
D91: Le planning inclut toutes les phases du projet | E91: Toutes les phases sont-elles couvertes dans le planning ? | F91: Oui | G91: Planning structuré par phases | H91: Oubli d’étapes clés | I91: Moyenne | J91: Délais non anticipés
D92: Le planning inclut les dépendances entre tâches | E92: Les dépendances sont-elles bien identifiées ? | F92: Oui | G92: Diagramme de Gantt | H92: Mauvaise priorisation | I92: Moyenne | J92: Goulots d’étranglement
C93: S’assurer qu’il existe un plan de projet initial | D93: Le planning directeur est formalisé et diffusé | E93: Le planning directeur est-il formellement rédigé et partagé ? | F93: Oui | G93: Planning directeur | H93: Manque de coordination entre équipes | I93: Élevée | J93: Retards cumulés
D94: Il est validé par les parties prenantes | E94: Le planning a-t-il été validé par tous les acteurs concernés ? | F94: Oui | G94: PV de validation | H94: Non-adhésion au planning | I94: Moyenne | J94: Modifications fréquentes
D95: Il est mis à jour en fonction de l'avancement | E95: Le planning est-il révisé régulièrement ? | F95: Non | G95: Historique de planning | H95: Décalage entre planification et réalité | I95: Élevée | J95: Irréalisme dans le pilotage
D96: Il prend en compte toutes les phases du projet | E96: Toutes les phases du projet sont-elles planifiées ? | F96: Oui | G96: Planning global | H96: Oubli de certaines étapes | I96: Moyenne | J96: Omissions dans l'exécution
D97: Il est partagé sur un support commun | E97: Le planning est-il accessible à tous ? | F97: Oui | G97: Plateforme collaborative | H97: Information non synchronisée | I97: Moyenne | J97: Incohérences dans les délais
C98: S’assurer que ce plan de projet a été révisé | D98: Le plan initial contient les objectifs du projet | E98: Le plan décrit-il clairement les objectifs ? | F98: Oui | G98: Plan de projet initial | H98: Vision floue du projet | I98: Moyenne | J98: Mauvaise orientation
D99: Les jalons principaux y sont identifiés | E99: Les étapes clés sont-elles bien définies ? | F99: Oui | G99: Planification des jalons | H99: Suivi difficile | I99: Moyenne | J99: Décalage du calendrier
D100: Les délais sont estimés | E100: Le plan donne-t-il une estimation de durée ? | F100: Non | G100: Chronogramme | H100: Imprécision temporelle | I100: Élevée | J100: Bousculade des tâches
D101: Les principales ressources sont identifiées | E101: Le plan indique-t-il les ressources clés ? | F101: Oui | G101: Feuille de route RH | H101: Planification incomplète | I101: Moyenne | J101: Ressources mal allouées
...

Sheet 4.4 audit du support ... 
A1: Domaines | B1: Points de contrôle | C1: Objectifs de contrôle | D1: critères d'évaluation | E1: Questions d'évaluation | F1: Réponses | G1: Documents Requis | H1: Risques | I1: Criticités | J1: Conséquences
A3: audit du support utilisateur et de la gestion du park | B3: Fonction support : audit fiabilité et sécurité | C3: S’assurer qu’une structure de centre d’assistance (help-desk) (HD) est mise en place | D3: Existence du help-desk | E3: Une structure de centre d’assistance (help-desk) est-elle mise en place ? | F3: Oui | G3: Document de création | H3: Omission d'informations | I3: Élevée | J3: Mauvaise gestion des demandes
D4: Accessibilité du service | E4: Le service est-il facilement accessible aux utilisateurs ? | F4: Oui | G4: Manuel d'accès | H4: Manque de visibilité | I4: Moyenne | J4: Retards dans le traitement
D5: Feedback intégré | E5: Le feedback sur le service de help-desk a-t-il été pris en compte ? | F5: Oui | G5: Rapport de feedback | H5: Ignorance des retours | I5: Moyenne | J5: Améliorations non appliquées
D6: Validation par les parties prenantes | E6: La structure a-t-elle été validée par les parties prenantes ? | F6: Oui | G6: Rapport de validation | H6: Manque de consensus | I6: Élevée | J6: Risques non identifiés
D7: Suivi des demandes | E7: Un suivi des demandes traitées est-il effectué ? | F7: Non | G7: Rapport de suivi | H7: Non-respect des délais | I7: Élevée | J7: Risques de non-conformité
C8: S’assurer qu’une procédure de gestion des demandes d’assistance est diffusée et connue des utilisateurs | D8: Diffusion de la procédure | E8: Une procédure de gestion des demandes d’assistance est-elle diffusée et connue des utilisateurs ? | F8: Oui | G8: Document de procédure | H8: Omission d'informations | I8: Élevée | J8: Mauvaise gestion des demandes
D9: Accessibilité de la procédure | E9: La procédure est-elle facilement accessible aux utilisateurs ? | F9: Oui | G9: Manuel d'accès | H9: Manque de visibilité | I9: Moyenne | J9: Retards dans le traitement
D10: Feedback intégré | E10: Le feedback sur la procédure a-t-il été pris en compte ? | F10: Oui | G10: Rapport de feedback | H10: Ignorance des retours | I10: Moyenne | J10: Améliorations non appliquées
D11: Validation par les parties prenantes | E11: La procédure a-t-elle été validée par les parties prenantes ? | F11: Oui | G11: Rapport de validation | H11: Manque de consensus | I11: Élevée | J11: Risques non identifiés
D12: Suivi des demandes | E12: Un suivi des demandes d’assistance est-il effectué ? | F12: Non | G12: Rapport de suivi | H12: Non-respect des délais | I12: Élevée | J12: Risques de non-conformité
C13: S’assurer qu’une procédure d'escalade mise en place | D13: Existence de la procédure | E13: Une procédure d'escalade est-elle mise en place ? | F13: Oui | G13: Document d'escalade | H13: Omission d'informations | I13: Élevée | J13: Mauvaise gestion des demandes
D14: Accessibilité de la procédure | E14: La procédure d'escalade est-elle facilement accessible ? | F14: Oui | G14: Manuel d'accès | H14: Manque de visibilité | I14: Moyenne | J14: Retards dans le traitement
D15: Feedback intégré | E15: Le feedback sur la procédure d'escalade a-t-il été pris en compte ? | F15: Oui | G15: Rapport de feedback | H15: Ignorance des retours | I15: Moyenne | J15: Améliorations non appliquées
D16: Validation par les parties prenantes | E16: La procédure a-t-elle été validée par les parties prenantes ? | F16: Oui | G16: Rapport de validation | H16: Manque de consensus | I16: Élevée | J16: Risques non identifiés
D17: Suivi des escalades | E17: Un suivi des escalades est-il effectué ? | F17: Non | G17: Rapport de suivi | H17: Non-respect des délais | I17: Élevée | J17: Risques de non-conformité
C18: S’assurer de la couverture géographique du HD | D18: Existence d'une couverture | E18: Le help-desk a-t-il une couverture géographique adéquate ? | F18: Oui | G18: Document de couverture | H18: Omission d'informations | I18: Élevée | J18: Mauvaise accessibilité
D19: Documentation de la couverture | E19: La couverture géographique est-elle bien documentée ? | F19: Oui | G19: Rapport de couverture | H19: Manque de clarté | I19: Élevée | J19: Difficultés d'audit
D20: Feedback intégré | E20: Le feedback sur la couverture a-t-il été pris en compte ? | F20: Oui | G20: Rapport de feedback | H20: Ignorance des retours | I20: Moyenne | J20: Améliorations non appliquées
D21: Validation par les parties prenantes | E21: La couverture a-t-elle été validée par les parties prenantes ? | F21: Oui | G21: Rapport de validation | H21: Manque de consensus | I21: Élevée | J21: Risques non identifiés
D22: Suivi de la couverture | E22: Un suivi de la couverture géographique est-il effectué ? | F22: Non | G22: Rapport de suivi | H22: Non-respect des délais | I22: Élevée | J22: Risques de non-conformité
C23: S’assurer qu’un outil est implémenté pour la prise d'appel et le suivi des tickets | D23: Existence de l'outil | E23: Un outil est-il implémenté pour la prise d'appel et le suivi des tickets ? | F23: Oui | G23: Document de l'outil | H23: Omission d'informations | I23: Élevée | J23: Mauvaise gestion des tickets
D24: Accessibilité de l'outil | E24: L'outil est-il facilement accessible aux utilisateurs ? | F24: Oui | G24: Manuel d'utilisation | H24: Manque de visibilité | I24: Moyenne | J24: Retards dans le traitement
D25: Formation à l'utilisation | E25: Les utilisateurs de l'outil ont-ils été formés à son utilisation ? | F25: Oui | G25: Document de formation | H25: Manque de préparation | I25: Élevée | J25: Difficultés d'utilisation
D26: Feedback intégré | E26: Le feedback sur l'outil a-t-il été pris en compte ? | F26: Oui | G26: Rapport de feedback | H26: Ignorance des retours | I26: Moyenne | J26: Améliorations non appliquées
D27: Validation par les parties prenantes | E27: L'outil a-t-il été validé par les parties prenantes ? | F27: Oui | G27: Rapport de validation | H27: Manque de consensus | I27: Élevée | J27: Risques non identifiés
C28: S’assurer que des critères à renseigner pour la qualification des tickets existent | D28: Existence des critères | E28: Des critères à renseigner pour la qualification des tickets existent-ils ? | F28: Oui | G28: Document des critères | H28: Omission d'informations | I28: Élevée | J28: Mauvaise gestion des tickets
D29: Documentation des critères | E29: Les critères de qualification sont-ils bien documentés ? | F29: Oui | G29: Rapport de documentation | H29: Manque de clarté | I29: Élevée | J29: Difficultés d'audit
D30: Feedback intégré | E30: Le feedback sur les critères a-t-il été pris en compte ? | F30: Oui | G30: Rapport de feedback | H30: Ignorance des retours | I30: Moyenne | J30: Améliorations non appliquées
D31: Validation par les parties prenantes | E31: Les critères ont-ils été validés par les parties prenantes ? | F31: Oui | G31: Rapport de validation | H31: Manque de consensus | I31: Élevée | J31: Risques non identifiés
D32: Suivi des critères | E32: Un suivi des critères de qualification est-il effectué ? | F32: Non | G32: Rapport de suivi | H32: Non-respect des délais | I32: Élevée | J32: Risques de non-conformité
C33: s'assurer qu’il existe une liste de questions à dérouler lors d'un appel afin préciser au mieux la demande de l'utilisateur | D33: Existence de la liste | E33: Existe-t-il une liste de questions à dérouler lors d'un appel afin de préciser au mieux la demande de l'utilisateur ? | F33: Oui | G33: Document de questions | H33: Omission d'informations | I33: Élevée | J33: Mauvaise gestion des demandes
D34: Documentation des questions | E34: La liste de questions est-elle bien documentée ? | F34: Oui | G34: Rapport de documentation | H34: Manque de clarté | I34: Élevée | J34: Difficultés d'audit
D35: Feedback intégré | E35: Le feedback sur la liste de questions a-t-il été pris en compte ? | F35: Oui | G35: Rapport de feedback | H35: Ignorance des retours | I35: Moyenne | J35: Améliorations non appliquées
D36: Validation par les parties prenantes | E36: La liste a-t-elle été validée par les parties prenantes ? | F36: Oui | G36: Rapport de validation | H36: Manque de consensus | I36: Élevée | J36: Risques non identifiés
D37: Suivi des questions | E37: Un suivi des questions posées est-il effectué ? | F37: Non | G37: Rapport de suivi | H37: Non-respect des délais | I37: Élevée | J37: Risques de non-conformité
C38: S’assurer que les problèmes sont gérés | D38: Suivi des problèmes | E38: Les problèmes sont-ils gérés de manière efficace ? | F38: Oui | G38: Rapport de gestion des problèmes | H38: Omission d'informations | I38: Élevée | J38: Mauvaise résolution des problèmes
D39: Documentation des problèmes | E39: Les problèmes sont-ils bien documentés ? | F39: Oui | G39: Document de problèmes | H39: Manque de clarté | I39: Élevée | J39: Difficultés d'audit
D40: Feedback intégré | E40: Le feedback sur la gestion des problèmes a-t-il été pris en compte ? | F40: Oui | G40: Rapport de feedback | H40: Ignorance des retours | I40: Moyenne | J40: Améliorations non appliquées
D41: Validation par les parties prenantes | E41: La gestion des problèmes a-t-elle été validée par les parties prenantes ? | F41: Oui | G41: Rapport de validation | H41: Manque de consensus | I41: Élevée | J41: Risques non identifiés
D42: Suivi des résolutions | E42: Un suivi des résolutions des problèmes est-il effectué ? | F42: Non | G42: Rapport de suivi | H42: Non-respect des délais | I42: Élevée | J42: Risques de non-conformité
C43: S’assurer qu’un processus de gestion des problèmes existe | D43: Existence du processus | E43: Un processus de gestion des problèmes existe-t-il ? | F43: Oui | G43: Document de processus | H43: Omission d'informations | I43: Élevée | J43: Mauvaise gestion des problèmes
D44: Accessibilité du processus | E44: Le processus est-il facilement accessible aux utilisateurs ? | F44: Oui | G44: Manuel d'accès | H44: Manque de visibilité | I44: Moyenne | J44: Retards dans la gestion
D45: Feedback intégré | E45: Le feedback sur le processus a-t-il été pris en compte ? | F45: Oui | G45: Rapport de feedback | H45: Ignorance des retours | I45: Moyenne | J45: Améliorations non appliquées
D46: Validation par les parties prenantes | E46: Le processus a-t-il été validé par les parties prenantes ? | F46: Oui | G46: Rapport de validation | H46: Manque de consensus | I46: Élevée | J46: Risques non identifiés
D47: Suivi des modifications | E47: Un suivi des modifications du processus est-il effectué ? | F47: Non | G47: Rapport de suivi | H47: Non-respect des délais | I47: Élevée | J47: Risques de non-conformité
B48: Fonction support : audit d'efficacité et de performance | C48: S’assurer qu’il existe une aide à la saisie pour la saisie des tickets | D48: Existence de l'aide | E48: Existe-t-il une aide à la saisie pour la saisie des tickets ? | F48: Oui | G48: Document d'aide | H48: Omission d'informations | I48: Élevée | J48: Mauvaise saisie des tickets
D49: Accessibilité de l'aide | E49: L'aide est-elle facilement accessible aux utilisateurs ? | F49: Oui | G49: Manuel d'accès | H49: Manque de visibilité | I49: Moyenne | J49: Retards dans le traitement
D50: Feedback intégré | E50: Le feedback sur l'aide à la saisie a-t-il été pris en compte ? | F50: Oui | G50: Rapport de feedback | H50: Ignorance des retours | I50: Moyenne | J50: Améliorations non appliquées
D51: Validation par les parties prenantes | E51: L'aide a-t-elle été validée par les parties prenantes ? | F51: Oui | G51: Rapport de validation | H51: Manque de consensus | I51: Élevée | J51: Risques non identifiés
D52: Suivi des améliorations | E52: Un suivi des améliorations de l'aide est-il effectué ? | F52: Non | G52: Rapport de suivi | H52: Non-respect des délais | I52: Élevée | J52: Risques de non-conformité
C53: S’assurer qu’il existe des revues qualité pour la saisie des tickets | D53: Existence de revues | E53: Existe-t-il des revues qualité pour la saisie des tickets ? | F53: Oui | G53: Document de revue | H53: Omission d'informations | I53: Élevée | J53: Mauvaise qualité des tickets
D54: Documentation des revues | E54: Les revues qualité sont-elles bien documentées ? | F54: Oui | G54: Rapport de revue | H54: Manque de clarté | I54: Élevée | J54: Difficultés d'audit
D55: Feedback intégré | E55: Le feedback sur les revues qualité a-t-il été pris en compte ? | F55: Oui | G55: Rapport de feedback | H55: Ignorance des retours | I55: Moyenne | J55: Améliorations non appliquées
D56: Validation par les parties prenantes | E56: Les revues ont-elles été validées par les parties prenantes ? | F56: Oui | G56: Rapport de validation | H56: Manque de consensus | I56: Élevée | J56: Risques non identifiés
D57: Suivi des résultats | E57: Un suivi des résultats des revues qualité est-il effectué ? | F57: Non | G57: Rapport de suivi | H57: Non-respect des délais | I57: Élevée | J57: Risques de non-conformité
C58: Vérifier l’existence d’une base de connaissance | D58: Existence de la base | E58: Existe-t-il une base de connaissance pour le help-desk ? | F58: Oui | G58: Document de base | H58: Omission d'informations | I58: Élevée | J58: Mauvaise gestion des demandes
D59: Accessibilité de la base | E59: La base de connaissance est-elle facilement accessible ? | F59: Oui | G59: Manuel d'accès | H59: Manque de visibilité | I59: Moyenne | J59: Retards dans le traitement
D60: Mise à jour régulière | E60: La base de connaissance est-elle mise à jour régulièrement ? | F60: Non | G60: Rapport de mise à jour | H60: Obsolescence | I60: Élevée | J60: Risques de non-conformité
D61: Feedback intégré | E61: Le feedback sur la base de connaissance a-t-il été pris en compte ? | F61: Oui | G61: Rapport de feedback | H61: Ignorance des retours | I61: Moyenne | J61: Améliorations non appliquées
D62: Validation par les parties prenantes | E62: La base a-t-elle été validée par les parties prenantes ? | F62: Oui | G62: Rapport de validation | H62: Manque de consensus | I62: Élevée | J62: Risques non identifiés
C63: S’assurer qu’une procédure de mise à jour de la base de connaissance existe | D63: Existence de la procédure | E63: Existe-t-il une procédure de mise à jour de la base de connaissance ? | F63: Oui | G63: Document de procédure | H63: Omission d'informations | I63: Élevée | J63: Mauvaise gestion des informations
D64: Accessibilité de la procédure | E64: La procédure est-elle facilement accessible ? | F64: Oui | G64: Manuel d'accès | H64: Manque de visibilité | I64: Moyenne | J64: Retards dans les mises à jour
D65: Feedback intégré | E65: Le feedback sur la procédure de mise à jour a-t-il été pris en compte ? | F65: Oui | G65: Rapport de feedback | H65: Ignorance des retours | I65: Moyenne | J65: Améliorations non appliquées
D66: Validation par les parties prenantes | E66: La procédure a-t-elle été validée par les parties prenantes ? | F66: Oui | G66: Rapport de validation | H66: Manque de consensus | I66: Élevée | J66: Risques non identifiés
D67: Suivi des mises à jour | E67: Un suivi des mises à jour de la base de connaissance est-il effectué ? | F67: Non | G67: Rapport de suivi | H67: Non-respect des délais | I67: Élevée | J67: Risques de non-conformité
C68: S’assurer que les appels sont enregistrés | D68: Existence d'un système d'enregistrement | E68: Les appels sont-ils enregistrés ? | F68: Oui | G68: Document d'enregistrement | H68: Omission d'informations | I68: Élevée | J68: Mauvaise traçabilité des demandes
D69: Accessibilité des enregistrements | E69: Les enregistrements sont-ils facilement accessibles ? | F69: Oui | G69: Manuel d'accès | H69: Manque de visibilité | I69: Moyenne | J69: Retards dans le traitement
D70: Feedback intégré | E70: Le feedback sur l'enregistrement des appels a-t-il été pris en compte ? | F70: Oui | G70: Rapport de feedback | H70: Ignorance des retours | I70: Moyenne | J70: Améliorations non appliquées
D71: Validation par les parties prenantes | E71: Les enregistrements ont-ils été validés par les parties prenantes ? | F71: Oui | G71: Rapport de validation | H71: Manque de consensus | I71: Élevée | J71: Risques non identifiés
D72: Suivi des enregistrements | E72: Un suivi des enregistrements est-il effectué ? | F72: Non | G72: Rapport de suivi | H72: Non-respect des délais | I72: Élevée | J72: Risques de non-conformité
C73: S’assurer que des études de satisfaction sont réalisées auprès des utilisateurs | D73: Existence d'études | E73: Des études de satisfaction sont-elles réalisées auprès des utilisateurs ? | F73: Oui | G73: Document d'étude | H73: Omission d'informations | I73: Élevée | J73: Mauvaise compréhension des besoins
D74: Documentation des résultats | E74: Les résultats des études de satisfaction sont-ils bien documentés ? | F74: Oui | G74: Rapport de satisfaction | H74: Manque de clarté | I74: Élevée | J74: Difficultés d'audit
D75: Feedback intégré | E75: Le feedback sur les études de satisfaction a-t-il été pris en compte ? | F75: Oui | G75: Rapport de feedback | H75: Ignorance des retours | I75: Moyenne | J75: Améliorations non appliquées
D76: Validation par les parties prenantes | E76: Les résultats ont-ils été validés par les parties prenantes ? | F76: Oui | G76: Rapport de validation | H76: Manque de consensus | I76: Élevée | J76: Risques non identifiés
D77: Suivi des actions | E77: Un suivi des actions résultant des études de satisfaction est-il effectué ? | F77: Non | G77: Rapport de suivi | H77: Non-respect des délais | I77: Élevée | J77: Risques de non-conformité
C78: S’assurer qu’il existe une évaluation de l’équipe HD, notamment pour les prestataires afin d’en évaluer le niveau de connaissance | D78: Existence d'une évaluation | E78: Existe-t-il une évaluation de l’équipe help-desk ? | F78: Oui | G78: Document d'évaluation | H78: Omission d'informations | I78: Élevée | J78: Mauvaise performance non détectée
D79: Accessibilité de l'évaluation | E79: L'évaluation de l’équipe est-elle facilement accessible ? | F79: Oui | G79: Manuel d'accès | H79: Manque de visibilité | I79: Moyenne | J79: Retards dans l'évaluation
D80: Feedback intégré | E80: Le feedback sur l'évaluation a-t-il été pris en compte ? | F80: Oui | G80: Rapport de feedback | H80: Ignorance des retours | I80: Moyenne | J80: Améliorations non appliquées
D81: Validation par les parties prenantes | E81: L'évaluation a-t-elle été validée par les parties prenantes ? | F81: Oui | G81: Rapport de validation | H81: Manque de consensus | I81: Élevée | J81: Risques non identifiés
D82: Suivi des résultats | E82: Un suivi des résultats de l'évaluation est-il effectué ? | F82: Non | G82: Rapport de suivi | H82: Non-respect des délais | I82: Élevée | J82: Risques de non-conformité
C83: S’assurer que l’obtention des certifications (ITIL, ISO, COBIT, SIGMA) est encouragée au sein de la DSI, et du HD en particulier | D83: Encouragement à l'obtention | E83: L'obtention des certifications (ITIL, ISO, COBIT, SIGMA) est-elle encouragée au sein de la DSI ? | F83: Oui | G83: Document de politique | H83: Omission d'informations | I83: Élevée | J83: Manque de compétence
D84: Documentation des efforts | E84: Les efforts pour obtenir des certifications sont-ils bien documentés ? | F84: Oui | G84: Rapport de certification | H84: Manque de clarté | I84: Élevée | J84: Difficultés d'audit
D85: Feedback intégré | E85: Le feedback sur les certifications a-t-il été pris en compte ? | F85: Oui | G85: Rapport de feedback | H85: Ignorance des retours | I85: Moyenne | J85: Améliorations non appliquées
D86: Validation par les parties prenantes | E86: Les efforts pour les certifications ont-ils été validés par les parties prenantes ? | F86: Oui | G86: Rapport de validation | H86: Manque de consensus | I86: Élevée | J86: Risques non identifiés
D87: Suivi des certifications | E87: Un suivi des certifications obtenues est-il effectué ? | F87: Non | G87: Rapport de suivi | H87: Non-respect des délais | I87: Élevée | J87: Risques de non-conformité
C88: Vérifier la stratégie de formation des utilisateurs et de l’équipe Helpdesk | D88: Existence des critères | E88: Des critères à renseigner pour la qualification des tickets existent-ils ? | F88: Oui | G88: Document des critères | H88: Omission d'informations | I88: Élevée | J88: Mauvaise gestion des tickets
D89: Documentation des critères | E89: Les critères de qualification sont-ils bien documentés ? | F89: Oui | G89: Rapport de documentation | H89: Manque de clarté | I89: Élevée | J89: Difficultés d'audit
D90: Feedback intégré | E90: Le feedback sur les critères a-t-il été pris en compte ? | F90: Oui | G90: Rapport de feedback | H90: Ignorance des retours | I90: Moyenne | J90: Améliorations non appliquées
D91: Validation par les parties prenantes | E91: Les critères ont-ils été validés par les parties prenantes ? | F91: Oui | G91: Rapport de validation | H91: Manque de consensus | I91: Élevée | J91: Risques non identifiés
D92: Suivi des critères | E92: Un suivi des critères de qualification est-il effectué ? | F92: Non | G92: Rapport de suivi | H92: Non-respect des délais | I92: Élevée | J92: Risques de non-conformité
B93: Gestion du parc matériel et logiciel : audit fiabilité et sécurité | C93: Vérifier la procédure de déploiement des mises à jour, d’un nouveau logiciel | D93: Existence de la liste | E93: Existe-t-il une liste de questions à dérouler lors d'un appel afin de préciser au mieux la demande de l'utilisateur ? | F93: Oui | G93: Document de questions | H93: Omission d'informations | I93: Élevée | J93: Mauvaise gestion des demandes
D94: Documentation des questions | E94: La liste de questions est-elle bien documentée ? | F94: Oui | G94: Rapport de documentation | H94: Manque de clarté | I94: Élevée | J94: Difficultés d'audit
D95: Feedback intégré | E95: Le feedback sur la liste de questions a-t-il été pris en compte ? | F95: Oui | G95: Rapport de feedback | H95: Ignorance des retours | I95: Moyenne | J95: Améliorations non appliquées
D96: Validation par les parties prenantes | E96: La liste a-t-elle été validée par les parties prenantes ? | F96: Oui | G96: Rapport de validation | H96: Manque de consensus | I96: Élevée | J96: Risques non identifiés
D97: Suivi des questions | E97: Un suivi des questions posées est-il effectué ? | F97: Non | G97: Rapport de suivi | H97: Non-respect des délais | I97: Élevée | J97: Risques de non-conformité
C98: Vérifier les outils mis en place pour gérer les versions des logiciels | D98: Existence de la stratégie | E98: Une stratégie de formation des utilisateurs et de l’équipe Helpdesk existe-t-elle ? | F98: Oui | G98: Document de stratégie | H98: Omission d'informations | I98: Élevée | J98: Mauvaise gestion des compétences
D99: Accessibilité de la stratégie | E99: La stratégie est-elle facilement accessible aux parties concernées ? | F99: Oui | G99: Manuel d'accès | H99: Manque de visibilité | I99: Moyenne | J99: Retards dans la formation
D100: Feedback intégré | E100: Le feedback sur la stratégie de formation a-t-il été pris en compte ? | F100: Oui | G100: Rapport de feedback | H100: Ignorance des retours | I100: Moyenne | J100: Améliorations non appliquées
D101: Validation par les parties prenantes | E101: La stratégie a-t-elle été validée par les parties prenantes ? | F101: Oui | G101: Rapport de validation | H101: Manque de consensus | I101: Élevée | J101: Risques non identifiés
...

Sheet 4.5 sécurité informatique
A1: Domaines | B1: Points de contrôle | C1: Objectifs de contrôle | D1: critères d'évaluation | E1: Question d'évaluation | F1: Réponses | G1: Documents Requis | H1: Risques | I1: Criticités | J1: Conséquences
A3: sécurité informatique | B3: Facteurs clés de succès | C3: Vérifier qu’une politique de sécurité est définie et correspond à l'activité de l'Organisation | D3: Existence d'une politique | E3: Une politique de sécurité est-elle définie et correspond-elle à l'activité de l'Organisation ? | F3: Oui | G3: Document de politique | H3: Omission d'informations | I3: Élevée | J3: Mauvaise gestion des risques
D4: Accessibilité de la politique | E4: La politique est-elle facilement accessible à tous les employés ? | F4: Oui | G4: Manuel d'accès | H4: Manque de visibilité | I4: Moyenne | J4: Retards dans la mise en œuvre
D5: Feedback intégré | E5: Le feedback sur la politique de sécurité a-t-il été pris en compte ? | F5: Oui | G5: Rapport de feedback | H5: Ignorance des retours | I5: Moyenne | J5: Améliorations non appliquées
D6: Validation par la direction | E6: La politique a-t-elle été validée par la direction ? | F6: Oui | G6: Rapport de validation | H6: Manque de consensus | I6: Élevée | J6: Risques non identifiés
D7: Suivi des mises à jour | E7: Un suivi des mises à jour de la politique est-il effectué ? | F7: Non | G7: Rapport de suivi | H7: Non-respect des délais | I7: Élevée | J7: Risques de non-conformité
C8: Vérifier qu’une démarche de mise en œuvre de la gestion de la sécurité est adoptée et compatible avec la culture de l'Organisation | D8: Existence d'une démarche | E8: Une démarche de mise en œuvre de la gestion de la sécurité est-elle adoptée ? | F8: Oui | G8: Document de démarche | H8: Omission d'informations | I8: Élevée | J8: Mauvaise gestion des risques
D9: Compatibilité avec la culture | E9: La démarche est-elle compatible avec la culture de l'Organisation ? | F9: Oui | G9: Rapport d'évaluation | H9: Manque de clarté | I9: Élevée | J9: Difficultés d'audit
D10: Feedback intégré | E10: Le feedback sur la démarche a-t-il été pris en compte ? | F10: Oui | G10: Rapport de feedback | H10: Ignorance des retours | I10: Moyenne | J10: Améliorations non appliquées
D11: Validation par la direction | E11: La démarche a-t-elle été validée par la direction ? | F11: Oui | G11: Rapport de validation | H11: Manque de consensus | I11: Élevée | J11: Risques non identifiés
D12: Suivi des actions | E12: Un suivi des actions de mise en œuvre est-il effectué ? | F12: Non | G12: Rapport de suivi | H12: Non-respect des délais | I12: Élevée | J12: Risques de non-conformité
C13: Vérifier que la direction assure un soutien total et un engagement visible pour la sécurité | D13: Engagement visible | E13: La direction assure-t-elle un soutien total et un engagement visible pour la sécurité ? | F13: Oui | G13: Document de soutien | H13: Omission d'informations | I13: Élevée | J13: Mauvaise sensibilisation
D14: Documentation de l'engagement | E14: L'engagement de la direction est-il bien documenté ? | F14: Oui | G14: Rapport d'engagement | H14: Manque de clarté | I14: Élevée | J14: Difficultés d'audit
D15: Feedback intégré | E15: Le feedback sur l'engagement a-t-il été pris en compte ? | F15: Oui | G15: Rapport de feedback | H15: Ignorance des retours | I15: Moyenne | J15: Améliorations non appliquées
D16: Validation par les parties prenantes | E16: L'engagement a-t-il été validé par les parties prenantes ? | F16: Oui | G16: Rapport de validation | H16: Manque de consensus | I16: Élevée | J16: Risques non identifiés
D17: Suivi des actions | E17: Un suivi des actions de soutien est-il effectué ? | F17: Non | G17: Rapport de suivi | H17: Non-respect des délais | I17: Élevée | J17: Risques de non-conformité
C18: Vérifier que les exigences de sécurité et les risques sont compris et évalués | D18: Évaluation des exigences | E18: Les exigences de sécurité et les risques sont-ils compris et évalués ? | F18: Oui | G18: Document d'évaluation | H18: Omission d'informations | I18: Élevée | J18: Mauvaise gestion des risques
D19: Documentation des évaluations | E19: Les évaluations des exigences sont-elles bien documentées ? | F19: Oui | G19: Rapport d'évaluation | H19: Manque de clarté | I19: Élevée | J19: Difficultés d'audit
D20: Feedback intégré | E20: Le feedback sur les évaluations a-t-il été pris en compte ? | F20: Oui | G20: Rapport de feedback | H20: Ignorance des retours | I20: Moyenne | J20: Améliorations non appliquées
D21: Validation par les parties prenantes | E21: Les évaluations ont-elles été validées par les parties prenantes ? | F21: Oui | G21: Rapport de validation | H21: Manque de consensus | I21: Élevée | J21: Risques non identifiés
D22: Suivi des actions | E22: Un suivi des actions résultant des évaluations est-il effectué ? | F22: Non | G22: Rapport de suivi | H22: Non-respect des délais | I22: Élevée | J22: Risques de non-conformité
C23: Vérifier que l’ensemble des responsables et des employés sont sensibilisés et informés | D23: Existence de programmes de sensibilisation | E23: L'ensemble des responsables et des employés sont-ils sensibilisés et informés ? | F23: Oui | G23: Document de sensibilisation | H23: Omission d'informations | I23: Élevée | J23: Mauvaise compréhension des enjeux
D24: Documentation des programmes | E24: Les programmes de sensibilisation sont-ils bien documentés ? | F24: Oui | G24: Rapport de sensibilisation | H24: Manque de clarté | I24: Élevée | J24: Difficultés d'audit
D25: Feedback intégré | E25: Le feedback sur les programmes de sensibilisation a-t-il été pris en compte ? | F25: Oui | G25: Rapport de feedback | H25: Ignorance des retours | I25: Moyenne | J25: Améliorations non appliquées
D26: Validation par les parties prenantes | E26: Les programmes ont-ils été validés par les parties prenantes ? | F26: Oui | G26: Rapport de validation | H26: Manque de consensus | I26: Élevée | J26: Risques non identifiés
D27: Suivi des actions | E27: Un suivi des actions de sensibilisation est-il effectué ? | F27: Non | G27: Rapport de suivi | H27: Non-respect des délais | I27: Élevée | J27: Risques de non-conformité
C28: Vérifier que les lignes directrices de la politique de sécurité et des normes de sécurité de l'information sont distribuées à tous les employés et à tous les fournisseurs | D28: Existence de lignes directrices | E28: Les lignes directrices de la politique de sécurité et des normes de sécurité de l'information sont-elles distribuées à tous les employés et fournisseurs ? | F28: Oui | G28: Document de lignes directrices | H28: Omission d'informations | I28: Élevée | J28: Mauvaise compréhension des normes
D29: Accessibilité des lignes directrices | E29: Les lignes directrices sont-elles facilement accessibles ? | F29: Oui | G29: Manuel d'accès | H29: Manque de visibilité | I29: Moyenne | J29: Retards dans la mise en œuvre
D30: Feedback intégré | E30: Le feedback sur la distribution a-t-il été pris en compte ? | F30: Oui | G30: Rapport de feedback | H30: Ignorance des retours | I30: Moyenne | J30: Améliorations non appliquées
D31: Validation par les parties prenantes | E31: Les lignes directrices ont-elles été validées par les parties prenantes ? | F31: Oui | G31: Rapport de validation | H31: Manque de consensus | I31: Élevée | J31: Risques non identifiés
D32: Suivi des distributions | E32: Un suivi des distributions des lignes directrices est-il effectué ? | F32: Non | G32: Rapport de suivi | H32: Non-respect des délais | I32: Élevée | J32: Risques de non-conformité
C33: vérifier la gestion de la sécurité | D33: Existence d'un programme de formation | E33: Les acteurs de la sécurité sont-ils formés de manière appropriée ? | F33: Oui | G33: Document de formation | H33: Omission d'informations | I33: Élevée | J33: Mauvaise gestion des incidents
D34: Documentation des formations | E34: Les formations sont-elles bien documentées ? | F34: Oui | G34: Rapport de formation | H34: Manque de clarté | I34: Élevée | J34: Difficultés d'audit
D35: Feedback intégré | E35: Le feedback sur les formations a-t-il été pris en compte ? | F35: Oui | G35: Rapport de feedback | H35: Ignorance des retours | I35: Moyenne | J35: Améliorations non appliquées
D36: Validation par la direction | E36: Les programmes de formation ont-ils été validés par la direction ? | F36: Oui | G36: Rapport de validation | H36: Manque de consensus | I36: Élevée | J36: Risques non identifiés
C37: Vérifier que les acteurs de la sécurité sont formés de manière appropriée | D37: Suivi des formations | E37: Un suivi des formations effectuées est-il réalisé ? | F37: Non | G37: Rapport de suivi | H37: Non-respect des délais | I37: Élevée | J37: Risques de non-conformité
D38: Existence d'un système de mesure | E38: Un système de mesure complet est-il mis en place pour évaluer l'efficacité de la gestion de la sécurité ? | F38: Oui | G38: Document de mesure | H38: Omission d'informations | I38: Élevée | J38: Mauvaise évaluation des risques
D39: Documentation des mesures | E39: Les mesures sont-elles bien documentées ? | F39: Oui | G39: Rapport de mesure | H39: Manque de clarté | I39: Élevée | J39: Difficultés d'audit
D40: Feedback intégré | E40: Le feedback sur le système de mesure a-t-il été pris en compte ? | F40: Oui | G40: Rapport de feedback | H40: Ignorance des retours | I40: Moyenne | J40: Améliorations non appliquées
D41: Validation par la direction | E41: Le système de mesure a-t-il été validé par la direction ? | F41: Oui | G41: Rapport de validation | H41: Manque de consensus | I41: Élevée | J41: Risques non identifiés
C42: Vérifier qu’un système de mesure complet est mis en place afin d'évaluer l'efficacité de la gestion de la sécurité de l'information et pour collecter les suggestions d'amélioration | D42: Suivi des suggestions | E42: Un suivi des suggestions d'amélioration est-il effectué ? | F42: Non | G42: Rapport de suivi | H42: Non-respect des délais | I42: Élevée | J42: Risques de non-conformité
D43: Existence d'une politique formalisée | E43: Une politique de sécurité formalisée existe-t-elle ? | F43: Oui | G43: Document de politique | H43: Omission d'informations | I43: Élevée | J43: Mauvaise gestion des risques
D44: Implication de la direction | E44: La politique implique-t-elle la direction générale ? | F44: Oui | G44: Rapport d'engagement | H44: Manque de clarté | I44: Élevée | J44: Difficultés d'audit
D45: Définition des responsabilités | E45: Les responsabilités sont-elles clairement définies ? | F45: Oui | G45: Document de responsabilités | H45: Manque de clarté | I45: Élevée | J45: Risques non identifiés
D46: Feedback intégré | E46: Le feedback sur la politique a-t-il été pris en compte ? | F46: Oui | G46: Rapport de feedback | H46: Ignorance des retours | I46: Moyenne | J46: Améliorations non appliquées
B47: Politique de sécurité | C47: S’assurer qu’il existe une politique de sécurité formalisée avec une implication de la direction générale et une définition claire des responsabilités | D47: Suivi des mises à jour | E47: Un suivi des mises à jour de la politique est-il effectué ? | F47: Non | G47: Rapport de suivi | H47: Non-respect des délais | I47: Élevée | J47: Risques de non-conformité
D48: Existence d'un plan de communication | E48: La communication se fait-elle à tous les utilisateurs sous une forme pertinente, accessible et compréhensible ? | F48: Oui | G48: Document de communication | H48: Omission d'informations | I48: Élevée | J48: Mauvaise compréhension des enjeux
D49: Accessibilité des communications | E49: Les communications sont-elles facilement accessibles ? | F49: Oui | G49: Manuel d'accès | H49: Manque de visibilité | I49: Moyenne | J49: Retards dans la sensibilisation
D50: Feedback intégré | E50: Le feedback sur la communication a-t-il été pris en compte ? | F50: Oui | G50: Rapport de feedback | H50: Ignorance des retours | I50: Moyenne | J50: Améliorations non appliquées
D51: Validation par la direction | E51: Les communications ont-elles été validées par la direction ? | F51: Oui | G51: Rapport de validation | H51: Manque de consensus | I51: Élevée | J51: Risques non identifiés
C52: S’assurer que la communication se fait à tous les utilisateurs sous une forme pertinente, accessible et compréhensible au lecteur | D52: Suivi des actions | E52: Un suivi des actions de communication est-il effectué ? | F52: Non | G52: Rapport de suivi | H52: Non-respect des délais | I52: Élevée | J52: Risques de non-conformité
D53: Existence de revues régulières | E53: Une revue régulière de la politique est-elle réalisée ? | F53: Oui | G53: Document de revue | H53: Omission d'informations | I53: Élevée | J53: Mauvaise gestion des risques
D54: Documentation des revues | E54: Les revues de la politique sont-elles bien documentées ? | F54: Oui | G54: Rapport de revue | H54: Manque de clarté | I54: Élevée | J54: Difficultés d'audit
D55: Feedback intégré | E55: Le feedback sur les revues a-t-il été pris en compte ? | F55: Oui | G55: Rapport de feedback | H55: Ignorance des retours | I55: Moyenne | J55: Améliorations non appliquées
D56: Validation par les parties prenantes | E56: Les revues ont-elles été validées par les parties prenantes ? | F56: Oui | G56: Rapport de validation | H56: Manque de consensus | I56: Élevée | J56: Risques non identifiés
C57: S’assurer qu’une revue régulière de la politique est réalisée afin de vérifier son adéquation avec | D57: Existence de revues régulières | E57: Une revue régulière de la politique est-elle réalisée pour vérifier son adéquation ? | F57: Oui | G57: Document de revue | H57: Omission d'informations | I57: Élevée | J57: Mauvaise gestion des risques
D58: Documentation des revues | E58: Les revues de la politique sont-elles bien documentées ? | F58: Oui | G58: Rapport de revue | H58: Manque de clarté | I58: Élevée | J58: Difficultés d'audit
D59: Feedback intégré | E59: Le feedback sur les revues a-t-il été pris en compte ? | F59: Oui | G59: Rapport de feedback | H59: Ignorance des retours | I59: Moyenne | J59: Améliorations non appliquées
D60: Validation par les parties prenantes | E60: Les revues ont-elles été validées par les parties prenantes ? | F60: Oui | G60: Rapport de validation | H60: Manque de consensus | I60: Élevée | J60: Risques non identifiés
D61: Suivi des recommandations | E61: Un suivi des recommandations issues des revues est-il effectué ? | F61: Non | G61: Rapport de suivi | H61: Non-respect des délais | I61: Élevée | J61: Risques de non-conformité
C62: s'assurer que la démarche de sécurité inclut la totalité de l’informatique et non les seuls réseaux, serveurs et applications. Les imprimantes et téléphones sous IP, l’informatique technique et industrielle, l’informatique de gestion technique des bâtiments, celle de gestion des accès et temps de travail, etc. bénéficient sans exception ni zone d’ombre du dispositif de sécurité. | D62: Inclusion de tous les systèmes | E62: La démarche de sécurité inclut-elle la totalité de l’informatique, y compris les imprimantes, téléphones IP, etc. ? | F62: Oui | G62: Document de sécurité | H62: Omission d'informations | I62: Élevée | J62: Mauvaise couverture des risques
D63: Documentation de la démarche | E63: La démarche est-elle bien documentée pour inclure tous les systèmes ? | F63: Oui | G63: Rapport de sécurité | H63: Manque de clarté | I63: Élevée | J63: Difficultés d'audit
D64: Feedback intégré | E64: Le feedback sur la démarche a-t-il été pris en compte ? | F64: Oui | G64: Rapport de feedback | H64: Ignorance des retours | I64: Moyenne | J64: Améliorations non appliquées
D65: Validation par la direction | E65: La démarche a-t-elle été validée par la direction ? | F65: Oui | G65: Rapport de validation | H65: Manque de consensus | I65: Élevée | J65: Risques non identifiés
D66: Suivi des systèmes | E66: Un suivi des systèmes inclus dans la démarche est-il effectué ? | F66: Non | G66: Rapport de suivi | H66: Non-respect des délais | I66: Élevée | J66: Risques de non-conformité
B67: Organisation de la sécurité | C67: S’assurer qu’il existe une structure dédiée à la gestion de la sécurité de l'information : un comité sécurité, un responsable de la sécurité du système d'information (RSSI) et des correspondants sécurité dans les unités | D67: Existence d'une structure | E67: Existe-t-il une structure dédiée à la gestion de la sécurité de l'information ? | F67: Oui | G67: Document de structure | H67: Omission d'informations | I67: Élevée | J67: Mauvaise gestion des incidents
D68: Documentation des rôles | E68: Les rôles (comité sécurité, RSSI, correspondants) sont-ils bien documentés ? | F68: Oui | G68: Rapport de structure | H68: Manque de clarté | I68: Élevée | J68: Difficultés d'audit
D69: Feedback intégré | E69: Le feedback sur la structure a-t-il été pris en compte ? | F69: Oui | G69: Rapport de feedback | H69: Ignorance des retours | I69: Moyenne | J69: Améliorations non appliquées
D70: Validation par la direction | E70: La structure a-t-elle été validée par la direction ? | F70: Oui | G70: Rapport de validation | H70: Manque de consensus | I70: Élevée | J70: Risques non identifiés
D71: Suivi des actions | E71: Un suivi des actions de la structure est-il effectué ? | F71: Non | G71: Rapport de suivi | H71: Non-respect des délais | I71: Élevée | J71: Risques de non-conformité
C72: Vérifier qu’il y a une attribution claire des responsabilités | D72: Existence d'une attribution claire | E72: Les responsabilités en matière de sécurité sont-elles clairement attribuées ? | F72: Oui | G72: Document de responsabilités | H72: Omission d'informations | I72: Élevée | J72: Mauvaise gestion des risques
D73: Documentation des attributions | E73: Les attributions sont-elles bien documentées ? | F73: Oui | G73: Rapport d'attribution | H73: Manque de clarté | I73: Élevée | J73: Difficultés d'audit
D74: Feedback intégré | E74: Le feedback sur les attributions a-t-il été pris en compte ? | F74: Oui | G74: Rapport de feedback | H74: Ignorance des retours | I74: Moyenne | J74: Améliorations non appliquées
D75: Validation par la direction | E75: Les attributions ont-elles été validées par la direction ? | F75: Oui | G75: Rapport de validation | H75: Manque de consensus | I75: Élevée | J75: Risques non identifiés
D76: Suivi des attributions | E76: Un suivi des attributions est-il effectué ? | F76: Non | G76: Rapport de suivi | H76: Non-respect des délais | I76: Élevée | J76: Risques de non-conformité
C77: S’assurer qu’un propriétaire est désigné, il est responsable de la mise en œuvre et du suivi des évolutions à apporter | D77: Existence d'un propriétaire | E77: Un propriétaire est-il désigné pour la mise en œuvre et le suivi des évolutions ? | F77: Oui | G77: Document de désignation | H77: Omission d'informations | I77: Élevée | J77: Mauvaise gestion des évolutions
D78: Documentation des responsabilités | E78: Les responsabilités du propriétaire sont-elles bien documentées ? | F78: Oui | G78: Rapport de désignation | H78: Manque de clarté | I78: Élevée | J78: Difficultés d'audit
D79: Feedback intégré | E79: Le feedback sur la désignation a-t-il été pris en compte ? | F79: Oui | G79: Rapport de feedback | H79: Ignorance des retours | I79: Moyenne | J79: Améliorations non appliquées
D80: Validation par la direction | E80: La désignation a-t-elle été validée par la direction ? | F80: Oui | G80: Rapport de validation | H80: Manque de consensus | I80: Élevée | J80: Risques non identifiés
D81: Suivi des actions | E81: Un suivi des actions entreprises par le propriétaire est-il effectué ? | F81: Non | G81: Rapport de suivi | H81: Non-respect des délais | I81: Élevée | J81: Risques de non-conformité
C82: S’assurer qu’il existe des procédures d'autorisation de nouveaux matériels ou logiciels | D82: Existence de procédures | E82: Existe-t-il des procédures d'autorisation pour de nouveaux matériels ou logiciels ? | F82: Oui | G82: Document de procédure | H82: Omission d'informations | I82: Élevée | J82: Mauvaise gestion des actifs
D83: Documentation des procédures | E83: Les procédures sont-elles bien documentées ? | F83: Oui | G83: Rapport de procédure | H83: Manque de clarté | I83: Élevée | J83: Difficultés d'audit
D84: Feedback intégré | E84: Le feedback sur les procédures a-t-il été pris en compte ? | F84: Oui | G84: Rapport de feedback | H84: Ignorance des retours | I84: Moyenne | J84: Améliorations non appliquées
D85: Validation par la direction | E85: Les procédures ont-elles été validées par la direction ? | F85: Oui | G85: Rapport de validation | H85: Manque de consensus | I85: Élevée | J85: Risques non identifiés
D86: Suivi des autorisations | E86: Un suivi des autorisations accordées est-il effectué ? | F86: Non | G86: Rapport de suivi | H86: Non-respect des délais | I86: Élevée | J86: Risques de non-conformité
C87: S’assurer qu’il existe des procédures applicables à l'accès aux informations de l'organisation par des tiers | D87: Existence de procédures | E87: Existe-t-il des procédures applicables à l'accès aux informations de l'organisation par des tiers ? | F87: Oui | G87: Document de procédure | H87: Omission d'informations | I87: Élevée | J87: Mauvaise gestion des accès
D88: Documentation des procédures | E88: Les procédures sont-elles bien documentées ? | F88: Oui | G88: Rapport de procédure | H88: Manque de clarté | I88: Élevée | J88: Difficultés d'audit
D89: Feedback intégré | E89: Le feedback sur les procédures a-t-il été pris en compte ? | F89: Oui | G89: Rapport de feedback | H89: Ignorance des retours | I89: Moyenne | J89: Améliorations non appliquées
D90: Validation par la direction | E90: Les procédures ont-elles été validées par la direction ? | F90: Oui | G90: Rapport de validation | H90: Manque de consensus | I90: Élevée | J90: Risques non identifiés
D91: Suivi des accès | E91: Un suivi des accès accordés aux tiers est-il effectué ? | F91: Non | G91: Rapport de suivi | H91: Non-respect des délais | I91: Élevée | J91: Risques de non-conformité
C92: S’assurer que des modalités de protection de l'information confiée à des sous-traitants existent | D92: Existence de modalités | E92: Existe-t-il des modalités de protection de l'information confiée à des sous-traitants ? | F92: Oui | G92: Document de protection | H92: Omission d'informations | I92: Élevée | J92: Mauvaise gestion des données
D93: Documentation des modalités | E93: Les modalités sont-elles bien documentées ? | F93: Oui | G93: Rapport de protection | H93: Manque de clarté | I93: Élevée | J93: Difficultés d'audit
D94: Feedback intégré | E94: Le feedback sur les modalités a-t-il été pris en compte ? | F94: Oui | G94: Rapport de feedback | H94: Ignorance des retours | I94: Moyenne | J94: Améliorations non appliquées
D95: Validation par la direction | E95: Les modalités ont-elles été validées par la direction ? | F95: Oui | G95: Rapport de validation | H95: Manque de consensus | I95: Élevée | J95: Risques non identifiés
D96: Suivi des informations confiées | E96: Un suivi des informations confiées aux sous-traitants est-il effectué ? | F96: Non | G96: Rapport de suivi | H96: Non-respect des délais | I96: Élevée | J96: Risques de non-conformité
C97: Vérifier qu'il existe des modalités de réaction aux incidents de sécurité et aux défauts de fonctionnement | D97: Existence de modalités | E97: Existe-t-il des modalités de réaction aux incidents de sécurité et aux défauts de fonctionnement ? | F97: Oui | G97: Document de réaction | H97: Omission d'informations | I97: Élevée | J97: Mauvaise gestion des incidents
D98: Documentation des modalités | E98: Les modalités sont-elles bien documentées ? | F98: Oui | G98: Rapport de réaction | H98: Manque de clarté | I98: Élevée | J98: Difficultés d'audit
D99: Feedback intégré | E99: Le feedback sur les modalités a-t-il été pris en compte ? | F99: Oui | G99: Rapport de feedback | H99: Ignorance des retours | I99: Moyenne | J99: Améliorations non appliquées
D100: Validation par la direction | E100: Les modalités ont-elles été validées par la direction ? | F100: Oui | G100: Rapport de validation | H100: Manque de consensus | I100: Élevée | J100: Risques non identifiés
D101: Suivi des incidents | E101: Un suivi des incidents et des réactions est-il effectué ? | F101: Non | G101: Rapport de suivi | H101: Non-respect des délais | I101: Élevée | J101: Risques de non-conformité
...
