Workbook

Sheet devoir_livre1
A1: Numéro d'ordre | B1: Domaine ou cycle concerné | C1: Structure compétente | D1: Poste de travail concerné | E1: Le ou les titulaires du poste de travail sur la période | F1: Le logiciel utilisé | G1: La phase ou l’étape du processus visé : | H1: Le point de contrôle évalué | I1: Le ou les critères d’évaluation | J1: a ou les questions d’évaluation | K1: La réponse associée | L1: es éléments requis (futurs éléments probants) | M1: Le risque associé | N1: La conséquence majeure en cas de réalisation du risque relevé | O1: La criticité subséquente | P1: Un commentaire le cas échéant
A2: 1 | B2: Informatique | C2: direction des SI | D2: Administrateur système | E2: FANTA Félicité | F2: SAP | G2: sauvegarde des données | H2: Vérification des sauvegardes | I2: conformité, sécurité | J2: les sauvegardes sont-elles effectuées quotidienement? | K2: oui | L2: Rapport de sauvegarde | M2: perte de données due à une sauvegarde défaillante | N2: interuption des opérations | O2: élevé | P2: sauvegarde vérifiée quotidienement
A3: 2 | B3: Finances | C3: Comptabilité | D3: comptable | E3: TAH-EPEN Alexandra | F3: excel | G3: saisie des données | H3: vérification des accès | I3: sécurité | J3: les accès sont-ils vérifiés régulièrement? | K3: non | L3: logs d'acccès | M3: accès non autorisé au système | N3: fraude financière | O3: critique | P3: accès non vérifiés depuis 3 mois
A4: 3 | B4: Ressources humaines | C4: RH | D4: Gestionnaire RH | E4: NAAMEN Manuella | F4: Logiciel RH | G4: Gestion des contrats | H4: validation des contrats | I4: conformité | J4: les contrats sont-ils validés par le responsable? | K4: partiellement | L4: contrat signé | M4: contrats non conformes | N4: litige juridique | O4: moyen | P4: certains contrats manquent de validation

Sheet Synthèse
C3: Synthèse Numérique | N3: Equipe de Mission
A5: N° | B5: Domaines | C5: Total OUI | D5: Total NON | E5: Total PAS | F5: Total | G5: Score | N5: Nom | O5: Prénom | P5: Grade
A6: 1 | B6: Application en service | C6: =COUNTIF(Application_en_Service!F2:F1019, "OUI") -> 217 | D6: =COUNTIF(Application_en_Service!F2:F1019, "NON") -> 219 | E6: =COUNTIF(Application_en_Service!F2:F1019, "PAS") -> 73 | F6: =SUM(C6:E6) -> 509 | G6: =C6/F6 -> 0.42632613 | L6: Chef : | N6: FANTA | O6: Félicité | P6: CIN-3
A7: 2 | B7: fonction informatique | C7: =COUNTIF(Fonction_info!G2:G321, "OUI") -> 0 | D7: =COUNTIF(Fonction_info!G2:G321, "NON") -> 320 | E7: =COUNTIF(Fonction_info!G2:G321, "PAS") -> 0 | F7: =SUM(C7:E7) -> 320 | G7: =C7/F7 -> 0
A8: 3 | B8: projet informatique | C8: =COUNTIF(Projet_Info!G2:G701, "OUI") -> 460 | D8: =COUNTIF(Projet_Info!G2:G701, "NON") -> 151 | E8: =COUNTIF(Projet_Info!G2:G701, "PAS") -> 89 | F8: =SUM(C8:E8) -> 700 | G8: =C8/F8 -> 0.65714286 | L8: Membres:
A9: 4 | B9: Support utilisateur | C9: =COUNTIF(Support_Util!F2:F201, "OUI") -> 25 | D9: =COUNTIF(Support_Util!F2:F201, "NON") -> 66 | E9: =COUNTIF(Support_Util!F2:F201, "PAS") -> 109 | F9: =SUM(C9:E9) -> 200 | G9: =C9/F9 -> 0.125 | M9: 1 | N9: FANTA | O9: Félicité | P9: CIN-3
A10: 5 | B10: Sécurité | C10: =COUNTIF(Sécurité!F2:F499, "OUI") -> 378 | D10: =COUNTIF(Sécurité!F2:F499, "NON") -> 102 | E10: =COUNTIF(Sécurité!F2:F499, "PAS") -> 18 | F10: =SUM(C10:E10) -> 498 | G10: =C10/F10 -> 0.75903614
B11: Total | C11: =SUM(C6:C10) -> 1080 | D11: =SUM(D6:D10) -> 858 | E11: =SUM(E6:E10) -> 289 | F11: =SUM(F6:F10) -> 2227 | G11: =C11/F11 -> 0.48495734
B15: Sythèse Graphique

Sheet Global
A1: Domaine | B1: Point de contrôle | C1: Objectifs de contrôle | D1: Critères d'évaluation | E1: Questions d'évaluation | F1: Réponses | G1: Documents requis | H1: risque | I1: criticité | J1: conséquences | K1: récommendations
A2: Application en service | B2: Organisation | C2: S’assurer de l’existence d'un comité informatique | D2: Existence d'un comité informatique | E2: Existe-t-il un comité informatique ? | F2: OUI | G2: Décision de création du comité informatique signée par le DG | H2: Inexistence d'un comité informatique | I2: Elevée | J2: Décisions informatiques déconnectées des besoins métiers. | K2: mpliquer les métiers dans les instances de décision concernant les SI.
G3: Procès-verbal de réunion attestant de la création du comité informatique. | K3: Formaliser les besoins métiers et les traduire en exigences fonctionnelles et techniques.
D4: Le Comité est présidé par le Directeur Général | E4: Le Comité est-il présidé par le Directeur Général ? | F4: NON | G4: PV de session du comité | H4: Le Comité n'est pas présidé par le Directeur Général | I4: Moyenne | J4: Manque d'autorité et de légitimité des décisions du comité. | K4: Clarifier les rôles et responsabilités du comité de pilotage SI.
G5: Décision de nomination du Président du comité informatique signée par le Directeur Général. | K5: Documenter les décisions prises et les diffuser aux parties prenantes.
D6: Les directions utilisatrices sont représentées au sein de ce Comité | E6: Les directions utilisatrices sont-elles représentées au sein de ce Comité ? | F6: PAS | G6: Décision d'affectation des directions au comité | H6: Les directions utilisatrices ne sont pas représentées au sein de ce Comité. | I6: Elevée | J6: Systèmes inadaptés aux besoins réels des utilisateurs. | K6: Mener des études d'utilisabilité et des tests utilisateurs avant et après la mise en production.
G7: PV de session du comité | K7: Mettre en place un processus de recueil et de gestion des feedbacks utilisateurs.
D8: Les directions utilisatrices sont influentes au sein de ce Comité | E8: Les directions utilisatrices sont-elles influentes au sein de ce Comité ? | F8: NON | G8: Procès-verbal des réunions mentionnant les contributions des directions utilisatrices | H8: Les directions utilisatrices ne sont pas influentes au sein de ce Comité | I8: Faible | J8: Faible adoption par les utilisateurs et non atteinte des objectifs métiers. | K8: Accompagner les utilisateurs dans la prise en main des nouveaux systèmes.
G9: Document de gouvernance IT attestant du poids décisionnel des directions métiers | K9: Définir des indicateurs de performance (KPI) pour mesurer l'adoption et l'atteinte des objectifs.
D10: L'ordre du jour des réunions est documenté? | E10: L'ordre du jour des réunions est-il documenté? | F10: NON | G10: Ordres du jour archivés des réunions du comité | H10: Systèmes inadaptés aux besoins métiers. | I10: Elevée | J10: Pertes de temps et sujets importants non traités. | K10: Prioriser les sujets et les tâches en fonction de leur importance et de leur urgence.
G11: Procès-verbaux des réunions avec suivi des points traités | K11: Mettre en place des outils de gestion de projet et de suivi des tâches.
C12: S’assurer de l’existence d'une politique relative aux applications | D12: Il existe une politique relative aux applications au sein de l'institution | E12: Existe-t-il une politique relative aux applications au sein de l'institution? | F12: OUI | G12: Document officiel de la politique applicative | H12: Réunions inefficaces. | I12: Moyenne | J12: Coûts élevés et duplication des fonctions. | K12: Rationaliser les applications et les systèmes existants.
G13: Procès-verbal de validation par la direction générale | K13: Automatiser les tâches répétitives et chronophages.
D14: La politique est connue des utilisateurs d'applications | E14: La politique est-elle connue des utilisateurs d'applications? | F14: OUI | G14: Registre des formations suivies par les utilisateurs | H14: Gestion anarchique des applications. | I14: Elevée | J14: Problèmes de sécurité et erreurs d'utilisation. | K14: Sensibiliser les utilisateurs aux bonnes pratiques de sécurité.
G15: Attestations de connaissance de la politique signées par les utilisateurs | K15: Mettre en place des contrôles d'accès et des mécanismes d'authentification robustes.
D16: La politique est largement diffusée | E16: La politique est-elle largement diffusée? | F16: OUI | G16: Plan de communication institutionnel | H16: Non-respect de la politique. | I16: Faible | J16: Application incomplète de la politique et problèmes de conformité. | K16: Formaliser et diffuser la politique de sécurité SI.
G17: Preuves matérielles de diffusion (emails, publications intranet) | K17: Effectuer des audits réguliers pour vérifier la conformité aux normes et réglementations.
D18: La politique est mise en œuvre | E18: La politique est-elle mise en œuvre? | F18: NON | G18: Rapport d'audit de conformité | H18: Méconnaissance de la politique par une partie du personnel. | I18: Elevée | J18: Aucun impact concret sur les pratiques et les problèmes persistent. | K18: Mettre en place un plan d'action correctif pour résoudre les problèmes identifiés.
G19: Journal des contrôles effectués | K19: Suivre l'efficacité des actions correctives et ajuster si nécessaire.
D20: La politique couvre l'ensemble du cycle de vie de l’application | E20: La politique couvre-t-elle l'ensemble du cycle de vie de l'application? | F20: PAS | G20: Document décrivant le cycle de vie complet des applications | H20: La politique reste théorique. | I20: Moyenne | J20: Problèmes de sécurité et erreurs lors de certaines phases du cycle de vie de l'application. | K20: Intégrer la sécurité dès la phase de conception des applications (approche Security by Design).
G21: Procédures opérationnelles pour chaque phase du cycle | K21: Réaliser des tests de sécurité tout au long du cycle de développement.
D22: La politique favorise la responsabilisation des utilisateurs dans l'usage de leur système d’information (application) | E22: La politique favorise-t-elle la responsabilisation des utilisateurs dans l'usage de leur système d'information (application)? | F22: NON | G22: Charte d'utilisation signée par les utilisateurs | H22: La politique est incomplète et ne couvre pas toutes les étapes. | I22: Elevée | J22: Mauvaise qualité des données et pertes d'informations. | K22: Mettre en place des processus de validation et de nettoyage des données.
G23: Registre des sanctions appliquées | K23: Sauvegarder régulièrement les données et mettre en place un plan de reprise d'activité.
D24: La politique préconise l'attribution formelle de responsabilités aux utilisateurs du système (application) | E24: La politique préconise-t-elle l'attribution formelle de responsabilités aux utilisateurs du système (application)? | F24: NON | G24: Fiches de poste avec responsabilités applicatives définies | H24: Manque d'implication des utilisateurs. | I24: Faible | J24: Manque de clarté sur qui fait quoi et erreurs fréquentes. | K24: Définir clairement les rôles et responsabilités de chaque acteur.
G25: Matrice RACI officielle | K25: Documenter les processus et les procédures.
C26: S’assurer que les rôle et responsabilités des utilisateurs sont bien définis | D26: Le rôle et les responsabilités des utilisateurs vis-à-vis de l’application sont clairement identifiés | E26: Le rôle et les responsabilités des utilisateurs vis-à-vis de l'application sont-ils clairement identifiés? | F26: OUI | G26: Manuel des procédures utilisateurs | H26: Responsabilités mal définies. | I26: Elevée | J26: Difficultés à identifier les responsables en cas de problème. | K26: Mettre en place une matrice RACI (Responsible, Accountable, Consulted, Informed).
G27: Tableau des droits d'accès par profil métier | K27: Définir un processus d'escalade des problèmes.
D28: Le rôle et les responsabilités des utilisateurs vis-à-vis de l’application couvrent l’analyse des risques | E28: Le rôle et les responsabilités des utilisateurs vis-à-vis de l'application couvrent-ils l'analyse des risques? | F28: OUI | G28: Rapport d'analyse des risques impliquant les utilisateurs métiers | H28: Manque de clarté sur les rôles et responsabilités. | I28: Moyenne | J28: Mesures de sécurité non adaptées. | K28: Effectuer une analyse de risques pour identifier les menaces et les vulnérabilités.
G29: Procès-verbal de validation des risques par les responsables métiers | K29: Mettre en place des mesures de sécurité appropriées pour atténuer les risques.
D30: Le rôle et les responsabilités des utilisateurs vis-à-vis de l’application couvrent la définition des besoins de sécurité | E30: Le rôle et les responsabilités des utilisateurs vis-à-vis de l'application couvrent-ils la définition des besoins de sécurité? | F30: OUI | G30: Cahier des charges sécurité co-construit avec les métiers | H30: Absence de prise en compte des besoins de sécurité par les utilisateurs. | I30: Elevée | J30: Systèmes obsolètes. | K30: Systèmes à jour et maintenus.
G31: PV de réunion de définition des exigences de sécurité | K31: Plan de secours et de reprise après sinistre.
D32: Le rôle et les responsabilités des utilisateurs vis-à-vis de l’application couvrent la gestion des changements et des évolutions | E32: Le rôle et les responsabilités des utilisateurs vis-à-vis de l'application couvrent-ils la gestion des changements et des évolutions? | F32: NON | G32: Procédure formalisée de gestion des changements | H32: Gestion des changements et des évolutions inadaptée aux besoins. | I32: Faible | J32: Difficultés à maintenir l'application et insatisfaction des utilisateurs. | K32: Définir des objectifs de sécurité clairs et mesurables.
G33: Registre des demandes d'évolution initiées par les métiers | K33: Suivre et évaluer régulièrement la performance de la sécurité.
D34: Le rôle et les responsabilités des utilisateurs vis-à-vis de l’application couvrent l’administration de l’application | E34: Le rôle et les responsabilités des utilisateurs vis-à-vis de l'application couvrent-ils l'administration de l'application? | F34: PAS | G34: Procédures d'administration déléguée aux utilisateurs | H34: Administration de l'application déconnectée des besoins des utilisateurs. | I34: Elevée | J34: Difficulté à maintenir l'application et insatisfaction des utilisateurs. | K34: Séparer les tâches critiques pour éviter les conflits d'intérêts et les fraudes.
G35: Journal des opérations administratives réalisées par les métiers | K35: Former le personnel sur les politiques et procédures de sécurité.
C36: S’assurer qu’une analyse des risques a été réalisée | D36: Une analyse des risques spécifique à l’application a été réalisée | E36: Une analyse des risques spécifique à l'application a-t-elle été réalisée? | F36: NON | G36: Rapport complet d'analyse des risques applicative | H36: Mauvaise identification des risques pour l'application. | I36: Moyenne | J36: Mauvaise identification des risques pour l'application. | K36: Définir un niveau de sécurité cible et allouer les ressources nécessaires.
G37: Grille d'évaluation des risques spécifique à l'application | K37: Mettre en œuvre des contrôles de sécurité pour surveiller et protéger les systèmes.
D38: L'analyse des risques a débouché sur la définition des besoins de sécurité | E38: L'analyse des risques a-t-elle débouché sur la définition des besoins de sécurité? | F38: NON | G38: Document de synthèse des besoins de sécurité | H38: Définition des besoins de sécurité incomplète ou inadaptée. | I38: Elevée | J38: Définition des besoins de sécurité incomplète ou inadéquate. | K38: Documenter la méthodologie utilisée pour l'analyse et la gestion des risques.
G39: PV de validation des exigences par la direction | K39: Former le personnel sur la méthodologie et les outils utilisés.
D40: La méthode d'analyse des risques est définie et documentée (ex: EBIOS Risk Manager, MEHARI)? | E40: La méthode d'analyse des risques est-elle définie et documentée (ex: EBIOS Risk Manager, MEHARI)? | F40: OUI | G40: Manuel méthodologique d'analyse des risques (EBIOS/MEHARI) | H40: Méthode d'analyse des risques non standardisée et non documentée. | I40: Faible | J40: Méthode d'analyse des risques non standardisée et non documentée. | K40: Prendre en compte la confidentialité, l'intégrité et la disponibilité des données lors de la conception et de la mise en œuvre des systèmes.
G41: Procédure d'évaluation des risques documentée | K41: Mettre en place des mesures pour protéger les données contre les accès non autorisés, les modifications et les pertes.
D42: Les risques identifiés sont classifiés et priorisés? | E42: Les risques identifiés sont-ils classifiés et priorisés? | F42: OUI | G42: Matrice de criticité des risques classés | H42: Risques mal identifiés et non priorisés. | I42: Elevée | J42: Risques mal identifiés et non priorisés. | K42: Effectuer une analyse de risques approfondie et prioriser les risques en fonction de leur impact potentiel.
G43: Plan de traitement des risques priorisés | K43: Mettre en place un processus de gestion des risques.
D44: Les mesures de sécurité mises en place sont proportionnées aux risques identifiés? | E44: Les mesures de sécurité mises en place sont-elles proportionnées aux risques identifiés? | F44: OUI | G44: Rapport de mise en œuvre des mesures de sécurité | H44: Mesures de sécurité inadaptées aux risques identifiés. | I44: Moyenne | J44: Mesures de sécurité inadaptées aux risques identifiés. | K44: Adopter des mesures de sécurité appropriées et proportionnées aux risques identifiés.
G45: Évaluation du niveau de couverture des risques | K45: Effectuer des tests de pénétration et des audits de sécurité réguliers.
C46: S’assurer que le prolongement de l'analyse de risque et de son expansion ont été réalisés | D46: Il y a eu un prolongement de l'analyse des risques et de l'expression des besoins de sécurité? | E46: Y a-t-il eu un prolongement de l'analyse des risques et de l'expression des besoins de sécurité? | F46: NON | G46: Compte-rendu d'extension de l'analyse des risques | H46: Expression des besoins de sécurité non prise en compte. | I46: Elevée | J46: Expression des besoins de sécurité non prise en compte. | K46: Recueillir et prendre en compte les besoins de sécurité des utilisateurs et des parties prenantes.
G47: Document d'évolution des besoins de sécurité | K47: Organiser des sessions de sensibilisation à la sécurité pour les utilisateurs.
D48: Un contrat de service (SLA) entre l'informatique et la direction utilisatrice a été mis en œuvre? | E48: Un contrat de service (SLA) entre l'informatique et la direction utilisatrice a-t-il été mis en œuvre? | F48: PAS | G48: Contrat de Service (SLA) signé avec la direction métier | H48: Contrat de service (SLA) inexistant ou non appliqué. | I48: Faible | J48: Contrat de service (SLA) inexistant ou non appliqué. | K48: Mettre en place un contrat de service (SLA) clair et précis qui définit les responsabilités en matière de sécurité.
G49: Annexe sécurité du SLA définissant les engagements | K49: S'assurer que le SLA est respecté et appliqué.
D50: L'analyse des risques est mise à jour régulièrement en fonction des évolutions de l'application et des menaces? | E50: L'analyse des risques est-elle mise à jour régulièrement en fonction des évolutions de l'application et des menaces? | F50: NON | G50: Plan de révision périodique des risques | H50: Analyse des risques non mise à jour régulièrement. | I50: Elevée | J50: Analyse des risques non mise à jour régulièrement. | K50: Mettre à jour régulièrement l'analyse des risques pour refléter l'évolution des menaces et des vulnérabilités.
G51: PV des mises à jour de l'analyse des risques | K51: Documenter les modifications apportées à l'analyse des risques.
D52: Les besoins de sécurité sont revus et validés par les parties prenantes? | E52: Les besoins de sécurité sont-ils revus et validés par les parties prenantes? | F52: NON | G52: PV de revue des besoins de sécurité | H52: Besoins de sécurité non revus ni validés. | I52: Moyenne | J52: Besoins de sécurité non revus ni validés. | K52: Revoir et valider régulièrement les besoins de sécurité pour s'assurer qu'ils restent pertinents.
G53: Fiche de validation des modifications par les métiers | K53: Documenter les besoins de sécurité et les décisions prises.
D54: Les résultats de l'analyse des risques sont utilisés pour définir les priorités en matière de sécurité? | E54: Les résultats de l'analyse des risques sont-ils utilisés pour définir les priorités en matière de sécurité? | F54: OUI | G54: Plan d'action sécurité priorisé | H54: Mauvaise définition des priorités en matière de sécurité. | I54: Elevée | J54: Mauvaise définition des priorités en matière de sécurité. | K54: Définir clairement les priorités en matière de sécurité en fonction des risques identifiés et des objectifs de l'organisation.
G55: Tableau de bord des risques résiduels | K55: Allouer les ressources nécessaires pour mettre en œuvre les mesures de sécurité prioritaires.
C56: S’assurer que l’analyse et évaluation du niveau de sensibilité a été réalisée | D56: Il y a une séparation des tâches au sein de la direction utilisatrice indépendamment de l'application? | E56: Il y a une séparation des tâches au sein de la direction utilisatrice indépendamment de l'application? | F56: OUI | G56: Organigramme fonctionnel avec séparation des tâches | H56: Absence de séparation des tâches au sein de la direction utilisatrice. | I56: Faible | J56: Absence de séparation des tâches au sein de la direction utilisatrice. | K56: Mettre en place une séparation des tâches pour les fonctions critiques au sein de la direction utilisatrice afin de minimiser les risques de conflits d'intérêts et de fraudes.
G57: Description des contrôles d'incompatibilité | K57: Définir des rôles et des responsabilités clairs pour chaque membre du personnel.
D58: Il y a une « maturité » de l'organisation vis-à-vis de ses systèmes d'information? | E58: Il y a une «maturité» de l'organisation vis-à-vis de ses systèmes d'information? | F58: OUI | G58: Rapport d'évaluation de la maturité organisationnelle | H58: Niveau de sécurité insuffisant. | I58: Elevée | J58: Niveau de sécurité insuffisant. | K58: Définir un niveau de sécurité cible et allouer les ressources nécessaires pour atteindre ce niveau.
G59: Plan d'amélioration continue des processus | K59: Mettre en œuvre des contrôles de sécurité pour surveiller et protéger les systèmes et les données.
D60: Une méthode d'évaluation de la sensibilité des données est définie et documentée? | E60: Une méthode d'évaluation de la sensibilité des données est définie et documentée? | F60: NON | G60: Politique de classification des données | H60: Méthode non définie et non documentée. | I60: Moyenne | J60: Méthode non définie et non documentée. | K60: Définir et documenter une méthodologie claire pour l'analyse et la gestion des risques de sécurité.
G61: Grille d'évaluation de la sensibilité des informations | K61: Former le personnel sur la méthodologie et les outils utilisés.
D62: L'évaluation prend en compte la confidentialité, l'intégrité et la disponibilité des données? | E62: L'évaluation prend en compte la confidentialité, l'intégrité et la disponibilité des données? | F62: PAS | G62: Rapport d'évaluation CID (Confidentialité, Intégrité, Disponibilité) | H62: Confidentialité, l'intégrité et la disponibilité non prises en compte. | I62: Elevée | J62: Confidentialité, l'intégrité et la disponibilité non prises en compte. | K62: Prendre en compte la confidentialité, l'intégrité et la disponibilité des données lors de la conception et de la mise en œuvre des systèmes.
G63: Cartographie des flux de données sensibles | K63: Mettre en place des mesures pour protéger les données contre les accès non autorisés, les modifications et les pertes.
D64: Les résultats de l'évaluation sont utilisés pour définir les mesures de sécurité appropriées? | E64: Les résultats de l'évaluation sont utilisés pour définir les mesures de sécurité appropriées? | F64: NON | G64: Plan de sécurité adapté aux niveaux de sensibilité | H64: Mesures de sécurité inappropriées. | I64: Faible | J64: Vulnérabilité aux menaces. | K64: Identifier et corriger les vulnérabilités.
G65: Matrice des mesures de protection par type de données | K65: Mettre en place des mesures de sécurité pour atténuer les menaces.
C66: Vérifier l’existence d’un manuel d'administration de l'application | D66: Un ou des manuels pour l’application existe | E66: Un ou des manuels pour l'application existe? | F66: NON | G66: Fiche de versionnage du manuel | H66: Manuels inexistants. | I66: Elevée | J66: Difficulté d'utilisation et erreurs potentielles. | K66: Simplifier l'interface utilisateur et fournir une documentation claire.
G67: Procès-verbal de validation | K67: Former les utilisateurs sur l'utilisation correcte de l'application.
D68: Le manuel est à jour | E68: Le manuel est à jour? | F68: OUI | G68: Registre de formation des utilisateurs | H68: Manuels non mis à jour. | I68: Moyenne | J68: Information obsolète et utilisation incorrecte de l'application. | K68: Mettre à jour régulièrement les informations et les données de l'application.
G69: Test de connaissance utilisateurs | K69: Fournir des instructions claires sur l'utilisation prévue de l'application.
D70: Le manuel est maitrisé | E70: Le manuel est maîtrisé? | F70: OUI | G70: Manuel utilisateur complet | H70: Manuels non maîtrisés. | I70: Elevée | J70: Difficulté à appliquer les bonnes pratiques et procédures. | K70: Fournir une formation et un soutien adéquats aux utilisateurs.
G71: Procédure opérationnelle standardisée | K71: Mettre en place des mécanismes pour encourager l'adoption des meilleures pratiques.
D72: Le manuel comprend un mode d'emploi | E72: Le manuel comprend un mode d'emploi? | F72: OUI | G72: Guide administrateur applicatif | H72: Absence de mode d'emploi. | I72: Faible | J72: Difficulté d'utilisation et erreurs potentielles. | K72: Concevoir une interface utilisateur intuitive et conviviale.
G73: Schéma d'architecture technique | K73: Mettre en œuvre des contrôles pour prévenir les erreurs potentielles.
D74: Le manuel comprend une présentation du module d’administration de l’application | E74: Le manuel comprend une présentation du module d'administration de l'application? | F74: NON | G74: Matrice des droits d'accès | H74: Absence de présentation du module d'administration. | I74: Elevée | J74: Administration difficile. | K74: Simplifier les tâches d'administration et automatiser les processus.
G75: Politique de sécurité applicative | K75: Fournir aux administrateurs les outils et la formation nécessaires.
D76: Le manuel comprend des droits d’accès | E76: Le manuel comprend des droits d'accès? | F76: PAS | G76: Formulaire de demande de modification | H76: Absence d'information sur les droits d'accès. | I76: Moyenne | J76: Accès non autorisés et gestion des droits inefficace. | K76: Mettre en place un contrôle d'accès strict et une gestion des droits efficace.
G77: Procès-verbal de validation propriétaire | K77: Surveiller régulièrement les accès et les activités des utilisateurs.
C78: Vérifier l’existence de procédures formalisées | D78: Des procédures formalisées imposant l’accord du « propriétaire » de l’application pour tout changement sur les programmes de l’application existent | E78: Des procédures formalisées imposant l'accord du «propriétaire» de l'application pour tout changement sur les programmes de l'application existent? | F78: NON | G78: Procédure de changement de planning | H78: Absence d'accord du « propriétaire » de l'application pour tout changement sur les programmes. | I78: Elevée | J78: Changement non autorisées. | K78: Mettre en place des contrôles pour empêcher les modifications non autorisées.
G79: Journal des modifications approuvées | K79: Enregistrer et auditer tous les changements.
D80: Des procédures formalisées imposant l’accord du « propriétaire » de l’application pour tout changement sur la planification des traitements informatiques existent | E80: Des procédures formalisées imposant l'accord du «propriétaire» de l'application pour tout changement sur la planification des traitements informatiques existent? | F80: NON | G80: Charte d'évolution technologique | H80: Absence d'accord du « propriétaire » de l'application pour la planification des traitements informatiques. | I80: Faible | J80: Risques liées à une gestion mauvaise. | K80: Adopter des pratiques de gestion des risques saines.
G81: PV du comité technique | K81: Examiner et mettre à jour régulièrement les politiques et les procédures.
D82: Des procédures formalisées imposant l’accord du « propriétaire » de l’application pour tout changement sur l’environnement technologique de l’application existent | E82: Des procédures formalisées imposant l'accord du «propriétaire» de l'application pour tout changement sur l'environnement technologique de l'application existent? | F82: OUI | G82: Procédures administratives formalisées | H82: Absence d'accord du « propriétaire » de l'application pour tout changement sur l'environnement technologique. | I82: Elevée | J82: Résolution lente des incidents. | K82: Mettre en place un processus efficace de gestion des incidents.
G83: Registre des opérations effectuées | K83: Allouer des ressources suffisantes pour la résolution des incidents.
D84: L'administration est bien assurée par les utilisateurs | E84: L'administration est bien assurée par les utilisateurs? | F84: OUI | G84: Processus de gestion des incidents | H84: Mauvaise gestion de l'application. | I84: Moyenne | J84: Identifier les performance des applications pas a jour | K84: Mettre en place une surveillance des performances et des alertes.
G85: Fiches types d'intervention | K85: Maintenir les applications à jour.
D86: Vérifier l'existence de procédures formalisées de gestion des incidents | E86: Des procédures formalisées de gestion des incidents sont-elles en place ? | F86: OUI | G86: Rapport mensuel de performance | H86: Problèmes de gestion des incidents. | I86: Elevée | J86: Résolution lente des incidents. | K86: Définir des accords de niveau de service (SLA) et des procédures d'escalade.
G87: Tableau de bord SLA | K87: Automatiser la résolution des incidents.
C88: S’assurer de l’existence et de la mise à disposition du compte rendu mensuel au propriétaire | D88: Le propriétaire dispose d'un compte rendu mensuel de la performance de l'application | E88: Le propriétaire dispose-t-il d'un compte rendu mensuel de la performance de l'application ? | F88: NON | G88: Engagement contractuel formalisé | H88: Manque de visibilité sur la performance de l'application. | I88: Faible | J88: Dégradation des performances non détectées. | K88: Mettre en place une surveillance proactive des performances.
G89: Preuve de livraison dans les délais | K89: Analyser les causes profondes des dégradations de performance.
D90: Le compte rendu respecte le contrat du service | E90: Le compte rendu respecte-t-il le contrat de service ? | F90: PAS | G90: Indicateurs clés de performance | H90: Non-respect des obligations contractuelles. | I90: Elevée | J90: Contentieux avec le fournisseur. | K90: Négocier des contrats clairs avec des clauses de pénalité.
G91: Commentaires du propriétaire | K91: Mettre en place une communication régulière avec le fournisseur.
D92: Le compte rendu est transmis au propriétaire dans les délais convenus? | E92: Le compte rendu est-il transmis au propriétaire dans les délais convenus ? | F92: NON | G92: Procédure de validation | H92: Comptes rendus incompréhensibles ou incomplets. | I92: Moyenne | J92: Compte rendu inexistant. | K92: Fournir des comptes rendus réguliers sur les performances et les incidents.
G93: Attestation de réception | K93: Documenter tous les échanges et les accords.
D94: Le compte rendu contient des indicateurs de performance pertinents pour le propriétaire? | E94: Le compte rendu contient-il des indicateurs de performance pertinents pour le propriétaire ? | F94: NON | G94: Manuel des procédures | H94: Mauvaise communication avec le propriétaire. | I94: Elevée | J94: Contrats de niveau service inadéquats. | K94: Négocier des contrats de niveau de service adaptés aux besoins de l'entreprise.
G95: Plan de diffusion interne | K95: Revoir régulièrement les contrats et les ajuster si nécessaire.
D96: Un processus est en place pour s'assurer que le propriétaire comprend et valide le compte rendu | E96: Un processus est-il en place pour s'assurer que le propriétaire comprend et valide le compte rendu ? | F96: OUI | G96: Registre de diffusion | H96: Absence de guide utilisateur. | I96: Faible | J96: Mauvaise connaissance et manque de conformité. | K96: Former le personnel sur les politiques, les procédures et les exigences de conformité.
G97: Accusés de réception | K97: Mettre à disposition des ressources et une documentation accessibles.
C98: S’assurer de l’existence d'un guide d'utilisateur, manuel de procédures | D98: Il existe un guide utilisateurs / manuel de procédures | E98: Existe-t-il un guide utilisateurs / manuel de procédures ? | F98: OUI | G98: Version officielle du manuel utilisateur | H98: Mauvaise diffusion des guides. | I98: Elevée | J98: Information inaccessible. | K98: Mettre en place des contrôles d'accès pour restreindre l'accès aux informations sensibles.
G99: Plan de diffusion et registre de distribution | K99: Chiffrer les données sensibles.
D100: Le manuel est diffusé | E100: Le manuel est-il diffusé ? | F100: OUI | G100: Historique des versions et dates de mise à jour | H100: Guides non mis à jour. | I100: Moyenne | J100: Mauvaise utilisation de l'outil. | K100: Fournir une formation adéquate sur l'utilisation correcte des outils.
...

Sheet Application_en_Service
A1: Domaine | B1: Point de contrôle | C1: Objectifs de contrôle | D1: Critères d'évaluation | E1: Questions d'évaluation | F1: Réponses | G1: Documents requis | H1: risque | I1: criticité | J1: conséquences | K1: récommendations
A2: Application en service | B2: Organisation | C2: S’assurer de l’existence d'un comité informatique | D2: Existence d'un comité informatique | E2: Existe-t-il un comité informatique ? | F2: OUI | G2: Décision de création du comité informatique signée par le DG | H2: Inexistence d'un comité informatique | I2: Elevée | J2: Décisions informatiques déconnectées des besoins métiers. | K2: mpliquer les métiers dans les instances de décision concernant les SI.
G3: Procès-verbal de réunion attestant de la création du comité informatique. | K3: Formaliser les besoins métiers et les traduire en exigences fonctionnelles et techniques.
D4: Le Comité est présidé par le Directeur Général | E4: Le Comité est-il présidé par le Directeur Général ? | F4: NON | G4: PV de session du comité | H4: Le Comité n'est pas présidé par le Directeur Général | I4: Moyenne | J4: Manque d'autorité et de légitimité des décisions du comité. | K4: Clarifier les rôles et responsabilités du comité de pilotage SI.
G5: Décision de nomination du Président du comité informatique signée par le Directeur Général. | K5: Documenter les décisions prises et les diffuser aux parties prenantes.
D6: Les directions utilisatrices sont représentées au sein de ce Comité | E6: Les directions utilisatrices sont-elles représentées au sein de ce Comité ? | F6: PAS | G6: Décision d'affectation des directions au comité | H6: Les directions utilisatrices ne sont pas représentées au sein de ce Comité. | I6: Elevée | J6: Systèmes inadaptés aux besoins réels des utilisateurs. | K6: Mener des études d'utilisabilité et des tests utilisateurs avant et après la mise en production.
G7: PV de session du comité | K7: Mettre en place un processus de recueil et de gestion des feedbacks utilisateurs.
D8: Les directions utilisatrices sont influentes au sein de ce Comité | E8: Les directions utilisatrices sont-elles influentes au sein de ce Comité ? | F8: NON | G8: Procès-verbal des réunions mentionnant les contributions des directions utilisatrices | H8: Les directions utilisatrices ne sont pas influentes au sein de ce Comité | I8: Faible | J8: Faible adoption par les utilisateurs et non atteinte des objectifs métiers. | K8: Accompagner les utilisateurs dans la prise en main des nouveaux systèmes.
G9: Document de gouvernance IT attestant du poids décisionnel des directions métiers | K9: Définir des indicateurs de performance (KPI) pour mesurer l'adoption et l'atteinte des objectifs.
D10: L'ordre du jour des réunions est documenté? | E10: L'ordre du jour des réunions est-il documenté? | F10: NON | G10: Ordres du jour archivés des réunions du comité | H10: Systèmes inadaptés aux besoins métiers. | I10: Elevée | J10: Pertes de temps et sujets importants non traités. | K10: Prioriser les sujets et les tâches en fonction de leur importance et de leur urgence.
G11: Procès-verbaux des réunions avec suivi des points traités | K11: Mettre en place des outils de gestion de projet et de suivi des tâches.
C12: S’assurer de l’existence d'une politique relative aux applications | D12: Il existe une politique relative aux applications au sein de l'institution | E12: Existe-t-il une politique relative aux applications au sein de l'institution? | F12: OUI | G12: Document officiel de la politique applicative | H12: Réunions inefficaces. | I12: Moyenne | J12: Coûts élevés et duplication des fonctions. | K12: Rationaliser les applications et les systèmes existants.
G13: Procès-verbal de validation par la direction générale | K13: Automatiser les tâches répétitives et chronophages.
D14: La politique est connue des utilisateurs d'applications | E14: La politique est-elle connue des utilisateurs d'applications? | F14: OUI | G14: Registre des formations suivies par les utilisateurs | H14: Gestion anarchique des applications. | I14: Elevée | J14: Problèmes de sécurité et erreurs d'utilisation. | K14: Sensibiliser les utilisateurs aux bonnes pratiques de sécurité.
G15: Attestations de connaissance de la politique signées par les utilisateurs | K15: Mettre en place des contrôles d'accès et des mécanismes d'authentification robustes.
D16: La politique est largement diffusée | E16: La politique est-elle largement diffusée? | F16: OUI | G16: Plan de communication institutionnel | H16: Non-respect de la politique. | I16: Faible | J16: Application incomplète de la politique et problèmes de conformité. | K16: Formaliser et diffuser la politique de sécurité SI.
G17: Preuves matérielles de diffusion (emails, publications intranet) | K17: Effectuer des audits réguliers pour vérifier la conformité aux normes et réglementations.
D18: La politique est mise en œuvre | E18: La politique est-elle mise en œuvre? | F18: NON | G18: Rapport d'audit de conformité | H18: Méconnaissance de la politique par une partie du personnel. | I18: Elevée | J18: Aucun impact concret sur les pratiques et les problèmes persistent. | K18: Mettre en place un plan d'action correctif pour résoudre les problèmes identifiés.
G19: Journal des contrôles effectués | K19: Suivre l'efficacité des actions correctives et ajuster si nécessaire.
D20: La politique couvre l'ensemble du cycle de vie de l’application | E20: La politique couvre-t-elle l'ensemble du cycle de vie de l'application? | F20: PAS | G20: Document décrivant le cycle de vie complet des applications | H20: La politique reste théorique. | I20: Moyenne | J20: Problèmes de sécurité et erreurs lors de certaines phases du cycle de vie de l'application. | K20: Intégrer la sécurité dès la phase de conception des applications (approche Security by Design).
G21: Procédures opérationnelles pour chaque phase du cycle | K21: Réaliser des tests de sécurité tout au long du cycle de développement.
D22: La politique favorise la responsabilisation des utilisateurs dans l'usage de leur système d’information (application) | E22: La politique favorise-t-elle la responsabilisation des utilisateurs dans l'usage de leur système d'information (application)? | F22: NON | G22: Charte d'utilisation signée par les utilisateurs | H22: La politique est incomplète et ne couvre pas toutes les étapes. | I22: Elevée | J22: Mauvaise qualité des données et pertes d'informations. | K22: Mettre en place des processus de validation et de nettoyage des données.
G23: Registre des sanctions appliquées | K23: Sauvegarder régulièrement les données et mettre en place un plan de reprise d'activité.
D24: La politique préconise l'attribution formelle de responsabilités aux utilisateurs du système (application) | E24: La politique préconise-t-elle l'attribution formelle de responsabilités aux utilisateurs du système (application)? | F24: NON | G24: Fiches de poste avec responsabilités applicatives définies | H24: Manque d'implication des utilisateurs. | I24: Faible | J24: Manque de clarté sur qui fait quoi et erreurs fréquentes. | K24: Définir clairement les rôles et responsabilités de chaque acteur.
G25: Matrice RACI officielle | K25: Documenter les processus et les procédures.
C26: S’assurer que les rôle et responsabilités des utilisateurs sont bien définis | D26: Le rôle et les responsabilités des utilisateurs vis-à-vis de l’application sont clairement identifiés | E26: Le rôle et les responsabilités des utilisateurs vis-à-vis de l'application sont-ils clairement identifiés? | F26: OUI | G26: Manuel des procédures utilisateurs | H26: Responsabilités mal définies. | I26: Elevée | J26: Difficultés à identifier les responsables en cas de problème. | K26: Mettre en place une matrice RACI (Responsible, Accountable, Consulted, Informed).
G27: Tableau des droits d'accès par profil métier | K27: Définir un processus d'escalade des problèmes.
D28: Le rôle et les responsabilités des utilisateurs vis-à-vis de l’application couvrent l’analyse des risques | E28: Le rôle et les responsabilités des utilisateurs vis-à-vis de l'application couvrent-ils l'analyse des risques? | F28: OUI | G28: Rapport d'analyse des risques impliquant les utilisateurs métiers | H28: Manque de clarté sur les rôles et responsabilités. | I28: Moyenne | J28: Mesures de sécurité non adaptées. | K28: Effectuer une analyse de risques pour identifier les menaces et les vulnérabilités.
G29: Procès-verbal de validation des risques par les responsables métiers | K29: Mettre en place des mesures de sécurité appropriées pour atténuer les risques.
D30: Le rôle et les responsabilités des utilisateurs vis-à-vis de l’application couvrent la définition des besoins de sécurité | E30: Le rôle et les responsabilités des utilisateurs vis-à-vis de l'application couvrent-ils la définition des besoins de sécurité? | F30: OUI | G30: Cahier des charges sécurité co-construit avec les métiers | H30: Absence de prise en compte des besoins de sécurité par les utilisateurs. | I30: Elevée | J30: Systèmes obsolètes. | K30: Systèmes à jour et maintenus.
G31: PV de réunion de définition des exigences de sécurité | K31: Plan de secours et de reprise après sinistre.
D32: Le rôle et les responsabilités des utilisateurs vis-à-vis de l’application couvrent la gestion des changements et des évolutions | E32: Le rôle et les responsabilités des utilisateurs vis-à-vis de l'application couvrent-ils la gestion des changements et des évolutions? | F32: NON | G32: Procédure formalisée de gestion des changements | H32: Gestion des changements et des évolutions inadaptée aux besoins. | I32: Faible | J32: Difficultés à maintenir l'application et insatisfaction des utilisateurs. | K32: Définir des objectifs de sécurité clairs et mesurables.
G33: Registre des demandes d'évolution initiées par les métiers | K33: Suivre et évaluer régulièrement la performance de la sécurité.
D34: Le rôle et les responsabilités des utilisateurs vis-à-vis de l’application couvrent l’administration de l’application | E34: Le rôle et les responsabilités des utilisateurs vis-à-vis de l'application couvrent-ils l'administration de l'application? | F34: PAS | G34: Procédures d'administration déléguée aux utilisateurs | H34: Administration de l'application déconnectée des besoins des utilisateurs. | I34: Elevée | J34: Difficulté à maintenir l'application et insatisfaction des utilisateurs. | K34: Séparer les tâches critiques pour éviter les conflits d'intérêts et les fraudes.
G35: Journal des opérations administratives réalisées par les métiers | K35: Former le personnel sur les politiques et procédures de sécurité.
C36: S’assurer qu’une analyse des risques a été réalisée | D36: Une analyse des risques spécifique à l’application a été réalisée | E36: Une analyse des risques spécifique à l'application a-t-elle été réalisée? | F36: NON | G36: Rapport complet d'analyse des risques applicative | H36: Mauvaise identification des risques pour l'application. | I36: Moyenne | J36: Mauvaise identification des risques pour l'application. | K36: Définir un niveau de sécurité cible et allouer les ressources nécessaires.
G37: Grille d'évaluation des risques spécifique à l'application | K37: Mettre en œuvre des contrôles de sécurité pour surveiller et protéger les systèmes.
D38: L'analyse des risques a débouché sur la définition des besoins de sécurité | E38: L'analyse des risques a-t-elle débouché sur la définition des besoins de sécurité? | F38: NON | G38: Document de synthèse des besoins de sécurité | H38: Définition des besoins de sécurité incomplète ou inadaptée. | I38: Elevée | J38: Définition des besoins de sécurité incomplète ou inadéquate. | K38: Documenter la méthodologie utilisée pour l'analyse et la gestion des risques.
G39: PV de validation des exigences par la direction | K39: Former le personnel sur la méthodologie et les outils utilisés.
D40: La méthode d'analyse des risques est définie et documentée (ex: EBIOS Risk Manager, MEHARI)? | E40: La méthode d'analyse des risques est-elle définie et documentée (ex: EBIOS Risk Manager, MEHARI)? | F40: OUI | G40: Manuel méthodologique d'analyse des risques (EBIOS/MEHARI) | H40: Méthode d'analyse des risques non standardisée et non documentée. | I40: Faible | J40: Méthode d'analyse des risques non standardisée et non documentée. | K40: Prendre en compte la confidentialité, l'intégrité et la disponibilité des données lors de la conception et de la mise en œuvre des systèmes.
G41: Procédure d'évaluation des risques documentée | K41: Mettre en place des mesures pour protéger les données contre les accès non autorisés, les modifications et les pertes.
D42: Les risques identifiés sont classifiés et priorisés? | E42: Les risques identifiés sont-ils classifiés et priorisés? | F42: OUI | G42: Matrice de criticité des risques classés | H42: Risques mal identifiés et non priorisés. | I42: Elevée | J42: Risques mal identifiés et non priorisés. | K42: Effectuer une analyse de risques approfondie et prioriser les risques en fonction de leur impact potentiel.
G43: Plan de traitement des risques priorisés | K43: Mettre en place un processus de gestion des risques.
D44: Les mesures de sécurité mises en place sont proportionnées aux risques identifiés? | E44: Les mesures de sécurité mises en place sont-elles proportionnées aux risques identifiés? | F44: OUI | G44: Rapport de mise en œuvre des mesures de sécurité | H44: Mesures de sécurité inadaptées aux risques identifiés. | I44: Moyenne | J44: Mesures de sécurité inadaptées aux risques identifiés. | K44: Adopter des mesures de sécurité appropriées et proportionnées aux risques identifiés.
G45: Évaluation du niveau de couverture des risques | K45: Effectuer des tests de pénétration et des audits de sécurité réguliers.
C46: S’assurer que le prolongement de l'analyse de risque et de son expansion ont été réalisés | D46: Il y a eu un prolongement de l'analyse des risques et de l'expression des besoins de sécurité? | E46: Y a-t-il eu un prolongement de l'analyse des risques et de l'expression des besoins de sécurité? | F46: NON | G46: Compte-rendu d'extension de l'analyse des risques | H46: Expression des besoins de sécurité non prise en compte. | I46: Elevée | J46: Expression des besoins de sécurité non prise en compte. | K46: Recueillir et prendre en compte les besoins de sécurité des utilisateurs et des parties prenantes.
G47: Document d'évolution des besoins de sécurité | K47: Organiser des sessions de sensibilisation à la sécurité pour les utilisateurs.
D48: Un contrat de service (SLA) entre l'informatique et la direction utilisatrice a été mis en œuvre? | E48: Un contrat de service (SLA) entre l'informatique et la direction utilisatrice a-t-il été mis en œuvre? | F48: PAS | G48: Contrat de Service (SLA) signé avec la direction métier | H48: Contrat de service (SLA) inexistant ou non appliqué. | I48: Faible | J48: Contrat de service (SLA) inexistant ou non appliqué. | K48: Mettre en place un contrat de service (SLA) clair et précis qui définit les responsabilités en matière de sécurité.
G49: Annexe sécurité du SLA définissant les engagements | K49: S'assurer que le SLA est respecté et appliqué.
D50: L'analyse des risques est mise à jour régulièrement en fonction des évolutions de l'application et des menaces? | E50: L'analyse des risques est-elle mise à jour régulièrement en fonction des évolutions de l'application et des menaces? | F50: NON | G50: Plan de révision périodique des risques | H50: Analyse des risques non mise à jour régulièrement. | I50: Elevée | J50: Analyse des risques non mise à jour régulièrement. | K50: Mettre à jour régulièrement l'analyse des risques pour refléter l'évolution des menaces et des vulnérabilités.
G51: PV des mises à jour de l'analyse des risques | K51: Documenter les modifications apportées à l'analyse des risques.
D52: Les besoins de sécurité sont revus et validés par les parties prenantes? | E52: Les besoins de sécurité sont-ils revus et validés par les parties prenantes? | F52: NON | G52: PV de revue des besoins de sécurité | H52: Besoins de sécurité non revus ni validés. | I52: Moyenne | J52: Besoins de sécurité non revus ni validés. | K52: Revoir et valider régulièrement les besoins de sécurité pour s'assurer qu'ils restent pertinents.
G53: Fiche de validation des modifications par les métiers | K53: Documenter les besoins de sécurité et les décisions prises.
D54: Les résultats de l'analyse des risques sont utilisés pour définir les priorités en matière de sécurité? | E54: Les résultats de l'analyse des risques sont-ils utilisés pour définir les priorités en matière de sécurité? | F54: OUI | G54: Plan d'action sécurité priorisé | H54: Mauvaise définition des priorités en matière de sécurité. | I54: Elevée | J54: Mauvaise définition des priorités en matière de sécurité. | K54: Définir clairement les priorités en matière de sécurité en fonction des risques identifiés et des objectifs de l'organisation.
G55: Tableau de bord des risques résiduels | K55: Allouer les ressources nécessaires pour mettre en œuvre les mesures de sécurité prioritaires.
C56: S’assurer que l’analyse et évaluation du niveau de sensibilité a été réalisée | D56: Il y a une séparation des tâches au sein de la direction utilisatrice indépendamment de l'application? | E56: Il y a une séparation des tâches au sein de la direction utilisatrice indépendamment de l'application? | F56: OUI | G56: Organigramme fonctionnel avec séparation des tâches | H56: Absence de séparation des tâches au sein de la direction utilisatrice. | I56: Faible | J56: Absence de séparation des tâches au sein de la direction utilisatrice. | K56: Mettre en place une séparation des tâches pour les fonctions critiques au sein de la direction utilisatrice afin de minimiser les risques de conflits d'intérêts et de fraudes.
G57: Description des contrôles d'incompatibilité | K57: Définir des rôles et des responsabilités clairs pour chaque membre du personnel.
D58: Il y a une « maturité » de l'organisation vis-à-vis de ses systèmes d'information? | E58: Il y a une «maturité» de l'organisation vis-à-vis de ses systèmes d'information? | F58: OUI | G58: Rapport d'évaluation de la maturité organisationnelle | H58: Niveau de sécurité insuffisant. | I58: Elevée | J58: Niveau de sécurité insuffisant. | K58: Définir un niveau de sécurité cible et allouer les ressources nécessaires pour atteindre ce niveau.
G59: Plan d'amélioration continue des processus | K59: Mettre en œuvre des contrôles de sécurité pour surveiller et protéger les systèmes et les données.
D60: Une méthode d'évaluation de la sensibilité des données est définie et documentée? | E60: Une méthode d'évaluation de la sensibilité des données est définie et documentée? | F60: NON | G60: Politique de classification des données | H60: Méthode non définie et non documentée. | I60: Moyenne | J60: Méthode non définie et non documentée. | K60: Définir et documenter une méthodologie claire pour l'analyse et la gestion des risques de sécurité.
G61: Grille d'évaluation de la sensibilité des informations | K61: Former le personnel sur la méthodologie et les outils utilisés.
D62: L'évaluation prend en compte la confidentialité, l'intégrité et la disponibilité des données? | E62: L'évaluation prend en compte la confidentialité, l'intégrité et la disponibilité des données? | F62: PAS | G62: Rapport d'évaluation CID (Confidentialité, Intégrité, Disponibilité) | H62: Confidentialité, l'intégrité et la disponibilité non prises en compte. | I62: Elevée | J62: Confidentialité, l'intégrité et la disponibilité non prises en compte. | K62: Prendre en compte la confidentialité, l'intégrité et la disponibilité des données lors de la conception et de la mise en œuvre des systèmes.
G63: Cartographie des flux de données sensibles | K63: Mettre en place des mesures pour protéger les données contre les accès non autorisés, les modifications et les pertes.
D64: Les résultats de l'évaluation sont utilisés pour définir les mesures de sécurité appropriées? | E64: Les résultats de l'évaluation sont utilisés pour définir les mesures de sécurité appropriées? | F64: NON | G64: Plan de sécurité adapté aux niveaux de sensibilité | H64: Mesures de sécurité inappropriées. | I64: Faible | J64: Vulnérabilité aux menaces. | K64: Identifier et corriger les vulnérabilités.
G65: Matrice des mesures de protection par type de données | K65: Mettre en place des mesures de sécurité pour atténuer les menaces.
C66: Vérifier l’existence d’un manuel d'administration de l'application | D66: Un ou des manuels pour l’application existe | E66: Un ou des manuels pour l'application existe? | F66: NON | G66: Fiche de versionnage du manuel | H66: Manuels inexistants. | I66: Elevée | J66: Difficulté d'utilisation et erreurs potentielles. | K66: Simplifier l'interface utilisateur et fournir une documentation claire.
G67: Procès-verbal de validation | K67: Former les utilisateurs sur l'utilisation correcte de l'application.
D68: Le manuel est à jour | E68: Le manuel est à jour? | F68: OUI | G68: Registre de formation des utilisateurs | H68: Manuels non mis à jour. | I68: Moyenne | J68: Information obsolète et utilisation incorrecte de l'application. | K68: Mettre à jour régulièrement les informations et les données de l'application.
G69: Test de connaissance utilisateurs | K69: Fournir des instructions claires sur l'utilisation prévue de l'application.
D70: Le manuel est maitrisé | E70: Le manuel est maîtrisé? | F70: OUI | G70: Manuel utilisateur complet | H70: Manuels non maîtrisés. | I70: Elevée | J70: Difficulté à appliquer les bonnes pratiques et procédures. | K70: Fournir une formation et un soutien adéquats aux utilisateurs.
G71: Procédure opérationnelle standardisée | K71: Mettre en place des mécanismes pour encourager l'adoption des meilleures pratiques.
D72: Le manuel comprend un mode d'emploi | E72: Le manuel comprend un mode d'emploi? | F72: OUI | G72: Guide administrateur applicatif | H72: Absence de mode d'emploi. | I72: Faible | J72: Difficulté d'utilisation et erreurs potentielles. | K72: Concevoir une interface utilisateur intuitive et conviviale.
G73: Schéma d'architecture technique | K73: Mettre en œuvre des contrôles pour prévenir les erreurs potentielles.
D74: Le manuel comprend une présentation du module d’administration de l’application | E74: Le manuel comprend une présentation du module d'administration de l'application? | F74: NON | G74: Matrice des droits d'accès | H74: Absence de présentation du module d'administration. | I74: Elevée | J74: Administration difficile. | K74: Simplifier les tâches d'administration et automatiser les processus.
G75: Politique de sécurité applicative | K75: Fournir aux administrateurs les outils et la formation nécessaires.
D76: Le manuel comprend des droits d’accès | E76: Le manuel comprend des droits d'accès? | F76: PAS | G76: Formulaire de demande de modification | H76: Absence d'information sur les droits d'accès. | I76: Moyenne | J76: Accès non autorisés et gestion des droits inefficace. | K76: Mettre en place un contrôle d'accès strict et une gestion des droits efficace.
G77: Procès-verbal de validation propriétaire | K77: Surveiller régulièrement les accès et les activités des utilisateurs.
C78: Vérifier l’existence de procédures formalisées | D78: Des procédures formalisées imposant l’accord du « propriétaire » de l’application pour tout changement sur les programmes de l’application existent | E78: Des procédures formalisées imposant l'accord du «propriétaire» de l'application pour tout changement sur les programmes de l'application existent? | F78: NON | G78: Procédure de changement de planning | H78: Absence d'accord du « propriétaire » de l'application pour tout changement sur les programmes. | I78: Elevée | J78: Changement non autorisées. | K78: Mettre en place des contrôles pour empêcher les modifications non autorisées.
G79: Journal des modifications approuvées | K79: Enregistrer et auditer tous les changements.
D80: Des procédures formalisées imposant l’accord du « propriétaire » de l’application pour tout changement sur la planification des traitements informatiques existent | E80: Des procédures formalisées imposant l'accord du «propriétaire» de l'application pour tout changement sur la planification des traitements informatiques existent? | F80: NON | G80: Charte d'évolution technologique | H80: Absence d'accord du « propriétaire » de l'application pour la planification des traitements informatiques. | I80: Faible | J80: Risques liées à une gestion mauvaise. | K80: Adopter des pratiques de gestion des risques saines.
G81: PV du comité technique | K81: Examiner et mettre à jour régulièrement les politiques et les procédures.
D82: Des procédures formalisées imposant l’accord du « propriétaire » de l’application pour tout changement sur l’environnement technologique de l’application existent | E82: Des procédures formalisées imposant l'accord du «propriétaire» de l'application pour tout changement sur l'environnement technologique de l'application existent? | F82: OUI | G82: Procédures administratives formalisées | H82: Absence d'accord du « propriétaire » de l'application pour tout changement sur l'environnement technologique. | I82: Elevée | J82: Résolution lente des incidents. | K82: Mettre en place un processus efficace de gestion des incidents.
G83: Registre des opérations effectuées | K83: Allouer des ressources suffisantes pour la résolution des incidents.
D84: L'administration est bien assurée par les utilisateurs | E84: L'administration est bien assurée par les utilisateurs? | F84: OUI | G84: Processus de gestion des incidents | H84: Mauvaise gestion de l'application. | I84: Moyenne | J84: Identifier les performance des applications pas a jour | K84: Mettre en place une surveillance des performances et des alertes.
G85: Fiches types d'intervention | K85: Maintenir les applications à jour.
D86: Vérifier l'existence de procédures formalisées de gestion des incidents | E86: Des procédures formalisées de gestion des incidents sont-elles en place ? | F86: OUI | G86: Rapport mensuel de performance | H86: Problèmes de gestion des incidents. | I86: Elevée | J86: Résolution lente des incidents. | K86: Définir des accords de niveau de service (SLA) et des procédures d'escalade.
G87: Tableau de bord SLA | K87: Automatiser la résolution des incidents.
C88: S’assurer de l’existence et de la mise à disposition du compte rendu mensuel au propriétaire | D88: Le propriétaire dispose d'un compte rendu mensuel de la performance de l'application | E88: Le propriétaire dispose-t-il d'un compte rendu mensuel de la performance de l'application ? | F88: NON | G88: Engagement contractuel formalisé | H88: Manque de visibilité sur la performance de l'application. | I88: Faible | J88: Dégradation des performances non détectées. | K88: Mettre en place une surveillance proactive des performances.
G89: Preuve de livraison dans les délais | K89: Analyser les causes profondes des dégradations de performance.
D90: Le compte rendu respecte le contrat du service | E90: Le compte rendu respecte-t-il le contrat de service ? | F90: PAS | G90: Indicateurs clés de performance | H90: Non-respect des obligations contractuelles. | I90: Elevée | J90: Contentieux avec le fournisseur. | K90: Négocier des contrats clairs avec des clauses de pénalité.
G91: Commentaires du propriétaire | K91: Mettre en place une communication régulière avec le fournisseur.
D92: Le compte rendu est transmis au propriétaire dans les délais convenus? | E92: Le compte rendu est-il transmis au propriétaire dans les délais convenus ? | F92: NON | G92: Procédure de validation | H92: Comptes rendus incompréhensibles ou incomplets. | I92: Moyenne | J92: Compte rendu inexistant. | K92: Fournir des comptes rendus réguliers sur les performances et les incidents.
G93: Attestation de réception | K93: Documenter tous les échanges et les accords.
D94: Le compte rendu contient des indicateurs de performance pertinents pour le propriétaire? | E94: Le compte rendu contient-il des indicateurs de performance pertinents pour le propriétaire ? | F94: NON | G94: Manuel des procédures | H94: Mauvaise communication avec le propriétaire. | I94: Elevée | J94: Contrats de niveau service inadéquats. | K94: Négocier des contrats de niveau de service adaptés aux besoins de l'entreprise.
G95: Plan de diffusion interne | K95: Revoir régulièrement les contrats et les ajuster si nécessaire.
D96: Un processus est en place pour s'assurer que le propriétaire comprend et valide le compte rendu | E96: Un processus est-il en place pour s'assurer que le propriétaire comprend et valide le compte rendu ? | F96: OUI | G96: Registre de diffusion | H96: Absence de guide utilisateur. | I96: Faible | J96: Mauvaise connaissance et manque de conformité. | K96: Former le personnel sur les politiques, les procédures et les exigences de conformité.
G97: Accusés de réception | K97: Mettre à disposition des ressources et une documentation accessibles.
C98: S’assurer de l’existence d'un guide d'utilisateur, manuel de procédures | D98: Il existe un guide utilisateurs / manuel de procédures | E98: Existe-t-il un guide utilisateurs / manuel de procédures ? | F98: OUI | G98: Version officielle du manuel utilisateur | H98: Mauvaise diffusion des guides. | I98: Elevée | J98: Information inaccessible. | K98: Mettre en place des contrôles d'accès pour restreindre l'accès aux informations sensibles.
G99: Plan de diffusion et registre de distribution | K99: Chiffrer les données sensibles.
D100: Le manuel est diffusé | E100: Le manuel est-il diffusé ? | F100: OUI | G100: Historique des versions et dates de mise à jour | H100: Guides non mis à jour. | I100: Moyenne | J100: Mauvaise utilisation de l'outil. | K100: Fournir une formation adéquate sur l'utilisation correcte des outils.
...

Sheet Fonction_info
A1: Audit de la Fonction Informatique | B1: Point de contrôle | C1: Objectif de contrôle | D1: Critères d'évaluation | E1: Questions d'évaluation | F1: Documents réquis | G1: Réponses | H1: Risques | I1: Conséquences | J1: Criticité | K1: Récommendations
B2: Rôle et positionnement de l'informatique dans l'organisation | C2: Vérifier qu’ont été créés des Comités « informatique » (stratégique, pilotage,..) regroupant les différentes directions de l’Organisation en charge de recenser les besoins et les opportunités, gérer les priorités et suivre les projets | D2: Existence formelle des comités | E2: Les comités informatiques sontils officiellement établis et documentés ? | F2: Procès-verbal de création des comités | G2: NON | H2: Absence de formalisation des instances de gouvernance | I2: Dégradation de la gouvernance IT et perte de contrôle stratégique | J2: Elevée | K2: Formaliser une charte de gouvernance IT avec validation DG
F3: Charte de gouvernance IT | G3: NON | H3: Non-respect des bonnes pratiques de gouvernance IT | I3: Exposition accrue aux risques opérationnels et réglementaires | J3: Moyenne | K3: Créer des comités décisionnels métier-IT mensuels
D4: Représentation transversale des directions | E4: Toutes les directions concernées sontelles représentées dans ces comités ? | F4: Liste des membres avec affiliations | G4: NON | H4: Manque de représentativité des métiers | I4: Décisions déséquilibrées favorisant certains métiers au détriment d'autres | J4: Moyenne | K4: Implémenter un outil de gestion des décisions avec historique
F5: PV de nomination des représentants | G5: NON | H5: Désignation non officielle des membres | I5: Légitimité réduite des décisions prises par le comité | J5: Elevée | K5: Réaliser un audit risques IT trimestriel avec plan d'action
D6: Rôles et responsabilités définis | E6: Les rôles et responsabilités des membres sontils clairement définis ? | F6: Fiches de mission des membres | G6: NON | H6: Flou sur les attributions précises | I6: Conflits de responsabilités et inefficacité opérationnelle | J6: Moyenne | K6: Automatiser le reporting de conformité réglementaire
F7: Matrice RACI du comité | G7: NON | H7: Responsabilités mal définies ou redondantes | I7: Retards dans les prises de décision critiques | J7: Elevée | K7: Imposer la désignation formelle de sponsors métiers
D8: Réunions régulières avec participation effective | E8: Les réunions se tiennentelles régulièrement avec un taux de participation satisfaisant ? | F8: Calendrier des réunions annuelles | G8: NON | H8: Irregularité dans les réunions de pilotage | I8: Perte de dynamique et d'efficacité des instances de gouvernance | J8: Moyenne | K8: Standardiser les templates de business case et cahiers des charges
F9: Registre de participation | G9: NON | H9: Faible implication des membres | I9: Décisions prises hors cadre formel sans traçabilité | J9: Moyenne | K9: Mettre en place des revues qualité à chaque phase projet
D10: Preuves de décisions impactantes | E10: Peuton citer des décisions concrètes issues de ces comités ? | F10: PV des décisions stratégiques | G10: NON | H10: Décisions non formalisées ni tracées | I10: Impossibilité de tracer l'historique des décisions stratégiques | J10: Elevée | K10: Centraliser les procédures dans un référentiel unique
F11: Rapports d'implémentation | G11: NON | H11: Retard dans la mise en œuvre des décisions | I11: Retards dans la réalisation des projets clés | J11: Moyenne | K11: Organiser des ateliers Kaizen trimestriels
D12: Document officiel approuvé | E12: La charte informatique estelle approuvée par la direction générale ? | F12: Charte IT signée | G12: NON | H12: Non-validation par la direction | I12: Manque de légitimité des orientations IT | J12: Moyenne | K12: Nommer des Data Stewards par domaine métier
C13: Vérifier l’existence d’une charte informatique ou de tout autre document définissant le rôle et le périmètre de responsabilité de la DSI | F13: Délibération du conseil d'administration | G13: NON | H13: Absence de portage hiérarchique | I13: Désengagement de la direction générale sur les sujets IT | J13: Moyenne | K13: Auditer trimestriellement les accès sensibles
D14: Définition claire des rôles et périmètres de la DSI | E14: Les rôles et périmètres de la DSI sontils précisément décrits dans le document ? | F14: Document de cadrage DSI | G14: NON | H14: Périmètres mal délimités | I14: Conflits permanents entre équipes sur les périmètres d'intervention | J14: Elevée | K14: Réaliser un audit complet des compétences IT/métiers
F15: Cartographie des périmètres | G15: NON | H15: Chevauchement de responsabilités | I15: Doublons de travaux et gaspillage de ressources | J15: Elevée | K15: Développer un catalogue de formations obligatoires
D16: Diffusion auprès des parties prenantes | E16: La charte atelle été communiquée à l'ensemble des parties prenantes ? | F16: Plan de diffusion | G16: NON | H16: Méconnaissance des règles par les utilisateurs | I16: Non-respect des politiques et procédures établies | J16: Moyenne | K16: Segmenter le budget IT par domaine de valeur
F17: Attestations de réception | G17: NON | H17: Défaut d'appropriation par les équipes | I17: Augmentation des incidents de sécurité et de non-conformité | J17: Moyenne | K17: Renégocier annuellement les contrats fournisseurs
D18: Mise à jour régulière | E18: Le document estil mis à jour périodiquement pour rester pertinent ? | F18: Journal des versions | G18: NON | H18: Document obsolète non actualisé | I18: Inadéquation des règles avec les besoins opérationnels actuels | J18: Elevée | K18: Aligner le schéma directeur sur la feuille de route métier
F19: PV de comité de révision | G19: NON | H19: Inadéquation avec l'évolution du contexte | I19: Perte d'efficacité et de pertinence des processus | J19: Elevée | K19: Créer un lab d'innovation avec budget dédié
D20: Conformité aux normes sectorielle | E20: La charte respectetelle les normes et réglementations du secteur ? | F20: Audit de conformité | G20: NON | H20: Non-conformité réglementaire | I20: Sanctions financières et atteinte à la réputation | J20: Moyenne | K20: Lancer un programme de sensibilisation transverse
F21: Référentiel réglementaire | G21: NON | H21: Exposition à des sanctions légales | I21: Interruption d'activité pour mise en conformité | J21: Elevée | K21: Standardiser les méthodologies de change management
D22: Compréhension des enjeux SI par la direction | E22: Les membres de la direction comprennentils les enjeux stratégiques du SI ? | F22: Support de formation DG | G22: NON | H22: Méconnaissance des enjeux IT | I22: Investissements IT non optimisés et inefficaces | J22: Elevée | K22: Programmer des audits surprises sur processus critiques
C23: Évaluer le degré d’implication et de maîtrise des organes de gestion dans les systèmes d’information de l’Organisation | F23: Compte-rendu stratégique | G23: NON | H23: Décisions non alignées avec la stratégie | I23: Retard dans la transformation digitale de l'entreprise | J23: Elevée | K23: Publier un barème sanctionnel transparent
D24: Participation aux arbitrages stratégiques | E24: Participentils activement aux décisions importantes concernant le SI ? | F24: Feuilles de présence COMEX | G24: NON | H24: Désengagement de la direction | I24: Blocage des projets stratégiques par manque d'arbitrage | J24: Elevée | K24: Déployer un tableau de bord unifié avec indicateurs prédictifs
F25: PV de décisions majeures | G25: NON | H25: Retard dans les arbitrages | I25: Démotivation des équipes IT | J25: Moyenne | K25: Adopter le framework COBIT pour la gouvernance
D26: Revue régulière des risques SI | E26: Les risques informatiques sontils régulièrement examinés par la direction ? | F26: Rapport risques SI | G26: NON | H26: Sous-estimation des risques cyber | I26: Incidents de sécurité majeurs non anticipés | J26: Elevée | K26: Prioriser les actions via une matrice impact/urgence
F27: Plan de traitement | G27: NON | H27: Absence de plan de traitement | I27: Coûts élevés de remediation post-incident | J27: Moyenne | K27: Désigner des responsables avec échéances claires
D28: Suivi via indicateurs et tableaux de bord | E28: Des tableaux de bord permettentils un suivi efficace des indicateurs clés ? | F28: Tableaux de bord opérationnels | G28: NON | H28: Indicateurs non pertinents ou absents | I28: Décisions stratégiques basées sur des intuitions plutôt que des faits | J28: Moyenne | K28: Mettre en place des indicateurs d'adoption des solutions
F29: Reporting mensuel | G29: NON | H29: Décisions basées sur des données erronées | I29: Impossibilité de mesurer la performance réelle | J29: Elevée | K29: Automatiser les contrôles récurrents clés
D30: Alignement des investissements SI avec la stratégie | E30: Les investissements IT sontils alignés sur la stratégie d'entreprise ? | F30: Business case projets | G30: NON | H30: Investissements non alignés avec la stratégie | I30: Gaspillage des ressources financières sur des projets non stratégiques | J30: Moyenne | K30: Certifier les processus critiques (ISO /)
F31: Plan d'investissement IT | G31: NON | H31: Gaspillage de ressources | I31: Retard dans l'acquisition de technologies clés | J31: Elevée | K31: Établir un comité de suivi mixte direction/opérationnels
D32: Sponsor métier identifié pour chaque projet | E32: Chaque projet important disposetil d'un sponsor métier identifié ? | F32: Désignation des sponsors | G32: NON | H32: Absence de portage métier | I32: Projets livrés sans adéquation aux besoins métiers | J32: Moyenne | K32: Implémenter une méthodologie de gestion de projet agile avec des sprints courts et des démonstrations fréquentes aux utilisateurs métiers
C33: Vérifier en pratique que le leadership des grands projets est assuré par les organes de gestion | F33: PV de kick-off | G33: NON | H33: Défaut d'implication des sponsors | I33: Frustration des utilisateurs finaux | J33: Moyenne | K33: Créer des comités de pilotage bimestriels métier-IT pour valider les orientations et prioriser les demandes
D34: Implication active dans les revues et jalons | F34: CR de comité de pilotage | G34: NON | H34: Désengagement des sponsors | I34: Décisions techniques prises sans considération des impacts métiers | J34: Elevée | K34: Développer un référentiel partagé des besoins métiers avec cartographie des processus et exigences fonctionnelles
E35: Les sponsors participentils activement aux revues de projet ? | F35: Liste de présence | G35: NON | H35: Décisions prises sans les métiers | I35: Augmentation des demandes de modifications post-livraison | J35: Moyenne | K35: Standardiser les procédures de recette utilisateur avec critères d'acceptation mesurables
D36: Suivi régulier de l’avancement et des risques | E36: L'avancement et les risques des projets sontils suivis systématiquement ? | F36: Dashboard projet | G36: NON | H36: Perte de visibilité sur l'avancement | I36: Dérapages fréquents sur les coûts et délais des projets | J36: Moyenne | K36: Mettre en place des indicateurs de satisfaction utilisateur et les intégrer aux évaluations de performance IT
F37: Matrice des risques | G37: NON | H37: Survenue de risques non anticipés | I37: Perte de confiance des parties prenantes | J37: Moyenne | K37: Instaurer des revues financières trimestrielles projets avec analyse des écarts et ajustements budgétaires
D38: Priorisation alignée sur les objectifs business | E38: La priorisation des projets reflètetelle bien les objectifs business ? | F38: Grille de priorisation | G38: NON | H38: Priorisations incohérentes | I38: Allocation inefficace des ressources limitées | J38: Elevée | K38: Déployer des outils de modélisation des processus métiers avant toute conception technique
F39: PV de CODIR IT | G39: NON | H39: Allocation déséquilibrée des ressources | I39: Retard dans les projets prioritaires | J39: Elevée | K39: Former systématiquement les MOA métiers à la formalisation des besoins et au suivi projet
D40: Gouvernance claire (matrice RACI, etc.) | E40: Les rôles et responsabilités sontils clairement définis (via matrice RACI) ? | F40: Matrice RACI projet | G40: NON | H40: Confusion dans les rôles | I40: Bloquages fréquents dans l'avancement des projets | J40: Moyenne | K40: Créer des environnements de pré-production métiers pour tests en conditions réelles
F41: Fiches de rôle | G41: NON | H41: Points de blocage non identifiés | I41: Frustration des équipes et retard global | J41: Moyenne | K41: Automatiser le suivi des demandes de modifications avec analyse d'impact et validation hiérarchique
E42: Les MOA métiers sontils officiellement désignés pour chaque projet ? | F42: Arrêté de nomination MOA | G42: NON | H42: MOA non identifiés ou non impliqués | I42: Expression incomplète ou erronée des besoins métiers | J42: Elevée | K42: Développer une cellule de change management dédiée accompagnant chaque déploiement
C43: Vérifier que les métiers assurent leur rôle de MOA | D43: Désignation formelle des MOA | F43: Organigramme projet | G43: NON | H43: Défaut d'expression des besoins | I43: Solutions techniques inadaptées aux processus réels | J43: Elevée | K43: Mettre en place des tableaux de bord projet unifiés avec alertes sur les dérives de coûts/délais
D44: Participation aux spécifications et tests | E44: Participentils à la définition des besoins et aux tests utilisateurs ? | F44: Cahier des charges | G44: NON | H44: Besoins mal recensés | I44: Livraison de solutions ne répondant pas aux attentes | J44: Moyenne | K44: Adopter une approche DevOps avec intégration continue des retours métiers
F45: Procès-verbal de recette | G45: NON | H45: Tests insuffisants ou non représentatifs | I45: Coûts supplémentaires pour les corrections | J45: Elevée | K45: Élaborer des parcours d'adoption utilisateur incluant formation et support post-livraison
D46: Validation des budgets et priorités | E46: Validentils les budgets et priorités des projets les concernant ? | F46: Budget validé | G46: NON | H46: Dépassements budgétaires | I46: Dépassements budgétaires récurrents | J46: Elevée | K46: Instaurer des audits qualité indépendants à mi-parcours des projets clés
F47: PV de comité des priorités | G47: NON | H47: Retards dans les livraisons | I47: Réduction forcée du périmètre des projets | J47: Elevée | K47: Créer un observatoire des technologies métiers pour anticiper les besoins émergents
D48: Collaboration structurée avec la MOE | E48: La collaboration entre MOA et MOE estelle formalisée et efficace ? | F48: Convention de collaboration | G48: NON | H48: Dysfonctionnements dans la collaboration | I48: Retards dans les livraisons impactant les métiers | J48: Elevée | K48: Développer des prototypes rapides pour validation conceptuelle avant investissement
F49: Procédure MOA-MOE | G49: NON | H49: Défaut de coordination | I49: Pénalités contractuelles avec les fournisseurs | J49: Moyenne | K49: Mettre en place des mécanismes de feedback continu via plateforme dédiée
D50: Évaluation des livrables et ROI | E50: Les livrables sontils évalués en termes de ROI et satisfaction utilisateur ? | F50: Étude ROI | G50: NON | H50: ROI non atteint | I50: Tensions entre métiers et IT sur les responsabilités | J50: Elevée | K50: Standardiser les contrats avec les fournisseurs incluant des pénalités pour non-conformité
F51: Enquête satisfaction | G51: NON | H51: Insatisfaction des utilisateurs | I51: Dégradation de la qualité des livrables | J51: Moyenne | K51: Développer des KPI métiers-IT alignés sur les objectifs opérationnels
D52: Cartographie complète des processus métiers couverts | E52: Tous les processus métiers critiques sontils couverts par le SI ? | F52: Cartographie processus | G52: NON | H52: Processus métiers non supportés | I52: Retour sur investissement non réalisé | J52: Moyenne | K52: Mettre en place un cadre de mesure du ROI IT avec indicateurs métiers et financiers
B53: Planification stratégique | C53: Vérifier la couverture du périmètre fonctionnel ; | F53: Couverture SI | G53: NON | H53: Points de rupture non identifiés | I53: Difficulté à justifier les budgets IT | J53: Elevée | K53: Développer des business cases standardisés intégrant analyse coûts/bénéfices
D54: Identification des zones non couvertes ou à améliorer | F54: Analyse des gaps | G54: NON | H54: Faille dans le couverture fonctionnelle | I54: Processus métiers inefficaces ou impossibles à exécuter | J54: Moyenne | K54: Cartographier et optimiser les processus métiers critiques avant digitalisation
E55: Les lacunes fonctionnelles ontelles été identifiées et documentées ? | F55: Registre des écarts | G55: NON | H55: Défaut de traçabilité des écarts | I55: Perte de productivité organisationnelle | J55: Elevée | K55: Instaurer des audits de productivité avec plans d'action spécifiques
D56: Adéquation entre besoins métiers et solutions informatiques | E56: Les solutions informatiques répondentelles aux besoins métiers actuels ? | F56: Audit fonctionnel | G56: NON | H56: Solutions inadaptées aux besoins | I56: Fonctionnalités manquantes critiques pour les opérations | J56: Moyenne | K56: Créer un comité des besoins métiers prioritaires pour guider les investissements IT
F57: Rapport d'adéquation | G57: NON | H57: Perte de productivité | I57: Frustration des utilisateurs et contournement des systèmes | J57: Moyenne | K57: Déployer des solutions d'automatisation pour les tâches à faible valeur ajoutée
D58: Documentation des écarts fonctionnels | E58: Les écarts entre besoins et solutions sontils clairement documentés ? | F58: Registre des écarts | G58: NON | H58: Écarts non documentés ni traités | I58: Baisse de la productivité des équipes métiers | J58: Elevée | K58: Établir un référentiel des écarts fonctionnels avec roadmap de correction
F59: Feuille de route | G59: NON | H59: Dégradation progressive | I59: Coûts supplémentaires pour développer des solutions alternatives | J59: Moyenne | K59: Mettre en place des revues qualité trimestrielles des systèmes en production
D60: Plan d’action pour combler les lacunes | E60: Existetil un plan pour combler les lacunes identifiées ? | F60: Plan de correction | G60: NON | H60: Absence de plan de correction | I60: Aggravation progressive des écarts fonctionnels | J60: Moyenne | K60: Standardiser les pratiques entre équipes via un centre d'excellence dédié
F61: Planning des évolutions | G61: NON | H61: Persistance des lacunes | I61: Coûts exponentiels de correction ultérieure | J61: Moyenne | K61: Implémenter un système de gestion des risques et conformité intégré
C62: Vérifier l’existence d’une analyse à jour des procédures de pilotage et de mise à jour du plan informatique | D62: Procédures formalisées et documentées | E62: Les procédures de pilotage sontelles formalisées et accessibles ? | F62: Manuel de procédures | G62: NON | H62: Procédures inexistantes ou inaccessibles | I62: Persistance de problèmes opérationnels récurrents | J62: Elevée | K62: Automatiser le contrôle des configurations pour prévenir les dérives
F63: Guide utilisateur | G63: NON | H63: Pratiques hétérogènes | I63: Dégradation continue de la performance | J63: Elevée | K63: Développer un schéma directeur IT aligné avec validation annuelle par la direction
D64: Dernière mise à jour récente (≤ 1 an) | E64: Ces procédures ontelles été mises à jour récemment (moins d'un an) ? | F64: Historique des mises à jour | G64: NON | H64: Procédures obsolètes | I64: Pratiques divergentes entre équipes et services | J64: Moyenne | K64: Maintenir un inventaire technologique à jour avec évaluation des risques
F65: PV de validation | G65: NON | H65: Non-respect des évolutions réglementaires | I65: Difficulté à garantir la qualité et la conformité | J65: Moyenne | K65: Créer des comités de gouvernance métier-IT avec pouvoir décisionnel
D66: Implication des parties prenantes (DSI, métiers, direction) | E66: Les différentes parties prenantes sontelles impliquées dans leur élaboration ? | F66: CR de workshop | G66: NON | H66: Exclusion des parties prenantes | I66: Non-respect des obligations légales et réglementaires | J66: Elevée | K66: Documenter les procédures opérationnelles critiques dans un wiki accessible
F67: Liste des contributeurs | G67: NON | H67: Manque d'adhésion aux procédures | I67: Exposition à des sanctions et amendes | J67: Elevée | K67: Instaurer des formations obligatoires sur les nouveaux systèmes et processus
D68: Mécanismes de revue et d’approbation | E68: Existetil un processus formel de validation des mises à jour ? | F68: Workflow de validation | G68: NON | H68: Validation non formalisée | I68: Rejet des nouvelles procédures par les équipes | J68: Moyenne | K68: Déployer un outil de gestion des contrats et obligations légales
F69: Charte de validation | G69: NON | H69: Modifications non contrôlées | I69: Maintien de pratiques obsolètes à risque | J69: Elevée | K69: Mettre en place des indicateurs de performance opérationnelle en temps réel
D70: Preuves d’application effective | E70: Peuton démontrer l'application effective de ces procédures ? | F70: Traces d'exécution | G70: NON | H70: Non-application des procédures | I70: Modifications incontrôlées créant des incohérences | J70: Elevée | K70: Automatiser les contrôles de conformité réglementaire
F71: Rapport d'audit | G71: NON | H71: Écarts non détectés | I71: Instabilité des environnements et systèmes | J71: Elevée | K71: Développer une politique de gestion du changement structurée
D72: Schéma directeur SI accessible et actualisé | E72: Le schéma directeur du SI estil facilement accessible ? | F72: Schéma directeur | G72: NON | H72: Schéma directeur non partagé | I72: Non-respect systématique des règles établies | J72: Elevée | K72: Créer un observatoire des meilleures pratiques sectorielles
C73: Vérifier l’existence des documents à jour d’urbanisme de l’Organisation | F73: Plan de communication | G73: NON | H73: Vision non commune | I73: Augmentation des incidents et anomalies | J73: Moyenne | K73: Implémenter des outils de décision basés sur l'analyse des données
D74: Cartographie des applications et infrastructures | E74: La cartographie des applications et infrastructures estelle à jour ? | F74: Inventaire applicatif | G74: NON | H74: Cartographie obsolète | I74: Vision divergente de la cible IT entre directions | J74: Elevée | K74: Établir des procédures de contrôle qualité automatisées
F75: Cartographie technique | G75: NON | H75: Inventaire incomplet | I75: Investissements incohérents et redondants | J75: Moyenne | K75: Développer des parcours de formation adaptés aux rôles
D76: Cohérence avec la stratégie globale | E76: Le schéma directeur estil cohérent avec la stratégie globale ? | F76: Analyse stratégique | G76: NON | H76: Incohérence avec la stratégie | I76: Prise de décision difficile faute d'inventaire exact | J76: Moyenne | K76: Mettre en place un système de gestion des connaissances organisationnelles
F77: PV de ratification | G77: NON | H77: Investissements mal orientés | I77: Problèmes de maintenance et de sécurité | J77: Elevée | K77: Automatiser la détection des anomalies opérationnelles
D78: Documentation des évolutions et migrations | E78: Les évolutions prévues sontelles correctement documentées ? | F78: Roadmap | G78: NON | H78: Évolutions non planifiées | I78: Investissements incohérents avec la stratégie globale | J78: Moyenne | K78: Instaurer des revues stratégiques semestrielles avec benchmark concurrentiel
F79: Plan de transition | G79: NON | H79: Rupture d'alignement | I79: Désalignement entre les objectifs métiers et les capacités IT | J79: Elevée | K79: Développer des tableaux de bord financiers prédictifs
D80: Validation par les instances décisionnelles | E80: Le schéma atil été validé par les instances décisionnelles ? | F80: Délibération validant le schéma | G80: NON | H80: Non-validation par les instances | I80: Perte de crédibilité des instances de gouvernance | J80: Moyenne | K80: Créer des processus d'optimisation continue des coûts
F81: CR de comité directeur | G81: NON | H81: Défaut de légitimité | I81: Décisions contestées et difficultés de mise en œuvre | J81: Moyenne | K81: Mettre en place un système de gestion des licences centralisé
D82: Procédures formalisées pour le POS | E82: Les procédures de gestion du POS sontelles formalisées ? | F82: Manuel POS | G82: NON | H82: Procédures inexistantes | I82: Improvisation dans la gestion des opérations critiques | J82: Elevée | K82: Élaborer des procédures opérationnelles standardisées pour les processus critiques avec validation régulière
C83: Vérifier l’existence d’une analyse à jour des procédures de pilotage et de mise à jour du plan d’occupation des sols (POS) | F83: Procédures opérationnelles | G83: NON | H83: Pratiques non standardisées | I83: Incohérences dans l'exécution des processus clés | J83: Moyenne | K83: Implémenter un système de gestion des processus métiers (BPM) avec modélisation et suivi des performances
D84: Dernière révision conforme aux besoins actuels | E84: Le POS atil été révisé récemment pour répondre aux besoins actuels ? | F84: Rapport de revue POS | G84: NON | H84: POS non actualisé | I84: Incapacité à répondre aux exigences opérationnelles actuelles | J84: Moyenne | K84: Créer un cadre d'évaluation continue des capacités opérationnelles face aux besoins métiers
F85: PV d'homologation | G85: NON | H85: Inadéquation aux besoins opérationnels | I85: Dégradation de la qualité des services fournis | J85: Moyenne | K85: Déployer un système de gestion de la qualité avec indicateurs et audits réguliers
D86: Implication des équipes opérationnelles | E86: Les équipes opérationnelles sontelles impliquées dans sa mise à jour ? | F86: CR d'atelier terrain | G86: NON | H86: Non-implication des équipes | I86: Résistance au changement et adoption difficile | J86: Elevée | K86: Mettre en place un programme structuré de changement incluant formation et accompagnement
F87: Questionnaire utilisateurs | G87: NON | H87: Rejet des processus | I87: Non-respect des obligations légales et contractuelles | J87: Elevée | K87: Établir un registre des obligations légales avec suivi et alertes des échéances
D88: Alignement avec les réglementations en vigueur | F88: Certificat de conformité | G88: NON | H88: Non-conformité réglementaire | I88: Exposition à des amendes et pénalités financières | J88: Moyenne | K88: Développer des contrôles automatiques de conformité intégrés aux processus
E89: Le POS respectetil les réglementations en vigueur ? | F89: Audit réglementaire | G89: NON | H89: Exposition à des risques | I89: Écart entre théorie et pratique opérationnelle | J89: Moyenne | K89: Réaliser des audits terrain réguliers pour identifier les écarts pratiques
D90: Preuves de mise en œuvre | E90: Peuton prouver son application concrète sur le terrain ? | F90: Journal des incidents | G90: NON | H90: Non-application sur le terrain | I90: Baisse de la performance et de la productivité | J90: Elevée | K90: Instaurer des tableaux de bord de performance opérationnelle en temps réel
F91: Preuves d'implémentation | G91: NON | H91: Écarts opérationnels | I91: Vision incomplète du patrimoine technologique | J91: Elevée | K91: Maintenir un inventaire technologique complet avec évaluation des risques
C92: Vérifier la cohérence et l’homogénéité des technologies | D92: Inventaire technologique centralisé | E92: Disposeton d'un inventaire complet des technologies utilisées ? | F92: Inventaire technologique | G92: NON | H92: Inventaire incomplet ou inexact | I92: Dépenses imprévues et mauvaise allocation des ressources | J92: Moyenne | K92: Créer un comité d'optimisation des coûts IT avec revue trimestrielle
F93: Base CMDB | G93: NON | H93: Gestion hasardeuse des actifs | I93: Complexité accrue de l'environnement IT | J93: Elevée | K93: Standardiser les architectures et interfaces pour améliorer l'interopérabilité
D94: Rationalisation des outils et plateformes | E94: Une politique de standardisation estelle définie et appliquée ? | F94: Politique technique | G94: NON | H94: Absence de standardisation | I94: Interopérabilité difficile entre systèmes | J94: Elevée | K94: Mettre en place des contrats de service (SLA) avec suivi rigoureux
F95: Référentiel normes | G95: NON | H95: Hétérogénéité technologique | I95: Coûts de support et maintenance non maîtrisés | J95: Elevée | K95: Développer des modèles de calcul de ROI pour chaque investissement IT
D96: Politique de standardisation documentée | E96: Les doublons et technologies obsolètes sontils identifiés et traités ? | F96: Rapport d'obsolescence | G96: NON | H96: Technologies obsolètes non identifiées | I96: Impossibilité de démontrer la valeur des investissements | J96: Elevée | K96: Instaurer des revues stratégiques basées sur des données avec validation des hypothèses
F97: Plan de migration | G97: NON | H97: Coûts de maintenance excessifs | I97: Choix stratégiques basés sur des intuitions plutôt que des faits | J97: Moyenne | K97: Créer un référentiel unique de données avec gouvernance dédiée
D98: Réduction des doublons et obsolescences | E98: Des gains d'efficacité ontils été mesurés suite aux rationalisations ? | F98: Étude de gains | G98: NON | H98: Gains non mesurés | I98: Incohérences dans les données de référence | J98: Elevée | K98: Automatiser les contrôles qualité sur les données et processus critiques
F99: Benchmark sectoriel | G99: NON | H99: Décisions non étayées | I99: Erreurs décisionnelles dues à des données non fiables | J99: Moyenne | K99: Déployer des solutions d'automatisation pour réduire les erreurs manuelles
D100: Évaluation des gains d’efficacité | E100: Les référentiels métiers sontils uniques et centralisés ? | F100: Référentiel métier | G100: NON | H100: Référentiels multiples et divergents | I100: Variabilité dans la qualité des outputs | J100: Moyenne | K100: Mettre en place des alertes automatiques sur les anomalies opérationnelles
...

Sheet Projet_Info
A1: Domaine | B1: Point de contrôle | C1: objectif de contrôle | D1: critères d'évaluation | E1: Questiond'évaluation | F1: Documments réquis | G1: Réponses | H1: Risques | I1: conséquence | J1: Criticité | K1: Récommendations
A2: Projet Informatique | D2: Présence d’une analyse détaillée des coûts et bénéfices | E2: Comment les aspects financiers ont-ils été analysés et quantifiés ? | F2: Rapport d'analyse financière | G2: NON | H2: Rapport d'analyse financière | I2: Données obsolètes ou inexactes | J2: Elevée | K2: Mettre en place un processus formel de validation et d'actualisation périodique des données critiques
B3: Objectifs et enjeux du projet | C3: S’assurer qu’une étude de la valeur et des études d'opportunité et d'impacts ont été réalisées | F3: Budget détaillé du projet | G3: PAS | H3: Données obsolètes ou inexactes | I3: Décisions financières erronées entraînant des pertes économiques | J3: Moyenne | K3: Implémenter une double validation des modèles financiers par un comité indépendant
D4: Identification claire des opportunités et risques potentiels | E4: Quels éléments positifs et négatifs ont été identifiés pour le projet ? | F4: SWOT formalisé | G4: OUI | H4: Budget détaillé du projet | I4: Dépassement de budget non contrôlé | J4: Moyenne | K4: Exiger un mécanisme d'alerte automatique dès 10% d'écart par rapport au budget prévisionnel
F5: Compte-rendu des ateliers de risques | G5: NON | H5: Dépassement de budget non contrôlé | I5: Détérioration de la rentabilité et difficultés de trésorerie | J5: Elevée | K5: Introduire une analyse des risques formalisée avec matrice de criticité mise à jour trimestriellement
D6: Évaluation des impacts organisationnels et techniques | E6: Quelles conséquences sur l'organisation et les systèmes ont été anticipées ? | F6: Cartographie des impacts organisationnels | G6: NON | H6: SWOT formalisé | I6: Mauvaise identification des menaces critiques | J6: Moyenne | K6: Établir un protocole de test utilisateur obligatoire avant tout déploiement de nouvelle solution
F7: Plan de transition des systèmes | G7: NON | H7: Mauvaise identification des menaces critiques | I7: Vulnérabilité accrue face à des risques majeurs non anticipés | J7: Elevée | K7: Développer un plan de continuité d'activité avec scénarios de bascule documentés
D8: Validation par les parties prenantes concernées | E8: Les conclusions ont-elles reçu l'approbation des acteurs impliqués ? | F8: PV de validation du comité de pilotage | G8: NON | H8: Compte-rendu des ateliers de risques | I8: Biais dans l'évaluation des risques | J8: Moyenne | K8: Formaliser systématiquement les décisions clés dans un registre centralisé avec preuves associées
F9: Emails/lettres de validation | G9: OUI | H9: Biais dans l'évaluation des risques | I9: Priorisation inadéquate des actions correctives | J9: Moyenne | K9: Créer une archive sécurisée des validations avec horodatage et signatures électroniques
D10: Documentation exhaustive des conclusions et recommandations | E10: Où peut-on consulter l'ensemble des analyses et propositions ? | F10: Dossier de conception complet | G10: OUI | H10: Cartographie des impacts organisationnels | I10: Sous-estimation des résistances au changement | J10: Elevée | K10: Instaurer des revues techniques croisées avant mise en production
F11: Répertoire partagé des études | G11: OUI | H11: Sous-estimation des résistances au changement | I11: Échec de l'adoption des nouvelles solutions par les utilisateurs | J11: Moyenne | K11: Renforcer les contrôles d'accès avec authentification multifacteur et traçage des consultations
D12: Inventaire complet des processus actuels | E12: Quelle méthodologie a été utilisée pour recenser les processus en place ? | F12: Référentiel des processus métiers | G12: OUI | H12: Plan de transition des systèmes | I12: Interruptions imprévues des services | J12: Moyenne | K12: Lancer un programme de révision annuelle des processus avec indicateurs d'efficacité
C13: S’assurer qu’un bilan critique des processus existants a été effectué | F13: Matrice RACI des processus | G13: OUI | H13: Interruptions imprévues des services | I13: Pertes de productivité et insatisfaction client | J13: Moyenne | K13: Élaborer une matrice RACI détaillée validée par toutes les parties prenantes
D14: Identification des dysfonctionnements et inefficacités | E14: Quels problèmes récurrents ont été constatés dans le fonctionnement actuel ? | F14: Registre des incidents récurrents | G14: OUI | H14: PV de validation du comité de pilotage | I14: Décisions non formalisées | J14: Elevée | K14: Implémenter un système de gestion des problèmes avec analyse racine et suivi des corrections
F15: Rapport d'audit des dysfonctionnements | G15: OUI | H15: Décisions non formalisées | I15: Confusion opérationnelle et conflits d'interprétation | J15: Elevée | K15: Prioriser les correctifs via une méthode de scoring basée sur l'impact et l'urgence
D16: Benchmarking des meilleures pratiques sectorielles | E16: Comment se positionne l'organisation par rapport aux pratiques du marché ? | F16: Benchmark sectoriel | G16: OUI | H16: Emails/lettres de validation | I16: Preuves de validation non archivées | J16: Moyenne | K16: Constituer un référentiel de données de référence certifié par les métiers
F17: Analyse comparative des pratiques | G17: OUI | H17: Preuves de validation non archivées | I17: Difficultés à démontrer la conformité lors d'audits | J17: Moyenne | K17: Valider systématiquement la pertinence des benchmarks avec les responsables opérationnels
D18: Implication des opérationnels dans l’analyse critique | E18: Les équipes opérationnelles ont-elles été consultées lors du diagnostic ? | F18: Comptes-rendus d'entretiens avec les équipes | G18: OUI | H18: Dossier de conception complet | I18: Incohérences techniques non détectées | J18: Elevée | K18: Organiser des ateliers terrain pour recueillir les besoins réels avant conception
F19: Synthèse des retours opérationnels | G19: OUI | H19: Incohérences techniques non détectées | I19: Dysfonctionnements majeurs en phase d'exploitation | J19: Elevée | K19: Mettre en place des canaux structurés de remontée et traitement du feedback
D20: Synthèse des écarts entre processus existants et besoins | E20: Quels écarts majeurs ont été identifiés entre l'existant et les besoins ? | F20: Analyse des écarts (AS-IS/TO-BE) | G20: OUI | H20: Répertoire partagé des études | I20: Accès non sécurisé aux documents | J20: Moyenne | K20: Instaurer des revues trimestrielles d'alignement objectifs/résultats avec indicateurs quantifiés
F21: Cahier des charges fonctionnel | G21: OUI | H21: Accès non sécurisé aux documents | I21: Fuites d'informations sensibles et violations de données | J21: Elevée | K21: Exiger la formalisation des exigences sous forme de critères d'acceptation testables
D22: Preuve d’une optimisation préalable des processus | E22: Quelles améliorations ont été apportées aux processus avant toute décision ? | F22: Journal des améliorations process | G22: OUI | H22: Référentiel des processus métiers | I22: Processus obsolètes non mis à jour | J22: Elevée | K22: Maintenir un journal des changements intégré au système de gestion de configuration
C23: S’assurer que le choix de recourir à un nouveau système est obtenu après optimisation des processus concernés et vérification que cette optimisation ne suffit pas à apporter par elle-même les gains de performance attendus | F23: Protocoles de tests des nouveaux processus | G23: OUI | H23: Processus obsolètes non mis à jour | I23: Inefficacité opérationnelle et non-conformité réglementaire | J23: Elevée | K23: Développer des scénarios de test couvrant 100% des cas critiques identifiés
D24: Comparaison des gains avec et sans nouveau système | E24: Quels avantages comparatifs ont été évalués entre les différentes options ? | F24: Étude comparative des solutions | G24: OUI | H24: Matrice RACI des processus | I24: Responsabilités mal définies | J24: Elevée | K24: Établir une grille de sélection pondérée et documentée pour les choix techniques
F25: Grille d'évaluation multicritère | G25: OUI | H25: Responsabilités mal définies | I25: Tâches non réalisées ou doublons coûteux | J25: Moyenne | K25: Introduire une analyse multicritère formalisée pour les décisions d'investissement
D26: Justification économique du choix technologique | E26: Sur quels arguments concrets repose le choix de la solution technologique ? | F26: Argumentaire technique de la solution | G26: OUI | H26: Registre des incidents récurrents | I26: Problèmes systémiques non résolus | J26: Elevée | K26: Réaliser une étude d'adéquation technologique avant toute sélection de solution
F27: Rapport d'évaluation des technologies | G27: OUI | H27: Problèmes systémiques non résolus | I27: Répétition des incidents et dégradation continue | J27: Moyenne | K27: Développer une stratégie multi-fournisseurs avec clauses de réversibilité
D28: Validation par les experts métiers et techniques | E28: Les experts concernés ont-ils validé la solution retenue ? | F28: Avis d'expertise technique | G28: OUI | H28: Rapport d'audit des dysfonctionnements | I28: Correctifs non priorisés | J28: Moyenne | K28: Mettre en place une déclaration obligatoire des conflits d'intérêts
F29: Procès-verbal de validation technique | G29: OUI | H29: Correctifs non priorisés | I29: Aggravation des vulnérabilités existantes | J29: Elevée | K29: Instaurer des checklists de validation complètes avec preuves à l'appui
D30: Documentation des scénarios écartés | E30: Où sont archivées les alternatives qui n'ont pas été retenues ? | F30: Base documentaire des options écartées | G30: OUI | H30: Benchmark sectoriel | I30: Données comparatives non représentatives | J30: Moyenne | K30: Exiger la traçabilité complète des décisions dans un système dédié
F31: Journal des décisions d'arbitrage | G31: OUI | H31: Données comparatives non représentatives | I31: Choix stratégiques inadaptés au marché | J31: Elevée | K31: Formaliser les justifications des choix stratégiques dans un référentiel unique
D32: Définition écrite des objectifs stratégiques et opérationnels | E32: Comment les buts du projet ont-ils été formalisés et communiqués ? | F32: Charte de projet formalisée | G32: OUI | H32: Analyse comparative des pratiques | I32: Biais dans la sélection des références | J32: Moyenne | K32: Établir un tableau de bord des engagements avec suivi des écarts
C33: S’assure que les objectifs et périmètres du projet sont définis, partagés et stabilisés | F33: Plan de communication initial | G33: OUI | H33: Biais dans la sélection des références | I33: Modèles de référence non pertinents pour l'organisation | J33: Moyenne | K33: Développer un plan de communication adapté à chaque catégorie de parties prenantes
D34: Cartographie précise du périmètre fonctionnel et technique | E34: Quelle méthodologie a permis de délimiter précisément le champ d'action ? | F34: Périmètre fonctionnel validé | G34: OUI | H34: Comptes-rendus d'entretiens avec les équipes | I34: Besoins opérationnels mal compris | J34: Elevée | K34: Implémenter un processus strict de gestion des changements avec seuils d'approbation
F35: Cartographie des processus cibles | G35: NON | H35: Besoins opérationnels mal compris | I35: Solutions techniques inadaptées aux réalités terrain | J35: Moyenne | K35: Réaliser une analyse de faisabilité opérationnelle pour chaque nouveau processus
D36: Accord formel des sponsors et utilisateurs clés | E36: Les décideurs et principaux utilisateurs ont-ils officialisé leur accord ? | F36: Engagement formel des sponsors | G36: NON | H36: Synthèse des retours opérationnels | I36: Feedback non pris en compte | J36: Moyenne | K36: Obtenir des engagements écrits de la direction avec revues formelles périodiques
F37: Accord des utilisateurs clés | G37: NON | H37: Feedback non pris en compte | I37: Démotivation des équipes et perte d'engagement | J37: Moyenne | K37: Concevoir un programme d'accompagnement au changement sur mesure
D38: Stabilité des exigences sur une période significative | E38: Les besoins sont-ils restés stables sur une période significative ? | F38: Historique des besoins stabilisés | G38: NON | H38: Analyse des écarts (AS-IS/TO-BE) | I38: Écarts critiques sous-évalués | J38: Elevée | K38: Mettre en place un comité de gouvernance dédié au contrôle des exigences
F39: Traçabilité des évolutions | G39: NON | H39: Écarts critiques sous-évalués | I39: Échec partiel ou total à atteindre les objectifs | J39: Elevée | K39: Utiliser un outil de gestion des demandes avec règles de priorisation automatisées
D40: Mécanismes de gestion des modifications de périmètre | E40: Comment sont gérées les éventuelles modifications de périmètre ? | F40: Procédure de gestion des changements | G40: NON | H40: Cahier des charges fonctionnel | I40: Exigences incomplètes ou ambiguës | J40: Moyenne | K40: Réaliser une analyse d'impact technique pour toute nouvelle intégration
F41: Registre des demandes de modifications | G41: NON | H41: Exigences incomplètes ou ambiguës | I41: Livrables ne répondant pas aux attentes métiers | J41: Moyenne | K41: Adopter des principes de conception modulaire pour faciliter les évolutions
D42: Description des architectures techniques et fonctionnelles | E42: Quels choix architecturaux ont été retenus pour la solution ? | F42: Schéma directeur d'architecture | G42: NON | H42: Journal des améliorations process | I42: Changements non documentés | J42: Elevée | K42: Organiser des comités d'alignement stratégique mensuels métier/IT
C43: S’assurer que les principales orientations du système cible ont été explicitées ; | F43: Spécifications techniques | G43: NON | H43: Changements non documentés | I43: Perte de traçabilité et difficultés de maintenance | J43: Elevée | K43: Intégrer des clauses contractuelles de mise à jour technologique
D44: Alignement avec la stratégie SI de l’organisation | E44: Comment la solution s'insère-t-elle dans la stratégie globale du SI ? | F44: Alignement stratégique du SI | G44: NON | H44: Protocoles de tests des nouveaux processus | I44: Scénarios de test non validés | J44: Moyenne | K44: Mettre en place des ateliers de conciliation pour résoudre les exigences contradictoires
F45: Feuille de route technologique | G45: NON | H45: Scénarios de test non validés | I45: Défauts majeurs passés en production | J45: Elevée | K45: Appliquer la méthode des cas types pour prioriser les développements
D46: Adéquation avec les besoins métiers prioritaires | E46: En quoi répond-elle précisément aux attentes métiers prioritaires ? | F46: Référentiel des exigences métiers | G46: NON | H46: Étude comparative des solutions | I46: Critères de sélection biaisés | J46: Elevée | K46: Nommer un responsable conformité avec accès direct à la direction
F47: Priorisation des cas d'usage | G47: NON | H47: Critères de sélection biaisés | I47: Choix de solutions sous-optimales | J47: Elevée | K47: Développer un programme de contrôle continu basé sur les risques
D48: Prise en compte des contraintes réglementaires | E48: Quelles obligations réglementaires ont été intégrées dans la conception ? | F48: Cadre réglementaire applicable | G48: OUI | H48: Grille d'évaluation multicritère | I48: Pondérations subjectives | J48: Elevée | K48: Tester systématiquement les plans de bascule avec scénarios de rollback
F49: Matrice de conformité normative | G49: OUI | H49: Pondérations subjectives | I49: Décisions d'investissement non objectives | J49: Moyenne | K49: Cartographier exhaustivement les besoins métiers avant conception
D50: Plan de transition depuis l’existant | E50: Comment s'effectuera le passage de l'ancien au nouveau système ? | F50: Plan de migration détaillé | G50: OUI | H50: Argumentaire technique de la solution | I50: Technologie inadaptée au besoin | J50: Elevée | K50: Élaborer une matrice de traçabilité besoins-solutions mise à jour hebdomadaire
F51: Scénarios de bascule | G51: OUI | H51: Technologie inadaptée au besoin | I51: Coûts supplémentaires pour adaptations ou remplacement | J51: Moyenne | K51: Prioriser les objectifs via une méthode MOSCOW validée par les sponsors
D52: Exhaustivité des exigences fonctionnelles et non-fonctionnelles | E52: Comment s'assure-t-on que tous les besoins ont été pris en compte ? | F52: Matrice de couverture des besoins | G52: OUI | H52: Rapport d'évaluation des technologies | I52: Dépendance à un fournisseur unique | J52: Moyenne | K52: Définir des indicateurs SMART alignés sur la stratégie d'entreprise
B53: Étude d'opportunité et expression des besoins | C53: S’assurer que l'expression détaillée des besoins est formalisée dans un cahier des charges fait par la MOA | F53: Traçabilité des exigences | G53: OUI | H53: Dépendance à un fournisseur unique | I53: Risques de rupture et perte de pouvoir de négociation | J53: Elevée | K53: Instaurer des critères d'acceptation stricts avec validation formelle
D54: Traçabilité des besoins vers les objectifs stratégiques | E54: Quelle méthode permet de relier chaque exigence aux objectifs globaux ? | F54: Arbre d'alignement stratégique | G54: OUI | H54: Avis d'expertise technique | I54: Conflits d'intérêts non déclarés | J54: Moyenne | K54: Mettre en œuvre des campagnes de recette complètes avec cas réels
F55: Tableau de traçabilité des objectifs | G55: OUI | H55: Conflits d'intérêts non déclarés | I55: Décisions techniques compromises | J55: Elevée | K55: Fixer des règles de stabilité des critères validées par le comité de pilotage
D56: Validation formelle par la maîtrise d’ouvrage | E56: La maîtrise d'ouvrage a-t-elle validé formellement les spécifications ? | F56: Spécifications validées par la MOA | G56: OUI | H56: Procès-verbal de validation technique | I56: Validations superficielles | J56: Moyenne | K56: Documenter systématiquement toutes les contraintes dans un référentiel partagé
F57: PV de recette des spécifications | G57: OUI | H57: Validations superficielles | I57: Acceptation de solutions non conformes aux besoins | J57: Elevée | K57: Réaliser des projections financières sous plusieurs scénarios réalistes
D58: Hiérarchisation des priorités | E58: Selon quels critères les priorités ont-elles été établies ? | F58: Grille de priorisation des fonctionnalités | G58: OUI | H58: Base documentaire des options écartées | I58: Décisions non traçables | J58: Elevée | K58: Effectuer des analyses de sensibilité sur les paramètres clés
F59: Accord sur les contraintes projet | G59: OUI | H59: Décisions non traçables | I59: Impossibilité d'auditer les choix stratégiques | J59: Elevée | K59: Lancer des audits ponctuels sur les coûts cachés potentiels
D60: Intégration des contraintes budgétaires et calendaires | E60: Comment les limites budgétaires et temporelles ont-elles été intégrées ? | F60: Business case actualisé | G60: PAS | H60: Journal des décisions d'arbitrage | I60: Justifications insuffisantes | J60: Elevée | K60: Établir des modèles de coût total de possession pour chaque solution
F61: Modèle financier projet | G61: PAS | H61: Justifications insuffisantes | I61: Difficultés à défendre les orientations prises | J61: Elevée | K61: Corréler systématiquement les bénéfices attendus avec indicateurs mesurables
D62: Modélisation financière des retours sur investissement | E62: Quelle méthodologie a permis d'évaluer le retour sur investissement ? | F62: Calcul des coûts complets | G62: PAS | H62: Charte de projet formalisée | I62: Engagements non respectés | J62: Elevée | K62: Développer des tableaux de bord opérationnels avec données temps réel
C63: S’assurer que ce document comprend les bénéfices attendus et la rentabilité économique du projet | F63: Analyse TCO (Total Cost of Ownership) | G63: PAS | H63: Engagements non respectés | I63: Perte de crédibilité auprès des parties prenantes | J63: Elevée | K63: Tester trimestriellement les plans de contingence via des exercices simulés
D64: Évaluation des coûts totaux de possession | E64: Comment ont été calculés les coûts complets de possession ? | F64: Projection des gains opérationnels | G64: PAS | H64: Plan de communication initial | I64: Parties prenantes mal informées | J64: Elevée | K64: Maintenir des réserves proportionnelles aux risques identifiés
F65: Indicateurs de performance cibles | G65: PAS | H65: Parties prenantes mal informées | I65: Désalignement et résistances au projet | J65: Elevée | K65: Automatiser les processus de collecte et consolidation des données
D66: Mesure des gains de productivité attendus | E66: Quels gains opérationnels concrets sont attendus ? | F66: Scénarios financiers alternatifs | G66: PAS | H66: Périmètre fonctionnel validé | I66: Scope creep non maîtrisé | J66: Elevée | K66: Introduire des mécanismes de contrôle croisé pour limiter les biais
F67: Plan de contingence budgétaire | G67: PAS | H67: Scope creep non maîtrisé | I67: Dérapages budgétaires et calendaires majeurs | J67: Elevée | K67: Nommer un responsable conformité dédié avec pouvoir de veto
D68: Scénarios de rentabilité différentiels | E68: Quels différents scénarios financiers ont été envisagés ? | F68: Tableau de bord de suivi post-implémentation | G68: PAS | H68: Cartographie des processus cibles | I68: Processus irréalistes | J68: Elevée | K68: Instaurer un système de suivi des actions correctives avec échéances
F69: Méthodologie de mesure d'impact | G69: PAS | H69: Processus irréalistes | I69: Impossibilité opérationnelle de mise en œuvre | J69: Elevée | K69: Réaliser des audits techniques indépendants sur les verrous technologiques
D70: Mécanismes de suivi post-déploiement | E70: Comment sera mesurée l'efficacité réelle après implémentation ? | F70: Recueil des obligations légales | G70: OUI | H70: Engagement formel des sponsors | I70: Soutien hiérarchique fluctuant | J70: Elevée | K70: Développer des prototypes pour valider les interfaces complexes
F71: Audit de conformité réglementaire | G71: OUI | H71: Soutien hiérarchique fluctuant | I71: Interruptions ou annulations imprévues du projet | J71: Moyenne | K71: Mettre en place une veille active sur les menaces externes émergentes
D72: Inventaire des contraintes réglementaires et légales | E72: Quelles obligations légales spécifiques impactent le projet ? | F72: Inventaire des limitations techniques | G72: OUI | H72: Accord des utilisateurs clés | I72: Résistance passive | J72: Moyenne | K72: Créer un comité de prospective analysant les signaux faibles
C73: S’assurer que ce document comprend les contraintes relatives au projet ; | F73: Évaluation des contraintes d'intégration | G73: OUI | H73: Résistance passive | I73: Retards dans l'adoption et faible utilisation | J73: Elevée | K73: Lancer un programme de transformation culturelle ciblé
D74: Limitations techniques identifiées | E74: Quelles limitations techniques ont été identifiées ? | F74: Matrice des risques externes | G74: OUI | H74: Historique des besoins stabilisés | I74: Dérives fréquentes des exigences | J74: Moyenne | K74: Mesurer régulièrement l'adoption via des indicateurs d'utilisation concrets
F75: Veille environnementale | G75: OUI | H75: Dérives fréquentes des exigences | I75: Livrables ne correspondant plus aux besoins initiaux | J75: Elevée | K75: Élaborer un plan d'amélioration continue basé sur les retours terrain
D76: Facteurs risques externes documentés | E76: Quels facteurs externes pourraient affecter le projet ? | F76: Diagnostic des freins organisationnels | G76: OUI | H76: Traçabilité des évolutions | I76: Changements non tracés | J76: Moyenne | K76: Réaliser une cartographie des risques systémiques avec plans d'atténuation
F77: Plan d'accompagnement au changement | G77: OUI | H77: Changements non tracés | I77: Perte de contrôle sur l'évolution du projet | J77: Moyenne | K77: Identifier et impliquer systématiquement les influenceurs clés
D78: Contraintes organisationnelles prises en compte | E78: Quels obstacles organisationnels ont été pris en compte ? | F78: Plan d'atténuation des contraintes | G78: OUI | H78: Procédure de gestion des changements | I78: Demandes non priorisées | J78: Elevée | K78: Documenter clairement les pouvoirs et limites de chaque acteur
F79: Fiches risques majeurs | G79: OUI | H79: Demandes non priorisées | I79: Allocation inefficace des ressources | J79: Moyenne | K79: Organiser des ateliers de clarification des rôles et responsabilités
D80: Plan d’atténuation des contraintes majeures | E80: Quelles mesures ont été prévues pour les contraintes les plus importantes ? | F80: Répertoire des parties prenantes | G80: OUI | H80: Registre des demandes de modifications | I80: Backlog ingérable | J80: Moyenne | K80: Mettre en place un baromètre trimestriel du climat social
F81: Cartographie des acteurs | G81: OUI | H81: Backlog ingérable | I81: Surcharge des équipes et retard généralisé | J81: Moyenne | K81: Instaurer des processus décisionnels accélérés pour les urgences
D82: Cartographie des parties prenantes internes/externes | E82: Qui sont tous les acteurs concernés par le projet ? | F82: Définition des rôles projet | G82: OUI | H82: Schéma directeur d'architecture | I82: Incompatibilités techniques futures | J82: Elevée | K82: Réaliser des études d'impact différencié pour les populations vulnérables
C83: S’assurer que ce document comprend la liste des acteurs concernés | F83: Organigramme des responsabilités | G83: OUI | H83: Incompatibilités techniques futures | I83: Coûts élevés de refonte ou d'intégration | J83: Elevée | K83: Impliquer des utilisateurs réels dans les tests utilisateurs
D84: Rôles et responsabilités formalisés | E84: Comment sont définis et répartis les rôles et responsabilités ? | F84: Plan d'engagement des parties prenantes | G84: OUI | H84: Spécifications techniques | I84: Spécifications trop rigides | J84: Moyenne | K84: Valider tous les messages clés via des focus groups représentatifs
F85: Suivi des participations aux réunions | G85: NON | H85: Spécifications trop rigides | I85: Difficultés d'adaptation aux évolutions | J85: Moyenne | K85: Diversifier les canaux de communication selon les cibles
D86: Mécanismes d’implication des acteurs clés | E86: Quels mécanismes assurent l'implication des parties prenantes clés ? | F86: Analyse d'impact différenciée | G86: PAS | H86: Alignement stratégique du SI | I86: Découplage avec la stratégie métier | J86: Elevée | K86: Organiser des médiations formelles pour résoudre les désaccords persistants
F87: Profils des utilisateurs finaux | G87: OUI | H87: Découplage avec la stratégie métier | I87: Solutions techniques non alignées aux besoins business | J87: Elevée | K87: Lier les engagements à des objectifs individuels évaluables
D88: Analyse des impacts par population concernée | E88: Quels impacts différenciés selon les populations ont été analysés ? | F88: Stratégie de communication ciblée | G88: NON | H88: Feuille de route technologique | I88: Obsolescence accélérée | J88: Moyenne | K88: Créer des équipes mixtes métier/IT avec objectifs partagés
F89: Supports adaptés par audience | G89: NON | H89: Obsolescence accélérée | I89: Investissements rapidement dépassés | J89: Elevée | K89: Instaurer un processus formel de suivi des recommandations
D90: Plan de communication adapté aux différents acteurs | E90: Comment la communication est-elle adaptée à chaque type d'intervenant ? | F90: Approbations écrites des métiers | G90: NON | H90: Référentiel des exigences métiers | I90: Exigences contradictoires | J90: Elevée | K90: Mettre en place des indicateurs de dérive avec seuils d'alerte
F91: Signatures des responsables | G91: NON | H91: Exigences contradictoires | I91: Conflits entre fonctions et parties prenantes | J91: Elevée | K91: Centraliser l'historique complet du projet dans un système unique
D92: Procès-verbal de revue par les directions métiers | E92: Existe-t-il une trace écrite des validations par les directions métiers ? | F92: Avis officiel de la DSI | G92: OUI | H92: Priorisation des cas d'usage | I92: Cas marginaux survalorisés | J92: Elevée | K92: Établir une grille de priorisation objective avec seuils d'éligibilité clairs
C93: S’assurer que l'étude d'opportunité a été revue par les directions utilisatrices et par la direction informatique ; | F93: Recommandations techniques | G93: OUI | H93: Cas marginaux survalorisés | I93: Allocation disproportionnée de ressources | J93: Moyenne | K93: Appliquer une méthodologie d'allocation basée sur l'analyse coûts-bénéfices
D94: Avis formalisé de la DSI | E94: La direction informatique a-t-elle émis un avis formalisé ? | F94: Registre des ajustements | G94: OUI | H94: Cadre réglementaire applicable | I94: Non-conformité légale | J94: Elevée | K94: Désigner un responsable conformité avec revue trimestrielle des obligations légales
F95: Suivi des modifications apportées | G95: OUI | H95: Non-conformité légale | I95: Sanctions réglementaires et amendes | J95: Moyenne | K95: Mettre en place un fonds de provision pour sanctions potentielles
D96: Modifications apportées suite aux retours | E96: Quels ajustements ont été faits suite aux retours reçus ? | F96: Consensus documenté | G96: OUI | H96: Matrice de conformité normative | I96: Contrôles insuffisants | J96: Moyenne | K96: Renforcer les contrôles avec audits surprises sur les processus critiques
F97: Hypothèses de base validées | G97: OUI | H97: Contrôles insuffisants | I97: Risques de non-conformité non détectés | J97: Elevée | K97: Implémenter un système de détection automatique des anomalies de conformité
D98: Consensus sur les hypothèses clés | E98: Un consensus existe-t-il sur les hypothèses fondamentales ? | F98: Preuve d'engagement des décideurs | G98: OUI | H98: Plan de migration détaillé | I98: Pannes lors de la bascule | J98: Moyenne | K98: Tester systématiquement les procédures de bascule en environnement réel
F99: Communication officielle de soutien | G99: OUI | H99: Pannes lors de la bascule | I99: Interruptions de service critiques | J99: Elevée | K99: Prévoir des solutions redondantes pour les services essentiels
D100: Engagement visible des décideurs | E100: L'engagement des décideurs est-il clairement manifeste ? | F100: Planning global du projet | G100: OUI | H100: Scénarios de bascule | I100: Plan de rollback inefficace | J100: Moyenne | K100: Documenter et tester les scénarios de rollback pour chaque mise en production
...

Sheet Support_Util
A1: Domaine | B1: Point de contrôle | C1: objectif de contrôle | D1: critères d'évaluation | E1: Questiond'évaluation | F1: Réponse | G1: Documents réquis | H1: Risque | I1: Conséquence | J1: criticité | K1: récommendations
A2: Support Utilisateur et de la Gestion du Parc | D2: Existence d'une équipe dédiée identifiée | E2: Qui est responsable du traitement des demandes d'assistance au sein de l'organisation ? | F2: OUI | G2: Organigramme du support | H2: Mauvaise coordination des équipes support | I2: Délais prolongés dans la résolution des incidents | J2: Elevée | K2: Mettre en place un processus structuré de gestion des incidents
B3: Fonction support : audit fiabilité et sécurité | C3: S’assurer qu’une structure de centre d’assistance (help-desk) (HD) est mise en place ; | F3: OUI | G3: Procédure de contact du support | H3: Inefficacité des canaux de communication | I3: Frustration accrue des utilisateurs finaux | J3: Moyenne | K3: Améliorer la communication entre les équipes et les utilisateurs finaux
D4: Canaux de contact multiples disponibles (téléphone, mail, chat) | E4: Par quels moyens peut-on contacter le support en cas de besoin ? | F4: OUI | G4: Plages horaires du support | H4: Délais de réponse inadaptés aux besoins | I4: Insatisfaction client et perte de confiance | J4: Moyenne | K4: Renforcer les mécanismes d’écoute client et la qualité du support
F5: OUI | G5: Calendrier des disponibilités | H5: Interruptions de service non couvertes | I5: Temps d'indisponibilité prolongé des services critiques | J5: Elevée | K5: Mettre en œuvre un plan de continuité pour les services critiques
D6: Horaires de service clairement définis | E6: Quelles sont les plages horaires pendant lesquelles le support est joignable ? | F6: OUI | G6: Manuel de suivi des tickets | H6: Perte de traçabilité des demandes | I6: Impossibilité de suivre l'historique des problèmes | J6: Moyenne | K6: Centraliser la base de données des incidents avec traçabilité complète
F7: OUI | G7: Procédure d'enregistrement des demandes | H7: Demandes mal enregistrées ou perdues | I7: Demandes non traitées ou perdues dans le système | J7: Elevée | K7: Automatiser le suivi et la relance des demandes en attente
D8: Outil de ticketing opérationnel | E8: Comment sont enregistrées et suivies les demandes d'assistance ? | F8: OUI | G8: Tableau de bord des KPI support | H8: Décisions basées sur des indicateurs erronés | I8: Prise de décisions stratégiques erronées | J8: Moyenne | K8: Utiliser des tableaux de bord décisionnels alimentés en temps réel
F9: OUI | G9: Rapports mensuels de performance | H9: Dégradation continue non détectée | I9: Détérioration silencieuse de la qualité de service | J9: Moyenne | K9: Mettre en place un système de mesure continue de la qualité
D10: Statistiques de fonctionnement régulièrement produites | E10: Comment mesure-t-on l'efficacité et la performance du support ? | F10: OUI | G10: Guide utilisateur du support | H10: Mauvaise utilisation des outils par les utilisateurs | I10: Augmentation des appels au support technique | J10: Elevée | K10: Renforcer le self-service et les canaux de support digital
F11: OUI | G11: Processus de traitement des demandes | H11: Incohérence dans le traitement des demandes | I11: Expérience utilisateur incohérente et frustrante | J11: Moyenne | K11: Standardiser les parcours utilisateurs pour plus de cohérence
D12: Document formalisé accessible à tous | E12: Où peut-on trouver les informations sur le processus de traitement des demandes ? | F12: OUI | G12: Workflow de traitement des tickets | H12: Goulots d'étranglement dans les processus | I12: Ralentissement global des processus de support | J12: Moyenne | K12: Optimiser les workflows de traitement et éliminer les frictions
C13: S’assurer qu’une procédure de gestion des demandes d’assistance est diffusée et connue des utilisateurs ; | F13: OUI | G13: Procédure d'escalade | H13: Retards dans le traitement des urgences | I13: Aggravation des situations d'urgence | J13: Moyenne | K13: Définir des protocoles d’urgence clairs et partagés
D14: Workflow de traitement expliqué | E14: Comment sont traitées les demandes une fois qu'elles sont soumises ? | F14: OUI | G14: Grille des délais d'intervention | H14: Non-respect des engagements temporels | I14: Pénalités contractuelles et pertes financières | J14: Elevée | K14: Suivre des KPIs contractuels et assurer un reporting régulier
F15: OUI | G15: SLA du support | H15: Litiges contractuels avec les clients | I15: Litiges coûteux et atteinte à la réputation | J15: Elevée | K15: Structurer les processus de gestion des litiges avec preuves à l’appui
D16: Délais de réponse communiqués | E16: Dans quels délais peut-on s'attendre à une réponse à une demande ? | F16: PAS | G16: Attestations de formation utilisateurs | H16: Compétences utilisateurs insuffisantes | I16: Augmentation des demandes d'assistance de base | J16: Moyenne | K16: Former les utilisateurs sur les demandes de premier niveau
F17: PAS | G17: Supports de formation | H17: Formation inefficace ou obsolète | I17: Compétences obsolètes et inefficacité opérationnelle | J17: Moyenne | K17: Organiser des plans de montée en compétence réguliers
D18: Formation des utilisateurs réalisée | E18: Les utilisateurs ont-ils reçu une formation sur l'utilisation du support ? | F18: PAS | G18: FAQ du support | H18: Résolution autonome impossible | I18: Surcharge inutile des équipes de support | J18: Elevée | K18: Définir une stratégie de répartition efficace de la charge de travail
F19: PAS | G19: Base de connaissances | H19: Redondance des demandes simples | I19: Duplication des efforts et gaspillage de ressources | J19: Elevée | K19: Mettre en place un système de gestion des connaissances unifié
D20: Supports d'aide à la compréhension disponibles | E20: Existe-t-il des documents d'aide pour comprendre le fonctionnement du support ? | F20: PAS | G20: Procédure de gestion des expertises | H20: Expertise non disponible quand nécessaire | I20: Temps d'attente prolongé pour les problèmes complexes | J20: Moyenne | K20: Créer un canal dédié aux demandes complexes avec ressources expertes
F21: PAS | G21: Référentiel des experts | H21: Compétences critiques non identifiées | I21: Points de défaillance uniques non identifiés | J21: Elevée | K21: Mettre en œuvre des audits réguliers des points critiques du SI
D22: Niveaux d'escalade clairement définis | E22: Comment sont gérées les demandes qui nécessitent une expertise particulière ? | F22: PAS | G22: Procédure d'escalade technique | H22: Escalade vers mauvais interlocuteur | I22: Transferts multiples et frustration des clients | J22: Elevée | K22: Former les équipes à la gestion de cas multi-niveaux
C23: S’assurer qu’une procédure d'escalade mise en place ; | F23: PAS | G23: Matrice de compétences | H23: Lacunes dans les compétences de l'équipe | I23: Incapacité à résoudre certains types de problèmes | J23: Elevée | K23: Créer un référentiel de résolution par typologie de problème
D24: Responsables identifiés à chaque niveau | E24: Qui intervient lorsque la complexité d'une demande dépasse les compétences du premier niveau ? | F24: PAS | G24: Grille de criticité des incidents | H24: Priorisation incorrecte des incidents | I24: Priorisation inefficace des ressources | J24: Elevée | K24: Utiliser un système intelligent d’allocation de ressources
F25: PAS | G25: SLA par niveau de criticité | H25: Traitement inadapté à la criticité | I25: Aggravation des incidents critiques | J25: Moyenne | K25: Structurer les escalades avec des seuils de criticité définis
D26: Délais d'intervention par niveau | E26: Quel est le temps maximum d'attente pour une réponse selon la criticité de la demande ? | F26: PAS | G26: Procédure de transfert de tickets | H26: Transferts inutiles entre équipes | I26: Perte de temps et d'efficacité | J26: Elevée | K26: Rationaliser les outils de gestion pour éviter les redondances
F27: PAS | G27: Journal des transferts | H27: Perte d'information lors des transferts | I27: Besoin de répéter les informations | J27: Moyenne | K27: Mettre en œuvre des solutions unifiées de support omnicanal
D28: Procédures de passage de niveau documentées | E28: Comment sont documentés les transferts de demandes entre niveaux de support ? | F28: PAS | G28: Base de données des incidents complexes | H28: Réponses incohérentes aux problèmes complexes | I28: Solutions inadéquates fournies aux utilisateurs | J28: Moyenne | K28: Formaliser les bonnes pratiques et les diffuser régulièrement
F29: PAS | G29: Rapports d'interventions spécialisées | H29: Répétition des mêmes erreurs | I29: Répétition des mêmes problèmes non résolus | J29: Elevée | K29: Créer un centre d’assistance régional ou virtuel
D30: Historique des escalades suivi | E30: Peut-on consulter l'historique des demandes ayant nécessité une intervention spécialisée ? | F30: PAS | G30: Carte des zones couvertes | H30: Couverture géographique incomplète | I30: Zones géographiques sans couverture de support | J30: Moyenne | K30: Étendre les plages horaires de couverture ou les ressources locales
F31: PAS | G31: Liste des centres de support | H31: Support non disponible dans certaines zones | I31: Clients dans certaines régions non servis | J31: Elevée | K31: Former les équipes à la communication interculturelle
D32: Zones géographiques couvertes documentées | E32: Dans quelles zones géographiques le support est-il disponible ? | F32: PAS | G32: Référentiel linguistique | H32: Barrières linguistiques | I32: Incompréhension mutuelle et erreurs de traitement | J32: Moyenne | K32: Mettre en place des modèles clairs de traitement des demandes
C33: S’assurer de la couverture géographique du HD ; | F33: PAS | G33: Procédure multilingue | H33: Incompréhension des demandes | I33: Demandes mal interprétées et mal traitées | J33: Moyenne | K33: Assurer une veille de la charge des équipes et rééquilibrer si besoin
D34: Langues supportées spécifiées | E34: Quelles langues sont prises en charge par le support ? | F34: PAS | G34: Plan d'adaptation aux fuseaux horaires | H34: Déséquilibre charge/ressources | I34: Équipes surchargées ou sous-utilisées | J34: Elevée | K34: Promouvoir la qualité de vie au travail et la reconnaissance
F35: PAS | G35: Tableau des rotations d'équipes | H35: Épuisement des équipes en rotation | I35: Fatigue et turnover accru du personnel | J35: Moyenne | K35: Suivre des indicateurs de performance individualisés
D36: Adaptation aux fuseaux horaires | E36: Comment le support s'adapte-t-il aux différents fuseaux horaires ? | F36: PAS | G36: Répartition des ressources par zone | H36: Déséquilibre régional des ressources | I36: Déséquilibre dans la qualité du service | J36: Moyenne | K36: Anticiper les pics de charge via des outils de monitoring
F37: PAS | G37: Rapports de charge par région | H37: Surcharge locale non détectée | I37: Détection tardive des problèmes de charge | J37: Moyenne | K37: Harmoniser les standards de service entre sites et équipes
D38: Répartition des ressources adaptée | E38: Comment les ressources sont-elles réparties selon les zones géographiques ? | F38: PAS | G38: Grille d'évaluation qualité par zone | H38: Qualité inégale selon les zones | I38: Expérience client inégale selon les localisations | J38: Elevée | K38: Mettre en place des plans d’amélioration de la performance support
F39: PAS | G39: Benchmarks régionaux | H39: Performance globale non optimisée | I39: Performance globale du support médiocre | J39: Elevée | K39: Filtrer et orienter les demandes entrantes dès la réception
D40: Indicateurs de couverture par zone | E40: Comment évalue-t-on la qualité du support dans chaque zone géographique ? | F40: PAS | G40: Catalogue des services supportés | H40: Demandes hors scope non filtrées | I40: Temps gaspillé sur des demandes non pertinentes | J40: Moyenne | K40: Mettre en place un outil de priorisation intelligent
F41: PAS | G41: Liste des problèmes résolubles | H41: Temps perdu sur problèmes non résolubles | I41: Productivité réduite des équipes de support | J41: Moyenne | K41: Organiser les équipes autour de pôles d’expertise
D42: Périmètre fonctionnel clairement délimité | E42: Quels types de problèmes peuvent être résolus par le support ? | F42: PAS | G42: Référentiel des catégories de demandes | H42: Mauvaise catégorisation des demandes | I42: Orientation incorrecte et retards de traitement | J42: Elevée | K42: Documenter les solutions aux incidents complexes de manière réutilisable
C43: S’assurer de la couverture fonctionnelle du HD | F43: PAS | G43: Arbre décisionnel de classification | H43: Orientation incorrecte des tickets | I43: Tickets routés vers les mauvaises équipes | J43: Elevée | K43: Adopter des processus adaptés selon le type de requêtes
D44: Types de demandes traitées listées | E44: Quelles sont les catégories de demandes prises en charge par le support ? | F44: PAS | G44: Annuaire des experts techniques | H44: Réseau d'experts sous-utilisé | I44: Expertise interne non pleinement exploitée | J44: Moyenne | K44: Optimiser le cycle de vie des tickets et limiter les rebonds
F45: PAS | G45: Matrice domaines/experts | H45: Expertise spécialisée non exploitée | I45: Problèmes complexes mal résolus | J45: Elevée | K45: Identifier et corriger les faiblesses via des revues post-incident
D46: Experts métiers identifiés | E46: Qui sont les experts référents pour les différents domaines techniques ? | F46: PAS | G46: Procédures par type de demande | H46: Procédures inadaptées au type de demande | I46: Procédures inefficaces pour certains types de demandes | J46: Elevée | K46: Définir une gouvernance claire des données du support
F47: PAS | G47: Workflows spécialisés | H47: Temps de résolution allongé | I47: Temps moyen de résolution augmenté | J47: Elevée | K47: Améliorer les formulaires pour capter toutes les informations dès le départ
D48: Procédures spécifiques par domaine | E48: Existe-t-il des procédures différentes selon le type de demande ? | F48: PAS | G48: Statistiques de résolution par catégorie | H48: Faiblesses non détectées par catégorie | I48: Faiblesses systémiques non corrigées | J48: Elevée | K48: Adopter une interface intuitive et simplifiée pour les utilisateurs
F49: PAS | G49: Tableaux de bord thématiques | H49: Prise de décision ralentie | I49: Prise de décision ralentie et inefficace | J49: Moyenne | K49: Unifier les processus à travers un cadre de gouvernance commun
D50: Indicateurs de résolution par catégorie | E50: Comment mesure-t-on le taux de résolution pour chaque type de problème ? | F50: PAS | G50: Guide de saisie des demandes | H50: Saisie incorrecte des demandes | I50: Données erronées dans le système de tickets | J50: Elevée | K50: Créer une base de connaissances validée pour les réponses standards
F51: PAS | G51: Checklist de validation des tickets | H51: Tickets incomplets ou inexploitables | I51: Nécessité de demander des informations supplémentaires | J51: Moyenne | K51: Constituer une bibliothèque d’articles approuvés et centralisés
D52: Guides contextuels intégrés | E52: Comment s'assure-t-on que les utilisateurs remplissent correctement les formulaires de demande ? | F52: PAS | G52: Assistant intelligent de saisie | H52: Interface utilisateur peu intuitive | I52: Difficulté d'utilisation et adoption réduite | J52: Moyenne | K52: Encourager la réutilisation des solutions et la capitalisation
B53: Fonction support : audit d'efficacité et de performance | C53: S’assurer qu’il existe une aide à la saisie pour la saisie des tickets ; | F53: PAS | G53: Modèles prédéfinis de tickets | H53: Standardisation insuffisante | I53: Manque de cohérence dans les processus | J53: Elevée | K53: Définir des critères de qualité de service mesurables
D54: Assistant intelligent disponible | E54: Existe-t-il des outils pour guider les utilisateurs dans la description de leur problème ? | F54: PAS | G54: Bibliothèque de modèles de tickets | H54: Bibliothèque de solutions sous-utilisée | I54: Réponses non standardisées aux problèmes courants | J54: Moyenne | K54: Mettre en place des audits qualité réguliers
F55: PAS | G55: Exemples de tickets bien formulés | H55: Réinvention permanente des solutions | I55: Réinvention constante des solutions connues | J55: Elevée | K55: Créer une gouvernance de la performance alignée sur les objectifs
D56: Modèles de tickets pré-remplis | E56: Peut-on trouver des modèles prédéfinis pour décrire les problèmes courants ? | F56: PAS | G56: Procédure de vérification des tickets | H56: Vérification aléatoire ou absente | I56: Qualité inégale du service fourni | J56: Moyenne | K56: Structurer un processus d’évaluation transparent et équitable
F57: PAS | G57: Grille d'analyse qualité des tickets | H57: Dégradation progressive de la qualité | I57: Baisse progressive des standards de qualité | J57: Elevée | K57: Partager les axes d’amélioration de manière constructive
D58: Validation automatique des saisies | E58: Comment vérifie-t-on la qualité et la complétude des informations soumises ? | F58: PAS | G58: Guides d'aide à la formulation | H58: Contrôles irréguliers ou incomplets | I58: Contrôles inefficaces et non représentatifs | J58: Elevée | K58: Créer des programmes de reconnaissance et de valorisation
F59: PAS | G59: Tutoriels vidéo | H59: Amélioration continue inefficace | I59: Absence d'amélioration tangible des processus | J59: Elevée | K59: Mettre en place un système d’analyse comparative interne
D60: Aide en ligne accessible | E60: Où les utilisateurs peuvent-ils trouver de l'aide pour formuler leurs demandes ? | F60: PAS | G60: Procédure de contrôle qualité | H60: Critères qualité subjectifs | I60: Jugements incohérents sur la performance | J60: Elevée | K60: Automatiser la mise à jour des informations dans les bases
F61: PAS | G61: Grille d'audit des tickets | H61: Évaluation biaisée des opérateurs | I61: Évaluations injustes et démoralisation | J61: Elevée | K61: Créer une FAQ dynamique pour les demandes fréquentes
D62: Processus de contrôle qualité défini | E62: Comment contrôle-t-on la qualité des enregistrements de demandes ? | F62: PAS | G62: Calendrier des contrôles qualité | H62: Feedback non constructif | I62: Manque d'orientation pour l'amélioration | J62: Elevée | K62: Assurer une indexation efficace de la documentation
C63: S’assurer qu’il existe des revues qualité pour la saisie des tickets ; | F63: PAS | G63: Rapports d'audit qualité | H63: Performance individuelle non suivie | I63: Incapacité à identifier les top performers | J63: Elevée | K63: Former les utilisateurs à la recherche d’information
D64: Échantillonnage régulier des tickets | E64: À quelle fréquence vérifie-t-on la qualité des tickets enregistrés ? | F64: PAS | G64: Référentiel des critères qualité | H64: Correction des faiblesses impossible | I64: Faiblesses persistantes non corrigées | J64: Elevée | K64: Planifier des revues documentaires périodiques
F65: PAS | G65: Grille d'évaluation des opérateurs | H65: Documentation obsolète ou incomplète | I65: Informations inexactes ou obsolètes | J65: Elevée | K65: Évaluer les politiques internes et assurer leur mise à jour
D66: Grille d'évaluation standardisée | E66: Quels sont les critères utilisés pour évaluer la qualité des tickets ? | F66: PAS | G66: Procédure de feedback aux opérateurs | H66: Questions récurrentes non résolues | I66: Questions répétitives au support | J66: Elevée | K66: Aligner la documentation avec les cas d’usage réels
F67: PAS | G67: Rapports individuels de performance | H67: Difficulté à trouver l'information | I67: Temps perdu à chercher des informations | J67: Elevée | K67: Identifier les rôles et responsabilités dans la gestion documentaire
D68: Feedback aux opérateurs | E68: Comment les opérateurs reçoivent-ils des retours sur leur travail ? | F68: PAS | G68: Tableau de bord d'amélioration continue | H68: Ressources documentaires inexploitées | I68: Ressources précises non utilisées | J68: Elevée | K68: Mettre en place un circuit de validation des documents
F69: PAS | G69: Plans d'action qualité | H69: Organisation documentaire illogique | I69: Difficulté à naviguer et trouver des documents | J69: Elevée | K69: Adopter une gouvernance documentaire par domaine fonctionnel
D70: Indicateurs qualité suivis | E70: Quels indicateurs permettent de suivre l'amélioration continue de la qualité ? | F70: PAS | G70: Base de connaissances | H70: Mises à jour non effectuées | I70: Documentation devenue inexacte avec le temps | J70: Elevée | K70: Utiliser des outils de versioning et de suivi d’évolution
F71: PAS | G71: FAQ technique | H71: Documents non révisés périodiquement | I71: Politiques et procédures obsolètes | J71: Moyenne | K71: Informer les utilisateurs des mises à jour critiques
D72: Base documentaire structurée | E72: Où peut-on trouver des solutions aux problèmes courants ? | F72: PAS | G72: Guide de recherche de solutions | H72: Ressources sous-utilisées | I72: Investissements documentaires non optimisés | J72: Moyenne | K72: Intégrer les messages clés dans un portail de communication
C73: Vérifier l’existence d’une base de connaissance ; | F73: PAS | G73: Moteur de recherche interne | H73: Besoins utilisateurs mal compris | I73: Besoins réels non satisfaits | J73: Elevée | K73: Tracer toutes les décisions et changements structurants
D74: Moteur de recherche efficace | E74: Comment rechercher efficacement des solutions existantes ? | F74: PAS | G74: Inventaire des ressources documentaires | H74: Responsabilités documentaires floues | I74: Confusion sur qui est responsable de quoi | J74: Moyenne | K74: Harmoniser les processus entre entités et équipes
F75: PAS | G75: Arborescence des documents | H75: Validation insuffisante | I75: Documents non validés et peu fiables | J75: Elevée | K75: Structurer les pratiques de saisie et d’archivage des données
D76: Articles techniques disponibles | E76: Quels types de ressources documentaires sont disponibles ? | F76: PAS | G76: Procédure de mise à jour documentaire | H76: Documentation non planifiée | I76: Documentation non alignée avec les besoins | J76: Moyenne | K76: Mettre en place une taxonomie commune à toutes les équipes
F77: PAS | G77: Calendrier des révisions | H77: Historique des modifications perdu | I77: Impossible de retracer l'évolution | J77: Moyenne | K77: Utiliser des outils de recherche avancée et centralisée
D78: FAQ régulièrement mise à jour | E78: Comment sont maintenues à jour les réponses aux questions fréquentes ? | F78: PAS | G78: Statistiques d'utilisation des ressources | H78: Utilisateurs non informés des mises à jour | I78: Utilisateurs travaillant avec des versions obsolètes | J78: Elevée | K78: Automatiser les notifications liées aux changements critiques
F79: PAS | G79: Rapports de popularité | H79: Communication inefficace | I79: Messages importants non reçus | J79: Moyenne | K79: Planifier les déploiements avec les parties prenantes clés
D80: Statistiques de consultation | E80: Peut-on connaître la popularité des différentes ressources documentaires ? | F80: PAS | G80: Matrice des responsabilités documentaires | H80: Traçabilité des actions perdue | I80: Impossibilité de reconstituer les événements | J80: Moyenne | K80: Tester les versions en environnement pré-production rigoureux
F81: PAS | G81: Procédure de validation documentaire | H81: Standardisation insuffisante | I81: Processus non uniformes entre équipes | J81: Moyenne | K81: Adopter une politique stricte de validation avant mise en ligne
D82: Rôles et responsabilités définis | E82: Qui est responsable de la mise à jour des ressources documentaires ? | F82: PAS | G82: Plan de révision documentaire | H82: Qualité d'enregistrement variable | I82: Qualité variable des données enregistrées | J82: Elevée | K82: Planifier des fenêtres de maintenance avec communication proactive
C83: S’assurer qu’une procédure de mise à jour de la base de connaissance existe ; | F83: PAS | G83: Journal des modifications | H83: Politique inconsistante | I83: Approche incohérente entre les équipes | J83: Elevée | K83: Mettre en place un système de rollback sécurisé
D84: Fréquence de mise à jour formalisée | E84: À quelle fréquence les ressources documentaires sont-elles révisées ? | F84: PAS | G84: Procédure de notification des mises à jour | H84: Délais de traitement excessifs | I84: Délais excessifs pour les utilisateurs | J84: Moyenne | K84: Superviser l’environnement post-déploiement avec alertes
F85: PAS | G85: Liste de diffusion des nouveautés | H85: Performance non mesurée | I85: Performance non mesurable ni améliorable | J85: Moyenne | K85: Impliquer les parties prenantes dans le processus de changement
D86: Validation des modifications | E86: Comment valide-t-on les nouvelles informations avant leur publication ? | F86: PAS | G86: Procédure de traçabilité des interactions | H86: Archivage désorganisé | I86: Difficulté à retrouver des informations historiques | J86: Elevée | K86: Standardiser les processus entre build, test et run
F87: PAS | G87: Modèle d'enregistrement des tickets | H87: Accès aux historiques difficile | I87: Accès difficile aux données passées | J87: Elevée | K87: Fournir une documentation complète à l’équipe support
D88: Historique des changements | E88: Peut-on consulter l'historique des modifications apportées aux ressources ? | F88: PAS | G88: Normes d'enregistrement des appels | H88: Planning de déploiement irréaliste | I88: Retards dans les déploiements critiques | J88: Moyenne | K88: Assurer la traçabilité complète des évolutions du code
F89: PAS | G89: Politique d'enregistrement des échanges | H89: Préparation insuffisante | I89: Problèmes non anticipés lors du déploiement | J89: Elevée | K89: Intégrer les changements dans une gestion de configuration robuste
D90: Diffusion des mises à jour | E90: Comment les utilisateurs sont-ils informés des nouvelles ressources disponibles ? | F90: PAS | G90: Statistiques de temps de traitement | H90: Tests incomplets ou absents | I90: Bugs et problèmes non détectés à temps | J90: Elevée | K90: Harmoniser la gestion de version et le cycle DevOps
F91: PAS | G91: Rapports de performance | H91: Qualité non vérifiée | I91: Qualité insuffisante des mises en production | J91: Elevée | K91: Favoriser l’automatisation des tests de régression
D92: Traçabilité complète des appels | E92: Comment s'assure-t-on de la traçabilité complète des interactions ? | F92: PAS | G92: Politique d'archivage des tickets | H92: Fenêtres de maintenance inadaptées | I92: Périodes de maintenance mal choisies | J92: Elevée | K92: Identifier en amont les dépendances et les incompatibilités
C93: S’assurer que les appels sont enregistrés ; | F93: PAS | G93: Procédure de gestion des archives | H93: Interruptions imprévues | I93: Interruptions de service imprévues | J93: Moyenne | K93: Adopter une posture proactive dans la résolution d’anomalies
D94: Métadonnées standardisées | E94: Quelles informations standardisées sont enregistrées pour chaque demande ? | F94: PAS | G94: Calendrier des déploiements | H94: Rollback impossible ou difficile | I94: Impossibilité de revenir à une version stable | J94: Elevée | K94: Créer un processus structuré de gestion des problèmes
F95: PAS | G95: Checklist pré-déploiement | H95: Incidents post-déploiement non gérés | I95: Problèmes post-déploiement non résolus | J95: Moyenne | K95: Maintenir un inventaire à jour et exhaustif
D96: Enregistrement des interactions | E96: Les échanges téléphoniques ou en ligne sont-ils enregistrés ? | F96: PAS | G96: Procédure de tests de validation | H96: Communication insuffisante | I96: Parties prenantes surprises par les changements | J96: Moyenne | K96: Mettre en place un outil de gestion de parc synchronisé
F97: PAS | G97: Rapports de tests | H97: Parties prenantes non informées | I97: Manque d'alignement entre les équipes | J97: Elevée | K97: Planifier un cycle de renouvellement basé sur les usages réels
D98: Durée des appels mesurée | E98: Comment mesure-t-on la durée moyenne de traitement des demandes ? | F98: PAS | G98: Fenêtres de maintenance autorisées | H98: Gestion des versions chaotique | I98: Versions incohérentes en production | J98: Moyenne | K98: Vérifier la couverture de maintenance sur tous les équipements
F99: PAS | G99: Calendrier des interruptions | H99: Documentation technique manquante | I99: Manque de documentation pour le support | J99: Elevée | K99: Mettre en œuvre un système d’étiquetage et de suivi des actifs
D100: Archivage sécurisé | E100: Où et comment sont archivées les données des demandes traitées ? | F100: PAS | G100: Plan de rollback | H100: Historique des versions perdu | I100: Impossible de retracer les évolutions | J100: Moyenne | K100: Structurer un processus d’affectation clair et traçable
...

Sheet Sécurité
A1: Domaine | B1: Point de contrôle | C1: objectif de contrôle | D1: critères d'évaluation | E1: Questiond'évaluation | F1: Réponse | G1: Documents réquis | H1: Risque | I1: Conséquence | J1: criticité | K1: Récommendations
A2: Sécurité | D2: Documentation complète et à jour de la politique de sécurité | E2: La politique de sécurité est-elle documentée et maintenue à jour ? | F2: NON | G2: Politique de sécurité documentée | H2: Perte de traçabilité des évolutions du système | I2: Non-conformité réglementaire | J2: Elevée | K2: Mettre en place un processus de veille et conformité réglementaire
B3: Facteurs clés de succès ; | C3: Vérifier qu’une politique de sécurité est définie et correspond à l'activité de l'Organisation ; | F3: PAS | G3: Historique des versions et mises à jour | H3: Désalignement entre sécurité et opérations métiers | I3: Augmentation des risques opérationnels | J3: Moyenne | K3: Réaliser une analyse des risques approfondie et régulière
D4: Adéquation entre les objectifs de sécurité et les enjeux métiers | E4: Comment les objectifs de sécurité correspondent-ils aux besoins métiers ? | F4: OUI | G4: Cartographie des objectifs sécurité vs besoins métiers | H4: Absence de validation formelle des orientations | I4: Décisions non alignées avec les besoins réels | J4: Moyenne | K4: Impliquer les métiers dans les processus décisionnels
F5: NON | G5: Procès-verbal d'alignement stratégique | H5: Manque de preuve des validations obtenues | I5: Difficulté à prouver la conformité | J5: Elevée | K5: Documenter systématiquement les preuves de conformité
D6: Validation de la politique par les parties prenantes clés | E6: Les parties prenantes clés ont-elles validé la politique ? | F6: NON | G6: Registre des validations par les parties prenantes | H6: Engagements non formalisés des parties prenantes | I6: Manque d'engagement des parties prenantes | J6: Moyenne | K6: Formaliser les engagements par des chartes signées
F7: NON | G7: Attestations de validation signées | H7: Politique de sécurité obsolète non mise à jour | I7: Exposition accrue aux menaces | J7: Elevée | K7: Mettre à jour les dispositifs de protection
D8: Existence d’un processus de mise à jour régulière | E8: Existe-t-il un processus défini pour mettre à jour la politique ? | F8: NON | G8: Procédure de mise à jour de la politique | H8: Revue de sécurité non planifiée ou retardée | I8: Détection tardive des vulnérabilités | J8: Moyenne | K8: Automatiser les scans de vulnérabilités
F9: OUI | G9: Calendrier des revues de sécurité | H9: Incapacité à prouver la diffusion des consignes | I9: Non-respect des obligations légales | J9: Moyenne | K9: Nommer un délégué à la conformité
D10: Preuves de communication aux employés et partenaires | E10: Des preuves montrent-elles que la politique a été communiquée ? | F10: OUI | G10: Preuves de diffusion (accusés de réception, logs) | H10: Supports de communication inefficaces ou inadaptés | I10: Mesures de sécurité inefficaces | J10: Elevée | K10: Réaliser des tests d'efficacité des contrôles
F11: OUI | G11: Supports de communication utilisés | H11: Non-conformité non détectée ou non corrigée | I11: Dégradation de la performance métier | J11: Moyenne | K11: Aligner les mesures de sécurité avec les processus métiers
D12: Analyse des pratiques existantes et leur cohérence avec la sécurité | E12: Les pratiques actuelles sont-elles alignées sur les exigences de sécurité ? | F12: OUI | G12: Rapport d'audit d'alignement des pratiques | H12: Plan d'action non formalisé ou incomplet | I12: Perte de confiance des dirigeants | J12: Moyenne | K12: Établir un reporting régulier à la direction
C13: Vérifier qu’une démarche de mise en œuvre de la gestion de la sécurité est adoptée et compatible avec la culture de l'Organisation ; | F13: OUI | G13: Plan de conformité sécurité | H13: Participation insuffisante des métiers | I13: Dépenses non contrôlées | J13: Moyenne | K13: Mettre en place un processus budgétaire strict
D14: Implication des équipes dans la définition des mesures | E14: Les équipes sont-elles impliquées dans la définition des mesures ? | F14: OUI | G14: Comptes-rendus des ateliers collaboratifs | H14: Contributions non enregistrées ou perdues | I14: Budget sécurité insuffisant | J14: Elevée | K14: Réaliser une étude des besoins financiers
F15: OUI | G15: Registre des contributions des équipes | H15: Outils de sécurité non ergonomiques mal adoptés | I15: Gaspillage des ressources | J15: Elevée | K15: Optimiser l'allocation des ressources
D16: Adaptation des outils aux habitudes de travail | E16: Les outils sont-ils adaptés aux habitudes de travail ? | F16: OUI | G16: Étude d'ergonomie des outils sécurité | H16: Besoins utilisateurs non pris en compte | I16: Incohérence dans la communication interne | J16: Moyenne | K16: Standardiser les canaux et messages de communication
F17: OUI | G17: Enquête de satisfaction utilisateurs | H17: Retours utilisateurs non capitalisés | I17: Baisse de la sensibilisation à la sécurité | J17: Moyenne | K17: Lancer des campagnes de sensibilisation régulières
D18: Retours d’expérience des employés sur les mesures appliquées | E18: Les employés fournissent-ils des retours sur les mesures appliquées ? | F18: OUI | G18: Registre des retours employés | H18: Améliorations non implémentées malgré les retours | I18: Confusion dans les rôles et responsabilités | J18: Elevée | K18: Définir clairement les rôles dans des fiches de poste
F19: OUI | G19: Analyse des feedbacks et améliorations | H19: Bonnes pratiques non partagées ou formalisées | I19: Désorganisation dans la gestion des risques | J19: Elevée | K19: Structurer un processus formel de gestion des risques
D20: Exemples concrets d’intégration réussie | E20: Des exemples montrent-ils une intégration réussie ? | F20: OUI | G20: Cas d'usage réussis documentés | H20: Manque d'adhésion des métiers à la sécurité | I20: Absence de documentation des décisions | J20: Moyenne | K20: Documenter systématiquement les décisions importantes
F21: OUI | G21: Témoignages métiers | H21: Participation directionnelle insuffisante | I21: Prise de décisions non sécurisées | J21: Elevée | K21: Instaurer une validation sécurité pour les décisions clés
D22: Participation active de la direction aux comités de sécurité | E22: La direction participe-t-elle activement aux comités de sécurité ? | F22: OUI | G22: Feuilles de présence aux comités | H22: Engagements financiers non tenus | I22: Évaluation des risques imprécise | J22: Elevée | K22: Adopter une méthodologie d'évaluation des risques reconnue
C23: Vérifier que la direction assure un soutien total et un engagement visible pour la sécurité; | F23: OUI | G23: Engagements budgétaires écrits | H23: Budget sécurité non maîtrisé ou sous-dimensionné | I23: Critères d'analyse incohérents | J23: Elevée | K23: Définir des critères d'analyse standardisés
D24: Budget alloué aux initiatives de sécurité | E24: Un budget est-il alloué aux initiatives de sécurité ? | F24: OUI | G24: Budget sécurité détaillé | H24: Dépenses sécurité non tracées ou non optimisées | I24: Perte de connaissance des risques passés | J24: Elevée | K24: Maintenir un registre historique des risques
F25: OUI | G25: Suivi des dépenses sécurité | H25: Communication directionnelle incohérente | I25: Expertise non exploitée | J25: Moyenne | K25: Solliciter systématiquement l'expertise métier
D26: Communication régulière de la direction sur l’importance de la sécurité | E26: La direction communique-t-elle régulièrement sur la sécurité ? | F26: OUI | G26: Archives des communications direction | H26: Campagnes de sensibilisation irrégulières | I26: Manque de légitimité des analyses | J26: Elevée | K26: Formaliser les processus d'analyse par des procédures
F27: OUI | G27: Calendrier des campagnes internes | H27: Responsabilités sécurité mal définies | I27: Réévaluation des risques absente | J27: Moyenne | K27: Planifier des réévaluations périodiques des risques
D28: Responsabilités claires attribuées aux membres de la direction | E28: Les responsabilités des membres de la direction sont-elles claires ? | F28: OUI | G28: Matrice RACI sécurité | H28: Rôles sécurité non actualisés avec l'organisation | I28: Impossible de suivre l'historique des risques | J28: Moyenne | K28: Implémenter un système de traçabilité des risques
F29: OUI | G29: Fiches de poste actualisées | H29: Décisions stratégiques non documentées | I29: Traitement inefficace des risques majeurs | J29: Elevée | K29: Prioriser le traitement des risques selon leur criticité
D30: Preuves de décisions alignées avec la politique de sécurité | E30: Les décisions sont-elles alignées sur la politique ? | F30: OUI | G30: Registre des décisions stratégiques | H30: Décisions non alignées avec la politique sécurité | I30: Corrections non appliquées | J30: Moyenne | K30: Mettre en place un suivi rigoureux des actions correctives
F31: OUI | G31: Vérification d'alignement des décisions | H31: Méthodologie d'analyse des risques absente | I31: Formation inadaptée aux besoins | J31: Elevée | K31: Réaliser une analyse des besoins en formation
D32: Existence d’une méthodologie d’évaluation des risques | E32: Une méthodologie d'évaluation des risques est-elle en place ? | F32: OUI | G32: Méthodologie d'analyse des risques | H32: Critères d'évaluation des risques inconsistants | I32: Sessions de formation mal organisées | J32: Moyenne | K32: Planifier les sessions selon les disponibilités des équipes
C33: Vérifier que les exigences de sécurité et les risques sont compris et évalués ; | F33: OUI | G33: Grille d'évaluation des risques | H33: Analyses de risques non documentées | I33: Supports pédagogiques inefficaces | J33: Moyenne | K33: Développer des supports pédagogiques adaptés
D34: Documentation des analyses de risques récentes | E34: Les analyses de risques récentes sont-elles documentées ? | F34: OUI | G34: Derniers rapports d'analyse de risques | H34: Capitalisation connaissances risques perdue | I34: Autoformation impossible | J34: Elevée | K34: Mettre en place une plateforme d'e-learning
F35: NON | G35: Base de connaissances des risques | H35: Expertise métier non sollicitée | I35: Acquisition des connaissances non vérifiée | J35: Moyenne | K35: Évaluer les acquis par des tests systématiques
D36: Implication des métiers dans l’identification des risques | E36: Les métiers participent-ils à l'identification des risques ? | F36: NON | G36: Liste des participants métiers aux analyses | H36: Implication métier non prouvée | I36: Efficacité des formations non mesurée | J36: Moyenne | K36: Mesurer l'impact des formations sur les pratiques
F37: NON | G37: Preuves de contribution métier | H37: Réévaluation des risques non planifiée | I37: Sensibilisation irrégulière | J37: Moyenne | K37: Établir un calendrier de sensibilisation annuel
D38: Mise à jour régulière des évaluations | E38: Les évaluations sont-elles mises à jour régulièrement ? | F38: NON | G38: Calendrier des réévaluations | H38: Historique des risques non conservé | I38: Participation faible aux formations | J38: Elevée | K38: Rendre obligatoire la participation aux formations clés
F39: NON | G39: Journal des mises à jour des risques | H39: Traitement des risques prioritaires inefficace | I39: Retours non pris en compte | J39: Elevée | K39: Implémenter un système de collecte et traitement des retours
D40: Plans d’action pour les risques identifiés | E40: Des plans d'action existent-ils pour les risques identifiés ? | F40: NON | G40: Plans d'action risques prioritaires | H40: Suivi des actions correctives non assuré | I40: Amélioration continue absente | J40: Moyenne | K40: Instaurer un processus formalisé d'amélioration continue
F41: NON | G41: Suivi des actions correctives | H41: Offre de formation non structurée | I41: Politique non approuvée | J41: Moyenne | K41: Soumettre la politique à validation formelle par la direction
D42: Programme de formation régulier et obligatoire | E42: Un programme de formation obligatoire est-il en place ? | F42: NON | G42: Catalogue des formations obligatoires | H42: Planification des sessions non optimale | I42: Validation non documentée | J42: Elevée | K42: Documenter toutes les validations obtenues
C43: Vérifier que l’ensemble des responsables et des employés sont sensibilisés et informés ; | F43: NON | G43: Planning des sessions de formation | H43: Supports pédagogiques inadaptés aux publics | I43: Rôles mal définis | J43: Elevée | K43: Mettre à jour le référentiel des rôles et responsabilités
D44: Supports adaptés aux différents rôles et niveaux | E44: Les supports sont-ils adaptés aux différents rôles ? | F44: NON | G44: Supports pédagogiques par public cible | H44: Autoformation impossible ou inefficace | I44: Responsabilités mal attribuées | J44: Moyenne | K44: Clarifier les responsabilités dans des matrices RACI
F45: NON | G45: Kits d'autoformation | H45: Acquisition des connaissances non mesurée | I45: Approbations non tracées | J45: Elevée | K45: Tracer systématiquement les approbations données
D46: Tests de connaissance après les formations | E46: Des tests de connaissance sont-ils effectués après les formations ? | F46: NON | G46: Résultats aux tests de connaissance | H46: Efficacité des formations non évaluée | I46: Processus non standardisé | J46: Elevée | K46: Standardiser les processus clés par des procédures écrites
F47: NON | G47: Taux de réussite par formation | H47: Campagnes de sensibilisation irrégulières | I47: Communication inefficace | J47: Elevée | K47: Élaborer un plan de communication structuré
D48: Campagnes de sensibilisation périodiques | E48: Des campagnes de sensibilisation sont-elles organisées ? | F48: OUI | G48: Planning des campagnes de sensibilisation | H48: Participation non suivie ou faible | I48: Diffusion incomplète des informations | J48: Elevée | K48: Contrôler systématiquement la diffusion des informations
F49: OUI | G49: Statistiques de participation | H49: Retours apprenants non analysés | I49: Historique des modifications perdu | J49: Moyenne | K49: Implémenter un système de gestion des versions
D50: Feedback des employés sur l’utilité des formations | E50: Les employés donnent-ils leur avis sur les formations ? | F50: OUI | G50: Synthèse des retours apprenants | H50: Amélioration continue non formalisée | I50: Comparaison des versions impossible | J50: Elevée | K50: Mettre en place des outils de comparaison de versions
F51: OUI | G51: Plan d'amélioration continue | H51: Politique non validée par la direction | I51: Base documentaire désorganisée | J51: Moyenne | K51: Organiser et classer la base documentaire
D52: Signature de la politique par la direction générale | E52: La politique est-elle signée par la direction générale ? | F52: OUI | G52: Politique signée par la DG | H52: Approbation formelle non documentée | I52: Langage incompréhensible | J52: Moyenne | K52: Adapter le langage aux différents publics cibles
B53: Politique de sécurité ; | C53: S’assurer qu’il existe une politique de sécurité formalisée avec une implication de la direction générale et une définition claire des responsabilités ; | F53: OUI | G53: Procès-verbal d'approbation | H53: Référentiel des rôles obsolète | I53: Canaux de communication mal utilisés | J53: Elevée | K53: Optimiser l'utilisation des canaux de communication
D54: Définition explicite des rôles et responsabilités | E54: Les rôles et responsabilités sont-ils clairement définis ? | F54: OUI | G54: Référentiel des rôles sécurité | H54: Responsabilités mal réparties | I54: Statistiques non analysées | J54: Moyenne | K54: Analyser régulièrement les statistiques d'utilisation
F55: OUI | G55: Organigramme des responsabilités | H55: Validations hiérarchiques non tracées | I55: Retours utilisateurs ignorés | J55: Elevée | K55: Mettre en place un mécanisme de collecte des retours
D56: Processus de validation hiérarchique des mesures | E56: Les mesures sont-elles validées hiérarchiquement ? | F56: OUI | G56: Procès-verbaux de validation hiérarchique | H56: Processus d'approbation non formalisé | I56: Suggestions non exploitées | J56: Moyenne | K56: Implémenter un système de gestion des suggestions
F57: OUI | G57: Workflow d'approbation | H57: Plan de communication non établi | I57: Bonnes pratiques non partagées | J57: Moyenne | K57: Formaliser et partager les bonnes pratiques
D58: Communication officielle aux parties prenantes | E58: La politique est-elle officiellement communiquée ? | F58: OUI | G58: Plan de communication officiel | H58: Diffusion non contrôlée ou incomplète | I58: Base de connaissances inexploitée | J58: Elevée | K58: Centraliser les connaissances dans une base unique
F59: OUI | G59: Preuves de diffusion large | H59: Historique des modifications perdu | I59: Revues non planifiées | J59: Moyenne | K59: Planifier des revues périodiques systématiques
D60: Preuves de révision régulière | E60: Des preuves de révision régulière existent-elles ? | F60: PAS | G60: Historique des révisions documenté | H60: Comparaison entre versions impossible | I60: Ordres du jour non standardisés | J60: Moyenne | K60: Standardiser les ordres du jour des réunions
C61: S’assurer que la communication se fait à tous les utilisateurs sous une forme pertinente, accessible et compréhensible au lecteur ; | F61: PAS | G61: Comparatif des versions | H61: Bibliothèque de supports désorganisée | I61: Participation non suivie | J61: Moyenne | K61: Tracer la participation aux réunions importantes
D62: Supports variés (vidéos, guides, affiches) adaptés aux cibles | E62: Les supports de communication sont-ils variés et adaptés ? | F62: PAS | G62: Bibliothèque des supports de communication | H62: Langage inadapté au public cible | I62: Comptes-rendus non produits | J62: Elevée | K62: Produire systématiquement des comptes-rendus
F63: PAS | G63: Guide de langage simplifié | H63: Canaux de communication mal utilisés | I63: Journal des modifications non tenu | J63: Elevée | K63: Tenir à jour un journal des modifications
D64: Langage clair et non technique pour les non-experts | E64: Le langage utilisé est-il compréhensible pour les non-experts ? | F64: PAS | G64: Matrice des canaux de communication | H64: Statistiques d'utilisation non analysées | I64: Traçabilité des changements perdue | J64: Moyenne | K64: Implémenter un système de traçabilité des changements
F65: PAS | G65: Statistiques d'utilisation des canaux | H65: Mécanisme de collecte des retours absent | I65: Analyse post-incident insuffisante | J65: Moyenne | K65: Réaliser des analyses post-incident approfondies
D66: Canaux de communication diversifiés (intranet, emails, réunions) | E66: Plusieurs canaux de communication sont-ils utilisés ? | F66: PAS | G66: Procédure de collecte des retours | H66: Suggestions d'amélioration ignorées | I66: Corrections non implémentées | J66: Elevée | K66: Suivre rigoureusement la mise en œuvre des corrections
F67: PAS | G67: Analyse des suggestions d'amélioration | H67: Bonnes pratiques non capitalisées | I67: Positionnement inconnu | J67: Elevée | K67: Réaliser un benchmark sectoriel régulier
D68: Mécanismes de feedback et questions/réponses | E68: Des mécanismes permettent-ils de recueillir des retours ? | F68: PAS | G68: Recueil des bonnes pratiques | H68: Base de connaissances non partagée | I68: Écarts non mesurés | J68: Moyenne | K68: Mesurer régulièrement les écarts avec les standards
F69: PAS | G69: Base de connaissances partagée | H69: Revues périodiques non planifiées | I69: Inventaire incomplet | J69: Elevée | K69: Maintenir un inventaire à jour des actifs
D70: Exemples de bonnes pratiques partagées | E70: Des bonnes pratiques sont-elles partagées ? | F70: OUI | G70: Calendrier des revues périodiques | H70: Ordres du jour non standardisés | I70: Couverture sécurité insuffisante | J70: Elevée | K70: Réaliser une analyse des couvertures de sécurité
C71: S’assurer qu’une revue régulière de la politique est réalisée afin de vérifier son adéquation avec ; | F71: OUI | G71: Ordres du jour types | H71: Participation aux comités non suivie | I71: Zones critiques non auditées | J71: Elevée | K71: Identifier et auditer régulièrement les zones critiques
D72: Calendrier défini pour les revues | E72: Un calendrier est-il défini pour les revues ? | F72: OUI | G72: Liste des participants aux revues | H72: Comptes-rendus des comités non produits | I72: Plan de renforcement absent | J72: Elevée | K72: Élaborer un plan de renforcement des contrôles
F73: OUI | G73: Comptes-rendus des comités | H73: Journal des modifications non tenu | I73: Contrôles incohérents | J73: Moyenne | K73: Harmoniser les contrôles à l'échelle de l'organisation
D74: Participation des métiers et de la direction | E74: Les métiers et la direction participent-ils aux revues ? | F74: OUI | G74: Journal des modifications apportées | H74: Traçabilité des changements perdue | I74: Checklist d'audit inadaptée | J74: Elevée | K74: Adapter les checklists d'audit aux besoins réels
F75: OUI | G75: Traçabilité des changements | H75: Analyse post-incident insuffisante | I75: Matrice RACI incomplète | J75: Moyenne | K75: Compléter et maintenir à jour les matrices RACI
D76: Documentation des modifications apportées | E76: Les modifications sont-elles documentées ? | F76: OUI | G76: Rapports d'analyse d'incidents | H76: Ajustements post-incident non implémentés | I76: Responsabilités floues | J76: Moyenne | K76: Clarifier la cartographie des responsabilités
F77: OUI | G77: Plan d'ajustement post-incident | H77: Positionnement sectoriel inconnu | I77: Désignation non formelle | J77: Elevée | K77: Formaliser la désignation des propriétaires de processus
D78: Analyse des incidents pour ajuster la politique | E78: Les incidents sont-ils analysés pour ajuster la politique ? | F78: OUI | G78: Benchmark sectoriel sécurité | H78: Écarts avec les standards non mesurés | I78: Registre non tenu | J78: Moyenne | K78: Tenir un registre central des responsables
F79: OUI | G79: Analyse des écarts avec les standards | H79: Inventaire des actifs incomplet | I79: Intégration inefficace | J79: Elevée | K79: Structurer un processus d'intégration formalisé
D80: Benchmarking avec les standards du secteur | E80: Un benchmarking est-il réalisé avec les standards du secteur ? | F80: OUI | G80: Inventaire complet des actifs | H80: Couverture sécurité insuffisante | I80: Kit d'intégration absent | J80: Moyenne | K80: Fournir un kit d'intégration complet
C81: S’assurer que la démarche de sécurité inclut la totalité de l’informatique et non les seuls réseaux, serveurs et applications Les imprimantes et téléphones sous IP, l’informatique technique et industrielle, l’informatique de gestion technique des bâtiments, celle de gestion des accès et temps de travail, etc bénéficient sans exception ni zone d’ombre du dispositif de sécurité | F81: OUI | G81: Rapport de couverture sécurité | H81: Zones critiques non auditées | I81: Rôles non vérifiés | J81: Moyenne | K81: Vérifier régulièrement l'adéquation des rôles
D82: Inventaire exhaustif des équipements et logiciels | E82: L'inventaire des équipements et logiciels est-il exhaustif ? | F82: OUI | G82: Audit des zones critiques | H82: Plan de renforcement absent | I82: Évaluations non réalisées | J82: Elevée | K82: Mettre en place des évaluations périodiques
F83: OUI | G83: Plan de renforcement | H83: Contrôles non uniformes | I83: Sanctions non définies | J83: Moyenne | K83: Définir une grille de sanctions claire
D84: Mesures de sécurité appliquées à tous les dispositifs (IoT, industriels, etc) | E84: Les mesures de sécurité couvrent-elles tous les dispositifs ? | F84: OUI | G84: Procédure de contrôle uniforme | H84: Checklist d'audit non adaptée | I84: Application non tracée | J84: Moyenne | K84: Tracer systématiquement l'application des sanctions
F85: OUI | G85: Checklist d'audit sécurité | H85: Matrice RACI incomplète | I85: Fiches de poste incomplètes | J85: Moyenne | K85: Compléter et mettre à jour les fiches de poste
D86: Absence d’exclusions non justifiées | E86: Aucune exclusion injustifiée n'est-elle constatée ? | F86: OUI | G86: Matrice RACI complète | H86: Cartographie des responsabilités floue | I86: Référentiel obsolète | J86: Elevée | K86: Actualiser régulièrement le référentiel des compétences
F87: OUI | G87: Cartographie des responsabilités | H87: Désignation des propriétaires non formelle | I87: Reporting non standardisé | J87: Elevée | K87: Standardiser les modèles de reporting
D88: Contrôles techniques et organisationnels uniformes | E88: Les contrôles sont-ils uniformes ? | F88: OUI | G88: Désignation officielle des propriétaires | H88: Registre des responsables non tenu | I88: Archives désorganisées | J88: Moyenne | K88: Mettre en place un système de classement et d'indexation
F89: NON | G89: Registre des responsables | H89: Onboarding sécurité inefficace | I89: Budget insuffisant | J89: Moyenne | K89: Réaliser une étude des besoins financiers
D90: Audit des zones traditionnellement négligées | E90: Les zones traditionnellement négligées sont-elles auditées ? | F90: NON | G90: Processus d'onboarding sécurité | H90: Kit d'intégration non fourni | I90: Dépenses non suivies | J90: Elevée | K90: Implémenter un outil de suivi budgétaire
F91: NON | G91: Kit d'intégration sécurité | H91: Contrôle des rôles non effectué | I91: Corrections non évaluées | J91: Elevée | K91: Établir un processus de validation des correctifs
D92: Matrice RACI (Responsible, Accountable, Consulted, Informed) définie | E92: Une matrice RACI est-elle définie ? | F92: NON | G92: Rapports de contrôle des rôles | H92: Évaluations périodiques non réalisées | I92: Indicateurs non définis | J92: Moyenne | K92: Développer des KPIs pertinents
F93: NON | G93: Évaluations périodiques | H93: Grille des sanctions non définie | I93: Alignement non vérifié | J93: Elevée | K93: Réaliser des audits d'alignement réguliers
D94: Désignation formelle des propriétaires d’actifs | E94: Les propriétaires d'actifs sont-ils formellement désignés ? | F94: NON | G94: Grille des sanctions applicables | H94: Application des sanctions non tracée | I94: Tableau de bord absent | J94: Elevée | K94: Concevoir un dashboard de pilotage
F95: NON | G95: Registre des sanctions appliquées | H95: Fiches de poste non détaillées | I95: Workflow non documenté | J95: Elevée | K95: Modéliser les processus clés
D96: Processus d’onboarding pour les nouvelles responsabilités | E96: Un processus d'onboarding existe-t-il pour les nouvelles responsabilités ? | F96: NON | G96: Fiches de poste détaillées | H96: Référentiel des compétences obsolète | I96: Validation non formalisée | J96: Elevée | K96: Créer des procédures de validation
F97: NON | G97: Référentiel des compétences | H97: Modèles de reporting non standardisés | I97: Référentiel obsolète | J97: Moyenne | K97: Actualiser les référentiels annuellement
D98: Contrôles réguliers de l’exécution des rôles | E98: L'exécution des rôles est-elle contrôlée régulièrement ? | F98: NON | G98: Modèles de reporting direction | H98: Archives des rapports non organisées | I98: Normes non établies | J98: Elevée | K98: Définir des standards internes
F99: NON | G99: Archives des rapports envoyés | H99: Budget des mises à jour insuffisant | I99: Plan directeur absent | J99: Moyenne | K99: Élaborer une feuille de route stratégique
D100: Sanctions en cas de non-respect des obligations | E100: Des sanctions sont-elles appliquées en cas de non-respect ? | F100: OUI | G100: Budget dédié aux mises à jour | H100: Suivi des dépenses non assuré | I100: Alignement non prouvé | J100: Moyenne | K100: Documenter les preuves d'alignement
...
