Workbook

Sheet Synthèse
B3: Synthèse Numérique
K4: Travail de :
B5: N° | C5: Domaines | D5: Total OUI | E5: Total NON | F5: Total PAS | G5: Total | H5: Score
B6: 1 | C6: Application en service | D6: =COUNTIF('4.1.Appli_En_Service'!F2:F251,"Oui") -> 85 | E6: =COUNTIF('4.1.Appli_En_Service'!F2:F251,"Non") -> 91 | F6: =COUNTIF('4.1.Appli_En_Service'!F2:F251,"Pas") -> 74 | G6: =SUM(D6:F6) -> 250 | H6: =D6/G6 -> 0.34 | M6: Nom | N6: Prénom | O6: Matricule | P6: Filière
B7: 2 | C7: Fonction informatique | D7: =COUNTIF('4.2.Fonction_informatique'!F2:F269,"Oui") -> 81 | E7: =COUNTIF('4.2.Fonction_informatique'!F2:F269,"Non") -> 74 | F7: =COUNTIF('4.2.Fonction_informatique'!F2:F269,"Pas") -> 64 | G7: =SUM(D7:F7) -> 219 | H7: =D7/G7 -> 0.36986301 | M7: NGUEGANG | N7: LUCRESSE | O7: 22P085 | P7: ICD-3
B8: 3 | C8: Projets informatiques | D8: =COUNTIF('4.3.Projets_Informatiques'!F2:F450,"Oui") -> 142 | E8: =COUNTIF('4.3.Projets_Informatiques'!F2:F450,"Non") -> 128 | F8: =COUNTIF('4.3.Projets_Informatiques'!F2:F450,"Pas") -> 104 | G8: =SUM(D8:F8) -> 374 | H8: =D8/G8 -> 0.37967914
B9: 4 | C9: Support utilisateur et de la gestion du parc | D9: =COUNTIF('4.4.SupportUser_GestParc'!F2:F301,"Oui") -> 90 | E9: =COUNTIF('4.4.SupportUser_GestParc'!F2:F301,"Non") -> 84 | F9: =COUNTIF('4.4.SupportUser_GestParc'!F2:F301,"Pas") -> 56 | G9: =SUM(D9:F9) -> 230 | H9: =D9/G9 -> 0.39130435
B10: 5 | C10: Sécurité informatique | D10: =COUNTIF('4.5.Sécurité_Informatique'!F2:F401,"Oui") -> 133 | E10: =COUNTIF('4.5.Sécurité_Informatique'!F2:F401,"Non") -> 118 | F10: =COUNTIF('4.5.Sécurité_Informatique'!F2:F401,"Pas") -> 84 | G10: =SUM(D10:F10) -> 335 | H10: =D10/G10 -> 0.39701493
B11: Total | D11: =SUM(D6:D10) -> 531 | E11: =SUM(E6:E10) -> 495 | F11: =SUM(F6:F10) -> 382 | G11: =SUM(D11:F11) -> 1408 | H11: =D11/G11 -> 0.37713068
C15: Synthèse Graphique

Sheet Global
A1: Domaines | B1: Points de contrôle | C1: Objectifs de contrôle | D1: Critères d'évaluation | E1: Questions d'évaluation | F1: Réponses | G1: Documents requis | H1: Risques | I1: Criticité | J1: Conséquences | K1: Recommandations
A2: Audit d'une application en service | B2: Organisation | C2: S’assurer de l’existence d'un comité informatique | D2: organigramme officiel doit inclure le comité informatique | E2: L'organigramme officiel inclut-il clairement le comité informatique ? | F2: Oui | G2: Organigramme officiel incluant le comité informatique | H2: Manque de coordination et de gouvernance | I2: elevée | J2: Décisions incohérentes, retards dans les projets, conflits entre équipes, perte de confiance des parties prenantes. | K2: Mettre en place une structure de gouvernance claire avec des rôles définis et des réunions régulières.
D3: Documentation formelle doit décrire les responsabilités du comité | E3: Les responsabilités du comité informatique sont-elles documentées de manière formelle ? | F3: Non | G3: Document formel décrivant les responsabilités du comité | H3: Confusion et chevauchement des tâches | I3: elevée | J3: Gaspillage de ressources, frustration des employés, responsabilités floues, omissions critiques. | K3: Clarifier les responsabilités via des fiches de poste et des procédures documentées.
D4: réunions frequentes et compte doivent etre rendus disponibles | E4: Les réunions du comité informatique sont-elles tenues régulièrement avec des comptes rendus disponibles ? | F4: Pas | G4: Comptes rendus des réunions du comité | H4: Perte d’informations importantes et de décisions non formalisées | I4: elevée | J4: Impossibilité de tracer les décisions, risques juridiques, erreurs répétées. | K4: Utiliser un système de gestion documentaire centralisé et sécurisé.
D5: les membres doivent etre désignés pour participer | E5: Les membres désignés participent-ils activement aux réunions et décisions du comité ? | F5: Non | G5: Liste de présence et participation des membres désignés | H5: Mauvaise prise de décisions et inactivité du comité | I5: elevée | J5: Opportunités manquées, dégradation de la performance, démotivation des équipes. | K5: Définir un ordre du jour clair pour chaque réunion du comité et assurer le suivi des décisions.
D6: la direction doit valider l'existence du comité | E6: La direction a-t-elle officiellement validé l’existence du comité informatique ? | F6: Oui | G6: Validation officielle de la direction attestant l’existence du comité | H6: Manque de légitimité et de reconnaissance | I6: moyenne | J6: Non-respect des directives, difficulté à faire appliquer les règles, perte d’autorité. | K6: Valoriser les instances décisionnelles par des communications officielles et des résultats concrets.
C7: S’assurer de l’existence d'une politique relative aux applications | D7: Existence d’un document formalisé couvrant la politique des applications | E7: Un document formalisé sur la politique des applications existe-t-il ? | F7: Pas | G7: Document formalisé couvrant la politique des applications | H7: Gestion incohérente des applications | I7: moyenne | J7: Surcharge des systèmes, coûts supplémentaires, failles de sécurité. | K7: Centraliser la gestion des applications avec une politique cohérente de gouvernance IT.
D8: la politique doit etre alignée avec les objectifs de l'organisation | E8: La politique des applications est-elle alignée avec les objectifs stratégiques de l’organisation ? | F8: Non | G8: Rapport d’alignement de la politique avec les objectifs de l’organisation | H8: Non-conformité aux priorités stratégiques | I8: moyenne | J8: Investissements inutiles, désavantage concurrentiel, échec des transformations. | K8: Aligner les projets et décisions sur les orientations stratégiques régulièrement mises à jour.
D9: Date de dernière révision et mise à jour disponible | E9: La dernière révision de la politique est-elle documentée avec une mise à jour récente ? | F9: Oui | G9: Historique des révisions et mise à jour de la politique | H9: Utilisation de directives obsolètes | I9: moyenne | J9: Non-conformité réglementaire, processus inefficaces, risques juridiques. | K9: Établir un processus de mise à jour régulière des directives et politiques internes.
D10: les parties prenantes doivent avoir acces a la poitique | E10: La politique des applications est-elle accessible aux parties prenantes concernées ? | F10: Oui | G10: Document accessible détaillant la politique pour les parties prenantes | H10: Mauvaise compréhension ou application des directives | I10: moyenne | J10: Erreurs opérationnelles, non-atteinte des objectifs, sanctions. | K10: Organiser des sessions de formation et de sensibilisation sur les directives.
D11: Processus pour signaler et traiter les non-conformités | E11: Un processus est-il défini pour signaler et résoudre les cas de non-conformité ? | F11: Non | G11: Procédure formelle pour signaler et traiter les non-conformités | H11: Non-traitement des écarts détectés | I11: moyenne | J11: Aggravation des faiblesses, incidents majeurs, perte de crédibilité. | K11: Mettre en place un système de suivi et de traitement systématique des écarts.
C12: S’assurer que les rôle et responsabilités des utilisateurs sont bien définis | D12: un document listant les rôles et responsabilités des utilisateurs doit etre disponible | E12: Existe-t-il un document formel listant les rôles et responsabilités des utilisateurs ? | F12: Pas | G12: Document listant les rôles et responsabilités des utilisateurs | H12: Attribution incorrecte des tâches | I12: moyenne | J12: Surcharge ou sous-utilisation des compétences, baisse de productivité, turnover. | K12: Utiliser un outil de planification pour affecter les tâches de manière transparente et documentée.
D13: Communication formelle des responsabilités aux utilisateurs concernés | E13: Les responsabilités des utilisateurs sont-elles communiquées de manière formelle ? | F13: Oui | G13: Preuve de communication formelle des responsabilités aux utilisateurs | H13: Incompréhension ou mauvaises pratiques | I13: basse | J13: Violations de sécurité, non-respect des procédures. | K13: Renforcer la formation et le mentorat pour uniformiser la compréhension des processus.
D14: Documentation des autorisations doit etre spécifiques par rôle | E14: Les autorisations spécifiques pour chaque rôle sont-elles documentées ? | F14: Non | G14: Document de gestion des autorisations spécifiques par rôle | H14: Accès non autorisé ou contrôle inefficace | I14: moyenne | J14: Fuites de données, cyberattaques facilitées, sanctions légales. | K14: Renforcer les contrôles d’accès et revoir régulièrement les droits attribués.
D15: Fréquence des mises à jour des descriptions des rôles | E15: Les descriptions de rôles sont-elles mises à jour régulièrement ? | F15: Pas | G15: Journal des mises à jour des descriptions de rôles | H15: Confusion ou manque de pertinence des responsabilités | I15: moyenne | J15: Tâches non réalisées, retards dans les processus critiques. | K15: Définir des rôles précis et communiquer clairement sur les responsabilités.
D16: Existence de formations liées aux rôles utilisateurs | E16: Des formations sont-elles proposées pour les utilisateurs en fonction de leurs rôles ? | F16: Pas | G16: Programme de formation lié aux rôles des utilisateurs | H16: Faible adoption des outils ou erreurs d’utilisation | I16: moyenne | J16: ROI faible, données corrompues ou incomplètes. | K16: Former les utilisateurs aux outils et assurer un support technique accessible.
C17: S’assurer qu’une analyse des risques a été réalisée | D17: un document d’analyse des risques formalisé doit etre disponible | E17: Un document formalisé d’analyse des risques est-il disponible ? | F17: Oui | G17: Document formalisé d’analyse des risques | H17: Ignorance face aux menaces potentielles | I17: moyenne | J17: Incidents non anticipés, crises majeures. | K17: Organiser des formations régulières sur la cybersécurité et les menaces actuelles.
D18: les principaux risques liés aux applications doivent etre identifiés | E18: Les principaux risques associés aux applications ont-ils été identifiés ? | F18: Non | G18: Rapport d’identification des principaux risques | H18: Dommages non anticipés | I18: basse | J18: Coûts de réparation élevés, interruptions d’activité. | K18: Réaliser des analyses de risques régulières et mettre en place des mesures préventives.
D19: Documentation des mesures doit etre atténuée pour chaque risque | E19: Les mesures d’atténuation associées à chaque risque sont-elles documentées ? | F19: Oui | G19: Rapport de documentation des mesures d’atténuation pour chaque risque | H19: Exposition accrue aux menaces | I19: elevée | J19: Pertes financières, atteinte à la réputation. | K19: Mettre en œuvre des mécanismes de surveillance active et d’alerte rapide.
D20: les parties prenantes doivent valider l'analyse | E20: L’analyse des risques a-t-elle été validée par les parties prenantes ? | F20: Pas | G20: Validation des analyses par les parties prenantes | H20: Manque d’adhésion aux résultats | I20: moyenne | J20: Résistance au changement, échec des projets. | K20: Impliquer les parties prenantes dès le départ pour renforcer l’engagement.
D21: Calendrier de révision régulière de l’analyse des risques | E21: Un calendrier de révision régulière de l’analyse des risques est-il défini ? | F21: Non | G21: Calendrier de révision des analyses des risques | H21: Décisions basées sur des données périmées | I21: elevée | J21: Stratégies inefficaces, opportunités perdues. | K21: Mettre en place des tableaux de bord mis à jour en temps réel pour appuyer les décisions.
C22: S’assurer que le prolongement de l'analyse de risque et de son expansion ont été réalisés | D22: les nouveaux risques doivent etre identifiés suite à l’expansion | E22: Les nouveaux risques liés à l’expansion ont-ils été identifiés ? | F22: Oui | G22: Rapport d’identification des nouveaux risques suite à l’expansion | H22: Vulnérabilités inattendues | I22: elevée | J22: Incidents de sécurité non anticipés, exploitation des failles par des attaquants | K22: Effectuer des tests réguliers de sécurité et des audits de vulnérabilités.
D23: Documentation supplémentaire liée à l’analyse étendue | E23: Une documentation supplémentaire a-t-elle été réalisée pour l’analyse étendue ? | F23: Non | G23: Documentation complémentaire pour l’analyse étendue | H23: Évaluation incomplète | I23: moyenne | J23: Analyse partielle des risques, couverture insuffisante des menaces | K23: Structurer les évaluations autour de critères complets et validés par les experts.
D24: Validation officielle de l’analyse élargie | E24: L’analyse élargie a-t-elle été validée officiellement par les responsables ? | F24: Pas | G24: Validation officielle de l’analyse élargie | H24: Non-fiabilité des résultats | I24: elevée | J24: Conclusions erronées, fausse impression de sécurité | K24: Recouper les résultats par plusieurs méthodes pour assurer leur fiabilité.
D25: . Ajustements aux mesures d’atténuation en conséquence | E25: Les mesures d’atténuation ont-elles été ajustées en fonction des nouveaux risques ? | F25: Oui | G25: Preuve des ajustements des mesures d’atténuation | H25: Solutions inefficaces pour de nouveaux risques | I25: elevée | J25: Protection inadéquate, persistance des vulnérabilités | K25: Anticiper les nouveaux risques via une cellule de veille stratégique.
D26: Communication des mises à jour aux parties prenantes | E26: Les mises à jour de l’analyse des risques ont-elles été communiquées aux parties prenantes ? | F26: Non | G26: Communication des mises à jour des analyses de risques aux parties concernées | H26: Décisions non éclairées par les parties concernées | I26: elevée | J26: Choix stratégiques inappropriés, conflits organisationnels | K26: Impliquer toutes les parties concernées lors de la prise de décision.
C27: S’assurer que l’analyse et évaluation du niveau de sensibilité a été réalisée | D27: Classification formelle des données en termes de sensibilité | E27: Les données ont-elles été classifiées formellement en fonction de leur niveau de sensibilité ? | F27: Pas | G27: Rapport de classification formelle des données par niveau de sensibilité | H27: Violation de données sensibles | I27: elevée | J27: Sanctions réglementaires, atteinte à la réputation, perte financière | K27: Renforcer la sécurité des données avec chiffrement, journalisation et contrôle d’accès.
D28: Présence d’un rapport d’évaluation du niveau de sensibilité | E28: Un rapport d’évaluation du niveau de sensibilité est-il disponible ? | F28: Non | G28: Rapport d’évaluation du niveau de sensibilité | H28: Non-identification des vulnérabilités | I28: basse | J28: Détection tardive des faiblesses, augmentation des risques résiduels | K28: Réaliser des audits de sécurité pour détecter les vulnérabilités latentes.
D29: Validation de l’évaluation par la direction | E29: L’évaluation du niveau de sensibilité a-t-elle été validée par la direction ? | F29: Oui | G29: Validation officielle de l’évaluation par la direction | H29: Manque de soutien des décideurs | I29: basse | J29: Blocage des initiatives de sécurité, budgets insuffisants | K29: Promouvoir les résultats et bénéfices auprès des décideurs pour obtenir leur appui.
D30: Ajustements des contrôles de sécurité en fonction de l’analyse | E30: Les contrôles de sécurité ont-ils été ajustés en fonction des résultats de l’analyse ? | F30: Pas | G30: Rapport sur les ajustements des contrôles de sécurité basés sur l’analyse | H30: Exposition accrue aux menaces | I30: elevée | J30: Augmentation des attaques réussies, coûts de remediation élevés | K30: Mettre à jour les analyses de risques régulièrement avec des données actuelles
D31: Fréquence des mises à jour de l’évaluation | E31: La fréquence des mises à jour de l’évaluation est-elle respectée ? | F31: Oui | G31: Rapport des mises à jour de l’évaluation | H31: Décisions basées sur des informations obsolètes | I31: moyenne | J31: Stratégies inefficaces, opportunités manquées
C32: Vérifier l’existence d’un manuel d'administration de l'application | D32: Présence du manuel dans un référentiel officiel | E32: Le manuel est-il stocké dans un référentiel officiel ? | F32: Non | G32: Manuel stocké dans un référentiel officiel | H32: Accessibilité limitée au manuel | I32: basse | J32: Retards dans les interventions, difficultés opérationnelles | K32: Rendre le manuel accessible sur une plateforme numérique centralisée.
D33: Date de dernière mise à jour du manuel | E33: La date de dernière mise à jour du manuel est-elle documentée ? | F33: Pas | G33: Historique des mises à jour du manuel | H33: Utilisation d’informations désuètes | I33: basse | J33: Processus obsolètes, non-conformité aux standards actuels | K33: Mettre en place un processus de validation et d’actualisation des contenus.
D34: Existence d’une section pour les procédures critiques | E34: Une section pour les procédures critiques est-elle incluse dans le manuel ? | F34: Non | G34: Section dédiée aux procédures critiques dans le manuel | H34: Mauvaise gestion des situations d’urgence | I34: moyenne | J34: Réponse désorganisée aux crises, aggravation des incidents | K34: Définir un plan d’urgence clair avec rôles, procédures et contacts.
D35: Accessibilité du manuel aux administrateurs concernés | E35: Le manuel est-il accessible aux administrateurs concernés ? | F35: Oui | G35: Preuve d’accessibilité du manuel pour les administrateurs concernés | H35: Non-utilisation des directives | I35: elevée | J35: Non-respect des politiques, exposition juridique | K35: Intégrer les directives dans les processus quotidiens avec un suivi d’application.
D36: Validation du contenu par un expert technique | E36: Le contenu du manuel a-t-il été validé par un expert technique ? | F36: Non | G36: Validation du contenu du manuel par un expert technique | H36: Contenu erroné ou incomplet | I36: elevée | J36: Erreurs de jugement, actions inappropriées | K36: Mettre en place une validation systématique des contenus diffusés.
C37: Vérifier l’existence de procédures formalisées | D37: Documentation formelle des procédures applicables | E37: Les procédures applicables sont-elles documentées de manière formelle ? | F37: Pas | G37: Document formel des procédures applicables | H37: Pratiques non uniformisées | I37: elevée | J37: Incohérences opérationnelles, difficultés de collaboration | K37: Normaliser les pratiques à travers des procédures et des formations partagées.
D38: Mise à jour régulière des procédures | E38: Les procédures sont-elles mises à jour régulièrement ? | F38: Oui | G38: Historique des mises à jour régulières des procédures | H38: Incompatibilité avec les besoins actuels | I38: elevée | J38: Inadéquation avec l'environnement réel, gaspillage de ressources | K38: Réévaluer régulièrement les outils et procédures pour les adapter aux besoins.
D39: Validation des procédures par les responsables | E39: Les procédures ont-elles été validées par les responsables ? | F39: Non | G39: Validation des procédures par les responsables | H39: Non-respect des directives | I39: moyenne | J39: Violations réglementaires, risques légaux | K39: Effectuer des audits internes sur le respect des directives et corriger les écarts.
D40: Disponibilité des procédures pour les utilisateurs concernés | E40: Les procédures sont-elles disponibles pour les utilisateurs concernés ? | F40: Oui | G40: Documentation prouvant la disponibilité des procédures pour les utilisateurs concernés | H40: Mauvaise application des processus | I40: moyenne | J40: Défaillances opérationnelles, non-qualité | K40: Réaliser des contrôles qualité sur l'application des processus définis.
D41: Archivage des anciennes versions pour référence | E41: Les anciennes versions des procédures sont-elles archivées pour référence ? | F41: Pas | G41: Archivage des anciennes versions des procédures | H41: Perte de références historiques | I41: moyenne | J41: Impossibilité d'analyser les tendances, perte de contexte | K41: Archiver systématiquement les décisions et données clés pour référence future.
C42: S’assurer de l’existence et de la mise à disposition du compte rendu mensuel au propriétaire | D42: Présence d’un format standard pour les comptes rendus mensuels | E42: Un format standard pour les comptes rendus mensuels est-il disponible ? | F42: Non | G42: Format standard pour les comptes rendus mensuels | H42: Non-conformité dans les rapports | I42: moyenne | J42: Rejets par les auditeurs, problèmes de conformité | K42: Standardiser les formats de rapports et mettre en place un processus de relecture.
D43: Rédaction systématique des comptes rendus chaque mois | E43: Les comptes rendus sont-ils rédigés systématiquement chaque mois ? | F43: Oui | G43: Rapport de rédaction systématique des comptes rendus chaque mois | H43: Perte d’informations clés | I43: moyenne | J43: Décisions sans historique, répétition d'erreurs | K43: Sauvegarder les informations clés sur des supports sécurisés et redondants.
D44: Archivage des comptes rendus dans un référentiel dédié | E44: Les comptes rendus sont-ils archivés dans un référentiel dédié ? | F44: Pas | G44: Référentiel dédié à l’archivage des comptes rendus | H44: Non-référencement historique | I44: moyenne | J44: Absence de traçabilité, difficultés d'audit | K44: Intégrer un système de gestion des versions et d’archivage structuré.
D45: Accès garanti au propriétaire pour chaque compte rendu | E45: Le propriétaire a-t-il un accès garanti à chaque compte rendu ? | F45: Non | G45: Preuve d’accès garanti au propriétaire pour chaque compte rendu | H45: Manque de communication | I45: moyenne | J45: Désalignement des équipes, actions non coordonnées | K45: Mettre en place une stratégie de communication interne efficace et multicanal.
D46: Confirmation de réception par le propriétaire chaque mois | E46: La réception des comptes rendus par le propriétaire est-elle confirmée chaque mois ? | F46: Oui | G46: Confirmation de réception des comptes rendus par le propriétaire | H46: Malentendus ou omissions | I46: basse | J46: Incompréhensions, erreurs d'exécution | K46: Clarifier les messages et valider les communications pour éviter les erreurs.
B47: Application | C47: S'assurer que l'accès aux ressources de l'application (données et transactions) est restreint par un système de gestion d'accès | D47: Présence d’un système de gestion d’accès centralisé | E47: Un système de gestion d’accès centralisé est-il en place ? | F47: Non | G47: Rapport sur le système de gestion d’accès centralisé | H47: Accès non autorisé | I47: moyenne | J47: Fuites de données, compromission d'informations | K47: Restreindre l’accès aux informations selon des droits strictement définis.
D48: Documentation des autorisations d’accès par utilisateur | E48: Les autorisations d’accès par utilisateur sont-elles documentées ? | F48: Pas | G48: Documentation des autorisations d’accès par utilisateur | H48: Confusion ou d’abus | I48: moyenne | J48: Utilisation abusive des ressources, détournements | K48: Créer un registre des accès et sensibiliser aux bonnes pratiques d’utilisation.
D49: Mise à jour régulière des droits d’accès | E49: Les droits d’accès sont-ils mis à jour régulièrement ? | F49: Oui | G49: Journal des mises à jour régulières des droits d’accès | H49: Permissions obsolètes ou inappropriées | I49: moyenne | J49: Privilèges excessifs, accès injustifiés aux systèmes sensibles | K49: Réviser régulièrement les permissions selon les besoins et responsabilités.
D50: Validation des accès par la direction | E50: Les accès sont-ils validés par la direction ? | F50: Non | G50: Validation des accès par la direction | H50: Mauvaise gestion des privilèges | I50: moyenne | J50: Accès non autorisés, permissions excessives, abus de droits | K50: Implémenter un processus formel de gestion des privilèges utilisateurs.
D51: Suivi des modifications des accès aux ressources | E51: Les modifications des accès aux ressources sont-elles suivies ? | F51: Pas | G51: Journal de suivi des modifications des accès aux ressources | H51: Contrôle insuffisant | I51: basse | J51: Failles non détectées, violations de sécurité persistantes | K51: Mettre en place un mécanisme de contrôle interne régulier et automatisé.
C52: S’assurer qu’une procédure de gestion des profils utilisateurs existe | D52: Existence d’un document formalisé des profils utilisateurs | E52: Un document formalisé des profils utilisateurs existe-t-il ? | F52: Oui | G52: Document formalisé des profils utilisateurs | H52: Gestion inefficace des utilisateurs | I52: elevée | J52: Comptes obsolètes actifs, accès non révoqués | K52: Définir clairement les rôles et responsabilités des utilisateurs dans un référentiel.
D53: Processus de création, modification et suppression des profils | E53: Un processus de création, modification et suppression des profils est-il défini ? | F53: Non | G53: Procédure formelle de création, modification et suppression des profils | H53: Désorganisation | I53: moyenne | J53: Confusion dans les accès, responsabilités floues | K53: Structurer les processus et documenter les procédures pour améliorer l’organisation.
D54: Validation des profils par les parties prenantes | E54: Les profils utilisateurs ont-ils été validés par les parties prenantes ? | F54: Oui | G54: Validation des profils par les parties prenantes | H54: Permissions incorrectes | I54: elevée | J54: Accès injustifiés à des données sensibles | K54: Réaliser une revue périodique des permissions attribuées aux utilisateurs.
D55: Suivi des modifications des profils utilisateurs | E55: Les modifications des profils utilisateurs sont-elles suivies ? | F55: Pas | G55: Journal de suivi des modifications des profils utilisateurs | H55: Non-conformité ou perte de traçabilité | I55: elevée | J55: Sanctions légales, impossibilité d'auditer les actions | K55: Implémenter un système de traçabilité centralisé et sécurisé.
D56: Formation des administrateurs sur la gestion des profils | E56: Les administrateurs ont-ils reçu une formation sur la gestion des profils ? | F56: Non | G56: Rapport de formation des administrateurs sur la gestion des profils | H56: Erreurs de gestion des profils | I56: moyenne | J56: Droits inadaptés aux besoins réels | K56: Assurer un processus formalisé de gestion des profils avec vérification.
C57: Vérifier que l’identification des utilisateurs est réalisée | D57: Utilisation de techniques d’authentification (ex. identifiant unique) | E57: Des techniques d’authentification, comme un identifiant unique, sont-elles utilisées ? | F57: Oui | G57: Rapport décrivant les techniques d’authentification utilisées | H57: Usurpation d’identité | I57: elevée | J57: Accès frauduleux, actions malveillantes au nom d'un utilisateur légitime | K57: Activer une authentification forte et surveiller les comportements suspects.
D58: Documentation des processus d’identification des utilisateurs | E58: Les processus d’identification des utilisateurs sont-ils documentés ? | F58: Pas | G58: Documentation des processus d’identification des utilisateurs | H58: Gestion inadéquate des accès | I58: elevée | J58: Exposition accrue aux menaces internes/externes | K58: Mettre en place un système de gestion des accès basé sur les rôles (RBAC).
D59: Validation des identifiants par l’administration | E59: Les identifiants des utilisateurs sont-ils validés par l’administration ? | F59: Non | G59: Validation des identifiants par l’administration | H59: Erreurs ou abus | I59: elevée | J59: Modifications non autorisées, fuites de données | K59: Sensibiliser les utilisateurs et intégrer des alertes sur les activités anormales.
D60: Fréquence des audits sur le processus d’identification | E60: Le processus d’identification est-il audité régulièrement ? | F60: Oui | G60: Rapport des audits réguliers sur le processus d’identification | H60: Failles non détectées | I60: elevée | J60: Exploitation par des attaquants, incidents majeurs | K60: Effectuer régulièrement des audits de sécurité pour identifier les failles.
D61: Suivi des tentatives d’usurpation d’identité | E61: Le suivi des tentatives d’usurpation d’identité est-il assuré ? | F61: Non | G61: Rapport de suivi des tentatives d’usurpation d’identité | H61: Sécurité compromise | I61: basse | J61: Perte de confidentialité/intégrité des données | K61: Renforcer les mesures de sécurité physique et logique sur les systèmes critiques.
C62: Vérifier qu’un mot de passe est associé à l'identifiant | D62: Présence obligatoire d’un mot de passe pour chaque utilisateur | E62: Un mot de passe est-il obligatoire pour chaque utilisateur ? | F62: Pas | G62: Preuve de la présence obligatoire d’un mot de passe pour chaque utilisateur | H62: Accès non sécurisé | I62: basse | J62: Interceptions de données, attaques MITM | K62: Sécuriser les connexions via des protocoles chiffrés et des firewalls.
D63: Respect des critères de complexité des mots de passe | E63: Les critères de complexité des mots de passe sont-ils respectés ? | F63: Oui | G63: Document décrivant les critères de complexité des mots de passe | H63: Mot de passe vulnérable | I63: elevée | J63: Piratage de comptes par force brute | K63: Appliquer une politique de mots de passe complexes et renouvelables.
D64: Fréquence de mise à jour des mots de passe | E64: La fréquence de mise à jour des mots de passe est-elle suffisante ? | F64: Non | G64: Rapport de mise à jour des mots de passe | H64: Usurpation via des mots de passe obsolètes | I64: elevée | J64: Accès avec d'anciens identifiants non révoqués | K64: Désactiver les comptes utilisant d’anciens mots de passe non conformes.
D65: Suivi des tentatives de connexion avec des mots de passe incorrects | E65: Le suivi des tentatives de connexion avec des mots de passe incorrects est-il effectué ? | F65: Pas | G65: Journal des tentatives de connexion avec des mots de passe incorrects | H65: Tentatives non détectées | I65: elevée | J65: Attaques réussies faute d'alertes | K65: Mettre en œuvre un système de détection d’intrusion avec alertes automatisées.
D66: Sensibilisation des utilisateurs aux bonnes pratiques de mot de passe | E66: Les utilisateurs sont-ils sensibilisés aux bonnes pratiques de mot de passe ? | F66: Non | G66: Programme de sensibilisation aux bonnes pratiques de mot de passe | H66: Comportements à risque des utilisateurs | I66: elevée | J66: Partage de comptes, négligence sécuritaire | K66: Former les utilisateurs à adopter de bonnes pratiques de cybersécurité.
C67: S’assurer que les tentatives de connexions infructueuses à l'application sont suivies | D67: Enregistrement des tentatives de connexion infructueuses | E67: Les tentatives de connexion infructueuses sont-elles enregistrées ? | F67: Oui | G67: Journal des tentatives de connexion infructueuses | H67: Diagnostics incomplets | I67: elevée | J67: Évaluations erronées des vulnérabilités | K67: Documenter tous les diagnostics et analyses dans un système de gestion des incidents.
D68: Analyse régulière des logs de connexion | E68: Les logs de connexion sont-ils analysés régulièrement ? | F68: Pas | G68: Rapport d’analyse régulière des logs de connexion | H68: Menaces non identifiées | I68: moyenne | J68: Exposition à des attaques connues non corrigées | K68: Effectuer une veille de sécurité pour identifier les nouvelles menaces.
D69: Signalement des anomalies détectées aux responsables | E69: Les anomalies détectées sont-elles signalées aux responsables ? | F69: Oui | G69: Signalements des anomalies détectées aux responsables | H69: Réponses inappropriées | I69: moyenne | J69: Aggravation des incidents, temps d'indisponibilité accru | K69: Élaborer un plan de réponse aux incidents avec des scénarios types.
D70: Présence d’un seuil de blocage après plusieurs tentatives échouées | E70: Un seuil de blocage est-il appliqué après plusieurs tentatives échouées ? | F70: Non | G70: Rapport définissant le seuil de blocage après plusieurs tentatives échouées | H70: Attaques persistantes | I70: moyenne | J70: Pénétration prolongée dans le système | K70: Mettre en place un système de surveillance continue et de réaction rapide.
D71: Mise en œuvre de mesures correctives pour les connexions suspectes | E71: Des mesures correctives pour les connexions suspectes sont-elles mises en œuvre ? | F71: Pas | G71: Plan d’action pour corriger les connexions suspectes | H71: Sécurité altérée | I71: moyenne | J71: Perte de confiance des parties prenantes | K71: Réviser les modèles d’accès régulièrement pour garantir leur pertinence.
C72: S’assurer que l'accès aux données et aux transactions de l’application est géré | D72: Utilisation de profils d’accès différenciés (par rôle) | E72: Des profils d’accès différenciés (par rôle) sont-ils utilisés ? | F72: Oui | G72: Documentation des profils d’accès différenciés (par rôle) | H72: Permissions inappropriées | I72: moyenne | J72: Accès excessifs ou insuffisants | K72: Centraliser les données critiques avec des sauvegardes régulières.
D73: Documentation des processus de gestion des accès | E73: Les processus de gestion des accès sont-ils documentés ? | F73: Non | G73: Manuel des processus de gestion des accès | H73: Confusion ou perte d’information | I73: moyenne | J73: Erreurs humaines, pertes de données | K73: Automatiser la détection des failles avec des outils spécialisés.
D74: Fréquence des audits des accès aux données et transactions | E74: Les accès aux données et transactions font-ils l’objet d’audits réguliers ? | F74: Pas | G74: Rapport des audits des accès aux données et transactions | H74: Failles non détectées | I74: moyenne | J74: Droits incohérents avec les rôles | K74: Revoir l’attribution des permissions après chaque changement organisationnel.
D75: Validation des droits d’accès par les parties prenantes | E75: Les droits d’accès ont-ils été validés par les parties prenantes ? | F75: Non | G75: Validation des droits d’accès par les parties prenantes | H75: Permissions mal attribuées | I75: basse | J75: Fuites d'informations sensibles | K75: Chiffrer les données sensibles et contrôler leur accès avec des journaux d’audit.
D76: Présence de systèmes de contrôle pour limiter les accès non autorisés | E76: Des systèmes de contrôle sont-ils en place pour limiter les accès non autorisés ? | F76: Oui | G76: Documentation des systèmes de contrôle pour limiter les accès non autorisés | H76: Violation des données | I76: moyenne | J76: Incapacité à investiguer les incidents | K76: Intégrer une solution de journalisation systématique pour chaque action utilisateur.
C77: Vérifier l’existence de pistes d’audit sur le système d’administration de l’application | D77: Activation des pistes d’audit dans le système | E77: Les pistes d’audit sont-elles activées dans le système ? | F77: Pas | G77: Rapport d’activation des pistes d’audit dans le système | H77: Traçabilité impossible | I77: moyenne | J77: Difficulté à analyser les tendances passées | K77: Automatiser les scans de vulnérabilités sur les systèmes critiques.
D78: Fréquence des analyses des pistes d’audit | E78: Les pistes d’audit sont-elles analysées régulièrement ? | F78: Oui | G78: Rapport des analyses régulières des pistes d’audit | H78: Failles non détectées | I78: moyenne | J78: Répétition des mêmes incidents | K78: Archiver systématiquement les décisions et événements de sécurité.
D79: Conservation des logs d’audit pendant une période définie | E79: Les logs d’audit sont-ils conservés pendant une période définie ? | F79: Non | G79: Logs d’audit conservés sur une période définie | H79: Absence de références historiques | I79: moyenne | J79: Données corrompues ou falsifiées | K79: Valider toutes les réponses via des processus de test avant déploiement.
D80: Signalement des anomalies détectées dans les audits | E80: Les anomalies détectées dans les audits sont-elles signalées ? | F80: Pas | G80: Signalements des anomalies détectées dans les audits | H80: Réponses inappropriées | I80: basse | J80: Prise de décision sur des bases erronées | K80: Mettre à jour les protocoles de réponse aux incidents selon les retours d’expérience.
D81: Présence d’un processus d’escalade pour les violations détectées | E81: Un processus d’escalade est-il en place pour les violations détectées ? | F81: Non | G81: Procédure d’escalade pour les violations détectées | H81: Réponses inefficaces | I81: elevée | J81: Dysfonctionnements opérationnels | K81: Mettre en place des protocoles de réponse standardisés et des formations régulières pour améliorer l'efficacité.
C82: Vérifier que tous les documents servant de base à la saisie sont pris en compte | D82: Documentation formelle des documents nécessaires à la saisie | E82: Les documents nécessaires à la saisie sont-ils documentés formellement ? | F82: Oui | G82: Documentation formelle des documents nécessaires à la saisie | H82: Erreurs dans les entrées | I82: moyenne | J82: Données erronées dans le système | K82: Utiliser des outils de validation automatisée pour détecter et corriger les erreurs dans les entrées de données.
D83: Validation des documents par les responsables | E83: Les documents utilisés pour la saisie ont-ils été validés par les responsables ? | F83: Non | G83: Validation officielle des documents par les responsables | H83: Inexactitudes dans les données | I83: elevée | J83: Informations inexactes affectant les décisions | K83: Implémenter des processus de vérification croisée pour garantir l'exactitude des données.
D84: Contrôle de l’intégrité des documents avant la saisie | E84: L’intégrité des documents est-elle contrôlée avant la saisie ? | F84: Pas | G84: Rapport de contrôle de l’intégrité des documents avant saisie | H84: Données incorrectes | I84: elevée | J84: Bases de données ou rapports falsifiés | K84: Appliquer des règles de gouvernance des données et des audits réguliers pour identifier les données incorrectes.
D85: Conservation des documents pour vérification ultérieure | E85: Les documents sont-ils conservés pour vérification ultérieure ? | F85: Oui | G85: Archives des documents pour vérification ultérieure | H85: Perte d’historique | I85: moyenne | J85: Impossibilité de consulter les actions passées | K85: Sauvegarder régulièrement les données et conserver un journal des modifications pour éviter la perte d'historique.
D86: Fréquence des mises à jour des documents utilisés | E86: Les documents utilisés sont-ils mis à jour régulièrement ? | F86: Non | G86: Rapport des mises à jour régulières des documents utilisés | H86: Informations obsolètes | I86: elevée | J86: Prise de décision sur des informations non actualisées | K86: Mettre à jour périodiquement les informations et automatiser les alertes pour les données obsolètes.
C87: S’assurer que les facilités de saisie, l’ergonomie de la saisie, les messages écrans et les contrôles sont mis en œuvre | D87: Tests réguliers de l’ergonomie des interfaces | E87: Des tests réguliers de l’ergonomie des interfaces sont-ils effectués ? | F87: Oui | G87: Rapport des tests réguliers de l’ergonomie des interfaces | H87: Expérience utilisateur médiocre | I87: elevée | J87: Frustration des utilisateurs, abandon des outils | K87: Concevoir des interfaces intuitives et recueillir des feedbacks utilisateurs pour améliorer l'expérience.
D88: Présence de messages d’erreur descriptifs à l’écran | E88: Des messages d’erreur descriptifs sont-ils présents à l’écran ? | F88: Pas | G88: Capture des messages d’erreur descriptifs affichés à l’écran | H88: Confusion pour l’utilisateur | I88: elevée | J88: Difficultés d'utilisation, erreurs répétées | K88: Simplifier les processus et fournir des guides clairs pour réduire la confusion des utilisateurs.
D89: Documentation des contrôles intégrés dans les interfaces | E89: Les contrôles intégrés dans les interfaces sont-ils documentés ? | F89: Non | G89: Documentation des contrôles intégrés dans les interfaces | H89: Failles et erreurs | I89: elevée | J89: Vulnérabilités exploitables dans le système | K89: Effectuer des tests de sécurité réguliers et corriger les failles et erreurs identifiées.
D90: Formation des utilisateurs sur les outils de saisie | E90: Les utilisateurs reçoivent-ils une formation sur les outils de saisie ? | F90: Oui | G90: Rapport de formation des utilisateurs sur les outils de saisie | H90: Mauvaises pratiques | I90: basse | J90: Maintien de méthodes non optimales | K90: Établir des bonnes pratiques documentées et former les équipes pour éviter les mauvaises pratiques.
D91: Collecte des retours utilisateurs pour améliorer les interfaces | E91: Les retours des utilisateurs sont-ils collectés pour améliorer les interfaces ? | F91: Pas | G91: Rapport de collecte des retours utilisateurs pour améliorer les interfaces | H91: Absence d’amélioration continue | I91: basse | J91: Stagnation des processus, pas d'optimisation | K91: Adopter une approche itérative avec des revues périodiques pour assurer l'amélioration continue.
B92: Fonction informatique | C92: S’assurer que les tâches relatives au développement et à l'exploitation de l'application sont bien suivies et documentées ; | D92: Disponibilité d’un journal de suivi des tâches | E92: Un journal de suivi des tâches est-il disponible ? | F92: Non | G92: Journal de suivi des tâches disponibles | H92: Perte de traçabilité | I92: elevée | J92: Impossibilité de retracer les actions et modifications | K92: Utiliser des systèmes de journalisation pour assurer la traçabilité des actions et modifications.
D93: Fréquence des mises à jour du journal de suivi | E93: Le journal de suivi des tâches est-il mis à jour régulièrement ? | F93: Oui | G93: Rapport des mises à jour régulières du journal de suivi | H93: Informations périmées | I93: moyenne | J93: Utilisation d'informations non valides | K93: Automatiser la détection et le remplacement des informations périmées.
D94: Documentation des processus liés au développement et à l'exploitation | E94: Les processus liés au développement et à l'exploitation sont-ils documentés ? | F94: Non | G94: Document décrivant les processus liés au développement et à l’exploitation | H94: Confusion et inefficacité | I94: basse | J94: Désorganisation, perte de temps | K94: Clarifier les rôles et responsabilités pour éviter la confusion et améliorer l'efficacité.
D95: Validation des tâches par les responsables | E95: Les tâches sont-elles validées par les responsables ? | F95: Pas | G95: Validation des tâches par les responsables | H95: Mauvaise coordination | I95: basse | J95: Actions non coordonnées entre services | K95: Mettre en place des outils de collaboration et des réunions de synchronisation pour une meilleure coordination.
D96: Archivage des anciennes tâches pour référence future | E96: Les anciennes tâches sont-elles archivées pour référence future ? | F96: Oui | G96: Archives des anciennes tâches pour référence future | H96: Perte d’historique | I96: moyenne | J96: Absence d'archivage des activités passées | K96: Protéger l'historique des modifications avec des sauvegardes et des accès sécurisés.
C97: S’assurer que l'accès aux bibliothèques de production est réglementé | D97: Documentation des droits d’accès aux bibliothèques de production | E97: Les droits d’accès aux bibliothèques de production sont-ils documentés ? | F97: Non | G97: Documentation des droits d’accès aux bibliothèques de production | H97: Confusion ou d’abus | I97: elevée | J97: Utilisation abusive des ressources | K97: Sensibiliser les utilisateurs et mettre en place des mécanismes de surveillance pour prévenir les abus.
D98: Présence d’un système de gestion des accès | E98: Un système de gestion des accès est-il en place pour les bibliothèques de production ? | F98: Pas | G98: Rapport sur la présence d’un système de gestion des accès | H98: Accès non autorisé | I98: elevée | J98: Accès illégitimes à des données sensibles | K98: Restreindre les accès avec des politiques de permissions strictes et des audits réguliers.
D99: Validation des autorisations par les responsables | E99: Les autorisations d’accès aux bibliothèques de production ont-elles été validées par les responsables ? | F99: Oui | G99: Validation des autorisations par les responsables | H99: Mauvaise gestion des droits | I99: elevée | J99: Droits d'accès mal attribués | K99: Réviser régulièrement les droits d'accès et former les gestionnaires à une meilleure gestion des droits.
D100: Fréquence des audits des accès | E100: Les audits des accès aux bibliothèques de production sont-ils réalisés régulièrement ? | F100: Non | G100: Rapport des audits réguliers des accès | H100: Failles non détectées | I100: elevée | J100: Vulnérabilités persistantes non corrigées | K100: Implémenter des systèmes de détection d'intrusions et des analyses de vulnérabilités pour identifier les failles.
...

Sheet COSO
A1: Domaines | B1: Points de contrôle | C1: Objectifs de contrôle | D1: Critères d'évaluation | E1: Questions d'évaluation | F1: Réponses | G1: Documents requis | H1: Risques | I1: Criticité | J1: Conséquences | K1: Recommandations
A2: Environnement de contrôle | B2: Engagement envers l’intégrité et les valeurs éthiques | C2: S’assurer que l'organisation dispose d'une charte éthique formelle qui couvre l'ensemble des pratiques professionnelles et des interactions au sein de l'organisation, y compris les activités liées aux systèmes d'information. | D2: La charte éthique est disponible et accessible à tous les employés (ex : intranet, affichage). | E2: La charte éthique est-elle disponible et accessible à tous les employés (ex : intranet, affichage) ? | F2: Non | G2: Charte éthique officielle | H2: absence de validation par les instances dirigeantes | I2: Elevée | J2: Décisions sans valeur légale | K2: Validation systématique par le service juridique
F3: Non | G3: Preuve de diffusion (intranet/affichage) | H3: non-conformité aux réglementations en vigueur | I3: Elevée | J3: Amendes et pénalités financières | K3: Audit mensuel des obligations réglementaires
D4: La charte couvre explicitement les pratiques professionnelles et les interactions internes. | E4: La charte couvre-t-elle explicitement les pratiques professionnelles et les interactions internes ? | F4: Non | G4: Manuel des procédures internes | H4: diffusion incomplète ou inégale au sein de l'organisation | I4: Elevée | J4: Certains services mal informés | K4: Mise en place d'un circuit d'information officiel
F5: Non | G5: Guide des bonnes pratiques | H5: interprétations divergentes des collaborateurs | I5: Elevée | J5: Chacun applique à sa manière | K5: Élaboration de protocoles standardisés
D6: La charte mentionne spécifiquement les activités liées aux systèmes d’information. | E6: La charte mentionne-t-elle spécifiquement les activités liées aux systèmes d’information ? | F6: Non | G6: Politique SI annexée à la charte | H6: obsolescence des processus décrits | I6: Elevée | J6: Procédures qui ne fonctionnent plus | K6: Revue trimestrielle des procédures opérationnelles
F7: Non | G7: Procès-verbal du COMEX | H7: inadaptation aux réalités opérationnelles | I7: Elevée | J7: Incompatibilité avec le travail réel | K7: Alignement des règles sur les pratiques terrain
D8: La charte a été officiellement approuvée par la direction (ex : signature, date). | E8: La charte a-t-elle été officiellement approuvée par la direction (ex : signature, date) ? | F8: Non | G8: Registre des mises à jour | H8: non-intégration des mises à jour réglementaires | I8: Elevée | J8: Problèmes avec les autorités | K8: Consultation préalable des autorités compétentes
F9: Non | G9: Historique des versions | H9: absence de traçabilité des modifications | I9: Elevée | J9: Impossible de retracer les changements | K9: Implémentation d'un journal des modifications
D10: La charte est régulièrement mise à jour pour rester pertinente. | E10: La charte est-elle régulièrement mise à jour pour rester pertinente ? | F10: Non | G10: Registre des signatures employés | H10: falsification ou usage frauduleux des signatures | I10: Elevée | J10: Risque de fraude immédiat | K10: Contrôles aléatoires antifraude
F11: Non | G11: Procédure d'engagement | H11: ambiguïté dans les obligations contractuelles | I11: Elevée | J11: Litiges avec les partenaires | K11: Clauses contractuelles détaillées et actualisées
C12: Vérifier que des mécanismes existent pour garantir que tous les acteurs (employés, partenaires, prestataires) respectent cette charte éthique dans leurs activités professionnelles, y compris dans leur utilisation des systèmes d'information. | D12: Tous les employés ont signé un engagement à respecter la charte éthique. | E12: Tous les employés ont-ils signé un engagement à respecter la charte éthique ? | F12: Non | G12: Clause éthique des contrats partenaires | H12: défaut de preuve de réception par les parties prenantes | I12: Elevée | J12: Impossible de prouver la réception | K12: Système d'accusé de réception électronique
F13: Non | G13: Preuve de transmission | H13: non-respect des fréquences de rappel prévues | I13: Elevée | J13: Oublis des obligations importantes | K13: Checklists automatisées pour les obligations légales
D14: Les partenaires et prestataires ont reçu une copie de la charte éthique. | E14: Les partenaires et prestataires ont-ils reçu une copie de la charte éthique ? | F14: Non | G14: Planning des rappels éthiques | H14: messages incohérents ou contradictoires | I14: Elevée | J14: Messages contradictoires entre services | K14: Messagerie unifiée pour les communications internes
F15: Non | G15: Supports de communication interne | H15: vulnérabilité aux représailles en cas de signalement | I15: Elevée | J15: Peur de parler par crainte de représailles | K15: Dispositif de signalement anonyme et sécurisé
D16: Des rappels réguliers sur la charte éthique sont envoyés aux employés (ex : mails, affichage). | E16: Des rappels réguliers sur la charte éthique sont-ils envoyés aux employés (ex : mails, affichage) ? | F16: Non | G16: Procédure de signalement | H16: compétences insuffisantes des référents désignés | I16: Elevée | J16: Référents qui donnent de mauvais conseils | K16: Validation hiérarchique des conseils des référents
F17: Non | G17: Liste des référents éthiques | H17: cas pratiques non représentatifs des risques réels | I17: Elevée | J17: Formations qui ne préparent pas au réel | K17: Formations basées sur des cas pratiques
D18: Un point de contact est disponible pour signaler les écarts éthiques (ex : email, hotline). | E18: Un point de contact est-il disponible pour signaler les écarts éthiques (ex : email, hotline) ? | F18: Non | G18: Recueil de cas pratiques | H18: perte d'accès aux documents historiques | I18: Elevée | J18: Documents anciens introuvables | K18: Archivage numérique sécurisé des documents
F19: Non | G19: Archives des communications | H19: inadéquation des bonnes pratiques avec la culture d'entreprise | I19: Elevée | J19: Bonnes pratiques rejetées par les équipes | K19: Concertation avec les équipes pour les bonnes pratiques
D20: Des exemples de bonnes pratiques éthiques sont partagés régulièrement avec les équipes. | E20: Des exemples de bonnes pratiques éthiques sont-ils partagés régulièrement avec les équipes ? | F20: Non | G20: Recueil des bonnes pratiques éthiques | H20: décisions non ratifiées par les instances compétentes | I20: Elevée | J20: Décisions qui tiennent pas la route | K20: Revue collégiale des décisions stratégiques
F21: Non | G21: Procès-verbal du dernier comité éthique | H21: formations non adaptées aux publics cibles | I21: Elevée | J21: Formations inutiles pour les métiers | K21: Formations adaptées aux besoins opérationnels
C22: S’assurer que des actions de sensibilisation, telles que des formations régulières, sont mises en place pour garantir que tous les employés et intervenants comprennent et appliquent les principes éthiques dans leurs interactions avec les systèmes d'information. | D22: Des formations sur l’éthique et les systèmes d’information sont proposées régulièrement aux employés. | E22: Des formations sur l’éthique et les systèmes d’information sont-elles proposées régulièrement aux employés ? | F22: Non | G22: Catalogue des formations en éthique | H22: annulation répétée des sessions prévues | I22: Elevée | J22: Sessions annulées en dernière minute | K22: Calendrier annuel fixe des sessions de formation
F23: Non | G23: Planning des sessions 2024 | H23: participation insuffisante aux sensibilisations | I23: Elevée | J23: Personne ne vient aux formations | K23: Obligation de participation avec suivi RH
D24: Un calendrier des sessions de sensibilisation est disponible et communiqué à tous. | E24: Un calendrier des sessions de sensibilisation est-il disponible et communiqué à tous ? | F24: Non | G24: Calendrier officiel des sensibilisations | H24: canal de communication non sécurisé | I24: Elevée | J24: Données qui fuient par des canaux non sécurisés | K24: Cryptage des données et canaux sécurisés
F25: Non | G25: Procédure de communication interne | H25: non-complétion du module par les nouveaux arrivants | I25: Elevée | J25: Nouveaux arrivants pas formés correctement | K25: Programme de tutorat pour les nouveaux arrivants
D26: Les nouveaux employés suivent une formation obligatoire sur la charte éthique lors de leur intégration. | E26: Les nouveaux employés suivent-ils une formation obligatoire sur la charte éthique lors de leur intégration ? | F26: Non | G26: Module d'introduction obligatoire | H26: suivi irrégulier des intégrations | I26: Elevée | J26: Intégration mal suivie | K26: Checklist d'intégration avec suivi RH
F27: Non | G27: Fiche de suivi des nouveaux employés | H27: directives trop génériques pour guider l'action | I27: Elevée | J27: Consignes trop vagues pour agir | K27: Rédaction de consignes opérationnelles claires
D28: Des supports de sensibilisation (ex : guides, vidéos) sont accessibles à tous les employés. | E28: Des supports de sensibilisation (ex : guides, vidéos) sont-ils accessibles à tous les employés ? | F28: Non | G28: Guide des bonnes pratiques éthiques | H28: indisponibilité technique de la plateforme | I28: Elevée | J28: Outils techniques qui plantent | K28: Maintenance préventive des outils informatiques
F29: Non | G29: Plateforme de ressources numériques | H29: données de participation erronées ou incomplètes | I29: Elevée | J29: Données fausses dans les rapports | K29: Vérification croisée des données avant publication
D30: Un taux de participation aux formations est mesuré et partagé avec la direction. | E30: Un taux de participation aux formations est-il mesuré et partagé avec la direction ? | F30: Non | G30: Tableau de bord des participations | H30: retard dans la remontée d'information à la direction | I30: Elevée | J30: Retards dans les prises de décision | K30: Délégation de pouvoir pour les décisions urgentes
F31: Non | G31: Rapport trimestriel à la direction | H31: procédure de signalement trop complexe | I31: Elevée | J31: Procédures trop compliquées pour signaler | K31: Simplification des procédures de remontée d'alertes
C32: S’assurer que l'organisation dispose d'un mécanisme de suivi et de gestion des violations éthiques, permettant de détecter, traiter et sanctionner tout comportement contraire à la charte éthique, y compris dans le cadre des activités liées aux systèmes d'information. | D32: Un canal de signalement des violations éthiques est accessible à tous (ex : hotline, boîte mail dédiée). | E32: Un canal de signalement des violations éthiques est-il accessible à tous (ex : hotline, boîte mail dédiée) ? | F32: Non | G32: Procédure de signalement écrite | H32: référents éthiques surchargés ou indisponibles | I32: Elevée | J32: Référents injoignables ou débordés | K32: Plages horaires dédiées pour les référents
F33: Non | G33: Liste des référents éthiques | H33: centralisation défaillante des signalements | I33: Elevée | J33: Signalements qui se perdent | K33: Système de ticketing avec suivi obligatoire
D34: Les violations signalées sont documentées et suivies dans un registre ou une base de données. | E34: Les violations signalées sont-elles documentées et suivies dans un registre ou une base de données ? | F34: Oui | G34: Registre central des signalements | H34: faille de confidentialité dans la base d'incidents | I34: Elevée | J34: Fuites d'informations confidentielles | K34: Protocole de gestion des documents confidentiels
F35: Oui | G35: Base de données des incidents | H35: partialité ou manque d'objectivité dans les enquêtes | I35: Elevée | J35: Enquêtes pas objectives | K35: Recours à des enquêteurs externes indépendants
D36: Des procédures claires définissent les étapes de traitement des violations (détection, enquête, sanction). | E36: Des procédures claires définissent-elles les étapes de traitement des violations (détection, enquête, sanction) ? | F36: Oui | G36: Protocole d'enquête interne | H36: sanctions incohérentes avec les manquements | I36: Elevée | J36: Sanctions disproportionnées ou absentes | K36: Grille de sanctions proportionnelle et transparente
F37: Oui | G37: Grille des sanctions types | H37: absence de suivi des sanctions prononcées | I37: Elevée | J37: Pas de suivi des punitions | K37: Suivi informatisé des mesures disciplinaires
D38: Des sanctions sont appliquées en cas de violation avérée et documentées. | E38: Des sanctions sont-elles appliquées en cas de violation avérée et documentées ? | F38: Oui | G38: Recueil des sanctions appliquées | H38: archivage non sécurisé des décisions sensibles | I38: Elevée | J38: Décisions sensibles mal protégées | K38: Classement sécurisé des décisions sensibles
F39: Oui | G39: Archives des décisions | H39: indicateurs non alignés sur les objectifs éthiques | I39: Elevée | J39: Indicateurs qui ne reflètent pas la réalité | K39: Audit externe des indicateurs clés
D40: Un rapport régulier sur les violations et leur gestion est partagé avec la direction. | E40: Un rapport régulier sur les violations et leur gestion est-il partagé avec la direction ? | F40: Oui | G40: Rapport annuel d'activité éthique | H40: communication édulcorée vers les instances dirigeantes | I40: Elevée | J40: Direction mal informée des vrais problèmes | K40: Remontée hebdomadaire des alertes terrain
F41: Oui | G41: Synthèse pour le conseil d'administration | H41: faille dans la distribution des documents clés | I41: Elevée | J41: Documents importants mal distribués | K41: Circuit contrôlé de distribution documentaire
C42: Vérifier que tous les employés ont reçu une copie de la charte éthique (par mail ou papier) et confirmer qu’ils l’ont bien reçue. | D42: Une copie de la charte éthique a été envoyée à tous les employés par mail ou remise en main propre. | E42: Une copie de la charte éthique a-t-elle été envoyée à tous les employés par mail ou remise en main propre ? | F42: Oui | G42: Preuve de distribution collective | H42: liste des destinataires non actualisée | I42: Elevée | J42: Listes de diffusion pas à jour | K42: Mise à jour mensuelle des listes de contacts
F43: Oui | G43: Liste de diffusion complète | H43: signature non vérifiée des accords confidentiels | I43: Elevée | J43: Signatures non vérifiées sur contrats | K43: Vérification systématique des signatures
D44: Un accusé de réception ou une confirmation écrite de chaque employé est disponible. | E44: Un accusé de réception ou une confirmation écrite de chaque employé est-il disponible ? | F44: Oui | G44: Registre des accords de confidentialité | H44: non-conservation des attestations individuelles | I44: Elevée | J44: Attestations perdues | K44: Double archivage physique/numérique des attestations
F45: Oui | G45: Dossiers individuels signés | H45: charte d'intégration non adaptée aux métiers | I45: Elevée | J45: Charte inadaptée aux différents métiers | K45: Chartes métiers avec exemples concrets
D46: Les nouveaux employés reçoivent la charte éthique lors de leur intégration. | E46: Les nouveaux employés reçoivent-ils la charte éthique lors de leur intégration ? | F46: Oui | G46: Charte d'intégration des nouveaux employés | H46: preuve de distribution non vérifiable | I46: Elevée | J46: Impossible de prouver qui a reçu quoi | K46: Registre électronique des accusés de réception
F47: Oui | G47: Registre de distribution signé | H47: base de données des destinataires corrompue | I47: Elevée | J47: Base de données des contacts corrompue | K47: Purge et sécurisation de la base de contacts
D48: Un registre centralisé recense les employés ayant reçu la charte éthique. | E48: Un registre centralisé recense-t-il les employés ayant reçu la charte éthique ? | F48: Oui | G48: Base de données des destinataires | H48: absence de preuve de réception collective | I48: Elevée | J48: Pas de preuve que tout le monde a bien reçu | K48: Confirmation écrite obligatoire pour les envois importants
F49: Oui | G49: Attestation de réception collective | H49: programmation des rappels non respectée | I49: Elevée | J49: Rappels qui ne sont pas faits à temps | K49: Alertes automatiques pour les échéances réglementaires
D50: Des rappels périodiques sont envoyés pour s’assurer que la charte reste accessible et connue. | E50: Des rappels périodiques sont-ils envoyés pour s’assurer que la charte reste accessible et connue ? | F50: Oui | G50: Programmation des rappels éthiques | H50: perte des historiques de communication | I50: Elevée | J50: Historique des échanges perdu | K50: Centralisation des échanges officiels
F51: Oui | G51: Archive des communications envoyées | H51: conflits d'intérêts non déclarés des administrateurs | I51: Elevée | J51: Problèmes d'objectivité chez les décideurs | K51: Formation des décideurs à l'analyse objective
B52: Le Conseil fait preuve d’indépendance vis-à-vis du management | C52: S’assurer que le Conseil est composé de membres indépendants du management, avec une structure de gouvernance claire garantissant cette indépendance. | D52: La majorité des membres du Conseil sont indépendants et n’occupent pas de fonctions opérationnelles dans l’organisation. | E52: La majorité des membres du Conseil sont-ils indépendants et n’occupent-ils pas de fonctions opérationnelles dans l’organisation ? | F52: Oui | G52: Liste actualisée des administrateurs | H52: procédure de nomination non transparente | I52: Elevée | J52: Décisions de nomination contestables | K52: Publication des critères de nomination
F53: Oui | G53: Procès-verbal de nomination récent | H53: déclaration d'indépendance falsifiée | I53: Elevée | J53: Fausses déclarations passant inaperçues | K53: Contrôle aléatoire des déclarations
D54: Les membres indépendants sont identifiés et listés dans les documents officiels du Conseil. | E54: Les membres indépendants sont-ils identifiés et listés dans les documents officiels du Conseil ? | F54: Oui | G54: Déclaration d'indépendance signée | H54: registre des intérêts non mis à jour | I54: Elevée | J54: Conflits d'intérêts non détectés | K54: Obligation de déclaration d'intérêts
F55: Oui | G55: Registre des liens d'intérêts | H55: critères d'indépendance trop subjectifs | I55: Elevée | J55: Jugements basés sur des opinions personnelles | K55: Grilles d'évaluation standardisées
D56: Une politique écrite définit les critères d’indépendance des membres du Conseil. | E56: Une politique écrite définit-elle les critères d’indépendance des membres du Conseil ? | F56: Oui | G56: Document cadre d'indépendance | H56: grille d'évaluation biaisée ou partiale | I56: Elevée | J56: Évaluations injustes dès le départ | K56: Formation aux biais cognitifs
F57: Oui | G57: Grille d'évaluation validée | H57: omission de déclarations d'intérêts | I57: Elevée | J57: Intérêts cachés influençant les décisions | K57: Médiation professionnelle pour les conflits
D58: Les conflits d’intérêts potentiels des membres du Conseil sont déclarés et documentés. | E58: Les conflits d’intérêts potentiels des membres du Conseil sont-ils déclarés et documentés ? | F58: Oui | G58: Formulaire de déclaration d'intérêts | H58: gestion opaque des conflits déclarés | I58: Elevée | J58: Conflits mal gérés créant des tensions | K58: Audit terrain des processus réels
F59: Oui | G59: Registre des conflits déclarés | H59: gouvernance en décalage avec les pratiques réelles | I59: Elevée | J59: Règles écrites différentes de la réalité | K59: Mise à jour trimestrielle de l'organigramme
D60: La structure de gouvernance est clairement définie et accessible (ex : organigramme, charte de gouvernance). | E60: La structure de gouvernance est-elle clairement définie et accessible (ex : organigramme, charte de gouvernance) ? | F60: Oui | G60: Charte de gouvernance en vigueur | H60: organigramme non reflétant les circuits de décision | I60: Elevée | J60: Organigramme inutile car inexact | K60: Checklists de vérification systématiques
F61: Oui | G61: Organigramme certifié par la direction | H61: contrôles internes insuffisants ou absents | I61: Elevée | J61: Problèmes non détectés par manque de vérification | K61: Cellule de crise pour les urgences opérationnelles
C62: Vérifier que le Conseil dispose des ressources et des informations nécessaires pour surveiller efficacement la mise en place et le bon fonctionnement du dispositif de contrôle interne. | D62: Le Conseil reçoit régulièrement des rapports détaillés sur l’état du contrôle interne. | E62: Le Conseil reçoit-il régulièrement des rapports détaillés sur l’état du contrôle interne ? | F62: Oui | G62: Rapport mensuel de contrôle interne | H62: points critiques non adressés dans les délais | I62: Elevée | J62: Urgences traitées en retard | K62: Évaluation pratique des formations dirigeants
F63: Oui | G63: Synthèse des points critiques | H63: plan de formation du Conseil irréaliste | I63: Elevée | J63: Formations du Conseil inefficaces | K63: Validation des supports par les utilisateurs
D64: Les membres du Conseil ont accès à des formations ou ressources pour comprendre les enjeux du contrôle interne. | E64: Les membres du Conseil ont-ils accès à des formations ou ressources pour comprendre les enjeux du contrôle interne ? | F64: Oui | G64: Plan de formation du Conseil | H64: ressources pédagogiques inadaptées | I64: Elevée | J64: Supports de formation inutilisables | K64: Alertes automatiques sur les dépassements budgétaires
F65: Oui | G65: Catalogue des ressources pédagogiques | H65: dépassement systématique du budget alloué | I65: Elevée | J65: Dépenses dépassant toujours le budget | K65: Double signature pour les engagements financiers
D66: Un budget spécifique est alloué au Conseil pour soutenir ses activités de surveillance. | E66: Un budget spécifique est-il alloué au Conseil pour soutenir ses activités de surveillance ? | F66: Oui | G66: Budget approuvé du Conseil | H66: dépenses non autorisées ou non justifiées | I66: Elevée | J66: Argent dépensé sans autorisation | K66: Appel d'offres obligatoire pour les consultants
F67: Oui | G67: Détail des dépenses autorisées | H67: recours abusif à des experts externes | I67: Elevée | J67: Trop dépendant des consultants externes | K67: Vérification des compétences des prestataires
D68: Le Conseil a accès à des experts indépendants (ex : auditeurs, consultants) si nécessaire. | E68: Le Conseil a-t-il accès à des experts indépendants (ex : auditeurs, consultants) si nécessaire ? | F68: Oui | G68: Protocole de recours aux experts | H68: compétences des consultants non vérifiées | I68: Elevée | J68: Experts pas compétents utilisés | K68: Traçage des modifications décisionnelles
F69: Oui | G69: Répertoire des consultants habilités | H69: décisions non enregistrées ou modifiées a posteriori | I69: Elevée | J69: Décisions modifiées après coup | K69: Validation des PV dans les 48 heures
D70: Les décisions et recommandations du Conseil sont documentées et suivies dans un registre officiel. | E70: Les décisions et recommandations du Conseil sont-elles documentées et suivies dans un registre officiel ? | F70: Oui | G70: Registre officiel des décisions | H70: comptes-rendus non validés par les participants | I70: Elevée | J70: Procès-verbaux non approuvés | K70: Contrôles inopinés par l'audit interne
F71: Oui | G71: Compte-rendu de réunion signé | H71: évaluation des contrôles superficielle ou biaisée | I71: Elevée | J71: Contrôles mal faits ou bidons | K71: Recoupement des indicateurs avec les données terrain
C72: S’assurer que le Conseil reçoit régulièrement des rapports détaillés sur l’efficacité du dispositif de contrôle interne et qu'il est impliqué dans l’évaluation des résultats des audits internes. | D72: Des rapports sur l’efficacité du contrôle interne sont présentés au Conseil à intervalles réguliers (ex : trimestriellement). | E72: Des rapports sur l’efficacité du contrôle interne sont-ils présentés au Conseil à intervalles réguliers (ex : trimestriellement) ? | F72: Oui | G72: Évaluation trimestrielle du contrôle interne | H72: KPI non pertinents ou mal mesurés | I72: Elevée | J72: Indicateurs qui ne reflètent pas la réalité | K72: Audit trimestriel des indicateurs par des experts externes
F73: Oui | G73: Tableau de bord des KPI | H73: écarts répétés non corrigés | I73: Elevée | J73: Problèmes qui reviennent sans cesse | K73: Analyse root cause systématique des problèmes récurrents
D74: Les rapports incluent des indicateurs clés de performance (KPI) et des analyses des écarts identifiés. | E74: Les rapports incluent-ils des indicateurs clés de performance (KPI) et des analyses des écarts identifiés ? | F74: Oui | G74: Analyse des écarts constatés | H74: plan correctif inapplicable ou inefficace | I74: Elevée | J74: Solutions proposées qui ne marchent pas | K74: Tests pilotes obligatoires avant déploiement des solutions
F75: Oui | G75: Plan correctif approuvé | H75: conclusions d'audit ignorées ou minimisées | I75: Elevée | J75: Recommandations d'audit ignorées | K75: Tableau de suivi mensuel des recommandations d'audit
D76: Le Conseil participe activement à l’examen des résultats des audits internes lors de ses réunions. | E76: Le Conseil participe-t-il activement à l’examen des résultats des audits internes lors de ses réunions ? | F76: Oui | G76: Relevé de conclusions d'audit | H76: légitimité des participants non vérifiée | I76: Elevée | J76: Participants aux réunions pas légitimes | K76: Vérification des habilitations avant chaque réunion
F77: Oui | G77: Liste des participants certifiée | H77: retard dans la mise en œuvre des recommandations | I77: Elevée | J77: Retards dans l'application des décisions | K77: Mise en place d'un système de suivi des décisions
D78: Les décisions et recommandations du Conseil suite à ces rapports sont documentées et suivies. | E78: Les décisions et recommandations du Conseil suite à ces rapports sont-elles documentées et suivies ? | F78: Oui | G78: Suivi des recommandations clés | H78: suivi des actions correctives non priorisé | I78: Elevée | J78: Priorités mal définies dans les corrections | K78: Matrice de priorisation claire pour les corrections
F79: Oui | G79: Fiche de progression hebdomadaire | H79: procédures de mise en œuvre trop rigides | I79: Elevée | J79: Procédures trop rigides bloquant l'action | K79: Assouplissement contrôlé des procédures critiques
D80: Un processus formel garantit que les actions correctives recommandées par le Conseil sont mises en œuvre. | E80: Un processus formel garantit-il que les actions correctives recommandées par le Conseil sont mises en œuvre ? | F80: Oui | G80: Procédure de mise en œuvre | H80: échéances constamment repoussées | I80: Elevée | J80: Délais jamais respectés | K80: Sanctions pour retard répété dans les délais
F81: Oui | G81: Échéancier des actions correctives | H81: orientations stratégiques floues ou contradictoires | I81: Elevée | J81: Stratégie floue ou contradictoire | K81: Elaboration d'une stratégie écrite et partagée
C82: Vérifier que le Conseil joue un rôle actif dans la définition des objectifs et des critères de performance du contrôle interne, et qu’il veille à leur alignement avec les objectifs stratégiques de l’organisation. | D82: Le Conseil participe à des réunions dédiées pour définir les objectifs du contrôle interne. | E82: Le Conseil participe-t-il à des réunions dédiées pour définir les objectifs du contrôle interne ? | F82: Oui | G82: Procès-verbal de réunion stratégique | H82: objectifs annuels non chiffrés ou non mesurables | I82: Elevée | J82: Objectifs pas clairs ou pas mesurables | K82: Définition d'objectifs SMART mesurables
F83: Oui | G83: Document d'objectifs annuels validé | H83: cadre de référence non partagé ou mal compris | I83: Elevée | J83: Personne ne comprend les référentiels | K83: Formation obligatoire aux référentiels
D84: Les objectifs du contrôle interne sont explicitement alignés avec les objectifs stratégiques de l’organisation. | E84: Les objectifs du contrôle interne sont-ils explicitement alignés avec les objectifs stratégiques de l’organisation ? | F84: Oui | G84: Cadre de référence stratégique | H84: matrice d'alignement non actualisée | I84: Elevée | J84: Outils d'alignement pas à jour | K84: Mise à jour semestrielle des outils d'alignement
F85: Oui | G85: Matrice d'alignement actualisée | H85: critères de performance subjectifs ou opaques | I85: Elevée | J85: Évaluations basées sur des critères flous | K85: Grilles d'évaluation standardisées et transparentes
D86: Les critères de performance du contrôle interne sont documentés et approuvés par le Conseil. | E86: Les critères de performance du contrôle interne sont-ils documentés et approuvés par le Conseil ? | F86: Oui | G86: Grille d'évaluation de performance | H86: validation formelle contournée ou ignorée | I86: Elevée | J86: Validations obligatoires contournées | K86: Contrôle aléatoire des validations obligatoires
F87: Oui | G87: Protocole de validation formelle | H87: écarts stratégiques non identifiés ou reportés | I87: Elevée | J87: Problèmes stratégiques non vus | K87: Revue stratégique trimestrielle par la direction
D88: Le Conseil examine régulièrement l’alignement entre les objectifs du contrôle interne et la stratégie globale. | E88: Le Conseil examine-t-il régulièrement l’alignement entre les objectifs du contrôle interne et la stratégie globale ? | F88: Oui | G88: Rapport d'alignement stratégique | H88: ajustements non validés par les instances compétentes | I88: Moyenne | J88: Ajustements pas validés officiellement | K88: Procédure officielle pour les ajustements
F89: Oui | G89: Proposition d'ajustements validée | H89: modifications non documentées ou non communiquées | I89: Moyenne | J89: Changements pas écrits ni communiqués | K89: Journal centralisé des changements
D90: Les ajustements proposés par le Conseil sont mis en œuvre et documentés. | E90: Les ajustements proposés par le Conseil sont-ils mis en œuvre et documentés ? | F90: Oui | G90: Journal des modifications approuvées | H90: déploiement inégal selon les entités | I90: Moyenne | J90: Application différente selon les services | K90: Harmonisation inter-services des pratiques
F91: Oui | G91: Preuve de déploiement effectif | H91: anomalies récurrentes non traitées | I91: Moyenne | J91: Problèmes récurrents non réglés | K91: Plan d'action priorisé avec responsables désignés
C92: S’assurer que le Conseil prend des mesures appropriées lorsque des dysfonctionnements ou des lacunes dans le contrôle interne sont identifiés, y compris la mise en place de plans d’action correctifs. | D92: Les dysfonctionnements ou lacunes identifiés sont documentés et présentés au Conseil. | E92: Les dysfonctionnements ou lacunes identifiés sont-ils documentés et présentés au Conseil ? | F92: Oui | G92: Registre des anomalies identifiées | H92: classification des risques erronée ou obsolète | I92: Moyenne | J92: Risques mal classés | K92: Actualisation mensuelle de la cartographie des risques
F93: Oui | G93: Classement par niveau de risque | H93: plans d'action non datés ou non suivis | I93: Moyenne | J93: Plans d'action sans date précise | K93: Fiches actions avec échéances contraignantes
D94: Le Conseil valide des plans d’action correctifs pour chaque problème identifié. | E94: Le Conseil valide-t-il des plans d’action correctifs pour chaque problème identifié ? | F94: Oui | G94: Plan d'action correctif daté | H94: calendrier de résolution non contraignant | I94: Moyenne | J94: Calendrier de résolution pas respecté | K94: Points hebdomadaires de suivi des résolutions
F95: Oui | G95: Calendrier de résolution contraignant | H95: responsabilités mal définies ou non assumées | I95: Moyenne | J95: Personne ne sait qui doit faire quoi | K95: Désignation claire des responsables
D96: Les responsables de la mise en œuvre des plans d’action sont clairement désignés. | E96: Les responsables de la mise en œuvre des plans d’action sont-ils clairement désignés ? | F96: Oui | G96: Désignation officielle des responsables | H96: missions mal définies ou hors périmètre | I96: Moyenne | J96: Missions pas claires ou hors cadre | K96: Cadrage écrit des missions et périmètres
F97: Oui | G97: Fiche de mission contresignée | H97: suivi opérationnel négligé ou falsifié | I97: Moyenne | J97: Suivi bâclé ou truqué | K97: Audit aléatoire des processus de suivi
D98: Un suivi régulier des plans d’action est effectué et partagé avec le Conseil. | E98: Un suivi régulier des plans d’action est-il effectué et partagé avec le Conseil ? | F98: Oui | G98: Tableau de suivi opérationnel | H98: rapports d'état incomplets ou trompeurs | I98: Moyenne | J98: Rapports incomplets ou faux | K98: Modèles de rapports standardisés obligatoires
F99: Oui | G99: Rapport d'état hebdomadaire | H99: corrections partielles ou non vérifiées | I99: Moyenne | J99: Corrections faites à moitié | K99: Validation externe des corrections implémentées
D100: Les résultats des actions correctives sont évalués et documentés dans les rapports du Conseil. | E100: Les résultats des actions correctives sont-ils évalués et documentés dans les rapports du Conseil ? | F100: Oui | G100: Bilan des corrections implémentées | H100: gains surestimés ou non pérennes | I100: Moyenne | J100: Bénéfices annoncés mais pas réels | K100: Mesure concrète des bénéfices obtenus
...

Sheet 4.1.Appli_En_Service
A1: Domaine | B1: Points de contrôle | C1: Objectifs de contrôle | D1: Critères d'évaluation | E1: Questions d'évaluation | F1: Réponses | G1: Documents requis | H1: Risques | I1: Criticité | J1: Conséquences | K1: Recommandations
A2: Application en service | B2: Organisation | C2: S’assurer de l’existence d'un comité informatique | D2: organigramme officiel doit inclure le comité informatique | E2: L'organigramme officiel inclut-il clairement le comité informatique ? | F2: Oui | G2: Organigramme officiel incluant le comité informatique | H2: Manque de coordination et de gouvernance | I2: elevée | J2: Décisions incohérentes, retards dans les projets, conflits entre équipes, perte de confiance des parties prenantes. | K2: Mettre en place une structure de gouvernance claire avec des rôles définis et des réunions régulières.
D3: Documentation formelle doit décrire les responsabilités du comité | E3: Les responsabilités du comité informatique sont-elles documentées de manière formelle ? | F3: Non | G3: Document formel décrivant les responsabilités du comité | H3: Confusion et chevauchement des tâches | I3: elevée | J3: Gaspillage de ressources, frustration des employés, responsabilités floues, omissions critiques. | K3: Clarifier les responsabilités via des fiches de poste et des procédures documentées.
D4: réunions frequentes et compte doivent etre rendus disponibles | E4: Les réunions du comité informatique sont-elles tenues régulièrement avec des comptes rendus disponibles ? | F4: Pas | G4: Comptes rendus des réunions du comité | H4: Perte d’informations importantes et de décisions non formalisées | I4: elevée | J4: Impossibilité de tracer les décisions, risques juridiques, erreurs répétées. | K4: Utiliser un système de gestion documentaire centralisé et sécurisé.
D5: les membres doivent etre désignés pour participer | E5: Les membres désignés participent-ils activement aux réunions et décisions du comité ? | F5: Non | G5: Liste de présence et participation des membres désignés | H5: Mauvaise prise de décisions et inactivité du comité | I5: elevée | J5: Opportunités manquées, dégradation de la performance, démotivation des équipes. | K5: Définir un ordre du jour clair pour chaque réunion du comité et assurer le suivi des décisions.
D6: la direction doit valider l'existence du comité | E6: La direction a-t-elle officiellement validé l’existence du comité informatique ? | F6: Oui | G6: Validation officielle de la direction attestant l’existence du comité | H6: Manque de légitimité et de reconnaissance | I6: moyenne | J6: Non-respect des directives, difficulté à faire appliquer les règles, perte d’autorité. | K6: Valoriser les instances décisionnelles par des communications officielles et des résultats concrets.
C7: S’assurer de l’existence d'une politique relative aux applications | D7: Existence d’un document formalisé couvrant la politique des applications | E7: Un document formalisé sur la politique des applications existe-t-il ? | F7: Pas | G7: Document formalisé couvrant la politique des applications | H7: Gestion incohérente des applications | I7: moyenne | J7: Surcharge des systèmes, coûts supplémentaires, failles de sécurité. | K7: Centraliser la gestion des applications avec une politique cohérente de gouvernance IT.
D8: la politique doit etre alignée avec les objectifs de l'organisation | E8: La politique des applications est-elle alignée avec les objectifs stratégiques de l’organisation ? | F8: Non | G8: Rapport d’alignement de la politique avec les objectifs de l’organisation | H8: Non-conformité aux priorités stratégiques | I8: moyenne | J8: Investissements inutiles, désavantage concurrentiel, échec des transformations. | K8: Aligner les projets et décisions sur les orientations stratégiques régulièrement mises à jour.
D9: Date de dernière révision et mise à jour disponible | E9: La dernière révision de la politique est-elle documentée avec une mise à jour récente ? | F9: Oui | G9: Historique des révisions et mise à jour de la politique | H9: Utilisation de directives obsolètes | I9: moyenne | J9: Non-conformité réglementaire, processus inefficaces, risques juridiques. | K9: Établir un processus de mise à jour régulière des directives et politiques internes.
D10: les parties prenantes doivent avoir acces a la poitique | E10: La politique des applications est-elle accessible aux parties prenantes concernées ? | F10: Oui | G10: Document accessible détaillant la politique pour les parties prenantes | H10: Mauvaise compréhension ou application des directives | I10: moyenne | J10: Erreurs opérationnelles, non-atteinte des objectifs, sanctions. | K10: Organiser des sessions de formation et de sensibilisation sur les directives.
D11: Processus pour signaler et traiter les non-conformités | E11: Un processus est-il défini pour signaler et résoudre les cas de non-conformité ? | F11: Non | G11: Procédure formelle pour signaler et traiter les non-conformités | H11: Non-traitement des écarts détectés | I11: moyenne | J11: Aggravation des faiblesses, incidents majeurs, perte de crédibilité. | K11: Mettre en place un système de suivi et de traitement systématique des écarts.
C12: S’assurer que les rôle et responsabilités des utilisateurs sont bien définis | D12: un document listant les rôles et responsabilités des utilisateurs doit etre disponible | E12: Existe-t-il un document formel listant les rôles et responsabilités des utilisateurs ? | F12: Pas | G12: Document listant les rôles et responsabilités des utilisateurs | H12: Attribution incorrecte des tâches | I12: moyenne | J12: Surcharge ou sous-utilisation des compétences, baisse de productivité, turnover. | K12: Utiliser un outil de planification pour affecter les tâches de manière transparente et documentée.
D13: Communication formelle des responsabilités aux utilisateurs concernés | E13: Les responsabilités des utilisateurs sont-elles communiquées de manière formelle ? | F13: Oui | G13: Preuve de communication formelle des responsabilités aux utilisateurs | H13: Incompréhension ou mauvaises pratiques | I13: basse | J13: Violations de sécurité, non-respect des procédures. | K13: Renforcer la formation et le mentorat pour uniformiser la compréhension des processus.
D14: Documentation des autorisations doit etre spécifiques par rôle | E14: Les autorisations spécifiques pour chaque rôle sont-elles documentées ? | F14: Non | G14: Document de gestion des autorisations spécifiques par rôle | H14: Accès non autorisé ou contrôle inefficace | I14: moyenne | J14: Fuites de données, cyberattaques facilitées, sanctions légales. | K14: Renforcer les contrôles d’accès et revoir régulièrement les droits attribués.
D15: Fréquence des mises à jour des descriptions des rôles | E15: Les descriptions de rôles sont-elles mises à jour régulièrement ? | F15: Pas | G15: Journal des mises à jour des descriptions de rôles | H15: Confusion ou manque de pertinence des responsabilités | I15: moyenne | J15: Tâches non réalisées, retards dans les processus critiques. | K15: Définir des rôles précis et communiquer clairement sur les responsabilités.
D16: Existence de formations liées aux rôles utilisateurs | E16: Des formations sont-elles proposées pour les utilisateurs en fonction de leurs rôles ? | F16: Pas | G16: Programme de formation lié aux rôles des utilisateurs | H16: Faible adoption des outils ou erreurs d’utilisation | I16: moyenne | J16: ROI faible, données corrompues ou incomplètes. | K16: Former les utilisateurs aux outils et assurer un support technique accessible.
C17: S’assurer qu’une analyse des risques a été réalisée | D17: un document d’analyse des risques formalisé doit etre disponible | E17: Un document formalisé d’analyse des risques est-il disponible ? | F17: Oui | G17: Document formalisé d’analyse des risques | H17: Ignorance face aux menaces potentielles | I17: moyenne | J17: Incidents non anticipés, crises majeures. | K17: Organiser des formations régulières sur la cybersécurité et les menaces actuelles.
D18: les principaux risques liés aux applications doivent etre identifiés | E18: Les principaux risques associés aux applications ont-ils été identifiés ? | F18: Non | G18: Rapport d’identification des principaux risques | H18: Dommages non anticipés | I18: basse | J18: Coûts de réparation élevés, interruptions d’activité. | K18: Réaliser des analyses de risques régulières et mettre en place des mesures préventives.
D19: Documentation des mesures doit etre atténuée pour chaque risque | E19: Les mesures d’atténuation associées à chaque risque sont-elles documentées ? | F19: Oui | G19: Rapport de documentation des mesures d’atténuation pour chaque risque | H19: Exposition accrue aux menaces | I19: elevée | J19: Pertes financières, atteinte à la réputation. | K19: Mettre en œuvre des mécanismes de surveillance active et d’alerte rapide.
D20: les parties prenantes doivent valider l'analyse | E20: L’analyse des risques a-t-elle été validée par les parties prenantes ? | F20: Pas | G20: Validation des analyses par les parties prenantes | H20: Manque d’adhésion aux résultats | I20: moyenne | J20: Résistance au changement, échec des projets. | K20: Impliquer les parties prenantes dès le départ pour renforcer l’engagement.
D21: Calendrier de révision régulière de l’analyse des risques | E21: Un calendrier de révision régulière de l’analyse des risques est-il défini ? | F21: Non | G21: Calendrier de révision des analyses des risques | H21: Décisions basées sur des données périmées | I21: elevée | J21: Stratégies inefficaces, opportunités perdues. | K21: Mettre en place des tableaux de bord mis à jour en temps réel pour appuyer les décisions.
C22: S’assurer que le prolongement de l'analyse de risque et de son expansion ont été réalisés | D22: les nouveaux risques doivent etre identifiés suite à l’expansion | E22: Les nouveaux risques liés à l’expansion ont-ils été identifiés ? | F22: Oui | G22: Rapport d’identification des nouveaux risques suite à l’expansion | H22: Vulnérabilités inattendues | I22: elevée | J22: Incidents de sécurité non anticipés, exploitation des failles par des attaquants | K22: Effectuer des tests réguliers de sécurité et des audits de vulnérabilités.
D23: Documentation supplémentaire liée à l’analyse étendue | E23: Une documentation supplémentaire a-t-elle été réalisée pour l’analyse étendue ? | F23: Non | G23: Documentation complémentaire pour l’analyse étendue | H23: Évaluation incomplète | I23: moyenne | J23: Analyse partielle des risques, couverture insuffisante des menaces | K23: Structurer les évaluations autour de critères complets et validés par les experts.
D24: Validation officielle de l’analyse élargie | E24: L’analyse élargie a-t-elle été validée officiellement par les responsables ? | F24: Pas | G24: Validation officielle de l’analyse élargie | H24: Non-fiabilité des résultats | I24: elevée | J24: Conclusions erronées, fausse impression de sécurité | K24: Recouper les résultats par plusieurs méthodes pour assurer leur fiabilité.
D25: . Ajustements aux mesures d’atténuation en conséquence | E25: Les mesures d’atténuation ont-elles été ajustées en fonction des nouveaux risques ? | F25: Oui | G25: Preuve des ajustements des mesures d’atténuation | H25: Solutions inefficaces pour de nouveaux risques | I25: elevée | J25: Protection inadéquate, persistance des vulnérabilités | K25: Anticiper les nouveaux risques via une cellule de veille stratégique.
D26: Communication des mises à jour aux parties prenantes | E26: Les mises à jour de l’analyse des risques ont-elles été communiquées aux parties prenantes ? | F26: Non | G26: Communication des mises à jour des analyses de risques aux parties concernées | H26: Décisions non éclairées par les parties concernées | I26: elevée | J26: Choix stratégiques inappropriés, conflits organisationnels | K26: Impliquer toutes les parties concernées lors de la prise de décision.
C27: S’assurer que l’analyse et évaluation du niveau de sensibilité a été réalisée | D27: Classification formelle des données en termes de sensibilité | E27: Les données ont-elles été classifiées formellement en fonction de leur niveau de sensibilité ? | F27: Pas | G27: Rapport de classification formelle des données par niveau de sensibilité | H27: Violation de données sensibles | I27: elevée | J27: Sanctions réglementaires, atteinte à la réputation, perte financière | K27: Renforcer la sécurité des données avec chiffrement, journalisation et contrôle d’accès.
D28: Présence d’un rapport d’évaluation du niveau de sensibilité | E28: Un rapport d’évaluation du niveau de sensibilité est-il disponible ? | F28: Non | G28: Rapport d’évaluation du niveau de sensibilité | H28: Non-identification des vulnérabilités | I28: basse | J28: Détection tardive des faiblesses, augmentation des risques résiduels | K28: Réaliser des audits de sécurité pour détecter les vulnérabilités latentes.
D29: Validation de l’évaluation par la direction | E29: L’évaluation du niveau de sensibilité a-t-elle été validée par la direction ? | F29: Oui | G29: Validation officielle de l’évaluation par la direction | H29: Manque de soutien des décideurs | I29: basse | J29: Blocage des initiatives de sécurité, budgets insuffisants | K29: Promouvoir les résultats et bénéfices auprès des décideurs pour obtenir leur appui.
D30: Ajustements des contrôles de sécurité en fonction de l’analyse | E30: Les contrôles de sécurité ont-ils été ajustés en fonction des résultats de l’analyse ? | F30: Pas | G30: Rapport sur les ajustements des contrôles de sécurité basés sur l’analyse | H30: Exposition accrue aux menaces | I30: elevée | J30: Augmentation des attaques réussies, coûts de remediation élevés | K30: Mettre à jour les analyses de risques régulièrement avec des données actuelles
D31: Fréquence des mises à jour de l’évaluation | E31: La fréquence des mises à jour de l’évaluation est-elle respectée ? | F31: Oui | G31: Rapport des mises à jour de l’évaluation | H31: Décisions basées sur des informations obsolètes | I31: moyenne | J31: Stratégies inefficaces, opportunités manquées
C32: Vérifier l’existence d’un manuel d'administration de l'application | D32: Présence du manuel dans un référentiel officiel | E32: Le manuel est-il stocké dans un référentiel officiel ? | F32: Non | G32: Manuel stocké dans un référentiel officiel | H32: Accessibilité limitée au manuel | I32: basse | J32: Retards dans les interventions, difficultés opérationnelles | K32: Rendre le manuel accessible sur une plateforme numérique centralisée.
D33: Date de dernière mise à jour du manuel | E33: La date de dernière mise à jour du manuel est-elle documentée ? | F33: Pas | G33: Historique des mises à jour du manuel | H33: Utilisation d’informations désuètes | I33: basse | J33: Processus obsolètes, non-conformité aux standards actuels | K33: Mettre en place un processus de validation et d’actualisation des contenus.
D34: Existence d’une section pour les procédures critiques | E34: Une section pour les procédures critiques est-elle incluse dans le manuel ? | F34: Non | G34: Section dédiée aux procédures critiques dans le manuel | H34: Mauvaise gestion des situations d’urgence | I34: moyenne | J34: Réponse désorganisée aux crises, aggravation des incidents | K34: Définir un plan d’urgence clair avec rôles, procédures et contacts.
D35: Accessibilité du manuel aux administrateurs concernés | E35: Le manuel est-il accessible aux administrateurs concernés ? | F35: Oui | G35: Preuve d’accessibilité du manuel pour les administrateurs concernés | H35: Non-utilisation des directives | I35: elevée | J35: Non-respect des politiques, exposition juridique | K35: Intégrer les directives dans les processus quotidiens avec un suivi d’application.
D36: Validation du contenu par un expert technique | E36: Le contenu du manuel a-t-il été validé par un expert technique ? | F36: Non | G36: Validation du contenu du manuel par un expert technique | H36: Contenu erroné ou incomplet | I36: elevée | J36: Erreurs de jugement, actions inappropriées | K36: Mettre en place une validation systématique des contenus diffusés.
C37: Vérifier l’existence de procédures formalisées | D37: Documentation formelle des procédures applicables | E37: Les procédures applicables sont-elles documentées de manière formelle ? | F37: Pas | G37: Document formel des procédures applicables | H37: Pratiques non uniformisées | I37: elevée | J37: Incohérences opérationnelles, difficultés de collaboration | K37: Normaliser les pratiques à travers des procédures et des formations partagées.
D38: Mise à jour régulière des procédures | E38: Les procédures sont-elles mises à jour régulièrement ? | F38: Oui | G38: Historique des mises à jour régulières des procédures | H38: Incompatibilité avec les besoins actuels | I38: elevée | J38: Inadéquation avec l'environnement réel, gaspillage de ressources | K38: Réévaluer régulièrement les outils et procédures pour les adapter aux besoins.
D39: Validation des procédures par les responsables | E39: Les procédures ont-elles été validées par les responsables ? | F39: Non | G39: Validation des procédures par les responsables | H39: Non-respect des directives | I39: moyenne | J39: Violations réglementaires, risques légaux | K39: Effectuer des audits internes sur le respect des directives et corriger les écarts.
D40: Disponibilité des procédures pour les utilisateurs concernés | E40: Les procédures sont-elles disponibles pour les utilisateurs concernés ? | F40: Oui | G40: Documentation prouvant la disponibilité des procédures pour les utilisateurs concernés | H40: Mauvaise application des processus | I40: moyenne | J40: Défaillances opérationnelles, non-qualité | K40: Réaliser des contrôles qualité sur l'application des processus définis.
D41: Archivage des anciennes versions pour référence | E41: Les anciennes versions des procédures sont-elles archivées pour référence ? | F41: Pas | G41: Archivage des anciennes versions des procédures | H41: Perte de références historiques | I41: moyenne | J41: Impossibilité d'analyser les tendances, perte de contexte | K41: Archiver systématiquement les décisions et données clés pour référence future.
C42: S’assurer de l’existence et de la mise à disposition du compte rendu mensuel au propriétaire | D42: Présence d’un format standard pour les comptes rendus mensuels | E42: Un format standard pour les comptes rendus mensuels est-il disponible ? | F42: Non | G42: Format standard pour les comptes rendus mensuels | H42: Non-conformité dans les rapports | I42: moyenne | J42: Rejets par les auditeurs, problèmes de conformité | K42: Standardiser les formats de rapports et mettre en place un processus de relecture.
D43: Rédaction systématique des comptes rendus chaque mois | E43: Les comptes rendus sont-ils rédigés systématiquement chaque mois ? | F43: Oui | G43: Rapport de rédaction systématique des comptes rendus chaque mois | H43: Perte d’informations clés | I43: moyenne | J43: Décisions sans historique, répétition d'erreurs | K43: Sauvegarder les informations clés sur des supports sécurisés et redondants.
D44: Archivage des comptes rendus dans un référentiel dédié | E44: Les comptes rendus sont-ils archivés dans un référentiel dédié ? | F44: Pas | G44: Référentiel dédié à l’archivage des comptes rendus | H44: Non-référencement historique | I44: moyenne | J44: Absence de traçabilité, difficultés d'audit | K44: Intégrer un système de gestion des versions et d’archivage structuré.
D45: Accès garanti au propriétaire pour chaque compte rendu | E45: Le propriétaire a-t-il un accès garanti à chaque compte rendu ? | F45: Non | G45: Preuve d’accès garanti au propriétaire pour chaque compte rendu | H45: Manque de communication | I45: moyenne | J45: Désalignement des équipes, actions non coordonnées | K45: Mettre en place une stratégie de communication interne efficace et multicanal.
D46: Confirmation de réception par le propriétaire chaque mois | E46: La réception des comptes rendus par le propriétaire est-elle confirmée chaque mois ? | F46: Oui | G46: Confirmation de réception des comptes rendus par le propriétaire | H46: Malentendus ou omissions | I46: basse | J46: Incompréhensions, erreurs d'exécution | K46: Clarifier les messages et valider les communications pour éviter les erreurs.
B47: Application | C47: S'assurer que l'accès aux ressources de l'application (données et transactions) est restreint par un système de gestion d'accès | D47: Présence d’un système de gestion d’accès centralisé | E47: Un système de gestion d’accès centralisé est-il en place ? | F47: Non | G47: Rapport sur le système de gestion d’accès centralisé | H47: Accès non autorisé | I47: moyenne | J47: Fuites de données, compromission d'informations | K47: Restreindre l’accès aux informations selon des droits strictement définis.
D48: Documentation des autorisations d’accès par utilisateur | E48: Les autorisations d’accès par utilisateur sont-elles documentées ? | F48: Pas | G48: Documentation des autorisations d’accès par utilisateur | H48: Confusion ou d’abus | I48: moyenne | J48: Utilisation abusive des ressources, détournements | K48: Créer un registre des accès et sensibiliser aux bonnes pratiques d’utilisation.
D49: Mise à jour régulière des droits d’accès | E49: Les droits d’accès sont-ils mis à jour régulièrement ? | F49: Oui | G49: Journal des mises à jour régulières des droits d’accès | H49: Permissions obsolètes ou inappropriées | I49: moyenne | J49: Privilèges excessifs, accès injustifiés aux systèmes sensibles | K49: Réviser régulièrement les permissions selon les besoins et responsabilités.
D50: Validation des accès par la direction | E50: Les accès sont-ils validés par la direction ? | F50: Non | G50: Validation des accès par la direction | H50: Mauvaise gestion des privilèges | I50: moyenne | J50: Accès non autorisés, permissions excessives, abus de droits | K50: Implémenter un processus formel de gestion des privilèges utilisateurs.
D51: Suivi des modifications des accès aux ressources | E51: Les modifications des accès aux ressources sont-elles suivies ? | F51: Pas | G51: Journal de suivi des modifications des accès aux ressources | H51: Contrôle insuffisant | I51: basse | J51: Failles non détectées, violations de sécurité persistantes | K51: Mettre en place un mécanisme de contrôle interne régulier et automatisé.
C52: S’assurer qu’une procédure de gestion des profils utilisateurs existe | D52: Existence d’un document formalisé des profils utilisateurs | E52: Un document formalisé des profils utilisateurs existe-t-il ? | F52: Oui | G52: Document formalisé des profils utilisateurs | H52: Gestion inefficace des utilisateurs | I52: elevée | J52: Comptes obsolètes actifs, accès non révoqués | K52: Définir clairement les rôles et responsabilités des utilisateurs dans un référentiel.
D53: Processus de création, modification et suppression des profils | E53: Un processus de création, modification et suppression des profils est-il défini ? | F53: Non | G53: Procédure formelle de création, modification et suppression des profils | H53: Désorganisation | I53: moyenne | J53: Confusion dans les accès, responsabilités floues | K53: Structurer les processus et documenter les procédures pour améliorer l’organisation.
D54: Validation des profils par les parties prenantes | E54: Les profils utilisateurs ont-ils été validés par les parties prenantes ? | F54: Oui | G54: Validation des profils par les parties prenantes | H54: Permissions incorrectes | I54: elevée | J54: Accès injustifiés à des données sensibles | K54: Réaliser une revue périodique des permissions attribuées aux utilisateurs.
D55: Suivi des modifications des profils utilisateurs | E55: Les modifications des profils utilisateurs sont-elles suivies ? | F55: Pas | G55: Journal de suivi des modifications des profils utilisateurs | H55: Non-conformité ou perte de traçabilité | I55: elevée | J55: Sanctions légales, impossibilité d'auditer les actions | K55: Implémenter un système de traçabilité centralisé et sécurisé.
D56: Formation des administrateurs sur la gestion des profils | E56: Les administrateurs ont-ils reçu une formation sur la gestion des profils ? | F56: Non | G56: Rapport de formation des administrateurs sur la gestion des profils | H56: Erreurs de gestion des profils | I56: moyenne | J56: Droits inadaptés aux besoins réels | K56: Assurer un processus formalisé de gestion des profils avec vérification.
C57: Vérifier que l’identification des utilisateurs est réalisée | D57: Utilisation de techniques d’authentification (ex. identifiant unique) | E57: Des techniques d’authentification, comme un identifiant unique, sont-elles utilisées ? | F57: Oui | G57: Rapport décrivant les techniques d’authentification utilisées | H57: Usurpation d’identité | I57: elevée | J57: Accès frauduleux, actions malveillantes au nom d'un utilisateur légitime | K57: Activer une authentification forte et surveiller les comportements suspects.
D58: Documentation des processus d’identification des utilisateurs | E58: Les processus d’identification des utilisateurs sont-ils documentés ? | F58: Pas | G58: Documentation des processus d’identification des utilisateurs | H58: Gestion inadéquate des accès | I58: elevée | J58: Exposition accrue aux menaces internes/externes | K58: Mettre en place un système de gestion des accès basé sur les rôles (RBAC).
D59: Validation des identifiants par l’administration | E59: Les identifiants des utilisateurs sont-ils validés par l’administration ? | F59: Non | G59: Validation des identifiants par l’administration | H59: Erreurs ou abus | I59: elevée | J59: Modifications non autorisées, fuites de données | K59: Sensibiliser les utilisateurs et intégrer des alertes sur les activités anormales.
D60: Fréquence des audits sur le processus d’identification | E60: Le processus d’identification est-il audité régulièrement ? | F60: Oui | G60: Rapport des audits réguliers sur le processus d’identification | H60: Failles non détectées | I60: elevée | J60: Exploitation par des attaquants, incidents majeurs | K60: Effectuer régulièrement des audits de sécurité pour identifier les failles.
D61: Suivi des tentatives d’usurpation d’identité | E61: Le suivi des tentatives d’usurpation d’identité est-il assuré ? | F61: Non | G61: Rapport de suivi des tentatives d’usurpation d’identité | H61: Sécurité compromise | I61: basse | J61: Perte de confidentialité/intégrité des données | K61: Renforcer les mesures de sécurité physique et logique sur les systèmes critiques.
C62: Vérifier qu’un mot de passe est associé à l'identifiant | D62: Présence obligatoire d’un mot de passe pour chaque utilisateur | E62: Un mot de passe est-il obligatoire pour chaque utilisateur ? | F62: Pas | G62: Preuve de la présence obligatoire d’un mot de passe pour chaque utilisateur | H62: Accès non sécurisé | I62: basse | J62: Interceptions de données, attaques MITM | K62: Sécuriser les connexions via des protocoles chiffrés et des firewalls.
D63: Respect des critères de complexité des mots de passe | E63: Les critères de complexité des mots de passe sont-ils respectés ? | F63: Oui | G63: Document décrivant les critères de complexité des mots de passe | H63: Mot de passe vulnérable | I63: elevée | J63: Piratage de comptes par force brute | K63: Appliquer une politique de mots de passe complexes et renouvelables.
D64: Fréquence de mise à jour des mots de passe | E64: La fréquence de mise à jour des mots de passe est-elle suffisante ? | F64: Non | G64: Rapport de mise à jour des mots de passe | H64: Usurpation via des mots de passe obsolètes | I64: elevée | J64: Accès avec d'anciens identifiants non révoqués | K64: Désactiver les comptes utilisant d’anciens mots de passe non conformes.
D65: Suivi des tentatives de connexion avec des mots de passe incorrects | E65: Le suivi des tentatives de connexion avec des mots de passe incorrects est-il effectué ? | F65: Pas | G65: Journal des tentatives de connexion avec des mots de passe incorrects | H65: Tentatives non détectées | I65: elevée | J65: Attaques réussies faute d'alertes | K65: Mettre en œuvre un système de détection d’intrusion avec alertes automatisées.
D66: Sensibilisation des utilisateurs aux bonnes pratiques de mot de passe | E66: Les utilisateurs sont-ils sensibilisés aux bonnes pratiques de mot de passe ? | F66: Non | G66: Programme de sensibilisation aux bonnes pratiques de mot de passe | H66: Comportements à risque des utilisateurs | I66: elevée | J66: Partage de comptes, négligence sécuritaire | K66: Former les utilisateurs à adopter de bonnes pratiques de cybersécurité.
C67: S’assurer que les tentatives de connexions infructueuses à l'application sont suivies | D67: Enregistrement des tentatives de connexion infructueuses | E67: Les tentatives de connexion infructueuses sont-elles enregistrées ? | F67: Oui | G67: Journal des tentatives de connexion infructueuses | H67: Diagnostics incomplets | I67: elevée | J67: Évaluations erronées des vulnérabilités | K67: Documenter tous les diagnostics et analyses dans un système de gestion des incidents.
D68: Analyse régulière des logs de connexion | E68: Les logs de connexion sont-ils analysés régulièrement ? | F68: Pas | G68: Rapport d’analyse régulière des logs de connexion | H68: Menaces non identifiées | I68: moyenne | J68: Exposition à des attaques connues non corrigées | K68: Effectuer une veille de sécurité pour identifier les nouvelles menaces.
D69: Signalement des anomalies détectées aux responsables | E69: Les anomalies détectées sont-elles signalées aux responsables ? | F69: Oui | G69: Signalements des anomalies détectées aux responsables | H69: Réponses inappropriées | I69: moyenne | J69: Aggravation des incidents, temps d'indisponibilité accru | K69: Élaborer un plan de réponse aux incidents avec des scénarios types.
D70: Présence d’un seuil de blocage après plusieurs tentatives échouées | E70: Un seuil de blocage est-il appliqué après plusieurs tentatives échouées ? | F70: Non | G70: Rapport définissant le seuil de blocage après plusieurs tentatives échouées | H70: Attaques persistantes | I70: moyenne | J70: Pénétration prolongée dans le système | K70: Mettre en place un système de surveillance continue et de réaction rapide.
D71: Mise en œuvre de mesures correctives pour les connexions suspectes | E71: Des mesures correctives pour les connexions suspectes sont-elles mises en œuvre ? | F71: Pas | G71: Plan d’action pour corriger les connexions suspectes | H71: Sécurité altérée | I71: moyenne | J71: Perte de confiance des parties prenantes | K71: Réviser les modèles d’accès régulièrement pour garantir leur pertinence.
C72: S’assurer que l'accès aux données et aux transactions de l’application est géré | D72: Utilisation de profils d’accès différenciés (par rôle) | E72: Des profils d’accès différenciés (par rôle) sont-ils utilisés ? | F72: Oui | G72: Documentation des profils d’accès différenciés (par rôle) | H72: Permissions inappropriées | I72: moyenne | J72: Accès excessifs ou insuffisants | K72: Centraliser les données critiques avec des sauvegardes régulières.
D73: Documentation des processus de gestion des accès | E73: Les processus de gestion des accès sont-ils documentés ? | F73: Non | G73: Manuel des processus de gestion des accès | H73: Confusion ou perte d’information | I73: moyenne | J73: Erreurs humaines, pertes de données | K73: Automatiser la détection des failles avec des outils spécialisés.
D74: Fréquence des audits des accès aux données et transactions | E74: Les accès aux données et transactions font-ils l’objet d’audits réguliers ? | F74: Pas | G74: Rapport des audits des accès aux données et transactions | H74: Failles non détectées | I74: moyenne | J74: Droits incohérents avec les rôles | K74: Revoir l’attribution des permissions après chaque changement organisationnel.
D75: Validation des droits d’accès par les parties prenantes | E75: Les droits d’accès ont-ils été validés par les parties prenantes ? | F75: Non | G75: Validation des droits d’accès par les parties prenantes | H75: Permissions mal attribuées | I75: basse | J75: Fuites d'informations sensibles | K75: Chiffrer les données sensibles et contrôler leur accès avec des journaux d’audit.
D76: Présence de systèmes de contrôle pour limiter les accès non autorisés | E76: Des systèmes de contrôle sont-ils en place pour limiter les accès non autorisés ? | F76: Oui | G76: Documentation des systèmes de contrôle pour limiter les accès non autorisés | H76: Violation des données | I76: moyenne | J76: Incapacité à investiguer les incidents | K76: Intégrer une solution de journalisation systématique pour chaque action utilisateur.
C77: Vérifier l’existence de pistes d’audit sur le système d’administration de l’application | D77: Activation des pistes d’audit dans le système | E77: Les pistes d’audit sont-elles activées dans le système ? | F77: Pas | G77: Rapport d’activation des pistes d’audit dans le système | H77: Traçabilité impossible | I77: moyenne | J77: Difficulté à analyser les tendances passées | K77: Automatiser les scans de vulnérabilités sur les systèmes critiques.
D78: Fréquence des analyses des pistes d’audit | E78: Les pistes d’audit sont-elles analysées régulièrement ? | F78: Oui | G78: Rapport des analyses régulières des pistes d’audit | H78: Failles non détectées | I78: moyenne | J78: Répétition des mêmes incidents | K78: Archiver systématiquement les décisions et événements de sécurité.
D79: Conservation des logs d’audit pendant une période définie | E79: Les logs d’audit sont-ils conservés pendant une période définie ? | F79: Non | G79: Logs d’audit conservés sur une période définie | H79: Absence de références historiques | I79: moyenne | J79: Données corrompues ou falsifiées | K79: Valider toutes les réponses via des processus de test avant déploiement.
D80: Signalement des anomalies détectées dans les audits | E80: Les anomalies détectées dans les audits sont-elles signalées ? | F80: Pas | G80: Signalements des anomalies détectées dans les audits | H80: Réponses inappropriées | I80: basse | J80: Prise de décision sur des bases erronées | K80: Mettre à jour les protocoles de réponse aux incidents selon les retours d’expérience.
D81: Présence d’un processus d’escalade pour les violations détectées | E81: Un processus d’escalade est-il en place pour les violations détectées ? | F81: Non | G81: Procédure d’escalade pour les violations détectées | H81: Réponses inefficaces | I81: elevée | J81: Dysfonctionnements opérationnels | K81: Mettre en place des protocoles de réponse standardisés et des formations régulières pour améliorer l'efficacité.
C82: Vérifier que tous les documents servant de base à la saisie sont pris en compte | D82: Documentation formelle des documents nécessaires à la saisie | E82: Les documents nécessaires à la saisie sont-ils documentés formellement ? | F82: Oui | G82: Documentation formelle des documents nécessaires à la saisie | H82: Erreurs dans les entrées | I82: moyenne | J82: Données erronées dans le système | K82: Utiliser des outils de validation automatisée pour détecter et corriger les erreurs dans les entrées de données.
D83: Validation des documents par les responsables | E83: Les documents utilisés pour la saisie ont-ils été validés par les responsables ? | F83: Non | G83: Validation officielle des documents par les responsables | H83: Inexactitudes dans les données | I83: elevée | J83: Informations inexactes affectant les décisions | K83: Implémenter des processus de vérification croisée pour garantir l'exactitude des données.
D84: Contrôle de l’intégrité des documents avant la saisie | E84: L’intégrité des documents est-elle contrôlée avant la saisie ? | F84: Pas | G84: Rapport de contrôle de l’intégrité des documents avant saisie | H84: Données incorrectes | I84: elevée | J84: Bases de données ou rapports falsifiés | K84: Appliquer des règles de gouvernance des données et des audits réguliers pour identifier les données incorrectes.
D85: Conservation des documents pour vérification ultérieure | E85: Les documents sont-ils conservés pour vérification ultérieure ? | F85: Oui | G85: Archives des documents pour vérification ultérieure | H85: Perte d’historique | I85: moyenne | J85: Impossibilité de consulter les actions passées | K85: Sauvegarder régulièrement les données et conserver un journal des modifications pour éviter la perte d'historique.
D86: Fréquence des mises à jour des documents utilisés | E86: Les documents utilisés sont-ils mis à jour régulièrement ? | F86: Non | G86: Rapport des mises à jour régulières des documents utilisés | H86: Informations obsolètes | I86: elevée | J86: Prise de décision sur des informations non actualisées | K86: Mettre à jour périodiquement les informations et automatiser les alertes pour les données obsolètes.
C87: S’assurer que les facilités de saisie, l’ergonomie de la saisie, les messages écrans et les contrôles sont mis en œuvre | D87: Tests réguliers de l’ergonomie des interfaces | E87: Des tests réguliers de l’ergonomie des interfaces sont-ils effectués ? | F87: Oui | G87: Rapport des tests réguliers de l’ergonomie des interfaces | H87: Expérience utilisateur médiocre | I87: elevée | J87: Frustration des utilisateurs, abandon des outils | K87: Concevoir des interfaces intuitives et recueillir des feedbacks utilisateurs pour améliorer l'expérience.
D88: Présence de messages d’erreur descriptifs à l’écran | E88: Des messages d’erreur descriptifs sont-ils présents à l’écran ? | F88: Pas | G88: Capture des messages d’erreur descriptifs affichés à l’écran | H88: Confusion pour l’utilisateur | I88: elevée | J88: Difficultés d'utilisation, erreurs répétées | K88: Simplifier les processus et fournir des guides clairs pour réduire la confusion des utilisateurs.
D89: Documentation des contrôles intégrés dans les interfaces | E89: Les contrôles intégrés dans les interfaces sont-ils documentés ? | F89: Non | G89: Documentation des contrôles intégrés dans les interfaces | H89: Failles et erreurs | I89: elevée | J89: Vulnérabilités exploitables dans le système | K89: Effectuer des tests de sécurité réguliers et corriger les failles et erreurs identifiées.
D90: Formation des utilisateurs sur les outils de saisie | E90: Les utilisateurs reçoivent-ils une formation sur les outils de saisie ? | F90: Oui | G90: Rapport de formation des utilisateurs sur les outils de saisie | H90: Mauvaises pratiques | I90: basse | J90: Maintien de méthodes non optimales | K90: Établir des bonnes pratiques documentées et former les équipes pour éviter les mauvaises pratiques.
D91: Collecte des retours utilisateurs pour améliorer les interfaces | E91: Les retours des utilisateurs sont-ils collectés pour améliorer les interfaces ? | F91: Pas | G91: Rapport de collecte des retours utilisateurs pour améliorer les interfaces | H91: Absence d’amélioration continue | I91: basse | J91: Stagnation des processus, pas d'optimisation | K91: Adopter une approche itérative avec des revues périodiques pour assurer l'amélioration continue.
B92: Fonction informatique | C92: S’assurer que les tâches relatives au développement et à l'exploitation de l'application sont bien suivies et documentées ; | D92: Disponibilité d’un journal de suivi des tâches | E92: Un journal de suivi des tâches est-il disponible ? | F92: Non | G92: Journal de suivi des tâches disponibles | H92: Perte de traçabilité | I92: elevée | J92: Impossibilité de retracer les actions et modifications | K92: Utiliser des systèmes de journalisation pour assurer la traçabilité des actions et modifications.
D93: Fréquence des mises à jour du journal de suivi | E93: Le journal de suivi des tâches est-il mis à jour régulièrement ? | F93: Oui | G93: Rapport des mises à jour régulières du journal de suivi | H93: Informations périmées | I93: moyenne | J93: Utilisation d'informations non valides | K93: Automatiser la détection et le remplacement des informations périmées.
D94: Documentation des processus liés au développement et à l'exploitation | E94: Les processus liés au développement et à l'exploitation sont-ils documentés ? | F94: Non | G94: Document décrivant les processus liés au développement et à l’exploitation | H94: Confusion et inefficacité | I94: basse | J94: Désorganisation, perte de temps | K94: Clarifier les rôles et responsabilités pour éviter la confusion et améliorer l'efficacité.
D95: Validation des tâches par les responsables | E95: Les tâches sont-elles validées par les responsables ? | F95: Pas | G95: Validation des tâches par les responsables | H95: Mauvaise coordination | I95: basse | J95: Actions non coordonnées entre services | K95: Mettre en place des outils de collaboration et des réunions de synchronisation pour une meilleure coordination.
D96: Archivage des anciennes tâches pour référence future | E96: Les anciennes tâches sont-elles archivées pour référence future ? | F96: Oui | G96: Archives des anciennes tâches pour référence future | H96: Perte d’historique | I96: moyenne | J96: Absence d'archivage des activités passées | K96: Protéger l'historique des modifications avec des sauvegardes et des accès sécurisés.
C97: S’assurer que l'accès aux bibliothèques de production est réglementé | D97: Documentation des droits d’accès aux bibliothèques de production | E97: Les droits d’accès aux bibliothèques de production sont-ils documentés ? | F97: Non | G97: Documentation des droits d’accès aux bibliothèques de production | H97: Confusion ou d’abus | I97: elevée | J97: Utilisation abusive des ressources | K97: Sensibiliser les utilisateurs et mettre en place des mécanismes de surveillance pour prévenir les abus.
D98: Présence d’un système de gestion des accès | E98: Un système de gestion des accès est-il en place pour les bibliothèques de production ? | F98: Pas | G98: Rapport sur la présence d’un système de gestion des accès | H98: Accès non autorisé | I98: elevée | J98: Accès illégitimes à des données sensibles | K98: Restreindre les accès avec des politiques de permissions strictes et des audits réguliers.
D99: Validation des autorisations par les responsables | E99: Les autorisations d’accès aux bibliothèques de production ont-elles été validées par les responsables ? | F99: Oui | G99: Validation des autorisations par les responsables | H99: Mauvaise gestion des droits | I99: elevée | J99: Droits d'accès mal attribués | K99: Réviser régulièrement les droits d'accès et former les gestionnaires à une meilleure gestion des droits.
D100: Fréquence des audits des accès | E100: Les audits des accès aux bibliothèques de production sont-ils réalisés régulièrement ? | F100: Non | G100: Rapport des audits réguliers des accès | H100: Failles non détectées | I100: elevée | J100: Vulnérabilités persistantes non corrigées | K100: Implémenter des systèmes de détection d'intrusions et des analyses de vulnérabilités pour identifier les failles.
...

Sheet 4.2.Fonction_informatique
A1: Domaine | B1: Points de contrôle | C1: Objectifs de contrôle | D1: Critères d'évaluation | E1: Questions d'évaluation | F1: Réponses | G1: Documents requis | H1: Risques | I1: Criticité | J1: Conséquences | K1: Recommandations
A2: Fonction informatique | B2: Rôle et positionnement de l'informatique dans l'organisation | C2: Vérifier qu’ont été créés des Comités « informatique » (stratégique, pilotage,..) regroupant les différentes directions de l’Organisation en charge de recenser les besoins et les opportunités, gérer les priorités et suivre les projets | D2: Les Comités "informatique" sont officiellement créés et documentés (PV de réunion, charte de fonctionnement) | E2: Les Comités "informatique" sont-ils officiellement créés et documentés (PV de réunion, charte de fonctionnement) ? | F2: Oui | G2: Charte des comités informatiques | H2: Absence de formalisation des rôles | I2: Élevée | J2: Décisions non alignées, perte de confiance | K2: Validation par la DG cruciale pour légitimité
G3: Procès-verbaux (PV) de réunions | H3: Décisions non suivies ou non partagées | I3: Moyenne | J3: Retards projets, divergences métiers/DSI | K3: PV clairs et diffusés améliorent la traçabilité
D4: Les directions métiers participent activement aux comités, avec une représentation équilibrée | E4: Les directions métiers participent-elles activement aux comités, avec une représentation équilibrée ? | F4: Oui | G4: Liste des membres désignés | H4: Représentation déséquilibrée | I4: Moyenne | J4: Besoins métiers mal pris en compte | K4: Établir des quotas par direction
G5: Feuilles de présence | H5: Participation irrégulière | I5: Faible | J5: Manque d'engagement | K5: Lier la participation aux objectifs individuels
D6: Les réunions sont tenues à une fréquence régulière (trimestrielle, semestrielle) avec un taux de participation satisfaisant | E6: Les réunions sont-elles tenues à une fréquence régulière (trimestrielle, semestrielle) avec un taux de participation satisfaisant ? | F6: Oui | G6: Calendrier annuel | H6: Délais non respectés | I6: Moyenne | J6: Accumulation de sujets | K6: Planifier 1 an à l'avance
G7: Statistiques de participation | H7: Quorum non atteint | I7: Faible | J7: Décisions non valides | K7: Prévoir un système de délégation
D8: Les décisions prises sont formalisées et suivies, avec des comptes-rendus partagés | E8: Les décisions prises sont-elles formalisées et suivies, avec des comptes-rendus partagés ? | F8: Oui | G8: Registre des décisions | H8: Non-application | I8: Élevée | J8: Blocages opérationnels | K8: Assigner un responsable par décision
G9: Dashboard de suivi | H9: Dérive des délais | I9: Moyenne | J9: Retards projets | K9: Revue mensuelle obligatoire
D10: Les priorités définies par les comités sont alignées sur la stratégie globale de l’organisation | E10: Les priorités définies par les comités sont-elles alignées sur la stratégie globale de l’organisation ? | F10: Oui | G10: Feuille de route SI | H10: Projets non stratégiques | I10: Élevée | J10: Gaspillage de ressources | K10: Validation annuelle par le COMEX
G11: Budget détaillé | H11: Déséquilibre financier | I11: Élevée | J11: Manque de fonds pour priorités | K11: Revue trimestrielle
C12: Vérifier l’existence d’une charte informatique ou de tout autre document définissant le rôle et le périmètre de responsabilité de la DSI | D12: Un document officiel (charte, politique) définit le rôle et les responsabilités de la DSI | E12: Un document officiel (charte, politique) définit-il le rôle et les responsabilités de la DSI ? | F12: Oui | G12: Charte de la DSI | H12: Périmètre flou | I12: Élevée | J12: Conflits de responsabilités | K12: Inclure un organigramme
G13: Politique SI | H13: Non-conformité | I13: Élevée | J13: Sanctions | K13: Validation juridique
D14: Le périmètre d’intervention de la DSI est clairement délimité | E14: Le périmètre d’intervention de la DSI est -il clairement délimité ? | F14: Non | G14: Cartographie processus | H14: Empiètement métiers | I14: Moyenne | J14: Doublons | K14: Mise à jour annuelle
G15: Matrice RACI | H15: Délégations floues | I15: Moyenne | J15: Retards décisionnels | K15: Former les managers
D16: Le document fait référence aux obligations légales et normes sectorielles applicables | E16: Le document fait-il référence aux obligations légales et normes sectorielles applicables ? | F16: Non | G16: Registre conformité | H16: Amendes réglementaires | I16: Élevée | J16: Sanctions financières | K16: Audit semestriel
G17: Procédures de mise à jour | H17: Non-actualisation | I17: Moyenne | J17: Non-conformité | K17: Automatiser les alertes
D18: La charte est validée et signée par les instances dirigeantes concernées | E18: La charte est-elle validée et signée par les instances dirigeantes concernées ? | F18: Pas | G18: PV de validation | H18: Non légitimité | I18: Élevée | J18: Rejet par les métiers | K18: Signature électronique
G19: Plan de diffusion | H19: Non accessibilité | I19: Faible | J19: Non application | K19: Publier sur l'intranet
D20: La charte est diffusée et accessible à l’ensemble des collaborateurs concernés | E20: La charte est-elle diffusée et accessible à l’ensemble des collaborateurs concernés ? | F20: Oui | G20: Registre de diffusion | H20: Non-connaissance des règles | I20: Moyenne | J20: Non-respect des processus | K20: Mettre en place un accusé de lecture
G21: Plateforme collaborative | H21: Accès difficile | I21: Faible | J21: Faible adoption | K21: Centraliser sur l'intranet
C22: Évaluer le degré d’implication et de maîtrise des organes de gestion dans les systèmes d’information de l’Organisation | D22: Les dirigeants participent activement aux comités stratégiques informatiques | E22: Les dirigeants participent-ils activement aux comités stratégiques informatiques ? | F22: Pas | G22: PV COMEX | H22: Décisions bloquées | I22: Élevée | J22: Paralysie | K22: Quorum C-level
G23: Plan communication | H23: Manque visibilité | I23: Faible | J23: Démotivation | K23: Synthèses mensuelles
D24: La direction générale comprend les enjeux clés des systèmes d’information | E24: La direction générale comprend t-elle les enjeux clés des systèmes d’information ? | F24: Non | G24: PV de formation | H24: Incompréhension | I24: Élevée | J24: Mauvaises décisions | K24: Formation annuelle
G25: Évaluation compétences | H25: Lacunes persistantes | I25: Moyenne | J25: Investissements inadaptés | K25: Coaching individuel
D26: Les budgets alloués aux projets informatiques reflètent les priorités stratégiques | E26: Les budgets alloués aux projets informatiques reflètent-ils les priorités stratégiques ? | F26: Non | G26: Budget projet | H26: Déséquilibre | I26: Élevée | J26: Projets non financés | K26: Alignement stratégique
G27: Rapport d'exécution | H27: Dérives | I27: Moyenne | J27: Dépassements | K27: Alertes automatiques
D28: Les dirigeants suivent des formations sur les enjeux de la gouvernance des SI | E28: Les dirigeants suivent-ils des formations sur les enjeux de la gouvernance des SI ? | F28: Non | G28: Planning formation | H28: Manque de culture SI | I28: Moyenne | J28: Décisions inadaptées | K28: Obligation annuelle
G29: Évaluations | H29: Lacunes non traitées | I29: Faible | J29: Risques persistants | K29: Suivi RH
D30: La direction réagit rapidement en cas d’incident majeur impactant les SI | E30: La direction réagit-elle rapidement en cas d’incident majeur impactant les SI ? | F30: Oui | G30: PRA/PCA | H30: Temps d'arrêt longs | I30: Élevée | J30: Pertes financières | K30: Tests trimestriels
G31: Compte-rendu incident | H31: Répétition erreurs | I31: Moyenne | J31: Perte de confiance | K31: Revue post-mortem
C32: Vérifier en pratique que le leadership des grands projets est assuré par les organes de gestion | D32: Un sponsor métier est désigné pour chaque projet majeur | E32: Un sponsor métier est-il désigné pour chaque projet majeur ? | F32: Oui | G32: Matrice responsabilités | H32: Portage insuffisant | I32: Élevée | J32: Échec projet | K32: Validation COMEX
G33: PV de lancement | H33: Engagement faible | I33: Moyenne | J33: Retards | K33: Évaluation performance
D34: Les dirigeants participent aux revues d’avancement des projets clés | E34: Les dirigeants participent-ils aux revues d’avancement des projets clés ? | F34: Non | G34: Planning revues | H34: Décisions tardives | I34: Moyenne | J34: Retards | K34: Bloquer agendas
G35: Comptes-rendus | H35: Actions non suivies | I35: Faible | J35: Dérives | K35: Assigner des responsables
D36: Les livrables majeurs sont validés par les instances dirigeantes concernées | E36: Les livrables majeurs sont-ils validés par les instances dirigeantes concernées ? | F36: Pas | G36: Procès-verbal validation | H36: Non-conformité | I36: Élevée | J36: Rejet livrable | K36: Checklist formelle
G37: Fiche de recette | H37: Bugs non détectés | I37: Moyenne | J37: Coûts supplémentaires | K37: Tests automatisés
D38: Les comités de risques projet impliquent les responsables métiers et la direction | E38: Les comités de risques projet impliquent-ils les responsables métiers et la direction ? | F38: Pas | G38: Registre des risques | H38: Risques ignorés | I38: Élevée | J38: Échecs projets | K38: Réunions bimestrielles
G39: Plans d'action | H39: Non mise en œuvre | I39: Moyenne | J39: Exposition aux risques | K39: Suivi dédié
D40: La communication interne sur les projets est portée par les dirigeants | E40: La communication interne sur les projets est-elle portée par les dirigeants ? | F40: Oui | G40: Plan communication | H40: Manque d'adhésion | I40: Moyenne | J40: Résistance au changement | K40: Messages vidéo
G41: Sondages feedback | H41: Démotivation | I41: Faible | J41: Baisse productivité | K41: Communication régulière
C42: Vérifier que les métiers assurent leur rôle de MOA | D42: Les besoins métiers sont formalisés dans des cahiers des charges ou spécifications | E42: Les besoins métiers sont-ils formalisés dans des cahiers des charges ou spécifications ? | F42: Oui | G42: Cahier des charges | H42: Incompréhension | I42: Élevée | J42: Solution inadaptée | K42: Validation formelle
G43: Protocole recette | H43: Non-qualité | I43: Élevée | J43: Refus utilisateurs | K43: Tests utilisateurs
D44: Un chef de projet MOA est désigné pour chaque projet ou domaine clé | E44: Un chef de projet MOA est-il désigné pour chaque projet ou domaine clé ? | F44: Oui | G44: Organigramme projet | H44: Manque de pilotage | I44: Élevée | J44: Dérives | K44: Nomination formelle
G45: Fiche de mission | H45: Périmètre flou | I45: Moyenne | J45: Conflits | K45: Définition claire des rôles
D46: Les spécifications fonctionnelles sont validées par les métiers avant développement | E46: Les spécifications fonctionnelles sont-elles validées par les métiers avant développement ? | F46: Oui | G46: PV de validation | H46: Écart besoins | I46: Élevée | J46: Refus livrable | K46: Signature obligatoire
G47: Versionning | H47: Modifications non tracées | I47: Moyenne | J47: Incohérences | K47: Outil collaboratif
D48: Les budgets MOA sont engagés pour financer les études et l’accompagnement utilisateurs | E48: Les budgets MOA sont-ils engagés pour financer les études et l’accompagnement utilisateurs ? | F48: Oui | G48: Budget prévisionnel | H48: Sous-financement | I48: Moyenne | J48: Accompagnement insuffisant | K48: Validation financière
G49: Reporting | H49: Dérives | I49: Faible | J49: Manque de visibilité | K49: Alertes automatiques
D50: Des réunions régulières entre MOA et MOE permettent d’ajuster les projets en cours | E50: Des réunions régulières entre MOA et MOE permettent-elles d’ajuster les projets en cours ? | F50: Non | G50: Planning réunions | H50: Décrochage | I50: Moyenne | J50: Livraison inadaptée | K50: Fréquence minimale
G51: Comptes-rendus | H51: Actions non suivies | I51: Faible | J51: Retards | K51: Outil de suivi partagé
B52: Planification stratégique | C52: Vérifier la couverture du périmètre fonctionnel | D52: Le périmètre fonctionnel couvre l’ensemble des processus métiers critiques de l’organisation | E52: Le périmètre fonctionnel couvre t-il l’ensemble des processus métiers critiques de l’organisation ? | F52: Non | G52: Cartographie processus | H52: Zones non couvertes | I52: Élevée | J52: Risques opérationnels | K52: Revue annuelle
G53: Analyse d'impact | H53: Faiblesses non traitées | I53: Moyenne | J53: Vulnérabilités | K53: Ateliers métiers
D54: Les applications supportant les fonctions clés sont clairement identifiées et documentées | E54: Les applications supportant les fonctions clés sont-elles clairement identifiées et documentées ? | F54: Non | G54: Inventaire applicatif | H54: Manque de visibilité | I54: Élevée | J54: Incidents majeurs | K54: Classification par criticité
G55: Documentation technique | H55: Dépendances cachées | I55: Moyenne | J55: Effet domino | K55: Mise à jour continue
D56: Les zones non couvertes par le système d’information sont recensées et justifiées | E56: Les zones non couvertes par le système d’information sont-elles recensées et justifiées ? | F56: Non | G56: Registre des gaps | H56: Risques non gérés | I56: Élevée | J56: Pertes d'opportunités | K56: Revue semestrielle
G57: Plan de correction | H57: Retards traitement | I57: Moyenne | J57: Accumulation problèmes | K57: Priorisation claire
D58: Les dépendances entre applications et processus métiers sont cartographiées | E58: Les dépendances entre applications et processus métiers sont-elles cartographiées ? | F58: Non | G58: Schéma d'architecture | H58: Points de rupture | I58: Élevée | J58: Incidents en cascade | K58: Mise à jour annuelle
G59: Matrice d'impact | H59: Vulnérabilités | I59: Moyenne | J59: Temps de réparation longs | K59: Simulation de crise
D60: Les fonctions obsolètes ou redondantes sont identifiées et planifiées pour suppression | E60: Les fonctions obsolètes ou redondantes sont-elles identifiées et planifiées pour suppression ? | F60: Non | G60: Plan de retrait | H60: Dette technique | I60: Moyenne | J60: Coûts de maintenance | K60: Planning formalisé
G61: Analyse coûts/bénéfices | H61: Retards élimination | I61: Faible | J61: Accumulation | K61: Budget dédié
C62: Vérifier l’existence d’une analyse à jour des procédures de pilotage et de mise à jour du plan informatique | D62: Les rôles et responsabilités dans la mise à jour du plan sont clairement attribués | E62: Les rôles et responsabilités dans la mise à jour du plan sont-ils clairement attribués ? | F62: Pas | G62: Matrice RACI | H62: Responsabilités floues | I62: Élevée | J62: Retards dans les mises à jour | K62: Formaliser dans les fiches de poste
G63: Procédure de mise à jour | H63: Processus non suivi | I63: Moyenne | J63: Incohérences | K63: Automatiser les rappels
D64: Les écarts entre le plan prévu et sa réalisation font l’objet d’analyses correctives | E64: Les écarts entre le plan prévu et sa réalisation font-ils l’objet d’analyses correctives ? | F64: Pas | G64: Rapport d'écarts | H64: Dérives non détectées | I64: Élevée | J64: Décisions inadaptées | K64: Revue trimestrielle obligatoire
G65: Plan d'actions correctives | H65: Retards de correction | I65: Moyenne | J65: Accumulation problèmes | K65: Suivi dans JIRA
D66: Les décisions d’ajustement du plan sont documentées et communiquées aux parties prenantes | E66: Les décisions d’ajustement du plan sont-elles documentées et communiquées aux parties prenantes ? | F66: Pas | G66: PV de comité de pilotage | H66: Traçabilité perdue | I66: Moyenne | J66: Incohérences | K66: Archivage centralisé
G67: Newsletter interne | H67: Mauvaise communication | I67: Faible | J67: Résistance au changement | K67: Format standardisé
D68: Les budgets et ressources nécessaires à l’exécution du plan sont validés annuellement | E68: Les budgets et ressources nécessaires à l’exécution du plan sont-ils validés annuellement ? | F68: Pas | G68: Budget validé | H68: Sous/sur-financement | I68: Élevée | J68: Projets bloqués | K68: Alignement stratégique
G69: Reporting financier | H69: Dérives non détectées | I69: Moyenne | J69: Dépassements | K69: Alertes automatiques
C70: Vérifier l’existence des documents à jour d’urbanisme de l’Organisation | D70: Une cartographie applicative à jour reflète l’état du système d’information | E70: Une cartographie applicative à jour reflète t-elle l’état du système d’information ? | F70: Pas | G70: Inventaire SI | H70: Vision obsolète | I70: Élevée | J70: Prises de décision erronées | K70: Mises à jour trimestrielles
G71: Diagramme d'architecture | H71: Dépendances cachées | I71: Moyenne | J71: Incidents en cascade | K71: Outil dédié (ex: LeanIX)
D72: Les principes d’urbanisme (modularité, interopérabilité) sont formalisés et appliqués | E72: Les principes d’urbanisme (modularité, interopérabilité) sont-ils formalisés et appliqués ? | F72: Pas | G72: Charte d'urbanisme | H72: Architecture désorganisée | I72: Élevée | J72: Coûts d'intégration élevés | K72: Validation par l'architecte
G73: Checklist de conformité | H73: Non-respect des normes | I73: Moyenne | J73: Dette technique | K73: Revue annuelle
D74: Les flux de données entre applications sont documentés et optimisés | E74: Les flux de données entre applications sont-ils documentés et optimisés ? | F74: Pas | G74: Catalogue de flux | H74: Goulots d'étranglement | I74: Moyenne | J74: Performances dégradées | K74: Documentation automatisée
G75: Audit d'optimisation | H75: Surcoûts techniques | I75: Moyenne | J75: Dépenses inutiles | K75: Outil d'analyse
D76: Les projets d’évolution du SI s’inscrivent dans la démarche d’urbanisme | E76: Les projets d’évolution du SI s’inscrivent-ils dans la démarche d’urbanisme ? | F76: Pas | G76: Fiche de cadrage | H76: Solutions inadaptées | I76: Élevée | J76: Réussite compromise | K76: Validation architecturale
G77: Matrice d'impact | H77: Effets secondaires | I77: Moyenne | J77: Régression | K77: Ateliers d'architecture
D78: La gouvernance de l’urbanisme implique les métiers et la DSI | E78: La gouvernance de l’urbanisme implique t-il les métiers et la DSI ? | F78: Pas | G78: PV de comité | H78: Décisions unilatérales | I78: Moyenne | J78: Rejet par les métiers | K78: Parité de représentation
G79: Enquête de satisfaction | H79: Démotivation | I79: Faible | J79: Mauvaise adoption | K79: Feedback trimestriel
C80: Vérifier l’existence d’une analyse à jour des procédures de pilotage et de mise à jour du plan d’occupation des sols (POS) | D80: Le POS est documenté et accessible aux équipes techniques et métiers | E80: Le POS est-il documenté et accessible aux équipes techniques et métiers ? | F80: Oui | G80: Document POS | H80: Connaissances dispersées | I80: Élevée | J80: Décisions incohérentes | K80: Portail dédié
G81: FAQ technique | H81: Mauvaises pratiques | I81: Faible | J81: Dette technique | K81: Wiki interactif
D82: Les règles d’allocation des ressources (serveurs, stockage) sont formalisées | E82: Les règles d’allocation des ressources (serveurs, stockage) sont-elles formalisées ? | F82: Oui | G82: Politique d'infra | H82: Surcharge des ressources | I82: Moyenne | J82: Pannes | K82: Supervision automatisée
G83: Dashboard utilisation | H83: Gaspillage | I83: Moyenne | J83: Coûts inutiles | K83: Alertes seuils
D84: Les procédures de mise à jour du POS intègrent les besoins métiers futurs | E84: Les procédures de mise à jour du POS intègrent-elles les besoins métiers futurs ? | F84: Oui | G84: Roadmap technique | H84: Obsolescence | I84: Élevée | J84: Coûts de migration | K84: Veille technologique
G85: Benchmark sectoriel | H85: Retard technologique | I85: Moyenne | J85: Perte compétitivité | K85: Revue semestrielle
D86: Les évolutions d’infrastructure suivent une planification pluriannuelle | E86: Les évolutions d’infrastructure suivent-elles une planification pluriannuelle ? | F86: Oui | G86: Plan 3-5 ans | H86: Réactivité insuffisante | I86: Moyenne | J86: Inadaptation | K86: Budget glissant
G87: Scénarios d'évolution | H87: Surprises | I87: Moyenne | J87: Décisions urgentes | K87: Ateliers prospectifs
D88: Les audits réguliers vérifient la conformité entre POS réel et documenté | E88: Les audits réguliers vérifient-ils la conformité entre POS réel et documenté ? | F88: Non | G88: Rapport d'audit complet | H88: Non-détection d'écarts | I88: Élevée | J88: Risques sécurité non maîtrisés | K88: Automatiser les contrôles
G89: Plan de correction | H89: Retard dans les corrections | I89: Moyenne | J89: Exposition prolongée aux risques | K89: Suivi mensuel par la direction
C90: Vérifier la cohérence et l’homogénéité des technologies | D90: Un référentiel des technologies autorisées est maintenu à jour | E90: Un référentiel des technologies autorisées est-il maintenu à jour ? | F90: Oui | G90: Catalogue des technologies approuvées | H90: Utilisation de technologies obsolètes | I90: Élevée | J90: Vulnérabilités de sécurité | K90: Mettre à jour trimestriellement
G91: Procès-verbal de validation | H91: Approbations non formalisées | I91: Moyenne | J91: Décisions contestables | K91: Signature électronique obligatoire
D92: Les écarts par rapport aux standards technologiques sont justifiés et planifiés | E92: Les écarts par rapport aux standards technologiques sont-ils justifiés et planifiés ? | F92: Pas | G92: Demandes de dérogation | H92: Prolifération de technologies non standards | I92: Élevée | J92: Complexité accrue du parc | K92: Instaurer un comité de validation
G93: Analyse d'impact | H93: Décisions non documentées | I93: Moyenne | J93: Manque de traçabilité | K93: Archivage centralisé
D94: Les compétences internes sont alignées sur le paysage technologique cible | E94: Les compétences internes sont-elles alignées sur le paysage technologique cible ? | F94: Non | G94: Plan de développement des compétences | H94: Inadéquation des compétences | I94: Élevée | J94: Retards sur les projets clés | K94: Cartographier les besoins annuellement
G95: Évaluations individuelles | H95: Lacunes non identifiées | I95: Moyenne | J95: Sous-performance persistante | K95: Entretiens semestriels
D96: Les coûts de licence et de maintenance sont optimisés par une approche consolidée | E96: Les coûts de licence et de maintenance sont-ils optimisés par une approche consolidée ? | F96: Oui | G96: Inventaire des licences | H96: Sur-achat de licences | I96: Moyenne | J96: Gaspillage budgétaire | K96: Audit semestriel
G97: Dashboard d'utilisation | H97: Sous-utilisation des outils | I97: Moyenne | J97: ROI insuffisant | K97: Alertes automatiques
D98: Un plan de migration progressive vers les standards est défini et budgété | E98: Un plan de migration progressive vers les standards est-il défini et budgété ? | F98: Oui | G98: Feuille de route de migration | H98: Retard dans les migrations | I98: Élevée | J98: Coûts de maintenance élevés | K98: Budget dédié
G99: Calendrier des migrations | H99: Délais non respectés | I99: Moyenne | J99: Prolongation du risque | K99: Points mensuels de suivi
C100: Vérifier l’existence et l’unicité des référentiels (clients, fournisseurs, articles…) et des saisies | D100: Un processus de gestion des données maîtres (MDM) est en place et appliqué | E100: Un processus de gestion des données maîtres (MDM) est-il en place et appliqué ? | F100: Oui | G100: Charte de gestion des données | H100: Incohérences dans les données | I100: Élevée | J100: Erreurs décisionnelles | K100: Nommer un data owner
...

Sheet 4.3.Projets_Informatiques
A1: Domaines | B1: Points de contrôle | C1: Objectifs de contrôle | D1: Critères d'évaluation | E1: Questions d'évaluation | F1: Réponses | G1: Documents requis | H1: Risques | I1: Criticité | J1: Conséquences | K1: Recommandations
A2: Projets informatiques | B2: Objectifs et enjeux du projet | C2: S’assurer qu’une étude de la valeur et des études d'opportunité et d'impacts ont été réalisées | D2: L’étude de la valeur du projet a été formellement documentée. | E2: L’étude de la valeur du projet a-t-elle été formellement documentée ? | F2: Oui | G2: Rapport d’étude de valeur | H2: Valeur mal estimée | I2: Élevée | J2: Mauvaise allocation des ressources | K2: Formaliser et valider l’étude avec les parties prenantes
G3: Présentation synthétique pour la direction | H3: Manque de visibilité | I3: Moyenne | J3: Décisions stratégiques erronées | K3: Communiquer clairement les résultats à la direction
D4: Une analyse coûts/bénéfices a été menée et validée. | E4: Une analyse coûts/bénéfices a-t-elle été menée et validée ? | F4: Oui | G4: Rapport d’analyse coûts/bénéfices | H4: Sous-estimation des coûts | I4: Élevée | J4: Dépassements budgétaires | K4: Réaliser une analyse détaillée et validée
G5: Validation formelle par comité projet | H5: Absence de validation | I5: Moyenne | J5: Retards dans la prise de décision | K5: Obtenir une validation formelle et documentée
D6: Les parties prenantes ont été consultées pour identifier les opportunités. | E6: Les parties prenantes ont-elles été consultées pour identifier les opportunités ? | F6: Oui | G6: Compte rendu des ateliers de consultation | H6: Opportunités non identifiées | I6: Moyenne | J6: Perte d’avantages compétitifs | K6: Impliquer toutes les parties prenantes clés
G7: Liste des parties prenantes consultées | H7: Omission d’acteurs clés | I7: Moyenne | J7: Résistance au changement | K7: Assurer une cartographie complète des parties prenantes
D8: Les impacts sur l’organisation, les processus et les utilisateurs ont été évalués. | E8: Les impacts sur l’organisation, les processus et les utilisateurs ont-ils été évalués ? | F8: Oui | G8: Rapport d’évaluation d’impacts | H8: Impacts non anticipés | I8: Élevée | J8: Résistances, échecs | K8: Réaliser une évaluation complète et multidimensionnelle
G9: Synthèse des retours utilisateurs | H9: Retours incomplets | I9: Moyenne | J9: Insatisfaction | K9: Collecter et analyser systématiquement les retours
D10: Des scénarios alternatifs ont été envisagés et comparés | E10: Des scénarios alternatifs ont-ils été envisagés et comparés ? | F10: Oui | G10: Document d’analyse comparative des scénarios | H10: Choix non optimal | I10: Élevée | J10: Surcoûts, inefficacité | K10: Étudier plusieurs scénarios avec critères objectifs
G11: Tableau comparatif synthétique | H11: Manque de clarté | I11: Moyenne | J11: Difficulté de décision | K11: Présenter un tableau clair et accessible
C12: S’assurer qu’un bilan critique des processus existants a été effectué | D12: Les processus métiers actuels ont été cartographiés. | E12: Les processus métiers actuels ont-ils été cartographiés ? | F12: Oui | G12: Cartographie des processus | H12: Processus non connus | I12: Élevée | J12: Mauvaise gestion du changement | K12: Réaliser une cartographie précise et à jour
G13: Documentation des processus | H13: Documentation incomplète | I13: Moyenne | J13: Confusion | K13: Maintenir une documentation exhaustive
D14: Des indicateurs de performance des processus existants ont été collectés. | E14: Des indicateurs de performance des processus existants ont-ils été collectés ? | F14: Non | G14: Tableau de bord des indicateurs | H14: Absence de mesure | I14: Moyenne | J14: Difficulté à piloter | K14: Mettre en place des indicateurs pertinents
G15: Rapport d’analyse des indicateurs | H15: Analyse insuffisante | I15: Moyenne | J15: Mauvaise prise de décision | K15: Analyser régulièrement les indicateurs
D16: Des entretiens avec les utilisateurs clés ont permis d’identifier les dysfonctionnements. | E16: Des entretiens avec les utilisateurs clés ont-ils permis d’identifier les dysfonctionnements ? | F16: Non | G16: Synthèse des entretiens | H16: Dysfonctionnements non détectés | I16: Moyenne | J16: Problèmes non résolus | K16: Organiser des entretiens structurés
G17: Liste des utilisateurs interviewés | H17: Échantillon non représentatif | I17: Moyenne | J17: Biais dans l’analyse | K17: Sélectionner un panel représentatif
D18: Les processus ont été évalués selon leur efficience et leur efficacité. | E18: Les processus ont-ils été évalués selon leur efficience et leur efficacité ? | F18: Pas | G18: Rapport d’évaluation des processus | H18: Évaluation partielle | I18: Moyenne | J18: Améliorations non ciblées | K18: Utiliser des critères clairs et mesurables
G19: Plan d’action d’amélioration | H19: Absence de plan | I19: Moyenne | J19: Stagnation | K19: Définir un plan d’amélioration concret
D20: Des pistes d’amélioration internes ont été proposées | E20: Des pistes d’amélioration internes ont-elles été proposées ? | F20: Oui | G20: Rapport de recommandations | H20: Absence d’amélioration | I20: Moyenne | J20: Perte d’opportunités | K20: Proposer des pistes réalistes et priorisées
G21: Plan de mise en œuvre | H21: Non suivi des recommandations | I21: Moyenne | J21: Résultats limités | K21: Assurer le suivi et la mise en œuvre
C22: S’assurer que le choix de recourir à un nouveau système est obtenu après optimisation des processus concernés et vérification que cette optimisation ne suffit pas à apporter par elle-même les gains de performance attendus | D22: Une démarche d’optimisation des processus existants a été engagée avant le choix du nouveau système. | E22: Une démarche d’optimisation des processus existants a-t-elle été engagée avant le choix du nouveau système ? | F22: Pas | G22: Rapport de démarche d’optimisation | H22: Saut direct vers solution coûteuse | I22: Élevée | J22: Surcoûts, inefficacité | K22: Prioriser l’optimisation avant changement
G23: Analyse comparative avant/après optimisation | H23: Absence de comparaison | I23: Moyenne | J23: Décision non justifiée | K23: Documenter les gains attendus
D24: Les résultats de l’optimisation ont été mesurés à l’aide d’indicateurs concrets. | E24: Les résultats de l’optimisation ont-ils été mesurés à l’aide d’indicateurs concrets ? | F24: Non | G24: Rapport d’indicateurs post-optimisation | H24: Résultats non mesurés | I24: Moyenne | J24: Difficulté à justifier le projet | K24: Mettre en place des indicateurs clairs
G25: Tableau de suivi des indicateurs | H25: Données non actualisées | I25: Moyenne | J25: Analyse erronée | K25: Actualiser régulièrement les données
D26: Un comparatif des gains attendus via optimisation seule vs. avec nouveau système a été établi. | E26: Un comparatif des gains attendus via optimisation seule vs. avec nouveau système a-t-il été établi ? | F26: Non | G26: Rapport comparatif | H26: Décision biaisée | I26: Élevée | J26: Choix non optimal | K26: Réaliser un comparatif objectif et documenté
G27: Présentation synthétique | H27: Manque de clarté | I27: Moyenne | J27: Difficulté à convaincre | K27: Présenter clairement les résultats
D28: Le choix du nouveau système est justifié par un écart de performance non couvert par l’optimisation. | E28: Le choix du nouveau système est-il justifié par un écart de performance non couvert par l’optimisation ? | F28: Non | G28: Rapport de justification | H28: Choix non justifié | I28: Élevée | J28: Investissement inutile | K28: Documenter clairement les écarts de performance
G29: Avis d’expert externe | H29: Absence d’avis indépendant | I29: Moyenne | J29: Risque de partialité | K29: Solliciter un expert reconnu
D30: Un avis d’expert métier ou externe a validé la nécessité du changement de système | E30: Un avis d’expert métier ou externe a-t-il validé la nécessité du changement de système ? | F30: Oui | G30: Rapport d’expertise | H30: Validation insuffisante | I30: Moyenne | J30: Décision contestée | K30: Obtenir un avis formel et documenté
G31: Lettre de mission de l’expert | H31: Absence de mandat clair | I31: Moyenne | J31: Risque de non-conformité | K31: Formaliser la mission de l’expert
C32: S’assurer que les principales orientations du système cible ont été explicitées | D32: Les fonctionnalités principales du système cible ont été définies et documentées. | E32: Les fonctionnalités principales du système cible ont-elles été définies et documentées ? | F32: Oui | G32: Cahier des charges fonctionnel | H32: Fonctionnalités floues | I32: Élevée | J32: Non-conformité | K32: Définir précisément les fonctionnalités clés
G33: Spécifications fonctionnelles détaillées | H33: Documentation incomplète | I33: Moyenne | J33: Mauvaise implémentation | K33: Compléter et valider les spécifications
D34: Les priorités fonctionnelles et techniques ont été clairement exprimées. | E34: Les priorités fonctionnelles et techniques ont-elles été clairement exprimées ? | F34: Non | G34: Document de priorisation | H34: Priorités confuses | I34: Moyenne | J34: Retards, conflits | K34: Clarifier et communiquer les priorités
G35: Plan de release ou roadmap | H35: Absence de planification | I35: Moyenne | J35: Mauvaise gestion des versions | K35: Planifier les releases selon priorités
D36: Les objectifs métiers traduits dans le système ont été formalisés. | E36: Les objectifs métiers traduits dans le système ont-ils été formalisés ? | F36: Pas | G36: Document d’objectifs métiers | H36: Objectifs non alignés | I36: Élevée | J36: Insatisfaction utilisateur | K36: Formaliser et valider les objectifs métiers
G37: Matrice de traçabilité objectifs-fonctionnalités | H37: Traçabilité insuffisante | I37: Moyenne | J37: Perte de contrôle | K37: Maintenir une matrice à jour
D38: Les contraintes technologiques et réglementaires ont été intégrées dans les orientations. | E38: Les contraintes technologiques et réglementaires ont-elles été intégrées dans les orientations ? | F38: Pas | G38: Document d’orientations techniques et réglementaires | H38: Non-conformité | I38: Élevée | J38: Sanctions, risques | K38: Intégrer toutes les contraintes dès la conception
G39: Rapport de conformité réglementaire | H39: Non-respect des normes | I39: Élevée | J39: Amendes, blocages | K39: Assurer la conformité réglementaire
D40: Les choix d’architecture du système (cloud, ERP, spécifique, etc.) ont été justifiés | E40: Les choix d’architecture du système (cloud, ERP, spécifique, etc.) ont-ils été justifiés ? | F40: Oui | G40: Document d’architecture | H40: Choix non argumentés | I40: Moyenne | J40: Risques techniques | K40: Justifier les choix avec analyses et comparatifs
G41: Rapport d’analyse d’architecture | H41: Absence d’analyse | I41: Moyenne | J41: Mauvaise performance | K41: Réaliser une analyse approfondie
C42: S’assurer que les principaux acteurs sont identifiés | D42: Une cartographie des parties prenantes a été établie. | E42: Une cartographie des parties prenantes a-t-elle été établie ? | F42: Oui | G42: Cartographie des parties prenantes | H42: Omission d’acteurs | I42: Moyenne | J42: Résistances | K42: Réaliser une cartographie complète et mise à jour
G43: Registre des parties prenantes | H43: Données obsolètes | I43: Moyenne | J43: Mauvaise communication | K43: Actualiser régulièrement
D44: Les rôles et responsabilités de chaque acteur ont été définis. | E44: Les rôles et responsabilités de chaque acteur ont-ils été définis ? | F44: Oui | G44: Matrice RACI | H44: Confusion des rôles | I44: Moyenne | J44: Inefficacité | K44: Définir clairement les rôles et responsabilités
G45: Fiches de poste | H45: Ambiguïtés | I45: Moyenne | J45: Manque d’engagement | K45: Clarifier et valider les fiches
D46: Les acteurs clés internes et externes sont clairement nommés. | E46: Les acteurs clés internes et externes sont-ils clairement nommés ? | F46: Oui | G46: Liste des acteurs clés | H46: Manque de visibilité | I46: Moyenne | J46: Difficulté de mobilisation | K46: Nommer clairement tous les acteurs clés
G47: Organigramme projet | H47: Flou organisationnel | I47: Moyenne | J47: Retards | K47: Formaliser l’organigramme
D48: Le sponsor du projet est identifié et engagé. | E48: Le sponsor du projet est-il identifié et engagé ? | F48: Oui | G48: Lettre de nomination du sponsor | H48: Absence de sponsor | I48: Élevée | J48: Manque de soutien stratégique | K48: Identifier et engager un sponsor officiel
G49: Plan de communication sponsor | H49: Manque de visibilité | I49: Moyenne | J49: Faible soutien | K49: Communiquer régulièrement avec le sponsor
D50: Les utilisateurs finaux ont été représentés dans les instances projet | E50: Les utilisateurs finaux ont-ils été représentés dans les instances projet ? | F50: Non | G50: Liste des représentants utilisateurs | H50: Non-représentation | I50: Moyenne | J50: Solutions inadaptées | K50: Impliquer les utilisateurs dans les instances clés
G51: Procès-verbaux de réunions | H51: Absence de participation | I51: Moyenne | J51: Décisions non validées | K51: Documenter la participation utilisateur
B52: Étude d'opportunité et expression des besoins | C52: S’assurer que l'expression détaillée des besoins est formalisée dans un cahier des charges fait par la MOA | D52: Un cahier des charges rédigé par la MOA est disponible et validé. | E52: Un cahier des charges rédigé par la MOA est-il disponible et validé ? | F52: Non | G52: Cahier des charges MOA validé | H52: Exigences floues | I52: Élevée | J52: Non-conformité | K52: Rédiger et valider un cahier des charges complet
G53: Procès-verbal de validation | H53: Absence de validation | I53: Moyenne | J53: Retards | K53: Obtenir une validation formelle
D54: Les besoins fonctionnels sont décrits de manière exhaustive et structurée. | E54: Les besoins fonctionnels sont-ils décrits de manière exhaustive et structurée ? | F54: Non | G54: Document des besoins fonctionnels | H54: Oublis | I54: Élevée | J54: Fonctionnalités manquantes | K54: Documenter exhaustivement les besoins
G55: Modèle de spécifications fonctionnelles | H55: Structure inadéquate | I55: Moyenne | J55: Difficulté de lecture | K55: Utiliser un modèle standardisé
D56: Les besoins techniques sont mentionnés lorsque nécessaire. | E56: Les besoins techniques sont-ils mentionnés lorsque nécessaire ? | F56: Non | G56: Document des besoins techniques | H56: Omission technique | I56: Moyenne | J56: Problèmes d’intégration | K56: Intégrer les besoins techniques dans les spécifications
G57: Rapport d’analyse technique | H57: Analyse incomplète | I57: Moyenne | J57: Risques techniques | K57: Compléter l’analyse technique
D58: Les cas d’usage ou scénarios utilisateurs sont inclus dans le document. | E58: Les cas d'usage ou scénarios utilisateurs sont-ils inclus dans le document ? | F58: Non | G58: Document des cas d’usage | H58: Absence de scénarios | I58: Moyenne | J58: Mauvaise compréhension | K58: Inclure des scénarios représentatifs
G59: Modèle de cas d’usage | H59: Non standardisé | I59: Moyenne | J59: Difficulté d’utilisation | K59: Utiliser un modèle reconnu
D60: Les exigences sont exprimées en langage métier compréhensible | E60: Les exigences sont-elles exprimées en langage métier compréhensible ? | F60: Non | G60: Document d’exigences métier | H60: Difficulté de compréhension | I60: Moyenne | J60: Mauvaise implémentation | K60: Rédiger en langage clair et accessible
G61: Glossaire métier | H61: Absence de définitions | I61: Moyenne | J61: Confusion | K61: Fournir un glossaire clair
C62: S’assurer que le cahier des charges préconise une solution fonctionnellement et techniquement pertinente au regard des besoins exprimés | D62: Le cahier des charges propose des scénarios de solutions adaptés aux besoins. | E62: Le cahier des charges propose-t-il des scénarios de solutions adaptés aux besoins ? | F62: Pas | G62: Document de scénarios de solutions | H62: Solutions inadaptées | I62: Moyenne | J62: Échec du projet | K62: Proposer plusieurs scénarios adaptés
G63: Analyse comparative des solutions | H63: Analyse partielle | I63: Moyenne | J63: Choix non optimal | K63: Réaliser une analyse complète
D64: Les préconisations tiennent compte des contraintes techniques de l’organisation. | E64: Les préconisations tiennent-elles compte des contraintes techniques de l'organisation ? | F64: Pas | G64: Rapport de préconisations | H64: Non prise en compte des contraintes | I64: Moyenne | J64: Incompatibilités | K64: Intégrer les contraintes organisationnelles
G65: Document d’architecture cible | H65: Non aligné | I65: Moyenne | J65: Risques techniques | K65: Aligner avec l’architecture existante
D66: Les solutions envisagées répondent aux fonctionnalités attendues. | E66: Les solutions envisagées répondent-elles aux fonctionnalités attendues ? | F66: Pas | G66: Cahier des charges fonctionnel | H66: Fonctionnalités non couvertes | I66: Élevée | J66: Insatisfaction | K66: Vérifier la couverture fonctionnelle
G67: Rapport d’évaluation des solutions | H67: Évaluation incomplète | I67: Moyenne | J67: Choix inadapté | K67: Évaluer rigoureusement les solutions
D68: Une analyse de faisabilité technique est intégrée dans le document. | E68: Une analyse de faisabilité technique est-elle intégrée dans le document ? | F68: Pas | G68: Rapport de faisabilité technique | H68: Risques non identifiés | I68: Élevée | J68: Échecs techniques | K68: Réaliser une analyse complète et documentée
G69: Validation de faisabilité | H69: Absence de validation | I69: Moyenne | J69: Retards | K69: Obtenir une validation formelle
D70: La pertinence des solutions est justifiée par rapport aux objectifs du projet | E70: La pertinence des solutions est-elle justifiée par rapport aux objectifs du projet ? | F70: Pas | G70: Rapport de justification | H70: Choix non justifié | I70: Moyenne | J70: Perte de temps et ressources | K70: Documenter clairement la justification
G71: Présentation synthétique | H71: Manque de clarté | I71: Moyenne | J71: Difficulté d’adhésion | K71: Présenter clairement les arguments
C72: S’assurer que les exigences utilisateurs, les populations ciblées, les options et principes de gestion retenus sont précisés et priorisés | D72: Les exigences des utilisateurs sont listées de manière explicite. | E72: Les exigences des utilisateurs sont-elles listées de manière explicite ? | F72: Pas | G72: Cahier des charges utilisateur | H72: Exigences floues ou incomplètes | I72: Élevée | J72: Mauvaise compréhension des besoins | K72: Documenter clairement chaque exigence utilisateur
G73: User stories ou spécifications fonctionnelles | H73: Exigences non testables ou ambiguës | I73: Moyenne | J73: Difficulté de validation | K73: Rédiger des exigences précises et testables
D74: Les profils des populations ciblées sont définis (ex : utilisateurs métier, clients, etc.). | E74: Les profils des populations ciblées sont-ils définis (ex : utilisateurs métier, clients, etc.) ? | F74: Pas | G74: Analyse des parties prenantes | H74: Omission de profils clés | I74: Moyenne | J74: Solutions inadaptées | K74: Identifier et documenter tous les profils utilisateurs
G75: Registre des utilisateurs cibles | H75: Données obsolètes ou incomplètes | I75: Moyenne | J75: Mauvaise prise en compte des besoins | K75: Mettre à jour régulièrement le registre
D76: Les options fonctionnelles retenues sont argumentées. | E76: Les options fonctionnelles retenues sont-elles argumentées ? | F76: Pas | G76: Rapport d’analyse fonctionnelle | H76: Choix non justifiés | I76: Moyenne | J76: Fonctionnalités inadaptées | K76: Justifier chaque option fonctionnelle retenue
G77: Présentation aux parties prenantes | H77: Manque de transparence | I77: Moyenne | J77: Résistance au changement | K77: Communiquer clairement les choix et leurs raisons
D78: Les principes de gestion (flux, autorisations, niveaux de responsabilité) sont décrits. | E78: Les principes de gestion (flux, autorisations, niveaux de responsabilité) sont-ils décrits ? | F78: Pas | G78: Document de gouvernance fonctionnelle | H78: Manque de clarté | I78: Moyenne | J78: Confusion dans les responsabilités | K78: Formaliser les principes de gestion
G79: Manuel des procédures | H79: Procédures non suivies | I79: Moyenne | J79: Erreurs opérationnelles | K79: Diffuser et former aux procédures
D80: Les exigences sont classées selon leur niveau de priorité | E80: Les exigences sont-elles classées selon leur niveau de priorité ? | F80: Oui | G80: Matrice de priorisation des exigences | H80: Priorisation floue | I80: Moyenne | J80: Ressources mal allouées | K80: Classer les exigences selon leur criticité
G81: Rapport de validation des priorités | H81: Absence de validation | I81: Moyenne | J81: Conflits | K81: Valider la priorisation avec les parties prenantes
C82: S’assurer que le projet est cohérent avec le plan directeur informatique | D82: Le projet est mentionné ou intégré dans le plan directeur informatique (PDI). | E82: Le projet est-il mentionné ou intégré dans le plan directeur informatique (PDI) ? | F82: Oui | G82: Plan directeur informatique (PDI) | H82: Projet non aligné | I82: Élevée | J82: Manque de cohérence stratégique | K82: Intégrer le projet dans le PDI
G83: Rapport d’alignement stratégique | H83: Absence d’analyse d’alignement | I83: Moyenne | J83: Décalage stratégique | K83: Réaliser une analyse d’alignement régulière
D84: Les objectifs du projet sont alignés avec les axes stratégiques du PDI. | E84: Les objectifs du projet sont-ils alignés avec les axes stratégiques du PDI ? | F84: Oui | G84: Document d’objectifs projet | H84: Objectifs divergents | I84: Élevée | J84: Perte d’efficacité | K84: Aligner les objectifs avec la stratégie SI
G85: Validation par comité stratégique | H85: Validation manquante | I85: Moyenne | J85: Décision non cohérente | K85: Obtenir une validation formelle
D86: Le calendrier du projet est compatible avec la feuille de route SI. | E86: Le calendrier du projet est-il compatible avec la feuille de route SI ? | F86: Oui | G86: Planning projet | H86: Incompatibilité des calendriers | I86: Moyenne | J86: Retards, conflits | K86: Synchroniser le planning avec la feuille de route SI
G87: Rapport de suivi de planning | H87: Suivi insuffisant | I87: Moyenne | J87: Dépassements | K87: Mettre en place un suivi rigoureux
D88: Les technologies retenues sont en adéquation avec celles recommandées par le PDI. | E88: Les technologies retenues sont-elles en adéquation avec celles recommandées par le PDI ? | F88: Non | G88: Document technique de choix technologiques | H88: Technologies incompatibles | I88: Moyenne | J88: Difficultés d’intégration | K88: Choisir des technologies conformes au PDI
G89: Analyse comparative technologique | H89: Analyse incomplète | I89: Moyenne | J89: Risques techniques | K89: Réaliser une analyse complète
D90: Le projet respecte les orientations en matière de cybersécurité définies dans le PDI | E90: Le projet respecte-t-il les orientations en matière de cybersécurité définies dans le PDI ? | F90: Oui | G90: Politique cybersécurité | H90: Non-conformité | I90: Élevée | J90: Vulnérabilités | K90: Appliquer les orientations cybersécurité du PDI
G91: Rapport d’audit sécurité | H91: Absence d’audit | I91: Moyenne | J91: Risques non détectés | K91: Réaliser des audits réguliers
C92: S’assurer que le projet est cohérent avec le SI actuel ou futur | D92: L’analyse de compatibilité avec l’architecture du SI actuel a été réalisée. | E92: L'analyse de compatibilité avec l'architecture du SI actuel a-t-elle été réalisée ? | F92: Pas | G92: Rapport d’analyse d’architecture | H92: Incompatibilités non détectées | I92: Élevée | J92: Dysfonctionnements | K92: Effectuer une analyse complète de compatibilité
G93: Schéma d’architecture cible | H93: Documentation incomplète | I93: Moyenne | J93: Difficulté d’intégration | K93: Maintenir à jour la documentation
D94: Le projet respecte les normes et standards du SI en place. | E94: Le projet respecte-t-il les normes et standards du SI en place ? | F94: Non | G94: Document de conformité aux normes | H94: Non-respect des normes | I94: Élevée | J94: Sanctions, échecs | K94: Respecter les normes et standards SI
G95: Rapport de conformité | H95: Absence de rapport | I95: Moyenne | J95: Non-conformité | K95: Mettre en place un suivi de conformité
D96: L’interopérabilité avec les applications existantes est assurée. | E96: L'interopérabilité avec les applications existantes est-elle assurée ? | F96: Oui | G96: Plan d’intégration | H96: Problèmes d’interopérabilité | I96: Élevée | J96: Incidents en production | K96: Planifier et tester l’intégration complète
G97: Rapport de tests d’intégration | H97: Tests incomplets | I97: Moyenne | J97: Incidents | K97: Réaliser des tests exhaustifs
D98: Les interfaces prévues sont compatibles avec les outils actuels. | E98: Les interfaces prévues sont-elles compatibles avec les outils actuels ? | F98: Oui | G98: Spécifications d’interfaces | H98: Incompatibilités | I98: Moyenne | J98: Erreurs de communication | K98: Vérifier la compatibilité des interfaces
G99: Documentation technique | H99: Documentation insuffisante | I99: Moyenne | J99: Difficulté d’utilisation | K99: Compléter la documentation
D100: Les impacts du projet sur le SI existant ont été identifiés et évalués | E100: Les impacts du projet sur le SI existant ont-ils été identifiés et évalués ? | F100: Oui | G100: Rapport d’impact SI | H100: Impacts non anticipés | I100: Élevée | J100: Perturbations | K100: Évaluer tous les impacts avant déploiement
...

Sheet 4.4.SupportUser_GestParc
A1: Domaine | B1: Points de contrôle | C1: Objectifs de contrôle | D1: Critères d'évaluation | E1: Questions d'évaluation | F1: Réponses | G1: Documents requis | H1: Risques | I1: Criticité | J1: Conséquences | K1: Recommandations
A2: Support utilisateur et de la gestion du parc | B2: Fonction support : audit fiabilité et sécurité | C2: S’assurer qu’une structure de centre d’assistance (help-desk) (HD) est mise en place | D2: La structure organisationnelle du HD est formalisée et documentée | E2: La structure organisationnelle du HD est-elle formalisée et documentée ? | F2: Oui | G2: Organigramme du HD | H2: Manque de clarification des rôles | I2: Moyenne | J2: Retards dans le traitement, conflits internes | K2: Mise à jour régulière nécessaire
G3: Fiches de poste | H3: Doublons ou lacunes dans les tâches | I3: Moyenne | J3: Inefficacité opérationnelle | K3: Validation par la direction
D4: Les rôles et responsabilités des membres du HD sont clairement définis | E4: Les rôles et responsabilités des membres du HD sont-ils clairement définis ? | F4: Oui | G4: Fiches de poste détaillées | H4: Confusion des responsabilités | I4: Moyenne | J4: Retards de traitement, conflits internes | K4: Mettre à jour les fiches annuellement et les valider par la hiérarchie.
G5: Matrice RACI (Responsable/Consulté/Informé) | H5: Doublons ou lacunes dans les tâches | I5: Moyenne | J5: Inefficacité opérationnelle | K5: Former les équipes à l’utilisation de la matrice.
D6: Les moyens humains et matériels alloués au HD sont suffisants pour assurer son fonctionnement | E6: Les moyens humains et matériels alloués au HD sont-ils suffisants pour assurer son fonctionnement ? | F6: Oui | G6: Budget annuel du HD | H6: Sous-effectif chronique | I6: Élevée | J6: Surcharge des équipes, dégradation du service | K6: Audit annuel recommandé
G7: Inventaire des ressources | H7: Pannes techniques fréquentes | I7: Moyenne | J7: Interruptions de service | K7: Plan de renouvellement du matériel
D8: Une charte ou un document de référence décrit les missions et le périmètre d’intervention du HD | E8: Une charte ou un document de référence décrit-il les missions et le périmètre d’intervention du HD ? | F8: Oui | G8: Charte du HD | H8: Dépassement du périmètre d'intervention | I8: Moyenne | J8: Conflits avec d'autres services | K8: Communication obligatoire à tous
G9: SLA (Accord de niveau de service) | H9: Non-respect des engagements | I9: Élevée | J9: Perte de confiance des utilisateurs | K9: Revue annuelle
D10: Une équipe dédiée est identifiée pour assurer la gestion des appels et des tickets | E10: Une équipe dédiée est-elle identifiée pour assurer la gestion des appels et des tickets ? | F10: Oui | G10: Liste de l'équipe support | H10: Absence de responsables identifiés | I10: Élevée | J10: Demandes non traitées, désorganisation | K10: Système de backup nécessaire
G11: Planning de permanence | H11: Manque de couverture horaire | I11: Moyenne | J11: Retards de réponse hors horaires | K11: Adapter aux pics d’activité
C12: S’assurer qu’une procédure de gestion des demandes d’assistance est diffusée et connue des utilisateurs | D12: La procédure de gestion des demandes d’assistance est documentée et accessible aux utilisateurs | E12: La procédure de gestion des demandes d’assistance est-elle documentée et accessible aux utilisateurs ? | F12: Oui | G12: Manuel de procédures | H12: Procédures obsolètes | I12: Moyenne | J12: Erreurs de traitement | K12: Système de versioning
G13: FAQ utilisateurs | H13: Mauvais usage du service | I13: Faible | J13: Demandes inappropriées | K13: Rendre la FAQ interactive (chatbot)
D14: Un rappel périodique des bonnes pratiques est diffusé aux utilisateurs | E14: Un rappel périodique des bonnes pratiques est-il diffusé aux utilisateurs ? | F14: Non | G14: Newsletter mensuelle | H14: Mauvaise adoption des outils | I14: Moyenne | J14: Augmentation des demandes basiques | K14: Mesurer l’impact via sondages
G15: Guide des bonnes pratiques | H15: Non-conformité persistante | I15: Moyenne | J15: Risques de sécurité | K15: Lier aux politiques de sécurité
D16: Les utilisateurs ont été formés ou informés sur les modalités de contact du HD | E16: Les utilisateurs ont-ils été formés ou informés sur les modalités de contact du HD ? | F16: Non | G16: Plan de formation | H16: Méconnaissance des canaux | I16: Moyenne | J16: Surcharge des canaux prioritaires | K16: Intégrer à l’onboarding
G17: Support visuel (affiches) | H17: Canaux mal utilisés | I17: Faible | J17: Contacts inefficaces | K17: Affichage en zones communes
D18: La procédure est affichée sur l’intranet ou un support accessible à tous les utilisateurs | E18: La procédure est-elle affichée sur l’intranet ou un support accessible à tous les utilisateurs ? | F18: Pas | G18: Page Intranet dédiée | H18: Information non actualisée | I18: Moyenne | J18: Procédures non suivies | K18: Désigner un responsable de mise à jour
G19: Application mobile | H19: Fracture numérique | I19: Faible | J19: Exclusion de certains utilisateurs | K19: Prévoir un support alternatif
D20: Un mécanisme de feedback permet de vérifier la compréhension des utilisateurs | E20: Un mécanisme de feedback permet-il de vérifier la compréhension des utilisateurs ? | F20: Oui | G20: Formulaire de satisfaction | H20: Améliorations non identifiées | I20: Moyenne | J20: Stagnation de la qualité | K20: Automatiser l’analyse des feedbacks
G21: Statistiques d'utilisation | H21: Besoins utilisateurs évolutifs | I21: Moyenne | J21: Inadéquation du service | K21: Croiser avec les tickets traités
C22: S’assurer qu’une procédure d'escalade mise en place | D22: La procédure d'escalade est formalisée et intégrée dans le processus de gestion des tickets | E22: La procédure d'escalade est-elle formalisée et intégrée dans le processus de gestion des tickets ? | F22: Pas | G22: Arbre d'escalade | H22: Blocages fréquents | I22: Élevée | J22: Résolution retardée des incidents critiques | K22: Simulations régulières
G23: Historique des escalades | H23: Erreurs répétées | I23: Moyenne | J23: Perte de temps et ressources | K23: Analyse trimestrielle
D24: Les niveaux d'escalade (niveau 1, niveau 2, expert, etc.) sont clairement définis | E24: Les niveaux d'escalade (niveau 1, niveau 2, expert, etc.) sont-ils clairement définis ? | F24: Non | G24: Matrice de compétences | H24: Escalades inappropriées | I24: Moyenne | J24: Surcharge des experts | K24: Associer des temps de réponse
G25: Annuaire des référents | H25: Contacts erronés | I25: Moyenne | J25: Retards dans la résolution | K25: Mise à jour en temps réel
D26: Les acteurs concernés par l'escalade sont identifiés et formés | E26: Les acteurs concernés par l'escalade sont-ils identifiés et formés ? | F26: Non | G26: Planning de formation | H26: Manque de compétences | I26: Élevée | J26: Dégradation du service | K26: Certification annuelle
G27: Registre des habilitations | H27: Accès non autorisés | I27: Moyenne | J27: Risques de sécurité | K27: Audit semestriel
D28: Des tests périodiques valident l’efficacité de la procédure d'escalade | E28: Des tests périodiques valident-ils l’efficacité de la procédure d'escalade? | F28: Non | G28: Compte-rendu de tests | H28: Procédure inefficace | I28: Moyenne | J28: Échec en situation réelle | K28: Scénarios réalistes
G29: Rapport d’améliorations | H29: Corrections non appliquées | I29: Moyenne | J29: Persistance des dysfonctionnements | K29: Suivi rigoureux des actions correctives
D30: Les délais de traitement par niveau d'escalade sont précisés et respectés | E30: Les délais de traitement par niveau d'escalade sont-ils précisés et respectés ? | F30: Oui | G30: SLA (Accord de niveau de service) | H30: Délais non respectés | I30: Élevée | J30: Insatisfaction des utilisateurs, perte de confiance | K30: Auditer mensuellement les délais et ajuster les ressources si nécessaire.
G31: Dashboard de suivi des tickets | H31: Dérives non détectées | I31: Moyenne | J31: Accumulation de retards critiques | K31: Automatiser les alertes de dépassement de délais.
C32: S’assurer de la couverture géographique du HD | D32: Le HD couvre l’ensemble des sites géographiques de l’organisation | E32: Le HD couvre-t-il l’ensemble des sites géographiques de l’organisation ? | F32: Oui | G32: Cartographie des sites couverts | H32: Zones non couvertes | I32: Élevée | J32: Inégalité de service entre sites | K32: Étendre le support via des partenariats locaux ou du télétravail.
G33: Rapport de couverture géographique | H33: Besoins locaux mal évalués | I33: Moyenne | J33: Frustration des utilisateurs | K33: Réaliser des enquêtes terrain annuelles.
D34: Les horaires d’ouverture du HD sont adaptés aux fuseaux horaires des différents sites | E34: Les horaires d’ouverture du HD sont-ils adaptés aux fuseaux horaires des différents sites ? | F34: Non | G34: Planning des plages horaires | H34: Désynchronisation des fuseaux | I34: Moyenne | J34: Demandes non traitées en temps utile | K34: Adopter un système de roulement ou de support 24/7 mutualisé.
G35: Registre des demandes hors horaire | H35: Surcharge des équipes de backup | I35: Faible | J35: Coûts supplémentaires | K35: Mettre en place un chatbot pour les demandes simples hors horaires.
D36: Un dispositif de support à distance est disponible pour les sites éloignés | E36: Un dispositif de support à distance est-il disponible pour les sites éloignés ? | F36: Pas | G36: Procédure de support à distance | H36: Indisponibilité technique | I36: Moyenne | J36: Exclusion des sites isolés | K36: Tester régulièrement les outils (VPN, accès distant).
G37: Inventaire des outils distants | H37: Outils obsolètes | I37: Faible | J37: Difficultés de connexion | K37: Migrer vers des solutions cloud sécurisées.
D38: Les utilisateurs des différentes zones géographiques confirment la disponibilité du support | E38: Les utilisateurs des différentes zones géographiques confirment-ils la disponibilité du support ? | F38: Pas | G38: Enquête de satisfaction utilisateurs | H38: Insatisfaction chronique | I38: Élevée | J38: Dégradation de l’image du HD | K38: Corriger les écarts identifiés dans un délai de 3 mois.
G39: Statistiques de disponibilité | H39: Écarts entre zones | I39: Moyenne | J39: Manque de transparence | K39: Publier un rapport trimestriel de disponibilité par site.
D40: Un plan de continuité d’activité (PCA) prévoit des solutions alternatives en cas d’indisponibilité locale | E40: Un plan de continuité d’activité (PCA) prévoit-il des solutions alternatives en cas d’indisponibilité locale ? | F40: Oui | G40: Plan de continuité d’activité (PCA) | H40: Indisponibilité prolongée | I40: Élevée | J40: Interruption majeure du service | K40: Tester le PCA deux fois par an via des scénarios réalistes.
G41: Liste des contacts d’urgence | H41: Contacts obsolètes | I41: Moyenne | J41: Retards dans la réactivation | K41: Mettre à jour les contacts trimestriellement
C42: S’assurer de la couverture fonctionnelle du HD | D42: Le périmètre fonctionnel du HD couvre l’ensemble des applications et services critiques | E42: Le périmètre fonctionnel du HD couvre-t-il l’ensemble des applications et services critiques ? | F42: Oui | G42: Cartographie des services critiques | H42: Services non couverts | I42: Élevée | J42: Impacts métiers graves | K42: Réviser la cartographie tous les 6 mois avec les métiers.
G43: Accord de couverture avec les métiers | H43: Attentes mal alignées | I43: Moyenne | J43: Conflits entre équipes | K43: Organiser des ateliers de cadrage annuels.
D44: Une cartographie des services couverts par le HD est mise à jour régulièrement | E44: Une cartographie des services couverts par le HD est-elle mise à jour régulièrement ? | F44: Oui | G44: Base de données des services | H44: Données obsolètes | I44: Moyenne | J44: Erreurs de redirection | K44: Désigner un administrateur dédié.
G45: Journal des mises à jour | H45: Manque de traçabilité | I45: Faible | J45: Difficultés d’audit | K45: Automatiser le suivi des modifications.
D46: Les compétences des agents du HD correspondent aux besoins fonctionnels des utilisateurs | E46: Les compétences des agents du HD correspondent-elles aux besoins fonctionnels des utilisateurs ? | F46: Oui | G46: Référentiel de compétences | H46: Lacunes techniques | I46: Élevée | J46: Incapacité à résoudre des incidents critiques | K46: Mettre en place un plan de formation continue.
G47: Évaluations annuelles des agents | H47: Démotivation des équipes | I47: Moyenne | J47: Turnover accru | K47: Lier les évaluations à des parcours de progression.
D48: Les demandes hors périmètre sont redirigées vers les services compétents | E48: Les demandes hors périmètre sont-elles redirigées vers les services compétents ? | F48: Oui | G48: Procédure de redirection | H48: Demandes perdues | I48: Moyenne | J48: Insatisfaction des utilisateurs | K48: Intégrer un système de suivi des redirections dans l’outil de ticketing.
G49: Annuaire des services externes | H49: Redirections inefficaces | I49: Faible | J49: Perte de temps | K49: Mettre à jour l’annuaire mensuellement.
D50: Un processus d’amélioration continue permet d’ajuster la couverture fonctionnelle | E50: Un processus d’amélioration continue permet-il d’ajuster la couverture fonctionnelle ? | F50: Non | G50: Rapport d’amélioration continue | H50: Stagnation de la qualité | I50: Moyenne | J50: Délais persistants, inefficacité | K50: Impliquer les utilisateurs dans les retours.
G51: Plan d’action correctif | H51: Actions non priorisées | I51: Faible | J51: Ressources mal utilisées | K51: Suivre les indicateurs clés (KPI) mensuellement.
C52: S’assurer qu’un outil est implémenté pour la prise d'appel et le suivi des tickets | D52: Un outil de ticketing est en place et utilisé pour tous les appels | E52: Un outil de ticketing est-il en place et utilisé pour tous les appels ? | F52: Non | G52: Politique d’utilisation du ticketing | H52: Utilisation partielle | I52: Élevée | J52: Demandes non tracées | K52: Imposer l’outil via des audits aléatoires.
G53: Logs d’accès à l’outil | H53: Contournement des procédures | I53: Moyenne | J53: Données incomplètes | K53: Bloquer les canaux non officiels (ex: emails directs)
D54: L’outil permet un suivi complet des tickets (création, attribution, résolution, clôture) | E54: L’outil permet-il un suivi complet des tickets (création, attribution, résolution, clôture) ? | F54: Non | G54: Manuel de l’outil de ticketing | H54: Étapes manquantes | I54: Moyenne | J54: Manque de transparence | K54: Former les agents aux bonnes pratiques de suivi.
G55: Audit des tickets clôturés | H55: Résolutions fictives | I55: Élevée | J55: Fausses statistiques | K55: Mettre en place des contrôles aléatoires.
D56: Les utilisateurs peuvent consulter l’état d’avancement de leurs demandes | E56: Les utilisateurs peuvent-ils consulter l’état d’avancement de leurs demandes ? | F56: Non | G56: Portail utilisateur self-service | H56: Dépendance accrue au HD | I56: Faible | J56: Charge supplémentaire pour les agents | K56: Promouvoir l’autonomie via des tutoriels.
G57: Notifications automatiques | H57: Manque de notifications | I57: Moyenne | J57: Insatisfaction des utilisateurs | K57: Configurer des alertes personnalisables
D58: L’outil génère des statistiques et indicateurs de performance | E58: L’outil génère-t-il des statistiques et indicateurs de performance ? | F58: Non | G58: Rapports de performance mensuels | H58: Décisions basées sur des données erronées | I58: Élevée | J58: Mauvaise allocation des ressources | K58: Automatiser la génération des rapports.
G59: Dashboard de supervision | H59: Réactivité retardée | I59: Moyenne | J59: Incidents non anticipés | K59: Configurer des seuils d’alerte
D60: Des sauvegardes et un plan de reprise garantissent la disponibilité de l’outil | E60: Des sauvegardes et un plan de reprise garantissent-elles la disponibilité de l’outil ? | F60: Non | G60: Plan de reprise après sinistre (PRA) | H60: Indisponibilité prolongée | I60: Élevée | J60: Interruption totale du service | K60: Tester le PRA semestriellement.
G61: Journal des sauvegardes | H61: Sauvegardes corrompues | I61: Moyenne | J61: Perte de données | K61: Vérifier les sauvegardes hebdomadairement.
C62: S’assurer que des critères à renseigner pour la qualification des tickets existent | D62: Une grille de qualification des tickets (urgence, impact, catégorie) est définie | E62: Une grille de qualification des tickets (urgence, impact, catégorie) est-elle définie ? | F62: Pas | G62: Grille de qualification (urgence/impact) | H62: Qualification incohérente | I62: Moyenne | J62: Priorisation erronée, retard sur incidents critiques | K62: Former les agents à l'utilisation de la grille et l'intégrer à l'outil.
G63: Exemples de tickets qualifiés | H63: Subjectivité dans l'évaluation | I63: Faible | J63: Inégalité de traitement | K63: Auditer 5% des tickets mensuellement pour vérifier la conformité
D64: Les champs obligatoires pour la création d’un ticket sont imposés dans l’outil | E64: Les champs obligatoires pour la création d’un ticket sont-ils imposés dans l’outil ? | F64: Oui | G64: Configuration de l'outil de ticketing | H64: Tickets incomplets | I64: Élevée | J64: Données manquantes pour le traitement | K64: Bloquer la soumission si les champs obligatoires sont vides.
G65: Guide de saisie des tickets | H65: Mauvaise compréhension des champs | I65: Moyenne | J65: Saisie erronée | K65: Ajouter des infobulles explicatives dans l'outil.
D66: Des règles de priorisation des tickets sont appliquées en fonction des critères renseignés | E66: Des règles de priorisation des tickets sont-elles appliquées en fonction des critères renseignés ? | F66: Oui | G66: Procédure de priorisation | H66: Délais non adaptés à l'urgence | I66: Élevée | J66: Incidents majeurs non traités en priorité | K66: Automatiser la priorisation via des règles dans l'outil.
G67: Historique des priorités appliquées | H67: Incohérences dans les décisions | I67: Moyenne | J67: Perte de crédibilité | K67: Revoir mensuellement les tickets mal priorisés.
D68: Les agents du HD sont formés à l’utilisation des critères de qualification | E68: Les agents du HD sont-ils formés à l’utilisation des critères de qualification ? | F68: Oui | G68: Programme de formation | H68: Erreurs récurrentes de qualification | I68: Moyenne | J68: Temps perdu en re-qualification | K68: Certifier les agents via des quiz pratiques.
G69: Fiches mémo pour agents | H69: Oublis des critères | I69: Faible | J69: Qualification partielle | K69: Distribuer des aide-mémoires physiques.
D70: Un contrôle qualité aléatoire vérifie la bonne qualification des tickets | E70: Un contrôle qualité aléatoire vérifie-t-il la bonne qualification des tickets ? | F70: Oui | G70: Rapport de contrôle qualité | H70: Dérives non détectées | I70: Moyenne | J70: Baisse de la qualité globale | K70: Auditer 10% des tickets hebdomadairement.
G71: Grille d'évaluation QA | H71: Critères de contrôle flous | I71: Faible | J71: Jugements subjectifs | K71: Standardiser la grille d'audit avec des critères mesurables.
C72: S’assurer qu’il existe une liste de questions à dérouler lors d'un appel afin préciser au mieux la demande de l'utilisateur | D72: Un script ou checklist standardisé guide les agents lors des appels | E72: Un script ou checklist standardisé guide-t-il les agents lors des appels ? | F72: Oui | G72: Script standardisé d'appel | H72: Oublis d'informations clés | I72: Moyenne | J72: Diagnostics incomplets | K72: Intégrer le script dans l'outil de ticketing.
G73: Enregistrements d'appels types | H73: Pratiques hétérogènes | I73: Faible | J73: Expérience utilisateur inégale | K73: Mettre à jour les scripts bimestriellement.
D74: La liste de questions couvre les éléments essentiels pour qualifier la demande | E74: La liste de questions couvre-t-elle les éléments essentiels pour qualifier la demande ? | F74: Oui | G74: Checklist de qualification | H74: Demandes mal comprises | I74: Élevée | J74: Solutions inadaptées | K74: Aligner la checklist sur les besoins métiers.
G75: Retours utilisateurs sur les questions | H75: Questions inutiles ou manquantes | I75: Moyenne | J75: Frustration des utilisateurs | K75: Ajouter un champ de feedback dans le ticket.
D76: Les agents appliquent systématiquement cette liste lors des premiers contacts | E76: Les agents appliquent-ils systématiquement cette liste lors des premiers contacts ? | F76: Non | G76: Statistiques d'utilisation de la checklist | H76: Contournement des procédures | I76: Moyenne | J76: Augmentation des réouvertures de tickets | K76: Lier l'application de la checklist aux KPI individuels.
G77: Rapport de non-conformité | H77: Procédures ignorées | I77: Faible | J77: Risque réglementaire | K77: Sensibiliser via des retours individuels.
D78: La liste est mise à jour en fonction des retours d’expérience | E78: La liste est-elle mise à jour en fonction des retours d’expérience ? | F78: Non | G78: Journal des mises à jour | H78: Checklist obsolète | I78: Moyenne | J78: Inadéquation aux nouveaux problèmes | K78: Créer un comité de revue trimestrielle.
G79: Base de connaissances des retours | H79: Améliorations non capitalisées | I79: Faible | J79: Progrès limités | K79: Automatiser le suivi des suggestions d'amélioration.
D80: Un audit aléatoire des appels vérifie l’application de la procédure | E80: Un audit aléatoire des appels vérifie-t-il l’application de la procédure ? | F80: Pas | G80: Rapport d'audit | H80: Non-respect des procédures | I80: Moyenne | J80: Dégradation de la qualité | K80: Rendre les audits obligatoires pour 5% des appels mensuels.
G81: Plan d'action correctif | H81: Corrections non appliquées | I81: Faible | J81: Répétition des erreurs | K81: Assigner des responsables pour chaque action.
C82: S’assurer que les problèmes sont gérés | D82: Un processus distinct de gestion des problèmes (Problem Management) est documenté | E82: Un processus distinct de gestion des problèmes (Problem Management) est-il documenté ? | F82: Oui | G82: Procédure de Problem Management | H82: Problèmes récurrents non résolus | I82: Élevée | J82: Augmentation des incidents | K82: Aligner la procédure sur ITIL et former les équipes.
G83: Workflow de gestion des problèmes | H83: Responsabilités floues | I83: Moyenne | J83: Retards dans les correctifs | K83: Définir un owner par problème.
D84: Les problèmes récurrents sont identifiés et analysés pour des correctifs durables | E84: Les problèmes récurrents sont-ils identifiés et analysés pour des correctifs durables ? | F84: Pas | G84: Fiches d'analyse RCA (Root Cause) | H84: Correctifs superficiels | I84: Élevée | J84: Répétition des incidents | K84: Imposer des revues systématiques pour les problèmes > 3 occurrences.
G85: Registre des problèmes récurrents | H85: Priorisation inadéquate | I85: Moyenne | J85: Ressources mal allouées | K85: Classer les problèmes par impact financier/opérationnel.
D86: Une base de connaissances (KB) recense les solutions aux problèmes connus | E86: Une base de connaissances (KB) recense-t-il les solutions aux problèmes connus ? | F86: Non | G86: Base de connaissances (KB) | H86: Redondance des efforts | I86: Moyenne | J86: Temps de résolution accru | K86: Intégrer la KB à l'outil de ticketing et notifier les agents des nouvelles solutions.
G87: Statistiques d'utilisation de la KB | H87: Solutions non consultées | I87: Faible | J87: Sous-utilisation des ressources | K87: Promouvoir la KB via des campagnes internes.
D88: Des revues périodiques des problèmes majeurs sont organisées | E88: Des revues périodiques des problèmes majeurs sont-elles organisées ? | F88: Non | G88: Compte-rendu de revues | H88: Problèmes systémiques non adressés | I88: Élevée | J88: Risques persistants | K88: Planifier des revues mensuelles avec la direction.
G89: Plan d'action post-revue | H89: Actions non suivies | I89: Moyenne | J89: Améliorations retardées | K89: Assigner des délais stricts pour les actions.
D90: Les statistiques de résolution des problèmes sont suivies et améliorées | E90: Les statistiques de résolution des problèmes sont-elles suivies et améliorées ? | F90: Non | G90: Dashboard de performance | H90: Décisions sans données | I90: Moyenne | J90: Stratégies inefficaces | K90: Automatiser le reporting avec alertes sur les tendances.
G91: Benchmark sectoriel | H91: Retard par rapport aux bonnes pratiques | I91: Faible | J91: Désavantage compétitif | K91: Participer à des groupes d'échange sectoriels.
C92: S’assurer qu’un processus de gestion des problèmes existe | D92: Le processus est aligné sur les bonnes pratiques ITIL ou équivalent | E92: Le processus est-il aligné sur les bonnes pratiques ITIL ou équivalent ? | F92: Oui | G92: Matrice de conformité ITIL | H92: Écarts par rapport aux standards | I92: Moyenne | J92: Difficultés de certification | K92: Engager un consultant ITIL pour un audit annuel.
G93: Plan de mise en conformité | H93: Non-respect des exigences | I93: Faible | J93: Sanctions potentielles | K93: Prioriser les écarts critiques.
D94: Les rôles et responsabilités dans la gestion des problèmes sont définis | E94: Les rôles et responsabilités dans la gestion des problèmes sont-ils définis ? | F94: Oui | G94: Fiches de rôle Problem Manager | H94: Dilution des responsabilités | I94: Élevée | J94: Problèmes orphelins | K94: Nommer un Problem Manager dédié.
G95: Organigramme du processus | H95: Chevauchements de fonctions | I95: Moyenne | J95: Conflits internes | K95: Clarifier les chaînes d'escalade.
D96: Un registre des problèmes (Known Error Database) est maintenu à jour | E96: Un registre des problèmes (Known Error Database) est-il maintenu à jour ? | F96: Non | G96: Base de données des erreurs connues | H96: Réincidents liés aux mêmes causes | I96: Élevée | J96: Perte de confiance des utilisateurs | K96: Mettre à jour la base après chaque résolution de problème.
G97: Procédure de mise à jour du registre | H97: Données obsolètes | I97: Moyenne | J97: Solutions inefficaces | K97: Automatiser les mises à jour via l'outil de ticketing.
D98: Des revues post-incident (Post-Mortem) sont réalisées pour les incidents majeurs | E98: Des revues post-incident (Post-Mortem) sont-elles réalisées pour les incidents majeurs ? | F98: Pas | G98: Template de revue Post-Mortem | H98: Non-apprentissage des incidents | I98: Élevée | J98: Répétition des échecs | K98: Imposer des Post-Mortem pour tout incident > 4h d'indisponibilité.
G99: Plan d'action Post-Mortem | H99: Correctifs non implémentés | I99: Moyenne | J99: Améliorations bloquées | K99: Suivre les actions via un outil de gestion de projet.
D100: Des indicateurs mesurent l’efficacité du processus (nombre de problèmes résolus, temps moyen, etc.) | E100: Des indicateurs mesurent-ils l’efficacité du processus (nombre de problèmes résolus, temps moyen, etc.) ? | F100: Pas | G100: Tableau de bord des indicateurs | H100: Décisions non éclairées | I100: Moyenne | J100: Ressources mal optimisées | K100: Définir des seuils d'alerte pour les indicateurs clés (ex: MTTR).
...

Sheet 4.5.Sécurité_Informatique
A1: Domaine | B1: Points de contrôle | C1: Objectifs de contrôle | D1: Critères d'évaluation | E1: Questions d'évaluation | F1: Réponses | G1: Documents Requis | H1: Risques | I1: Criticité | J1: Conséquences | K1: Recommandations
A2: Sécurité informatique | B2: Facteurs clés de succès | C2: Vérifier qu’une politique de sécurité est définie et correspond à l'activité de l'Organisation | D2: La politique de sécurité est documentée et approuvée par la direction | E2: La politique de sécurité est-elle documentée et approuvée par la direction ? | F2: Oui | G2: Politique de sécurité signée | H2: Absence de cadre formel | I2: Élevée | J2: Non-conformité réglementaire | K2: Faire valider la politique par le COMEX annuellement
G3: Procès-verbal d'approbation | H3: Décisions non tracées | I3: Moyenne | J3: Contestations ultérieures | K3: Archiver numériquement les PV
D4: La politique est alignée sur les objectifs stratégiques et opérationnels de l'organisation | E4: La politique est-elle alignée sur les objectifs stratégiques et opérationnels de l'organisation ? | F4: Oui | G4: Cartographie d'alignement | H4: Priorités divergentes | I4: Élevée | J4: Ressources mal allouées | K4: Réaliser un atelier stratégique biannuel
G5: Rapport d'analyse d'impact | H5: Décisions non éclairées | I5: Moyenne | J5: Investissements inefficaces | K5: Croiser avec les indicateurs business
D6: La politique couvre tous les domaines clés de la sécurité de l'information pertinents pour l'organisation | E6: La politique couvre-t-elle tous les domaines clés de la sécurité de l'information pertinents pour l'organisation ? | F6: Oui | G6: Matrice de couverture | H6: Zones à risque non adressées | I6: Élevée | J6: Vulnérabilités critiques | K6: Réviser via une analyse SWOT annuelle
G7: Benchmark sectoriel | H7: Retard compétitif | I7: Moyenne | J7: Image dégradée | K7: S'aligner sur ISO 27002
D8: La politique définit clairement les rôles et responsabilités en matière de sécurité | E8: La politique définit-elle clairement les rôles et responsabilités en matière de sécurité ? | F8: Oui | G8: Matrice RACI sécurité | H8: Confusion des responsabilités | I8: Élevée | J8: Incidents non traités | K8: Intégrer aux fiches de poste
G9: Organigramme sécurité | H9: Chevauchements | I9: Moyenne | J9: Conflits internes | K9: Clarifier les chaînes hiérarchiques
D10: La politique est accessible à toutes les parties prenantes concernées | E10: La politique est-elle accessible à toutes les parties prenantes concernées ? | F10: Oui | G10: Plateforme de diffusion | H10: Non-accessibilité | I10: Moyenne | J10: Non-respect involontaire | K10: Centraliser sur l'intranet
G11: Logs de consultation | H11: Information non lue | I11: Faible | J11: Application partielle | K11: Ajouter des notifications push
