Workbook

Sheet Synthese
C3: SYNTHESE NUMERIQUE | J3: Equipe de Mission
J4: NOMS | K4: PRENOMS | L4: SPECIALITE | M4: MATRICULE
B5: N° | C5: Domaines | D5: Total OUI | E5: Total NON | F5: Total PAS | G5: Total | H5: Score | J5: DIFFO DONGMO | K5: STEVE MERANDA | L5: L3-Data Science | M5: 22P091
B6: 1 | C6: Audit des Applications en Service | D6: =COUNTIF('4.1'!F4:F258,"OUI") -> 130 | E6: =COUNTIF('4.1'!F4:F258,"NON") -> 90 | F6: =COUNTIF('4.1'!F4:F258,"PAS") -> 35 | G6: =SUM(D6:F6) -> 255 | H6: =D6/G6 -> 0.50980392
B7: 2 | C7: Audit de la Fonction Informatique | D7: =COUNTIF('4.2'!G4:G173,"OUI") -> 75 | E7: =COUNTIF('4.2'!G4:G173,"NON") -> 74 | F7: =COUNTIF('4.2'!G4:G173,"PAS") -> 21 | G7: =SUM(D7:F7) -> 170 | H7: =D7/G7 -> 0.44117647
B8: 3 | C8: Audit et Contrôle des Projets Informatiques | D8: =COUNTIF('4.3'!F4:F468,"OUI") -> 238 | E8: =COUNTIF('4.3'!F4:F468,"NON") -> 169 | F8: =COUNTIF('4.3'!F4:F468,"PAS") -> 58 | G8: =SUM(D8:F8) -> 465 | H8: =D8/G8 -> 0.51182796
B9: 4 | C9: Audit du Support Utilisateur et de la Gestion du Parc | D9: =COUNTIF('4.4'!F3:F102,"OUI") -> 30 | E9: =COUNTIF('4.4'!F3:F102,"NON") -> 54 | F9: =COUNTIF('4.4'!F3:F102,"PAS") -> 16 | G9: =SUM(D9:F9) -> 100 | H9: =D9/G9 -> 0.3
B10: 5 | C10: Audit de Sécurité Informatique | D10: =COUNTIF('4.5'!F3:F242,"OUI") -> 93 | E10: =COUNTIF('4.5'!F3:F242,"NON") -> 113 | F10: =COUNTIF('4.5'!F3:F242,"PAS") -> 34 | G10: =SUM(D10:F10) -> 240 | H10: =D10/G10 -> 0.3875
B11: Total | D11: =SUM(D6:D10) -> 566 | E11: =SUM(E6:E10) -> 500 | F11: =SUM(F6:F10) -> 164 | G11: =SUM(D11:F11) -> 1230 | H11: =D11/G11 -> 0.4601626
G14: Synthese Graphique

Sheet 4.1
A3: Domaines | B3: Points de Contrôle | C3: Objectifs de Contrôle | D3: Critère d’Évaluation | E3: Question d’Évaluation | F3: Réponses | G3: Documents Requis | H3: Risques | I3: Criticités | J3: Conséquences | K3: Recommandations
A4: Audit des Applications en Service | B4: Organisation | C4: S’assurer de l’existence d'un comité informatique | D4: Un comité informatique est officiellement constitué et documenté. | E4: Un comité informatique est-il formellement mis en place ? | F4: OUI | G4: Charte du comité, Organigramme du comité | H4: Absence de gouvernance informatique | I4: Élevée | J4: Difficulté de suivre les transactions. | K4: Mettre en place une gouvernance informatique claire et adaptée pour mieux coordonner les projets.
D5: La liste des membres du comité est disponible et mise à jour. | E5: La liste des membres du comité est-elle tenue à jour ? | F5: NON | G5: Liste des membres, PV de nomination | H5: Manque de clarté sur les responsabilités | I5: Moyenne | J5: Confusion concernant les responsabilités et rôle des membres du comité. | K5: Clarifier les rôles et responsabilités à travers des procédures bien définies.
D6: Le comité se réunit régulièrement (ex. : mensuellement ou trimestriellement). | E6: Le comité informatique tient-il des réunions régulières ? | F6: NON | G6: Calendrier des réunions, PV des réunions | H6: Manque de suivi des décisions stratégiques | I6: Élevée | J6: Décisions stratégiques non mises en œuvre ou abandonnées. | K6: Établir un suivi régulier des décisions stratégiques avec des outils adaptés.
D7: Des comptes rendus de réunion sont archivés et accessibles. | E7: Les comptes rendus des réunions sont-ils archivés et consultables ? | F7: OUI | G7: Registre des comptes rendus, Plateforme de stockage documentaire | H7: Manque de traçabilité des décisions | I7: Moyenne | J7: Risque de perte d'informations critiques dans les décisions. | K7: Documenter et stocker systématiquement toutes les décisions sur une plateforme sécurisée.
D8: Le comité prend des décisions stratégiques et suit des actions correctives. | E8: Le comité suit-il l’exécution des décisions et actions correctives ? | F8: OUI | G8: Plan d’actions, Rapports de suivi | H8: Actions non suivies ou inefficaces | I8: Élevée | J8: Objectifs stratégiques non atteints en raison d'un manque de suivi des actions. | K8: Instituer un mécanisme de suivi des actions pour assurer leur mise en œuvre.
C9: S’assurer que les rôle et responsabilités des utilisateurs sont bien définis | D9: Chaque utilisateur a un rôle clairement défini dans l’organisation. | E9: Les rôles des utilisateurs sont-ils documentés ? | F9: OUI | G9: Manuel des responsabilités, Organigramme | H9: Confusion des responsabilités | I9: Moyenne | J9: Inefficacité et tensions internes dues au flou sur les responsabilités. | K9: Formaliser un manuel des responsabilités pour chaque acteur ou département impliqué.
D10: Un document officiel détaille les responsabilités de chaque rôle. | E10: Un document formel précise-t-il les responsabilités de chaque poste ? | F10: OUI | G10: Fiches de poste, Manuel interne | H10: Attribution floue des responsabilités | I10: Moyenne | J10: Délais dans les projets et surcharge des équipes en raison d'un manque de responsabilité claire. | K10: Revoir les fiches de poste pour mieux définir et distribuer les responsabilités.
D11: Les utilisateurs ont accès uniquement aux fonctionnalités nécessaires à leur travail. | E11: Les accès des utilisateurs sont-ils restreints à leurs besoins ? | F11: OUI | G11: Liste des droits d’accès, Rapports de permissions | H11: Accès excessifs aux ressources | I11: Élevée | J11: Risque d'accès non autorisé aux ressources organisationnelles. | K11: Renforcer la gestion des droits d'accès pour limiter les permissions aux utilisateurs autorisés.
D12: Les droits et accès sont revus périodiquement pour éviter les abus. | E12: Un audit des accès est-il effectué régulièrement ? | F12: NON | G12: Rapports d’audit d’accès, Politique de gestion des accès | H12: Risque d’abus ou de fraude | I12: Élevée | J12: Possibilité d'abus ou fraude interne impactant les ressources organisationnelles. | K12: Effectuer des audits réguliers et appliquer une politique stricte pour détecter les abus.
D13: Une procédure existe pour modifier ou supprimer des droits en cas de changement de poste. | E13: Un processus formel gère-t-il les modifications d’accès ? | F13: PAS | G13: Procédure de gestion des droits, Journal des modifications d’accès | H13: Maintien d’accès injustifiés | I13: Élevée | J13: Exposition accrue aux risques opérationnels dus aux accès injustifiés. | K13: Mettre en œuvre des procédures de révision et de mise à jour des droits d'accès.
C14: S’assurer qu’une analyse des risques a été réalisée | D14: Une analyse des risques a été formellement menée et documentée. | E14: Une analyse des risques SI a-t-elle été réalisée ? | F14: OUI | G14: Rapport d’analyse des risques, Cartographie des risques | H14: Manque de visibilité sur les menaces | I14: Élevée | J14: Incapacité à surveiller et répondre efficacement aux menaces émergentes. | K14: Instaurer une analyse proactive des menaces via un tableau de bord dédié.
D15: Les risques identifiés sont classés en fonction de leur criticité. | E15: Les risques SI sont-ils classés selon leur criticité ? | F15: OUI | G15: Matrice des risques, Liste des risques classifiés | H15: Gestion inefficace des priorités | I15: Moyenne | J15: Difficulté à prioriser les risques et à allouer les ressources efficacement. | K15: Développer une matrice des risques pour aider à la classification et priorisation.
D16: Des mesures de mitigation des risques ont été définies. | E16: Des mesures de mitigation des risques ont-elles été établies ? | F16: NON | G16: Plan de mitigation, Rapports de suivi des risques | H16: Absence de stratégie de réduction des risques | I16: Élevée | J16: Gestion des risques non alignée aux besoins actuels, augmentant les impacts. | K16: Réviser les plans de mitigation et assurer leur pertinence par des mises à jour régulières.
D17: L’analyse des risques est revue périodiquement. | E17: L’analyse des risques est-elle régulièrement mise à jour ? | F17: OUI | G17: Planning des revues, Historique des mises à jour | H17: Risques non pris en compte | I17: Élevée | J17: Difficulté à anticiper et éviter des incidents futurs. | K17: Établir un historique et des revues systématiques des risques pour mieux les intégrer dans la gestion.
D18: La direction a validé et approuvé les résultats de l’analyse | E18: La direction valide-t-elle l’analyse des risques ? | F18: PAS | G18: PV d’approbation, Rapports aux décideurs | H18: Absence de soutien stratégique | I18: Moyenne | J18: Risques stratégiques non pris en compte lors des décisions. | K18: Renforcer la communication entre décideurs pour garantir la prise en compte des risques stratégiques.
C19: S’assurer que le prolongement de l'analyse de risque et de son expansion ont été réalisés | D19: L’analyse des risques est mise à jour après chaque évolution majeure de l’application. | E19: L’analyse des risques est-elle mise à jour après un changement majeur ? | F19: OUI | G19: Rapports de mise à jour, Liste des nouvelles menaces | H19: Failles de sécurité non identifiées | I19: Élevée | J19: Manque de sensibilisation des parties prenantes aux enjeux de sécurité. | K19: Organiser des campagnes de sensibilisation et de formation pour engager davantage les parties prenantes.
D20: Les nouveaux risques identifiés sont ajoutés et évalués. | E20: Les nouveaux risques sont-ils évalués lors des mises à jour ? | F20: PAS | G20: Matrice des risques, Registre des incidents | H20: Menaces émergentes non anticipées | I20: Élevée | J20: Défauts persistants en raison de correctifs mal appliqués. | K20: Instituer un mécanisme de suivi des correctifs pour assurer leur application complète.
D21: Les mesures de contrôle sont adaptées en fonction des nouvelles menaces. | E21: Les contrôles de sécurité évoluent-ils selon les nouvelles menaces ? | F21: PAS | G21: Rapport de mise à jour des contrôles, Registre des actions correctives | H21: Mesures inadaptées aux menaces actuelles | I21: Élevée | J21: Risques accrus de perte ou de vol de données sensibles en cas de mauvaise gestion. | K21: Renforcer les politiques de sécurité des données sensibles et leur classification.
D22: Les responsables sont informés des mises à jour de l’analyse de risque. | E22: Les responsables sont-ils informés des mises à jour des risques ? | F22: PAS | G22: Notes de service, Comptes rendus de réunion | H22: Manque de sensibilisation des parties prenantes | I22: Moyenne | J22: Données mal catégorisées entraînant une faible visibilité et sécurité. | K22: Actualiser régulièrement la classification des données pour refléter les évolutions organisationnelles.
D23: Un suivi est effectué pour s’assurer que les nouvelles mesures sont appliquées. | E23: Les mesures correctives sont-elles suivies et validées ? | F23: PAS | G23: Rapports de conformité, Journal des actions mises en œuvre | H23: Absence de suivi des correctifs | I23: Élevée | J23: Absence de suivi des correctifs entraînant des erreurs répétitives. | K23: Mettre en place un processus rigoureux pour suivre et valider les correctifs.
C24: S’assurer que l’analyse et évaluation du niveau de sensibilité a été réalisée | D24: Un document définit les niveaux de sensibilité des données de l’application. | E24: Un document de classification des données existe-t-il ? | F24: NON | G24: Politique de classification des données, Registre des données sensibles | H24: Manque de gestion des données sensibles | I24: Élevée | J24: Risques accrus de violations de confidentialité des données sensibles. | K24: Renforcer les politiques de gestion et protection des données sensibles.
D25: La classification des données est basée sur leur impact potentiel en cas de perte. | E25: Les niveaux de classification tiennent-ils compte des impacts potentiels ? | F25: NON | G25: Étude d’impact, Registre de classification | H25: Mauvaise catégorisation des données | I25: Moyenne | J25: Données mal catégorisées entraînant une gestion inefficace. | K25: Revoir la catégorisation des données pour les aligner avec les besoins opérationnels.
D26: Les données sensibles ont des mesures de protection spécifiques. | E26: Des mesures spécifiques protègent-elles les données sensibles ? | F26: NON | G26: Politique de sécurité des données, Rapport d’audit de sécurité | H26: Protection insuffisante des données critiques | I26: Élevée | J26: Faible protection des données critiques, augmentant les risques de pertes. | K26: Étendre les mesures de sécurité telles que le chiffrement et les contrôles d’accès.
D27: Une procédure existe pour modifier la classification en cas d’évolution. | E27: Une procédure de mise à jour de la classification est-elle en place ? | F27: NON | G27: Procédure de modification des classifications, Journal des modifications | H27: Classification obsolète | I27: Moyenne | J27: Obsolescence des classifications réduisant l'accessibilité des données. | K27: Mettre à jour régulièrement les classifications pour refléter les évolutions organisationnelles.
D28: L’accès aux données sensibles est restreint et contrôlé. | E28: L’accès aux données sensibles est-il limité et surveillé ? | F28: NON | G28: Liste des accès aux données sensibles, Logs d’accès | H28: Accès non autorisés aux données sensibles | I28: Élevée | J28: Accès non autorisés aux données sensibles pouvant provoquer des violations. | K28: Revoir et restreindre les droits d’accès pour garantir une sécurité accrue.
C29: Vérifier l’existence d’un manuel d'administration de l'application | D29: Un manuel d’administration est disponible et à jour. | E29: Un manuel d’administration est-il disponible ? | F29: OUI | G29: Manuel d’administration, Documentation technique | H29: Manque de référence pour les administrateurs | I29: Élevée | J29: Temps prolongé pour résoudre les incidents en raison de procédures inefficaces. | K29: Simplifier et documenter les procédures de dépannage pour une résolution rapide.
D30: Il décrit les configurations techniques et les paramètres de l’application. | E30: Le manuel contient-il les configurations techniques et les paramètres de l’application ? | F30: OUI | G30: Manuel d’administration, Liste des configurations | H30: Mauvaise gestion des configurations | I30: Élevée | J30: Mauvaise gestion des configurations augmentant les risques de dysfonctionnement. | K30: Mettre en œuvre des contrôles réguliers pour garantir la conformité des configurations.
D31: Les procédures de maintenance et de dépannage y sont documentées. | E31: Les procédures de maintenance et de dépannage sont-elles documentées ? | F31: PAS | G31: Manuel d’administration, Guide de dépannage | H31: Temps d’arrêt prolongé en cas d’incident | I31: Élevée | J31: Incidents critiques mal gérés entraînant des interruptions prolongées. | K31: Développer un plan de gestion des incidents clair et structuré.
D32: Seuls les administrateurs autorisés ont accès au manuel. | E32: L’accès au manuel d’administration est-il restreint aux administrateurs ? | F32: OUI | G32: Liste des administrateurs autorisés, Registre des accès | H32: Risque d’accès non autorisé à des informations sensibles | I32: Élevée | J32: Configurations obsolètes réduisant l’efficacité opérationnelle. | K32: Instaurer des mises à jour périodiques des configurations pour garantir leur pertinence.
D33: Le manuel est régulièrement mis à jour en cas de changement dans l’application. | E33: Le manuel d’administration est-il mis à jour après chaque modification majeure ? | F33: OUI | G33: Historique des mises à jour, Procédure de validation des mises à jour | H33: Utilisation de configurations obsolètes | I33: Moyenne | J33: Processus non conformes aux exigences entraînant des retards. | K33: Standardiser et aligner les processus avec les normes de conformité.
C34: Vérifier l’existence de procédures formalisées | D34: Toutes les procédures liées à l’application sont documentées. | E34: Toutes les procédures de l’application sont-elles documentées ? | F34: OUI | G34: Référentiel des procédures, Guide utilisateur | H34: Manque de standardisation des processus | I34: Moyenne | J34: Utilisation de procédures obsolètes augmentant les inefficacités. | K34: Mettre à jour régulièrement les procédures pour les adapter aux besoins actuels.
D35: Les documents sont accessibles aux utilisateurs concernés. | E35: Les documents sont-ils accessibles uniquement aux utilisateurs concernés ? | F35: OUI | G35: Liste des accès aux documents, Plateforme documentaire | H35: Accès non autorisé aux documents sensibles | I35: Élevée | J35: Manque de suivi des performances et anomalies affectant la qualité. | K35: Développer un tableau de bord des performances pour surveiller et analyser les anomalies.
D36: Les procédures couvrent les opérations courantes et exceptionnelles. | E36: Les procédures documentées couvrent-elles toutes les opérations ? | F36: OUI | G36: Manuel des procédures, Rapports d’incidents | H36: Mauvaise gestion des situations exceptionnelles | I36: Moyenne | J36: Absence d’indicateurs de suivi limitant la capacité à évaluer les progrès. | K36: Définir des indicateurs clés de performance pour un suivi efficace.
D37: Elles sont validées par les responsables avant leur mise en application. | E37: Les responsables valident-ils les procédures avant leur application ? | F37: OUI | G37: PV de validation, Workflow d’approbation | H37: Procédures non conformes aux exigences | I37: Moyenne | J37: Manque de traçabilité des décisions prises entraînant des pertes d’information. | K37: Instaurer des processus de documentation et de stockage systématiques pour chaque décision.
D38: Un processus de mise à jour des procédures est défini | E38: Un processus de mise à jour des procédures est-il formalisé ? | F38: OUI | G38: Plan de mise à jour des procédures, Historique des révisions | H38: Utilisation de procédures obsolètes | I38: Moyenne | J38: Mauvaise compréhension des outils et fonctionnalités, impactant l’efficacité. | K38: Organiser des sessions de formation pour améliorer la connaissance des utilisateurs.
C39: S’assurer de l’existence et de la mise à disposition du compte rendu mensuel au propriétaire | D39: Un compte rendu est produit chaque mois. | E39: Un compte rendu sur l’application est-il produit mensuellement ? | F39: NON | G39: Rapports mensuels, Registre des comptes rendus | H39: Manque de suivi des performances et anomalies | I39: Élevée | J39: Non-conformité avec les standards de sécurité augmentant les risques juridiques. | K39: Revoir les politiques de sécurité pour les aligner aux normes (ISO 27001, RGPD).
D40: Il contient des informations sur l’utilisation et la performance de l’application. | E40: Le compte rendu contient-il des indicateurs de performance ? | F40: NON | G40: Modèle de compte rendu, Tableau de bord des performances | H40: Absence d’indicateurs de suivi | I40: Moyenne | J40: Risque de contrôles exposant à des violations de données sensibles. | K40: Renforcer les contrôles pour prévenir les violations et garantir la confidentialité.
D41: Le propriétaire de l’application reçoit et valide ce compte rendu. | E41: Le propriétaire de l’application valide-t-il le compte rendu mensuel ? | F41: NON | G41: PV de validation, Liste des destinataires du rapport | H41: Décisions non prises sur la base d’informations validées | I41: Moyenne | J41: Accès résiduels exploités par d'anciens collaborateurs après leur départ. | K41: Mettre en œuvre un processus de désactivation systématique des accès après le départ des employés.
D42: Des actions correctives sont proposées en cas d’anomalie. | E42: Des actions correctives sont-elles proposées dans les comptes rendus ? | F42: NON | G42: Plan d’actions correctives, Historique des corrections | H42: Non-prise en charge des anomalies identifiées | I42: Élevée | J42: Incohérences dans la gestion des profils impactant les performances. | K42: Clarifier et formaliser la gestion des profils pour réduire les incohérences.
D43: Les comptes rendus sont archivés pour référence future. | E43: Les comptes rendus sont-ils archivés et accessibles ? | F43: NON | G43: Registre des comptes rendus, Plateforme de stockage | H43: Perte d’historique et de traçabilité | I43: Moyenne | J43: Perte d'historique et de traçabilité. | K43: Instaurer des sauvegardes régulières et des outils de traçabilité pour préserver les données critiques.
C44: S’assurer de l’existence d'un guide d'utilisateur, manuel de procédure | D44: Un guide d’utilisateur est disponible et facile à comprendre. | E44: Un guide utilisateur est-il disponible ? | F44: NON | G44: Guide utilisateur, Manuel de prise en main | H44: Difficulté d’utilisation de l’application | I44: Moyenne | J44: Difficulté d'utilisation de l'application. | K44: Simplifier l’interface utilisateur et offrir un guide de prise en main détaillé et accessible.
D45: Il couvre les fonctionnalités principales de l’application. | E45: Le guide utilisateur couvre-t-il toutes les fonctionnalités principales ? | F45: PAS | G45: Guide utilisateur, Liste des fonctionnalités | H45: Manque de compréhension des fonctionnalités | I45: Moyenne | J45: Manque de compréhension des fonctionnalités. | K45: Fournir une liste exhaustive des fonctionnalités accompagnée d’exemples d’utilisation adaptés.
D46: Il est mis à jour à chaque changement majeur. | E46: Le guide utilisateur est-il mis à jour après chaque évolution majeure ? | F46: PAS | G46: Historique des mises à jour, Procédure de validation des mises à jour | H46: Utilisation d’informations obsolètes | I46: Moyenne | J46: Informations obsolètes. | K46: Mettre en œuvre une procédure de validation et mise à jour régulière des données pour garantir leur pertinence.
D47: Les nouveaux utilisateurs reçoivent une formation basée sur ce guide. | E47: Une formation basée sur le guide utilisateur est-elle dispensée aux nouveaux utilisateurs ? | F47: PAS | G47: Plan de formation, Liste des participants aux formations | H47: Manque de compétences des nouveaux utilisateurs | I47: Moyenne | J47: Manque de compétences des nouveaux utilisateurs. | K47: Organiser des sessions de formation fréquentes pour les utilisateurs débutants.
D48: Le guide est accessible aux utilisateurs autorisés. | E48: L’accès au guide utilisateur est-il restreint aux utilisateurs concernés ? | F48: PAS | G48: Liste des accès aux documents, Plateforme documentaire | H48: Accès non contrôlé au guide utilisateur | I48: Faible | J48: Accès non contrôlé au guide utilisateur. | K48: Restreindre les droits d’accès au guide utilisateur aux personnes autorisées uniquement.
B49: Application | C49: S'assurer que l'accès aux ressources de l'application (données et transactions) est restreint par un système de gestion d'accès | D49: Existence d'un système formalisé de gestion des accès | E49: Existe-t-il un système formalisé de gestion des accès ? | F49: OUI | G49: Politique de sécurité des accès (document officiel) | H49: Non-conformité avec les standards de sécurité (ISO 27001, RGPD) | I49: Elevée | J49: Non-conformité avec les standards de sécurité. | K49: Aligner les politiques de sécurité avec les normes ISO 27001 et RGPD pour garantir leur conformité.
D50: Le système est activé et effectivement appliqué sur l'application | E50: Le système est-il activé et effectivement appliqué sur l'application? | F50: OUI | G50: Preuve de configuration | H50: Accès non contrôlés exposant à des violations de données | I50: Elevée | J50: Accès non contrôlés exposant à des violations de données. | K50: Revoir les configurations pour restreindre les accès et garantir la sécurité des données sensibles.
D51: Les accès aux fonctions sensibles (données critiques, transactions) sont spécifiquement restreints | E51: Les accès aux fonctions sensibles (données critiques, transactions) sont-elles spécifiquement restreints? | F51: NON | G51: Matrice des droits (tableau des accès par rôle/métier) | H51: Fraude ou fuite de données critiques | I51: Elevée | J51: Fuite de données critiques. | K51: Mettre en œuvre des mécanismes de contrôle rigoureux pour prévenir les pertes de données critiques.
D52: Les droits d'accès sont attribués en fonction des rôles et responsabilités des utilisateurs | E52: Les droits d'accès sont-ils attribués en fonction des rôles et responsabilités des utilisateurs ? | F52: NON | G52: Fiches de poste ou descriptions des responsabilités | H52: Privilèges excessifs (violation du principe de moindre privilège) | I52: Moyenne | J52: Accès excessifs violant le principe de moindre privilège. | K52: Réévaluer les droits d’accès pour les limiter strictement aux besoins professionnels.
D53: Les révocations d'accès sont immédiates en cas de changement de poste ou de départ | E53: Les révocations d'accès sont-elles immédiates en cas de changement de poste ou de départ? | F53: NON | G53: Procédure de départ et journal des désactivations | H53: Accès résiduels exploités par d'anciens collaborateurs | I53: Elevée | J53: Comptes exploités par d'anciens collaborateurs. | K53: Automatiser la désactivation des comptes après le départ des employés pour prévenir les abus.
C54: S’assurer qu’une procédure de gestion des profils utilisateurs existe | D54: Existence d’une procédure écrite de gestion des profils utilisateurs | E54: Existe t-il une procédure écrite de gestion des profils utilisateurs? | F54: OUI | G54: Manuel des procédures utilisateurs | H54: Incohérence dans la gestion des profils | I54: Moyenne | J54: Incohérences dans la gestion des profils. | K54: Standardiser les procédures de gestion des profils pour minimiser les erreurs et garantir leur uniformité.
D55: La procédure définit clairement les rôles et permissions associés | E55: La procédure définit-elle clairement les rôles et permissions associés? | F55: OUI | G55: Arbre des rôles | H55: Attribution arbitraire des droits | I55: Moyenne | J55: Création d'accès non autorisés. | K55: Renforcer les contrôles et audits périodiques pour prévenir les créations frauduleuses d’accès.
D56: Les demandes de création/modification de profils suivent un processus formalisé | E56: Les demandes de création/modification de profils suivent-elles un processus formalisé? | F56: OUI | G56: Formulaires de demande | H56: Création de profils non autorisés | I56: Moyenne | J56: Création de fils non autorisés. | K56: Mettre en place un système de validation stricte avant toute création de fils ou de connexions.
D57: Les profils inactifs ou obsolètes sont régulièrement supprimés ou désactivés | E57: Les profils inactifs ou obsolètes sont-ils régulièrement supprimés ou désactivés? | F57: NON | G57: Rapport des comptes désactivés (historique 6 mois) | H57: Portes dérobées pour attaques (comptes zombies) | I57: Elevée | J57: Failles pour attaques via des comptes zombies. | K57: Supprimer systématiquement les comptes inactifs ou inutilisés pour réduire les risques d’attaque.
D58: Un suivi des modifications apportées aux profils est maintenu et auditable. | E58: Un suivi des modifications apportées aux profils est-il maintenu et auditable? | F58: NON | G58: Logs des changements (exports Active Directory/outil IAM) | H58: Impossible de tracer les changements frauduleux | I58: Moyenne | J58: Impossible de tracer les changements frauduleux. | K58: Intégrer des outils de journalisation avancés pour détecter et corriger rapidement tout changement suspect.
C59: Vérifier que l’identification des utilisateurs est réalisée | D59: Chaque utilisateur possède un identifiant unique et personnel | E59: Chaque utilisateur possède t-il un identifiant unique et personnel? | F59: OUI | G59: Liste des comptes actifs de l'application | H59: Impossible d'imputer les actions aux utilisateurs | I59: Elevée | J59: Compromission par les actions des utilisateurs. | K59: Renforcer les audits pour surveiller les actions des utilisateurs et garantir leur conformité.
D60: L’authentification requiert au moins un facteur robuste (mot de passe complexe, MFA, etc.) | E60: L’authentification requiert-il au moins un facteur robuste (mot de passe complexe, ,,.)? | F60: OUI | G60: Preuve de configuration | H60: Compromission facile des comptes | I60: Elevée | J60: Modification facile des comptes. | K60: Imposer des processus de validation complexes avant toute modification de compte pour assurer leur sécurité.
D61: Les comptes génériques ou partagés sont interdits ou strictement contrôlés | E61: Les comptes génériques ou partagés sont-ils interdits ou strictement contrôlés? | F61: OUI | G61: Audit des comptes (recherche de comptes génériques) | H61: Point d'entrée pour attaques internes | I61: Moyenne | J61: Failles pour attaques internes. | K61: Identifier et neutraliser les comptes génériques ou mal protégés via des audits réguliers.
D62: Le système bloque les tentatives d’accès après plusieurs échecs d’authentification | E62: Le système bloque t-il les tentatives d’accès après plusieurs échecs d’authentification? | F62: NON | G62: Paramètres de sécurité (seuil de verrouillage) | H62: Attaques par force brute possibles | I62: Elevée | J62: Attaques par force brute possibles. | K62: Augmenter la robustesse des paramètres de verrouillage pour minimiser les risques de force brute.
D63: Les identifiants inactifs sont automatiquement désactivés après une période définie | E63: Les identifiants inactifs sont-ils automatiquement désactivés après une période définie? | F63: NON | G63: Politique d'inactivité et liste des comptes désactivés | H63: Réutilisation par des tiers malveillants | I63: Elevée | J63: Exploitation par des tiers malveillants. | K63: Activer une politique d’inactivité stricte pour désactiver automatiquement les comptes dormants.
C64: Vérifier qu’un mot de passe est associé à l'identifiant | D64: Tous les identifiants actifs disposent d'un mot de passe enregistré | E64: Tous les identifiants actifs disposent-ils d'un mot de passe enregistré? | F64: OUI | G64: Test de connexion (vérification sur échantillon) | H64: Accès sans authentification | I64: Elevée | J64: Point d'entrée pour authentification. | K64: Effectuer des tests réguliers pour sécuriser les points d’entrée d’authentification.
D65: Les mots de passe répondent aux exigences de complexité définies | E65: Les mots de passe répondent-ils aux exigences de complexité définiesv | F65: OUI | G65: Règles de sécurité | H65: Cassage facile des mots de passe | I65: Moyenne | J65: Compromission des mots de passe. | K65: Mettre en place des politiques solides pour garantir la complexité et le renouvellement des mots de passe.
D66: Le stockage des mots de passe est chiffré et sécurisé | E66: Le stockage des mots de passe est-il chiffré et sécurisé? | F66: NON | G66: Preuve de hachage | H66: Fuite des credentials en clair | I66: Elevée | J66: Mots de passe initiaux en clair. | K66: Imposer le chiffrement des mots de passe initiaux et sécuriser leur stockage.
D67: La réinitialisation du mot de passe nécessite une validation sécurisée | E67: La réinitialisation du mot de passe nécessite t-il une validation sécurisée? | F67: NON | G67: Processus de reset | H67: Détournement de compte | I67: Elevée | J67: Prise de contrôle de compte. | K67: Instituer une double authentification pour chaque processus de reset afin de renforcer la sécurité.
D68: Les mots de passe sont renouvelés périodiquement selon la politique établie | E68: Les mots de passe sont-ils renouvelés périodiquement selon la politique établie? | F68: NON | G68: Historique des changements (logs de rotations) | H68: Mots de passe périmés toujours actifs | I68: Faible | J68: Mots de passe périmés toujours actifs. | K68: Définir des durées de vie pour les mots de passe et s’assurer de leur rotation régulière.
C69: S’assurer que les tentatives de connexions infructueuses à l'application sont suivies | D69: Toutes les tentatives de connexion infructueuses sont enregistrées dans un fichier de logs dédié | E69: Toutes les tentatives de connexion infructueuses sont-elles enregistrées dans un fichier de logs dédié? | F69: NON | G69: Fichiers de logs | H69: Impossible de détecter les attaques | I69: Moyenne | J69: Impossible de détecter les attaques. | K69: Intégrer des outils avancés d’analyse de logs pour améliorer la détection des attaques.
D70: Les logs contiennent systématiquement l'identifiant utilisé, l'horodatage et l'adresse IP source | E70: Les logs contiennent-ils systématiquement l'identifiant utilisé ? | F70: NON | G70: fichier de logs | H70: Investigation impossible après incident | I70: Moyenne | J70: Investigation impossible après incident. | K70: Instaurer une journalisation détaillée pour faciliter les enquêtes post-incidents.
D71: Un mécanisme de blocage temporaire est déclenché après X tentatives infructueuses consécutives | E71: Un mécanisme de blocage temporaire est-il déclenché après X tentatives infructueuses consécutives? | F71: NON | G71: Paramètres de verrouillage | H71: Attaques par dictionnaire facilitées | I71: Elevée | J71: Accès non autorisés facilités. | K71: Renforcer les paramètres de verrouillage pour minimiser les accès non autorisés.
D72: Les logs des tentatives infructueuses sont conservés pendant une durée minimale de Y jours | E72: Les logs des tentatives infructueuses sont-ils conservés pendant une durée minimale de Y jours? | F72: NON | G72: Politique de rétention | H72: Non-conformité réglementaire | I72: Faible | J72: Non-conformité réglementaire. | K72: Mettre en place une politique de rétention conforme aux réglementations en vigueur.
D73: Une alerte automatique est générée en cas de nombre anormal de tentatives infructueuses | E73: Une alerte automatique est-elle générée en cas de nombre anormal de tentatives infructueuses? | F73: NON | G73: Rapports d'alertes | H73: Détection tardive des intrusions | I73: Moyenne | J73: Détection tardive des intrusions. | K73: Utiliser des systèmes de détection proactifs pour identifier rapidement les intrusions.
C74: Vérifier que le niveau d’information et de moyen de contrôle adapté | D74: S'assurer que les informations critiques sont accessibles aux parties prenantes concernées. | E74: Les informations critiques sont-elles accessibles aux parties prenantes concernées ? | F74: OUI | G74: Politique de gestion des accès | H74: Accès non autorisé aux informations critiques | I74: Elevée | J74: Accès non autorisés aux informations critiques. | K74: Implémenter une politique stricte de gestion des accès pour protéger les informations sensibles.
D75: Vérifier que les moyens de contrôle mis en place couvrent efficacement les risques identifiés. | E75: Les moyens de contrôle mis en place couvrent-ils efficacement les risques identifiés ? | F75: OUI | G75: Cartographie des risques | H75: Risques non couverts pouvant impacter l’organisation | I75: Moyenne | J75: Risques pouvant impacter l'organisation. | K75: Élaborer une cartographie complète des risques pour prévoir les impacts potentiels.
D76: Confirmer que les outils et ressources utilisés pour le contrôle sont adaptés aux besoins de l'organisation. | E76: Les outils et ressources utilisés pour le contrôle sont-ils adaptés aux besoins de l'organisation ? | F76: OUI | G76: Inventaire des outils de contrôle | H76: Utilisation d’outils inadaptés entraînant des contrôles inefficaces | I76: Elevée | J76: Utilisation d'outils inadaptés entraînant des contrôles inefficaces. | K76: Réviser l'inventaire des outils de contrôle pour sélectionner ceux qui sont les mieux adaptés.
D77: Garantir que les processus de contrôle sont documentés et mis à jour régulièrement. | E77: Les processus de contrôle sont-ils documentés et mis à jour régulièrement ? | F77: NON | G77: Procédures de contrôle interne | H77: Procédures de contrôle obsolètes ou inexistantes | I77: Elevée | J77: Contrôles obsolètes ou inexistants. | K77: Moderniser les procédures de contrôle interne pour garantir leur efficacité.
D78: Évaluer l'efficacité des contrôles en analysant les résultats et en identifiant d'éventuelles lacunes. | E78: L’efficacité des contrôles est-elle évaluée à travers l’analyse des résultats et l’identification des lacunes ? | F78: NON | G78: Rapports d’audit interne | H78: Détection tardive des failles de contrôle | I78: Faible | J78: Absence de fiabilité des contrôles. | K78: Réaliser des audits internes réguliers pour assurer la fiabilité des contrôles existants.
C79: Vérifier que les contrôles utilisateurs des états de sortie sont effectifs | D79: Confirmer que les utilisateurs effectuent des vérifications sur les états de sortie avant leur utilisation. | E79: Les utilisateurs effectuent-ils des vérifications sur les états de sortie avant leur utilisation ? | F79: NON | G79: Journal des vérifications utilisateur | H79: Utilisation de données erronées en raison d’un manque de vérification | I79: Moyenne | J79: Utilisation de données erronées en raison d'un manque de vérification. | K79: Mettre en œuvre une vérification rigoureuse des données utilisateur avant leur exploitation.
D80: Vérifier la traçabilité des contrôles réalisés par les utilisateurs. | E80: Existe-t-il une traçabilité des contrôles réalisés par les utilisateurs ? | F80: NON | G80: Logs d’audit des systèmes | H80: Absence de traçabilité rendant difficile l’identification des erreurs | I80: Moyenne | J80: Absence de traçabilité rendant difficile l'identification des erreurs. | K80: Intégrer des logs d’audit détaillés pour améliorer la traçabilité des systèmes.
D81: S'assurer que des actions correctives sont mises en place en cas d'erreur détectée. | E81: Des actions correctives sont-elles mises en place en cas d'erreur détectée ? | F81: NON | G81: Registre des anomalies et corrections | H81: Non-correction des erreurs pouvant entraîner des impacts financiers ou opérationnels | I81: Elevée | J81: Non-conformité des données pouvant entraîner des impacts financiers ou opérationnels. | K81: Mettre en place un registre systématique des anomalies et corrections pour limiter les non-conformités.
D82: Évaluer la formation des utilisateurs sur les contrôles à effectuer. | E82: Les utilisateurs sont-ils formés aux contrôles à effectuer ? | F82: NON | G82: Registre des formations | H82: Manque de compétences des utilisateurs sur les contrôles à effectuer | I82: Faible | J82: Manque de compétences des utilisateurs sur les contrôles à effectuer. | K82: Organiser des formations adaptées pour renforcer les compétences des utilisateurs.
D83: Vérifier que les outils utilisés pour la vérification des états de sortie sont adaptés et performants. | E83: Les outils utilisés pour la vérification des états de sortie sont-ils adaptés et performants ? | F83: PAS | G83: Rapports de performance des outils | H83: Faible fiabilité des outils de vérification entraînant des erreurs non détectées | I83: Moyenne | J83: Faible fiabilité des outils de vérification entraînant des erreurs non détectées. | K83: Améliorer les outils de vérification pour garantir la fiabilité des contrôles.
C84: S’assurer que les procédures de validation des résultats existent | D84: Vérifier l'existence de procédures documentées de validation des résultats. | E84: Existe-t-il des procédures documentées de validation des résultats ? | F84: OUI | G84: Manuel des procédures | H84: Absence de validation des résultats pouvant fausser les décisions | I84: Elevée | J84: Utilisation de procédures obsolètes pouvant fausser les décisions. | K84: Actualiser les manuels de procédures régulièrement pour refléter les changements organisationnels.
D85: S'assurer que ces procédures sont appliquées de manière systématique. | E85: Ces procédures sont-elles appliquées de manière systématique ? | F85: NON | G85: Journal des validations effectuées | H85: Procédures de validation non appliquées, compromettant la qualité des données | I85: Moyenne | J85: Validation non appliquée, compromettant la qualité des données. | K85: Renforcer les processus de validation pour assurer une qualité optimale des données.
D86: Confirmer que les validations sont effectuées par des personnes autorisées. | E86: Les validations sont-elles effectuées par des personnes autorisées ? | F86: NON | G86: Liste des personnes habilitées | H86: Validations effectuées par des personnes non autorisées, augmentant le risque d’erreurs | I86: Elevée | J86: Validation des accès par des personnes non autorisées, augmentant le risque d'erreurs. | K86: Vérifier systématiquement la liste des habilitations pour garantir leur conformité.
D87: Vérifier que les résultats validés sont archivés de manière sécurisée. | E87: Les résultats validés sont-ils archivés de manière sécurisée ? | F87: NON | G87: Politique d’archivage | H87: Perte ou falsification des résultats validés | I87: Elevée | J87: Perte ou altération des résultats validés. | K87: Protéger les résultats validés avec des sauvegardes sécurisées et des processus d’archivage rigoureux.
D88: Évaluer l'efficacité des procédures à travers des tests ou des simulations. | E88: L’efficacité des procédures est-elle évaluée à travers des tests ou des simulations ? | F88: OUI | G88: Rapports de tests | H88: Procédures inefficaces ne permettant pas d’identifier les anomalies | I88: Faible | J88: Tests inefficaces ne permettant pas d'identifier les anomalies. | K88: Réviser les plans de tests pour améliorer leur efficacité et détecter les anomalies critiques.
C89: S’assurer que l'intégrité et l'exhaustivité des données transmises entre les différents modules est garantie | D89: Vérifier l'existence de mécanismes de contrôle garantissant l'intégrité des données transmises. | E89: Des mécanismes de contrôle garantissent-ils l'intégrité des données transmises ? | F89: OUI | G89: Documentation des mécanismes de validation des données | H89: Altération ou perte de données lors des transmissions | I89: Moyenne | J89: Altération de données lors des transmissions. | K89: Utiliser des mécanismes de validation des données pour sécuriser les transmissions.
D90: S'assurer que les données transmises entre modules ne subissent pas de perte ou d'altération. | E90: Les données transmises entre modules subissent-elles une perte ou une altération ? | F90: NON | G90: Rapports de comparaison avant/après transmission | H90: Transmission incomplète ou corrompue des données entre modules | I90: Moyenne | J90: Comparaison incomplète ou compromise des données entre modules. | K90: Standardiser les processus de comparaison avant/après transmission des données entre modules.
D91: Vérifier que des mécanismes de journalisation et de traçabilité des échanges existent. | E91: Des mécanismes de journalisation et de traçabilité des échanges existent-ils ? | F91: NON | G91: Logs de transaction | H91: Absence de journalisation empêchant la traçabilité des échanges | I91: Elevée | J91: Absence de traçabilité empêchant la traçabilité des échanges. | K91: Instaurer des logs de transaction détaillés pour garantir une traçabilité optimale.
D92: Évaluer la gestion des erreurs en cas d'incohérence des données. | E92: La gestion des erreurs en cas d'incohérence des données est-elle efficace ? | F92: OUI | G92: Registre des erreurs et incidents | H92: Données erronées non détectées à temps | I92: Faible | J92: Données non détectées à temps. | K92: Intégrer des registres d’erreurs et incidents pour une détection rapide des anomalies.
D93: Confirmer que des tests réguliers sont réalisés pour garantir l’exactitude des transmissions. | E93: Des tests réguliers sont-ils réalisés pour garantir l’exactitude des transmissions ? | F93: NON | G93: Planning des tests | H93: Défauts non corrigés entraînant des décisions basées sur des informations incorrectes | I93: Moyenne | J93: Défauts non corrigés entraînant des décisions basées sur des informations incorrectes. | K93: Planifier et suivre systématiquement les corrections des défauts identifiés pendant les tests.
B94: Fonction informatique | C94: S’assurer que les tâches relatives au développement et à l'exploitation de l'application sont bien suivies et documentées | D94: Vérifier l'existence d'une documentation détaillée pour le développement et l’exploitation. | E94: Existe-t-il une documentation détaillée pour le développement et l’exploitation ? | F94: OUI | G94: Documentation technique de l’application | H94: Manque de documentation entraînant des difficultés de maintenance et d’exploitation | I94: Moyenne | J94: Documentation entraînant des difficultés de maintenance et d'exploitation. | K94: Moderniser et simplifier la documentation technique pour faciliter la maintenance et l’exploitation.
D95: S'assurer que les modifications et mises à jour sont bien suivies et validées. | E95: Les modifications et mises à jour sont-elles bien suivies et validées ? | F95: OUI | G95: Registre des modifications | H95: Changements non maîtrisés pouvant générer des dysfonctionnements | I95: Elevée | J95: Changements non maîtrisés pouvant générer des dysfonctionnements. | K95: Documenter et contrôler tous les changements pour prévenir les dysfonctionnements.
D96: Confirmer que les rôles et responsabilités des intervenants sont définis et respectés. | E96: Les rôles et responsabilités des intervenants sont-ils définis et respectés ? | F96: OUI | G96: Organigramme des responsabilités | H96: Absence de définition des responsabilités entraînant une mauvaise répartition des tâches | I96: Faible | J96: Absence de définition des responsabilités entraînant une mauvaise répartition des tâches. | K96: Instaurer un organigramme clair des responsabilités pour améliorer la répartition des tâches.
D97: Vérifier la mise en place d’un processus de gestion des incidents et des anomalies. | E97: Un processus de gestion des incidents et des anomalies est-il mis en place ? | F97: NON | G97: Procédure de gestion des incidents | H97: Non-traitement des incidents pouvant perturber l’activité | I97: Moyenne | J97: Non-traitement des incidents pouvant perturber l'activité. | K97: Élaborer une procédure de gestion des incidents pour garantir leur résolution rapide.
D98: S'assurer que des audits internes ou revues régulières sont réalisés pour garantir le suivi et la documentation. | E98: Des audits internes ou revues régulières sont-ils réalisés pour garantir le suivi et la documentation ? | F98: NON | G98: Plan d’audit interne | H98: Manque d’audits internes favorisant la persistance des failles et des erreurs | I98: Elevée | J98: Manque d'audits internes favorisant la persistance des failles et des erreurs. | K98: Réaliser des audits internes réguliers pour identifier et corriger les failles rapidement.
C99: Vérifier que la maintenance de la séparation des tâches est effective | D99: Les responsabilités des différents utilisateurs sont distinctes et clairement attribuées. | E99: Les responsabilités des utilisateurs sont-elles clairement définies ? | F99: OUI | G99: Organigramme des responsabilités, Fiches de poste | H99: Confusion des rôles et responsabilités | I99: Élevée | J99: Confusion dans les rôles et responsabilités. | K99: Définir et documenter clairement les rôles et responsabilités de chaque membre via un organigramme mis à jour.
D100: - Il existe un mécanisme de contrôle empêchant les conflits d’intérêt dans les tâches critiques. | E100: Un contrôle empêche-t-il les conflits d’intérêts ? | F100: OUI | G100: Matrice de séparation des tâches, Rapport d’audit interne | H100: Risque de fraude interne | I100: Élevée | J100: Risque d'audit interne mal structuré ou inefficace. | K100: Réaliser régulièrement des audits internes et mettre à jour la matrice de séparation des tâches pour éviter les conflits.
D101: - Les accès aux environnements de développement, test et production sont bien séparés. | E101: Les accès aux environnements sont-ils strictement séparés ? | F101: OUI | G101: Politique de gestion des accès, Liste des utilisateurs autorisés | H101: Risque d’erreurs en production | I101: Élevée | J101: Erreurs en production dues à des accès non gérés. | K101: Mettre en place une politique stricte de gestion des accès avec des journaux de suivi.
D102: - Toute modification des droits est soumise à une validation formelle. | E102: Une validation formelle est-elle requise pour modifier les droits ? | F102: OUI | G102: Procédure de gestion des accès, Journal des modifications | H102: Risque d’accès non autorisé | I102: Élevée | J102: Accès non autorisé aux systèmes critiques. | K102: Documenter et auditer régulièrement les accès pour s'assurer de leur conformité aux règles établies.
...

Sheet 4.2
B2: Domaine | C2: points de contrôles | D2: objectifs de contrôle | E2: critères d'évaluation | F2: Questions d’évaluation | G2: Réponses | H2: Documents Requis | I2: Risques | J2: Criticités | K2: Conséquences | L2: Recommandations
B4: Audit de la Fonction Informatique | C4: Rôle et positionnement de l'informatique dans l'organisation | D4: Vérifier qu’ont été créés des Comités « informatique » (stratégique, pilotage,..) regroupant les différentes directions de l’Organisation en charge de recenser les besoins et les opportunités, gérer les priorités et suivre les projets | E4: Existence d’une documentation officielle sur la création des comités | F4: Les comités informatiques ont-ils été officiellement créés ? | G4: NON | H4: Actes de création, Statuts | I4: Absence de structure officielle et légitimité réduite. | J4: Élevée | K4: Difficulté à structurer les responsabilités et les décisions. | L4: Créer officiellement les comités avec des statuts et un acte de création validés.
E5: Fréquence et régularité des réunions organisées par ces comités | F5: Les réunions se tiennent-elles régulièrement selon un calendrier défini ? | G5: NON | H5: Procès-verbaux, Calendrier | I5: Manque de suivi et de coordination. | J5: Moyenne | K5: Projets retardés ou mal alignés avec les objectifs stratégiques. | L5: Établir un calendrier régulier pour les réunions et garantir leur tenue systématique.
E6: Représentation équitable des différentes directions dans la composition des comités. | F6: Les directions concernées sont-elles toutes représentées dans ces comités ? | G6: OUI | H6: Organigrammes, Listes de membres | I6: Représentation limitée entraînant des biais dans les décisions. | J6: Élevée | K6: Perspectives restreintes et solutions non inclusives. | L6: Assurer la représentation équitable de toutes les directions concernées.
E7: Qualité des rapports produits par les comités (priorités identifiées, suivi des projets, etc.) | F7: Les décisions des comités sont-elles documentées et suivies ? | G7: OUI | H7: Rapports de réunion, Registres | I7: Manque de traçabilité, ce qui peut générer des incohérences et pertes d’informations importantes. | J7: Élevée | K7: Décisions oubliées ou mal appliquées. | L7: Documenter systématiquement toutes les décisions et en assurer le suivi via des rapports.
E8: Évaluation des impacts des décisions des comités sur les projets informatiques de l’organisation | F8: Les comités ont-ils un impact mesurable sur les projets IT ? | G8: OUI | H8: KPI, Rapports d’impact | I8: Difficulté à démontrer leur valeur ajoutée ou à justifier leur maintien. | J8: Moyenne | K8: Réduction de l’efficacité organisationnelle et méfiance des parties prenantes. | L8: Définir des indicateurs de performance pour mesurer l’impact des comités sur les projets.
D9: . Vérifier l’existence d’une charte informatique ou de tout autre document définissant le rôle et le périmètre de responsabilité de la DSI ; | E9: Disponibilité et accessibilité du document aux parties prenantes concernées. | F9: La charte informatique est-elle documentée et validée ? | G9: OUI | H9: Charte validée, Procès-verbal d’approbation | I9: Manque de clarté dans la gouvernance informatique. | J9: Élevée | K9: Actions non coordonnées, entraînant des inefficacités. | L9: Documenter et valider la charte informatique pour formaliser la gouvernance.
E10: Clarté dans la définition des rôles et responsabilités de la DSI | F10: La charte est-elle accessible aux collaborateurs concernés ? | G10: OUI | H10: Copies de la charte, Portail interne | I10: Collaborateurs mal informés sur leurs rôles et responsabilités. | J10: Élevée | K10: Actions incohérentes avec les objectifs de la charte. | L10: Rendre la charte accessible via un portail ou par distribution directe.
E11: Conformité de la charte aux objectifs stratégiques de l’organisation | F11: Les rôles et responsabilités de la DSI y sont-ils clairement définis ? | G11: NON | H11: Organigrammes, Guides de procédures | I11: Ambiguïtés organisationnelles, causant des conflits ou doublons dans les tâches. | J11: Moyenne | K11: Baisse de productivité et tensions entre équipes. | L11: Clarifier et communiquer les rôles de la DSI à travers des organigrammes et des procédures précises.
E12: Validation et approbation formelles par la direction générale. | F12: La charte est-elle alignée sur les objectifs organisationnels ? | G12: PAS | H12: Plan stratégique, Objectifs de la charte | I12: Incohérence entre les objectifs IT et la stratégie globale de l’organisation. | J12: Moyenne | K12: Perte d’efficacité et projets mal adaptés. | L12: Aligner les objectifs de la charte avec ceux de l’organisation à travers une revue stratégique.
E13: Mise à jour régulière de la charte pour refléter les évolutions organisationnelles et technologiques. | F13: Est-elle mise à jour régulièrement pour refléter les évolutions ? | G13: OUI | H13: Historique des mises à jour, Procédures d’audit | I13: Informations obsolètes, entraînant des décisions basées sur des données dépassées. | J13: Moyenne | K13: Processus inefficaces ou inadéquats par rapport aux besoins actuels. | L13: Mettre en place un processus de mise à jour continue et systématique de la charte.
D14: Évaluer le degré d’implication et de maîtrise des organes de gestion dans les systèmes d’information de l’Organisation ; | E14: Participation active des organes de gestion dans les projets clés liés aux systèmes d’information | F14: Les dirigeants participent-ils aux projets clés liés aux systèmes d’information ? | G14: OUI | H14: Procédures de contrôle, Rapports d'audit | I14: Absence de mécanismes de contrôle pour vérifier l'application des responsabilités. | J14: Moyenne | K14: Réduction de la conformité et de la fiabilité des engagements. | L14: Mettre en place des mécanismes de contrôle pour garantir l'application des responsabilités.
E15: Taux de formation et de sensibilisation des dirigeants sur les enjeux numériques et de cybersécurité. | F15: Les dirigeants reçoivent-ils des formations sur les enjeux numériques ? | G15: NON | H15: Documents de conformité, Registres | I15: Non-identification des écarts par rapport aux exigences des documents contractuels. | J15: Moyenne | K15: Compromet les engagements pris et augmente le risque d'incohérences. | L15: Identifier et corriger les écarts pour assurer la conformité avec les exigences documentaires.
E16: Analyse des décisions stratégiques prises par la direction concernant les systèmes d’information | F16: Leurs décisions concernant les systèmes d’information sont-elles stratégiques ? | G16: OUI | H16: Clauses contractuelles, Annexes | I16: Absence de détails sur les modalités de transition dans les documents contractuels. | J16: Moyenne | K16: Provoque des ambiguïtés post-projet et des conflits potentiels. | L16: Intégrer des modalités de transition précises dans les contrats pour éviter les ambiguïtés.
E17: Niveau d’interaction entre la direction et la DSI sur les projets en cours | F17: Un dialogue régulier existe-t-il entre la direction et la DSI ? | G17: PAS | H17: Documents de validation, Procès-verbaux | I17: Absence de validation formelle des contrats par les parties prenantes. | J17: Élevée | K17: Diminue leur légitimité et peut entraîner des contestations ultérieures. | L17: Garantir une validation formelle des contrats par toutes les parties prenantes.
E18: Retour d’expérience des organes de gestion concernant l’efficacité des systèmes d’information. | F18: Les retours d’expérience des dirigeants influencent-ils les projets IT ? | G18: OUI | H18: Clauses de responsabilité, Rapports | I18: Responsabilités mal définies pendant et après la garantie. | J18: Moyenne | K18: Crée des ambiguïtés et ralentit la gestion post-garantie. | L18: Définir clairement les responsabilités pendant et après la période de garantie.
D19: Vérifier en pratique que le leadership des grands projets est assuré par les organes de gestion ; | E19: Définition claire des rôles de leadership pour chaque projet | F19: Les rôles de leadership pour chaque projet sont-ils bien définis ? | G19: PAS | H19: Plans de maintenance, Manuel d'utilisation | I19: Absence de documentation sur les procédures de maintenance post-garantie. | J19: Moyenne | K19: Limite leur application efficace et augmente les risques de défaillances. | L19: Documenter rigoureusement les procédures de maintenance post-garantie.
E20: Analyse des performances des projets dirigés par les organes de gestion (respect des délais, des budgets, des objectifs). | F20: Les organes de gestion suivent-ils les performances des projets ? | G20: PAS | H20: Référentiels contractuels, Base documentaire | I20: Traçabilité et accessibilité limitées des documents contractuels. | J20: Moyenne | K20: Complexifie la gestion administrative et réduit la transparence. | L20: Assurer la traçabilité et l'accessibilité des documents pour une gestion simplifiée.
E21: Documentation des décisions importantes prises par la direction pour les grands projets | F21: Les décisions stratégiques sont-elles correctement documentées ? | G21: PAS | H21: Contrats, Chartes de responsabilités | I21: Obligations des membres et fournisseurs mal définies. | J21: Élevée | K21: Génère des conflits organisationnels et des retards dans les projets. | L21: Définir précisément les obligations des membres et des fournisseurs.
E22: Suivi des projets via des tableaux de bord ou des indicateurs de performance clés | F22: Des tableaux de bord ou indicateurs suivent-ils la progression des projets ? | G22: PAS | H22: Registre des suivis, Indicateurs de conformité | I22: Suivi insuffisant des responsabilités des parties prenantes. | J22: Élevée | K22: Nuance au respect des engagements et retards dans les livrables. | L22: Mettre en place un suivi rigoureux des responsabilités pour garantir le respect des engagements.
E23: Satisfaction des parties prenantes quant à l’efficacité et à la coordination du leadership. | F23: Les parties prenantes sont-elles satisfaites du leadership exercé ? | G23: NON | H23: Rapports d'audit, Listes de conformité | I23: Absence d’audits réguliers pour vérifier la conformité des fournisseurs. | J23: Élevée | K23: Limite le contrôle et augmente les risques de non-conformité. | L23: Réaliser des audits réguliers pour vérifier la conformité et les performances des fournisseurs.
D24: Vérifier que les métiers assurent leur rôle de MOA. | E24: Clarité des responsabilités des métiers dans la documentation des projets (exigences, spécifications, etc.). | F24: Les métiers participent-ils activement à la documentation des projets ? | G24: NON | H24: Clauses pénales, Contrats | I24: Absence de sanctions en cas de non-respect des obligations contractuelles. | J24: Moyenne | K24: Réduit la dissuasion et peut encourager les manquements. | L24: Intégrer des sanctions claires et proportionnées dans les contrats pour renforcer la dissuasion.
E25: Niveau d’engagement des métiers dans les étapes de conception et de validation des solutions IT. | F25: Les métiers valident-ils les besoins fonctionnels des projets IT ? | G25: NON | H25: Engagements fournisseurs, Contrats | I25: Engagements des fournisseurs non intégrés dans les documents contractuels. | J25: Élevée | K25: Diminue leur force juridique et leur application effective. | L25: Formaliser et intégrer les engagements des fournisseurs dans les contrats pour en renforcer la valeur.
E26: Capacité des métiers à définir les besoins fonctionnels en lien avec les objectifs organisationnels | F26: Les livrables sont-ils validés par les métiers à chaque étape ? | G26: NON | H26: Livrables validés, Rapports d'étapes | I26: Absence de validation formelle des livrables par les métiers. | J26: Moyenne | K26: Risques d'incohérence et de non-conformité des livrables. | L26: Valider systématiquement les livrables par les métiers à chaque étape du projet.
E27: Suivi et validation des livrables par les métiers durant le cycle de vie des projets. | F27: Les métiers collaborent-ils efficacement avec la DSI ? | G27: NON | H27: Comptes-rendus de collaboration, Indicateurs | I27: Collaboration insuffisante entre les métiers et la DSI. | J27: Moyenne | K27: Difficulté à coordonner les efforts et à respecter les délais du projet. | L27: Renforcer la collaboration via des réunions régulières et des outils de suivi.
E28: Feedback des métiers sur la collaboration avec la DSI et les prestataires externes. | F28: Les métiers donnent-ils un retour structuré sur les projets livrés ? | G28: OUI | H28: Rapports de retour, Matrice d'évaluation | I28: Absence de retour structuré sur les projets livrés. | J28: Moyenne | K28: Risque d'amélioration continue limitée et accumulation d'erreurs dans les projets futurs. | L28: Mettre en place un processus structuré pour collecter et analyser les retours des métiers.
C29: Planification stratégique | D29: Vérifier la couverture du périmètre fonctionnel | E29: Analyse des processus fonctionnels inclus et exclus du périmètre défini. | F29: La procédure de mise en production est-elle documentée ? | G29: OUI | H29: Documentation des procédures, Historique des mises à jour | I29: Absence de documentation claire pour les procédures de mise en production. | J29: Moyenne | K29: Manque de standardisation et augmentation des erreurs lors des mises en production. | L29: Documenter toutes les étapes de mise en production pour améliorer leur application.
E30: Vérification des ressources allouées pour couvrir intégralement les besoins fonctionnels. | F30: Les étapes de validation (tests, approbations) sont-elles clairement définies ? | G30: PAS | H30: Étapes de validation, Procédures écrites | I30: Validation non formalisée des tests et des approbations. | J30: Moyenne | K30: Incohérences dans les résultats et non-respect des standards. | L30: Définir clairement les étapes de validation et les formaliser dans des procédures écrites.
E31: Conformité du périmètre aux objectifs stratégiques de l’organisation. | F31: La procédure inclut-elle un plan de retour en arrière ? | G31: OUI | H31: Plan de retour en arrière, Dossier technique | I31: Absence de plan de retour en arrière en cas d’échec. | J31: Moyenne | K31: Risques accrus lors d’un échec de mise en production, impactant les opérations. | L31: Intégrer un plan de retour en arrière clair dans chaque procédure de mise en production.
E32: Cohérence entre le périmètre défini et les priorités opérationnelles. | F32: Les rôles pour chaque étape sont-ils clairement attribués ? | G32: OUI | H32: Attribution des rôles, Organigrammes | I32: Rôles et responsabilités mal définis pour chaque étape. | J32: Moyenne | K32: Confusion organisationnelle et inefficacité dans l’exécution des tâches. | L32: Définir clairement les rôles pour chaque étape et les formaliser dans un organigramme.
E33: Détection des lacunes ou chevauchements dans la couverture fonctionnelle. | F33: Des suivis post-mise en production sont-ils effectués pour identifier les anomalies ? | G33: OUI | H33: Rapports d’anomalies, Indicateurs | I33: Suivi insuffisant des anomalies post-mise en production. | J33: Moyenne | K33: Défauts non corrigés affectant la qualité des systèmes et services. | L33: Mettre en place un suivi rigoureux des anomalies pour identifier et corriger rapidement les défauts.
D34: Vérifier l’existence d’une analyse à jour des procédures de pilotage et de mise à jour du plan informatique ; | E34: Existence de documents récents et validés sur le pilotage du plan informatique. | F34: Les documents de pilotage du plan informatique sont-ils récents et validés ? | G34: OUI | H34: Plans validés, Registres de validation | I34: Documents de pilotage non mis à jour ou non validés. | J34: Élevée | K34: Risques d’obsolescence des informations et inefficacité dans le pilotage. | L34: Actualiser régulièrement les documents de pilotage et s’assurer de leur validation.
E35: Fréquence de mise à jour des procédures et leur alignement avec les évolutions technologiques. | F35: Les procédures sont-elles mises à jour régulièrement en fonction des évolutions technologiques ? | G35: OUI | H35: Historique des mises à jour, Rapports d'audit | I35: Procédures non mises à jour en fonction des évolutions techniques. | J35: Moyenne | K35: Retards dans l’adoption de nouvelles technologies et baisse de performance des systèmes. | L35: Mettre à jour régulièrement les procédures pour refléter les évolutions techniques.
E36: Clarté des responsabilités dans le processus de mise à jour des plans. | F36: Les responsabilités pour la mise à jour des plans sont-elles clairement définies ? | G36: OUI | H36: Assignation des responsabilités, Procès-verbaux | I36: Responsabilités mal définies pour la mise à jour des plans. | J36: Moyenne | K36: Confusion et manque de responsabilité dans l’actualisation des plans. | L36: Clarifier et assigner les responsabilités liées à la mise à jour des documents.
E37: Cohérence entre les procédures de pilotage et les besoins identifiés par l’organisation. | F37: Les procédures de pilotage répondent-elles aux besoins identifiés de l’organisation ? | G37: OUI | H37: Analyse des besoins, Procédures de pilotage | I37: Procédures de pilotage inadéquates pour répondre aux besoins identifiés. | J37: Élevée | K37: Objectifs de l’organisation mal soutenus par les processus existants. | L37: Revoir les procédures pour les aligner avec les besoins organisationnels identifiés.
E38: Impact des mises à jour sur les performances des systèmes informatiques. | F38: Les mises à jour améliorent-elles les performances des systèmes informatiques ? | G38: NON | H38: Rapports d'analyse de performance | I38: Absence de suivi sur les impacts des mises à jour sur les performances des systèmes. | J38: Moyenne | K38: Difficulté à mesurer les bénéfices des évolutions mises en place. | L38: Suivre les performances après chaque mise à jour pour évaluer les impacts.
D39: Vérifier l’existence des documents à jour d’urbanisme de l’Organisation | E39: Disponibilité des documents d’urbanisme dans leur version la plus récente. | F39: Les documents d’urbanisme sont-ils disponibles dans leur version la plus récente ? | G39: NON | H39: Documents urbanistiques, Versions validées | I39: Documents urbanistiques non disponibles dans leur version récente. | J39: Moyenne | K39: Planification impactée par des informations obsolètes ou erronées. | L39: Garantir la disponibilité des documents urbanistiques les plus récents.
E40: Évaluation de la conformité des documents aux normes et réglementations applicables. | F40: Les documents d’urbanisme respectent-ils les normes et réglementations applicables ? | G40: NON | H40: Rapports de conformité, Réglementations | I40: Documents urbanistiques non alignés avec les normes et réglementations applicables. | J40: Moyenne | K40: Non-conformité réglementaire entraînant des risques juridiques. | L40: S’assurer que tous les documents urbanistiques respectent les réglementations en vigueur.
E41: Cohérence des documents avec la stratégie globale de l’organisation. | F41: Les documents d’urbanisme sont-ils alignés avec la stratégie globale de l’organisation ? | G41: NON | H41: Analyse stratégique, Plans organisationnels | I41: Documents urbanistiques non alignés avec la stratégie globale de l’organisation. | J41: Moyenne | K41: Déconnexion entre les plans urbains et les objectifs stratégiques. | L41: Aligner les documents urbanistiques avec la stratégie globale de l’organisation.
E42: Qualité des informations contenues dans les documents (précision, pertinence). | F42: Les informations contenues dans les documents sont-elles précises et pertinentes ? | G42: NON | H42: Revues techniques, Rapports précis | I42: Informations contenues dans les documents imprécises ou non pertinentes. | J42: Moyenne | K42: Mauvaises décisions basées sur des informations erronées. | L42: Mettre en œuvre des processus de revue technique pour garantir l’exactitude des documents.
E43: Évaluation de l’utilisation opérationnelle des documents pour la gestion organisationnelle. | F43: Les documents sont-ils utilisés efficacement pour la gestion organisationnelle ? | G43: NON | H43: Rapports d'analyse, Études techniques | I43: Analyses inexactes ou obsolètes sur le plan d'occupation des sols. | J43: Faible | K43: Mauvaises décisions stratégiques basées sur des données erronées. | L43: Mettre à jour régulièrement les analyses pour garantir leur exactitude et pertinence.
D44: Vérifier l’existence d’une analyse à jour des procédures de pilotage et de mise à jour du plan d’occupation des sols (POS) | E44: Validation de l’exactitude des analyses récentes sur le plan d’occupation des sols. | F44: Les analyses récentes sur le plan d’occupation des sols sont-elles exactes ? | G44: PAS | H44: Historique des révisions, Procès-verbaux | I44: Fréquence inadéquate des révisions du plan d'occupation des sols. | J44: Faible | K44: Planification inefficace et inadéquation avec les besoins actuels. | L44: Réviser le plan à une fréquence adaptée aux évolutions des besoins.
E45: Vérification de la fréquence de révision du plan pour refléter les besoins actuels. | F45: Le plan d’occupation des sols est-il révisé à une fréquence adaptée aux besoins actuels ? | G45: PAS | H45: Plans stratégiques, Rapports de conformité | I45: Absence d'alignement entre les analyses et les stratégies de développement. | J45: Faible | K45: Décalage entre les objectifs stratégiques et les actions mises en œuvre. | L45: Aligner les analyses avec les stratégies de développement pour maximiser leur impact.
E46: Alignement des analyses avec les stratégies de croissance ou de développement. | F46: Les analyses sont-elles alignées avec les stratégies de développement ? | G46: PAS | H46: Registres de consultation, Comptes-rendus | I46: Inclusion insuffisante des parties prenantes dans la mise à jour du POS. | J46: Faible | K46: Décisions non représentatives des besoins réels des parties prenantes. | L46: Impliquer activement toutes les parties prenantes dans les processus de mise à jour.
E47: Inclusion des parties prenantes dans le processus de mise à jour du POS. | F47: Les parties prenantes sont-elles incluses dans la mise à jour du POS ? | G47: PAS | H47: Indicateurs de performance, Études d'impact | I47: Modifications du POS sans évaluation de leur impact sur les objectifs organisationnels. | J47: Moyenne | K47: Difficulté à mesurer l’efficacité des changements apportés. | L47: Évaluer systématiquement l’impact des modifications sur les objectifs organisationnels.
E48: Évaluation des impacts des modifications du POS sur les objectifs organisationnels. | F48: Les modifications du POS ont-elles un impact mesurable sur les objectifs organisationnels ? | G48: OUI | H48: Normes sectorielles, Rapports d’audit | I48: Technologies utilisées non conformes aux standards sectoriels. | J48: Faible | K48: Risques de non-conformité réglementaire et inefficacité opérationnelle. | L48: S’assurer que toutes les technologies respectent les standards sectoriels en vigueur.
D49: Vérifier la cohérence et l’homogénéité des technologies | E49: Comparaison des technologies utilisées par rapport aux standards sectoriels. | F49: Les technologies utilisées respectent-elles les standards sectoriels ? | G49: OUI | H49: Rapports de compatibilité, Inventaires techniques | I49: Incompatibilités entre les technologies déployées. | J49: Faible | K49: Dysfonctionnements et inefficacités dans les processus. | L49: Vérifier la compatibilité des technologies avant leur déploiement.
E50: Analyse de l’interopérabilité entre les technologies déployées dans l’organisation. | F50: Les technologies déployées sont-elles compatibles entre elles ? | G50: NON | H50: Inventaires, Rapports d’audit | I50: Duplications ou incompatibilités inutiles dans l’environnement technologique. | J50: Moyenne | K50: Augmentation des coûts et complexité inutile dans la gestion des systèmes. | L50: Rationaliser l’environnement technologique pour éliminer les duplications et incompatibilités.
E51: Évaluation des duplications inutiles ou incompatibilités dans l’environnement technologique. | F51: L’environnement technologique contient-il des duplications ou incompatibilités inutiles ? | G51: NON | H51: Études fonctionnelles, Rapports d’utilisation | I51: Outils technologiques inadaptés à leurs fonctions prévues. | J51: Faible | K51: Baisse de productivité et inefficacité dans les processus. | L51: Évaluer et adapter les outils technologiques pour qu’ils répondent à leurs fonctions prévues.
E52: Qualité et adéquation des outils technologiques à leurs fonctions prévues. | F52: Les outils technologiques sont-ils adaptés à leurs fonctions prévues ? | G52: NON | H52: Indicateurs de performance, Études d’impact | I52: Technologies ne contribuant pas à l’amélioration des performances globales. | J52: Moyenne | K52: Investissements technologiques peu rentables et inefficaces. | L52: Prioriser les technologies qui démontrent un impact positif sur les performances globales.
E53: Impact des technologies sur les performances générales de l’organisation. | F53: Les technologies contribuent-elles à améliorer les performances générales de l’organisation ? | G53: OUI | H53: Registres centralisés, Rapports d’audit | I53: Absence de centralisation des référentiels, entraînant des doublons. | J53: Moyenne | K53: Perte de temps et inefficacité dans la gestion des données. | L53: Centraliser les référentiels pour éviter les doublons et améliorer la gestion des données.
D54: Vérifier l’existence et l’unicité des référentiels (clients, fournisseurs, articles…) et des saisies | E54: Analyse de la centralisation des référentiels pour éviter les doublons. | F54: La centralisation des référentiels permet-elle d’éviter les doublons ? | G54: OUI | H54: Historique des mises à jour, Rapports de conformité | I54: Référentiels non mis à jour périodiquement. | J54: Faible | K54: Décisions basées sur des données obsolètes, entraînant des erreurs stratégiques. | L54: Mettre à jour régulièrement les référentiels pour garantir leur pertinence.
E55: Vérification de la mise à jour régulière des référentiels pour garantir leur pertinence | F55: Les référentiels sont-ils mis à jour régulièrement pour garantir leur pertinence ? | G55: OUI | H55: Rapports d’intégration, Études de qualité | I55: Données saisies inexactes ou mal intégrées. | J55: Moyenne | K55: Résultats erronés et inefficacités dans les processus décisionnels. | L55: Vérifier l’exactitude et l’intégration des données saisies pour garantir leur fiabilité.
E56: Évaluation de l’exactitude et de l’intégrité des données saisies. | F56: Les données saisies sont-elles exactes et intègres ? | G56: NON | H56: Rapports d’utilisation, Comptes-rendus | I56: Référentiels utilisés de manière incohérente par les départements. | J56: Faible | K56: Manque de coordination et inefficacité dans les processus organisationnels. | L56: Promouvoir une utilisation cohérente des référentiels entre tous les départements.
E57: Utilisation cohérente des référentiels dans tous les départements de l’organisation. | F57: Les référentiels sont-ils utilisés de manière cohérente par tous les départements ? | G57: NON | H57: Manuels de processus, Historique des mises à jour | I57: Processus existants non documentés ou non mis à jour régulièrement. | J57: Moyenne | K57: Inefficacité opérationnelle et perte de savoir-faire organisationnel. | L57: Documenter rigoureusement les processus existants et garantir leur mise à jour régulière.
E58: Vérification de la sécurisation des référentiels pour protéger les données sensibles. | F58: Les référentiels sont-ils sécurisés pour protéger les données sensibles ? | G58: OUI | H58: Organigrammes, Rapports internes | I58: Rôles et responsabilités mal définis au sein de l’organisation. | J58: Faible | K58: Conflits internes, duplication des efforts, et baisse de productivité. | L58: Clarifier les rôles et responsabilités via des organigrammes et des rapports internes.
C59: Budgets et coûts informatiques | D59: Évaluer l’organisation et les processus existants | E59: Vérifier la documentation des processus existants et leur mise à jour régulière. | F59: Les processus existants sont-ils documentés et régulièrement mis à jour ? | G59: OUI | H59: Plans de communication, Procès-verbaux | I59: Communication inefficace entre les parties prenantes. | J59: Faible | K59: Mauvaise coordination et retards dans la mise en œuvre des projets. | L59: Renforcer la communication via des outils adaptés et des réunions fréquentes.
E60: Évaluer la clarté des responsabilités et des rôles définis au sein de l’organisation. | F60: Les rôles et responsabilités au sein de l’organisation sont-ils clairs ? | G60: OUI | H60: Stratégies organisationnelles, Plans opérationnels | I60: Processus non alignés sur les objectifs stratégiques de l’organisation. | J60: Faible | K60: Inefficacité à atteindre les objectifs stratégiques et ressources mal utilisées. | L60: Revoir et aligner les processus sur les objectifs stratégiques organisationnels.
E61: Analyser l’efficacité des mécanismes de communication entre les parties prenantes. | F61: La communication entre les parties prenantes est-elle efficace ? | G61: NON | H61: Rapports d’audit, Comptes-rendus des dysfonctionnements | I61: Dysfonctionnements ou redondances dans les processus. | J61: Moyenne | K61: Augmentation des coûts et baisse de la performance globale. | L61: Identifier les dysfonctionnements et rationaliser les processus pour réduire les redondances.
E62: Vérifier l’alignement des processus avec les objectifs stratégiques de l’organisation. | F62: Les processus sont-ils alignés sur les objectifs stratégiques de l’organisation ? | G62: NON | H62: Calculs financiers, Benchmarks sectoriels | I62: Ratios pertinents non calculés régulièrement ou mal exploités. | J62: Moyenne | K62: Difficulté à établir des analyses financières précises et à optimiser les performances économiques. | L62: Calculer régulièrement les ratios et les comparer à des benchmarks sectoriels pour améliorer les analyses.
E63: Identifier les points de dysfonctionnement ou de redondance dans les processus opérationnels | F63: Y a-t-il des dysfonctionnements ou redondances dans les processus ? | G63: OUI | H63: Études de pertinence, Sources fiables | I63: Données utilisées pour les ratios inexactes ou non pertinentes. | J63: Moyenne | K63: Décisions stratégiques basées sur des informations erronées. | L63: Vérifier systématiquement l’exactitude et la pertinence des données avant de les utiliser.
D64: Vérifier l’existence des ratios et des éléments de benchmark (interne et/ou externe, ratio coûts/CA, …) | E64: Examiner si des ratios pertinents (coûts/CA, coûts unitaires) sont calculés régulièrement. | F64: Les ratios pertinents (coûts/CA, etc.) sont-ils calculés régulièrement ? | G64: OUI | H64: Rapports d’analyse, Revues stratégiques | I64: Résultats des benchmark non exploités pour des décisions stratégiques. | J64: Faible | K64: Potentiel d’amélioration non utilisé et faible compétitivité. | L64: Intégrer systématiquement les résultats des benchmark dans les décisions stratégiques.
E65: Comparer les ratios internes à des références externes ou sectorielles pour détecter les écarts | F65: Les ratios internes sont-ils comparés à des références externes ou sectorielles ? | G65: NON | H65: Rapports de dépenses, Historique budgétaire | I65: Absence de catégorisation précise et de suivi des dépenses prioritaires. | J65: Faible | K65: Difficulté à analyser les dépenses et retards dans l’atteinte des objectifs financiers. | L65: Catégoriser précisément les dépenses et aligner celles prioritaires avec les objectifs organisationnels.
E66: Évaluer la pertinence et l’exactitude des données utilisées pour calculer ces ratios | F66: Les données utilisées pour les ratios sont-elles exactes et pertinentes ? | G66: NON | H66: Données vérifiées, Sources fiables | I66: Inexactitude ou non-pertinence des données utilisées pour les ratios. | J66: Faible | K66: Décisions stratégiques basées sur des informations erronées. | L66: Vérifier systématiquement l’exactitude et la pertinence des données avant leur utilisation.
E67: Vérifier si les résultats des benchmarks sont exploités pour prendre des décisions stratégiques. | F67: Les résultats des benchmarks sont-ils exploités pour des décisions stratégiques ? | G67: NON | H67: Rapports de benchmark, Études stratégiques | I67: Résultats des benchmarks non exploités pour des décisions stratégiques. | J67: Moyenne | K67: Potentiel d’amélioration non utilisé et faible compétitivité. | L67: Intégrer systématiquement les résultats des benchmarks dans les décisions stratégiques.
E68: Contrôler la fréquence d’analyse des ratios et des benchmarks pour garantir leur actualité. | F68: Les analyses des ratios sont-elles réalisées régulièrement ? | G68: NON | H68: Historique des analyses, Rapports périodiques | I68: Analyses des ratios non réalisées régulièrement. | J68: Faible | K68: Difficulté à identifier les tendances et à optimiser les performances. | L68: Mettre en place un calendrier régulier pour la réalisation des analyses des ratios.
D69: Analyser la répartition des dépenses | E69: Identifier les catégories de dépenses et leur répartition (logiciels, matériels, services cloud, maintenance, etc.). | F69: Les dépenses sont-elles catégorisées et répertoriées avec précision ? | G69: NON | H69: Registres de dépenses, Catégorisation précise | I69: Absence de catégorisation et de répertoriage précis des dépenses. | J69: Faible | K69: Difficulté à analyser les dépenses et retards dans l’atteinte des objectifs financiers. | L69: Catégoriser précisément les dépenses pour faciliter leur analyse et aligner celles prioritaires avec les objectifs.
E70: Analyser la proportion des dépenses allouées aux priorités stratégiques | F70: Les dépenses prioritaires sont-elles alignées avec les objectifs stratégiques ? | G70: NON | H70: Plans stratégiques, Rapports financiers | I70: Dépenses prioritaires non alignées avec les objectifs stratégiques. | J70: Faible | K70: Inefficacité dans l’utilisation des ressources et échec des objectifs stratégiques. | L70: Aligner les dépenses prioritaires avec les objectifs stratégiques pour maximiser leur impact.
E71: Vérifier l’existence d’un suivi régulier des dépenses par catégorie | F71: Existe-t-il un suivi régulier des dépenses par catégorie ? | G71: NON | H71: Rapports de suivi, Indicateurs de performance | I71: Suivi irrégulier des dépenses par catégorie. | J71: Faible | K71: Manque de visibilité sur les écarts et inefficacité dans la gestion financière. | L71: Instaurer un suivi régulier des dépenses par catégorie pour améliorer la gestion financière.
E72: Détecter les écarts éventuels entre les budgets prévus et les dépenses réelles | F72: Les écarts entre budget prévu et dépenses réelles sont-ils analysés ? | G72: NON | H72: Rapports d’écarts, Études budgétaires | I72: Écarts entre budget prévu et dépenses réelles non analysés. | J72: Moyenne | K72: Difficulté à ajuster les budgets et à optimiser les ressources. | L72: Analyser systématiquement les écarts pour ajuster les budgets et améliorer la gestion des ressources.
E73: Évaluer si des initiatives d’optimisation des coûts (comme la consolidation ou la migration vers le cloud) sont mises en œuvre. | F73: Des initiatives d’optimisation des coûts sont-elles mises en œuvre ? | G73: OUI | H73: Plans d’optimisation, Rapports d’initiatives | I73: Initiatives d’optimisation des coûts non mises en œuvre. | J73: Faible | K73: Augmentation des coûts et inefficacité dans la gestion des projets. | L73: Mettre en œuvre des initiatives d’optimisation des coûts pour réduire les dépenses inutiles.
D74: Évaluer la rentabilité des investissements IT | E74: Vérifier si des analyses de retour sur investissement (ROI) sont effectuées avant tout projet. | F74: Le retour sur investissement (ROI) est-il évalué avant chaque projet IT ? | G74: OUI | H74: Études de ROI, Rapports pré-projets | I74: Retour sur investissement (ROI) non évalué avant chaque projet IT. | J74: Faible | K74: Risques d’investissements non rentables et inefficaces. | L74: Évaluer systématiquement le ROI avant chaque projet IT pour garantir leur rentabilité.
E75: Contrôler si les bénéfices attendus des investissements IT sont mesurés après leur mise en œuvre | F75: Les bénéfices des investissements IT sont-ils mesurés après leur mise en œuvre ? | G75: OUI | H75: Rapports post-projets, Indicateurs de bénéfices | I75: Bénéfices des investissements IT non mesurés après leur mise en œuvre. | J75: Moyenne | K75: Difficulté à démontrer la valeur ajoutée des investissements et à justifier leur maintien. | L75: Mesurer les bénéfices des investissements IT après leur mise en œuvre pour évaluer leur impact.
E76: Comparer les coûts des projets IT aux bénéfices réalisés pour évaluer leur rentabilité | F76: Les coûts des projets IT sont-ils comparés aux bénéfices obtenus ? | G76: NON | H76: Études comparatives, Rapports d’analyse | I76: Coûts des projets IT non comparés aux bénéfices obtenus. | J76: Faible | K76: Risques de surinvestissement et inefficacité dans la gestion des ressources. | L76: Comparer systématiquement les coûts des projets IT aux bénéfices obtenus pour optimiser les investissements.
E77: Examiner la contribution des investissements IT aux objectifs stratégiques de l’organisation. | F77: Les investissements IT contribuent-ils aux objectifs stratégiques ? | G77: NON | H77: Plans stratégiques, Rapports d’alignement | I77: Investissements IT non alignés avec les objectifs stratégiques. | J77: Moyenne | K77: Décalage entre les actions IT et les objectifs organisationnels. | L77: Aligner les investissements IT avec les objectifs stratégiques pour maximiser leur impact.
E78: Analyser si des outils de suivi sont utilisés pour mesurer la rentabilité des projets IT sur le long terme | F78: Des outils sont-ils utilisés pour suivre la rentabilité des projets IT sur le long terme ? | G78: NON | H78: Outils de suivi, Rapports de rentabilité | I78: Absence d’outils pour suivre la rentabilité des projets IT sur le long terme. | J78: Moyenne | K78: Difficulté à évaluer la performance des projets et à ajuster les stratégies. | L78: Utiliser des outils de suivi pour surveiller la rentabilité des projets IT sur le long terme.
D79: Contrôler la conformité budgétaire | E79: Vérifier si les budgets sont alignés avec les politiques financières internes et les objectifs stratégiques | F79: Les budgets respectent-ils les politiques financières internes et les objectifs ? | G79: NON | H79: Politiques financières, Rapports budgétaires | I79: Budgets non représentatifs des politiques financières internes et des objectifs. | J79: Moyenne | K79: Incohérence entre les budgets et les objectifs organisationnels. | L79: Revoir les budgets pour les aligner avec les politiques financières internes et les objectifs.
E80: Examiner la documentation des processus de validation des budgets (approbations, ajustements, etc.). | F80: Les processus de validation des budgets sont-ils bien documentés ? | G80: NON | H80: Procédures de validation, Rapports de conformité | I80: Processus de validation des budgets non documentés. | J80: Faible | K80: Manque de transparence et difficulté à justifier les décisions budgétaires. | L80: Documenter les processus de validation des budgets pour renforcer leur transparence et leur fiabilité.
E81: Contrôler la gestion des écarts entre budgets et dépenses réelles, et les actions correctives mises en place. | F81: Les écarts entre budget et dépenses sont-ils gérés de manière proactive ? | G81: NON | H81: Rapports d’écarts, Plans d’ajustement | I81: Écarts entre budget et dépenses non gérés de manière proactive. | J81: Moyenne | K81: Accumulation de retards et inefficacité dans la gestion financière. | L81: Gérer de manière proactive les écarts pour limiter les impacts négatifs sur les budgets.
E82: S’assurer que les budgets respectent les réglementations financières locales et sectorielles | F82: Les budgets respectent-ils les réglementations financières en vigueur ? | G82: PAS | H82: Rapports réglementaires, Études de conformité | I82: Budgets ne respectant pas les réglementations financières en vigueur. | J82: Faible | K82: Risques juridiques et non-conformité réglementaire. | L82: S’assurer que les budgets respectent les réglementations financières en vigueur.
E83: Évaluer la mise en œuvre d’outils de reporting pour surveiller l’état des budgets en temps réel | F83: Des outils de reporting sont-ils utilisés pour surveiller les budgets en temps réel ? | G83: OUI | H83: Outils de reporting, Indicateurs en temps réel | I83: Absence d’outils de reporting pour surveiller les budgets en temps réel. | J83: Faible | K83: Manque de visibilité sur les écarts et difficulté à ajuster les budgets rapidement. | L83: Utiliser des outils de reporting pour surveiller les budgets en temps réel et améliorer leur gestion.
C84: Mesure et suivi de la performance informatique | D84: Vérifier que des objectifs de court, moyen et long termes existent et sont assignés à la DSI (approche BSC ?) et que ces objectifs sont déclinés au sein de l’entité | E84: Existence de documents officiels définissant les objectifs à court, moyen et long termes. | F84: Les objectifs à court, moyen et long terme sont-ils documentés ? | G84: NON | H84: Documentation des objectifs, Plans stratégiques | I84: Objectifs non documentés, entraînant un manque de clarté et de suivi. | J84: Moyenne | K84: Difficulté à aligner les actions avec les priorités organisationnelles. | L84: Documenter les objectifs à court, moyen et long terme pour garantir leur clarté et leur suivi.
E85: Alignement des objectifs avec la stratégie globale de l'organisation. | F85: Les objectifs sont-ils alignés sur la stratégie globale de l’organisation ? | G85: NON | H85: Stratégies organisationnelles, Rapports d’alignement | I85: Objectifs non alignés avec la stratégie globale de l’organisation. | J85: Moyenne | K85: Décalage entre les actions et les objectifs stratégiques, réduisant l’efficacité globale. | L85: Aligner les objectifs avec la stratégie globale pour maximiser leur impact.
E86: Déclinaison des objectifs au niveau des différentes équipes ou départements de la DSI | F86: Les objectifs sont-ils déclinés dans les équipes ou départements de la DSI ? | G86: NON | H86: Plans opérationnels, Rapports internes | I86: Objectifs non déclinés dans les équipes ou départements de la DSI. | J86: Moyenne | K86: Manque de coordination et d’implication des équipes dans l’atteinte des objectifs. | L86: Décliner les objectifs dans les équipes pour renforcer leur implication et leur efficacité.
E87: Mise en place d’un processus de suivi et d’évaluation des objectifs (par exemple : Balanced Scorecard, BSC). | F87: Un processus de suivi des objectifs est-il mis en place ? | G87: OUI | H87: Procédures de suivi, Indicateurs de performance | I87: Absence de processus de suivi des objectifs. | J87: Moyenne | K87: Difficulté à mesurer les progrès et à ajuster les actions en conséquence. | L87: Mettre en place un processus de suivi des objectifs pour garantir leur atteinte.
E88: Fréquence et régularité de la révision ou de l’ajustement des objectifs selon les évolutions | F88: Les objectifs sont-ils révisés régulièrement pour s’adapter aux évolutions ? | G88: OUI | H88: Rapports d’évaluation, Historique des révisions | I88: Objectifs non révisés régulièrement pour s’adapter aux évolutions. | J88: Moyenne | K88: Objectifs obsolètes, limitant leur pertinence et leur efficacité. | L88: Réviser régulièrement les objectifs pour les adapter aux évolutions et aux besoins émergents.
D89: Vérifier l’existence d’un comité informatique regroupant les différentes directions de l’organisation | E89: Création officielle d’un comité informatique avec des documents attestant de son existence | F89: Un comité informatique a-t-il été officiellement créé ? | G89: NON | H89: Actes de création, Statuts | I89: Comité informatique non officiellement créé. | J89: Moyenne | K89: Manque de structure formelle et de légitimité dans la gouvernance informatique. | L89: Créer officiellement un comité informatique avec des statuts validés.
E90: Représentation équitable des différentes directions dans le comité (métier, IT, finance, etc.). | F90: Les directions concernées sont-elles équitablement représentées dans le comité ? | G90: NON | H90: Organigrammes, Listes de membres | I90: Directions concernées non systématiquement représentées dans le comité. | J90: Moyenne | K90: Décisions biaisées et non représentatives des besoins globaux. | L90: S’assurer que toutes les directions concernées sont représentées dans le comité.
E91: Régularité des réunions organisées par le comité (fréquence définie et respectée) | F91: Les réunions du comité sont-elles organisées régulièrement ? | G91: OUI | H91: Calendrier des réunions, Comptes-rendus | I91: Réunions du comité non organisées régulièrement. | J91: Moyenne | K91: Manque de coordination et de suivi des projets IT. | L91: Établir un calendrier régulier pour les réunions et garantir leur tenue systématique.
E92: Qualité des décisions prises par le comité et leur impact mesurable sur les projets IT | F92: Les décisions du comité ont-elles un impact mesurable sur les projets IT ? | G92: NON | H92: Rapports d’impact, Indicateurs de performance | I92: Décisions du comité sans impact mesurable sur les projets IT. | J92: Moyenne | K92: Difficulté à démontrer la valeur ajoutée du comité. | L92: Définir des indicateurs pour mesurer l’impact des décisions du comité sur les projets IT.
E93: Documentation systématique des comptes rendus et des décisions prises lors des réunions. | F93: Les comptes rendus des réunions sont-ils systématiquement documentés ? | G93: OUI | H93: Comptes-rendus, Registres des décisions | I93: Décisions du comité non documentées systématiquement. | J93: Moyenne | K93: Perte d’informations et manque de traçabilité. | L93: Documenter systématiquement toutes les décisions prises par le comité.
D94: Évaluer la pertinence des indicateurs de qualité et de performance ainsi que les moyens et outils de mesure | E94: Clarté et pertinence des indicateurs de performance définis pour évaluer la qualité des services IT | F94: Les indicateurs de performance définis sont-ils clairs et pertinents ? | G94: OUI | H94: Indicateurs définis, Rapports d’analyse | I94: Indicateurs de performance non clairs ou non pertinents. | J94: Faible | K94: Difficulté à évaluer les performances et à ajuster les actions. | L94: Définir des indicateurs clairs et pertinents pour mesurer efficacement les performances.
E95: Adéquation des outils de mesure utilisés pour collecter et analyser les données | F95: Les outils utilisés pour mesurer les données sont-ils adéquats ? | G95: OUI | H95: Outils d’analyse, Rapports techniques | I95: Outils utilisés pour mesurer les données non adaptés. | J95: Moyenne | K95: Résultats biaisés ou peu fiables, limitant la prise de décision. | L95: Utiliser des outils adaptés pour garantir la fiabilité des mesures et des analyses.
E96: Mise à jour régulière des indicateurs pour refléter les priorités et les besoins actuels de l’organisation | F96: Les indicateurs sont-ils mis à jour régulièrement pour refléter les besoins ? | G96: NON | H96: Historique des mises à jour, Procédures d’audit | I96: Indicateurs non mis à jour régulièrement pour refléter les besoins. | J96: Moyenne | K96: Décalage entre les indicateurs et les besoins actuels, réduisant leur pertinence. | L96: Mettre à jour régulièrement les indicateurs pour les aligner avec les besoins évolutifs.
E97: Existence de seuils ou d’objectifs mesurables liés à ces indicateurs | F97: Des objectifs mesurables sont-ils définis pour chaque indicateur ? | G97: NON | H97: Objectifs mesurables, Rapports de suivi | I97: Absence d’objectifs mesurables pour chaque indicateur. | J97: Élevée | K97: Difficulté à évaluer les progrès et à atteindre les objectifs. | L97: Définir des objectifs mesurables pour chaque indicateur afin de faciliter leur suivi.
E98: Analyse des écarts entre les performances mesurées et les objectifs fixés | F98: Les écarts entre résultats et objectifs sont-ils analysés ? | G98: OUI | H98: Rapports d’écarts, Études d’analyse | I98: Écarts entre résultats et objectifs non analysés. | J98: Moyenne | K98: Difficulté à identifier les causes des écarts et à ajuster les actions. | L98: Analyser systématiquement les écarts pour ajuster les actions et améliorer les performances.
D99: Vérifier que la DSI tient un tableau de bord (idéalement de type BSC) permettant un suivi consolidé de la performance (opérationnelle et financière) et de la qualité des prestations informatiques | E99: Existence d’un tableau de bord consolidé permettant une visualisation claire des performances. | F99: Un tableau de bord consolidé existe-t-il pour visualiser les performances ? | G99: OUI | H99: Tableaux de bord consolidés, Rapports de synthèse | I99: Absence de tableau de bord consolidé pour visualiser les performances. | J99: Faible | K99: Manque de visibilité globale sur les performances et les progrès. | L99: Mettre en place un tableau de bord consolidé pour visualiser et suivre les performances.
E100: Utilisation d’une méthode reconnue comme le Balanced Scorecard (BSC) pour structurer le tableau de bord. | F100: Le tableau de bord est-il structuré avec une méthode comme le BSC ? | G100: OUI | H100: Méthodologie BSC, Documentation structurant le tableau de bord | I100: Absence de méthode structurante comme le BSC pour le tableau de bord. | J100: Moyenne | K100: Informations désorganisées, rendant les décisions stratégiques moins efficaces. | L100: Structurer le tableau de bord avec une méthode comme le BSC pour optimiser la prise de décision.
E101: Inclusion de données opérationnelles et financières dans le tableau de bord. | F101: Le tableau de bord inclut-il des données opérationnelles et financières ? | G101: OUI | H101: Rapports financiers et opérationnels | I101: Données opérationnelles et financières non intégrées dans le tableau de bord. | J101: Moyenne | K101: Analyse incomplète des performances organisationnelles. | L101: Inclure des données opérationnelles et financières dans le tableau de bord pour une vue complète.
E102: Actualisation régulière des données figurant dans le tableau de bord pour refléter la situation en temps réel. | F102: Les données du tableau de bord sont-elles régulièrement actualisées ? | G102: NON | H102: Historique des mises à jour, Rapports d’actualisation | I102: Actualisation irrégulière des données du tableau de bord. | J102: Moyenne | K102: Décisions basées sur des données obsolètes et risques d’erreurs stratégiques. | L102: Mettre à jour régulièrement les données du tableau de bord pour garantir leur pertinence.
...

Sheet 4.3
A3: Domaines | B3: Points de Contrôle | C3: Objectifs de Contrôle | D3: Critère d’Évaluation | E3: Question d’Évaluation | F3: Réponses | G3: Documents Requis | H3: Risques | I3: Criticités | J3: Conséquences | K3: Recommandations
A4: Audit et Contrôle des Projets Informatiques | B4: Objectifs et enjeux du projet | C4: S’assurer qu’une étude de la valeur et des études d'opportunité et d'impacts ont été réalisées | D4: Exhaustivité des données collectées pour l’étude | E4: Les données collectées couvrent-elles toutes les exigences de l'étude ? | F4: OUI | G4: Le document décrivant les responsabilités des directions des projets et de la production. | H4: de ne pas évaluer de manière exhaustive les besoins des utilisateurs. | I4: Élevée | J4: Décisions prises basées sur des besoins utilisateurs mal évalués, menant à une faible satisfaction des parties prenantes. | K4: Développer des méthodologies pour évaluer avec précision les besoins des utilisateurs finaux.
D5: Pertinence de l’analyse des bénéfices attendus | E5: Les bénéfices analysés sont-ils conformes aux objectifs de l'étude ? | F5: NON | G5: Le formulaire de demandes d'évolution standardisé. | H5: de non-conformité des évolutions aux normes en vigueur. | I5: Moyenne | J5: Application d'évolutions non conformes aux normes, entraînant des sanctions réglementaires et des retards dans le projet. | K5: Mettre en œuvre des audits pour garantir que toutes les évolutions respectent les normes applicables.
D6: Identification précise des coûts associés à l’étude | E6: Les coûts identifiés sont-ils détaillés et justifiés ? | F6: NON | G6: Le registre dédié aux évolutions du périmètre. | H6: de mauvaise communication entre la MOA et la MOE entraînant des malentendus. | I6: Élevée | J6: Malentendus entre la MOA et la MOE pouvant causer des livrables non adaptés aux exigences initiales. | K6: Améliorer la communication entre la MOA et la MOE pour aligner les attentes et les livrables.
D7: Évaluation rigoureuse des risques potentiels | E7: Les risques ont-ils été évalués de manière exhaustive et cohérente ? | F7: OUI | G7: La procédure formalisée de gestion des évolutions. | H7: de surcharge ou d'indisponibilité des ressources clés pour le projet. | I7: Moyenne | J7: Retards et surcharges opérationnelles dus à l'indisponibilité ou mauvaise gestion des ressources clés. | K7: Renforcer la gestion des ressources pour éviter les retards et les surcharges.
D8: Cohérence entre les résultats de l’étude et les objectifs stratégiques. | E8: Les résultats obtenus sont-ils alignés avec les objectifs stratégiques fixés ? | F8: OUI | G8: Les analyses d’impact des évolutions documentées. | H8: Risque de non-respect des délais dans la mise en œuvre des solutions. | I8: Élevée | J8: Non-respect des délais prévus, nuisant à la crédibilité et aux relations avec les parties prenantes. | K8: Mettre en place des outils de suivi des délais afin d'assurer le respect des échéances.
C9: S’assurer qu’un bilan critique des processus existants a été effectué | D9: Identification des processus obsolètes. | E9: Les processus obsolètes ont-ils été correctement identifiés ? | F9: OUI | G9: Les validations contractuelles pour la transition garantie-maintenance. | H9: Risque d’un manque de clarté dans la définition des rôles et responsabilités. | I9: Moyenne | J9: Définition floue des rôles et responsabilités entraînant des conflits et une inefficacité organisationnelle. | K9: Clarifier les rôles et responsabilités pour réduire les conflits organisationnels.
D10: Analyse des inefficacités majeures des processus. | E10: Les inefficacités identifiées affectent-elles significativement la performance ? | F10: OUI | G10: Les registres des versions archivées. | H10: Risque de conflits mal gérés entre parties prenantes, impactant le projet. | I10: Moyenne | J10: Conflits mal gérés entre parties prenantes provoquant des retards ou l'arrêt complet du projet. | K10: Introduire des stratégies pour prévenir et gérer efficacement les conflits entre parties prenantes.
D11: Évaluation des améliorations possibles dans les processus. | E11: Les propositions d'amélioration répondent-elles aux besoins des parties prenantes ? | F11: OUI | G11: Les feuilles de temps ou les journaux de suivi des tâches. | H11: Risque d'insuffisance des compétences des équipes pour utiliser les nouvelles technologies. | I11: Élevée | J11: Incapacité des équipes à utiliser correctement les nouvelles technologies, générant des erreurs et une baisse de qualité. | K11: Former les équipes aux nouvelles technologies pour minimiser les erreurs et améliorer la qualité.
D12: Définition claire des priorités dans le bilan critique. | E12: Les priorités sont-elles définies avec clarté et validées ? | F12: NON | G12: La documentation des tests réalisés par la MOE. | H12: Risque de dérive des coûts liés à une mauvaise estimation des besoins. | I12: Élevée | J12: Mauvaise estimation des besoins entraînant une dérive des coûts, impactant le budget global. | K12: Réaliser des estimations budgétaires précises pour limiter les dérives des coûts.
D13: Usage d'une méthode systématique pour le bilan. | E13: La méthode utilisée est-elle systématique et reconnue ? | F13: PAS | G13: Les rapports de validation des décisions prises. | H13: Risque de documentation des spécifications techniques incomplète ou erronée. | I13: Élevée | J13: Spécifications techniques incomplètes ou erronées provoquant des livrables non conformes aux attentes. | K13: Valider et compléter les spécifications techniques avant le démarrage du projet.
C14: S’assurer que le choix de recourir à un nouveau système est obtenu après optimisation des processus concernés et vérification que cette optimisation ne suffit pas à apporter par elle-même les gains de performance attendus | D14: Exhaustivité de l’analyse des processus existants. | E14: Les scénarios envisagés couvrent-ils toutes les possibilités pertinentes ? | F14: OUI | G14: Les audits réguliers des actions des fournisseurs. | H14: Risque d'incompatibilité des nouvelles versions avec les systèmes existants. | I14: Élevée | J14: Nouveaux systèmes incompatibles avec les infrastructures existantes, provoquant des dysfonctionnements majeurs. | K14: Tester la compatibilité des nouveaux systèmes avec les infrastructures existantes.
D15: Justification claire du recours au nouveau système. | E15: Les impacts des évolutions technologiques ont-ils été correctement évalués ? | F15: OUI | G15: Les contrats intégrant les engagements des fournisseurs. | H15: Risque d’un manque de traçabilité des décisions prises durant le projet. | I15: Moyenne | J15: Absence de traçabilité des décisions compliquant la justification et la révision des orientations stratégiques. | K15: Instaurer un système de traçabilité pour documenter et justifier les décisions stratégiques.
D16: Identification des gains de performance attendus et mesurables. | E16: Les coûts liés aux nouvelles solutions ont-ils été estimés avec précision ? | F16: NON | G16: Un document détaillant les responsabilités respectives lors de la mise en production. | H16: Risque de non-adhésion des utilisateurs finaux en raison de besoins mal définis. | I16: Élevée | J16: Besoins mal définis des utilisateurs finaux causant une faible adhésion et des difficultés de mise en œuvre. | K16: Mieux définir les besoins des utilisateurs pour faciliter l'adhésion et la mise en œuvre des projets.
D17: Évaluation des limites de l’optimisation des processus actuels. | E17: Les risques identifiés pour chaque alternative sont-ils exhaustifs et documentés ? | F17: OUI | G17: Un manuel d’utilisation validé par les parties prenantes. | H17: Risque d'impacts sous-évalués des décisions sur les objectifs globaux. | I17: Élevée | J17: Impacts sous-évalués sur les objectifs globaux affectant la réussite et la viabilité du projet. | K17: Évaluer les impacts sur les objectifs globaux pour anticiper et réduire les risques.
D18: Analyse des coûts et des bénéfices comparatifs entre l’optimisation et le nouveau système. | E18: Les critères d’évaluation utilisés pour choisir une solution sont-ils objectifs et pertinents ? | F18: PAS | G18: Les plans d’audit pour évaluer la conformité des actions des fournisseurs. | H18: Risque de non-conformité des procédures aux évolutions des réglementations. | I18: Moyenne | J18: Procédures non conformes aux évolutions réglementaires entraînant des risques juridiques et opérationnels. | K18: Mettre à jour les procédures pour garantir leur conformité aux évolutions réglementaires.
C19: S’assure que les objectifs et périmètres du projet sont définis, partagés et stabilisés | D19: Clarté et alignement des objectifs stratégiques du projet. | E19: Les demandes d’évolution du périmètre respectent-elles les procédures définies ? | F19: OUI | G19: Les rapports d’analyse des bénéfices et impacts des évolutions. | H19: Risque d'une mauvaise priorisation des tâches critiques du projet. | I19: Élevée | J19: Mauvaise priorisation des tâches critiques causant des retards et des inefficacités dans la gestion du projet. | K19: Prioriser les tâches critiques pour améliorer la gestion globale des projets.
D20: Définition précise et réaliste des périmètres du projet. | E20: Les mesures d’impact des changements sont-elles conformes aux attentes du projet ? | F20: PAS | G20: La documentation détaillée des procédures de validation des étapes du projet. | H20: Risque d’évolutions demandées sans validation approfondie des impacts. | I20: Élevée | J20: Évolutions mises en œuvre sans validation approfondie générant des incohérences et des coûts supplémentaires. | K20: Valider minutieusement toutes les évolutions avant leur mise en œuvre.
D21: Validation formelle des objectifs et périmètres par les parties prenantes. | E21: Les tests effectués par la MOE garantissent-ils la conformité fonctionnelle des composants ? | F21: PAS | G21: Les registres des anomalies identifiées et des corrections effectuées. | H21: Risque d’une mauvaise gestion des sauvegardes et de la sécurité des données. | I21: Élevée | J21: Mauvaise gestion des sauvegardes et de la sécurité des données entraînant des pertes ou des violations. | K21: Améliorer la gestion des sauvegardes et renforcer les mécanismes de sécurité des données.
D22: Mise en place d’indicateurs pour le suivi des périmètres. | E22: Les décisions prises dans le projet respectent-elles les délais établis ? | F22: PAS | G22: Les contrats formalisant les engagements pour la période post-garantie. | H22: Risque d’interfaces insuffisamment testées et causant des erreurs dans le SI. | I22: Moyenne | J22: Interfaces non testées provoquant des erreurs fonctionnelles affectant la productivité et la satisfaction des utilisateurs. | K22: Tester systématiquement les interfaces pour prévenir les erreurs fonctionnelles.
D23: Stabilité des objectifs et périmètres au cours du projet. | E23: La transition de la garantie à la maintenance est-elle clairement encadrée par des documents contractuels ? | F23: PAS | G23: Les fiches de suivi des tâches et des avancements par équipe. | H23: Risque d’une mauvaise évaluation de la criticité des risques documentés. | I23: Élevée | J23: Criticité des risques documentés mal évaluée provoquant des difficultés dans leur gestion et leur mitigation. | K23: Évaluer correctement la criticité des risques afin de faciliter leur gestion.
C24: S’assurer que les principales orientations du système cible ont été explicitées ; | D24: Définition des priorités stratégiques dans les orientations. | E24: Les priorités stratégiques définies sont-elles adaptées aux besoins de l'organisation ? | F24: NON | G24: Les documents validant les tests fonctionnels réalisés. | H24: Risque d'inadéquation des priorités stratégiques aux besoins réels de l'organisation. | I24: Élevée | J24: Inadéquation des priorités stratégiques aux besoins réels de l'organisation menant à une perte d'efficacité. | K24: Aligner les priorités stratégiques aux besoins réels pour renforcer l'efficacité organisationnelle.
D25: Identification des ressources nécessaires au système cible | E25: Les ressources nécessaires au système cible ont-elles été identifiées correctement ? | F25: NON | G25: Les accords de validation des versions mises en production. | H25: Risque de mauvaise identification des ressources nécessaires au système cible. | I25: Moyenne | J25: Ressources nécessaires mal identifiées ou sous-estimées provoquant une surcharge opérationnelle. | K25: Identifier et allouer efficacement les ressources nécessaires au projet.
D26: Alignement des orientations avec les besoins de l’organisation. | E26: Les orientations prises s'alignent-elles avec les objectifs à long terme de l'organisation ? | F26: NON | G26: Rapport d'analyse des orientations stratégiques | H26: Risque de divergence entre les orientations prises et les objectifs à long terme. | I26: Élevée | J26: Orientations divergentes par rapport aux objectifs à long terme impactant la cohérence et la réussite du projet. | K26: Réconcilier les objectifs à court terme avec les objectifs stratégiques à long terme.
D27: Cohérence des orientations avec les objectifs à long terme. | E27: Les orientations proposées sont-elles techniquement et financièrement faisables ? | F27: NON | G27: Étude de faisabilité technique et financière | H27: Risque d'infaisabilité technique ou financière des orientations proposées. | I27: Moyenne | J27: Orientations techniques ou financières irréalisables causant une perte de temps et d'investissements inutiles. | K27: Élaborer des orientations techniques et financières réalistes pour limiter les pertes.
D28: Faisabilité technique et financière des orientations proposées | E28: Les rôles et responsabilités des acteurs ont-ils été définis clairement ? | F28: NON | G28: Document de répartition des rôles et responsabilités | H28: Risque de flou dans la définition des rôles et responsabilités des acteurs. | I28: Élevée | J28: Flou dans la définition des rôles et responsabilités créant des zones d'ombre et des conflits organisationnels. | K28: Définir clairement les responsabilités pour éviter les conflits et zones d'ombre.
C29: S’assurer que les principaux acteurs sont identifiés | D29: Identification exhaustive des parties prenantes clés. | E29: Les compétences et ressources des acteurs identifiés sont-elles suffisantes ? | F29: OUI | G29: Fiche d'évaluation des compétences et ressources disponibles | H29: Risque d'insuffisance des compétences ou des ressources des acteurs identifiés. | I29: Élevée | J29: Compétences ou ressources insuffisantes entraînant des retards et une diminution de la qualité des livrables. | K29: Renforcer les compétences ou ressources pour éviter les retards et garantir la qualité des livrables.
D30: Définition claire des rôles et responsabilités de chaque acteur. | E30: Les acteurs adhèrent-ils pleinement aux objectifs du projet ? | F30: OUI | G30: Questionnaire de feedback des acteurs sur leur engagement | H30: Risque de désengagement des acteurs vis-à-vis des objectifs du projet. | I30: Élevée | J30: Désengagement des acteurs vis-à-vis des objectifs du projet nuisant à la coordination et à la motivation globale. | K30: Créer des initiatives pour maintenir l’engagement des acteurs sur les objectifs du projet.
D31: Évaluation des compétences et ressources des acteurs identifiés. | E31: Les estimations des coûts sont-elles précises et conformes aux objectifs ? | F31: PAS | G31: Rapport d'estimation des coûts | H31: Risque d'imprécision des estimations de coûts par rapport aux objectifs définis. | I31: Élevée | J31: Dépassement des coûts par rapport aux objectifs définis impactant la viabilité financière du projet. | K31: Mettre en œuvre une gestion rigoureuse des coûts pour éviter les dépassements budgétaires.
D32: Engagement et adhésion des parties prenantes au projet. | E32: Les écarts identifiés sont-ils correctement gérés et documentés ? | F32: OUI | G32: Registre de suivi des écarts | H32: Risque de gestion inefficace des écarts identifiés. | I32: Élevée | J32: Gestion inefficace des incidents identifiés augmentant les risques et les coûts indirects. | K32: Améliorer la gestion des incidents pour réduire les risques et les coûts indirects.
D33: Coordination entre les différents acteurs pour garantir l’atteinte des objectifs. | E33: Les impacts sur les infrastructures existantes ont-ils été évalués efficacement ? | F33: OUI | G33: Étude d'impact sur les infrastructures | H33: Risque de sous-évaluation des impacts sur les infrastructures existantes. | I33: Moyenne | J33: Sous-évaluation des impacts sur les infrastructures existantes provoquant des perturbations majeures. | K33: Analyser en profondeur les impacts des évolutions sur les infrastructures existantes.
C34: S’assurer que les coûts sont évalués | D34: Précision des estimations des coûts | E34: Les méthodes de gestion des changements sont-elles clairement définies et appliquées ? | F34: OUI | G34: Manuel des procédures de gestion des changements | H34: Risque d'une mauvaise définition ou application des méthodes de gestion des changements. | I34: Moyenne | J34: Une mauvaise définition ou application des méthodes de gestion des changements entraîne des retards et des incohérences dans le projet. | K34: Définir et appliquer des méthodes de gestion des changements cohérentes et efficaces.
D35: Exhaustivité des données de coûts | E35: Les risques liés aux évolutions sont-ils évalués et documentés avant mise en œuvre ? | F35: OUI | G35: Document d'analyse des risques des évolutions | H35: Risque d'une évaluation inadéquate ou d'une documentation insuffisante des risques liés aux évolutions. | I35: Élevée | J35: Une évaluation inadéquate ou une documentation insuffisante des risques liés aux évolutions augmente les probabilités de défaillances imprévues. | K35: Documenter les risques liés aux évolutions pour anticiper et prévenir les défaillances imprévues.
D36: Conformité des méthodes d’évaluation des coûts | E36: Les parties prenantes validant les évolutions sont-elles impliquées à chaque étape ? | F36: OUI | G36: Rapports de validation des évolutions par les parties prenantes | H36: Risque d'une implication insuffisante des parties prenantes dans la validation des évolutions. | I36: Moyenne | J36: Une implication insuffisante des parties prenantes dans la validation des évolutions provoque un manque d'adhésion et des résistances à la mise en œuvre. | K36: Accroître l’implication des parties prenantes dans la validation des évolutions pour garantir leur adhésion.
D37: Documentation et traçabilité des coûts | E37: Les délais de traitement des évolutions respectent-ils les objectifs du projet ? | F37: OUI | G37: Journal des délais de traitement des évolutions | H37: Risque de dépassement des délais de traitement des évolutions par rapport aux objectifs. | I37: Moyenne | J37: Un dépassement des délais de traitement des évolutions par rapport aux objectifs compromet la livraison dans les délais. | K37: Optimiser les délais de traitement pour assurer la livraison dans les temps prévus.
D38: Identification et gestion des écarts | E38: Les procédures de validation des versions sont-elles respectées et documentées ? | F38: OUI | G38: Registre des procédures de validation des versions | H38: Risque d'incohérence ou de non-respect des procédures de validation des versions. | I38: Moyenne | J38: Une incohérence ou un non-respect des procédures de validation des versions conduit à des incompatibilités ou à des erreurs dans le produit final. | K38: Établir des procédures strictes de validation des versions pour éviter les incohérences.
C39: S’assurer que les liens et impacts avec des projets connexes et les infrastructures (Datacenter, réseaux, etc.) sont pris en compte. | D39: Identification des interdépendances | E39: Les tests utilisateurs couvrent-ils l’ensemble des scénarios d’utilisation prévus ? | F39: NON | G39: Scénarios de test utilisateur | H39: Risque d'une couverture insuffisante des scénarios d'utilisation dans les tests utilisateurs. | I39: Élevée | J39: Une couverture insuffisante des scénarios d'utilisation dans les tests utilisateurs réduit la fiabilité des résultats et la satisfaction des utilisateurs. | K39: Améliorer la couverture des scénarios d’utilisation lors des tests utilisateurs pour fiabiliser les résultats.
D40: Évaluation des impacts sur les infrastructures existantes | E40: Les résultats des tests sont-ils analysés et utilisés pour améliorer les livrables ? | F40: NON | G40: Rapport d'analyse des résultats de tests | H40: Risque d'une analyse insuffisante ou d'une mauvaise utilisation des résultats des tests. | I40: Moyenne | J40: Une analyse insuffisante ou une mauvaise utilisation des résultats des tests limite l'identification des failles ou des améliorations nécessaires. | K40: Utiliser efficacement les résultats des tests pour identifier et corriger les failles.
D41: Alignement avec les projets connexes | E41: La documentation liée aux tests est-elle complète et accessible ? | F41: NON | G41: Dossier de documentation des tests | H41: Risque d'une documentation des tests incomplète ou inaccessible. | I41: Moyenne | J41: Une documentation incomplète ou inaccessible des tests complique leur traçabilité et réduit leur valeur en termes d’audit. | K41: Créer une documentation complète et accessible pour faciliter la traçabilité et l’audit.
D42: Planification des ressources partagées | E42: Les livrables finaux répondent-ils aux spécifications définies dans le cahier des charges ? | F42: NON | G42: Document de conformité des livrables au cahier des charges | H42: Risque de non-conformité des livrables finaux aux spécifications du cahier des charges. | I42: Élevée | J42: Une non-conformité des livrables finaux aux spécifications du cahier des charges entraîne des insatisfactions et des retours coûteux. | K42: S’assurer que les livrables finaux répondent précisément aux spécifications du cahier des charges.
D43: Validation par les parties prenantes | E43: Les indicateurs de performance permettent-ils de mesurer l’atteinte des objectifs ? | F43: NON | G43: Tableau de bord des indicateurs de performance | H43: d'indicateurs de performance inadéquats pour mesurer l'atteinte des objectifs. | I43: Moyenne | J43: Des indicateurs de performance inadéquats pour mesurer l'atteinte des objectifs donnent une vision fausse ou incomplète de la réussite du projet. | K43: Adapter les indicateurs de performance pour fournir une vision claire de l’atteinte des objectifs.
B44: Étude d'opportunité et expression des besoins | C44: S’assurer que l'expression détaillée des besoins est formalisée dans un cahier des charges fait par la MOA | D44: Exhaustivité des besoins exprimés dans le cahier des charges. | E44: Les besoins exprimés dans le cahier des charges sont-ils exhaustifs ? | F44: OUI | G44: Cahier des charges validé par les parties prenantes clés | H44: Inadéquation entre le cahier des charges et les attentes des parties prenantes clés. | I44: Elevée | J44: Non satisfaction des parties prenantes clés, ce qui entraîne des retours négatifs sur le projet. | K44: Maximiser la satisfaction des parties prenantes clés en répondant à leurs attentes.
D45: Précision et clarté des descriptions fonctionnelles et techniques | E45: Les descriptions fonctionnelles et techniques sont-elles précises et claires ? | F45: OUI | G45: Descriptions fonctionnelles et techniques détaillées | H45: Solutions proposées non adaptées aux exigences fonctionnelles et techniques. | I45: Elevée | J45: Non atteinte des objectifs fonctionnels et techniques, compromettant la valeur du projet. | K45: Garantir l’atteinte des objectifs fonctionnels et techniques pour assurer la valeur du projet.
D46: Validation des besoins par les parties prenantes clés. | E46: Les besoins exprimés ont-ils été validés par les parties prenantes clés ? | F46: NON | G46: Validation formelle des besoins exprimés avec les parties prenantes | H46: Manque de validation formelle des besoins exprimés avec les parties prenantes. | I46: Elevée | J46: Non prise en compte des besoins des parties prenantes, créant des solutions inadaptées. | K46: Prendre en compte les besoins des utilisateurs pour concevoir des solutions adaptées.
D47: Cohérence entre les besoins exprimés et les objectifs stratégiques | E47: Les besoins exprimés sont-ils cohérents avec les objectifs stratégiques ? | F47: NON | G47: Rapport d’analyse de la cohérence entre les besoins et les objectifs stratégiques | H47: Mauvaise cohérence entre les besoins identifiés et les objectifs stratégiques. | I47: Moyenne | J47: Non atteinte des objectifs stratégiques, nuisant à la pertinence globale du projet. | K47: Aligner le projet avec les objectifs stratégiques pour maximiser sa pertinence globale.
D48: Accessibilité et traçabilité des informations du cahier des charges | E48: Les informations du cahier des charges sont-elles accessibles et traçables ? | F48: NON | G48: Traçabilité des informations incluses dans le cahier des charges | H48: Manque de traçabilité des informations incluses dans le cahier des charges. | I48: Elevée | J48: Difficulté à suivre et vérifier les informations, générant des pertes de temps dans les phases critiques. | K48: Organiser les informations pour réduire les pertes de temps dans les phases critiques.
C49: S’assurer que le cahier des charges préconise une solution fonctionnellement et techniquement pertinente au regard des besoins exprimés | D49: Pertinence de la solution proposée par rapport aux besoins identifiés | E49: La solution proposée est-elle pertinente par rapport aux besoins identifiés ? | F49: OUI | G49: Étude de pertinence de la solution proposée | H49: Non-pertinence des solutions proposées par rapport aux problématiques métiers. | I49: Moyenne | J49: Non résolution des problématiques métiers, limitant l’impact opérationnel des solutions livrées. | K49: Analyser les problématiques métiers pour augmenter l’impact opérationnel des solutions livrées.
D50: Évaluation de la faisabilité technique de la solution | E50: La faisabilité technique de la solution a-t-elle été évaluée ? | F50: OUI | G50: Analyse de la faisabilité technique de la solution | H50: Impossibilité technique ou financière des solutions envisagées. | I50: Moyenne | J50: Non réalisation des solutions envisagées, provoquant des retards et une augmentation des coûts. | K50: Optimiser la gestion des solutions envisagées pour limiter les coûts et respecter les délais.
D51: Comparaison des solutions proposées avec des alternatives disponibles | E51: Les solutions proposées ont-elles été comparées avec des alternatives disponibles ? | F51: OUI | G51: Comparaison des solutions proposées avec des alternatives existantes | H51: Absence de comparaison des solutions avec des alternatives existantes. | I51: Moyenne | J51: Non identification des meilleures solutions, réduisant l'efficacité du choix final. | K51: Gérer efficacement les ressources pour garantir des décisions finales appropriées.
D52: Impact de la solution sur les processus métiers existants. | E52: L’impact de la solution sur les processus métiers existants a-t-il été analysé ? | F52: NON | G52: Étude d’impact des solutions sur les processus métiers existants | H52: Impact négatif des solutions sur les processus métiers actuels. | I52: Elevée | J52: Perturbation des processus métiers, entraînant des inefficacités et des pertes économiques. | K52: Réduire les perturbations des processus métiers pour maintenir leur efficacité économique.
D53: Alignement entre la solution et les exigences de performance définies. | E53: La solution est-elle alignée avec les exigences de performance définies ? | F53: NON | G53: Rapport sur la conformité de la solution aux exigences de performance | H53: Non-conformité des solutions aux exigences de performance définies. | I53: Moyenne | J53: Non atteinte des niveaux de performance requis, diminuant la qualité des livrables. | K53: S’assurer que les niveaux de performance requis sont atteints pour garantir la qualité des livrables.
C54: S’assurer que les exigences utilisateurs, les populations ciblées, les options et principes de gestion retenus sont précisés et priorisés | D54: Identification claire des exigences utilisateurs et des populations ciblées. | E54: Les exigences utilisateurs et les populations ciblées sont-elles identifiées clairement ? | F54: OUI | G54: Identification claire des exigences utilisateurs et des populations ciblées | H54: Identification insuffisante des exigences et des utilisateurs ciblés. | I54: Elevée | J54: Non satisfaction des besoins des utilisateurs, ce qui limite leur adoption des livrables. | K54: Renforcer la prise en compte des besoins des utilisateurs pour améliorer l'adoption des livrables.
D55: Priorisation des besoins et des principes de gestion retenus | E55: Les besoins et principes de gestion retenus ont-ils été priorisés correctement ? | F55: OUI | G55: Documentation des besoins et principes de gestion priorisés | H55: Priorisation inefficace des besoins et principes de gestion identifiés. | I55: Elevée | J55: Non atteinte des objectifs prioritaires, impactant directement les résultats du projet. | K55: Définir clairement les objectifs prioritaires pour aligner les résultats avec les attentes stratégiques.
D56: Documentation exhaustive des options disponibles pour les utilisateurs | E56: Les options disponibles pour les utilisateurs sont-elles documentées exhaustivement ? | F56: OUI | G56: Liste exhaustive des options disponibles pour les utilisateurs | H56: Options disponibles pour les utilisateurs mal évaluées ou incomplètes. | I56: Moyenne | J56: Non satisfaction des utilisateurs, créant une résistance à l’utilisation des solutions proposées. | K56: Accroître la satisfaction des utilisateurs pour réduire la résistance aux solutions proposées.
D57: Validation des priorités avec les parties prenantes. | E57: Les priorités définies ont-elles été validées avec les parties prenantes ? | F57: NON | G57: Validation des priorités définies par les parties prenantes | H57: Absence de validation des priorités définies avec les parties prenantes. | I57: Elevée | J57: Non prise en compte des priorités des parties prenantes, générant des désalignements stratégiques. | K57: Intégrer les priorités des parties prenantes dans la planification pour améliorer le désalignement stratégique.
D58: Pertinence des principes de gestion par rapport aux objectifs stratégiques. | E58: Les principes de gestion retenus sont-ils pertinents par rapport aux objectifs stratégiques ? | F58: NON | G58: Rapport sur la pertinence des principes de gestion vis-à-vis des objectifs stratégiques | H58: Non-alignement des principes de gestion avec les objectifs stratégiques. | I58: Elevée | J58: Non atteinte des objectifs stratégiques, réduisant la cohérence globale du projet. | K58: Adapter les actions entreprises afin de maximiser l'atteinte des objectifs stratégiques définis.
C59: S’assurer que le projet est cohérent avec le plan directeur informatique | D59: Conformité du projet avec les orientations stratégiques du plan directeur. | E59: Le projet est-il conforme aux orientations stratégiques du plan directeur ? | F59: OUI | G59: Document décrivant la conformité du projet aux orientations stratégiques du plan directeur | H59: Non-conformité du projet aux orientations stratégiques du plan directeur. | I59: Elevée | J59: Non atteinte des orientations stratégiques, limitant l’efficacité des actions entreprises. | K59: Garantir que les orientations stratégiques sont suivies pour accroître l'efficacité globale du projet.
D60: Intégration des ressources nécessaires prévues dans le plan directeur. | E60: Les ressources nécessaires prévues dans le plan directeur sont-elles intégrées correctement ? | F60: OUI | G60: Intégration des ressources nécessaires dans le plan directeur | H60: Mauvaise intégration des ressources nécessaires dans le plan directeur. | I60: Moyenne | J60: Non disponibilité des ressources nécessaires, ce qui ralentit ou bloque les activités prévues. | K60: Allouer les ressources nécessaires en temps opportun pour éviter les ralentissements.
D61: Impact du projet sur les projets et initiatives en cours | E61: L’impact du projet sur les projets et initiatives en cours a-t-il été évalué ? | F61: NON | G61: Évaluation de l’impact du projet sur les projets et initiatives en cours | H61: Impact négatif du projet sur les projets et initiatives existants. | I61: Elevée | J61: Perturbation des projets existants, causant des conflits de priorités au sein de l’organisation. | K61: Harmoniser les priorités entre les projets pour éviter les perturbations ou conflits internes.
D62: Alignement des objectifs du projet avec les priorités informatiques. | E62: Les objectifs du projet sont-ils alignés avec les priorités informatiques ? | F62: NON | G62: Analyse de l’alignement des objectifs du projet avec les priorités informatiques | H62: Objectifs du projet non alignés avec les priorités informatiques. | I62: Elevée | J62: Non atteinte des priorités informatiques, diminuant la compétitivité de l’organisation. | K62: Identifier les priorités informatiques pour optimiser leur atteinte et renforcer la compétitivité.
D63: Validation de la cohérence par les responsables du plan directeur. | E63: La cohérence du projet a-t-elle été validée par les responsables du plan directeur ? | F63: NON | G63: Validation de la cohérence du projet par les responsables du plan directeur | H63: Incohérence globale du projet avec le plan directeur validé. | I63: Faible | J63: Non atteinte des objectifs du plan directeur, compromettant la vision stratégique globale. | K63: Réaligner les objectifs du plan directeur pour garantir la cohérence stratégique globale.
C64: S’assurer que le projet est cohérent avec le SI actuel ou futur | D64: Compatibilité technique avec le système d'information actuel. | E64: La compatibilité technique avec le système d’information actuel a-t-elle été vérifiée ? | F64: NON | G64: Rapport de vérification de la compatibilité technique avec le système d’information actuel | H64: Incompatibilité technique avec le système d’information actuel. | I64: Moyenne | J64: Non intégration avec le système d’information, provoquant des erreurs dans les processus. | K64: Améliorer l'intégration des systèmes d'information pour minimiser les erreurs de processus.
D65: Prise en compte des évolutions futures du système d'information. | E65: Les évolutions futures du système d’information ont-elles été prises en compte ? | F65: NON | G65: Documentation intégrant les évolutions futures du système d’information | H65: Absence de prise en compte des évolutions futures du système d’information. | I65: Moyenne | J65: Non anticipation des évolutions futures, limitant l’adaptabilité du projet à long terme. | K65: Anticiper les évolutions futures pour améliorer l'adaptabilité à long terme.
D66: Intégration des fonctionnalités du projet avec celles existantes. | E66: Les fonctionnalités du projet ont-elles été intégrées aux fonctionnalités existantes ? | F66: NON | G66: Intégration des fonctionnalités du projet dans les fonctionnalités existantes | H66: Fonctionnalités projetées mal intégrées aux fonctionnalités existantes. | I66: Elevée | J66: Non satisfaction des besoins futurs, entraînant des coûts imprévus pour des ajustements. | K66: Prendre en compte les besoins futurs pour éviter les coûts imprévus.
D67: Analyse des impacts de l’intégration sur les processus métiers. | E67: Les impacts de l’intégration sur les processus métiers ont-ils été analysés ? | F67: NON | G67: Étude d’impact sur les processus métiers suite à l’intégration | H67: Perturbation des processus métiers suite à une intégration insuffisante. | I67: Faible | J67: Perturbation des processus métiers, augmentant les coûts et réduisant l'efficacité opérationnelle. | K67: Réduire les impacts négatifs des perturbations des processus métiers pour accroître leur efficacité.
D68: Évaluation des besoins de formation pour les utilisateurs du nouveau SI. | E68: Les besoins de formation pour les utilisateurs du nouveau SI ont-ils été évalués ? | F68: NON | G68: Évaluation des besoins de formation pour les utilisateurs du nouveau SI | H68: Besoins de formation des utilisateurs mal évalués ou sous-estimés. | I68: Moyenne | J68: Non satisfaction des besoins de formation, limitant les performances des utilisateurs. | K68: Adapter les besoins de formation pour maximiser les performances des utilisateurs.
C69: S’assurer que la direction est bien impliquée dans le projet | D69: Participation active de la direction dans les instances de gouvernance. | E69: La direction participe-t-elle activement aux instances de gouvernance ? | F69: OUI | G69: Acte de participation active de la direction dans les instances de gouvernance | H69: Faible participation de la direction dans les instances de gouvernance. | I69: Elevée | J69: Non prise en compte des orientations de la direction, ce qui entraîne un désalignement stratégique. | K69: Respecter les orientations de la direction pour éviter un désalignement stratégique.
D70: Validation par la direction des objectifs et des périmètres du projet. | E70: Les objectifs et périmètres du projet ont-ils été validés par la direction ? | F70: OUI | G70: Validation des objectifs et périmètres du projet par la direction | H70: Objectifs et périmètre du projet non validés clairement par la direction. | I70: Moyenne | J70: Non prise en compte des risques, augmentant la probabilité d’incidents imprévus. | K70: Identifier et gérer les risques pour réduire la probabilité d'incidents imprévus.
D71: Engagement de la direction dans la communication sur le projet. | E71: La direction s’est-elle engagée dans la communication sur le projet ? | F71: OUI | G71: Plan de communication mis en œuvre par la direction | H71: Plan de mise en œuvre mal structuré ou non suivi efficacement. | I71: Elevée | J71: Non suivi efficace du projet, provoquant une mauvaise gestion des délais et des budgets. | K71: Suivre efficacement le projet pour garantir une bonne gestion des délais et budgets.
D72: Suivi régulier par la direction des avancements du projet. | E72: La direction suit-elle régulièrement les avancements du projet ? | F72: NON | G72: Suivi régulier des avancements du projet par la direction | H72: Avancements du projet suivis de manière irrégulière par la direction. | I72: Elevée | J72: Non prise en compte des orientations stratégiques, limitant l’efficacité globale des initiatives. | K72: Alignement des initiatives avec les orientations stratégiques pour maximiser leur efficacité globale.
D73: Prise en compte des retours et orientations stratégiques de la direction. | E73: Les retours et orientations stratégiques de la direction sont-ils pris en compte ? | F73: NON | G73: Documentation des retours et orientations stratégiques de la direction | H73: Retours et orientations stratégiques de la direction mal documentés ou inexploitables. | I73: Faible | J73: L'absence de validation officielle du planning directeur entraîne des malentendus et une perte de crédibilité. | K73: Validation officielle du planning directeur pour éviter malentendus ou pertes de crédibilité.
B74: Planification | C74: S’assurer qu’il existe un planning directeur commun à tout le projet | D74: Existence d’un planning directeur écrit et validé. | E74: Le planning directeur est-il écrit et validé ? | F74: OUI | G74: Plan directeur écrit et validé officiellement | H74: Le planning directeur n'est pas écrit ni validé officiellement. | I74: Moyenne | J74: Les phases importantes non incluses dans le planning causent des retards critiques dans l'exécution du projet. | K74: Inclure toutes les phases importantes dans le planning pour réduire les retards critiques.
D75: Prise en compte des différentes phases du projet dans le planning. | E75: Le planning prend-il en compte toutes les phases du projet ? | F75: OUI | G75: Calendrier détaillé des phases du projet | H75: Les phases importantes du projet ne sont pas prises en compte dans le planning. | I75: Elevée | J75: Un planning mal aligné avec les objectifs stratégiques génère des incohérences dans les priorités et la direction du projet. | K75: Alignement du planning avec les objectifs stratégiques pour éviter les incohérences dans les priorités.
D76: Alignement du planning directeur avec les objectifs stratégiques du projet. | E76: Le planning directeur est-il aligné avec les objectifs stratégiques du projet ? | F76: OUI | G76: Document de validation des objectifs stratégiques du projet | H76: Le planning directeur est mal aligné avec les objectifs stratégiques du projet. | I76: Faible | J76: L'accessibilité limitée du planning aux parties prenantes crée des difficultés de coordination et de suivi. | K76: Garantir l'accessibilité du planning aux parties prenantes pour améliorer la coordination.
D77: Communication et accessibilité du planning à toutes les parties prenantes. | E77: Le planning est-il communiqué et accessible à toutes les parties prenantes ? | F77: NON | G77: Procédure de communication pour le planning avec les parties prenantes | H77: Le planning n’est pas communiqué ou accessible à toutes les parties prenantes. | I77: Moyenne | J77: Un planning non mis à jour régulièrement devient obsolète, impactant la pertinence des activités planifiées. | K77: Mettre à jour régulièrement le planning pour maintenir sa pertinence.
D78: Mise à jour régulière du planning directeur en fonction des évolutions du projet | E78: Le planning est-il régulièrement mis à jour en fonction des évolutions du projet ? | F78: NON | G78: Journal des mises à jour régulières du planning | H78: Le planning n’est pas mis à jour régulièrement selon les évolutions du projet. | I78: Elevée | J78: Un plan de projet initial incomplet ou ambigu entraîne une mauvaise compréhension des étapes par les équipes. | K78: Compléter le planning initial pour éviter une mauvaise compréhension des étapes par les équipes.
C79: S’assurer qu’il existe un plan de projet initial | D79: Documentation complète et claire du plan de projet initial. | E79: Le plan de projet initial est-il documenté de manière complète et claire ? | F79: OUI | G79: Plan de projet initial documenté de manière complète | H79: Le plan de projet initial est incomplet ou ambigu. | I79: Élevée | J79: L'absence de validation du plan initial par toutes les parties prenantes clés compromet son adoption. | K79: Valider le plan initial avec toutes les parties prenantes clés pour assurer son adoption.
D80: Validation du plan initial par toutes les parties prenantes clés. | E80: Le plan initial a-t-il été validé par toutes les parties prenantes clés ? | F80: OUI | G80: Validation formelle du plan initial par les parties prenantes clés | H80: Le plan initial n’a pas été validé par toutes les parties prenantes clés. | I80: Élevée | J80: Les ressources non intégrées dans le plan initial provoquent des pénuries ou une allocation inefficace. | K80: Intégrer les ressources au plan initial afin d'éviter des pénuries ou une mauvaise allocation.
D81: Intégration des ressources nécessaires dans le plan initial. | E81: Les ressources nécessaires sont-elles intégrées dans le plan initial ? | F81: OUI | G81: Répartition des ressources nécessaires dans le plan initial | H81: Les ressources nécessaires ne sont pas intégrées dans le plan initial. | I81: Élevée | J81: Un plan initial incohérent par rapport aux objectifs du projet entraîne des écarts dans les résultats attendus. | K81: Garantir la cohérence du plan initial avec les objectifs pour minimiser les écarts dans les résultats.
D82: Cohérence entre les objectifs du projet et le plan initial | E82: Le plan initial est-il cohérent avec les objectifs du projet ? | F82: OUI | G82: Rapport de cohérence entre le plan initial et les objectifs du projet | H82: Le plan initial est incohérent par rapport aux objectifs du projet. | I82: Élevée | J82: Les risques identifiés non analysés en profondeur augmentent la probabilité de défaillances imprévues. | K82: Analyser en profondeur les risques identifiés pour mieux les anticiper.
D83: Analyse des risques potentiels identifiés dans le plan de projet. | E83: Les risques potentiels identifiés dans le plan de projet ont-ils été analysés ? | F83: NON | G83: Étude d'analyse des risques potentiels dans le plan de projet | H83: Les risques potentiels identifiés ne sont pas analysés en profondeur. | I83: Élevée | J83: Un plan de projet non actualisé suite à des changements crée des désalignements avec les besoins actuels. | K83: Actualiser régulièrement le plan de projet pour refléter les changements et les besoins actuels.
C84: S’assurer que ce plan de projet a été révisé | D84: Mise à jour régulière du plan de projet en fonction des changements. | E84: Le plan de projet est-il régulièrement mis à jour en fonction des changements ? | F84: NON | G84: Journal des mises à jour du plan en fonction des changements | H84: Le plan de projet n'est pas actualisé en fonction des changements survenus. | I84: Moyenne | J84: Les écarts non identifiés entre le plan initial et la situation actuelle génèrent des inefficacités et des retards. | K84: Identifier et combler les écarts entre le plan initial et la réalité actuelle pour éviter inefficacités.
D85: Identification des écarts entre le plan initial et la situation actuelle. | E85: Les écarts entre le plan initial et la situation actuelle ont-ils été identifiés ? | F85: OUI | G85: Liste des écarts identifiés entre le plan initial et la situation actuelle | H85: Les écarts entre le plan initial et la situation actuelle ne sont pas identifiés. | I85: Élevée | J85: Les révisions du plan non validées par les parties prenantes compromettent leur pertinence et leur adoption. | K85: Faire valider les révisions du plan par les parties prenantes pour garantir leur pertinence.
D86: Validation des révisions du plan par les parties prenantes. | E86: Les révisions du plan ont-elles été validées par les parties prenantes ? | F86: NON | G86: Validation officielle des révisions du plan par les parties prenantes | H86: Les révisions du plan ne sont pas validées par les parties prenantes. | I86: Élevée | J86: Les révisions apportées au plan non traçables compliquent la justification et l'amélioration des choix effectués. | K86: Documenter de manière traçable les révisions pour faciliter les ajustements et le suivi.
D87: Traçabilité des modifications apportées au plan de projet. | E87: Les modifications apportées au plan de projet sont-elles traçables ? | F87: PAS | G87: Registre des modifications traçables du plan de projet | H87: Les modifications apportées au plan de projet ne sont pas traçables. | I87: Moyenne | J87: Les nouvelles contraintes ou opportunités non intégrées au plan révisé limitent son adaptabilité. | K87: Intégrer les nouvelles contraintes ou opportunités au plan révisé pour maximiser son adaptabilité.
D88: Intégration des nouvelles contraintes ou opportunités dans le plan révisé. | E88: Les nouvelles contraintes ou opportunités sont-elles intégrées dans le plan révisé ? | F88: PAS | G88: Liste des contraintes et opportunités intégrées dans le plan révisé | H88: Les nouvelles contraintes ou opportunités ne sont pas intégrées au plan révisé. | I88: Moyenne | J88: Les étapes clés et livrables mal définis nuisent à la clarté et à la supervision du projet. | K88: Définir précisément les étapes clés et les livrables pour améliorer la clarté et la supervision.
C89: S’assurer qu’il existe des plans détaillés | D89: Définition détaillée des étapes clés et des livrables du projet. | E89: Les étapes clés et les livrables du projet sont-ils définis en détail ? | F89: OUI | G89: Définition détaillée des étapes clés et livrables du projet | H89: Les étapes clés et livrables du projet ne sont pas définis avec précision. | I89: Moyenne | J89: Les dépendances non identifiées entre les étapes provoquent des erreurs et des retards dans l'exécution. | K89: Identifier les dépendances entre les étapes pour éviter erreurs et retards.
D90: Identification des ressources nécessaires pour chaque étape | E90: Les ressources nécessaires pour chaque étape ont-elles été identifiées ? | F90: OUI | G90: Liste des ressources nécessaires identifiées pour chaque étape | H90: Les ressources nécessaires à chaque étape ne sont pas correctement identifiées. | I90: Moyenne | J90: Les délais et jalons imprécis ou inadéquats affectent la planification et le respect des échéances. | K90: Préciser et ajuster les délais et jalons pour garantir le respect des échéances.
D91: Précision des délais et des jalons dans les plans détaillés. | E91: Les délais et les jalons des plans détaillés sont-ils précis ? | F91: OUI | G91: Document décrivant les délais et jalons précis des plans détaillés | H91: Les délais et jalons des plans détaillés sont imprécis ou inadéquats. | I91: Moyenne | J91: Les plans non partagés avec les équipes concernées créent des malentendus et des incohérences dans leur exécution. | K91: Partager les plans avec toutes les équipes concernées pour éviter malentendus et incohérences.
D92: Communication des plans détaillés aux équipes concernées. | E92: Les plans détaillés sont-ils communiqués aux équipes concernées ? | F92: NON | G92: Procédure de communication des plans détaillés aux équipes concernées | H92: Les plans détaillés ne sont pas partagés avec les équipes concernées. | I92: Élevée | J92: L'absence de révision régulière des plans détaillés les rend obsolètes et inadaptés aux évolutions du projet. | K92: Réviser régulièrement les plans détaillés pour qu'ils restent pertinents et adaptés aux évolutions.
D93: Validation des plans détaillés par les parties prenantes. | E93: Les plans détaillés ont-ils été validés par les parties prenantes ? | F93: NON | G93: Journal des révisions régulières des plans détaillés | H93: Les plans détaillés ne sont pas révisés régulièrement pour garantir leur pertinence. | I93: Moyenne | J93: Les écarts non analysés entre les plans détaillés et la réalité opérationnelle génèrent des inefficacités. | K93: Analyser et combler les écarts entre les plans détaillés et la réalité pour réduire les inefficacités.
C94: S’assurer que ces plans ont été révisés | D94: Revue régulière des plans détaillés pour s’assurer de leur pertinence | E94: Les plans détaillés sont-ils revus régulièrement pour assurer leur pertinence ? | F94: NON | G94: Analyse des écarts entre les plans détaillés et la réalité opérationnelle | H94: Les écarts entre les plans détaillés et la réalité opérationnelle ne sont pas analysés. | I94: Élevée | J94: Les modifications des plans non validées par les parties prenantes réduisent leur pertinence et leur application. | K94: Documenter les modifications des plans pour garantir leur transparence et supervision.
D95: Analyse des écarts entre les plans détaillés et la réalité opérationnelle. | E95: Les écarts entre les plans détaillés et la réalité opérationnelle sont-ils analysés ? | F95: NON | G95: Validation formelle des modifications des plans détaillés | H95: Les modifications des plans détaillés ne sont pas validées par les parties prenantes. | I95: Moyenne | J95: Les révisions non documentées de manière traçable limitent la transparence et la supervision. | K95: Tirer parti des retours d'expérience pour améliorer continuellement les révisions des plans.
D96: Validation des modifications apportées aux plans détaillés. | E96: Les modifications des plans détaillés sont-elles validées par les parties prenantes ? | F96: NON | G96: Documentation traçable des révisions des plans | H96: Les révisions des plans ne sont pas documentées de manière traçable. | I96: Moyenne | J96: Les retours d'expérience non utilisés pour ajuster les révisions des plans empêchent l'amélioration continue. | K96: Identifier précisément les ressources disponibles et nécessaires pour une allocation optimale.
D97: Documentation des révisions pour garantir une traçabilité complète | E97: Les révisions des plans sont-elles documentées pour garantir une traçabilité ? | F97: NON | G97: Integration des retours d’expérience dans les révisions des plans | H97: Les retours d’expérience ne sont pas utilisés pour ajuster les révisions des plans. | I97: Élevée | J97: L'identification imprécise des ressources disponibles et nécessaires provoque des pénuries ou une surutilisation. | K97: Réduire les gaspillages dans l'utilisation des ressources pour limiter les coûts.
D98: Intégration des retours d’expérience dans les révisions des plans. | E98: Les retours d’expérience sont-ils intégrés dans les révisions des plans ? | F98: NON | G98: Identification précise des ressources disponibles et nécessaires | H98: Les ressources disponibles et nécessaires ne sont pas précisément identifiées. | I98: Moyenne | J98: Une allocation inefficace des ressources disponibles génère des goulets d'étranglement et des retards. | K98: Mettre en place un suivi continu pour améliorer l'efficacité et la gestion des ressources.
C99: S’assurer que les plans intègrent une gestion optimale des ressources | D99: Identification précise des ressources disponibles et nécessaires. | E99: Les ressources disponibles et nécessaires sont-elles précisément identifiées ? | F99: NON | G99: Liste d’évaluation de la sufficance des ressources pour chaque étape | H99: Les ressources disponibles ne sont pas allouées correctement pour chaque étape. | I99: Moyenne | J99: Les gaspillages non réduits dans l'utilisation des ressources augmentent les coûts du projet. | K99: Évaluer et prioriser correctement les risques spécifiques au projet.
D100: Allocation efficace des ressources pour chaque étape du projet. | E100: Les ressources sont-elles allouées efficacement pour chaque étape du projet ? | F100: NON | G100: Procédures de réduction des gaspillages dans l’utilisation des ressources | H100: Les gaspillages dans l’utilisation des ressources ne sont pas réduits. | I100: Élevée | J100: L'absence de suivi continu des ressources diminue leur efficacité et leur gestion. | K100: Mettre en œuvre les stratégies de mitigation identifiées pour réduire les risques.
D101: Réduction des gaspillages dans l’utilisation des ressources. | E101: Les gaspillages dans l’utilisation des ressources sont-ils réduits au minimum ? | F101: NON | G101: Journal de surveillance continue des ressources | H101: L'utilisation des ressources n’est pas surveillée de manière continue. | I101: Moyenne | J101: Les besoins en ressources non reflétés dans les ajustements des plans réduisent leur pertinence et leur adéquation. | K101: Sensibiliser les parties prenantes aux stratégies de mitigation pour favoriser leur application.
D102: Surveillance continue de l’utilisation des ressources. | E102: L’utilisation des ressources est-elle surveillée en continu ? | F102: NON | G102: Mise à jour des plans en fonction des besoins en ressources | H102: Les besoins en ressources ne sont pas reflétés dans les ajustements des plans. | I102: Moyenne | J102: L'identification incomplète des risques spécifiques au projet laisse des vulnérabilités importantes non adressées. | K102: Identifier et gérer les risques technologiques pour éviter des problèmes techniques.
...

Sheet 4.4
A2: DOMAINE | B2: POINT DE CONTRÔLE | C2: OBJECTIF DE CONTRÔLE | D2: CRITERE D'EVALUATION | E2: QUESTION D'EVALUATION | F2: Réponses | G2: DOCUMENTS REQUIS | H2: RISQUES | I2: Criticités | J2: CONSEQUENCES | K2: RECOMMANDATIONS
A3: Audit du Support Utilisateur et de la Gestion du Parc | B3: Audit fiabilité et sécurité | C3: S’assurer qu’une structure de centre d’assistance (help-desk) (HD) est mise en place | D3: Document formalisé décrivant la structure du help-desk. | E3: Un document validé par la direction décrit-il l'organisation du help-desk ? | F3: OUI | G3: Procès-verbal de création. | H3: Structuration inefficace. | I3: Élevée | J3: Perte de crédibilité. | K3: Renforcer les mécanismes de contrôle qualité pour éviter les erreurs et maintenir une image professionnelle.
D4: Désignation d'une équipe dédiée avec rôles clairs. | E4: L'équipe dispose-t-elle des compétences requises ? | F4: OUI | G4: Organigramme et fiches de poste. | H4: Compétences inadaptées. | I4: Élevée | J4: Erreurs récurrentes. | K4: Mettre en place un système de revue régulière des processus afin de minimiser les erreurs.
D5: Existence d'un SLA (accord de niveau de service). | E5: Le SLA définit-il les délais de réponse ? | F5: OUI | G5: SLA signé. | H5: Délais non respectés. | I5: Moyenne | J5: Insatisfaction clients. | K5: Améliorer le service client et adapter les produits ou services aux besoins réels des clients.
D6: Infrastructure technique opérationnelle (logiciels, bases de connaissances). | E6: Les outils du help-desk sont-ils fonctionnels et sécurisés ? | F6: NON | G6: Audit technique des outils. | H6: Outils obsolètes. | I6: Élevée | J6: Fuites de données. | K6: Instaurer des mécanismes de chiffrement et des contrôles d'accès stricts pour protéger les données sensibles.
D7: Mécanisme de suivi des performances (KPI). | E7: Des indicateurs de performance sont-ils mesurés mensuellement ? | F7: OUI | G7: Rapports de performance. | H7: Décisions non data-driven. | I7: Élevée | J7: Coûts de réorganisation. | K7: Planifier les ressources de manière optimale et améliorer l’efficacité organisationnelle pour réduire les coûts imprévus.
C8: S’assurer qu’une procédure de gestion des demandes d’assistance est diffusée et connue des utilisateurs | D8: Procédure documentée et versionnée. | E8: La procédure est-elle accessible sur l'intranet ? | F8: NON | G8: Procédure PDF datée. | H8: Demandes ignorées. | I8: Moyenne | J8: Retards critiques. | K8: Instaurer des outils de gestion des délais et des indicateurs pour garantir le respect des échéances.
D9: Diffusion via des canaux officiels (intranet, email). | E9: Les utilisateurs ont-ils reçu une formation ? | F9: PAS | G9: Attestations de formation. | H9: Mauvaise utilisation des outils. | I9: Élevée | J9: Formation coûteuse. | K9: Investir dans des solutions de formation en ligne ou hybrides pour réduire les coûts tout en garantissant une montée en compétence.
D10: Formation obligatoire des utilisateurs. | E10: Un FAQ est-il disponible pour les demandes courantes ? | F10: NON | G10: Accès au FAQ. | H10: Surcharge du help-desk. | I10: Élevée | J10: Coûts de support supplémentaires. | K10: Standardiser les processus pour réduire les besoins de support et les coûts liés.
D11: Existence d'un FAQ accessible. | E11: La procédure a-t-elle été mise à jour dans les 12 mois ? | F11: OUI | G11: Historique des versions. | H11: Procédures obsolètes. | I11: Moyenne | J11: Non-conformité réglementaire. | K11: Effectuer des audits réguliers pour garantir la conformité aux normes et réglementations en vigueur.
D12: Mise à jour annuelle de la procédure. | E12: Des retours utilisateurs sont-ils collectés ? | F12: NON | G12: Enquêtes de satisfaction. | H12: Détérioration de l'expérience utilisateur. | I12: Moyenne | J12: Perte de clients. | K12: Lancer des initiatives de fidélisation pour reconquérir la satisfaction des clients et prévenir les départs.
C13: S’assurer qu’une procédure d'escalade mise en place | D13: Procédure d'escalade documentée. | E13: Existe-t-il un circuit d'escalade pour les incidents critiques ? | F13: NON | G13: Procédure validée. | H13: Incidents non résolus. | I13: Moyenne | J13: Interruptions opérationnelles. | K13: Déployer des plans de continuité opérationnelle pour éviter les interruptions et limiter leurs impacts.
D14: Délais maximums définis pour chaque niveau. | E14: Les délais d'escalade sont-ils respectés ? | F14: NON | G14: Logs de résolution. | H14: Délais dépassés. | I14: Moyenne | J14: Amendes pour non-respect de SLA. | K14: Renforcer les mécanismes de respect des accords de niveau de service et surveiller leur application systématique.
D15: Responsables désignés pour chaque type d'incident. | E15: Les responsables sont-ils joignables 24/7 ? | F15: NON | G15: Liste des contacts d'urgence. | H15: Responsables indisponibles. | I15: Moyenne | J15: Perte de confiance. | K15: Revoir les méthodes de communication pour instaurer la transparence et regagner la confiance des parties prenantes.
D16: Historique des escalades traitées. | E16: Des simulations d'urgence ont-elles été réalisées ? | F16: NON | G16: Rapports de tests. | H16: Procédure non testée. | I16: Moyenne | J16: Crises non gérées. | K16: Introduire un protocole clair de gestion de crise et former les équipes pour une réactivité accrue.
D17: Tests annuels de la procédure. | E17: Les escalades sont-elles analysées pour amélioration ? | F17: OUI | G17: Analyses post-incident. | H17: Répétition des erreurs. | I17: Élevée | J17: Coûts juridiques. | K17: Instaurer des mécanismes préventifs pour éviter les litiges et réduire les dépenses juridiques inutiles.
C18: S’assurer de la couverture géographique du HD | D18: Zones géographiques couvertes documentées. | E18: Le help-desk couvre-t-il les filiales internationales ? | F18: PAS | G18: Carte des zones couvertes. | H18: Inégalités de service. | I18: Moyenne | J18: Perte de parts de marché. | K18: Adapter les stratégies commerciales aux tendances pour regagner des parts de marché perdues.
D19: Support multilingue si nécessaire. | E19: Les utilisateurs non francophones sont-ils assistés ? | F19: NON | G19: Traductions disponibles. | H19: Barrières linguistiques. | I19: Moyenne | J19: Contentieux linguistiques. | K19: Revoir les politiques linguistiques et introduire des standards pour minimiser les malentendus et conflits.
D20: Infrastructure locale (serveurs, équipes). | E20: Des équipes locales sont-elles déployées ? | F20: PAS | G20: Preuves de présence locale. | H20: Latence technique. | I20: Moyenne | J20: Coûts d'infrastructure. | K20: Optimiser la gestion des infrastructures pour réduire les dépenses excessives tout en maintenant leur efficacité.
D21: Délais de réponse identiques pour toutes les zones. | E21: Les délais de réponse sont-ils homogènes ? | F21: NON | G21: Statistiques de réponse. | H21: Insatisfaction régionale. | I21: Élevée | J21: Sanctions locales. | K21: Collaborer avec les autorités locales pour anticiper et répondre aux exigences réglementaires spécifiques.
D22: Mesure de la satisfaction par région. | E22: La satisfaction est-elle mesurée par région ? | F22: NON | G22: Enquêtes régionales. | H22: Conflits internes. | I22: Élevée | J22: Réputation entachée. | K22: Lancer des campagnes de communication positives pour restaurer l’image publique de l’organisation.
C23: S’assurer de la couverture fonctionnelle du HD | D23: Liste des fonctions supportées (IT, RH, etc.). | E23: Toutes les fonctions critiques sont-elles couvertes ? | F23: NON | G23: Catalogue de services. | H23: Demandes non traitées. | I23: Élevée | J23: Blocage des processus. | K23: Évaluer et restructurer les processus critiques pour améliorer leur fluidité et leur efficacité.
D24: Experts métier identifiés pour chaque domaine. | E24: Des experts métier sont-ils associés au help-desk ? | F24: NON | G24: Fiches d'expertise. | H24: Décisions inadaptées. | I24: Moyenne | J24: Erreurs stratégiques. | K24: Introduire des analyses approfondies avant toute prise de décision stratégique pour éviter des erreurs coûteuses.
D25: Intégration avec les processus métiers. | E25: Le help-desk participe-t-il aux réunions métiers ? | F25: PAS | G25: PV de réunions. | H25: Silotage des équipes. | I25: Élevée | J25: Frais de consultance externes. | K25: Renforcer les compétences internes pour réduire la dépendance aux consultants externes et limiter les coûts.
D26: SLA alignés sur les besoins fonctionnels. | E26: Les SLA sont-ils adaptés à chaque fonction ? | F26: PAS | G26: SLA par fonction. | H26: SLA irréalistes. | I26: Moyenne | J26: Pénalités contractuelles. | K26: Instaurer des mécanismes d’application rigoureux pour respecter les engagements contractuels.
D27: Revue trimestrielle des besoins. | E27: La couverture est-elle réévaluée régulièrement ? | F27: OUI | G27: Comptes-rendus de revue. | H27: Obsolescence des services. | I27: Moyenne | J27: Retard technologique. | K27: Investir dans des technologies modernes et offrir des formations pour garantir une adoption rapide et efficace.
B28: Audit d'efficacité et de performance | C28: S’assurer qu’il existe une aide à la saisie pour la saisie des tickets | D28: Existence d'un guide utilisateur accessible | E28: Le guide est-il accessible depuis l'interface ? | F28: NON | G28: Capture d'écran de l'aide | H28: Saisie erronée | I28: Moyenne | J28: Retards de traitement (+20% de temps) | K28: Réduire les retards de traitement en optimisant les processus pour améliorer l'efficacité globale.
D29: Intégration de suggestions automatisées | E29: Le système propose-t-il des suggestions ? | F29: OUI | G29: Logs des suggestions | H29: Mauvaise adoption | I29: Moyenne | J29: Coûts de correction (5-15k€/an) | K29: Introduire des solutions pour minimiser les coûts de correction et garantir la qualité dès la première exécution.
D30: Formation des utilisateurs documentée | E30: Les formations sont-elles attestées ? | F30: NON | G30: Attestations de formation | H30: Incompétence utilisateur | I30: Moyenne | J30: Re-formations coûteuses | K30: Adapter les programmes de formation pour réduire les coûts liés aux re-formations coûteuses.
D31: Mesure du taux d'utilisation de l'aide | E31: Le taux d'utilisation est-il >70% ? | F31: NON | G31: Rapport d'analytics | H31: Outil sous-utilisé | I31: Moyenne | J31: ROI faible | K31: Identifier les leviers pour améliorer le ROI des projets et investissements.
D32: Mises à jour annuelles du support | E32: Le support a-t-il été mis à jour cette année ? | F32: OUI | G32: Registre des versions | H32: Informations obsolètes | I32: Moyenne | J32: Non-conformité | K32: Garantir la conformité aux normes et réglementations pour éviter des sanctions ou des impacts légaux.
C33: S’assurer qu’il existe des revues qualité pour la saisie des tickets | D33: Procédure de revue documentée | E33: Existe-t-il une procédure écrite ? | F33: PAS | G33: Procédure versionnée | H33: Qualité hétérogène | I33: Moyenne | J33: 30% de tickets rejetés | K33: Améliorer la qualité des tickets pour réduire les rejets et optimiser leur traitement.
D34: Échantillonnage hebdomadaire (≥5%) | E34: L'échantillonnage est-il respecté ? | F34: PAS | G34: Registre d'échantillonnage | H34: Problèmes non détectés | I34: Élevée | J34: Insatisfaction client | K34: Renforcer la satisfaction client par une écoute proactive et une amélioration continue des services.
D35: Grille d'évaluation standardisée | E35: La grille couvre-t-elle tous les critères ? | F35: OUI | G35: Grille validée | H35: Évaluations subjectives | I35: Moyenne | J35: Litiges contractuels | K35: Mettre en place des outils pour prévenir les litiges contractuels et assurer une transparence accrue.
D36: Actions correctives tracées | E36: 90% des actions sont-elles closes ? | F36: NON | G36: Suivi des actions | H36: Corrections retardées | I36: Moyenne | J36: Délais allongés | K36: Optimiser les délais pour garantir une exécution rapide et respectueuse des engagements.
D37: Revue par un comité dédié | E37: PV du comité existe-t-il ? | F37: NON | G37: PV trimestriels | H37: Décisions non alignées | I37: Élevée | J37: Perte de certification | K37: Instaurer des audits pour maintenir les certifications nécessaires.
C38: Vérifier l’existence d’une base de connaissance | D38: Accès centralisé | E38: La base est-elle accessible à tous ? | F38: NON | G38: URL d'accès | H38: Duplication d'efforts | I38: Moyenne | J38: +40% d'appels | K38: Réduire le volume d'appels en améliorant les mécanismes de support et résolution.
D39: ≥80% des solutions documentées | E39: Couvre-t-elle les incidents majeurs ? | F39: NON | G39: Inventaire des solutions | H39: Résolutions improvisées | I39: Moyenne | J39: Erreurs récurrentes | K39: Identifier et corriger les causes des erreurs récurrentes pour renforcer la qualité des opérations.
D40: Moteur de recherche fonctionnel | E40: Le moteur renvoie-t-il des résultats pertinents ? | F40: NON | G40: Tests de recherche | H40: Temps de recherche ×3 | I40: Moyenne | J40: Coûts de formation | K40: Investir dans des formations efficaces pour réduire les coûts de montée en compétence.
D41: Contrôle d'accès RBAC | E41: Les droits sont-ils granularisés ? | F41: PAS | G41: Matrice des droits | H41: Fuites d'infos | I41: Moyenne | J41: Amendes RGPD | K41: Assurer la conformité RGPD pour éviter des amendes coûteuses et protéger les données.
D42: Archivage des anciennes versions | E42: Version 2023 est-elle archivée ? | F42: NON | G42: Backup des versions | H42: Perte de savoir | I42: Moyenne | J42: Perte de compétences | K42: Préserver les compétences critiques grâce à des programmes de gestion des talents.
C43: S’assurer qu’une procédure de mise à jour de la base de connaissance existe | D43: Rôles clairement définis | E43: Qui est responsable des mises à jour ? | F43: NON | G43: Fiches de poste | H43: Contenu obsolète | I43: Faible | J43: Support inefficace | K43: Améliorer l'efficacité du support par une formation ciblée et des outils adaptés.
D44: Cycle de mise à jour trimestriel | E44: Les mises à jour sont-elles planifiées ? | F44: NON | G44: Calendrier des mises à jour | H44: Retards critiques | I44: Faible | J44: Pénalités contractuelles | K44: Respecter les engagements contractuels pour éviter les pénalités.
D45: Validation par le RSSI | E45: Le RSSI a-t-il signé la dernière version ? | F45: NON | G45: Approbations | H45: Non-conformité | I45: Faible | J45: Vulnérabilités sécurité | K45: Protéger les systèmes contre les vulnérabilités en renforçant les mesures de sécurité.
D46: Journal des modifications | E46: Le journal est-il à jour ? | F46: NON | G46: Log des changements | H46: Traçabilité perdue | I46: Faible | J46: Litiges juridiques | K46: Anticiper et gérer les litiges juridiques par des conseils adaptés et des stratégies préventives.
D47: Tests post-mise à jour | E47: Tests automatisés existent-ils ? | F47: OUI | G47: Rapports de tests | H47: Rétrocompatibilité brisée | I47: Moyenne | J47: Coûts de rollback | K47: Réduire les coûts de rollback grâce à une planification efficace et une gestion proactive.
C48: S’assurer que les appels sont enregistrés | D48: Politique de conservation (6 mois min) | E48: Les enregistrements sont-ils conservés 6 mois ? | F48: OUI | G48: Politique documentée | H48: Preuves perdues | I48: Faible | J48: Non-recours juridique | K48: Instaurer des mécanismes de recours juridique pour protéger l'organisation en cas de litiges.
D49: Chiffrement des enregistrements | E49: Sont-ils chiffrés (AES-256) ? | F49: NON | G49: Certificat de chiffrement | H49: Données exposées | I49: Faible | J49: Amendes (4% CA) | K49: Adapter les pratiques pour éviter les amendes calculées en pourcentage du chiffre d'affaires.
D50: Consentement utilisateur documenté | E50: Les utilisateurs ont-ils consenti ? | F50: OUI | G50: Registre des consentements | H50: Violation RGPD | I50: Moyenne | J50: Perte de confiance | K50: Renforcer la confiance avec des pratiques transparentes et des engagements clairs.
D51: Accès restreint aux enregistrements | E51: Seuls les auditeurs y ont-ils accès ? | F51: PAS | G51: Logs d'accès | H51: Utilisation abusive | I51: Faible | J51: Réputation entachée | K51: Restaurer la réputation par des campagnes de communication positives et une amélioration des performances.
D52: Procédure de suppression automatique | E52: La suppression est-elle automatisée ? | F52: NON | G52: Scripts de purge | H52: Stockage illimité | I52: Moyenne | J52: Coûts de stockage | K52: Optimiser la gestion des espaces de stockage pour réduire les coûts tout en garantissant leur efficacité.
B53: Audit fiabilité et sécurité | C53: Vérifier la procédure de déploiement des mises à jour, d’un nouveau logiciel | D53: Procédure documentée avec matrice RACI | E53: La matrice RACI inclut-elle un responsable de rollback ? | F53: NON | G53: Document RACI versionné | H53: Responsabilité floue | I53: Moyenne | J53: 8h de troubleshooting (25k€) | K53: Identifier les causes des troubleshooting et investir dans des solutions pour réduire les coûts associés.
D54: Tests automatisés (unitaires/intégration) | E54: Le pipeline CI/CD exécute-t-il ≥95% de couverture de tests ? | F54: NON | G54: Rapport SonarQube | H54: Régressions fonctionnelles | I54: Faible | J54: 15% d'incidents post-déploiement | K54: Réduire les incidents post-déploiement en testant rigoureusement les systèmes avant leur mise en production.
D55: Fenêtre de maintenance approuvée par la direction | E55: La fenêtre est-elle communiquée 72h à l'avance ? | F55: NON | G55: Email de notification | H55: Conflits avec les utilisateurs | I55: Moyenne | J55: Amendes pour non-respect SLA | K55: Respecter les SLA pour éviter les amendes en améliorant la gestion des délais et des ressources.
D56: Journal des déploiements avec timestamp et checksum | E56: Le journal contient-il les hashs SHA-256 des packages ? | F56: NON | G56: Logs Ansible/Jenkins | H56: Altération des binaires | I56: Faible | J56: Compromission données | K56: Mettre en place des mécanismes de détection et de prévention des compromissions de données.
D57: Scan de vulnérabilités pré-production | E57: Le scan Nessus montre-t-il <5 vulnérabilités critiques ? | F57: OUI | G57: Rapport Nessus PDF | H57: Exploits en production | I57: Moyenne | J57: Sanctions RGPD (4% CA) | K57: Garantir la conformité RGPD pour éviter les sanctions en formant les équipes et en renforçant les mesures de sécurité.
C58: Vérifier les outils mis en place pour gérer les versions des logiciels | D58: Single Source of Truth (Git/Bitbucket) | E58: 100% du code est-il dans le dépôt central ? | F58: PAS | G58: Audit Git avec git ls-remote | H58: Code fantôme | I58: Faible | J58: 40h de recherche de code | K58: Minimiser le temps consacré à la recherche de code en utilisant des outils automatisés et une documentation claire.
D59: Politique de branching (GitFlow) | E59: Existe-t-il un document de politique de branching ? | F59: OUI | G59: Politique PDF signée | H59: Merges chaotiques | I59: Faible | J59: 30% de temps perdu en résolution | K59: Réduire le temps perdu en résolution par une meilleure formation et des outils de diagnostic avancés.
D60: Tagging sémantique (v1.2.3) | E60: Les tags suivent-ils SEMVER ? | F60: NON | G60: Liste des tags (git tag -l) | H60: Incompatibilités | I60: Faible | J60: Coût de migration ×3 | K60: Optimiser le processus de migration pour éviter que les coûts ne soient multipliés.
D61: Synchronisation CMDB-SCM | E61: La CMDB reflète-t-elle la version en production ? | F61: PAS | G61: Export CMDB en JSON | H61: Désynchronisation assets | I61: Moyenne | J61: Erreurs d'inventaire | K61: Effectuer des inventaires précis pour éviter les erreurs et garantir une bonne gestion des actifs.
D62: Historique des changements sur 5 ans | E62: Peut-on retrouver le code d'il y a 3 ans ? | F62: OUI | G62: Backup LTO des dépôts | H62: Non-reproductibilité | I62: Moyenne | J62: Non-conformité SOX | K62: Assurer la conformité SOX en effectuant des audits réguliers et en suivant les standards établis.
C63: Vérifier les outils mis en place pour gérer le matériel informatique | D63: CMDB à jour (≤7 jours) | E63: Le scan Lansweeper a-t-il <5% d'écarts ? | F63: OUI | G63: Diff CMDB/Lansweeper | H63: Shadow IT | I63: Moyenne | J63: 60k€ de licences inutiles | K63: Éviter les coûts inutiles en surveillant l'utilisation des licences logicielles et en ajustant les besoins.
D64: Découverte automatique des assets | E64: Les nouveaux VMs sont-ils détectés en <1h ? | F64: OUI | G64: Logs ServiceNow Discovery | H64: Assets non managés | I64: Faible | J64: 20h/semaine de gestion manuelle | K64: Automatiser les tâches manuelles pour réduire les 20 heures hebdomadaires de gestion manuelle.
D65: SBOM pour tous les logiciels | E65: Les BOM contiennent-ils les CPE ? | F65: OUI | G65: Fichiers CycloneDX | H65: Vulnérabilités inconnues | I65: Faible | J65: Failures log4j-like | K65: Se prémunir contre les vulnérabilités comme celles de Log4j en surveillant et corrigeant les failles logicielles.
D66: Alerte sur EOL/EOS | E66: Les alertes EOL sont-elles envoyées 6 mois à l'avance ? | F66: PAS | G66: Alertes SCOM/Qualys | H66: Panne critique | I66: Faible | J66: Indisponibilité majeure | K66: Renforcer les mesures de continuité pour réduire les indisponibilités majeures des systèmes.
D67: Rapport d'obsolescence trimestriel | E67: Le rapport identifie-t-il ≥90% des assets obsolètes ? | F67: PAS | G67: Rapport PDF avec plan de remplacement | H67: Coûts de maintien ×5 | I67: Moyenne | J67: Dépenses CAPEX imprévues | K67: Prévoir et maîtriser les dépenses CAPEX pour éviter les imprévus financiers.
C68: S’assurer qu’il existe un processus spécifique pour le suivi des mises à jour sur les portables | D68: Inventaire MDM exhaustif | E68: Le MDM couvre-t-il ≥98% des devices ? | F68: NON | G68: Rapport Intune/JAMF | H68: Portables non patchés | I68: Faible | J68: Infection ransomware | K68: Mettre en œuvre des protections efficaces contre les ransomwares et former les équipes sur les bonnes pratiques.
D69: Politique de patchs critiques (<72h) | E69: Les patchs MS17-010 sont-ils déployés en <72h ? | F69: NON | G69: Logs WSUS/SCCM | H69: Breaches 0-day | I69: Faible | J69: Fuite données (PII) | K69: Protéger les données personnelles (PII) contre les fuites en utilisant des solutions de chiffrement robustes.
D70: VPN obligatoire pour les mises à jour | E70: Le VPN est-il requis via Always On VPN ? | F70: NON | G70: Config GPO/PowerShell | H70: Mises à jour corrompues | I70: Faible | J70: Coût de remediation 50k€ | K70: Réduire les coûts de remédiation en adoptant des stratégies de prévention proactive.
D71: Reporting de conformité hebdomadaire | E71: Le taux de conformité est-il >95% ? | F71: NON | G71: Dashboard Power BI | H71: Non-conformité | I71: Faible | J71: Suspension certifications | K71: Préserver les certifications par une amélioration continue et le respect des critères d’audit.
D72: Procédure pour appareils non connectés (>30j) | E72: Existe-t-il un processus pour les "dormants" ? | F72: NON | G72: Procédure documentée | H72: Backdoors persistantes | I72: Moyenne | J72: Coûts légaux (500k€+) | K72: Limiter les coûts juridiques grâce à une conformité stricte et des mécanismes de résolution des conflits.
C73: S’assurer que le déploiement de nouveaux logiciels ou mises à jour est possible à distance (utile pour les utilisateurs nomades) | D73: Solution centralisée (SCCM/Ansible) | E73: 100% des devices sont-ils managés ? | F73: NON | G73: Console SCCM screenshot | H73: Désynchronisation | I73: Faible | J73: 200h de déploiements manuels | K73: Automatiser les déploiements pour réduire les 200 heures de travail manuel et améliorer l'efficacité.
D74: Bande passante garantie (≥10Mbps/device) | E74: Le débit est-il monitoré via PRTG ? | F74: PAS | G74: Graphiques PRTG | H74: Échecs de déploiement | I74: Faible | J74: 30% de retries | K74: Diminuer le taux de retries en identifiant et en résolvant les causes des erreurs initiales.
D75: Rollback automatisé si échec | E75: Le rollback s'exécute-t-il en <15min ? | F75: PAS | G75: Playbook Ansible | H75: Bricking des devices | I75: Moyenne | J75: Remplacement hardware | K75: Planifier le remplacement du matériel pour minimiser les interruptions et optimiser les budgets.
D76: Journalisation complète (qui/quand/quoi) | E76: Les logs incluent-ils l'user Azure AD ? | F76: NON | G76: Logs Sentinel/SIEM | H76: Actions non tracées | I76: Faible | J76: Non-repudiation impossible | K76: Assurer la non-répudiation en utilisant des mécanismes de signature électronique et des journaux sécurisés.
D77: Authentification MFA obligatoire | E77: La MFA est-elle activée via Conditional Access ? | F77: OUI | G77: Rapport MFA Azure AD | H77: Accès compromis | I77: Moyenne | J77: Incident de sécurité majeur | K77: Renforcer les mécanismes de contrôle qualité pour réduire les erreurs dans la gestion des actifs.
B78: audit d'efficacité et de performance | C78: Vérifier comment est effectué l'inventaire des licences (logiciel, version, date de mise en production, nombre d'utilisateurs) | D78: Qualité de l’inventaire des licences | E78: L’inventaire des licences est-il complet, à jour et documenté ? | F78: NON | G78: Base d’inventaire actualisée incluant logiciel, version, date, utilisateurs | H78: Données incomplètes ou erronées | I78: Moyenne | J78: Risques juridiques, redressements ou surcoûts en cas de contrôle | K78: Mettre en place des audits réguliers pour garantir la conformité réglementaire et limiter les litiges.
D79: Utilisation d’outils SAM | E79: Des outils SAM sont-ils utilisés pour automatiser la gestion des licences ? | F79: OUI | G79: Déploiement d’un outil SAM intégré aux systèmes d’information | H79: Absence de contrôle automatisé des actifs logiciels | I79: Moyenne | J79: Mauvaise gestion des licences, surcoût ou pénalités | K79: Déployer des systèmes automatisés pour gérer les licences et éviter les pénalités pour non-conformité.
D80: Fréquence des revues de licences | E80: Les licences font-elles l’objet de revues régulières ? | F80: NON | G80: Planning annuel de revues avec rapports de conformité | H80: Logiciels non détectés ou non conformes | I80: Faible | J80: Non-conformité contractuelle, amendes ou litiges | K80: Adapter les processus décisionnels aux données disponibles pour améliorer l'efficacité des décisions.
D81: Existence d’une CMDB opérationnelle | E81: Une base CMDB intègre-t-elle les composants logiciels et leurs statuts ? | F81: OUI | G81: CMDB structurée, documentée et synchronisée avec le SI | H81: Désalignement entre l’infrastructure réelle et la base de référence | I81: Moyenne | J81: Erreurs de gestion, décisions IT inefficaces | K81: Former les équipes sur les bonnes pratiques pour minimiser les erreurs de gestion des licences.
D82: Niveau de sensibilisation de la DSI | E82: La DSI est-elle formée aux risques liés à la non-conformité des licences ? | F82: OUI | G82: Sessions de sensibilisation et documentation interne disponibles | H82: Méconnaissance des obligations légales en matière de licences | I82: Faible | J82: Risques financiers et réputationnels accrus en cas de contrôle externe | K82: Introduire des outils de gestion pour surveiller et optimiser l’utilisation des actifs logiciels.
C83: S’assurer que les outils de type SAM (Software Asset Management) sont déployés | D83: Inventaire des licences | E83: Comment est structuré l’inventaire des licences (logiciels, versions, dates, utilisateurs) ? | F83: NON | G83: Inventaire formalisé et mis à jour régulièrement | H83: Données inexactes ou incomplètes | I83: Faible | J83: Risque de non-conformité et pénalités en cas d’audit | K83: Instaurer des politiques internes claires pour standardiser les processus liés aux audits externes.
D84: Outils de gestion SAM | E84: Des outils de type SAM sont-ils déployés pour gérer les actifs logiciels ? | F84: OUI | G84: Outil SAM fonctionnel et intégré au SI | H84: Manque de visibilité sur l’usage des licences | I84: Moyenne | J84: Surcoûts liés aux licences inutilisées ou non déclarées | K84: Protéger la réputation de l’organisation en réduisant les risques de litiges par une gestion proactive.
D85: Revue des licences | E85: Une revue périodique des licences est-elle effectuée ? | F85: PAS | G85: Planning annuel de revues avec comptes-rendus | H85: Utilisation de logiciels non conformes | I85: Moyenne | J85: Risques juridiques et atteinte à l’image de l’organisation | K85: Identifier les écarts de conformité grâce à des systèmes de reporting efficaces et précis.
D86: Gestion des configurations via CMDB | E86: Une CMDB est-elle utilisée pour recenser les composants logiciels ? | F86: NON | G86: Base CMDB complète, structurée et synchronisée | H86: Désalignement entre infrastructure réelle et référencée | I86: Moyenne | J86: Décisions IT inefficaces, erreurs dans la gestion des actifs | K86: Analyser les données de manière continue pour anticiper les besoins en licences et éviter les surcoûts.
D87: Sensibilisation des équipes IT | E87: La DSI est-elle formée et sensibilisée à la gestion des licences ? | F87: NON | G87: Sessions de sensibilisation régulières, support documentaire | H87: Faible connaissance des obligations légales | I87: Moyenne | J87: Manquements en cas de contrôle externe, sanctions possibles | K87: Renforcer la collaboration inter-département pour adresser efficacement les contrôles externes.
C88: S’assurer qu’il existe des revues régulières des licences | D88: Existence d’un processus de revue | E88: Des revues de licences sont-elles planifiées régulièrement ? | F88: NON | G88: Planning annuel formalisé avec comptes rendus | H88: Suivi non systématique de la conformité | I88: Moyenne | J88: Risques de non-renouvellement ou de dépassement de licence | K88: Mettre en œuvre des correctifs adaptés pour répondre rapidement aux problèmes identifiés pendant les audits.
D89: Implication des parties prenantes | E89: Qui participe aux revues de licences ? | F89: NON | G89: Comité avec DSI, achats, juridique | H89: Manque de coordination | I89: Moyenne | J89: Erreurs d’évaluation ou sous-licenciement | K89: Instaurer un suivi précis des licences pour assurer leur renouvellement dans les délais.
D90: Traçabilité des résultats | E90: Les résultats des revues sont-ils archivés ? | F90: NON | G90: Rapports stockés dans un référentiel sécurisé | H90: Perte d’historique de conformité | I90: Moyenne | J90: Difficulté à prouver la conformité lors d’un audit | K90: Automatiser la gestion des écarts afin de garantir leur correction rapide et efficace.
D91: Prise en compte des évolutions | E91: Les changements dans le parc sont-ils intégrés aux revues ? | F91: OUI | G91: Mécanisme de mise à jour intégré au processus | H91: Revues obsolètes ou incomplètes | I91: Moyenne | J91: Non-détection de nouveaux logiciels ou d’usages | K91: Suivre de manière proactive les évolutions réglementaires pour adapter les pratiques internes.
D92: Alignement avec les contrats éditeurs | E92: Les revues tiennent-elles compte des clauses contractuelles ? | F92: NON | G92: Liste des contrats intégrée dans la revue | H92: Écarts avec les droits d’usage | I92: Moyenne | J92: Litiges ou redressements contractuels | K92: Améliorer la traçabilité des décisions IT pour répondre aux exigences des audits externes.
C93: S’assurer qu’il existe une base de données de gestion de configuration de type CMDB (Configuration Management Data Base) | D93: Existence d’une CMDB | E93: Existe-t-il une CMDB recensant les actifs logiciels ? | F93: OUI | G93: Base de données centralisée et à jour | H93: Absence de référentiel fiable | I93: Moyenne | J93: Décisions IT prises sur des données incomplètes | K93: Prendre des décisions IT basées sur des données complètes et fiables.
D94: Qualité des données | E94: La CMDB est-elle maintenue avec des données fiables ? | F94: NON | G94: Procédures de mise à jour régulière | H94: Données obsolètes ou inexactes | I94: Faible | J94: Analyse erronée des besoins en licences | K94: Mettre en place des analyses approfondies pour évaluer précisément les besoins en licences.
D95: Intégration avec d’autres outils | E95: La CMDB est-elle reliée aux outils SAM ou d’inventaire ? | F95: OUI | G95: Interfaçage opérationnel et automatisé | H95: Données incohérentes ou redondantes | I95: Moyenne | J95: Temps perdu à recouper manuellement les informations | K95: Automatiser le recoupement des informations pour éviter la perte de temps.
D96: Gouvernance de la CMDB | E96: Qui est responsable de sa mise à jour ? | F96: NON | G96: RACI documenté avec rôles définis | H96: Absence de responsabilité claire | I96: Moyenne | J96: CMDB inutilisée ou négligée | K96: Utiliser et maintenir la CMDB de manière rigoureuse pour garantir son efficacité.
D97: Auditabilité | E97: La CMDB est-elle auditée régulièrement ? | F97: OUI | G97: Rapports d’audit internes disponibles | H97: Manque de contrôle qualité | I97: Élevée | J97: Inexactitudes non détectées entraînant des écarts de conformité | K97: Mettre en place des contrôles pour détecter et corriger les inexactitudes avant qu'elles n'entraînent des écarts de conformité.
C98: S’assurer que la DSI est sensibilisée aux enjeux de la maîtrise des licences ? (notamment en cas de contrôle) | D98: Niveau de formation de la DSI | E98: La DSI a-t-elle reçu une formation sur la gestion des licences ? | F98: OUI | G98: Programmes de formation ou sensibilisation en place | H98: Méconnaissance des règles de conformité | I98: Moyenne | J98: Mauvaises pratiques internes | K98: Sensibiliser les équipes aux bonnes pratiques internes pour éviter des erreurs répétées.
D99: Communication interne | E99: Les enjeux des licences sont-ils régulièrement rappelés ? | F99: NON | G99: Supports internes de communication | H99: Oubli ou négligence des obligations | I99: Faible | J99: Accumulation d’écarts non contrôlés | K99: Suivre régulièrement les écarts identifiés pour éviter leur accumulation.
D100: Implication de la direction | E100: La direction est-elle impliquée dans la gouvernance des licences ? | F100: OUI | G100: Réunions dédiées, pilotage par la gouvernance IT | H100: Manque de soutien stratégique | I100: Moyenne | J100: Difficulté à appliquer des mesures correctives | K100: Simplifier et clarifier les processus pour faciliter l’application des mesures correctives.
D101: Réactivité en cas de contrôle | E101: Existe-t-il un plan d’action en cas d’audit éditeur ? | F101: NON | G101: Scénario d’audit formalisé avec référents désignés | H101: Mauvaise préparation aux audits | I101: Moyenne | J101: Sanctions financières ou juridiques | K101: Renforcer la conformité réglementaire pour minimiser le risque de sanctions financières ou juridiques.
...

Sheet 4.5
A2: Domaines | B2: Points de Contrôle | C2: Objectifs de Contrôle | D2: Critère d’Évaluation | E2: Question d’Évaluation | F2: Réponses | G2: Documents Requis | H2: Risques | I2: Criticités | J2: Conséquences | K2: Recommandations
A3: Audit de la Sécurité Informatique | B3: Facteurs clés de succès | C3: Vérifier qu’une politique de sécurité est définie et correspond à l'activité de l'Organisation | D3: La politique est documentée et accessible. | E3: La politique de sécurité est-elle documentée et accessible à tous les employés ? | F3: OUI | G3: Politique de sécurité documentée et accessible | H3: Non-application des politiques de sécurité en raison d'un manque de clarté ou de diffusion. | I3: Élevée | J3: Exposition accrue aux cyberattaques | K3: Clarifier et diffuser les politiques de sécurité.
D4: La politique couvre tous les aspects critiques. | E4: La politique de sécurité couvre-t-elle les aspects critiques tels que la protection des réseaux industriels ? | F4: OUI | G4: Politique formelle couvrant les aspects critiques | H4: Exposition accrue aux cyberattaques sur les systèmes critiques. | I4: Élevée | J4: Mauvaise adaptation aux menaces actuelles | K4: Réviser les politiques pour qu'elles soient adaptées.
D5: La politique est mise à jour régulièrement. | E5: À quelle fréquence la politique de sécurité est-elle mise à jour ? | F5: OUI | G5: Plan de mise à jour de la politique | H5: Utilisation de politiques obsolètes ne répondant pas aux menaces actuelles. | I5: Élevée | J5: Non-respect des politiques | K5: Organiser des campagnes de sensibilisation.
D6: La politique est communiquée efficacement. | E6: Tous les employés et tiers concernés ont-ils accès à la politique de sécurité ? | F6: OUI | G6: Liste des utilisateurs ayant accès à la politique | H6: Mauvaise sensibilisation des employés et non-respect des politiques. | I6: Moyenne | J6: Mise en œuvre limitée | K6: Fournir un soutien stratégique et opérationnel.
D7: La politique est soutenue par la direction. | E7: La direction s’engage-t-elle dans la mise en œuvre et le respect de la politique de sécurité ? | F7: NON | G7: Engagement écrit de la direction | H7: Manque de soutien pour la mise en œuvre des initiatives de sécurité. | I7: Élevée | J7: Risques organisationnels | K7: Définir clairement les rôles en matière de sécurité.
C8: Vérifier qu’une démarche de mise en œuvre de la gestion de la sécurité est adoptée et compatible avec la culture de l'Organisation | D8: La démarche de gestion de la sécurité est clairement définie et documentée. | E8: La démarche de gestion est-elle documentée et accessible à toutes les parties concernées ? | F8: OUI | G8: Manuel de gestion de la sécurité | H8: Confusion dans la gestion des rôles et responsabilités en matière de sécurité. | I8: Élevée | J8: Adoption limitée | K8: Impliquer les employés dans les processus.
D9: Les processus de sécurité sont alignés avec la stratégie et les valeurs de l’Organisation. | E9: Les processus de sécurité sont-ils adaptés à la culture organisationnelle ? | F9: NON | G9: Analyse d'adéquation entre processus et culture | H9: Résistance des employés aux nouvelles initiatives de sécurité. | I9: Moyenne | J9: Menaces persistantes | K9: Investir dans des technologies adaptées.
D10: La démarche est soutenue par des outils ou technologies conformes. | E10: Les outils utilisés dans la mise en œuvre de la sécurité sont-ils compatibles avec les besoins organisationnels ? | F10: PAS | G10: Évaluation des outils utilisés | H10: Utilisation inefficace ou inadéquate des technologies de sécurité. | I10: Élevée | J10: Gestion des risques inefficace | K10: Renforcer la supervision des politiques.
D11: Un responsable de la mise en œuvre est désigné et actif. | E11: Existe-t-il un responsable chargé de superviser la mise en œuvre de la gestion de la sécurité ? | F11: NON | G11: Organigramme et rôle du RSSI | H11: Absence de supervision claire, entraînant une gestion désorganisée de la sécurité. | I11: Élevée | J11: Vulnérabilités amplifiées | K11: Identifier et corriger les failles rapidement.
D12: Les résultats de la mise en œuvre sont régulièrement évalués. | E12: Les performances de la gestion de la sécurité sont-elles régulièrement évaluées et révisées ? | F12: OUI | G12: Rapports d'évaluation des performances de sécurité | H12: Faiblesse des politiques de sécurité non identifiée à temps. | I12: Moyenne | J12: Résultats des initiatives limités | K12: Promouvoir des actions engageantes.
C13: Vérifier que la direction assure un soutien total et un engagement visible pour la sécurité | D13: La direction exprime un engagement formel pour la sécurité. | E13: La direction a-t-elle publié un engagement officiel envers la gestion de la sécurité ? | F13: NON | G13: Déclaration publique d'engagement | H13: Faible engagement des employés envers les initiatives de sécurité. | I13: Moyenne | J13: Objectifs de sécurité non atteints | K13: Augmenter le budget pour la sécurité.
D14: Les ressources nécessaires sont allouées à la sécurité. | E14: La direction assure-t-elle la disponibilité des ressources pour atteindre les objectifs de sécurité ? | F14: NON | G14: Budget alloué pour les mesures de sécurité | H14: Insuffisance des moyens financiers pour répondre aux exigences de sécurité. | I14: Moyenne | J14: Non-adaptation continue | K14: Mettre en place un suivi rigoureux des évolutions.
D15: La direction participe aux audits et réunions de suivi de la sécurité. | E15: Les membres de la direction participent-ils activement aux revues de sécurité ? | F15: NON | G15: Procès-verbal des réunions de revues de sécurité | H15: Manque de suivi dans l'amélioration continue des politiques de sécurité. | I15: Moyenne | J15: Failles organisationnelles | K15: Revoir les mécanismes de coordination.
D16: Les employés perçoivent le soutien actif de la direction. | E16: Les employés reconnaissent-ils le rôle actif de la direction dans les initiatives de sécurité ? | F16: NON | G16: Enquête sur l'implication des employés | H16: Manque de soutien interne, limitant l'efficacité des politiques de sécurité. | I16: Moyenne | J16: Impact négatif sur les systèmes industriels | K16: Développer des outils pour détecter les risques.
D17: La communication entre la direction et les responsables de sécurité est fluide. | E17: Y a-t-il des réunions ou rapports réguliers entre la direction et les responsables de la sécurité ? | F17: NON | G17: Calendrier des réunions sécurité-direction | H17: Mauvaise coordination entraînant des failles organisationnelles. | I17: Moyenne | J17: Vulnérabilités croissantes | K17: Harmoniser les processus de gestion des risques.
C18: Vérifier que les exigences de sécurité et les risques sont compris et évalués | D18: Les risques spécifiques aux processus critiques sont identifiés. | E18: Les risques liés aux infrastructures industrielles ou énergétiques ont-ils été identifiés et évalués ? | F18: OUI | G18: Rapport d'analyse des risques | H18: Risques critiques non détectés, mettant en péril les systèmes industriels. | I18: Élevée | J18: Mauvaises orientations | K18: Collecter des données fiables pour éclairer les décisions.
D19: Une méthodologie d’évaluation des risques est en place. | E19: Une méthodologie standard est-elle utilisée pour l’évaluation des risques ? | F19: PAS | G19: Méthodologie standardisée de gestion des risques | H19: Gestion des risques incohérente, augmentant les vulnérabilités. | I19: Moyenne | J19: Exposition accrue | K19: Renforcer les mesures pour diminuer les impacts.
D20: Les résultats de l’évaluation sont documentés et communiqués. | E20: Les résultats des évaluations des risques sont-ils bien documentés et partagés avec les parties prenantes ? | F20: NON | G20: Résultats des évaluations de risques | H20: Décision stratégique mal éclairée par manque de données fiables. | I20: Moyenne | J20: Systèmes non adaptés | K20: Déployer des solutions face aux menaces émergentes.
D21: Les mesures d’atténuation des risques sont intégrées aux pratiques. | E21: Les mesures mises en place pour atténuer les risques sont-elles opérationnelles et surveillées ? | F21: PAS | G21: Tableau des plans d'atténuation des risques | H21: Mauvaise réduction des impacts des menaces identifiées. | I21: Moyenne | J21: Mauvaise réduction des impacts des menaces identifiées | K21: Renforcer les mesures pour mieux atténuer les impacts.
D22: Une mise à jour périodique de l’évaluation des risques est effectuée. | E22: Les évaluations des risques sont-elles mises à jour en cas de changement ou de nouvelles menaces ? | F22: NON | G22: Rapport d'actualisation des risques | H22: Non-réponse aux nouvelles menaces, augmentant l'exposition globale. | I22: Élevée | J22: Augmentation de l’exposition globale aux nouvelles menaces | K22: Déployer des solutions adaptées aux menaces émergentes.
C23: Vérifier que l’ensemble des responsables et des employés sont sensibilisés et informés | D23: Des formations régulières sont organisées pour tous les employés. | E23: Tous les employés ont-ils accès à des formations sur les bonnes pratiques en sécurité ? | F23: NON | G23: Programme de formation des employés | H23: Mauvaise application des bonnes pratiques de sécurité par manque de connaissances. | I23: Élevée | J23: Manque de connaissances sur les bonnes pratiques de sécurité | K23: Organiser des sessions de formation pour sensibiliser et former.
D24: La sensibilisation aux menaces numériques est continue. | E24: Des campagnes de sensibilisation aux cybermenaces sont-elles régulièrement organisées ? | F24: NON | G24: Plan de sensibilisation aux cybermenaces | H24: Augmentation des incidents dus à des erreurs humaines évitables. | I24: Élevée | J24: Augmentation des incidents dus à des erreurs humaines évitables | K24: Automatiser les processus critiques pour minimiser les erreurs humaines.
D25: Les nouvelles recrues reçoivent une formation sur la sécurité. | E25: Les nouveaux employés bénéficient-ils d’un programme d’intégration traitant des politiques de sécurité ? | F25: NON | G25: Programme d'intégration des employés | H25: Non-respect des politiques de sécurité par les nouveaux arrivants. | I25: Moyenne | J25: Non-respect des politiques de sécurité par les nouveaux arrivants | K25: Mettre en place des campagnes de sensibilisation adaptées aux nouveaux employés.
