Workbook

Sheet Synthese
B3: Synthèse Numérique | J3: Equipe de Mission
B5: N° | C5: Domaines | D5: Total OUI | E5: Total NON | F5: Total PAS | G5: Total | H5: Score | M5: Nom | N5: Prénom | O5: Grade
B6: 1 | C6: COSO | D6: =COUNTIF(Coso!J2:J516,"OUI") -> 475 | E6: =COUNTIF(Coso!J2:J516,"NON") -> 37 | F6: =COUNTIF(Coso!J2:J516,"PAS") -> 3 | G6: =SUM(D6:F6) -> 515 | H6: =D6/G6 -> 0.9223301 | K6: Chef :
B7: 2 | C7: Application en service | D7: =COUNTIF('4.1'!J2:J506,"OUI") -> 464 | E7: =COUNTIF('4.1'!J2:J506,"NON") -> 38 | F7: =COUNTIF([1]Global!J8:J10,"PAS") -> 1 | G7: =SUM(D7:F7) -> 503 | H7: =D7/G7 -> 0.92246521
B8: 3 | C8: Fonction informatique | D8: =COUNTIF('4.2'!J2:J206,"OUI") -> 184 | E8: =COUNTIF('4.2'!J2:J206,"NON") -> 18 | F8: =COUNTIF('4.1'!J2:J506,"PAS") -> 3 | G8: =SUM(D8:F8) -> 205 | H8: =D8/G8 -> 0.89756098 | K8: Membres:
B9: 4 | C9: Contrôle des Projets Informatiques | D9: =COUNTIF('4.3'!J2:J1141,"OUI") -> 1046 | E9: =COUNTIF('4.3'!J2:J1141,"NON") -> 87 | F9: =COUNTIF('4.3'!J2:J1141,"PAS") -> 7 | G9: =SUM(D9:F9) -> 1140 | H9: =D9/G9 -> 0.91754386 | L9: 1
B10: 5 | C10: Support Utilisateur et de la Gestion du Parc | D10: =COUNTIF('4.4'!J2:J231,"OUI") -> 203 | E10: =COUNTIF('4.4'!J2:J231,"NON") -> 25 | F10: =COUNTIF('4.4'!J2:J231,"PAS") -> 2 | G10: =SUM(D10:F10) -> 230 | H10: =D10/G10 -> 0.8826087 | L10: 2
B11: 6 | C11: Sécurité Informatique | D11: =COUNTIF('4.5'!J2:J336,"OUI") -> 298 | E11: =COUNTIF('4.5'!J2:J336,"NON") -> 35 | F11: =COUNTIF('4.5'!J2:J336,"NON") -> 35 | G11: =SUM(D11:F11) -> 368 | H11: =D11/G11 -> 0.80978261 | L11: 3
B12: 7 | C12: Contrôle de la Fonction Etude | D12: =COUNTIF('4.6'!J2:J126,"OUI") -> 104 | E12: =COUNTIF('4.6'!J2:J126,"NON") -> 19 | F12: =COUNTIF('4.6'!J2:J126,"PAS") -> 2 | G12: =SUM(D12:F12) -> 125 | H12: =D12/G12 -> 0.832 | L12: 4
B13: Total | D13: =SUM(D6:D12) -> 2774 | E13: =SUM(E6:E12) -> 259 | F13: =SUM(F6:F12) -> 53 | G13: =SUM(D13:F13) -> 3086 | H13: =D13/G13 -> 0.89889825 | K13: Chauffeur:
H21: Sythèse Graphique

Sheet Global
A1: Domaines | B1: Responsables | C1: Durée | D1: Moyens pour la réalisation | E1: Parties Prenantes | F1: Points de Contrôle | G1: Objectifs de Contrôle | H1: Critère d’Évaluation | I1: Question d’Évaluation | J1: Réponses | K1: Documents requis | L1: Risques | M1: Criticités | N1: conséquences | O1: Recommendations
A2: Environnement de Contrôle | F2: Engagement envers l’intégrité et les valeurs éthiques | G2: S’assurer que l'organisation dispose d'une charte éthique formelle qui couvre l'ensemble des pratiques professionnelles et des interactions au sein de l'organisation, y compris les activités liées aux systèmes d'information. | H2: La charte éthique est alignée sur les normes de rédaction légales nationales et internationales | I2: La charte éthique est-elle alignée sur les normes de rédaction légales nationales et internationales ? | J2: OUI | K2: Charte éthique de l'organisation | L2: Non-respect des normes légales nationales et internationales | M2: Élevée | N2: Non-respect des obligations légales entraînant des sanctions financières et des poursuites judiciaires. | O2: Mettre en place un système de veille régulier pour se conformer aux obligations légales et éviter les sanctions.
H3: La charte respecte les principes relatifs aux droit des employés en entreprise | I3: La charte respecte-t-elle les principes relatifs aux droits des employés en entreprise ? | J3: OUI | K3: Référentiels juridiques nationaux et internationaux utilisés | L3: Violation des droits des employés | M3: Élevée | N3: Détérioration de la réputation de l'entreprise due à des violations répétées des droits des employés. | O3: Élaborer un plan de communication proactive pour restaurer l'image de l'entreprise après des violations répétées.
H4: La charte éthique est communiquée à tous les employés | I4: La charte éthique est-elle communiquée à tous les employés ? | J4: OUI | K4: Document de conformité légale de la charte | L4: Manque de communication de la charte éthique aux employés | M4: Élevée | N4: Confusion généralisée parmi les employés sur les comportements attendus en l'absence de communication claire de la charte éthique. | O4: Diffuser une version simplifiée et accessible de la charte éthique pour clarifier les attentes envers les employés.
H5: La charte est régulièrement mise à jour et révisée | I5: La charte est-elle régulièrement mise à jour et révisée ? | J5: OUI | K5: Procédure interne de validation de la charte par les instances dirigeantes | L5: Défaut de mise à jour régulière de la charte | M5: Élevée | N5: Inadéquation des pratiques actuelles avec les nouvelles réglementations en raison du défaut de mise à jour de la charte. | O5: Actualiser annuellement la charte éthique pour garantir son alignement avec les nouvelles réglementations.
H6: La charte éthique est formalisée et approuvée par la direction de l'organisation | I6: La charte éthique est-elle formalisée et approuvée par la direction de l'organisation ? | J6: OUI | K6: Preuves de diffusion de la charte à l’ensemble des employés (emails, affiches, intranet) | L6: Absence de formalisation et d'approbation par la direction | M6: Élevée | N6: Manque de légitimité des politiques internes sans formalisation et approbation par la direction. | O6: Soumettre la charte éthique à une validation formelle par la direction pour renforcer sa légitimité.
G7: Vérifier que des mécanismes existent pour garantir que tous les acteurs (employés, partenaires, prestataires) respectent cette charte éthique dans leurs activités professionnelles, y compris dans leur utilisation des systèmes d'information | H7: Les employés et les partenaires semblent engages à respecter les règles établies dans la charte | I7: Les employés et les partenaires semblent-ils engagés à respecter les règles établies dans la charte ? | J7: OUI | K7: Historique des mises à jour de la charte | L7: Manque d'engagement des employés et partenaires | M7: Élevée | N7: Démotivation des équipes et désengagement des partenaires commerciaux. | O7: Organiser des ateliers collaboratifs pour identifier les causes de désengagement et proposer des solutions concrètes.
H8: Les employés sont régulièrement encourager à signaler les cas de non-conformité a la charte | I8: Les employés sont-ils régulièrement encouragés à signaler les cas de non-conformité à la charte ? | J8: OUI | K8: Procès-verbaux des réunions d’approbation de la charte | L8: Absence de signalement des non-conformités | M8: Élevée | N8: Persistance de comportements non éthiques par peur ou méconnaissance des canaux de signalement. | O8: Promouvoir les canaux de signalement anonymes pour encourager le reporting des comportements non éthiques.
H9: Les mécanismes de contrôle sont ajustes en fonction des retours effectues et des changements de l'organisation | I9: Les mécanismes de contrôle sont-ils ajustés en fonction des retours effectués et des changements de l'organisation ? | J9: OUI | K9: Engagements signés par les employés et partenaires | L9: Inadaptation des mécanismes de contrôle aux retours et changements | M9: Moyenne | N9: Contrôles inefficaces ne permettant pas de détecter les risques émergents. | O9: Déployer des outils de monitoring en temps réel pour détecter les risques émergents plus efficacement.
H10: Les mécanismes en place permettent de détecter et de corriger rapidement les écarts | I10: Les mécanismes en place permettent-ils de détecter et de corriger rapidement les écarts ? | J10: NON | K10: Registre ou plateforme de signalement des non-conformités | L10: Détection et correction lentes des écarts | M10: Élevée | N10: Augmentation des coûts liés à la correction tardive des problèmes identifiés. | O10: Allouer des ressources dédiées à la correction immédiate des problèmes identifiés pour réduire les coûts.
H11: Les mécanismes de contrôle ont été clairement expliques et compris par tous les employés | I11: Les mécanismes de contrôle ont-ils été clairement expliqués et compris par tous les employés ? | J11: OUI | K11: Rapports de contrôle interne avec retour d'expérience | L11: Mécanismes de contrôle mal compris par les employés | M11: Élevée | N11: Erreurs répétées des employés par méconnaissance des procédures de contrôle. | O11: Former régulièrement les employés sur les procédures de contrôle pour minimiser les erreurs opérationnelles.
G12: S’assurer que des actions de sensibilisation, telles que des formations régulières, sont mises en place pour garantir que tous les employés et intervenants comprennent et appliquent les principes éthiques dans leurs interactions avec les systèmes d'information | H12: Les formations et actes de sensibilisation sont alignées sur les besoins réels des employés | I12: Les formations et actes de sensibilisation sont-ils alignés sur les besoins réels des employés ? | J12: OUI | K12: Rapports d’audit sur les mécanismes de détection | L12: Formations non alignées sur les besoins réels | M12: Élevée | N12: Baisse de productivité due à des formations non adaptées aux besoins opérationnels. | O12: Adapter les programmes de formation en fonction des retours opérationnels pour améliorer la productivité.
H13: Les actions de sensibilisations sont organisées de façon régulière | I13: Les actions de sensibilisation sont-elles organisées de façon régulière ? | J13: OUI | K13: Documents de formation ou communication sur les mécanismes de contrôle | L13: Actions de sensibilisation irrégulières | M13: Élevée | N13: Sensibilisation insuffisante aux enjeux éthiques avec des actions ponctuelles et irrégulières. | O13: Planifier des sessions de sensibilisation trimestrielles pour maintenir une culture éthique forte.
H14: Les effets des actions de formation sont visibles et les employés actifs | I14: Les effets des actions de formation sont-ils visibles et les employés actifs ? | J14: OUI | K14: Plan de formation aligné avec les besoins des employés | L14: Effets non visibles des actions de formation | M14: Élevée | N14: Absence d'amélioration tangible des compétences malgré les investissements en formation. | O14: Évaluer l'impact des formations via des indicateurs concrets pour ajuster les investissements.
H15: Les effets des actions de formation sont mesurables | I15: Les effets des actions de formation sont-ils mesurables ? | J15: OUI | K15: Calendrier des actions de sensibilisation | L15: Impossibilité de mesurer l'impact des formations | M15: Élevée | N15: Impossibilité d'ajuster les programmes de formation sans données mesurables sur leur impact. | O15: Intégrer des méthodes pédagogiques interactives pour améliorer la rétention des connaissances.
H16: Les actions de formation utilise divers moyens (e-learning, ateliers, ...) pour toucher leurs cible | I16: Les actions de formation utilisent-elles divers moyens (e-learning, ateliers, ...) pour toucher leurs cibles ? | J16: OUI | K16: Rapports d’évaluation post-formation | L16: Méthodes de formation non diversifiées | M16: Élevée | N16: Faible rétention des connaissances avec des méthodes de formation monotones et non interactives. | O16: Développer des parcours de carrière clairs pour fidéliser les talents clés et réduire le turnover.
G17: S’assurer que l'organisation dispose d'un mécanisme de suivi et de gestion des violations éthiques, permettant de détecter, traiter et sanctionner tout comportement contraire à la charte éthique, y compris dans le cadre des activités liées aux systèmes d'information. | H17: Les violations sont rapidement traiter et détecter | I17: Les violations sont-elles rapidement traitées et détectées ? | J17: OUI | K17: Indicateurs de performance post-formation | L17: Traitement lent des violations | M17: Élevée | N17: Prolongation des situations à risque en raison d'un traitement lent des violations signalées. | O17: Mettre en place un système de reconnaissance basé sur des critères objectifs pour renforcer l'engagement.
H18: Les processus de gestions des violations sont clairs et bien communiquées | I18: Les processus de gestion des violations sont-ils clairs et bien communiqués ? | J18: OUI | K18: Supports pédagogiques variés (supports e-learning, ateliers, etc.) | L18: Processus de gestion des violations flous | M18: Élevée | N18: Injustice perçue par les employés face à des sanctions incohérentes ou disproportionnées. | O18: Proposer des solutions flexibles pour équilibrer vie professionnelle et personnelle.
H19: Les sanctions sont appliquées de manière juste et proportionnée | I19: Les sanctions sont-elles appliquées de manière juste et proportionnée ? | J19: OUI | K19: Registre des violations détectées et traitées | L19: Sanctions injustes ou disproportionnées | M19: Élevée | N19: Rétention d'informations par crainte de représailles en l'absence de confidentialité des signalements. | O19: Créer des enquêtes anonymes pour recueillir le feedback employé et ajuster les programmes RH.
H20: Les actions de signalement sont reçues et examinées de façon confidentielle pour la protection des parties concernées | I20: Les actions de signalement sont-elles reçues et examinées de façon confidentielle pour la protection des parties concernées ? | J20: OUI | K20: Procédures de gestion des violations | L20: Manque de confidentialité dans le traitement des signalements | M20: Élevée | N20: Persistance des faiblesses du système par non-prise en compte des retours d'expérience. | O20: Établir des critères transparents pour les promotions et augmentations afin d'éviter les perceptions d'injustice.
H21: Les retours d'expérience des cas de traitement des violations sont utilisées pou l'amélioration de la charte | I21: Les retours d'expérience des cas de traitement des violations sont-ils utilisés pour l'amélioration de la charte ? | J21: OUI | K21: Registre des sanctions appliquées avec justificatifs | L21: Non-utilisation des retours d'expérience pour améliorer la charte | M21: Élevée | N21: Exposition accrue aux risques opérationnels sans anticipation des violations potentielles. | O21: Aligner les objectifs individuels avec la stratégie globale via des entretiens annuels structurés.
G22: S'assurer que l'organisation dispose d'un processus de gestion et de prevention des risques lies a la securite des donnees et du systeme d'information | H22: Les risques de violation de la charte sont anticipes avant leurs matérialisation | I22: Les risques de violation de la charte sont-ils anticipés avant leur matérialisation ? | J22: OUI | K22: Politique de confidentialité liée aux signalements | L22: Non-anticipation des risques de violation de la charte | M22: Élevée | N22: Vulnérabilité aux cyberattaques par manque de formation sur la sécurité des données. | O22: Fournir des retours constructifs et réguliers pour soutenir le développement professionnel.
H23: Les employés sont formes pour reconnaitre et prévenir les risques lies a la sécurité des données | I23: Les employés sont-ils formés pour reconnaître et prévenir les risques liés à la sécurité des données ? | J23: NON | K23: Rapports d’analyse post-violation | L23: Manque de formation des employés sur la sécurité des données | M23: Élevée | N23: Impossibilité d'identifier les tendances ou causes racines sans documentation des incidents. | O23: Rendre publics les critères d'évaluation pour renforcer la transparence dans la gestion des carrières.
H24: Les incidents de sécurités sont documentées et analysées pour éviter des répétitions | I24: Les incidents de sécurité sont-ils documentés et analysés pour éviter des répétitions ? | J24: OUI | K24: Cartographie des risques | L24: Absence de documentation et d'analyse des incidents de sécurité | M24: Élevée | N24: Pertes financières importantes en cas d'incident majeur sans plan de continuité adapté. | O24: Utiliser les résultats d'évaluation pour identifier les besoins en formation et développement.
H25: L'organisation dispose d'un plan de continuité en cas de violation de sécurité | I25: L'organisation dispose-t-elle d'un plan de continuité en cas de violation de sécurité ? | J25: OUI | K25: Plan de formation en sécurité des données | L25: Défaut de plan de continuité en cas de violation de sécurité | M25: Moyenne | N25: Exposition aux menaces informatiques avec des mesures de sécurité non alignées sur la stratégie. | O25: Coordonner les initiatives de gestion des talents entre les départements pour éviter les redondances.
H26: Les mesures de sécurité des systèmes d'information respectent les objectifs stratégiques de l'organisation | I26: Les mesures de sécurité des systèmes d'information respectent-elles les objectifs stratégiques de l'organisation ? | J26: NON | K26: Rapports d’analyse des incidents de sécurité | L26: Inadéquation des mesures de sécurité avec les objectifs stratégiques | M26: Élevée | N26: Décisions biaisées en faveur des intérêts personnels du management au détriment de l'organisation. | O26: Réviser les processus RH pour les aligner sur la stratégie globale et améliorer la performance.
F27: Le Conseil fait preuve d’indépendance vis-à-vis du management. | G27: S’assurer que le Conseil est composé de membres indépendants du management, avec une structure de gouvernance claire garantissant cette indépendance. | H27: Les membres du conseil sont libres de toute influencent venant du management | I27: Les membres du conseil sont-ils libres de toute influence venant du management ? | J27: OUI | K27: Plan de continuité d’activité | L27: Influence du management sur les membres du conseil | M27: Élevée | N27: Surveillance inefficace des opérations par manque de compétences du conseil. | O27: Adopter une approche agile pour adapter rapidement les processus aux changements du marché.
H28: Les membres du conseil disposent de compétences de supervision efficaces dans leurs rôle | I28: Les membres du conseil disposent-ils de compétences de supervision efficaces dans leur rôle ? | J28: OUI | K28: Politique de sécurité des systèmes d’information | L28: Manque de compétences de supervision des membres du conseil | M28: Élevée | N28: Méfiance des parties prenantes face à des décisions perçues comme opaques ou arbitraires. | O28: Mettre en place des boîtes à suggestions anonymes pour encourager les feedbacks constructifs.
H29: les décisions du conseil sont prises de manière transparente | I29: Les décisions du conseil sont-elles prises de manière transparente ? | J29: OUI | K29: Charte de gouvernance précisant l’indépendance du conseil | L29: Opacité dans les décisions du conseil | M29: Moyenne | N29: Désalignement stratégique dû à une faible implication du conseil dans les orientations clés. | O29: Définir clairement les rôles et responsabilités dans des documents accessibles à tous.
H30: Les membres du conseil sont activement impliques lors des prises de décision stratégiques | I30: Les membres du conseil sont-ils activement impliqués lors des prises de décision stratégiques ? | J30: OUI | K30: CV ou profils des membres du conseil démontrant leurs compétences | L30: Faible implication des membres du conseil dans les décisions stratégiques | M30: Élevée | N30: Stagnation des performances sans évaluation régulière et constructive du conseil. | O30: Documenter toutes les attributions et décisions pour faciliter les audits et vérifications.
H31: Les performances du conseil sont régulièrement évaluées pour vérifier leurs efficacité | I31: Les performances du conseil sont-elles régulièrement évaluées pour vérifier leur efficacité ? | J31: OUI | K31: Procès-verbaux des décisions du conseil | L31: Absence d'évaluation régulière des performances du conseil | M31: Élevée | N31: Prise de décision à l'aveugle par manque d'accès aux informations critiques. | O31: Déployer un portail centralisé d’accès aux données critiques pour faciliter la prise de décision éclairée.
G32: Vérifier que le Conseil dispose des ressources et des informations nécessaires pour surveiller efficacement la mise en place et le bon fonctionnement du dispositif de contrôle interne | H32: Le conseil a un accès sur toutes les informations de l'organisation pour augmenter la justesse de leurs décisions | I32: Le conseil a-t-il accès à toutes les informations de l'organisation pour augmenter la justesse de ses décisions ? | J32: OUI | K32: Documents de participation active aux réunions stratégiques | L32: Accès limité du conseil aux informations de l'organisation | M32: Élevée | N32: Fonctionnement inefficace du conseil par manque de soutien logistique et technique. | O32: Renforcer les moyens logistiques et techniques du conseil pour optimiser son fonctionnement.
H33: Le conseil dispose de soutien administratif et techniques en cas de nécessité | I33: Le conseil dispose-t-il de soutien administratif et technique en cas de nécessité ? | J33: OUI | K33: Rapports d’évaluation du conseil | L33: Manque de soutien administratif et technique pour le conseil | M33: Élevée | N33: Compétences obsolètes des membres du conseil sans formation continue adaptée. | O33: Instaurer un programme obligatoire de formation continue pour les membres du conseil.
H34: Les membres du conseil sont régulièrement formes pour rester à jour sur les tendances actuelles | I34: Les membres du conseil sont-ils régulièrement formés pour rester à jour sur les tendances actuelles ? | J34: NON | K34: Documents d’accès à l’information par le conseil | L34: Défaut de formation continue des membres du conseil | M34: Élevée | N34: Silos organisationnels et inefficacités opérationnelles par manque de collaboration. | O34: Promouvoir des réunions transversales et outils collaboratifs pour briser les silos.
H35: Le conseil collabore activement avec les autres entités de l'organisation | I35: Le conseil collabore-t-il activement avec les autres entités de l'organisation ? | J35: OUI | K35: Liste des soutiens administratifs et techniques attribués au conseil | L35: Collaboration insuffisante du conseil avec les autres entités | M35: Élevée | N35: Contrôle insuffisant des activités clés avec un budget inadapté aux missions du conseil. | O35: Réviser le budget alloué au conseil pour mieux couvrir ses missions essentielles.
H36: Le conseil dispose d'un budget suffisant pour ses missions | I36: Le conseil dispose-t-il d'un budget suffisant pour ses missions ? | J36: OUI | K36: Planning des formations continues des membres du conseil | L36: Budget insuffisant pour les missions du conseil | M36: Élevée | N36: Décisions tardives ou inopportunes en raison de retards dans la production des rapports. | O36: Automatiser la génération de rapports pour accélérer leur production et diffusion.
G37: S’assurer que le Conseil reçoit régulièrement des rapports détaillés sur l’efficacité du dispositif de contrôle interne et qu'il est impliqué dans l’évaluation des résultats des audits internes | H37: Des rapports sont fournis régulièrement et en temps opportun | I37: Des rapports sont-ils fournis régulièrement et en temps opportun ? | J37: OUI | K37: Preuves de collaboration entre conseil et autres entités | L37: Retards ou irrégularité dans la production des rapports | M37: Élevée | N37: Impossibilité d'analyser finement les risques avec des rapports superficiels ou incomplets. | O37: Standardiser les modèles de rapports avec des indicateurs clés pour une analyse approfondie.
H38: Les rapports contient toutes les informations nécessaires de façon très détaille | I38: Les rapports contiennent-ils toutes les informations nécessaires de façon très détaillée ? | J38: OUI | K38: Budget du conseil | L38: Manque de détails dans les rapports fournis | M38: Élevée | N38: Frustration des parties prenantes recevant des rapports inadaptés à leurs besoins. | O38: Personnaliser les rapports en fonction des besoins spécifiques de chaque partie prenante.
H39: Les rapports fournis sont toujours adaptes aux besoins du conseil | I39: Les rapports fournis sont-ils toujours adaptés aux besoins du conseil ? | J39: OUI | K39: Calendrier des rapports fournis | L39: Inadéquation des rapports aux besoins du conseil | M39: Moyenne | N39: Perte de confiance dans la gouvernance avec des rapports ne reflétant pas la réalité. | O39: Mettre en place un audit indépendant pour vérifier l’exactitude des rapports.
H40: Les rapports respectent fidèlement la réalité des missions | I40: Les rapports respectent-ils fidèlement la réalité des missions ? | J40: OUI | K40: Contenu détaillé des rapports | L40: Défaut de fidélité des rapports à la réalité | M40: Élevée | N40: Opportunités d'amélioration manquées par non-utilisation des rapports pour des corrections. | O40: Utiliser les rapports comme base pour des revues d’amélioration continue.
H41: Le conseil utilise les rapports pour prendre des mesures correctives si nécessaire | I41: Le conseil utilise-t-il les rapports pour prendre des mesures correctives si nécessaire ? | J41: OUI | K41: Études des besoins informationnels du conseil | L41: Non-utilisation des rapports pour des mesures correctives | M41: Moyenne | N41: Exposition accrue aux risques par désalignement entre contrôles et stratégie globale. | O41: Alignez les contrôles internes avec la stratégie globale via des ateliers de cadrage.
G42: Vérifier que le Conseil joue un rôle actif dans la définition des objectifs et des critères de performance du contrôle interne, et qu’il veille à leur alignement avec les objectifs stratégiques de l’organisation. | H42: Les objectifs de contrôle internes sont en harmonise avec les objectifs stratégiques de l'organisation | I42: Les objectifs de contrôle internes sont-ils en harmonie avec les objectifs stratégiques de l'organisation ? | J42: OUI | K42: Rapports d’activité fidèles aux missions | L42: Désalignement des objectifs de contrôle avec les objectifs stratégiques | M42: Élevée | N42: Objectifs contradictoires ou redondants par manque de participation du conseil à leur définition. | O42: Impliquer systématiquement le conseil dans la définition des objectifs stratégiques.
H43: Le conseil participe activement à la définition des critères de performances | I43: Le conseil participe-t-il activement à la définition des critères de performance ? | J43: OUI | K43: Preuves d’utilisation des rapports pour mesures correctives | L43: Faible participation du conseil à la définition des critères de performance | M43: Élevée | N43: Confusion des équipes sur les priorités avec des critères de performance flous. | O43: Définir des critères de performance SMART et les communiquer clairement aux équipes.
H44: Les objectifs et critères sont claires et communiques dans toute l'organisation | I44: Les objectifs et critères sont-ils clairs et communiqués dans toute l'organisation ? | J44: OUI | K44: Tableaux de correspondance entre objectifs internes et stratégie | L44: Critères de performance flous ou mal communiqués | M44: Élevée | N44: Dérive des projets sans suivi régulier des indicateurs clés. | O44: Suivre les indicateurs clés via des tableaux de bord en temps réel.
H45: Le conseil suit la progression vers leurs objectifs qui ont été fixes de manière régulière | I45: Le conseil suit-il la progression vers ses objectifs de manière régulière ? | J45: OUI | K45: Procès-verbaux de réunions de définition des critères de performance | L45: Suivi irrégulier de la progression vers les objectifs | M45: Élevée | N45: Rigidité organisationnelle face aux changements avec des objectifs non révisés. | O45: Réviser trimestriellement les objectifs pour s’adapter aux changements.
H46: Les objectifs sont modifiés en cas de changements interne ou externes | I46: Les objectifs sont-ils modifiés en cas de changements internes ou externes ? | J46: OUI | K46: Documents de communication des objectifs | L46: Inflexibilité des objectifs face aux changements | M46: Élevée | N46: Aggravation des problèmes opérationnels par réaction tardive du conseil. | O46: Instaurer des points d’étape mensuels pour anticiper les problèmes opérationnels.
G47: S’assurer que le Conseil prend des mesures appropriées lorsque des dysfonctionnements ou des lacunes dans le contrôle interne sont identifiés, y compris la mise en place de plans d’action correctifs. | H47: Le conseil est rapide dans ses réactions en cas de dysfonctionnement signales | I47: Le conseil est-il rapide dans ses réactions en cas de dysfonctionnement signalé ? | J47: PAS | K47: Rapports de suivi des objectifs | L47: Lenteur du conseil à réagir aux dysfonctionnements | M47: Élevée | N47: Solutions inefficaces ou temporaires avec une mise en œuvre laxiste des corrections. | O47: Élaborer des plans d’action correctifs avec des responsables désignés et des échéances.
H48: Les mesures correctives sont mises en œuvres de façon rigoureuse | I48: Les mesures correctives sont-elles mises en œuvre de façon rigoureuse ? | J48: OUI | K48: Documents de mise à jour des objectifs | L48: Mise en œuvre laxiste des mesures correctives | M48: Élevée | N48: Manque de transparence et difficulté à auditer les actions du conseil sans documentation. | O48: Documenter systématiquement les décisions et actions du conseil pour traçabilité.
H49: Les actions du conseil sont documentées et communiquées aux parties prenantes | I49: Les actions du conseil sont-elles documentées et communiquées aux parties prenantes ? | J49: OUI | K49: Alertes ou compte-rendus de dysfonctionnements traités | L49: Défaut de documentation et de communication des actions du conseil | M49: Élevée | N49: Récurrence des problèmes par absence de solutions durables et systémiques. | O49: Mener des analyses post-projet pour identifier les causes racines des échecs.
H50: Les mesures prises résolvent les problèmes de façon durable | I50: Les mesures prises résolvent-elles les problèmes de façon durable ? | J50: OUI | K50: Preuves de mise en œuvre des mesures correctives | L50: Solutions non durables aux problèmes identifiés | M50: Élevée | N50: Répétition des mêmes erreurs par non-analyse des dysfonctionnements passés. | O50: Créer une base de connaissances des incidents passés pour éviter leur répétition.
H51: Le conseil tire des leçons des dysfonctionnement pour s'améliorer | I51: Le conseil tire-t-il des leçons des dysfonctionnements pour s'améliorer ? | J51: OUI | K51: Rapports de communication aux parties prenantes | L51: Non-apprentissage des dysfonctionnements passés | M51: Élevée | N51: Subjectivité dans l'appréciation des performances avec des critères d'évaluation imprécis. | O51: Définir des grilles d’évaluation objectives et les appliquer uniformément.
G52: Vérifier que le Conseil évalue régulièrement la performance des responsables du contrôle interne et veille à ce que leurs actions soient indépendantes et objectives. | H52: Les évaluations sont basées sur des critères clairs et précis | I52: Les évaluations sont-elles basées sur des critères clairs et précis ? | J52: OUI | K52: Études d’impact des mesures prises | L52: Critères d'évaluation flous ou imprécis | M52: Élevée | N52: Démotivation des équipes par manque de reconnaissance ou feedback constructif. | O52: Instaurer un système de reconnaissance formalisé basé sur les résultats.
H53: Les évaluations sont réalisées régulièrement pour une amélioration continue de l'organisation | I53: Les évaluations sont-elles réalisées régulièrement pour une amélioration continue de l'organisation ? | J53: OUI | K53: Analyse post-dysfonctionnement | L53: Évaluations irrégulières ou absentes | M53: Élevée | N53: Décisions managériales biaisées par des évaluations non objectives ou indépendantes. | O53: Externaliser les évaluations critiques pour garantir leur objectivité.
H54: Les responsables reçoivent des retours constructifs pour l'amélioration des performances | I54: Les responsables reçoivent-ils des retours constructifs pour l'amélioration des performances ? | J54: OUI | K54: Grilles d’évaluation utilisées | L54: Retours non constructifs aux responsables | M54: Élevée | N54: Gaspillage des ressources sans utilisation des résultats d'évaluation pour progresser. | O54: Utiliser les résultats d’évaluation pour piloter les plans de développement.
H55: Les évaluations sont menées de façon indépendante et impartiale | I55: Les évaluations sont-elles menées de façon indépendante et impartiale ? | J55: OUI | K55: Calendriers des évaluations | L55: Évaluations biaisées ou non indépendantes | M55: Élevée | N55: Conflits et chevauchements de rôles par responsabilités mal définies. | O55: Cartographier précisément les rôles et responsabilités dans un référentiel accessible.
H56: Les résultats des évaluations sont enregistrées et utilisées pour apporter des améliorations dans les missions de l'organisation | I56: Les résultats des évaluations sont-ils enregistrés et utilisés pour apporter des améliorations dans les missions de l'organisation ? | J56: OUI | K56: Fiches de feedback fournies aux responsables | L56: Non-utilisation des résultats d'évaluation pour l'amélioration | M56: Élevée | N56: Incohérences opérationnelles avec une structure non alignée sur la stratégie. | O56: Réaligner l’organigramme avec la stratégie via un comité dédié.
F57: Structures, autorités et responsabilités | G57: S’assurer que la structure organisationnelle est clairement définie, incluant les rattachements hiérarchiques, les rôles, les responsabilités et les pouvoirs de chaque collaborateur. | H57: Les rôles et responsabilités de tout un chacun sont clairement définies et compris par tous | I57: Les rôles et responsabilités de tout un chacun sont-ils clairement définis et compris par tous ? | J57: OUI | K57: Rapports d’évaluation externe | L57: Rôles et responsabilités mal définis ou incompris | M57: Élevée | N57: Résistance au changement et innovation entravée par une structure trop rigide. | O57: Introduire des mécanismes d’innovation comme des hackathons ou boîtes à idées.
H58: La structure organisationnelle est alignée avec les objectifs stratégiques de l'organisation | I58: La structure organisationnelle est-elle alignée avec les objectifs stratégiques de l'organisation ? | J58: OUI | K58: Registres de résultats d’évaluations | L58: Désalignement de la structure organisationnelle avec les objectifs stratégiques | M58: Moyenne | N58: Décisions prises sur des informations partielles ou biaisées par une circulation inéquitable. | O58: Mettre en place un système de circulation de l’information équitable et transparent.
H59: La structure de l'organisation est suffisamment flexible pour s'adapter aux changements | I59: La structure de l'organisation est-elle suffisamment flexible pour s'adapter aux changements ? | J59: OUI | K59: Organigrammes avec définition des rôles | L59: Rigidité de la structure face aux changements | M59: Élevée | N59: Lenteur décisionnelle avec une structure hiérarchique trop complexe. | O59: Simplifier la structure hiérarchique pour accélérer les prises de décision.
H60: L'information circule de façon équitable dans tous les niveaux de l'organisation | I60: L'information circule-t-elle de façon équitable dans tous les niveaux de l'organisation ? | J60: OUI | K60: Documents stratégiques de structure organisationnelle | L60: Circulation inéquitable de l'information | M60: Élevée | N60: Incompétences dans des postes clés par mauvaise attribution des responsabilités. | O60: Auditer les compétences des postes clés et mettre en place des plans de succession.
H61: La structure permet une prise de décision rapide et efficace | I61: La structure permet-elle une prise de décision rapide et efficace ? | J61: OUI | K61: Rapports de révision de structure | L61: Structure entravant la prise de décision | M61: Élevée | N61: Abus de pouvoir ou favoritisme liés à des conflits d'intérêts non gérés. | O61: Instaurer une déclaration obligatoire des conflits d’intérêts et leur gestion.
G62: Vérifier que les responsabilités et laes pouvoirs sont attribués de manière appropriée, en fonction des compétences et des objectifs stratégiques de l’organisation. | H62: Les responsabilités sont attribués en fonction des compétences et de l'expérience des collaborateurs | I62: Les responsabilités sont-elles attribuées en fonction des compétences et de l'expérience des collaborateurs ? | J62: OUI | K62: Procès-verbaux de consultation des employés | L62: Attribution des responsabilités sans considération des compétences | M62: Élevée | N62: Impossibilité de vérifier les responsabilités sans documentation accessible. | O62: Centraliser la documentation des responsabilités dans un référentiel unique.
H63: Les pouvoirs sont distribués de manière équitable pour éviter les conflits d'intérêts | I63: Les pouvoirs sont-ils distribués de manière équitable pour éviter les conflits d'intérêts ? | J63: OUI | K63: Communiqués internes sur les changements | L63: Conflits d'intérêts dus à une distribution inéquitable des pouvoirs | M63: Élevée | N63: Manque de transparence et impunité potentielle par absence de redevabilité. | O63: Créer un comité d’éthique indépendant pour renforcer la redevabilité.
H64: Les attributions de responsabilités sont documentées et accessibles | I64: Les attributions de responsabilités sont-elles documentées et accessibles ? | J64: OUI | K64: Études d’impact des révisions structurelles | L64: Documentation absente ou inaccessible sur les attributions de responsabilités | M64: Élevée | N64: Inadaptation persistante des rôles face aux évolutions métier par ajustements tardifs. | O64: Mener des revues semestrielles des rôles pour s’adapter aux évolutions métier.
H65: Les responsables rendent comptes régulièrement de leurs actions et décisions | I65: Les responsables rendent-ils compte régulièrement de leurs actions et décisions ? | J65: NON | K65: Rapports de validation conseil-management | L65: Défaut de redevabilité des responsables | M65: Élevée | N65: Réactivité insuffisante aux changements marché ou réglementaires. | O65: Désigner un responsable veille pour anticiper les changements marché/réglementaires.
H66: Les attributions de responsabilités sont ajustées en fonction des évolutions de l'organisation | I66: Les attributions de responsabilités sont-elles ajustées en fonction des évolutions de l'organisation ? | J66: OUI | K66: Procès-verbaux des décisions de modification | L66: Ajustements tardifs des attributions de responsabilités | M66: Élevée | N66: Solutions inadaptées par non-consultation des employés concernés. | O66: Associer systématiquement les employés concernés dans les groupes de travail.
G67: S’assurer que la structure organisationnelle est régulièrement revue et mise à jour pour tenir compte des changements dans l’environnement interne ou externe de l’organisation. | H67: La structure est ajustée en réponse aux changements internes et externes | I67: La structure est-elle ajustée en réponse aux changements internes et externes ? | J67: OUI | K67: Études d’impact post-modification | L67: Réactivité insuffisante aux changements internes/externes | M67: Élevée | N67: Confusion et résistance au changement par modifications mal communiquées. | O67: Élaborer un plan de communication dédié pour chaque transformation structurelle.
H68: Les employés sont consultes lors des révisions de la structure organisationnelle | I68: Les employés sont-ils consultés lors des révisions de la structure organisationnelle ? | J68: OUI | K68: Preuves de communication sur les modifications | L68: Non-consultation des employés lors des révisions structurelles | M68: Élevée | N68: Perturbations opérationnelles avec des révisions structurelles mal planifiées. | O68: Planifier des phases pilotes et tests avant déploiement des réorganisations.
H69: Les modifications de la structure sont documentées et communiquées | I69: Les modifications de la structure sont-elles documentées et communiquées ? | J69: OUI | K69: Supports d'information sur la structure | L69: Modifications non documentées ou mal communiquées | M69: Élevée | N69: Désorganisation persistante après des révisions inefficaces ou incomplètes. | O69: Auditer l’efficacité des réorganisations passées pour guider les futures.
H70: Les révisions de la structure ont un impact positif et efficace sur l'organisation | I70: Les révisions de la structure ont-elles un impact positif et efficace sur l'organisation ? | J70: OUI | K70: Documents de structure en langage simplifié | L70: Impact négatif des révisions structurelles | M70: Élevée | N70: Décisions stratégiques incohérentes par manque de collaboration conseil-management. | O70: Organiser des comités conjoints direction-conseil pour alignement stratégique.
H71: La structure reste alignée avec les objectifs stratégiques de l'organisation a chaque révision | I71: La structure reste-t-elle alignée avec les objectifs stratégiques de l'organisation à chaque révision ? | J71: OUI | K71: Historique des mises à jour de structure | L71: Désalignement persistant après révisions | M71: Élevée | N71: Méfiance des équipes face à des modifications perçues comme arbitraires ou opaques. | O71: Communiquer régulièrement sur la raison d’être des changements via des FAQ.
G72: Vérifier que le management reçoit l’approbation du Conseil pour les modifications de la structure organisationnelle, afin d’assurer une supervision adéquate des changements importants | H72: Le conseil et le management collabore intimement pour valider les modifications | I72: Le conseil et le management collaborent-ils intimement pour valider les modifications ? | J72: OUI | K72: Questionnaires ou entretiens de compréhension des rôles | L72: Collaboration insuffisante conseil-management dans les modifications | M72: Élevée | N72: Changements cosmétiques sans impact réel sur l'efficacité organisationnelle. | O72: Lier les modifications structurelles à des indicateurs de performance clairs.
H73: Les décisions de modification sont prises de manière transparente | I73: Les décisions de modification sont-elles prises de manière transparente ? | J73: OUI | K73: Boîtes à idées ou plateformes de retour des employés | L73: Décisions de modification opaques | M73: Élevée | N73: Impossibilité de mesurer l'efficacité des changements sans suivi post-implantation. | O73: Mesurer l’impact des changements via des enquêtes et indicateurs post-déploiement.
H74: Les modifications approuvées ont un impact positif sur l'organisation | I74: Les modifications approuvées ont-elles un impact positif sur l'organisation ? | J74: OUI | K74: Tableaux des responsabilités hiérarchiques | L74: Modifications sans impact positif | M74: Élevée | N74: Rumours et incertitudes par communication défaillante sur les évolutions structurelles. | O74: Désigner un référent unique comme point de contact pour les questions sur les évolutions.
H75: Les effets de modifications sont évalues et suivis après leurs mises en œuvre | I75: Les effets des modifications sont-ils évalués et suivis après leur mise en œuvre ? | J75: NON | K75: Manuel d’organisation | L75: Suivi absent des effets des modifications | M75: Élevée | N75: Difficultés d'accès aux informations nécessaires pour le bon fonctionnement des équipes. | O75: Créer une bibliothèque centralisée de documents avec contrôle d’accès différencié.
H76: Les modifications sont bien communiquées à tous les niveaux de l'organisation | I76: Les modifications sont-elles bien communiquées à tous les niveaux de l'organisation ? | J76: OUI | K76: Rapports d’audit opérationnel | L76: Communication défaillante des modifications | M76: Élevée | N76: Incompréhension des processus et procédures avec un langage technique ou obscur. | O76: Former les rédacteurs à l’écriture de procédures claires et accessibles.
G77: S’assurer que des mécanismes sont en place pour communiquer la structure organisationnelle à tous les collaborateurs, afin qu'ils comprennent clairement leurs rôles et leurs responsabilités. | H77: Les informations sur la structure sont facilement accessibles à tous les employés | I77: Les informations sur la structure sont-elles facilement accessibles à tous les employés ? | J77: OUI | K77: Historique de mise à jour documentaire | L77: Accès difficile aux informations sur la structure | M77: Élevée | N77: Non-conformité réglementaire avec des documents obsolètes ou non mis à jour. | O77: Instaurer un calendrier de révision systématique des documents réglementaires.
H78: Les documents relatifs à la structure sont rédiges dans un langage clair et compréhensible | I78: Les documents relatifs à la structure sont-ils rédigés dans un langage clair et compréhensible ? | J78: OUI | K78: Registres de décisions organisationnelles | L78: Langage obscur dans les documents structurels | M78: Élevée | N78: Erreurs opérationnelles par méconnaissance des rôles et responsabilités. | O78: Développer des fiches de poste détaillées et accessibles à tous les employés.
H79: Les informations sur la structure sont régulièrement mis à jour | I79: Les informations sur la structure sont-elles régulièrement mises à jour ? | J79: OUI | K79: Politique de recrutement | L79: Documents structurels non mis à jour | M79: Élevée | N79: Frustration des employés sans mécanismes pour remonter les problèmes structurels. | O79: Mettre en place une plateforme de remontée des problèmes structurels.
H80: Les employés semblent bien comprendre leurs rôles et leurs responsabilités | I80: Les employés semblent-ils bien comprendre leurs rôles et leurs responsabilités ? | J80: OUI | K80: Grilles de sélection des candidats | L80: Incompréhension des rôles et responsabilités par les employés | M80: Élevée | N80: Imprécision dans l'exécution des tâches avec des descriptions de poste incomplètes. | O80: Standardiser les descriptions de poste selon un référentiel commun.
H81: Des mécanismes existent pour collecter les retours des employés sur la structure organisationnelle | I81: Des mécanismes existent-ils pour collecter les retours des employés sur la structure organisationnelle ? | J81: OUI | K81: Rapport de temps et efficacité de recrutement | L81: Absence de mécanismes de feedback sur la structure | M81: Élevée | N81: Inégalité d'accès aux informations nécessaires entre différents services ou niveaux hiérarchiques. | O81: Auditer régulièrement l’accès à l’information pour garantir l’équité.
G82: Vérifier que les structures, les rattachements et les responsabilités sont clairement documentés et accessibles pour consultation, garantissant une traçabilité des décisions organisationnelles. | H82: Toutes les responsabilités et rattachements hiérarchiques sont bien documentées | I82: Toutes les responsabilités et rattachements hiérarchiques sont-ils bien documentés ? | J82: OUI | K82: Politique de diversité et inclusion | L82: Documentation incomplète des responsabilités et rattachements | M82: Élevée | N82: Dissonance entre théorie et pratique avec des documents ne reflétant pas la réalité. | O82: Organiser des ateliers pour recaler les documents avec les pratiques réelles.
H83: Les documents sont facilement accessibles pour consultation par les employés | I83: Les documents sont-ils facilement accessibles pour consultation par les employés ? | J83: OUI | K83: Modèle de feedback candidat | L83: Documents inaccessibles aux employés | M83: Élevée | N83: Risques juridiques et opérationnels avec des documents non révisés régulièrement. | O83: Automatiser les alertes pour les révisions obligatoires des documents.
H84: Les documents reflètent clairement et fidèlement la réalité des opérations de l'organisation | I84: Les documents reflètent-ils clairement et fidèlement la réalité des opérations de l'organisation ? | J84: OUI | K84: Plans de formation annuels | L84: Documents ne reflétant pas la réalité opérationnelle | M84: Élevée | N84: Impossibilité de retracer l'historique décisionnel pour audit ou analyse. | O84: Implémenter un système de gestion documentaire avec historique des versions.
H85: Les documents sont régulièrement révises pour rester à jour | I85: Les documents sont-ils régulièrement révisés pour rester à jour ? | J85: PAS | K85: Calendrier de formations continues | L85: Documents non révisés régulièrement | M85: Élevée | N85: Difficulté à attirer des profils qualifiés avec un processus de recrutement inefficace. | O85: Réviser les processus de recrutement pour réduire les délais de traitement.
H86: Les décisions organisationnelles sont traçables grâce à la documentation | I86: Les décisions organisationnelles sont-elles traçables grâce à la documentation ? | J86: OUI | K86: Rapports de participation aux formations | L86: Traçabilité absente des décisions organisationnelles | M86: Élevée | N86: Subjectivité et discrimination potentielle dans les embauches avec des critères flous. | O86: Former les recruteurs sur les biais inconscients et critères objectifs.
F87: Compétences des individus | G87: S’assurer que l’organisation dispose de processus clairs et formalisés pour attirer des talents qualifiés dans les domaines nécessaires à son fonctionnement, y compris pour les systèmes d’information. | H87: Les processus de recrutement sont conçus pour attirer des candidats qualifies | I87: Les processus de recrutement sont-ils conçus pour attirer des candidats qualifiés ? | J87: OUI | K87: Indicateurs de performance post-formation | L87: Processus de recrutement inefficace pour attirer des talents | M87: Élevée | N87: Perte de talents clés vers la concurrence en raison d'un recrutement trop lent. | O87: Développer un vivier de talents et programme de marque employeur.
H88: Les critères de sélections sont clairement définis et communiques aux candidats | I88: Les critères de sélection sont-ils clairement définis et communiqués aux candidats ? | J88: OUI | K88: Supports de formation variés | L88: Critères de sélection flous ou non communiqués | M88: Élevée | N88: Manque de diversité des perspectives et d'innovation par homogénéité des recrutements. | O88: Introduire des quotas volontaires pour favoriser la diversité des recrutements.
H89: Le processus de recrutement permet de recruter rapidement et efficacement les talents | I89: Le processus de recrutement permet-il de recruter rapidement et efficacement les talents ? | J89: OUI | K89: Résultats d’enquêtes de satisfaction | L89: Lenteur ou inefficacité du recrutement | M89: Élevée | N89: Image employeur dégradée par l'absence de retours aux candidats rejetés. | O89: Automatiser les accusés de réception et retours aux candidats rejetés.
H90: Le processus de recrutement encourage la diversité et l'inclusion sociale | I90: Le processus de recrutement encourage-t-il la diversité et l'inclusion sociale ? | J90: OUI | K90: Plan de fidélisation des talents | L90: Manque de diversité et d'inclusion dans le recrutement | M90: Élevée | N90: Compétences obsolètes ou inadéquates par des formations non alignées sur les besoins. | O90: Réaliser des audits de compétences pour identifier les besoins de formation.
H91: Les candidats reçoivent des retours constructifs sur leurs candidatures | I91: Les candidats reçoivent-ils des retours constructifs sur leurs candidatures ? | J91: OUI | K91: Politique de récompense interne | L91: Absence de retours constructifs aux candidats | M91: Élevée | N91: Décrochage des standards de compétences avec des formations trop espacées. | O91: Planifier des formations courtes et fréquentes plutôt que des sessions annuelles.
G92: Vérifier que l’organisation met en place des programmes de formation continue pour ses collaborateurs, en particulier dans les domaines stratégiques comme la gestion des systèmes d'information et la cybersécurité. | H92: Les formations sont adaptées aux besoins réels des employés et de l'organisation | I92: Les formations sont-elles adaptées aux besoins réels des employés et de l'organisation ? | J92: OUI | K92: Politique d’équilibre vie pro/perso | L92: Formations inadaptées aux besoins | M92: Élevée | N92: Temps et budget formation gaspillés par participation passive sans acquis concrets. | O92: Privilégier les méthodes actives (ateliers, mises en situation) en formation.
H93: Les formations sont régulières pour maintenir le niveau global de l'entreprise a jour | I93: Les formations sont-elles régulières pour maintenir le niveau global de l'entreprise à jour ? | J93: OUI | K93: Questionnaires de satisfaction sur la fidélisation | L93: Formations irrégulières | M93: Élevée | N93: Impossibilité de justifier les investissements en formation sans mesure d'impact. | O93: Développer des indicateurs ROI pour mesurer l’impact des formations.
H94: Les employés participent activement aux formations et en tirent des bénéfices | I94: Les employés participent-ils activement aux formations et en tirent-ils des bénéfices ? | J94: OUI | K94: Grilles d’évaluation de performance | L94: Participation passive ou bénéfices non visibles des formations | M94: Élevée | N94: Démotivation des apprenants face à des méthodes pédagogiques monotones. | O94: Introduire des éléments de gamification dans les parcours de formation.
H95: L'impact des formations est mesurable sur la performance des employés | I95: L'impact des formations est-il mesurable sur la performance des employés ? | J95: OUI | K95: Calendriers des campagnes d’évaluation | L95: Impact non mesurable des formations | M95: Élevée | N95: Turnover accru des talents clés par manque de perspectives d'évolution. | O95: Proposer des plans de développement individuel avec mentorat.
H96: Les formations utilisent des méthodes variées d'apprentissage | I96: Les formations utilisent-elles des méthodes variées d'apprentissage ? | J96: OUI | K96: Fiches de feedback individuel | L96: Méthodes de formation monotones | M96: Moyenne | N96: Baisse de la performance et de l'engagement par système de reconnaissance inefficace. | O96: Instaurer un système de récompenses non financières (reconnaissance publique).
G97: S’assurer que des mécanismes de fidélisation des talents sont en place, tels que des parcours de carrière, des avantages compétitifs et des opportunités de développement personnel, pour encourager les collaborateurs à rester au sein de l’organisation. | H97: Les employés semblent satisfait des opportunités de développement disponibles | I97: Les employés semblent-ils satisfaits des opportunités de développement disponibles ? | J97: OUI | K97: Documents de communication sur les critères d’évaluation | L97: Insatisfaction des employés sur les opportunités de développement | M97: Élevée | N97: Épuisement professionnel et absentéisme par déséquilibre vie privée-travail. | O97: Promouvoir le télétravail et horaires flexibles pour l’équilibre vie pro/perso.
H98: Des mesures efficaces existent pour maintenir les talents clés | I98: Des mesures efficaces existent-elles pour maintenir les talents clés ? | J98: OUI | K98: Rapports d’exploitation des résultats d’évaluation | L98: Absence de mesures de rétention des talents clés | M98: Élevée | N98: Programmes de fidélisation inadaptés par non-prise en compte du feedback employé. | O98: Mener des enquêtes régulières pour adapter les programmes de fidélisation.
H99: Un system de récompense existe pour récompenser les employés | I99: Un système de récompense existe-t-il pour récompenser les employés ? | J99: NON | K99: Cartographie des processus RH | L99: Système de récompense absent ou inefficace | M99: Élevée | N99: Injustice perçue dans les promotions ou augmentations avec des critères subjectifs. | O99: Publier les critères et processus de promotion pour plus de transparence.
H100: Les mécanismes offrent un équilibre entre vie privée et vie professionnelle | I100: Les mécanismes offrent-ils un équilibre entre vie privée et vie professionnelle ? | J100: OUI | K100: Plan de coordination RH global | L100: Déséquilibre vie privée-professionnelle | M100: Élevée | N100: Manque d'alignement des objectifs individuels et organisationnels par évaluations rares. | O100: Organiser des entretiens semestriels pour aligner objectifs individuels/entreprise.
...

Sheet Coso
A1: Domaines | B1: Responsables | C1: Durée | D1: Moyens pour la réalisation | E1: Parties Prenantes | F1: Points de Contrôle | G1: Objectifs de Contrôle | H1: Critère d’Évaluation | I1: Question d’Évaluation | J1: Réponses | K1: Documents requis | L1: Risques | M1: Criticités | N1: conséquences | O1: Recommendations
A2: Environnement de Contrôle | F2: Engagement envers l’intégrité et les valeurs éthiques | G2: S’assurer que l'organisation dispose d'une charte éthique formelle qui couvre l'ensemble des pratiques professionnelles et des interactions au sein de l'organisation, y compris les activités liées aux systèmes d'information. | H2: La charte éthique est alignée sur les normes de rédaction légales nationales et internationales | I2: La charte éthique est-elle alignée sur les normes de rédaction légales nationales et internationales ? | J2: OUI | K2: Charte éthique de l'organisation | L2: Non-respect des normes légales nationales et internationales | M2: Élevée | N2: Non-respect des obligations légales entraînant des sanctions financières et des poursuites judiciaires. | O2: Mettre en place un système de veille régulier pour se conformer aux obligations légales et éviter les sanctions.
H3: La charte respecte les principes relatifs aux droit des employés en entreprise | I3: La charte respecte-t-elle les principes relatifs aux droits des employés en entreprise ? | J3: OUI | K3: Référentiels juridiques nationaux et internationaux utilisés | L3: Violation des droits des employés | M3: Élevée | N3: Détérioration de la réputation de l'entreprise due à des violations répétées des droits des employés. | O3: Élaborer un plan de communication proactive pour restaurer l'image de l'entreprise après des violations répétées.
H4: La charte éthique est communiquée à tous les employés | I4: La charte éthique est-elle communiquée à tous les employés ? | J4: OUI | K4: Document de conformité légale de la charte | L4: Manque de communication de la charte éthique aux employés | M4: Élevée | N4: Confusion généralisée parmi les employés sur les comportements attendus en l'absence de communication claire de la charte éthique. | O4: Diffuser une version simplifiée et accessible de la charte éthique pour clarifier les attentes envers les employés.
H5: La charte est régulièrement mise à jour et révisée | I5: La charte est-elle régulièrement mise à jour et révisée ? | J5: OUI | K5: Procédure interne de validation de la charte par les instances dirigeantes | L5: Défaut de mise à jour régulière de la charte | M5: Élevée | N5: Inadéquation des pratiques actuelles avec les nouvelles réglementations en raison du défaut de mise à jour de la charte. | O5: Actualiser annuellement la charte éthique pour garantir son alignement avec les nouvelles réglementations.
H6: La charte éthique est formalisée et approuvée par la direction de l'organisation | I6: La charte éthique est-elle formalisée et approuvée par la direction de l'organisation ? | J6: OUI | K6: Preuves de diffusion de la charte à l’ensemble des employés (emails, affiches, intranet) | L6: Absence de formalisation et d'approbation par la direction | M6: Élevée | N6: Manque de légitimité des politiques internes sans formalisation et approbation par la direction. | O6: Soumettre la charte éthique à une validation formelle par la direction pour renforcer sa légitimité.
G7: Vérifier que des mécanismes existent pour garantir que tous les acteurs (employés, partenaires, prestataires) respectent cette charte éthique dans leurs activités professionnelles, y compris dans leur utilisation des systèmes d'information | H7: Les employés et les partenaires semblent engages à respecter les règles établies dans la charte | I7: Les employés et les partenaires semblent-ils engagés à respecter les règles établies dans la charte ? | J7: OUI | K7: Historique des mises à jour de la charte | L7: Manque d'engagement des employés et partenaires | M7: Élevée | N7: Démotivation des équipes et désengagement des partenaires commerciaux. | O7: Organiser des ateliers collaboratifs pour identifier les causes de désengagement et proposer des solutions concrètes.
H8: Les employés sont régulièrement encourager à signaler les cas de non-conformité a la charte | I8: Les employés sont-ils régulièrement encouragés à signaler les cas de non-conformité à la charte ? | J8: OUI | K8: Procès-verbaux des réunions d’approbation de la charte | L8: Absence de signalement des non-conformités | M8: Élevée | N8: Persistance de comportements non éthiques par peur ou méconnaissance des canaux de signalement. | O8: Promouvoir les canaux de signalement anonymes pour encourager le reporting des comportements non éthiques.
H9: Les mécanismes de contrôle sont ajustes en fonction des retours effectues et des changements de l'organisation | I9: Les mécanismes de contrôle sont-ils ajustés en fonction des retours effectués et des changements de l'organisation ? | J9: OUI | K9: Engagements signés par les employés et partenaires | L9: Inadaptation des mécanismes de contrôle aux retours et changements | M9: Moyenne | N9: Contrôles inefficaces ne permettant pas de détecter les risques émergents. | O9: Déployer des outils de monitoring en temps réel pour détecter les risques émergents plus efficacement.
H10: Les mécanismes en place permettent de détecter et de corriger rapidement les écarts | I10: Les mécanismes en place permettent-ils de détecter et de corriger rapidement les écarts ? | J10: NON | K10: Registre ou plateforme de signalement des non-conformités | L10: Détection et correction lentes des écarts | M10: Élevée | N10: Augmentation des coûts liés à la correction tardive des problèmes identifiés. | O10: Allouer des ressources dédiées à la correction immédiate des problèmes identifiés pour réduire les coûts.
H11: Les mécanismes de contrôle ont été clairement expliques et compris par tous les employés | I11: Les mécanismes de contrôle ont-ils été clairement expliqués et compris par tous les employés ? | J11: OUI | K11: Rapports de contrôle interne avec retour d'expérience | L11: Mécanismes de contrôle mal compris par les employés | M11: Élevée | N11: Erreurs répétées des employés par méconnaissance des procédures de contrôle. | O11: Former régulièrement les employés sur les procédures de contrôle pour minimiser les erreurs opérationnelles.
G12: S’assurer que des actions de sensibilisation, telles que des formations régulières, sont mises en place pour garantir que tous les employés et intervenants comprennent et appliquent les principes éthiques dans leurs interactions avec les systèmes d'information | H12: Les formations et actes de sensibilisation sont alignées sur les besoins réels des employés | I12: Les formations et actes de sensibilisation sont-ils alignés sur les besoins réels des employés ? | J12: OUI | K12: Rapports d’audit sur les mécanismes de détection | L12: Formations non alignées sur les besoins réels | M12: Élevée | N12: Baisse de productivité due à des formations non adaptées aux besoins opérationnels. | O12: Adapter les programmes de formation en fonction des retours opérationnels pour améliorer la productivité.
H13: Les actions de sensibilisations sont organisées de façon régulière | I13: Les actions de sensibilisation sont-elles organisées de façon régulière ? | J13: OUI | K13: Documents de formation ou communication sur les mécanismes de contrôle | L13: Actions de sensibilisation irrégulières | M13: Élevée | N13: Sensibilisation insuffisante aux enjeux éthiques avec des actions ponctuelles et irrégulières. | O13: Planifier des sessions de sensibilisation trimestrielles pour maintenir une culture éthique forte.
H14: Les effets des actions de formation sont visibles et les employés actifs | I14: Les effets des actions de formation sont-ils visibles et les employés actifs ? | J14: OUI | K14: Plan de formation aligné avec les besoins des employés | L14: Effets non visibles des actions de formation | M14: Élevée | N14: Absence d'amélioration tangible des compétences malgré les investissements en formation. | O14: Évaluer l'impact des formations via des indicateurs concrets pour ajuster les investissements.
H15: Les effets des actions de formation sont mesurables | I15: Les effets des actions de formation sont-ils mesurables ? | J15: OUI | K15: Calendrier des actions de sensibilisation | L15: Impossibilité de mesurer l'impact des formations | M15: Élevée | N15: Impossibilité d'ajuster les programmes de formation sans données mesurables sur leur impact. | O15: Intégrer des méthodes pédagogiques interactives pour améliorer la rétention des connaissances.
H16: Les actions de formation utilise divers moyens (e-learning, ateliers, ...) pour toucher leurs cible | I16: Les actions de formation utilisent-elles divers moyens (e-learning, ateliers, ...) pour toucher leurs cibles ? | J16: OUI | K16: Rapports d’évaluation post-formation | L16: Méthodes de formation non diversifiées | M16: Élevée | N16: Faible rétention des connaissances avec des méthodes de formation monotones et non interactives. | O16: Développer des parcours de carrière clairs pour fidéliser les talents clés et réduire le turnover.
G17: S’assurer que l'organisation dispose d'un mécanisme de suivi et de gestion des violations éthiques, permettant de détecter, traiter et sanctionner tout comportement contraire à la charte éthique, y compris dans le cadre des activités liées aux systèmes d'information. | H17: Les violations sont rapidement traiter et détecter | I17: Les violations sont-elles rapidement traitées et détectées ? | J17: OUI | K17: Indicateurs de performance post-formation | L17: Traitement lent des violations | M17: Élevée | N17: Prolongation des situations à risque en raison d'un traitement lent des violations signalées. | O17: Mettre en place un système de reconnaissance basé sur des critères objectifs pour renforcer l'engagement.
H18: Les processus de gestions des violations sont clairs et bien communiquées | I18: Les processus de gestion des violations sont-ils clairs et bien communiqués ? | J18: OUI | K18: Supports pédagogiques variés (supports e-learning, ateliers, etc.) | L18: Processus de gestion des violations flous | M18: Élevée | N18: Injustice perçue par les employés face à des sanctions incohérentes ou disproportionnées. | O18: Proposer des solutions flexibles pour équilibrer vie professionnelle et personnelle.
H19: Les sanctions sont appliquées de manière juste et proportionnée | I19: Les sanctions sont-elles appliquées de manière juste et proportionnée ? | J19: OUI | K19: Registre des violations détectées et traitées | L19: Sanctions injustes ou disproportionnées | M19: Élevée | N19: Rétention d'informations par crainte de représailles en l'absence de confidentialité des signalements. | O19: Créer des enquêtes anonymes pour recueillir le feedback employé et ajuster les programmes RH.
H20: Les actions de signalement sont reçues et examinées de façon confidentielle pour la protection des parties concernées | I20: Les actions de signalement sont-elles reçues et examinées de façon confidentielle pour la protection des parties concernées ? | J20: OUI | K20: Procédures de gestion des violations | L20: Manque de confidentialité dans le traitement des signalements | M20: Élevée | N20: Persistance des faiblesses du système par non-prise en compte des retours d'expérience. | O20: Établir des critères transparents pour les promotions et augmentations afin d'éviter les perceptions d'injustice.
H21: Les retours d'expérience des cas de traitement des violations sont utilisées pou l'amélioration de la charte | I21: Les retours d'expérience des cas de traitement des violations sont-ils utilisés pour l'amélioration de la charte ? | J21: OUI | K21: Registre des sanctions appliquées avec justificatifs | L21: Non-utilisation des retours d'expérience pour améliorer la charte | M21: Élevée | N21: Exposition accrue aux risques opérationnels sans anticipation des violations potentielles. | O21: Aligner les objectifs individuels avec la stratégie globale via des entretiens annuels structurés.
G22: S'assurer que l'organisation dispose d'un processus de gestion et de prevention des risques lies a la securite des donnees et du systeme d'information | H22: Les risques de violation de la charte sont anticipes avant leurs matérialisation | I22: Les risques de violation de la charte sont-ils anticipés avant leur matérialisation ? | J22: OUI | K22: Politique de confidentialité liée aux signalements | L22: Non-anticipation des risques de violation de la charte | M22: Élevée | N22: Vulnérabilité aux cyberattaques par manque de formation sur la sécurité des données. | O22: Fournir des retours constructifs et réguliers pour soutenir le développement professionnel.
H23: Les employés sont formes pour reconnaitre et prévenir les risques lies a la sécurité des données | I23: Les employés sont-ils formés pour reconnaître et prévenir les risques liés à la sécurité des données ? | J23: NON | K23: Rapports d’analyse post-violation | L23: Manque de formation des employés sur la sécurité des données | M23: Élevée | N23: Impossibilité d'identifier les tendances ou causes racines sans documentation des incidents. | O23: Rendre publics les critères d'évaluation pour renforcer la transparence dans la gestion des carrières.
H24: Les incidents de sécurités sont documentées et analysées pour éviter des répétitions | I24: Les incidents de sécurité sont-ils documentés et analysés pour éviter des répétitions ? | J24: OUI | K24: Cartographie des risques | L24: Absence de documentation et d'analyse des incidents de sécurité | M24: Élevée | N24: Pertes financières importantes en cas d'incident majeur sans plan de continuité adapté. | O24: Utiliser les résultats d'évaluation pour identifier les besoins en formation et développement.
H25: L'organisation dispose d'un plan de continuité en cas de violation de sécurité | I25: L'organisation dispose-t-elle d'un plan de continuité en cas de violation de sécurité ? | J25: OUI | K25: Plan de formation en sécurité des données | L25: Défaut de plan de continuité en cas de violation de sécurité | M25: Moyenne | N25: Exposition aux menaces informatiques avec des mesures de sécurité non alignées sur la stratégie. | O25: Coordonner les initiatives de gestion des talents entre les départements pour éviter les redondances.
H26: Les mesures de sécurité des systèmes d'information respectent les objectifs stratégiques de l'organisation | I26: Les mesures de sécurité des systèmes d'information respectent-elles les objectifs stratégiques de l'organisation ? | J26: NON | K26: Rapports d’analyse des incidents de sécurité | L26: Inadéquation des mesures de sécurité avec les objectifs stratégiques | M26: Élevée | N26: Décisions biaisées en faveur des intérêts personnels du management au détriment de l'organisation. | O26: Réviser les processus RH pour les aligner sur la stratégie globale et améliorer la performance.
F27: Le Conseil fait preuve d’indépendance vis-à-vis du management. | G27: S’assurer que le Conseil est composé de membres indépendants du management, avec une structure de gouvernance claire garantissant cette indépendance. | H27: Les membres du conseil sont libres de toute influencent venant du management | I27: Les membres du conseil sont-ils libres de toute influence venant du management ? | J27: OUI | K27: Plan de continuité d’activité | L27: Influence du management sur les membres du conseil | M27: Élevée | N27: Surveillance inefficace des opérations par manque de compétences du conseil. | O27: Adopter une approche agile pour adapter rapidement les processus aux changements du marché.
H28: Les membres du conseil disposent de compétences de supervision efficaces dans leurs rôle | I28: Les membres du conseil disposent-ils de compétences de supervision efficaces dans leur rôle ? | J28: OUI | K28: Politique de sécurité des systèmes d’information | L28: Manque de compétences de supervision des membres du conseil | M28: Élevée | N28: Méfiance des parties prenantes face à des décisions perçues comme opaques ou arbitraires. | O28: Mettre en place des boîtes à suggestions anonymes pour encourager les feedbacks constructifs.
H29: les décisions du conseil sont prises de manière transparente | I29: Les décisions du conseil sont-elles prises de manière transparente ? | J29: OUI | K29: Charte de gouvernance précisant l’indépendance du conseil | L29: Opacité dans les décisions du conseil | M29: Moyenne | N29: Désalignement stratégique dû à une faible implication du conseil dans les orientations clés. | O29: Définir clairement les rôles et responsabilités dans des documents accessibles à tous.
H30: Les membres du conseil sont activement impliques lors des prises de décision stratégiques | I30: Les membres du conseil sont-ils activement impliqués lors des prises de décision stratégiques ? | J30: OUI | K30: CV ou profils des membres du conseil démontrant leurs compétences | L30: Faible implication des membres du conseil dans les décisions stratégiques | M30: Élevée | N30: Stagnation des performances sans évaluation régulière et constructive du conseil. | O30: Documenter toutes les attributions et décisions pour faciliter les audits et vérifications.
H31: Les performances du conseil sont régulièrement évaluées pour vérifier leurs efficacité | I31: Les performances du conseil sont-elles régulièrement évaluées pour vérifier leur efficacité ? | J31: OUI | K31: Procès-verbaux des décisions du conseil | L31: Absence d'évaluation régulière des performances du conseil | M31: Élevée | N31: Prise de décision à l'aveugle par manque d'accès aux informations critiques. | O31: Déployer un portail centralisé d’accès aux données critiques pour faciliter la prise de décision éclairée.
G32: Vérifier que le Conseil dispose des ressources et des informations nécessaires pour surveiller efficacement la mise en place et le bon fonctionnement du dispositif de contrôle interne | H32: Le conseil a un accès sur toutes les informations de l'organisation pour augmenter la justesse de leurs décisions | I32: Le conseil a-t-il accès à toutes les informations de l'organisation pour augmenter la justesse de ses décisions ? | J32: OUI | K32: Documents de participation active aux réunions stratégiques | L32: Accès limité du conseil aux informations de l'organisation | M32: Élevée | N32: Fonctionnement inefficace du conseil par manque de soutien logistique et technique. | O32: Renforcer les moyens logistiques et techniques du conseil pour optimiser son fonctionnement.
H33: Le conseil dispose de soutien administratif et techniques en cas de nécessité | I33: Le conseil dispose-t-il de soutien administratif et technique en cas de nécessité ? | J33: OUI | K33: Rapports d’évaluation du conseil | L33: Manque de soutien administratif et technique pour le conseil | M33: Élevée | N33: Compétences obsolètes des membres du conseil sans formation continue adaptée. | O33: Instaurer un programme obligatoire de formation continue pour les membres du conseil.
H34: Les membres du conseil sont régulièrement formes pour rester à jour sur les tendances actuelles | I34: Les membres du conseil sont-ils régulièrement formés pour rester à jour sur les tendances actuelles ? | J34: NON | K34: Documents d’accès à l’information par le conseil | L34: Défaut de formation continue des membres du conseil | M34: Élevée | N34: Silos organisationnels et inefficacités opérationnelles par manque de collaboration. | O34: Promouvoir des réunions transversales et outils collaboratifs pour briser les silos.
H35: Le conseil collabore activement avec les autres entités de l'organisation | I35: Le conseil collabore-t-il activement avec les autres entités de l'organisation ? | J35: OUI | K35: Liste des soutiens administratifs et techniques attribués au conseil | L35: Collaboration insuffisante du conseil avec les autres entités | M35: Élevée | N35: Contrôle insuffisant des activités clés avec un budget inadapté aux missions du conseil. | O35: Réviser le budget alloué au conseil pour mieux couvrir ses missions essentielles.
H36: Le conseil dispose d'un budget suffisant pour ses missions | I36: Le conseil dispose-t-il d'un budget suffisant pour ses missions ? | J36: OUI | K36: Planning des formations continues des membres du conseil | L36: Budget insuffisant pour les missions du conseil | M36: Élevée | N36: Décisions tardives ou inopportunes en raison de retards dans la production des rapports. | O36: Automatiser la génération de rapports pour accélérer leur production et diffusion.
G37: S’assurer que le Conseil reçoit régulièrement des rapports détaillés sur l’efficacité du dispositif de contrôle interne et qu'il est impliqué dans l’évaluation des résultats des audits internes | H37: Des rapports sont fournis régulièrement et en temps opportun | I37: Des rapports sont-ils fournis régulièrement et en temps opportun ? | J37: OUI | K37: Preuves de collaboration entre conseil et autres entités | L37: Retards ou irrégularité dans la production des rapports | M37: Élevée | N37: Impossibilité d'analyser finement les risques avec des rapports superficiels ou incomplets. | O37: Standardiser les modèles de rapports avec des indicateurs clés pour une analyse approfondie.
H38: Les rapports contient toutes les informations nécessaires de façon très détaille | I38: Les rapports contiennent-ils toutes les informations nécessaires de façon très détaillée ? | J38: OUI | K38: Budget du conseil | L38: Manque de détails dans les rapports fournis | M38: Élevée | N38: Frustration des parties prenantes recevant des rapports inadaptés à leurs besoins. | O38: Personnaliser les rapports en fonction des besoins spécifiques de chaque partie prenante.
H39: Les rapports fournis sont toujours adaptes aux besoins du conseil | I39: Les rapports fournis sont-ils toujours adaptés aux besoins du conseil ? | J39: OUI | K39: Calendrier des rapports fournis | L39: Inadéquation des rapports aux besoins du conseil | M39: Moyenne | N39: Perte de confiance dans la gouvernance avec des rapports ne reflétant pas la réalité. | O39: Mettre en place un audit indépendant pour vérifier l’exactitude des rapports.
H40: Les rapports respectent fidèlement la réalité des missions | I40: Les rapports respectent-ils fidèlement la réalité des missions ? | J40: OUI | K40: Contenu détaillé des rapports | L40: Défaut de fidélité des rapports à la réalité | M40: Élevée | N40: Opportunités d'amélioration manquées par non-utilisation des rapports pour des corrections. | O40: Utiliser les rapports comme base pour des revues d’amélioration continue.
H41: Le conseil utilise les rapports pour prendre des mesures correctives si nécessaire | I41: Le conseil utilise-t-il les rapports pour prendre des mesures correctives si nécessaire ? | J41: OUI | K41: Études des besoins informationnels du conseil | L41: Non-utilisation des rapports pour des mesures correctives | M41: Moyenne | N41: Exposition accrue aux risques par désalignement entre contrôles et stratégie globale. | O41: Alignez les contrôles internes avec la stratégie globale via des ateliers de cadrage.
G42: Vérifier que le Conseil joue un rôle actif dans la définition des objectifs et des critères de performance du contrôle interne, et qu’il veille à leur alignement avec les objectifs stratégiques de l’organisation. | H42: Les objectifs de contrôle internes sont en harmonise avec les objectifs stratégiques de l'organisation | I42: Les objectifs de contrôle internes sont-ils en harmonie avec les objectifs stratégiques de l'organisation ? | J42: OUI | K42: Rapports d’activité fidèles aux missions | L42: Désalignement des objectifs de contrôle avec les objectifs stratégiques | M42: Élevée | N42: Objectifs contradictoires ou redondants par manque de participation du conseil à leur définition. | O42: Impliquer systématiquement le conseil dans la définition des objectifs stratégiques.
H43: Le conseil participe activement à la définition des critères de performances | I43: Le conseil participe-t-il activement à la définition des critères de performance ? | J43: OUI | K43: Preuves d’utilisation des rapports pour mesures correctives | L43: Faible participation du conseil à la définition des critères de performance | M43: Élevée | N43: Confusion des équipes sur les priorités avec des critères de performance flous. | O43: Définir des critères de performance SMART et les communiquer clairement aux équipes.
H44: Les objectifs et critères sont claires et communiques dans toute l'organisation | I44: Les objectifs et critères sont-ils clairs et communiqués dans toute l'organisation ? | J44: OUI | K44: Tableaux de correspondance entre objectifs internes et stratégie | L44: Critères de performance flous ou mal communiqués | M44: Élevée | N44: Dérive des projets sans suivi régulier des indicateurs clés. | O44: Suivre les indicateurs clés via des tableaux de bord en temps réel.
H45: Le conseil suit la progression vers leurs objectifs qui ont été fixes de manière régulière | I45: Le conseil suit-il la progression vers ses objectifs de manière régulière ? | J45: OUI | K45: Procès-verbaux de réunions de définition des critères de performance | L45: Suivi irrégulier de la progression vers les objectifs | M45: Élevée | N45: Rigidité organisationnelle face aux changements avec des objectifs non révisés. | O45: Réviser trimestriellement les objectifs pour s’adapter aux changements.
H46: Les objectifs sont modifiés en cas de changements interne ou externes | I46: Les objectifs sont-ils modifiés en cas de changements internes ou externes ? | J46: OUI | K46: Documents de communication des objectifs | L46: Inflexibilité des objectifs face aux changements | M46: Élevée | N46: Aggravation des problèmes opérationnels par réaction tardive du conseil. | O46: Instaurer des points d’étape mensuels pour anticiper les problèmes opérationnels.
G47: S’assurer que le Conseil prend des mesures appropriées lorsque des dysfonctionnements ou des lacunes dans le contrôle interne sont identifiés, y compris la mise en place de plans d’action correctifs. | H47: Le conseil est rapide dans ses réactions en cas de dysfonctionnement signales | I47: Le conseil est-il rapide dans ses réactions en cas de dysfonctionnement signalé ? | J47: PAS | K47: Rapports de suivi des objectifs | L47: Lenteur du conseil à réagir aux dysfonctionnements | M47: Élevée | N47: Solutions inefficaces ou temporaires avec une mise en œuvre laxiste des corrections. | O47: Élaborer des plans d’action correctifs avec des responsables désignés et des échéances.
H48: Les mesures correctives sont mises en œuvres de façon rigoureuse | I48: Les mesures correctives sont-elles mises en œuvre de façon rigoureuse ? | J48: OUI | K48: Documents de mise à jour des objectifs | L48: Mise en œuvre laxiste des mesures correctives | M48: Élevée | N48: Manque de transparence et difficulté à auditer les actions du conseil sans documentation. | O48: Documenter systématiquement les décisions et actions du conseil pour traçabilité.
H49: Les actions du conseil sont documentées et communiquées aux parties prenantes | I49: Les actions du conseil sont-elles documentées et communiquées aux parties prenantes ? | J49: OUI | K49: Alertes ou compte-rendus de dysfonctionnements traités | L49: Défaut de documentation et de communication des actions du conseil | M49: Élevée | N49: Récurrence des problèmes par absence de solutions durables et systémiques. | O49: Mener des analyses post-projet pour identifier les causes racines des échecs.
H50: Les mesures prises résolvent les problèmes de façon durable | I50: Les mesures prises résolvent-elles les problèmes de façon durable ? | J50: OUI | K50: Preuves de mise en œuvre des mesures correctives | L50: Solutions non durables aux problèmes identifiés | M50: Élevée | N50: Répétition des mêmes erreurs par non-analyse des dysfonctionnements passés. | O50: Créer une base de connaissances des incidents passés pour éviter leur répétition.
H51: Le conseil tire des leçons des dysfonctionnement pour s'améliorer | I51: Le conseil tire-t-il des leçons des dysfonctionnements pour s'améliorer ? | J51: OUI | K51: Rapports de communication aux parties prenantes | L51: Non-apprentissage des dysfonctionnements passés | M51: Élevée | N51: Subjectivité dans l'appréciation des performances avec des critères d'évaluation imprécis. | O51: Définir des grilles d’évaluation objectives et les appliquer uniformément.
G52: Vérifier que le Conseil évalue régulièrement la performance des responsables du contrôle interne et veille à ce que leurs actions soient indépendantes et objectives. | H52: Les évaluations sont basées sur des critères clairs et précis | I52: Les évaluations sont-elles basées sur des critères clairs et précis ? | J52: OUI | K52: Études d’impact des mesures prises | L52: Critères d'évaluation flous ou imprécis | M52: Élevée | N52: Démotivation des équipes par manque de reconnaissance ou feedback constructif. | O52: Instaurer un système de reconnaissance formalisé basé sur les résultats.
H53: Les évaluations sont réalisées régulièrement pour une amélioration continue de l'organisation | I53: Les évaluations sont-elles réalisées régulièrement pour une amélioration continue de l'organisation ? | J53: OUI | K53: Analyse post-dysfonctionnement | L53: Évaluations irrégulières ou absentes | M53: Élevée | N53: Décisions managériales biaisées par des évaluations non objectives ou indépendantes. | O53: Externaliser les évaluations critiques pour garantir leur objectivité.
H54: Les responsables reçoivent des retours constructifs pour l'amélioration des performances | I54: Les responsables reçoivent-ils des retours constructifs pour l'amélioration des performances ? | J54: OUI | K54: Grilles d’évaluation utilisées | L54: Retours non constructifs aux responsables | M54: Élevée | N54: Gaspillage des ressources sans utilisation des résultats d'évaluation pour progresser. | O54: Utiliser les résultats d’évaluation pour piloter les plans de développement.
H55: Les évaluations sont menées de façon indépendante et impartiale | I55: Les évaluations sont-elles menées de façon indépendante et impartiale ? | J55: OUI | K55: Calendriers des évaluations | L55: Évaluations biaisées ou non indépendantes | M55: Élevée | N55: Conflits et chevauchements de rôles par responsabilités mal définies. | O55: Cartographier précisément les rôles et responsabilités dans un référentiel accessible.
H56: Les résultats des évaluations sont enregistrées et utilisées pour apporter des améliorations dans les missions de l'organisation | I56: Les résultats des évaluations sont-ils enregistrés et utilisés pour apporter des améliorations dans les missions de l'organisation ? | J56: OUI | K56: Fiches de feedback fournies aux responsables | L56: Non-utilisation des résultats d'évaluation pour l'amélioration | M56: Élevée | N56: Incohérences opérationnelles avec une structure non alignée sur la stratégie. | O56: Réaligner l’organigramme avec la stratégie via un comité dédié.
F57: Structures, autorités et responsabilités | G57: S’assurer que la structure organisationnelle est clairement définie, incluant les rattachements hiérarchiques, les rôles, les responsabilités et les pouvoirs de chaque collaborateur. | H57: Les rôles et responsabilités de tout un chacun sont clairement définies et compris par tous | I57: Les rôles et responsabilités de tout un chacun sont-ils clairement définis et compris par tous ? | J57: OUI | K57: Rapports d’évaluation externe | L57: Rôles et responsabilités mal définis ou incompris | M57: Élevée | N57: Résistance au changement et innovation entravée par une structure trop rigide. | O57: Introduire des mécanismes d’innovation comme des hackathons ou boîtes à idées.
H58: La structure organisationnelle est alignée avec les objectifs stratégiques de l'organisation | I58: La structure organisationnelle est-elle alignée avec les objectifs stratégiques de l'organisation ? | J58: OUI | K58: Registres de résultats d’évaluations | L58: Désalignement de la structure organisationnelle avec les objectifs stratégiques | M58: Moyenne | N58: Décisions prises sur des informations partielles ou biaisées par une circulation inéquitable. | O58: Mettre en place un système de circulation de l’information équitable et transparent.
H59: La structure de l'organisation est suffisamment flexible pour s'adapter aux changements | I59: La structure de l'organisation est-elle suffisamment flexible pour s'adapter aux changements ? | J59: OUI | K59: Organigrammes avec définition des rôles | L59: Rigidité de la structure face aux changements | M59: Élevée | N59: Lenteur décisionnelle avec une structure hiérarchique trop complexe. | O59: Simplifier la structure hiérarchique pour accélérer les prises de décision.
H60: L'information circule de façon équitable dans tous les niveaux de l'organisation | I60: L'information circule-t-elle de façon équitable dans tous les niveaux de l'organisation ? | J60: OUI | K60: Documents stratégiques de structure organisationnelle | L60: Circulation inéquitable de l'information | M60: Élevée | N60: Incompétences dans des postes clés par mauvaise attribution des responsabilités. | O60: Auditer les compétences des postes clés et mettre en place des plans de succession.
H61: La structure permet une prise de décision rapide et efficace | I61: La structure permet-elle une prise de décision rapide et efficace ? | J61: OUI | K61: Rapports de révision de structure | L61: Structure entravant la prise de décision | M61: Élevée | N61: Abus de pouvoir ou favoritisme liés à des conflits d'intérêts non gérés. | O61: Instaurer une déclaration obligatoire des conflits d’intérêts et leur gestion.
G62: Vérifier que les responsabilités et laes pouvoirs sont attribués de manière appropriée, en fonction des compétences et des objectifs stratégiques de l’organisation. | H62: Les responsabilités sont attribués en fonction des compétences et de l'expérience des collaborateurs | I62: Les responsabilités sont-elles attribuées en fonction des compétences et de l'expérience des collaborateurs ? | J62: OUI | K62: Procès-verbaux de consultation des employés | L62: Attribution des responsabilités sans considération des compétences | M62: Élevée | N62: Impossibilité de vérifier les responsabilités sans documentation accessible. | O62: Centraliser la documentation des responsabilités dans un référentiel unique.
H63: Les pouvoirs sont distribués de manière équitable pour éviter les conflits d'intérêts | I63: Les pouvoirs sont-ils distribués de manière équitable pour éviter les conflits d'intérêts ? | J63: OUI | K63: Communiqués internes sur les changements | L63: Conflits d'intérêts dus à une distribution inéquitable des pouvoirs | M63: Élevée | N63: Manque de transparence et impunité potentielle par absence de redevabilité. | O63: Créer un comité d’éthique indépendant pour renforcer la redevabilité.
H64: Les attributions de responsabilités sont documentées et accessibles | I64: Les attributions de responsabilités sont-elles documentées et accessibles ? | J64: OUI | K64: Études d’impact des révisions structurelles | L64: Documentation absente ou inaccessible sur les attributions de responsabilités | M64: Élevée | N64: Inadaptation persistante des rôles face aux évolutions métier par ajustements tardifs. | O64: Mener des revues semestrielles des rôles pour s’adapter aux évolutions métier.
H65: Les responsables rendent comptes régulièrement de leurs actions et décisions | I65: Les responsables rendent-ils compte régulièrement de leurs actions et décisions ? | J65: NON | K65: Rapports de validation conseil-management | L65: Défaut de redevabilité des responsables | M65: Élevée | N65: Réactivité insuffisante aux changements marché ou réglementaires. | O65: Désigner un responsable veille pour anticiper les changements marché/réglementaires.
H66: Les attributions de responsabilités sont ajustées en fonction des évolutions de l'organisation | I66: Les attributions de responsabilités sont-elles ajustées en fonction des évolutions de l'organisation ? | J66: OUI | K66: Procès-verbaux des décisions de modification | L66: Ajustements tardifs des attributions de responsabilités | M66: Élevée | N66: Solutions inadaptées par non-consultation des employés concernés. | O66: Associer systématiquement les employés concernés dans les groupes de travail.
G67: S’assurer que la structure organisationnelle est régulièrement revue et mise à jour pour tenir compte des changements dans l’environnement interne ou externe de l’organisation. | H67: La structure est ajustée en réponse aux changements internes et externes | I67: La structure est-elle ajustée en réponse aux changements internes et externes ? | J67: OUI | K67: Études d’impact post-modification | L67: Réactivité insuffisante aux changements internes/externes | M67: Élevée | N67: Confusion et résistance au changement par modifications mal communiquées. | O67: Élaborer un plan de communication dédié pour chaque transformation structurelle.
H68: Les employés sont consultes lors des révisions de la structure organisationnelle | I68: Les employés sont-ils consultés lors des révisions de la structure organisationnelle ? | J68: OUI | K68: Preuves de communication sur les modifications | L68: Non-consultation des employés lors des révisions structurelles | M68: Élevée | N68: Perturbations opérationnelles avec des révisions structurelles mal planifiées. | O68: Planifier des phases pilotes et tests avant déploiement des réorganisations.
H69: Les modifications de la structure sont documentées et communiquées | I69: Les modifications de la structure sont-elles documentées et communiquées ? | J69: OUI | K69: Supports d'information sur la structure | L69: Modifications non documentées ou mal communiquées | M69: Élevée | N69: Désorganisation persistante après des révisions inefficaces ou incomplètes. | O69: Auditer l’efficacité des réorganisations passées pour guider les futures.
H70: Les révisions de la structure ont un impact positif et efficace sur l'organisation | I70: Les révisions de la structure ont-elles un impact positif et efficace sur l'organisation ? | J70: OUI | K70: Documents de structure en langage simplifié | L70: Impact négatif des révisions structurelles | M70: Élevée | N70: Décisions stratégiques incohérentes par manque de collaboration conseil-management. | O70: Organiser des comités conjoints direction-conseil pour alignement stratégique.
H71: La structure reste alignée avec les objectifs stratégiques de l'organisation a chaque révision | I71: La structure reste-t-elle alignée avec les objectifs stratégiques de l'organisation à chaque révision ? | J71: OUI | K71: Historique des mises à jour de structure | L71: Désalignement persistant après révisions | M71: Élevée | N71: Méfiance des équipes face à des modifications perçues comme arbitraires ou opaques. | O71: Communiquer régulièrement sur la raison d’être des changements via des FAQ.
G72: Vérifier que le management reçoit l’approbation du Conseil pour les modifications de la structure organisationnelle, afin d’assurer une supervision adéquate des changements importants | H72: Le conseil et le management collabore intimement pour valider les modifications | I72: Le conseil et le management collaborent-ils intimement pour valider les modifications ? | J72: OUI | K72: Questionnaires ou entretiens de compréhension des rôles | L72: Collaboration insuffisante conseil-management dans les modifications | M72: Élevée | N72: Changements cosmétiques sans impact réel sur l'efficacité organisationnelle. | O72: Lier les modifications structurelles à des indicateurs de performance clairs.
H73: Les décisions de modification sont prises de manière transparente | I73: Les décisions de modification sont-elles prises de manière transparente ? | J73: OUI | K73: Boîtes à idées ou plateformes de retour des employés | L73: Décisions de modification opaques | M73: Élevée | N73: Impossibilité de mesurer l'efficacité des changements sans suivi post-implantation. | O73: Mesurer l’impact des changements via des enquêtes et indicateurs post-déploiement.
H74: Les modifications approuvées ont un impact positif sur l'organisation | I74: Les modifications approuvées ont-elles un impact positif sur l'organisation ? | J74: OUI | K74: Tableaux des responsabilités hiérarchiques | L74: Modifications sans impact positif | M74: Élevée | N74: Rumours et incertitudes par communication défaillante sur les évolutions structurelles. | O74: Désigner un référent unique comme point de contact pour les questions sur les évolutions.
H75: Les effets de modifications sont évalues et suivis après leurs mises en œuvre | I75: Les effets des modifications sont-ils évalués et suivis après leur mise en œuvre ? | J75: NON | K75: Manuel d’organisation | L75: Suivi absent des effets des modifications | M75: Élevée | N75: Difficultés d'accès aux informations nécessaires pour le bon fonctionnement des équipes. | O75: Créer une bibliothèque centralisée de documents avec contrôle d’accès différencié.
H76: Les modifications sont bien communiquées à tous les niveaux de l'organisation | I76: Les modifications sont-elles bien communiquées à tous les niveaux de l'organisation ? | J76: OUI | K76: Rapports d’audit opérationnel | L76: Communication défaillante des modifications | M76: Élevée | N76: Incompréhension des processus et procédures avec un langage technique ou obscur. | O76: Former les rédacteurs à l’écriture de procédures claires et accessibles.
G77: S’assurer que des mécanismes sont en place pour communiquer la structure organisationnelle à tous les collaborateurs, afin qu'ils comprennent clairement leurs rôles et leurs responsabilités. | H77: Les informations sur la structure sont facilement accessibles à tous les employés | I77: Les informations sur la structure sont-elles facilement accessibles à tous les employés ? | J77: OUI | K77: Historique de mise à jour documentaire | L77: Accès difficile aux informations sur la structure | M77: Élevée | N77: Non-conformité réglementaire avec des documents obsolètes ou non mis à jour. | O77: Instaurer un calendrier de révision systématique des documents réglementaires.
H78: Les documents relatifs à la structure sont rédiges dans un langage clair et compréhensible | I78: Les documents relatifs à la structure sont-ils rédigés dans un langage clair et compréhensible ? | J78: OUI | K78: Registres de décisions organisationnelles | L78: Langage obscur dans les documents structurels | M78: Élevée | N78: Erreurs opérationnelles par méconnaissance des rôles et responsabilités. | O78: Développer des fiches de poste détaillées et accessibles à tous les employés.
H79: Les informations sur la structure sont régulièrement mis à jour | I79: Les informations sur la structure sont-elles régulièrement mises à jour ? | J79: OUI | K79: Politique de recrutement | L79: Documents structurels non mis à jour | M79: Élevée | N79: Frustration des employés sans mécanismes pour remonter les problèmes structurels. | O79: Mettre en place une plateforme de remontée des problèmes structurels.
H80: Les employés semblent bien comprendre leurs rôles et leurs responsabilités | I80: Les employés semblent-ils bien comprendre leurs rôles et leurs responsabilités ? | J80: OUI | K80: Grilles de sélection des candidats | L80: Incompréhension des rôles et responsabilités par les employés | M80: Élevée | N80: Imprécision dans l'exécution des tâches avec des descriptions de poste incomplètes. | O80: Standardiser les descriptions de poste selon un référentiel commun.
H81: Des mécanismes existent pour collecter les retours des employés sur la structure organisationnelle | I81: Des mécanismes existent-ils pour collecter les retours des employés sur la structure organisationnelle ? | J81: OUI | K81: Rapport de temps et efficacité de recrutement | L81: Absence de mécanismes de feedback sur la structure | M81: Élevée | N81: Inégalité d'accès aux informations nécessaires entre différents services ou niveaux hiérarchiques. | O81: Auditer régulièrement l’accès à l’information pour garantir l’équité.
G82: Vérifier que les structures, les rattachements et les responsabilités sont clairement documentés et accessibles pour consultation, garantissant une traçabilité des décisions organisationnelles. | H82: Toutes les responsabilités et rattachements hiérarchiques sont bien documentées | I82: Toutes les responsabilités et rattachements hiérarchiques sont-ils bien documentés ? | J82: OUI | K82: Politique de diversité et inclusion | L82: Documentation incomplète des responsabilités et rattachements | M82: Élevée | N82: Dissonance entre théorie et pratique avec des documents ne reflétant pas la réalité. | O82: Organiser des ateliers pour recaler les documents avec les pratiques réelles.
H83: Les documents sont facilement accessibles pour consultation par les employés | I83: Les documents sont-ils facilement accessibles pour consultation par les employés ? | J83: OUI | K83: Modèle de feedback candidat | L83: Documents inaccessibles aux employés | M83: Élevée | N83: Risques juridiques et opérationnels avec des documents non révisés régulièrement. | O83: Automatiser les alertes pour les révisions obligatoires des documents.
H84: Les documents reflètent clairement et fidèlement la réalité des opérations de l'organisation | I84: Les documents reflètent-ils clairement et fidèlement la réalité des opérations de l'organisation ? | J84: OUI | K84: Plans de formation annuels | L84: Documents ne reflétant pas la réalité opérationnelle | M84: Élevée | N84: Impossibilité de retracer l'historique décisionnel pour audit ou analyse. | O84: Implémenter un système de gestion documentaire avec historique des versions.
H85: Les documents sont régulièrement révises pour rester à jour | I85: Les documents sont-ils régulièrement révisés pour rester à jour ? | J85: PAS | K85: Calendrier de formations continues | L85: Documents non révisés régulièrement | M85: Élevée | N85: Difficulté à attirer des profils qualifiés avec un processus de recrutement inefficace. | O85: Réviser les processus de recrutement pour réduire les délais de traitement.
H86: Les décisions organisationnelles sont traçables grâce à la documentation | I86: Les décisions organisationnelles sont-elles traçables grâce à la documentation ? | J86: OUI | K86: Rapports de participation aux formations | L86: Traçabilité absente des décisions organisationnelles | M86: Élevée | N86: Subjectivité et discrimination potentielle dans les embauches avec des critères flous. | O86: Former les recruteurs sur les biais inconscients et critères objectifs.
F87: Compétences des individus | G87: S’assurer que l’organisation dispose de processus clairs et formalisés pour attirer des talents qualifiés dans les domaines nécessaires à son fonctionnement, y compris pour les systèmes d’information. | H87: Les processus de recrutement sont conçus pour attirer des candidats qualifies | I87: Les processus de recrutement sont-ils conçus pour attirer des candidats qualifiés ? | J87: OUI | K87: Indicateurs de performance post-formation | L87: Processus de recrutement inefficace pour attirer des talents | M87: Élevée | N87: Perte de talents clés vers la concurrence en raison d'un recrutement trop lent. | O87: Développer un vivier de talents et programme de marque employeur.
H88: Les critères de sélections sont clairement définis et communiques aux candidats | I88: Les critères de sélection sont-ils clairement définis et communiqués aux candidats ? | J88: OUI | K88: Supports de formation variés | L88: Critères de sélection flous ou non communiqués | M88: Élevée | N88: Manque de diversité des perspectives et d'innovation par homogénéité des recrutements. | O88: Introduire des quotas volontaires pour favoriser la diversité des recrutements.
H89: Le processus de recrutement permet de recruter rapidement et efficacement les talents | I89: Le processus de recrutement permet-il de recruter rapidement et efficacement les talents ? | J89: OUI | K89: Résultats d’enquêtes de satisfaction | L89: Lenteur ou inefficacité du recrutement | M89: Élevée | N89: Image employeur dégradée par l'absence de retours aux candidats rejetés. | O89: Automatiser les accusés de réception et retours aux candidats rejetés.
H90: Le processus de recrutement encourage la diversité et l'inclusion sociale | I90: Le processus de recrutement encourage-t-il la diversité et l'inclusion sociale ? | J90: OUI | K90: Plan de fidélisation des talents | L90: Manque de diversité et d'inclusion dans le recrutement | M90: Élevée | N90: Compétences obsolètes ou inadéquates par des formations non alignées sur les besoins. | O90: Réaliser des audits de compétences pour identifier les besoins de formation.
H91: Les candidats reçoivent des retours constructifs sur leurs candidatures | I91: Les candidats reçoivent-ils des retours constructifs sur leurs candidatures ? | J91: OUI | K91: Politique de récompense interne | L91: Absence de retours constructifs aux candidats | M91: Élevée | N91: Décrochage des standards de compétences avec des formations trop espacées. | O91: Planifier des formations courtes et fréquentes plutôt que des sessions annuelles.
G92: Vérifier que l’organisation met en place des programmes de formation continue pour ses collaborateurs, en particulier dans les domaines stratégiques comme la gestion des systèmes d'information et la cybersécurité. | H92: Les formations sont adaptées aux besoins réels des employés et de l'organisation | I92: Les formations sont-elles adaptées aux besoins réels des employés et de l'organisation ? | J92: OUI | K92: Politique d’équilibre vie pro/perso | L92: Formations inadaptées aux besoins | M92: Élevée | N92: Temps et budget formation gaspillés par participation passive sans acquis concrets. | O92: Privilégier les méthodes actives (ateliers, mises en situation) en formation.
H93: Les formations sont régulières pour maintenir le niveau global de l'entreprise a jour | I93: Les formations sont-elles régulières pour maintenir le niveau global de l'entreprise à jour ? | J93: OUI | K93: Questionnaires de satisfaction sur la fidélisation | L93: Formations irrégulières | M93: Élevée | N93: Impossibilité de justifier les investissements en formation sans mesure d'impact. | O93: Développer des indicateurs ROI pour mesurer l’impact des formations.
H94: Les employés participent activement aux formations et en tirent des bénéfices | I94: Les employés participent-ils activement aux formations et en tirent-ils des bénéfices ? | J94: OUI | K94: Grilles d’évaluation de performance | L94: Participation passive ou bénéfices non visibles des formations | M94: Élevée | N94: Démotivation des apprenants face à des méthodes pédagogiques monotones. | O94: Introduire des éléments de gamification dans les parcours de formation.
H95: L'impact des formations est mesurable sur la performance des employés | I95: L'impact des formations est-il mesurable sur la performance des employés ? | J95: OUI | K95: Calendriers des campagnes d’évaluation | L95: Impact non mesurable des formations | M95: Élevée | N95: Turnover accru des talents clés par manque de perspectives d'évolution. | O95: Proposer des plans de développement individuel avec mentorat.
H96: Les formations utilisent des méthodes variées d'apprentissage | I96: Les formations utilisent-elles des méthodes variées d'apprentissage ? | J96: OUI | K96: Fiches de feedback individuel | L96: Méthodes de formation monotones | M96: Moyenne | N96: Baisse de la performance et de l'engagement par système de reconnaissance inefficace. | O96: Instaurer un système de récompenses non financières (reconnaissance publique).
G97: S’assurer que des mécanismes de fidélisation des talents sont en place, tels que des parcours de carrière, des avantages compétitifs et des opportunités de développement personnel, pour encourager les collaborateurs à rester au sein de l’organisation. | H97: Les employés semblent satisfait des opportunités de développement disponibles | I97: Les employés semblent-ils satisfaits des opportunités de développement disponibles ? | J97: OUI | K97: Documents de communication sur les critères d’évaluation | L97: Insatisfaction des employés sur les opportunités de développement | M97: Élevée | N97: Épuisement professionnel et absentéisme par déséquilibre vie privée-travail. | O97: Promouvoir le télétravail et horaires flexibles pour l’équilibre vie pro/perso.
H98: Des mesures efficaces existent pour maintenir les talents clés | I98: Des mesures efficaces existent-elles pour maintenir les talents clés ? | J98: OUI | K98: Rapports d’exploitation des résultats d’évaluation | L98: Absence de mesures de rétention des talents clés | M98: Élevée | N98: Programmes de fidélisation inadaptés par non-prise en compte du feedback employé. | O98: Mener des enquêtes régulières pour adapter les programmes de fidélisation.
H99: Un system de récompense existe pour récompenser les employés | I99: Un système de récompense existe-t-il pour récompenser les employés ? | J99: NON | K99: Cartographie des processus RH | L99: Système de récompense absent ou inefficace | M99: Élevée | N99: Injustice perçue dans les promotions ou augmentations avec des critères subjectifs. | O99: Publier les critères et processus de promotion pour plus de transparence.
H100: Les mécanismes offrent un équilibre entre vie privée et vie professionnelle | I100: Les mécanismes offrent-ils un équilibre entre vie privée et vie professionnelle ? | J100: OUI | K100: Plan de coordination RH global | L100: Déséquilibre vie privée-professionnelle | M100: Élevée | N100: Manque d'alignement des objectifs individuels et organisationnels par évaluations rares. | O100: Organiser des entretiens semestriels pour aligner objectifs individuels/entreprise.
...

Sheet 4.1
A1: Domaines | B1: Responssables | C1: Durée | D1: Moyens pour la réalisation | E1: Parties Prenantes | F1: points de contrôles | G1: objectifs de contrôle | H1: critères d'évaluation | I1: questions d'évaluation | J1: Réponses | K1: Documents requis | L1: Risques | M1: Criticités | N1: conséquences | O1: Recommendations
A2: Application en service | F2: Organisation | G2: S’assurer de l’existence d'un comité informatique | H2: Vérifier l’existence d’un organigramme officiel du comité signé par la direction. | I2: L'organigramme du comité est-il signé par la direction ? | J2: OUI | K2: Organigramme de l’entité | L2: Absence de gouvernance clairement définie | M2: Élevée | N2: Non-conformité aux réglementations en vigueur entraînant des sanctions légales. | O2: Élaborer un cadre de gouvernance aligné sur COBIT ou ISO 27001 en formalisant les rôles et responsabilités.
H3: Confirmer la présence d’au moins 3 procès-verbaux de réunion datés des 6 derniers mois. | I3: Trois procès-verbaux de réunion existent-ils pour les 6 derniers mois ? | J3: NON | K3: Organigramme fonctionnel de la DSI | L3: Documentation insuffisante des décisions stratégiques | M3: Moyenne | N3: Détérioration de la confiance des parties prenantes due à l'absence de traçabilité des décisions. | O3: Documenter et diffuser les politiques de sécurité et les procédures internes pour garantir leur accessibilité.
H4: Analyser la composition du comité (CV/certifications des membres). | I4: Les CV et certifications des membres du comité sont-ils disponibles ? | J4: OUI | K4: Procès-verbaux des réunions du comité | L4: Incompétence des membres du comité de pilotage | M4: Élevée | N4: Augmentation des erreurs opérationnelles par manque de directives claires. | O4: Mettre en place une formation continue sur les enjeux de sécurité et la conformité réglementaire pour les employés.
H5: Identifier un mandat écrit précisant les missions et la fréquence des réunions. | I5: Un mandat écrit définit-il les missions et la fréquence des réunions ? | J5: OUI | K5: Fiches de postes de la DSI | L5: Définition floue des responsabilités du comité | M5: Élevée | N5: Vulnérabilité accrue aux cyberattaques en raison de politiques obsolètes. | O5: Implémenter des contrôles d'accès stricts basés sur le principe du moindre privilège et revoir périodiquement les habilitations.
H6: Contrôler la diffusion des décisions du comité via des emails ou documents internes. | I6: Les décisions du comité sont-elles diffusées par email ou documents internes ? | J6: OUI | K6: Politique des Applications approuvée par la direction | L6: Non-diffusion des orientations stratégiques aux équipes | M6: Élevée | N6: Inefficacité des contrôles internes causant des pertes financières. | O6: Concevoir et tester régulièrement un plan de continuité d'activité (PCA) et un plan de reprise d'activité (PRA).
G7: S’assurer de l’existence d'une politique relative aux applications | H7: Vérifier la présence d’un document intitulé "Politique des Applications" approuvé par la direction. | I7: La "Politique des Applications" est-elle approuvée par la direction ? | J7: OUI | K7: Accusés de réception des employés pour la politique | L7: Politique de sécurité non formalisée | M7: Élevée | N7: Exposition à des litiges juridiques faute de documentation appropriée. | O7: Instaurer une matrice des risques mise à jour annuellement et intégrée aux processus décisionnels.
H8: Confirmer la date de la dernière mise à jour (moins de 12 mois). | I8: La dernière mise à jour date-t-elle de moins de 12 mois ? | J8: NON | K8: Plan de formation annuel lié à la politique | L8: Non-conformité réglementaire | M8: Moyenne | N8: Dysfonctionnements dans la gestion des accès menant à des fuites de données sensibles. | O8: Automatiser les contrôles de validation des données critiques pour réduire les erreurs manuelles.
H9: Analyser les mentions de conformité RGPD/ISO dans le document. | I9: Le document mentionne-t-il la conformité RGPD/ISO ? | J9: OUI | K9: Matrice des autorisations/droits d’accès | L9: Manque de sensibilisation des employés aux politiques | M9: Moyenne | N9: Interruptions prolongées des activités en cas de sinistre non anticipé. | O9: Déployer des outils de surveillance en temps réel pour détecter les anomalies et les activités suspectes.
H10: Vérifier la diffusion de la politique aux employés (accusés de réception signés). | I10: Les employés ont-ils signé des accusés de réception pour la politique ? | J10: OUI | K10: Liste des 100 derniers incidents du domaine d’audit | L10: Absence de formation continue sur les enjeux de sécurité | M10: Élevée | N10: Dégradation de la performance des systèmes due à une maintenance inadéquate. | O10: Réaliser des audits réguliers des configurations des systèmes et des droits d'accès privilégiés.
H11: Identifier un plan de formation annuel lié à cette politique. | I11: Un plan de formation annuel lié à cette politique existe-t-il ? | J11: OUI | K11: Rapport d’analyse des risques récent (moins de 12 mois) | L11: Définition imprécise des rôles utilisateurs | M11: Élevée | N11: Non-respect des engagements contractuels envers les clients ou partenaires. | O11: Mettre en œuvre des mécanismes de chiffrement des données en transit et au repos conformes aux normes ISO 27001.
G12: S’assurer que les rôle et responsabilités des utilisateurs sont bien définis | H12: Contrôler l’existence de fiches de poste pour chaque profil utilisateur. | I12: Des fiches de poste sont-elles disponibles pour chaque profil utilisateur ? | J12: OUI | K12: Document de classification des données (public, interne, confidentiel) | L12: Violation des engagements contractuels | M12: Élevée | N12: Augmentation des coûts opérationnels liés à des processus inefficients. | O12: Séparer les environnements de développement, de test et de production pour limiter les risques de corruption.
H13: Vérifier la signature des utilisateurs sur des chartes d’utilisation. | I13: Les utilisateurs ont-ils signé des chartes d'utilisation ? | J13: OUI | K13: Manuel d’administration des applications | L13: Droits d'accès obsolètes ou inadaptées | M13: Élevée | N13: Perte de données critiques par absence de sauvegardes fiables. | O13: Établir des procédures de gestion des incidents incluant une analyse post-mortem et des plans d'action correctifs.
H14: Confirmer la mise à jour des habilitations dans un tableau de gestion des accès. | I14: Le tableau de gestion des accès est-il à jour ? | J14: OUI | K14: Logs d’accès aux données sensibles sur 30 jours | L14: Détournement de privilèges | M14: Élevée | N14: Retards dans les prises de décision faute d’informations actualisées. | O14: Valider l'exhaustivité et l'intégrité des sauvegardes via des tests de restauration périodiques.
H15: Analyser des logs d’accès pour corréler avec les rôles déclarés. | I15: Les logs d'accès correspondent-ils aux rôles déclarés ? | J15: OUI | K15: Procédures écrites pour les processus critiques | L15: Absence de revue périodique des habilitations | M15: Élevée | N15: Compromission de l’intégrité des données financières ou métiers. | O15: Créer un comité de pilotage IT pour superviser l'alignement stratégique des projets avec les objectifs métiers.
H16: Identifier des procédures de révision trimestrielle des droits. | I16: Une procédure de révision trimestrielle des droits est-elle en place ? | J16: NON | K16: Comptes rendus mensuels de l’application | L16: Fraude interne via l'exploitation de droits excessifs | M16: Élevée | N16: Risque accru de fraude interne en l’absence de séparation des tâches. | O16: Utiliser des outils de gestion des identités et des accès (IAM) pour centraliser et auditer les permissions.
G17: S’assurer qu’une analyse des risques a été réalisée | H17: Vérifier un rapport d’analyse des risques daté de moins de 12 mois. | I17: Un rapport d'analyse des risques de moins de 12 mois existe-t-il ? | J17: OUI | K17: Guide utilisateur et manuel de procédures | L17: Évaluation des risques non actualisée | M17: Élevée | N17: Détérioration de la qualité des services IT impactant la satisfaction client. | O17: Réaliser des tests de pénétration et des audits de code pour identifier les vulnérabilités applicatives.
H18: Confirmer l’utilisation d’une méthodologie reconnue (ex : EBIOS, OCTAVE). | I18: La méthodologie utilisée est-elle reconnue (EBIOS, OCTAVE) ? | J18: NON | K18: Matrice des tâches et fonctions incompatibles | L18: Utilisation de méthodologies obsolètes | M18: Élevée | N18: Exposition à des amendes réglementaires pour non-conformité RGPD. | O18: Documenter les flux de données et les interfaces entre systèmes pour garantir la traçabilité des échanges.
H19: Analyser la liste des risques identifiés (au moins 10 risques critiques). | I19: Au moins 10 risques critiques sont-ils identifiés ? | J19: OUI | K19: Contrat de maintenance ou d’assistance | L19: Sous-estimation des menaces critiques | M19: Élevée | N19: Interruptions fréquentes des services en production par manque de redondance. | O19: Adopter une politique de gestion des correctifs avec des délais stricts pour les mises à jour critiques.
H20: Identifier un plan d’action avec des responsables et des échéances. | I20: Un plan d'action avec responsables et échéances est-il établi ? | J20: OUI | K20: Plan de continuité des activités (PCA) | L20: Absence de planification corrective | M20: Élevée | N20: Difficultés à assurer la continuité des activités lors de crises majeures. | O20: Instaurer des contrôles d'intégrité des données lors des migrations ou des transferts inter-systèmes.
H21: Contrôler des preuves de mise en œuvre des actions (rapports de suivi). | I21: Des preuves de mise en œuvre des actions sont-elles disponibles ? | J21: OUI | K21: Plan de reprise d’activité (PRA) | L21: Contrôles inefficaces face aux risques identifiés | M21: Élevée | N21: Dépendance excessive vis-à-vis de prestataires externes non supervisés. | O21: Mettre en place une journalisation centralisée et une analyse proactive des logs pour détecter les menaces.
G22: S’assurer que le prolongement de l'analyse de risque et de son expansion ont été réalisés | H22: Vérifier des mises à jour de l’analyse des risques (au moins 2 révisions annuelles). | I22: L'analyse des risques a-t-elle été mise à jour deux fois dans l'année ? | J22: OUI | K22: Rapports de traitements des incidents | L22: Ignorance des nouvelles vulnérabilités | M22: Élevée | N22: Altération de la réputation de l’organisation suite à des incidents récurrents. | O22: Élaborer une charte de sécurité informatique incluant des clauses contractuelles avec les fournisseurs externes.
H23: Confirmer l’intégration des nouveaux risques (ex : cybermenaces, RGPD). | I23: Les nouveaux risques (cybermenaces, RGPD) sont-ils intégrés ? | J23: OUI | K23: Inventaire des licences | L23: Défaut de reporting aux instances décisionnelles | M23: Élevée | N23: Inefficacité des plans de reprise après sinistre prolongeant les temps d’arrêt. | O23: Concevoir des tableaux de bord de performance alignés sur les KPI métiers pour mesurer l'efficacité des SI.
H24: Analyser des indicateurs de suivi des risques (tableaux de bord). | I24: Des indicateurs de suivi des risques existent-ils ? | J24: OUI | K24: Bilan de qualité logiciel | L24: Culture du risque insuffisante dans l'organisation | M24: Élevée | N24: Augmentation des vulnérabilités logicielles par absence de mises à jour. | O24: Sensibiliser les utilisateurs aux risques de phishing et d'ingénierie sociale via des simulations régulières.
H25: Identifier des procédures de reporting aux instances dirigeantes. | I25: Des procédures de reporting aux instances dirigeantes sont-elles définies ? | J25: OUI | K25: Bilan de satisfaction des utilisateurs | L25: Classification inappropriée des données sensibles | M25: Moyenne | N25: Désorganisation des équipes IT faute de procédures standardisées. | O25: Auditer régulièrement les configurations des pare-feux et des équipements réseau pour prévenir les attaques.
H26: Contrôler des preuves de sensibilisation des équipes aux risques majeurs. | I26: Les équipes sont-elles sensibilisées aux risques majeurs ? | J26: OUI | K26: Schéma d’interaction des applications métiers | L26: Exposition de données critiques | M26: Moyenne | N26: Non-atteinte des objectifs stratégiques en raison d’un mauvais alignement IT-métier. | O26: Intégrer des contrôles de conformité RGPD dans les processus de traitement des données personnelles.
G27: S’assurer que l’analyse et évaluation du niveau de sensibilité a été réalisée | H27: Vérifier un document classifiant les données par niveau de sensibilité (public, interne, confidentiel). | I27: Un document classe-t-il les données (public, interne, confidentiel) ? | J27: PAS | K27: Diagramme de flux de données des applications | L27: Surveillance inadéquate des accès privilégiés | M27: Élevée | N27: Perte de compétitivité due à des technologies obsolètes ou sous-utilisées. | O27: Définir une stratégie de gestion des actifs numériques incluant leur classification et leur cycle de vie.
H28: Confirmer la mise à jour de la classification (moins de 6 mois). | I28: La classification a-t-elle été mise à jour dans les 6 mois ? | J28: OUI | K28: Procédures de gestion des changements | L28: Protection insuffisante des actifs informationnels | M28: Élevée | N28: Erreurs humaines accrues par manque de formation ou de documentation. | O28: Mettre en œuvre des contrôles d'accès physique aux salles serveurs et aux centres de données.
H29: Analyser des logs d’accès aux données sensibles sur 30 jours. | I29: Les logs d'accès aux données sensibles sur 30 jours sont-ils analysables ? | J29: OUI | K29: Logs de connexion avec adresses IP et horodatages | L29: Manque de formation sur la manipulation des données | M29: Moyenne | N29: Détection tardive des anomalies opérationnelles réduisant la réactivité. | O29: Réaliser des audits de sécurité des APIs pour prévenir les exploitations malveillantes.
H30: Identifier des procédures de protection spécifiques pour les données critiques. | I30: Des procédures spécifiques protègent-elles les données critiques ? | J30: OUI | K30: Politique de sécurité des mots de passe | L30: Documentation technique obsolète | M30: Élevée | N30: Fuite d’informations confidentielles par des contrôles d’accès laxistes. | O30: Standardiser les procédures de gestion des changements avec validation technique et métier préalable.
H31: Contrôler des preuves de formation des utilisateurs sur la classification. | I31: Les utilisateurs sont-ils formés sur la classification des données ? | J31: OUI | K31: Procédures de gestion des identifiants et mots de passe | L31: Procédures de secours non testées | M31: Élevée | N31: Dégradation de la productivité des utilisateurs face à des outils inadaptés. | O31: Instaurer des revues indépendantes des architectures techniques pour garantir leur résilience.
G32: Vérifier l’existence d’un manuel d'administration de l'application | H32: Vérifier l’existence d’un manuel d’administration mis à jour (moins de 12 mois). | I32: Le manuel d'administration est-il à jour (moins de 12 mois) ? | J32: NON | K32: Document de stratégie de migration des données | L32: Dépendance excessive au savoir-faire individuel | M32: Élevée | N32: Difficultés à auditer les systèmes en raison d’une journalisation insuffisante. | O32: Adopter des contrats de service (SLA) clairs avec des pénalités en cas de non-respect des engagements.
H33: Confirmer la couverture des procédures clés (ex : sauvegarde, restauration). | I33: Les procédures clés (sauvegarde, restauration) sont-elles couvertes ? | J33: OUI | K33: Procédures de sauvegarde et restauration | L33: Absence de capitalisation des connaissances | M33: Élevée | N33: Augmentation des coûts de conformité pour rattraper les lacunes identifiées. | O33: Utiliser des solutions de détection d'intrusion (IDS/IPS) pour surveiller les activités réseau anormales.
H34: Analyser des exemples de procédures détaillées (étapes, screenshots). | I34: Des procédures détaillées avec étapes et captures existent-elles ? | J34: OUI | K34: Rapports de tests de restauration après sinistre | L34: Défaut de traçabilité des opérations sensibles | M34: Élevée | N34: Risque de corruption des données lors de migrations non contrôlées. | O34: Documenter les dépendances critiques entre systèmes pour anticiper les impacts des pannes.
H35: Identifier des preuves d’utilisation du manuel (logs de consultation). | I35: Des logs de consultation du manuel sont-ils disponibles ? | J35: OUI | K35: Clauses de contrat SLA avec les fournisseurs | L35: Contrôles métier inefficaces | M35: Élevée | N35: Incapacité à répondre aux audits externes faute de preuves tangibles. | O35: Mettre en place une politique de gestion des mots de passe exigeant une complexité et une rotation régulière.
H36: Contrôler des formations dédiées à l’équipe d’administration. | I36: L'équipe d'administration reçoit-elle des formations dédiées ? | J36: OUI | K36: Feuille de route technologique approuvée | L36: Non-respect des bonnes pratiques sectorielles | M36: Élevée | N36: Fragilisation de la gouvernance IT par une supervision inefficace. | O36: Auditer les configurations des bases de données pour limiter les risques d'exposition non autorisée.
G37: Vérifier l’existence de procédures formalisées | H37: Vérifier des procédures écrites pour au moins 5 processus critiques (ex : gestion des incidents). | I37: Cinq procédures écrites pour processus critiques existent-elles ? | J37: OUI | K37: Rapports d’évaluation de l’alignement stratégique | L37: Défaut de supervision des processus clés | M37: Élevée | N37: Exposition à des attaques ciblées en l’absence de surveillance proactive. | O37: Formaliser une procédure de réponse aux incidents cyber incluant une communication structurée.
H38: Confirmer la signature des procédures par les responsables concernés. | I38: Les responsables ont-ils signé ces procédures ? | J38: OUI | K38: Spécifications fonctionnelles signées | L38: Erreurs de conception des workflows | M38: Élevée | N38: Déséquilibre entre investissements IT et retours sur investissement attendus. | O38: Implémenter des contrôles d'accès hiérarchiques pour les environnements virtualisés et cloud.
H39: Analyser des preuves d’application (logs, rapports d’exécution). | I39: Des preuves d'application (logs, rapports) sont-elles vérifiables ? | J39: OUI | K39: Fiches de poste détaillant les tâches des utilisateurs | L39: Interface utilisateur peu intuitive | M39: Élevée | N39: Perte de données historiques critiques par archivage défaillant. | O39: Réaliser des évaluations de maturité des processus IT selon le référentiel COBIT.
H40: Identifier des indicateurs de performance liés aux procédures. | I40: Des indicateurs de performance liés aux procédures existent-ils ? | J40: OUI | K40: Rapports de performance des systèmes parallèles | L40: Absence de validation automatique des saisies | M40: Moyenne | N40: Complexification des processus métier due à des interfaces peu ergonomiques. | O40: Instaurer des mécanismes de contrôle qualité automatisés dans les pipelines DevOps.
H41: Contrôler des mises à jour récentes (moins de 6 mois). | I41: Les procédures ont-elles été mises à jour dans les 6 mois ? | J41: OUI | K41: Retours d’expérience des utilisateurs sur l’adéquation | L41: Défaut de maintenance évolutive | M41: Moyenne | N41: Délais prolongés dans les projets IT par mauvaise gestion des priorités. | O41: Mettre à jour régulièrement les politiques de sécurité pour refléter l'évolution des menaces.
G42: S’assurer de l’existence et de la mise à disposition du compte rendu mensuel au propriétaire | H42: Vérifier des comptes rendus mensuels datés des 6 derniers mois. | I42: Des comptes rendus mensuels existent-ils pour les 6 derniers mois ? | J42: OUI | K42: Rapport ROI (Return on Investment) avec calculs détaillés | L42: Incohérences dans les données de référence | M42: Élevée | N42: Non-respect des SLA entraînant des pénalités contractuelles. | O42: Créer un référentiel unique des configurations matérielles et logicielles pour éviter les divergences.
H43: Confirmer la signature des comptes rendus par le propriétaire de l’application. | I43: Le propriétaire de l'application a-t-il signé ces comptes rendus ? | J43: OUI | K43: Contrats signés avec les fournisseurs | L43: Faiblesses dans les mécanismes de réconciliation | M43: Élevée | N43: Détérioration de la relation avec les fournisseurs par manque de suivi. | O43: Effectuer des audits de conformité des licences logicielles pour prévenir les risques juridiques.
H44: Analyser des indicateurs clés inclus (ex : disponibilité, incidents). | I44: Des indicateurs clés (disponibilité, incidents) sont-ils inclus ? | J44: OUI | K44: Calendrier de mise en œuvre du projet | L44: Manque d'intégrité des données | M44: Élevée | N44: Augmentation des conflits internes liés à des rôles mal définis. | O44: Déployer des solutions de protection contre les attaques DDoS pour les services exposés en ligne.
H45: Identifier des actions correctives planifiées dans les comptes rendus. | I45: Des actions correctives sont-elles planifiées dans les comptes rendus ? | J45: OUI | K45: Bilan post-projet avec conclusions | L45: Exposition des flux inter-applicatifs | M45: Élevée | N45: Incapacité à capitaliser sur les innovations technologiques par rigidité organisationnelle. | O45: Établir des procédures de destruction sécurisée des données en fin de cycle de vie.
H46: Contrôler des preuves de suivi des actions (rapports de clôture). | I46: Des preuves de suivi des actions (rapports de clôture) existent-elles ? | J46: NON | K46: Rapports d’économie réalisées | L46: Défaut de chiffrement des transmissions | M46: Élevée | N46: Risque de non-conformité aux standards sectoriels nuisant à la crédibilité. | O46: Réaliser des tests de résistance des infrastructures face aux catastrophes naturelles.
G47: S’assurer de l’existence d'un guide d'utilisateur, manuel de procédure | H47: Vérifier l’existence d’un guide d’utilisateur et d’un manuel de procédures. | I47: Un guide utilisateur et un manuel de procédures sont-ils disponibles ? | J47: OUI | K47: Document de réingénierie des processus | L47: Contournement des contrôles d'accès | M47: Élevée | N47: Désalignement entre les besoins métier et les capacités techniques disponibles. | O47: Intégrer des contrôles de sécurité dans les phases de conception des applications (Security by Design).
H48: Confirmer la mise à jour des documents (moins de 12 mois). | I48: Ces documents ont-ils été mis à jour dans les 12 mois ? | J48: NON | K48: Rapport d’architecture technique de l’application | L48: Journalisation insuffisante des activités | M48: Élevée | N48: Fragmentation des systèmes réduisant l’efficacité globale de l’infrastructure. | O48: Mettre en place une veille technologique pour anticiper les risques liés aux nouvelles technologies.
H49: Analyser des exemples de procédures détaillées (étapes, screenshots). | I49: Des procédures détaillées avec captures d'écran existent-elles ? | J49: OUI | K49: Tableaux de bord avec indicateurs de performance (KPI) | L49: Détection tardive des incidents de sécurité | M49: Élevée | N49: Exposition à des erreurs de traitement par absence de validation automatisée. | O49: Auditer régulièrement les fournisseurs tiers pour s'assurer de leur conformité aux exigences de sécurité.
H50: Identifier des preuves de diffusion aux utilisateurs (accusés de réception). | I50: Des accusés de réception prouvent-ils la diffusion aux utilisateurs ? | J50: OUI | K50: Rapports de maturité technologique (ex : Gartner) | L50: Absence de revue des journaux d'audit | M50: Élevée | N50: Détérioration de la qualité des données utilisées pour la prise de décision. | O50: Documenter les procédures de gestion des identités temporaires et des comptes de service.
H51: Contrôler des formations dédiées à l’utilisation des documents. | I51: Des formations sur l'utilisation des documents sont-elles organisées ? | J51: OUI | K51: Procédures de gestion des accès privilégiés | L51: Failles dans les interfaces d'intégration | M51: Élevée | N51: Inadéquation des compétences des équipes face aux évolutions technologiques. | O51: Instaurer des revues post-incident pour améliorer continuellement les processus de sécurité.
F52: Application | G52: S'assurer que l'accès aux ressources de l'application (données et transactions) est restreint par un système de gestion d'accès | H52: Vérifier l’existence d’un système RBAC (Role-Based Access Control) actif. | I52: Un système RBAC est-il actif ? | J52: OUI | K52: Logs d’actions administratives sur 90 jours | L52: Corruption des données lors des échanges | M52: Élevée | N52: Augmentation des temps d’indisponibilité des systèmes critiques. | O52: Adopter des outils de monitoring des performances applicatives pour détecter les goulets d'étranglement.
H53: Confirmer la présence de logs d’accès aux données sensibles sur 30 jours. | I53: Des logs d'accès aux données sensibles sur 30 jours existent-ils ? | J53: OUI | K53: Procédures de révocation des accès en cas de départ | L53: Absence de mécanismes de rejeu | M53: Élevée | N53: Perte d’opportunités commerciales par lenteur des processus informatiques. | O53: Mettre en œuvre une politique de gestion des clés de chiffrement incluant leur rotation et stockage sécurisé.
H54: Analyser la liste des utilisateurs avec droits administrateurs (moins de 5% du total). | I54: Moins de 5% des utilisateurs ont-ils des droits administrateur ? | J54: OUI | K54: Document de schéma-directeur du SI | L54: Perte de données critiques | M54: Élevée | N54: Dépassements budgétaires récurrents dans les projets IT non maîtrisés. | O54: Réaliser des audits de code statique et dynamique (SAST/DAST) pour les applications critiques.
H55: Tester le rejet d’accès hors profil via un compte test. | I55: Un compte test confirme-t-il le rejet d'accès hors profil ? | J55: OUI | K55: Procédures de contrôle qualité des données saisies | L55: Archivage non conforme | M55: Élevée | N55: Risque de perte de savoir-faire interne par dépendance à des solutions externes. | O55: Formaliser une stratégie de sortie pour les technologies obsolètes incluant leur remplacement progressif.
H56: Identifier une procédure de révocation des accès en cas de départ. | I56: Une procédure de révocation des accès en cas de départ existe-t-elle ? | J56: OUI | K56: Manuels d’exploitation mis à jour | L56: Restauration impossible après incident | M56: Élevée | N56: Difficultés à maintenir la cohérence des données entre systèmes hétérogènes. | O56: Instaurer des contrôles d'accès basés sur les rôles (RBAC) pour les environnements cloud.
G57: S’assurer qu’une procédure de gestion des profils utilisateurs existe | H57: Contrôler un workflow de création/suppression de profils (outil Jira ou équivalent). | I57: Un workflow de gestion des profils (Jira ou équivalent) est-il utilisé ? | J57: NON | K57: Procédures de gestion des correctifs urgents | L57: Pertes d'informations historiques | M57: Élevée | N57: Détérioration de l’expérience utilisateur impactant l’adoption des outils. | O57: Documenter les procédures de gestion des vulnérabilités logicielles et des correctifs d'urgence.
H58: Vérifier des traces de validation hiérarchique pour 5 profils aléatoires. | I58: La validation hiérarchique pour 5 profils aléatoires est-elle tracée ? | J58: OUI | K58: Rapports de revue de code pour les projets récents | L58: Défaut de purge sécurisée | M58: Moyenne | N58: Non-respect des exigences réglementaires en matière de transparence. | O58: Mettre en place des mécanismes de détection des fuites de données (DLP) pour les informations sensibles.
H59: Analyser l’existence d’un référentiel des profils types (PDF ou Excel). | I59: Un référentiel des profils types (PDF/Excel) est-il disponible ? | J59: OUI | K59: Procédures de déploiement en environnement de production | L59: Défaut de gestion des anomalies | M59: Élevée | N59: Augmentation des coûts de maintenance corrective faute de prévention. | O59: Auditer les configurations des conteneurs et des orchestrateurs pour limiter les risques d'exploitation.
H60: Confirmer la réalisation d’un audit semestriel des droits. | I60: Un audit semestriel des droits est-il réalisé ? | J60: OUI | K60: Contrats incluant des clauses « Escrow Agreement » | L60: Absence de processus de correction | M60: Élevée | N60: Incapacité à détecter les anomalies en temps réel par monitoring insuffisant. | O60: Implémenter une politique de gestion des risques spécifique aux projets d'intelligence artificielle.
H61: Identifier des sanctions en cas de non-respect (ex : mentions dans des PV). | I61: Des sanctions pour non-respect sont-elles prévues (mention dans PV) ? | J61: NON | K61: Rapports de tests de montée en charge | L61: Défaut de traçabilité des corrections | M61: Élevée | N61: Dégradation de la résilience des systèmes face aux perturbations externes. | O61: Réaliser des tests d'intégration pour valider la cohérence des données entre systèmes hétérogènes.
G62: Vérifier que l’identification des utilisateurs est réalisée | H62: Tester l’impossibilité de se connecter sans identifiant unique. | I62: La connexion sans identifiant unique est-elle impossible ? | J62: OUI | K62: Procédures de gestion des données archivées | L62: Réintégration non contrôlée des données | M62: Élevée | N62: Exposition à des conflits d’intérêts dans la gestion des fournisseurs IT. | O62: Instaurer des contrôles d'accès biométriques pour les zones sensibles des datacenters.
H63: Vérifier l’absence de comptes génériques ("admin", "invité"). | I63: Les comptes génériques ("admin", "invité") sont-ils absents ? | J63: OUI | K63: Rapports de suivi des paiements des redevances | L63: Validation insuffisante des correctifs | M63: Élevée | N63: Perte de contrôle sur les actifs informationnels par mauvaise gouvernance. | O63: Documenter les procédures de gestion des incidents liés aux fournisseurs de services cloud.
H64: Analyser l’existence d’un annuaire LDAP/Active Directory synchronisé. | I64: Un annuaire LDAP/Active Directory est-il synchronisé ? | J64: OUI | K64: Procédures de gestion des partenariats avec les éditeurs | L64: Défaut de supervision des mises à jour | M64: Élevée | N64: Risque de non-reconnaissance des dépenses IT par manque de traçabilité. | O64: Mettre en œuvre des solutions de segmentation réseau pour isoler les flux critiques.
H65: Confirmer la présence d’une procédure de réinitialisation sécurisée des identifiants. | I65: Une procédure sécurisée de réinitialisation des identifiants existe-t-elle ? | J65: OUI | K65: Documentation technique des interfaces d’intégration | L65: Exposition aux vulnérabilités non patchées | M65: Élevée | N65: Désorganisation des workflows métier par intégration défaillante des systèmes. | O65: Auditer régulièrement les configurations des équipements IoT pour prévenir les compromissions.
H66: Contrôler des logs de connexion avec adresses IP et horodatages. | I66: Les logs de connexion incluent-ils adresses IP et horodatages ? | J66: OUI | K66: Procédures de suppression sécurisée des données obsolètes | L66: Journalisation incomplète des modifications | M66: Élevée | N66: Augmentation des erreurs de saisie manuelle par absence de contrôles automatisés. | O66: Formaliser une politique de gestion des journaux d'activité conforme aux exigences réglementaires.
G67: Vérifier qu’un mot de passe est associé à l'identifiant | H67: Vérifier que chaque identifiant est associé à un mot de passe unique. | I67: Chaque identifiant a-t-il un mot de passe unique ? | J67: OUI | K67: Rapports de performance de l’équipe de maintenance | L67: Défaut de détection des changements non autorisés | M67: Élevée | N67: Fragilisation de la position concurrentielle par retard technologique. | O67: Implémenter des contrôles de validation des entrées utilisateur pour prévenir les injections SQL.
H68: Confirmer l’application d’une politique de complexité des mots de passe (ex : 12 caractères, majuscules, chiffres). | I68: La politique impose-t-elle 12 caractères avec majuscules et chiffres ? | J68: OUI | K68: Procédures de recrutement et formation des équipes IT | L68: Absence de revue des configurations | M68: Élevée | N68: Incapacité à répondre aux attentes des utilisateurs finaux par rigidité des processus. | O68: Réaliser des audits de conformité aux normes sectorielles (PCI DSS, HIPAA, etc.).
H69: Analyser des logs de connexion pour détecter des mots de passe faibles. | I69: Les logs de connexion révèlent-ils des mots de passe faibles ? | J69: OUI | K69: Retours d’expérience du club utilisateurs | L69: Contrôles automatisés inefficaces | M69: Élevée | N69: Détérioration de la coordination entre équipes IT et métier par communication inefficace. | O69: Instaurer des mécanismes de surveillance des activités des robots logiciels (RPA).
H70: Tester la réinitialisation forcée après 90 jours. | I70: La réinitialisation forcée a-t-elle lieu après 90 jours ? | J70: OUI | K70: Procédures de gestion des mises à jour logicielles | L70: Défaut d'alerte sur les anomalies | M70: Élevée | N70: Exposition à des sanctions pour non-respect des clauses contractuelles avec les éditeurs. | O70: Documenter les procédures de gestion des certificats SSL/TLS pour éviter leur expiration.
H71: Identifier des alertes en cas de tentative de réutilisation d’un ancien mot de passe. | I71: Des alertes signalent-elles la réutilisation d'anciens mots de passe ? | J71: OUI | K71: Rapports d’évaluation de la conformité RGPD/ISO | L71: Absence de suivi des indicateurs clés | M71: Élevée | N71: Perte de données opérationnelles par corruption ou suppression accidentelle. | O71: Mettre en place des contrôles d'accès contextuels pour les applications métiers sensibles.
G72: S’assurer que les tentatives de connexions infructueuses à l'application sont suivies | H72: Vérifier des logs de tentatives infructueuses sur 30 jours. | I72: Les tentatives infructueuses sur 30 jours sont-elles tracées ? | J72: OUI | K72: Procédures de gestion des accès aux bibliothèques logicielles | L72: Reporting incomplet ou erroné | M72: Élevée | N72: Augmentation des vulnérabilités réseau par configuration inadéquate. | O72: Auditer les configurations des systèmes de virtualisation pour garantir leur isolation.
H73: Confirmer la présence d’un système de verrouillage après 5 échecs. | I73: Le système se verrouille-t-il après 5 échecs ? | J73: OUI | K73: Logs de consultation de la documentation par les utilisateurs | L73: Décisions basées sur des informations obsolètes | M73: Élevée | N73: Incapacité à anticiper les besoins futurs par planification stratégique absente. | O73: Implémenter des contrôles de sécurité physique pour les supports de sauvegarde hors site.
H74: Analyser des alertes automatiques envoyées à l’administrateur. | I74: Des alertes automatiques sont-elles envoyées à l'administrateur ? | J74: OUI | K74: Procédures de validation hiérarchique des profils utilisateurs | L74: Distribution non sécurisée des états | M74: Élevée | N74: Dégradation de la qualité des services supportés par des outils obsolètes. | O74: Réaliser des tests de résistance aux attaques zero-day via des simulations réalistes.
H75: Tester la réinitialisation manuelle par l’administrateur. | I75: La réinitialisation manuelle par l'admin est-elle fonctionnelle ? | J75: NON | K75: Rapports d’audit semestriel des droits d’accès | L75: Accès non contrôlé aux informations sensibles | M75: Élevée | N75: Risque de non-atteinte des objectifs de transformation numérique. | O75: Instaurer une politique de gestion des données archivées incluant leur classification et chiffrement.
H76: Identifier des procédures de suivi des tentatives suspectes. | I76: Une procédure de suivi des tentatives suspectes existe-t-elle ? | J76: OUI | K76: Procédures de gestion des alertes de sécurité automatiques | L76: Validation manquante des outputs | M76: Élevée | N76: Exposition à des litiges liés à la propriété intellectuelle des développements logiciels. | O76: Documenter les procédures de réponse aux fuites de données personnelles conformes au RGPD.
G77: S’assurer que l'accès aux données et aux transactions de l’application est géré | H77: Vérifier des logs d’accès aux transactions sensibles sur 30 jours. | I77: Les logs d'accès aux transactions sensibles sur 30 jours existent-ils ? | J77: OUI | K77: Documents de référence des règles de gestion des données | L77: Erreurs de traitement non détectées | M77: Élevée | N77: Perte de flexibilité opérationnelle par architecture technique rigide. | O77: Mettre en œuvre des contrôles d'intégrité des métadonnées associées aux données critiques.
H78: Confirmer la présence d’un système de chiffrement des données en transit. | I78: Les données en transit sont-elles chiffrées ? | J78: OUI | K78: Procédures de contrôle qualité des corrections de données | L78: Incohérences dans les codifications | M78: Élevée | N78: Détérioration de la collaboration interne par outils collaboratifs inadaptés. | O78: Auditer les configurations des systèmes de gestion des identités (IAM) pour limiter les erreurs.
H79: Analyser des procédures de validation des accès par un supérieur hiérarchique. | I79: Un supérieur hiérarchique valide-t-il les accès sensibles ? | J79: OUI | K79: Rapports de tests d’interopérabilité avec les systèmes existants | L79: Défaut d'application des règles métier | M79: Élevée | N79: Augmentation des délais de livraison des projets IT par mauvaise gestion des ressources. | O79: Implémenter des mécanismes de détection des comportements anormaux des utilisateurs.
H80: Tester le rejet d’accès hors profil via un compte test. | I80: Un compte test confirme-t-il le rejet d'accès hors profil ? | J80: OUI | K80: Procédures de gestion des environnements (dev/test/prod) | L80: Défaut de cohérence inter-modules | M80: Élevée | N80: Incapacité à garantir l’authenticité des transactions électroniques. | O80: Réaliser des revues architecturales pour s'assurer de la résilience des infrastructures hybrides.
H81: Identifier des alertes en cas d’accès hors heures ouvrables. | I81: Des alertes existent-elles pour les accès hors heures ouvrables ? | J81: OUI | K81: Rapports de tests de modularité de l’application | L81: Interfaces non sécurisées | M81: Élevée | N81: Fragilisation de la chaîne d’approvisionnement IT par dépendance à un seul fournisseur. | O81: Instaurer des contrôles d'accès temporaires avec expiration automatique pour les prestataires.
G82: Vérifier l’existence de pistes d’audit sur le système d’administration de l’application | H82: Vérifier des logs d’audit des actions administratives sur 90 jours. | I82: Les logs d'actions administratives sur 90 jours sont-ils disponibles ? | J82: OUI | K82: Procédures de gestion des versions logicielles | L82: Défaut de validation des développements | M82: Élevée | N82: Détérioration de l’image de marque suite à des incidents de sécurité médiatisés. | O82: Documenter les procédures de gestion des risques liés à l'utilisation de l'Internet des objets (IoT).
H83: Confirmer la présence d’un système de journalisation centralisé. | I83: Un système de journalisation centralisé est-il en place ? | J83: OUI | K83: Rapports de suivi des demandes de maintenance utilisateur | L83: Code non conforme aux standards | M83: Élevée | N83: Non-respect des engagements environnementaux liés à la gestion des infrastructures IT. | O83: Mettre en place des solutions de chiffrement homomorphique pour les données sensibles en traitement.
H84: Analyser des alertes automatiques pour les actions critiques (ex : suppression de données). | I84: Des alertes automatiques pour actions critiques existent-elles ? | J84: OUI | K84: Procédures de gestion des clés SSH/API | L84: Absence de revue par les pairs | M84: Élevée | N84: Augmentation des coûts de licence par utilisation non optimisée des logiciels. | O84: Auditer les configurations des passerelles API pour prévenir les exploitations malveillantes.
H85: Tester la traçabilité des actions via un compte administrateur. | I85: La traçabilité des actions via un compte admin est-elle vérifiable ? | J85: OUI | K85: Rapports de performance des travaux batch | L85: Déploiement non contrôlé en production | M85: Élevée | N85: Incapacité à maintenir la cohérence des données lors de fusions ou acquisitions. | O85: Implémenter des contrôles de sécurité dans les pipelines CI/CD pour les déploiements automatisés.
H86: Identifier des procédures de revue trimestrielle des logs. | I86: Une revue trimestrielle des logs est-elle prévue ? | J86: NON | K86: Procédures de gestion des données rejetées | L86: Accès non autorisé aux environnements critiques | M86: Élevée | N86: Dégradation de l’agilité organisationnelle par lenteur des processus IT. | O86: Réaliser des tests de charge pour valider la scalabilité des applications critiques.
G87: Vérifier que tous les documents servant de base à la saisie sont pris en compte | H87: Vérifier des exemples de documents sources (ex : factures, bons de commande). | I87: Des exemples de documents sources (factures, bons de commande) existent-ils ? | J87: OUI | K87: Rapports de tests de compatibilité ascendante/descendante | L87: Défaut de séparation des environnements | M87: Élevée | N87: Exposition à des erreurs de configuration entraînant des pannes critiques. | O87: Instaurer une politique de gestion des secrets applicatifs (mots de passe, clés API).
H88: Confirmer la présence d’un workflow de validation des documents. | I88: Un workflow de validation des documents est-il établi ? | J88: OUI | K88: Procédures de gestion des formations utilisateurs | L88: Gestion hasardeuse des accès privilégiés | M88: Élevée | N88: Perte de compétitivité sur le marché par innovation technologique insuffisante. | O88: Documenter les procédures de gestion des incidents liés aux systèmes de paiement électronique.
H89: Analyser des logs de saisie pour corréler avec les documents sources. | I89: Les logs de saisie correspondent-ils aux documents sources ? | J89: OUI | K89: Rapports de suivi des indicateurs de satisfaction utilisateur | L89: Compromission des clés d'accès | M89: Élevée | N89: Détérioration de la satisfaction client due à des services IT peu fiables. | O89: Mettre en œuvre des contrôles d'accès physiques et logiques pour les salles de contrôle.
H90: Tester la reprise des données après une erreur de saisie. | I90: La reprise des données après erreur de saisie est-elle possible ? | J90: OUI | K90: Procédures de gestion des risques résiduels | L90: Défaut de rotation des identifiants | M90: Moyenne | N90: Augmentation des risques liés à l’externalisation non supervisée. | O90: Auditer les configurations des systèmes SCADA/OT pour limiter les risques cyberindustriels.
H91: Identifier des procédures de contrôle qualité des données saisies. | I91: Des procédures de contrôle qualité des données saisies existent-elles ? | J91: OUI | K91: Rapports de revue trimestrielle des logs d’activité | L91: Compétences insuffisantes des équipes | M91: Élevée | N91: Incapacité à aligner les investissements IT sur les priorités métier. | O91: Implémenter des mécanismes de protection contre les attaques par ingénierie sociale.
G92: S’assurer que les facilités de saisie, l’ergonomie de la saisie, les messages écrans et les contrôles sont mis en œuvre | H92: Vérifier des captures d’écran des interfaces de saisie. | I92: Des captures d'écran des interfaces de saisie sont-elles disponibles ? | J92: OUI | K92: Procédures de gestion des accès hors heures ouvrables | L92: Défaut de plan de continuité d'activité | M92: Élevée | N92: Fragilisation de la conformité aux normes internationales par pratiques obsolètes. | O92: Réaliser des revues de conformité des contrats avec les fournisseurs de services managés.
H93: Confirmer la présence de messages d’erreur clairs et explicites. | I93: Les messages d'erreur sont-ils clairs et explicites ? | J93: OUI | K93: Rapports de tests de stabilité des technologies utilisées | L93: Procédures de secours non opérationnelles | M93: Élevée | N93: Détérioration de la capacité à auditer les processus internes efficacement. | O93: Instaurer des contrôles de sécurité pour les environnements DevOps et les outils low-code.
H94: Analyser des tests utilisateurs pour évaluer l’ergonomie. | I94: Des tests utilisateurs évaluent-ils l'ergonomie ? | J94: OUI | K94: Procédures de gestion des budgets d’extension d’infrastructure | L94: Temps de restauration excessif | M94: Élevée | N94: Exposition à des interruptions d’activité par absence de redondance des systèmes. | O94: Documenter les procédures de gestion des risques liés à l'adoption de la blockchain.
H95: Tester la validation automatique des champs obligatoires. | I95: La validation automatique des champs obligatoires fonctionne-t-elle ? | J95: OUI | K95: Rapports de tests de réversibilité en cas d’échec de déploiement | L95: Perte de disponibilité du système | M95: Élevée | N95: Perte de données stratégiques par absence de politiques de sauvegarde robustes. | O95: Mettre en place des mécanismes de validation des données en temps réel pour les transactions.
H96: Identifier des procédures de mise à jour des interfaces. | I96: Des procédures de mise à jour des interfaces existent-elles ? | J96: OUI | K96: Procédures de gestion des alertes de tentative d’accès non autorisé | L96: Défaut de tests de reprise | M96: Élevée | N96: Augmentation des conflits entre équipes par manque de clarté des responsabilités. | O96: Auditer les configurations des systèmes de gestion de contenu (CMS) pour prévenir les vulnérabilités.
G97: S’assurer que les contrôles de validation des « brouillards » de saisie pour validation par réconciliation existent | H97: Vérifier des exemples de brouillards de saisie validés. | I97: Des brouillards de saisie validés sont-ils disponibles ? | J97: OUI | K97: Rapports de suivi des indicateurs de productivité des processus | L97: Inadéquation des sauvegardes | M97: Élevée | N97: Incapacité à répondre aux audits réglementaires faute de documentation adéquate. | O97: Implémenter des contrôles d'accès basés sur l'attestation pour les appareils connectés.
H98: Confirmer la présence d’un workflow de réconciliation. | I98: Un workflow de réconciliation est-il en place ? | J98: NON | K98: Procédures de gestion des mises à jour des spécifications fonctionnelles | L98: Exposition aux sinistres majeurs | M98: Élevée | N98: Dégradation de la qualité des décisions managériales par données incomplètes. | O98: Réaliser des tests de résilience des infrastructures face aux pannes matérielles.
H99: Analyser des logs de validation pour corréler avec les brouillards. | I99: Les logs de validation correspondent-ils aux brouillards ? | J99: OUI | K99: Rapports de tests de performance des développements spécifiques | L99: Non-respect des SLA | M99: Élevée | N99: Risque de non-conformité aux exigences sectorielles spécifiques. | O99: Instaurer une politique de gestion des correctifs critiques avec des délais contraignants.
H100: Tester la détection d’erreurs de saisie via des contrôles automatiques. | I100: Les contrôles automatiques détectent-ils les erreurs de saisie ? | J100: OUI | K100: Procédures de gestion des partenariats avec les clubs utilisateurs | L100: Dégradation de la qualité de service | M100: Élevée | N100: Détérioration de la collaboration avec les partenaires externes par systèmes incompatibles. | O100: Documenter les procédures de gestion des risques liés aux technologies émergentes (IA, 5G).
...

Sheet 4.2
A1: Domaines | B1: Responsables | C1: Durée | D1: Moyens pour la réalisation | E1: Parties Prenantes | F1: Points de Contrôle | G1: Objectifs de Contrôle | H1: Critère d’Évaluation | I1: Question d’Évaluation | J1: Réponses | K1: Documents requis | L1: Risques | M1: Criticités | N1: conséquences | O1: Recommendations
A2: Fonction informatique | F2: Rôle et positionnement de l'informatique dans l'organisation | G2: Vérifier qu’ont été créés des Comités « informatique » (stratégique, pilotage,..) regroupant les différentes directions de l’Organisation en charge de recenser les besoins et les opportunités, gérer les priorités et suivre les projets | H2: Vérifier la présence de procès-verbaux des réunions des comités informatiques. | I2: Comment vérifier la présence des procès-verbaux des réunions des comités informatiques ? | J2: OUI | K2: Procès-verbaux des réunions des comités informatiques | L2: Absence de traçabilité des décisions prises lors des comités informatiques | M2: Élevée | N2: Décisions non documentées entraînant des incohérences et des conflits. | O2: Documentez systématiquement toutes les décisions pour éviter les incohérences.
H3: Analyser la fréquence des réunions des comités pour s'assurer de leur régularité. | I3: À quelle fréquence les comités informatiques se réunissent-ils et comment s’assurer de leur régularité ? | J3: OUI | K3: Calendrier des réunions des comités informatiques | L3: Manque de régularité dans les réunions des comités informatiques | M3: Élevée | N3: Retards dans les prises de décision stratégiques et opérationnelles. | O3: Établissez des délais stricts pour les prises de décision stratégiques et opérationnelles.
H4: Confirmer la participation active des représentants des différentes directions aux comités. | I4: Les représentants des différentes directions participent-ils activement aux comités informatiques ? | J4: OUI | K4: Liste de présence des participants aux comités informatiques | L4: Désengagement des représentants des directions dans les comités informatiques | M4: Élevée | N4: Manque d'engagement des parties prenantes réduisant l'efficacité des comités. | O4: Impliquez activement les parties prenantes dans les comités pour renforcer leur engagement.
H5: Évaluer l'alignement des priorités définies par les comités avec la stratégie globale de l'organisation. | I5: Comment évaluer si les priorités des comités s’alignent sur la stratégie globale de l’organisation ? | J5: OUI | K5: Comptes rendus des décisions des comités informatiques | L5: Décalage entre les priorités des comités et la stratégie globale de l'organisation | M5: Élevée | N5: Mauvaise allocation des ressources due à un désalignement stratégique. | O5: Alignez l'allocation des ressources sur la stratégie globale de l'entreprise.
H6: Vérifier la traçabilité des décisions prises lors des comités dans les projets informatiques. | I6: Les décisions prises lors des comités sont-elles retracées dans les projets informatiques ? | J6: NON | K6: Charte informatique approuvée par la direction | L6: Décisions des comités non retranscrites dans les projets informatiques | M6: Élevée | N6: Projets informatiques ne répondant pas aux attentes des métiers. | O6: Collaborez étroitement avec les métiers pour définir les attentes des projets informatiques.
G7: Vérifier l’existence d’une charte informatique ou de tout autre document définissant le rôle et le périmètre de responsabilité de la DSI | H7: S'assurer de l'existence d'une charte informatique formalisée et approuvée par la direction. | I7: Existe-t-il une charte informatique formalisée et approuvée par la direction ? | J7: OUI | K7: Document de mise à jour de la charte informatique | L7: Absence de charte informatique formalisée et approuvée | M7: Élevée | N7: Absence de cadre clair générant des pratiques disparates et non conformes. | O7: Définissez un cadre clair et uniforme pour standardiser les pratiques.
H8: Vérifier que la charte définit clairement les rôles et responsabilités de la DSI. | I8: La charte informatique définit-elle clairement les rôles et responsabilités de la DSI ? | J8: OUI | K8: Procédure de communication de la charte informatique | L8: Rôles et responsabilités de la DSI mal définis dans la charte informatique | M8: Élevée | N8: Confusion sur les attributions de la DSI entraînant des retards et des chevauchements. | O8: Clarifiez les attributions de la DSI pour éviter les chevauchements et retards.
H9: Confirmer que la charte est régulièrement mise à jour pour refléter les évolutions organisationnelles. | I9: La charte informatique est-elle régulièrement mise à jour pour refléter les évolutions organisationnelles ? | J9: OUI | K9: Ordres du jour des réunions de direction mentionnant les SI | L9: Charte informatique obsolète ne reflétant pas les évolutions organisationnelles | M9: Élevée | N9: Charte inadaptée aux besoins actuels, limitant son utilité. | O9: Mettez à jour la charte pour qu'elle réponde aux besoins actuels.
H10: Évaluer la communication de la charte à l'ensemble des collaborateurs concernés. | I10: Comment la charte informatique est-elle communiquée à l’ensemble des collaborateurs concernés ? | J10: OUI | K10: Rapports d'état des systèmes d'information soumis à la direction | L10: Mauvaise communication de la charte informatique aux collaborateurs | M10: Moyenne | N10: Méconnaissance des règles par les employés augmentant les risques de non-conformité. | O10: Formez les employés sur les règles pour réduire les risques de non-conformité.
H11: Vérifier l'intégration des principes de la charte dans les processus opérationnels de la DSI. | I11: Les principes de la charte sont-ils intégrés dans les processus opérationnels de la DSI ? | J11: OUI | K11: Procès-verbaux des décisions stratégiques liées à l'informatique | L11: Non-intégration des principes de la charte dans les processus opérationnels de la DSI | M11: Élevée | N11: Processus opérationnels inefficaces faute d'intégration des principes de la charte. | O11: Intégrez les principes de la charte dans les processus opérationnels.
G12: Évaluer le degré d’implication et de maîtrise des organes de gestion dans les systèmes d’information de l’Organisation | H12: Analyser les comptes rendus de réunions de direction mentionnant les systèmes d'information. | I12: Les réunions de direction mentionnent-elles régulièrement les systèmes d’information ? | J12: OUI | K12: Budget alloué à la DSI et aux projets informatiques | L12: Manque de discussion sur les systèmes d'information lors des réunions de direction | M12: Moyenne | N12: Opportunités manquées pour aligner les SI sur la stratégie globale. | O12: Saisissez les opportunités pour aligner les SI sur la stratégie globale.
H13: Vérifier la présence de rapports réguliers sur l'état des systèmes d'information soumis à la direction. | I13: Des rapports sur l’état des systèmes d’information sont-ils soumis régulièrement à la direction ? | J13: OUI | K13: Programme de formation de la direction sur les enjeux des SI | L13: Absence de rapports réguliers sur l'état des systèmes d'information à la direction | M13: Élevée | N13: Manque de visibilité sur l'état des SI pour la prise de décision. | O13: Améliorez la visibilité sur l'état des SI pour faciliter la prise de décision.
H14: Évaluer la participation de la direction aux décisions stratégiques liées à l'informatique. | I14: La direction participe-t-elle activement aux décisions stratégiques liées à l’informatique ? | J14: OUI | K14: Désignation officielle des responsables de projets informatiques | L14: Désengagement de la direction dans les décisions stratégiques liées à l'informatique | M14: Élevée | N14: Décisions stratégiques informatiques prises sans expertise adéquate. | O14: Assurez-vous que les décisions stratégiques informatiques bénéficient d'une expertise adéquate.
H15: Confirmer l'allocation de budgets adaptés aux enjeux informatiques identifiés par la direction. | I15: Les budgets alloués correspondent-ils aux enjeux informatiques identifiés par la direction ? | J15: NON | K15: Comptes rendus des revues de projet | L15: Budget informatique inadapté aux enjeux identifiés | M15: Élevée | N15: Investissements insuffisants pour répondre aux besoins critiques. | O15: Allouez des investissements suffisants pour répondre aux besoins critiques.
H16: Vérifier que la direction dispose d'une formation aux enjeux actuels des systèmes d'information. | I16: La direction bénéficie-t-elle d’une formation sur les enjeux actuels des systèmes d’information ? | J16: OUI | K16: Documentation des décisions pour les phases clés des projets | L16: Manque de formation de la direction sur les enjeux des systèmes d'information | M16: Élevée | N16: Direction mal informée sur les enjeux technologiques et leurs impacts. | O16: Informez régulièrement la direction sur les enjeux technologiques et leurs impacts.
G17: Vérifier en pratique que le leadership des grands projets est assuré par les organes de gestion | H17: Examiner les documents de désignation des responsables de grands projets informatiques. | I17: Les responsables des grands projets informatiques sont-ils désignés officiellement ? | J17: OUI | K17: Document d'alignement des objectifs de projet avec la stratégie | L17: Responsables de projets informatiques non désignés officiellement | M17: Élevée | N17: Projets bloqués ou retardés faute de responsables identifiés. | O17: Désignez des responsables clairs pour chaque projet.
H18: Vérifier la présence de revues de projet auxquelles participent les organes de gestion. | I18: Des revues de projet impliquant les organes de gestion sont-elles régulièrement organisées ? | J18: OUI | K18: Procédures de résolution des problèmes signalés par les organes de gestion | L18: Absence de revues de projet impliquant les organes de gestion | M18: Élevée | N18: Absence de suivi des projets entraînant des dérives budgétaires et temporelles. | O18: Mettez en place un suivi rigoureux des projets pour éviter les dérives.
H19: Analyser les procès-verbaux de décision pour les phases clés des projets. | I19: Les décisions pour les phases clés des projets sont-elles documentées dans des procès-verbaux ? | J19: OUI | K19: Description des responsabilités de la MOA dans les documents internes | L19: Décisions des phases clés des projets non documentées | M19: Élevée | N19: Perte de traçabilité des décisions clés, compliquant le suivi. | O19: Tracez toutes les décisions clés pour faciliter le suivi.
H20: Confirmer l'alignement des objectifs des projets avec la stratégie organisationnelle. | I20: Les objectifs des projets sont-ils alignés sur la stratégie de l’organisation ? | J20: OUI | K20: Procès-verbaux des ateliers de conception avec les métiers | L20: Objectifs des projets non alignés sur la stratégie organisationnelle | M20: Élevée | N20: Projets non prioritaires gaspillant des ressources limitées. | O20: Priorisez les projets pour optimiser l'utilisation des ressources.
H21: Évaluer l'efficacité des mécanismes de résolution des problèmes signalés par les organes de gestion. | I21: Les mécanismes de résolution des problèmes signalés par les organes de gestion sont-ils efficaces ? | J21: NON | K21: Spécifications fonctionnelles validées par les utilisateurs métiers | L21: Mécanismes de résolution des problèmes inefficaces | M21: Élevée | N21: Problèmes récurrents non résolus faute de processus efficaces. | O21: Élaborez des processus efficaces pour résoudre les problèmes récurrents.
G22: Vérifier que les métiers assurent leur rôle de MOA | H22: Vérifier la définition officielle des responsabilités de la maîtrise d'ouvrage (MOA) dans les documents internes. | I22: Les responsabilités de la maîtrise d’ouvrage (MOA) sont-elles clairement définies dans les documents internes ? | J22: OUI | K22: Documentation des retours utilisateurs et des évolutions applicatives | L22: Responsabilités de la MOA mal définies dans les documents internes | M22: Élevée | N22: Chevauchement des rôles ou responsabilités non assumées. | O22: Clarifiez les rôles et responsabilités pour éviter les chevauchements.
H23: Analyser la participation des représentants métiers aux ateliers de conception des applications. | I23: Les représentants métiers participent-ils aux ateliers de conception des applications ? | J23: OUI | K23: Rapports de conformité des solutions déployées aux besoins métiers | L23: Faible participation des métiers aux ateliers de conception | M23: Élevée | N23: Solutions inadaptées aux besoins réels des utilisateurs finaux. | O23: Impliquez les utilisateurs finaux dans la conception des solutions.
H24: Confirmer la validation des spécifications fonctionnelles par les utilisateurs métiers. | I24: Les spécifications fonctionnelles sont-elles validées par les utilisateurs métiers ? | J24: OUI | K24: Documents d'urbanisme informatique actualisés | L24: Spécifications fonctionnelles non validées par les utilisateurs métiers | M24: Élevée | N24: Erreurs dans les spécifications entraînant des développements inutiles. | O24: Vérifiez les spécifications pour éviter les développements inutiles.
H25: Évaluer la prise en compte des retours utilisateurs dans les évolutions des applications. | I25: Les retours utilisateurs sont-ils pris en compte dans les évolutions des applications ? | J25: OUI | K25: Documentation de l'architecture technique alignée sur l'urbanisme | L25: Retours utilisateurs ignorés dans les évolutions des applications | M25: Élevée | N25: Frustration des utilisateurs et baisse de l'adoption des outils. | O25: Sensibilisez les utilisateurs pour augmenter l'adoption des outils.
H26: Vérifier l'adéquation des solutions déployées avec les besoins opérationnels des métiers. | I26: Les solutions déployées correspondent-elles aux besoins opérationnels des métiers ? | J26: OUI | K26: Schémas directeurs mis à jour | L26: Solutions déployées ne correspondant pas aux besoins opérationnels des métiers | M26: Élevée | N26: Applications peu utilisées ou rejetées par les métiers. | O26: Évaluez les besoins des métiers avant de développer de nouvelles applications.
F27: Planification stratégique | G27: Vérifier la couverture du périmètre fonctionnel | H27: Examiner les documents d'urbanisme informatique pour s'assurer de leur existence et actualisation. | I27: Existe-t-il des documents d’urbanisme informatique actualisés ? | J27: OUI | K27: Procédures de communication des documents d'urbanisme | L27: Urbanisme informatique non actualisé ou inaccessible | M27: Élevée | N27: Architecture désorganisée compliquant les évolutions futures. | O27: Rationalisez l'architecture pour faciliter les évolutions futures.
H28: Vérifier la cohérence entre l'urbanisme défini et l'architecture technique en place. | I28: L’architecture technique est-elle cohérente avec l’urbanisme défini ? | J28: OUI | K28: Référentiels clients, fournisseurs et articles uniques | L28: Architecture technique non alignée sur l'urbanisme défini | M28: Élevée | N28: Systèmes instables ou incompatibles entre eux. | O28: Assurez la compatibilité et la stabilité des systèmes entre eux.
H29: Confirmer l'alignement de l'urbanisme avec les objectifs stratégiques de l'organisation. | I29: L’urbanisme informatique s’aligne-t-il sur les objectifs stratégiques de l’organisation ? | J29: OUI | K29: Procédures standardisées de saisie des données critiques | L29: Urbanisme informatique non aligné sur les objectifs stratégiques | M29: Élevée | N29: Investissements technologiques non alignés sur les objectifs stratégiques. | O29: Alignez les investissements technologiques sur les objectifs stratégiques.
H30: Évaluer la mise à jour régulière des schémas directeurs en fonction des évolutions technologiques. | I30: Les schémas directeurs sont-ils mis à jour en fonction des évolutions technologiques ? | J30: OUI | K30: Documentation des contrôles automatisés anti-doublons | L30: Schémas directeurs obsolètes face aux évolutions technologiques | M30: Élevée | N30: Technologies obsolètes limitant la compétitivité. | O30: Modernisez les technologies pour rester compétitif.
H31: Vérifier la communication des documents d'urbanisme aux parties prenantes concernées. | I31: Les documents d’urbanisme sont-ils communiqués aux parties prenantes concernées ? | J31: OUI | K31: Programme de formation des utilisateurs aux règles de saisie | L31: Mauvaise communication des documents d'urbanisme aux parties prenantes | M31: Élevée | N31: Incompréhension des orientations techniques par les parties prenantes. | O31: Communiquez clairement les orientations techniques aux parties prenantes.
G32: Vérifier l’existence d’une analyse à jour des procédures de pilotage et de mise à jour du plan informatique | H32: Analyser les référentiels clients, fournisseurs et articles pour vérifier leur unicité et cohérence. | I32: Les référentiels clients, fournisseurs et articles sont-ils uniques et cohérents ? | J32: NON | K32: Règles de gestion documentées pour les référentiels | L32: Référentiels clients, fournisseurs et articles non uniques ou incohérents | M32: Élevée | N32: Données incohérentes perturbant les analyses et décisions. | O32: Standardisez les données pour éviter les incohérences.
H33: Vérifier l'existence de procédures de saisie standardisées pour les données critiques. | I33: Existe-t-il des procédures standardisées pour la saisie des données critiques ? | J33: OUI | K33: Liste des indicateurs de performance (KPI) de la DSI | L33: Absence de procédures standardisées pour la saisie des données critiques | M33: Élevée | N33: Erreurs fréquentes dans les données critiques. | O33: Contrôlez régulièrement la qualité des données critiques.
H34: Confirmer la mise en place de contrôles automatisés pour éviter les doublons dans les référentiels. | I34: Des contrôles automatisés évitent-ils les doublons dans les référentiels ? | J34: OUI | K34: Tableaux de bord des KPI opérationnels et financiers | L34: Doublons dans les référentiels non contrôlés automatiquement | M34: Élevée | N34: Doublons et incohérences non détectés affectant la qualité des données. | O34: Détectez et éliminez les doublons et incohérences dans les données.
H35: Évaluer la formation des utilisateurs aux règles de saisie des données. | I35: Les utilisateurs sont-ils formés aux règles de saisie des données ? | J35: OUI | K35: Outils de mesure et reporting des KPI | L35: Utilisateurs non formés aux règles de saisie des données | M35: Élevée | N35: Saisie erronée des données par manque de formation. | O35: Formez les employés à la saisie correcte des données.
H36: Vérifier la documentation des règles de gestion applicables aux référentiels. | I36: Les règles de gestion applicables aux référentiels sont-elles documentées ? | J36: OUI | K36: Benchmarks sectoriels pour comparaison des KPI | L36: Règles de gestion des référentiels non documentées | M36: Élevée | N36: Gestion inefficace des référentiels due à l'absence de règles claires. | O36: Établissez des règles claires pour la gestion des référentiels.
G37: Vérifier l’existence des documents à jour d’urbanisme de l’Organisation | H37: Examiner les indicateurs de performance (KPI) définis pour la fonction informatique. | I37: Quels indicateurs de performance (KPI) sont définis pour la fonction informatique ? | J37: OUI | K37: Documents de prise de décision stratégique utilisant les KPI | L37: Indicateurs de performance (KPI) informatiques mal définis ou absents | M37: Moyenne | N37: Impossibilité d'évaluer la performance réelle des SI. | O37: Définissez des indicateurs pour évaluer la performance des SI.
H38: Vérifier que les KPI couvrent à la fois les aspects opérationnels et financiers. | I38: Les KPI couvrent-ils à la fois les aspects opérationnels et financiers ? | J38: OUI | K38: Organigramme actualisé de la DSI | L38: KPI ne couvrant pas les aspects opérationnels et financiers | M38: Élevée | N38: Décisions basées sur des informations partielles ou inexactes. | O38: Vérifiez l'exactitude des informations avant de prendre des décisions.
H39: Confirmer la mise en place d'outils de mesure et de reporting pour suivre les KPI. | I39: Des outils de mesure et de reporting permettent-ils de suivre les KPI ? | J39: OUI | K39: Descriptions de poste détaillées pour chaque fonction | L39: Outils de mesure et reporting des KPI inexistants ou inefficaces | M39: Élevée | N39: Manque de visibilité sur les coûts et la performance opérationnelle. | O39: Améliorez la visibilité sur les coûts et la performance opérationnelle.
H40: Évaluer la comparaison régulière des résultats avec des benchmarks sectoriels. | I40: Les résultats des KPI sont-ils comparés à des benchmarks sectoriels ? | J40: OUI | K40: Documentation de la répartition des rôles entre études, exploitation et support | L40: KPI non comparés à des benchmarks sectoriels | M40: Élevée | N40: Absence de benchmarking réduisant la compétitivité. | O40: Utilisez le benchmarking pour renforcer la compétitivité.
H41: Vérifier l'utilisation des KPI dans les prises de décision stratégiques de la DSI. | I41: Les KPI sont-ils utilisés dans les prises de décision stratégiques de la DSI ? | J41: OUI | K41: Plan d'effectifs de la DSI adapté aux besoins | L41: KPI non utilisés dans les prises de décision stratégiques de la DSI | M41: Élevée | N41: Stratégie IT non ajustée faute de KPIs pertinents. | O41: Définissez des KPIs pertinents pour ajuster la stratégie IT.
G42: Vérifier l’existence d’une analyse à jour des procédures de pilotage et de mise à jour du plan d’occupation des sols (POS) | H42: Analyser l'organigramme actuel de la DSI pour s'assurer de son exactitude. | I42: L’organigramme de la DSI reflète-t-il avec exactitude sa structure actuelle ? | J42: NON | K42: Plans de formation individuels des membres de la DSI | L42: Organigramme de la DSI ne reflétant pas la structure actuelle | M42: Élevée | N42: Structure organisationnelle inadaptée aux besoins actuels. | O42: Adaptez la structure organisationnelle aux besoins actuels.
H43: Vérifier la correspondance entre les postes définis et les responsabilités exercées. | I43: Les postes définis correspondent-ils aux responsabilités réellement exercées ? | J43: OUI | K43: Programmes de formation correspondant aux compétences requises | L43: Descriptions de poste ne correspondant pas aux responsabilités réelles | M43: Élevée | N43: Employés surchargés ou sous-utilisés selon les postes. | O43: Optimisez la répartition des tâches pour éviter la surcharge.
H44: Confirmer la séparation claire des rôles entre les équipes études, exploitation et support. | I44: Les rôles entre équipes études, exploitation et support sont-ils clairement séparés ? | J44: OUI | K44: Bilan des heures de formation vs objectifs | L44: Rôles mal séparés entre études, exploitation et support | M44: Élevée | N44: Conflits de responsabilités entre équipes. | O44: Clarifiez les responsabilités entre équipes pour éviter les conflits.
H45: Évaluer l'adéquation des effectifs avec les besoins opérationnels et projets en cours. | I45: Les effectifs de la DSI sont-ils adaptés aux besoins opérationnels et projets en cours ? | J45: OUI | K45: Évaluations d'impact des formations sur les compétences | L45: Effectifs de la DSI inadaptés à la charge de travail | M45: Élevée | N45: Délais non tenus et qualité dégradée faute de ressources. | O45: Allouez les ressources nécessaires pour respecter les délais et la qualité.
H46: Vérifier la présence de descriptions de poste détaillées pour chaque fonction informatique. | I46: Chaque fonction informatique dispose-t-elle d’une description de poste détaillée ? | J46: OUI | K46: Contrats des informaticiens incluant des clauses de confidentialité | L46: Absence de plans de succession pour les postes clés de la DSI | M46: Élevée | N46: Risque de perte de compétences clés en cas de départ. | O46: Identifiez et formez des remplaçants pour les compétences clés.
G47: Vérifier la cohérence et l’homogénéité des technologies | H47: Examiner les plans de formation individuels des membres de la DSI. | I47: Les membres de la DSI ont-ils des plans de formation individuels ? | J47: OUI | K47: Clauses de non-concurrence dans les contrats du personnel | L47: Plans de formation non adaptés aux compétences requises | M47: Élevée | N47: Compétences manquantes pour répondre aux besoins technologiques. | O47: Formez les employés aux nouvelles technologies.
H48: Vérifier l'adéquation des formations aux compétences requises pour les postes occupés. | I48: Les formations suivies correspondent-elles aux compétences requises pour leurs postes ? | J48: OUI | K48: Documentation de conformité aux obligations légales de protection des données | L48: Formations suivies ne correspondant pas aux besoins techniques et fonctionnels | M48: Élevée | N48: Formations inefficaces n'adressant pas les lacunes réelles. | O48: Adaptez les formations pour combler les lacunes réelles.
H49: Confirmer le suivi des heures de formation effectuées par rapport aux objectifs fixés. | I49: Les heures de formation effectuées sont-elles comparées aux objectifs fixés ? | J49: OUI | K49: Procédures de contrôle des accès non autorisés aux systèmes | L49: Efficacité des formations non évaluée | M49: Élevée | N49: Ressources humaines inadaptées aux nouvelles technologies. | O49: Recrutez ou formez des ressources adaptées aux nouvelles technologies.
H50: Évaluer l'impact des formations sur l'amélioration des compétences et des processus. | I50: Les formations ont-elles un impact mesurable sur l’amélioration des compétences et processus ? | J50: OUI | K50: Politique de chiffrement conforme aux exigences réglementaires | L50: Compétences du personnel non mises à jour face aux évolutions technologiques | M50: Élevée | N50: Risque accru de fuites de données sensibles. | O50: Renforcez les contrôles pour prévenir les fuites de données sensibles.
H51: Vérifier la présence de clauses de confidentialité dans les contrats des informaticiens. | I51: Les contrats des informaticiens incluent-ils des clauses de confidentialité ? | J51: OUI | K51: Procédures documentées de gestion des incidents de sécurité | L51: Absence de clauses de confidentialité dans les contrats des informaticiens | M51: Élevée | N51: Anciens employés conservant un accès non autorisé. | O51: Révoquez immédiatement les accès des anciens employés.
G52: Vérifier l’existence et l’unicité des référentiels (clients, fournisseurs, articles…) et des saisies | H52: Analyser les dispositions contractuelles relatives à la non-concurrence après départ. | I52: Les dispositions contractuelles prévoient-elles des clauses de non-concurrence après départ ? | J52: OUI | K52: Plans de reprise d'activité (PRA) testés | L52: Droits d'accès non révoqués lors des départs ou mutations | M52: Élevée | N52: Conflits d'intérêts non détectés ou mal gérés. | O52: Mettez en place un processus de détection et gestion des conflits d'intérêts.
H53: Confirmer le respect des obligations légales en matière de protection des données personnelles. | I53: Les obligations légales en matière de protection des données personnelles sont-elles respectées ? | J53: OUI | K53: Mises à jour annuelles des documents de continuité d'activité | L53: Dispositifs insuffisants pour prévenir les conflits d'intérêts | M53: Élevée | N53: Sanctions légales et amendes pour non-conformité. | O53: Conformez-vous aux réglementations pour éviter les sanctions.
H54: Évaluer les mesures techniques mises en place pour prévenir les accès non autorisés. | I54: Des mesures techniques empêchent-elles les accès non autorisés aux systèmes ? | J54: OUI | K54: Programme de sensibilisation aux risques de cybersécurité | L54: Non-conformité aux lois sur la protection des données et la cybersécurité | M54: Élevée | N54: Incidents de sécurité non maîtrisés faute de procédures. | O54: Élaborez des procédures pour maîtriser les incidents de sécurité.
H55: Vérifier la conformité des pratiques de chiffrement avec les exigences réglementaires. | I55: Les pratiques de chiffrement sont-elles conformes aux exigences réglementaires ? | J55: NON | K55: Traçabilité des actions correctives suite aux incidents de sécurité | L55: Procédures de réponse aux incidents de sécurité inexistantes ou inefficaces | M55: Élevée | N55: Impossibilité de restaurer les systèmes après un incident. | O55: Testez régulièrement les plans de restauration des systèmes.
H56: Examiner les procédures de gestion des incidents de sécurité informatique. | I56: Existe-t-il des procédures documentées pour gérer les incidents de sécurité informatique ? | J56: OUI | K56: Procédures de surveillance des accès aux serveurs et bases de données | L56: Plans de reprise d'activité (PRA) non testés régulièrement | M56: Élevée | N56: Systèmes vulnérables aux attaques actuelles. | O56: Renforcez la sécurité des systèmes contre les attaques actuelles.
F57: Budgets et coûts informatiques | G57: Évaluer l’organisation et les processus existants | H57: Vérifier l'existence de tests réguliers des plans de reprise d'activité (PRA). | I57: Les plans de reprise d’activité (PRA) sont-ils testés régulièrement ? | J57: OUI | K57: Documentation de la séparation des environnements (dev, test, prod) | L57: Politiques de sécurité non mises à jour face aux menaces actuelles | M57: Élevée | N57: Données exposées en cas de violation. | O57: Protégez les données contre les violations.
H58: Confirmer la mise à jour annuelle des documents relatifs à la continuité d'activité. | I58: Les documents relatifs à la continuité d’activité sont-ils mis à jour annuellement ? | J58: NON | K58: Contrôles d'accès physiques et logiques aux infrastructures critiques | L58: Chiffrement des données non conforme aux exigences réglementaires | M58: Moyenne | N58: Invalidité des signatures électroniques dans un cadre légal. | O58: Utilisez des signatures électroniques conformes aux exigences légales.
H59: Évaluer la sensibilisation des équipes aux risques liés à la cybersécurité. | I59: Les équipes sont-elles sensibilisées aux risques liés à la cybersécurité ? | J59: OUI | K59: Procédures documentées de sauvegarde et restauration des données | L59: Pratiques de signature électronique non conformes aux normes légales | M59: Élevée | N59: Risques juridiques liés à l'utilisation de logiciels piratés. | O59: Évitez l'utilisation de logiciels piratés pour réduire les risques juridiques.
H60: Vérifier la traçabilité des actions correctives suite à des incidents de sécurité. | I60: Les actions correctives suite à des incidents de sécurité sont-elles tracées ? | J60: OUI | K60: Rapports de mise en œuvre des recommandations d'audits précédents | L60: Utilisation de logiciels non licenciés non contrôlée | M60: Élevée | N60: Violations involontaires de la propriété intellectuelle. | O60: Sensibilisez les équipes aux enjeux de la propriété intellectuelle.
H61: Analyser les mécanismes de surveillance des accès aux serveurs et bases de données. | I61: Les accès aux serveurs et bases de données sont-ils surveillés efficacement ? | J61: OUI | K61: Documentation des actions correctives issues des audits antérieurs | L61: Sensibilisation insuffisante aux enjeux de la propriété intellectuelle | M61: Élevée | N61: Non-conformité aux exigences légales d'archivage. | O61: Conformez-vous aux exigences légales d'archivage.
G62: Vérifier l’existence des ratios et des éléments de benchmark (interne et/ou externe, ratio coûts/CA, … | H62: Confirmer la séparation des environnements de développement, test et production. | I62: Les environnements de développement, test et production sont-ils séparés ? | J62: OUI | K62: Retours d'expérience des audits intégrés dans les processus | L62: Processus d'archivage électronique non conformes aux exigences légales | M62: Moyenne | N62: Documents inaccessibles en cas d'audit ou de litige. | O62: Assurez l'accessibilité des documents en cas d'audit.
H63: Évaluer l'efficacité des contrôles d'accès physiques et logiques aux infrastructures critiques. | I63: Les contrôles d’accès physiques et logiques aux infrastructures critiques sont-ils efficaces ? | J63: OUI | K63: Documentation d'intégration des bonnes pratiques sectorielles | L63: Documents archivés non traçables ou inaccessibles | M63: Moyenne | N63: Absence de détection des écarts de conformité. | O63: Mettez en place un système de détection des écarts de conformité.
H64: Vérifier la documentation des procédures de sauvegarde et de restauration des données. | I64: Les procédures de sauvegarde et de restauration des données sont-elles documentées ? | J64: OUI | K64: Procédures formalisées de création et fonctionnement des comités | L64: Absence d'audits internes ou externes sur la conformité réglementaire | M64: Élevée | N64: Changements non contrôlés entraînant des incidents. | O64: Contrôlez rigoureusement les changements pour éviter les incidents.
H65: Examiner les rapports d'audit précédents pour identifier les recommandations récurrentes. | I65: Les recommandations des audits précédents ont-elles été mises en œuvre ? | J65: OUI | K65: Comptes rendus réguliers des réunions des comités stratégiques | L65: Procédures de gestion des changements informatiques non formalisées | M65: Élevée | N65: Absence de traçabilité des modifications critiques. | O65: Tracez toutes les modifications critiques.
H66: Confirmer la mise en œuvre des actions correctives issues des audits antérieurs. | I66: Les actions correctives issues des audits antérieurs ont-elles été appliquées ? | J66: OUI | K66: Listes de présence vérifiables aux comités | L66: Interventions techniques sur les applications critiques non consignées | M66: Élevée | N66: Contamination des environnements de production par des erreurs. | O66: Isolez les environnements de test et de production.
F67: Mesure et suivi de la performance informatique | G67: Vérifier que des objectifs de court, moyen et long termes existent et sont assignés à la DSI (approche BSC ?) et que ces objectifs sont déclinés au sein de l’entité | H67: Évaluer l'amélioration continue des processus grâce aux retours d'expérience des audits. | I67: Les processus s’améliorent-ils grâce aux retours d’expérience des audits ? | J67: OUI | K67: Documentation d'alignement des décisions des comités avec la stratégie | L67: Environnements de développement, test et production non séparés | M67: Élevée | N67: Accès non autorisés ou malveillants par des prestataires. | O67: Contrôlez les accès des prestataires externes.
H68: Vérifier l'intégration des bonnes pratiques sectorielles dans les méthodologies de travail. | I68: Les bonnes pratiques sectorielles sont-elles intégrées dans les méthodologies de travail ? | J68: OUI | K68: Traçabilité des priorités et projets suivis par les comités | L68: Accès des prestataires externes non contrôlés | M68: Élevée | N68: Instabilité des systèmes due à des correctifs non testés. | O68: Testez rigoureusement les correctifs avant déploiement.
H69: Présence de procédures formalisées pour la création et le fonctionnement des comités informatiques. | I69: Existe-t-il des procédures formalisées pour la création et le fonctionnement des comités ? | J69: OUI | K69: Charte informatique signée et diffusée | L69: Correctifs non validés avant déploiement en production | M69: Élevée | N69: Temps d'arrêt prolongés en cas d'incident majeur. | O69: Élaborez un plan de reprise d'activité pour les incidents majeurs.
H70: Existence de comptes rendus réguliers des réunions des comités stratégiques et de pilotage. | I70: Des comptes rendus réguliers des réunions des comités stratégiques sont-ils disponibles ? | J70: OUI | K70: Historique des mises à jour de la charte informatique | L70: Procédures de gestion des incidents majeurs inexistantes | M70: Élevée | N70: Impossibilité d'analyser les tendances ou causes racines. | O70: Analysez les tendances pour identifier les causes racines.
H71: Vérification de la participation effective des représentants des différentes directions aux comités. | I71: La participation effective des représentants des directions aux comités est-elle vérifiable ? | J71: OUI | K71: Documentation des rôles réels de la DSI vs charte | L71: Registre des incidents non tenu à jour | M71: Élevée | N71: Employés incapables de réagir efficacement aux crises. | O71: Formez les employés à la gestion de crise.
G72: Vérifier l’existence d’un comité informatique regroupant les différentes directions de l’organisation | H72: Analyse de l'alignement des décisions des comités avec les objectifs stratégiques de l'organisation. | I72: Les décisions des comités correspondent-elles aux objectifs stratégiques de l’organisation ? | J72: NON | K72: Mécanismes de contrôle du respect de la charte | L72: Équipes non formées aux procédures d'urgence | M72: Élevée | N72: Données perdues définitivement en cas de sinistre. | O72: Sauvegardez régulièrement les données critiques.
H73: Évaluation de la traçabilité des priorités et des projets suivis par les comités. | I73: Les priorités et projets suivis par les comités sont-ils traçables ? | J73: OUI | K73: Preuves de connaissance de la charte par les collaborateurs | L73: Sauvegardes non testées régulièrement | M73: Élevée | N73: Interruptions de service faute de redondance. | O73: Mettez en place des systèmes redondants pour éviter les interruptions.
H74: Existence d'une charte informatique signée et diffusée aux parties prenantes. | I74: La charte informatique est-elle signée et diffusée aux parties prenantes ? | J74: OUI | K74: Rapports d'évaluation sur la maîtrise des SI pour la direction | L74: Infrastructures critiques sans redondance | M74: Élevée | N74: Délais de résolution prolongés faute de SLA. | O74: Établissez des SLA contraignants pour réduire les délais de résolution.
H75: Vérification de la mise à jour régulière de la charte en fonction des évolutions organisationnelles. | I75: La charte est-elle mise à jour pour refléter les changements organisationnels ? | J75: OUI | K75: Ordres du jour des instances décisionnelles mentionnant la gouvernance IT | L75: Contrats de maintenance sans engagements de niveaux de service (SLA) | M75: Élevée | N75: Contrats désavantageux ou non adaptés aux besoins. | O75: Revoyez les contrats pour qu'ils répondent aux besoins actuels.
H76: Adéquation des rôles et responsabilités de la DSI définis dans la charte avec les activités réelles. | I76: Les rôles de la DSI dans la charte correspondent-ils à leurs activités réelles ? | J76: OUI | K76: Documents d'arbitrage budgétaire des projets IT par la direction | L76: Clauses contractuelles avec les fournisseurs IT obsolètes | M76: Élevée | N76: Prestataires sous-performants non identifiés. | O76: Surveillez et évaluez régulièrement les prestataires.
G77: Évaluer la pertinence des indicateurs de qualité et de performance ainsi que les moyens et outils de mesure | H77: Présence de mécanismes de contrôle pour garantir le respect de la charte informatique. | I77: Des mécanismes de contrôle garantissent-ils le respect de la charte informatique ? | J77: OUI | K77: Programmes de formation des dirigeants aux enjeux des SI | L77: Performances des prestataires non comparées aux engagements | M77: Élevée | N77: Sélection de partenaires inadaptés faute de processus. | O77: Définissez des critères clairs pour sélectionner les partenaires.
H78: Évaluation de la connaissance de la charte par les collaborateurs concernés. | I78: Les collaborateurs concernés connaissent-ils la charte informatique ? | J78: OUI | K78: Dispositifs de remontée d'alertes sur les risques informatiques | L78: Processus de sélection des partenaires technologiques non formalisés | M78: Élevée | N78: Fuites de données via des fournisseurs non fiables. | O78: Choisissez des fournisseurs fiables pour éviter les fuites de données.
H79: Existence de rapports d'évaluation de la maîtrise des SI par les organes de direction. | I79: La direction dispose-t-elle de rapports d’évaluation sur la maîtrise des SI ? | J79: OUI | K79: Documents de désignation formelle des responsables de projets par les instances | L79: Contrats sans clauses de confidentialité ou protection des données | M79: Élevée | N79: Projets sous-financés entraînant des échecs. | O79: Allouez des budgets suffisants pour éviter l'échec des projets.
H80: Vérification de la présence de la gouvernance informatique dans les ordres du jour des instances décisionnelles. | I80: La gouvernance informatique figure-t-elle aux ordres du jour des instances décisionnelles ? | J80: NON | K80: Documentation de cohérence des objectifs de projet avec la stratégie | L80: Budget IT inadapté aux besoins opérationnels | M80: Élevée | N80: Difficulté à suivre et contrôler les dépenses. | O80: Mettez en place un suivi financier rigoureux.
H81: Analyse de l'implication de la direction dans les arbitrages budgétaires liés aux projets IT. | I81: La direction est-elle impliquée dans les arbitrages budgétaires des projets IT ? | J81: OUI | K81: Retours d'expérience des projets précédents documentés | L81: Dépenses informatiques non traçables | M81: Élevée | N81: Dépassements budgétaires non justifiés ou expliqués. | O81: Analysez les dépassements budgétaires pour en comprendre les causes.
G82: Vérifier que la DSI tient un tableau de bord (idéalement de type BSC) permettant un suivi consolidé de la performance (opérationnelle et financière) et de la qualité des prestations informatiques | H82: Évaluation de la formation des dirigeants aux enjeux actuels des systèmes d'information. | I82: Les dirigeants sont-ils formés aux enjeux actuels des systèmes d’information ? | J82: OUI | K82: Comptes rendus des revues d'avancement des projets avec les parties prenantes | L82: Écarts budgétaires non documentés ou expliqués | M82: Élevée | N82: Gaspillage de ressources faute d'optimisation. | O82: Optimisez l'utilisation des ressources pour éviter le gaspillage.
H83: Présence de dispositifs de remontée d'alertes liées aux risques informatiques vers la direction. | I83: Existe-t-il des dispositifs de remontée d’alertes sur les risques informatiques vers la direction ? | J83: OUI | K83: Documents internes définissant les responsabilités de la MOA | L83: Coûts des licences et infrastructures non optimisés | M83: Élevée | N83: Décisions financières inadaptées aux besoins IT. | O83: Alignez les décisions financières sur les besoins IT.
