Workbook

Sheet Global
A1: Domaine | B1: Points de Contrôle | C1: Objectifs de Contrôle | D1: Critère d’Évaluation | E1: Question d’Évaluation | F1: Réponses | G1: Documents Requis | H1: Risques | I1: Criticités | J1: Conséquences | K1: Recommandations
A2: Application en service | B2: Organisation | C2: S’assurer de l’existence d'un comité informatique | D2: Existence d'un comité informatique | E2: Existe-t-il un comité informatique ? | F2: OUI | G2: Charte du comité informatique, liste des membres, procès-verbaux des réunions | H2: Absence de gouvernance claire | I2: Élevé | J2: Décisions incohérentes et manque de coordination | K2: Mettre en place un comité de gouvernance structuré
D3: Le Comité est présidé par le Directeur Général | E3: Le comité est-il présidé par le Directeur Général ? | F3: OUI | G3: Document de nomination du Directeur Général, procès-verbaux des réunions | H3: Manque de leadership dans la prise de décisions stratégiques | I3: Élevé | J3: Retards et décisions inefficaces | K3: Nommer un leader compétent avec des pouvoirs clairs
D4: Les directions utilisatrices sont représentées au sein de ce Comité | E4: Les directions utilisatrices sont-elles représentées au sein du comité ? | F4: OUI | G4: Liste des membres du comité, organigramme | H4: Mauvaise représentation des parties prenantes | I4: Élevé | J4: Conflits d'intérêts et mauvaise acceptation des décisions | K4: Garantir l’inclusion des parties prenantes critiques
D5: Les directions utilisatrices sont influentes au sein de ce Comité | E5: Les directions utilisatrices sont-elles influentes au sein du comité ? | F5: NON | G5: Comptes rendus des réunions, décisions prises incluant les contributions des directions utilisatrices | H5: Négligence des apports des directions utilisatrices | I5: Élevé | J5: Solutions non adaptées aux besoins réels | K5: Renforcer la collaboration avec les utilisateurs finaux
D6: Présence de membres qualifiés et diversifiés | E6: Les membres du comité sont-ils qualifiés et diversifiés ? | F6: OUI | G6: Profils des membres, CV, évaluation des compétences | H6: Compétences inadéquates des membres du comité | I6: Élevé | J6: Erreurs stratégiques et décisions inefficaces | K6: Former ou remplacer les membres avec des experts qualifiés
C7: S’assurer de l’existence d'une politique relative aux applications | D7: Il existe une politique relative aux applications au sein de l'institution | E7: Une politique relative aux applications existe-t-elle au sein de l'institution ? | F7: OUI | G7: Politique des applications, document de gouvernance | H7: Non-existence ou non-application de la politique. | I7: Élevé | J7: Désorganisation et manque de cadre | K7: Élaborer et appliquer une politique claire et documentée
D8: La politique est connue des utilisateurs d'applications | E8: Les utilisateurs d'applications connaissent-ils cette politique ? | F8: OUI | G8: Rapport de sensibilisation ou de communication | H8: Méconnaissance des obligations des utilisateurs | I8: Élevé | J8: Non-respect des procédures et inefficacité | K8: Sensibiliser et former les utilisateurs sur leurs responsabilités
D9: La politique est largement diffusée | E9: La politique est-elle largement diffusée ? | F9: NON | G9: Support de communication (emails, brochures, affiches) | H9: Faible diffusion des informations | I9: Moyen | J9: Manque de transparence et communication inefficace | K9: Utiliser des outils modernes de gestion des informations
D10: La politique est mise en œuvre | E10: La politique est-elle mise en œuvre ? | F10: PAS | G10: Rapports d'audit de conformité | H10: Non-conformité aux normes | I10: Élevé | J10: Risques juridiques et pénalités | K10: Auditer et corriger les écarts avec les normes
D11: La politique couvre l'ensemble du cycle de vie de l’application | E11: La politique couvre-t-elle l'ensemble du cycle de vie de l'application ? | F11: PAS | G11: Documentation de la politique, schéma de cycle de vie | H11: Gestion incohérente des étapes du cycle de vie des applications | I11: Élevé | J11: Dysfonctionnements fréquents | K11: Automatiser le suivi du cycle de vie des applications
C12: S’assurer que les rôle et responsabilités des utilisateurs sont bien définis | D12: Le rôle et les responsabilités des utilisateurs vis-à-vis de l’application sont clairement identifiés | E12: Les rôles et responsabilités des utilisateurs vis-à-vis de l'application sont-ils clairement identifiés ? | F12: OUI | G12: Matrice des rôles et responsabilités, charte utilisateur | H12: Absence de définition claire des rôles | I12: Élevé | J12: Confusion et responsabilités non assumées | K12: Formaliser et communiquer les rôles clairement
D13: Le rôle et les responsabilités des utilisateurs vis-à-vis de l’application couvrent l’analyse des risques | E13: Les rôles et responsabilités des utilisateurs vis-à-vis de l'application couvrent-ils l'analyse des risques ? | F13: NON | G13: Documentation d'analyse des risques, rapports spécifiques | H13: Non-réalisation des analyses des risques | I13: Élevé | J13: Survenue imprévisible de risques importants | K13: Planifier et réaliser des analyses régulières des risques
D14: Le rôle et les responsabilités des utilisateurs vis-à-vis de l’application couvrent la définition des besoins de sécurité | E14: Les rôles et responsabilités des utilisateurs vis-à-vis de l'application couvrent-ils la définition des besoins de sécurité ? | F14: NON | G14: Expression des besoins de sécurité | H14: Non-définition des besoins de sécurité | I14: Élevé | J14: Failles exploitables par des acteurs malveillants | K14: Identifier et intégrer les exigences sécuritaires dès la conception
D15: Le rôle et les responsabilités des utilisateurs vis-à-vis de l’application couvrent la gestion des changements et des évolutions | E15: Les rôles et responsabilités des utilisateurs vis-à-vis de l'application couvrent-ils la gestion des changements et des évolutions ? | F15: NON | G15: Processus de gestion des changements | H15: Changements mal gérés | I15: Élevé | J15: Instabilité du système | K15: Mettre en place un processus de gestion des changements standardisé
D16: Le rôle et les responsabilités des utilisateurs vis-à-vis de l’application couvrent l’administration de l’application | E16: Les rôles et responsabilités des utilisateurs vis-à-vis de l'application couvrent-ils l'administration de l'application ? | F16: NON | G16: Procédure d'administration de l'application | H16: Administration non sécurisée | I16: Élevé | J16: Accès non autorisé et perte de données | K16: Renforcer les contrôles d’administration et les audits
C17: S’assurer qu’une analyse des risques a été réalisée | D17: Une analyse des risques spécifique à l'application a été réalisée | E17: Une analyse des risques spécifique à l'application a-t-elle été réalisée ? | F17: OUI | G17: Rapport d'analyse des risques spécifiques | H17: Documentation insuffisante des risques critiques | I17: Moyen | J17: Problèmes non identifiés et résolus | K17: Compléter la documentation des risques prioritaires
D18: L'analyse des risques a débouché sur la définition des besoins de sécurité | E18: L'analyse des risques a-t-elle débouché sur la définition des besoins de sécurité ? | F18: OUI | G18: Plan de sécurité, documentation des besoins de sécurité | H18: Non-prise en compte des besoins de sécurité | I18: Élevé | J18: Vulnérabilité accrue face aux cyberattaques | K18: Prioriser les mécanismes de sécurité dans les opérations
D19: Les résultats de l'analyse des risques sont documentés et approuvés | E19: Les résultats de l'analyse des risques sont-ils documentés et approuvés ? | F19: OUI | G19: Rapports d'approbation, validation formelle des résultats | H19: Absence de validation formelle | I19: Élevé | J19: Détection tardive des erreurs | K19: Mettre en place des étapes de validation rigoureuses
D20: L'analyse des risques est mise à jour régulièrement | E20: L'analyse des risques est-elle mise à jour régulièrement ? | F20: OUI | G20: Historique des mises à jour, calendrier des analyses | H20: Analyses de risques obsolètes | I20: Élevé | J20: Décisions basées sur des informations incorrectes | K20: Mettre à jour les analyses périodiquement
D21: Les risques identifiés sont pris en compte dans le plan d'action de sécurité | E21: Les risques identifiés sont-ils pris en compte dans le plan d'action de sécurité ? | F21: OUI | G21: Plan d'action de sécurité, rapports d'intégration des risques | H21: Actions non mises en œuvre | I21: Élevé | J21: Maintien des risques identifiés | K21: Suivre et exécuter les plans d'action
C22: S’assurer que le prolongement de l'analyse de risque et de son expansion ont été réalisés | D22: Il y a eu un prolongement de l'analyse des risques et de l'expression des besoins de sécurité | E22: Le prolongement de l'analyse des risques et de l'expression des besoins de sécurité a-t-il eu lieu ? | F22: PAS | G22: Contrat de service SLA, documentation de mise en œuvre | H22: Non-respect des SLA | I22: Élevé | J22: Insatisfaction et perte de clients | K22: Surveiller et respecter strictement les SLA établis
D23: Un contrat de service (SLA) entre l'informatique et la direction utilisatrice a été mis en œuvre | E23: Un contrat de service (SLA) entre l'informatique et la direction utilisatrice a-t-il été mis en œuvre ? | F23: PAS | G23: Politique de contrôle d'accès, matrice des rôles | H23: Accès inappropriés | I23: Élevé | J23: Fuites ou abus de données sensibles | K23: Réévaluer et contrôler régulièrement les droits d'accès
D24: L'analyse des risques étendue couvre tous les aspects de l'application | E24: L'analyse des risques étendue couvre-t-elle tous les aspects de l'application ? | F24: OUI | G24: Journal des droits d'accès, rapports d'audit | H24: Absence de journalisation | I24: Élevé | J24: Impossibilité de retracer les activités suspectes | K24: Implémenter un système de journalisation des événements
D25: Les résultats de l'analyse des risques étendue sont communiqués aux parties prenantes | E25: Les résultats de l'analyse des risques étendue sont-ils communiqués aux parties prenantes ? | F25: OUI | G25: Journaux d'accès, rapports de surveillance | H25: Activités suspectes non détectées | I25: Élevé | J25: Survenue de failles de sécurité | K25: Utiliser des outils de surveillance et détection proactive
D26: L'analyse des risques étendue est utilisée pour la planification stratégique | E26: L'analyse des risques étendue est-elle utilisée pour la planification stratégique ? | F26: OUI | G26: Procédure de révocation des accès | H26: Retard dans la révocation des accès | I26: Élevé | J26: Accès non autorisé prolongé | K26: Automatiser la gestion des accès pour une révocation rapide
B27: Application | C27: S'assurer que l'accès aux ressources de l'application (données et transactions) est restreint par un système de gestion d'accès | D27: Contrôle d'accès basé sur les rôles est mis en place | E27: Un contrôle d'accès basé sur les rôles est-il mis en place ? | F27: OUI | G27: Spécifications techniques de l'authentification, rapports de mise en œuvre | H27: Faiblesse dans l’authentification | I27: Élevé | J27: Compromission des comptes et données sensibles | K27: Renforcer les mécanismes d'authentification
D28: Les droits d'accès sont attribués de manière appropriée | E28: Les droits d'accès sont-ils attribués de manière appropriée ? | F28: OUI | G28: Politique de mots de passe, guides utilisateurs | H28: Mauvaises pratiques de mots de passe | I28: Élevé | J28: Vulnérabilité aux attaques par force brute | K28: Éduquer les utilisateurs sur les bonnes pratiques de gestion des mots de passe
D29: Les accès sont journalisés et surveillés | E29: Les accès sont-ils journalisés et surveillés ? | F29: OUI | G29: Journaux des tentatives de connexion | H29: Tentatives suspectes non identifiées | I29: Élevé | J29: Intrusions non détectées | K29: Mettre en place des solutions de détection des anomalies
D30: Un processus est en place pour révoquer les accès | E30: Un processus est-il en place pour révoquer les accès ? | F30: PAS | G30: Rapports d'incidents, base de données des suivis d'incidents | H30: Absence de suivi des incidents | I30: Élevé | J30: Problèmes récurrents non résolus | K30: Créer un processus clair de gestion des incidents
D31: Les accès sont audités régulièrement | E31: Les accès sont-ils audités régulièrement ? | F31: NON | G31: Charte du comité informatique, liste des membres, procès-verbaux des réunions | H31: Absence de gouvernance claire | I31: Élevé | J31: Décisions incohérentes et manque de coordination | K31: Établir des structures de gouvernance précises et documentées
C32: S’assurer qu’une procédure de gestion des profils utilisateurs existe | D32: Procédure documentée pour la création, modification et suppression des profils | E32: Une procédure documentée pour la création, modification et suppression des profils existe-t-elle ? | F32: OUI | G32: Document de nomination du Directeur Général, procès-verbaux des réunions | H32: Manque de leadership dans la prise de décisions stratégiques | I32: Élevé | J32: Retards et décisions inefficaces | K32: Nommer un responsable qualifié pour les décisions stratégiques
D33: Les droits d'accès sont attribués en fonction des rôles | E33: Les droits d'accès sont-ils attribués en fonction des rôles ? | F33: OUI | G33: Liste des membres du comité, organigramme | H33: Mauvaise représentation des parties prenantes | I33: Moyen | J33: Conflits et résistance aux décisions prises | K33: Assurer une représentation équitable des parties prenantes
D34: Les profils sont révisés régulièrement | E34: Les profils sont-ils révisés régulièrement ? | F34: OUI | G34: Comptes rendus des réunions, décisions prises incluant les contributions des directions utilisatrices | H34: Négligence des apports des directions utilisatrices | I34: Moyen | J34: Solutions inadaptées aux besoins réels | K34: Renforcer les échanges avec les directions utilisatrices
D35: La procédure est communiquée aux parties prenantes | E35: La procédure est-elle communiquée aux parties prenantes ? | F35: PAS | G35: Profils des membres, CV, évaluation des compétences | H35: Compétences inadéquates des membres du comité | I35: Élevé | J35: Décisions inefficaces et erreurs majeures | K35: Organiser des formations ou ajuster la composition du comité
D36: Des outils d'automatisation sont utilisés pour la gestion des profils | E36: Des outils d'automatisation sont-ils utilisés pour la gestion des profils ? | F36: PAS | G36: Politique des applications, document de gouvernance | H36: Non-existence ou non-application de la politique | I36: Élevé | J36: Désorganisation opérationnelle | K36: Créer et appliquer une politique claire et standardisée
C37: Vérifier que l’identification des utilisateurs est réalisée | D37: Mécanismes d'identification uniques sont utilisés | E37: Des mécanismes d'identification uniques sont-ils utilisés ? | F37: OUI | G37: Rapport de sensibilisation ou de communication | H37: Méconnaissance des obligations des utilisateurs | I37: Moyen | J37: Utilisation incorrecte des applications | K37: Former les utilisateurs sur leurs responsabilités
D38: Authentification forte est mise en place | E38: Une authentification forte est-elle mise en place ? | F38: OUI | G38: Support de communication (emails, brochures, affiches) | H38: Faible diffusion des informations | I38: Moyen | J38: Collaboration et coordination limitées | K38: Utiliser des outils modernes pour améliorer la communication
D39: Procédure de gestion des identifiants est claire | E39: La procédure de gestion des identifiants est-elle claire ? | F39: OUI | G39: Rapports d'audit de conformité | H39: Non-conformité aux normes | I39: Élevé | J39: Risques juridiques et pertes financières | K39: Réaliser des audits réguliers pour garantir la conformité
D40: Les identifiants sont protégés | E40: Les identifiants sont-ils protégés ? | F40: OUI | G40: Documentation de la politique, schéma de cycle de vie | H40: Gestion incohérente des étapes du cycle de vie des applications | I40: Élevé | J40: Dysfonctionnements et retards fréquents | K40: Automatiser le suivi des étapes clés du cycle de vie.
D41: Les identifiants sont audités régulièrement | E41: Les identifiants sont-ils audités régulièrement ? | F41: NON | G41: Matrice des rôles et responsabilités, charte utilisateur | H41: Absence de définition claire des rôles | I41: Moyen | J41: Confusion et duplication des responsabilités | K41: Clarifier et documenter les rôles et responsabilités
C42: Vérifier qu’un mot de passe est associé à l'identifiant | D42: Politique de mots de passe est en place | E42: Une politique de mots de passe est-elle en place ? | F42: OUI | G42: Documentation d'analyse des risques, rapports spécifiques | H42: Non-réalisation des analyses des risques | I42: Élevé | J42: Risques non identifiés pouvant entraîner des interruptions majeures | K42: Mettre en place une stratégie d'analyse des risques régulière
D43: Les mots de passe sont stockés de manière sécurisée | E43: Les mots de passe sont-ils stockés de manière sécurisée ? | F43: OUI | G43: Expression des besoins de sécurité | H43: Non-définition des besoins de sécurité | I43: Élevé | J43: Failles exploitables entraînant des violations de données | K43: Identifier et documenter les besoins de sécurité dès la conception
D44: Procédure de gestion des mots de passe est claire | E44: La procédure de gestion des mots de passe est-elle claire ? | F44: PAS | G44: Processus de gestion des changements | H44: Changements mal gérés | I44: Élevé | J44: Instabilité opérationnelle et pannes récurrentes | K44: Adopter un processus de gestion des changements standardisé
D45: Les utilisateurs sont formés sur les bonnes pratiques de mots de passe | E45: Les utilisateurs sont-ils formés sur les bonnes pratiques de mots de passe ? | F45: OUI | G45: Procédure d'administration de l'application | H45: Administration non sécurisée | I45: Élevé | J45: Accès non autorisé et compromission des données sensibles | K45: Renforcer les contrôles d'accès et sécuriser les outils d'administration
D46: Les mots de passe sont audités régulièrement | E46: Les mots de passe sont-ils audités régulièrement ? | F46: NON | G46: Rapport d'analyse des risques spécifiques | H46: Documentation insuffisante des risques critiques | I46: Élevé | J46: Incapacité à prévoir et à atténuer les problèmes majeurs | K46: Compléter et maintenir à jour une documentation détaillée des risques critiques
C47: S’assurer que les tentatives de connexions infructueuses à l'application sont suivies | D47: Les tentatives de connexion sont journalisées | E47: Les tentatives de connexion sont-elles journalisées ? | F47: NON | G47: Plan de sécurité, documentation des besoins de sécurité | H47: Non-prise en compte des besoins de sécurité | I47: Moyen | J47: Exploitation accrue par des acteurs malveillants | K47: Intégrer les besoins en sécurité dans toutes les étapes du projet
D48: Des alertes sont générées en cas d'activité suspecte | E48: Des alertes sont-elles générées en cas d'activité suspecte ? | F48: PAS | G48: Rapports d'approbation, validation formelle des résultats | H48: Absence de validation formelle | I48: Moyen | J48: Erreurs non détectées et performance insuffisante | K48: Mettre en place des processus formalisés de validation et tests rigoureux
D49: Les journaux de connexion sont analysés régulièrement | E49: Les journaux de connexion sont-ils analysés régulièrement ? | F49: PAS | G49: Historique des mises à jour, calendrier des analyses | H49: Analyses de risques obsolètes | I49: Moyen | J49: Décisions basées sur des informations périmées | K49: Réaliser des mises à jour périodiques des analyses de risques
D50: Les comptes sont bloqués en cas de tentatives répétées | E50: Les comptes sont-ils bloqués en cas de tentatives répétées ? | F50: OUI | G50: Plan d'action de sécurité, rapports d'intégration des risques | H50: Actions non mises en œuvre. | I50: Élevé | J50: Risques identifiés persistant sans résolution | K50: Mettre en place un suivi rigoureux des plans d'actions recommandés
D51: Les incidents de sécurité sont documentés et suivis | E51: Les incidents de sécurité sont-ils documentés et suivis ? | F51: OUI | G51: Contrat de service SLA, documentation de mise en œuvre | H51: Non-respect des SLA | I51: Élevé | J51: Insatisfaction des clients, perte de confiance et potentiels litiges | K51: Surveiller les SLA et établir des mécanismes de correction en cas de déviation
B52: Fonction informatique | C52: S’assurer que les tâches relatives au développement et à l'exploitation de l'application sont bien suivies et documentées | D52: Existence d'un plan de projet détaillé avec les tâches, les responsabilités et les échéances | E52: Existe-il un plan de projet detaillé avec les tâches, les responsabilités et les échéances? | F52: OUI | G52: Plan de projet, diagramme de Gantt, feuille de route des tâches | H52: Mauvaise gestion des délais et des tâches | I52: Élevé | J52: Retards importants et baisse de productivité | K52: Mettre en place un planification stricte et un suivi des échéances
D53: Utilisation d'outils de suivi de projet pour gérer les tâches et les progrès | E53: Des outils de suivi de projet sont-ils utilisés pour gérer les tâches et les progrès ? | F53: OUI | G53: Liste des outils de suivi (exemple : Jira, Trello), rapports de suivi | H53: Absence de suivi centralisé des progrès | I53: Élevé | J53: Difficulté à évaluer l'état d'avancement des projets | K53: Utiliser des outils de gestion centralisés tels que des tableaux de bord
D54: Documentation des activités de développement et d'exploitation (journal des modifications, rapports d'incidents... | E54: Les activités de développement et d'exploitation sont-elles documentées (journal des modifications, rapports d'incidents, etc.) ? | F54: OUI | G54: Journal des modifications, rapport d’incidents, documentation des processus | H54: Manque de traçabilité | I54: Moyen | J54: Perte d'informations et incapacité à reproduire les étapes | K54: Implémenter des systèmes qui assurent une traçabilité complète
D55: Communication régulière entre les équipes de développement et d'exploitation | E55: Une communication régulière existe-t-elle entre les équipes de développement et d'exploitation ? | F55: PAS | G55: Comptes rendus de réunions, rapports de communication inter-équipes | H55: Communication insuffisante entre équipes | I55: Élevé | J55: Risques de malentendus et travail en silo | K55: Favoriser des outils de collaboration et organiser des réunions régulières
D56: Validation des livrables et des jalons par les parties prenantes concernées | E56: Les livrables et jalons sont-ils validés par les parties prenantes concernées ? | F56: OUI | G56: Rapport de validation des livrables, procès-verbaux de réunions | H56: Livrables non validés | I56: Moyen | J56: Qualité réduite et non-conformité aux attentes | K56: Mettre en œuvre un processus rigoureux de validation des livrables
C57: S’assurer que l'accès aux bibliothèques de production est réglementé | D57: Existence d'une procédure formelle pour gérer l'accès aux bibliothèques de production | E57: Existe-t-il une procédure formelle pour gérer l'accès aux bibliothèques de production ? | F57: NON | G57: Documentation des procédures d’accès, matrice des rôles | H57: Mauvaise définition des accès | I57: Élevé | J57: Risques d’accès non autorisé ou accès excessif | K57: Réévaluer et clarifier les permissions d’accès
D58: Attribution des droits d'accès basée sur les rôles et les responsabilités | E58: Les droits d'accès sont-ils attribués en fonction des rôles et responsabilités ? | F58: OUI | G58: Matrice des droits d’accès, charte des rôles | H58: Droits d'accès inappropriés | I58: Élevé | J58: Exploitation des systèmes et violations de sécurité | K58: Limiter les accès aux rôles nécessaires et effectuer des audits réguliers
D59: Journalisation des accès aux bibliothèques de production | E59: Les accès aux bibliothèques de production sont-ils journalisés ? | F59: PAS | G59: Journaux d’accès, rapports d’audit des accès | H59: Absence de journalisation | I59: Moyen | J59: Impossible de retracer les incidents | K59: Activer et surveiller la journalisation dans les systèmes
D60: Révision régulière des droits d'accès | E60: Les droits d'accès sont-ils révisés régulièrement ? | F60: PAS | G60: Historique des révisions, rapport de conformité | H60: Révisions non effectuées régulièrement | I60: Élevé | J60: Découverte tardive d’erreurs et risques accrus | K60: Mettre en place une politique de révision périodique
D61: Mise en place de contrôles pour prévenir les modifications non autorisées | E61: Des contrôles sont-ils mis en place pour prévenir les modifications non autorisées ? | F61: OUI | G61: Documentation des contrôles, journal des modifications | H61: Changements non documentés | I61: Moyen | J61: Difficulté à comprendre l’historique des modifications | K61: Maintenir un registre de tous les changements effectués
C62: Vérifier que la maintenance de la séparation des tâches est effective | D62: Définition claire des rôles et des responsabilités pour les tâches sensibles | E62: Les rôles et responsabilités pour les tâches sensibles sont-ils clairement définis ? | F62: OUI | G62: Description des rôles, charte des responsabilités | H62: Définitions floues des rôles | I62: Moyen | J62: Confusion et responsabilités non assumées | K62: Documenter et diffuser clairement les rôles attribués
D63: Implémentation de contrôles pour prévenir les conflits d'intérêts | E63: Des contrôles sont-ils implémentés pour prévenir les conflits d'intérêts ? | F63: OUI | G63: Politique de contrôle des conflits, rapport de conformité | H63: Conflits d’intérêts mal gérés | I63: Élevé | J63: Décisions biaisées et manque de transparence | K63: Appliquer des politiques claires pour éviter les conflits d’intérêts
D64: Journalisation des activités des utilisateurs ayant des privilèges élevés | E64: Les activités des utilisateurs ayant des privilèges élevés sont-elles journalisées ? | F64: PAS | G64: Journaux d’audit, rapports d’accès privilégié | H64: Absence de surveillance des utilisateurs privilégiés | I64: Élevé | J64: Exploitation non autorisée des privilèges | K64: Introduire une surveillance régulière des comptes privilégiés
D65: Révision régulière des rôles et des responsabilités | E65: Les rôles et responsabilités sont-ils révisés régulièrement ? | F65: NON | G65: Rapports d’évaluation des rôles, documentation des mises à jour des responsabilités | H65: Rôles ou responsabilités obsolètes | I65: Moyen | J65: Inefficacité et duplication des efforts | K65: Réévaluer et adapter régulièrement les rôles et responsabilités
D66: Formation des utilisateurs sur l'importance de la séparation des tâches | E66: Les utilisateurs sont-ils formés sur l'importance de la séparation des tâches ? | F66: NON | G66: Programme de formation, rapport de participation des utilisateurs | H66: Absence de formation des utilisateurs | I66: Moyen | J66: Mauvaise utilisation des systèmes | K66: Organiser des sessions de formation adaptées aux besoins
C67: S’assurer que l'équipe actuelle en charge de la maintenance est autonome et compétente | D67: Membres de l'équipe possédant les compétences techniques et fonctionnelles nécessaires | E67: Les membres de l'équipe possèdent-ils les compétences techniques et fonctionnelles nécessaires ? | F67: OUI | G67: CV des membres, résultats d’évaluations des compétences | H67: Compétences insuffisantes | I67: Élevé | J67: Failles dans la gestion et erreurs fréquentes | K67: Identifier les besoins et fournir des formations ciblées
D68: Existence d'un plan de formation continue pour l'équipe de maintenance | E68: Un plan de formation continue pour l'équipe de maintenance existe-t-il ? | F68: PAS | G68: Plan de formation continue, calendrier des sessions | H68: Manque de formation continue | I68: Moyen | J68: Obsolescence des compétences | K68: Instaurer un programme de développement continu des compétences
D69: Documentation des connaissances et des procédures de maintenance | E69: Les connaissances et procédures de maintenance sont-elles documentées ? | F69: OUI | G69: Guides de maintenance, base de connaissances | H69: Documentation de maintenance insuffisante | I69: Élevé | J69: Retards et inefficacités dans la gestion de la maintenance | K69: Tenir une documentation complète et à jour pour chaque système
D70: Capacité de l'équipe à résoudre les problèmes et à répondre aux incidents | E70: L'équipe est-elle capable de résoudre les problèmes et de répondre aux incidents ? | F70: OUI | G70: Rapport d’évaluation des performances, historique des incidents résolus | H70: Performances non évaluées | I70: Élevé | J70: Absence d’amélioration et maintien des inefficacités | K70: Mettre en place des processus d’évaluation régulière des performances
D71: Evaluation régulière des performances de l'équipe de maintenance | E71: Les performances de l'équipe de maintenance sont-elles évaluées régulièrement ? | F71: OUI | G71: Rapports d’évaluation des performances | H71: Plan de maintenance inexistant ou mal appliqué | I71: Moyen | J71: Augmentation des pannes et dégradations | K71: Élaborer et mettre en œuvre un plan de maintenance détaillé
C72: S’assurer de l’existence de procédure formalisée et standard de maintenance de l’application | D72: Existence d'un plan de maintenance documenté | E72: Un plan de maintenance documenté existe-t-il ? | F72: PAS | G72: Plan de maintenance, rapport de stratégie | H72: Activités mal planifiées ou non réalisées | I72: Élevé | J72: Délais non respectés et inefficience dans l’exécution | K72: Formaliser un plan détaillé et surveiller la réalisation des tâches
D73: Définition des activités de maintenance préventive et corrective | E73: Les activités de maintenance préventive et corrective sont-elles définies ? | F73: OUI | G73: Liste des activités préventives/correctives, calendrier de maintenance | H73: Absence d'outils adaptés | I73: Élevé | J73: Inefficacité dans les opérations | K73: Investir dans des outils adaptés aux besoins et les intégrer efficacement
D74: Utilisation d'outils de gestion des incidents et des problèmes | E74: Des outils de gestion des incidents et des problèmes sont-ils utilisés ? | F74: OUI | G74: Liste des outils de gestion (exemple : ServiceNow), rapports d’incidents | H74: Tests insuffisants ou inexistants | I74: Élevé | J74: Failles non détectées et dysfonctionnements fréquents | K74: Effectuer des tests rigoureux et réguliers pour garantir la qualité
D75: Mise en place de procédures de test et de validation des modifications | E75: Des procédures de test et de validation des modifications sont-elles mises en place ? | F75: OUI | G75: Plan de tests, procédure de validation | H75: Changements non communiqués | I75: Moyen | J75: Confusion et interruption des processus | K75: Documenter et communiquer tous les changements aux parties concernées
D76: Communication des changements et des mises à jour aux utilisateurs | E76: Les changements et mises à jour sont-ils communiqués aux utilisateurs ? | F76: OUI | G76: Rapports de communication des changements | H76: Schéma directeur obsolète ou mal aligné aux objectifs stratégiques | I76: Élevé | J76: Dysfonctionnement et inadéquation stratégique | K76: Mettre à jour et aligner le schéma directeur sur les objectifs
B77: Adéquation de l'application aux besoins | C77: Vérifier qu’un Schéma-directeur du système d’information existe et est à jour | D77: Existence d'un Schéma-directeur du système d'information (SDSI) documenté | E77: Un Schéma-directeur du système d'information (SDSI) documenté existe-t-il ? | F77: PAS | G77: Schéma directeur documenté, plan stratégique IT | H77: Absence d'évaluation approfondie | I77: Élevé | J77: Risques non identifiés ou mal gérés | K77: Réaliser une évaluation complète et fréquente des risques
D78: Le SDSI couvre tous les aspects du système d'information | E78: Le SDSI couvre-t-il tous les aspects du système d'information ? | F78: PAS | G78: Rapport d’évaluation du SDSI | H78: Stratégies mal alignées | I78: Élevé | J78: Décisions inefficaces et déviation des objectifs | K78: Alignement stratégique avec les objectifs organisationnels
D79: Le SDSI est aligné sur la stratégie de l'entreprise | E79: Le SDSI est-il aligné sur la stratégie de l'entreprise ? | F79: PAS | G79: Documentation de l’alignement stratégique | H79: Mises à jour non suivies | I79: Moyen | J79: Instabilité du système et failles potentielles | K79: Mettre en place un suivi systématique des mises à jour
D80: Le SDSI est mis à jour régulièrement | E80: Le SDSI est-il mis à jour régulièrement ? | F80: PAS | G80: Historique des mises à jour | H80: Information mal diffusée | I80: Moyen | J80: Manque de coordination et erreurs fréquentes | K80: Utiliser des outils collaboratifs pour partager les informations
D81: Le SDSI est communiqué aux parties prenantes concernées | E81: Le SDSI est-il communiqué aux parties prenantes concernées ? | F81: PAS | G81: Liste de diffusion, rapports de communication | H81: Non-évaluation de l'alignement stratégique | I81: Moyen | J81: Ressources mal utilisées et inefficacité globale | K81: Intégrer des revues régulières de l’alignement stratégique
C82: S’assurer qu’une évaluation de l’alignement stratégique de l’application avec les orientation de l’entreprise a été réalisée | D82: Existence d'un document d'évaluation de l'alignement stratégique | E82: Un document d'évaluation de l'alignement stratégique existe-t-il ? | F82: NON | G82: Document d’évaluation de l’alignement stratégique | H82: Évaluations superficielles | I82: Moyen | J82: Résultats insuffisants et décisions biaisées | K82: Réaliser des analyses détaillées et approfondies
D83: L'évaluation couvre les aspects fonctionnels, techniques et financiers | E83: L'évaluation couvre-t-elle les aspects fonctionnels, techniques et financiers ? | F83: OUI | G83: Rapports d’évaluation détaillés | H83: Experts non qualifiés | I83: Élevé | J83: Erreurs majeures et inefficacité dans les processus | K83: Engager ou former des experts compétents
D84: L'évaluation est réalisée par des experts qualifiés | E84: L'évaluation est-elle réalisée par des experts qualifiés ? | F84: OUI | G84: Profil des évaluateurs, rapport d’expertise | H84: Absence de mise à jour | I84: Moyen | J84: Décisions basées sur des données périmées | K84: Actualiser régulièrement les données et analyses
D85: L'évaluation est mise à jour régulièrement | E85: L'évaluation est-elle mise à jour régulièrement ? | F85: PAS | G85: Rapports de mise à jour de l’évaluation | H85: Résultats mal communiqués | I85: Moyen | J85: Confusion et résistance aux conclusions | K85: Standardiser le processus de communication des résultats
D86: Les résultats de l'évaluation sont communiqués aux parties prenantes concernées | E86: Les résultats de l'évaluation sont-ils communiqués aux parties prenantes concernées ? | F86: OUI | G86: Documentation de communication des résultats | H86: Spécifications incomplètes ou imprécises | I86: Élevé | J86: Mauvaise conception et risques d’incompatibilité | K86: Clarifier et documenter minutieusement les spécifications
C87: S’assurer que la définition des spécifications ou les critères de choix de la solution a été clairement établie | D87: Existence d'un document de spécifications ou de critères de choix | E87: Un document de spécifications ou de critères de choix existe-t-il ? | F87: OUI | G87: Document de spécifications, cahier des charges | H87: Critères non validés | I87: Élevé | J87: Solutions non adaptées et insatisfaction des utilisateurs | K87: Valider les critères avec des experts et parties prenantes
D88: Les spécifications ou les critères de choix sont clairs, précis et mesurables | E88: Les spécifications ou critères de choix sont-ils clairs, précis et mesurables ? | F88: OUI | G88: Documentation des critères de choix validés | H88: Validation insuffisante | I88: Moyen | J88: Défauts et dysfonctionnements non détectés | K88: Mettre en place des tests rigoureux avant déploiement
D89: Les spécifications ou les critères de choix sont validés par les parties prenantes concernées | E89: Les spécifications ou critères de choix sont-ils validés par les parties prenantes concernées ? | F89: OUI | G89: Rapports de validation, signatures des parties prenantes | H89: Critères de comparaison partiels | I89: Moyen | J89: Décisions biaisées et manque d’équité | K89: Compléter et harmoniser les critères de comparaison
D90: Les spécifications ou les critères de choix sont utilisés pour évaluer les solutions potentielles | E90: Les spécifications ou critères de choix sont-ils utilisés pour évaluer les solutions potentielles ? | F90: OUI | G90: Matrice d’évaluation des solutions, documentation de comparaison | H90: Processus de sélection non documenté | I90: Moyen | J90: Difficulté à justifier les choix effectués | K90: Documenter toutes les étapes du processus de sélection
D91: Le processus de sélection de la solution est documenté | E91: Le processus de sélection de la solution est-il documenté ? | F91: NON | G91: Documentation du processus de sélection | H91: Rôles mal définis ou mal répartis | I91: Moyen | J91: Confusion et inefficacité dans l’exécution des tâches | K91: Revoir et clarifier la répartition des rôles
C92: Vérifier que les tâches des utilisateurs dans l’application sont clairement définies | D92: Existence d'une documentation des rôles et des responsabilités des utilisateurs | E92: Une documentation des rôles et des responsabilités des utilisateurs existe-t-elle ? | F92: OUI | G92: Charte des rôles, description des responsabilités | H92: Tâches mal documentées | I92: Moyen | J92: Pertes de temps et erreurs dans les opérations | K92: Tenir un registre précis et détaillé des tâches effectuées
D93: Les tâches des utilisateurs sont définies de manière précise et détaillée | E93: Les tâches des utilisateurs sont-elles définies de manière précise et détaillée ? | F93: OUI | G93: Guide des tâches des utilisateurs, procédures définies | H93: Processus non alignés avec les objectifs | I93: Élevé | J93: Inefficacité globale et gaspillage de ressources | K93: Revoir et ajuster les processus pour qu’ils soutiennent les objectifs
D94: Les tâches des utilisateurs sont alignées sur les processus métier | E94: Les tâches des utilisateurs sont-elles alignées sur les processus métier ? | F94: OUI | G94: Documentation de l’alignement des tâches et processus | H94: Utilisateurs non formés | I94: Moyen | J94: Erreurs fréquentes et mauvaise utilisation des systèmes | K94: Instaurer des programmes de formation adaptés
D95: Les utilisateurs sont formés sur leurs tâches et responsabilités | E95: Les utilisateurs sont-ils formés sur leurs tâches et responsabilités ? | F95: NON | G95: Rapports de formation, supports de formation | H95: Performances non évaluées | I95: Moyen | J95: Maintien des inefficacités et absence d’améliorations | K95: Mettre en place des indicateurs et audits de performances
D96: Les performances des utilisateurs sont évaluées régulièrement | E96: Les performances des utilisateurs sont-elles évaluées régulièrement ? | F96: NON | G96: Rapports d’évaluation des performances | H96: Absence de systèmes parallèles | I96: Élevé | J96: Interruption totale en cas de panne | K96: Déployer des systèmes de secours ou parallèles
C97: Vérifier que des systèmes parallèles sont maintenus en activité | D97: Existence de systèmes parallèles pour les fonctions critiques | E97: Des systèmes parallèles pour les fonctions critiques existent-ils ? | F97: OUI | G97: Documentation des systèmes parallèles, plan de secours | H97: Systèmes parallèles non testés régulièrement | I97: Moyen | J97: Dysfonctionnements non détectés | K97: Effectuer des tests périodiques des systèmes de secours
D98: Les systèmes parallèles sont maintenus à jour et testés régulièrement | E98: Les systèmes parallèles sont-ils maintenus à jour et testés régulièrement ? | F98: OUI | G98: Historique des tests et mises à jour des systèmes | H98: Manque de formation aux systèmes parallèles | I98: Moyen | J98: Difficulté à basculer vers les systèmes de secours | K98: Former les équipes à l’utilisation des systèmes parallèles
D99: Les utilisateurs sont formés à l'utilisation des systèmes parallèles | E99: Les utilisateurs sont-ils formés à l'utilisation des systèmes parallèles ? | F99: NON | G99: Rapports de formation, guides utilisateurs | H99: Procédures de basculement non documentées | I99: Élevé | J99: Retards en cas de transition entre systèmes | K99: Documenter et diffuser les procédures de basculement
D100: Les procédures de basculement vers les systèmes parallèles sont documentées | E100: Les procédures de basculement vers les systèmes parallèles sont-elles documentées ? | F100: OUI | G100: Documentation de basculement | H100: Performances des systèmes non surveillées | I100: Élevé | J100: Dégradations non détectées et inefficacité | K100: Mettre en place des outils de surveillance continue
...

Sheet Synthèse
B3: Synthèse Numérique | J3: Equipe de Mission
B5: N° | C5: Domaines | D5: Total OUI | E5: Total NON | F5: Total PAS | G5: Total | H5: Score | M5: Nom | N5: Prénom | O5: Spécialité
B6: 1 | C6: Application en service | D6: =COUNTIF('4.1 Application en service'!F2:F151, "OUI") -> 100 | E6: =COUNTIF('4.1 Application en service'!F2:F151, "NON") -> 18 | F6: =COUNTIF('4.1 Application en service'!F2:F151, "PAS") -> 32 | G6: =SUM(D6:F6) -> 150 | H6: =D6/G6 -> 0.66666667 | K6: Chef : | M6: TENE | N6: Mathieu | O6: DS
B7: 2 | C7: Fonction informatique | D7: =COUNTIF('4.2 Fonction Informatique'!F2:F269,"OUI") -> 81 | E7: =COUNTIF('4.2 Fonction Informatique'!F2:F269,"NON") -> 74 | F7: =COUNTIF('4.2 Fonction Informatique'!F2:F269,"PAS") -> 64 | G7: =SUM(D7:F7) -> 219 | H7: =D7/G7 -> 0.36986301
B8: 3 | C8: Contrôle des projets informatique | D8: =COUNTIF('4.3 Projets Informatiques'!F2:F671, "OUI") -> 310 | E8: =COUNTIF('4.3 Projets Informatiques'!F2:F671, "NON") -> 254 | F8: =COUNTIF('4.3 Projets Informatiques'!F2:F671, "PAS") -> 106 | G8: =SUM(G6:G7) -> 369 | H8: =D8/G8 -> 0.8401084 | K8: Membres:
B9: 4 | C9: Support utilisateur | D9: =COUNTIF('4.4 Support Utilisateur'!F2:F156, "OUI") -> 80 | E9: =COUNTIF('4.4 Support Utilisateur'!F2:F156, "NON") -> 51 | F9: =COUNTIF('4.4 Support Utilisateur'!F2:F156, "PAS") -> 24 | G9: =SUM(D9:F9) -> 155 | H9: =D9/G9 -> 0.51612903
B10: 5 | C10: Sécurité informatique | D10: =COUNTIF('4.5 Sécurité Informatique'!F2:F126, "OUI") -> 75 | E10: =COUNTIF('4.5 Sécurité Informatique'!F2:F126, "NON") -> 35 | F10: =COUNTIF('4.5 Sécurité Informatique'!F2:F126, "PAS") -> 15 | G10: =SUM(D10:F10) -> 125 | H10: =D10/G10 -> 0.6
B11: Total | D11: =SUM(D3:D9) -> 571 | E11: =SUM(E3:E9) -> 397 | F11: =SUM(F3:F9) -> 226 | G11: =SUM(D11:F11) -> 1194 | H11: =D11/G11 -> 0.47822446
K14: Chauffeur:
B16: Sythèse Graphique

Sheet COSO
A1: Domaines | B1: Responsables | C1: Durée | D1: Moyens pour la réalisation | E1: Parties Prenantes | F1: Points de Contrôle | G1: Objectifs de Contrôle | H1: Critère d’Évaluation | I1: Question d’Évaluation | J1: Réponses | K1: Documents Requis | L1: Risques | M1: Criticités | N1: Conséquences | O1: Remarques
A2: Gestion des Comptes | F2: Création des comptes comptables | G2: Assurer que les comptes sont créés conformément au plan comptable. | H2: Le compte suit le format et les catégories du plan comptable de l’entreprise | I2: Le compte est-il conforme aux catégories prédéfinies dans le plan comptable ? | J2: OUI | K2: Plan comptable de l’entreprise | L2: Non-conformité avec le plan comptable | M2: Elevée | N2: Difficulté de suivre les transactions
H3: Conformité avec le plan comptable officiel. | I3: le compte est t'il conforme au plan comptable officiel?
H4: Respect des normes comptables internes. | I4: les normes comptables internes sont elles respectées?
H5: Exactitude des codes et des numéros de comptes. | I5: les codes et les numéros de comptes sont-ils exacte ou conforme?
H6: Conformité avec les règles fiscales applicables. | I6: les comptes sont-ils conformes aux règles fiscales applicables ?
G7: Vérifier que les comptes comptables sont créés selon les procédures et les instructions internes | H7: Respect du processus de création des comptes. | I7: le processus de création des compte est-il respecté?
H8: Documentation complète des procédures suivies. | I8: les procédures suivies sont-elles entierement documentées?
H9: Validation des comptes par les personnes autorisées. | I9: est ce que les comptes sont validés par les personnes autorisées?
H10: Mise en place de contrôles internes pour la création des comptes. | I10: des contrôles internes pour la creation des comptes sont-ils mit en place?
H11: Conformité avec les contrôles de sécurité liés à la création des comptes. | I11: les comptes comptables sont-ils conforméments aux contrôles de sécurité?
G12: S'assurer que les comptes comptables sont créés avec les informations exactes et complètes | H12: Exactitude des données saisies (nom, description, catégorie, etc.). | I12: les données saisies sont-elles exactes?
H13: Complétude des informations demandées pour chaque compte. | I13: les informations demandées pour chaque comptes sont-elles complètes?
H14: Vérification des informations dans les systèmes sources (factures, contrats, etc.). | I14: les informations ont-elles été vérifiées dans les systèmes sources ?
H15: Absence d’erreurs de saisie (validation des données). | I15: les données saisies sont-elles valides? (absences d'erreurs)
H16: Mise à jour des informations en cas de changement. | I16: en cas de changement les données sont-elles mises à jour?
G17: Valider que les comptes créés sont correctement classifiés selon les catégories appropriées | H17: Conformité avec le plan comptable et les règles de classification. | I17: les comptes crées sont-ils conforme au plan comptable et aux règles de validations?
H18: Vérification de la logique de classement selon les types de comptes (actifs, passifs, charges, produits). | I18: les comptes sont-ils classés par types?
H19: Cohérence avec les pratiques comptables sectorielles. | I19: les comptes sont-ils crées en cohérence avec les pratiques comptables sectorielles?
H20: Validation par un responsable avant classification finale. | I20: les comptes sont-ils validés par un responsable avant la classification finale?
H21: Réconciliation avec les comptes précédemment classifiés. | I21: les comptes sont-ils en conciliation avec les ceux précédemment classifiés?
G22: Contrôler que la création des comptes est effectuée avec les autorisations requises | H22: Vérification des niveaux d’approbation des comptes créés. | I22: est ce que les niveaux d'approbations des comptes ont été vérifiés?
H23: Conformité avec les politiques d'accès et d'autorisation internes. | I23: les comptes sont-ils conformes aux politiques d'accès ?
H24: Existence de journaux de validation des créations de comptes. | I24: existe-t-il des journaux de validation de création de compte?
H25: Séparation des rôles pour éviter les conflits d’intérêts. | I25: les rôles ont-il élé bien séparé ?
H26: Suivi des comptes créés sans validation ou autorisation appropriée. | I26: les comptes sont-ils suivis avec validation ou autorisation appropriées?
G27: Effectuer une réconciliation périodique des comptes créés avec le plan comptable officielle | H27: Vérification de la fréquence des réconciliations effectuées (mensuelle, trimestrielle, etc.). | I27: les réconcialiation effectuées sont elles fréquemment suivis?
H28: Conformité de la réconciliation avec les normes comptables en vigueur. | I28: la réconciliation des comptes est-elle conforme aux normes en vigueur?
H29: Exactitude des correspondances entre les comptes créés et le plan comptable officiel. | I29: les correspondances entre les comptes créés et le plan comptable officiel sont -elles exactes?
H30: Validation de la réconciliation par une personne autorisée avant l'enregistrement. | I30: la réconciliation des comptes est-elle validée par des personnes autorisées?
H31: Documentation des écarts et corrections effectuées lors de la réconciliation. | I31: les écarts et corrections effectués lors de la réconciliation sont-elles documentés?
F32: Validation des comptes créés | G32: Assurer l’exactitude et la validation des nouveaux comptes créés. | H32: Vérification de la complétude et de la précision des informations relatives aux nouveaux comptes. | I32: Les comptes créés ont-ils été validés par un responsable ? | J32: OUI | K32: Fiche d’approbation des comptes | L32: Création de comptes non validés | M32: Moyenne | N32: Comptes redondants ou erronés
H33: Mise en place de contrôles de validation avant l'activation des nouveaux comptes dans le système comptable. | I33: le contrôle de validation est-il mit en place?
H34: Documentation des validations effectuées pour chaque nouveau compte. | I34: est ce que la documentation des validations est effectuée pour chaque nouveau compte?
H35: Réconciliation des nouveaux comptes avec les documents justificatifs avant validation. | I35: est ce que les nouveaux comptes sont en normes avec les documents avant validation?
H36: Suivi des anomalies ou erreurs de validation détectées et des actions correctives entreprises. | I36: les anomalies détectées sont elles suivies et corrigées?
G37: Vérifier la conformité des comptes validés avec le plan comptable. | H37: Conformité des codes de comptes validés avec ceux du plan comptable officiel. | I37: les codes de comptes validés sont-ils conforme avec ceux du plan comptable?
H38: Vérification de la classification correcte des comptes dans les catégories appropriées. | I38: les comptes sont-ils correctement classifiés dans les catégories appropriées?
H39: Contrôle de la correspondance des comptes validés avec les informations sources (factures, contrats, etc.). | I39: les comptes validés correspondent-ils aux informations sources?
H40: Validation des comptes validés par un responsable qualifié. | I40: les comptes sont-ils validés par un responsable qualifié?
H41: Documentation des comptes validés et validation par une personne autorisée. | I41: les documents des comptes sont-ils validés par un responsable qualifié?
G42: S'assurer que la validation des comptes est effectuée par des personnes autorisées. | H42: Vérification des niveaux d’autorisation pour la validation des comptes. | I42: existe-t-il des niveaux d'autorisation pour la validation des comptes?
H43: Conformité des processus de validation avec les politiques internes d’approbation. | I43: les processus de validation sont-ils conformes aux politique internes d'approbation?
H44: Suivi des comptes validés sans autorisation ou validation par des personnes non qualifiées. | I44: est ce que les comptes sont suivis et validés par des personnes qualifiées?
H45: Contrôles de sécurité pour limiter les accès aux processus de validation. | I45: les processus de validation ont-ils un accès limité?
H46: Documentation de toutes les validations effectuées, incluant les noms des personnes autorisées. | I46: les validations effectuées sont-elles documentées?
G47: Contrôler que les comptes validés sont correctement classifiés et référencés | H47: Vérification de la classification des comptes en fonction des normes comptables et des instructions internes. | I47: les comptes sont-ils classés en fonctions des normes comptables et des instructions internes?
H48: Conformité avec les catégories définies dans le plan comptable (actif, passif, charges, produits). | I48: les comptes sont -ils conformes aux catégories définies dans le plan comptable?
H49: Validation des classifications des comptes par une personne autorisée avant l’enregistrement final. | I49: les comptes sont-ils classifés et valider par les personnes autorisées?
H50: Suivi des erreurs ou incohérences dans les classifications et documentation des actions correctives. | I50: les erreurs dans les classifications sont-elles suivis?
H51: Réconciliation des classifications avec les états financiers et les rapports internes. | I51: les classifications avec les états financiers et les rapports internes sont-ils en accord?
G52: Assurer que les comptes validés sont enregistrés dans les systèmes comptables de manière cohérente | H52: Vérification de l'enregistrement systématique des comptes validés dans le système comptable. | I52: les comptes validés ont-ils bien été enregistré?
H53: Conformité des comptes enregistrés avec les procédures internes d'enregistrement. | I53: les comptes ont-ils été enregistrés conformément aux procédures interne d'enregistrement?
H54: Réconciliation des comptes enregistrés avec les comptes validés. | I54: les comptes enregistrés sont-ils en accord avec le comptes validés?
H55: Absence d’erreurs ou de doublons dans les enregistrements des comptes validés. | I55: les comptes validés sont-ils correctement enregistrés?
H56: Documentation des enregistrements effectués, avec trace de la personne responsable. | I56: les enregistrés effectués sont-ils documentés?
G57: Vérifier que la validation des comptes est documentée et traçable | H57: Existence d'un enregistrement formel pour chaque validation de compte. | I57: existe-t-il un enregistrement formel pour chaque validation de compte?
H58: Accès à une trace complète de toutes les étapes de la validation des comptes. | I58: Les étapes de la validation des comptes sont-elles entièrement traçables et accessibles ?
H59: Vérification que les documents de validation sont bien conservés dans le système de gestion comptable. | I59: Les documents de validation sont-ils correctement conservés et accessibles dans le système de gestion comptable ?
H60: Suivi des comptes validés sans documentation ou traçabilité adéquate. | I60: Existe-t-il un suivi pour les comptes validés sans documentation ou traçabilité suffisante ?
H61: Réconciliation entre les validations des comptes et les rapports comptables. | I61: La réconciliation entre les validations des comptes et les rapports comptables est-elle régulièrement effectuée et documentée ?
B62: LINDSAY | F62: Mise à jour des soldes de comptes | G62: Vérifier que les soldes sont actualisés après chaque transaction. | H62: Les soldes sont révisés en temps réel après chaque transaction. | I62: Les soldes des comptes sont-ils automatiquement mis à jour ? | J62: OUI | K62: Journal de transactions | L62: Retard dans la mise à jour des soldes | M62: Moyenne | N62: Déséquilibres financiers
H63: Suivi des écarts entre les soldes prévus et les soldes réels après transaction. | I63: Les écarts entre les soldes prévus et réels après transaction sont-ils régulièrement suivis et documentés ?
H64: Existence de contrôles internes automatisés pour vérifier l’actualisation des soldes. | I64: Des contrôles internes automatisés sont-ils en place pour vérifier l’actualisation des soldes ?
H65: Conformité des soldes actualisés avec les documents justificatifs des transactions. | I65: Les soldes actualisés sont-ils conformes aux documents justificatifs des transactions ?
H66: Validation des soldes actualisés par un responsable avant leur finalisation. | I66: Les soldes actualisés sont-ils validés par un responsable avant leur finalisation ?
G67: Vérifier la conformité des comptes validés avec le plan comptable. | H67: Contrôle de la correspondance des comptes validés avec le plan comptable officiel. | I67: Les comptes validés sont-ils contrôlés pour assurer leur correspondance avec le plan comptable officiel ?
H68: Vérification de la classification correcte des comptes dans les catégories appropriées. | I68: Les comptes sont-ils correctement classifiés dans les catégories appropriées ?
H69: Réconciliation des comptes validés avec les catégories du plan comptable. | I69: Les comptes validés sont-ils réconciliés avec les catégories du plan comptable ?
H70: Validation par un responsable de la conformité de chaque compte avec les normes comptables. | I70: Un responsable valide-t-il la conformité de chaque compte avec les normes comptables avant leur finalisation ?
H71: Documentation de la validation de la conformité des comptes avec le plan comptable. | I71: La validation de la conformité des comptes avec le plan comptable est-elle correctement documentée ?
G72: S'assurer que la validation des comptes est effectuée par des personnes autorisées. | H72: Vérification que seules les personnes autorisées validant les comptes selon les rôles définis. | I72: Seules les personnes autorisées valident-elles les comptes, conformément aux rôles définis ?
H73: Contrôle des niveaux d’autorisation pour la validation des comptes. | I73: Les niveaux d’autorisation pour la validation des comptes sont-ils contrôlés et respectés ?
H74: Suivi des comptes validés sans les autorisations requises. | I74: Les comptes validés sans les autorisations requises sont-ils suivis et rectifiés ?
H75: Mise en place de mécanismes de contrôle d’accès aux processus de validation. | I75: Des mécanismes de contrôle d’accès aux processus de validation sont-ils en place ?
H76: Documentation des validations effectuées, incluant les noms et signatures des personnes autorisées. | I76: Les validations effectuées sont-elles documentées, incluant les noms et signatures des personnes autorisées ?
G77: Contrôler que les comptes validés sont correctement classifiés et référencés | H77: Vérification que chaque compte validé est correctement classifié selon le plan comptable. | I77: Chaque compte validé est-il correctement classifié selon le plan comptable ?
H78: Assurer que chaque compte validé est référencé de manière unique et cohérente. | I78: Chaque compte validé est-il référencé de manière unique et cohérente ?
H79: Conformité des classifications des comptes validés avec les catégories du plan comptable. | I79: Les classifications des comptes validés sont-elles conformes aux catégories du plan comptable ?
H80: Documentation des catégories et références des comptes dans le système comptable. | I80: Les catégories et références des comptes sont-elles correctement documentées dans le système comptable ?
H81: Suivi des erreurs de classification et correction dans les plus brefs délais. | I81: Les erreurs de classification sont-elles suivies et corrigées dans les plus brefs délais ?
G82: Assurer que les comptes validés sont enregistrés dans les systèmes comptables de manière cohérente. | H82: Vérification de l'enregistrement cohérent des comptes dans le système comptable. | I82: L'enregistrement des comptes dans le système comptable est-il cohérent et exact ?
H83: Conformité avec le plan comptable lors de l'enregistrement des comptes. | I83: L’enregistrement des comptes est-il conforme au plan comptable ?
H84: Absence de doublons ou de conflits dans les enregistrements des comptes. | I84: Il n'y a-t-il pas de doublons ou de conflits dans les enregistrements des comptes ?
H85: Réconciliation des comptes créés et enregistrés avec les documents justificatifs. | I85: Les comptes créés et enregistrés sont-ils réconciliés avec les documents justificatifs ?
H86: Documentation des enregistrements, y compris les informations sur les responsables des validations. | I86: Les enregistrements sont-ils correctement documentés, incluant les informations sur les responsables des validations ?
G87: Vérifier que la validation des comptes est documentée et traçable. | H87: Existence d’une documentation complète pour chaque validation de compte. | I87: Existe-t-il une documentation complète pour chaque validation de compte ?
H88: Accès à un historique des validations dans le système comptable. | I88: L'historique des validations est-il accessible dans le système comptable ?
H89: Vérification de l'intégrité et de l'exhaustivité des documents de validation. | I89: L'intégrité et l'exhaustivité des documents de validation sont-elles vérifiées ?
H90: Suivi de l'approbation par les personnes responsables et autorisées. | I90: L'approbation par les personnes responsables et autorisées est-elle suivie ?
H91: Traçabilité des actions de validation et des décisions prises pour chaque compte. | I91: La traçabilité des actions de validation et des décisions prises pour chaque compte est-elle garantie ?
A92: Saisie des Écritures Comptables | F92: Exactitude des informations saisies | G92: Garantir que les transactions sont enregistrées correctement. | H92: Les écritures saisies incluent tous les détails (montant, comptes concernés, date). | I92: Les écritures saisies incluent-elles tous les détails nécessaires (montant, comptes concernés, date) ? | J92: NON | K92: Pièce justificative | L92: Saisie incomplète des informations | M92: Elevée | N92: Informations comptables inexactes
H93: Comparaison des transactions avec les pièces justificatives (factures, bons de commande). | I93: Les transactions sont-elles comparées aux pièces justificatives (factures, bons de commande) ?
H94: Vérification que les erreurs de saisie sont corrigées avant l'enregistrement. | I94: Les erreurs de saisie sont-elles corrigées avant l'enregistrement des transactions ?
H95: Suivi des erreurs récurrentes et des actions correctives mises en place. | I95: Les erreurs récurrentes sont-elles suivies et des actions correctives mises en place ?
H96: Validation des transactions par un responsable ou une personne autorisée. | I96: Les transactions sont-elles validées par un responsable ou une personne autorisée ?
G97: Vérifier que les informations saisies sont conformes aux documents justificatifs (factures, contrats, etc.) | H97: Comparaison minutieuse des données saisies avec les documents justificatifs pertinents. | I97: Les données saisies sont-elles minutieusement comparées avec les documents justificatifs pertinents ?
H98: Vérification de la présence des pièces justificatives pour chaque transaction. | I98: Les pièces justificatives sont-elles présentes pour chaque transaction ?
H99: Suivi des anomalies entre les informations saisies et les documents justificatifs. | I99: Les anomalies entre les informations saisies et les documents justificatifs sont-elles suivies ?
H100: Existence d'un processus de contrôle pour valider la conformité des informations saisies. | I100: Un processus de contrôle pour valider la conformité des informations saisies existe-t-il ?
...

Sheet 4.1 Application en service
A1: Domaine | B1: Points de Contrôle | C1: Objectifs de Contrôle | D1: Critère d’Évaluation | E1: Question d’Évaluation | F1: Réponses | G1: Documents Requis | H1: Risques | I1: Criticités | J1: Conséquences | K1: Recommandations
A2: Application en service | B2: Organisation | C2: S’assurer de l’existence d'un comité informatique | D2: Existence d'un comité informatique | E2: Existe-t-il un comité informatique ? | F2: OUI | G2: Charte du comité informatique, liste des membres, procès-verbaux des réunions | H2: Absence de gouvernance claire | I2: Élevé | J2: Décisions incohérentes et manque de coordination | K2: Mettre en place un comité de gouvernance structuré
D3: Le Comité est présidé par le Directeur Général | E3: Le comité est-il présidé par le Directeur Général ? | F3: OUI | G3: Document de nomination du Directeur Général, procès-verbaux des réunions | H3: Manque de leadership dans la prise de décisions stratégiques | I3: Élevé | J3: Retards et décisions inefficaces | K3: Nommer un leader compétent avec des pouvoirs clairs
D4: Les directions utilisatrices sont représentées au sein de ce Comité | E4: Les directions utilisatrices sont-elles représentées au sein du comité ? | F4: OUI | G4: Liste des membres du comité, organigramme | H4: Mauvaise représentation des parties prenantes | I4: Élevé | J4: Conflits d'intérêts et mauvaise acceptation des décisions | K4: Garantir l’inclusion des parties prenantes critiques
D5: Les directions utilisatrices sont influentes au sein de ce Comité | E5: Les directions utilisatrices sont-elles influentes au sein du comité ? | F5: NON | G5: Comptes rendus des réunions, décisions prises incluant les contributions des directions utilisatrices | H5: Négligence des apports des directions utilisatrices | I5: Élevé | J5: Solutions non adaptées aux besoins réels | K5: Renforcer la collaboration avec les utilisateurs finaux
D6: Présence de membres qualifiés et diversifiés | E6: Les membres du comité sont-ils qualifiés et diversifiés ? | F6: OUI | G6: Profils des membres, CV, évaluation des compétences | H6: Compétences inadéquates des membres du comité | I6: Élevé | J6: Erreurs stratégiques et décisions inefficaces | K6: Former ou remplacer les membres avec des experts qualifiés
C7: S’assurer de l’existence d'une politique relative aux applications | D7: Il existe une politique relative aux applications au sein de l'institution | E7: Une politique relative aux applications existe-t-elle au sein de l'institution ? | F7: OUI | G7: Politique des applications, document de gouvernance | H7: Non-existence ou non-application de la politique. | I7: Élevé | J7: Désorganisation et manque de cadre | K7: Élaborer et appliquer une politique claire et documentée
D8: La politique est connue des utilisateurs d'applications | E8: Les utilisateurs d'applications connaissent-ils cette politique ? | F8: OUI | G8: Rapport de sensibilisation ou de communication | H8: Méconnaissance des obligations des utilisateurs | I8: Élevé | J8: Non-respect des procédures et inefficacité | K8: Sensibiliser et former les utilisateurs sur leurs responsabilités
D9: La politique est largement diffusée | E9: La politique est-elle largement diffusée ? | F9: NON | G9: Support de communication (emails, brochures, affiches) | H9: Faible diffusion des informations | I9: Moyen | J9: Manque de transparence et communication inefficace | K9: Utiliser des outils modernes de gestion des informations
D10: La politique est mise en œuvre | E10: La politique est-elle mise en œuvre ? | F10: PAS | G10: Rapports d'audit de conformité | H10: Non-conformité aux normes | I10: Élevé | J10: Risques juridiques et pénalités | K10: Auditer et corriger les écarts avec les normes
D11: La politique couvre l'ensemble du cycle de vie de l’application | E11: La politique couvre-t-elle l'ensemble du cycle de vie de l'application ? | F11: PAS | G11: Documentation de la politique, schéma de cycle de vie | H11: Gestion incohérente des étapes du cycle de vie des applications | I11: Élevé | J11: Dysfonctionnements fréquents | K11: Automatiser le suivi du cycle de vie des applications
C12: S’assurer que les rôle et responsabilités des utilisateurs sont bien définis | D12: Le rôle et les responsabilités des utilisateurs vis-à-vis de l’application sont clairement identifiés | E12: Les rôles et responsabilités des utilisateurs vis-à-vis de l'application sont-ils clairement identifiés ? | F12: OUI | G12: Matrice des rôles et responsabilités, charte utilisateur | H12: Absence de définition claire des rôles | I12: Élevé | J12: Confusion et responsabilités non assumées | K12: Formaliser et communiquer les rôles clairement
D13: Le rôle et les responsabilités des utilisateurs vis-à-vis de l’application couvrent l’analyse des risques | E13: Les rôles et responsabilités des utilisateurs vis-à-vis de l'application couvrent-ils l'analyse des risques ? | F13: NON | G13: Documentation d'analyse des risques, rapports spécifiques | H13: Non-réalisation des analyses des risques | I13: Élevé | J13: Survenue imprévisible de risques importants | K13: Planifier et réaliser des analyses régulières des risques
D14: Le rôle et les responsabilités des utilisateurs vis-à-vis de l’application couvrent la définition des besoins de sécurité | E14: Les rôles et responsabilités des utilisateurs vis-à-vis de l'application couvrent-ils la définition des besoins de sécurité ? | F14: NON | G14: Expression des besoins de sécurité | H14: Non-définition des besoins de sécurité | I14: Élevé | J14: Failles exploitables par des acteurs malveillants | K14: Identifier et intégrer les exigences sécuritaires dès la conception
D15: Le rôle et les responsabilités des utilisateurs vis-à-vis de l’application couvrent la gestion des changements et des évolutions | E15: Les rôles et responsabilités des utilisateurs vis-à-vis de l'application couvrent-ils la gestion des changements et des évolutions ? | F15: NON | G15: Processus de gestion des changements | H15: Changements mal gérés | I15: Élevé | J15: Instabilité du système | K15: Mettre en place un processus de gestion des changements standardisé
D16: Le rôle et les responsabilités des utilisateurs vis-à-vis de l’application couvrent l’administration de l’application | E16: Les rôles et responsabilités des utilisateurs vis-à-vis de l'application couvrent-ils l'administration de l'application ? | F16: NON | G16: Procédure d'administration de l'application | H16: Administration non sécurisée | I16: Élevé | J16: Accès non autorisé et perte de données | K16: Renforcer les contrôles d’administration et les audits
C17: S’assurer qu’une analyse des risques a été réalisée | D17: Une analyse des risques spécifique à l'application a été réalisée | E17: Une analyse des risques spécifique à l'application a-t-elle été réalisée ? | F17: OUI | G17: Rapport d'analyse des risques spécifiques | H17: Documentation insuffisante des risques critiques | I17: Moyen | J17: Problèmes non identifiés et résolus | K17: Compléter la documentation des risques prioritaires
D18: L'analyse des risques a débouché sur la définition des besoins de sécurité | E18: L'analyse des risques a-t-elle débouché sur la définition des besoins de sécurité ? | F18: OUI | G18: Plan de sécurité, documentation des besoins de sécurité | H18: Non-prise en compte des besoins de sécurité | I18: Élevé | J18: Vulnérabilité accrue face aux cyberattaques | K18: Prioriser les mécanismes de sécurité dans les opérations
D19: Les résultats de l'analyse des risques sont documentés et approuvés | E19: Les résultats de l'analyse des risques sont-ils documentés et approuvés ? | F19: OUI | G19: Rapports d'approbation, validation formelle des résultats | H19: Absence de validation formelle | I19: Élevé | J19: Détection tardive des erreurs | K19: Mettre en place des étapes de validation rigoureuses
D20: L'analyse des risques est mise à jour régulièrement | E20: L'analyse des risques est-elle mise à jour régulièrement ? | F20: OUI | G20: Historique des mises à jour, calendrier des analyses | H20: Analyses de risques obsolètes | I20: Élevé | J20: Décisions basées sur des informations incorrectes | K20: Mettre à jour les analyses périodiquement
D21: Les risques identifiés sont pris en compte dans le plan d'action de sécurité | E21: Les risques identifiés sont-ils pris en compte dans le plan d'action de sécurité ? | F21: OUI | G21: Plan d'action de sécurité, rapports d'intégration des risques | H21: Actions non mises en œuvre | I21: Élevé | J21: Maintien des risques identifiés | K21: Suivre et exécuter les plans d'action
C22: S’assurer que le prolongement de l'analyse de risque et de son expansion ont été réalisés | D22: Il y a eu un prolongement de l'analyse des risques et de l'expression des besoins de sécurité | E22: Le prolongement de l'analyse des risques et de l'expression des besoins de sécurité a-t-il eu lieu ? | F22: PAS | G22: Contrat de service SLA, documentation de mise en œuvre | H22: Non-respect des SLA | I22: Élevé | J22: Insatisfaction et perte de clients | K22: Surveiller et respecter strictement les SLA établis
D23: Un contrat de service (SLA) entre l'informatique et la direction utilisatrice a été mis en œuvre | E23: Un contrat de service (SLA) entre l'informatique et la direction utilisatrice a-t-il été mis en œuvre ? | F23: PAS | G23: Politique de contrôle d'accès, matrice des rôles | H23: Accès inappropriés | I23: Élevé | J23: Fuites ou abus de données sensibles | K23: Réévaluer et contrôler régulièrement les droits d'accès
D24: L'analyse des risques étendue couvre tous les aspects de l'application | E24: L'analyse des risques étendue couvre-t-elle tous les aspects de l'application ? | F24: OUI | G24: Journal des droits d'accès, rapports d'audit | H24: Absence de journalisation | I24: Élevé | J24: Impossibilité de retracer les activités suspectes | K24: Implémenter un système de journalisation des événements
D25: Les résultats de l'analyse des risques étendue sont communiqués aux parties prenantes | E25: Les résultats de l'analyse des risques étendue sont-ils communiqués aux parties prenantes ? | F25: OUI | G25: Journaux d'accès, rapports de surveillance | H25: Activités suspectes non détectées | I25: Élevé | J25: Survenue de failles de sécurité | K25: Utiliser des outils de surveillance et détection proactive
D26: L'analyse des risques étendue est utilisée pour la planification stratégique | E26: L'analyse des risques étendue est-elle utilisée pour la planification stratégique ? | F26: OUI | G26: Procédure de révocation des accès | H26: Retard dans la révocation des accès | I26: Élevé | J26: Accès non autorisé prolongé | K26: Automatiser la gestion des accès pour une révocation rapide
B27: Application | C27: S'assurer que l'accès aux ressources de l'application (données et transactions) est restreint par un système de gestion d'accès | D27: Contrôle d'accès basé sur les rôles est mis en place | E27: Un contrôle d'accès basé sur les rôles est-il mis en place ? | F27: OUI | G27: Spécifications techniques de l'authentification, rapports de mise en œuvre | H27: Faiblesse dans l’authentification | I27: Élevé | J27: Compromission des comptes et données sensibles | K27: Renforcer les mécanismes d'authentification
D28: Les droits d'accès sont attribués de manière appropriée | E28: Les droits d'accès sont-ils attribués de manière appropriée ? | F28: OUI | G28: Politique de mots de passe, guides utilisateurs | H28: Mauvaises pratiques de mots de passe | I28: Élevé | J28: Vulnérabilité aux attaques par force brute | K28: Éduquer les utilisateurs sur les bonnes pratiques de gestion des mots de passe
D29: Les accès sont journalisés et surveillés | E29: Les accès sont-ils journalisés et surveillés ? | F29: OUI | G29: Journaux des tentatives de connexion | H29: Tentatives suspectes non identifiées | I29: Élevé | J29: Intrusions non détectées | K29: Mettre en place des solutions de détection des anomalies
D30: Un processus est en place pour révoquer les accès | E30: Un processus est-il en place pour révoquer les accès ? | F30: PAS | G30: Rapports d'incidents, base de données des suivis d'incidents | H30: Absence de suivi des incidents | I30: Élevé | J30: Problèmes récurrents non résolus | K30: Créer un processus clair de gestion des incidents
D31: Les accès sont audités régulièrement | E31: Les accès sont-ils audités régulièrement ? | F31: NON | G31: Charte du comité informatique, liste des membres, procès-verbaux des réunions | H31: Absence de gouvernance claire | I31: Élevé | J31: Décisions incohérentes et manque de coordination | K31: Établir des structures de gouvernance précises et documentées
C32: S’assurer qu’une procédure de gestion des profils utilisateurs existe | D32: Procédure documentée pour la création, modification et suppression des profils | E32: Une procédure documentée pour la création, modification et suppression des profils existe-t-elle ? | F32: OUI | G32: Document de nomination du Directeur Général, procès-verbaux des réunions | H32: Manque de leadership dans la prise de décisions stratégiques | I32: Élevé | J32: Retards et décisions inefficaces | K32: Nommer un responsable qualifié pour les décisions stratégiques
D33: Les droits d'accès sont attribués en fonction des rôles | E33: Les droits d'accès sont-ils attribués en fonction des rôles ? | F33: OUI | G33: Liste des membres du comité, organigramme | H33: Mauvaise représentation des parties prenantes | I33: Moyen | J33: Conflits et résistance aux décisions prises | K33: Assurer une représentation équitable des parties prenantes
D34: Les profils sont révisés régulièrement | E34: Les profils sont-ils révisés régulièrement ? | F34: OUI | G34: Comptes rendus des réunions, décisions prises incluant les contributions des directions utilisatrices | H34: Négligence des apports des directions utilisatrices | I34: Moyen | J34: Solutions inadaptées aux besoins réels | K34: Renforcer les échanges avec les directions utilisatrices
D35: La procédure est communiquée aux parties prenantes | E35: La procédure est-elle communiquée aux parties prenantes ? | F35: PAS | G35: Profils des membres, CV, évaluation des compétences | H35: Compétences inadéquates des membres du comité | I35: Élevé | J35: Décisions inefficaces et erreurs majeures | K35: Organiser des formations ou ajuster la composition du comité
D36: Des outils d'automatisation sont utilisés pour la gestion des profils | E36: Des outils d'automatisation sont-ils utilisés pour la gestion des profils ? | F36: PAS | G36: Politique des applications, document de gouvernance | H36: Non-existence ou non-application de la politique | I36: Élevé | J36: Désorganisation opérationnelle | K36: Créer et appliquer une politique claire et standardisée
C37: Vérifier que l’identification des utilisateurs est réalisée | D37: Mécanismes d'identification uniques sont utilisés | E37: Des mécanismes d'identification uniques sont-ils utilisés ? | F37: OUI | G37: Rapport de sensibilisation ou de communication | H37: Méconnaissance des obligations des utilisateurs | I37: Moyen | J37: Utilisation incorrecte des applications | K37: Former les utilisateurs sur leurs responsabilités
D38: Authentification forte est mise en place | E38: Une authentification forte est-elle mise en place ? | F38: OUI | G38: Support de communication (emails, brochures, affiches) | H38: Faible diffusion des informations | I38: Moyen | J38: Collaboration et coordination limitées | K38: Utiliser des outils modernes pour améliorer la communication
D39: Procédure de gestion des identifiants est claire | E39: La procédure de gestion des identifiants est-elle claire ? | F39: OUI | G39: Rapports d'audit de conformité | H39: Non-conformité aux normes | I39: Élevé | J39: Risques juridiques et pertes financières | K39: Réaliser des audits réguliers pour garantir la conformité
D40: Les identifiants sont protégés | E40: Les identifiants sont-ils protégés ? | F40: OUI | G40: Documentation de la politique, schéma de cycle de vie | H40: Gestion incohérente des étapes du cycle de vie des applications | I40: Élevé | J40: Dysfonctionnements et retards fréquents | K40: Automatiser le suivi des étapes clés du cycle de vie.
D41: Les identifiants sont audités régulièrement | E41: Les identifiants sont-ils audités régulièrement ? | F41: NON | G41: Matrice des rôles et responsabilités, charte utilisateur | H41: Absence de définition claire des rôles | I41: Moyen | J41: Confusion et duplication des responsabilités | K41: Clarifier et documenter les rôles et responsabilités
C42: Vérifier qu’un mot de passe est associé à l'identifiant | D42: Politique de mots de passe est en place | E42: Une politique de mots de passe est-elle en place ? | F42: OUI | G42: Documentation d'analyse des risques, rapports spécifiques | H42: Non-réalisation des analyses des risques | I42: Élevé | J42: Risques non identifiés pouvant entraîner des interruptions majeures | K42: Mettre en place une stratégie d'analyse des risques régulière
D43: Les mots de passe sont stockés de manière sécurisée | E43: Les mots de passe sont-ils stockés de manière sécurisée ? | F43: OUI | G43: Expression des besoins de sécurité | H43: Non-définition des besoins de sécurité | I43: Élevé | J43: Failles exploitables entraînant des violations de données | K43: Identifier et documenter les besoins de sécurité dès la conception
D44: Procédure de gestion des mots de passe est claire | E44: La procédure de gestion des mots de passe est-elle claire ? | F44: PAS | G44: Processus de gestion des changements | H44: Changements mal gérés | I44: Élevé | J44: Instabilité opérationnelle et pannes récurrentes | K44: Adopter un processus de gestion des changements standardisé
D45: Les utilisateurs sont formés sur les bonnes pratiques de mots de passe | E45: Les utilisateurs sont-ils formés sur les bonnes pratiques de mots de passe ? | F45: OUI | G45: Procédure d'administration de l'application | H45: Administration non sécurisée | I45: Élevé | J45: Accès non autorisé et compromission des données sensibles | K45: Renforcer les contrôles d'accès et sécuriser les outils d'administration
D46: Les mots de passe sont audités régulièrement | E46: Les mots de passe sont-ils audités régulièrement ? | F46: NON | G46: Rapport d'analyse des risques spécifiques | H46: Documentation insuffisante des risques critiques | I46: Élevé | J46: Incapacité à prévoir et à atténuer les problèmes majeurs | K46: Compléter et maintenir à jour une documentation détaillée des risques critiques
C47: S’assurer que les tentatives de connexions infructueuses à l'application sont suivies | D47: Les tentatives de connexion sont journalisées | E47: Les tentatives de connexion sont-elles journalisées ? | F47: NON | G47: Plan de sécurité, documentation des besoins de sécurité | H47: Non-prise en compte des besoins de sécurité | I47: Moyen | J47: Exploitation accrue par des acteurs malveillants | K47: Intégrer les besoins en sécurité dans toutes les étapes du projet
D48: Des alertes sont générées en cas d'activité suspecte | E48: Des alertes sont-elles générées en cas d'activité suspecte ? | F48: PAS | G48: Rapports d'approbation, validation formelle des résultats | H48: Absence de validation formelle | I48: Moyen | J48: Erreurs non détectées et performance insuffisante | K48: Mettre en place des processus formalisés de validation et tests rigoureux
D49: Les journaux de connexion sont analysés régulièrement | E49: Les journaux de connexion sont-ils analysés régulièrement ? | F49: PAS | G49: Historique des mises à jour, calendrier des analyses | H49: Analyses de risques obsolètes | I49: Moyen | J49: Décisions basées sur des informations périmées | K49: Réaliser des mises à jour périodiques des analyses de risques
D50: Les comptes sont bloqués en cas de tentatives répétées | E50: Les comptes sont-ils bloqués en cas de tentatives répétées ? | F50: OUI | G50: Plan d'action de sécurité, rapports d'intégration des risques | H50: Actions non mises en œuvre. | I50: Élevé | J50: Risques identifiés persistant sans résolution | K50: Mettre en place un suivi rigoureux des plans d'actions recommandés
D51: Les incidents de sécurité sont documentés et suivis | E51: Les incidents de sécurité sont-ils documentés et suivis ? | F51: OUI | G51: Contrat de service SLA, documentation de mise en œuvre | H51: Non-respect des SLA | I51: Élevé | J51: Insatisfaction des clients, perte de confiance et potentiels litiges | K51: Surveiller les SLA et établir des mécanismes de correction en cas de déviation
B52: Fonction informatique | C52: S’assurer que les tâches relatives au développement et à l'exploitation de l'application sont bien suivies et documentées | D52: Existence d'un plan de projet détaillé avec les tâches, les responsabilités et les échéances | E52: Existe-il un plan de projet detaillé avec les tâches, les responsabilités et les échéances? | F52: OUI | G52: Plan de projet, diagramme de Gantt, feuille de route des tâches | H52: Mauvaise gestion des délais et des tâches | I52: Élevé | J52: Retards importants et baisse de productivité | K52: Mettre en place un planification stricte et un suivi des échéances
D53: Utilisation d'outils de suivi de projet pour gérer les tâches et les progrès | E53: Des outils de suivi de projet sont-ils utilisés pour gérer les tâches et les progrès ? | F53: OUI | G53: Liste des outils de suivi (exemple : Jira, Trello), rapports de suivi | H53: Absence de suivi centralisé des progrès | I53: Élevé | J53: Difficulté à évaluer l'état d'avancement des projets | K53: Utiliser des outils de gestion centralisés tels que des tableaux de bord
D54: Documentation des activités de développement et d'exploitation (journal des modifications, rapports d'incidents... | E54: Les activités de développement et d'exploitation sont-elles documentées (journal des modifications, rapports d'incidents, etc.) ? | F54: OUI | G54: Journal des modifications, rapport d’incidents, documentation des processus | H54: Manque de traçabilité | I54: Moyen | J54: Perte d'informations et incapacité à reproduire les étapes | K54: Implémenter des systèmes qui assurent une traçabilité complète
D55: Communication régulière entre les équipes de développement et d'exploitation | E55: Une communication régulière existe-t-elle entre les équipes de développement et d'exploitation ? | F55: PAS | G55: Comptes rendus de réunions, rapports de communication inter-équipes | H55: Communication insuffisante entre équipes | I55: Élevé | J55: Risques de malentendus et travail en silo | K55: Favoriser des outils de collaboration et organiser des réunions régulières
D56: Validation des livrables et des jalons par les parties prenantes concernées | E56: Les livrables et jalons sont-ils validés par les parties prenantes concernées ? | F56: OUI | G56: Rapport de validation des livrables, procès-verbaux de réunions | H56: Livrables non validés | I56: Moyen | J56: Qualité réduite et non-conformité aux attentes | K56: Mettre en œuvre un processus rigoureux de validation des livrables
C57: S’assurer que l'accès aux bibliothèques de production est réglementé | D57: Existence d'une procédure formelle pour gérer l'accès aux bibliothèques de production | E57: Existe-t-il une procédure formelle pour gérer l'accès aux bibliothèques de production ? | F57: NON | G57: Documentation des procédures d’accès, matrice des rôles | H57: Mauvaise définition des accès | I57: Élevé | J57: Risques d’accès non autorisé ou accès excessif | K57: Réévaluer et clarifier les permissions d’accès
D58: Attribution des droits d'accès basée sur les rôles et les responsabilités | E58: Les droits d'accès sont-ils attribués en fonction des rôles et responsabilités ? | F58: OUI | G58: Matrice des droits d’accès, charte des rôles | H58: Droits d'accès inappropriés | I58: Élevé | J58: Exploitation des systèmes et violations de sécurité | K58: Limiter les accès aux rôles nécessaires et effectuer des audits réguliers
D59: Journalisation des accès aux bibliothèques de production | E59: Les accès aux bibliothèques de production sont-ils journalisés ? | F59: PAS | G59: Journaux d’accès, rapports d’audit des accès | H59: Absence de journalisation | I59: Moyen | J59: Impossible de retracer les incidents | K59: Activer et surveiller la journalisation dans les systèmes
D60: Révision régulière des droits d'accès | E60: Les droits d'accès sont-ils révisés régulièrement ? | F60: PAS | G60: Historique des révisions, rapport de conformité | H60: Révisions non effectuées régulièrement | I60: Élevé | J60: Découverte tardive d’erreurs et risques accrus | K60: Mettre en place une politique de révision périodique
D61: Mise en place de contrôles pour prévenir les modifications non autorisées | E61: Des contrôles sont-ils mis en place pour prévenir les modifications non autorisées ? | F61: OUI | G61: Documentation des contrôles, journal des modifications | H61: Changements non documentés | I61: Moyen | J61: Difficulté à comprendre l’historique des modifications | K61: Maintenir un registre de tous les changements effectués
C62: Vérifier que la maintenance de la séparation des tâches est effective | D62: Définition claire des rôles et des responsabilités pour les tâches sensibles | E62: Les rôles et responsabilités pour les tâches sensibles sont-ils clairement définis ? | F62: OUI | G62: Description des rôles, charte des responsabilités | H62: Définitions floues des rôles | I62: Moyen | J62: Confusion et responsabilités non assumées | K62: Documenter et diffuser clairement les rôles attribués
D63: Implémentation de contrôles pour prévenir les conflits d'intérêts | E63: Des contrôles sont-ils implémentés pour prévenir les conflits d'intérêts ? | F63: OUI | G63: Politique de contrôle des conflits, rapport de conformité | H63: Conflits d’intérêts mal gérés | I63: Élevé | J63: Décisions biaisées et manque de transparence | K63: Appliquer des politiques claires pour éviter les conflits d’intérêts
D64: Journalisation des activités des utilisateurs ayant des privilèges élevés | E64: Les activités des utilisateurs ayant des privilèges élevés sont-elles journalisées ? | F64: PAS | G64: Journaux d’audit, rapports d’accès privilégié | H64: Absence de surveillance des utilisateurs privilégiés | I64: Élevé | J64: Exploitation non autorisée des privilèges | K64: Introduire une surveillance régulière des comptes privilégiés
D65: Révision régulière des rôles et des responsabilités | E65: Les rôles et responsabilités sont-ils révisés régulièrement ? | F65: NON | G65: Rapports d’évaluation des rôles, documentation des mises à jour des responsabilités | H65: Rôles ou responsabilités obsolètes | I65: Moyen | J65: Inefficacité et duplication des efforts | K65: Réévaluer et adapter régulièrement les rôles et responsabilités
D66: Formation des utilisateurs sur l'importance de la séparation des tâches | E66: Les utilisateurs sont-ils formés sur l'importance de la séparation des tâches ? | F66: NON | G66: Programme de formation, rapport de participation des utilisateurs | H66: Absence de formation des utilisateurs | I66: Moyen | J66: Mauvaise utilisation des systèmes | K66: Organiser des sessions de formation adaptées aux besoins
C67: S’assurer que l'équipe actuelle en charge de la maintenance est autonome et compétente | D67: Membres de l'équipe possédant les compétences techniques et fonctionnelles nécessaires | E67: Les membres de l'équipe possèdent-ils les compétences techniques et fonctionnelles nécessaires ? | F67: OUI | G67: CV des membres, résultats d’évaluations des compétences | H67: Compétences insuffisantes | I67: Élevé | J67: Failles dans la gestion et erreurs fréquentes | K67: Identifier les besoins et fournir des formations ciblées
D68: Existence d'un plan de formation continue pour l'équipe de maintenance | E68: Un plan de formation continue pour l'équipe de maintenance existe-t-il ? | F68: PAS | G68: Plan de formation continue, calendrier des sessions | H68: Manque de formation continue | I68: Moyen | J68: Obsolescence des compétences | K68: Instaurer un programme de développement continu des compétences
D69: Documentation des connaissances et des procédures de maintenance | E69: Les connaissances et procédures de maintenance sont-elles documentées ? | F69: OUI | G69: Guides de maintenance, base de connaissances | H69: Documentation de maintenance insuffisante | I69: Élevé | J69: Retards et inefficacités dans la gestion de la maintenance | K69: Tenir une documentation complète et à jour pour chaque système
D70: Capacité de l'équipe à résoudre les problèmes et à répondre aux incidents | E70: L'équipe est-elle capable de résoudre les problèmes et de répondre aux incidents ? | F70: OUI | G70: Rapport d’évaluation des performances, historique des incidents résolus | H70: Performances non évaluées | I70: Élevé | J70: Absence d’amélioration et maintien des inefficacités | K70: Mettre en place des processus d’évaluation régulière des performances
D71: Evaluation régulière des performances de l'équipe de maintenance | E71: Les performances de l'équipe de maintenance sont-elles évaluées régulièrement ? | F71: OUI | G71: Rapports d’évaluation des performances | H71: Plan de maintenance inexistant ou mal appliqué | I71: Moyen | J71: Augmentation des pannes et dégradations | K71: Élaborer et mettre en œuvre un plan de maintenance détaillé
C72: S’assurer de l’existence de procédure formalisée et standard de maintenance de l’application | D72: Existence d'un plan de maintenance documenté | E72: Un plan de maintenance documenté existe-t-il ? | F72: PAS | G72: Plan de maintenance, rapport de stratégie | H72: Activités mal planifiées ou non réalisées | I72: Élevé | J72: Délais non respectés et inefficience dans l’exécution | K72: Formaliser un plan détaillé et surveiller la réalisation des tâches
D73: Définition des activités de maintenance préventive et corrective | E73: Les activités de maintenance préventive et corrective sont-elles définies ? | F73: OUI | G73: Liste des activités préventives/correctives, calendrier de maintenance | H73: Absence d'outils adaptés | I73: Élevé | J73: Inefficacité dans les opérations | K73: Investir dans des outils adaptés aux besoins et les intégrer efficacement
D74: Utilisation d'outils de gestion des incidents et des problèmes | E74: Des outils de gestion des incidents et des problèmes sont-ils utilisés ? | F74: OUI | G74: Liste des outils de gestion (exemple : ServiceNow), rapports d’incidents | H74: Tests insuffisants ou inexistants | I74: Élevé | J74: Failles non détectées et dysfonctionnements fréquents | K74: Effectuer des tests rigoureux et réguliers pour garantir la qualité
D75: Mise en place de procédures de test et de validation des modifications | E75: Des procédures de test et de validation des modifications sont-elles mises en place ? | F75: OUI | G75: Plan de tests, procédure de validation | H75: Changements non communiqués | I75: Moyen | J75: Confusion et interruption des processus | K75: Documenter et communiquer tous les changements aux parties concernées
D76: Communication des changements et des mises à jour aux utilisateurs | E76: Les changements et mises à jour sont-ils communiqués aux utilisateurs ? | F76: OUI | G76: Rapports de communication des changements | H76: Schéma directeur obsolète ou mal aligné aux objectifs stratégiques | I76: Élevé | J76: Dysfonctionnement et inadéquation stratégique | K76: Mettre à jour et aligner le schéma directeur sur les objectifs
B77: Adéquation de l'application aux besoins | C77: Vérifier qu’un Schéma-directeur du système d’information existe et est à jour | D77: Existence d'un Schéma-directeur du système d'information (SDSI) documenté | E77: Un Schéma-directeur du système d'information (SDSI) documenté existe-t-il ? | F77: PAS | G77: Schéma directeur documenté, plan stratégique IT | H77: Absence d'évaluation approfondie | I77: Élevé | J77: Risques non identifiés ou mal gérés | K77: Réaliser une évaluation complète et fréquente des risques
D78: Le SDSI couvre tous les aspects du système d'information | E78: Le SDSI couvre-t-il tous les aspects du système d'information ? | F78: PAS | G78: Rapport d’évaluation du SDSI | H78: Stratégies mal alignées | I78: Élevé | J78: Décisions inefficaces et déviation des objectifs | K78: Alignement stratégique avec les objectifs organisationnels
D79: Le SDSI est aligné sur la stratégie de l'entreprise | E79: Le SDSI est-il aligné sur la stratégie de l'entreprise ? | F79: PAS | G79: Documentation de l’alignement stratégique | H79: Mises à jour non suivies | I79: Moyen | J79: Instabilité du système et failles potentielles | K79: Mettre en place un suivi systématique des mises à jour
D80: Le SDSI est mis à jour régulièrement | E80: Le SDSI est-il mis à jour régulièrement ? | F80: PAS | G80: Historique des mises à jour | H80: Information mal diffusée | I80: Moyen | J80: Manque de coordination et erreurs fréquentes | K80: Utiliser des outils collaboratifs pour partager les informations
D81: Le SDSI est communiqué aux parties prenantes concernées | E81: Le SDSI est-il communiqué aux parties prenantes concernées ? | F81: PAS | G81: Liste de diffusion, rapports de communication | H81: Non-évaluation de l'alignement stratégique | I81: Moyen | J81: Ressources mal utilisées et inefficacité globale | K81: Intégrer des revues régulières de l’alignement stratégique
C82: S’assurer qu’une évaluation de l’alignement stratégique de l’application avec les orientation de l’entreprise a été réalisée | D82: Existence d'un document d'évaluation de l'alignement stratégique | E82: Un document d'évaluation de l'alignement stratégique existe-t-il ? | F82: NON | G82: Document d’évaluation de l’alignement stratégique | H82: Évaluations superficielles | I82: Moyen | J82: Résultats insuffisants et décisions biaisées | K82: Réaliser des analyses détaillées et approfondies
D83: L'évaluation couvre les aspects fonctionnels, techniques et financiers | E83: L'évaluation couvre-t-elle les aspects fonctionnels, techniques et financiers ? | F83: OUI | G83: Rapports d’évaluation détaillés | H83: Experts non qualifiés | I83: Élevé | J83: Erreurs majeures et inefficacité dans les processus | K83: Engager ou former des experts compétents
D84: L'évaluation est réalisée par des experts qualifiés | E84: L'évaluation est-elle réalisée par des experts qualifiés ? | F84: OUI | G84: Profil des évaluateurs, rapport d’expertise | H84: Absence de mise à jour | I84: Moyen | J84: Décisions basées sur des données périmées | K84: Actualiser régulièrement les données et analyses
D85: L'évaluation est mise à jour régulièrement | E85: L'évaluation est-elle mise à jour régulièrement ? | F85: PAS | G85: Rapports de mise à jour de l’évaluation | H85: Résultats mal communiqués | I85: Moyen | J85: Confusion et résistance aux conclusions | K85: Standardiser le processus de communication des résultats
D86: Les résultats de l'évaluation sont communiqués aux parties prenantes concernées | E86: Les résultats de l'évaluation sont-ils communiqués aux parties prenantes concernées ? | F86: OUI | G86: Documentation de communication des résultats | H86: Spécifications incomplètes ou imprécises | I86: Élevé | J86: Mauvaise conception et risques d’incompatibilité | K86: Clarifier et documenter minutieusement les spécifications
C87: S’assurer que la définition des spécifications ou les critères de choix de la solution a été clairement établie | D87: Existence d'un document de spécifications ou de critères de choix | E87: Un document de spécifications ou de critères de choix existe-t-il ? | F87: OUI | G87: Document de spécifications, cahier des charges | H87: Critères non validés | I87: Élevé | J87: Solutions non adaptées et insatisfaction des utilisateurs | K87: Valider les critères avec des experts et parties prenantes
D88: Les spécifications ou les critères de choix sont clairs, précis et mesurables | E88: Les spécifications ou critères de choix sont-ils clairs, précis et mesurables ? | F88: OUI | G88: Documentation des critères de choix validés | H88: Validation insuffisante | I88: Moyen | J88: Défauts et dysfonctionnements non détectés | K88: Mettre en place des tests rigoureux avant déploiement
D89: Les spécifications ou les critères de choix sont validés par les parties prenantes concernées | E89: Les spécifications ou critères de choix sont-ils validés par les parties prenantes concernées ? | F89: OUI | G89: Rapports de validation, signatures des parties prenantes | H89: Critères de comparaison partiels | I89: Moyen | J89: Décisions biaisées et manque d’équité | K89: Compléter et harmoniser les critères de comparaison
D90: Les spécifications ou les critères de choix sont utilisés pour évaluer les solutions potentielles | E90: Les spécifications ou critères de choix sont-ils utilisés pour évaluer les solutions potentielles ? | F90: OUI | G90: Matrice d’évaluation des solutions, documentation de comparaison | H90: Processus de sélection non documenté | I90: Moyen | J90: Difficulté à justifier les choix effectués | K90: Documenter toutes les étapes du processus de sélection
D91: Le processus de sélection de la solution est documenté | E91: Le processus de sélection de la solution est-il documenté ? | F91: NON | G91: Documentation du processus de sélection | H91: Rôles mal définis ou mal répartis | I91: Moyen | J91: Confusion et inefficacité dans l’exécution des tâches | K91: Revoir et clarifier la répartition des rôles
C92: Vérifier que les tâches des utilisateurs dans l’application sont clairement définies | D92: Existence d'une documentation des rôles et des responsabilités des utilisateurs | E92: Une documentation des rôles et des responsabilités des utilisateurs existe-t-elle ? | F92: OUI | G92: Charte des rôles, description des responsabilités | H92: Tâches mal documentées | I92: Moyen | J92: Pertes de temps et erreurs dans les opérations | K92: Tenir un registre précis et détaillé des tâches effectuées
D93: Les tâches des utilisateurs sont définies de manière précise et détaillée | E93: Les tâches des utilisateurs sont-elles définies de manière précise et détaillée ? | F93: OUI | G93: Guide des tâches des utilisateurs, procédures définies | H93: Processus non alignés avec les objectifs | I93: Élevé | J93: Inefficacité globale et gaspillage de ressources | K93: Revoir et ajuster les processus pour qu’ils soutiennent les objectifs
D94: Les tâches des utilisateurs sont alignées sur les processus métier | E94: Les tâches des utilisateurs sont-elles alignées sur les processus métier ? | F94: OUI | G94: Documentation de l’alignement des tâches et processus | H94: Utilisateurs non formés | I94: Moyen | J94: Erreurs fréquentes et mauvaise utilisation des systèmes | K94: Instaurer des programmes de formation adaptés
D95: Les utilisateurs sont formés sur leurs tâches et responsabilités | E95: Les utilisateurs sont-ils formés sur leurs tâches et responsabilités ? | F95: NON | G95: Rapports de formation, supports de formation | H95: Performances non évaluées | I95: Moyen | J95: Maintien des inefficacités et absence d’améliorations | K95: Mettre en place des indicateurs et audits de performances
D96: Les performances des utilisateurs sont évaluées régulièrement | E96: Les performances des utilisateurs sont-elles évaluées régulièrement ? | F96: NON | G96: Rapports d’évaluation des performances | H96: Absence de systèmes parallèles | I96: Élevé | J96: Interruption totale en cas de panne | K96: Déployer des systèmes de secours ou parallèles
C97: Vérifier que des systèmes parallèles sont maintenus en activité | D97: Existence de systèmes parallèles pour les fonctions critiques | E97: Des systèmes parallèles pour les fonctions critiques existent-ils ? | F97: OUI | G97: Documentation des systèmes parallèles, plan de secours | H97: Systèmes parallèles non testés régulièrement | I97: Moyen | J97: Dysfonctionnements non détectés | K97: Effectuer des tests périodiques des systèmes de secours
D98: Les systèmes parallèles sont maintenus à jour et testés régulièrement | E98: Les systèmes parallèles sont-ils maintenus à jour et testés régulièrement ? | F98: OUI | G98: Historique des tests et mises à jour des systèmes | H98: Manque de formation aux systèmes parallèles | I98: Moyen | J98: Difficulté à basculer vers les systèmes de secours | K98: Former les équipes à l’utilisation des systèmes parallèles
D99: Les utilisateurs sont formés à l'utilisation des systèmes parallèles | E99: Les utilisateurs sont-ils formés à l'utilisation des systèmes parallèles ? | F99: NON | G99: Rapports de formation, guides utilisateurs | H99: Procédures de basculement non documentées | I99: Élevé | J99: Retards en cas de transition entre systèmes | K99: Documenter et diffuser les procédures de basculement
D100: Les procédures de basculement vers les systèmes parallèles sont documentées | E100: Les procédures de basculement vers les systèmes parallèles sont-elles documentées ? | F100: OUI | G100: Documentation de basculement | H100: Performances des systèmes non surveillées | I100: Élevé | J100: Dégradations non détectées et inefficacité | K100: Mettre en place des outils de surveillance continue
...

Sheet 4.2 Fonction Informatique
A1: Domaine | B1: Points de contrôle | C1: Objectifs de contrôle | D1: Critères d'évaluation | E1: Questions d'évaluation | F1: Réponses | G1: Documents requis | H1: Risques | I1: Criticité | J1: Conséquences | K1: Recommandations
A2: Fonction informatique | B2: Rôle et positionnement de l'informatique dans l'organisation | C2: Vérifier qu’ont été créés des Comités « informatique » (stratégique, pilotage,..) regroupant les différentes directions de l’Organisation en charge de recenser les besoins et les opportunités, gérer les priorités et suivre les projets | D2: Les Comités "informatique" sont officiellement créés et documentés (PV de réunion, charte de fonctionnement) | E2: Les Comités "informatique" sont-ils officiellement créés et documentés (PV de réunion, charte de fonctionnement) ? | F2: OUI | G2: Charte des comités informatiques | H2: Absence de formalisation des rôles | I2: Élevée | J2: Décisions non alignées, perte de confiance | K2: Validation par la DG cruciale pour légitimité
G3: Procès-verbaux (PV) de réunions | H3: Décisions non suivies ou non partagées | I3: Moyenne | J3: Retards projets, divergences métiers/DSI | K3: PV clairs et diffusés améliorent la traçabilité
D4: Les directions métiers participent activement aux comités, avec une représentation équilibrée | E4: Les directions métiers participent-elles activement aux comités, avec une représentation équilibrée ? | F4: OUI | G4: Liste des membres désignés | H4: Représentation déséquilibrée | I4: Moyenne | J4: Besoins métiers mal pris en compte | K4: Établir des quotas par direction
G5: Feuilles de présence | H5: Participation irrégulière | I5: Faible | J5: Manque d'engagement | K5: Lier la participation aux objectifs individuels
D6: Les réunions sont tenues à une fréquence régulière (trimestrielle, semestrielle) avec un taux de participation satisfaisant | E6: Les réunions sont-elles tenues à une fréquence régulière (trimestrielle, semestrielle) avec un taux de participation satisfaisant ? | F6: OUI | G6: Calendrier annuel | H6: Délais non respectés | I6: Moyenne | J6: Accumulation de sujets | K6: Planifier 1 an à l'avance
G7: Statistiques de participation | H7: Quorum non atteint | I7: Faible | J7: Décisions non valides | K7: Prévoir un système de délégation
D8: Les décisions prises sont formalisées et suivies, avec des comptes-rendus partagés | E8: Les décisions prises sont-elles formalisées et suivies, avec des comptes-rendus partagés ? | F8: OUI | G8: Registre des décisions | H8: Non-application | I8: Élevée | J8: Blocages opérationnels | K8: Assigner un responsable par décision
G9: Dashboard de suivi | H9: Dérive des délais | I9: Moyenne | J9: Retards projets | K9: Revue mensuelle obligatoire
D10: Les priorités définies par les comités sont alignées sur la stratégie globale de l’organisation | E10: Les priorités définies par les comités sont-elles alignées sur la stratégie globale de l’organisation ? | F10: OUI | G10: Feuille de route SI | H10: Projets non stratégiques | I10: Élevée | J10: Gaspillage de ressources | K10: Validation annuelle par le COMEX
G11: Budget détaillé | H11: Déséquilibre financier | I11: Élevée | J11: Manque de fonds pour priorités | K11: Revue trimestrielle
C12: Vérifier l’existence d’une charte informatique ou de tout autre document définissant le rôle et le périmètre de responsabilité de la DSI | D12: Un document officiel (charte, politique) définit le rôle et les responsabilités de la DSI | E12: Un document officiel (charte, politique) définit-il le rôle et les responsabilités de la DSI ? | F12: OUI | G12: Charte de la DSI | H12: Périmètre flou | I12: Élevée | J12: Conflits de responsabilités | K12: Inclure un organigramme
G13: Politique SI | H13: Non-conformité | I13: Élevée | J13: Sanctions | K13: Validation juridique
D14: Le périmètre d’intervention de la DSI est clairement délimité | E14: Le périmètre d’intervention de la DSI est -il clairement délimité ? | F14: NON | G14: Cartographie processus | H14: Empiètement métiers | I14: Moyenne | J14: Doublons | K14: Mise à jour annuelle
G15: Matrice RACI | H15: Délégations floues | I15: Moyenne | J15: Retards décisionnels | K15: Former les managers
D16: Le document fait référence aux obligations légales et normes sectorielles applicables | E16: Le document fait-il référence aux obligations légales et normes sectorielles applicables ? | F16: NON | G16: Registre conformité | H16: Amendes réglementaires | I16: Élevée | J16: Sanctions financières | K16: Audit semestriel
G17: Procédures de mise à jour | H17: Non-actualisation | I17: Moyenne | J17: Non-conformité | K17: Automatiser les alertes
D18: La charte est validée et signée par les instances dirigeantes concernées | E18: La charte est-elle validée et signée par les instances dirigeantes concernées ? | F18: PAS | G18: PV de validation | H18: Non légitimité | I18: Élevée | J18: Rejet par les métiers | K18: Signature électronique
G19: Plan de diffusion | H19: Non accessibilité | I19: Faible | J19: Non application | K19: Publier sur l'intranet
D20: La charte est diffusée et accessible à l’ensemble des collaborateurs concernés | E20: La charte est-elle diffusée et accessible à l’ensemble des collaborateurs concernés ? | F20: OUI | G20: Registre de diffusion | H20: Non-connaissance des règles | I20: Moyenne | J20: Non-respect des processus | K20: Mettre en place un accusé de lecture
G21: Plateforme collaborative | H21: Accès difficile | I21: Faible | J21: Faible adoption | K21: Centraliser sur l'intranet
C22: Évaluer le degré d’implication et de maîtrise des organes de gestion dans les systèmes d’information de l’Organisation | D22: Les dirigeants participent activement aux comités stratégiques informatiques | E22: Les dirigeants participent-ils activement aux comités stratégiques informatiques ? | F22: PAS | G22: PV COMEX | H22: Décisions bloquées | I22: Élevée | J22: Paralysie | K22: Quorum C-level
G23: Plan communication | H23: Manque visibilité | I23: Faible | J23: Démotivation | K23: Synthèses mensuelles
D24: La direction générale comprend les enjeux clés des systèmes d’information | E24: La direction générale comprend t-elle les enjeux clés des systèmes d’information ? | F24: NON | G24: PV de formation | H24: Incompréhension | I24: Élevée | J24: Mauvaises décisions | K24: Formation annuelle
G25: Évaluation compétences | H25: Lacunes persistantes | I25: Moyenne | J25: Investissements inadaptés | K25: Coaching individuel
D26: Les budgets alloués aux projets informatiques reflètent les priorités stratégiques | E26: Les budgets alloués aux projets informatiques reflètent-ils les priorités stratégiques ? | F26: NON | G26: Budget projet | H26: Déséquilibre | I26: Élevée | J26: Projets non financés | K26: Alignement stratégique
G27: Rapport d'exécution | H27: Dérives | I27: Moyenne | J27: Dépassements | K27: Alertes automatiques
D28: Les dirigeants suivent des formations sur les enjeux de la gouvernance des SI | E28: Les dirigeants suivent-ils des formations sur les enjeux de la gouvernance des SI ? | F28: NON | G28: Planning formation | H28: Manque de culture SI | I28: Moyenne | J28: Décisions inadaptées | K28: Obligation annuelle
G29: Évaluations | H29: Lacunes non traitées | I29: Faible | J29: Risques persistants | K29: Suivi RH
D30: La direction réagit rapidement en cas d’incident majeur impactant les SI | E30: La direction réagit-elle rapidement en cas d’incident majeur impactant les SI ? | F30: OUI | G30: PRA/PCA | H30: Temps d'arrêt longs | I30: Élevée | J30: Pertes financières | K30: Tests trimestriels
G31: Compte-rendu incident | H31: Répétition erreurs | I31: Moyenne | J31: Perte de confiance | K31: Revue post-mortem
C32: Vérifier en pratique que le leadership des grands projets est assuré par les organes de gestion | D32: Un sponsor métier est désigné pour chaque projet majeur | E32: Un sponsor métier est-il désigné pour chaque projet majeur ? | F32: OUI | G32: Matrice responsabilités | H32: Portage insuffisant | I32: Élevée | J32: Échec projet | K32: Validation COMEX
G33: PV de lancement | H33: Engagement faible | I33: Moyenne | J33: Retards | K33: Évaluation performance
D34: Les dirigeants participent aux revues d’avancement des projets clés | E34: Les dirigeants participent-ils aux revues d’avancement des projets clés ? | F34: NON | G34: Planning revues | H34: Décisions tardives | I34: Moyenne | J34: Retards | K34: Bloquer agendas
G35: Comptes-rendus | H35: Actions non suivies | I35: Faible | J35: Dérives | K35: Assigner des responsables
D36: Les livrables majeurs sont validés par les instances dirigeantes concernées | E36: Les livrables majeurs sont-ils validés par les instances dirigeantes concernées ? | F36: PAS | G36: Procès-verbal validation | H36: Non-conformité | I36: Élevée | J36: Rejet livrable | K36: Checklist formelle
G37: Fiche de recette | H37: Bugs non détectés | I37: Moyenne | J37: Coûts supplémentaires | K37: Tests automatisés
D38: Les comités de risques projet impliquent les responsables métiers et la direction | E38: Les comités de risques projet impliquent-ils les responsables métiers et la direction ? | F38: PAS | G38: Registre des risques | H38: Risques ignorés | I38: Élevée | J38: Échecs projets | K38: Réunions bimestrielles
G39: Plans d'action | H39: Non mise en œuvre | I39: Moyenne | J39: Exposition aux risques | K39: Suivi dédié
D40: La communication interne sur les projets est portée par les dirigeants | E40: La communication interne sur les projets est-elle portée par les dirigeants ? | F40: OUI | G40: Plan communication | H40: Manque d'adhésion | I40: Moyenne | J40: Résistance au changement | K40: Messages vidéo
G41: Sondages feedback | H41: Démotivation | I41: Faible | J41: Baisse productivité | K41: Communication régulière
C42: Vérifier que les métiers assurent leur rôle de MOA | D42: Les besoins métiers sont formalisés dans des cahiers des charges ou spécifications | E42: Les besoins métiers sont-ils formalisés dans des cahiers des charges ou spécifications ? | F42: OUI | G42: Cahier des charges | H42: Incompréhension | I42: Élevée | J42: Solution inadaptée | K42: Validation formelle
G43: Protocole recette | H43: Non-qualité | I43: Élevée | J43: Refus utilisateurs | K43: Tests utilisateurs
D44: Un chef de projet MOA est désigné pour chaque projet ou domaine clé | E44: Un chef de projet MOA est-il désigné pour chaque projet ou domaine clé ? | F44: OUI | G44: Organigramme projet | H44: Manque de pilotage | I44: Élevée | J44: Dérives | K44: Nomination formelle
G45: Fiche de mission | H45: Périmètre flou | I45: Moyenne | J45: Conflits | K45: Définition claire des rôles
D46: Les spécifications fonctionnelles sont validées par les métiers avant développement | E46: Les spécifications fonctionnelles sont-elles validées par les métiers avant développement ? | F46: OUI | G46: PV de validation | H46: Écart besoins | I46: Élevée | J46: Refus livrable | K46: Signature obligatoire
G47: Versionning | H47: Modifications non tracées | I47: Moyenne | J47: Incohérences | K47: Outil collaboratif
D48: Les budgets MOA sont engagés pour financer les études et l’accompagnement utilisateurs | E48: Les budgets MOA sont-ils engagés pour financer les études et l’accompagnement utilisateurs ? | F48: OUI | G48: Budget prévisionnel | H48: Sous-financement | I48: Moyenne | J48: Accompagnement insuffisant | K48: Validation financière
G49: Reporting | H49: Dérives | I49: Faible | J49: Manque de visibilité | K49: Alertes automatiques
D50: Des réunions régulières entre MOA et MOE permettent d’ajuster les projets en cours | E50: Des réunions régulières entre MOA et MOE permettent-elles d’ajuster les projets en cours ? | F50: NON | G50: Planning réunions | H50: Décrochage | I50: Moyenne | J50: Livraison inadaptée | K50: Fréquence minimale
G51: Comptes-rendus | H51: Actions non suivies | I51: Faible | J51: Retards | K51: Outil de suivi partagé
B52: Planification stratégique | C52: Vérifier la couverture du périmètre fonctionnel | D52: Le périmètre fonctionnel couvre l’ensemble des processus métiers critiques de l’organisation | E52: Le périmètre fonctionnel couvre t-il l’ensemble des processus métiers critiques de l’organisation ? | F52: NON | G52: Cartographie processus | H52: Zones non couvertes | I52: Élevée | J52: Risques opérationnels | K52: Revue annuelle
G53: Analyse d'impact | H53: Faiblesses non traitées | I53: Moyenne | J53: Vulnérabilités | K53: Ateliers métiers
D54: Les applications supportant les fonctions clés sont clairement identifiées et documentées | E54: Les applications supportant les fonctions clés sont-elles clairement identifiées et documentées ? | F54: NON | G54: Inventaire applicatif | H54: Manque de visibilité | I54: Élevée | J54: Incidents majeurs | K54: Classification par criticité
G55: Documentation technique | H55: Dépendances cachées | I55: Moyenne | J55: Effet domino | K55: Mise à jour continue
D56: Les zones non couvertes par le système d’information sont recensées et justifiées | E56: Les zones non couvertes par le système d’information sont-elles recensées et justifiées ? | F56: NON | G56: Registre des gaps | H56: Risques non gérés | I56: Élevée | J56: Pertes d'opportunités | K56: Revue semestrielle
G57: Plan de correction | H57: Retards traitement | I57: Moyenne | J57: Accumulation problèmes | K57: Priorisation claire
D58: Les dépendances entre applications et processus métiers sont cartographiées | E58: Les dépendances entre applications et processus métiers sont-elles cartographiées ? | F58: NON | G58: Schéma d'architecture | H58: Points de rupture | I58: Élevée | J58: Incidents en cascade | K58: Mise à jour annuelle
G59: Matrice d'impact | H59: Vulnérabilités | I59: Moyenne | J59: Temps de réparation longs | K59: Simulation de crise
D60: Les fonctions obsolètes ou redondantes sont identifiées et planifiées pour suppression | E60: Les fonctions obsolètes ou redondantes sont-elles identifiées et planifiées pour suppression ? | F60: NON | G60: Plan de retrait | H60: Dette technique | I60: Moyenne | J60: Coûts de maintenance | K60: Planning formalisé
G61: Analyse coûts/bénéfices | H61: Retards élimination | I61: Faible | J61: Accumulation | K61: Budget dédié
C62: Vérifier l’existence d’une analyse à jour des procédures de pilotage et de mise à jour du plan informatique | D62: Les rôles et responsabilités dans la mise à jour du plan sont clairement attribués | E62: Les rôles et responsabilités dans la mise à jour du plan sont-ils clairement attribués ? | F62: PAS | G62: Matrice RACI | H62: Responsabilités floues | I62: Élevée | J62: Retards dans les mises à jour | K62: Formaliser dans les fiches de poste
G63: Procédure de mise à jour | H63: Processus non suivi | I63: Moyenne | J63: Incohérences | K63: Automatiser les rappels
D64: Les écarts entre le plan prévu et sa réalisation font l’objet d’analyses correctives | E64: Les écarts entre le plan prévu et sa réalisation font-ils l’objet d’analyses correctives ? | F64: PAS | G64: Rapport d'écarts | H64: Dérives non détectées | I64: Élevée | J64: Décisions inadaptées | K64: Revue trimestrielle obligatoire
G65: Plan d'actions correctives | H65: Retards de correction | I65: Moyenne | J65: Accumulation problèmes | K65: Suivi dans JIRA
D66: Les décisions d’ajustement du plan sont documentées et communiquées aux parties prenantes | E66: Les décisions d’ajustement du plan sont-elles documentées et communiquées aux parties prenantes ? | F66: PAS | G66: PV de comité de pilotage | H66: Traçabilité perdue | I66: Moyenne | J66: Incohérences | K66: Archivage centralisé
G67: Newsletter interne | H67: Mauvaise communication | I67: Faible | J67: Résistance au changement | K67: Format standardisé
D68: Les budgets et ressources nécessaires à l’exécution du plan sont validés annuellement | E68: Les budgets et ressources nécessaires à l’exécution du plan sont-ils validés annuellement ? | F68: PAS | G68: Budget validé | H68: Sous/sur-financement | I68: Élevée | J68: Projets bloqués | K68: Alignement stratégique
G69: Reporting financier | H69: Dérives non détectées | I69: Moyenne | J69: Dépassements | K69: Alertes automatiques
C70: Vérifier l’existence des documents à jour d’urbanisme de l’Organisation | D70: Une cartographie applicative à jour reflète l’état du système d’information | E70: Une cartographie applicative à jour reflète t-elle l’état du système d’information ? | F70: PAS | G70: Inventaire SI | H70: Vision obsolète | I70: Élevée | J70: Prises de décision erronées | K70: Mises à jour trimestrielles
G71: Diagramme d'architecture | H71: Dépendances cachées | I71: Moyenne | J71: Incidents en cascade | K71: Outil dédié (ex: LeanIX)
D72: Les principes d’urbanisme (modularité, interopérabilité) sont formalisés et appliqués | E72: Les principes d’urbanisme (modularité, interopérabilité) sont-ils formalisés et appliqués ? | F72: PAS | G72: Charte d'urbanisme | H72: Architecture désorganisée | I72: Élevée | J72: Coûts d'intégration élevés | K72: Validation par l'architecte
G73: Checklist de conformité | H73: Non-respect des normes | I73: Moyenne | J73: Dette technique | K73: Revue annuelle
D74: Les flux de données entre applications sont documentés et optimisés | E74: Les flux de données entre applications sont-ils documentés et optimisés ? | F74: PAS | G74: Catalogue de flux | H74: Goulots d'étranglement | I74: Moyenne | J74: Performances dégradées | K74: Documentation automatisée
G75: Audit d'optimisation | H75: Surcoûts techniques | I75: Moyenne | J75: Dépenses inutiles | K75: Outil d'analyse
D76: Les projets d’évolution du SI s’inscrivent dans la démarche d’urbanisme | E76: Les projets d’évolution du SI s’inscrivent-ils dans la démarche d’urbanisme ? | F76: PAS | G76: Fiche de cadrage | H76: Solutions inadaptées | I76: Élevée | J76: Réussite compromise | K76: Validation architecturale
G77: Matrice d'impact | H77: Effets secondaires | I77: Moyenne | J77: Régression | K77: Ateliers d'architecture
D78: La gouvernance de l’urbanisme implique les métiers et la DSI | E78: La gouvernance de l’urbanisme implique t-il les métiers et la DSI ? | F78: PAS | G78: PV de comité | H78: Décisions unilatérales | I78: Moyenne | J78: Rejet par les métiers | K78: Parité de représentation
G79: Enquête de satisfaction | H79: Démotivation | I79: Faible | J79: Mauvaise adoption | K79: Feedback trimestriel
C80: Vérifier l’existence d’une analyse à jour des procédures de pilotage et de mise à jour du plan d’occupation des sols (POS) | D80: Le POS est documenté et accessible aux équipes techniques et métiers | E80: Le POS est-il documenté et accessible aux équipes techniques et métiers ? | F80: OUI | G80: Document POS | H80: Connaissances dispersées | I80: Élevée | J80: Décisions incohérentes | K80: Portail dédié
G81: FAQ technique | H81: Mauvaises pratiques | I81: Faible | J81: Dette technique | K81: Wiki interactif
D82: Les règles d’allocation des ressources (serveurs, stockage) sont formalisées | E82: Les règles d’allocation des ressources (serveurs, stockage) sont-elles formalisées ? | F82: OUI | G82: Politique d'infra | H82: Surcharge des ressources | I82: Moyenne | J82: Pannes | K82: Supervision automatisée
G83: Dashboard utilisation | H83: Gaspillage | I83: Moyenne | J83: Coûts inutiles | K83: Alertes seuils
D84: Les procédures de mise à jour du POS intègrent les besoins métiers futurs | E84: Les procédures de mise à jour du POS intègrent-elles les besoins métiers futurs ? | F84: OUI | G84: Roadmap technique | H84: Obsolescence | I84: Élevée | J84: Coûts de migration | K84: Veille technologique
G85: Benchmark sectoriel | H85: Retard technologique | I85: Moyenne | J85: Perte compétitivité | K85: Revue semestrielle
D86: Les évolutions d’infrastructure suivent une planification pluriannuelle | E86: Les évolutions d’infrastructure suivent-elles une planification pluriannuelle ? | F86: OUI | G86: Plan 3-5 ans | H86: Réactivité insuffisante | I86: Moyenne | J86: Inadaptation | K86: Budget glissant
G87: Scénarios d'évolution | H87: Surprises | I87: Moyenne | J87: Décisions urgentes | K87: Ateliers prospectifs
D88: Les audits réguliers vérifient la conformité entre POS réel et documenté | E88: Les audits réguliers vérifient-ils la conformité entre POS réel et documenté ? | F88: NON | G88: Rapport d'audit complet | H88: Non-détection d'écarts | I88: Élevée | J88: Risques sécurité non maîtrisés | K88: Automatiser les contrôles
G89: Plan de correction | H89: Retard dans les corrections | I89: Moyenne | J89: Exposition prolongée aux risques | K89: Suivi mensuel par la direction
C90: Vérifier la cohérence et l’homogénéité des technologies | D90: Un référentiel des technologies autorisées est maintenu à jour | E90: Un référentiel des technologies autorisées est-il maintenu à jour ? | F90: OUI | G90: Catalogue des technologies approuvées | H90: Utilisation de technologies obsolètes | I90: Élevée | J90: Vulnérabilités de sécurité | K90: Mettre à jour trimestriellement
G91: Procès-verbal de validation | H91: Approbations non formalisées | I91: Moyenne | J91: Décisions contestables | K91: Signature électronique obligatoire
D92: Les écarts par rapport aux standards technologiques sont justifiés et planifiés | E92: Les écarts par rapport aux standards technologiques sont-ils justifiés et planifiés ? | F92: PAS | G92: Demandes de dérogation | H92: Prolifération de technologies non standards | I92: Élevée | J92: Complexité accrue du parc | K92: Instaurer un comité de validation
G93: Analyse d'impact | H93: Décisions non documentées | I93: Moyenne | J93: Manque de traçabilité | K93: Archivage centralisé
D94: Les compétences internes sont alignées sur le paysage technologique cible | E94: Les compétences internes sont-elles alignées sur le paysage technologique cible ? | F94: NON | G94: Plan de développement des compétences | H94: Inadéquation des compétences | I94: Élevée | J94: Retards sur les projets clés | K94: Cartographier les besoins annuellement
G95: Évaluations individuelles | H95: Lacunes non identifiées | I95: Moyenne | J95: Sous-performance persistante | K95: Entretiens semestriels
D96: Les coûts de licence et de maintenance sont optimisés par une approche consolidée | E96: Les coûts de licence et de maintenance sont-ils optimisés par une approche consolidée ? | F96: OUI | G96: Inventaire des licences | H96: Sur-achat de licences | I96: Moyenne | J96: Gaspillage budgétaire | K96: Audit semestriel
G97: Dashboard d'utilisation | H97: Sous-utilisation des outils | I97: Moyenne | J97: ROI insuffisant | K97: Alertes automatiques
D98: Un plan de migration progressive vers les standards est défini et budgété | E98: Un plan de migration progressive vers les standards est-il défini et budgété ? | F98: OUI | G98: Feuille de route de migration | H98: Retard dans les migrations | I98: Élevée | J98: Coûts de maintenance élevés | K98: Budget dédié
G99: Calendrier des migrations | H99: Délais non respectés | I99: Moyenne | J99: Prolongation du risque | K99: Points mensuels de suivi
C100: Vérifier l’existence et l’unicité des référentiels (clients, fournisseurs, articles…) et des saisies | D100: Un processus de gestion des données maîtres (MDM) est en place et appliqué | E100: Un processus de gestion des données maîtres (MDM) est-il en place et appliqué ? | F100: OUI | G100: Charte de gestion des données | H100: Incohérences dans les données | I100: Élevée | J100: Erreurs décisionnelles | K100: Nommer un data owner
...

Sheet 4.3 Projets Informatiques
A1: DOMAINE | B1: POINT DE CONTRÔLE | C1: OBJECTIF DE CONTRÔLE | D1: CRITERE D'EVALUATION | E1: QUESTION D'EVALUATION | F1: Réponses | G1: documents requis | H1: risque | I1: criticité | J1: conséquence | K1: recommandation
A2: AUDIT ET CONTRÔLE DES PROJETS INFORMATIQUE | B2: Obectifs et enjeux du projet | C2: S’assurer qu’une étude de la valeur et des études d'opportunité et d'impacts ont été réalisées | D2: Existence d’un document formalisé d’étude d’opportunité | E2: Existe-t-il un document formalisé d’étude d’opportunité ? | F2: OUI | H2: Non-évaluation complète de l'opportunité | I2: Elevée | J2: Décision basée sur des informations incomplètes, entraînant un projet mal orienté. | K2: Effectuer une analyse approfondie des opportunités avant la prise de décision.
D3: Analyse des coûts, bénéfices et risques clairement présentée | E3: L’analyse présente-t-elle clairement les coûts, les bénéfices et les risques ? | F3: NON | G3: Analyse coûts-bénéfices-risques | H3: Mauvaise estimation des coûts et bénéfices | I3: Elevée | J3: Surcoût ou manque de rentabilité du projet, impactant sa viabilité. | K3: Réaliser une estimation détaillée des coûts et bénéfices en impliquant toutes les parties prenantes.
D4: Identification et évaluation des impacts organisationnels et techniques | E4: Les impacts organisationnels et techniques sont-ils identifiés et évalués ? | F4: PAS | G4: Étude d’impact organisationnel et technique | H4: Impacts organisationnels ou techniques non identifiés | I4: Elevée | J4: Problèmes de coordination ou dysfonctionnements non anticipés, affectant le succès du projet. | K4: Identifier et évaluer les impacts organisationnels et techniques à chaque phase du projet.
D5: Prise en compte des scénarios alternatifs ou de non-réalisation | E5: Des scénarios alternatifs ou celui de la non-réalisation ont-ils été pris en compte ? | F5: OUI | G5: Étude d’opportunité avec scénarios alternatifs | H5: Non-considération de scénarios alternatifs | I5: Faible | J5: Absence de solutions adaptées en cas de changement, réduisant la flexibilité du projet. | K5: Considérer plusieurs scénarios alternatifs avant de prendre une décision finale.
D6: Validation de l’étude par les parties prenantes clés | E6: L’étude d’opportunité a-t-elle été validée par les parties prenantes clés ? | F6: OUI | G6: PV de validation de l’étude d’opportunité | H6: Absence de validation par les parties prenantes | I6: Elevée | J6: Manque d'adhésion et de soutien, entraînant des conflits et une mauvaise exécution. | K6: Assurer une validation continue du projet par les parties prenantes tout au long de son cycle de vie.
C7: S’assurer qu’un bilan critique des processus existants a été effectué | D7: Cartographie des processus existants disponible et à jour | E7: Existe-t-il une cartographie des processus existants, à jour et disponible ? | F7: OUI | G7: Cartographie des processus existants à jour | H7: Cartographie obsolète ou incomplète des processus | I7: Elevée | J7: Perte de visibilité sur les processus, entraînant inefficacité et erreurs. | K7: Mettre à jour régulièrement la cartographie des processus pour refléter l’évolution des besoins et des systèmes.
D8: Analyse des inefficiences ou dysfonctionnements documentée | E8: Les inefficiences ou dysfonctionnements des processus sont-ils documentés ? | F8: OUI | G8: Rapport d’analyse des dysfonctionnements | H8: Maintien des inefficiences ou dysfonctionnements non détectés | I8: Moyenne | J8: Non-amélioration des processus existants, entraînant des coûts supplémentaires. | K8: Mettre en place un suivi continu des inefficiences et dysfonctionnements pour les détecter rapidement.
D9: Collecte d’avis des utilisateurs sur les processus actuels | E9: Les utilisateurs ont-ils été consultés sur les processus actuels ? | F9: PAS | G9: Compte-rendu de consultation utilisateurs | H9: Non-prise en compte des retours des utilisateurs | I9: Elevée | J9: Insatisfaction des utilisateurs, manque d’engagement et mauvaise adoption des solutions. | K9: Collecter activement les retours des utilisateurs pour ajuster les solutions en fonction de leurs besoins réels.
D10: Rapport comparatif entre les processus actuels et les bonnes pratiques | E10: Un rapport comparatif existe-t-il entre les processus actuels et les bonnes pratiques ? | F10: PAS | G10: Rapport d’écart processus / bonnes pratiques | H10: Écart entre les processus actuels et les bonnes pratiques | I10: Elevée | J10: Disparité entre les pratiques actuelles et les meilleures pratiques, entraînant des inefficacités. | K10: Comparer les processus actuels aux meilleures pratiques pour combler les écarts.
D11: Prise en compte de la performance actuelle (indicateurs, KPI) | E11: La performance actuelle est-elle analysée à l’aide d’indicateurs ou de KPI ? | F11: PAS | G11: Tableau de bord des KPI actuels | H11: Absence d’indicateurs de performance clairs et mesurables | I11: Elevée | J11: Manque de mesures de performance, rendant difficile l'évaluation des progrès du projet. | K11: Définir des indicateurs de performance clairs et mesurables dès le début du projet.
C12: S’assurer que le choix de recourir à un nouveau système est obtenu après optimisation des processus concernés et vérification que cette optimisation ne suffit pas à apporter par elle-même les gains de performance attendus | D12: Étude d’optimisation des processus réalisée en amont | E12: Une étude d’optimisation des processus a-t-elle été réalisée en amont ? | F12: NON | G12: Rapport d’étude d’optimisation des processus | H12: Négligence des optimisations des processus en amont | I12: Elevée | J12: Perte d'opportunités d'optimisation, impactant la compétitivité et les coûts. | K12: Optimiser les processus en amont pour réduire les inefficiences et les coûts à long terme.
D13: Simulation ou projection des gains après optimisation sans SI | E13: Une simulation ou projection des gains sans SI a-t-elle été effectuée ? | F13: NON | G13: Simulation des gains hors SI | H13: Mauvaise estimation des gains d’optimisation sans SI | I13: Elevée | J13: Sous-performance du projet à cause de solutions mal adaptées. | K13: Evaluer avec précision les gains d’optimisation possibles, y compris sans systèmes informatiques.
D14: Rapport de justification du recours à une solution SI | E14: Un rapport de justification du recours à une solution SI est-il disponible ? | F14: OUI | G14: Note de justification du recours au SI | H14: Justification insuffisante de l’usage d’une solution SI | I14: Elevée | J14: Justification insuffisante, rendant le choix de la solution difficile à défendre. | K14: Justifier clairement le recours à une solution SI en comparant les alternatives disponibles.
D15: Analyse des écarts entre performance attendue et optimisation seule | E15: Les écarts entre les performances attendues et l’optimisation sans SI ont-ils été analysés ? | F15: NON | G15: Rapport d’analyse des écarts avec optimisation sans SI | H15: Sous-estimation des écarts entre performance attendue et optimisation | I15: Elevée | J15: Manque de visibilité sur les écarts, créant de mauvaises attentes et des ajustements inappropriés. | K15: Identifier les écarts potentiels entre les performances attendues et les gains d’optimisation avant de prendre des décisions.
D16: Validation du raisonnement par la direction ou comité projet | E16: Le raisonnement ayant conduit à une solution SI a-t-il été validé par la direction ou un comité projet ? | F16: OUI | G16: PV de validation du recours au SI | H16: Décision non validée par la direction ou le comité projet | I16: Elevée | J16: Décisions prises sans une vue d'ensemble, créant des conflits ou une mauvaise direction. | K16: Valider les décisions stratégiques avec la direction ou le comité de pilotage avant tout lancement.
C17: S’assure que les objectifs et périmètres du projet sont définis, partagés et stabilisés | D17: Document de cadrage/projet validé et diffusé | E17: Existe-t-il un document de cadrage ou de projet validé et diffusé ? | F17: OUI | G17: Document de cadrage ou note de cadrage projet | H17: Mauvaise communication ou manque de diffusion du cadrage | I17: Elevée | J17: Absence de communication, créant des malentendus et un manque d'alignement. | K17: Communiquer efficacement le cadrage du projet à toutes les parties prenantes pour garantir une compréhension partagée.
D18: Objectifs SMART (Spécifiques, Mesurables, etc.) formalisés | E18: Les objectifs du projet sont-ils formalisés selon la méthode SMART ? | F18: OUI | G18: Fiche d’objectifs SMART du projet | H18: Formulation imprécise des objectifs | I18: Elevée | J18: Objectifs flous, entraînant une confusion dans les attentes et la direction du projet. | K18: Définir des objectifs clairs, précis et mesurables pour éviter toute ambiguïté dans leur réalisation.
D19: Périmètre du projet clairement décrit et approuvé | E19: Le périmètre du projet est-il clairement décrit et approuvé ? | F19: NON | G19: Description formelle du périmètre du projet | H19: Périmètre mal défini ou flou | I19: Moyenne | J19: Manque de clarté dans les responsabilités, entraînant un travail redondant ou non couvert. | K19: Définir un périmètre précis et validé pour éviter les dérives et les malentendus.
D20: Revue formelle des changements de périmètre (gestion des écarts) | E20: Existe-t-il une revue formelle des changements de périmètre ? | F20: NON | G20: Procédure de revue de périmètre | H20: Gestion inadéquate des changements de périmètre | I20: Elevée | J20: Mauvaise gestion des attentes, impactant la qualité des livrables. | K20: Gérer les changements de périmètre avec rigueur et transparence pour éviter toute perturbation.
D21: Communication des objectifs aux parties prenantes clés | E21: Les objectifs ont-ils été communiqués aux parties prenantes clés ? | F21: NON | G21: Plan de communication initial ou note d’information | H21: Mauvaise communication des objectifs aux parties prenantes | I21: Elevée | J21: Difficulté à mesurer le succès, entraînant une mauvaise gestion des priorités. | K21: Assurer une bonne communication des objectifs et de leur évolution tout au long du projet.
C22: S’assurer que les principales orientations du système cible ont été explicitées | D22: Schéma directeur ou dossier d’architecture cible rédigé | E22: Un schéma directeur ou dossier d’architecture cible est-il rédigé ? | F22: OUI | G22: Schéma directeur SI ou dossier d’architecture cible | H22: Non-alignment de l’architecture cible avec les besoins | I22: Elevée | J22: Non-prise en compte des évolutions, rendant la solution non durable. | K22: S’assurer que l’architecture cible est bien alignée avec les besoins réels des utilisateurs et de l'organisation.
D23: Description fonctionnelle et technique du système cible | E23: Le système cible est-il décrit de manière fonctionnelle et technique ? | F23: PAS | G23: Dossier de description fonctionnelle et technique du SI cible | H23: Mauvaise ou insuffisante description du système cible | I23: Elevée | J23: Non-réalisation des tests nécessaires, rendant la solution moins fiable et augmentant les risques. | K23: Décrire de manière exhaustive et précise le système cible pour éviter toute confusion lors de son développement.
D24: Alignement du système cible avec la stratégie de l’entité | E24: Le système cible est-il aligné avec la stratégie de l’entité ? | F24: NON | G24: Alignement stratégique documenté | H24: Incompatibilité avec la stratégie de l’entité | I24: Moyenne | J24: Décisions prises sur la base de solutions inadaptées aux objectifs. | K24: Vérifier la compatibilité de la solution avec la stratégie de l’entité avant de procéder à son adoption.
D25: Consultation des utilisateurs finaux et responsables métiers | E25: Les utilisateurs finaux et responsables métiers ont-ils été consultés ? | F25: NON | G25: Compte-rendu de consultations métiers et utilisateurs | H25: Non-consultation des utilisateurs ou métiers | I25: Elevée | J25: Problèmes de compatibilité, entraînant des coûts d'intégration et de maintenance élevés. | K25: Impliquer activement les utilisateurs ou les métiers dans toutes les phases du projet pour garantir son adéquation avec les besoins réels.
D26: Existence de livrables validés décrivant les choix technologiques majeurs | E26: Des livrables validés décrivent-ils les choix technologiques majeurs ? | F26: OUI | G26: Fiches de choix technologiques validées | H26: Choix technologiques non validés ou mal documentés | I26: Elevée | J26: Absence de validation d'options critiques, augmentant les risques techniques. | K26: Valider les choix technologiques avec des experts internes ou externes et les documenter de manière détaillée.
B27: Etudes d'opportunité et expression des besoins | C27: S'assurer que l'expression détaillée des besoins est formalisée dans un cahier des charges fait par la MOA | D27: Cahier des charges rédigé et validé par la maîtrise d’ouvrage | E27: Le cahier des charges a-t-il été rédigé et validé par la MOA ? | F27: PAS | G27: Cahier des charges fonctionnel validé | H27: Cahier des charges incomplet ou mal validé | I27: Elevée | J27: Solutions mal adaptées aux besoins métiers, causant une mauvaise adoption et de l'insatisfaction. | K27: Valider et compléter le cahier des charges en impliquant les parties prenantes afin d’éviter toute omission.
D28: Besoins fonctionnels et non fonctionnels clairement définis | E28: Les besoins fonctionnels et non fonctionnels sont-ils clairement définis ? | F28: OUI | G28: Expression des besoins (fonctionnels et non fonctionnels) | H28: Besoins fonctionnels mal définis ou incomplets | I28: Elevée | J28: Manque de traçabilité, créant une confusion dans la gestion des exigences. | K28: Clarifier et formaliser les besoins fonctionnels afin de garantir que toutes les attentes sont prises en compte.
D29: Prise en compte des contraintes métier et réglementaires | E29: Les contraintes métier et réglementaires ont-elles été prises en compte ? | F29: OUI | G29: Document de prise en compte des contraintes métiers et réglementaires | H29: Non-prise en compte des contraintes métier et réglementaires | I29: Elevée | J29: Négligence des aspects réglementaires, entraînant des non-conformités et des pénalités. | K29: Tenir compte des contraintes métier et réglementaires dans l’ensemble du processus de décision.
D30: Traçabilité des besoins vers les exigences utilisateurs | E30: Existe-t-il une traçabilité des besoins vers les exigences utilisateurs ? | F30: OUI | G30: Matrice de traçabilité besoins / exigences | H30: Manque de traçabilité des besoins utilisateurs | I30: Elevée | J30: Absence d’adéquation entre les solutions et les exigences, entraînant des erreurs et des révisions coûteuses. | K30: Assurer la traçabilité complète des besoins utilisateurs pour faciliter leur gestion tout au long du projet.
D31: Implication des utilisateurs dans la phase de recueil des besoins | E31: Les utilisateurs ont-ils été impliqués dans la phase de recueil des besoins ? | F31: NON | G31: Compte-rendu des ateliers de recueil des besoins | H31: Sous-implication des utilisateurs dans le recueil des besoins | I31: Elevée | J31: Choix technologiques non optimaux, entraînant des coûts plus élevés ou une performance inférieure. | K31: Impliquer les utilisateurs dans le recueil des besoins pour obtenir des informations complètes et précises.
C32: S’assurer que le cahier des charges préconise une solution fonctionnellement et techniquement pertinente au regard des besoins exprimés | D32: Adéquation des fonctionnalités proposées avec les besoins exprimés | E32: Les fonctionnalités proposées répondent-elles aux besoins exprimés ? | F32: NON | G32: Matrice de couverture des besoins vs. fonctionnalités | H32: Non-adéquation des fonctionnalités proposées aux besoins | I32: Elevée | J32: Manque de consultation des parties prenantes, conduisant à des choix inadaptés ou non soutenus. | K32: S’assurer que les fonctionnalités proposées répondent réellement aux besoins exprimés par les utilisateurs.
D33: Analyse comparative des différentes solutions étudiées | E33: Une analyse comparative des différentes solutions a-t-elle été effectuée ? | F33: PAS | G33: Analyse comparative de solutions | H33: Mauvaise évaluation des solutions possibles | I33: Elevée | J33: Non-conformité avec les exigences fonctionnelles, entraînant des ajustements coûteux ou des rejets de la solution. | K33: Evaluer avec soin les différentes solutions possibles avant de prendre une décision définitive.
D34: Pertinence de l’architecture technique proposée | E34: L’architecture technique proposée est-elle pertinente ? | F34: PAS | G34: Dossier d’architecture technique validé | H34: Choix d’architecture technique non pertinent | I34: Elevée | J34: Problèmes de communication des priorités, entraînant une mauvaise gestion des attentes. | K34: Choisir une architecture technique en fonction des besoins à long terme, avec une évaluation des risques et de la maintenabilité.
D35: Évaluation de la maintenabilité et de l’évolutivité de la solution | E35: La solution choisie est-elle maintenable et évolutive ? | F35: PAS | G35: Note de maintien en conditions opérationnelles | H35: Négligence sur la maintenabilité ou évolutivité de la solution | I35: Elevée | J35: Sous-estimation des besoins, conduisant à un manque de ressources ou de temps. | K35: Vérifier la maintenabilité et l’évolutivité des solutions proposées avant leur adoption.
D36: Validation du choix de solution par les parties prenantes | E36: Le choix de la solution a-t-il été validé par les parties prenantes ? | F36: OUI | G36: PV de validation du choix de la solution | H36: Validation des choix par des parties prenantes non représentatives | I36: Elevée | J36: Non-prise en compte des besoins métiers dans la solution, entraînant une inadéquation avec la réalité du terrain. | K36: Valider les choix de l'architecture et des parties prenantes représentatives de l'ensemble des intérêts.
C37: S’assurer que les exigences utilisateurs, les populations ciblées, les options et principes de gestion retenus sont précisés et priorisés | D37: Identification claire des populations cibles | E37: Les populations cibles ont-elles été clairement identifiées ? | F37: OUI | G37: Fiche de description des populations cibles | H37: Mauvaise identification des populations cibles | I37: Elevée | J37: Perte de temps et d’efficacité due à des processus non optimisés. | K37: Identifier correctement les populations cibles afin de garantir la pertinence de la solution pour tous les utilisateurs.
D38: Exigences utilisateurs classées par priorité ou criticité | E38: Les exigences utilisateurs sont-elles classées par priorité ou criticité ? | F38: OUI | G38: Grille de priorisation des exigences | H38: Mauvaises priorités dans les exigences utilisateurs | I38: Elevée | J38: Problèmes liés à des dépendances extérieures, créant des retards ou des surcoûts. | K38: Prioriser correctement les exigences des utilisateurs en fonction de leur impact et de leur urgence.
D39: Description des scénarios d’usage représentatifs | E39: Des scénarios d’usage représentatifs sont-ils décrits ? | F39: OUI | G39: Dossier de scénarios d’usage | H39: Utilisation de scénarios d’usage non représentatifs | I39: Elevée | J39: Non-évaluation des impacts, créant des surprises à un stade avancé du projet. | K39: Utiliser des scénarios d’usage représentatifs pour tester la solution et en garantir l’adéquation.
D40: Validation formelle des principes de gestion avec les métiers | E40: Les principes de gestion ont-ils été validés formellement avec les métiers ? | F40: NON | G40: Document de validation des principes de gestion | H40: Non-validation des principes de gestion avec les métiers | I40: Elevée | J40: Mauvaise communication des risques, rendant leur gestion difficile. | K40: Valider les principes de gestion avec les métiers pour assurer l’alignement des objectifs et des processus.
D41: Documentation des arbitrages effectués entre options | E41: Les arbitrages entre options ont-ils été documentés ? | F41: NON | G41: Rapport sur les arbitrages documentés | H41: Non-documentation des arbitrages entre options | I41: Elevée | J41: Absence de révision des plans, entraînant des projets mal pilotés et des risques non maîtrisés. | K41: Documenter tous les arbitrages et décisions concernant les options afin de faciliter la traçabilité et la justification.
C42: S’assurer que le projet est cohérent avec le plan directeur informatique | D42: Alignement des objectifs du projet avec les orientations stratégiques du SI | E42: Les objectifs du projet sont-ils alignés avec les orientations stratégiques du SI ? | F42: OUI | G42: Note d’alignement stratégique SI / projet | H42: Déviation des objectifs du projet par rapport à la stratégie SI | I42: Moyenne | J42: Problèmes de maintenance futurs, créant des coûts additionnels à long terme. | K42: S'assurer que les objectifs du projet sont bien en ligne avec la stratégie SI de l'entreprise.
D43: Inclusion du projet dans le portefeuille stratégique du DSI | E43: Le projet est-il intégré dans le portefeuille stratégique du DSI ? | F43: OUI | G43: Portefeuille de projets SI actualisé | H43: Exclusion du projet du portefeuille stratégique du DSI | I43: Elevée | J43: Risques de sécurité et de compatibilité non pris en compte, entraînant des violations ou des défaillances. | K43: Inclure le projet dans le portefeuille stratégique du DSI pour garantir qu’il bénéficie de la visibilité et des ressources nécessaires.
D44: Vérification de la compatibilité avec les standards technologiques du plan directeur | E44: La compatibilité avec les standards technologiques du plan directeur est-elle vérifiée ? | F44: NON | G44: Vérification de conformité aux standards techniques | H44: Non-respect des standards technologiques | I44: Elevée | J44: Erreurs coûteuses dues à un manque d'anticipation sur les risques techniques. | K44: Respecter les standards technologiques établis pour assurer la cohérence et la compatibilité avec l’infrastructure existante.
D45: Prise en compte des priorités d’investissement du plan directeur | E45: Les priorités d’investissement du plan directeur sont-elles prises en compte ? | F45: PAS | G45: Plan directeur SI avec priorités d’investissement | H45: Non-alignment avec le plan directeur du SI | I45: Elevée | J45: Incapacité à répondre aux incidents rapidement, augmentant le temps d'indisponibilité. | K45: S’assurer que le projet est aligné avec le plan directeur du SI pour éviter des incohérences à long terme.
D46: Approbation formelle du projet par le comité stratégique SI | E46: Le projet a-t-il reçu une approbation formelle du comité stratégique SI ? | F46: NON | G46: PV d’approbation du comité stratégique SI | H46: Non-prise en compte des priorités du plan directeur | I46: Elevée | J46: Planification inadéquate, entraînant des retards ou un mauvais usage des ressources. | K46: Tenir compte des priorités du plan directeur du SI lors de la planification du projet.
C47: S’assurer que le projet est cohérent avec le SI actuel ou futur | D47: Analyse d’impact sur les systèmes existants | E47: Les impacts sur les systèmes existants ont-ils été analysés ? | F47: PAS | G47: Étude d’impact sur systèmes existants | H47: Approbation sans validation par le comité stratégique | I47: Elevée | J47: Non-suivi des progrès du projet, créant des erreurs ou une mauvaise gestion des priorités. | K47: Obtenir une validation préalable du comité stratégique avant toute décision importante.
D48: Conformité avec les standards d’urbanisation du SI | E48: Le projet est-il conforme aux standards d’urbanisation du SI ? | F48: NON | G48: Vérification des règles d’urbanisation SI | H48: Impact négatif sur les systèmes existants | I48: Elevée | J48: Problèmes de lisibilité du projet, réduisant la capacité à prendre des décisions informées. | K48: Evaluer l'impact potentiel du projet sur les systèmes existants afin d’éviter des perturbations.
D49: Intégration prévue avec les applications existantes | E49: L’intégration avec les applications existantes est-elle prévue ? | F49: PAS | G49: Dossier d’intégration applicative | H49: Non-conformité avec les standards d'urbanisation du SI | I49: Elevée | J49: Désorganisation du projet, entraînant un retard dans la réalisation des objectifs. | K49: Vérifier que le projet respecte les standards d'urbanisation du SI pour garantir une intégration efficace.
D50: Prise en compte de la roadmap technologique du SI | E50: La roadmap technologique du SI a-t-elle été prise en compte ? | F50: PAS | G50: Roadmap technologique du SI | H50: Intégration difficile avec les applications existantes | I50: Moyenne | J50: Non-suivi des risques, rendant difficile la gestion des imprévus. | K50: Prévoir une stratégie d'intégration adéquate avec les applications existantes pour éviter les conflits ou les incompatibilités.
D51: Existence de livrables d’architecture technique compatibles avec le SI cible | E51: Des livrables d’architecture technique compatibles avec le SI cible existent-ils ? | F51: OUI | G51: Livrables d’architecture technique alignés SI cible | H51: Non-prise en compte de la roadmap technologique | I51: Elevée | J51: Absence de soutien directionnel, réduisant l’efficacité des décisions et de l’équipe projet. | K51: Intégrer la roadmap technologique dans le plan de projet pour garantir une évolution harmonieuse.
C52: S’assurer que la direction est bien impliquée dans le projet | D52: Présence de la direction dans les comités de pilotage | E52: La direction est-elle présente dans les comités de pilotage ? | F52: OUI | G52: Ordres du jour et PV des comités de pilotage | H52: Architecture technique incompatible avec le SI cible | I52: Elevée | J52: Non-prise en compte des priorités métiers, entraînant un échec de l’implémentation des solutions. | K52: S’assurer que l’architecture technique est compatible avec le SI cible pour éviter des dérives ou des obstacles à l’intégration.
D53: Suivi régulier du projet par le sponsor ou un représentant de la direction | E53: Le projet est-il suivi régulièrement par le sponsor ou un représentant de la direction ? | F53: OUI | G53: Fiche de suivi sponsor / direction | H53: Manque de présence de la direction dans les comités de pilotage | I53: Elevée | J53: Manque de coordination entre équipes, augmentant le risque de conflits et de retards. | K53: Impliquer la direction dans les comités de pilotage pour garantir l’engagement et la prise de décision rapide.
D54: Appui de la direction dans les décisions majeures | E54: La direction soutient-elle activement les décisions majeures du projet ? | F54: OUI | G54: Notes de communication de la direction | H54: Suivi insuffisant du projet par la direction | I54: Elevée | J54: Problèmes de validation des décisions, créant des erreurs dans les processus décisionnels. | K54: Assurer un suivi régulier du projet par la direction pour garantir sa progression et sa bonne exécution.
D55: Communication formelle de la direction sur le projet | E55: La direction communique-t-elle formellement sur le projet ? | F55: OUI | G55: Validation formelle de l’engagement des ressources | H55: Manque d’appui de la direction dans les décisions clés | I55: Elevée | J55: Manque de structure de gouvernance, entraînant une mauvaise gestion et un projet incohérent. | K55: Obtenir un appui constant de la direction pour prendre des décisions clés et assurer la réussite du projet.
D56: Engagement des ressources validé au niveau de la direction | E56: L’engagement des ressources a-t-il été validé au niveau de la direction ? | F56: PAS | G56: Organigramme projet avec fiches de rôle | H56: Mauvaise communication formelle de la direction | I56: Elevée | J56: Échec dans l’accomplissement des objectifs à cause d'une mauvaise planification ou d'un manque de ressources. | K56: Communiquer formellement la vision de la direction et les priorités du projet pour une compréhension claire par toutes les parties.
C57: S’assurer que les acteurs de l'équipe projet et leurs responsabilités sont bien identifiés | D57: Organisation projet formalisée (organigramme, fiches de rôle) | E57: L’organisation projet est-elle formalisée avec organigramme et fiches de rôle ? | F57: PAS | G57: Liste nominative des acteurs projet | H57: Engagement insuffisant des ressources validées | I57: Elevée | J57: Manque de visibilité ou de préparation avant les réunions, réduisant l'efficacité des prises de décision. | K57: Garantir l’engagement des ressources validées en fonction des besoins du projet et de la charge de travail estimée.
D58: Acteurs désignés et disponibles selon leurs rôles | E58: Les acteurs projet ont-ils été désignés et sont-ils disponibles selon leurs rôles ? | F58: PAS | G58: RACI ou document de répartition des responsabilités | H58: Mauvaise organisation projet ou manquement de documentation | I58: Elevée | J58: Risques d’indisponibilité des ressources critiques, entraînant des interruptions dans le projet. | K58: Structurer le projet et la documentation de manière claire pour éviter toute ambiguïté dans l’organisation.
D59: Description claire des responsabilités de chacun | E59: Les responsabilités de chacun sont-elles clairement décrites ? | F59: NON | G59: PV de validation organisation projet | H59: Manque de disponibilité des acteurs désignés | I59: Elevée | J59: Ralentissement du projet dû à une mauvaise évaluation des risques. | K59: Assurer la disponibilité des acteurs clés pour éviter des retards dans l'exécution du projet.
D60: Validation de l’organisation projet par le comité de pilotage | E60: L’organisation projet a-t-elle été validée par le comité de pilotage ? | F60: NON | G60: Organigramme versionné avec date de mise à jour | H60: Absence de clarification des responsabilités | I60: Elevée | J60: Retards significatifs si la révision des plannings n'est pas faite régulièrement. | K60: Clarifier les responsabilités et veiller à leur respect pour éviter toute confusion dans l'exécution.
D61: Mise à jour de l’organigramme en cas d’évolution des ressources | E61: L’organigramme est-il mis à jour en cas de changement de ressources ? | F61: NON | G61: Planning global projet validé | H61: Validation non formalisée de l’organisation projet | I61: Elevée | J61: Problèmes d’intégration si les responsabilités sont mal réparties ou non suivies. | K61: Formaliser la validation de l’organisation du projet pour garantir sa solidité et sa cohérence.
B62: planification | C62: S’assurer qu’il existe un planning directeur commun à tout le projet | D62: lanning global du projet formalisé et partagé | E62: Le planning global du projet est-il formalisé et partagé ? | F62: PAS | G62: Planning des phases, jalons et livrables | H62: Manque de mise à jour de l’organigramme en cas d’évolution | I62: Elevée | J62: Non-prise en compte des besoins réels, entraînant un échec du projet à répondre aux attentes. | K62: Mettre à jour l’organigramme du projet en cas d’évolution pour garantir une organisation claire et à jour.
D63: Intégration des grandes phases, jalons, livrables clés | E63: Le planning intègre-t-il les grandes phases, jalons et livrables clés ? | F63: NON | G63: Planning directeur et plannings détaillés alignés | H63: Mauvaise planification du projet ou non partage | I63: Elevée | J63: Retards dans l'exécution, surcoût, mauvaise qualité de livraison, confusion au sein de l’équipe projet. | K63: Partager et valider régulièrement la planification du projet avec toutes les parties prenantes pour garantir son bon déroulement.
D64: Cohérence entre le planning directeur et les plannings détaillés | E64: Le planning directeur est-il cohérent avec les plannings détaillés ? | F64: OUI | G64: PV de validation des plannings par responsables de lots | H64: Non-cohérence entre le planning directeur et les plannings détaillés | I64: Elevée | J64: Difficulté à respecter les délais, risque de non-respect des objectifs. | K64: Assurer une cohérence totale entre le planning directeur et les plannings détaillés.
D65: Validation du planning par les responsables de chaque lot ou domaine | E65: Le planning a-t-il été validé par les responsables de chaque lot ou domaine ? | F65: OUI | G65: Planning directeur versionné avec historique | H65: Non-validation des plannings par les responsables | I65: Elevée | J65: Risque de mauvaise gestion du projet, décision non validée, responsabilité floue. | K65: Valider les plannings avec les responsables concernés pour garantir leur pertinence et leur réalisme.
D66: Mises à jour régulières du planning directeur en cas de changement | E66: Le planning directeur est-il mis à jour régulièrement en cas de changement ? | F66: OUI | G66: Plan de projet complet (lots, livrables, délais, ressources) | H66: Mise à jour insuffisante ou inappropriée du planning | I66: Elevée | J66: Risque de non-alignement avec les objectifs du projet, problèmes d'organisation. | K66: Mettre à jour régulièrement le planning du projet pour tenir compte des imprévus ou ajustements nécessaires.
C67: S’assurer qu’il existe un plan de projet initial | D67: Plan de projet rédigé dès la phase de lancement | E67: Un plan de projet a-t-il été rédigé dès la phase de lancement ? | F67: OUI | G67: PV de validation du plan par MOA et MOE | H67: Planification incomplète dès la phase de lancement | I67: Elevée | J67: Risque de retard de livraison, mauvaise préparation des phases suivantes du projet. | K67: Finaliser le planning dès la phase de lancement et éviter les modifications fréquentes.
D68: Définition des lots, livrables, ressources et délais | E68: Les lots, livrables, ressources et délais sont-ils bien définis ? | F68: OUI | G68: Budget prévisionnel intégré au plan de projet | H68: Mauvaises prévisions des lots, livrables ou ressources | I68: Elevée | J68: Non-respect des délais, maldistribution des tâches et des ressources. | K68: Réaliser une estimation réaliste des lots, livrables et ressources dès le début du projet.
D69: Plan validé par la maîtrise d’ouvrage et la maîtrise d’œuvre | E69: Le plan est-il validé par la MOA et la MOE ? | F69: OUI | G69: Référencement documentaire du plan | H69: Non-réalisation de mises à jour régulières du plan | I69: Elevée | J69: Risque de non-atteinte des objectifs en raison de l'absence de mise à jour en temps réel. | K69: Réaliser des mises à jour régulières du plan en fonction de l’évolution des besoins et des ressources.
D70: Intégration d’un budget prévisionnel dans le plan | E70: Un budget prévisionnel est-il intégré dans le plan de projet ? | F70: OUI | G70: Historique des versions du plan | H70: Non-suivi des écarts entre prévision et réalité | I70: Elevée | J70: Risque d’écarts entre la planification et la réalité, difficultés d’anticipation. | K70: Suivre de près les écarts entre les prévisions et la réalité afin d’ajuster rapidement les actions à prendre.
D71: Référencement du plan dans la documentation projet | E71: Le plan est-il référencé dans la documentation projet ? | F71: OUI | G71: Suivi des écarts prévision/réalisation | H71: Révision insuffisante du plan après chaque phase majeure | I71: Elevée | J71: Mauvaise gestion des ressources, retard de réalisation des jalons. | K71: Réviser régulièrement le plan de projet après chaque phase majeure pour intégrer les enseignements tirés.
C72: S’assurer que ce plan de projet a été révisé | D72: Existence de versions successives du plan avec historique des modifications | E72: Existe-t-il des versions successives du plan avec un historique des modifications ? | F72: OUI | G72: PV de révision post-revue de phase | H72: Non-prise en compte des risques dans la révision du plan | I72: Elevée | J72: Risque d'oublier certains risques, impact sur la planification et la gestion des ressources. | K72: Prendre en compte les risques et réviser les plans en fonction de ceux-ci pour éviter des dérives.
D73: Suivi des écarts entre prévision et réalisation | E73: Les écarts entre prévision et réalisation sont-ils suivis ? | F73: NON | G73: Plan actualisé en fonction des risques | H73: Non-validation des révisions par les responsables concernés | I73: Elevée | J73: Risque d'inefficacité dans la prise de décisions, perte de temps dans les phases critiques. | K73: Valider systématiquement les révisions du plan avec les responsables concernés avant de les appliquer.
D74: Révision du plan après chaque phase majeure ou revue de projet | E74: Le plan est-il révisé après chaque phase majeure ou revue de projet ? | F74: NON | G74: PV de validation après chaque révision | H74: Révision des plans trop tardive ou incohérente | I74: Elevée | J74: Risque de perte de contrôle sur l’évolution du projet, erreurs de gestion. | K74: Eviter des révisions tardives et incohérentes en anticipant les ajustements nécessaires.
D75: Plan mis à jour en fonction des risques identifiés | E75: Le plan est-il mis à jour en fonction des risques identifiés ? | F75: OUI | G75: Plans détaillés par lot ou sous-projet | H75: Mauvaise gestion des ressources humaines | I75: Elevée | J75: Mauvaise gestion des ressources humaines, surcharge de travail ou sous-utilisation. | K75: Optimiser la gestion des ressources humaines en fonction des besoins du projet et des compétences disponibles.
D76: Nouvelle version validée à chaque révision | E76: Chaque révision du plan fait-elle l’objet d’une nouvelle validation ? | F76: OUI | G76: Planning détaillé avec tâches, durées, dépendances | H76: Mauvaise optimisation des charges entre les équipes | I76: Elevée | J76: Problèmes de communication interne, perte d’efficacité. | K76: Répartir les charges entre les équipes pour éviter les déséquilibres et garantir une gestion optimale des ressources.
C77: S’assurer qu’il existe des plans détaillés | D77: Plans détaillés disponibles pour chaque lot ou sous-projet | E77: Des plans détaillés sont-ils disponibles pour chaque lot ou sous-projet ? | F77: OUI | G77: Liste des responsables d’activités | H77: Manque de visibilité sur la charge restante et la capacité projetée | I77: Moyenne | J77: Manque de clarté sur les tâches à réaliser, manque de performance. | K77: Augmenter la visibilité sur la charge restante et la capacité projetée pour éviter des sous-estimations.
D78: Description des tâches, durées, ressources et dépendances | E78: Les tâches, durées, ressources et dépendances sont-elles décrites ? | F78: PAS | G78: Alignement entre plannings détaillés et planning directeur | H78: Mauvaise réallocation des ressources en cas d’imprévus | I78: Elevée | J78: Risque de perte de visibilité sur les progrès du projet, mauvaise gestion des priorités. | K78: Réallouer les ressources rapidement en cas d’imprévus pour minimiser les retards.
D79: Responsables identifiés pour chaque activité | E79: Des responsables sont-ils identifiés pour chaque activité ? | F79: PAS | G79: Outil de planification utilisé (ex. Gantt, Trello) | H79: Négligence des risques spécifiques au type de projet | I79: Elevée | J79: Échec dans la résolution des problèmes imprévus, baisse de qualité du projet. | K79: Identifier et traiter les risques spécifiques liés au type de projet pour éviter des échecs.
D80: Plans compatibles avec le planning directeur | E80: Les plans détaillés sont-ils compatibles avec le planning directeur ? | F80: OUI | G80: Historique des révisions des plans | H80: Mauvaise analyse de la criticité des risques | I80: Elevée | J80: Incapacité à anticiper les risques spécifiques, impact sur la performance du projet. | K80: Analyser les risques de manière détaillée et classer leur criticité pour une gestion proactive.
D81: Outils de suivi utilisés pour les plans détaillés (ex. Gantt, Trello, etc.) | E81: Des outils de suivi (ex. Gantt, Trello) sont-ils utilisés pour les plans détaillés ? | F81: OUI | G81: Rapport d’avancement avec ajustements documentés | H81: Plans de réponse aux risques inappropriés ou incomplets | I81: Elevée | J81: Mauvaise prise en charge des risques stratégiques ou opérationnels. | K81: Concevoir des plans de réponse aux risques appropriés et en tenir compte dans la gestion quotidienne du projet.
C82: S’assurer que ces plans ont été révisés | D82: Historique des révisions disponible | E82: L’historique des révisions de plans est-il disponible ? | F82: NON | G82: PV de validation des révisions par responsables | H82: Non-suivi régulier du registre des risques | I82: Elevée | J82: Incapacité à atténuer efficacement les risques, perturbations dans le projet. | K82: Suivre régulièrement le registre des risques pour assurer une mise à jour constante.
D83: Révision des plans en fonction de l’avancement réel | E83: Les plans sont-ils révisés selon l’avancement réel du projet ? | F83: NON | G83: CR des comités avec point sur les plans | H83: Absence de révisions régulières des risques | I83: Elevée | J83: Absence de prise en compte de l'impact des risques, manque de réactivité. | K83: Réévaluer les risques de manière périodique pour prendre en compte les nouveaux éléments et les imprévus.
D84: Ajustement des plans selon les ressources et contraintes rencontrées | E84: Les plans sont-ils ajustés en fonction des ressources et contraintes rencontrées ? | F84: NON | G84: Tableau de suivi de l’affectation des ressources | H84: Oubli des risques techniques spécifiques à la solution | I84: Elevée | J84: Manque de visibilité sur les progrès du projet, retard dans l’atteinte des objectifs. | K84: Considérer spécifiquement les risques techniques liés à la solution envisagée pour éviter des perturbations.
D85: Validation des révisions par les responsables concernés | E85: Les révisions sont-elles validées par les responsables concernés ? | F85: NON | G85: Prise en compte des contraintes RH documentée | H85: Dépendance excessive vis-à-vis de technologies externes | I85: Elevée | J85: Non-assurance d’une gestion proactive des risques, altération des processus du projet. | K85: Diversifier les solutions et ne pas trop dépendre de technologies externes pour limiter les risques.
D86: Révision systématique lors des comités de suivi | E86: Les comités de suivi incluent-ils une révision systématique des plans ? | F86: NON | G86: Rapport d’optimisation de charge inter-équipes | H86: Non-évaluation de la maturité des technologies utilisées | I86: Elevée | J86: Mauvaise révision des risques après chaque étape importante, manque de réactivité face aux imprévus. | K86: Evaluer la maturité des technologies utilisées pour éviter des surprises pendant la phase de mise en œuvre.
C87: S’assurer que les plans intègrent une gestion optimale des ressources | D87: Affectation des ressources alignée avec les disponibilités réelles | E87: L’affectation des ressources est-elle alignée avec leur disponibilité réelle ? | F87: OUI | G87: Indicateur de charge restante vs. capacité | H87: Absence de solutions de contournement en cas de défaillance | I87: Elevée | J87: Risque d’erreur dans les choix technologiques, défaillance du projet. | K87: Prévoir des solutions de contournement en cas de défaillance pour garantir la continuité du projet.
D88: Prise en compte des congés, formations et autres contraintes humaines | E88: Les contraintes humaines (congés, formations) sont-elles prises en compte ? | F88: OUI | G88: Procédure de réallocation de ressources | H88: Non-prise en compte des risques de sécurité et de compatibilité | I88: Elevée | J88: Risque d'interruption du projet en cas de défaillance de la technologie externe. | K88: Intégrer les risques de sécurité et de compatibilité dans l’analyse globale des risques.
D89: Optimisation des charges entre les différentes équipes | E89: La charge est-elle optimisée entre les différentes équipes ? | F89: OUI | G89: Registre des risques projet | H89: Mauvaise identification des risques spécifiques au projet | I89: Elevée | J89: Risques de faible performance technique, erreurs critiques non identifiées. | K89: Identifier spécifiquement les risques liés au projet et mettre en place des plans d'atténuation adaptés.
D90: Visibilité sur la charge restante et la capacité projetée | E90: Existe-t-il une visibilité sur la charge restante et la capacité projetée ? | F90: OUI | G90: Analyse des risques (criticité, probabilité) | H90: Mise à jour insuffisante du registre des risques | I90: Elevée | J90: Absence de préparation aux risques techniques, impact négatif sur la livraison. | K90: Mettre à jour régulièrement le registre des risques pour refléter l'évolution de la situation du projet.
D91: Mécanisme de réallocation des ressources en cas d’imprévus | E91: Un mécanisme de réallocation des ressources est-il prévu en cas d’imprévus ? | F91: PAS | G91: Plan de réponse aux risques majeurs | H91: Absence d'analyse d'impact ou de plan de traitement des risques | I91: Elevée | J91: Risques opérationnels majeurs si la technologie échoue ou devient obsolète. | K91: Analyser l'impact de chaque risque et prévoir un plan de traitement adapté pour limiter leur impact.
C92: S’assurer qu’il existe une évaluation des risques liés à la nature du projet | D92: Identification des risques spécifiques au type de projet (ex. complexité, innovation) | E92: Les risques spécifiques au type de projet sont-ils identifiés ? | F92: PAS | G92: Mise à jour régulière du registre des risques | H92: Mauvaise communication des risques aux parties prenantes | I92: Elevée | J92: Manque de solutions de secours, prolongation des délais. | K92: Communiquer régulièrement sur les risques aux parties prenantes pour garantir une gestion transparente.
D93: Analyse de criticité et probabilité de survenue | E93: Les risques sont-ils analysés en termes de criticité et de probabilité ? | F93: OUI | G93: Procédure de revue périodique des risques | H93: Non-suivi des plans d'atténuation ou des mesures correctives | I93: Elevée | J93: Risque de mise en échec du projet, données compromises, non-conformité. | K93: Suivre de près l’efficacité des plans d'atténuation et des mesures correctives pour garantir leur efficacité.
D94: Élaboration de plans de réponse aux risques majeurs | E94: Des plans de réponse aux risques majeurs sont-ils élaborés ? | F94: PAS | G94: Liste des risques techniques documentés | H94: Analyse insuffisante des points critiques du planning | I94: Elevée | J94: Identification incorrecte des risques spécifiques, absence d’outils d’atténuation. | K94: Analyser régulièrement les points critiques du planning et agir rapidement en cas de dérives.
D95: Suivi régulier du registre des risques | E95: Le registre des risques est-il suivi régulièrement ? | F95: OUI | G95: Analyse des dépendances technologiques | H95: Mauvaise évaluation des marges de manœuvre | I95: Elevée | J95: Mauvaise communication de l'impact des risques sur le projet, perturbation des équipes. | K95: Evaluer correctement les marges de manœuvre disponibles pour anticiper les retards ou obstacles éventuels.
D96: Révisions périodiques de l’évaluation des risques | E96: L’évaluation des risques fait-elle l’objet de révisions périodiques ? | F96: PAS | G96: Évaluation de maturité technologique | H96: Dérive non anticipée par jalon | I96: Elevée | J96: Risques techniques non traités, risques d’échec pour le produit final. | K96: Anticiper les dérives à chaque jalon pour pouvoir prendre les mesures nécessaires en temps utile.
C97: S’assurer qu’il existe une évaluation des risques liés à la technologie utilisée | D97: Identification des risques techniques propres à la solution retenue | E97: Les risques techniques liés à la solution retenue sont-ils identifiés ? | F97: OUI | G97: Plan de contournement en cas de défaillance | H97: Non-mise en place d'indicateurs d'alerte sur les retards | I97: Elevée | J97: Incapacité à gérer les imprévus, absence de plans de contingence, mauvaises décisions. | K97: Mettre en place des indicateurs d'alerte précoces pour identifier les retards avant qu'ils ne deviennent problématiques.
D98: Analyse des dépendances vis-à-vis de technologies externes | E98: Les dépendances technologiques externes sont-elles analysées ? | F98: PAS | G98: Évaluation des risques de sécurité et de maintenance | H98: Plans de rattrapage inadaptés | I98: Elevée | J98: Pas de suivi des actions et de mesures correctives, erreur persistante. | K98: Mettre en place des plans de rattrapage réalistes pour pallier aux retards identifiés.
D99: Évaluation de la maturité des technologies utilisées | E99: La maturité des technologies utilisées est-elle évaluée ? | F99: OUI | G99: Registre consolidé des risques projets actifs | H99: Mauvaise documentation de l’organigramme de pilotage | I99: Elevée | J99: Manque d’indicateurs de performance, mauvaise gestion des ressources. | K99: Documenter clairement l'organigramme de pilotage pour éviter toute ambiguïté dans la gestion du projet.
D100: Existence de solutions de contournement en cas de défaillance | E100: Des solutions de contournement sont-elles prévues en cas de défaillance ? | F100: PAS | G100: Tableau de bord d’analyse des impacts de risques | H100: Manque de communication des rôles et responsabilités | I100: Elevée | J100: Risque de décision incohérente, impact sur la phase de développement et les livrables. | K100: Assurer une communication claire et formelle des rôles et responsabilités à toutes les parties prenantes.
...

Sheet 4.4 Support Utilisateur
A1: Domaine | B1: Points de controle | C1: Objectifs de controle | D1: Criteres d'évaluations | E1: Questions d'évaluation | F1: Réponses | G1: Document requis | H1: Risque | I1: Criticités | J1: Conséquence | K1: Recommandations
A2: Support utilisateur | B2: Fonction support | C2: S’assurer qu’une structure de centre d’assistance (help-desk) (HD) est mise en place | D2: Vérifier l'existence d'une charte du HD | E2: Où trouver la charte officielle du HD ? | F2: NON | G2: Charte du help desk validée | H2: Non-respect des procédures | I2: Elevée | J2: Incohérence dans le service | K2: Publier la charte sur l'intranet et la partager lors des formations
D3: S'assurer de la définition des rôles (techniciens, superviseurs) | E3: Qui compose l'équipe du help desk ? | F3: OUI | G3: Organigramme de l'équipe HD | H3: Manque de visibilité sur les interlocuteurs | I3: Moyenne | J3: Retards de traitement | K3: Mettre à jour trimestriellement l'organigramme avec contacts
D4: Contrôler l'organisation des plannings | E4: Comment sont organisées les permanences ? | F4: OUI | G4: Planning des permanences | H4: Désorganisation des plannings | I4: Moyenne | J4: Absence de couverture | K4: Automatiser la gestion des plannings avec alertes de chevauchement
D5: Vérifier les locaux et équipements dédiés | E5: Existe-t-il un espace physique dédié ? | F5: OUI | G5: Inventaire des locaux | H5: Conditions de travail inadaptées | I5: Elevée | J5: Baisse de productivité | K5: Prévoir un espace ergonomique conforme aux normes
D6: S'assurer du budget alloué | E6: Quel budget annuel est consacré au HD ? | F6: NON | G6: Budget annuel approuvé | H6: Dépenses non contrôlées | I6: Moyenne | J6: Dérives financières | K6: Établir un suivi budgétaire mensuel
C7: S’assurer qu’une procédure de gestion des demandes d’assistance est diffusée et connue des utilisateurs | D7: Vérifier le document de procédure validé | E7: Où consulter la procédure complète ? | F7: NON | G7: Manuel des procédures HD | H7: Application disparate des règles | I7: Elevée | J7: Service hétérogène | K7: Centraliser la documentation dans un référentiel unique
D8: S'assurer des canaux de diffusion (intranet, affichage) | E8: Comment les utilisateurs accèdent-ils à l'info ? | F8: NON | G8: Guide d'accès aux ressources | H8: Mauvaise information des usagers | I8: Moyenne | J8: Surcharge du support | K8: Créer un portail self-service avec FAQ intelligente
D9: Contrôler les sessions d'information utilisateurs | E9: Quand ont eu lieu les dernières formations ? | F9: NON | G9: Registre des formations | H9: Compétences obsolètes | I9: Moyenne | J9: Erreurs de diagnostic | K9: Planifier des formations semestrielles obligatoires
D10: Vérifier l'existence de supports synthétiques | E10: Existe-t-il une fiche mémo utilisateur ? | F10: PAS | G10: Kit d'autoformation utilisateur | H10: Appels évitables | I10: Elevée | J10: Saturation du help desk | K10: Distribuer des fiches visuelles par processus métier
D11: S'assurer des tests de connaissance | E11: Comment évalue-t-on la compréhension des usagers ? | F11: NON | G11: Questionnaire de satisfaction | H11: Besoins mal identifiés | I11: Moyenne | J11: Solutions inadaptées | K11: Implémenter un système de feedback après résolution
C12: S’assurer qu’une procédure d'escalade mise en place | D12: Vérifier les niveaux d'escalade définis | E12: Combien de niveaux d'escalade existent ? | F12: NON | G12: Procédure d'escalade | H12: Blocage des tickets complexes | I12: Moyenne | J12: Délais excessifs | K12: Limiter à 3 niveaux maximum avec délais définis
D13: S'assurer des seuils de déclenchement | E13: Quels critères déclenchent une escalade ? | F13: NON | G13: Grille de critères d'escalade | H13: Escalades inappropriées | I13: Moyenne | J13: Mauvaise allocation des ressources | K13: Définir des seuils objectifs (temps, criticité)
D14: Contrôler les fiches contacts urgents | E14: Où trouver les contacts des experts ? | F14: NON | G14: Annuaire des référents techniques | H14: Perte de temps en recherche | I14: Elevée | J14: Résolution retardée | K14: Maintenir une liste certifiée mise à jour mensuellement
D15: Vérifier les délais de réponse par niveau | E15: Quel délai maximum pour un problème critique ? | F15: OUI | G15: SLA formalisé | H15: Dégradation de service | I15: Elevée | J15: Impact opérationnel majeur | K15: Fixer un délai de 2h max pour les P1 avec alerte automatique
D16: S'assurer des comptes-rendus d'incident | E16: Comment sont documentés les incidents majeurs ? | F16: OUI | G16: Fiche post-mortem d'incident | H16: Répétition des erreurs | I16: Moyenne | J16: Indisponibilités récurrentes | K16: Rédiger systématiquement un retour d'expérience
C17: S’assurer de la couverture géographique du HD | D17: Vérifier les zones desservies | E17: Quels sites/pays sont couverts ? | F17: OUI | G17: Périmètre de couverture géographique | H17: Demandes hors zone | I17: Moyenne | J17: Frustration des usagers | K17: Cartographier clairement les zones couvertes/non couvertes
D18: S'assurer des horaires de disponibilité | E18: Quelles sont les plages horaires d'ouverture ? | F18: PAS | G18: Tableau des horaires de service | H18: Attentes déçues | I18: Elevée | J18: Insatisfaction client | K18: Afficher les horaires sur tous les canaux de contact
D19: Contrôler les compétences linguistiques | E19: Quelles langues sont disponibles ? | F19: OUI | G19: Politique linguistique du support | H19: Barrière de communication | I19: Elevée | J19: Incompréhension | K19: Recruter des agents multilingues pour les langues principales
D20: Vérifier les fuseaux horaires couverts | E20: Comment gère-t-on les différences horaires ? | F20: NON | G20: Procédure de gestion des fuseaux | H20: Erreurs de planning | I20: Moyenne | J20: Service non disponible | K20: Utiliser un outil de planification avec fuseaux horaires
D21: S'assurer des relais locaux | E21: Existe-t-il des correspondants locaux ? | F21: PAS | G21: Liste des correspondants locaux | H21: Délais de réponse allongés | I21: Elevée | J21: Résolution inefficace | K21: Désigner un référent par zone géographique
C22: S’assurer de la couverture fonctionnelle du HD | D22: Vérifier la liste des applications supportées | E22: Quels logiciels sont pris en charge ? | F22: NON | G22: Catalogue des applications supportées | H22: Demandes hors périmètre | I22: Elevée | J22: Perte de temps | K22: Mettre à jour le catalogue à chaque nouvelle version
D23: S'assurer des périmètres d'intervention | E23: Quelles demandes sont hors périmètre ? | F23: NON | G23: Liste des exclusions de service | H23: Attentes irréalistes | I23: Elevée | J23: Conflits avec les usagers | K23: Communiquer clairement sur les limites du support
D24: Contrôler les limites d'assistance documentées | E24: Où sont listées les limites d'intervention ? | F24: NON | G24: Charte des responsabilités | H24: Empiètement sur d'autres services | I24: Elevée | J24: Tensions internes | K24: Délimiter visuellement les zones de responsabilité
D25: Vérifier les compétences techniques de l'équipe | E25: L'équipe a-t-elle les certifications nécessaires ? | F25: OUI | G25: Registre des certifications | H25: Incompétence technique | I25: Moyenne | J25: Résolutions inadéquates | K25: Financer les certifications obligatoires annuellement
D26: S'assurer des partenariats avec les éditeurs | E26: Comment contacter les support éditeurs ? | F26: OUI | G26: Liste des contacts éditeurs | H26: Délais prolongés | I26: Elevée | J26: Prolongation des incidents | K26: Négocier des canaux prioritaires avec les éditeurs clés
C27: S’assurer qu’un outil est implémenté pour la prise d'appel et le suivi des tickets ; | D27: Vérifier l'existence d'un logiciel dédié | E27: Quel outil est utilisé pour la gestion des tickets ? | F27: OUI | G27: Documentation de l'outil ITSM | H27: Mauvaise utilisation de l'outil | I27: Moyenne | J27: Données inexploitables | K27: Former les agents à l'outil et auditer son usage
D28: S'assurer de l'intégration avec les autres systèmes | E28: Est-il connecté à l'annuaire et au monitoring ? | F28: OUI | G28: Architecture d'intégration | H28: Silos d'information | I28: Moyenne | J28: Diagnostic incomplet | K28: Automatiser les flux entre systèmes via API
D29: Contrôler les fonctionnalités de base (création, suivi, clôture) | E29: Peut-on suivre l'historique complet d'un ticket ? | F29: OUI | G29: Politique de rétention des données | H29: Manque de transparence | I29: Elevée | J29: Difficulté d'audit | K29: Configurer l'outil pour conserver l'historique 12 mois
D30: Vérifier les droits d'accès différenciés | E30: Comment gère-t-on les droits des agents ? | F30: NON | G30: Matrice des habilitations | H30: Accès non autorisés | I30: Moyenne | J30: Fuites d'information | K30: Appliquer le principe du moindre privilège
D31: S'assurer des sauvegardes régulières | E31: Quelle est la fréquence des sauvegardes ? | F31: NON | G31: Politique de sauvegarde | H31: Perte de données | I31: Moyenne | J31: Interruption de service | K31: Sauvegarder quotidiennement avec test mensuel de restauration
C32: S’assurer que des critères à renseigner pour la qualification des tickets existent | D32: Vérifier la grille de qualification obligatoire | E32: Quels critères doivent être renseignés ? | F32: NON | G32: Template de ticket obligatoire | H32: Tickets incomplets | I32: Moyenne | J32: Retards de traitement | K32: Rendre obligatoires les champs critiques (urgence, impact)
D33: S'assurer de la typologie des tickets | E33: Comment classe-t-on les demandes (incident, requête | F33: NON | G33: Arbre de décision de classification | H33: Mauvaise priorisation | I33: Elevée | J33: Ressources mal allouées | K33: Utiliser des algorithmes de classification automatique
D34: Contrôler les champs obligatoires | E34: Quels champs ne peuvent pas être laissés vides ? | F34: PAS | G34: Règles de validation des tickets | H34: Données manquantes | I34: Elevée | J34: Impossible à traiter | K34: Configurer des validations obligatoires dans l'outil
D35: Vérifier les règles d'affectation automatique | E35: Comment sont attribués les tickets aux techniciens ? | F35: NON | G35: Procédure d'assignation | H35: Charge déséquilibrée | I35: Moyenne | J35: Surcharge des experts | K35: Automatiser l'assignation par compétences/disponibilité
D36: S'assurer des indicateurs de qualité | E36: Comment mesure-t-on la qualité de qualification ? | F36: NON | G36: Grille d'évaluation des tickets | H36: Erreurs répétées | I36: Moyenne | J36: Réouvertures fréquentes | K36: Auditer aléatoirement 10% des tickets qualifiés
C37: S’assure qu’il existe une liste de questions à dérouler lors d'un appel afin préciser au mieux la demande de l'utilisateur | D37: Vérifier l'existence d'un arbre de questions | E37: Où trouver le script des questions standard ? | F37: NON | G37: Bibliothèque de scripts | H37: Approche non standardisée | I37: Elevée | J37: Informations manquantes | K37: Intégrer les scripts dans l'outil de ticketing
D38: S'assurer de l'adaptation aux différents types de demandes | E38: Existe-t-il des variantes selon la nature du problème ? | F38: NON | G38: Arbres décisionnels par type d'incident | H38: Diagnostic imprécis | I38: Elevée | J38: Résolution inadaptée | K38: Développer des workflows spécifiques par catégorie
D39: Contrôler la mise à jour régulière | E39: Quand a-t-il été mis à jour pour la dernière fois ? | F39: OUI | G39: Historique des versions des scripts | H39: Questions obsolètes | I39: Moyenne | J39: Efficacité réduite | K39: Réviser les scripts tous les 6 mois
D40: Vérifier l'ergonomie du questionnaire | E40: Le questionnaire est-il facile à utiliser ? | F40: OUI | G40: Rapport d'ergonomie | H40: Résistance des agents | I40: Elevée | J40: Non-utilisation | K40: Concevoir des interfaces intuitives avec UX designer
D41: S'assurer de l'utilisation effective | E41: Comment vérifie-t-on son application ? | F41: OUI | G41: Procédure d'audit des appels | H41: Écarts par rapport au script | I41: Moyenne | J41: Qualité inconstante | K41: Enregistrer et analyser aléatoirement des appels
C42: S’assurer qu’il existe une aide à la saisie pour la saisie des tickets | D42: Un guide de saisie complet et actualisé est disponible pour les utilisateurs | E42: Existe-t-il un document ou un module d'aide détaillant la procédure de création des tickets ? | F42: PAS | G42: Manuel de procédure de ticketing | H42: Tickets mal formulés | I42: Elevée | J42: Retards de traitement | K42: Développer un guide interactif avec vidéos explicatives
D43: L'aide à la saisie est facilement accessible depuis l'interface de ticket | E43: Les utilisateurs peuvent-ils accéder à l'aide directement dans l'outil de ticketing ? | F43: OUI | G43: Capture d'écran de l'interface | H43: Mauvaise utilisation | I43: Elevée | J43: Saisie incomplète | K43: Intégrer un chatbot d'assistance contextuelle
D44: Des exemples concrets et des modèles sont fournis pour faciliter la saisie | E44: L'aide comprend-elle des cas pratiques et des templates prédéfinis ? | F44: NON | G44: Bibliothèque de templates | H44: Incohérence des données | I44: Moyenne | J44: Difficultés d'analyse | K44: Standardiser 5 templates types couvrant 80% des cas
D45: Un mécanisme d'auto-complétion ou d'assistance intelligente est implémenté | E45: L'outil propose-t-il des suggestions automatiques pendant la saisie ? | F45: PAS | G45: Logs des fonctionnalités IA | H45: Erreurs de saisie | I45: Elevée | J45: Mauvais routage | K45: Implémenter une IA de suggestion basée sur l'historique
D46: Une formation initiale sur l'utilisation de l'aide est dispensée aux nouveaux utilisateurs | E46: Les collaborateurs reçoivent-ils une formation spécifique sur l'utilisation des outils d'aide ? | F46: PAS | G46: Programme de formation | H46: Sous-utilisation | I46: Elevée | J46: ROI faible | K46: Organiser des ateliers mensuels "découverte"
C47: S’assurer qu’il existe des revues qualité pour la saisie des tickets | D47: S'assurer qu'il existe des revues qualité pour la saisie des tickets | E47: 1. Une procédure formalisée de revue qualité est documentée et accessible | F47: PAS | G47: Procédure QC signée | H47: Non-conformité | I47: Elevée | J47: Amendes | K47: Nommer un responsable qualité dédié
D48: Les revues qualité sont planifiées régulièrement avec une fréquence définie | E48: Des sessions de revue sont-elles organisées au moins mensuellement ? | F48: NON | G48: PV des réunions QC | H48: Problèmes récurrents | I48: Elevée | J48: Insatisfaction | K48: Automatiser les rappels de réunion
D49: Un comité pluridisciplinaire participe activement aux revues qualité | E49: Plusieurs services concernés sont-ils représentés dans les revues ? | F49: NON | G49: Liste des participants | H49: Silotage | I49: Moyenne | J49: Solutions partielles | K49: Imposer 3 services minimum par revue
D50: Un système de suivi des actions correctives est mis en place | E50: Les anomalies identifiées font-elles l'objet d'un plan d'action avec responsable et échéance ? | F50: OUI | G50: Fiche d'action corrective | H50: Corrections inefficaces | I50: Elevée | J50: Répétition erreurs | K50: Utiliser la méthode 5W2H pour les actions
D51: Des indicateurs de performance mesurent l'impact des revues qualité | E51: Peut-on constater une amélioration quantitative de la qualité des tickets après mise en œuvre des revues ? | F51: OUI | G51: Dashboard qualité | H51: Décisions non data-driven | I51: Moyenne | J51: Gaspillage | K51: Suivre 3 KPIs clés (complétude, temps, réouverture)
C52: Vérifier l’existence d’une base de connaissance | D52: Vérifier l'existence d'une base de connaissance | E52: 1. La base de connaissance est centralisée et accessible à l'ensemble des acteurs concernés | F52: OUI | G52: Inventaire des ressources | H52: Duplication | I52: Moyenne | J52: Confusion | K52: Migrer vers une plateforme unique type SharePoint
D53: Le contenu est organisé par thématiques et mots-clés pertinents | E53: La recherche d'informations dans la base est-elle intuitive et efficace ? | F53: OUI | G53: Rapport d'UX | H53: Abandon des recherches | I53: Elevée | J53: Appels évitables | K53: Ajouter un moteur de recherche sémantique
D54: Un processus de validation et de mise à jour des articles est formalisé | E54: Chaque article de la base fait-il l'objet d'une validation avant publication ? | F54: OUI | G54: Workflow de publication | H54: Information erronée | I54: Moyenne | J54: Décisions fautives | K54: Mettre en place une validation à 2 niveaux
D55: La base intègre des fonctionnalités de feedback utilisateur | E55: Les utilisateurs peuvent-ils noter et commenter les articles ? | F55: OUI | G55: Système de feedback | H55: Contenu obsolète | I55: Elevée | J55: Perte de confiance | K55: Implémenter un "like/dislike" avec commentaires
D56: Des statistiques d'utilisation et d'efficacité sont régulièrement analysées | E56: La fréquentation et l'utilité perçue de la base sont-elles mesurées ? | F56: OUI | G56: Analytics d'usage | H56: Investissement non justifié | I56: Moyenne | J56: Désengagement | K56: Calculer un indice de satisfaction (CSAT)
C57: S’assurer que les appels sont enregistrés+B62 | D57: S'assurer que les appels sont enregistrés | E57: 1. L'ensemble des canaux de communication avec les utilisateurs fait l'objet d'enregistrements | F57: OUI | G57: Audit de conformité | H57: Sanctions | I57: Moyenne | J57: Amendes | K57: Désigner un DPO interne
D58: La politique d'enregistrement est conforme aux réglementations en vigueur | E58: Les modalités d'enregistrement respectent-elles les exigences du RGPD ? | F58: OUI | G58: Matrice des habilitations | H58: Fuites de données | I58: Elevée | J58: Atteinte réputation | K58: Mettre en place un PAM (Privileged Access Management)
D59: Les enregistrements sont stockés de manière sécurisée avec contrôle d'accès | E59: Seules les personnes autorisées peuvent-elles accéder aux enregistrements ? | F59: OUI | G59: Politique de rétention | H59: Stockage illégal | I59: Elevée | J59: Problèmes légaux | K59: Appliquer la durée maximale de 13 mois
D60: La durée de conservation des enregistrements est définie et appliquée | E60: Existe-t-il une règle claire concernant la période de conservation des données ? | F60: NON | G60: Catalogue des cas d'apprentissage | H60: Opportunités perdues | I60: Moyenne | J60: Stagnation | K60: Créer une librairie anonymisée pour le coaching
D61: Un échantillonnage des enregistrements est utilisé pour l'amélioration continue | E61: Les enregistrements servent-ils régulièrement à des fins de formation et d'optimisation ? | F61: NON | G61: Politique de réutilisation | H61: Non valorisation | I61: Elevée | J61: Retour sur investissement faible | K61: Formaliser un processus d'extraction de bonnes pratiques
C62: S’assurer que les appels sont enregistrés | D62: Image master standardisée disponible | E62: Existe-t-il des images système de référence ? | F62: NON | I62: Moyenne
D63: Configuration minimum définie | E63: Les spécifications minimales sont-elles documentées ? | F63: OUI | I63: Elevée
D64: Processus de déploiement automatisé | E64: L'installation peut-elle se faire sans intervention manuelle ? | F64: OUI | I64: Elevée
D65: Tests de conformité post-installation | E65: Vérifie-t-on la conformité des machines déployées ? | F65: OUI | I65: Moyenne
D66: Mise à jour régulière du master | E66: L'image de référence est-elle actualisée trimestriellement ? | F66: OUI | I66: Elevée
C67: S’assurer que des études de satisfaction sont réalisées auprès des utilisateurs | D67: S'assurer que des études de satisfaction sont réalisées | E67: 1. Un questionnaire standardisé est utilisé pour mesurer la satisfaction utilisateur | F67: NON | G67: Modèle de questionnaire validé | H67: Feedback non standardisé | I67: Elevée | J67: Données non comparables | K67: Adopter un outil professionnel type NPS/CSAT
D68: La fréquence des enquêtes permet un suivi significatif de l'évolution | E68: Des enquêtes sont-elles menées après chaque interaction significative avec les utilisateurs ? | F68: NON | G68: Calendrier des enquêtes | H68: Perception incomplète | I68: Elevée | J68: Opportunités manquées | K68: Automatiser les sondages post-intervention
D69: Les résultats sont analysés et présentés sous forme de tableaux de bord | E69: Les données de satisfaction font-elles l'objet d'un reporting mensuel ? | F69: NON | G69: Exemple de dashboard satisfaction | H69: Décisions sans données | I69: Elevée | J69: Stagnation qualité | K69: Produire un rapport analytique mensuel
D70: Des actions correctives sont engagées lorsque les scores sont insuffisants | E70: Les retours négatifs déclenchent-ils systématiquement un plan d'amélioration ? | F70: NON | G70: Procédure gestion réclamations | H70: Problèmes récurrents | I70: Moyenne | J70: Dégradation service | K70: Instaurer un processus de traitement en 48h
D71: La communication des résultats et des améliorations est faite auprès des utilisateurs | E71: Les clients sont-ils informés des mesures prises suite à leurs feedbacks ? | F71: PAS | G71: Modèle de communication post-feedback | H71: Manque de transparence | I71: Moyenne | J71: Perte de confiance | K71: Envoyer un retour personnalisé sous 5 jours
C72: S’assurer qu’il existe une évaluation de l’équipe HD, notamment pour les prestataires afin d’en évaluer le niveau de connaissance | D72: S'assurer qu'il existe une évaluation de l'équipe HD | E72: 1. Un référentiel de compétences techniques et relationnelles est défini pour le HD | F72: NON | G72: Référentiel métier complet | H72: Compétences hétérogènes | I72: Elevée | J72: Service inégal | K72: Cartographier 10 compétences clés
D73: Le processus d'évaluation inclut des mesures objectives et des feedbacks qualitatifs | E73: Les évaluations combinent-elles des KPI quantitatifs et des appréciations managériales ? | F73: NON | G73: Grille d'évaluation mixte | H73: Jugement subjectif | I73: Moyenne | J73: Démotivation | K73: Pondérer 70% KPI/30% qualitatif
D74: Les prestataires externes sont soumis aux mêmes exigences d'évaluation que le personnel interne | E74: Les sous-traitants font-ils l'objet d'évaluations régulières selon les mêmes critères ? | F74: NON | G74: Rapport d'évaluation fournisseurs | H74: Double standard | I74: Elevée | J74: Risque qualité | K74: Appliquer le même référentiel
D75: Les résultats des évaluations influent sur les plans de formation individuels | E75: Chaque collaborateur dispose-t-il d'un programme de développement personnalisé ? | F75: NON | G75: Plan de développement individuel | H75: Stagnation compétences | I75: Moyenne | J75: Turnover | K75: Co-construire des PDP annuels
D76: La performance globale de l'équipe HD est suivie dans le temps | E76: Des indicateurs synthétiques permettent-ils de mesurer les progrès collectifs ? | F76: OUI | G76: Tableau de bord des compétences | H76: Vision parcellaire | I76: Moyenne | J76: Décisions erronées | K76: Calculer un indice de maturité trimestriel
C77: S’assurer que l’obtention des certifications (ITIL, ISO, COBIT, SIGMA) est encouragée au sein de la DSI, et du HD en particulier | D77: Encourager l'obtention de certifications | E77: 1. La direction affiche clairement son soutien à la démarche de certification | F77: OUI | G77: PV de comité de direction | H77: Manque d'engagement | I77: Elevée | J77: Échec certification | K77: Inclure la certification dans la stratégie
