Workbook

Sheet SYNTHESE
B2: Synthèse Numérique | J2: Equipe de Mission
B4: N° | C4: Domaines | D4: Total OUI | E4: Total NON | F4: Total PAS | G4: Total | H4: Score | L4: Nom | N4: Prénom | O4: Grade | P4: MATRICULE
B5: 1 | C5: AUDIT DES APPLICATIONS EN SERVICE | D5: =COUNTIF(APPLICATION_EN_SERVICE!E3:E507,"OUI ") -> 400 | E5: =COUNTIF(APPLICATION_EN_SERVICE!E3:E507,"NON ") -> 105 | F5: =COUNTIF(APPLICATION_EN_SERVICE!E3:E507,"PAS ") -> 0 | G5: =SUM(D5:F5) -> 505 | H5: =D5/G5 -> 0.79207921 | K5: Chef : | L5: TSAKENG | N5: CLAUDY JUNIOR | O5: L3 HN DS | P5: 22P088
B6: 2 | C6: FONCTION INFORMATIQUE | D6: =COUNTIF('(4.2)_REF_FONCTION_INFORMATIQUE'!E6:E510,"OUI") -> 266 | E6: =COUNTIF('(4.2)_REF_FONCTION_INFORMATIQUE'!E6:E510,"NON") -> 175 | F6: =COUNTIF('(4.2)_REF_FONCTION_INFORMATIQUE'!E6:E510,"PAS") -> 64 | G6: =SUM(D6:F6) -> 505 | H6: =D6/G6 -> 0.52673267
B7: 3 | C7: AUDIT DE CONTRÔLE DES PROJETS INFORMATIQUES | D7: =COUNTIF('(4.3)CONTROLE_PROJET_INFORMATIQ'!G3:G372,"OUI") -> 178 | E7: =COUNTIF('(4.3)CONTROLE_PROJET_INFORMATIQ'!G3:G372,"NON") -> 140 | F7: =COUNTIF('(4.3)CONTROLE_PROJET_INFORMATIQ'!G3:G372,"PAS") -> 52 | G7: =SUM(D7:F7) -> 370 | H7: =D7/G7 -> 0.48108108
B8: 4 | C8: AUDIT DES SUPPORTS UTILISATEURS | D8: =COUNTIF('(4.4)_AUDIT_SUPPORT_UTILISATEUR'!F4:F103,"OUI") -> 34 | E8: =COUNTIF('(4.4)_AUDIT_SUPPORT_UTILISATEUR'!F4:F103,"NON") -> 33 | F8: =COUNTIF('(4.4)_AUDIT_SUPPORT_UTILISATEUR'!F4:F103,"PAS") -> 33 | G8: =SUM(D8:F8) -> 100 | H8: =D8/G8 -> 0.34
B9: 5 | C9: AUDIT DE LA SECURITE INFORMATIQUE | D9: =COUNTIF('(4.5)_SECURITE_INFORMATIQUE'!E2:E331,"OUI") -> 188 | E9: =COUNTIF('(4.5)_SECURITE_INFORMATIQUE'!E2:E331,"NON") -> 122 | F9: =COUNTIF('(4.5)_SECURITE_INFORMATIQUE'!E2:E331,"PAS") -> 20 | G9: =SUM(D9:F9) -> 330 | H9: =D9/G9 -> 0.56969697
B10: 8 | C10: COSO | D10: =COUNTIF(COSO!F3:F402,"OUI") -> 317 | E10: =COUNTIF('(4.5)_SECURITE_INFORMATIQUE'!E2:E331,"NON") -> 122 | F10: =COUNTIF('(4.5)_SECURITE_INFORMATIQUE'!E2:E331,"PAS") -> 20 | G10: =SUM(D10:F10) -> 459 | H10: =D10/G10 -> 0.69063181
B11: Total | D11: =SUM(D5:D10) -> 1383 | E11: =SUM(E5:E10) -> 697 | F11: =SUM(F5:F10) -> 189 | G11: =SUM(G5:G10) -> 2269 | H11: =D11/G11 -> 0.60951961
B13: Sythèse Graphique

Sheet GLOBAL(du 4.1 au 4.5)
A1: DOMAINES | B1: points de contrôles | C1: objectifs de contrôle | D1: critères d'évaluation | E1: questions d'évaluation | F1: Réponses | G1: Documents requis | H1: Risques | I1: Criticités | J1: conséquences | K1: Recommendations
A2: AUDIT DES APPLICATIONS EN SERVICE | B2: Organisation | C2: S’assurer de l’existence d'un comité informatique | D2: Vérifier l’existence d’un organigramme officiel du comité signé par la direction. | E2: L'organigramme du comité est-il signé par la direction ? | F2: OUI | G2: Organigramme de l’entité | H2: Absence de gouvernance clairement définie | I2: Élevée | J2: Non-conformité aux réglementations en vigueur entraînant des sanctions légales. | K2: Élaborer un cadre de gouvernance aligné sur COBIT ou ISO 27001 en formalisant les rôles et responsabilités.
D3: Confirmer la présence d’au moins 3 procès-verbaux de réunion datés des 6 derniers mois. | E3: Trois procès-verbaux de réunion existent-ils pour les 6 derniers mois ? | F3: NON | G3: Organigramme fonctionnel de la DSI | H3: Documentation insuffisante des décisions stratégiques | I3: Moyenne | J3: Détérioration de la confiance des parties prenantes due à l'absence de traçabilité des décisions. | K3: Documenter et diffuser les politiques de sécurité et les procédures internes pour garantir leur accessibilité.
D4: Analyser la composition du comité (CV/certifications des membres). | E4: Les CV et certifications des membres du comité sont-ils disponibles ? | F4: OUI | G4: Procès-verbaux des réunions du comité | H4: Incompétence des membres du comité de pilotage | I4: Élevée | J4: Augmentation des erreurs opérationnelles par manque de directives claires. | K4: Mettre en place une formation continue sur les enjeux de sécurité et la conformité réglementaire pour les employés.
D5: Identifier un mandat écrit précisant les missions et la fréquence des réunions. | E5: Un mandat écrit définit-il les missions et la fréquence des réunions ? | F5: OUI | G5: Fiches de postes de la DSI | H5: Définition floue des responsabilités du comité | I5: Élevée | J5: Vulnérabilité accrue aux cyberattaques en raison de politiques obsolètes. | K5: Implémenter des contrôles d'accès stricts basés sur le principe du moindre privilège et revoir périodiquement les habilitations.
D6: Contrôler la diffusion des décisions du comité via des emails ou documents internes. | E6: Les décisions du comité sont-elles diffusées par email ou documents internes ? | F6: NON | G6: Politique des Applications approuvée par la direction | H6: Non-diffusion des orientations stratégiques aux équipes | I6: Élevée | J6: Inefficacité des contrôles internes causant des pertes financières. | K6: Concevoir et tester régulièrement un plan de continuité d'activité (PCA) et un plan de reprise d'activité (PRA).
C7: S’assurer de l’existence d'une politique relative aux applications | D7: Vérifier la présence d’un document intitulé "Politique des Applications" approuvé par la direction. | E7: La "Politique des Applications" est-elle approuvée par la direction ? | F7: OUI | G7: Accusés de réception des employés pour la politique | H7: Politique de sécurité non formalisée | I7: Élevée | J7: Exposition à des litiges juridiques faute de documentation appropriée. | K7: Instaurer une matrice des risques mise à jour annuellement et intégrée aux processus décisionnels.
D8: Confirmer la date de la dernière mise à jour (moins de 12 mois). | E8: La dernière mise à jour date-t-elle de moins de 12 mois ? | F8: NON | G8: Plan de formation annuel lié à la politique | H8: Non-conformité réglementaire | I8: Moyenne | J8: Dysfonctionnements dans la gestion des accès menant à des fuites de données sensibles. | K8: Automatiser les contrôles de validation des données critiques pour réduire les erreurs manuelles.
D9: Analyser les mentions de conformité RGPD/ISO dans le document. | E9: Le document mentionne-t-il la conformité RGPD/ISO ? | F9: OUI | G9: Matrice des autorisations/droits d’accès | H9: Manque de sensibilisation des employés aux politiques | I9: Moyenne | J9: Interruptions prolongées des activités en cas de sinistre non anticipé. | K9: Déployer des outils de surveillance en temps réel pour détecter les anomalies et les activités suspectes.
D10: Vérifier la diffusion de la politique aux employés (accusés de réception signés). | E10: Les employés ont-ils signé des accusés de réception pour la politique ? | F10: OUI | G10: Liste des 100 derniers incidents du domaine d’audit | H10: Absence de formation continue sur les enjeux de sécurité | I10: Élevée | J10: Dégradation de la performance des systèmes due à une maintenance inadéquate. | K10: Réaliser des audits réguliers des configurations des systèmes et des droits d'accès privilégiés.
D11: Identifier un plan de formation annuel lié à cette politique. | E11: Un plan de formation annuel lié à cette politique existe-t-il ? | F11: NON | G11: Rapport d’analyse des risques récent (moins de 12 mois) | H11: Définition imprécise des rôles utilisateurs | I11: Élevée | J11: Non-respect des engagements contractuels envers les clients ou partenaires. | K11: Mettre en œuvre des mécanismes de chiffrement des données en transit et au repos conformes aux normes ISO 27001.
C12: S’assurer que les rôle et responsabilités des utilisateurs sont bien définis | D12: Contrôler l’existence de fiches de poste pour chaque profil utilisateur. | E12: Des fiches de poste sont-elles disponibles pour chaque profil utilisateur ? | F12: OUI | G12: Document de classification des données (public, interne, confidentiel) | H12: Violation des engagements contractuels | I12: Élevée | J12: Augmentation des coûts opérationnels liés à des processus inefficients. | K12: Séparer les environnements de développement, de test et de production pour limiter les risques de corruption.
D13: Vérifier la signature des utilisateurs sur des chartes d’utilisation. | E13: Les utilisateurs ont-ils signé des chartes d'utilisation ? | F13: OUI | G13: Manuel d’administration des applications | H13: Droits d'accès obsolètes ou inadaptées | I13: Élevée | J13: Perte de données critiques par absence de sauvegardes fiables. | K13: Établir des procédures de gestion des incidents incluant une analyse post-mortem et des plans d'action correctifs.
D14: Confirmer la mise à jour des habilitations dans un tableau de gestion des accès. | E14: Le tableau de gestion des accès est-il à jour ? | F14: NON | G14: Logs d’accès aux données sensibles sur 30 jours | H14: Détournement de privilèges | I14: Élevée | J14: Retards dans les prises de décision faute d’informations actualisées. | K14: Valider l'exhaustivité et l'intégrité des sauvegardes via des tests de restauration périodiques.
D15: Analyser des logs d’accès pour corréler avec les rôles déclarés. | E15: Les logs d'accès correspondent-ils aux rôles déclarés ? | F15: OUI | G15: Procédures écrites pour les processus critiques | H15: Absence de revue périodique des habilitations | I15: Élevée | J15: Compromission de l’intégrité des données financières ou métiers. | K15: Créer un comité de pilotage IT pour superviser l'alignement stratégique des projets avec les objectifs métiers.
D16: Identifier des procédures de révision trimestrielle des droits. | E16: Une procédure de révision trimestrielle des droits est-elle en place ? | F16: OUI | G16: Comptes rendus mensuels de l’application | H16: Fraude interne via l'exploitation de droits excessifs | I16: Élevée | J16: Risque accru de fraude interne en l’absence de séparation des tâches. | K16: Utiliser des outils de gestion des identités et des accès (IAM) pour centraliser et auditer les permissions.
C17: S’assurer qu’une analyse des risques a été réalisée | D17: Vérifier un rapport d’analyse des risques daté de moins de 12 mois. | E17: Un rapport d'analyse des risques de moins de 12 mois existe-t-il ? | F17: OUI | G17: Guide utilisateur et manuel de procédures | H17: Évaluation des risques non actualisée | I17: Élevée | J17: Détérioration de la qualité des services IT impactant la satisfaction client. | K17: Réaliser des tests de pénétration et des audits de code pour identifier les vulnérabilités applicatives.
D18: Confirmer l’utilisation d’une méthodologie reconnue (ex : EBIOS, OCTAVE). | E18: La méthodologie utilisée est-elle reconnue (EBIOS, OCTAVE) ? | F18: NON | G18: Matrice des tâches et fonctions incompatibles | H18: Utilisation de méthodologies obsolètes | I18: Élevée | J18: Exposition à des amendes réglementaires pour non-conformité RGPD. | K18: Documenter les flux de données et les interfaces entre systèmes pour garantir la traçabilité des échanges.
D19: Analyser la liste des risques identifiés (au moins 10 risques critiques). | E19: Au moins 10 risques critiques sont-ils identifiés ? | F19: OUI | G19: Contrat de maintenance ou d’assistance | H19: Sous-estimation des menaces critiques | I19: Élevée | J19: Interruptions fréquentes des services en production par manque de redondance. | K19: Adopter une politique de gestion des correctifs avec des délais stricts pour les mises à jour critiques.
D20: Identifier un plan d’action avec des responsables et des échéances. | E20: Un plan d'action avec responsables et échéances est-il établi ? | F20: OUI | G20: Plan de continuité des activités (PCA) | H20: Absence de planification corrective | I20: Élevée | J20: Difficultés à assurer la continuité des activités lors de crises majeures. | K20: Instaurer des contrôles d'intégrité des données lors des migrations ou des transferts inter-systèmes.
D21: Contrôler des preuves de mise en œuvre des actions (rapports de suivi). | E21: Des preuves de mise en œuvre des actions sont-elles disponibles ? | F21: NON | G21: Plan de reprise d’activité (PRA) | H21: Contrôles inefficaces face aux risques identifiés | I21: Élevée | J21: Dépendance excessive vis-à-vis de prestataires externes non supervisés. | K21: Mettre en place une journalisation centralisée et une analyse proactive des logs pour détecter les menaces.
C22: S’assurer que le prolongement de l'analyse de risque et de son expansion ont été réalisés | D22: Vérifier des mises à jour de l’analyse des risques (au moins 2 révisions annuelles). | E22: L'analyse des risques a-t-elle été mise à jour deux fois dans l'année ? | F22: OUI | G22: Rapports de traitements des incidents | H22: Ignorance des nouvelles vulnérabilités | I22: Élevée | J22: Altération de la réputation de l’organisation suite à des incidents récurrents. | K22: Élaborer une charte de sécurité informatique incluant des clauses contractuelles avec les fournisseurs externes.
D23: Confirmer l’intégration des nouveaux risques (ex : cybermenaces, RGPD). | E23: Les nouveaux risques (cybermenaces, RGPD) sont-ils intégrés ? | F23: OUI | G23: Inventaire des licences | H23: Défaut de reporting aux instances décisionnelles | I23: Élevée | J23: Inefficacité des plans de reprise après sinistre prolongeant les temps d’arrêt. | K23: Concevoir des tableaux de bord de performance alignés sur les KPI métiers pour mesurer l'efficacité des SI.
D24: Analyser des indicateurs de suivi des risques (tableaux de bord). | E24: Des indicateurs de suivi des risques existent-ils ? | F24: OUI | G24: Bilan de qualité logiciel | H24: Culture du risque insuffisante dans l'organisation | I24: Élevée | J24: Augmentation des vulnérabilités logicielles par absence de mises à jour. | K24: Sensibiliser les utilisateurs aux risques de phishing et d'ingénierie sociale via des simulations régulières.
D25: Identifier des procédures de reporting aux instances dirigeantes. | E25: Des procédures de reporting aux instances dirigeantes sont-elles définies ? | F25: NON | G25: Bilan de satisfaction des utilisateurs | H25: Classification inappropriée des données sensibles | I25: Moyenne | J25: Désorganisation des équipes IT faute de procédures standardisées. | K25: Auditer régulièrement les configurations des pare-feux et des équipements réseau pour prévenir les attaques.
D26: Contrôler des preuves de sensibilisation des équipes aux risques majeurs. | E26: Les équipes sont-elles sensibilisées aux risques majeurs ? | F26: OUI | G26: Schéma d’interaction des applications métiers | H26: Exposition de données critiques | I26: Moyenne | J26: Non-atteinte des objectifs stratégiques en raison d’un mauvais alignement IT-métier. | K26: Intégrer des contrôles de conformité RGPD dans les processus de traitement des données personnelles.
C27: S’assurer que l’analyse et évaluation du niveau de sensibilité a été réalisée | D27: Vérifier un document classifiant les données par niveau de sensibilité (public, interne, confidentiel). | E27: Un document classe-t-il les données (public, interne, confidentiel) ? | F27: NON | G27: Diagramme de flux de données des applications | H27: Surveillance inadéquate des accès privilégiés | I27: Élevée | J27: Perte de compétitivité due à des technologies obsolètes ou sous-utilisées. | K27: Définir une stratégie de gestion des actifs numériques incluant leur classification et leur cycle de vie.
D28: Confirmer la mise à jour de la classification (moins de 6 mois). | E28: La classification a-t-elle été mise à jour dans les 6 mois ? | F28: OUI | G28: Procédures de gestion des changements | H28: Protection insuffisante des actifs informationnels | I28: Élevée | J28: Erreurs humaines accrues par manque de formation ou de documentation. | K28: Mettre en œuvre des contrôles d'accès physique aux salles serveurs et aux centres de données.
D29: Analyser des logs d’accès aux données sensibles sur 30 jours. | E29: Les logs d'accès aux données sensibles sur 30 jours sont-ils analysables ? | F29: OUI | G29: Logs de connexion avec adresses IP et horodatages | H29: Manque de formation sur la manipulation des données | I29: Faible | J29: Détection tardive des anomalies opérationnelles réduisant la réactivité. | K29: Réaliser des audits de sécurité des APIs pour prévenir les exploitations malveillantes.
D30: Identifier des procédures de protection spécifiques pour les données critiques. | E30: Des procédures spécifiques protègent-elles les données critiques ? | F30: NON | G30: Politique de sécurité des mots de passe | H30: Documentation technique obsolète | I30: Élevée | J30: Fuite d’informations confidentielles par des contrôles d’accès laxistes. | K30: Standardiser les procédures de gestion des changements avec validation technique et métier préalable.
D31: Contrôler des preuves de formation des utilisateurs sur la classification. | E31: Les utilisateurs sont-ils formés sur la classification des données ? | F31: OUI | G31: Procédures de gestion des identifiants et mots de passe | H31: Procédures de secours non testées | I31: Élevée | J31: Dégradation de la productivité des utilisateurs face à des outils inadaptés. | K31: Instaurer des revues indépendantes des architectures techniques pour garantir leur résilience.
C32: Vérifier l’existence d’un manuel d'administration de l'application | D32: Vérifier l’existence d’un manuel d’administration mis à jour (moins de 12 mois). | E32: Le manuel d'administration est-il à jour (moins de 12 mois) ? | F32: OUI | G32: Document de stratégie de migration des données | H32: Dépendance excessive au savoir-faire individuel | I32: Élevée | J32: Difficultés à auditer les systèmes en raison d’une journalisation insuffisante. | K32: Adopter des contrats de service (SLA) clairs avec des pénalités en cas de non-respect des engagements.
D33: Confirmer la couverture des procédures clés (ex : sauvegarde, restauration). | E33: Les procédures clés (sauvegarde, restauration) sont-elles couvertes ? | F33: OUI | G33: Procédures de sauvegarde et restauration | H33: Absence de capitalisation des connaissances | I33: Élevée | J33: Augmentation des coûts de conformité pour rattraper les lacunes identifiées. | K33: Utiliser des solutions de détection d'intrusion (IDS/IPS) pour surveiller les activités réseau anormales.
D34: Analyser des exemples de procédures détaillées (étapes, screenshots). | E34: Des procédures détaillées avec étapes et captures existent-elles ? | F34: NON | G34: Rapports de tests de restauration après sinistre | H34: Défaut de traçabilité des opérations sensibles | I34: Élevée | J34: Risque de corruption des données lors de migrations non contrôlées. | K34: Documenter les dépendances critiques entre systèmes pour anticiper les impacts des pannes.
D35: Identifier des preuves d’utilisation du manuel (logs de consultation). | E35: Des logs de consultation du manuel sont-ils disponibles ? | F35: OUI | G35: Clauses de contrat SLA avec les fournisseurs | H35: Contrôles métier inefficaces | I35: Élevée | J35: Incapacité à répondre aux audits externes faute de preuves tangibles. | K35: Mettre en place une politique de gestion des mots de passe exigeant une complexité et une rotation régulière.
D36: Contrôler des formations dédiées à l’équipe d’administration. | E36: L'équipe d'administration reçoit-elle des formations dédiées ? | F36: OUI | G36: Feuille de route technologique approuvée | H36: Non-respect des bonnes pratiques sectorielles | I36: Élevée | J36: Fragilisation de la gouvernance IT par une supervision inefficace. | K36: Auditer les configurations des bases de données pour limiter les risques d'exposition non autorisée.
C37: Vérifier l’existence de procédures formalisées | D37: Vérifier des procédures écrites pour au moins 5 processus critiques (ex : gestion des incidents). | E37: Cinq procédures écrites pour processus critiques existent-elles ? | F37: OUI | G37: Rapports d’évaluation de l’alignement stratégique | H37: Défaut de supervision des processus clés | I37: Moyenne | J37: Exposition à des attaques ciblées en l’absence de surveillance proactive. | K37: Formaliser une procédure de réponse aux incidents cyber incluant une communication structurée.
D38: Confirmer la signature des procédures par les responsables concernés. | E38: Les responsables ont-ils signé ces procédures ? | F38: OUI | G38: Spécifications fonctionnelles signées | H38: Erreurs de conception des workflows | I38: Moyenne | J38: Déséquilibre entre investissements IT et retours sur investissement attendus. | K38: Implémenter des contrôles d'accès hiérarchiques pour les environnements virtualisés et cloud.
D39: Analyser des preuves d’application (logs, rapports d’exécution). | E39: Des preuves d'application (logs, rapports) sont-elles vérifiables ? | F39: NON | G39: Fiches de poste détaillant les tâches des utilisateurs | H39: Interface utilisateur peu intuitive | I39: Moyenne | J39: Perte de données historiques critiques par archivage défaillant. | K39: Réaliser des évaluations de maturité des processus IT selon le référentiel COBIT.
D40: Identifier des indicateurs de performance liés aux procédures. | E40: Des indicateurs de performance liés aux procédures existent-ils ? | F40: OUI | G40: Rapports de performance des systèmes parallèles | H40: Absence de validation automatique des saisies | I40: Faible | J40: Complexification des processus métier due à des interfaces peu ergonomiques. | K40: Instaurer des mécanismes de contrôle qualité automatisés dans les pipelines DevOps.
D41: Contrôler des mises à jour récentes (moins de 6 mois). | E41: Les procédures ont-elles été mises à jour dans les 6 mois ? | F41: OUI | G41: Retours d’expérience des utilisateurs sur l’adéquation | H41: Défaut de maintenance évolutive | I41: Moyenne | J41: Délais prolongés dans les projets IT par mauvaise gestion des priorités. | K41: Mettre à jour régulièrement les politiques de sécurité pour refléter l'évolution des menaces.
C42: S’assurer de l’existence et de la mise à disposition du compte rendu mensuel au propriétaire | D42: Vérifier des comptes rendus mensuels datés des 6 derniers mois. | E42: Des comptes rendus mensuels existent-ils pour les 6 derniers mois ? | F42: OUI | G42: Rapport ROI (Return on Investment) avec calculs détaillés | H42: Incohérences dans les données de référence | I42: Élevée | J42: Non-respect des SLA entraînant des pénalités contractuelles. | K42: Créer un référentiel unique des configurations matérielles et logicielles pour éviter les divergences.
D43: Confirmer la signature des comptes rendus par le propriétaire de l’application. | E43: Le propriétaire de l'application a-t-il signé ces comptes rendus ? | F43: NON | G43: Contrats signés avec les fournisseurs | H43: Faiblesses dans les mécanismes de réconciliation | I43: Élevée | J43: Détérioration de la relation avec les fournisseurs par manque de suivi. | K43: Effectuer des audits de conformité des licences logicielles pour prévenir les risques juridiques.
D44: Analyser des indicateurs clés inclus (ex : disponibilité, incidents). | E44: Des indicateurs clés (disponibilité, incidents) sont-ils inclus ? | F44: OUI | G44: Calendrier de mise en œuvre du projet | H44: Manque d'intégrité des données | I44: Élevée | J44: Augmentation des conflits internes liés à des rôles mal définis. | K44: Déployer des solutions de protection contre les attaques DDoS pour les services exposés en ligne.
D45: Identifier des actions correctives planifiées dans les comptes rendus. | E45: Des actions correctives sont-elles planifiées dans les comptes rendus ? | F45: OUI | G45: Bilan post-projet avec conclusions | H45: Exposition des flux inter-applicatifs | I45: Élevée | J45: Incapacité à capitaliser sur les innovations technologiques par rigidité organisationnelle. | K45: Établir des procédures de destruction sécurisée des données en fin de cycle de vie.
D46: Contrôler des preuves de suivi des actions (rapports de clôture). | E46: Des preuves de suivi des actions (rapports de clôture) existent-elles ? | F46: OUI | G46: Rapports d’économie réalisées | H46: Défaut de chiffrement des transmissions | I46: Élevée | J46: Risque de non-conformité aux standards sectoriels nuisant à la crédibilité. | K46: Réaliser des tests de résistance des infrastructures face aux catastrophes naturelles.
C47: S’assurer de l’existence d'un guide d'utilisateur, manuel de procédure | D47: Vérifier l’existence d’un guide d’utilisateur et d’un manuel de procédures. | E47: Un guide utilisateur et un manuel de procédures sont-ils disponibles ? | F47: OUI | G47: Document de réingénierie des processus | H47: Contournement des contrôles d'accès | I47: Élevée | J47: Désalignement entre les besoins métier et les capacités techniques disponibles. | K47: Intégrer des contrôles de sécurité dans les phases de conception des applications (Security by Design).
D48: Confirmer la mise à jour des documents (moins de 12 mois). | E48: Ces documents ont-ils été mis à jour dans les 12 mois ? | F48: NON | G48: Rapport d’architecture technique de l’application | H48: Journalisation insuffisante des activités | I48: Élevée | J48: Fragmentation des systèmes réduisant l’efficacité globale de l’infrastructure. | K48: Mettre en place une veille technologique pour anticiper les risques liés aux nouvelles technologies.
D49: Analyser des exemples de procédures détaillées (étapes, screenshots). | E49: Des procédures détaillées avec captures d'écran existent-elles ? | F49: OUI | G49: Tableaux de bord avec indicateurs de performance (KPI) | H49: Détection tardive des incidents de sécurité | I49: Élevée | J49: Exposition à des erreurs de traitement par absence de validation automatisée. | K49: Auditer régulièrement les fournisseurs tiers pour s'assurer de leur conformité aux exigences de sécurité.
D50: Identifier des preuves de diffusion aux utilisateurs (accusés de réception). | E50: Des accusés de réception prouvent-ils la diffusion aux utilisateurs ? | F50: OUI | G50: Rapports de maturité technologique (ex : Gartner) | H50: Absence de revue des journaux d'audit | I50: Élevée | J50: Détérioration de la qualité des données utilisées pour la prise de décision. | K50: Documenter les procédures de gestion des identités temporaires et des comptes de service.
D51: Contrôler des formations dédiées à l’utilisation des documents. | E51: Des formations sur l'utilisation des documents sont-elles organisées ? | F51: OUI | G51: Procédures de gestion des accès privilégiés | H51: Failles dans les interfaces d'intégration | I51: Élevée | J51: Inadéquation des compétences des équipes face aux évolutions technologiques. | K51: Instaurer des revues post-incident pour améliorer continuellement les processus de sécurité.
B52: Application | C52: S'assurer que l'accès aux ressources de l'application (données et transactions) est restreint par un système de gestion d'accès | D52: Vérifier l’existence d’un système RBAC (Role-Based Access Control) actif. | E52: Un système RBAC est-il actif ? | F52: NON | G52: Logs d’actions administratives sur 90 jours | H52: Corruption des données lors des échanges | I52: Élevée | J52: Augmentation des temps d’indisponibilité des systèmes critiques. | K52: Adopter des outils de monitoring des performances applicatives pour détecter les goulets d'étranglement.
D53: Confirmer la présence de logs d’accès aux données sensibles sur 30 jours. | E53: Des logs d'accès aux données sensibles sur 30 jours existent-ils ? | F53: OUI | G53: Procédures de révocation des accès en cas de départ | H53: Absence de mécanismes de rejeu | I53: Élevée | J53: Perte d’opportunités commerciales par lenteur des processus informatiques. | K53: Mettre en œuvre une politique de gestion des clés de chiffrement incluant leur rotation et stockage sécurisé.
D54: Analyser la liste des utilisateurs avec droits administrateurs (moins de 5% du total). | E54: Moins de 5% des utilisateurs ont-ils des droits administrateur ? | F54: OUI | G54: Document de schéma-directeur du SI | H54: Perte de données critiques | I54: Élevée | J54: Dépassements budgétaires récurrents dans les projets IT non maîtrisés. | K54: Réaliser des audits de code statique et dynamique (SAST/DAST) pour les applications critiques.
D55: Tester le rejet d’accès hors profil via un compte test. | E55: Un compte test confirme-t-il le rejet d'accès hors profil ? | F55: OUI | G55: Procédures de contrôle qualité des données saisies | H55: Archivage non conforme | I55: Élevée | J55: Risque de perte de savoir-faire interne par dépendance à des solutions externes. | K55: Formaliser une stratégie de sortie pour les technologies obsolètes incluant leur remplacement progressif.
D56: Identifier une procédure de révocation des accès en cas de départ. | E56: Une procédure de révocation des accès en cas de départ existe-t-elle ? | F56: OUI | G56: Manuels d’exploitation mis à jour | H56: Restauration impossible après incident | I56: Élevée | J56: Difficultés à maintenir la cohérence des données entre systèmes hétérogènes. | K56: Instaurer des contrôles d'accès basés sur les rôles (RBAC) pour les environnements cloud.
C57: S’assurer qu’une procédure de gestion des profils utilisateurs existe | D57: Contrôler un workflow de création/suppression de profils (outil Jira ou équivalent). | E57: Un workflow de gestion des profils (Jira ou équivalent) est-il utilisé ? | F57: NON | G57: Procédures de gestion des correctifs urgents | H57: Pertes d'informations historiques | I57: Élevée | J57: Détérioration de l’expérience utilisateur impactant l’adoption des outils. | K57: Documenter les procédures de gestion des vulnérabilités logicielles et des correctifs d'urgence.
D58: Vérifier des traces de validation hiérarchique pour 5 profils aléatoires. | E58: La validation hiérarchique pour 5 profils aléatoires est-elle tracée ? | F58: OUI | G58: Rapports de revue de code pour les projets récents | H58: Défaut de purge sécurisée | I58: Moyenne | J58: Non-respect des exigences réglementaires en matière de transparence. | K58: Mettre en place des mécanismes de détection des fuites de données (DLP) pour les informations sensibles.
D59: Analyser l’existence d’un référentiel des profils types (PDF ou Excel). | E59: Un référentiel des profils types (PDF/Excel) est-il disponible ? | F59: OUI | G59: Procédures de déploiement en environnement de production | H59: Défaut de gestion des anomalies | I59: Élevée | J59: Augmentation des coûts de maintenance corrective faute de prévention. | K59: Auditer les configurations des conteneurs et des orchestrateurs pour limiter les risques d'exploitation.
D60: Confirmer la réalisation d’un audit semestriel des droits. | E60: Un audit semestriel des droits est-il réalisé ? | F60: OUI | G60: Contrats incluant des clauses « Escrow Agreement » | H60: Absence de processus de correction | I60: Élevée | J60: Incapacité à détecter les anomalies en temps réel par monitoring insuffisant. | K60: Implémenter une politique de gestion des risques spécifique aux projets d'intelligence artificielle.
D61: Identifier des sanctions en cas de non-respect (ex : mentions dans des PV). | E61: Des sanctions pour non-respect sont-elles prévues (mention dans PV) ? | F61: OUI | G61: Rapports de tests de montée en charge | H61: Défaut de traçabilité des corrections | I61: Élevée | J61: Dégradation de la résilience des systèmes face aux perturbations externes. | K61: Réaliser des tests d'intégration pour valider la cohérence des données entre systèmes hétérogènes.
C62: Vérifier que l’identification des utilisateurs est réalisée | D62: Tester l’impossibilité de se connecter sans identifiant unique. | E62: La connexion sans identifiant unique est-elle impossible ? | F62: NON | G62: Procédures de gestion des données archivées | H62: Réintégration non contrôlée des données | I62: Moyenne | J62: Exposition à des conflits d’intérêts dans la gestion des fournisseurs IT. | K62: Instaurer des contrôles d'accès biométriques pour les zones sensibles des datacenters.
D63: Vérifier l’absence de comptes génériques ("admin", "invité"). | E63: Les comptes génériques ("admin", "invité") sont-ils absents ? | F63: OUI | G63: Rapports de suivi des paiements des redevances | H63: Validation insuffisante des correctifs | I63: Moyenne | J63: Perte de contrôle sur les actifs informationnels par mauvaise gouvernance. | K63: Documenter les procédures de gestion des incidents liés aux fournisseurs de services cloud.
D64: Analyser l’existence d’un annuaire LDAP/Active Directory synchronisé. | E64: Un annuaire LDAP/Active Directory est-il synchronisé ? | F64: OUI | G64: Procédures de gestion des partenariats avec les éditeurs | H64: Défaut de supervision des mises à jour | I64: Élevée | J64: Risque de non-reconnaissance des dépenses IT par manque de traçabilité. | K64: Mettre en œuvre des solutions de segmentation réseau pour isoler les flux critiques.
D65: Confirmer la présence d’une procédure de réinitialisation sécurisée des identifiants. | E65: Une procédure sécurisée de réinitialisation des identifiants existe-t-elle ? | F65: OUI | G65: Documentation technique des interfaces d’intégration | H65: Exposition aux vulnérabilités non patchées | I65: Élevée | J65: Désorganisation des workflows métier par intégration défaillante des systèmes. | K65: Auditer régulièrement les configurations des équipements IoT pour prévenir les compromissions.
D66: Contrôler des logs de connexion avec adresses IP et horodatages. | E66: Les logs de connexion incluent-ils adresses IP et horodatages ? | F66: OUI | G66: Procédures de suppression sécurisée des données obsolètes | H66: Journalisation incomplète des modifications | I66: Élevée | J66: Augmentation des erreurs de saisie manuelle par absence de contrôles automatisés. | K66: Formaliser une politique de gestion des journaux d'activité conforme aux exigences réglementaires.
C67: Vérifier qu’un mot de passe est associé à l'identifiant | D67: Vérifier que chaque identifiant est associé à un mot de passe unique. | E67: Chaque identifiant a-t-il un mot de passe unique ? | F67: NON | G67: Rapports de performance de l’équipe de maintenance | H67: Défaut de détection des changements non autorisés | I67: Élevée | J67: Fragilisation de la position concurrentielle par retard technologique. | K67: Implémenter des contrôles de validation des entrées utilisateur pour prévenir les injections SQL.
D68: Confirmer l’application d’une politique de complexité des mots de passe (ex : 12 caractères, majuscules, chiffres). | E68: La politique impose-t-elle 12 caractères avec majuscules et chiffres ? | F68: OUI | G68: Procédures de recrutement et formation des équipes IT | H68: Absence de revue des configurations | I68: Élevée | J68: Incapacité à répondre aux attentes des utilisateurs finaux par rigidité des processus. | K68: Réaliser des audits de conformité aux normes sectorielles (PCI DSS, HIPAA, etc.).
D69: Analyser des logs de connexion pour détecter des mots de passe faibles. | E69: Les logs de connexion révèlent-ils des mots de passe faibles ? | F69: OUI | G69: Retours d’expérience du club utilisateurs | H69: Contrôles automatisés inefficaces | I69: Élevée | J69: Détérioration de la coordination entre équipes IT et métier par communication inefficace. | K69: Instaurer des mécanismes de surveillance des activités des robots logiciels (RPA).
D70: Tester la réinitialisation forcée après 90 jours. | E70: La réinitialisation forcée a-t-elle lieu après 90 jours ? | F70: OUI | G70: Procédures de gestion des mises à jour logicielles | H70: Défaut d'alerte sur les anomalies | I70: Élevée | J70: Exposition à des sanctions pour non-respect des clauses contractuelles avec les éditeurs. | K70: Documenter les procédures de gestion des certificats SSL/TLS pour éviter leur expiration.
D71: Identifier des alertes en cas de tentative de réutilisation d’un ancien mot de passe. | E71: Des alertes signalent-elles la réutilisation d'anciens mots de passe ? | F71: OUI | G71: Rapports d’évaluation de la conformité RGPD/ISO | H71: Absence de suivi des indicateurs clés | I71: Élevée | J71: Perte de données opérationnelles par corruption ou suppression accidentelle. | K71: Mettre en place des contrôles d'accès contextuels pour les applications métiers sensibles.
C72: S’assurer que les tentatives de connexions infructueuses à l'application sont suivies | D72: Vérifier des logs de tentatives infructueuses sur 30 jours. | E72: Les tentatives infructueuses sur 30 jours sont-elles tracées ? | F72: NON | G72: Procédures de gestion des accès aux bibliothèques logicielles | H72: Reporting incomplet ou erroné | I72: Élevée | J72: Augmentation des vulnérabilités réseau par configuration inadéquate. | K72: Auditer les configurations des systèmes de virtualisation pour garantir leur isolation.
D73: Confirmer la présence d’un système de verrouillage après 5 échecs. | E73: Le système se verrouille-t-il après 5 échecs ? | F73: OUI | G73: Logs de consultation de la documentation par les utilisateurs | H73: Décisions basées sur des informations obsolètes | I73: Élevée | J73: Incapacité à anticiper les besoins futurs par planification stratégique absente. | K73: Implémenter des contrôles de sécurité physique pour les supports de sauvegarde hors site.
D74: Analyser des alertes automatiques envoyées à l’administrateur. | E74: Des alertes automatiques sont-elles envoyées à l'administrateur ? | F74: OUI | G74: Procédures de validation hiérarchique des profils utilisateurs | H74: Distribution non sécurisée des états | I74: Élevée | J74: Dégradation de la qualité des services supportés par des outils obsolètes. | K74: Réaliser des tests de résistance aux attaques zero-day via des simulations réalistes.
D75: Tester la réinitialisation manuelle par l’administrateur. | E75: La réinitialisation manuelle par l'admin est-elle fonctionnelle ? | F75: OUI | G75: Rapports d’audit semestriel des droits d’accès | H75: Accès non contrôlé aux informations sensibles | I75: Élevée | J75: Risque de non-atteinte des objectifs de transformation numérique. | K75: Instaurer une politique de gestion des données archivées incluant leur classification et chiffrement.
D76: Identifier des procédures de suivi des tentatives suspectes. | E76: Une procédure de suivi des tentatives suspectes existe-t-elle ? | F76: OUI | G76: Procédures de gestion des alertes de sécurité automatiques | H76: Validation manquante des outputs | I76: Élevée | J76: Exposition à des litiges liés à la propriété intellectuelle des développements logiciels. | K76: Documenter les procédures de réponse aux fuites de données personnelles conformes au RGPD.
C77: S’assurer que l'accès aux données et aux transactions de l’application est géré | D77: Vérifier des logs d’accès aux transactions sensibles sur 30 jours. | E77: Les logs d'accès aux transactions sensibles sur 30 jours existent-ils ? | F77: NON | G77: Documents de référence des règles de gestion des données | H77: Erreurs de traitement non détectées | I77: Élevée | J77: Perte de flexibilité opérationnelle par architecture technique rigide. | K77: Mettre en œuvre des contrôles d'intégrité des métadonnées associées aux données critiques.
D78: Confirmer la présence d’un système de chiffrement des données en transit. | E78: Les données en transit sont-elles chiffrées ? | F78: OUI | G78: Procédures de contrôle qualité des corrections de données | H78: Incohérences dans les codifications | I78: Élevée | J78: Détérioration de la collaboration interne par outils collaboratifs inadaptés. | K78: Auditer les configurations des systèmes de gestion des identités (IAM) pour limiter les erreurs.
D79: Analyser des procédures de validation des accès par un supérieur hiérarchique. | E79: Un supérieur hiérarchique valide-t-il les accès sensibles ? | F79: OUI | G79: Rapports de tests d’interopérabilité avec les systèmes existants | H79: Défaut d'application des règles métier | I79: Élevée | J79: Augmentation des délais de livraison des projets IT par mauvaise gestion des ressources. | K79: Implémenter des mécanismes de détection des comportements anormaux des utilisateurs.
D80: Tester le rejet d’accès hors profil via un compte test. | E80: Un compte test confirme-t-il le rejet d'accès hors profil ? | F80: OUI | G80: Procédures de gestion des environnements (dev/test/prod) | H80: Défaut de cohérence inter-modules | I80: Élevée | J80: Incapacité à garantir l’authenticité des transactions électroniques. | K80: Réaliser des revues architecturales pour s'assurer de la résilience des infrastructures hybrides.
D81: Identifier des alertes en cas d’accès hors heures ouvrables. | E81: Des alertes existent-elles pour les accès hors heures ouvrables ? | F81: OUI | G81: Rapports de tests de modularité de l’application | H81: Interfaces non sécurisées | I81: Élevée | J81: Fragilisation de la chaîne d’approvisionnement IT par dépendance à un seul fournisseur. | K81: Instaurer des contrôles d'accès temporaires avec expiration automatique pour les prestataires.
C82: Vérifier l’existence de pistes d’audit sur le système d’administration de l’application | D82: Vérifier des logs d’audit des actions administratives sur 90 jours. | E82: Les logs d'actions administratives sur 90 jours sont-ils disponibles ? | F82: NON | G82: Procédures de gestion des versions logicielles | H82: Défaut de validation des développements | I82: Élevée | J82: Détérioration de l’image de marque suite à des incidents de sécurité médiatisés. | K82: Documenter les procédures de gestion des risques liés à l'utilisation de l'Internet des objets (IoT).
D83: Confirmer la présence d’un système de journalisation centralisé. | E83: Un système de journalisation centralisé est-il en place ? | F83: OUI | G83: Rapports de suivi des demandes de maintenance utilisateur | H83: Code non conforme aux standards | I83: Élevée | J83: Non-respect des engagements environnementaux liés à la gestion des infrastructures IT. | K83: Mettre en place des solutions de chiffrement homomorphique pour les données sensibles en traitement.
D84: Analyser des alertes automatiques pour les actions critiques (ex : suppression de données). | E84: Des alertes automatiques pour actions critiques existent-elles ? | F84: OUI | G84: Procédures de gestion des clés SSH/API | H84: Absence de revue par les pairs | I84: Moyenne | J84: Augmentation des coûts de licence par utilisation non optimisée des logiciels. | K84: Auditer les configurations des passerelles API pour prévenir les exploitations malveillantes.
D85: Tester la traçabilité des actions via un compte administrateur. | E85: La traçabilité des actions via un compte admin est-elle vérifiable ? | F85: OUI | G85: Rapports de performance des travaux batch | H85: Déploiement non contrôlé en production | I85: Moyenne | J85: Incapacité à maintenir la cohérence des données lors de fusions ou acquisitions. | K85: Implémenter des contrôles de sécurité dans les pipelines CI/CD pour les déploiements automatisés.
D86: Identifier des procédures de revue trimestrielle des logs. | E86: Une revue trimestrielle des logs est-elle prévue ? | F86: OUI | G86: Procédures de gestion des données rejetées | H86: Accès non autorisé aux environnements critiques | I86: Moyenne | J86: Dégradation de l’agilité organisationnelle par lenteur des processus IT. | K86: Réaliser des tests de charge pour valider la scalabilité des applications critiques.
C87: Vérifier que tous les documents servant de base à la saisie sont pris en compte | D87: Vérifier des exemples de documents sources (ex : factures, bons de commande). | E87: Des exemples de documents sources (factures, bons de commande) existent-ils ? | F87: NON | G87: Rapports de tests de compatibilité ascendante/descendante | H87: Défaut de séparation des environnements | I87: Moyenne | J87: Exposition à des erreurs de configuration entraînant des pannes critiques. | K87: Instaurer une politique de gestion des secrets applicatifs (mots de passe, clés API).
D88: Confirmer la présence d’un workflow de validation des documents. | E88: Un workflow de validation des documents est-il établi ? | F88: OUI | G88: Procédures de gestion des formations utilisateurs | H88: Gestion hasardeuse des accès privilégiés | I88: Moyenne | J88: Perte de compétitivité sur le marché par innovation technologique insuffisante. | K88: Documenter les procédures de gestion des incidents liés aux systèmes de paiement électronique.
D89: Analyser des logs de saisie pour corréler avec les documents sources. | E89: Les logs de saisie correspondent-ils aux documents sources ? | F89: OUI | G89: Rapports de suivi des indicateurs de satisfaction utilisateur | H89: Compromission des clés d'accès | I89: Moyenne | J89: Détérioration de la satisfaction client due à des services IT peu fiables. | K89: Mettre en œuvre des contrôles d'accès physiques et logiques pour les salles de contrôle.
D90: Tester la reprise des données après une erreur de saisie. | E90: La reprise des données après erreur de saisie est-elle possible ? | F90: OUI | G90: Procédures de gestion des risques résiduels | H90: Défaut de rotation des identifiants | I90: Moyenne | J90: Augmentation des risques liés à l’externalisation non supervisée. | K90: Auditer les configurations des systèmes SCADA/OT pour limiter les risques cyberindustriels.
D91: Identifier des procédures de contrôle qualité des données saisies. | E91: Des procédures de contrôle qualité des données saisies existent-elles ? | F91: OUI | G91: Rapports de revue trimestrielle des logs d’activité | H91: Compétences insuffisantes des équipes | I91: Moyenne | J91: Incapacité à aligner les investissements IT sur les priorités métier. | K91: Implémenter des mécanismes de protection contre les attaques par ingénierie sociale.
C92: S’assurer que les facilités de saisie, l’ergonomie de la saisie, les messages écrans et les contrôles sont mis en œuvre | D92: Vérifier des captures d’écran des interfaces de saisie. | E92: Des captures d'écran des interfaces de saisie sont-elles disponibles ? | F92: NON | G92: Procédures de gestion des accès hors heures ouvrables | H92: Défaut de plan de continuité d'activité | I92: Moyenne | J92: Fragilisation de la conformité aux normes internationales par pratiques obsolètes. | K92: Réaliser des revues de conformité des contrats avec les fournisseurs de services managés.
D93: Confirmer la présence de messages d’erreur clairs et explicites. | E93: Les messages d'erreur sont-ils clairs et explicites ? | F93: OUI | G93: Rapports de tests de stabilité des technologies utilisées | H93: Procédures de secours non opérationnelles | I93: Moyenne | J93: Détérioration de la capacité à auditer les processus internes efficacement. | K93: Instaurer des contrôles de sécurité pour les environnements DevOps et les outils low-code.
D94: Analyser des tests utilisateurs pour évaluer l’ergonomie. | E94: Des tests utilisateurs évaluent-ils l'ergonomie ? | F94: OUI | G94: Procédures de gestion des budgets d’extension d’infrastructure | H94: Temps de restauration excessif | I94: Moyenne | J94: Exposition à des interruptions d’activité par absence de redondance des systèmes. | K94: Documenter les procédures de gestion des risques liés à l'adoption de la blockchain.
D95: Tester la validation automatique des champs obligatoires. | E95: La validation automatique des champs obligatoires fonctionne-t-elle ? | F95: OUI | G95: Rapports de tests de réversibilité en cas d’échec de déploiement | H95: Perte de disponibilité du système | I95: Moyenne | J95: Perte de données stratégiques par absence de politiques de sauvegarde robustes. | K95: Mettre en place des mécanismes de validation des données en temps réel pour les transactions.
D96: Identifier des procédures de mise à jour des interfaces. | E96: Des procédures de mise à jour des interfaces existent-elles ? | F96: OUI | G96: Procédures de gestion des alertes de tentative d’accès non autorisé | H96: Défaut de tests de reprise | I96: Faible | J96: Augmentation des conflits entre équipes par manque de clarté des responsabilités. | K96: Auditer les configurations des systèmes de gestion de contenu (CMS) pour prévenir les vulnérabilités.
C97: S’assurer que les contrôles de validation des « brouillards » de saisie pour validation par réconciliation existent | D97: Vérifier des exemples de brouillards de saisie validés. | E97: Des brouillards de saisie validés sont-ils disponibles ? | F97: NON | G97: Rapports de suivi des indicateurs de productivité des processus | H97: Inadéquation des sauvegardes | I97: Élevée | J97: Incapacité à répondre aux audits réglementaires faute de documentation adéquate. | K97: Implémenter des contrôles d'accès basés sur l'attestation pour les appareils connectés.
D98: Confirmer la présence d’un workflow de réconciliation. | E98: Un workflow de réconciliation est-il en place ? | F98: OUI | G98: Procédures de gestion des mises à jour des spécifications fonctionnelles | H98: Exposition aux sinistres majeurs | I98: Élevée | J98: Dégradation de la qualité des décisions managériales par données incomplètes. | K98: Réaliser des tests de résilience des infrastructures face aux pannes matérielles.
D99: Analyser des logs de validation pour corréler avec les brouillards. | E99: Les logs de validation correspondent-ils aux brouillards ? | F99: OUI | G99: Rapports de tests de performance des développements spécifiques | H99: Non-respect des SLA | I99: Élevée | J99: Risque de non-conformité aux exigences sectorielles spécifiques. | K99: Instaurer une politique de gestion des correctifs critiques avec des délais contraignants.
D100: Tester la détection d’erreurs de saisie via des contrôles automatiques. | E100: Les contrôles automatiques détectent-ils les erreurs de saisie ? | F100: OUI | G100: Procédures de gestion des partenariats avec les clubs utilisateurs | H100: Dégradation de la qualité de service | I100: Élevée | J100: Détérioration de la collaboration avec les partenaires externes par systèmes incompatibles. | K100: Documenter les procédures de gestion des risques liés aux technologies émergentes (IA, 5G).
...

Sheet APPLICATION_EN_SERVICE
A2: points de contrôles | B2: objectifs de contrôle | C2: critères d'évaluation | D2: questions d'évaluation | E2: Réponses | F2: Documents requis | G2: Risques | H2: Criticités | I2: conséquences | J2: Recommendations
A3: Organisation | B3: S’assurer de l’existence d'un comité informatique | C3: Vérifier l’existence d’un organigramme officiel du comité signé par la direction. | D3: L'organigramme du comité est-il signé par la direction ? | E3: OUI | F3: Organigramme de l’entité | G3: Absence de gouvernance clairement définie | H3: Élevée | I3: Non-conformité aux réglementations en vigueur entraînant des sanctions légales. | J3: Élaborer un cadre de gouvernance aligné sur COBIT ou ISO 27001 en formalisant les rôles et responsabilités.
C4: Confirmer la présence d’au moins 3 procès-verbaux de réunion datés des 6 derniers mois. | D4: Trois procès-verbaux de réunion existent-ils pour les 6 derniers mois ? | E4: NON | F4: Organigramme fonctionnel de la DSI | G4: Documentation insuffisante des décisions stratégiques | H4: Moyenne | I4: Détérioration de la confiance des parties prenantes due à l'absence de traçabilité des décisions. | J4: Documenter et diffuser les politiques de sécurité et les procédures internes pour garantir leur accessibilité.
C5: Analyser la composition du comité (CV/certifications des membres). | D5: Les CV et certifications des membres du comité sont-ils disponibles ? | E5: OUI | F5: Procès-verbaux des réunions du comité | G5: Incompétence des membres du comité de pilotage | H5: Élevée | I5: Augmentation des erreurs opérationnelles par manque de directives claires. | J5: Mettre en place une formation continue sur les enjeux de sécurité et la conformité réglementaire pour les employés.
C6: Identifier un mandat écrit précisant les missions et la fréquence des réunions. | D6: Un mandat écrit définit-il les missions et la fréquence des réunions ? | E6: OUI | F6: Fiches de postes de la DSI | G6: Définition floue des responsabilités du comité | H6: Élevée | I6: Vulnérabilité accrue aux cyberattaques en raison de politiques obsolètes. | J6: Implémenter des contrôles d'accès stricts basés sur le principe du moindre privilège et revoir périodiquement les habilitations.
C7: Contrôler la diffusion des décisions du comité via des emails ou documents internes. | D7: Les décisions du comité sont-elles diffusées par email ou documents internes ? | E7: NON | F7: Politique des Applications approuvée par la direction | G7: Non-diffusion des orientations stratégiques aux équipes | H7: Élevée | I7: Inefficacité des contrôles internes causant des pertes financières. | J7: Concevoir et tester régulièrement un plan de continuité d'activité (PCA) et un plan de reprise d'activité (PRA).
B8: S’assurer de l’existence d'une politique relative aux applications | C8: Vérifier la présence d’un document intitulé "Politique des Applications" approuvé par la direction. | D8: La "Politique des Applications" est-elle approuvée par la direction ? | E8: OUI | F8: Accusés de réception des employés pour la politique | G8: Politique de sécurité non formalisée | H8: Élevée | I8: Exposition à des litiges juridiques faute de documentation appropriée. | J8: Instaurer une matrice des risques mise à jour annuellement et intégrée aux processus décisionnels.
C9: Confirmer la date de la dernière mise à jour (moins de 12 mois). | D9: La dernière mise à jour date-t-elle de moins de 12 mois ? | E9: NON | F9: Plan de formation annuel lié à la politique | G9: Non-conformité réglementaire | H9: Moyenne | I9: Dysfonctionnements dans la gestion des accès menant à des fuites de données sensibles. | J9: Automatiser les contrôles de validation des données critiques pour réduire les erreurs manuelles.
C10: Analyser les mentions de conformité RGPD/ISO dans le document. | D10: Le document mentionne-t-il la conformité RGPD/ISO ? | E10: OUI | F10: Matrice des autorisations/droits d’accès | G10: Manque de sensibilisation des employés aux politiques | H10: Moyenne | I10: Interruptions prolongées des activités en cas de sinistre non anticipé. | J10: Déployer des outils de surveillance en temps réel pour détecter les anomalies et les activités suspectes.
C11: Vérifier la diffusion de la politique aux employés (accusés de réception signés). | D11: Les employés ont-ils signé des accusés de réception pour la politique ? | E11: OUI | F11: Liste des 100 derniers incidents du domaine d’audit | G11: Absence de formation continue sur les enjeux de sécurité | H11: Élevée | I11: Dégradation de la performance des systèmes due à une maintenance inadéquate. | J11: Réaliser des audits réguliers des configurations des systèmes et des droits d'accès privilégiés.
C12: Identifier un plan de formation annuel lié à cette politique. | D12: Un plan de formation annuel lié à cette politique existe-t-il ? | E12: NON | F12: Rapport d’analyse des risques récent (moins de 12 mois) | G12: Définition imprécise des rôles utilisateurs | H12: Élevée | I12: Non-respect des engagements contractuels envers les clients ou partenaires. | J12: Mettre en œuvre des mécanismes de chiffrement des données en transit et au repos conformes aux normes ISO 27001.
B13: S’assurer que les rôle et responsabilités des utilisateurs sont bien définis | C13: Contrôler l’existence de fiches de poste pour chaque profil utilisateur. | D13: Des fiches de poste sont-elles disponibles pour chaque profil utilisateur ? | E13: OUI | F13: Document de classification des données (public, interne, confidentiel) | G13: Violation des engagements contractuels | H13: Élevée | I13: Augmentation des coûts opérationnels liés à des processus inefficients. | J13: Séparer les environnements de développement, de test et de production pour limiter les risques de corruption.
C14: Vérifier la signature des utilisateurs sur des chartes d’utilisation. | D14: Les utilisateurs ont-ils signé des chartes d'utilisation ? | E14: OUI | F14: Manuel d’administration des applications | G14: Droits d'accès obsolètes ou inadaptées | H14: Élevée | I14: Perte de données critiques par absence de sauvegardes fiables. | J14: Établir des procédures de gestion des incidents incluant une analyse post-mortem et des plans d'action correctifs.
C15: Confirmer la mise à jour des habilitations dans un tableau de gestion des accès. | D15: Le tableau de gestion des accès est-il à jour ? | E15: NON | F15: Logs d’accès aux données sensibles sur 30 jours | G15: Détournement de privilèges | H15: Élevée | I15: Retards dans les prises de décision faute d’informations actualisées. | J15: Valider l'exhaustivité et l'intégrité des sauvegardes via des tests de restauration périodiques.
C16: Analyser des logs d’accès pour corréler avec les rôles déclarés. | D16: Les logs d'accès correspondent-ils aux rôles déclarés ? | E16: OUI | F16: Procédures écrites pour les processus critiques | G16: Absence de revue périodique des habilitations | H16: Élevée | I16: Compromission de l’intégrité des données financières ou métiers. | J16: Créer un comité de pilotage IT pour superviser l'alignement stratégique des projets avec les objectifs métiers.
C17: Identifier des procédures de révision trimestrielle des droits. | D17: Une procédure de révision trimestrielle des droits est-elle en place ? | E17: OUI | F17: Comptes rendus mensuels de l’application | G17: Fraude interne via l'exploitation de droits excessifs | H17: Élevée | I17: Risque accru de fraude interne en l’absence de séparation des tâches. | J17: Utiliser des outils de gestion des identités et des accès (IAM) pour centraliser et auditer les permissions.
B18: S’assurer qu’une analyse des risques a été réalisée | C18: Vérifier un rapport d’analyse des risques daté de moins de 12 mois. | D18: Un rapport d'analyse des risques de moins de 12 mois existe-t-il ? | E18: OUI | F18: Guide utilisateur et manuel de procédures | G18: Évaluation des risques non actualisée | H18: Élevée | I18: Détérioration de la qualité des services IT impactant la satisfaction client. | J18: Réaliser des tests de pénétration et des audits de code pour identifier les vulnérabilités applicatives.
C19: Confirmer l’utilisation d’une méthodologie reconnue (ex : EBIOS, OCTAVE). | D19: La méthodologie utilisée est-elle reconnue (EBIOS, OCTAVE) ? | E19: NON | F19: Matrice des tâches et fonctions incompatibles | G19: Utilisation de méthodologies obsolètes | H19: Élevée | I19: Exposition à des amendes réglementaires pour non-conformité RGPD. | J19: Documenter les flux de données et les interfaces entre systèmes pour garantir la traçabilité des échanges.
C20: Analyser la liste des risques identifiés (au moins 10 risques critiques). | D20: Au moins 10 risques critiques sont-ils identifiés ? | E20: OUI | F20: Contrat de maintenance ou d’assistance | G20: Sous-estimation des menaces critiques | H20: Élevée | I20: Interruptions fréquentes des services en production par manque de redondance. | J20: Adopter une politique de gestion des correctifs avec des délais stricts pour les mises à jour critiques.
C21: Identifier un plan d’action avec des responsables et des échéances. | D21: Un plan d'action avec responsables et échéances est-il établi ? | E21: OUI | F21: Plan de continuité des activités (PCA) | G21: Absence de planification corrective | H21: Élevée | I21: Difficultés à assurer la continuité des activités lors de crises majeures. | J21: Instaurer des contrôles d'intégrité des données lors des migrations ou des transferts inter-systèmes.
C22: Contrôler des preuves de mise en œuvre des actions (rapports de suivi). | D22: Des preuves de mise en œuvre des actions sont-elles disponibles ? | E22: NON | F22: Plan de reprise d’activité (PRA) | G22: Contrôles inefficaces face aux risques identifiés | H22: Élevée | I22: Dépendance excessive vis-à-vis de prestataires externes non supervisés. | J22: Mettre en place une journalisation centralisée et une analyse proactive des logs pour détecter les menaces.
B23: S’assurer que le prolongement de l'analyse de risque et de son expansion ont été réalisés | C23: Vérifier des mises à jour de l’analyse des risques (au moins 2 révisions annuelles). | D23: L'analyse des risques a-t-elle été mise à jour deux fois dans l'année ? | E23: OUI | F23: Rapports de traitements des incidents | G23: Ignorance des nouvelles vulnérabilités | H23: Élevée | I23: Altération de la réputation de l’organisation suite à des incidents récurrents. | J23: Élaborer une charte de sécurité informatique incluant des clauses contractuelles avec les fournisseurs externes.
C24: Confirmer l’intégration des nouveaux risques (ex : cybermenaces, RGPD). | D24: Les nouveaux risques (cybermenaces, RGPD) sont-ils intégrés ? | E24: OUI | F24: Inventaire des licences | G24: Défaut de reporting aux instances décisionnelles | H24: Élevée | I24: Inefficacité des plans de reprise après sinistre prolongeant les temps d’arrêt. | J24: Concevoir des tableaux de bord de performance alignés sur les KPI métiers pour mesurer l'efficacité des SI.
C25: Analyser des indicateurs de suivi des risques (tableaux de bord). | D25: Des indicateurs de suivi des risques existent-ils ? | E25: OUI | F25: Bilan de qualité logiciel | G25: Culture du risque insuffisante dans l'organisation | H25: Élevée | I25: Augmentation des vulnérabilités logicielles par absence de mises à jour. | J25: Sensibiliser les utilisateurs aux risques de phishing et d'ingénierie sociale via des simulations régulières.
C26: Identifier des procédures de reporting aux instances dirigeantes. | D26: Des procédures de reporting aux instances dirigeantes sont-elles définies ? | E26: NON | F26: Bilan de satisfaction des utilisateurs | G26: Classification inappropriée des données sensibles | H26: Moyenne | I26: Désorganisation des équipes IT faute de procédures standardisées. | J26: Auditer régulièrement les configurations des pare-feux et des équipements réseau pour prévenir les attaques.
C27: Contrôler des preuves de sensibilisation des équipes aux risques majeurs. | D27: Les équipes sont-elles sensibilisées aux risques majeurs ? | E27: OUI | F27: Schéma d’interaction des applications métiers | G27: Exposition de données critiques | H27: Moyenne | I27: Non-atteinte des objectifs stratégiques en raison d’un mauvais alignement IT-métier. | J27: Intégrer des contrôles de conformité RGPD dans les processus de traitement des données personnelles.
B28: S’assurer que l’analyse et évaluation du niveau de sensibilité a été réalisée | C28: Vérifier un document classifiant les données par niveau de sensibilité (public, interne, confidentiel). | D28: Un document classe-t-il les données (public, interne, confidentiel) ? | E28: NON | F28: Diagramme de flux de données des applications | G28: Surveillance inadéquate des accès privilégiés | H28: Élevée | I28: Perte de compétitivité due à des technologies obsolètes ou sous-utilisées. | J28: Définir une stratégie de gestion des actifs numériques incluant leur classification et leur cycle de vie.
C29: Confirmer la mise à jour de la classification (moins de 6 mois). | D29: La classification a-t-elle été mise à jour dans les 6 mois ? | E29: OUI | F29: Procédures de gestion des changements | G29: Protection insuffisante des actifs informationnels | H29: Élevée | I29: Erreurs humaines accrues par manque de formation ou de documentation. | J29: Mettre en œuvre des contrôles d'accès physique aux salles serveurs et aux centres de données.
C30: Analyser des logs d’accès aux données sensibles sur 30 jours. | D30: Les logs d'accès aux données sensibles sur 30 jours sont-ils analysables ? | E30: OUI | F30: Logs de connexion avec adresses IP et horodatages | G30: Manque de formation sur la manipulation des données | H30: Faible | I30: Détection tardive des anomalies opérationnelles réduisant la réactivité. | J30: Réaliser des audits de sécurité des APIs pour prévenir les exploitations malveillantes.
C31: Identifier des procédures de protection spécifiques pour les données critiques. | D31: Des procédures spécifiques protègent-elles les données critiques ? | E31: NON | F31: Politique de sécurité des mots de passe | G31: Documentation technique obsolète | H31: Élevée | I31: Fuite d’informations confidentielles par des contrôles d’accès laxistes. | J31: Standardiser les procédures de gestion des changements avec validation technique et métier préalable.
C32: Contrôler des preuves de formation des utilisateurs sur la classification. | D32: Les utilisateurs sont-ils formés sur la classification des données ? | E32: OUI | F32: Procédures de gestion des identifiants et mots de passe | G32: Procédures de secours non testées | H32: Élevée | I32: Dégradation de la productivité des utilisateurs face à des outils inadaptés. | J32: Instaurer des revues indépendantes des architectures techniques pour garantir leur résilience.
B33: Vérifier l’existence d’un manuel d'administration de l'application | C33: Vérifier l’existence d’un manuel d’administration mis à jour (moins de 12 mois). | D33: Le manuel d'administration est-il à jour (moins de 12 mois) ? | E33: OUI | F33: Document de stratégie de migration des données | G33: Dépendance excessive au savoir-faire individuel | H33: Élevée | I33: Difficultés à auditer les systèmes en raison d’une journalisation insuffisante. | J33: Adopter des contrats de service (SLA) clairs avec des pénalités en cas de non-respect des engagements.
C34: Confirmer la couverture des procédures clés (ex : sauvegarde, restauration). | D34: Les procédures clés (sauvegarde, restauration) sont-elles couvertes ? | E34: OUI | F34: Procédures de sauvegarde et restauration | G34: Absence de capitalisation des connaissances | H34: Élevée | I34: Augmentation des coûts de conformité pour rattraper les lacunes identifiées. | J34: Utiliser des solutions de détection d'intrusion (IDS/IPS) pour surveiller les activités réseau anormales.
C35: Analyser des exemples de procédures détaillées (étapes, screenshots). | D35: Des procédures détaillées avec étapes et captures existent-elles ? | E35: NON | F35: Rapports de tests de restauration après sinistre | G35: Défaut de traçabilité des opérations sensibles | H35: Élevée | I35: Risque de corruption des données lors de migrations non contrôlées. | J35: Documenter les dépendances critiques entre systèmes pour anticiper les impacts des pannes.
C36: Identifier des preuves d’utilisation du manuel (logs de consultation). | D36: Des logs de consultation du manuel sont-ils disponibles ? | E36: OUI | F36: Clauses de contrat SLA avec les fournisseurs | G36: Contrôles métier inefficaces | H36: Élevée | I36: Incapacité à répondre aux audits externes faute de preuves tangibles. | J36: Mettre en place une politique de gestion des mots de passe exigeant une complexité et une rotation régulière.
C37: Contrôler des formations dédiées à l’équipe d’administration. | D37: L'équipe d'administration reçoit-elle des formations dédiées ? | E37: OUI | F37: Feuille de route technologique approuvée | G37: Non-respect des bonnes pratiques sectorielles | H37: Élevée | I37: Fragilisation de la gouvernance IT par une supervision inefficace. | J37: Auditer les configurations des bases de données pour limiter les risques d'exposition non autorisée.
B38: Vérifier l’existence de procédures formalisées | C38: Vérifier des procédures écrites pour au moins 5 processus critiques (ex : gestion des incidents). | D38: Cinq procédures écrites pour processus critiques existent-elles ? | E38: OUI | F38: Rapports d’évaluation de l’alignement stratégique | G38: Défaut de supervision des processus clés | H38: Moyenne | I38: Exposition à des attaques ciblées en l’absence de surveillance proactive. | J38: Formaliser une procédure de réponse aux incidents cyber incluant une communication structurée.
C39: Confirmer la signature des procédures par les responsables concernés. | D39: Les responsables ont-ils signé ces procédures ? | E39: OUI | F39: Spécifications fonctionnelles signées | G39: Erreurs de conception des workflows | H39: Moyenne | I39: Déséquilibre entre investissements IT et retours sur investissement attendus. | J39: Implémenter des contrôles d'accès hiérarchiques pour les environnements virtualisés et cloud.
C40: Analyser des preuves d’application (logs, rapports d’exécution). | D40: Des preuves d'application (logs, rapports) sont-elles vérifiables ? | E40: NON | F40: Fiches de poste détaillant les tâches des utilisateurs | G40: Interface utilisateur peu intuitive | H40: Moyenne | I40: Perte de données historiques critiques par archivage défaillant. | J40: Réaliser des évaluations de maturité des processus IT selon le référentiel COBIT.
C41: Identifier des indicateurs de performance liés aux procédures. | D41: Des indicateurs de performance liés aux procédures existent-ils ? | E41: OUI | F41: Rapports de performance des systèmes parallèles | G41: Absence de validation automatique des saisies | H41: Faible | I41: Complexification des processus métier due à des interfaces peu ergonomiques. | J41: Instaurer des mécanismes de contrôle qualité automatisés dans les pipelines DevOps.
C42: Contrôler des mises à jour récentes (moins de 6 mois). | D42: Les procédures ont-elles été mises à jour dans les 6 mois ? | E42: OUI | F42: Retours d’expérience des utilisateurs sur l’adéquation | G42: Défaut de maintenance évolutive | H42: Moyenne | I42: Délais prolongés dans les projets IT par mauvaise gestion des priorités. | J42: Mettre à jour régulièrement les politiques de sécurité pour refléter l'évolution des menaces.
B43: S’assurer de l’existence et de la mise à disposition du compte rendu mensuel au propriétaire | C43: Vérifier des comptes rendus mensuels datés des 6 derniers mois. | D43: Des comptes rendus mensuels existent-ils pour les 6 derniers mois ? | E43: OUI | F43: Rapport ROI (Return on Investment) avec calculs détaillés | G43: Incohérences dans les données de référence | H43: Élevée | I43: Non-respect des SLA entraînant des pénalités contractuelles. | J43: Créer un référentiel unique des configurations matérielles et logicielles pour éviter les divergences.
C44: Confirmer la signature des comptes rendus par le propriétaire de l’application. | D44: Le propriétaire de l'application a-t-il signé ces comptes rendus ? | E44: NON | F44: Contrats signés avec les fournisseurs | G44: Faiblesses dans les mécanismes de réconciliation | H44: Élevée | I44: Détérioration de la relation avec les fournisseurs par manque de suivi. | J44: Effectuer des audits de conformité des licences logicielles pour prévenir les risques juridiques.
C45: Analyser des indicateurs clés inclus (ex : disponibilité, incidents). | D45: Des indicateurs clés (disponibilité, incidents) sont-ils inclus ? | E45: OUI | F45: Calendrier de mise en œuvre du projet | G45: Manque d'intégrité des données | H45: Élevée | I45: Augmentation des conflits internes liés à des rôles mal définis. | J45: Déployer des solutions de protection contre les attaques DDoS pour les services exposés en ligne.
C46: Identifier des actions correctives planifiées dans les comptes rendus. | D46: Des actions correctives sont-elles planifiées dans les comptes rendus ? | E46: OUI | F46: Bilan post-projet avec conclusions | G46: Exposition des flux inter-applicatifs | H46: Élevée | I46: Incapacité à capitaliser sur les innovations technologiques par rigidité organisationnelle. | J46: Établir des procédures de destruction sécurisée des données en fin de cycle de vie.
C47: Contrôler des preuves de suivi des actions (rapports de clôture). | D47: Des preuves de suivi des actions (rapports de clôture) existent-elles ? | E47: OUI | F47: Rapports d’économie réalisées | G47: Défaut de chiffrement des transmissions | H47: Élevée | I47: Risque de non-conformité aux standards sectoriels nuisant à la crédibilité. | J47: Réaliser des tests de résistance des infrastructures face aux catastrophes naturelles.
B48: S’assurer de l’existence d'un guide d'utilisateur, manuel de procédure | C48: Vérifier l’existence d’un guide d’utilisateur et d’un manuel de procédures. | D48: Un guide utilisateur et un manuel de procédures sont-ils disponibles ? | E48: OUI | F48: Document de réingénierie des processus | G48: Contournement des contrôles d'accès | H48: Élevée | I48: Désalignement entre les besoins métier et les capacités techniques disponibles. | J48: Intégrer des contrôles de sécurité dans les phases de conception des applications (Security by Design).
C49: Confirmer la mise à jour des documents (moins de 12 mois). | D49: Ces documents ont-ils été mis à jour dans les 12 mois ? | E49: NON | F49: Rapport d’architecture technique de l’application | G49: Journalisation insuffisante des activités | H49: Élevée | I49: Fragmentation des systèmes réduisant l’efficacité globale de l’infrastructure. | J49: Mettre en place une veille technologique pour anticiper les risques liés aux nouvelles technologies.
C50: Analyser des exemples de procédures détaillées (étapes, screenshots). | D50: Des procédures détaillées avec captures d'écran existent-elles ? | E50: OUI | F50: Tableaux de bord avec indicateurs de performance (KPI) | G50: Détection tardive des incidents de sécurité | H50: Élevée | I50: Exposition à des erreurs de traitement par absence de validation automatisée. | J50: Auditer régulièrement les fournisseurs tiers pour s'assurer de leur conformité aux exigences de sécurité.
C51: Identifier des preuves de diffusion aux utilisateurs (accusés de réception). | D51: Des accusés de réception prouvent-ils la diffusion aux utilisateurs ? | E51: OUI | F51: Rapports de maturité technologique (ex : Gartner) | G51: Absence de revue des journaux d'audit | H51: Élevée | I51: Détérioration de la qualité des données utilisées pour la prise de décision. | J51: Documenter les procédures de gestion des identités temporaires et des comptes de service.
C52: Contrôler des formations dédiées à l’utilisation des documents. | D52: Des formations sur l'utilisation des documents sont-elles organisées ? | E52: OUI | F52: Procédures de gestion des accès privilégiés | G52: Failles dans les interfaces d'intégration | H52: Élevée | I52: Inadéquation des compétences des équipes face aux évolutions technologiques. | J52: Instaurer des revues post-incident pour améliorer continuellement les processus de sécurité.
A53: Application | B53: S'assurer que l'accès aux ressources de l'application (données et transactions) est restreint par un système de gestion d'accès | C53: Vérifier l’existence d’un système RBAC (Role-Based Access Control) actif. | D53: Un système RBAC est-il actif ? | E53: NON | F53: Logs d’actions administratives sur 90 jours | G53: Corruption des données lors des échanges | H53: Élevée | I53: Augmentation des temps d’indisponibilité des systèmes critiques. | J53: Adopter des outils de monitoring des performances applicatives pour détecter les goulets d'étranglement.
C54: Confirmer la présence de logs d’accès aux données sensibles sur 30 jours. | D54: Des logs d'accès aux données sensibles sur 30 jours existent-ils ? | E54: OUI | F54: Procédures de révocation des accès en cas de départ | G54: Absence de mécanismes de rejeu | H54: Élevée | I54: Perte d’opportunités commerciales par lenteur des processus informatiques. | J54: Mettre en œuvre une politique de gestion des clés de chiffrement incluant leur rotation et stockage sécurisé.
C55: Analyser la liste des utilisateurs avec droits administrateurs (moins de 5% du total). | D55: Moins de 5% des utilisateurs ont-ils des droits administrateur ? | E55: OUI | F55: Document de schéma-directeur du SI | G55: Perte de données critiques | H55: Élevée | I55: Dépassements budgétaires récurrents dans les projets IT non maîtrisés. | J55: Réaliser des audits de code statique et dynamique (SAST/DAST) pour les applications critiques.
C56: Tester le rejet d’accès hors profil via un compte test. | D56: Un compte test confirme-t-il le rejet d'accès hors profil ? | E56: OUI | F56: Procédures de contrôle qualité des données saisies | G56: Archivage non conforme | H56: Élevée | I56: Risque de perte de savoir-faire interne par dépendance à des solutions externes. | J56: Formaliser une stratégie de sortie pour les technologies obsolètes incluant leur remplacement progressif.
C57: Identifier une procédure de révocation des accès en cas de départ. | D57: Une procédure de révocation des accès en cas de départ existe-t-elle ? | E57: OUI | F57: Manuels d’exploitation mis à jour | G57: Restauration impossible après incident | H57: Élevée | I57: Difficultés à maintenir la cohérence des données entre systèmes hétérogènes. | J57: Instaurer des contrôles d'accès basés sur les rôles (RBAC) pour les environnements cloud.
B58: S’assurer qu’une procédure de gestion des profils utilisateurs existe | C58: Contrôler un workflow de création/suppression de profils (outil Jira ou équivalent). | D58: Un workflow de gestion des profils (Jira ou équivalent) est-il utilisé ? | E58: NON | F58: Procédures de gestion des correctifs urgents | G58: Pertes d'informations historiques | H58: Élevée | I58: Détérioration de l’expérience utilisateur impactant l’adoption des outils. | J58: Documenter les procédures de gestion des vulnérabilités logicielles et des correctifs d'urgence.
C59: Vérifier des traces de validation hiérarchique pour 5 profils aléatoires. | D59: La validation hiérarchique pour 5 profils aléatoires est-elle tracée ? | E59: OUI | F59: Rapports de revue de code pour les projets récents | G59: Défaut de purge sécurisée | H59: Moyenne | I59: Non-respect des exigences réglementaires en matière de transparence. | J59: Mettre en place des mécanismes de détection des fuites de données (DLP) pour les informations sensibles.
C60: Analyser l’existence d’un référentiel des profils types (PDF ou Excel). | D60: Un référentiel des profils types (PDF/Excel) est-il disponible ? | E60: OUI | F60: Procédures de déploiement en environnement de production | G60: Défaut de gestion des anomalies | H60: Élevée | I60: Augmentation des coûts de maintenance corrective faute de prévention. | J60: Auditer les configurations des conteneurs et des orchestrateurs pour limiter les risques d'exploitation.
C61: Confirmer la réalisation d’un audit semestriel des droits. | D61: Un audit semestriel des droits est-il réalisé ? | E61: OUI | F61: Contrats incluant des clauses « Escrow Agreement » | G61: Absence de processus de correction | H61: Élevée | I61: Incapacité à détecter les anomalies en temps réel par monitoring insuffisant. | J61: Implémenter une politique de gestion des risques spécifique aux projets d'intelligence artificielle.
C62: Identifier des sanctions en cas de non-respect (ex : mentions dans des PV). | D62: Des sanctions pour non-respect sont-elles prévues (mention dans PV) ? | E62: OUI | F62: Rapports de tests de montée en charge | G62: Défaut de traçabilité des corrections | H62: Élevée | I62: Dégradation de la résilience des systèmes face aux perturbations externes. | J62: Réaliser des tests d'intégration pour valider la cohérence des données entre systèmes hétérogènes.
B63: Vérifier que l’identification des utilisateurs est réalisée | C63: Tester l’impossibilité de se connecter sans identifiant unique. | D63: La connexion sans identifiant unique est-elle impossible ? | E63: NON | F63: Procédures de gestion des données archivées | G63: Réintégration non contrôlée des données | H63: Moyenne | I63: Exposition à des conflits d’intérêts dans la gestion des fournisseurs IT. | J63: Instaurer des contrôles d'accès biométriques pour les zones sensibles des datacenters.
C64: Vérifier l’absence de comptes génériques ("admin", "invité"). | D64: Les comptes génériques ("admin", "invité") sont-ils absents ? | E64: OUI | F64: Rapports de suivi des paiements des redevances | G64: Validation insuffisante des correctifs | H64: Moyenne | I64: Perte de contrôle sur les actifs informationnels par mauvaise gouvernance. | J64: Documenter les procédures de gestion des incidents liés aux fournisseurs de services cloud.
C65: Analyser l’existence d’un annuaire LDAP/Active Directory synchronisé. | D65: Un annuaire LDAP/Active Directory est-il synchronisé ? | E65: OUI | F65: Procédures de gestion des partenariats avec les éditeurs | G65: Défaut de supervision des mises à jour | H65: Élevée | I65: Risque de non-reconnaissance des dépenses IT par manque de traçabilité. | J65: Mettre en œuvre des solutions de segmentation réseau pour isoler les flux critiques.
C66: Confirmer la présence d’une procédure de réinitialisation sécurisée des identifiants. | D66: Une procédure sécurisée de réinitialisation des identifiants existe-t-elle ? | E66: OUI | F66: Documentation technique des interfaces d’intégration | G66: Exposition aux vulnérabilités non patchées | H66: Élevée | I66: Désorganisation des workflows métier par intégration défaillante des systèmes. | J66: Auditer régulièrement les configurations des équipements IoT pour prévenir les compromissions.
C67: Contrôler des logs de connexion avec adresses IP et horodatages. | D67: Les logs de connexion incluent-ils adresses IP et horodatages ? | E67: OUI | F67: Procédures de suppression sécurisée des données obsolètes | G67: Journalisation incomplète des modifications | H67: Élevée | I67: Augmentation des erreurs de saisie manuelle par absence de contrôles automatisés. | J67: Formaliser une politique de gestion des journaux d'activité conforme aux exigences réglementaires.
B68: Vérifier qu’un mot de passe est associé à l'identifiant | C68: Vérifier que chaque identifiant est associé à un mot de passe unique. | D68: Chaque identifiant a-t-il un mot de passe unique ? | E68: NON | F68: Rapports de performance de l’équipe de maintenance | G68: Défaut de détection des changements non autorisés | H68: Élevée | I68: Fragilisation de la position concurrentielle par retard technologique. | J68: Implémenter des contrôles de validation des entrées utilisateur pour prévenir les injections SQL.
C69: Confirmer l’application d’une politique de complexité des mots de passe (ex : 12 caractères, majuscules, chiffres). | D69: La politique impose-t-elle 12 caractères avec majuscules et chiffres ? | E69: OUI | F69: Procédures de recrutement et formation des équipes IT | G69: Absence de revue des configurations | H69: Élevée | I69: Incapacité à répondre aux attentes des utilisateurs finaux par rigidité des processus. | J69: Réaliser des audits de conformité aux normes sectorielles (PCI DSS, HIPAA, etc.).
C70: Analyser des logs de connexion pour détecter des mots de passe faibles. | D70: Les logs de connexion révèlent-ils des mots de passe faibles ? | E70: OUI | F70: Retours d’expérience du club utilisateurs | G70: Contrôles automatisés inefficaces | H70: Élevée | I70: Détérioration de la coordination entre équipes IT et métier par communication inefficace. | J70: Instaurer des mécanismes de surveillance des activités des robots logiciels (RPA).
C71: Tester la réinitialisation forcée après 90 jours. | D71: La réinitialisation forcée a-t-elle lieu après 90 jours ? | E71: OUI | F71: Procédures de gestion des mises à jour logicielles | G71: Défaut d'alerte sur les anomalies | H71: Élevée | I71: Exposition à des sanctions pour non-respect des clauses contractuelles avec les éditeurs. | J71: Documenter les procédures de gestion des certificats SSL/TLS pour éviter leur expiration.
C72: Identifier des alertes en cas de tentative de réutilisation d’un ancien mot de passe. | D72: Des alertes signalent-elles la réutilisation d'anciens mots de passe ? | E72: OUI | F72: Rapports d’évaluation de la conformité RGPD/ISO | G72: Absence de suivi des indicateurs clés | H72: Élevée | I72: Perte de données opérationnelles par corruption ou suppression accidentelle. | J72: Mettre en place des contrôles d'accès contextuels pour les applications métiers sensibles.
B73: S’assurer que les tentatives de connexions infructueuses à l'application sont suivies | C73: Vérifier des logs de tentatives infructueuses sur 30 jours. | D73: Les tentatives infructueuses sur 30 jours sont-elles tracées ? | E73: NON | F73: Procédures de gestion des accès aux bibliothèques logicielles | G73: Reporting incomplet ou erroné | H73: Élevée | I73: Augmentation des vulnérabilités réseau par configuration inadéquate. | J73: Auditer les configurations des systèmes de virtualisation pour garantir leur isolation.
C74: Confirmer la présence d’un système de verrouillage après 5 échecs. | D74: Le système se verrouille-t-il après 5 échecs ? | E74: OUI | F74: Logs de consultation de la documentation par les utilisateurs | G74: Décisions basées sur des informations obsolètes | H74: Élevée | I74: Incapacité à anticiper les besoins futurs par planification stratégique absente. | J74: Implémenter des contrôles de sécurité physique pour les supports de sauvegarde hors site.
C75: Analyser des alertes automatiques envoyées à l’administrateur. | D75: Des alertes automatiques sont-elles envoyées à l'administrateur ? | E75: OUI | F75: Procédures de validation hiérarchique des profils utilisateurs | G75: Distribution non sécurisée des états | H75: Élevée | I75: Dégradation de la qualité des services supportés par des outils obsolètes. | J75: Réaliser des tests de résistance aux attaques zero-day via des simulations réalistes.
C76: Tester la réinitialisation manuelle par l’administrateur. | D76: La réinitialisation manuelle par l'admin est-elle fonctionnelle ? | E76: OUI | F76: Rapports d’audit semestriel des droits d’accès | G76: Accès non contrôlé aux informations sensibles | H76: Élevée | I76: Risque de non-atteinte des objectifs de transformation numérique. | J76: Instaurer une politique de gestion des données archivées incluant leur classification et chiffrement.
C77: Identifier des procédures de suivi des tentatives suspectes. | D77: Une procédure de suivi des tentatives suspectes existe-t-elle ? | E77: OUI | F77: Procédures de gestion des alertes de sécurité automatiques | G77: Validation manquante des outputs | H77: Élevée | I77: Exposition à des litiges liés à la propriété intellectuelle des développements logiciels. | J77: Documenter les procédures de réponse aux fuites de données personnelles conformes au RGPD.
B78: S’assurer que l'accès aux données et aux transactions de l’application est géré | C78: Vérifier des logs d’accès aux transactions sensibles sur 30 jours. | D78: Les logs d'accès aux transactions sensibles sur 30 jours existent-ils ? | E78: NON | F78: Documents de référence des règles de gestion des données | G78: Erreurs de traitement non détectées | H78: Élevée | I78: Perte de flexibilité opérationnelle par architecture technique rigide. | J78: Mettre en œuvre des contrôles d'intégrité des métadonnées associées aux données critiques.
C79: Confirmer la présence d’un système de chiffrement des données en transit. | D79: Les données en transit sont-elles chiffrées ? | E79: OUI | F79: Procédures de contrôle qualité des corrections de données | G79: Incohérences dans les codifications | H79: Élevée | I79: Détérioration de la collaboration interne par outils collaboratifs inadaptés. | J79: Auditer les configurations des systèmes de gestion des identités (IAM) pour limiter les erreurs.
C80: Analyser des procédures de validation des accès par un supérieur hiérarchique. | D80: Un supérieur hiérarchique valide-t-il les accès sensibles ? | E80: OUI | F80: Rapports de tests d’interopérabilité avec les systèmes existants | G80: Défaut d'application des règles métier | H80: Élevée | I80: Augmentation des délais de livraison des projets IT par mauvaise gestion des ressources. | J80: Implémenter des mécanismes de détection des comportements anormaux des utilisateurs.
C81: Tester le rejet d’accès hors profil via un compte test. | D81: Un compte test confirme-t-il le rejet d'accès hors profil ? | E81: OUI | F81: Procédures de gestion des environnements (dev/test/prod) | G81: Défaut de cohérence inter-modules | H81: Élevée | I81: Incapacité à garantir l’authenticité des transactions électroniques. | J81: Réaliser des revues architecturales pour s'assurer de la résilience des infrastructures hybrides.
C82: Identifier des alertes en cas d’accès hors heures ouvrables. | D82: Des alertes existent-elles pour les accès hors heures ouvrables ? | E82: OUI | F82: Rapports de tests de modularité de l’application | G82: Interfaces non sécurisées | H82: Élevée | I82: Fragilisation de la chaîne d’approvisionnement IT par dépendance à un seul fournisseur. | J82: Instaurer des contrôles d'accès temporaires avec expiration automatique pour les prestataires.
B83: Vérifier l’existence de pistes d’audit sur le système d’administration de l’application | C83: Vérifier des logs d’audit des actions administratives sur 90 jours. | D83: Les logs d'actions administratives sur 90 jours sont-ils disponibles ? | E83: NON | F83: Procédures de gestion des versions logicielles | G83: Défaut de validation des développements | H83: Élevée | I83: Détérioration de l’image de marque suite à des incidents de sécurité médiatisés. | J83: Documenter les procédures de gestion des risques liés à l'utilisation de l'Internet des objets (IoT).
C84: Confirmer la présence d’un système de journalisation centralisé. | D84: Un système de journalisation centralisé est-il en place ? | E84: OUI | F84: Rapports de suivi des demandes de maintenance utilisateur | G84: Code non conforme aux standards | H84: Élevée | I84: Non-respect des engagements environnementaux liés à la gestion des infrastructures IT. | J84: Mettre en place des solutions de chiffrement homomorphique pour les données sensibles en traitement.
C85: Analyser des alertes automatiques pour les actions critiques (ex : suppression de données). | D85: Des alertes automatiques pour actions critiques existent-elles ? | E85: OUI | F85: Procédures de gestion des clés SSH/API | G85: Absence de revue par les pairs | H85: Moyenne | I85: Augmentation des coûts de licence par utilisation non optimisée des logiciels. | J85: Auditer les configurations des passerelles API pour prévenir les exploitations malveillantes.
C86: Tester la traçabilité des actions via un compte administrateur. | D86: La traçabilité des actions via un compte admin est-elle vérifiable ? | E86: OUI | F86: Rapports de performance des travaux batch | G86: Déploiement non contrôlé en production | H86: Moyenne | I86: Incapacité à maintenir la cohérence des données lors de fusions ou acquisitions. | J86: Implémenter des contrôles de sécurité dans les pipelines CI/CD pour les déploiements automatisés.
C87: Identifier des procédures de revue trimestrielle des logs. | D87: Une revue trimestrielle des logs est-elle prévue ? | E87: OUI | F87: Procédures de gestion des données rejetées | G87: Accès non autorisé aux environnements critiques | H87: Moyenne | I87: Dégradation de l’agilité organisationnelle par lenteur des processus IT. | J87: Réaliser des tests de charge pour valider la scalabilité des applications critiques.
B88: Vérifier que tous les documents servant de base à la saisie sont pris en compte | C88: Vérifier des exemples de documents sources (ex : factures, bons de commande). | D88: Des exemples de documents sources (factures, bons de commande) existent-ils ? | E88: NON | F88: Rapports de tests de compatibilité ascendante/descendante | G88: Défaut de séparation des environnements | H88: Moyenne | I88: Exposition à des erreurs de configuration entraînant des pannes critiques. | J88: Instaurer une politique de gestion des secrets applicatifs (mots de passe, clés API).
C89: Confirmer la présence d’un workflow de validation des documents. | D89: Un workflow de validation des documents est-il établi ? | E89: OUI | F89: Procédures de gestion des formations utilisateurs | G89: Gestion hasardeuse des accès privilégiés | H89: Moyenne | I89: Perte de compétitivité sur le marché par innovation technologique insuffisante. | J89: Documenter les procédures de gestion des incidents liés aux systèmes de paiement électronique.
C90: Analyser des logs de saisie pour corréler avec les documents sources. | D90: Les logs de saisie correspondent-ils aux documents sources ? | E90: OUI | F90: Rapports de suivi des indicateurs de satisfaction utilisateur | G90: Compromission des clés d'accès | H90: Moyenne | I90: Détérioration de la satisfaction client due à des services IT peu fiables. | J90: Mettre en œuvre des contrôles d'accès physiques et logiques pour les salles de contrôle.
C91: Tester la reprise des données après une erreur de saisie. | D91: La reprise des données après erreur de saisie est-elle possible ? | E91: OUI | F91: Procédures de gestion des risques résiduels | G91: Défaut de rotation des identifiants | H91: Moyenne | I91: Augmentation des risques liés à l’externalisation non supervisée. | J91: Auditer les configurations des systèmes SCADA/OT pour limiter les risques cyberindustriels.
C92: Identifier des procédures de contrôle qualité des données saisies. | D92: Des procédures de contrôle qualité des données saisies existent-elles ? | E92: OUI | F92: Rapports de revue trimestrielle des logs d’activité | G92: Compétences insuffisantes des équipes | H92: Moyenne | I92: Incapacité à aligner les investissements IT sur les priorités métier. | J92: Implémenter des mécanismes de protection contre les attaques par ingénierie sociale.
B93: S’assurer que les facilités de saisie, l’ergonomie de la saisie, les messages écrans et les contrôles sont mis en œuvre | C93: Vérifier des captures d’écran des interfaces de saisie. | D93: Des captures d'écran des interfaces de saisie sont-elles disponibles ? | E93: NON | F93: Procédures de gestion des accès hors heures ouvrables | G93: Défaut de plan de continuité d'activité | H93: Moyenne | I93: Fragilisation de la conformité aux normes internationales par pratiques obsolètes. | J93: Réaliser des revues de conformité des contrats avec les fournisseurs de services managés.
C94: Confirmer la présence de messages d’erreur clairs et explicites. | D94: Les messages d'erreur sont-ils clairs et explicites ? | E94: OUI | F94: Rapports de tests de stabilité des technologies utilisées | G94: Procédures de secours non opérationnelles | H94: Moyenne | I94: Détérioration de la capacité à auditer les processus internes efficacement. | J94: Instaurer des contrôles de sécurité pour les environnements DevOps et les outils low-code.
C95: Analyser des tests utilisateurs pour évaluer l’ergonomie. | D95: Des tests utilisateurs évaluent-ils l'ergonomie ? | E95: OUI | F95: Procédures de gestion des budgets d’extension d’infrastructure | G95: Temps de restauration excessif | H95: Moyenne | I95: Exposition à des interruptions d’activité par absence de redondance des systèmes. | J95: Documenter les procédures de gestion des risques liés à l'adoption de la blockchain.
C96: Tester la validation automatique des champs obligatoires. | D96: La validation automatique des champs obligatoires fonctionne-t-elle ? | E96: OUI | F96: Rapports de tests de réversibilité en cas d’échec de déploiement | G96: Perte de disponibilité du système | H96: Moyenne | I96: Perte de données stratégiques par absence de politiques de sauvegarde robustes. | J96: Mettre en place des mécanismes de validation des données en temps réel pour les transactions.
C97: Identifier des procédures de mise à jour des interfaces. | D97: Des procédures de mise à jour des interfaces existent-elles ? | E97: OUI | F97: Procédures de gestion des alertes de tentative d’accès non autorisé | G97: Défaut de tests de reprise | H97: Faible | I97: Augmentation des conflits entre équipes par manque de clarté des responsabilités. | J97: Auditer les configurations des systèmes de gestion de contenu (CMS) pour prévenir les vulnérabilités.
B98: S’assurer que les contrôles de validation des « brouillards » de saisie pour validation par réconciliation existent | C98: Vérifier des exemples de brouillards de saisie validés. | D98: Des brouillards de saisie validés sont-ils disponibles ? | E98: NON | F98: Rapports de suivi des indicateurs de productivité des processus | G98: Inadéquation des sauvegardes | H98: Élevée | I98: Incapacité à répondre aux audits réglementaires faute de documentation adéquate. | J98: Implémenter des contrôles d'accès basés sur l'attestation pour les appareils connectés.
C99: Confirmer la présence d’un workflow de réconciliation. | D99: Un workflow de réconciliation est-il en place ? | E99: OUI | F99: Procédures de gestion des mises à jour des spécifications fonctionnelles | G99: Exposition aux sinistres majeurs | H99: Élevée | I99: Dégradation de la qualité des décisions managériales par données incomplètes. | J99: Réaliser des tests de résilience des infrastructures face aux pannes matérielles.
C100: Analyser des logs de validation pour corréler avec les brouillards. | D100: Les logs de validation correspondent-ils aux brouillards ? | E100: OUI | F100: Rapports de tests de performance des développements spécifiques | G100: Non-respect des SLA | H100: Élevée | I100: Risque de non-conformité aux exigences sectorielles spécifiques. | J100: Instaurer une politique de gestion des correctifs critiques avec des délais contraignants.
C101: Tester la détection d’erreurs de saisie via des contrôles automatiques. | D101: Les contrôles automatiques détectent-ils les erreurs de saisie ? | E101: OUI | F101: Procédures de gestion des partenariats avec les clubs utilisateurs | G101: Dégradation de la qualité de service | H101: Élevée | I101: Détérioration de la collaboration avec les partenaires externes par systèmes incompatibles. | J101: Documenter les procédures de gestion des risques liés aux technologies émergentes (IA, 5G).
...

Sheet (4.2)_REF_FONCTION_INFORMATIQUE
A5: points de contrôles | B5: objectifs de contrôle | C5: critères d'évaluation | D5: questions d'évaluation | E5: Réponses | F5: Documents requis | G5: risques | H5: Criticités | I5: conséquences | J5: Recommandations
A6: Organisation | B6: S’assurer de l’existence d'un comité informatique | C6: Vérifier l’existence d’un organigramme officiel du comité signé par la direction. | D6: Un organigramme officiel du comité signé par la direction est-il disponible ? | E6: OUI | F6: Organigramme signé, charte du comité | G6: Rôles mal définis | H6: MOYEN | I6: Mauvaise gouvernance | J6: Mise à jour annuelle recommandée
C7: Confirmer la présence d’au moins 3 procès-verbaux de réunion datés des 6 derniers mois. | D7: Y a-t-il au moins 3 procès-verbaux de réunion datant des 6 derniers mois ? | E7: NON | F7: PV de réunion, feuilles de présence | G7: Absence de suivi | H7: ÉLEVÉ | I7: Décisions non appliquées | J7: Archiver tous les PV dans un répertoire partagé
C8: Analyser la composition du comité (CV/certifications des membres). | D8: Les CV et certifications des membres du comité sont-ils vérifiés et à jour ? | E8: NON | F8: Dossiers RH, CV, diplômes | G8: Incompétence potentielle | H8: MOYEN | I8: Mauvaises décisions | J8: Vérification annuelle recommandée
C9: Identifier un mandat écrit précisant les missions et la fréquence des réunions. | D9: Existe-t-il un mandat écrit définissant les missions et la fréquence des réunions du comité ? | E9: OUI | F9: Mandat signé, note de cadrage | G9: Objectifs flous | H9: MOYEN | I9: Inefficacité | J9: Doit être communiqué à tous les membres
C10: Contrôler la diffusion des décisions du comité via des emails ou documents internes. | D10: Les décisions du comité sont-elles diffusées via des emails ou documents internes ? | E10: OUI | F10: Emails, bulletins, intranet | G10: Communication défaillante | H10: ÉLEVÉ | I10: Non-exécution des décisions | J10: Utiliser une solution de diffusion centralisée
B11: S’assurer de l’existence d'une politique relative aux applications | C11: Vérifier la présence d’un document intitulé "Politique des Applications" approuvé par la direction. | D11: Un document intitulé "Politique des Applications" approuvé par la direction est-il disponible ? | E11: OUI | F11: Politique signée, version validée | G11: Politique inexistante | H11: ÉLEVÉ | I11: Risques non couverts | J11: Stocker la politique dans un référentiel qualité
C12: Confirmer la date de la dernière mise à jour (moins de 12 mois). | D12: La politique a-t-elle été mise à jour il y a moins de 12 mois ? | E12: OUI | F12: Historique des versions | G12: Politique obsolète | H12: MOYEN | I12: Actions inadaptées | J12: Date de mise à jour clairement indiquée
C13: Analyser les mentions de conformité RGPD/ISO dans le document. | D13: La politique mentionne-t-elle la conformité RGPD/ISO ? | E13: OUI | F13: Contenu de la politique | G13: Incohérence avec les normes | H13: MOYEN | I13: Risques juridiques | J13: Intégrer explicitement les obligations légales
C14: Vérifier la diffusion de la politique aux employés (accusés de réception signés). | D14: Les employés ont-ils signé des accusés de réception après diffusion de la politique ? | E14: NON | F14: Feuilles de signature, accusés numériques | G14: Non-application des règles | H14: ÉLEVÉ | I14: Manque de responsabilité | J14: Traçabilité indispensable en cas d’audit
C15: Identifier un plan de formation annuel lié à cette politique. | D15: Existe-t-il un plan de formation annuel lié à cette politique ? | E15: PAS | F15: Plan de formation, calendrier RH | G15: Employés non formés | H15: FAIBLE | I15: Erreurs ou négligences | J15: Prévoir au moins une session annuelle
B16: S’assurer que les rôle et responsabilités des utilisateurs sont bien définis | C16: Contrôler l’existence de fiches de poste pour chaque profil utilisateur. | D16: Des fiches de poste sont-elles disponibles pour chaque profil utilisateur ? | E16: OUI | F16: Fiches de poste, référentiel RH | G16: Ambiguïté des rôles | H16: MOYEN | I16: Attribution inadéquate des droits | J16: Vérification à chaque embauche ou changement
C17: Vérifier la signature des utilisateurs sur des chartes d’utilisation. | D17: Les utilisateurs ont-ils signé des chartes d’utilisation ? | E17: OUI | F17: Chartes, feuilles de signature | G17: Mauvais usage des outils | H17: FAIBLE | I17: Failles de sécurité | J17: Intégrer la charte au processus d’arrivée
C18: Confirmer la mise à jour des habilitations dans un tableau de gestion des accès. | D18: Le tableau de gestion des accès est-il mis à jour régulièrement ? | E18: NON | F18: Tableau des droits, journal de modifications | G18: Accès injustifiés | H18: MOYEN | I18: Violations de données | J18: Mise à jour mensuelle conseillée
C19: Analyser des logs d’accès pour corréler avec les rôles déclarés. | D19: Les comptes des utilisateurs sont-ils désactivés à la sortie ? | E19: OUI | F19: Liste des départs, journal d'accès | G19: Comptes actifs après départ | H19: FAIBLE | I19: Intrusion potentielle | J19: Processus automatique recommandé
C20: Identifier des procédures de révision trimestrielle des droits. | D20: Des procédures de révision trimestrielle des droits sont-elles appliquées ? | E20: PAS | F20: Procédures, rapports de révision | G20: Droits non conformes | H20: ÉLEVÉ | I20: Risques d’accès abusif | J20: Documenter chaque révision effectuée
B21: S’assurer qu’une analyse des risques a été réalisée | C21: Vérifier un rapport d’analyse des risques daté de moins de 12 mois. | D21: Un rapport d’analyse des risques datant de moins de 12 mois est-il disponible ? | E21: OUI | F21: Rapport de risques | G21: Vision dépassée des risques | H21: ÉLEVÉ | I21: Absence de planification adéquate | J21: Doit être actualisé annuellement
C22: Confirmer l’utilisation d’une méthodologie reconnue (ex : EBIOS, OCTAVE). | D22: Une méthodologie reconnue (EBIOS, OCTAVE) a-t-elle été utilisée ? | E22: PAS | F22: Méthode mentionnée dans le rapport | G22: Faible crédibilité de l’analyse | H22: MOYEN | I22: Recommandations inappropriées | J22: Préférer une méthode reconnue par l’ANSSI
C23: Analyser la liste des risques identifiés (au moins 10 risques critiques). | D23: Au moins 10 risques critiques sont-ils identifiés dans le rapport ? | E23: PAS | F23: Rapport détaillé, tableau des risques | G23: Analyse superficielle | H23: MOYEN | I23: Omission de menaces majeures | J23: Évaluation complète indispensable
C24: Identifier un plan d’action avec des responsables et des échéances. | D24: Un plan d’action avec responsables et échéances est-il documenté ? | E24: PAS | F24: Plan d’action, fiches de suivi | G24: Actions non suivies | H24: MOYEN | I24: Retards ou abandons | J24: Affecter clairement les responsables
C25: Contrôler des preuves de mise en œuvre des actions (rapports de suivi). | D25: Des preuves de mise en œuvre des actions sont-elles disponibles ? | E25: PAS | F25: Captures d’écran, rapports, emails | G25: Aucune traçabilité | H25: MOYEN | I25: Doute sur l’exécution | J25: Archiver toutes les preuves de réalisation
B26: S’assurer que le prolongement de l'analyse de risque et de son expansion ont été réalisés | C26: Vérifier des mises à jour de l’analyse des risques (au moins 2 révisions annuelles). | D26: L’analyse des risques a-t-elle été mise à jour au moins 2 fois par an ? | E26: NON | F26: Rapports d'analyse des risques, historique des mises à jour | G26: Décalage avec les menaces actuelles | H26: MOYEN | I26: Exposition accrue, conformité non assurée | J26: Mettre un rappel semestriel de mise à jour
C27: Confirmer l’intégration des nouveaux risques (ex : cybermenaces, RGPD). | D27: Les nouveaux risques (cybermenaces, RGPD) sont-ils intégrés dans l’analyse ? | E27: NON | F27: Liste des risques, documentation RGPD, veille sécurité | G27: Oubli de menaces critiques | H27: FAIBLE | I27: Sanctions réglementaires, incidents non anticipés | J27: Intégrer une veille réglementaire automatisée
C28: Analyser des indicateurs de suivi des risques (tableaux de bord). | D28: Des indicateurs de suivi des risques (tableaux de bord) sont-ils analysés ? | E28: NON | F28: Tableaux de bord, rapports de suivi, comptes-rendus de réunions | G28: Pilotage inefficace | H28: MOYEN | I28: Mauvaise allocation des ressources, erreurs de priorisation | J28: Utiliser un outil de BI (PowerBI, Tableau)
C29: Identifier des procédures de reporting aux instances dirigeantes. | D29: Des procédures de reporting aux instances dirigeantes existent-elles ? | E29: NON | F29: Procédure écrite, exemples de rapports envoyés | G29: Manque de transparence | H29: MOYEN | I29: Sous-évaluation des enjeux par la direction | J29: Prévoir un point sécurité régulier en comité
C30: Contrôler des preuves de sensibilisation des équipes aux risques majeurs. | D30: Des preuves de sensibilisation des équipes aux risques majeurs sont-elles disponibles ? | E30: NON | F30: Attestations de formation, listes de présence, supports | G30: Personnel mal préparé | H30: FAIBLE | I30: Augmentation du risque humain | J30: Organiser des ateliers de simulation
B31: S’assurer que l’analyse et évaluation du niveau de sensibilité a été réalisée | C31: Vérifier un document classifiant les données par niveau de sensibilité (public, interne, confidentiel). | D31: Un document classifiant les données par niveau de sensibilité est-il disponible ? | E31: OUI | F31: Document de classification, référentiel documentaire | G31: Confusion dans la manipulation des données | H31: FAIBLE | I31: Fuites de données sensibles | J31: Associer des étiquettes visibles aux fichiers
C32: Confirmer la mise à jour de la classification (moins de 6 mois). | D32: La classification des données a-t-elle été mise à jour il y a moins de 6 mois ? | E32: OUI | F32: Historique de versions, validation de la DSI | G32: Classification obsolète | H32: MOYEN | I32: Mauvaises décisions de sécurité | J32: Intégrer un processus de révision semestriel
C33: Analyser des logs d’accès aux données sensibles sur 30 jours. | D33: Les logs d’accès aux données sensibles sur 30 jours sont-ils analysés ? | E33: PAS | F33: Fichiers de logs, rapports d’analyse, outils SIEM | G33: Accès anormaux non détectés | H33: FAIBLE | I33: Perte ou vol de données non tracé | J33: Automatiser l’analyse avec alertes
C34: Identifier des procédures de protection spécifiques pour les données critiques. | D34: Des procédures de protection spécifiques pour les données critiques existent-elles ? | E34: OUI | F34: Procédures écrites, plan de chiffrement, gestion des droits | G34: Risque élevé sur les données clés | H34: MOYEN | I34: Atteinte à l’intégrité, disponibilité ou confidentialité | J34: S'assurer d'un chiffrement fort et accès restreint
C35: Contrôler des preuves de formation des utilisateurs sur la classification. | D35: Des preuves de formation des utilisateurs sur la sécurité des données sont-elles disponibles ? | E35: OUI | F35: Registres de formation, e-learnings validés | G35: Mauvaises pratiques utilisateurs | H35: FAIBLE | I35: Risques internes accrus | J35: Intégrer un module sécurité obligatoire à l’arrivée
B36: Vérifier l’existence d’un manuel d'administration de l'application | C36: Vérifier l’existence d’un manuel d’administration mis à jour (moins de 12 mois). | D36: Un manuel d’administration mis à jour est-il disponible ? | E36: OUI | F36: Dernière version du manuel, date de mise à jour | G36: Erreurs d’administration | H36: MOYEN | I36: Incidents techniques récurrents | J36: Archiver les anciennes versions pour audit
C37: Confirmer la couverture des procédures clés (ex : sauvegarde, restauration). | D37: Les procédures clés (sauvegarde, restauration...) sont-elles couvertes dans le manuel ? | E37: OUI | F37: Manuel, procédure de sauvegarde/restauration | G37: Incapacité à restaurer rapidement | H37: MOYEN | I37: Perte de données, arrêt de service | J37: Réaliser un test de restauration trimestriel
C38: Analyser des exemples de procédures détaillées (étapes, screenshots). | D38: Des exemples de procédures détaillées sont-ils inclus ? | E38: OUI | F38: Captures d’écran, guides pas-à-pas | G38: Interprétation variable des consignes | H38: FAIBLE | I38: Risques d’erreurs ou d’inefficacité | J38: Prévoir une mise à jour visuelle du manuel
C39: Identifier des preuves d’utilisation du manuel (logs de consultation). | D39: Des logs de consultation du manuel existent-ils ? | E39: OUI | F39: Logs d’accès, portails internes | G39: Non-utilisation du manuel | H39: FAIBLE | I39: Procédures contournées, perte de maîtrise | J39: Suivi possible via intranet ou SharePoint
C40: Contrôler des formations dédiées à l’équipe d’administration. | D40: Des formations dédiées à l’équipe d’administration sont-elles organisées ? | E40: OUI | F40: Registre de formation, agendas, supports | G40: Compétences non actualisées | H40: MOYEN | I40: Failles dans l’administration système | J40: Prévoir au moins 1 formation technique/an
B41: Vérifier l’existence de procédures formalisées | C41: Vérifier des procédures écrites pour au moins 5 processus critiques (ex : gestion des incidents). | D41: Des procédures écrites pour au moins 5 processus critiques (ex : gestion des incidents) existent-elles ? | E41: NON | F41: Procédures détaillées validées, documentation des processus | G41: Réponses désorganisées aux incidents critiques | H41: ÉLEVÉ | I41: Allongement des temps de résolution, aggravation de l’impact | J41: Identifier et prioriser les processus critiques métier
C42: Confirmer la signature des procédures par les responsables concernés. | D42: Les procédures sont-elles signées par les responsables concernés ? | E42: NON | F42: Procédures signées, liste des signataires | G42: Manque d’engagement ou de validation | H42: ÉLEVÉ | I42: Contestation ou non-application | J42: Centraliser les signatures dans un répertoire partagé
C43: Analyser des preuves d’application (logs, rapports d’exécution). | D43: Des preuves d’application des procédures (logs, rapports) sont-elles disponibles ? | E43: NON | F43: Journaux d’exécution, comptes rendus, tickets d’incident | G43: Procédures non respectées | H43: MOYEN | I43: Failles de sécurité, erreurs opérationnelles | J43: Mettre en place un audit de conformité
C44: Identifier des indicateurs de performance liés aux procédures. | D44: Des indicateurs de performance liés aux procédures sont-ils définis ? | E44: NON | F44: Tableaux de bord, KPI associés, référentiels ITIL | G44: Absence de pilotage objectif | H44: MOYEN | I44: Dérives non détectées, inefficacité | J44: Utiliser des KPIs simples et régulièrement suivis
C45: Contrôler des mises à jour récentes (moins de 6 mois). | D45: Les procédures ont-elles été mises à jour il y a moins de 6 mois ? | E45: NON | F45: Historique de modification, version actuelle | G45: Obsolescence des actions décrites | H45: MOYEN | I45: Risques non maîtrisés, mauvaises pratiques | J45: Établir un calendrier de révision semestriel
B46: S’assurer de l’existence et de la mise à disposition du compte rendu mensuel au propriétaire | C46: Vérifier des comptes rendus mensuels datés des 6 derniers mois. | D46: Un modèle standardisé de compte rendu mensuel est-il documenté ? | E46: OUI | F46: Modèle de rapport, note de cadrage | G46: Hétérogénéité des remontées d'information | H46: FAIBLE | I46: Difficulté à consolider ou comparer les données | J46: Créer un template structuré validé par la DSI
C47: Confirmer la signature des comptes rendus par le propriétaire de l’application. | D47: Le compte rendu contient-il des indicateurs de performance (KPI) pertinents pour le propriétaire ? | E47: OUI | F47: Rapports mensuels, liste des KPIs | G47: Décisions prises sans base objective | H47: MOYEN | I47: Mauvaise priorisation ou pilotage | J47: Impliquer le propriétaire dans la définition des KPI
C48: Analyser des indicateurs clés inclus (ex : disponibilité, incidents). | D48: Le compte rendu est-il systématiquement validé et signé par le responsable avant transmission ? | E48: NON | F48: Compte rendu signé, horodaté | G48: Informations non relues, erreurs | H48: ÉLEVÉ | I48: Diffusion d’informations erronées | J48: Utiliser une validation électronique automatique
C49: Identifier des actions correctives planifiées dans les comptes rendus. | D49: Le compte rendu est-il transmis au propriétaire dans les délais impartis ? | E49: NON | F49: Suivi de transmission, planning | G49: Décalage entre état réel et informations reçues | H49: MOYEN | I49: Retards d’action, mauvaises décisions | J49: Automatiser l’envoi avec accusé de réception
C50: Contrôler des preuves de suivi des actions (rapports de clôture). | D50: Les comptes rendus sont-ils archivés de manière sécurisée et organisée ? | E50: NON | F50: Répertoire sécurisé, classement daté | G50: Perte d’historique | H50: MOYEN | I50: Impossible de tracer ou auditer | J50: Utiliser un archivage avec droits restreints
B51: S’assurer de l’existence d'un guide d'utilisateur, manuel de procédure | C51: Vérifier l’existence d’un guide d’utilisateur et d’un manuel de procédures. | D51: Un guide utilisateur ou manuel de procédures simplifiées est-il disponible ? | E51: OUI | F51: Guide PDF, manuel de procédures | G51: Utilisation erronée des outils ou logiciels | H51: MOYEN | I51: Failles opérationnelles, inefficacité | J51: Prévoir un format synthétique + version vidéo
C52: Confirmer la mise à jour des documents (moins de 12 mois). | D52: Le manuel de procédures décrit-il précisément les processus avec les rôles et responsabilités ? | E52: OUI | F52: Manuel de procédures détaillé, organigramme | G52: Confusion des tâches | H52: MOYEN | I52: Risques d’erreur ou de conflit d’autorité | J52: Mentionner les contacts de référence dans chaque section
C53: Analyser des exemples de procédures détaillées (étapes, screenshots). | D53: Le processus formel de mise à jour des versions du système est-il défini ? | E53: OUI | F53: Procédure de mise à jour, planning des releases | G53: Versions non maîtrisées | H53: MOYEN | I53: Vulnérabilités, incompatibilités | J53: Adopter une gouvernance des versions logicielle
C54: Identifier des preuves de diffusion aux utilisateurs (accusés de réception). | D54: Existe-t-il plusieurs formats disponibles (PDF, en ligne, imprimé) selon les besoins ? | E54: NON | F54: Liste des formats disponibles, accès intranet | G54: Inaccessibilité de l'information | H54: MOYEN | I54: Perte de temps, non-respect des procédures | J54: Favoriser le format numérique interactif
C55: Contrôler des formations dédiées à l’utilisation des documents. | D55: Un responsable est-il désigné pour la maintenance des documents ? | E55: NON | F55: Fiche de rôle, désignation officielle | G55: Mises à jour irrégulières | H55: MOYEN | I55: Obsolescence des référentiels | J55: Nommer un référent documentaire par domaine
A56: Application | B56: S'assurer que l'accès aux ressources de l'application (données et transactions) est restreint par un système de gestion d'accès | C56: Vérifier l’existence d’un système RBAC (Role-Based Access Control) actif. | D56: Un système RBAC (Role-Based Access Control) est-il actif ? | E56: OUI | F56: Politique de gestion des accès, configurations | G56: Accès non contrôlé aux données | H56: MOYEN | I56: Fuite de données sensibles, violation de conformité | J56: Implémenter et documenter un système RBAC
C57: Confirmer la présence de logs d’accès aux données sensibles sur 30 jours. | D57: Les logs d’accès aux données sensibles sur 30 jours sont-ils conservés ? | E57: OUI | F57: Journaux d'accès, politique de rétention | G57: Absence de traçabilité des accès | H57: ÉLEVÉ | I57: Impossible d’auditer en cas d’incident | J57: Mettre en place une journalisation centralisée avec rétention de 30 jours minimum
C58: Analyser la liste des utilisateurs avec droits administrateurs (moins de 5% du total). | D58: Le nombre d’utilisateurs avec droits administrateurs est-il inférieur à 5 % du total ? | E58: NON | F58: Liste des utilisateurs, droits attribués | G58: Trop d’utilisateurs avec des privilèges élevés | H58: ÉLEVÉ | I58: Hausse du risque d’erreurs critiques ou malveillantes | J58: Limiter les droits admin, revue régulière des accès
C59: Tester le rejet d’accès hors profil via un compte test. | D59: Un compte test a-t-il été utilisé pour vérifier le rejet d’accès hors profil ? | E59: NON | F59: Rapport de tests d’accès | G59: Accès non prévu validé par erreur | H59: ÉLEVÉ | I59: Brèche de sécurité ou mauvaise configuration | J59: Prévoir des tests réguliers de non-conformité aux profils d'accès
C60: Identifier une procédure de révocation des accès en cas de départ. | D60: Une procédure de révocation des accès en cas de départ est-elle appliquée ? | E60: OUI | F60: Procédure RH, registre des départs, journal | G60: Anciens employés ayant toujours accès | H60: ÉLEVÉ | I60: Accès illégitime, fuite d’informations, compromission | J60: Automatiser la révocation des comptes dès départ enregistré
B61: S’assurer qu’une procédure de gestion des profils utilisateurs existe | C61: Contrôler un workflow de création/suppression de profils (outil Jira ou équivalent). | D61: Un workflow de création/suppression de profils (ex: Jira) est-il en place ? | E61: OUI | F61: Diagramme du workflow, tickets de demandes | G61: Accès non documenté, erreurs de configuration | H61: MOYEN | I61: Création ou suppression non contrôlée des droits d'accès | J61: Formaliser un workflow validé et automatisé
C62: Vérifier des traces de validation hiérarchique pour 5 profils aléatoires. | D62: Des traces de validation hiérarchique pour les profils aléatoires existent-elles ? | E62: NON | F62: Logs d'approbation, emails, tickets | G62: Absence de validation formelle | H62: ÉLEVÉ | I62: Attribution de droits non justifiés | J62: Ajouter une étape de validation hiérarchique obligatoire
C63: Analyser l’existence d’un référentiel des profils types (PDF ou Excel). | D63: Un référentiel des profils types (PDF/Excel) est-il disponible ? | E63: NON | F63: Référentiel des profils, manuel utilisateur | G63: Hétérogénéité des droits | H63: ÉLEVÉ | I63: Difficultés d’audit, risques d’accès inapproprié | J63: Maintenir un référentiel de profils à jour
C64: Confirmer la réalisation d’un audit semestriel des droits. | D64: Un audit semestriel des droits est-il effectué ? | E64: NON | F64: Rapports d’audit, PV de réunions | G64: Accumulation de droits obsolètes | H64: ÉLEVÉ | I64: Risque de compromission accru | J64: Effectuer un audit formel des droits tous les 6 mois
C65: Identifier des sanctions en cas de non-respect (ex : mentions dans des PV). | D65: Des sanctions en cas de non-respect des procédures sont-elles documentées ? | E65: NON | F65: Code de conduite, charte informatique | G65: Manque de dissuasion | H65: MOYEN | I65: Répétition des fautes, faible culture de sécurité | J65: Inscrire les sanctions dans les politiques internes
B66: Vérifier que l’identification des utilisateurs est réalisée | C66: Tester l’impossibilité de se connecter sans identifiant unique. | D66: Est-il impossible de se connecter sans identifiant unique ? | E66: NON | F66: Politique d’authentification | G66: Usurpation d’identité | H66: FAIBLE | I66: Impossibilité de traçabilité | J66: Imposer l’identifiant unique pour chaque utilisateur
C67: Vérifier l’absence de comptes génériques ("admin", "invité"). | D67: Les comptes génériques (ex: "admin", "invité") sont-ils absents ? | E67: NON | F67: Liste des comptes utilisateurs | G67: Partage de compte, anonymat des actions | H67: ÉLEVÉ | I67: Non-conformité RGPD, traçabilité impossible | J67: Supprimer les comptes génériques ou les restreindre drastiquement
C68: Analyser l’existence d’un annuaire LDAP/Active Directory synchronisé. | D68: Un annuaire LDAP/Active Directory synchronisé est-il utilisé ? | E68: NON | F68: Diagramme d’architecture, logs de synchronisation | G68: Comptes désynchronisés ou incohérents | H68: MOYEN | I68: Accès désactivé non répercuté ou mauvaise gestion des identités | J68: Intégrer tous les accès via un annuaire centralisé
C69: Confirmer la présence d’une procédure de réinitialisation sécurisée des identifiants. | D69: Une procédure d’identification des destinataires existe-t-elle ? | E69: NON | F69: Politique de gestion des données, registre des accès | G69: Envoi de données à de mauvais destinataires | H69: MOYEN | I69: Fuite de données sensibles | J69: Identifier clairement les destinataires autorisés
C70: Contrôler des logs de connexion avec adresses IP et horodatages. | D70: Les logs de connexion incluent-ils adresse IP et horodatage ? | E70: OUI | F70: Journaux d’audit, outils de monitoring | G70: Traçabilité partielle | H70: MOYEN | I70: Impossible de retracer certaines actions | J70: Enregistrer systématiquement l’IP et la date/heure de connexion
B71: Vérifier qu’un mot de passe est associé à l'identifiant | C71: Vérifier que chaque identifiant est associé à un mot de passe unique. | D71: Chaque utilisateur a-t-il un mot de passe unique ? | E71: OUI | F71: Politique de sécurité, configuration des comptes | G71: Partage ou réutilisation de mots de passe | H71: MOYEN | I71: Perte de traçabilité, risque de compromission | J71: Forcer l’unicité des mots de passe par utilisateur
C72: Confirmer l’application d’une politique de complexité des mots de passe (ex : 12 caractères, majuscules, chiffres). | D72: Une politique de complexité des mots de passe (caractères, majuscules, chiffres) est-elle appliquée ? | E72: OUI | F72: Politique de mot de passe, configuration système | G72: Faiblesse des mots de passe | H72: ÉLEVÉ | I72: Accès non autorisé par force brute ou dictionnaire | J72: Appliquer une politique forte de complexité et rotation régulière
C73: Analyser des logs de connexion pour détecter des mots de passe faibles. | D73: Des tests de rejet de mot de passe simple sont-ils réalisés ? | E73: NON | F73: Rapports de tests de sécurité | G73: Mots de passe faibles acceptés | H73: ÉLEVÉ | I73: Vulnérabilité aux attaques automatisées | J73: Intégrer des tests automatisés dans le processus de création de compte
C74: Tester la réinitialisation forcée après 90 jours. | D74: Une procédure de réinitialisation sécurisée du mot de passe est-elle en place ? | E74: NON | F74: Procédure IT, documentation utilisateur | G74: Accès au compte via ingénierie sociale | H74: ÉLEVÉ | I74: Compromission de comptes | J74: Mettre en place une vérification multi-étapes pour réinitialisation
C75: Identifier des alertes en cas de tentative de réutilisation d’un ancien mot de passe. | D75: Des tests de la procédure ont-ils été réalisés ? | E75: OUI | F75: Rapport de test, PV de validation | G75: Procédures non fonctionnelles en cas d’urgence | H75: MOYEN | I75: Blocage d’accès, perte de productivité | J75: Tester régulièrement les procédures critiques
B76: S’assurer que les tentatives de connexions infructueuses à l'application sont suivies | C76: Vérifier des logs de tentatives infructueuses sur 30 jours. | D76: Un système de verrouillage après 5 échecs est-il activé ? | E76: OUI | F76: Politique de sécurité, paramètres du système | G76: Tentatives illimitées de connexion | H76: FAIBLE | I76: Risques accrus de brute force | J76: Activer un verrouillage temporaire après X tentatives
C77: Confirmer la présence d’un système de verrouillage après 5 échecs. | D77: Des alertes automatiques sont-elles envoyées à l’administrateur en cas d’échecs ? | E77: OUI | F77: Paramétrage de la supervision, journal d’alertes | G77: Retard dans la détection d’attaques | H77: MOYEN | I77: Intrusions non détectées à temps | J77: Configurer des alertes en temps réel
C78: Analyser des alertes automatiques envoyées à l’administrateur. | D78: La réinitialisation manuelle par l’administrateur a-t-elle été testée ? | E78: NON | F78: Rapport de test, procédure IT | G78: Erreur humaine ou procédure incorrecte | H78: ÉLEVÉ | I78: Compte bloqué, mauvaise réattribution | J78: Documenter et tester la procédure périodiquement
C79: Tester la réinitialisation manuelle par l’administrateur. | D79: Des procédures de suivi des tentatives suspectes existent-elles ? | E79: NON | F79: Politique de sécurité, outil SIEM | G79: Activité malveillante non détectée | H79: MOYEN | I79: Compromission prolongée sans réaction | J79: Mettre en place un suivi automatisé avec règles de détection
C80: Identifier des procédures de suivi des tentatives suspectes. | D80: Des logs d’accès aux fichiers sensibles sont-ils archivés et analysés ? | E80: OUI | F80: Journaux d’accès, rapports d’audit | G80: Accès illégitime non détecté | H80: MOYEN | I80: Fuite ou altération de données sensibles | J80: Archiver et analyser régulièrement les logs critiques
B81: S’assurer que l'accès aux données et aux transactions de l’application est géré | C81: Vérifier des logs d’accès aux transactions sensibles sur 30 jours. | D81: Le mécanisme RBAC est-il configuré pour restreindre les fichiers selon les profils ? | E81: OUI | F81: Politiques RBAC, paramétrages des fichiers | G81: Accès non restreint à des documents sensibles | H81: FAIBLE | I81: Divulgation d’informations confidentielles | J81: Configurer des ACLs strictes selon les profils définis
C82: Confirmer la présence d’un système de chiffrement des données en transit. | D82: Les accès aux données critiques sont-ils validés par un supérieur hiérarchique ? | E82: OUI | F82: Formulaires de validation, workflow | G82: Droits attribués sans contrôle | H82: FAIBLE | I82: Attributions abusives ou inappropriées | J82: Rendre la validation managériale obligatoire pour les données sensibles
C83: Analyser des procédures de validation des accès par un supérieur hiérarchique. | D83: Des preuves de validation sont-elles conservées ? | E83: OUI | F83: Emails, tickets Jira, logs de validation | G83: Aucun historique d'approbation | H83: ÉLEVÉ | I83: Difficulté à prouver la conformité ou remonter un incident | J83: Archiver les validations dans un système centralisé
C84: Tester le rejet d’accès hors profil via un compte test. | D84: Les droits sont-ils désactivés pour les accès non utilisés depuis 30 jours ? | E84: NON | F84: Relevés d’activité, rapport d’audit | G84: Maintien de droits obsolètes | H84: MOYEN | I84: Risque de compromission par comptes inactifs | J84: Automatiser la désactivation des comptes inactifs
C85: Identifier des alertes en cas d’accès hors heures ouvrables. | D85: Des alertes sont-elles configurées pour les accès utilisateurs non autorisés ? | E85: NON | F85: Outils de monitoring, rapports de sécurité | G85: Intrusion non détectée | H85: FAIBLE | I85: Accès frauduleux prolongé | J85: Définir des règles d’alerte sur comportements suspects
B86: Vérifier l’existence de pistes d’audit sur le système d’administration de l’application | C86: Vérifier des logs d’audit des actions administratives sur 90 jours. | D86: Une procédure de désactivation des comptes administratifs (ex: suppression de données) ? | E86: OUI | F86: Procédure IT, journal des comptes | G86: Comptes puissants non désactivés après usage | H86: MOYEN | I86: Risque élevé d’abus ou d’erreur | J86: Créer une procédure d’expiration/désactivation ciblée
C87: Confirmer la présence d’un système de journalisation centralisé. | D87: La traçabilité des actions administratives est-elle testée ? | E87: NON | F87: Logs système, rapport de tests | G87: Actions non traçables | H87: ÉLEVÉ | I87: Impossible d’identifier un administrateur fautif | J87: Tester régulièrement la qualité des logs
C88: Analyser des alertes automatiques pour les actions critiques (ex : suppression de données). | D88: La traçabilité des actions critiques d’un utilisateur est-elle planifiée ? | E88: PAS | F88: Politique de journalisation | G88: Traçabilité partielle | H88: ÉLEVÉ | I88: Incapacité à reconstituer une chronologie précise | J88: Inclure les actions critiques dans les logs par défaut
C89: Tester la traçabilité des actions via un compte administrateur. | D89: Des exemples de documents sources sont-ils archivés avec les données saisies ? | E89: PAS | F89: Base de données, GED, workflow | G89: Absence de preuve ou de vérification | H89: ÉLEVÉ | I89: Données non vérifiables | J89: Conserver systématiquement les pièces jointes et documents justificatifs
C90: Identifier des procédures de revue trimestrielle des logs. | D90: La table d’audit est-elle synchronisée avec le journal d’intégrité ? | E90: OUI | F90: Base de données, outils de contrôle d’intégrité | G90: Audit partiel ou incohérent | H90: ÉLEVÉ | I90: Informations inexploitables ou erronées | J90: Synchroniser les systèmes de logs et audits
B91: Vérifier que tous les documents servant de base à la saisie sont pris en compte | C91: Vérifier des exemples de documents sources (ex : factures, bons de commande). | D91: Des tests de reprise des données après une saisie ont-ils été réalisés ? | E91: OUI | F91: Rapport de tests, procédures de sauvegarde | G91: Perte de données en cas de panne ou incident | H91: ÉLEVÉ | I91: Saisie à refaire, interruption de service | J91: Réaliser des tests de restauration réguliers
C92: Confirmer la présence d’un workflow de validation des documents. | D92: Les données saisies sont-elles validées au moment de la saisie ? | E92: OUI | F92: Spécifications fonctionnelles, code source | G92: Saisie erronée ou incohérente | H92: ÉLEVÉ | I92: Mauvaise qualité de données | J92: Appliquer des règles de validation côté client et serveur
C93: Analyser des logs de saisie pour corréler avec les documents sources. | D93: Les champs obligatoires sont-ils identifiés par des indicateurs clairs ? | E93: NON | F93: Interfaces utilisateur, maquettes | G93: Omission de données importantes | H93: ÉLEVÉ | I93: Incomplétude des dossiers, erreurs métier | J93: Rendre visuellement explicites les champs obligatoires
C94: Tester la reprise des données après une erreur de saisie. | D94: Les utilisateurs confirment-ils que le message d’erreur les aide à corriger leurs erreurs ? | E94: NON | F94: Retour utilisateurs, tests UX | G94: Messages d’erreur non compréhensibles | H94: MOYEN | I94: Abandon ou saisie incorrecte persistante | J94: Tester les messages avec les utilisateurs, les rendre pédagogiques
C95: Identifier des procédures de contrôle qualité des données saisies. | D95: Des tests de validation sur formulaire ont-ils été réalisés ? | E95: NON | F95: Rapports de test fonctionnel | G95: Failles ou erreurs de validation | H95: MOYEN | I95: Contournement du contrôle, enregistrement invalide | J95: Intégrer des scénarios de test de validation dans la QA
B96: S’assurer que les facilités de saisie, l’ergonomie de la saisie, les messages écrans et les contrôles sont mis en œuvre | C96: Vérifier des captures d’écran des interfaces de saisie. | D96: Un message de confirmation est-il affiché après chaque saisie ? | E96: NON | F96: Maquettes, spécifications fonctionnelles | G96: Saisie non perçue comme réussie | H96: FAIBLE | I96: Doubles enregistrements ou abandon par doute | J96: Toujours afficher un accusé clair de succès ou d’échec
C97: Confirmer la présence de messages d’erreur clairs et explicites. | D97: Un système de journalisation des modifications est-il en place ? | E97: NON | F97: Journaux d’événements, logs applicatifs | G97: Modifications non tracées | H97: MOYEN | I97: Impossible d’identifier l’auteur des changements | J97: Mettre en place une journalisation fine des changements
C98: Analyser des tests utilisateurs pour évaluer l’ergonomie. | D98: Les messages de journalisation sont-ils exploitables ? | E98: NON | F98: Journaux, outils de supervision | G98: Journaux incompréhensibles ou trop verbeux | H98: ÉLEVÉ | I98: Analyse difficile, perte de temps en cas d’incident | J98: Structurer les logs et former les équipes à leur interprétation
C99: Tester la validation automatique des champs obligatoires. | D99: Des horodatages précis (date + heure + utilisateur) sont-ils présents ? | E99: NON | F99: Fichier de log, base de données | G99: Manque de contexte temporel | H99: MOYEN | I99: Impossible de corréler les événements | J99: Ajouter un horodatage complet et standardisé à chaque événement
C100: Identifier des procédures de mise à jour des interfaces. | D100: Des données critiques sont-elles systématiquement revues et validées ? | E100: NON | F100: Procédures de validation, PV de contrôles | G100: Données erronées non détectées | H100: FAIBLE | I100: Décisions prises sur des données fausses | J100: Imposer une relecture/validation des données sensibles
B101: S’assurer que les contrôles de validation des « brouillards » de saisie pour validation par réconciliation existent | C101: Vérifier des exemples de brouillards de saisie validés. | D101: Des exemples de brouillards de saisie validés par réconciliation sont-ils archivés ? | E101: NON | F101: Schéma de base, spécifications fonctionnelles | G101: Perte de l’état antérieur des données | H101: FAIBLE | I101: Impossible de retracer l’évolution des informations | J101: Mettre en place une table d’historique ou un système de versionning
C102: Confirmer la présence d’un workflow de réconciliation. | D102: Un workflow de réconciliation entre les brouillards et les données finales est-il documenté ? | E102: NON | F102: Interfaces utilisateur, base de données | G102: Utilisateur sans visibilité sur les modifications | H102: MOYEN | I102: Perte de confiance, erreurs non détectées | J102: Intégrer l’historique dans l’interface de consultation
C103: Analyser des logs de validation pour corréler avec les brouillards. | D103: Les logs de validation des brouillards sont-ils corrélés avec les données enregistrées ? | E103: NON | F103: Organigramme, politique de gouvernance | G103: Données mal gérées ou sans supervision | H103: ÉLEVÉ | I103: Responsabilités floues, absence de redevabilité | J103: Désigner un responsable pour chaque domaine de données
C104: Tester la détection d’erreurs de saisie via des contrôles automatiques. | D104: Des contrôles automatiques détectent-ils les écarts lors de la réconciliation ? | E104: NON | F104: Procédures internes, manuel qualité | G104: Données erronées conservées | H104: MOYEN | I104: Mauvaise qualité de la base, décisions erronées | J104: Mettre en place une procédure claire de correction validée
...

Sheet (4.3)CONTROLE_PROJET_INFORMATIQ
C2: points de contrôles | D2: Objectifs de contrôle | E2: Critères d'évaluations | F2: Questions d'évaluations | G2: Réponse | H2: Documents requis | I2: Risques | J2: Criticités | K2: Conséquences | L2: Recommandation
C3: Objectifs et enjeux du projet ; | D3: S’assurer qu’une étude de la valeur et des études d’opportunité et d’impacts ont été réalisées ; | E3: Existence d’une étude de valeur | F3: Une étude de valeur a-t-elle été menée ? | G3: OUI | H3: Étude de valeur | I3: Mauvaise estimation des bénéfices attendus | J3: MOYEN | K3: Investissement peu rentable | L3: Réaliser systématiquement une étude de valeur préalable
E4: Analyse des coûts/bénéfices | F4: Une analyse coût/bénéfice a-t-elle été réalisée ? | G4: OUI | H4: Rapport d’analyse économique | I4: Décision sur des bases incomplètes | J4: ÉLEVÉ | K4: Mauvais ROI | L4: Intégrer systématiquement cette analyse à la phase d’opportunité
E5: Prise en compte des impacts organisationnels | F5: Les impacts organisationnels ont-ils été évalués ? | G5: OUI | H5: Rapport d’impact | I5: Résistances au changement | J5: MOYEN | K5: Retards de mise en œuvre | L5: Anticiper les changements organisationnels
E6: Participation des métiers | F6: Les utilisateurs finaux ont-ils été consultés ? | G6: NON | H6: PV de réunions | I6: Inadéquation du système aux besoins | J6: ÉLEVÉ | K6: Refus d’adoption | L6: Impliquer les métiers dès l’étude d’opportunité
E7: Comparaison avec d’autres options | F7: D’autres options ont-elles été évaluées ? | G7: PAS | H7: Benchmark | I7: Décision biaisée | J7: MOYEN | K7: Choix sous-optimal | L7: Évaluer au moins deux scénarios alternatifs
D8: S’assurer qu’un bilan critique des processus existants a été effectué ; | E8: Existence d’un état des lieux | F8: Un état des lieux des processus a-t-il été effectué ? | G8: OUI | H8: Rapport d’état des lieux | I8: Conception basée sur des données erronées | J8: MOYEN | K8: Inefficacité | L8: Réaliser une cartographie détaillée
E9: Identification des dysfonctionnements | F9: Les dysfonctionnements ont-ils été listés ? | G9: OUI | H9: Diagnostic des processus | I9: Répétition des erreurs | J9: ÉLEVÉ | K9: Système inefficace | L9: Mener des ateliers d’analyse
E10: Consultation des utilisateurs | F10: Les utilisateurs ont-ils participé à l’analyse ? | G10: NON | H10: PV de réunions | I10: Sous-estimation des problèmes réels | J10: ÉLEVÉ | K10: Mécontentement | L10: Associer les utilisateurs dans le diagnostic
E11: Documentation des processus | F11: Les processus sont-ils documentés ? | G11: OUI | H11: Procédures internes | I11: Zones d’ombre dans l’analyse | J11: MOYEN | K11: Mauvaise conception | L11: Documenter les procédures avant l’analyse
E12: Existence d’indicateurs | F12: Des indicateurs de performance sont-ils suivis ? | G12: PAS | H12: Tableaux de bord | I12: Incapacité à mesurer les améliorations | J12: MOYEN | K12: Pertes de gains potentiels | L12: Définir des KPI pertinents avant projet
D13: S’assurer que le choix de recourir à un nouveau système est obtenu après optimisation des processus concernés et vérification que cette optimisation ne suffit pas à apporter par elle-même les gains de performance attendus ; | E13: Analyse préalable des processus | F13: Une optimisation des processus a-t-elle été tentée ? | G13: OUI | H13: Rapport d’optimisation | I13: Mise en œuvre d’un projet inutile | J13: ÉLEVÉ | K13: Gaspillage de ressources | L13: Tenter d’améliorer les processus avant tout projet
E14: Justification du recours au système | F14: Le nouveau système est-il justifié par des limites identifiées ? | G14: OUI | H14: Rapport d’étude de faisabilité | I14: Système inadapté aux enjeux | J14: MOYEN | K14: Coût élevé pour faible valeur ajoutée | L14: Valider l’écart entre besoins et solutions
E15: Analyse comparative "avant/après" | F15: Une analyse comparative a-t-elle été faite ? | G15: NON | H15: Rapport d’analyse comparative | I15: Absence de preuve de bénéfice | J15: MOYEN | K15: Difficultés de validation budgétaire | L15: Réaliser une analyse d’impact
E16: Intégration des retours d’expérience | F16: Les projets passés ont-ils été analysés ? | G16: PAS | H16: Compte-rendus d’expériences précédentes | I16: Répétition d’erreurs passées | J16: ÉLEVÉ | K16: Projet rejeté | L16: Capitaliser sur les expériences antérieures
E17: Implication des directions métier | F17: Les métiers ont-ils validé le besoin ? | G17: OUI | H17: PV de validation métier | I17: Faible adhésion | J17: MOYEN | K17: Résistance au changement | L17: Valider avec les utilisateurs finaux
D18: S’assure que les objectifs et périmètres du projet sont définis, partagés et stabilisés ; | E18: Définition claire des objectifs | F18: Les objectifs sont-ils clairement définis ? | G18: OUI | H18: Document d’objectifs | I18: Dérive de périmètre | J18: ÉLEVÉ | K18: Retards et surcoûts | L18: Définir des objectifs SMART
E19: Validation des objectifs par la direction | F19: La direction a-t-elle validé les objectifs ? | G19: OUI | H19: PV de comité de pilotage | I19: Décalage entre stratégie et projet | J19: MOYEN | K19: Perte d’alignement stratégique | L19: Impliquer la direction dès le départ
E20: Communication du périmètre aux acteurs | F20: Le périmètre est-il connu de tous les acteurs ? | G20: NON | H20: Plan de communication projet | I20: Incompréhensions | J20: MOYEN | K20: Conflits de responsabilités | L20: Communiquer en amont
E21: Existence d’un cadrage formalisé | F21: Un document de cadrage est-il disponible ? | G21: OUI | H21: Note de cadrage | I21: Ambiguïté dans les limites | J21: MOYEN | K21: Mauvaise planification | L21: Formaliser un document de cadrage précis
E22: Stabilisation du périmètre | F22: Le périmètre a-t-il été figé avant lancement ? | G22: NON | H22: PV de validation de périmètre | I22: Modifications en cours de projet | J22: ÉLEVÉ | K22: Retards / surcoûts | L22: Fixer une phase de validation ferme
D23: S’assurer que les principales orientations du système cible ont été explicitées ; | E23: Présentation des orientations dans les documents | F23: Les orientations sont-elles formalisées ? | G23: OUI | H23: Document d’architecture cible | I23: Ambiguïté sur les choix techniques | J23: MOYEN | K23: Retards d’implémentation | L23: Documenter l’architecture cible
E24: Validation des orientations par les métiers | F24: Les métiers valident-ils les orientations ? | G24: NON | H24: PV de réunion | I24: Détournement des usages | J24: ÉLEVÉ | K24: Refus d’adoption | L24: Impliquer les utilisateurs en amont
E25: Existence d’un document d’urbanisation SI | F25: L’urbanisation du SI a-t-elle été prise en compte ? | G25: PAS | H25: Schéma directeur | I25: Incohérence avec le SI existant | J25: ÉLEVÉ | K25: Coûts de refonte | L25: Intégrer le système dans une vision globale
E26: Prise en compte des enjeux métier | F26: Les orientations tiennent-elles compte des enjeux métier ? | G26: OUI | H26: Analyse d’impacts | I26: Système peu pertinent | J26: MOYEN | K26: Perte d’efficacité | L26: Aligner les objectifs métiers et techniques
E27: Mise à jour du document d’orientation | F27: Le document est-il mis à jour régulièrement ? | G27: NON | H27: Historique de versions | I27: Décalage avec les réalités du projet | J27: MOYEN | K27: Mauvais pilotage | L27: Maintenir un document vivant et évolutif
C28: Étude d'opportunité et expression des besoins ; | D28: S’assurer que l'expression détaillée des besoins est formalisée dans un cahier des charges fait par la MOA ; | E28: Existence du cahier des charges | F28: Le cahier des charges a-t-il été rédigé ? | G28: OUI | H28: Cahier des charges | I28: Absence de vision claire | J28: ÉLEVÉ | K28: Mauvaise conception du système | L28: Formaliser un CDC complet validé
E29: Origine des besoins | F29: Les besoins ont-ils été exprimés par la MOA ? | G29: OUI | H29: Compte rendu d’ateliers MOA | I29: Décalage avec les attentes réelles | J29: MOYEN | K29: Inadéquation fonctionnelle | L29: Impliquer directement les utilisateurs
E30: Validation du CDC par les utilisateurs | F30: Les utilisateurs ont-ils validé le document ? | G30: NON | H30: PV de validation | I30: Rejets ou résistances | J30: ÉLEVÉ | K30: Retard ou échec de projet | L30: Impliquer les utilisateurs finaux pour validation
E31: Traçabilité des besoins | F31: Les besoins sont-ils tracés dans le CDC ? | G31: PAS | H31: Matrice de traçabilité | I31: Risque de non-couverture | J31: MOYEN | K31: Lacunes fonctionnelles | L31: Structurer les besoins avec des indicateurs clairs
E32: Révision du CDC | F32: Le CDC est-il mis à jour ? | G32: NON | H32: Historique de versions | I32: Obsolescence | J32: MOYEN | K32: Écarts dans le développement | L32: Prévoir un processus de mise à jour contrôlée
D33: S’assurer que le cahier des charges préconise une solution fonctionnellement et techniquement pertinente au regard des besoins exprimés ; | E33: Adéquation fonctionnelle | F33: La solution proposée répond-elle aux besoins exprimés ? | G33: PAS | H33: Cahier des charges fonctionnel | I33: Inadéquation entre solution et attentes | J33: ÉLEVÉ | K33: Non-adhésion des utilisateurs | L33: Revoir les besoins avec les utilisateurs et ajuster la solution
E34: Pertinence technique | F34: La solution est-elle techniquement réaliste et maîtrisable ? | G34: OUI | H34: Étude de faisabilité | I34: Implémentation complexe | J34: MOYEN | K34: Retards ou abandon de projet | L34: Évaluer systématiquement la faisabilité technique
E35: Prise en compte des contraintes opérationnelles | F35: Le cahier des charges intègre-t-il les contraintes de déploiement ? | G35: NON | H35: Cahier des charges détaillé | I35: Blocages en phase de mise en œuvre | J35: MOYEN | K35: Problèmes en production | L35: Intégrer l’équipe d’exploitation dans la phase de cadrage
E36: Analyse des scénarios alternatifs | F36: Des scénarios alternatifs ont-ils été envisagés et comparés ? | G36: NON | H36: Étude comparative de solutions | I36: Mauvais choix stratégique | J36: ÉLEVÉ | K36: Coûts supplémentaires pour réajuster | L36: Réaliser une analyse multicritère avant le choix
E37: Alignement avec les priorités métiers | F37: La solution respecte-t-elle les priorités métiers ? | G37: OUI | H37: Cahier des charges validé par MOA | I37: Conflits d’usage ou de gestion | J37: MOYEN | K37: Perte d’efficacité métier | L37: Co-construire la solution avec les représentants métiers
D38: S’assurer que les exigences utilisateurs, les populations ciblées, les options et principes de gestion retenus sont précisés et priorisés ; | E38: Identification des utilisateurs cibles | F38: Les populations ciblées sont-elles clairement identifiées ? | G38: OUI | H38: Analyse des parties prenantes | I38: Fonctionnalités inadaptées | J38: MOYEN | K38: Rejet de la solution par certains profils | L38: Mener des ateliers utilisateurs en amont
E39: Hiérarchisation des besoins | F39: Les besoins sont-ils classés par ordre de priorité ? | G39: NON | H39: Cahier des charges utilisateur | I39: Focalisation sur des besoins secondaires | J39: ÉLEVÉ | K39: Inefficacité fonctionnelle | L39: Prioriser les exigences en concertation avec les métiers
E40: Définition des options de gestion | F40: Les options de gestion sont-elles formalisées ? | G40: NON | H40: Document de gestion des processus | I40: Ambiguïté dans les processus métiers | J40: MOYEN | K40: Mauvaise adoption opérationnelle | L40: Documenter clairement les choix de gestion retenus
E41: Validation par les utilisateurs | F41: Les exigences ont-elles été validées par les utilisateurs finaux ? | G41: PAS | H41: PV de validation ou comptes rendus d’ateliers | I41: Mauvaise prise en compte des besoins réels | J41: ÉLEVÉ | K41: Révision tardive du projet | L41: Intégrer des points de validation utilisateurs à chaque phase
E42: Documentation des exigences | F42: Les exigences sont-elles documentées de manière structurée ? | G42: OUI | H42: Cahier des exigences utilisateur | I42: Perte d’information ou oubli de besoins | J42: MOYEN | K42: Spécification incomplète | L42: Utiliser un modèle structuré pour la rédaction des exigences
D43: S’assurer que le projet est cohérent avec le plan directeur informatique ; | E43: Référencement dans le plan directeur | F43: Le projet est-il inscrit dans le plan ? | G43: OUI | H43: Plan directeur | I43: Projet isolé sans vision long terme | J43: MOYEN | K43: Difficultés d'intégration | L43: Intégrer tous les projets au plan directeur
E44: Cohérence avec les priorités stratégiques | F44: Le projet répond-il aux priorités ? | G44: OUI | H44: Schéma stratégique | I44: Perte de valeur | J44: FAIBLE | K44: Déviation des objectifs SI | L44: Aligner projet et feuille de route stratégique
E45: Synchronisation avec les autres projets | F45: Le calendrier est-il coordonné ? | G45: NON | H45: Planning transversal | I45: Conflits de ressources | J45: MOYEN | K45: Retards croisés | L45: Harmoniser les calendriers projets
E46: Validation du projet par la DSI | F46: La DSI a-t-elle validé le projet ? | G46: PAS | H46: PV de validation | I46: Absence de gouvernance | J46: MOYEN | K46: Difficulté à obtenir les ressources | L46: Intégrer le projet dans le portefeuille SI
E47: Suivi par comité stratégique | F47: Le projet est-il suivi par un comité SI ? | G47: NON | H47: Compte rendu comité SI | I47: Décrochage du pilotage | J47: ÉLEVÉ | K47: Projet à la dérive | L47: Instaurer un pilotage stratégique régulier
D48: S’assurer que le projet est cohérent avec le SI actuel ou futur ; | E48: Analyse d’impacts sur le SI existant | F48: Une étude d’impact sur le SI actuel a-t-elle été réalisée ? | G48: NON | H48: Rapport d’impact SI | I48: Incompatibilité avec les systèmes actuels | J48: ÉLEVÉ | K48: Dysfonctionnements en production | L48: Réaliser systématiquement une analyse d’impact technique
E49: Intégration dans l’architecture cible | F49: Le projet respecte-t-il l’architecture cible définie ? | G49: PAS | H49: Schéma d’architecture cible | I49: Perte de cohérence du SI | J49: ÉLEVÉ | K49: Augmentation des coûts de maintenance | L49: Aligner le projet avec l’urbanisation du SI
E50: Réutilisation des composants existants | F50: Des briques existantes sont-elles réutilisées ? | G50: NON | H50: Référentiel des composants SI | I50: Redondance fonctionnelle | J50: MOYEN | K50: Coûts supplémentaires | L50: Favoriser la mutualisation des composants
E51: Compatibilité avec les normes SI internes | F51: La solution respecte-t-elle les normes SI de l’organisation ? | G51: OUI | H51: Référentiel de normes internes | I51: Non-conformité technique | J51: MOYEN | K51: Difficulté d’évolutivité | L51: Appliquer les standards techniques dès la conception
E52: Coordination avec la DSI | F52: Le projet est-il suivi techniquement par la DSI ? | G52: OUI | H52: PV de suivi technique | I52: Isolement des équipes projet | J52: FAIBLE | K52: Décisions inadaptées | L52: Maintenir une coordination étroite avec la DSI
C53: Planification ; | D53: S’assurer qu’il existe un planning directeur commun à tout le projet ; | E53: Existence du planning directeur | F53: Le planning directeur du projet existe-t-il ? | G53: OUI | H53: Planning directeur validé | I53: Manque de vision globale | J53: MOYEN | K53: Retards ou chevauchements d'activités | L53: Mettre à jour régulièrement le planning
E54: Partage du planning | F54: Le planning est-il communiqué à toutes les parties prenantes ? | G54: NON | H54: Emails de diffusion, CR de réunion | I54: Coordination insuffisante | J54: ÉLEVÉ | K54: Risques de désalignement entre équipes | L54: Formaliser la communication du planning
E55: Répartition des jalons | F55: Les jalons majeurs sont-ils identifiés dans le planning ? | G55: OUI | H55: Planning projet | I55: Difficulté de pilotage | J55: MOYEN | K55: Non-respect des délais critiques | L55: Définir des points de contrôle réguliers
E56: Mise à jour du planning | F56: Le planning est-il révisé à chaque changement majeur ? | G56: PAS | H56: Historique des versions du planning | I56: Incohérences projet / terrain | J56: ÉLEVÉ | K56: Décalage entre planification et exécution | L56: Mettre en place un processus de mise à jour continue
E57: Alignement avec les autres plannings | F57: Le planning est-il synchronisé avec ceux des autres projets liés ? | G57: NON | H57: Plannings des projets connexes | I57: Conflits de ressources | J57: MOYEN | K57: Dérives budgétaires ou temporelles | L57: Instaurer une revue croisée des plannings
D58: S’assurer qu’il existe un plan de projet initial ; | E58: Existence formelle | F58: Le plan de projet initial existe-t-il ? | G58: OUI | H58: Plan de projet validé | I58: Absence de ligne directrice | J58: ÉLEVÉ | K58: Projet mal cadré ou désorganisé | L58: Élaborer le plan avant tout démarrage
E59: Contenu structuré | F59: Le plan couvre-t-il les aspects budget, délai, risques, qualité ? | G59: OUI | H59: Plan projet détaillé | I59: Mauvaise anticipation | J59: MOYEN | K59: Réajustements fréquents | L59: Utiliser un modèle structuré et validé
E60: Validation | F60: Le plan est-il validé par toutes les parties prenantes ? | G60: NON | H60: PV de validation | I60: Manque d’adhésion | J60: MOYEN | K60: Blocages ou tensions en cours de projet | L60: Organiser une réunion de validation collective
E61: Mise à jour | F61: Le plan a-t-il été mis à jour suite à des changements de contexte ? | G61: PAS | H61: Historique des mises à jour | I61: Obsolescence du plan | J61: MOYEN | K61: Mauvais alignement avec la réalité | L61: Prévoir une revue périodique du plan
E62: Référencement | F62: Le plan est-il référencé dans les outils de gestion de projet ? | G62: NON | H62: Référentiel documentaire | I62: Non-consultation du plan | J62: FAIBLE | K62: Informations oubliées ou ignorées | L62: Centraliser tous les documents de pilotage
D63: S’assurer que ce plan de projet a été révisé ; | E63: Révision périodique | F63: Le plan de projet est-il révisé périodiquement ? | G63: OUI | H63: Historique des révisions | I63: Retards dans les ajustements | J63: MOYEN | K63: Inadéquation entre le plan et l’avancement réel | L63: Mettre en place des révisions régulières (mensuelles)
E64: Prise en compte des imprévus | F64: Les modifications imprévues sont-elles prises en compte dans les révisions ? | G64: OUI | H64: Journaux de modifications | I64: Non-prise en compte des imprévus | J64: ÉLEVÉ | K64: Risque de déviation par rapport aux objectifs | L64: Intégrer un processus de gestion des changements dans le plan
E65: Appropriabilité des révisions | F65: Les révisions sont-elles comprises et acceptées par toutes les parties prenantes ? | G65: NON | H65: PV de révision, communications | I65: Non-adhésion des parties prenantes | J65: MOYEN | K65: Blocage ou mauvaise coopération | L65: Organiser des sessions de validation après chaque révision
E66: Impact des révisions | F66: Les révisions ont-elles un impact sur le calendrier global ? | G66: OUI | H66: Plan révisé et plan d’action | I66: Décalage de délais | J66: ÉLEVÉ | K66: Risques de retard ou de dépassement | L66: Analyser l’impact des révisions sur les délais avant validation
E67: Suivi des révisions | F67: Les révisions sont-elles suivies de manière proactive ? | G67: PAS | H67: Liste de suivi des actions | I67: Manque de suivi | J67: MOYEN | K67: Rejets ou oublis dans l’exécution | L67: Mettre en place un suivi formalisé des actions après chaque révision
D68: S’assurer qu’il existe des plans détaillés ; | E68: Existence de plans détaillés | F68: Des plans détaillés pour chaque domaine (budget, ressources, risques) existent-ils ? | G68: OUI | H68: Plans détaillés validés | I68: Absence de détails opérationnels | J68: ÉLEVÉ | K68: Difficulté d’exécution, imprévus | L68: Déléguer des responsables pour chaque domaine spécifique
E69: Détail des ressources | F69: Les ressources humaines et matérielles nécessaires sont-elles clairement définies ? | G69: OUI | H69: Planning de ressources | I69: Manque de ressources, surcharges | J69: MOYEN | K69: Incapacité à respecter le planning | L69: Mettre à jour la planification des ressources selon les besoins
E70: Allocation des tâches | F70: Les tâches sont-elles bien réparties et assignées à des responsables spécifiques ? | G70: OUI | H70: Grille de répartition des tâches | I70: Confusion dans les responsabilités | J70: MOYEN | K70: Tâches non réalisées ou mal réalisées | L70: Revue périodique de la répartition des tâches
E71: Validation des plans | F71: Les plans détaillés ont-ils été validés par toutes les parties prenantes ? | G71: NON | H71: PV de validation | I71: Non-adhésion des parties prenantes | J71: ÉLEVÉ | K71: Dérives, mauvaise coopération | L71: Assurer une validation par toutes les parties prenantes
E72: Suivi des plans | F72: Un suivi des plans détaillés est-il effectué pour s’assurer qu’ils sont respectés ? | G72: PAS | H72: Tableau de bord de suivi | I72: Non-respect des délais ou budget | J72: ÉLEVÉ | K72: Risques de dépassement de budget ou de temps | L72: Mettre en place un tableau de bord de suivi quotidien
D73: S’assurer que ces plans ont été révisés ; | E73: Fréquence de révision | F73: Les plans sont-ils révisés régulièrement en fonction de l’évolution du projet ? | G73: OUI | H73: Journal des révisions | I73: Retards dans l’adaptation | J73: MOYEN | K73: Risques de mauvaise gestion du projet | L73: Prévoir des révisions chaque mois ou dès qu'un changement majeur se produit
E74: Adaptation aux changements | F74: Les révisions intègrent-elles les changements internes et externes ? | G74: OUI | H74: Plan de révision avec impact | I74: Non-prise en compte des changements | J74: ÉLEVÉ | K74: Dérives et blocages | L74: Mettre en place un processus de gestion des modifications
E75: Suivi des impacts | F75: L'impact des révisions sur les coûts et les délais est-il suivi ? | G75: NON | H75: Rapport d’impact de révision | I75: Non-respect des nouveaux délais | J75: ÉLEVÉ | K75: Augmentation des coûts et des délais | L75: Définir un suivi précis de l’impact des révisions
E76: Communication des révisions | F76: Les révisions sont-elles communiquées à tous les acteurs du projet ? | G76: NON | H76: Rapport de communication | I76: Désalignement des parties prenantes | J76: MOYEN | K76: Conflits et confusion | L76: Organiser des réunions de présentation des révisions
E77: Formalisation des révisions | F77: Les révisions sont-elles bien documentées et archivées ? | G77: OUI | H77: Archivage des révisions | I77: Pertes de révisions précédentes | J77: FAIBLE | K77: Difficulté de traçabilité | L77: Mettre en place un système de gestion documentaire centralisé
C78: Instances de pilotage; | D78: S’assurer que la structure de pilotage est formalisée et connue de tous les acteurs ; | E78: Formalisation de la structure | F78: La structure de pilotage est-elle formalisée et documentée ? | G78: OUI | H78: Organigramme, documents de gouvernance | I78: Manque de clarté | J78: MOYEN | K78: Confusion des rôles et responsabilités | L78: Mettre à jour régulièrement la documentation
E79: Communication de la structure | F79: La structure de pilotage est-elle bien communiquée à tous les acteurs ? | G79: NON | H79: Note de communication interne | I79: Mauvaise coordination | J79: ÉLEVÉ | K79: Conflits ou actions en décalage avec la stratégie | L79: Organiser des réunions régulières pour clarifier les rôles
E80: Accessibilité de l’information | F80: Les informations sur la structure de pilotage sont-elles facilement accessibles ? | G80: OUI | H80: Intranet ou manuel de gouvernance | I80: Difficulté d’accès à l’information | J80: MOYEN | K80: Lenteur de décision | L80: Créer un accès centralisé à la documentation
E81: Prise en compte des parties prenantes | F81: La structure de pilotage prend-elle en compte toutes les parties prenantes ? | G81: OUI | H81: Liste des parties prenantes, organigramme | I81: Exclusion de parties prenantes clés | J81: ÉLEVÉ | K81: Retards ou mauvaise direction stratégique | L81: Revoir la structure pour s'assurer de la représentation de tous les acteurs
E82: Evolution de la structure | F82: La structure de pilotage est-elle revue lors de changements majeurs dans le projet ? | G82: NON | H82: Journal des révisions | I82: Non-adaptation de la structure | J82: MOYEN | K82: Dysfonctionnements en cas de réajustement nécessaire | L82: Mettre en place une révision régulière de la structure
D83: S’assurer que les différentes instances de pilotage connaissent leurs niveaux de délégation ; | E83: Clarté des délégations | F83: Les niveaux de délégation sont-ils clairement définis ? | G83: OUI | H83: Organigramme avec niveaux de délégation | I83: Ambiguïté sur les responsabilités | J83: ÉLEVÉ | K83: Retards, manque de direction | L83: Clarifier les niveaux de délégation dans la documentation
E84: Acceptation des délégations | F84: Les responsables acceptent-ils et comprennent-ils leurs délégations ? | G84: OUI | H84: PV de réunion, courriers de confirmation | I84: Rejet des responsabilités | J84: MOYEN | K84: Blocage de l'avancement du projet | L84: Confirmer l’acceptation formelle des délégations par les acteurs
E85: Communication des délégations | F85: Les délégations sont-elles communiquées de manière efficace ? | G85: NON | H85: Liste de diffusion, emails | I85: Délégations non suivies | J85: ÉLEVÉ | K85: Incohérence dans les décisions | L85: Organiser des réunions de clarification des délégations
E86: Suivi des délégations | F86: Un suivi est-il effectué pour vérifier la bonne exécution des délégations ? | G86: PAS | H86: Tableau de suivi des délégations | I86: Mauvais contrôle des actions | J86: MOYEN | K86: Risques de non-exécution | L86: Mettre en place un tableau de suivi et une vérification régulière
E87: Mise à jour des délégations | F87: Les délégations sont-elles régulièrement mises à jour ? | G87: NON | H87: Historique des délégations | I87: Non-adaptation aux évolutions du projet | J87: MOYEN | K87: Problèmes de gestion de projet | L87: Intégrer une révision régulière des délégations dans les réunions
D88: S’assurer que les objectifs des délégations sont atteints ; | E88: Atteinte des objectifs | F88: Les objectifs des délégations sont-ils atteints dans les délais ? | G88: OUI | H88: Rapport de suivi des objectifs | I88: Non-atteinte des objectifs | J88: ÉLEVÉ | K88: Retards, non-atteinte des résultats | L88: Organiser des points de suivi réguliers pour évaluer les progrès
E89: Contrôle de performance | F89: Des indicateurs de performance ont-ils été définis pour chaque délégation ? | G89: OUI | H89: KPI définis, rapports d’avancement | I89: Manque de performance mesurable | J89: ÉLEVÉ | K89: Difficulté d’évaluer l’efficacité des actions | L89: Définir des indicateurs mesurables et clairs pour chaque délégation
E90: Suivi de l'avancement | F90: L’avancement des actions déléguées est-il régulièrement suivi ? | G90: NON | H90: Tableau de bord de suivi | I90: Retards ou actions non réalisées | J90: MOYEN | K90: Risque de retard sur l'ensemble du projet | L90: Assurer un suivi hebdomadaire de l’avancement des délégations
E91: Réajustement des actions | F91: Les actions sont-elles réajustées en cas de non-atteinte des objectifs ? | G91: OUI | H91: Compte rendu de réunion, plan d’action | I91: Non-ajustement des actions | J91: ÉLEVÉ | K91: Impact négatif sur le projet | L91: Créer un plan d’action en cas de retard ou d’échec de délégation
E92: Validation des résultats | F92: Les résultats des délégations sont-ils validés par les parties prenantes ? | G92: NON | H92: Validation des livrables | I92: Résultats non validés | J92: MOYEN | K92: Non-conformité des livrables | L92: Impliquer systématiquement les parties prenantes dans la validation
D93: S’assurer qu’il existe un comité de pilotage ; | E93: Existence d'un comité | F93: Un comité de pilotage existe-t-il pour superviser le projet ? | G93: OUI | H93: Liste des membres du comité | I93: Absence de supervision | J93: ÉLEVÉ | K93: Mauvaise direction stratégique | L93: Former un comité de pilotage avec des responsables clés
E94: Rôle du comité | F94: Le rôle du comité de pilotage est-il bien défini et compris ? | G94: OUI | H94: Charte du comité de pilotage | I94: Ambiguïté sur les rôles | J94: MOYEN | K94: Conflits de responsabilités | L94: Définir clairement les attributions et responsabilités
E95: Réunions régulières | F95: Le comité de pilotage se réunit-il régulièrement pour faire le point sur l’avancement ? | G95: OUI | H95: PV des réunions | I95: Manque de communication | J95: MOYEN | K95: Dérives, perte de cohésion | L95: Programmer des réunions régulières, documenter les décisions
E96: Prise de décision | F96: Les décisions prises par le comité sont-elles exécutées efficacement ? | G96: NON | H96: Compte-rendu des décisions | I96: Lenteur dans la mise en œuvre des décisions | J96: ÉLEVÉ | K96: Décisions non mises en œuvre | L96: Mettre en place un suivi strict des décisions du comité
E97: Communication avec l'équipe | F97: Le comité de pilotage communique-t-il efficacement avec les autres parties prenantes ? | G97: OUI | H97: Rapports de communication | I97: Désalignement avec l'équipe | J97: MOYEN | K97: Mauvaise coordination, erreurs dans les actions | L97: Améliorer la communication entre le comité et l’équipe projet
D98: S’assurer qu’il existe un comité de projet ; | E98: Existence du comité | F98: Un comité de projet existe-t-il pour gérer les opérations quotidiennes ? | G98: OUI | H98: Liste des membres du comité | I98: Absence de coordination | J98: ÉLEVÉ | K98: Désorganisation du projet | L98: Créer un comité avec des représentants des différentes équipes
E99: Fréquence des réunions | F99: Le comité de projet se réunit-il régulièrement pour faire un suivi ? | G99: OUI | H99: Agenda des réunions | I99: Non-suivi des actions | J99: MOYEN | K99: Déviation du projet par rapport aux objectifs | L99: Programmer des réunions régulières de suivi
E100: Prise en charge des actions | F100: Les actions décidées par le comité de projet sont-elles prises en charge et suivies ? | G100: NON | H100: Plan d’action du comité | I100: Action tardive ou non réalisée | J100: ÉLEVÉ | K100: Délai d’exécution, baisse de performance | L100: Suivre rigoureusement les décisions et assigner des responsables pour chaque action
E101: Définition des rôles | F101: Les rôles au sein du comité de projet sont-ils clairement définis ? | G101: OUI | H101: Charte de gouvernance du projet | I101: Ambiguïté dans la répartition des tâches | J101: MOYEN | K101: Confusion sur les responsabilités | L101: Clarifier les rôles de chaque membre dans le comité
...

Sheet (4.4)_AUDIT_SUPPORT_UTILISATEUR
B3: POINT DE CONTRÔLE | C3: OBJECTIF DE CONTRÔLE | D3: CRITERE D'EVALUATION | E3: QUESTION D'EVALUATION | F3: Réponses | G3: ELEMENT REQUIS | H3: RISQUES | I3: CRITICITES | J3: CONSEQUENCES | K3: RECOMMANDATIONS
B4: Audit fiabilité et sécurité | C4: S’assurer qu’une structure de centre d’assistance (help-desk) (HD) est mise en place | D4: Document formalisé décrivant la structure du help-desk. | E4: Un document validé par la direction décrit-il l'organisation du help-desk ? | F4: OUI | G4: Procès-verbal de création. | H4: Structuration inefficace. | I4: FAIBLE | J4: Perte de crédibilité. | K4: Maintenir la structure actuelle et effectuer des contrôles périodiques
D5: Désignation d'une équipe dédiée avec rôles clairs. | E5: L'équipe dispose-t-elle des compétences requises ? | F5: NON | G5: Organigramme et fiches de poste. | H5: Compétences inadaptées. | I5: ÉLEVÉ | J5: Erreurs récurrentes. | K5: Définir clairement la structure du centre d’assistance avec un organigramme validé
D6: Existence d'un SLA (accord de niveau de service). | E6: Le SLA définit-il les délais de réponse ? | F6: PAS | G6: SLA signé. | H6: Délais non respectés. | I6: MOYEN | J6: Insatisfaction clients. | K6: Lancer une évaluation pour clarifier la structure et responsabiliser les parties prenantes
D7: Infrastructure technique opérationnelle (logiciels, bases de connaissances). | E7: Les outils du help-desk sont-ils fonctionnels et sécurisés ? | F7: OUI | G7: Audit technique des outils. | H7: Outils obsolètes. | I7: FAIBLE | J7: Fuites de données. | K7: Maintenir l’attribution actuelle des rôles et responsabilités
D8: Mécanisme de suivi des performances (KPI). | E8: Des indicateurs de performance sont-ils mesurés mensuellement ? | F8: NON | G8: Rapports de performance. | H8: Décisions non data-driven. | I8: ÉLEVÉ | J8: Coûts de réorganisation. | K8: Documenter et attribuer les rôles et responsabilités à chaque acteur du centre
C9: S’assurer qu’une procédure de gestion des demandes d’assistance est diffusée et connue des utilisateurs | D9: Procédure documentée et versionnée. | E9: La procédure est-elle accessible sur l'intranet ? | F9: PAS | G9: Procédure PDF datée. | H9: Demandes ignorées. | I9: MOYEN | J9: Retards critiques. | K9: Réaliser un atelier de définition des rôles avec les parties prenantes
D10: Diffusion via des canaux officiels (intranet, email). | E10: Les utilisateurs ont-ils reçu une formation ? | F10: OUI | G10: Attestations de formation. | H10: Mauvaise utilisation des outils. | I10: FAIBLE | J10: Formation coûteuse. | K10: Conserver les processus actuels et assurer leur mise à jour régulière
D11: Formation obligatoire des utilisateurs. | E11: Un FAQ est-il disponible pour les demandes courantes ? | F11: NON | G11: Accès au FAQ. | H11: Surcharge du help-desk. | I11: ÉLEVÉ | J11: Coûts de support supplémentaires. | K11: Déployer des processus clairs de gestion des demandes avec des indicateurs de performance
D12: Existence d'un FAQ accessible. | E12: La procédure a-t-elle été mise à jour dans les 12 mois ? | F12: PAS | G12: Historique des versions. | H12: Procédures obsolètes. | I12: MOYEN | J12: Non-conformité réglementaire. | K12: Identifier les étapes critiques et documenter les processus existants
D13: Mise à jour annuelle de la procédure. | E13: Des retours utilisateurs sont-ils collectés ? | F13: OUI | G13: Enquêtes de satisfaction. | H13: Détérioration de l'expérience utilisateur. | I13: FAIBLE | J13: Perte de clients. | K13: Continuer à utiliser les outils en place et assurer leur maintenance
C14: S’assurer qu’une procédure d'escalade mise en place | D14: Procédure d'escalade documentée. | E14: Existe-t-il un circuit d'escalade pour les incidents critiques ? | F14: NON | G14: Procédure validée. | H14: Incidents non résolus. | I14: ÉLEVÉ | J14: Interruptions opérationnelles. | K14: Implémenter une solution de gestion des tickets avec reporting intégré
D15: Délais maximums définis pour chaque niveau. | E15: Les délais d'escalade sont-ils respectés ? | F15: PAS | G15: Logs de résolution. | H15: Délais dépassés. | I15: MOYEN | J15: Amendes pour non-respect de SLA. | K15: Evaluer les outils actuels et sélectionner une solution plus adaptée si nécessaire
D16: Responsables désignés pour chaque type d'incident. | E16: Les responsables sont-ils joignables 24/7 ? | F16: OUI | G16: Liste des contacts d'urgence. | H16: Responsables indisponibles. | I16: FAIBLE | J16: Perte de confiance. | K16: Poursuivre les pratiques actuelles et les ajuster selon les retours des utilisateurs
D17: Historique des escalades traitées. | E17: Des simulations d'urgence ont-elles été réalisées ? | F17: NON | G17: Rapports de tests. | H17: Procédure non testée. | I17: ÉLEVÉ | J17: Crises non gérées. | K17: Redéfinir l’organisation du centre d’assistance pour plus d’efficacité
D18: Tests annuels de la procédure. | E18: Les escalades sont-elles analysées pour amélioration ? | F18: PAS | G18: Analyses post-incident. | H18: Répétition des erreurs. | I18: MOYEN | J18: Coûts juridiques. | K18: Réaliser un audit d’efficacité organisationnelle et proposer des ajustements
C19: S’assurer de la couverture géographique du HD | D19: Zones géographiques couvertes documentées. | E19: Le help-desk couvre-t-il les filiales internationales ? | F19: OUI | G19: Carte des zones couvertes. | H19: Inégalités de service. | I19: FAIBLE | J19: Perte de parts de marché. | K19: Assurer la diffusion régulière de la documentation
D20: Support multilingue si nécessaire. | E20: Les utilisateurs non francophones sont-ils assistés ? | F20: NON | G20: Traductions disponibles. | H20: Barrières linguistiques. | I20: ÉLEVÉ | J20: Contentieux linguistiques. | K20: Documenter les procédures et les rendre disponibles à tous les utilisateurs
D21: Infrastructure locale (serveurs, équipes). | E21: Des équipes locales sont-elles déployées ? | F21: PAS | G21: Preuves de présence locale. | H21: Latence technique. | I21: MOYEN | J21: Coûts d'infrastructure. | K21: Créer une version provisoire de la procédure et valider avec les utilisateurs
D22: Délais de réponse identiques pour toutes les zones. | E22: Les délais de réponse sont-ils homogènes ? | F22: OUI | G22: Statistiques de réponse. | H22: Insatisfaction régionale. | I22: FAIBLE | J22: Sanctions locales. | K22: Maintenir les pratiques actuelles de diffusion
D23: Mesure de la satisfaction par région. | E23: La satisfaction est-elle mesurée par région ? | F23: NON | G23: Enquêtes régionales. | H23: Conflits internes. | I23: ELEVEE | J23: Réputation entachée. | K23: Mettre en place un canal officiel pour la communication des procédures
C24: S’assurer de la couverture fonctionnelle du HD | D24: Liste des fonctions supportées (IT, RH, etc.). | E24: Toutes les fonctions critiques sont-elles couvertes ? | F24: PAS | G24: Catalogue de services. | H24: Demandes non traitées. | I24: MOYEN | J24: Blocage des processus. | K24: Élaborer un plan de communication interne pour la diffusion de la procédure
D25: Experts métier identifiés pour chaque domaine. | E25: Des experts métier sont-ils associés au help-desk ? | F25: OUI | G25: Fiches d'expertise. | H25: Décisions inadaptées. | I25: FAIBLE | J25: Erreurs stratégiques. | K25: Maintenir les compétences actuelles du personnel du centre d’assistance
D26: Intégration avec les processus métiers. | E26: Le help-desk participe-t-il aux réunions métiers ? | F26: NON | G26: PV de réunions. | H26: Silotage des équipes. | I26: ÉLEVÉ | J26: Frais de consultance externes. | K26: Former le personnel pour mieux répondre aux besoins des utilisateurs
D27: SLA alignés sur les besoins fonctionnels. | E27: Les SLA sont-ils adaptés à chaque fonction ? | F27: PAS | G27: SLA par fonction. | H27: SLA irréalistes. | I27: MOYEN | J27: Pénalités contractuelles. | K27: Réaliser une évaluation complète des compétences et proposer un plan de formation
D28: Revue trimestrielle des besoins. | E28: La couverture est-elle réévaluée régulièrement ? | F28: OUI | G28: Comptes-rendus de revue. | H28: Obsolescence des services. | I28: FAIBLE | J28: Retard technologique. | K28: Continuer à adapter les outils et ressources aux besoins évolutifs
B29: Audit d'efficacité et de performance | C29: S’assurer qu’il existe une aide à la saisie pour la saisie des tickets | D29: Existence d'un guide utilisateur accessible | E29: Le guide est-il accessible depuis l'interface ? | F29: NON | G29: Capture d'écran de l'aide | H29: Saisie erronée | I29: ELEVEE | J29: Retards de traitement (+20% de temps) | K29: Mettre en place une analyse des besoins utilisateurs et adapter les outils en conséquence
D30: Intégration de suggestions automatisées | E30: Le système propose-t-il des suggestions ? | F30: PAS | G30: Logs des suggestions | H30: Mauvaise adoption | I30: MOYEN | J30: Coûts de correction (5-15k€/an) | K30: Lancer une enquête pour identifier les lacunes des outils actuels
D31: Formation des utilisateurs documentée | E31: Les formations sont-elles attestées ? | F31: OUI | G31: Attestations de formation | H31: Incompétence utilisateur | I31: FAIBLE | J31: Re-formations coûteuses | K31: Poursuivre l’assistance fonctionnelle actuelle
D32: Mesure du taux d'utilisation de l'aide | E32: Le taux d'utilisation est-il >70% ? | F32: NON | G32: Rapport d'analytics | H32: Outil sous-utilisé | I32: ELEVEE | J32: ROI faible | K32: Étendre l’assistance aux fonctionnalités manquantes
D33: Mises à jour annuelles du support | E33: Le support a-t-il été mis à jour cette année ? | F33: PAS | G33: Registre des versions | H33: Informations obsolètes | I33: MOYEN | J33: Non-conformité | K33: Identifier les fonctionnalités peu couvertes et améliorer le support
C34: S’assurer qu’il existe des revues qualité pour la saisie des tickets | D34: Procédure de revue documentée | E34: Existe-t-il une procédure écrite ? | F34: OUI | G34: Procédure versionnée | H34: Qualité hétérogène | I34: FAIBLE | J34: 30% de tickets rejetés | K34: Maintenir le niveau de couverture fonctionnelle actuel
D35: Échantillonnage hebdomadaire (≥5%) | E35: L'échantillonnage est-il respecté ? | F35: NON | G35: Registre d'échantillonnage | H35: Problèmes non détectés | I35: ÉLEVÉ | J35: Insatisfaction client | K35: Revoir les services pour mieux répondre aux attentes utilisateurs
D36: Grille d'évaluation standardisée | E36: La grille couvre-t-elle tous les critères ? | F36: PAS | G36: Grille validée | H36: Évaluations subjectives | I36: MOYEN | J36: Litiges contractuels | K36: Mettre en place des indicateurs de satisfaction sur la couverture fonctionnelle
D37: Actions correctives tracées | E37: 90% des actions sont-elles closes ? | F37: OUI | G37: Suivi des actions | H37: Corrections retardées | I37: FAIBLE | J37: Délais allongés | K37: Conserver les aides à la saisie actuelles
D38: Revue par un comité dédié | E38: PV du comité existe-t-il ? | F38: NON | G38: PV trimestriels | H38: Décisions non alignées | I38: ÉLEVÉ | J38: Perte de certification | K38: Développer une aide à la saisie facilement accessible
C39: Vérifier l’existence d’une base de connaissance | D39: Accès centralisé | E39: La base est-elle accessible à tous ? | F39: PAS | G39: URL d'accès | H39: Duplication d'efforts | I39: MOYEN | J39: +40% d'appels | K39: Clarifier et rendre visibles les aides existantes
D40: ≥80% des solutions documentées | E40: Couvre-t-elle les incidents majeurs ? | F40: OUI | G40: Inventaire des solutions | H40: Résolutions improvisées | I40: FAIBLE | J40: Erreurs récurrentes | K40: Maintenir le format clair actuel de l’aide à la saisie
D41: Moteur de recherche fonctionnel | E41: Le moteur renvoie-t-il des résultats pertinents ? | F41: NON | G41: Tests de recherche | H41: Temps de recherche ×3 | I41: MOYEN | J41: Coûts de formation | K41: Revoir le contenu pour garantir concision et clarté
D42: Contrôle d'accès RBAC | E42: Les droits sont-ils granularisés ? | F42: PAS | G42: Matrice des droits | H42: Fuites d'infos | I42: MOYEN | J42: Amendes RGPD | K42: Tester la compréhension de l’aide auprès des utilisateurs
D43: Archivage des anciennes versions | E43: Version 2023 est-elle archivée ? | F43: OUI | G43: Backup des versions | H43: Perte de savoir | I43: FAIBLE | J43: Perte de compétences | K43: Continuer à adapter l’aide à la saisie aux besoins
C44: S’assurer qu’une procédure de mise à jour de la base de connaissance existe | D44: Rôles clairement définis | E44: Qui est responsable des mises à jour ? | F44: NON | G44: Fiches de poste | H44: Contenu obsolète | I44: ÉLEVÉ | J44: Support inefficace | K44: Reconcevoir l’aide en fonction des cas d’usage utilisateurs
D45: Cycle de mise à jour trimestriel | E45: Les mises à jour sont-elles planifiées ? | F45: PAS | G45: Calendrier des mises à jour | H45: Retards critiques | I45: MOYEN | J45: Pénalités contractuelles | K45: Recueillir les besoins réels pour améliorer l’aide à la saisie
D46: Validation par le RSSI | E46: Le RSSI a-t-il signé la dernière version ? | F46: OUI | G46: Approbations | H46: Non-conformité | I46: FAIBLE | J46: Vulnérabilités sécurité | K46: Maintenir les processus actuels de saisie
D47: Journal des modifications | E47: Le journal est-il à jour ? | F47: NON | G47: Log des changements | H47: Traçabilité perdue | I47: ELEVEE | J47: Litiges juridiques | K47: Simplifier l’interface et le processus de saisie
D48: Tests post-mise à jour | E48: Tests automatisés existent-ils ? | F48: PAS | G48: Rapports de tests | H48: Rétrocompatibilité brisée | I48: MOYEN | J48: Coûts de rollback | K48: Former les utilisateurs à la saisie correcte de tickets
C49: S’assurer que les appels sont enregistrés | D49: Politique de conservation (6 mois min) | E49: Les enregistrements sont-ils conservés 6 mois ? | F49: OUI | G49: Politique documentée | H49: Preuves perdues | I49: FAIBLE | J49: Non-recours juridique | K49: Maintenir l’aide actuelle à la saisie des tickets
D50: Chiffrement des enregistrements | E50: Sont-ils chiffrés (AES-256) ? | F50: NON | G50: Certificat de chiffrement | H50: Données exposées | I50: MOYEN | J50: Amendes (4% CA) | K50: Réviser l’aide contextuelle et la rendre plus intuitive
D51: Consentement utilisateur documenté | E51: Les utilisateurs ont-ils consenti ? | F51: PAS | G51: Registre des consentements | H51: Violation RGPD | I51: MOYEN | J51: Perte de confiance | K51: Améliorer la visibilité de l’aide à la saisie
D52: Accès restreint aux enregistrements | E52: Seuls les auditeurs y ont-ils accès ? | F52: OUI | G52: Logs d'accès | H52: Utilisation abusive | I52: FAIBLE | J52: Réputation entachée | K52: Poursuivre les revues qualité mises en place
D53: Procédure de suppression automatique | E53: La suppression est-elle automatisée ? | F53: NON | G53: Scripts de purge | H53: Stockage illimité | I53: ÉLEVÉ | J53: Coûts de stockage | K53: Mettre en place un processus de revue qualité systématique
B54: Audit fiabilité et sécurité | C54: Vérifier la procédure de déploiement des mises à jour, d’un nouveau logiciel | D54: Procédure documentée avec matrice RACI | E54: La matrice RACI inclut-elle un responsable de rollback ? | F54: PAS | G54: Document RACI versionné | H54: Responsabilité floue | I54: MOYEN | J54: 8h de troubleshooting (25k€) | K54: Définir un calendrier régulier de revues qualité
D55: Tests automatisés (unitaires/intégration) | E55: Le pipeline CI/CD exécute-t-il ≥95% de couverture de tests ? | F55: OUI | G55: Rapport SonarQube | H55: Régressions fonctionnelles | I55: FAIBLE | J55: 15% d'incidents post-déploiement | K55: Conserver la fréquence actuelle des revues qualité
D56: Fenêtre de maintenance approuvée par la direction | E56: La fenêtre est-elle communiquée 72h à l'avance ? | F56: NON | G56: Email de notification | H56: Conflits avec les utilisateurs | I56: MOYEN | J56: Amendes pour non-respect SLA | K56: Planifier des revues qualité périodiques
D57: Journal des déploiements avec timestamp et checksum | E57: Le journal contient-il les hashs SHA-256 des packages ? | F57: PAS | G57: Logs Ansible/Jenkins | H57: Altération des binaires | I57: MOYEN | J57: Compromission données | K57: Clarifier la fréquence attendue des revues qualité
D58: Scan de vulnérabilités pré-production | E58: Le scan Nessus montre-t-il <5 vulnérabilités critiques ? | F58: OUI | G58: Rapport Nessus PDF | H58: Exploits en production | I58: FAIBLE | J58: Sanctions RGPD (4% CA) | K58: Maintenir la compétence des réviseurs actuels
C59: Vérifier les outils mis en place pour gérer les versions des logiciels | D59: Single Source of Truth (Git/Bitbucket) | E59: 100% du code est-il dans le dépôt central ? | F59: NON | G59: Audit Git avec git ls-remote | H59: Code fantôme | I59: ÉLEVÉ | J59: 40h de recherche de code | K59: Désigner et former du personnel qualifié pour les revues qualité
D60: Politique de branching (GitFlow) | E60: Existe-t-il un document de politique de branching ? | F60: PAS | G60: Politique PDF signée | H60: Merges chaotiques | I60: MOYEN | J60: 30% de temps perdu en résolution | K60: Évaluer les compétences des responsables qualité
D61: Tagging sémantique (v1.2.3) | E61: Les tags suivent-ils SEMVER ? | F61: OUI | G61: Liste des tags (git tag -l) | H61: Incompatibilités | I61: FAIBLE | J61: Coût de migration ×3 | K61: Poursuivre l’utilisation des résultats qualité
D62: Synchronisation CMDB-SCM | E62: La CMDB reflète-t-elle la version en production ? | F62: NON | G62: Export CMDB en JSON | H62: Désynchronisation assets | I62: ÉLEVÉ | J62: Erreurs d'inventaire | K62: Utiliser les résultats pour améliorer les pratiques de saisie
D63: Historique des changements sur 5 ans | E63: Peut-on retrouver le code d'il y a 3 ans ? | F63: PAS | G63: Backup LTO des dépôts | H63: Non-reproductibilité | I63: MOYEN | J63: Non-conformité SOX | K63: Instaurer une boucle de retour entre revue et amélioration
C64: Vérifier les outils mis en place pour gérer le matériel informatique | D64: CMDB à jour (≤7 jours) | E64: Le scan Lansweeper a-t-il <5% d'écarts ? | F64: OUI | G64: Diff CMDB/Lansweeper | H64: Shadow IT | I64: FAIBLE | J64: 60k€ de licences inutiles | K64: Maintenir la satisfaction sur les revues qualité
D65: Découverte automatique des assets | E65: Les nouveaux VMs sont-ils détectés en <1h ? | F65: NON | G65: Logs ServiceNow Discovery | H65: Assets non managés | I65: MOYEN | J65: 20h/semaine de gestion manuelle | K65: Interroger les causes d’insatisfaction et ajuster les pratiques
D66: SBOM pour tous les logiciels | E66: Les BOM contiennent-ils les CPE ? | F66: PAS | G66: Fichiers CycloneDX | H66: Vulnérabilités inconnues | I66: MOYEN | J66: Failures log4j-like | K66: Mettre en place un suivi de satisfaction post-revue
D67: Alerte sur EOL/EOS | E67: Les alertes EOL sont-elles envoyées 6 mois à l'avance ? | F67: OUI | G67: Alertes SCOM/Qualys | H67: Panne critique | I67: FAIBLE | J67: Indisponibilité majeure | K67: Poursuivre l’exploitation de la base de connaissance
D68: Rapport d'obsolescence trimestriel | E68: Le rapport identifie-t-il ≥90% des assets obsolètes ? | F68: NON | G68: Rapport PDF avec plan de remplacement | H68: Coûts de maintien ×5 | I68: ÉLEVÉ | J68: Dépenses CAPEX imprévues | K68: Mettre en place une base de connaissance accessible
C69: S’assurer qu’il existe un processus spécifique pour le suivi des mises à jour sur les portables | D69: Inventaire MDM exhaustif | E69: Le MDM couvre-t-il ≥98% des devices ? | F69: PAS | G69: Rapport Intune/JAMF | H69: Portables non patchés | I69: MOYEN | J69: Infection ransomware | K69: Initier la construction d’une base partielle à enrichir
D70: Politique de patchs critiques (<72h) | E70: Les patchs MS17-010 sont-ils déployés en <72h ? | F70: OUI | G70: Logs WSUS/SCCM | H70: Breaches 0-day | I70: FAIBLE | J70: Fuite données (PII) | K70: Maintenir l’exhaustivité de la base de connaissance
D71: VPN obligatoire pour les mises à jour | E71: Le VPN est-il requis via Always On VPN ? | F71: NON | G71: Config GPO/PowerShell | H71: Mises à jour corrompues | I71: ÉLEVÉ | J71: Coût de remediation 50k€ | K71: Compléter les contenus manquants identifiés
D72: Reporting de conformité hebdomadaire | E72: Le taux de conformité est-il >95% ? | F72: PAS | G72: Dashboard Power BI | H72: Non-conformité | I72: MOYEN | J72: Suspension certifications | K72: Identifier les zones à améliorer dans la base
D73: Procédure pour appareils non connectés (>30j) | E73: Existe-t-il un processus pour les "dormants" ? | F73: OUI | G73: Procédure documentée | H73: Backdoors persistantes | I73: FAIBLE | J73: Coûts légaux (500k€+) | K73: Assurer la mise à jour continue de la base
C74: S’assurer que le déploiement de nouveaux logiciels ou mises à jour est possible à distance (utile pour les utilisateurs nomades) | D74: Solution centralisée (SCCM/Ansible) | E74: 100% des devices sont-ils managés ? | F74: NON | G74: Console SCCM screenshot | H74: Désynchronisation | I74: ÉLEVÉ | J74: 200h de déploiements manuels | K74: Mettre en place un processus de mise à jour systématique
D75: Bande passante garantie (≥10Mbps/device) | E75: Le débit est-il monitoré via PRTG ? | F75: PAS | G75: Graphiques PRTG | H75: Échecs de déploiement | I75: MOYEN | J75: 30% de retries | K75: Programmer des revues de contenu régulières
D76: Rollback automatisé si échec | E76: Le rollback s'exécute-t-il en <15min ? | F76: OUI | G76: Playbook Ansible | H76: Bricking des devices | I76: FAIBLE | J76: Remplacement hardware | K76: Maintenir l’accessibilité à tous les utilisateurs concernés
D77: Journalisation complète (qui/quand/quoi) | E77: Les logs incluent-ils l'user Azure AD ? | F77: NON | G77: Logs Sentinel/SIEM | H77: Actions non tracées | I77: MOYEN | J77: Non-repudiation impossible | K77: Améliorer l’accès par droits ou ergonomie
D78: Authentification MFA obligatoire | E78: La MFA est-elle activée via Conditional Access ? | F78: PAS | G78: Rapport MFA Azure AD | H78: Accès compromis | I78: MOYEN | J78: Incident de sécurité majeur | K78: Réaliser un audit d’accessibilité de la base
B79: audit d'efficacité et de performance | C79: Vérifier comment est effectué l'inventaire des licences (logiciel, version, date de mise en production, nombre d'utilisateurs) | D79: Qualité de l’inventaire des licences | E79: L’inventaire des licences est-il complet, à jour et documenté ? | F79: OUI | G79: Base d’inventaire actualisée incluant logiciel, version, date, utilisateurs | H79: Données incomplètes ou erronées | I79: FAIBLE | J79: Risques juridiques, redressements ou surcoûts en cas de contrôle | K79: Continuer les pratiques actuelles de mise à jour
D80: Utilisation d’outils SAM | E80: Des outils SAM sont-ils utilisés pour automatiser la gestion des licences ? | F80: NON | G80: Déploiement d’un outil SAM intégré aux systèmes d’information | H80: Absence de contrôle automatisé des actifs logiciels | I80: ÉLEVÉ | J80: Mauvaise gestion des licences, surcoût ou pénalités | K80: Écrire une procédure claire et documentée
D81: Fréquence des revues de licences | E81: Les licences font-elles l’objet de revues régulières ? | F81: PAS | G81: Planning annuel de revues avec rapports de conformité | H81: Logiciels non détectés ou non conformes | I81: MOYEN | J81: Non-conformité contractuelle, amendes ou litiges | K81: Standardiser la mise à jour via un processus établi
D82: Existence d’une CMDB opérationnelle | E82: Une base CMDB intègre-t-elle les composants logiciels et leurs statuts ? | F82: OUI | G82: CMDB structurée, documentée et synchronisée avec le SI | H82: Désalignement entre l’infrastructure réelle et la base de référence | I82: FAIBLE | J82: Erreurs de gestion, décisions IT inefficaces | K82: Maintenir la complétude de l’inventaire en vérifiant régulièrement les champs requis
D83: Niveau de sensibilisation de la DSI | E83: La DSI est-elle formée aux risques liés à la non-conformité des licences ? | F83: NON | G83: Sessions de sensibilisation et documentation interne disponibles | H83: Méconnaissance des obligations légales en matière de licences | I83: ELEVEE | J83: Risques financiers et réputationnels accrus en cas de contrôle externe | K83: Compléter l’inventaire avec les données manquantes : logiciel, version, date, utilisateurs
C84: S’assurer que les outils de type SAM (Software Asset Management) sont déployés | D84: Inventaire des licences | E84: Comment est structuré l’inventaire des licences (logiciels, versions, dates, utilisateurs) ? | F84: PAS | G84: Inventaire formalisé et mis à jour régulièrement | H84: Données inexactes ou incomplètes | I84: MOYEN | J84: Risque de non-conformité et pénalités en cas d’audit | K84: Réaliser une revue pour identifier les éléments incomplets ou absents
D85: Outils de gestion SAM | E85: Des outils de type SAM sont-ils déployés pour gérer les actifs logiciels ? | F85: OUI | G85: Outil SAM fonctionnel et intégré au SI | H85: Manque de visibilité sur l’usage des licences | I85: FAIBLE | J85: Surcoûts liés aux licences inutilisées ou non déclarées | K85: Poursuivre les mises à jour régulières
D86: Revue des licences | E86: Une revue périodique des licences est-elle effectuée ? | F86: NON | G86: Planning annuel de revues avec comptes-rendus | H86: Utilisation de logiciels non conformes | I86: ÉLEVÉ | J86: Risques juridiques et atteinte à l’image de l’organisation | K86: Mettre en place une procédure de mise à jour systématique et planifiée
D87: Gestion des configurations via CMDB | E87: Une CMDB est-elle utilisée pour recenser les composants logiciels ? | F87: PAS | G87: Base CMDB complète, structurée et synchronisée | H87: Désalignement entre infrastructure réelle et référencée | I87: MOYEN | J87: Décisions IT inefficaces, erreurs dans la gestion des actifs | K87: Évaluer la fréquence actuelle et l'ajuster selon les besoins
D88: Sensibilisation des équipes IT | E88: La DSI est-elle formée et sensibilisée à la gestion des licences ? | F88: OUI | G88: Sessions de sensibilisation régulières, support documentaire | H88: Faible connaissance des obligations légales | I88: FAIBLE | J88: Manquements en cas de contrôle externe, sanctions possibles | K88: Conserver les accès actuels s’ils respectent les règles de sécurité
C89: S’assurer qu’il existe des revues régulières des licences | D89: Existence d’un processus de revue | E89: Des revues de licences sont-elles planifiées régulièrement ? | F89: NON | G89: Planning annuel formalisé avec comptes rendus | H89: Suivi non systématique de la conformité | I89: ÉLEVÉ | J89: Risques de non-renouvellement ou de dépassement de licence | K89: Restreindre les accès à des utilisateurs autorisés uniquement
D90: Implication des parties prenantes | E90: Qui participe aux revues de licences ? | F90: PAS | G90: Comité avec DSI, achats, juridique | H90: Manque de coordination | I90: MOYEN | J90: Erreurs d’évaluation ou sous-licenciement | K90: Définir clairement les profils ayant droit d'accès et les mettre à jour
D91: Traçabilité des résultats | E91: Les résultats des revues sont-ils archivés ? | F91: OUI | G91: Rapports stockés dans un référentiel sécurisé | H91: Perte d’historique de conformité | I91: FAIBLE | J91: Difficulté à prouver la conformité lors d’un audit | K91: Consolider les bonnes pratiques ayant conduit à la satisfaction
D92: Prise en compte des évolutions | E92: Les changements dans le parc sont-ils intégrés aux revues ? | F92: NON | G92: Mécanisme de mise à jour intégré au processus | H92: Revues obsolètes ou incomplètes | I92: MOYEN | J92: Non-détection de nouveaux logiciels ou d’usages | K92: Identifier les points d’insatisfaction et ajuster l’inventaire en conséquence
D93: Alignement avec les contrats éditeurs | E93: Les revues tiennent-elles compte des clauses contractuelles ? | F93: PAS | G93: Liste des contrats intégrée dans la revue | H93: Écarts avec les droits d’usage | I93: MOYEN | J93: Litiges ou redressements contractuels | K93: Réaliser une enquête ciblée pour comprendre les attentes des utilisateurs
C94: S’assurer qu’il existe une base de données de gestion de configuration de type CMDB (Configuration Management Data Base) | D94: Existence d’une CMDB | E94: Existe-t-il une CMDB recensant les actifs logiciels ? | F94: OUI | G94: Base de données centralisée et à jour | H94: Absence de référentiel fiable | I94: FAIBLE | J94: Décisions IT prises sur des données incomplètes | K94: Maintenir le déploiement des outils SAM actuels
D95: Qualité des données | E95: La CMDB est-elle maintenue avec des données fiables ? | F95: NON | G95: Procédures de mise à jour régulière | H95: Données obsolètes ou inexactes | I95: ÉLEVÉ | J95: Analyse erronée des besoins en licences | K95: Déployer immédiatement une solution SAM adaptée à l’organisation
D96: Intégration avec d’autres outils | E96: La CMDB est-elle reliée aux outils SAM ou d’inventaire ? | F96: PAS | G96: Interfaçage opérationnel et automatisé | H96: Données incohérentes ou redondantes | I96: MOYEN | J96: Temps perdu à recouper manuellement les informations | K96: Lancer un projet d’analyse de besoins pour sélectionner un outil SAM pertinent
D97: Gouvernance de la CMDB | E97: Qui est responsable de sa mise à jour ? | F97: OUI | G97: RACI documenté avec rôles définis | H97: Absence de responsabilité claire | I97: FAIBLE | J97: CMDB inutilisée ou négligée | K97: Vérifier régulièrement que la configuration reste adaptée aux besoins
D98: Auditabilité | E98: La CMDB est-elle auditée régulièrement ? | F98: NON | G98: Rapports d’audit internes disponibles | H98: Manque de contrôle qualité | I98: ÉLEVÉ | J98: Inexactitudes non détectées entraînant des écarts de conformité | K98: Configurer correctement les outils SAM selon les processus métier
C99: S’assurer que la DSI est sensibilisée aux enjeux de la maîtrise des licences ? (notamment en cas de contrôle) | D99: Niveau de formation de la DSI | E99: La DSI a-t-elle reçu une formation sur la gestion des licences ? | F99: PAS | G99: Programmes de formation ou sensibilisation en place | H99: Méconnaissance des règles de conformité | I99: MOYEN | J99: Mauvaises pratiques internes | K99: Réaliser un audit de la configuration des outils SAM
D100: Communication interne | E100: Les enjeux des licences sont-ils régulièrement rappelés ? | F100: OUI | G100: Supports internes de communication | H100: Oubli ou négligence des obligations | I100: FAIBLE | J100: Accumulation d’écarts non contrôlés | K100: Poursuivre l’utilisation des outils SAM selon la fréquence actuelle
D101: Implication de la direction | E101: La direction est-elle impliquée dans la gouvernance des licences ? | F101: NON | G101: Réunions dédiées, pilotage par la gouvernance IT | H101: Manque de soutien stratégique | I101: ÉLEVÉ | J101: Difficulté à appliquer des mesures correctives | K101: Intégrer l’utilisation des outils SAM dans les processus quotidiens
D102: Réactivité en cas de contrôle | E102: Existe-t-il un plan d’action en cas d’audit éditeur ? | F102: PAS | G102: Scénario d’audit formalisé avec référents désignés | H102: Mauvaise préparation aux audits | I102: MOYEN | J102: Sanctions financières ou juridiques | K102: Définir des moments clés pour l’utilisation des outils dans la gestion des licences
...

Sheet (4.5)_SECURITE_INFORMATIQUE
A1: points de contrôles | B1: objectifs de contrôle | C1: critères d'évaluation | D1: questions d'évaluation | E1: Réponses | F1: Documents requis | G1: Risques | H1: Criticités | I1: conséquences | J1: Recommandations
A2: Facteurs clés de succès | B2: Vérifier qu’une politique de sécurité est définie et correspond à l'activité de l'Organisation | C2: Gestion des permissions | D2: Les permissions d’accès sont-elles revues régulièrement ? | E2: NON | F2: Liste des autorisations | G2: Accès non sécurisé | H2: ÉLEVÉ | I2: Risque de compromission et fuite de données | J2: Instaurer des contrôles stricts et des audits périodiques
C3: Authentification renforcée | D3: Une authentification multi-facteurs est-elle activée pour les systèmes critiques ? | E3: OUI | F3: Politique de sécurité | G3: Vol d’identifiants | H3: MOYEN | I3: Risque d’accès non autorisé | J3: Renforcer la surveillance et l'éducation des utilisateurs
C4: Suivi des connexions | D4: Les journaux des accès sont-ils conservés et analysés périodiquement ? | E4: NON | F4: Logs d’accès | G4: Intrusions non détectées | H4: ÉLEVÉ | I4: Compromission du système et exfiltration de données | J4: Mettre en place une surveillance renforcée avec alertes automatiques
C5: Gestion des accès à distance | D5: Les accès distants aux systèmes critiques sont-ils sécurisés ? | E5: NON | F5: Politique de gestion des accès | G5: Exploitation de failles | H5: ÉLEVÉ | I5: Risque de prise de contrôle par un attaquant | J5: Restreindre et monitorer les accès distants
C6: Revue des comptes utilisateurs | D6: Une revue semestrielle des comptes est-elle réalisée pour éviter les accès inutiles ? | E6: PAS | F6: Registre des comptes | G6: Comptes fantômes exploités | H6: MOYEN | I6: Risque de fraude interne | J6: Appliquer une politique stricte de désactivation des comptes inactifs
B7: Vérifier qu’une démarche de mise en œuvre de la gestion de la sécurité est adoptée et compatible avec la culture de l'Organisation | C7: Plan de sécurité validé | D7: Un plan formel de sécurité est-il établi ? | E7: NON | F7: Plan de sécurité | G7: Absence de directives claires | H7: ÉLEVÉ | I7: Mise en œuvre incohérente des mesures | J7: Formaliser un plan de sécurité clair et validé
C8: Responsabilité définie | D8: Les rôles de sécurité sont-ils attribués ? | E8: OUI | F8: Organigramme de sécurité | G8: Ambiguïté des responsabilités | H8: MOYEN | I8: Retard dans les réponses aux incidents | J8: Clarifier et communiquer les responsabilités
